Workbook

Sheet Parameters
A1: Parameter | B1: Value | C1: Notes
A2: MO inflation | B2: 0.025
A3: Base MO per ADM (FY25) | B3: 9936
A4: Fixed share of MO | B4: 0.3
A5: Ops savings (keep-open) | B5: 0.007
A6: Extra savings (Co-location) | B6: 0.015
A7: Echo base ADM | B7: 257
A8: Pima base ADM | B8: 296
A9: Total base ADM | B9: 553 | C9: =B6+B7 -> 0
A10: Repurpose TI per closed site (FY26) | B10: 1200000
A13: Receiving overhead taper (h) | B13: FY2026 | C13: FY2027 | D13: FY2028 | E13: FY2029 | F13: FY2030
A14: h ($/retained) | B14: 1000 | C14: 800 | D14: 600 | E14: 400 | F14: 300
A16: Fixed-carry path (Lease/Sale f) | B16: FY2026 | C16: FY2027 | D16: FY2028 | E16: FY2029 | F16: FY2030
A17: f_lease | B17: 0.4 | C17: 0.3 | D17: 0.2 | E17: 0.1 | F17: 0
A19: Fixed-carry path (Ops f) | B19: FY2026 | C19: FY2027 | D19: FY2028 | E19: FY2029 | F19: FY2030
A20: f_ops | B20: 0.4 | C20: 0.35 | D20: 0.3 | E20: 0.25 | F20: 0.2

Sheet Calc
A1: Helper | B1: FY26 | C1: FY27 | D1: FY28 | E1: FY29 | F1: FY30
A2: Fixed total ($) | B2: 1689592 | C2: 1731831.8 | D2: 1775127.6 | E2: 1819505.7 | F2: 1864993.4
A3: Var unit ($/student) | B3: 7129.08 | C3: 7307.307 | D3: 7489.9897 | E3: 7677.2394 | F3: 7869.1704
A4: Echo fixed ($) | B4: 785217.24 | C4: 804847.67 | D4: 824968.86 | E4: 845593.08 | F4: 866732.91
A5: Pima fixed ($) | B5: 904374.72 | C5: 926984.09 | D5: 950158.69 | E5: 973912.66 | F5: 998260.47

Sheet Scenarios
A1: ScenarioKey | B1: Label | C1: Overlay | D1: CloseEcho | E1: ClosePima | F1: EchoShareDist | G1: ExtraSave | H1: Ramp | I1: Umbrella
A2: A_Repurpose_Both_lease | B2: A. Repurpose Both (Lease/Sale) | C2: 0 | D2: 1 | E2: 1 | F2: 0.5 | G2: 0 | H2: 0 | I2: lease
A3: A_Repurpose_Both_ops | B3: A. Repurpose Both (Ops) | C3: 0 | D3: 1 | E3: 1 | F3: 0.5 | G3: 0 | H3: 0 | I3: ops
A4: B_Repurpose_Echo_Grow_Pima_lease | B4: B. Repurpose Echo; Grow Pima (Lease) | C4: 0 | D4: 1 | E4: 0 | F4: 0.5 | G4: 0 | H4: 0 | I4: lease
A5: B_Repurpose_Echo_Grow_Pima_ops | B5: B. Repurpose Echo; Grow Pima (Ops) | C5: 0 | D5: 1 | E5: 0 | F5: 0.5 | G5: 0 | H5: 0 | I5: ops
A6: C_Repurpose_Pima_Grow_Echo_lease | B6: C. Repurpose Pima; Grow Echo (Lease) | C6: 0 | D6: 0 | E6: 1 | F6: 0.5 | G6: 0 | H6: 0 | I6: lease
A7: C_Repurpose_Pima_Grow_Echo_ops | B7: C. Repurpose Pima; Grow Echo (Ops) | C7: 0 | D7: 0 | E7: 1 | F7: 0.5 | G7: 0 | H7: 0 | I7: ops
A8: D_Grow_Both_0 | B8: D. Grow Both (Overlay 0) | C8: 0 | D8: 0 | E8: 0 | F8: 0.5 | G8: 0 | H8: 0
A9: D_Grow_Both_100 | B9: D. Grow Both (Overlay 100) | C9: 100 | D9: 0 | E9: 0 | F9: 0.5 | G9: 0 | H9: 0
A10: D_Grow_Both_150 | B10: D. Grow Both (Overlay 150) | C10: 150 | D10: 0 | E10: 0 | F10: 0.5 | G10: 0 | H10: 0
A11: E_StatusQuo_Targets_0 | B11: E. Status-Quo + Targets (0) | C11: 0 | D11: 0 | E11: 0 | F11: 0.5 | G11: 0 | H11: 0
A12: E_StatusQuo_Targets_100 | B12: E. Status-Quo + Targets (100) | C12: 100 | D12: 0 | E12: 0 | F12: 0.5 | G12: 0 | H12: 0
A13: E_StatusQuo_Targets_150 | B13: E. Status-Quo + Targets (150) | C13: 150 | D13: 0 | E13: 0 | F13: 0.5 | G13: 0 | H13: 0
A14: F_CoLocation_Echo_0 | B14: F. Co-Location @ Echo (0) | C14: 0 | D14: 0 | E14: 0 | F14: 0.7 | G14: 0.015 | H14: 0
A15: F_CoLocation_Echo_100 | B15: F. Co-Location @ Echo (100) | C15: 100 | D15: 0 | E15: 0 | F15: 0.7 | G15: 0.015 | H15: 0
A16: F_CoLocation_Echo_150 | B16: F. Co-Location @ Echo (150) | C16: 150 | D16: 0 | E16: 0 | F16: 0.7 | G16: 0.015 | H16: 0
A17: G_DHub_EchoRamp | B17: G. D-Hub @ Echo (Ramp 70/30) | C17: 150 | D17: 0 | E17: 0 | F17: 0.7 | G17: 0 | H17: 1

Sheet MultiYear_ProForma
A1: ScenarioKey | B1: Year | C1: Overlay | D1: Echo_ADM | E1: Pima_ADM | F1: Total_ADM | G1: EchoFixed$ | H1: PimaFixed$ | I1: VarUnit$ | J1: TI_add$ | K1: OpsFactor | L1: ExtraSave | M1: Total_MO$ | N1: MO_per_ADM$ | O1: KeyYr
A2: =Scenarios!A2 -> 0 | B2: FY2026 | C2: =Scenarios!C2 -> 0 | D2: =IF(=Scenarios!D2=1,0, Parameters!B6 + =ROUNDUP(=IF(=Scenarios!H2=1, IF("FY2026"="FY2026",50, IF("FY2026"="FY2027",100,150)), =Scenarios!C2)*=Scenarios!F2,0)) -> 0 | E2: =IF(=Scenarios!E2=1,0, Parameters!B7 + ==IF(=Scenarios!H2=1, IF("FY2026"="FY2026",50, IF("FY2026"="FY2027",100,150)), =Scenarios!C2)-(=ROUNDUP(=IF(=Scenarios!H2=1, IF("FY2026"="FY2026",50, IF("FY2026"="FY2027",100,150)), =Scenarios!C2)*=Scenarios!F2,0))) -> 0 | F2: =D2+E2 -> 0 | G2: =IF(=Scenarios!D2=1, IF(=Scenarios!I2="lease", Calc!B4*Parameters!B16, Calc!B4*Parameters!B19), Calc!B4) -> 0 | H2: =IF(=Scenarios!E2=1, IF(=Scenarios!I2="lease", Calc!B5*Parameters!B16, Calc!B5*Parameters!B19), Calc!B5) -> 0 | I2: =Calc!B3 -> 0 | J2: =IF("FY2026"="FY2026", (IF(=Scenarios!D2=1, Parameters!B9,0) + IF(=Scenarios!E2=1, Parameters!B9,0)), 0) -> 0 | K2: =(1-Parameters!B4) -> 0 | L2: =Scenarios!G2 -> 0 | M2: =(IF(Scenarios!D21, IF(Scenarios!I2"lease", Calc!B4*Parameters!B16, Calc!B4*Parameters!B19), Calc!B4) + IF(Scenarios!E21, IF(Scenarios!I2"lease", Calc!B5*Parameters!B16, Calc!B5*Parameters!B19), Calc!B5) + Calc!B3*=D2+E2)*=(1-Parameters!B4)*(1-J2) + =IF("FY2026"="FY2026", (IF(=Scenarios!D2=1, Parameters!B9,0) + IF(=Scenarios!E2=1, Parameters!B9,0)), 0) -> 0 | N2: =IF(F2>0, L2/F2, NA()) -> 0 | O2: ==Scenarios!A2&"|FY2026" -> 0
A3: =Scenarios!A2 -> 0 | B3: FY2027 | C3: =Scenarios!C2 -> 0 | D3: =IF(=Scenarios!D2=1,0, Parameters!B6 + =ROUNDUP(=IF(=Scenarios!H2=1, IF("FY2027"="FY2026",50, IF("FY2027"="FY2027",100,150)), =Scenarios!C2)*=Scenarios!F2,0)) -> 0 | E3: =IF(=Scenarios!E2=1,0, Parameters!B7 + ==IF(=Scenarios!H2=1, IF("FY2027"="FY2026",50, IF("FY2027"="FY2027",100,150)), =Scenarios!C2)-(=ROUNDUP(=IF(=Scenarios!H2=1, IF("FY2027"="FY2026",50, IF("FY2027"="FY2027",100,150)), =Scenarios!C2)*=Scenarios!F2,0))) -> 0 | F3: =D3+E3 -> 0 | G3: =IF(=Scenarios!D2=1, IF(=Scenarios!I2="lease", Calc!C4*Parameters!C16, Calc!C4*Parameters!C19), Calc!C4) -> 0 | H3: =IF(=Scenarios!E2=1, IF(=Scenarios!I2="lease", Calc!C5*Parameters!C16, Calc!C5*Parameters!C19), Calc!C5) -> 0 | I3: =Calc!C3 -> 0 | J3: =IF("FY2027"="FY2026", (IF(=Scenarios!D2=1, Parameters!B9,0) + IF(=Scenarios!E2=1, Parameters!B9,0)), 0) -> 0 | K3: =(1-Parameters!B4) -> 0 | L3: =Scenarios!G2 -> 0 | M3: =(IF(Scenarios!D21, IF(Scenarios!I2"lease", Calc!C4*Parameters!C16, Calc!C4*Parameters!C19), Calc!C4) + IF(Scenarios!E21, IF(Scenarios!I2"lease", Calc!C5*Parameters!C16, Calc!C5*Parameters!C19), Calc!C5) + Calc!C3*=D3+E3)*=(1-Parameters!B4)*(1-J3) + =IF("FY2027"="FY2026", (IF(=Scenarios!D2=1, Parameters!B9,0) + IF(=Scenarios!E2=1, Parameters!B9,0)), 0) -> 0 | N3: =IF(F3>0, L3/F3, NA()) -> 0 | O3: ==Scenarios!A2&"|FY2027" -> 0
A4: =Scenarios!A2 -> 0 | B4: FY2028 | C4: =Scenarios!C2 -> 0 | D4: =IF(=Scenarios!D2=1,0, Parameters!B6 + =ROUNDUP(=IF(=Scenarios!H2=1, IF("FY2028"="FY2026",50, IF("FY2028"="FY2027",100,150)), =Scenarios!C2)*=Scenarios!F2,0)) -> 0 | E4: =IF(=Scenarios!E2=1,0, Parameters!B7 + ==IF(=Scenarios!H2=1, IF("FY2028"="FY2026",50, IF("FY2028"="FY2027",100,150)), =Scenarios!C2)-(=ROUNDUP(=IF(=Scenarios!H2=1, IF("FY2028"="FY2026",50, IF("FY2028"="FY2027",100,150)), =Scenarios!C2)*=Scenarios!F2,0))) -> 0 | F4: =D4+E4 -> 0 | G4: =IF(=Scenarios!D2=1, IF(=Scenarios!I2="lease", Calc!D4*Parameters!D16, Calc!D4*Parameters!D19), Calc!D4) -> 0 | H4: =IF(=Scenarios!E2=1, IF(=Scenarios!I2="lease", Calc!D5*Parameters!D16, Calc!D5*Parameters!D19), Calc!D5) -> 0 | I4: =Calc!D3 -> 0 | J4: =IF("FY2028"="FY2026", (IF(=Scenarios!D2=1, Parameters!B9,0) + IF(=Scenarios!E2=1, Parameters!B9,0)), 0) -> 0 | K4: =(1-Parameters!B4) -> 0 | L4: =Scenarios!G2 -> 0 | M4: =(IF(Scenarios!D21, IF(Scenarios!I2"lease", Calc!D4*Parameters!D16, Calc!D4*Parameters!D19), Calc!D4) + IF(Scenarios!E21, IF(Scenarios!I2"lease", Calc!D5*Parameters!D16, Calc!D5*Parameters!D19), Calc!D5) + Calc!D3*=D4+E4)*=(1-Parameters!B4)*(1-J4) + =IF("FY2028"="FY2026", (IF(=Scenarios!D2=1, Parameters!B9,0) + IF(=Scenarios!E2=1, Parameters!B9,0)), 0) -> 0 | N4: =IF(F4>0, L4/F4, NA()) -> 0 | O4: ==Scenarios!A2&"|FY2028" -> 0
A5: =Scenarios!A2 -> 0 | B5: FY2029 | C5: =Scenarios!C2 -> 0 | D5: =IF(=Scenarios!D2=1,0, Parameters!B6 + =ROUNDUP(=IF(=Scenarios!H2=1, IF("FY2029"="FY2026",50, IF("FY2029"="FY2027",100,150)), =Scenarios!C2)*=Scenarios!F2,0)) -> 0 | E5: =IF(=Scenarios!E2=1,0, Parameters!B7 + ==IF(=Scenarios!H2=1, IF("FY2029"="FY2026",50, IF("FY2029"="FY2027",100,150)), =Scenarios!C2)-(=ROUNDUP(=IF(=Scenarios!H2=1, IF("FY2029"="FY2026",50, IF("FY2029"="FY2027",100,150)), =Scenarios!C2)*=Scenarios!F2,0))) -> 0 | F5: =D5+E5 -> 0 | G5: =IF(=Scenarios!D2=1, IF(=Scenarios!I2="lease", Calc!E4*Parameters!E16, Calc!E4*Parameters!E19), Calc!E4) -> 0 | H5: =IF(=Scenarios!E2=1, IF(=Scenarios!I2="lease", Calc!E5*Parameters!E16, Calc!E5*Parameters!E19), Calc!E5) -> 0 | I5: =Calc!E3 -> 0 | J5: =IF("FY2029"="FY2026", (IF(=Scenarios!D2=1, Parameters!B9,0) + IF(=Scenarios!E2=1, Parameters!B9,0)), 0) -> 0 | K5: =(1-Parameters!B4) -> 0 | L5: =Scenarios!G2 -> 0 | M5: =(IF(Scenarios!D21, IF(Scenarios!I2"lease", Calc!E4*Parameters!E16, Calc!E4*Parameters!E19), Calc!E4) + IF(Scenarios!E21, IF(Scenarios!I2"lease", Calc!E5*Parameters!E16, Calc!E5*Parameters!E19), Calc!E5) + Calc!E3*=D5+E5)*=(1-Parameters!B4)*(1-J5) + =IF("FY2029"="FY2026", (IF(=Scenarios!D2=1, Parameters!B9,0) + IF(=Scenarios!E2=1, Parameters!B9,0)), 0) -> 0 | N5: =IF(F5>0, L5/F5, NA()) -> 0 | O5: ==Scenarios!A2&"|FY2029" -> 0
A6: =Scenarios!A2 -> 0 | B6: FY2030 | C6: =Scenarios!C2 -> 0 | D6: =IF(=Scenarios!D2=1,0, Parameters!B6 + =ROUNDUP(=IF(=Scenarios!H2=1, IF("FY2030"="FY2026",50, IF("FY2030"="FY2027",100,150)), =Scenarios!C2)*=Scenarios!F2,0)) -> 0 | E6: =IF(=Scenarios!E2=1,0, Parameters!B7 + ==IF(=Scenarios!H2=1, IF("FY2030"="FY2026",50, IF("FY2030"="FY2027",100,150)), =Scenarios!C2)-(=ROUNDUP(=IF(=Scenarios!H2=1, IF("FY2030"="FY2026",50, IF("FY2030"="FY2027",100,150)), =Scenarios!C2)*=Scenarios!F2,0))) -> 0 | F6: =D6+E6 -> 0 | G6: =IF(=Scenarios!D2=1, IF(=Scenarios!I2="lease", Calc!F4*Parameters!F16, Calc!F4*Parameters!F19), Calc!F4) -> 0 | H6: =IF(=Scenarios!E2=1, IF(=Scenarios!I2="lease", Calc!F5*Parameters!F16, Calc!F5*Parameters!F19), Calc!F5) -> 0 | I6: =Calc!F3 -> 0 | J6: =IF("FY2030"="FY2026", (IF(=Scenarios!D2=1, Parameters!B9,0) + IF(=Scenarios!E2=1, Parameters!B9,0)), 0) -> 0 | K6: =(1-Parameters!B4) -> 0 | L6: =Scenarios!G2 -> 0 | M6: =(IF(Scenarios!D21, IF(Scenarios!I2"lease", Calc!F4*Parameters!F16, Calc!F4*Parameters!F19), Calc!F4) + IF(Scenarios!E21, IF(Scenarios!I2"lease", Calc!F5*Parameters!F16, Calc!F5*Parameters!F19), Calc!F5) + Calc!F3*=D6+E6)*=(1-Parameters!B4)*(1-J6) + =IF("FY2030"="FY2026", (IF(=Scenarios!D2=1, Parameters!B9,0) + IF(=Scenarios!E2=1, Parameters!B9,0)), 0) -> 0 | N6: =IF(F6>0, L6/F6, NA()) -> 0 | O6: ==Scenarios!A2&"|FY2030" -> 0
A7: =Scenarios!A3 -> 0 | B7: FY2026 | C7: =Scenarios!C3 -> 0 | D7: =IF(=Scenarios!D3=1,0, Parameters!B6 + =ROUNDUP(=IF(=Scenarios!H3=1, IF("FY2026"="FY2026",50, IF("FY2026"="FY2027",100,150)), =Scenarios!C3)*=Scenarios!F3,0)) -> 0 | E7: =IF(=Scenarios!E3=1,0, Parameters!B7 + ==IF(=Scenarios!H3=1, IF("FY2026"="FY2026",50, IF("FY2026"="FY2027",100,150)), =Scenarios!C3)-(=ROUNDUP(=IF(=Scenarios!H3=1, IF("FY2026"="FY2026",50, IF("FY2026"="FY2027",100,150)), =Scenarios!C3)*=Scenarios!F3,0))) -> 0 | F7: =D7+E7 -> 0 | G7: =IF(=Scenarios!D3=1, IF(=Scenarios!I3="lease", Calc!B4*Parameters!B16, Calc!B4*Parameters!B19), Calc!B4) -> 0 | H7: =IF(=Scenarios!E3=1, IF(=Scenarios!I3="lease", Calc!B5*Parameters!B16, Calc!B5*Parameters!B19), Calc!B5) -> 0 | I7: =Calc!B3 -> 0 | J7: =IF("FY2026"="FY2026", (IF(=Scenarios!D3=1, Parameters!B9,0) + IF(=Scenarios!E3=1, Parameters!B9,0)), 0) -> 0 | K7: =(1-Parameters!B4) -> 0 | L7: =Scenarios!G3 -> 0 | M7: =(IF(Scenarios!D31, IF(Scenarios!I3"lease", Calc!B4*Parameters!B16, Calc!B4*Parameters!B19), Calc!B4) + IF(Scenarios!E31, IF(Scenarios!I3"lease", Calc!B5*Parameters!B16, Calc!B5*Parameters!B19), Calc!B5) + Calc!B3*=D7+E7)*=(1-Parameters!B4)*(1-J7) + =IF("FY2026"="FY2026", (IF(=Scenarios!D3=1, Parameters!B9,0) + IF(=Scenarios!E3=1, Parameters!B9,0)), 0) -> 0 | N7: =IF(F7>0, L7/F7, NA()) -> 0 | O7: ==Scenarios!A3&"|FY2026" -> 0
A8: =Scenarios!A3 -> 0 | B8: FY2027 | C8: =Scenarios!C3 -> 0 | D8: =IF(=Scenarios!D3=1,0, Parameters!B6 + =ROUNDUP(=IF(=Scenarios!H3=1, IF("FY2027"="FY2026",50, IF("FY2027"="FY2027",100,150)), =Scenarios!C3)*=Scenarios!F3,0)) -> 0 | E8: =IF(=Scenarios!E3=1,0, Parameters!B7 + ==IF(=Scenarios!H3=1, IF("FY2027"="FY2026",50, IF("FY2027"="FY2027",100,150)), =Scenarios!C3)-(=ROUNDUP(=IF(=Scenarios!H3=1, IF("FY2027"="FY2026",50, IF("FY2027"="FY2027",100,150)), =Scenarios!C3)*=Scenarios!F3,0))) -> 0 | F8: =D8+E8 -> 0 | G8: =IF(=Scenarios!D3=1, IF(=Scenarios!I3="lease", Calc!C4*Parameters!C16, Calc!C4*Parameters!C19), Calc!C4) -> 0 | H8: =IF(=Scenarios!E3=1, IF(=Scenarios!I3="lease", Calc!C5*Parameters!C16, Calc!C5*Parameters!C19), Calc!C5) -> 0 | I8: =Calc!C3 -> 0 | J8: =IF("FY2027"="FY2026", (IF(=Scenarios!D3=1, Parameters!B9,0) + IF(=Scenarios!E3=1, Parameters!B9,0)), 0) -> 0 | K8: =(1-Parameters!B4) -> 0 | L8: =Scenarios!G3 -> 0 | M8: =(IF(Scenarios!D31, IF(Scenarios!I3"lease", Calc!C4*Parameters!C16, Calc!C4*Parameters!C19), Calc!C4) + IF(Scenarios!E31, IF(Scenarios!I3"lease", Calc!C5*Parameters!C16, Calc!C5*Parameters!C19), Calc!C5) + Calc!C3*=D8+E8)*=(1-Parameters!B4)*(1-J8) + =IF("FY2027"="FY2026", (IF(=Scenarios!D3=1, Parameters!B9,0) + IF(=Scenarios!E3=1, Parameters!B9,0)), 0) -> 0 | N8: =IF(F8>0, L8/F8, NA()) -> 0 | O8: ==Scenarios!A3&"|FY2027" -> 0
A9: =Scenarios!A3 -> 0 | B9: FY2028 | C9: =Scenarios!C3 -> 0 | D9: =IF(=Scenarios!D3=1,0, Parameters!B6 + =ROUNDUP(=IF(=Scenarios!H3=1, IF("FY2028"="FY2026",50, IF("FY2028"="FY2027",100,150)), =Scenarios!C3)*=Scenarios!F3,0)) -> 0 | E9: =IF(=Scenarios!E3=1,0, Parameters!B7 + ==IF(=Scenarios!H3=1, IF("FY2028"="FY2026",50, IF("FY2028"="FY2027",100,150)), =Scenarios!C3)-(=ROUNDUP(=IF(=Scenarios!H3=1, IF("FY2028"="FY2026",50, IF("FY2028"="FY2027",100,150)), =Scenarios!C3)*=Scenarios!F3,0))) -> 0 | F9: =D9+E9 -> 0 | G9: =IF(=Scenarios!D3=1, IF(=Scenarios!I3="lease", Calc!D4*Parameters!D16, Calc!D4*Parameters!D19), Calc!D4) -> 0 | H9: =IF(=Scenarios!E3=1, IF(=Scenarios!I3="lease", Calc!D5*Parameters!D16, Calc!D5*Parameters!D19), Calc!D5) -> 0 | I9: =Calc!D3 -> 0 | J9: =IF("FY2028"="FY2026", (IF(=Scenarios!D3=1, Parameters!B9,0) + IF(=Scenarios!E3=1, Parameters!B9,0)), 0) -> 0 | K9: =(1-Parameters!B4) -> 0 | L9: =Scenarios!G3 -> 0 | M9: =(IF(Scenarios!D31, IF(Scenarios!I3"lease", Calc!D4*Parameters!D16, Calc!D4*Parameters!D19), Calc!D4) + IF(Scenarios!E31, IF(Scenarios!I3"lease", Calc!D5*Parameters!D16, Calc!D5*Parameters!D19), Calc!D5) + Calc!D3*=D9+E9)*=(1-Parameters!B4)*(1-J9) + =IF("FY2028"="FY2026", (IF(=Scenarios!D3=1, Parameters!B9,0) + IF(=Scenarios!E3=1, Parameters!B9,0)), 0) -> 0 | N9: =IF(F9>0, L9/F9, NA()) -> 0 | O9: ==Scenarios!A3&"|FY2028" -> 0
A10: =Scenarios!A3 -> 0 | B10: FY2029 | C10: =Scenarios!C3 -> 0 | D10: =IF(=Scenarios!D3=1,0, Parameters!B6 + =ROUNDUP(=IF(=Scenarios!H3=1, IF("FY2029"="FY2026",50, IF("FY2029"="FY2027",100,150)), =Scenarios!C3)*=Scenarios!F3,0)) -> 0 | E10: =IF(=Scenarios!E3=1,0, Parameters!B7 + ==IF(=Scenarios!H3=1, IF("FY2029"="FY2026",50, IF("FY2029"="FY2027",100,150)), =Scenarios!C3)-(=ROUNDUP(=IF(=Scenarios!H3=1, IF("FY2029"="FY2026",50, IF("FY2029"="FY2027",100,150)), =Scenarios!C3)*=Scenarios!F3,0))) -> 0 | F10: =D10+E10 -> 0 | G10: =IF(=Scenarios!D3=1, IF(=Scenarios!I3="lease", Calc!E4*Parameters!E16, Calc!E4*Parameters!E19), Calc!E4) -> 0 | H10: =IF(=Scenarios!E3=1, IF(=Scenarios!I3="lease", Calc!E5*Parameters!E16, Calc!E5*Parameters!E19), Calc!E5) -> 0 | I10: =Calc!E3 -> 0 | J10: =IF("FY2029"="FY2026", (IF(=Scenarios!D3=1, Parameters!B9,0) + IF(=Scenarios!E3=1, Parameters!B9,0)), 0) -> 0 | K10: =(1-Parameters!B4) -> 0 | L10: =Scenarios!G3 -> 0 | M10: =(IF(Scenarios!D31, IF(Scenarios!I3"lease", Calc!E4*Parameters!E16, Calc!E4*Parameters!E19), Calc!E4) + IF(Scenarios!E31, IF(Scenarios!I3"lease", Calc!E5*Parameters!E16, Calc!E5*Parameters!E19), Calc!E5) + Calc!E3*=D10+E10)*=(1-Parameters!B4)*(1-J10) + =IF("FY2029"="FY2026", (IF(=Scenarios!D3=1, Parameters!B9,0) + IF(=Scenarios!E3=1, Parameters!B9,0)), 0) -> 0 | N10: =IF(F10>0, L10/F10, NA()) -> 0 | O10: ==Scenarios!A3&"|FY2029" -> 0
A11: =Scenarios!A3 -> 0 | B11: FY2030 | C11: =Scenarios!C3 -> 0 | D11: =IF(=Scenarios!D3=1,0, Parameters!B6 + =ROUNDUP(=IF(=Scenarios!H3=1, IF("FY2030"="FY2026",50, IF("FY2030"="FY2027",100,150)), =Scenarios!C3)*=Scenarios!F3,0)) -> 0 | E11: =IF(=Scenarios!E3=1,0, Parameters!B7 + ==IF(=Scenarios!H3=1, IF("FY2030"="FY2026",50, IF("FY2030"="FY2027",100,150)), =Scenarios!C3)-(=ROUNDUP(=IF(=Scenarios!H3=1, IF("FY2030"="FY2026",50, IF("FY2030"="FY2027",100,150)), =Scenarios!C3)*=Scenarios!F3,0))) -> 0 | F11: =D11+E11 -> 0 | G11: =IF(=Scenarios!D3=1, IF(=Scenarios!I3="lease", Calc!F4*Parameters!F16, Calc!F4*Parameters!F19), Calc!F4) -> 0 | H11: =IF(=Scenarios!E3=1, IF(=Scenarios!I3="lease", Calc!F5*Parameters!F16, Calc!F5*Parameters!F19), Calc!F5) -> 0 | I11: =Calc!F3 -> 0 | J11: =IF("FY2030"="FY2026", (IF(=Scenarios!D3=1, Parameters!B9,0) + IF(=Scenarios!E3=1, Parameters!B9,0)), 0) -> 0 | K11: =(1-Parameters!B4) -> 0 | L11: =Scenarios!G3 -> 0 | M11: =(IF(Scenarios!D31, IF(Scenarios!I3"lease", Calc!F4*Parameters!F16, Calc!F4*Parameters!F19), Calc!F4) + IF(Scenarios!E31, IF(Scenarios!I3"lease", Calc!F5*Parameters!F16, Calc!F5*Parameters!F19), Calc!F5) + Calc!F3*=D11+E11)*=(1-Parameters!B4)*(1-J11) + =IF("FY2030"="FY2026", (IF(=Scenarios!D3=1, Parameters!B9,0) + IF(=Scenarios!E3=1, Parameters!B9,0)), 0) -> 0 | N11: =IF(F11>0, L11/F11, NA()) -> 0 | O11: ==Scenarios!A3&"|FY2030" -> 0
A12: =Scenarios!A4 -> 0 | B12: FY2026 | C12: =Scenarios!C4 -> 0 | D12: =IF(=Scenarios!D4=1,0, Parameters!B6 + =ROUNDUP(=IF(=Scenarios!H4=1, IF("FY2026"="FY2026",50, IF("FY2026"="FY2027",100,150)), =Scenarios!C4)*=Scenarios!F4,0)) -> 0 | E12: =IF(=Scenarios!E4=1,0, Parameters!B7 + ==IF(=Scenarios!H4=1, IF("FY2026"="FY2026",50, IF("FY2026"="FY2027",100,150)), =Scenarios!C4)-(=ROUNDUP(=IF(=Scenarios!H4=1, IF("FY2026"="FY2026",50, IF("FY2026"="FY2027",100,150)), =Scenarios!C4)*=Scenarios!F4,0))) -> 0 | F12: =D12+E12 -> 0 | G12: =IF(=Scenarios!D4=1, IF(=Scenarios!I4="lease", Calc!B4*Parameters!B16, Calc!B4*Parameters!B19), Calc!B4) -> 0 | H12: =IF(=Scenarios!E4=1, IF(=Scenarios!I4="lease", Calc!B5*Parameters!B16, Calc!B5*Parameters!B19), Calc!B5) -> 0 | I12: =Calc!B3 -> 0 | J12: =IF("FY2026"="FY2026", (IF(=Scenarios!D4=1, Parameters!B9,0) + IF(=Scenarios!E4=1, Parameters!B9,0)), 0) -> 0 | K12: =(1-Parameters!B4) -> 0 | L12: =Scenarios!G4 -> 0 | M12: =(IF(Scenarios!D41, IF(Scenarios!I4"lease", Calc!B4*Parameters!B16, Calc!B4*Parameters!B19), Calc!B4) + IF(Scenarios!E41, IF(Scenarios!I4"lease", Calc!B5*Parameters!B16, Calc!B5*Parameters!B19), Calc!B5) + Calc!B3*=D12+E12)*=(1-Parameters!B4)*(1-J12) + =IF("FY2026"="FY2026", (IF(=Scenarios!D4=1, Parameters!B9,0) + IF(=Scenarios!E4=1, Parameters!B9,0)), 0) -> 0 | N12: =IF(F12>0, L12/F12, NA()) -> 0 | O12: ==Scenarios!A4&"|FY2026" -> 0
A13: =Scenarios!A4 -> 0 | B13: FY2027 | C13: =Scenarios!C4 -> 0 | D13: =IF(=Scenarios!D4=1,0, Parameters!B6 + =ROUNDUP(=IF(=Scenarios!H4=1, IF("FY2027"="FY2026",50, IF("FY2027"="FY2027",100,150)), =Scenarios!C4)*=Scenarios!F4,0)) -> 0 | E13: =IF(=Scenarios!E4=1,0, Parameters!B7 + ==IF(=Scenarios!H4=1, IF("FY2027"="FY2026",50, IF("FY2027"="FY2027",100,150)), =Scenarios!C4)-(=ROUNDUP(=IF(=Scenarios!H4=1, IF("FY2027"="FY2026",50, IF("FY2027"="FY2027",100,150)), =Scenarios!C4)*=Scenarios!F4,0))) -> 0 | F13: =D13+E13 -> 0 | G13: =IF(=Scenarios!D4=1, IF(=Scenarios!I4="lease", Calc!C4*Parameters!C16, Calc!C4*Parameters!C19), Calc!C4) -> 0 | H13: =IF(=Scenarios!E4=1, IF(=Scenarios!I4="lease", Calc!C5*Parameters!C16, Calc!C5*Parameters!C19), Calc!C5) -> 0 | I13: =Calc!C3 -> 0 | J13: =IF("FY2027"="FY2026", (IF(=Scenarios!D4=1, Parameters!B9,0) + IF(=Scenarios!E4=1, Parameters!B9,0)), 0) -> 0 | K13: =(1-Parameters!B4) -> 0 | L13: =Scenarios!G4 -> 0 | M13: =(IF(Scenarios!D41, IF(Scenarios!I4"lease", Calc!C4*Parameters!C16, Calc!C4*Parameters!C19), Calc!C4) + IF(Scenarios!E41, IF(Scenarios!I4"lease", Calc!C5*Parameters!C16, Calc!C5*Parameters!C19), Calc!C5) + Calc!C3*=D13+E13)*=(1-Parameters!B4)*(1-J13) + =IF("FY2027"="FY2026", (IF(=Scenarios!D4=1, Parameters!B9,0) + IF(=Scenarios!E4=1, Parameters!B9,0)), 0) -> 0 | N13: =IF(F13>0, L13/F13, NA()) -> 0 | O13: ==Scenarios!A4&"|FY2027" -> 0
A14: =Scenarios!A4 -> 0 | B14: FY2028 | C14: =Scenarios!C4 -> 0 | D14: =IF(=Scenarios!D4=1,0, Parameters!B6 + =ROUNDUP(=IF(=Scenarios!H4=1, IF("FY2028"="FY2026",50, IF("FY2028"="FY2027",100,150)), =Scenarios!C4)*=Scenarios!F4,0)) -> 0 | E14: =IF(=Scenarios!E4=1,0, Parameters!B7 + ==IF(=Scenarios!H4=1, IF("FY2028"="FY2026",50, IF("FY2028"="FY2027",100,150)), =Scenarios!C4)-(=ROUNDUP(=IF(=Scenarios!H4=1, IF("FY2028"="FY2026",50, IF("FY2028"="FY2027",100,150)), =Scenarios!C4)*=Scenarios!F4,0))) -> 0 | F14: =D14+E14 -> 0 | G14: =IF(=Scenarios!D4=1, IF(=Scenarios!I4="lease", Calc!D4*Parameters!D16, Calc!D4*Parameters!D19), Calc!D4) -> 0 | H14: =IF(=Scenarios!E4=1, IF(=Scenarios!I4="lease", Calc!D5*Parameters!D16, Calc!D5*Parameters!D19), Calc!D5) -> 0 | I14: =Calc!D3 -> 0 | J14: =IF("FY2028"="FY2026", (IF(=Scenarios!D4=1, Parameters!B9,0) + IF(=Scenarios!E4=1, Parameters!B9,0)), 0) -> 0 | K14: =(1-Parameters!B4) -> 0 | L14: =Scenarios!G4 -> 0 | M14: =(IF(Scenarios!D41, IF(Scenarios!I4"lease", Calc!D4*Parameters!D16, Calc!D4*Parameters!D19), Calc!D4) + IF(Scenarios!E41, IF(Scenarios!I4"lease", Calc!D5*Parameters!D16, Calc!D5*Parameters!D19), Calc!D5) + Calc!D3*=D14+E14)*=(1-Parameters!B4)*(1-J14) + =IF("FY2028"="FY2026", (IF(=Scenarios!D4=1, Parameters!B9,0) + IF(=Scenarios!E4=1, Parameters!B9,0)), 0) -> 0 | N14: =IF(F14>0, L14/F14, NA()) -> 0 | O14: ==Scenarios!A4&"|FY2028" -> 0
A15: =Scenarios!A4 -> 0 | B15: FY2029 | C15: =Scenarios!C4 -> 0 | D15: =IF(=Scenarios!D4=1,0, Parameters!B6 + =ROUNDUP(=IF(=Scenarios!H4=1, IF("FY2029"="FY2026",50, IF("FY2029"="FY2027",100,150)), =Scenarios!C4)*=Scenarios!F4,0)) -> 0 | E15: =IF(=Scenarios!E4=1,0, Parameters!B7 + ==IF(=Scenarios!H4=1, IF("FY2029"="FY2026",50, IF("FY2029"="FY2027",100,150)), =Scenarios!C4)-(=ROUNDUP(=IF(=Scenarios!H4=1, IF("FY2029"="FY2026",50, IF("FY2029"="FY2027",100,150)), =Scenarios!C4)*=Scenarios!F4,0))) -> 0 | F15: =D15+E15 -> 0 | G15: =IF(=Scenarios!D4=1, IF(=Scenarios!I4="lease", Calc!E4*Parameters!E16, Calc!E4*Parameters!E19), Calc!E4) -> 0 | H15: =IF(=Scenarios!E4=1, IF(=Scenarios!I4="lease", Calc!E5*Parameters!E16, Calc!E5*Parameters!E19), Calc!E5) -> 0 | I15: =Calc!E3 -> 0 | J15: =IF("FY2029"="FY2026", (IF(=Scenarios!D4=1, Parameters!B9,0) + IF(=Scenarios!E4=1, Parameters!B9,0)), 0) -> 0 | K15: =(1-Parameters!B4) -> 0 | L15: =Scenarios!G4 -> 0 | M15: =(IF(Scenarios!D41, IF(Scenarios!I4"lease", Calc!E4*Parameters!E16, Calc!E4*Parameters!E19), Calc!E4) + IF(Scenarios!E41, IF(Scenarios!I4"lease", Calc!E5*Parameters!E16, Calc!E5*Parameters!E19), Calc!E5) + Calc!E3*=D15+E15)*=(1-Parameters!B4)*(1-J15) + =IF("FY2029"="FY2026", (IF(=Scenarios!D4=1, Parameters!B9,0) + IF(=Scenarios!E4=1, Parameters!B9,0)), 0) -> 0 | N15: =IF(F15>0, L15/F15, NA()) -> 0 | O15: ==Scenarios!A4&"|FY2029" -> 0
A16: =Scenarios!A4 -> 0 | B16: FY2030 | C16: =Scenarios!C4 -> 0 | D16: =IF(=Scenarios!D4=1,0, Parameters!B6 + =ROUNDUP(=IF(=Scenarios!H4=1, IF("FY2030"="FY2026",50, IF("FY2030"="FY2027",100,150)), =Scenarios!C4)*=Scenarios!F4,0)) -> 0 | E16: =IF(=Scenarios!E4=1,0, Parameters!B7 + ==IF(=Scenarios!H4=1, IF("FY2030"="FY2026",50, IF("FY2030"="FY2027",100,150)), =Scenarios!C4)-(=ROUNDUP(=IF(=Scenarios!H4=1, IF("FY2030"="FY2026",50, IF("FY2030"="FY2027",100,150)), =Scenarios!C4)*=Scenarios!F4,0))) -> 0 | F16: =D16+E16 -> 0 | G16: =IF(=Scenarios!D4=1, IF(=Scenarios!I4="lease", Calc!F4*Parameters!F16, Calc!F4*Parameters!F19), Calc!F4) -> 0 | H16: =IF(=Scenarios!E4=1, IF(=Scenarios!I4="lease", Calc!F5*Parameters!F16, Calc!F5*Parameters!F19), Calc!F5) -> 0 | I16: =Calc!F3 -> 0 | J16: =IF("FY2030"="FY2026", (IF(=Scenarios!D4=1, Parameters!B9,0) + IF(=Scenarios!E4=1, Parameters!B9,0)), 0) -> 0 | K16: =(1-Parameters!B4) -> 0 | L16: =Scenarios!G4 -> 0 | M16: =(IF(Scenarios!D41, IF(Scenarios!I4"lease", Calc!F4*Parameters!F16, Calc!F4*Parameters!F19), Calc!F4) + IF(Scenarios!E41, IF(Scenarios!I4"lease", Calc!F5*Parameters!F16, Calc!F5*Parameters!F19), Calc!F5) + Calc!F3*=D16+E16)*=(1-Parameters!B4)*(1-J16) + =IF("FY2030"="FY2026", (IF(=Scenarios!D4=1, Parameters!B9,0) + IF(=Scenarios!E4=1, Parameters!B9,0)), 0) -> 0 | N16: =IF(F16>0, L16/F16, NA()) -> 0 | O16: ==Scenarios!A4&"|FY2030" -> 0
A17: =Scenarios!A5 -> 0 | B17: FY2026 | C17: =Scenarios!C5 -> 0 | D17: =IF(=Scenarios!D5=1,0, Parameters!B6 + =ROUNDUP(=IF(=Scenarios!H5=1, IF("FY2026"="FY2026",50, IF("FY2026"="FY2027",100,150)), =Scenarios!C5)*=Scenarios!F5,0)) -> 0 | E17: =IF(=Scenarios!E5=1,0, Parameters!B7 + ==IF(=Scenarios!H5=1, IF("FY2026"="FY2026",50, IF("FY2026"="FY2027",100,150)), =Scenarios!C5)-(=ROUNDUP(=IF(=Scenarios!H5=1, IF("FY2026"="FY2026",50, IF("FY2026"="FY2027",100,150)), =Scenarios!C5)*=Scenarios!F5,0))) -> 0 | F17: =D17+E17 -> 0 | G17: =IF(=Scenarios!D5=1, IF(=Scenarios!I5="lease", Calc!B4*Parameters!B16, Calc!B4*Parameters!B19), Calc!B4) -> 0 | H17: =IF(=Scenarios!E5=1, IF(=Scenarios!I5="lease", Calc!B5*Parameters!B16, Calc!B5*Parameters!B19), Calc!B5) -> 0 | I17: =Calc!B3 -> 0 | J17: =IF("FY2026"="FY2026", (IF(=Scenarios!D5=1, Parameters!B9,0) + IF(=Scenarios!E5=1, Parameters!B9,0)), 0) -> 0 | K17: =(1-Parameters!B4) -> 0 | L17: =Scenarios!G5 -> 0 | M17: =(IF(Scenarios!D51, IF(Scenarios!I5"lease", Calc!B4*Parameters!B16, Calc!B4*Parameters!B19), Calc!B4) + IF(Scenarios!E51, IF(Scenarios!I5"lease", Calc!B5*Parameters!B16, Calc!B5*Parameters!B19), Calc!B5) + Calc!B3*=D17+E17)*=(1-Parameters!B4)*(1-J17) + =IF("FY2026"="FY2026", (IF(=Scenarios!D5=1, Parameters!B9,0) + IF(=Scenarios!E5=1, Parameters!B9,0)), 0) -> 0 | N17: =IF(F17>0, L17/F17, NA()) -> 0 | O17: ==Scenarios!A5&"|FY2026" -> 0
A18: =Scenarios!A5 -> 0 | B18: FY2027 | C18: =Scenarios!C5 -> 0 | D18: =IF(=Scenarios!D5=1,0, Parameters!B6 + =ROUNDUP(=IF(=Scenarios!H5=1, IF("FY2027"="FY2026",50, IF("FY2027"="FY2027",100,150)), =Scenarios!C5)*=Scenarios!F5,0)) -> 0 | E18: =IF(=Scenarios!E5=1,0, Parameters!B7 + ==IF(=Scenarios!H5=1, IF("FY2027"="FY2026",50, IF("FY2027"="FY2027",100,150)), =Scenarios!C5)-(=ROUNDUP(=IF(=Scenarios!H5=1, IF("FY2027"="FY2026",50, IF("FY2027"="FY2027",100,150)), =Scenarios!C5)*=Scenarios!F5,0))) -> 0 | F18: =D18+E18 -> 0 | G18: =IF(=Scenarios!D5=1, IF(=Scenarios!I5="lease", Calc!C4*Parameters!C16, Calc!C4*Parameters!C19), Calc!C4) -> 0 | H18: =IF(=Scenarios!E5=1, IF(=Scenarios!I5="lease", Calc!C5*Parameters!C16, Calc!C5*Parameters!C19), Calc!C5) -> 0 | I18: =Calc!C3 -> 0 | J18: =IF("FY2027"="FY2026", (IF(=Scenarios!D5=1, Parameters!B9,0) + IF(=Scenarios!E5=1, Parameters!B9,0)), 0) -> 0 | K18: =(1-Parameters!B4) -> 0 | L18: =Scenarios!G5 -> 0 | M18: =(IF(Scenarios!D51, IF(Scenarios!I5"lease", Calc!C4*Parameters!C16, Calc!C4*Parameters!C19), Calc!C4) + IF(Scenarios!E51, IF(Scenarios!I5"lease", Calc!C5*Parameters!C16, Calc!C5*Parameters!C19), Calc!C5) + Calc!C3*=D18+E18)*=(1-Parameters!B4)*(1-J18) + =IF("FY2027"="FY2026", (IF(=Scenarios!D5=1, Parameters!B9,0) + IF(=Scenarios!E5=1, Parameters!B9,0)), 0) -> 0 | N18: =IF(F18>0, L18/F18, NA()) -> 0 | O18: ==Scenarios!A5&"|FY2027" -> 0
A19: =Scenarios!A5 -> 0 | B19: FY2028 | C19: =Scenarios!C5 -> 0 | D19: =IF(=Scenarios!D5=1,0, Parameters!B6 + =ROUNDUP(=IF(=Scenarios!H5=1, IF("FY2028"="FY2026",50, IF("FY2028"="FY2027",100,150)), =Scenarios!C5)*=Scenarios!F5,0)) -> 0 | E19: =IF(=Scenarios!E5=1,0, Parameters!B7 + ==IF(=Scenarios!H5=1, IF("FY2028"="FY2026",50, IF("FY2028"="FY2027",100,150)), =Scenarios!C5)-(=ROUNDUP(=IF(=Scenarios!H5=1, IF("FY2028"="FY2026",50, IF("FY2028"="FY2027",100,150)), =Scenarios!C5)*=Scenarios!F5,0))) -> 0 | F19: =D19+E19 -> 0 | G19: =IF(=Scenarios!D5=1, IF(=Scenarios!I5="lease", Calc!D4*Parameters!D16, Calc!D4*Parameters!D19), Calc!D4) -> 0 | H19: =IF(=Scenarios!E5=1, IF(=Scenarios!I5="lease", Calc!D5*Parameters!D16, Calc!D5*Parameters!D19), Calc!D5) -> 0 | I19: =Calc!D3 -> 0 | J19: =IF("FY2028"="FY2026", (IF(=Scenarios!D5=1, Parameters!B9,0) + IF(=Scenarios!E5=1, Parameters!B9,0)), 0) -> 0 | K19: =(1-Parameters!B4) -> 0 | L19: =Scenarios!G5 -> 0 | M19: =(IF(Scenarios!D51, IF(Scenarios!I5"lease", Calc!D4*Parameters!D16, Calc!D4*Parameters!D19), Calc!D4) + IF(Scenarios!E51, IF(Scenarios!I5"lease", Calc!D5*Parameters!D16, Calc!D5*Parameters!D19), Calc!D5) + Calc!D3*=D19+E19)*=(1-Parameters!B4)*(1-J19) + =IF("FY2028"="FY2026", (IF(=Scenarios!D5=1, Parameters!B9,0) + IF(=Scenarios!E5=1, Parameters!B9,0)), 0) -> 0 | N19: =IF(F19>0, L19/F19, NA()) -> 0 | O19: ==Scenarios!A5&"|FY2028" -> 0
A20: =Scenarios!A5 -> 0 | B20: FY2029 | C20: =Scenarios!C5 -> 0 | D20: =IF(=Scenarios!D5=1,0, Parameters!B6 + =ROUNDUP(=IF(=Scenarios!H5=1, IF("FY2029"="FY2026",50, IF("FY2029"="FY2027",100,150)), =Scenarios!C5)*=Scenarios!F5,0)) -> 0 | E20: =IF(=Scenarios!E5=1,0, Parameters!B7 + ==IF(=Scenarios!H5=1, IF("FY2029"="FY2026",50, IF("FY2029"="FY2027",100,150)), =Scenarios!C5)-(=ROUNDUP(=IF(=Scenarios!H5=1, IF("FY2029"="FY2026",50, IF("FY2029"="FY2027",100,150)), =Scenarios!C5)*=Scenarios!F5,0))) -> 0 | F20: =D20+E20 -> 0 | G20: =IF(=Scenarios!D5=1, IF(=Scenarios!I5="lease", Calc!E4*Parameters!E16, Calc!E4*Parameters!E19), Calc!E4) -> 0 | H20: =IF(=Scenarios!E5=1, IF(=Scenarios!I5="lease", Calc!E5*Parameters!E16, Calc!E5*Parameters!E19), Calc!E5) -> 0 | I20: =Calc!E3 -> 0 | J20: =IF("FY2029"="FY2026", (IF(=Scenarios!D5=1, Parameters!B9,0) + IF(=Scenarios!E5=1, Parameters!B9,0)), 0) -> 0 | K20: =(1-Parameters!B4) -> 0 | L20: =Scenarios!G5 -> 0 | M20: =(IF(Scenarios!D51, IF(Scenarios!I5"lease", Calc!E4*Parameters!E16, Calc!E4*Parameters!E19), Calc!E4) + IF(Scenarios!E51, IF(Scenarios!I5"lease", Calc!E5*Parameters!E16, Calc!E5*Parameters!E19), Calc!E5) + Calc!E3*=D20+E20)*=(1-Parameters!B4)*(1-J20) + =IF("FY2029"="FY2026", (IF(=Scenarios!D5=1, Parameters!B9,0) + IF(=Scenarios!E5=1, Parameters!B9,0)), 0) -> 0 | N20: =IF(F20>0, L20/F20, NA()) -> 0 | O20: ==Scenarios!A5&"|FY2029" -> 0
A21: =Scenarios!A5 -> 0 | B21: FY2030 | C21: =Scenarios!C5 -> 0 | D21: =IF(=Scenarios!D5=1,0, Parameters!B6 + =ROUNDUP(=IF(=Scenarios!H5=1, IF("FY2030"="FY2026",50, IF("FY2030"="FY2027",100,150)), =Scenarios!C5)*=Scenarios!F5,0)) -> 0 | E21: =IF(=Scenarios!E5=1,0, Parameters!B7 + ==IF(=Scenarios!H5=1, IF("FY2030"="FY2026",50, IF("FY2030"="FY2027",100,150)), =Scenarios!C5)-(=ROUNDUP(=IF(=Scenarios!H5=1, IF("FY2030"="FY2026",50, IF("FY2030"="FY2027",100,150)), =Scenarios!C5)*=Scenarios!F5,0))) -> 0 | F21: =D21+E21 -> 0 | G21: =IF(=Scenarios!D5=1, IF(=Scenarios!I5="lease", Calc!F4*Parameters!F16, Calc!F4*Parameters!F19), Calc!F4) -> 0 | H21: =IF(=Scenarios!E5=1, IF(=Scenarios!I5="lease", Calc!F5*Parameters!F16, Calc!F5*Parameters!F19), Calc!F5) -> 0 | I21: =Calc!F3 -> 0 | J21: =IF("FY2030"="FY2026", (IF(=Scenarios!D5=1, Parameters!B9,0) + IF(=Scenarios!E5=1, Parameters!B9,0)), 0) -> 0 | K21: =(1-Parameters!B4) -> 0 | L21: =Scenarios!G5 -> 0 | M21: =(IF(Scenarios!D51, IF(Scenarios!I5"lease", Calc!F4*Parameters!F16, Calc!F4*Parameters!F19), Calc!F4) + IF(Scenarios!E51, IF(Scenarios!I5"lease", Calc!F5*Parameters!F16, Calc!F5*Parameters!F19), Calc!F5) + Calc!F3*=D21+E21)*=(1-Parameters!B4)*(1-J21) + =IF("FY2030"="FY2026", (IF(=Scenarios!D5=1, Parameters!B9,0) + IF(=Scenarios!E5=1, Parameters!B9,0)), 0) -> 0 | N21: =IF(F21>0, L21/F21, NA()) -> 0 | O21: ==Scenarios!A5&"|FY2030" -> 0
A22: =Scenarios!A6 -> 0 | B22: FY2026 | C22: =Scenarios!C6 -> 0 | D22: =IF(=Scenarios!D6=1,0, Parameters!B6 + =ROUNDUP(=IF(=Scenarios!H6=1, IF("FY2026"="FY2026",50, IF("FY2026"="FY2027",100,150)), =Scenarios!C6)*=Scenarios!F6,0)) -> 0 | E22: =IF(=Scenarios!E6=1,0, Parameters!B7 + ==IF(=Scenarios!H6=1, IF("FY2026"="FY2026",50, IF("FY2026"="FY2027",100,150)), =Scenarios!C6)-(=ROUNDUP(=IF(=Scenarios!H6=1, IF("FY2026"="FY2026",50, IF("FY2026"="FY2027",100,150)), =Scenarios!C6)*=Scenarios!F6,0))) -> 0 | F22: =D22+E22 -> 0 | G22: =IF(=Scenarios!D6=1, IF(=Scenarios!I6="lease", Calc!B4*Parameters!B16, Calc!B4*Parameters!B19), Calc!B4) -> 0 | H22: =IF(=Scenarios!E6=1, IF(=Scenarios!I6="lease", Calc!B5*Parameters!B16, Calc!B5*Parameters!B19), Calc!B5) -> 0 | I22: =Calc!B3 -> 0 | J22: =IF("FY2026"="FY2026", (IF(=Scenarios!D6=1, Parameters!B9,0) + IF(=Scenarios!E6=1, Parameters!B9,0)), 0) -> 0 | K22: =(1-Parameters!B4) -> 0 | L22: =Scenarios!G6 -> 0 | M22: =(IF(Scenarios!D61, IF(Scenarios!I6"lease", Calc!B4*Parameters!B16, Calc!B4*Parameters!B19), Calc!B4) + IF(Scenarios!E61, IF(Scenarios!I6"lease", Calc!B5*Parameters!B16, Calc!B5*Parameters!B19), Calc!B5) + Calc!B3*=D22+E22)*=(1-Parameters!B4)*(1-J22) + =IF("FY2026"="FY2026", (IF(=Scenarios!D6=1, Parameters!B9,0) + IF(=Scenarios!E6=1, Parameters!B9,0)), 0) -> 0 | N22: =IF(F22>0, L22/F22, NA()) -> 0 | O22: ==Scenarios!A6&"|FY2026" -> 0
A23: =Scenarios!A6 -> 0 | B23: FY2027 | C23: =Scenarios!C6 -> 0 | D23: =IF(=Scenarios!D6=1,0, Parameters!B6 + =ROUNDUP(=IF(=Scenarios!H6=1, IF("FY2027"="FY2026",50, IF("FY2027"="FY2027",100,150)), =Scenarios!C6)*=Scenarios!F6,0)) -> 0 | E23: =IF(=Scenarios!E6=1,0, Parameters!B7 + ==IF(=Scenarios!H6=1, IF("FY2027"="FY2026",50, IF("FY2027"="FY2027",100,150)), =Scenarios!C6)-(=ROUNDUP(=IF(=Scenarios!H6=1, IF("FY2027"="FY2026",50, IF("FY2027"="FY2027",100,150)), =Scenarios!C6)*=Scenarios!F6,0))) -> 0 | F23: =D23+E23 -> 0 | G23: =IF(=Scenarios!D6=1, IF(=Scenarios!I6="lease", Calc!C4*Parameters!C16, Calc!C4*Parameters!C19), Calc!C4) -> 0 | H23: =IF(=Scenarios!E6=1, IF(=Scenarios!I6="lease", Calc!C5*Parameters!C16, Calc!C5*Parameters!C19), Calc!C5) -> 0 | I23: =Calc!C3 -> 0 | J23: =IF("FY2027"="FY2026", (IF(=Scenarios!D6=1, Parameters!B9,0) + IF(=Scenarios!E6=1, Parameters!B9,0)), 0) -> 0 | K23: =(1-Parameters!B4) -> 0 | L23: =Scenarios!G6 -> 0 | M23: =(IF(Scenarios!D61, IF(Scenarios!I6"lease", Calc!C4*Parameters!C16, Calc!C4*Parameters!C19), Calc!C4) + IF(Scenarios!E61, IF(Scenarios!I6"lease", Calc!C5*Parameters!C16, Calc!C5*Parameters!C19), Calc!C5) + Calc!C3*=D23+E23)*=(1-Parameters!B4)*(1-J23) + =IF("FY2027"="FY2026", (IF(=Scenarios!D6=1, Parameters!B9,0) + IF(=Scenarios!E6=1, Parameters!B9,0)), 0) -> 0 | N23: =IF(F23>0, L23/F23, NA()) -> 0 | O23: ==Scenarios!A6&"|FY2027" -> 0
A24: =Scenarios!A6 -> 0 | B24: FY2028 | C24: =Scenarios!C6 -> 0 | D24: =IF(=Scenarios!D6=1,0, Parameters!B6 + =ROUNDUP(=IF(=Scenarios!H6=1, IF("FY2028"="FY2026",50, IF("FY2028"="FY2027",100,150)), =Scenarios!C6)*=Scenarios!F6,0)) -> 0 | E24: =IF(=Scenarios!E6=1,0, Parameters!B7 + ==IF(=Scenarios!H6=1, IF("FY2028"="FY2026",50, IF("FY2028"="FY2027",100,150)), =Scenarios!C6)-(=ROUNDUP(=IF(=Scenarios!H6=1, IF("FY2028"="FY2026",50, IF("FY2028"="FY2027",100,150)), =Scenarios!C6)*=Scenarios!F6,0))) -> 0 | F24: =D24+E24 -> 0 | G24: =IF(=Scenarios!D6=1, IF(=Scenarios!I6="lease", Calc!D4*Parameters!D16, Calc!D4*Parameters!D19), Calc!D4) -> 0 | H24: =IF(=Scenarios!E6=1, IF(=Scenarios!I6="lease", Calc!D5*Parameters!D16, Calc!D5*Parameters!D19), Calc!D5) -> 0 | I24: =Calc!D3 -> 0 | J24: =IF("FY2028"="FY2026", (IF(=Scenarios!D6=1, Parameters!B9,0) + IF(=Scenarios!E6=1, Parameters!B9,0)), 0) -> 0 | K24: =(1-Parameters!B4) -> 0 | L24: =Scenarios!G6 -> 0 | M24: =(IF(Scenarios!D61, IF(Scenarios!I6"lease", Calc!D4*Parameters!D16, Calc!D4*Parameters!D19), Calc!D4) + IF(Scenarios!E61, IF(Scenarios!I6"lease", Calc!D5*Parameters!D16, Calc!D5*Parameters!D19), Calc!D5) + Calc!D3*=D24+E24)*=(1-Parameters!B4)*(1-J24) + =IF("FY2028"="FY2026", (IF(=Scenarios!D6=1, Parameters!B9,0) + IF(=Scenarios!E6=1, Parameters!B9,0)), 0) -> 0 | N24: =IF(F24>0, L24/F24, NA()) -> 0 | O24: ==Scenarios!A6&"|FY2028" -> 0
A25: =Scenarios!A6 -> 0 | B25: FY2029 | C25: =Scenarios!C6 -> 0 | D25: =IF(=Scenarios!D6=1,0, Parameters!B6 + =ROUNDUP(=IF(=Scenarios!H6=1, IF("FY2029"="FY2026",50, IF("FY2029"="FY2027",100,150)), =Scenarios!C6)*=Scenarios!F6,0)) -> 0 | E25: =IF(=Scenarios!E6=1,0, Parameters!B7 + ==IF(=Scenarios!H6=1, IF("FY2029"="FY2026",50, IF("FY2029"="FY2027",100,150)), =Scenarios!C6)-(=ROUNDUP(=IF(=Scenarios!H6=1, IF("FY2029"="FY2026",50, IF("FY2029"="FY2027",100,150)), =Scenarios!C6)*=Scenarios!F6,0))) -> 0 | F25: =D25+E25 -> 0 | G25: =IF(=Scenarios!D6=1, IF(=Scenarios!I6="lease", Calc!E4*Parameters!E16, Calc!E4*Parameters!E19), Calc!E4) -> 0 | H25: =IF(=Scenarios!E6=1, IF(=Scenarios!I6="lease", Calc!E5*Parameters!E16, Calc!E5*Parameters!E19), Calc!E5) -> 0 | I25: =Calc!E3 -> 0 | J25: =IF("FY2029"="FY2026", (IF(=Scenarios!D6=1, Parameters!B9,0) + IF(=Scenarios!E6=1, Parameters!B9,0)), 0) -> 0 | K25: =(1-Parameters!B4) -> 0 | L25: =Scenarios!G6 -> 0 | M25: =(IF(Scenarios!D61, IF(Scenarios!I6"lease", Calc!E4*Parameters!E16, Calc!E4*Parameters!E19), Calc!E4) + IF(Scenarios!E61, IF(Scenarios!I6"lease", Calc!E5*Parameters!E16, Calc!E5*Parameters!E19), Calc!E5) + Calc!E3*=D25+E25)*=(1-Parameters!B4)*(1-J25) + =IF("FY2029"="FY2026", (IF(=Scenarios!D6=1, Parameters!B9,0) + IF(=Scenarios!E6=1, Parameters!B9,0)), 0) -> 0 | N25: =IF(F25>0, L25/F25, NA()) -> 0 | O25: ==Scenarios!A6&"|FY2029" -> 0
A26: =Scenarios!A6 -> 0 | B26: FY2030 | C26: =Scenarios!C6 -> 0 | D26: =IF(=Scenarios!D6=1,0, Parameters!B6 + =ROUNDUP(=IF(=Scenarios!H6=1, IF("FY2030"="FY2026",50, IF("FY2030"="FY2027",100,150)), =Scenarios!C6)*=Scenarios!F6,0)) -> 0 | E26: =IF(=Scenarios!E6=1,0, Parameters!B7 + ==IF(=Scenarios!H6=1, IF("FY2030"="FY2026",50, IF("FY2030"="FY2027",100,150)), =Scenarios!C6)-(=ROUNDUP(=IF(=Scenarios!H6=1, IF("FY2030"="FY2026",50, IF("FY2030"="FY2027",100,150)), =Scenarios!C6)*=Scenarios!F6,0))) -> 0 | F26: =D26+E26 -> 0 | G26: =IF(=Scenarios!D6=1, IF(=Scenarios!I6="lease", Calc!F4*Parameters!F16, Calc!F4*Parameters!F19), Calc!F4) -> 0 | H26: =IF(=Scenarios!E6=1, IF(=Scenarios!I6="lease", Calc!F5*Parameters!F16, Calc!F5*Parameters!F19), Calc!F5) -> 0 | I26: =Calc!F3 -> 0 | J26: =IF("FY2030"="FY2026", (IF(=Scenarios!D6=1, Parameters!B9,0) + IF(=Scenarios!E6=1, Parameters!B9,0)), 0) -> 0 | K26: =(1-Parameters!B4) -> 0 | L26: =Scenarios!G6 -> 0 | M26: =(IF(Scenarios!D61, IF(Scenarios!I6"lease", Calc!F4*Parameters!F16, Calc!F4*Parameters!F19), Calc!F4) + IF(Scenarios!E61, IF(Scenarios!I6"lease", Calc!F5*Parameters!F16, Calc!F5*Parameters!F19), Calc!F5) + Calc!F3*=D26+E26)*=(1-Parameters!B4)*(1-J26) + =IF("FY2030"="FY2026", (IF(=Scenarios!D6=1, Parameters!B9,0) + IF(=Scenarios!E6=1, Parameters!B9,0)), 0) -> 0 | N26: =IF(F26>0, L26/F26, NA()) -> 0 | O26: ==Scenarios!A6&"|FY2030" -> 0
A27: =Scenarios!A7 -> 0 | B27: FY2026 | C27: =Scenarios!C7 -> 0 | D27: =IF(=Scenarios!D7=1,0, Parameters!B6 + =ROUNDUP(=IF(=Scenarios!H7=1, IF("FY2026"="FY2026",50, IF("FY2026"="FY2027",100,150)), =Scenarios!C7)*=Scenarios!F7,0)) -> 0 | E27: =IF(=Scenarios!E7=1,0, Parameters!B7 + ==IF(=Scenarios!H7=1, IF("FY2026"="FY2026",50, IF("FY2026"="FY2027",100,150)), =Scenarios!C7)-(=ROUNDUP(=IF(=Scenarios!H7=1, IF("FY2026"="FY2026",50, IF("FY2026"="FY2027",100,150)), =Scenarios!C7)*=Scenarios!F7,0))) -> 0 | F27: =D27+E27 -> 0 | G27: =IF(=Scenarios!D7=1, IF(=Scenarios!I7="lease", Calc!B4*Parameters!B16, Calc!B4*Parameters!B19), Calc!B4) -> 0 | H27: =IF(=Scenarios!E7=1, IF(=Scenarios!I7="lease", Calc!B5*Parameters!B16, Calc!B5*Parameters!B19), Calc!B5) -> 0 | I27: =Calc!B3 -> 0 | J27: =IF("FY2026"="FY2026", (IF(=Scenarios!D7=1, Parameters!B9,0) + IF(=Scenarios!E7=1, Parameters!B9,0)), 0) -> 0 | K27: =(1-Parameters!B4) -> 0 | L27: =Scenarios!G7 -> 0 | M27: =(IF(Scenarios!D71, IF(Scenarios!I7"lease", Calc!B4*Parameters!B16, Calc!B4*Parameters!B19), Calc!B4) + IF(Scenarios!E71, IF(Scenarios!I7"lease", Calc!B5*Parameters!B16, Calc!B5*Parameters!B19), Calc!B5) + Calc!B3*=D27+E27)*=(1-Parameters!B4)*(1-J27) + =IF("FY2026"="FY2026", (IF(=Scenarios!D7=1, Parameters!B9,0) + IF(=Scenarios!E7=1, Parameters!B9,0)), 0) -> 0 | N27: =IF(F27>0, L27/F27, NA()) -> 0 | O27: ==Scenarios!A7&"|FY2026" -> 0
A28: =Scenarios!A7 -> 0 | B28: FY2027 | C28: =Scenarios!C7 -> 0 | D28: =IF(=Scenarios!D7=1,0, Parameters!B6 + =ROUNDUP(=IF(=Scenarios!H7=1, IF("FY2027"="FY2026",50, IF("FY2027"="FY2027",100,150)), =Scenarios!C7)*=Scenarios!F7,0)) -> 0 | E28: =IF(=Scenarios!E7=1,0, Parameters!B7 + ==IF(=Scenarios!H7=1, IF("FY2027"="FY2026",50, IF("FY2027"="FY2027",100,150)), =Scenarios!C7)-(=ROUNDUP(=IF(=Scenarios!H7=1, IF("FY2027"="FY2026",50, IF("FY2027"="FY2027",100,150)), =Scenarios!C7)*=Scenarios!F7,0))) -> 0 | F28: =D28+E28 -> 0 | G28: =IF(=Scenarios!D7=1, IF(=Scenarios!I7="lease", Calc!C4*Parameters!C16, Calc!C4*Parameters!C19), Calc!C4) -> 0 | H28: =IF(=Scenarios!E7=1, IF(=Scenarios!I7="lease", Calc!C5*Parameters!C16, Calc!C5*Parameters!C19), Calc!C5) -> 0 | I28: =Calc!C3 -> 0 | J28: =IF("FY2027"="FY2026", (IF(=Scenarios!D7=1, Parameters!B9,0) + IF(=Scenarios!E7=1, Parameters!B9,0)), 0) -> 0 | K28: =(1-Parameters!B4) -> 0 | L28: =Scenarios!G7 -> 0 | M28: =(IF(Scenarios!D71, IF(Scenarios!I7"lease", Calc!C4*Parameters!C16, Calc!C4*Parameters!C19), Calc!C4) + IF(Scenarios!E71, IF(Scenarios!I7"lease", Calc!C5*Parameters!C16, Calc!C5*Parameters!C19), Calc!C5) + Calc!C3*=D28+E28)*=(1-Parameters!B4)*(1-J28) + =IF("FY2027"="FY2026", (IF(=Scenarios!D7=1, Parameters!B9,0) + IF(=Scenarios!E7=1, Parameters!B9,0)), 0) -> 0 | N28: =IF(F28>0, L28/F28, NA()) -> 0 | O28: ==Scenarios!A7&"|FY2027" -> 0
A29: =Scenarios!A7 -> 0 | B29: FY2028 | C29: =Scenarios!C7 -> 0 | D29: =IF(=Scenarios!D7=1,0, Parameters!B6 + =ROUNDUP(=IF(=Scenarios!H7=1, IF("FY2028"="FY2026",50, IF("FY2028"="FY2027",100,150)), =Scenarios!C7)*=Scenarios!F7,0)) -> 0 | E29: =IF(=Scenarios!E7=1,0, Parameters!B7 + ==IF(=Scenarios!H7=1, IF("FY2028"="FY2026",50, IF("FY2028"="FY2027",100,150)), =Scenarios!C7)-(=ROUNDUP(=IF(=Scenarios!H7=1, IF("FY2028"="FY2026",50, IF("FY2028"="FY2027",100,150)), =Scenarios!C7)*=Scenarios!F7,0))) -> 0 | F29: =D29+E29 -> 0 | G29: =IF(=Scenarios!D7=1, IF(=Scenarios!I7="lease", Calc!D4*Parameters!D16, Calc!D4*Parameters!D19), Calc!D4) -> 0 | H29: =IF(=Scenarios!E7=1, IF(=Scenarios!I7="lease", Calc!D5*Parameters!D16, Calc!D5*Parameters!D19), Calc!D5) -> 0 | I29: =Calc!D3 -> 0 | J29: =IF("FY2028"="FY2026", (IF(=Scenarios!D7=1, Parameters!B9,0) + IF(=Scenarios!E7=1, Parameters!B9,0)), 0) -> 0 | K29: =(1-Parameters!B4) -> 0 | L29: =Scenarios!G7 -> 0 | M29: =(IF(Scenarios!D71, IF(Scenarios!I7"lease", Calc!D4*Parameters!D16, Calc!D4*Parameters!D19), Calc!D4) + IF(Scenarios!E71, IF(Scenarios!I7"lease", Calc!D5*Parameters!D16, Calc!D5*Parameters!D19), Calc!D5) + Calc!D3*=D29+E29)*=(1-Parameters!B4)*(1-J29) + =IF("FY2028"="FY2026", (IF(=Scenarios!D7=1, Parameters!B9,0) + IF(=Scenarios!E7=1, Parameters!B9,0)), 0) -> 0 | N29: =IF(F29>0, L29/F29, NA()) -> 0 | O29: ==Scenarios!A7&"|FY2028" -> 0
A30: =Scenarios!A7 -> 0 | B30: FY2029 | C30: =Scenarios!C7 -> 0 | D30: =IF(=Scenarios!D7=1,0, Parameters!B6 + =ROUNDUP(=IF(=Scenarios!H7=1, IF("FY2029"="FY2026",50, IF("FY2029"="FY2027",100,150)), =Scenarios!C7)*=Scenarios!F7,0)) -> 0 | E30: =IF(=Scenarios!E7=1,0, Parameters!B7 + ==IF(=Scenarios!H7=1, IF("FY2029"="FY2026",50, IF("FY2029"="FY2027",100,150)), =Scenarios!C7)-(=ROUNDUP(=IF(=Scenarios!H7=1, IF("FY2029"="FY2026",50, IF("FY2029"="FY2027",100,150)), =Scenarios!C7)*=Scenarios!F7,0))) -> 0 | F30: =D30+E30 -> 0 | G30: =IF(=Scenarios!D7=1, IF(=Scenarios!I7="lease", Calc!E4*Parameters!E16, Calc!E4*Parameters!E19), Calc!E4) -> 0 | H30: =IF(=Scenarios!E7=1, IF(=Scenarios!I7="lease", Calc!E5*Parameters!E16, Calc!E5*Parameters!E19), Calc!E5) -> 0 | I30: =Calc!E3 -> 0 | J30: =IF("FY2029"="FY2026", (IF(=Scenarios!D7=1, Parameters!B9,0) + IF(=Scenarios!E7=1, Parameters!B9,0)), 0) -> 0 | K30: =(1-Parameters!B4) -> 0 | L30: =Scenarios!G7 -> 0 | M30: =(IF(Scenarios!D71, IF(Scenarios!I7"lease", Calc!E4*Parameters!E16, Calc!E4*Parameters!E19), Calc!E4) + IF(Scenarios!E71, IF(Scenarios!I7"lease", Calc!E5*Parameters!E16, Calc!E5*Parameters!E19), Calc!E5) + Calc!E3*=D30+E30)*=(1-Parameters!B4)*(1-J30) + =IF("FY2029"="FY2026", (IF(=Scenarios!D7=1, Parameters!B9,0) + IF(=Scenarios!E7=1, Parameters!B9,0)), 0) -> 0 | N30: =IF(F30>0, L30/F30, NA()) -> 0 | O30: ==Scenarios!A7&"|FY2029" -> 0
A31: =Scenarios!A7 -> 0 | B31: FY2030 | C31: =Scenarios!C7 -> 0 | D31: =IF(=Scenarios!D7=1,0, Parameters!B6 + =ROUNDUP(=IF(=Scenarios!H7=1, IF("FY2030"="FY2026",50, IF("FY2030"="FY2027",100,150)), =Scenarios!C7)*=Scenarios!F7,0)) -> 0 | E31: =IF(=Scenarios!E7=1,0, Parameters!B7 + ==IF(=Scenarios!H7=1, IF("FY2030"="FY2026",50, IF("FY2030"="FY2027",100,150)), =Scenarios!C7)-(=ROUNDUP(=IF(=Scenarios!H7=1, IF("FY2030"="FY2026",50, IF("FY2030"="FY2027",100,150)), =Scenarios!C7)*=Scenarios!F7,0))) -> 0 | F31: =D31+E31 -> 0 | G31: =IF(=Scenarios!D7=1, IF(=Scenarios!I7="lease", Calc!F4*Parameters!F16, Calc!F4*Parameters!F19), Calc!F4) -> 0 | H31: =IF(=Scenarios!E7=1, IF(=Scenarios!I7="lease", Calc!F5*Parameters!F16, Calc!F5*Parameters!F19), Calc!F5) -> 0 | I31: =Calc!F3 -> 0 | J31: =IF("FY2030"="FY2026", (IF(=Scenarios!D7=1, Parameters!B9,0) + IF(=Scenarios!E7=1, Parameters!B9,0)), 0) -> 0 | K31: =(1-Parameters!B4) -> 0 | L31: =Scenarios!G7 -> 0 | M31: =(IF(Scenarios!D71, IF(Scenarios!I7"lease", Calc!F4*Parameters!F16, Calc!F4*Parameters!F19), Calc!F4) + IF(Scenarios!E71, IF(Scenarios!I7"lease", Calc!F5*Parameters!F16, Calc!F5*Parameters!F19), Calc!F5) + Calc!F3*=D31+E31)*=(1-Parameters!B4)*(1-J31) + =IF("FY2030"="FY2026", (IF(=Scenarios!D7=1, Parameters!B9,0) + IF(=Scenarios!E7=1, Parameters!B9,0)), 0) -> 0 | N31: =IF(F31>0, L31/F31, NA()) -> 0 | O31: ==Scenarios!A7&"|FY2030" -> 0
A32: =Scenarios!A8 -> 0 | B32: FY2026 | C32: =Scenarios!C8 -> 0 | D32: =IF(=Scenarios!D8=1,0, Parameters!B6 + =ROUNDUP(=IF(=Scenarios!H8=1, IF("FY2026"="FY2026",50, IF("FY2026"="FY2027",100,150)), =Scenarios!C8)*=Scenarios!F8,0)) -> 0 | E32: =IF(=Scenarios!E8=1,0, Parameters!B7 + ==IF(=Scenarios!H8=1, IF("FY2026"="FY2026",50, IF("FY2026"="FY2027",100,150)), =Scenarios!C8)-(=ROUNDUP(=IF(=Scenarios!H8=1, IF("FY2026"="FY2026",50, IF("FY2026"="FY2027",100,150)), =Scenarios!C8)*=Scenarios!F8,0))) -> 0 | F32: =D32+E32 -> 0 | G32: =IF(=Scenarios!D8=1, IF(=Scenarios!I8="lease", Calc!B4*Parameters!B16, Calc!B4*Parameters!B19), Calc!B4) -> 0 | H32: =IF(=Scenarios!E8=1, IF(=Scenarios!I8="lease", Calc!B5*Parameters!B16, Calc!B5*Parameters!B19), Calc!B5) -> 0 | I32: =Calc!B3 -> 0 | J32: =IF("FY2026"="FY2026", (IF(=Scenarios!D8=1, Parameters!B9,0) + IF(=Scenarios!E8=1, Parameters!B9,0)), 0) -> 0 | K32: =(1-Parameters!B4) -> 0 | L32: =Scenarios!G8 -> 0 | M32: =(IF(Scenarios!D81, IF(Scenarios!I8"lease", Calc!B4*Parameters!B16, Calc!B4*Parameters!B19), Calc!B4) + IF(Scenarios!E81, IF(Scenarios!I8"lease", Calc!B5*Parameters!B16, Calc!B5*Parameters!B19), Calc!B5) + Calc!B3*=D32+E32)*=(1-Parameters!B4)*(1-J32) + =IF("FY2026"="FY2026", (IF(=Scenarios!D8=1, Parameters!B9,0) + IF(=Scenarios!E8=1, Parameters!B9,0)), 0) -> 0 | N32: =IF(F32>0, L32/F32, NA()) -> 0 | O32: ==Scenarios!A8&"|FY2026" -> 0
A33: =Scenarios!A8 -> 0 | B33: FY2027 | C33: =Scenarios!C8 -> 0 | D33: =IF(=Scenarios!D8=1,0, Parameters!B6 + =ROUNDUP(=IF(=Scenarios!H8=1, IF("FY2027"="FY2026",50, IF("FY2027"="FY2027",100,150)), =Scenarios!C8)*=Scenarios!F8,0)) -> 0 | E33: =IF(=Scenarios!E8=1,0, Parameters!B7 + ==IF(=Scenarios!H8=1, IF("FY2027"="FY2026",50, IF("FY2027"="FY2027",100,150)), =Scenarios!C8)-(=ROUNDUP(=IF(=Scenarios!H8=1, IF("FY2027"="FY2026",50, IF("FY2027"="FY2027",100,150)), =Scenarios!C8)*=Scenarios!F8,0))) -> 0 | F33: =D33+E33 -> 0 | G33: =IF(=Scenarios!D8=1, IF(=Scenarios!I8="lease", Calc!C4*Parameters!C16, Calc!C4*Parameters!C19), Calc!C4) -> 0 | H33: =IF(=Scenarios!E8=1, IF(=Scenarios!I8="lease", Calc!C5*Parameters!C16, Calc!C5*Parameters!C19), Calc!C5) -> 0 | I33: =Calc!C3 -> 0 | J33: =IF("FY2027"="FY2026", (IF(=Scenarios!D8=1, Parameters!B9,0) + IF(=Scenarios!E8=1, Parameters!B9,0)), 0) -> 0 | K33: =(1-Parameters!B4) -> 0 | L33: =Scenarios!G8 -> 0 | M33: =(IF(Scenarios!D81, IF(Scenarios!I8"lease", Calc!C4*Parameters!C16, Calc!C4*Parameters!C19), Calc!C4) + IF(Scenarios!E81, IF(Scenarios!I8"lease", Calc!C5*Parameters!C16, Calc!C5*Parameters!C19), Calc!C5) + Calc!C3*=D33+E33)*=(1-Parameters!B4)*(1-J33) + =IF("FY2027"="FY2026", (IF(=Scenarios!D8=1, Parameters!B9,0) + IF(=Scenarios!E8=1, Parameters!B9,0)), 0) -> 0 | N33: =IF(F33>0, L33/F33, NA()) -> 0 | O33: ==Scenarios!A8&"|FY2027" -> 0
A34: =Scenarios!A8 -> 0 | B34: FY2028 | C34: =Scenarios!C8 -> 0 | D34: =IF(=Scenarios!D8=1,0, Parameters!B6 + =ROUNDUP(=IF(=Scenarios!H8=1, IF("FY2028"="FY2026",50, IF("FY2028"="FY2027",100,150)), =Scenarios!C8)*=Scenarios!F8,0)) -> 0 | E34: =IF(=Scenarios!E8=1,0, Parameters!B7 + ==IF(=Scenarios!H8=1, IF("FY2028"="FY2026",50, IF("FY2028"="FY2027",100,150)), =Scenarios!C8)-(=ROUNDUP(=IF(=Scenarios!H8=1, IF("FY2028"="FY2026",50, IF("FY2028"="FY2027",100,150)), =Scenarios!C8)*=Scenarios!F8,0))) -> 0 | F34: =D34+E34 -> 0 | G34: =IF(=Scenarios!D8=1, IF(=Scenarios!I8="lease", Calc!D4*Parameters!D16, Calc!D4*Parameters!D19), Calc!D4) -> 0 | H34: =IF(=Scenarios!E8=1, IF(=Scenarios!I8="lease", Calc!D5*Parameters!D16, Calc!D5*Parameters!D19), Calc!D5) -> 0 | I34: =Calc!D3 -> 0 | J34: =IF("FY2028"="FY2026", (IF(=Scenarios!D8=1, Parameters!B9,0) + IF(=Scenarios!E8=1, Parameters!B9,0)), 0) -> 0 | K34: =(1-Parameters!B4) -> 0 | L34: =Scenarios!G8 -> 0 | M34: =(IF(Scenarios!D81, IF(Scenarios!I8"lease", Calc!D4*Parameters!D16, Calc!D4*Parameters!D19), Calc!D4) + IF(Scenarios!E81, IF(Scenarios!I8"lease", Calc!D5*Parameters!D16, Calc!D5*Parameters!D19), Calc!D5) + Calc!D3*=D34+E34)*=(1-Parameters!B4)*(1-J34) + =IF("FY2028"="FY2026", (IF(=Scenarios!D8=1, Parameters!B9,0) + IF(=Scenarios!E8=1, Parameters!B9,0)), 0) -> 0 | N34: =IF(F34>0, L34/F34, NA()) -> 0 | O34: ==Scenarios!A8&"|FY2028" -> 0
A35: =Scenarios!A8 -> 0 | B35: FY2029 | C35: =Scenarios!C8 -> 0 | D35: =IF(=Scenarios!D8=1,0, Parameters!B6 + =ROUNDUP(=IF(=Scenarios!H8=1, IF("FY2029"="FY2026",50, IF("FY2029"="FY2027",100,150)), =Scenarios!C8)*=Scenarios!F8,0)) -> 0 | E35: =IF(=Scenarios!E8=1,0, Parameters!B7 + ==IF(=Scenarios!H8=1, IF("FY2029"="FY2026",50, IF("FY2029"="FY2027",100,150)), =Scenarios!C8)-(=ROUNDUP(=IF(=Scenarios!H8=1, IF("FY2029"="FY2026",50, IF("FY2029"="FY2027",100,150)), =Scenarios!C8)*=Scenarios!F8,0))) -> 0 | F35: =D35+E35 -> 0 | G35: =IF(=Scenarios!D8=1, IF(=Scenarios!I8="lease", Calc!E4*Parameters!E16, Calc!E4*Parameters!E19), Calc!E4) -> 0 | H35: =IF(=Scenarios!E8=1, IF(=Scenarios!I8="lease", Calc!E5*Parameters!E16, Calc!E5*Parameters!E19), Calc!E5) -> 0 | I35: =Calc!E3 -> 0 | J35: =IF("FY2029"="FY2026", (IF(=Scenarios!D8=1, Parameters!B9,0) + IF(=Scenarios!E8=1, Parameters!B9,0)), 0) -> 0 | K35: =(1-Parameters!B4) -> 0 | L35: =Scenarios!G8 -> 0 | M35: =(IF(Scenarios!D81, IF(Scenarios!I8"lease", Calc!E4*Parameters!E16, Calc!E4*Parameters!E19), Calc!E4) + IF(Scenarios!E81, IF(Scenarios!I8"lease", Calc!E5*Parameters!E16, Calc!E5*Parameters!E19), Calc!E5) + Calc!E3*=D35+E35)*=(1-Parameters!B4)*(1-J35) + =IF("FY2029"="FY2026", (IF(=Scenarios!D8=1, Parameters!B9,0) + IF(=Scenarios!E8=1, Parameters!B9,0)), 0) -> 0 | N35: =IF(F35>0, L35/F35, NA()) -> 0 | O35: ==Scenarios!A8&"|FY2029" -> 0
A36: =Scenarios!A8 -> 0 | B36: FY2030 | C36: =Scenarios!C8 -> 0 | D36: =IF(=Scenarios!D8=1,0, Parameters!B6 + =ROUNDUP(=IF(=Scenarios!H8=1, IF("FY2030"="FY2026",50, IF("FY2030"="FY2027",100,150)), =Scenarios!C8)*=Scenarios!F8,0)) -> 0 | E36: =IF(=Scenarios!E8=1,0, Parameters!B7 + ==IF(=Scenarios!H8=1, IF("FY2030"="FY2026",50, IF("FY2030"="FY2027",100,150)), =Scenarios!C8)-(=ROUNDUP(=IF(=Scenarios!H8=1, IF("FY2030"="FY2026",50, IF("FY2030"="FY2027",100,150)), =Scenarios!C8)*=Scenarios!F8,0))) -> 0 | F36: =D36+E36 -> 0 | G36: =IF(=Scenarios!D8=1, IF(=Scenarios!I8="lease", Calc!F4*Parameters!F16, Calc!F4*Parameters!F19), Calc!F4) -> 0 | H36: =IF(=Scenarios!E8=1, IF(=Scenarios!I8="lease", Calc!F5*Parameters!F16, Calc!F5*Parameters!F19), Calc!F5) -> 0 | I36: =Calc!F3 -> 0 | J36: =IF("FY2030"="FY2026", (IF(=Scenarios!D8=1, Parameters!B9,0) + IF(=Scenarios!E8=1, Parameters!B9,0)), 0) -> 0 | K36: =(1-Parameters!B4) -> 0 | L36: =Scenarios!G8 -> 0 | M36: =(IF(Scenarios!D81, IF(Scenarios!I8"lease", Calc!F4*Parameters!F16, Calc!F4*Parameters!F19), Calc!F4) + IF(Scenarios!E81, IF(Scenarios!I8"lease", Calc!F5*Parameters!F16, Calc!F5*Parameters!F19), Calc!F5) + Calc!F3*=D36+E36)*=(1-Parameters!B4)*(1-J36) + =IF("FY2030"="FY2026", (IF(=Scenarios!D8=1, Parameters!B9,0) + IF(=Scenarios!E8=1, Parameters!B9,0)), 0) -> 0 | N36: =IF(F36>0, L36/F36, NA()) -> 0 | O36: ==Scenarios!A8&"|FY2030" -> 0
A37: =Scenarios!A9 -> 0 | B37: FY2026 | C37: =Scenarios!C9 -> 0 | D37: =IF(=Scenarios!D9=1,0, Parameters!B6 + =ROUNDUP(=IF(=Scenarios!H9=1, IF("FY2026"="FY2026",50, IF("FY2026"="FY2027",100,150)), =Scenarios!C9)*=Scenarios!F9,0)) -> 0 | E37: =IF(=Scenarios!E9=1,0, Parameters!B7 + ==IF(=Scenarios!H9=1, IF("FY2026"="FY2026",50, IF("FY2026"="FY2027",100,150)), =Scenarios!C9)-(=ROUNDUP(=IF(=Scenarios!H9=1, IF("FY2026"="FY2026",50, IF("FY2026"="FY2027",100,150)), =Scenarios!C9)*=Scenarios!F9,0))) -> 0 | F37: =D37+E37 -> 0 | G37: =IF(=Scenarios!D9=1, IF(=Scenarios!I9="lease", Calc!B4*Parameters!B16, Calc!B4*Parameters!B19), Calc!B4) -> 0 | H37: =IF(=Scenarios!E9=1, IF(=Scenarios!I9="lease", Calc!B5*Parameters!B16, Calc!B5*Parameters!B19), Calc!B5) -> 0 | I37: =Calc!B3 -> 0 | J37: =IF("FY2026"="FY2026", (IF(=Scenarios!D9=1, Parameters!B9,0) + IF(=Scenarios!E9=1, Parameters!B9,0)), 0) -> 0 | K37: =(1-Parameters!B4) -> 0 | L37: =Scenarios!G9 -> 0 | M37: =(IF(Scenarios!D91, IF(Scenarios!I9"lease", Calc!B4*Parameters!B16, Calc!B4*Parameters!B19), Calc!B4) + IF(Scenarios!E91, IF(Scenarios!I9"lease", Calc!B5*Parameters!B16, Calc!B5*Parameters!B19), Calc!B5) + Calc!B3*=D37+E37)*=(1-Parameters!B4)*(1-J37) + =IF("FY2026"="FY2026", (IF(=Scenarios!D9=1, Parameters!B9,0) + IF(=Scenarios!E9=1, Parameters!B9,0)), 0) -> 0 | N37: =IF(F37>0, L37/F37, NA()) -> 0 | O37: ==Scenarios!A9&"|FY2026" -> 0
A38: =Scenarios!A9 -> 0 | B38: FY2027 | C38: =Scenarios!C9 -> 0 | D38: =IF(=Scenarios!D9=1,0, Parameters!B6 + =ROUNDUP(=IF(=Scenarios!H9=1, IF("FY2027"="FY2026",50, IF("FY2027"="FY2027",100,150)), =Scenarios!C9)*=Scenarios!F9,0)) -> 0 | E38: =IF(=Scenarios!E9=1,0, Parameters!B7 + ==IF(=Scenarios!H9=1, IF("FY2027"="FY2026",50, IF("FY2027"="FY2027",100,150)), =Scenarios!C9)-(=ROUNDUP(=IF(=Scenarios!H9=1, IF("FY2027"="FY2026",50, IF("FY2027"="FY2027",100,150)), =Scenarios!C9)*=Scenarios!F9,0))) -> 0 | F38: =D38+E38 -> 0 | G38: =IF(=Scenarios!D9=1, IF(=Scenarios!I9="lease", Calc!C4*Parameters!C16, Calc!C4*Parameters!C19), Calc!C4) -> 0 | H38: =IF(=Scenarios!E9=1, IF(=Scenarios!I9="lease", Calc!C5*Parameters!C16, Calc!C5*Parameters!C19), Calc!C5) -> 0 | I38: =Calc!C3 -> 0 | J38: =IF("FY2027"="FY2026", (IF(=Scenarios!D9=1, Parameters!B9,0) + IF(=Scenarios!E9=1, Parameters!B9,0)), 0) -> 0 | K38: =(1-Parameters!B4) -> 0 | L38: =Scenarios!G9 -> 0 | M38: =(IF(Scenarios!D91, IF(Scenarios!I9"lease", Calc!C4*Parameters!C16, Calc!C4*Parameters!C19), Calc!C4) + IF(Scenarios!E91, IF(Scenarios!I9"lease", Calc!C5*Parameters!C16, Calc!C5*Parameters!C19), Calc!C5) + Calc!C3*=D38+E38)*=(1-Parameters!B4)*(1-J38) + =IF("FY2027"="FY2026", (IF(=Scenarios!D9=1, Parameters!B9,0) + IF(=Scenarios!E9=1, Parameters!B9,0)), 0) -> 0 | N38: =IF(F38>0, L38/F38, NA()) -> 0 | O38: ==Scenarios!A9&"|FY2027" -> 0
A39: =Scenarios!A9 -> 0 | B39: FY2028 | C39: =Scenarios!C9 -> 0 | D39: =IF(=Scenarios!D9=1,0, Parameters!B6 + =ROUNDUP(=IF(=Scenarios!H9=1, IF("FY2028"="FY2026",50, IF("FY2028"="FY2027",100,150)), =Scenarios!C9)*=Scenarios!F9,0)) -> 0 | E39: =IF(=Scenarios!E9=1,0, Parameters!B7 + ==IF(=Scenarios!H9=1, IF("FY2028"="FY2026",50, IF("FY2028"="FY2027",100,150)), =Scenarios!C9)-(=ROUNDUP(=IF(=Scenarios!H9=1, IF("FY2028"="FY2026",50, IF("FY2028"="FY2027",100,150)), =Scenarios!C9)*=Scenarios!F9,0))) -> 0 | F39: =D39+E39 -> 0 | G39: =IF(=Scenarios!D9=1, IF(=Scenarios!I9="lease", Calc!D4*Parameters!D16, Calc!D4*Parameters!D19), Calc!D4) -> 0 | H39: =IF(=Scenarios!E9=1, IF(=Scenarios!I9="lease", Calc!D5*Parameters!D16, Calc!D5*Parameters!D19), Calc!D5) -> 0 | I39: =Calc!D3 -> 0 | J39: =IF("FY2028"="FY2026", (IF(=Scenarios!D9=1, Parameters!B9,0) + IF(=Scenarios!E9=1, Parameters!B9,0)), 0) -> 0 | K39: =(1-Parameters!B4) -> 0 | L39: =Scenarios!G9 -> 0 | M39: =(IF(Scenarios!D91, IF(Scenarios!I9"lease", Calc!D4*Parameters!D16, Calc!D4*Parameters!D19), Calc!D4) + IF(Scenarios!E91, IF(Scenarios!I9"lease", Calc!D5*Parameters!D16, Calc!D5*Parameters!D19), Calc!D5) + Calc!D3*=D39+E39)*=(1-Parameters!B4)*(1-J39) + =IF("FY2028"="FY2026", (IF(=Scenarios!D9=1, Parameters!B9,0) + IF(=Scenarios!E9=1, Parameters!B9,0)), 0) -> 0 | N39: =IF(F39>0, L39/F39, NA()) -> 0 | O39: ==Scenarios!A9&"|FY2028" -> 0
A40: =Scenarios!A9 -> 0 | B40: FY2029 | C40: =Scenarios!C9 -> 0 | D40: =IF(=Scenarios!D9=1,0, Parameters!B6 + =ROUNDUP(=IF(=Scenarios!H9=1, IF("FY2029"="FY2026",50, IF("FY2029"="FY2027",100,150)), =Scenarios!C9)*=Scenarios!F9,0)) -> 0 | E40: =IF(=Scenarios!E9=1,0, Parameters!B7 + ==IF(=Scenarios!H9=1, IF("FY2029"="FY2026",50, IF("FY2029"="FY2027",100,150)), =Scenarios!C9)-(=ROUNDUP(=IF(=Scenarios!H9=1, IF("FY2029"="FY2026",50, IF("FY2029"="FY2027",100,150)), =Scenarios!C9)*=Scenarios!F9,0))) -> 0 | F40: =D40+E40 -> 0 | G40: =IF(=Scenarios!D9=1, IF(=Scenarios!I9="lease", Calc!E4*Parameters!E16, Calc!E4*Parameters!E19), Calc!E4) -> 0 | H40: =IF(=Scenarios!E9=1, IF(=Scenarios!I9="lease", Calc!E5*Parameters!E16, Calc!E5*Parameters!E19), Calc!E5) -> 0 | I40: =Calc!E3 -> 0 | J40: =IF("FY2029"="FY2026", (IF(=Scenarios!D9=1, Parameters!B9,0) + IF(=Scenarios!E9=1, Parameters!B9,0)), 0) -> 0 | K40: =(1-Parameters!B4) -> 0 | L40: =Scenarios!G9 -> 0 | M40: =(IF(Scenarios!D91, IF(Scenarios!I9"lease", Calc!E4*Parameters!E16, Calc!E4*Parameters!E19), Calc!E4) + IF(Scenarios!E91, IF(Scenarios!I9"lease", Calc!E5*Parameters!E16, Calc!E5*Parameters!E19), Calc!E5) + Calc!E3*=D40+E40)*=(1-Parameters!B4)*(1-J40) + =IF("FY2029"="FY2026", (IF(=Scenarios!D9=1, Parameters!B9,0) + IF(=Scenarios!E9=1, Parameters!B9,0)), 0) -> 0 | N40: =IF(F40>0, L40/F40, NA()) -> 0 | O40: ==Scenarios!A9&"|FY2029" -> 0
A41: =Scenarios!A9 -> 0 | B41: FY2030 | C41: =Scenarios!C9 -> 0 | D41: =IF(=Scenarios!D9=1,0, Parameters!B6 + =ROUNDUP(=IF(=Scenarios!H9=1, IF("FY2030"="FY2026",50, IF("FY2030"="FY2027",100,150)), =Scenarios!C9)*=Scenarios!F9,0)) -> 0 | E41: =IF(=Scenarios!E9=1,0, Parameters!B7 + ==IF(=Scenarios!H9=1, IF("FY2030"="FY2026",50, IF("FY2030"="FY2027",100,150)), =Scenarios!C9)-(=ROUNDUP(=IF(=Scenarios!H9=1, IF("FY2030"="FY2026",50, IF("FY2030"="FY2027",100,150)), =Scenarios!C9)*=Scenarios!F9,0))) -> 0 | F41: =D41+E41 -> 0 | G41: =IF(=Scenarios!D9=1, IF(=Scenarios!I9="lease", Calc!F4*Parameters!F16, Calc!F4*Parameters!F19), Calc!F4) -> 0 | H41: =IF(=Scenarios!E9=1, IF(=Scenarios!I9="lease", Calc!F5*Parameters!F16, Calc!F5*Parameters!F19), Calc!F5) -> 0 | I41: =Calc!F3 -> 0 | J41: =IF("FY2030"="FY2026", (IF(=Scenarios!D9=1, Parameters!B9,0) + IF(=Scenarios!E9=1, Parameters!B9,0)), 0) -> 0 | K41: =(1-Parameters!B4) -> 0 | L41: =Scenarios!G9 -> 0 | M41: =(IF(Scenarios!D91, IF(Scenarios!I9"lease", Calc!F4*Parameters!F16, Calc!F4*Parameters!F19), Calc!F4) + IF(Scenarios!E91, IF(Scenarios!I9"lease", Calc!F5*Parameters!F16, Calc!F5*Parameters!F19), Calc!F5) + Calc!F3*=D41+E41)*=(1-Parameters!B4)*(1-J41) + =IF("FY2030"="FY2026", (IF(=Scenarios!D9=1, Parameters!B9,0) + IF(=Scenarios!E9=1, Parameters!B9,0)), 0) -> 0 | N41: =IF(F41>0, L41/F41, NA()) -> 0 | O41: ==Scenarios!A9&"|FY2030" -> 0
A42: =Scenarios!A10 -> 0 | B42: FY2026 | C42: =Scenarios!C10 -> 0 | D42: =IF(=Scenarios!D10=1,0, Parameters!B6 + =ROUNDUP(=IF(=Scenarios!H10=1, IF("FY2026"="FY2026",50, IF("FY2026"="FY2027",100,150)), =Scenarios!C10)*=Scenarios!F10,0)) -> 0 | E42: =IF(=Scenarios!E10=1,0, Parameters!B7 + ==IF(=Scenarios!H10=1, IF("FY2026"="FY2026",50, IF("FY2026"="FY2027",100,150)), =Scenarios!C10)-(=ROUNDUP(=IF(=Scenarios!H10=1, IF("FY2026"="FY2026",50, IF("FY2026"="FY2027",100,150)), =Scenarios!C10)*=Scenarios!F10,0))) -> 0 | F42: =D42+E42 -> 0 | G42: =IF(=Scenarios!D10=1, IF(=Scenarios!I10="lease", Calc!B4*Parameters!B16, Calc!B4*Parameters!B19), Calc!B4) -> 0 | H42: =IF(=Scenarios!E10=1, IF(=Scenarios!I10="lease", Calc!B5*Parameters!B16, Calc!B5*Parameters!B19), Calc!B5) -> 0 | I42: =Calc!B3 -> 0 | J42: =IF("FY2026"="FY2026", (IF(=Scenarios!D10=1, Parameters!B9,0) + IF(=Scenarios!E10=1, Parameters!B9,0)), 0) -> 0 | K42: =(1-Parameters!B4) -> 0 | L42: =Scenarios!G10 -> 0 | M42: =(IF(Scenarios!D101, IF(Scenarios!I10"lease", Calc!B4*Parameters!B16, Calc!B4*Parameters!B19), Calc!B4) + IF(Scenarios!E101, IF(Scenarios!I10"lease", Calc!B5*Parameters!B16, Calc!B5*Parameters!B19), Calc!B5) + Calc!B3*=D42+E42)*=(1-Parameters!B4)*(1-J42) + =IF("FY2026"="FY2026", (IF(=Scenarios!D10=1, Parameters!B9,0) + IF(=Scenarios!E10=1, Parameters!B9,0)), 0) -> 0 | N42: =IF(F42>0, L42/F42, NA()) -> 0 | O42: ==Scenarios!A10&"|FY2026" -> 0
A43: =Scenarios!A10 -> 0 | B43: FY2027 | C43: =Scenarios!C10 -> 0 | D43: =IF(=Scenarios!D10=1,0, Parameters!B6 + =ROUNDUP(=IF(=Scenarios!H10=1, IF("FY2027"="FY2026",50, IF("FY2027"="FY2027",100,150)), =Scenarios!C10)*=Scenarios!F10,0)) -> 0 | E43: =IF(=Scenarios!E10=1,0, Parameters!B7 + ==IF(=Scenarios!H10=1, IF("FY2027"="FY2026",50, IF("FY2027"="FY2027",100,150)), =Scenarios!C10)-(=ROUNDUP(=IF(=Scenarios!H10=1, IF("FY2027"="FY2026",50, IF("FY2027"="FY2027",100,150)), =Scenarios!C10)*=Scenarios!F10,0))) -> 0 | F43: =D43+E43 -> 0 | G43: =IF(=Scenarios!D10=1, IF(=Scenarios!I10="lease", Calc!C4*Parameters!C16, Calc!C4*Parameters!C19), Calc!C4) -> 0 | H43: =IF(=Scenarios!E10=1, IF(=Scenarios!I10="lease", Calc!C5*Parameters!C16, Calc!C5*Parameters!C19), Calc!C5) -> 0 | I43: =Calc!C3 -> 0 | J43: =IF("FY2027"="FY2026", (IF(=Scenarios!D10=1, Parameters!B9,0) + IF(=Scenarios!E10=1, Parameters!B9,0)), 0) -> 0 | K43: =(1-Parameters!B4) -> 0 | L43: =Scenarios!G10 -> 0 | M43: =(IF(Scenarios!D101, IF(Scenarios!I10"lease", Calc!C4*Parameters!C16, Calc!C4*Parameters!C19), Calc!C4) + IF(Scenarios!E101, IF(Scenarios!I10"lease", Calc!C5*Parameters!C16, Calc!C5*Parameters!C19), Calc!C5) + Calc!C3*=D43+E43)*=(1-Parameters!B4)*(1-J43) + =IF("FY2027"="FY2026", (IF(=Scenarios!D10=1, Parameters!B9,0) + IF(=Scenarios!E10=1, Parameters!B9,0)), 0) -> 0 | N43: =IF(F43>0, L43/F43, NA()) -> 0 | O43: ==Scenarios!A10&"|FY2027" -> 0
A44: =Scenarios!A10 -> 0 | B44: FY2028 | C44: =Scenarios!C10 -> 0 | D44: =IF(=Scenarios!D10=1,0, Parameters!B6 + =ROUNDUP(=IF(=Scenarios!H10=1, IF("FY2028"="FY2026",50, IF("FY2028"="FY2027",100,150)), =Scenarios!C10)*=Scenarios!F10,0)) -> 0 | E44: =IF(=Scenarios!E10=1,0, Parameters!B7 + ==IF(=Scenarios!H10=1, IF("FY2028"="FY2026",50, IF("FY2028"="FY2027",100,150)), =Scenarios!C10)-(=ROUNDUP(=IF(=Scenarios!H10=1, IF("FY2028"="FY2026",50, IF("FY2028"="FY2027",100,150)), =Scenarios!C10)*=Scenarios!F10,0))) -> 0 | F44: =D44+E44 -> 0 | G44: =IF(=Scenarios!D10=1, IF(=Scenarios!I10="lease", Calc!D4*Parameters!D16, Calc!D4*Parameters!D19), Calc!D4) -> 0 | H44: =IF(=Scenarios!E10=1, IF(=Scenarios!I10="lease", Calc!D5*Parameters!D16, Calc!D5*Parameters!D19), Calc!D5) -> 0 | I44: =Calc!D3 -> 0 | J44: =IF("FY2028"="FY2026", (IF(=Scenarios!D10=1, Parameters!B9,0) + IF(=Scenarios!E10=1, Parameters!B9,0)), 0) -> 0 | K44: =(1-Parameters!B4) -> 0 | L44: =Scenarios!G10 -> 0 | M44: =(IF(Scenarios!D101, IF(Scenarios!I10"lease", Calc!D4*Parameters!D16, Calc!D4*Parameters!D19), Calc!D4) + IF(Scenarios!E101, IF(Scenarios!I10"lease", Calc!D5*Parameters!D16, Calc!D5*Parameters!D19), Calc!D5) + Calc!D3*=D44+E44)*=(1-Parameters!B4)*(1-J44) + =IF("FY2028"="FY2026", (IF(=Scenarios!D10=1, Parameters!B9,0) + IF(=Scenarios!E10=1, Parameters!B9,0)), 0) -> 0 | N44: =IF(F44>0, L44/F44, NA()) -> 0 | O44: ==Scenarios!A10&"|FY2028" -> 0
A45: =Scenarios!A10 -> 0 | B45: FY2029 | C45: =Scenarios!C10 -> 0 | D45: =IF(=Scenarios!D10=1,0, Parameters!B6 + =ROUNDUP(=IF(=Scenarios!H10=1, IF("FY2029"="FY2026",50, IF("FY2029"="FY2027",100,150)), =Scenarios!C10)*=Scenarios!F10,0)) -> 0 | E45: =IF(=Scenarios!E10=1,0, Parameters!B7 + ==IF(=Scenarios!H10=1, IF("FY2029"="FY2026",50, IF("FY2029"="FY2027",100,150)), =Scenarios!C10)-(=ROUNDUP(=IF(=Scenarios!H10=1, IF("FY2029"="FY2026",50, IF("FY2029"="FY2027",100,150)), =Scenarios!C10)*=Scenarios!F10,0))) -> 0 | F45: =D45+E45 -> 0 | G45: =IF(=Scenarios!D10=1, IF(=Scenarios!I10="lease", Calc!E4*Parameters!E16, Calc!E4*Parameters!E19), Calc!E4) -> 0 | H45: =IF(=Scenarios!E10=1, IF(=Scenarios!I10="lease", Calc!E5*Parameters!E16, Calc!E5*Parameters!E19), Calc!E5) -> 0 | I45: =Calc!E3 -> 0 | J45: =IF("FY2029"="FY2026", (IF(=Scenarios!D10=1, Parameters!B9,0) + IF(=Scenarios!E10=1, Parameters!B9,0)), 0) -> 0 | K45: =(1-Parameters!B4) -> 0 | L45: =Scenarios!G10 -> 0 | M45: =(IF(Scenarios!D101, IF(Scenarios!I10"lease", Calc!E4*Parameters!E16, Calc!E4*Parameters!E19), Calc!E4) + IF(Scenarios!E101, IF(Scenarios!I10"lease", Calc!E5*Parameters!E16, Calc!E5*Parameters!E19), Calc!E5) + Calc!E3*=D45+E45)*=(1-Parameters!B4)*(1-J45) + =IF("FY2029"="FY2026", (IF(=Scenarios!D10=1, Parameters!B9,0) + IF(=Scenarios!E10=1, Parameters!B9,0)), 0) -> 0 | N45: =IF(F45>0, L45/F45, NA()) -> 0 | O45: ==Scenarios!A10&"|FY2029" -> 0
A46: =Scenarios!A10 -> 0 | B46: FY2030 | C46: =Scenarios!C10 -> 0 | D46: =IF(=Scenarios!D10=1,0, Parameters!B6 + =ROUNDUP(=IF(=Scenarios!H10=1, IF("FY2030"="FY2026",50, IF("FY2030"="FY2027",100,150)), =Scenarios!C10)*=Scenarios!F10,0)) -> 0 | E46: =IF(=Scenarios!E10=1,0, Parameters!B7 + ==IF(=Scenarios!H10=1, IF("FY2030"="FY2026",50, IF("FY2030"="FY2027",100,150)), =Scenarios!C10)-(=ROUNDUP(=IF(=Scenarios!H10=1, IF("FY2030"="FY2026",50, IF("FY2030"="FY2027",100,150)), =Scenarios!C10)*=Scenarios!F10,0))) -> 0 | F46: =D46+E46 -> 0 | G46: =IF(=Scenarios!D10=1, IF(=Scenarios!I10="lease", Calc!F4*Parameters!F16, Calc!F4*Parameters!F19), Calc!F4) -> 0 | H46: =IF(=Scenarios!E10=1, IF(=Scenarios!I10="lease", Calc!F5*Parameters!F16, Calc!F5*Parameters!F19), Calc!F5) -> 0 | I46: =Calc!F3 -> 0 | J46: =IF("FY2030"="FY2026", (IF(=Scenarios!D10=1, Parameters!B9,0) + IF(=Scenarios!E10=1, Parameters!B9,0)), 0) -> 0 | K46: =(1-Parameters!B4) -> 0 | L46: =Scenarios!G10 -> 0 | M46: =(IF(Scenarios!D101, IF(Scenarios!I10"lease", Calc!F4*Parameters!F16, Calc!F4*Parameters!F19), Calc!F4) + IF(Scenarios!E101, IF(Scenarios!I10"lease", Calc!F5*Parameters!F16, Calc!F5*Parameters!F19), Calc!F5) + Calc!F3*=D46+E46)*=(1-Parameters!B4)*(1-J46) + =IF("FY2030"="FY2026", (IF(=Scenarios!D10=1, Parameters!B9,0) + IF(=Scenarios!E10=1, Parameters!B9,0)), 0) -> 0 | N46: =IF(F46>0, L46/F46, NA()) -> 0 | O46: ==Scenarios!A10&"|FY2030" -> 0
A47: =Scenarios!A11 -> 0 | B47: FY2026 | C47: =Scenarios!C11 -> 0 | D47: =IF(=Scenarios!D11=1,0, Parameters!B6 + =ROUNDUP(=IF(=Scenarios!H11=1, IF("FY2026"="FY2026",50, IF("FY2026"="FY2027",100,150)), =Scenarios!C11)*=Scenarios!F11,0)) -> 0 | E47: =IF(=Scenarios!E11=1,0, Parameters!B7 + ==IF(=Scenarios!H11=1, IF("FY2026"="FY2026",50, IF("FY2026"="FY2027",100,150)), =Scenarios!C11)-(=ROUNDUP(=IF(=Scenarios!H11=1, IF("FY2026"="FY2026",50, IF("FY2026"="FY2027",100,150)), =Scenarios!C11)*=Scenarios!F11,0))) -> 0 | F47: =D47+E47 -> 0 | G47: =IF(=Scenarios!D11=1, IF(=Scenarios!I11="lease", Calc!B4*Parameters!B16, Calc!B4*Parameters!B19), Calc!B4) -> 0 | H47: =IF(=Scenarios!E11=1, IF(=Scenarios!I11="lease", Calc!B5*Parameters!B16, Calc!B5*Parameters!B19), Calc!B5) -> 0 | I47: =Calc!B3 -> 0 | J47: =IF("FY2026"="FY2026", (IF(=Scenarios!D11=1, Parameters!B9,0) + IF(=Scenarios!E11=1, Parameters!B9,0)), 0) -> 0 | K47: =(1-Parameters!B4) -> 0 | L47: =Scenarios!G11 -> 0 | M47: =(IF(Scenarios!D111, IF(Scenarios!I11"lease", Calc!B4*Parameters!B16, Calc!B4*Parameters!B19), Calc!B4) + IF(Scenarios!E111, IF(Scenarios!I11"lease", Calc!B5*Parameters!B16, Calc!B5*Parameters!B19), Calc!B5) + Calc!B3*=D47+E47)*=(1-Parameters!B4)*(1-J47) + =IF("FY2026"="FY2026", (IF(=Scenarios!D11=1, Parameters!B9,0) + IF(=Scenarios!E11=1, Parameters!B9,0)), 0) -> 0 | N47: =IF(F47>0, L47/F47, NA()) -> 0 | O47: ==Scenarios!A11&"|FY2026" -> 0
A48: =Scenarios!A11 -> 0 | B48: FY2027 | C48: =Scenarios!C11 -> 0 | D48: =IF(=Scenarios!D11=1,0, Parameters!B6 + =ROUNDUP(=IF(=Scenarios!H11=1, IF("FY2027"="FY2026",50, IF("FY2027"="FY2027",100,150)), =Scenarios!C11)*=Scenarios!F11,0)) -> 0 | E48: =IF(=Scenarios!E11=1,0, Parameters!B7 + ==IF(=Scenarios!H11=1, IF("FY2027"="FY2026",50, IF("FY2027"="FY2027",100,150)), =Scenarios!C11)-(=ROUNDUP(=IF(=Scenarios!H11=1, IF("FY2027"="FY2026",50, IF("FY2027"="FY2027",100,150)), =Scenarios!C11)*=Scenarios!F11,0))) -> 0 | F48: =D48+E48 -> 0 | G48: =IF(=Scenarios!D11=1, IF(=Scenarios!I11="lease", Calc!C4*Parameters!C16, Calc!C4*Parameters!C19), Calc!C4) -> 0 | H48: =IF(=Scenarios!E11=1, IF(=Scenarios!I11="lease", Calc!C5*Parameters!C16, Calc!C5*Parameters!C19), Calc!C5) -> 0 | I48: =Calc!C3 -> 0 | J48: =IF("FY2027"="FY2026", (IF(=Scenarios!D11=1, Parameters!B9,0) + IF(=Scenarios!E11=1, Parameters!B9,0)), 0) -> 0 | K48: =(1-Parameters!B4) -> 0 | L48: =Scenarios!G11 -> 0 | M48: =(IF(Scenarios!D111, IF(Scenarios!I11"lease", Calc!C4*Parameters!C16, Calc!C4*Parameters!C19), Calc!C4) + IF(Scenarios!E111, IF(Scenarios!I11"lease", Calc!C5*Parameters!C16, Calc!C5*Parameters!C19), Calc!C5) + Calc!C3*=D48+E48)*=(1-Parameters!B4)*(1-J48) + =IF("FY2027"="FY2026", (IF(=Scenarios!D11=1, Parameters!B9,0) + IF(=Scenarios!E11=1, Parameters!B9,0)), 0) -> 0 | N48: =IF(F48>0, L48/F48, NA()) -> 0 | O48: ==Scenarios!A11&"|FY2027" -> 0
A49: =Scenarios!A11 -> 0 | B49: FY2028 | C49: =Scenarios!C11 -> 0 | D49: =IF(=Scenarios!D11=1,0, Parameters!B6 + =ROUNDUP(=IF(=Scenarios!H11=1, IF("FY2028"="FY2026",50, IF("FY2028"="FY2027",100,150)), =Scenarios!C11)*=Scenarios!F11,0)) -> 0 | E49: =IF(=Scenarios!E11=1,0, Parameters!B7 + ==IF(=Scenarios!H11=1, IF("FY2028"="FY2026",50, IF("FY2028"="FY2027",100,150)), =Scenarios!C11)-(=ROUNDUP(=IF(=Scenarios!H11=1, IF("FY2028"="FY2026",50, IF("FY2028"="FY2027",100,150)), =Scenarios!C11)*=Scenarios!F11,0))) -> 0 | F49: =D49+E49 -> 0 | G49: =IF(=Scenarios!D11=1, IF(=Scenarios!I11="lease", Calc!D4*Parameters!D16, Calc!D4*Parameters!D19), Calc!D4) -> 0 | H49: =IF(=Scenarios!E11=1, IF(=Scenarios!I11="lease", Calc!D5*Parameters!D16, Calc!D5*Parameters!D19), Calc!D5) -> 0 | I49: =Calc!D3 -> 0 | J49: =IF("FY2028"="FY2026", (IF(=Scenarios!D11=1, Parameters!B9,0) + IF(=Scenarios!E11=1, Parameters!B9,0)), 0) -> 0 | K49: =(1-Parameters!B4) -> 0 | L49: =Scenarios!G11 -> 0 | M49: =(IF(Scenarios!D111, IF(Scenarios!I11"lease", Calc!D4*Parameters!D16, Calc!D4*Parameters!D19), Calc!D4) + IF(Scenarios!E111, IF(Scenarios!I11"lease", Calc!D5*Parameters!D16, Calc!D5*Parameters!D19), Calc!D5) + Calc!D3*=D49+E49)*=(1-Parameters!B4)*(1-J49) + =IF("FY2028"="FY2026", (IF(=Scenarios!D11=1, Parameters!B9,0) + IF(=Scenarios!E11=1, Parameters!B9,0)), 0) -> 0 | N49: =IF(F49>0, L49/F49, NA()) -> 0 | O49: ==Scenarios!A11&"|FY2028" -> 0
A50: =Scenarios!A11 -> 0 | B50: FY2029 | C50: =Scenarios!C11 -> 0 | D50: =IF(=Scenarios!D11=1,0, Parameters!B6 + =ROUNDUP(=IF(=Scenarios!H11=1, IF("FY2029"="FY2026",50, IF("FY2029"="FY2027",100,150)), =Scenarios!C11)*=Scenarios!F11,0)) -> 0 | E50: =IF(=Scenarios!E11=1,0, Parameters!B7 + ==IF(=Scenarios!H11=1, IF("FY2029"="FY2026",50, IF("FY2029"="FY2027",100,150)), =Scenarios!C11)-(=ROUNDUP(=IF(=Scenarios!H11=1, IF("FY2029"="FY2026",50, IF("FY2029"="FY2027",100,150)), =Scenarios!C11)*=Scenarios!F11,0))) -> 0 | F50: =D50+E50 -> 0 | G50: =IF(=Scenarios!D11=1, IF(=Scenarios!I11="lease", Calc!E4*Parameters!E16, Calc!E4*Parameters!E19), Calc!E4) -> 0 | H50: =IF(=Scenarios!E11=1, IF(=Scenarios!I11="lease", Calc!E5*Parameters!E16, Calc!E5*Parameters!E19), Calc!E5) -> 0 | I50: =Calc!E3 -> 0 | J50: =IF("FY2029"="FY2026", (IF(=Scenarios!D11=1, Parameters!B9,0) + IF(=Scenarios!E11=1, Parameters!B9,0)), 0) -> 0 | K50: =(1-Parameters!B4) -> 0 | L50: =Scenarios!G11 -> 0 | M50: =(IF(Scenarios!D111, IF(Scenarios!I11"lease", Calc!E4*Parameters!E16, Calc!E4*Parameters!E19), Calc!E4) + IF(Scenarios!E111, IF(Scenarios!I11"lease", Calc!E5*Parameters!E16, Calc!E5*Parameters!E19), Calc!E5) + Calc!E3*=D50+E50)*=(1-Parameters!B4)*(1-J50) + =IF("FY2029"="FY2026", (IF(=Scenarios!D11=1, Parameters!B9,0) + IF(=Scenarios!E11=1, Parameters!B9,0)), 0) -> 0 | N50: =IF(F50>0, L50/F50, NA()) -> 0 | O50: ==Scenarios!A11&"|FY2029" -> 0
A51: =Scenarios!A11 -> 0 | B51: FY2030 | C51: =Scenarios!C11 -> 0 | D51: =IF(=Scenarios!D11=1,0, Parameters!B6 + =ROUNDUP(=IF(=Scenarios!H11=1, IF("FY2030"="FY2026",50, IF("FY2030"="FY2027",100,150)), =Scenarios!C11)*=Scenarios!F11,0)) -> 0 | E51: =IF(=Scenarios!E11=1,0, Parameters!B7 + ==IF(=Scenarios!H11=1, IF("FY2030"="FY2026",50, IF("FY2030"="FY2027",100,150)), =Scenarios!C11)-(=ROUNDUP(=IF(=Scenarios!H11=1, IF("FY2030"="FY2026",50, IF("FY2030"="FY2027",100,150)), =Scenarios!C11)*=Scenarios!F11,0))) -> 0 | F51: =D51+E51 -> 0 | G51: =IF(=Scenarios!D11=1, IF(=Scenarios!I11="lease", Calc!F4*Parameters!F16, Calc!F4*Parameters!F19), Calc!F4) -> 0 | H51: =IF(=Scenarios!E11=1, IF(=Scenarios!I11="lease", Calc!F5*Parameters!F16, Calc!F5*Parameters!F19), Calc!F5) -> 0 | I51: =Calc!F3 -> 0 | J51: =IF("FY2030"="FY2026", (IF(=Scenarios!D11=1, Parameters!B9,0) + IF(=Scenarios!E11=1, Parameters!B9,0)), 0) -> 0 | K51: =(1-Parameters!B4) -> 0 | L51: =Scenarios!G11 -> 0 | M51: =(IF(Scenarios!D111, IF(Scenarios!I11"lease", Calc!F4*Parameters!F16, Calc!F4*Parameters!F19), Calc!F4) + IF(Scenarios!E111, IF(Scenarios!I11"lease", Calc!F5*Parameters!F16, Calc!F5*Parameters!F19), Calc!F5) + Calc!F3*=D51+E51)*=(1-Parameters!B4)*(1-J51) + =IF("FY2030"="FY2026", (IF(=Scenarios!D11=1, Parameters!B9,0) + IF(=Scenarios!E11=1, Parameters!B9,0)), 0) -> 0 | N51: =IF(F51>0, L51/F51, NA()) -> 0 | O51: ==Scenarios!A11&"|FY2030" -> 0
A52: =Scenarios!A12 -> 0 | B52: FY2026 | C52: =Scenarios!C12 -> 0 | D52: =IF(=Scenarios!D12=1,0, Parameters!B6 + =ROUNDUP(=IF(=Scenarios!H12=1, IF("FY2026"="FY2026",50, IF("FY2026"="FY2027",100,150)), =Scenarios!C12)*=Scenarios!F12,0)) -> 0 | E52: =IF(=Scenarios!E12=1,0, Parameters!B7 + ==IF(=Scenarios!H12=1, IF("FY2026"="FY2026",50, IF("FY2026"="FY2027",100,150)), =Scenarios!C12)-(=ROUNDUP(=IF(=Scenarios!H12=1, IF("FY2026"="FY2026",50, IF("FY2026"="FY2027",100,150)), =Scenarios!C12)*=Scenarios!F12,0))) -> 0 | F52: =D52+E52 -> 0 | G52: =IF(=Scenarios!D12=1, IF(=Scenarios!I12="lease", Calc!B4*Parameters!B16, Calc!B4*Parameters!B19), Calc!B4) -> 0 | H52: =IF(=Scenarios!E12=1, IF(=Scenarios!I12="lease", Calc!B5*Parameters!B16, Calc!B5*Parameters!B19), Calc!B5) -> 0 | I52: =Calc!B3 -> 0 | J52: =IF("FY2026"="FY2026", (IF(=Scenarios!D12=1, Parameters!B9,0) + IF(=Scenarios!E12=1, Parameters!B9,0)), 0) -> 0 | K52: =(1-Parameters!B4) -> 0 | L52: =Scenarios!G12 -> 0 | M52: =(IF(Scenarios!D121, IF(Scenarios!I12"lease", Calc!B4*Parameters!B16, Calc!B4*Parameters!B19), Calc!B4) + IF(Scenarios!E121, IF(Scenarios!I12"lease", Calc!B5*Parameters!B16, Calc!B5*Parameters!B19), Calc!B5) + Calc!B3*=D52+E52)*=(1-Parameters!B4)*(1-J52) + =IF("FY2026"="FY2026", (IF(=Scenarios!D12=1, Parameters!B9,0) + IF(=Scenarios!E12=1, Parameters!B9,0)), 0) -> 0 | N52: =IF(F52>0, L52/F52, NA()) -> 0 | O52: ==Scenarios!A12&"|FY2026" -> 0
A53: =Scenarios!A12 -> 0 | B53: FY2027 | C53: =Scenarios!C12 -> 0 | D53: =IF(=Scenarios!D12=1,0, Parameters!B6 + =ROUNDUP(=IF(=Scenarios!H12=1, IF("FY2027"="FY2026",50, IF("FY2027"="FY2027",100,150)), =Scenarios!C12)*=Scenarios!F12,0)) -> 0 | E53: =IF(=Scenarios!E12=1,0, Parameters!B7 + ==IF(=Scenarios!H12=1, IF("FY2027"="FY2026",50, IF("FY2027"="FY2027",100,150)), =Scenarios!C12)-(=ROUNDUP(=IF(=Scenarios!H12=1, IF("FY2027"="FY2026",50, IF("FY2027"="FY2027",100,150)), =Scenarios!C12)*=Scenarios!F12,0))) -> 0 | F53: =D53+E53 -> 0 | G53: =IF(=Scenarios!D12=1, IF(=Scenarios!I12="lease", Calc!C4*Parameters!C16, Calc!C4*Parameters!C19), Calc!C4) -> 0 | H53: =IF(=Scenarios!E12=1, IF(=Scenarios!I12="lease", Calc!C5*Parameters!C16, Calc!C5*Parameters!C19), Calc!C5) -> 0 | I53: =Calc!C3 -> 0 | J53: =IF("FY2027"="FY2026", (IF(=Scenarios!D12=1, Parameters!B9,0) + IF(=Scenarios!E12=1, Parameters!B9,0)), 0) -> 0 | K53: =(1-Parameters!B4) -> 0 | L53: =Scenarios!G12 -> 0 | M53: =(IF(Scenarios!D121, IF(Scenarios!I12"lease", Calc!C4*Parameters!C16, Calc!C4*Parameters!C19), Calc!C4) + IF(Scenarios!E121, IF(Scenarios!I12"lease", Calc!C5*Parameters!C16, Calc!C5*Parameters!C19), Calc!C5) + Calc!C3*=D53+E53)*=(1-Parameters!B4)*(1-J53) + =IF("FY2027"="FY2026", (IF(=Scenarios!D12=1, Parameters!B9,0) + IF(=Scenarios!E12=1, Parameters!B9,0)), 0) -> 0 | N53: =IF(F53>0, L53/F53, NA()) -> 0 | O53: ==Scenarios!A12&"|FY2027" -> 0
A54: =Scenarios!A12 -> 0 | B54: FY2028 | C54: =Scenarios!C12 -> 0 | D54: =IF(=Scenarios!D12=1,0, Parameters!B6 + =ROUNDUP(=IF(=Scenarios!H12=1, IF("FY2028"="FY2026",50, IF("FY2028"="FY2027",100,150)), =Scenarios!C12)*=Scenarios!F12,0)) -> 0 | E54: =IF(=Scenarios!E12=1,0, Parameters!B7 + ==IF(=Scenarios!H12=1, IF("FY2028"="FY2026",50, IF("FY2028"="FY2027",100,150)), =Scenarios!C12)-(=ROUNDUP(=IF(=Scenarios!H12=1, IF("FY2028"="FY2026",50, IF("FY2028"="FY2027",100,150)), =Scenarios!C12)*=Scenarios!F12,0))) -> 0 | F54: =D54+E54 -> 0 | G54: =IF(=Scenarios!D12=1, IF(=Scenarios!I12="lease", Calc!D4*Parameters!D16, Calc!D4*Parameters!D19), Calc!D4) -> 0 | H54: =IF(=Scenarios!E12=1, IF(=Scenarios!I12="lease", Calc!D5*Parameters!D16, Calc!D5*Parameters!D19), Calc!D5) -> 0 | I54: =Calc!D3 -> 0 | J54: =IF("FY2028"="FY2026", (IF(=Scenarios!D12=1, Parameters!B9,0) + IF(=Scenarios!E12=1, Parameters!B9,0)), 0) -> 0 | K54: =(1-Parameters!B4) -> 0 | L54: =Scenarios!G12 -> 0 | M54: =(IF(Scenarios!D121, IF(Scenarios!I12"lease", Calc!D4*Parameters!D16, Calc!D4*Parameters!D19), Calc!D4) + IF(Scenarios!E121, IF(Scenarios!I12"lease", Calc!D5*Parameters!D16, Calc!D5*Parameters!D19), Calc!D5) + Calc!D3*=D54+E54)*=(1-Parameters!B4)*(1-J54) + =IF("FY2028"="FY2026", (IF(=Scenarios!D12=1, Parameters!B9,0) + IF(=Scenarios!E12=1, Parameters!B9,0)), 0) -> 0 | N54: =IF(F54>0, L54/F54, NA()) -> 0 | O54: ==Scenarios!A12&"|FY2028" -> 0
A55: =Scenarios!A12 -> 0 | B55: FY2029 | C55: =Scenarios!C12 -> 0 | D55: =IF(=Scenarios!D12=1,0, Parameters!B6 + =ROUNDUP(=IF(=Scenarios!H12=1, IF("FY2029"="FY2026",50, IF("FY2029"="FY2027",100,150)), =Scenarios!C12)*=Scenarios!F12,0)) -> 0 | E55: =IF(=Scenarios!E12=1,0, Parameters!B7 + ==IF(=Scenarios!H12=1, IF("FY2029"="FY2026",50, IF("FY2029"="FY2027",100,150)), =Scenarios!C12)-(=ROUNDUP(=IF(=Scenarios!H12=1, IF("FY2029"="FY2026",50, IF("FY2029"="FY2027",100,150)), =Scenarios!C12)*=Scenarios!F12,0))) -> 0 | F55: =D55+E55 -> 0 | G55: =IF(=Scenarios!D12=1, IF(=Scenarios!I12="lease", Calc!E4*Parameters!E16, Calc!E4*Parameters!E19), Calc!E4) -> 0 | H55: =IF(=Scenarios!E12=1, IF(=Scenarios!I12="lease", Calc!E5*Parameters!E16, Calc!E5*Parameters!E19), Calc!E5) -> 0 | I55: =Calc!E3 -> 0 | J55: =IF("FY2029"="FY2026", (IF(=Scenarios!D12=1, Parameters!B9,0) + IF(=Scenarios!E12=1, Parameters!B9,0)), 0) -> 0 | K55: =(1-Parameters!B4) -> 0 | L55: =Scenarios!G12 -> 0 | M55: =(IF(Scenarios!D121, IF(Scenarios!I12"lease", Calc!E4*Parameters!E16, Calc!E4*Parameters!E19), Calc!E4) + IF(Scenarios!E121, IF(Scenarios!I12"lease", Calc!E5*Parameters!E16, Calc!E5*Parameters!E19), Calc!E5) + Calc!E3*=D55+E55)*=(1-Parameters!B4)*(1-J55) + =IF("FY2029"="FY2026", (IF(=Scenarios!D12=1, Parameters!B9,0) + IF(=Scenarios!E12=1, Parameters!B9,0)), 0) -> 0 | N55: =IF(F55>0, L55/F55, NA()) -> 0 | O55: ==Scenarios!A12&"|FY2029" -> 0
A56: =Scenarios!A12 -> 0 | B56: FY2030 | C56: =Scenarios!C12 -> 0 | D56: =IF(=Scenarios!D12=1,0, Parameters!B6 + =ROUNDUP(=IF(=Scenarios!H12=1, IF("FY2030"="FY2026",50, IF("FY2030"="FY2027",100,150)), =Scenarios!C12)*=Scenarios!F12,0)) -> 0 | E56: =IF(=Scenarios!E12=1,0, Parameters!B7 + ==IF(=Scenarios!H12=1, IF("FY2030"="FY2026",50, IF("FY2030"="FY2027",100,150)), =Scenarios!C12)-(=ROUNDUP(=IF(=Scenarios!H12=1, IF("FY2030"="FY2026",50, IF("FY2030"="FY2027",100,150)), =Scenarios!C12)*=Scenarios!F12,0))) -> 0 | F56: =D56+E56 -> 0 | G56: =IF(=Scenarios!D12=1, IF(=Scenarios!I12="lease", Calc!F4*Parameters!F16, Calc!F4*Parameters!F19), Calc!F4) -> 0 | H56: =IF(=Scenarios!E12=1, IF(=Scenarios!I12="lease", Calc!F5*Parameters!F16, Calc!F5*Parameters!F19), Calc!F5) -> 0 | I56: =Calc!F3 -> 0 | J56: =IF("FY2030"="FY2026", (IF(=Scenarios!D12=1, Parameters!B9,0) + IF(=Scenarios!E12=1, Parameters!B9,0)), 0) -> 0 | K56: =(1-Parameters!B4) -> 0 | L56: =Scenarios!G12 -> 0 | M56: =(IF(Scenarios!D121, IF(Scenarios!I12"lease", Calc!F4*Parameters!F16, Calc!F4*Parameters!F19), Calc!F4) + IF(Scenarios!E121, IF(Scenarios!I12"lease", Calc!F5*Parameters!F16, Calc!F5*Parameters!F19), Calc!F5) + Calc!F3*=D56+E56)*=(1-Parameters!B4)*(1-J56) + =IF("FY2030"="FY2026", (IF(=Scenarios!D12=1, Parameters!B9,0) + IF(=Scenarios!E12=1, Parameters!B9,0)), 0) -> 0 | N56: =IF(F56>0, L56/F56, NA()) -> 0 | O56: ==Scenarios!A12&"|FY2030" -> 0
A57: =Scenarios!A13 -> 0 | B57: FY2026 | C57: =Scenarios!C13 -> 0 | D57: =IF(=Scenarios!D13=1,0, Parameters!B6 + =ROUNDUP(=IF(=Scenarios!H13=1, IF("FY2026"="FY2026",50, IF("FY2026"="FY2027",100,150)), =Scenarios!C13)*=Scenarios!F13,0)) -> 0 | E57: =IF(=Scenarios!E13=1,0, Parameters!B7 + ==IF(=Scenarios!H13=1, IF("FY2026"="FY2026",50, IF("FY2026"="FY2027",100,150)), =Scenarios!C13)-(=ROUNDUP(=IF(=Scenarios!H13=1, IF("FY2026"="FY2026",50, IF("FY2026"="FY2027",100,150)), =Scenarios!C13)*=Scenarios!F13,0))) -> 0 | F57: =D57+E57 -> 0 | G57: =IF(=Scenarios!D13=1, IF(=Scenarios!I13="lease", Calc!B4*Parameters!B16, Calc!B4*Parameters!B19), Calc!B4) -> 0 | H57: =IF(=Scenarios!E13=1, IF(=Scenarios!I13="lease", Calc!B5*Parameters!B16, Calc!B5*Parameters!B19), Calc!B5) -> 0 | I57: =Calc!B3 -> 0 | J57: =IF("FY2026"="FY2026", (IF(=Scenarios!D13=1, Parameters!B9,0) + IF(=Scenarios!E13=1, Parameters!B9,0)), 0) -> 0 | K57: =(1-Parameters!B4) -> 0 | L57: =Scenarios!G13 -> 0 | M57: =(IF(Scenarios!D131, IF(Scenarios!I13"lease", Calc!B4*Parameters!B16, Calc!B4*Parameters!B19), Calc!B4) + IF(Scenarios!E131, IF(Scenarios!I13"lease", Calc!B5*Parameters!B16, Calc!B5*Parameters!B19), Calc!B5) + Calc!B3*=D57+E57)*=(1-Parameters!B4)*(1-J57) + =IF("FY2026"="FY2026", (IF(=Scenarios!D13=1, Parameters!B9,0) + IF(=Scenarios!E13=1, Parameters!B9,0)), 0) -> 0 | N57: =IF(F57>0, L57/F57, NA()) -> 0 | O57: ==Scenarios!A13&"|FY2026" -> 0
A58: =Scenarios!A13 -> 0 | B58: FY2027 | C58: =Scenarios!C13 -> 0 | D58: =IF(=Scenarios!D13=1,0, Parameters!B6 + =ROUNDUP(=IF(=Scenarios!H13=1, IF("FY2027"="FY2026",50, IF("FY2027"="FY2027",100,150)), =Scenarios!C13)*=Scenarios!F13,0)) -> 0 | E58: =IF(=Scenarios!E13=1,0, Parameters!B7 + ==IF(=Scenarios!H13=1, IF("FY2027"="FY2026",50, IF("FY2027"="FY2027",100,150)), =Scenarios!C13)-(=ROUNDUP(=IF(=Scenarios!H13=1, IF("FY2027"="FY2026",50, IF("FY2027"="FY2027",100,150)), =Scenarios!C13)*=Scenarios!F13,0))) -> 0 | F58: =D58+E58 -> 0 | G58: =IF(=Scenarios!D13=1, IF(=Scenarios!I13="lease", Calc!C4*Parameters!C16, Calc!C4*Parameters!C19), Calc!C4) -> 0 | H58: =IF(=Scenarios!E13=1, IF(=Scenarios!I13="lease", Calc!C5*Parameters!C16, Calc!C5*Parameters!C19), Calc!C5) -> 0 | I58: =Calc!C3 -> 0 | J58: =IF("FY2027"="FY2026", (IF(=Scenarios!D13=1, Parameters!B9,0) + IF(=Scenarios!E13=1, Parameters!B9,0)), 0) -> 0 | K58: =(1-Parameters!B4) -> 0 | L58: =Scenarios!G13 -> 0 | M58: =(IF(Scenarios!D131, IF(Scenarios!I13"lease", Calc!C4*Parameters!C16, Calc!C4*Parameters!C19), Calc!C4) + IF(Scenarios!E131, IF(Scenarios!I13"lease", Calc!C5*Parameters!C16, Calc!C5*Parameters!C19), Calc!C5) + Calc!C3*=D58+E58)*=(1-Parameters!B4)*(1-J58) + =IF("FY2027"="FY2026", (IF(=Scenarios!D13=1, Parameters!B9,0) + IF(=Scenarios!E13=1, Parameters!B9,0)), 0) -> 0 | N58: =IF(F58>0, L58/F58, NA()) -> 0 | O58: ==Scenarios!A13&"|FY2027" -> 0
A59: =Scenarios!A13 -> 0 | B59: FY2028 | C59: =Scenarios!C13 -> 0 | D59: =IF(=Scenarios!D13=1,0, Parameters!B6 + =ROUNDUP(=IF(=Scenarios!H13=1, IF("FY2028"="FY2026",50, IF("FY2028"="FY2027",100,150)), =Scenarios!C13)*=Scenarios!F13,0)) -> 0 | E59: =IF(=Scenarios!E13=1,0, Parameters!B7 + ==IF(=Scenarios!H13=1, IF("FY2028"="FY2026",50, IF("FY2028"="FY2027",100,150)), =Scenarios!C13)-(=ROUNDUP(=IF(=Scenarios!H13=1, IF("FY2028"="FY2026",50, IF("FY2028"="FY2027",100,150)), =Scenarios!C13)*=Scenarios!F13,0))) -> 0 | F59: =D59+E59 -> 0 | G59: =IF(=Scenarios!D13=1, IF(=Scenarios!I13="lease", Calc!D4*Parameters!D16, Calc!D4*Parameters!D19), Calc!D4) -> 0 | H59: =IF(=Scenarios!E13=1, IF(=Scenarios!I13="lease", Calc!D5*Parameters!D16, Calc!D5*Parameters!D19), Calc!D5) -> 0 | I59: =Calc!D3 -> 0 | J59: =IF("FY2028"="FY2026", (IF(=Scenarios!D13=1, Parameters!B9,0) + IF(=Scenarios!E13=1, Parameters!B9,0)), 0) -> 0 | K59: =(1-Parameters!B4) -> 0 | L59: =Scenarios!G13 -> 0 | M59: =(IF(Scenarios!D131, IF(Scenarios!I13"lease", Calc!D4*Parameters!D16, Calc!D4*Parameters!D19), Calc!D4) + IF(Scenarios!E131, IF(Scenarios!I13"lease", Calc!D5*Parameters!D16, Calc!D5*Parameters!D19), Calc!D5) + Calc!D3*=D59+E59)*=(1-Parameters!B4)*(1-J59) + =IF("FY2028"="FY2026", (IF(=Scenarios!D13=1, Parameters!B9,0) + IF(=Scenarios!E13=1, Parameters!B9,0)), 0) -> 0 | N59: =IF(F59>0, L59/F59, NA()) -> 0 | O59: ==Scenarios!A13&"|FY2028" -> 0
A60: =Scenarios!A13 -> 0 | B60: FY2029 | C60: =Scenarios!C13 -> 0 | D60: =IF(=Scenarios!D13=1,0, Parameters!B6 + =ROUNDUP(=IF(=Scenarios!H13=1, IF("FY2029"="FY2026",50, IF("FY2029"="FY2027",100,150)), =Scenarios!C13)*=Scenarios!F13,0)) -> 0 | E60: =IF(=Scenarios!E13=1,0, Parameters!B7 + ==IF(=Scenarios!H13=1, IF("FY2029"="FY2026",50, IF("FY2029"="FY2027",100,150)), =Scenarios!C13)-(=ROUNDUP(=IF(=Scenarios!H13=1, IF("FY2029"="FY2026",50, IF("FY2029"="FY2027",100,150)), =Scenarios!C13)*=Scenarios!F13,0))) -> 0 | F60: =D60+E60 -> 0 | G60: =IF(=Scenarios!D13=1, IF(=Scenarios!I13="lease", Calc!E4*Parameters!E16, Calc!E4*Parameters!E19), Calc!E4) -> 0 | H60: =IF(=Scenarios!E13=1, IF(=Scenarios!I13="lease", Calc!E5*Parameters!E16, Calc!E5*Parameters!E19), Calc!E5) -> 0 | I60: =Calc!E3 -> 0 | J60: =IF("FY2029"="FY2026", (IF(=Scenarios!D13=1, Parameters!B9,0) + IF(=Scenarios!E13=1, Parameters!B9,0)), 0) -> 0 | K60: =(1-Parameters!B4) -> 0 | L60: =Scenarios!G13 -> 0 | M60: =(IF(Scenarios!D131, IF(Scenarios!I13"lease", Calc!E4*Parameters!E16, Calc!E4*Parameters!E19), Calc!E4) + IF(Scenarios!E131, IF(Scenarios!I13"lease", Calc!E5*Parameters!E16, Calc!E5*Parameters!E19), Calc!E5) + Calc!E3*=D60+E60)*=(1-Parameters!B4)*(1-J60) + =IF("FY2029"="FY2026", (IF(=Scenarios!D13=1, Parameters!B9,0) + IF(=Scenarios!E13=1, Parameters!B9,0)), 0) -> 0 | N60: =IF(F60>0, L60/F60, NA()) -> 0 | O60: ==Scenarios!A13&"|FY2029" -> 0
A61: =Scenarios!A13 -> 0 | B61: FY2030 | C61: =Scenarios!C13 -> 0 | D61: =IF(=Scenarios!D13=1,0, Parameters!B6 + =ROUNDUP(=IF(=Scenarios!H13=1, IF("FY2030"="FY2026",50, IF("FY2030"="FY2027",100,150)), =Scenarios!C13)*=Scenarios!F13,0)) -> 0 | E61: =IF(=Scenarios!E13=1,0, Parameters!B7 + ==IF(=Scenarios!H13=1, IF("FY2030"="FY2026",50, IF("FY2030"="FY2027",100,150)), =Scenarios!C13)-(=ROUNDUP(=IF(=Scenarios!H13=1, IF("FY2030"="FY2026",50, IF("FY2030"="FY2027",100,150)), =Scenarios!C13)*=Scenarios!F13,0))) -> 0 | F61: =D61+E61 -> 0 | G61: =IF(=Scenarios!D13=1, IF(=Scenarios!I13="lease", Calc!F4*Parameters!F16, Calc!F4*Parameters!F19), Calc!F4) -> 0 | H61: =IF(=Scenarios!E13=1, IF(=Scenarios!I13="lease", Calc!F5*Parameters!F16, Calc!F5*Parameters!F19), Calc!F5) -> 0 | I61: =Calc!F3 -> 0 | J61: =IF("FY2030"="FY2026", (IF(=Scenarios!D13=1, Parameters!B9,0) + IF(=Scenarios!E13=1, Parameters!B9,0)), 0) -> 0 | K61: =(1-Parameters!B4) -> 0 | L61: =Scenarios!G13 -> 0 | M61: =(IF(Scenarios!D131, IF(Scenarios!I13"lease", Calc!F4*Parameters!F16, Calc!F4*Parameters!F19), Calc!F4) + IF(Scenarios!E131, IF(Scenarios!I13"lease", Calc!F5*Parameters!F16, Calc!F5*Parameters!F19), Calc!F5) + Calc!F3*=D61+E61)*=(1-Parameters!B4)*(1-J61) + =IF("FY2030"="FY2026", (IF(=Scenarios!D13=1, Parameters!B9,0) + IF(=Scenarios!E13=1, Parameters!B9,0)), 0) -> 0 | N61: =IF(F61>0, L61/F61, NA()) -> 0 | O61: ==Scenarios!A13&"|FY2030" -> 0
A62: =Scenarios!A14 -> 0 | B62: FY2026 | C62: =Scenarios!C14 -> 0 | D62: =IF(=Scenarios!D14=1,0, Parameters!B6 + =ROUNDUP(=IF(=Scenarios!H14=1, IF("FY2026"="FY2026",50, IF("FY2026"="FY2027",100,150)), =Scenarios!C14)*=Scenarios!F14,0)) -> 0 | E62: =IF(=Scenarios!E14=1,0, Parameters!B7 + ==IF(=Scenarios!H14=1, IF("FY2026"="FY2026",50, IF("FY2026"="FY2027",100,150)), =Scenarios!C14)-(=ROUNDUP(=IF(=Scenarios!H14=1, IF("FY2026"="FY2026",50, IF("FY2026"="FY2027",100,150)), =Scenarios!C14)*=Scenarios!F14,0))) -> 0 | F62: =D62+E62 -> 0 | G62: =IF(=Scenarios!D14=1, IF(=Scenarios!I14="lease", Calc!B4*Parameters!B16, Calc!B4*Parameters!B19), Calc!B4) -> 0 | H62: =IF(=Scenarios!E14=1, IF(=Scenarios!I14="lease", Calc!B5*Parameters!B16, Calc!B5*Parameters!B19), Calc!B5) -> 0 | I62: =Calc!B3 -> 0 | J62: =IF("FY2026"="FY2026", (IF(=Scenarios!D14=1, Parameters!B9,0) + IF(=Scenarios!E14=1, Parameters!B9,0)), 0) -> 0 | K62: =(1-Parameters!B4) -> 0 | L62: =Scenarios!G14 -> 0 | M62: =(IF(Scenarios!D141, IF(Scenarios!I14"lease", Calc!B4*Parameters!B16, Calc!B4*Parameters!B19), Calc!B4) + IF(Scenarios!E141, IF(Scenarios!I14"lease", Calc!B5*Parameters!B16, Calc!B5*Parameters!B19), Calc!B5) + Calc!B3*=D62+E62)*=(1-Parameters!B4)*(1-J62) + =IF("FY2026"="FY2026", (IF(=Scenarios!D14=1, Parameters!B9,0) + IF(=Scenarios!E14=1, Parameters!B9,0)), 0) -> 0 | N62: =IF(F62>0, L62/F62, NA()) -> 0 | O62: ==Scenarios!A14&"|FY2026" -> 0
A63: =Scenarios!A14 -> 0 | B63: FY2027 | C63: =Scenarios!C14 -> 0 | D63: =IF(=Scenarios!D14=1,0, Parameters!B6 + =ROUNDUP(=IF(=Scenarios!H14=1, IF("FY2027"="FY2026",50, IF("FY2027"="FY2027",100,150)), =Scenarios!C14)*=Scenarios!F14,0)) -> 0 | E63: =IF(=Scenarios!E14=1,0, Parameters!B7 + ==IF(=Scenarios!H14=1, IF("FY2027"="FY2026",50, IF("FY2027"="FY2027",100,150)), =Scenarios!C14)-(=ROUNDUP(=IF(=Scenarios!H14=1, IF("FY2027"="FY2026",50, IF("FY2027"="FY2027",100,150)), =Scenarios!C14)*=Scenarios!F14,0))) -> 0 | F63: =D63+E63 -> 0 | G63: =IF(=Scenarios!D14=1, IF(=Scenarios!I14="lease", Calc!C4*Parameters!C16, Calc!C4*Parameters!C19), Calc!C4) -> 0 | H63: =IF(=Scenarios!E14=1, IF(=Scenarios!I14="lease", Calc!C5*Parameters!C16, Calc!C5*Parameters!C19), Calc!C5) -> 0 | I63: =Calc!C3 -> 0 | J63: =IF("FY2027"="FY2026", (IF(=Scenarios!D14=1, Parameters!B9,0) + IF(=Scenarios!E14=1, Parameters!B9,0)), 0) -> 0 | K63: =(1-Parameters!B4) -> 0 | L63: =Scenarios!G14 -> 0 | M63: =(IF(Scenarios!D141, IF(Scenarios!I14"lease", Calc!C4*Parameters!C16, Calc!C4*Parameters!C19), Calc!C4) + IF(Scenarios!E141, IF(Scenarios!I14"lease", Calc!C5*Parameters!C16, Calc!C5*Parameters!C19), Calc!C5) + Calc!C3*=D63+E63)*=(1-Parameters!B4)*(1-J63) + =IF("FY2027"="FY2026", (IF(=Scenarios!D14=1, Parameters!B9,0) + IF(=Scenarios!E14=1, Parameters!B9,0)), 0) -> 0 | N63: =IF(F63>0, L63/F63, NA()) -> 0 | O63: ==Scenarios!A14&"|FY2027" -> 0
A64: =Scenarios!A14 -> 0 | B64: FY2028 | C64: =Scenarios!C14 -> 0 | D64: =IF(=Scenarios!D14=1,0, Parameters!B6 + =ROUNDUP(=IF(=Scenarios!H14=1, IF("FY2028"="FY2026",50, IF("FY2028"="FY2027",100,150)), =Scenarios!C14)*=Scenarios!F14,0)) -> 0 | E64: =IF(=Scenarios!E14=1,0, Parameters!B7 + ==IF(=Scenarios!H14=1, IF("FY2028"="FY2026",50, IF("FY2028"="FY2027",100,150)), =Scenarios!C14)-(=ROUNDUP(=IF(=Scenarios!H14=1, IF("FY2028"="FY2026",50, IF("FY2028"="FY2027",100,150)), =Scenarios!C14)*=Scenarios!F14,0))) -> 0 | F64: =D64+E64 -> 0 | G64: =IF(=Scenarios!D14=1, IF(=Scenarios!I14="lease", Calc!D4*Parameters!D16, Calc!D4*Parameters!D19), Calc!D4) -> 0 | H64: =IF(=Scenarios!E14=1, IF(=Scenarios!I14="lease", Calc!D5*Parameters!D16, Calc!D5*Parameters!D19), Calc!D5) -> 0 | I64: =Calc!D3 -> 0 | J64: =IF("FY2028"="FY2026", (IF(=Scenarios!D14=1, Parameters!B9,0) + IF(=Scenarios!E14=1, Parameters!B9,0)), 0) -> 0 | K64: =(1-Parameters!B4) -> 0 | L64: =Scenarios!G14 -> 0 | M64: =(IF(Scenarios!D141, IF(Scenarios!I14"lease", Calc!D4*Parameters!D16, Calc!D4*Parameters!D19), Calc!D4) + IF(Scenarios!E141, IF(Scenarios!I14"lease", Calc!D5*Parameters!D16, Calc!D5*Parameters!D19), Calc!D5) + Calc!D3*=D64+E64)*=(1-Parameters!B4)*(1-J64) + =IF("FY2028"="FY2026", (IF(=Scenarios!D14=1, Parameters!B9,0) + IF(=Scenarios!E14=1, Parameters!B9,0)), 0) -> 0 | N64: =IF(F64>0, L64/F64, NA()) -> 0 | O64: ==Scenarios!A14&"|FY2028" -> 0
A65: =Scenarios!A14 -> 0 | B65: FY2029 | C65: =Scenarios!C14 -> 0 | D65: =IF(=Scenarios!D14=1,0, Parameters!B6 + =ROUNDUP(=IF(=Scenarios!H14=1, IF("FY2029"="FY2026",50, IF("FY2029"="FY2027",100,150)), =Scenarios!C14)*=Scenarios!F14,0)) -> 0 | E65: =IF(=Scenarios!E14=1,0, Parameters!B7 + ==IF(=Scenarios!H14=1, IF("FY2029"="FY2026",50, IF("FY2029"="FY2027",100,150)), =Scenarios!C14)-(=ROUNDUP(=IF(=Scenarios!H14=1, IF("FY2029"="FY2026",50, IF("FY2029"="FY2027",100,150)), =Scenarios!C14)*=Scenarios!F14,0))) -> 0 | F65: =D65+E65 -> 0 | G65: =IF(=Scenarios!D14=1, IF(=Scenarios!I14="lease", Calc!E4*Parameters!E16, Calc!E4*Parameters!E19), Calc!E4) -> 0 | H65: =IF(=Scenarios!E14=1, IF(=Scenarios!I14="lease", Calc!E5*Parameters!E16, Calc!E5*Parameters!E19), Calc!E5) -> 0 | I65: =Calc!E3 -> 0 | J65: =IF("FY2029"="FY2026", (IF(=Scenarios!D14=1, Parameters!B9,0) + IF(=Scenarios!E14=1, Parameters!B9,0)), 0) -> 0 | K65: =(1-Parameters!B4) -> 0 | L65: =Scenarios!G14 -> 0 | M65: =(IF(Scenarios!D141, IF(Scenarios!I14"lease", Calc!E4*Parameters!E16, Calc!E4*Parameters!E19), Calc!E4) + IF(Scenarios!E141, IF(Scenarios!I14"lease", Calc!E5*Parameters!E16, Calc!E5*Parameters!E19), Calc!E5) + Calc!E3*=D65+E65)*=(1-Parameters!B4)*(1-J65) + =IF("FY2029"="FY2026", (IF(=Scenarios!D14=1, Parameters!B9,0) + IF(=Scenarios!E14=1, Parameters!B9,0)), 0) -> 0 | N65: =IF(F65>0, L65/F65, NA()) -> 0 | O65: ==Scenarios!A14&"|FY2029" -> 0
A66: =Scenarios!A14 -> 0 | B66: FY2030 | C66: =Scenarios!C14 -> 0 | D66: =IF(=Scenarios!D14=1,0, Parameters!B6 + =ROUNDUP(=IF(=Scenarios!H14=1, IF("FY2030"="FY2026",50, IF("FY2030"="FY2027",100,150)), =Scenarios!C14)*=Scenarios!F14,0)) -> 0 | E66: =IF(=Scenarios!E14=1,0, Parameters!B7 + ==IF(=Scenarios!H14=1, IF("FY2030"="FY2026",50, IF("FY2030"="FY2027",100,150)), =Scenarios!C14)-(=ROUNDUP(=IF(=Scenarios!H14=1, IF("FY2030"="FY2026",50, IF("FY2030"="FY2027",100,150)), =Scenarios!C14)*=Scenarios!F14,0))) -> 0 | F66: =D66+E66 -> 0 | G66: =IF(=Scenarios!D14=1, IF(=Scenarios!I14="lease", Calc!F4*Parameters!F16, Calc!F4*Parameters!F19), Calc!F4) -> 0 | H66: =IF(=Scenarios!E14=1, IF(=Scenarios!I14="lease", Calc!F5*Parameters!F16, Calc!F5*Parameters!F19), Calc!F5) -> 0 | I66: =Calc!F3 -> 0 | J66: =IF("FY2030"="FY2026", (IF(=Scenarios!D14=1, Parameters!B9,0) + IF(=Scenarios!E14=1, Parameters!B9,0)), 0) -> 0 | K66: =(1-Parameters!B4) -> 0 | L66: =Scenarios!G14 -> 0 | M66: =(IF(Scenarios!D141, IF(Scenarios!I14"lease", Calc!F4*Parameters!F16, Calc!F4*Parameters!F19), Calc!F4) + IF(Scenarios!E141, IF(Scenarios!I14"lease", Calc!F5*Parameters!F16, Calc!F5*Parameters!F19), Calc!F5) + Calc!F3*=D66+E66)*=(1-Parameters!B4)*(1-J66) + =IF("FY2030"="FY2026", (IF(=Scenarios!D14=1, Parameters!B9,0) + IF(=Scenarios!E14=1, Parameters!B9,0)), 0) -> 0 | N66: =IF(F66>0, L66/F66, NA()) -> 0 | O66: ==Scenarios!A14&"|FY2030" -> 0
A67: =Scenarios!A15 -> 0 | B67: FY2026 | C67: =Scenarios!C15 -> 0 | D67: =IF(=Scenarios!D15=1,0, Parameters!B6 + =ROUNDUP(=IF(=Scenarios!H15=1, IF("FY2026"="FY2026",50, IF("FY2026"="FY2027",100,150)), =Scenarios!C15)*=Scenarios!F15,0)) -> 0 | E67: =IF(=Scenarios!E15=1,0, Parameters!B7 + ==IF(=Scenarios!H15=1, IF("FY2026"="FY2026",50, IF("FY2026"="FY2027",100,150)), =Scenarios!C15)-(=ROUNDUP(=IF(=Scenarios!H15=1, IF("FY2026"="FY2026",50, IF("FY2026"="FY2027",100,150)), =Scenarios!C15)*=Scenarios!F15,0))) -> 0 | F67: =D67+E67 -> 0 | G67: =IF(=Scenarios!D15=1, IF(=Scenarios!I15="lease", Calc!B4*Parameters!B16, Calc!B4*Parameters!B19), Calc!B4) -> 0 | H67: =IF(=Scenarios!E15=1, IF(=Scenarios!I15="lease", Calc!B5*Parameters!B16, Calc!B5*Parameters!B19), Calc!B5) -> 0 | I67: =Calc!B3 -> 0 | J67: =IF("FY2026"="FY2026", (IF(=Scenarios!D15=1, Parameters!B9,0) + IF(=Scenarios!E15=1, Parameters!B9,0)), 0) -> 0 | K67: =(1-Parameters!B4) -> 0 | L67: =Scenarios!G15 -> 0 | M67: =(IF(Scenarios!D151, IF(Scenarios!I15"lease", Calc!B4*Parameters!B16, Calc!B4*Parameters!B19), Calc!B4) + IF(Scenarios!E151, IF(Scenarios!I15"lease", Calc!B5*Parameters!B16, Calc!B5*Parameters!B19), Calc!B5) + Calc!B3*=D67+E67)*=(1-Parameters!B4)*(1-J67) + =IF("FY2026"="FY2026", (IF(=Scenarios!D15=1, Parameters!B9,0) + IF(=Scenarios!E15=1, Parameters!B9,0)), 0) -> 0 | N67: =IF(F67>0, L67/F67, NA()) -> 0 | O67: ==Scenarios!A15&"|FY2026" -> 0
A68: =Scenarios!A15 -> 0 | B68: FY2027 | C68: =Scenarios!C15 -> 0 | D68: =IF(=Scenarios!D15=1,0, Parameters!B6 + =ROUNDUP(=IF(=Scenarios!H15=1, IF("FY2027"="FY2026",50, IF("FY2027"="FY2027",100,150)), =Scenarios!C15)*=Scenarios!F15,0)) -> 0 | E68: =IF(=Scenarios!E15=1,0, Parameters!B7 + ==IF(=Scenarios!H15=1, IF("FY2027"="FY2026",50, IF("FY2027"="FY2027",100,150)), =Scenarios!C15)-(=ROUNDUP(=IF(=Scenarios!H15=1, IF("FY2027"="FY2026",50, IF("FY2027"="FY2027",100,150)), =Scenarios!C15)*=Scenarios!F15,0))) -> 0 | F68: =D68+E68 -> 0 | G68: =IF(=Scenarios!D15=1, IF(=Scenarios!I15="lease", Calc!C4*Parameters!C16, Calc!C4*Parameters!C19), Calc!C4) -> 0 | H68: =IF(=Scenarios!E15=1, IF(=Scenarios!I15="lease", Calc!C5*Parameters!C16, Calc!C5*Parameters!C19), Calc!C5) -> 0 | I68: =Calc!C3 -> 0 | J68: =IF("FY2027"="FY2026", (IF(=Scenarios!D15=1, Parameters!B9,0) + IF(=Scenarios!E15=1, Parameters!B9,0)), 0) -> 0 | K68: =(1-Parameters!B4) -> 0 | L68: =Scenarios!G15 -> 0 | M68: =(IF(Scenarios!D151, IF(Scenarios!I15"lease", Calc!C4*Parameters!C16, Calc!C4*Parameters!C19), Calc!C4) + IF(Scenarios!E151, IF(Scenarios!I15"lease", Calc!C5*Parameters!C16, Calc!C5*Parameters!C19), Calc!C5) + Calc!C3*=D68+E68)*=(1-Parameters!B4)*(1-J68) + =IF("FY2027"="FY2026", (IF(=Scenarios!D15=1, Parameters!B9,0) + IF(=Scenarios!E15=1, Parameters!B9,0)), 0) -> 0 | N68: =IF(F68>0, L68/F68, NA()) -> 0 | O68: ==Scenarios!A15&"|FY2027" -> 0
A69: =Scenarios!A15 -> 0 | B69: FY2028 | C69: =Scenarios!C15 -> 0 | D69: =IF(=Scenarios!D15=1,0, Parameters!B6 + =ROUNDUP(=IF(=Scenarios!H15=1, IF("FY2028"="FY2026",50, IF("FY2028"="FY2027",100,150)), =Scenarios!C15)*=Scenarios!F15,0)) -> 0 | E69: =IF(=Scenarios!E15=1,0, Parameters!B7 + ==IF(=Scenarios!H15=1, IF("FY2028"="FY2026",50, IF("FY2028"="FY2027",100,150)), =Scenarios!C15)-(=ROUNDUP(=IF(=Scenarios!H15=1, IF("FY2028"="FY2026",50, IF("FY2028"="FY2027",100,150)), =Scenarios!C15)*=Scenarios!F15,0))) -> 0 | F69: =D69+E69 -> 0 | G69: =IF(=Scenarios!D15=1, IF(=Scenarios!I15="lease", Calc!D4*Parameters!D16, Calc!D4*Parameters!D19), Calc!D4) -> 0 | H69: =IF(=Scenarios!E15=1, IF(=Scenarios!I15="lease", Calc!D5*Parameters!D16, Calc!D5*Parameters!D19), Calc!D5) -> 0 | I69: =Calc!D3 -> 0 | J69: =IF("FY2028"="FY2026", (IF(=Scenarios!D15=1, Parameters!B9,0) + IF(=Scenarios!E15=1, Parameters!B9,0)), 0) -> 0 | K69: =(1-Parameters!B4) -> 0 | L69: =Scenarios!G15 -> 0 | M69: =(IF(Scenarios!D151, IF(Scenarios!I15"lease", Calc!D4*Parameters!D16, Calc!D4*Parameters!D19), Calc!D4) + IF(Scenarios!E151, IF(Scenarios!I15"lease", Calc!D5*Parameters!D16, Calc!D5*Parameters!D19), Calc!D5) + Calc!D3*=D69+E69)*=(1-Parameters!B4)*(1-J69) + =IF("FY2028"="FY2026", (IF(=Scenarios!D15=1, Parameters!B9,0) + IF(=Scenarios!E15=1, Parameters!B9,0)), 0) -> 0 | N69: =IF(F69>0, L69/F69, NA()) -> 0 | O69: ==Scenarios!A15&"|FY2028" -> 0
A70: =Scenarios!A15 -> 0 | B70: FY2029 | C70: =Scenarios!C15 -> 0 | D70: =IF(=Scenarios!D15=1,0, Parameters!B6 + =ROUNDUP(=IF(=Scenarios!H15=1, IF("FY2029"="FY2026",50, IF("FY2029"="FY2027",100,150)), =Scenarios!C15)*=Scenarios!F15,0)) -> 0 | E70: =IF(=Scenarios!E15=1,0, Parameters!B7 + ==IF(=Scenarios!H15=1, IF("FY2029"="FY2026",50, IF("FY2029"="FY2027",100,150)), =Scenarios!C15)-(=ROUNDUP(=IF(=Scenarios!H15=1, IF("FY2029"="FY2026",50, IF("FY2029"="FY2027",100,150)), =Scenarios!C15)*=Scenarios!F15,0))) -> 0 | F70: =D70+E70 -> 0 | G70: =IF(=Scenarios!D15=1, IF(=Scenarios!I15="lease", Calc!E4*Parameters!E16, Calc!E4*Parameters!E19), Calc!E4) -> 0 | H70: =IF(=Scenarios!E15=1, IF(=Scenarios!I15="lease", Calc!E5*Parameters!E16, Calc!E5*Parameters!E19), Calc!E5) -> 0 | I70: =Calc!E3 -> 0 | J70: =IF("FY2029"="FY2026", (IF(=Scenarios!D15=1, Parameters!B9,0) + IF(=Scenarios!E15=1, Parameters!B9,0)), 0) -> 0 | K70: =(1-Parameters!B4) -> 0 | L70: =Scenarios!G15 -> 0 | M70: =(IF(Scenarios!D151, IF(Scenarios!I15"lease", Calc!E4*Parameters!E16, Calc!E4*Parameters!E19), Calc!E4) + IF(Scenarios!E151, IF(Scenarios!I15"lease", Calc!E5*Parameters!E16, Calc!E5*Parameters!E19), Calc!E5) + Calc!E3*=D70+E70)*=(1-Parameters!B4)*(1-J70) + =IF("FY2029"="FY2026", (IF(=Scenarios!D15=1, Parameters!B9,0) + IF(=Scenarios!E15=1, Parameters!B9,0)), 0) -> 0 | N70: =IF(F70>0, L70/F70, NA()) -> 0 | O70: ==Scenarios!A15&"|FY2029" -> 0
A71: =Scenarios!A15 -> 0 | B71: FY2030 | C71: =Scenarios!C15 -> 0 | D71: =IF(=Scenarios!D15=1,0, Parameters!B6 + =ROUNDUP(=IF(=Scenarios!H15=1, IF("FY2030"="FY2026",50, IF("FY2030"="FY2027",100,150)), =Scenarios!C15)*=Scenarios!F15,0)) -> 0 | E71: =IF(=Scenarios!E15=1,0, Parameters!B7 + ==IF(=Scenarios!H15=1, IF("FY2030"="FY2026",50, IF("FY2030"="FY2027",100,150)), =Scenarios!C15)-(=ROUNDUP(=IF(=Scenarios!H15=1, IF("FY2030"="FY2026",50, IF("FY2030"="FY2027",100,150)), =Scenarios!C15)*=Scenarios!F15,0))) -> 0 | F71: =D71+E71 -> 0 | G71: =IF(=Scenarios!D15=1, IF(=Scenarios!I15="lease", Calc!F4*Parameters!F16, Calc!F4*Parameters!F19), Calc!F4) -> 0 | H71: =IF(=Scenarios!E15=1, IF(=Scenarios!I15="lease", Calc!F5*Parameters!F16, Calc!F5*Parameters!F19), Calc!F5) -> 0 | I71: =Calc!F3 -> 0 | J71: =IF("FY2030"="FY2026", (IF(=Scenarios!D15=1, Parameters!B9,0) + IF(=Scenarios!E15=1, Parameters!B9,0)), 0) -> 0 | K71: =(1-Parameters!B4) -> 0 | L71: =Scenarios!G15 -> 0 | M71: =(IF(Scenarios!D151, IF(Scenarios!I15"lease", Calc!F4*Parameters!F16, Calc!F4*Parameters!F19), Calc!F4) + IF(Scenarios!E151, IF(Scenarios!I15"lease", Calc!F5*Parameters!F16, Calc!F5*Parameters!F19), Calc!F5) + Calc!F3*=D71+E71)*=(1-Parameters!B4)*(1-J71) + =IF("FY2030"="FY2026", (IF(=Scenarios!D15=1, Parameters!B9,0) + IF(=Scenarios!E15=1, Parameters!B9,0)), 0) -> 0 | N71: =IF(F71>0, L71/F71, NA()) -> 0 | O71: ==Scenarios!A15&"|FY2030" -> 0
A72: =Scenarios!A16 -> 0 | B72: FY2026 | C72: =Scenarios!C16 -> 0 | D72: =IF(=Scenarios!D16=1,0, Parameters!B6 + =ROUNDUP(=IF(=Scenarios!H16=1, IF("FY2026"="FY2026",50, IF("FY2026"="FY2027",100,150)), =Scenarios!C16)*=Scenarios!F16,0)) -> 0 | E72: =IF(=Scenarios!E16=1,0, Parameters!B7 + ==IF(=Scenarios!H16=1, IF("FY2026"="FY2026",50, IF("FY2026"="FY2027",100,150)), =Scenarios!C16)-(=ROUNDUP(=IF(=Scenarios!H16=1, IF("FY2026"="FY2026",50, IF("FY2026"="FY2027",100,150)), =Scenarios!C16)*=Scenarios!F16,0))) -> 0 | F72: =D72+E72 -> 0 | G72: =IF(=Scenarios!D16=1, IF(=Scenarios!I16="lease", Calc!B4*Parameters!B16, Calc!B4*Parameters!B19), Calc!B4) -> 0 | H72: =IF(=Scenarios!E16=1, IF(=Scenarios!I16="lease", Calc!B5*Parameters!B16, Calc!B5*Parameters!B19), Calc!B5) -> 0 | I72: =Calc!B3 -> 0 | J72: =IF("FY2026"="FY2026", (IF(=Scenarios!D16=1, Parameters!B9,0) + IF(=Scenarios!E16=1, Parameters!B9,0)), 0) -> 0 | K72: =(1-Parameters!B4) -> 0 | L72: =Scenarios!G16 -> 0 | M72: =(IF(Scenarios!D161, IF(Scenarios!I16"lease", Calc!B4*Parameters!B16, Calc!B4*Parameters!B19), Calc!B4) + IF(Scenarios!E161, IF(Scenarios!I16"lease", Calc!B5*Parameters!B16, Calc!B5*Parameters!B19), Calc!B5) + Calc!B3*=D72+E72)*=(1-Parameters!B4)*(1-J72) + =IF("FY2026"="FY2026", (IF(=Scenarios!D16=1, Parameters!B9,0) + IF(=Scenarios!E16=1, Parameters!B9,0)), 0) -> 0 | N72: =IF(F72>0, L72/F72, NA()) -> 0 | O72: ==Scenarios!A16&"|FY2026" -> 0
A73: =Scenarios!A16 -> 0 | B73: FY2027 | C73: =Scenarios!C16 -> 0 | D73: =IF(=Scenarios!D16=1,0, Parameters!B6 + =ROUNDUP(=IF(=Scenarios!H16=1, IF("FY2027"="FY2026",50, IF("FY2027"="FY2027",100,150)), =Scenarios!C16)*=Scenarios!F16,0)) -> 0 | E73: =IF(=Scenarios!E16=1,0, Parameters!B7 + ==IF(=Scenarios!H16=1, IF("FY2027"="FY2026",50, IF("FY2027"="FY2027",100,150)), =Scenarios!C16)-(=ROUNDUP(=IF(=Scenarios!H16=1, IF("FY2027"="FY2026",50, IF("FY2027"="FY2027",100,150)), =Scenarios!C16)*=Scenarios!F16,0))) -> 0 | F73: =D73+E73 -> 0 | G73: =IF(=Scenarios!D16=1, IF(=Scenarios!I16="lease", Calc!C4*Parameters!C16, Calc!C4*Parameters!C19), Calc!C4) -> 0 | H73: =IF(=Scenarios!E16=1, IF(=Scenarios!I16="lease", Calc!C5*Parameters!C16, Calc!C5*Parameters!C19), Calc!C5) -> 0 | I73: =Calc!C3 -> 0 | J73: =IF("FY2027"="FY2026", (IF(=Scenarios!D16=1, Parameters!B9,0) + IF(=Scenarios!E16=1, Parameters!B9,0)), 0) -> 0 | K73: =(1-Parameters!B4) -> 0 | L73: =Scenarios!G16 -> 0 | M73: =(IF(Scenarios!D161, IF(Scenarios!I16"lease", Calc!C4*Parameters!C16, Calc!C4*Parameters!C19), Calc!C4) + IF(Scenarios!E161, IF(Scenarios!I16"lease", Calc!C5*Parameters!C16, Calc!C5*Parameters!C19), Calc!C5) + Calc!C3*=D73+E73)*=(1-Parameters!B4)*(1-J73) + =IF("FY2027"="FY2026", (IF(=Scenarios!D16=1, Parameters!B9,0) + IF(=Scenarios!E16=1, Parameters!B9,0)), 0) -> 0 | N73: =IF(F73>0, L73/F73, NA()) -> 0 | O73: ==Scenarios!A16&"|FY2027" -> 0
A74: =Scenarios!A16 -> 0 | B74: FY2028 | C74: =Scenarios!C16 -> 0 | D74: =IF(=Scenarios!D16=1,0, Parameters!B6 + =ROUNDUP(=IF(=Scenarios!H16=1, IF("FY2028"="FY2026",50, IF("FY2028"="FY2027",100,150)), =Scenarios!C16)*=Scenarios!F16,0)) -> 0 | E74: =IF(=Scenarios!E16=1,0, Parameters!B7 + ==IF(=Scenarios!H16=1, IF("FY2028"="FY2026",50, IF("FY2028"="FY2027",100,150)), =Scenarios!C16)-(=ROUNDUP(=IF(=Scenarios!H16=1, IF("FY2028"="FY2026",50, IF("FY2028"="FY2027",100,150)), =Scenarios!C16)*=Scenarios!F16,0))) -> 0 | F74: =D74+E74 -> 0 | G74: =IF(=Scenarios!D16=1, IF(=Scenarios!I16="lease", Calc!D4*Parameters!D16, Calc!D4*Parameters!D19), Calc!D4) -> 0 | H74: =IF(=Scenarios!E16=1, IF(=Scenarios!I16="lease", Calc!D5*Parameters!D16, Calc!D5*Parameters!D19), Calc!D5) -> 0 | I74: =Calc!D3 -> 0 | J74: =IF("FY2028"="FY2026", (IF(=Scenarios!D16=1, Parameters!B9,0) + IF(=Scenarios!E16=1, Parameters!B9,0)), 0) -> 0 | K74: =(1-Parameters!B4) -> 0 | L74: =Scenarios!G16 -> 0 | M74: =(IF(Scenarios!D161, IF(Scenarios!I16"lease", Calc!D4*Parameters!D16, Calc!D4*Parameters!D19), Calc!D4) + IF(Scenarios!E161, IF(Scenarios!I16"lease", Calc!D5*Parameters!D16, Calc!D5*Parameters!D19), Calc!D5) + Calc!D3*=D74+E74)*=(1-Parameters!B4)*(1-J74) + =IF("FY2028"="FY2026", (IF(=Scenarios!D16=1, Parameters!B9,0) + IF(=Scenarios!E16=1, Parameters!B9,0)), 0) -> 0 | N74: =IF(F74>0, L74/F74, NA()) -> 0 | O74: ==Scenarios!A16&"|FY2028" -> 0
A75: =Scenarios!A16 -> 0 | B75: FY2029 | C75: =Scenarios!C16 -> 0 | D75: =IF(=Scenarios!D16=1,0, Parameters!B6 + =ROUNDUP(=IF(=Scenarios!H16=1, IF("FY2029"="FY2026",50, IF("FY2029"="FY2027",100,150)), =Scenarios!C16)*=Scenarios!F16,0)) -> 0 | E75: =IF(=Scenarios!E16=1,0, Parameters!B7 + ==IF(=Scenarios!H16=1, IF("FY2029"="FY2026",50, IF("FY2029"="FY2027",100,150)), =Scenarios!C16)-(=ROUNDUP(=IF(=Scenarios!H16=1, IF("FY2029"="FY2026",50, IF("FY2029"="FY2027",100,150)), =Scenarios!C16)*=Scenarios!F16,0))) -> 0 | F75: =D75+E75 -> 0 | G75: =IF(=Scenarios!D16=1, IF(=Scenarios!I16="lease", Calc!E4*Parameters!E16, Calc!E4*Parameters!E19), Calc!E4) -> 0 | H75: =IF(=Scenarios!E16=1, IF(=Scenarios!I16="lease", Calc!E5*Parameters!E16, Calc!E5*Parameters!E19), Calc!E5) -> 0 | I75: =Calc!E3 -> 0 | J75: =IF("FY2029"="FY2026", (IF(=Scenarios!D16=1, Parameters!B9,0) + IF(=Scenarios!E16=1, Parameters!B9,0)), 0) -> 0 | K75: =(1-Parameters!B4) -> 0 | L75: =Scenarios!G16 -> 0 | M75: =(IF(Scenarios!D161, IF(Scenarios!I16"lease", Calc!E4*Parameters!E16, Calc!E4*Parameters!E19), Calc!E4) + IF(Scenarios!E161, IF(Scenarios!I16"lease", Calc!E5*Parameters!E16, Calc!E5*Parameters!E19), Calc!E5) + Calc!E3*=D75+E75)*=(1-Parameters!B4)*(1-J75) + =IF("FY2029"="FY2026", (IF(=Scenarios!D16=1, Parameters!B9,0) + IF(=Scenarios!E16=1, Parameters!B9,0)), 0) -> 0 | N75: =IF(F75>0, L75/F75, NA()) -> 0 | O75: ==Scenarios!A16&"|FY2029" -> 0
A76: =Scenarios!A16 -> 0 | B76: FY2030 | C76: =Scenarios!C16 -> 0 | D76: =IF(=Scenarios!D16=1,0, Parameters!B6 + =ROUNDUP(=IF(=Scenarios!H16=1, IF("FY2030"="FY2026",50, IF("FY2030"="FY2027",100,150)), =Scenarios!C16)*=Scenarios!F16,0)) -> 0 | E76: =IF(=Scenarios!E16=1,0, Parameters!B7 + ==IF(=Scenarios!H16=1, IF("FY2030"="FY2026",50, IF("FY2030"="FY2027",100,150)), =Scenarios!C16)-(=ROUNDUP(=IF(=Scenarios!H16=1, IF("FY2030"="FY2026",50, IF("FY2030"="FY2027",100,150)), =Scenarios!C16)*=Scenarios!F16,0))) -> 0 | F76: =D76+E76 -> 0 | G76: =IF(=Scenarios!D16=1, IF(=Scenarios!I16="lease", Calc!F4*Parameters!F16, Calc!F4*Parameters!F19), Calc!F4) -> 0 | H76: =IF(=Scenarios!E16=1, IF(=Scenarios!I16="lease", Calc!F5*Parameters!F16, Calc!F5*Parameters!F19), Calc!F5) -> 0 | I76: =Calc!F3 -> 0 | J76: =IF("FY2030"="FY2026", (IF(=Scenarios!D16=1, Parameters!B9,0) + IF(=Scenarios!E16=1, Parameters!B9,0)), 0) -> 0 | K76: =(1-Parameters!B4) -> 0 | L76: =Scenarios!G16 -> 0 | M76: =(IF(Scenarios!D161, IF(Scenarios!I16"lease", Calc!F4*Parameters!F16, Calc!F4*Parameters!F19), Calc!F4) + IF(Scenarios!E161, IF(Scenarios!I16"lease", Calc!F5*Parameters!F16, Calc!F5*Parameters!F19), Calc!F5) + Calc!F3*=D76+E76)*=(1-Parameters!B4)*(1-J76) + =IF("FY2030"="FY2026", (IF(=Scenarios!D16=1, Parameters!B9,0) + IF(=Scenarios!E16=1, Parameters!B9,0)), 0) -> 0 | N76: =IF(F76>0, L76/F76, NA()) -> 0 | O76: ==Scenarios!A16&"|FY2030" -> 0
A77: =Scenarios!A17 -> 0 | B77: FY2026 | C77: =Scenarios!C17 -> 0 | D77: =IF(=Scenarios!D17=1,0, Parameters!B6 + =ROUNDUP(=IF(=Scenarios!H17=1, IF("FY2026"="FY2026",50, IF("FY2026"="FY2027",100,150)), =Scenarios!C17)*=Scenarios!F17,0)) -> 0 | E77: =IF(=Scenarios!E17=1,0, Parameters!B7 + ==IF(=Scenarios!H17=1, IF("FY2026"="FY2026",50, IF("FY2026"="FY2027",100,150)), =Scenarios!C17)-(=ROUNDUP(=IF(=Scenarios!H17=1, IF("FY2026"="FY2026",50, IF("FY2026"="FY2027",100,150)), =Scenarios!C17)*=Scenarios!F17,0))) -> 0 | F77: =D77+E77 -> 0 | G77: =IF(=Scenarios!D17=1, IF(=Scenarios!I17="lease", Calc!B4*Parameters!B16, Calc!B4*Parameters!B19), Calc!B4) -> 0 | H77: =IF(=Scenarios!E17=1, IF(=Scenarios!I17="lease", Calc!B5*Parameters!B16, Calc!B5*Parameters!B19), Calc!B5) -> 0 | I77: =Calc!B3 -> 0 | J77: =IF("FY2026"="FY2026", (IF(=Scenarios!D17=1, Parameters!B9,0) + IF(=Scenarios!E17=1, Parameters!B9,0)), 0) -> 0 | K77: =(1-Parameters!B4) -> 0 | L77: =Scenarios!G17 -> 0 | M77: =(IF(Scenarios!D171, IF(Scenarios!I17"lease", Calc!B4*Parameters!B16, Calc!B4*Parameters!B19), Calc!B4) + IF(Scenarios!E171, IF(Scenarios!I17"lease", Calc!B5*Parameters!B16, Calc!B5*Parameters!B19), Calc!B5) + Calc!B3*=D77+E77)*=(1-Parameters!B4)*(1-J77) + =IF("FY2026"="FY2026", (IF(=Scenarios!D17=1, Parameters!B9,0) + IF(=Scenarios!E17=1, Parameters!B9,0)), 0) -> 0 | N77: =IF(F77>0, L77/F77, NA()) -> 0 | O77: ==Scenarios!A17&"|FY2026" -> 0
A78: =Scenarios!A17 -> 0 | B78: FY2027 | C78: =Scenarios!C17 -> 0 | D78: =IF(=Scenarios!D17=1,0, Parameters!B6 + =ROUNDUP(=IF(=Scenarios!H17=1, IF("FY2027"="FY2026",50, IF("FY2027"="FY2027",100,150)), =Scenarios!C17)*=Scenarios!F17,0)) -> 0 | E78: =IF(=Scenarios!E17=1,0, Parameters!B7 + ==IF(=Scenarios!H17=1, IF("FY2027"="FY2026",50, IF("FY2027"="FY2027",100,150)), =Scenarios!C17)-(=ROUNDUP(=IF(=Scenarios!H17=1, IF("FY2027"="FY2026",50, IF("FY2027"="FY2027",100,150)), =Scenarios!C17)*=Scenarios!F17,0))) -> 0 | F78: =D78+E78 -> 0 | G78: =IF(=Scenarios!D17=1, IF(=Scenarios!I17="lease", Calc!C4*Parameters!C16, Calc!C4*Parameters!C19), Calc!C4) -> 0 | H78: =IF(=Scenarios!E17=1, IF(=Scenarios!I17="lease", Calc!C5*Parameters!C16, Calc!C5*Parameters!C19), Calc!C5) -> 0 | I78: =Calc!C3 -> 0 | J78: =IF("FY2027"="FY2026", (IF(=Scenarios!D17=1, Parameters!B9,0) + IF(=Scenarios!E17=1, Parameters!B9,0)), 0) -> 0 | K78: =(1-Parameters!B4) -> 0 | L78: =Scenarios!G17 -> 0 | M78: =(IF(Scenarios!D171, IF(Scenarios!I17"lease", Calc!C4*Parameters!C16, Calc!C4*Parameters!C19), Calc!C4) + IF(Scenarios!E171, IF(Scenarios!I17"lease", Calc!C5*Parameters!C16, Calc!C5*Parameters!C19), Calc!C5) + Calc!C3*=D78+E78)*=(1-Parameters!B4)*(1-J78) + =IF("FY2027"="FY2026", (IF(=Scenarios!D17=1, Parameters!B9,0) + IF(=Scenarios!E17=1, Parameters!B9,0)), 0) -> 0 | N78: =IF(F78>0, L78/F78, NA()) -> 0 | O78: ==Scenarios!A17&"|FY2027" -> 0
A79: =Scenarios!A17 -> 0 | B79: FY2028 | C79: =Scenarios!C17 -> 0 | D79: =IF(=Scenarios!D17=1,0, Parameters!B6 + =ROUNDUP(=IF(=Scenarios!H17=1, IF("FY2028"="FY2026",50, IF("FY2028"="FY2027",100,150)), =Scenarios!C17)*=Scenarios!F17,0)) -> 0 | E79: =IF(=Scenarios!E17=1,0, Parameters!B7 + ==IF(=Scenarios!H17=1, IF("FY2028"="FY2026",50, IF("FY2028"="FY2027",100,150)), =Scenarios!C17)-(=ROUNDUP(=IF(=Scenarios!H17=1, IF("FY2028"="FY2026",50, IF("FY2028"="FY2027",100,150)), =Scenarios!C17)*=Scenarios!F17,0))) -> 0 | F79: =D79+E79 -> 0 | G79: =IF(=Scenarios!D17=1, IF(=Scenarios!I17="lease", Calc!D4*Parameters!D16, Calc!D4*Parameters!D19), Calc!D4) -> 0 | H79: =IF(=Scenarios!E17=1, IF(=Scenarios!I17="lease", Calc!D5*Parameters!D16, Calc!D5*Parameters!D19), Calc!D5) -> 0 | I79: =Calc!D3 -> 0 | J79: =IF("FY2028"="FY2026", (IF(=Scenarios!D17=1, Parameters!B9,0) + IF(=Scenarios!E17=1, Parameters!B9,0)), 0) -> 0 | K79: =(1-Parameters!B4) -> 0 | L79: =Scenarios!G17 -> 0 | M79: =(IF(Scenarios!D171, IF(Scenarios!I17"lease", Calc!D4*Parameters!D16, Calc!D4*Parameters!D19), Calc!D4) + IF(Scenarios!E171, IF(Scenarios!I17"lease", Calc!D5*Parameters!D16, Calc!D5*Parameters!D19), Calc!D5) + Calc!D3*=D79+E79)*=(1-Parameters!B4)*(1-J79) + =IF("FY2028"="FY2026", (IF(=Scenarios!D17=1, Parameters!B9,0) + IF(=Scenarios!E17=1, Parameters!B9,0)), 0) -> 0 | N79: =IF(F79>0, L79/F79, NA()) -> 0 | O79: ==Scenarios!A17&"|FY2028" -> 0
A80: =Scenarios!A17 -> 0 | B80: FY2029 | C80: =Scenarios!C17 -> 0 | D80: =IF(=Scenarios!D17=1,0, Parameters!B6 + =ROUNDUP(=IF(=Scenarios!H17=1, IF("FY2029"="FY2026",50, IF("FY2029"="FY2027",100,150)), =Scenarios!C17)*=Scenarios!F17,0)) -> 0 | E80: =IF(=Scenarios!E17=1,0, Parameters!B7 + ==IF(=Scenarios!H17=1, IF("FY2029"="FY2026",50, IF("FY2029"="FY2027",100,150)), =Scenarios!C17)-(=ROUNDUP(=IF(=Scenarios!H17=1, IF("FY2029"="FY2026",50, IF("FY2029"="FY2027",100,150)), =Scenarios!C17)*=Scenarios!F17,0))) -> 0 | F80: =D80+E80 -> 0 | G80: =IF(=Scenarios!D17=1, IF(=Scenarios!I17="lease", Calc!E4*Parameters!E16, Calc!E4*Parameters!E19), Calc!E4) -> 0 | H80: =IF(=Scenarios!E17=1, IF(=Scenarios!I17="lease", Calc!E5*Parameters!E16, Calc!E5*Parameters!E19), Calc!E5) -> 0 | I80: =Calc!E3 -> 0 | J80: =IF("FY2029"="FY2026", (IF(=Scenarios!D17=1, Parameters!B9,0) + IF(=Scenarios!E17=1, Parameters!B9,0)), 0) -> 0 | K80: =(1-Parameters!B4) -> 0 | L80: =Scenarios!G17 -> 0 | M80: =(IF(Scenarios!D171, IF(Scenarios!I17"lease", Calc!E4*Parameters!E16, Calc!E4*Parameters!E19), Calc!E4) + IF(Scenarios!E171, IF(Scenarios!I17"lease", Calc!E5*Parameters!E16, Calc!E5*Parameters!E19), Calc!E5) + Calc!E3*=D80+E80)*=(1-Parameters!B4)*(1-J80) + =IF("FY2029"="FY2026", (IF(=Scenarios!D17=1, Parameters!B9,0) + IF(=Scenarios!E17=1, Parameters!B9,0)), 0) -> 0 | N80: =IF(F80>0, L80/F80, NA()) -> 0 | O80: ==Scenarios!A17&"|FY2029" -> 0
A81: =Scenarios!A17 -> 0 | B81: FY2030 | C81: =Scenarios!C17 -> 0 | D81: =IF(=Scenarios!D17=1,0, Parameters!B6 + =ROUNDUP(=IF(=Scenarios!H17=1, IF("FY2030"="FY2026",50, IF("FY2030"="FY2027",100,150)), =Scenarios!C17)*=Scenarios!F17,0)) -> 0 | E81: =IF(=Scenarios!E17=1,0, Parameters!B7 + ==IF(=Scenarios!H17=1, IF("FY2030"="FY2026",50, IF("FY2030"="FY2027",100,150)), =Scenarios!C17)-(=ROUNDUP(=IF(=Scenarios!H17=1, IF("FY2030"="FY2026",50, IF("FY2030"="FY2027",100,150)), =Scenarios!C17)*=Scenarios!F17,0))) -> 0 | F81: =D81+E81 -> 0 | G81: =IF(=Scenarios!D17=1, IF(=Scenarios!I17="lease", Calc!F4*Parameters!F16, Calc!F4*Parameters!F19), Calc!F4) -> 0 | H81: =IF(=Scenarios!E17=1, IF(=Scenarios!I17="lease", Calc!F5*Parameters!F16, Calc!F5*Parameters!F19), Calc!F5) -> 0 | I81: =Calc!F3 -> 0 | J81: =IF("FY2030"="FY2026", (IF(=Scenarios!D17=1, Parameters!B9,0) + IF(=Scenarios!E17=1, Parameters!B9,0)), 0) -> 0 | K81: =(1-Parameters!B4) -> 0 | L81: =Scenarios!G17 -> 0 | M81: =(IF(Scenarios!D171, IF(Scenarios!I17"lease", Calc!F4*Parameters!F16, Calc!F4*Parameters!F19), Calc!F4) + IF(Scenarios!E171, IF(Scenarios!I17"lease", Calc!F5*Parameters!F16, Calc!F5*Parameters!F19), Calc!F5) + Calc!F3*=D81+E81)*=(1-Parameters!B4)*(1-J81) + =IF("FY2030"="FY2026", (IF(=Scenarios!D17=1, Parameters!B9,0) + IF(=Scenarios!E17=1, Parameters!B9,0)), 0) -> 0 | N81: =IF(F81>0, L81/F81, NA()) -> 0 | O81: ==Scenarios!A17&"|FY2030" -> 0

Sheet Summary_Costs
A1: ScenarioKey | B1: Overlay | C1: Key | D1: Comparable_$FY2028 | E1: Comparable_$FY2030 | F1: Comparable_3yrAvg_$
A2: =Scenarios!A2 -> 0 | B2: 0 | C2: =A2&"|"&"FY2028" -> 0 | D2: =IFERROR( (INDEX(MultiYear_ProForma!$L:$L, MATCH($C2, MultiYear_ProForma!$O:$O,0)) + (IFERROR(VLOOKUP($A2,$H$3:$I$8,2,FALSE),0)*$I$11*(INDEX(MultiYear_ProForma!$I:$I, MATCH($C2, MultiYear_ProForma!$O:$O,0)) + VLOOKUP("FY2028",$H$13:$J$17,2,FALSE))) ) / ( INDEX(MultiYear_ProForma!$F:$F, MATCH($C2, MultiYear_ProForma!$O:$O,0)) + IFERROR(VLOOKUP($A2,$H$3:$I$8,2,FALSE),0)*$I$11 ), "") -> 0 | E2: =IFERROR( (INDEX(MultiYear_ProForma!$L:$L, MATCH($A2&"|FY2030", MultiYear_ProForma!$O:$O,0)) + (IFERROR(VLOOKUP($A2,$H$3:$I$8,2,FALSE),0)*$I$11*(INDEX(MultiYear_ProForma!$I:$I, MATCH($A2&"|FY2030", MultiYear_ProForma!$O:$O,0)) + VLOOKUP("FY2030",$H$13:$J$17,2,FALSE))) ) / ( INDEX(MultiYear_ProForma!$F:$F, MATCH($A2&"|FY2030", MultiYear_ProForma!$O:$O,0)) + IFERROR(VLOOKUP($A2,$H$3:$I$8,2,FALSE),0)*$I$11 ), "") -> 0 | F2: =AVERAGE(( (INDEX(MultiYear_ProForma!$L:$L, MATCH($A2&"|FY2026", MultiYear_ProForma!$O:$O,0)) + (IFERROR(VLOOKUP($A2,$H$3:$I$8,2,FALSE),0)*$I$11*(INDEX(MultiYear_ProForma!$I:$I, MATCH($A2&"|FY2026", MultiYear_ProForma!$O:$O,0)) + VLOOKUP("FY2026",$H$13:$J$17,2,FALSE)))) / ( INDEX(MultiYear_ProForma!$F:$F, MATCH($A2&"|FY2026", MultiYear_ProForma!$O:$O,0)) + IFERROR(VLOOKUP($A2,$H$3:$I$8,2,FALSE),0)*$I$11 ),( (INDEX(MultiYear_ProForma!$L:$L, MATCH($A2&"|FY2027", MultiYear_ProForma!$O:$O,0)) + (IFERROR(VLOOKUP($A2,$H$3:$I$8,2,FALSE),0)*$I$11*(INDEX(MultiYear_ProForma!$I:$I, MATCH($A2&"|FY2027", MultiYear_ProForma!$O:$O,0)) + VLOOKUP("FY2027",$H$13:$J$17,2,FALSE)))) / ( INDEX(MultiYear_ProForma!$F:$F, MATCH($A2&"|FY2027", MultiYear_ProForma!$O:$O,0)) + IFERROR(VLOOKUP($A2,$H$3:$I$8,2,FALSE),0)*$I$11 ),( (INDEX(MultiYear_ProForma!$L:$L, MATCH($A2&"|FY2028", MultiYear_ProForma!$O:$O,0)) + (IFERROR(VLOOKUP($A2,$H$3:$I$8,2,FALSE),0)*$I$11*(INDEX(MultiYear_ProForma!$I:$I, MATCH($A2&"|FY2028", MultiYear_ProForma!$O:$O,0)) + VLOOKUP("FY2028",$H$13:$J$17,2,FALSE)))) / ( INDEX(MultiYear_ProForma!$F:$F, MATCH($A2&"|FY2028", MultiYear_ProForma!$O:$O,0)) + IFERROR(VLOOKUP($A2,$H$3:$I$8,2,FALSE),0)*$I$11 )) -> 0
A3: =Scenarios!A3 -> 0 | B3: 0 | C3: =A3&"|"&"FY2028" -> 0 | D3: =IFERROR( (INDEX(MultiYear_ProForma!$L:$L, MATCH($C3, MultiYear_ProForma!$O:$O,0)) + (IFERROR(VLOOKUP($A3,$H$3:$I$8,2,FALSE),0)*$I$11*(INDEX(MultiYear_ProForma!$I:$I, MATCH($C3, MultiYear_ProForma!$O:$O,0)) + VLOOKUP("FY2028",$H$13:$J$17,2,FALSE))) ) / ( INDEX(MultiYear_ProForma!$F:$F, MATCH($C3, MultiYear_ProForma!$O:$O,0)) + IFERROR(VLOOKUP($A3,$H$3:$I$8,2,FALSE),0)*$I$11 ), "") -> 0 | E3: =IFERROR( (INDEX(MultiYear_ProForma!$L:$L, MATCH($A3&"|FY2030", MultiYear_ProForma!$O:$O,0)) + (IFERROR(VLOOKUP($A3,$H$3:$I$8,2,FALSE),0)*$I$11*(INDEX(MultiYear_ProForma!$I:$I, MATCH($A3&"|FY2030", MultiYear_ProForma!$O:$O,0)) + VLOOKUP("FY2030",$H$13:$J$17,2,FALSE))) ) / ( INDEX(MultiYear_ProForma!$F:$F, MATCH($A3&"|FY2030", MultiYear_ProForma!$O:$O,0)) + IFERROR(VLOOKUP($A3,$H$3:$I$8,2,FALSE),0)*$I$11 ), "") -> 0 | F3: =AVERAGE(( (INDEX(MultiYear_ProForma!$L:$L, MATCH($A3&"|FY2026", MultiYear_ProForma!$O:$O,0)) + (IFERROR(VLOOKUP($A3,$H$3:$I$8,2,FALSE),0)*$I$11*(INDEX(MultiYear_ProForma!$I:$I, MATCH($A3&"|FY2026", MultiYear_ProForma!$O:$O,0)) + VLOOKUP("FY2026",$H$13:$J$17,2,FALSE)))) / ( INDEX(MultiYear_ProForma!$F:$F, MATCH($A3&"|FY2026", MultiYear_ProForma!$O:$O,0)) + IFERROR(VLOOKUP($A3,$H$3:$I$8,2,FALSE),0)*$I$11 ),( (INDEX(MultiYear_ProForma!$L:$L, MATCH($A3&"|FY2027", MultiYear_ProForma!$O:$O,0)) + (IFERROR(VLOOKUP($A3,$H$3:$I$8,2,FALSE),0)*$I$11*(INDEX(MultiYear_ProForma!$I:$I, MATCH($A3&"|FY2027", MultiYear_ProForma!$O:$O,0)) + VLOOKUP("FY2027",$H$13:$J$17,2,FALSE)))) / ( INDEX(MultiYear_ProForma!$F:$F, MATCH($A3&"|FY2027", MultiYear_ProForma!$O:$O,0)) + IFERROR(VLOOKUP($A3,$H$3:$I$8,2,FALSE),0)*$I$11 ),( (INDEX(MultiYear_ProForma!$L:$L, MATCH($A3&"|FY2028", MultiYear_ProForma!$O:$O,0)) + (IFERROR(VLOOKUP($A3,$H$3:$I$8,2,FALSE),0)*$I$11*(INDEX(MultiYear_ProForma!$I:$I, MATCH($A3&"|FY2028", MultiYear_ProForma!$O:$O,0)) + VLOOKUP("FY2028",$H$13:$J$17,2,FALSE)))) / ( INDEX(MultiYear_ProForma!$F:$F, MATCH($A3&"|FY2028", MultiYear_ProForma!$O:$O,0)) + IFERROR(VLOOKUP($A3,$H$3:$I$8,2,FALSE),0)*$I$11 )) -> 0 | H3: Helper: Displaced by ScenarioKey | I3: Displaced_T
A4: =Scenarios!A4 -> 0 | B4: 0 | C4: =A4&"|"&"FY2028" -> 0 | D4: =IFERROR( (INDEX(MultiYear_ProForma!$L:$L, MATCH($C4, MultiYear_ProForma!$O:$O,0)) + (IFERROR(VLOOKUP($A4,$H$3:$I$8,2,FALSE),0)*$I$11*(INDEX(MultiYear_ProForma!$I:$I, MATCH($C4, MultiYear_ProForma!$O:$O,0)) + VLOOKUP("FY2028",$H$13:$J$17,2,FALSE))) ) / ( INDEX(MultiYear_ProForma!$F:$F, MATCH($C4, MultiYear_ProForma!$O:$O,0)) + IFERROR(VLOOKUP($A4,$H$3:$I$8,2,FALSE),0)*$I$11 ), "") -> 0 | E4: =IFERROR( (INDEX(MultiYear_ProForma!$L:$L, MATCH($A4&"|FY2030", MultiYear_ProForma!$O:$O,0)) + (IFERROR(VLOOKUP($A4,$H$3:$I$8,2,FALSE),0)*$I$11*(INDEX(MultiYear_ProForma!$I:$I, MATCH($A4&"|FY2030", MultiYear_ProForma!$O:$O,0)) + VLOOKUP("FY2030",$H$13:$J$17,2,FALSE))) ) / ( INDEX(MultiYear_ProForma!$F:$F, MATCH($A4&"|FY2030", MultiYear_ProForma!$O:$O,0)) + IFERROR(VLOOKUP($A4,$H$3:$I$8,2,FALSE),0)*$I$11 ), "") -> 0 | F4: =AVERAGE(( (INDEX(MultiYear_ProForma!$L:$L, MATCH($A4&"|FY2026", MultiYear_ProForma!$O:$O,0)) + (IFERROR(VLOOKUP($A4,$H$3:$I$8,2,FALSE),0)*$I$11*(INDEX(MultiYear_ProForma!$I:$I, MATCH($A4&"|FY2026", MultiYear_ProForma!$O:$O,0)) + VLOOKUP("FY2026",$H$13:$J$17,2,FALSE)))) / ( INDEX(MultiYear_ProForma!$F:$F, MATCH($A4&"|FY2026", MultiYear_ProForma!$O:$O,0)) + IFERROR(VLOOKUP($A4,$H$3:$I$8,2,FALSE),0)*$I$11 ),( (INDEX(MultiYear_ProForma!$L:$L, MATCH($A4&"|FY2027", MultiYear_ProForma!$O:$O,0)) + (IFERROR(VLOOKUP($A4,$H$3:$I$8,2,FALSE),0)*$I$11*(INDEX(MultiYear_ProForma!$I:$I, MATCH($A4&"|FY2027", MultiYear_ProForma!$O:$O,0)) + VLOOKUP("FY2027",$H$13:$J$17,2,FALSE)))) / ( INDEX(MultiYear_ProForma!$F:$F, MATCH($A4&"|FY2027", MultiYear_ProForma!$O:$O,0)) + IFERROR(VLOOKUP($A4,$H$3:$I$8,2,FALSE),0)*$I$11 ),( (INDEX(MultiYear_ProForma!$L:$L, MATCH($A4&"|FY2028", MultiYear_ProForma!$O:$O,0)) + (IFERROR(VLOOKUP($A4,$H$3:$I$8,2,FALSE),0)*$I$11*(INDEX(MultiYear_ProForma!$I:$I, MATCH($A4&"|FY2028", MultiYear_ProForma!$O:$O,0)) + VLOOKUP("FY2028",$H$13:$J$17,2,FALSE)))) / ( INDEX(MultiYear_ProForma!$F:$F, MATCH($A4&"|FY2028", MultiYear_ProForma!$O:$O,0)) + IFERROR(VLOOKUP($A4,$H$3:$I$8,2,FALSE),0)*$I$11 )) -> 0 | H4: A_Repurpose_Both_lease | I4: 553
A5: =Scenarios!A5 -> 0 | B5: 0 | C5: =A5&"|"&"FY2028" -> 0 | D5: =IFERROR( (INDEX(MultiYear_ProForma!$L:$L, MATCH($C5, MultiYear_ProForma!$O:$O,0)) + (IFERROR(VLOOKUP($A5,$H$3:$I$8,2,FALSE),0)*$I$11*(INDEX(MultiYear_ProForma!$I:$I, MATCH($C5, MultiYear_ProForma!$O:$O,0)) + VLOOKUP("FY2028",$H$13:$J$17,2,FALSE))) ) / ( INDEX(MultiYear_ProForma!$F:$F, MATCH($C5, MultiYear_ProForma!$O:$O,0)) + IFERROR(VLOOKUP($A5,$H$3:$I$8,2,FALSE),0)*$I$11 ), "") -> 0 | E5: =IFERROR( (INDEX(MultiYear_ProForma!$L:$L, MATCH($A5&"|FY2030", MultiYear_ProForma!$O:$O,0)) + (IFERROR(VLOOKUP($A5,$H$3:$I$8,2,FALSE),0)*$I$11*(INDEX(MultiYear_ProForma!$I:$I, MATCH($A5&"|FY2030", MultiYear_ProForma!$O:$O,0)) + VLOOKUP("FY2030",$H$13:$J$17,2,FALSE))) ) / ( INDEX(MultiYear_ProForma!$F:$F, MATCH($A5&"|FY2030", MultiYear_ProForma!$O:$O,0)) + IFERROR(VLOOKUP($A5,$H$3:$I$8,2,FALSE),0)*$I$11 ), "") -> 0 | F5: =AVERAGE(( (INDEX(MultiYear_ProForma!$L:$L, MATCH($A5&"|FY2026", MultiYear_ProForma!$O:$O,0)) + (IFERROR(VLOOKUP($A5,$H$3:$I$8,2,FALSE),0)*$I$11*(INDEX(MultiYear_ProForma!$I:$I, MATCH($A5&"|FY2026", MultiYear_ProForma!$O:$O,0)) + VLOOKUP("FY2026",$H$13:$J$17,2,FALSE)))) / ( INDEX(MultiYear_ProForma!$F:$F, MATCH($A5&"|FY2026", MultiYear_ProForma!$O:$O,0)) + IFERROR(VLOOKUP($A5,$H$3:$I$8,2,FALSE),0)*$I$11 ),( (INDEX(MultiYear_ProForma!$L:$L, MATCH($A5&"|FY2027", MultiYear_ProForma!$O:$O,0)) + (IFERROR(VLOOKUP($A5,$H$3:$I$8,2,FALSE),0)*$I$11*(INDEX(MultiYear_ProForma!$I:$I, MATCH($A5&"|FY2027", MultiYear_ProForma!$O:$O,0)) + VLOOKUP("FY2027",$H$13:$J$17,2,FALSE)))) / ( INDEX(MultiYear_ProForma!$F:$F, MATCH($A5&"|FY2027", MultiYear_ProForma!$O:$O,0)) + IFERROR(VLOOKUP($A5,$H$3:$I$8,2,FALSE),0)*$I$11 ),( (INDEX(MultiYear_ProForma!$L:$L, MATCH($A5&"|FY2028", MultiYear_ProForma!$O:$O,0)) + (IFERROR(VLOOKUP($A5,$H$3:$I$8,2,FALSE),0)*$I$11*(INDEX(MultiYear_ProForma!$I:$I, MATCH($A5&"|FY2028", MultiYear_ProForma!$O:$O,0)) + VLOOKUP("FY2028",$H$13:$J$17,2,FALSE)))) / ( INDEX(MultiYear_ProForma!$F:$F, MATCH($A5&"|FY2028", MultiYear_ProForma!$O:$O,0)) + IFERROR(VLOOKUP($A5,$H$3:$I$8,2,FALSE),0)*$I$11 )) -> 0 | H5: A_Repurpose_Both_ops | I5: 553
A6: =Scenarios!A6 -> 0 | B6: 0 | C6: =A6&"|"&"FY2028" -> 0 | D6: =IFERROR( (INDEX(MultiYear_ProForma!$L:$L, MATCH($C6, MultiYear_ProForma!$O:$O,0)) + (IFERROR(VLOOKUP($A6,$H$3:$I$8,2,FALSE),0)*$I$11*(INDEX(MultiYear_ProForma!$I:$I, MATCH($C6, MultiYear_ProForma!$O:$O,0)) + VLOOKUP("FY2028",$H$13:$J$17,2,FALSE))) ) / ( INDEX(MultiYear_ProForma!$F:$F, MATCH($C6, MultiYear_ProForma!$O:$O,0)) + IFERROR(VLOOKUP($A6,$H$3:$I$8,2,FALSE),0)*$I$11 ), "") -> 0 | E6: =IFERROR( (INDEX(MultiYear_ProForma!$L:$L, MATCH($A6&"|FY2030", MultiYear_ProForma!$O:$O,0)) + (IFERROR(VLOOKUP($A6,$H$3:$I$8,2,FALSE),0)*$I$11*(INDEX(MultiYear_ProForma!$I:$I, MATCH($A6&"|FY2030", MultiYear_ProForma!$O:$O,0)) + VLOOKUP("FY2030",$H$13:$J$17,2,FALSE))) ) / ( INDEX(MultiYear_ProForma!$F:$F, MATCH($A6&"|FY2030", MultiYear_ProForma!$O:$O,0)) + IFERROR(VLOOKUP($A6,$H$3:$I$8,2,FALSE),0)*$I$11 ), "") -> 0 | F6: =AVERAGE(( (INDEX(MultiYear_ProForma!$L:$L, MATCH($A6&"|FY2026", MultiYear_ProForma!$O:$O,0)) + (IFERROR(VLOOKUP($A6,$H$3:$I$8,2,FALSE),0)*$I$11*(INDEX(MultiYear_ProForma!$I:$I, MATCH($A6&"|FY2026", MultiYear_ProForma!$O:$O,0)) + VLOOKUP("FY2026",$H$13:$J$17,2,FALSE)))) / ( INDEX(MultiYear_ProForma!$F:$F, MATCH($A6&"|FY2026", MultiYear_ProForma!$O:$O,0)) + IFERROR(VLOOKUP($A6,$H$3:$I$8,2,FALSE),0)*$I$11 ),( (INDEX(MultiYear_ProForma!$L:$L, MATCH($A6&"|FY2027", MultiYear_ProForma!$O:$O,0)) + (IFERROR(VLOOKUP($A6,$H$3:$I$8,2,FALSE),0)*$I$11*(INDEX(MultiYear_ProForma!$I:$I, MATCH($A6&"|FY2027", MultiYear_ProForma!$O:$O,0)) + VLOOKUP("FY2027",$H$13:$J$17,2,FALSE)))) / ( INDEX(MultiYear_ProForma!$F:$F, MATCH($A6&"|FY2027", MultiYear_ProForma!$O:$O,0)) + IFERROR(VLOOKUP($A6,$H$3:$I$8,2,FALSE),0)*$I$11 ),( (INDEX(MultiYear_ProForma!$L:$L, MATCH($A6&"|FY2028", MultiYear_ProForma!$O:$O,0)) + (IFERROR(VLOOKUP($A6,$H$3:$I$8,2,FALSE),0)*$I$11*(INDEX(MultiYear_ProForma!$I:$I, MATCH($A6&"|FY2028", MultiYear_ProForma!$O:$O,0)) + VLOOKUP("FY2028",$H$13:$J$17,2,FALSE)))) / ( INDEX(MultiYear_ProForma!$F:$F, MATCH($A6&"|FY2028", MultiYear_ProForma!$O:$O,0)) + IFERROR(VLOOKUP($A6,$H$3:$I$8,2,FALSE),0)*$I$11 )) -> 0 | H6: B_Repurpose_Echo_Grow_Pima_lease | I6: 257
A7: =Scenarios!A7 -> 0 | B7: 0 | C7: =A7&"|"&"FY2028" -> 0 | D7: =IFERROR( (INDEX(MultiYear_ProForma!$L:$L, MATCH($C7, MultiYear_ProForma!$O:$O,0)) + (IFERROR(VLOOKUP($A7,$H$3:$I$8,2,FALSE),0)*$I$11*(INDEX(MultiYear_ProForma!$I:$I, MATCH($C7, MultiYear_ProForma!$O:$O,0)) + VLOOKUP("FY2028",$H$13:$J$17,2,FALSE))) ) / ( INDEX(MultiYear_ProForma!$F:$F, MATCH($C7, MultiYear_ProForma!$O:$O,0)) + IFERROR(VLOOKUP($A7,$H$3:$I$8,2,FALSE),0)*$I$11 ), "") -> 0 | E7: =IFERROR( (INDEX(MultiYear_ProForma!$L:$L, MATCH($A7&"|FY2030", MultiYear_ProForma!$O:$O,0)) + (IFERROR(VLOOKUP($A7,$H$3:$I$8,2,FALSE),0)*$I$11*(INDEX(MultiYear_ProForma!$I:$I, MATCH($A7&"|FY2030", MultiYear_ProForma!$O:$O,0)) + VLOOKUP("FY2030",$H$13:$J$17,2,FALSE))) ) / ( INDEX(MultiYear_ProForma!$F:$F, MATCH($A7&"|FY2030", MultiYear_ProForma!$O:$O,0)) + IFERROR(VLOOKUP($A7,$H$3:$I$8,2,FALSE),0)*$I$11 ), "") -> 0 | F7: =AVERAGE(( (INDEX(MultiYear_ProForma!$L:$L, MATCH($A7&"|FY2026", MultiYear_ProForma!$O:$O,0)) + (IFERROR(VLOOKUP($A7,$H$3:$I$8,2,FALSE),0)*$I$11*(INDEX(MultiYear_ProForma!$I:$I, MATCH($A7&"|FY2026", MultiYear_ProForma!$O:$O,0)) + VLOOKUP("FY2026",$H$13:$J$17,2,FALSE)))) / ( INDEX(MultiYear_ProForma!$F:$F, MATCH($A7&"|FY2026", MultiYear_ProForma!$O:$O,0)) + IFERROR(VLOOKUP($A7,$H$3:$I$8,2,FALSE),0)*$I$11 ),( (INDEX(MultiYear_ProForma!$L:$L, MATCH($A7&"|FY2027", MultiYear_ProForma!$O:$O,0)) + (IFERROR(VLOOKUP($A7,$H$3:$I$8,2,FALSE),0)*$I$11*(INDEX(MultiYear_ProForma!$I:$I, MATCH($A7&"|FY2027", MultiYear_ProForma!$O:$O,0)) + VLOOKUP("FY2027",$H$13:$J$17,2,FALSE)))) / ( INDEX(MultiYear_ProForma!$F:$F, MATCH($A7&"|FY2027", MultiYear_ProForma!$O:$O,0)) + IFERROR(VLOOKUP($A7,$H$3:$I$8,2,FALSE),0)*$I$11 ),( (INDEX(MultiYear_ProForma!$L:$L, MATCH($A7&"|FY2028", MultiYear_ProForma!$O:$O,0)) + (IFERROR(VLOOKUP($A7,$H$3:$I$8,2,FALSE),0)*$I$11*(INDEX(MultiYear_ProForma!$I:$I, MATCH($A7&"|FY2028", MultiYear_ProForma!$O:$O,0)) + VLOOKUP("FY2028",$H$13:$J$17,2,FALSE)))) / ( INDEX(MultiYear_ProForma!$F:$F, MATCH($A7&"|FY2028", MultiYear_ProForma!$O:$O,0)) + IFERROR(VLOOKUP($A7,$H$3:$I$8,2,FALSE),0)*$I$11 )) -> 0 | H7: B_Repurpose_Echo_Grow_Pima_ops | I7: 257
A8: =Scenarios!A8 -> 0 | B8: 0 | C8: =A8&"|"&"FY2028" -> 0 | D8: =IFERROR( (INDEX(MultiYear_ProForma!$L:$L, MATCH($C8, MultiYear_ProForma!$O:$O,0)) + (IFERROR(VLOOKUP($A8,$H$3:$I$8,2,FALSE),0)*$I$11*(INDEX(MultiYear_ProForma!$I:$I, MATCH($C8, MultiYear_ProForma!$O:$O,0)) + VLOOKUP("FY2028",$H$13:$J$17,2,FALSE))) ) / ( INDEX(MultiYear_ProForma!$F:$F, MATCH($C8, MultiYear_ProForma!$O:$O,0)) + IFERROR(VLOOKUP($A8,$H$3:$I$8,2,FALSE),0)*$I$11 ), "") -> 0 | E8: =IFERROR( (INDEX(MultiYear_ProForma!$L:$L, MATCH($A8&"|FY2030", MultiYear_ProForma!$O:$O,0)) + (IFERROR(VLOOKUP($A8,$H$3:$I$8,2,FALSE),0)*$I$11*(INDEX(MultiYear_ProForma!$I:$I, MATCH($A8&"|FY2030", MultiYear_ProForma!$O:$O,0)) + VLOOKUP("FY2030",$H$13:$J$17,2,FALSE))) ) / ( INDEX(MultiYear_ProForma!$F:$F, MATCH($A8&"|FY2030", MultiYear_ProForma!$O:$O,0)) + IFERROR(VLOOKUP($A8,$H$3:$I$8,2,FALSE),0)*$I$11 ), "") -> 0 | F8: =AVERAGE(( (INDEX(MultiYear_ProForma!$L:$L, MATCH($A8&"|FY2026", MultiYear_ProForma!$O:$O,0)) + (IFERROR(VLOOKUP($A8,$H$3:$I$8,2,FALSE),0)*$I$11*(INDEX(MultiYear_ProForma!$I:$I, MATCH($A8&"|FY2026", MultiYear_ProForma!$O:$O,0)) + VLOOKUP("FY2026",$H$13:$J$17,2,FALSE)))) / ( INDEX(MultiYear_ProForma!$F:$F, MATCH($A8&"|FY2026", MultiYear_ProForma!$O:$O,0)) + IFERROR(VLOOKUP($A8,$H$3:$I$8,2,FALSE),0)*$I$11 ),( (INDEX(MultiYear_ProForma!$L:$L, MATCH($A8&"|FY2027", MultiYear_ProForma!$O:$O,0)) + (IFERROR(VLOOKUP($A8,$H$3:$I$8,2,FALSE),0)*$I$11*(INDEX(MultiYear_ProForma!$I:$I, MATCH($A8&"|FY2027", MultiYear_ProForma!$O:$O,0)) + VLOOKUP("FY2027",$H$13:$J$17,2,FALSE)))) / ( INDEX(MultiYear_ProForma!$F:$F, MATCH($A8&"|FY2027", MultiYear_ProForma!$O:$O,0)) + IFERROR(VLOOKUP($A8,$H$3:$I$8,2,FALSE),0)*$I$11 ),( (INDEX(MultiYear_ProForma!$L:$L, MATCH($A8&"|FY2028", MultiYear_ProForma!$O:$O,0)) + (IFERROR(VLOOKUP($A8,$H$3:$I$8,2,FALSE),0)*$I$11*(INDEX(MultiYear_ProForma!$I:$I, MATCH($A8&"|FY2028", MultiYear_ProForma!$O:$O,0)) + VLOOKUP("FY2028",$H$13:$J$17,2,FALSE)))) / ( INDEX(MultiYear_ProForma!$F:$F, MATCH($A8&"|FY2028", MultiYear_ProForma!$O:$O,0)) + IFERROR(VLOOKUP($A8,$H$3:$I$8,2,FALSE),0)*$I$11 )) -> 0 | H8: C_Repurpose_Pima_Grow_Echo_lease | I8: 296
A9: =Scenarios!A9 -> 0 | B9: 100 | C9: =A9&"|"&"FY2028" -> 0 | D9: =IFERROR( (INDEX(MultiYear_ProForma!$L:$L, MATCH($C9, MultiYear_ProForma!$O:$O,0)) + (IFERROR(VLOOKUP($A9,$H$3:$I$8,2,FALSE),0)*$I$11*(INDEX(MultiYear_ProForma!$I:$I, MATCH($C9, MultiYear_ProForma!$O:$O,0)) + VLOOKUP("FY2028",$H$13:$J$17,2,FALSE))) ) / ( INDEX(MultiYear_ProForma!$F:$F, MATCH($C9, MultiYear_ProForma!$O:$O,0)) + IFERROR(VLOOKUP($A9,$H$3:$I$8,2,FALSE),0)*$I$11 ), "") -> 0 | E9: =IFERROR( (INDEX(MultiYear_ProForma!$L:$L, MATCH($A9&"|FY2030", MultiYear_ProForma!$O:$O,0)) + (IFERROR(VLOOKUP($A9,$H$3:$I$8,2,FALSE),0)*$I$11*(INDEX(MultiYear_ProForma!$I:$I, MATCH($A9&"|FY2030", MultiYear_ProForma!$O:$O,0)) + VLOOKUP("FY2030",$H$13:$J$17,2,FALSE))) ) / ( INDEX(MultiYear_ProForma!$F:$F, MATCH($A9&"|FY2030", MultiYear_ProForma!$O:$O,0)) + IFERROR(VLOOKUP($A9,$H$3:$I$8,2,FALSE),0)*$I$11 ), "") -> 0 | F9: =AVERAGE(( (INDEX(MultiYear_ProForma!$L:$L, MATCH($A9&"|FY2026", MultiYear_ProForma!$O:$O,0)) + (IFERROR(VLOOKUP($A9,$H$3:$I$8,2,FALSE),0)*$I$11*(INDEX(MultiYear_ProForma!$I:$I, MATCH($A9&"|FY2026", MultiYear_ProForma!$O:$O,0)) + VLOOKUP("FY2026",$H$13:$J$17,2,FALSE)))) / ( INDEX(MultiYear_ProForma!$F:$F, MATCH($A9&"|FY2026", MultiYear_ProForma!$O:$O,0)) + IFERROR(VLOOKUP($A9,$H$3:$I$8,2,FALSE),0)*$I$11 ),( (INDEX(MultiYear_ProForma!$L:$L, MATCH($A9&"|FY2027", MultiYear_ProForma!$O:$O,0)) + (IFERROR(VLOOKUP($A9,$H$3:$I$8,2,FALSE),0)*$I$11*(INDEX(MultiYear_ProForma!$I:$I, MATCH($A9&"|FY2027", MultiYear_ProForma!$O:$O,0)) + VLOOKUP("FY2027",$H$13:$J$17,2,FALSE)))) / ( INDEX(MultiYear_ProForma!$F:$F, MATCH($A9&"|FY2027", MultiYear_ProForma!$O:$O,0)) + IFERROR(VLOOKUP($A9,$H$3:$I$8,2,FALSE),0)*$I$11 ),( (INDEX(MultiYear_ProForma!$L:$L, MATCH($A9&"|FY2028", MultiYear_ProForma!$O:$O,0)) + (IFERROR(VLOOKUP($A9,$H$3:$I$8,2,FALSE),0)*$I$11*(INDEX(MultiYear_ProForma!$I:$I, MATCH($A9&"|FY2028", MultiYear_ProForma!$O:$O,0)) + VLOOKUP("FY2028",$H$13:$J$17,2,FALSE)))) / ( INDEX(MultiYear_ProForma!$F:$F, MATCH($A9&"|FY2028", MultiYear_ProForma!$O:$O,0)) + IFERROR(VLOOKUP($A9,$H$3:$I$8,2,FALSE),0)*$I$11 )) -> 0 | H9: C_Repurpose_Pima_Grow_Echo_ops | I9: 296
A10: =Scenarios!A10 -> 0 | B10: 150 | C10: =A10&"|"&"FY2028" -> 0 | D10: =IFERROR( (INDEX(MultiYear_ProForma!$L:$L, MATCH($C10, MultiYear_ProForma!$O:$O,0)) + (IFERROR(VLOOKUP($A10,$H$3:$I$8,2,FALSE),0)*$I$11*(INDEX(MultiYear_ProForma!$I:$I, MATCH($C10, MultiYear_ProForma!$O:$O,0)) + VLOOKUP("FY2028",$H$13:$J$17,2,FALSE))) ) / ( INDEX(MultiYear_ProForma!$F:$F, MATCH($C10, MultiYear_ProForma!$O:$O,0)) + IFERROR(VLOOKUP($A10,$H$3:$I$8,2,FALSE),0)*$I$11 ), "") -> 0 | E10: =IFERROR( (INDEX(MultiYear_ProForma!$L:$L, MATCH($A10&"|FY2030", MultiYear_ProForma!$O:$O,0)) + (IFERROR(VLOOKUP($A10,$H$3:$I$8,2,FALSE),0)*$I$11*(INDEX(MultiYear_ProForma!$I:$I, MATCH($A10&"|FY2030", MultiYear_ProForma!$O:$O,0)) + VLOOKUP("FY2030",$H$13:$J$17,2,FALSE))) ) / ( INDEX(MultiYear_ProForma!$F:$F, MATCH($A10&"|FY2030", MultiYear_ProForma!$O:$O,0)) + IFERROR(VLOOKUP($A10,$H$3:$I$8,2,FALSE),0)*$I$11 ), "") -> 0 | F10: =AVERAGE(( (INDEX(MultiYear_ProForma!$L:$L, MATCH($A10&"|FY2026", MultiYear_ProForma!$O:$O,0)) + (IFERROR(VLOOKUP($A10,$H$3:$I$8,2,FALSE),0)*$I$11*(INDEX(MultiYear_ProForma!$I:$I, MATCH($A10&"|FY2026", MultiYear_ProForma!$O:$O,0)) + VLOOKUP("FY2026",$H$13:$J$17,2,FALSE)))) / ( INDEX(MultiYear_ProForma!$F:$F, MATCH($A10&"|FY2026", MultiYear_ProForma!$O:$O,0)) + IFERROR(VLOOKUP($A10,$H$3:$I$8,2,FALSE),0)*$I$11 ),( (INDEX(MultiYear_ProForma!$L:$L, MATCH($A10&"|FY2027", MultiYear_ProForma!$O:$O,0)) + (IFERROR(VLOOKUP($A10,$H$3:$I$8,2,FALSE),0)*$I$11*(INDEX(MultiYear_ProForma!$I:$I, MATCH($A10&"|FY2027", MultiYear_ProForma!$O:$O,0)) + VLOOKUP("FY2027",$H$13:$J$17,2,FALSE)))) / ( INDEX(MultiYear_ProForma!$F:$F, MATCH($A10&"|FY2027", MultiYear_ProForma!$O:$O,0)) + IFERROR(VLOOKUP($A10,$H$3:$I$8,2,FALSE),0)*$I$11 ),( (INDEX(MultiYear_ProForma!$L:$L, MATCH($A10&"|FY2028", MultiYear_ProForma!$O:$O,0)) + (IFERROR(VLOOKUP($A10,$H$3:$I$8,2,FALSE),0)*$I$11*(INDEX(MultiYear_ProForma!$I:$I, MATCH($A10&"|FY2028", MultiYear_ProForma!$O:$O,0)) + VLOOKUP("FY2028",$H$13:$J$17,2,FALSE)))) / ( INDEX(MultiYear_ProForma!$F:$F, MATCH($A10&"|FY2028", MultiYear_ProForma!$O:$O,0)) + IFERROR(VLOOKUP($A10,$H$3:$I$8,2,FALSE),0)*$I$11 )) -> 0
A11: =Scenarios!A11 -> 0 | B11: 0 | C11: =A11&"|"&"FY2028" -> 0 | D11: =IFERROR( (INDEX(MultiYear_ProForma!$L:$L, MATCH($C11, MultiYear_ProForma!$O:$O,0)) + (IFERROR(VLOOKUP($A11,$H$3:$I$8,2,FALSE),0)*$I$11*(INDEX(MultiYear_ProForma!$I:$I, MATCH($C11, MultiYear_ProForma!$O:$O,0)) + VLOOKUP("FY2028",$H$13:$J$17,2,FALSE))) ) / ( INDEX(MultiYear_ProForma!$F:$F, MATCH($C11, MultiYear_ProForma!$O:$O,0)) + IFERROR(VLOOKUP($A11,$H$3:$I$8,2,FALSE),0)*$I$11 ), "") -> 0 | E11: =IFERROR( (INDEX(MultiYear_ProForma!$L:$L, MATCH($A11&"|FY2030", MultiYear_ProForma!$O:$O,0)) + (IFERROR(VLOOKUP($A11,$H$3:$I$8,2,FALSE),0)*$I$11*(INDEX(MultiYear_ProForma!$I:$I, MATCH($A11&"|FY2030", MultiYear_ProForma!$O:$O,0)) + VLOOKUP("FY2030",$H$13:$J$17,2,FALSE))) ) / ( INDEX(MultiYear_ProForma!$F:$F, MATCH($A11&"|FY2030", MultiYear_ProForma!$O:$O,0)) + IFERROR(VLOOKUP($A11,$H$3:$I$8,2,FALSE),0)*$I$11 ), "") -> 0 | F11: =AVERAGE(( (INDEX(MultiYear_ProForma!$L:$L, MATCH($A11&"|FY2026", MultiYear_ProForma!$O:$O,0)) + (IFERROR(VLOOKUP($A11,$H$3:$I$8,2,FALSE),0)*$I$11*(INDEX(MultiYear_ProForma!$I:$I, MATCH($A11&"|FY2026", MultiYear_ProForma!$O:$O,0)) + VLOOKUP("FY2026",$H$13:$J$17,2,FALSE)))) / ( INDEX(MultiYear_ProForma!$F:$F, MATCH($A11&"|FY2026", MultiYear_ProForma!$O:$O,0)) + IFERROR(VLOOKUP($A11,$H$3:$I$8,2,FALSE),0)*$I$11 ),( (INDEX(MultiYear_ProForma!$L:$L, MATCH($A11&"|FY2027", MultiYear_ProForma!$O:$O,0)) + (IFERROR(VLOOKUP($A11,$H$3:$I$8,2,FALSE),0)*$I$11*(INDEX(MultiYear_ProForma!$I:$I, MATCH($A11&"|FY2027", MultiYear_ProForma!$O:$O,0)) + VLOOKUP("FY2027",$H$13:$J$17,2,FALSE)))) / ( INDEX(MultiYear_ProForma!$F:$F, MATCH($A11&"|FY2027", MultiYear_ProForma!$O:$O,0)) + IFERROR(VLOOKUP($A11,$H$3:$I$8,2,FALSE),0)*$I$11 ),( (INDEX(MultiYear_ProForma!$L:$L, MATCH($A11&"|FY2028", MultiYear_ProForma!$O:$O,0)) + (IFERROR(VLOOKUP($A11,$H$3:$I$8,2,FALSE),0)*$I$11*(INDEX(MultiYear_ProForma!$I:$I, MATCH($A11&"|FY2028", MultiYear_ProForma!$O:$O,0)) + VLOOKUP("FY2028",$H$13:$J$17,2,FALSE)))) / ( INDEX(MultiYear_ProForma!$F:$F, MATCH($A11&"|FY2028", MultiYear_ProForma!$O:$O,0)) + IFERROR(VLOOKUP($A11,$H$3:$I$8,2,FALSE),0)*$I$11 )) -> 0 | H11: Retention r (central) | I11: 0.75
A12: =Scenarios!A12 -> 0 | B12: 100 | C12: =A12&"|"&"FY2028" -> 0 | D12: =IFERROR( (INDEX(MultiYear_ProForma!$L:$L, MATCH($C12, MultiYear_ProForma!$O:$O,0)) + (IFERROR(VLOOKUP($A12,$H$3:$I$8,2,FALSE),0)*$I$11*(INDEX(MultiYear_ProForma!$I:$I, MATCH($C12, MultiYear_ProForma!$O:$O,0)) + VLOOKUP("FY2028",$H$13:$J$17,2,FALSE))) ) / ( INDEX(MultiYear_ProForma!$F:$F, MATCH($C12, MultiYear_ProForma!$O:$O,0)) + IFERROR(VLOOKUP($A12,$H$3:$I$8,2,FALSE),0)*$I$11 ), "") -> 0 | E12: =IFERROR( (INDEX(MultiYear_ProForma!$L:$L, MATCH($A12&"|FY2030", MultiYear_ProForma!$O:$O,0)) + (IFERROR(VLOOKUP($A12,$H$3:$I$8,2,FALSE),0)*$I$11*(INDEX(MultiYear_ProForma!$I:$I, MATCH($A12&"|FY2030", MultiYear_ProForma!$O:$O,0)) + VLOOKUP("FY2030",$H$13:$J$17,2,FALSE))) ) / ( INDEX(MultiYear_ProForma!$F:$F, MATCH($A12&"|FY2030", MultiYear_ProForma!$O:$O,0)) + IFERROR(VLOOKUP($A12,$H$3:$I$8,2,FALSE),0)*$I$11 ), "") -> 0 | F12: =AVERAGE(( (INDEX(MultiYear_ProForma!$L:$L, MATCH($A12&"|FY2026", MultiYear_ProForma!$O:$O,0)) + (IFERROR(VLOOKUP($A12,$H$3:$I$8,2,FALSE),0)*$I$11*(INDEX(MultiYear_ProForma!$I:$I, MATCH($A12&"|FY2026", MultiYear_ProForma!$O:$O,0)) + VLOOKUP("FY2026",$H$13:$J$17,2,FALSE)))) / ( INDEX(MultiYear_ProForma!$F:$F, MATCH($A12&"|FY2026", MultiYear_ProForma!$O:$O,0)) + IFERROR(VLOOKUP($A12,$H$3:$I$8,2,FALSE),0)*$I$11 ),( (INDEX(MultiYear_ProForma!$L:$L, MATCH($A12&"|FY2027", MultiYear_ProForma!$O:$O,0)) + (IFERROR(VLOOKUP($A12,$H$3:$I$8,2,FALSE),0)*$I$11*(INDEX(MultiYear_ProForma!$I:$I, MATCH($A12&"|FY2027", MultiYear_ProForma!$O:$O,0)) + VLOOKUP("FY2027",$H$13:$J$17,2,FALSE)))) / ( INDEX(MultiYear_ProForma!$F:$F, MATCH($A12&"|FY2027", MultiYear_ProForma!$O:$O,0)) + IFERROR(VLOOKUP($A12,$H$3:$I$8,2,FALSE),0)*$I$11 ),( (INDEX(MultiYear_ProForma!$L:$L, MATCH($A12&"|FY2028", MultiYear_ProForma!$O:$O,0)) + (IFERROR(VLOOKUP($A12,$H$3:$I$8,2,FALSE),0)*$I$11*(INDEX(MultiYear_ProForma!$I:$I, MATCH($A12&"|FY2028", MultiYear_ProForma!$O:$O,0)) + VLOOKUP("FY2028",$H$13:$J$17,2,FALSE)))) / ( INDEX(MultiYear_ProForma!$F:$F, MATCH($A12&"|FY2028", MultiYear_ProForma!$O:$O,0)) + IFERROR(VLOOKUP($A12,$H$3:$I$8,2,FALSE),0)*$I$11 )) -> 0
A13: =Scenarios!A13 -> 0 | B13: 150 | C13: =A13&"|"&"FY2028" -> 0 | D13: =IFERROR( (INDEX(MultiYear_ProForma!$L:$L, MATCH($C13, MultiYear_ProForma!$O:$O,0)) + (IFERROR(VLOOKUP($A13,$H$3:$I$8,2,FALSE),0)*$I$11*(INDEX(MultiYear_ProForma!$I:$I, MATCH($C13, MultiYear_ProForma!$O:$O,0)) + VLOOKUP("FY2028",$H$13:$J$17,2,FALSE))) ) / ( INDEX(MultiYear_ProForma!$F:$F, MATCH($C13, MultiYear_ProForma!$O:$O,0)) + IFERROR(VLOOKUP($A13,$H$3:$I$8,2,FALSE),0)*$I$11 ), "") -> 0 | E13: =IFERROR( (INDEX(MultiYear_ProForma!$L:$L, MATCH($A13&"|FY2030", MultiYear_ProForma!$O:$O,0)) + (IFERROR(VLOOKUP($A13,$H$3:$I$8,2,FALSE),0)*$I$11*(INDEX(MultiYear_ProForma!$I:$I, MATCH($A13&"|FY2030", MultiYear_ProForma!$O:$O,0)) + VLOOKUP("FY2030",$H$13:$J$17,2,FALSE))) ) / ( INDEX(MultiYear_ProForma!$F:$F, MATCH($A13&"|FY2030", MultiYear_ProForma!$O:$O,0)) + IFERROR(VLOOKUP($A13,$H$3:$I$8,2,FALSE),0)*$I$11 ), "") -> 0 | F13: =AVERAGE(( (INDEX(MultiYear_ProForma!$L:$L, MATCH($A13&"|FY2026", MultiYear_ProForma!$O:$O,0)) + (IFERROR(VLOOKUP($A13,$H$3:$I$8,2,FALSE),0)*$I$11*(INDEX(MultiYear_ProForma!$I:$I, MATCH($A13&"|FY2026", MultiYear_ProForma!$O:$O,0)) + VLOOKUP("FY2026",$H$13:$J$17,2,FALSE)))) / ( INDEX(MultiYear_ProForma!$F:$F, MATCH($A13&"|FY2026", MultiYear_ProForma!$O:$O,0)) + IFERROR(VLOOKUP($A13,$H$3:$I$8,2,FALSE),0)*$I$11 ),( (INDEX(MultiYear_ProForma!$L:$L, MATCH($A13&"|FY2027", MultiYear_ProForma!$O:$O,0)) + (IFERROR(VLOOKUP($A13,$H$3:$I$8,2,FALSE),0)*$I$11*(INDEX(MultiYear_ProForma!$I:$I, MATCH($A13&"|FY2027", MultiYear_ProForma!$O:$O,0)) + VLOOKUP("FY2027",$H$13:$J$17,2,FALSE)))) / ( INDEX(MultiYear_ProForma!$F:$F, MATCH($A13&"|FY2027", MultiYear_ProForma!$O:$O,0)) + IFERROR(VLOOKUP($A13,$H$3:$I$8,2,FALSE),0)*$I$11 ),( (INDEX(MultiYear_ProForma!$L:$L, MATCH($A13&"|FY2028", MultiYear_ProForma!$O:$O,0)) + (IFERROR(VLOOKUP($A13,$H$3:$I$8,2,FALSE),0)*$I$11*(INDEX(MultiYear_ProForma!$I:$I, MATCH($A13&"|FY2028", MultiYear_ProForma!$O:$O,0)) + VLOOKUP("FY2028",$H$13:$J$17,2,FALSE)))) / ( INDEX(MultiYear_ProForma!$F:$F, MATCH($A13&"|FY2028", MultiYear_ProForma!$O:$O,0)) + IFERROR(VLOOKUP($A13,$H$3:$I$8,2,FALSE),0)*$I$11 )) -> 0 | H13: Year | I13: h | J13: var
A14: =Scenarios!A14 -> 0 | B14: 0 | C14: =A14&"|"&"FY2028" -> 0 | D14: =IFERROR( (INDEX(MultiYear_ProForma!$L:$L, MATCH($C14, MultiYear_ProForma!$O:$O,0)) + (IFERROR(VLOOKUP($A14,$H$3:$I$8,2,FALSE),0)*$I$11*(INDEX(MultiYear_ProForma!$I:$I, MATCH($C14, MultiYear_ProForma!$O:$O,0)) + VLOOKUP("FY2028",$H$13:$J$17,2,FALSE))) ) / ( INDEX(MultiYear_ProForma!$F:$F, MATCH($C14, MultiYear_ProForma!$O:$O,0)) + IFERROR(VLOOKUP($A14,$H$3:$I$8,2,FALSE),0)*$I$11 ), "") -> 0 | E14: =IFERROR( (INDEX(MultiYear_ProForma!$L:$L, MATCH($A14&"|FY2030", MultiYear_ProForma!$O:$O,0)) + (IFERROR(VLOOKUP($A14,$H$3:$I$8,2,FALSE),0)*$I$11*(INDEX(MultiYear_ProForma!$I:$I, MATCH($A14&"|FY2030", MultiYear_ProForma!$O:$O,0)) + VLOOKUP("FY2030",$H$13:$J$17,2,FALSE))) ) / ( INDEX(MultiYear_ProForma!$F:$F, MATCH($A14&"|FY2030", MultiYear_ProForma!$O:$O,0)) + IFERROR(VLOOKUP($A14,$H$3:$I$8,2,FALSE),0)*$I$11 ), "") -> 0 | F14: =AVERAGE(( (INDEX(MultiYear_ProForma!$L:$L, MATCH($A14&"|FY2026", MultiYear_ProForma!$O:$O,0)) + (IFERROR(VLOOKUP($A14,$H$3:$I$8,2,FALSE),0)*$I$11*(INDEX(MultiYear_ProForma!$I:$I, MATCH($A14&"|FY2026", MultiYear_ProForma!$O:$O,0)) + VLOOKUP("FY2026",$H$13:$J$17,2,FALSE)))) / ( INDEX(MultiYear_ProForma!$F:$F, MATCH($A14&"|FY2026", MultiYear_ProForma!$O:$O,0)) + IFERROR(VLOOKUP($A14,$H$3:$I$8,2,FALSE),0)*$I$11 ),( (INDEX(MultiYear_ProForma!$L:$L, MATCH($A14&"|FY2027", MultiYear_ProForma!$O:$O,0)) + (IFERROR(VLOOKUP($A14,$H$3:$I$8,2,FALSE),0)*$I$11*(INDEX(MultiYear_ProForma!$I:$I, MATCH($A14&"|FY2027", MultiYear_ProForma!$O:$O,0)) + VLOOKUP("FY2027",$H$13:$J$17,2,FALSE)))) / ( INDEX(MultiYear_ProForma!$F:$F, MATCH($A14&"|FY2027", MultiYear_ProForma!$O:$O,0)) + IFERROR(VLOOKUP($A14,$H$3:$I$8,2,FALSE),0)*$I$11 ),( (INDEX(MultiYear_ProForma!$L:$L, MATCH($A14&"|FY2028", MultiYear_ProForma!$O:$O,0)) + (IFERROR(VLOOKUP($A14,$H$3:$I$8,2,FALSE),0)*$I$11*(INDEX(MultiYear_ProForma!$I:$I, MATCH($A14&"|FY2028", MultiYear_ProForma!$O:$O,0)) + VLOOKUP("FY2028",$H$13:$J$17,2,FALSE)))) / ( INDEX(MultiYear_ProForma!$F:$F, MATCH($A14&"|FY2028", MultiYear_ProForma!$O:$O,0)) + IFERROR(VLOOKUP($A14,$H$3:$I$8,2,FALSE),0)*$I$11 )) -> 0 | H14: FY2026 | I14: 1000 | J14: 7129.08
A15: =Scenarios!A15 -> 0 | B15: 100 | C15: =A15&"|"&"FY2028" -> 0 | D15: =IFERROR( (INDEX(MultiYear_ProForma!$L:$L, MATCH($C15, MultiYear_ProForma!$O:$O,0)) + (IFERROR(VLOOKUP($A15,$H$3:$I$8,2,FALSE),0)*$I$11*(INDEX(MultiYear_ProForma!$I:$I, MATCH($C15, MultiYear_ProForma!$O:$O,0)) + VLOOKUP("FY2028",$H$13:$J$17,2,FALSE))) ) / ( INDEX(MultiYear_ProForma!$F:$F, MATCH($C15, MultiYear_ProForma!$O:$O,0)) + IFERROR(VLOOKUP($A15,$H$3:$I$8,2,FALSE),0)*$I$11 ), "") -> 0 | E15: =IFERROR( (INDEX(MultiYear_ProForma!$L:$L, MATCH($A15&"|FY2030", MultiYear_ProForma!$O:$O,0)) + (IFERROR(VLOOKUP($A15,$H$3:$I$8,2,FALSE),0)*$I$11*(INDEX(MultiYear_ProForma!$I:$I, MATCH($A15&"|FY2030", MultiYear_ProForma!$O:$O,0)) + VLOOKUP("FY2030",$H$13:$J$17,2,FALSE))) ) / ( INDEX(MultiYear_ProForma!$F:$F, MATCH($A15&"|FY2030", MultiYear_ProForma!$O:$O,0)) + IFERROR(VLOOKUP($A15,$H$3:$I$8,2,FALSE),0)*$I$11 ), "") -> 0 | F15: =AVERAGE(( (INDEX(MultiYear_ProForma!$L:$L, MATCH($A15&"|FY2026", MultiYear_ProForma!$O:$O,0)) + (IFERROR(VLOOKUP($A15,$H$3:$I$8,2,FALSE),0)*$I$11*(INDEX(MultiYear_ProForma!$I:$I, MATCH($A15&"|FY2026", MultiYear_ProForma!$O:$O,0)) + VLOOKUP("FY2026",$H$13:$J$17,2,FALSE)))) / ( INDEX(MultiYear_ProForma!$F:$F, MATCH($A15&"|FY2026", MultiYear_ProForma!$O:$O,0)) + IFERROR(VLOOKUP($A15,$H$3:$I$8,2,FALSE),0)*$I$11 ),( (INDEX(MultiYear_ProForma!$L:$L, MATCH($A15&"|FY2027", MultiYear_ProForma!$O:$O,0)) + (IFERROR(VLOOKUP($A15,$H$3:$I$8,2,FALSE),0)*$I$11*(INDEX(MultiYear_ProForma!$I:$I, MATCH($A15&"|FY2027", MultiYear_ProForma!$O:$O,0)) + VLOOKUP("FY2027",$H$13:$J$17,2,FALSE)))) / ( INDEX(MultiYear_ProForma!$F:$F, MATCH($A15&"|FY2027", MultiYear_ProForma!$O:$O,0)) + IFERROR(VLOOKUP($A15,$H$3:$I$8,2,FALSE),0)*$I$11 ),( (INDEX(MultiYear_ProForma!$L:$L, MATCH($A15&"|FY2028", MultiYear_ProForma!$O:$O,0)) + (IFERROR(VLOOKUP($A15,$H$3:$I$8,2,FALSE),0)*$I$11*(INDEX(MultiYear_ProForma!$I:$I, MATCH($A15&"|FY2028", MultiYear_ProForma!$O:$O,0)) + VLOOKUP("FY2028",$H$13:$J$17,2,FALSE)))) / ( INDEX(MultiYear_ProForma!$F:$F, MATCH($A15&"|FY2028", MultiYear_ProForma!$O:$O,0)) + IFERROR(VLOOKUP($A15,$H$3:$I$8,2,FALSE),0)*$I$11 )) -> 0 | H15: FY2027 | I15: 800 | J15: 7307.307
A16: =Scenarios!A16 -> 0 | B16: 150 | C16: =A16&"|"&"FY2028" -> 0 | D16: =IFERROR( (INDEX(MultiYear_ProForma!$L:$L, MATCH($C16, MultiYear_ProForma!$O:$O,0)) + (IFERROR(VLOOKUP($A16,$H$3:$I$8,2,FALSE),0)*$I$11*(INDEX(MultiYear_ProForma!$I:$I, MATCH($C16, MultiYear_ProForma!$O:$O,0)) + VLOOKUP("FY2028",$H$13:$J$17,2,FALSE))) ) / ( INDEX(MultiYear_ProForma!$F:$F, MATCH($C16, MultiYear_ProForma!$O:$O,0)) + IFERROR(VLOOKUP($A16,$H$3:$I$8,2,FALSE),0)*$I$11 ), "") -> 0 | E16: =IFERROR( (INDEX(MultiYear_ProForma!$L:$L, MATCH($A16&"|FY2030", MultiYear_ProForma!$O:$O,0)) + (IFERROR(VLOOKUP($A16,$H$3:$I$8,2,FALSE),0)*$I$11*(INDEX(MultiYear_ProForma!$I:$I, MATCH($A16&"|FY2030", MultiYear_ProForma!$O:$O,0)) + VLOOKUP("FY2030",$H$13:$J$17,2,FALSE))) ) / ( INDEX(MultiYear_ProForma!$F:$F, MATCH($A16&"|FY2030", MultiYear_ProForma!$O:$O,0)) + IFERROR(VLOOKUP($A16,$H$3:$I$8,2,FALSE),0)*$I$11 ), "") -> 0 | F16: =AVERAGE(( (INDEX(MultiYear_ProForma!$L:$L, MATCH($A16&"|FY2026", MultiYear_ProForma!$O:$O,0)) + (IFERROR(VLOOKUP($A16,$H$3:$I$8,2,FALSE),0)*$I$11*(INDEX(MultiYear_ProForma!$I:$I, MATCH($A16&"|FY2026", MultiYear_ProForma!$O:$O,0)) + VLOOKUP("FY2026",$H$13:$J$17,2,FALSE)))) / ( INDEX(MultiYear_ProForma!$F:$F, MATCH($A16&"|FY2026", MultiYear_ProForma!$O:$O,0)) + IFERROR(VLOOKUP($A16,$H$3:$I$8,2,FALSE),0)*$I$11 ),( (INDEX(MultiYear_ProForma!$L:$L, MATCH($A16&"|FY2027", MultiYear_ProForma!$O:$O,0)) + (IFERROR(VLOOKUP($A16,$H$3:$I$8,2,FALSE),0)*$I$11*(INDEX(MultiYear_ProForma!$I:$I, MATCH($A16&"|FY2027", MultiYear_ProForma!$O:$O,0)) + VLOOKUP("FY2027",$H$13:$J$17,2,FALSE)))) / ( INDEX(MultiYear_ProForma!$F:$F, MATCH($A16&"|FY2027", MultiYear_ProForma!$O:$O,0)) + IFERROR(VLOOKUP($A16,$H$3:$I$8,2,FALSE),0)*$I$11 ),( (INDEX(MultiYear_ProForma!$L:$L, MATCH($A16&"|FY2028", MultiYear_ProForma!$O:$O,0)) + (IFERROR(VLOOKUP($A16,$H$3:$I$8,2,FALSE),0)*$I$11*(INDEX(MultiYear_ProForma!$I:$I, MATCH($A16&"|FY2028", MultiYear_ProForma!$O:$O,0)) + VLOOKUP("FY2028",$H$13:$J$17,2,FALSE)))) / ( INDEX(MultiYear_ProForma!$F:$F, MATCH($A16&"|FY2028", MultiYear_ProForma!$O:$O,0)) + IFERROR(VLOOKUP($A16,$H$3:$I$8,2,FALSE),0)*$I$11 )) -> 0 | H16: FY2028 | I16: 600 | J16: 7489.9897
A17: =Scenarios!A17 -> 0 | B17: 150 | C17: =A17&"|"&"FY2028" -> 0 | D17: =IFERROR( (INDEX(MultiYear_ProForma!$L:$L, MATCH($C17, MultiYear_ProForma!$O:$O,0)) + (IFERROR(VLOOKUP($A17,$H$3:$I$8,2,FALSE),0)*$I$11*(INDEX(MultiYear_ProForma!$I:$I, MATCH($C17, MultiYear_ProForma!$O:$O,0)) + VLOOKUP("FY2028",$H$13:$J$17,2,FALSE))) ) / ( INDEX(MultiYear_ProForma!$F:$F, MATCH($C17, MultiYear_ProForma!$O:$O,0)) + IFERROR(VLOOKUP($A17,$H$3:$I$8,2,FALSE),0)*$I$11 ), "") -> 0 | E17: =IFERROR( (INDEX(MultiYear_ProForma!$L:$L, MATCH($A17&"|FY2030", MultiYear_ProForma!$O:$O,0)) + (IFERROR(VLOOKUP($A17,$H$3:$I$8,2,FALSE),0)*$I$11*(INDEX(MultiYear_ProForma!$I:$I, MATCH($A17&"|FY2030", MultiYear_ProForma!$O:$O,0)) + VLOOKUP("FY2030",$H$13:$J$17,2,FALSE))) ) / ( INDEX(MultiYear_ProForma!$F:$F, MATCH($A17&"|FY2030", MultiYear_ProForma!$O:$O,0)) + IFERROR(VLOOKUP($A17,$H$3:$I$8,2,FALSE),0)*$I$11 ), "") -> 0 | F17: =AVERAGE(( (INDEX(MultiYear_ProForma!$L:$L, MATCH($A17&"|FY2026", MultiYear_ProForma!$O:$O,0)) + (IFERROR(VLOOKUP($A17,$H$3:$I$8,2,FALSE),0)*$I$11*(INDEX(MultiYear_ProForma!$I:$I, MATCH($A17&"|FY2026", MultiYear_ProForma!$O:$O,0)) + VLOOKUP("FY2026",$H$13:$J$17,2,FALSE)))) / ( INDEX(MultiYear_ProForma!$F:$F, MATCH($A17&"|FY2026", MultiYear_ProForma!$O:$O,0)) + IFERROR(VLOOKUP($A17,$H$3:$I$8,2,FALSE),0)*$I$11 ),( (INDEX(MultiYear_ProForma!$L:$L, MATCH($A17&"|FY2027", MultiYear_ProForma!$O:$O,0)) + (IFERROR(VLOOKUP($A17,$H$3:$I$8,2,FALSE),0)*$I$11*(INDEX(MultiYear_ProForma!$I:$I, MATCH($A17&"|FY2027", MultiYear_ProForma!$O:$O,0)) + VLOOKUP("FY2027",$H$13:$J$17,2,FALSE)))) / ( INDEX(MultiYear_ProForma!$F:$F, MATCH($A17&"|FY2027", MultiYear_ProForma!$O:$O,0)) + IFERROR(VLOOKUP($A17,$H$3:$I$8,2,FALSE),0)*$I$11 ),( (INDEX(MultiYear_ProForma!$L:$L, MATCH($A17&"|FY2028", MultiYear_ProForma!$O:$O,0)) + (IFERROR(VLOOKUP($A17,$H$3:$I$8,2,FALSE),0)*$I$11*(INDEX(MultiYear_ProForma!$I:$I, MATCH($A17&"|FY2028", MultiYear_ProForma!$O:$O,0)) + VLOOKUP("FY2028",$H$13:$J$17,2,FALSE)))) / ( INDEX(MultiYear_ProForma!$F:$F, MATCH($A17&"|FY2028", MultiYear_ProForma!$O:$O,0)) + IFERROR(VLOOKUP($A17,$H$3:$I$8,2,FALSE),0)*$I$11 )) -> 0 | H17: FY2029 | I17: 400 | J17: 7677.2394
H18: FY2030 | I18: 300 | J18: 7869.1704

Sheet BreakEven_Calc
A1: Helper | B1: FY28 | C1: FY30
A2: Fixed_total ($) | B2: 1775127.6 | C2: 1864993.4
A3: Var_unit ($/student) | B3: 7489.9897 | C3: 7869.1704
A4: Total base ADM | B4: 553 | C4: 553
A6: Select target ScenarioKey (from Scenarios) | B6: D_Grow_Both_150
A7: Select overlay (0/100/150) | B7: 150
A8: Select year (2028 or 2030) | B8: 2030
A9: Receiving overhead h ($) | B9: 300
A10: Fixed-carry f (fraction) | B10: 0.2
A12: C_target (Comparable $/student)
B13: =IF($B$8="2028", INDEX(Summary_Costs!$D:$D, MATCH($B$6&"|"&$B$7, Summary_Costs!$C:$C,0)), INDEX(Summary_Costs!$E:$E, MATCH($B$6&"|"&$B$7, Summary_Costs!$C:$C,0))) -> 0
A15: Break‑even retention r*
B16: =IF($B$8="2028", ($B$10*$B$2)/( $B$4 * ($B$12 - ($B$3 + $B$8)) ), ($B$10*$C$2)/( $B$4 * ($B$12 - ($C$3 + $B$8)) )) -> 0
A18: How to use | B18: 1) Select target/overlay/year; 2) Set h and f; 3) Read r*. If r*≤0, A is already cheaper at those assumptions; if 0<r*<1, A can beat comparator if actual retention ≥ r*; if r*≥1, A cannot break even under those assumptions.
A20: Grid: r* vs f (rows) by h (cols)
A21: f \ h | B21: 200 | C21: 300 | D21: 400 | E21: 600 | F21: 800 | G21: 1000 | H21: 1200 | I21: 1500
A22: 0 | B22: =IF($B$8="2028", (0.0*$B$2)/($B$4*($B$12-($B$3+200))), (0.0*$C$2)/($B$4*($B$12-($C$3+200)))) -> 0 | C22: =IF($B$8="2028", (0.0*$B$2)/($B$4*($B$12-($B$3+300))), (0.0*$C$2)/($B$4*($B$12-($C$3+300)))) -> 0 | D22: =IF($B$8="2028", (0.0*$B$2)/($B$4*($B$12-($B$3+400))), (0.0*$C$2)/($B$4*($B$12-($C$3+400)))) -> 0 | E22: =IF($B$8="2028", (0.0*$B$2)/($B$4*($B$12-($B$3+600))), (0.0*$C$2)/($B$4*($B$12-($C$3+600)))) -> 0 | F22: =IF($B$8="2028", (0.0*$B$2)/($B$4*($B$12-($B$3+800))), (0.0*$C$2)/($B$4*($B$12-($C$3+800)))) -> 0 | G22: =IF($B$8="2028", (0.0*$B$2)/($B$4*($B$12-($B$3+1000))), (0.0*$C$2)/($B$4*($B$12-($C$3+1000)))) -> 0 | H22: =IF($B$8="2028", (0.0*$B$2)/($B$4*($B$12-($B$3+1200))), (0.0*$C$2)/($B$4*($B$12-($C$3+1200)))) -> 0 | I22: =IF($B$8="2028", (0.0*$B$2)/($B$4*($B$12-($B$3+1500))), (0.0*$C$2)/($B$4*($B$12-($C$3+1500)))) -> 0
A23: 0.05 | B23: =IF($B$8="2028", (0.05*$B$2)/($B$4*($B$12-($B$3+200))), (0.05*$C$2)/($B$4*($B$12-($C$3+200)))) -> 0 | C23: =IF($B$8="2028", (0.05*$B$2)/($B$4*($B$12-($B$3+300))), (0.05*$C$2)/($B$4*($B$12-($C$3+300)))) -> 0 | D23: =IF($B$8="2028", (0.05*$B$2)/($B$4*($B$12-($B$3+400))), (0.05*$C$2)/($B$4*($B$12-($C$3+400)))) -> 0 | E23: =IF($B$8="2028", (0.05*$B$2)/($B$4*($B$12-($B$3+600))), (0.05*$C$2)/($B$4*($B$12-($C$3+600)))) -> 0 | F23: =IF($B$8="2028", (0.05*$B$2)/($B$4*($B$12-($B$3+800))), (0.05*$C$2)/($B$4*($B$12-($C$3+800)))) -> 0 | G23: =IF($B$8="2028", (0.05*$B$2)/($B$4*($B$12-($B$3+1000))), (0.05*$C$2)/($B$4*($B$12-($C$3+1000)))) -> 0 | H23: =IF($B$8="2028", (0.05*$B$2)/($B$4*($B$12-($B$3+1200))), (0.05*$C$2)/($B$4*($B$12-($C$3+1200)))) -> 0 | I23: =IF($B$8="2028", (0.05*$B$2)/($B$4*($B$12-($B$3+1500))), (0.05*$C$2)/($B$4*($B$12-($C$3+1500)))) -> 0
A24: 0.1 | B24: =IF($B$8="2028", (0.1*$B$2)/($B$4*($B$12-($B$3+200))), (0.1*$C$2)/($B$4*($B$12-($C$3+200)))) -> 0 | C24: =IF($B$8="2028", (0.1*$B$2)/($B$4*($B$12-($B$3+300))), (0.1*$C$2)/($B$4*($B$12-($C$3+300)))) -> 0 | D24: =IF($B$8="2028", (0.1*$B$2)/($B$4*($B$12-($B$3+400))), (0.1*$C$2)/($B$4*($B$12-($C$3+400)))) -> 0 | E24: =IF($B$8="2028", (0.1*$B$2)/($B$4*($B$12-($B$3+600))), (0.1*$C$2)/($B$4*($B$12-($C$3+600)))) -> 0 | F24: =IF($B$8="2028", (0.1*$B$2)/($B$4*($B$12-($B$3+800))), (0.1*$C$2)/($B$4*($B$12-($C$3+800)))) -> 0 | G24: =IF($B$8="2028", (0.1*$B$2)/($B$4*($B$12-($B$3+1000))), (0.1*$C$2)/($B$4*($B$12-($C$3+1000)))) -> 0 | H24: =IF($B$8="2028", (0.1*$B$2)/($B$4*($B$12-($B$3+1200))), (0.1*$C$2)/($B$4*($B$12-($C$3+1200)))) -> 0 | I24: =IF($B$8="2028", (0.1*$B$2)/($B$4*($B$12-($B$3+1500))), (0.1*$C$2)/($B$4*($B$12-($C$3+1500)))) -> 0
A25: 0.15 | B25: =IF($B$8="2028", (0.15*$B$2)/($B$4*($B$12-($B$3+200))), (0.15*$C$2)/($B$4*($B$12-($C$3+200)))) -> 0 | C25: =IF($B$8="2028", (0.15*$B$2)/($B$4*($B$12-($B$3+300))), (0.15*$C$2)/($B$4*($B$12-($C$3+300)))) -> 0 | D25: =IF($B$8="2028", (0.15*$B$2)/($B$4*($B$12-($B$3+400))), (0.15*$C$2)/($B$4*($B$12-($C$3+400)))) -> 0 | E25: =IF($B$8="2028", (0.15*$B$2)/($B$4*($B$12-($B$3+600))), (0.15*$C$2)/($B$4*($B$12-($C$3+600)))) -> 0 | F25: =IF($B$8="2028", (0.15*$B$2)/($B$4*($B$12-($B$3+800))), (0.15*$C$2)/($B$4*($B$12-($C$3+800)))) -> 0 | G25: =IF($B$8="2028", (0.15*$B$2)/($B$4*($B$12-($B$3+1000))), (0.15*$C$2)/($B$4*($B$12-($C$3+1000)))) -> 0 | H25: =IF($B$8="2028", (0.15*$B$2)/($B$4*($B$12-($B$3+1200))), (0.15*$C$2)/($B$4*($B$12-($C$3+1200)))) -> 0 | I25: =IF($B$8="2028", (0.15*$B$2)/($B$4*($B$12-($B$3+1500))), (0.15*$C$2)/($B$4*($B$12-($C$3+1500)))) -> 0
A26: 0.2 | B26: =IF($B$8="2028", (0.2*$B$2)/($B$4*($B$12-($B$3+200))), (0.2*$C$2)/($B$4*($B$12-($C$3+200)))) -> 0 | C26: =IF($B$8="2028", (0.2*$B$2)/($B$4*($B$12-($B$3+300))), (0.2*$C$2)/($B$4*($B$12-($C$3+300)))) -> 0 | D26: =IF($B$8="2028", (0.2*$B$2)/($B$4*($B$12-($B$3+400))), (0.2*$C$2)/($B$4*($B$12-($C$3+400)))) -> 0 | E26: =IF($B$8="2028", (0.2*$B$2)/($B$4*($B$12-($B$3+600))), (0.2*$C$2)/($B$4*($B$12-($C$3+600)))) -> 0 | F26: =IF($B$8="2028", (0.2*$B$2)/($B$4*($B$12-($B$3+800))), (0.2*$C$2)/($B$4*($B$12-($C$3+800)))) -> 0 | G26: =IF($B$8="2028", (0.2*$B$2)/($B$4*($B$12-($B$3+1000))), (0.2*$C$2)/($B$4*($B$12-($C$3+1000)))) -> 0 | H26: =IF($B$8="2028", (0.2*$B$2)/($B$4*($B$12-($B$3+1200))), (0.2*$C$2)/($B$4*($B$12-($C$3+1200)))) -> 0 | I26: =IF($B$8="2028", (0.2*$B$2)/($B$4*($B$12-($B$3+1500))), (0.2*$C$2)/($B$4*($B$12-($C$3+1500)))) -> 0
A27: 0.25 | B27: =IF($B$8="2028", (0.25*$B$2)/($B$4*($B$12-($B$3+200))), (0.25*$C$2)/($B$4*($B$12-($C$3+200)))) -> 0 | C27: =IF($B$8="2028", (0.25*$B$2)/($B$4*($B$12-($B$3+300))), (0.25*$C$2)/($B$4*($B$12-($C$3+300)))) -> 0 | D27: =IF($B$8="2028", (0.25*$B$2)/($B$4*($B$12-($B$3+400))), (0.25*$C$2)/($B$4*($B$12-($C$3+400)))) -> 0 | E27: =IF($B$8="2028", (0.25*$B$2)/($B$4*($B$12-($B$3+600))), (0.25*$C$2)/($B$4*($B$12-($C$3+600)))) -> 0 | F27: =IF($B$8="2028", (0.25*$B$2)/($B$4*($B$12-($B$3+800))), (0.25*$C$2)/($B$4*($B$12-($C$3+800)))) -> 0 | G27: =IF($B$8="2028", (0.25*$B$2)/($B$4*($B$12-($B$3+1000))), (0.25*$C$2)/($B$4*($B$12-($C$3+1000)))) -> 0 | H27: =IF($B$8="2028", (0.25*$B$2)/($B$4*($B$12-($B$3+1200))), (0.25*$C$2)/($B$4*($B$12-($C$3+1200)))) -> 0 | I27: =IF($B$8="2028", (0.25*$B$2)/($B$4*($B$12-($B$3+1500))), (0.25*$C$2)/($B$4*($B$12-($C$3+1500)))) -> 0
A28: 0.3 | B28: =IF($B$8="2028", (0.3*$B$2)/($B$4*($B$12-($B$3+200))), (0.3*$C$2)/($B$4*($B$12-($C$3+200)))) -> 0 | C28: =IF($B$8="2028", (0.3*$B$2)/($B$4*($B$12-($B$3+300))), (0.3*$C$2)/($B$4*($B$12-($C$3+300)))) -> 0 | D28: =IF($B$8="2028", (0.3*$B$2)/($B$4*($B$12-($B$3+400))), (0.3*$C$2)/($B$4*($B$12-($C$3+400)))) -> 0 | E28: =IF($B$8="2028", (0.3*$B$2)/($B$4*($B$12-($B$3+600))), (0.3*$C$2)/($B$4*($B$12-($C$3+600)))) -> 0 | F28: =IF($B$8="2028", (0.3*$B$2)/($B$4*($B$12-($B$3+800))), (0.3*$C$2)/($B$4*($B$12-($C$3+800)))) -> 0 | G28: =IF($B$8="2028", (0.3*$B$2)/($B$4*($B$12-($B$3+1000))), (0.3*$C$2)/($B$4*($B$12-($C$3+1000)))) -> 0 | H28: =IF($B$8="2028", (0.3*$B$2)/($B$4*($B$12-($B$3+1200))), (0.3*$C$2)/($B$4*($B$12-($C$3+1200)))) -> 0 | I28: =IF($B$8="2028", (0.3*$B$2)/($B$4*($B$12-($B$3+1500))), (0.3*$C$2)/($B$4*($B$12-($C$3+1500)))) -> 0
A29: 0.35 | B29: =IF($B$8="2028", (0.35*$B$2)/($B$4*($B$12-($B$3+200))), (0.35*$C$2)/($B$4*($B$12-($C$3+200)))) -> 0 | C29: =IF($B$8="2028", (0.35*$B$2)/($B$4*($B$12-($B$3+300))), (0.35*$C$2)/($B$4*($B$12-($C$3+300)))) -> 0 | D29: =IF($B$8="2028", (0.35*$B$2)/($B$4*($B$12-($B$3+400))), (0.35*$C$2)/($B$4*($B$12-($C$3+400)))) -> 0 | E29: =IF($B$8="2028", (0.35*$B$2)/($B$4*($B$12-($B$3+600))), (0.35*$C$2)/($B$4*($B$12-($C$3+600)))) -> 0 | F29: =IF($B$8="2028", (0.35*$B$2)/($B$4*($B$12-($B$3+800))), (0.35*$C$2)/($B$4*($B$12-($C$3+800)))) -> 0 | G29: =IF($B$8="2028", (0.35*$B$2)/($B$4*($B$12-($B$3+1000))), (0.35*$C$2)/($B$4*($B$12-($C$3+1000)))) -> 0 | H29: =IF($B$8="2028", (0.35*$B$2)/($B$4*($B$12-($B$3+1200))), (0.35*$C$2)/($B$4*($B$12-($C$3+1200)))) -> 0 | I29: =IF($B$8="2028", (0.35*$B$2)/($B$4*($B$12-($B$3+1500))), (0.35*$C$2)/($B$4*($B$12-($C$3+1500)))) -> 0
A30: 0.4 | B30: =IF($B$8="2028", (0.4*$B$2)/($B$4*($B$12-($B$3+200))), (0.4*$C$2)/($B$4*($B$12-($C$3+200)))) -> 0 | C30: =IF($B$8="2028", (0.4*$B$2)/($B$4*($B$12-($B$3+300))), (0.4*$C$2)/($B$4*($B$12-($C$3+300)))) -> 0 | D30: =IF($B$8="2028", (0.4*$B$2)/($B$4*($B$12-($B$3+400))), (0.4*$C$2)/($B$4*($B$12-($C$3+400)))) -> 0 | E30: =IF($B$8="2028", (0.4*$B$2)/($B$4*($B$12-($B$3+600))), (0.4*$C$2)/($B$4*($B$12-($C$3+600)))) -> 0 | F30: =IF($B$8="2028", (0.4*$B$2)/($B$4*($B$12-($B$3+800))), (0.4*$C$2)/($B$4*($B$12-($C$3+800)))) -> 0 | G30: =IF($B$8="2028", (0.4*$B$2)/($B$4*($B$12-($B$3+1000))), (0.4*$C$2)/($B$4*($B$12-($C$3+1000)))) -> 0 | H30: =IF($B$8="2028", (0.4*$B$2)/($B$4*($B$12-($B$3+1200))), (0.4*$C$2)/($B$4*($B$12-($C$3+1200)))) -> 0 | I30: =IF($B$8="2028", (0.4*$B$2)/($B$4*($B$12-($B$3+1500))), (0.4*$C$2)/($B$4*($B$12-($C$3+1500)))) -> 0

Sheet Sources
A1: Topic | B1: Source (paste link) | C1: Use
A2: SUSD ACFR (fund structure) | B2: ACFR PDF | C2: Confirm M&O vs Debt Service; plant carry persists without lease/sale.
A3: AZ Auditor General—transport | B3: Auditor General K‑12 transportation reports | C3: Set the h bands ($500–$1,500) with midline ~$1,000.
A4: Chicago 2013 closures—retention/outcomes | B4: UChicago Consortium (2015) | C4: Retention/context for r bands; caution on overshoot.
A5: Denver closures—charter capture & pause | B5: Chalkbeat/Denverite (2024–2025) | C5: Choice‑market retention risk; case for iterate‑and‑evaluate.
A6: Kyrene revision (9→7) | B6: Kyrene ESD | C6: Local iteration example.
A7: SUSD Strategic Plan / WIG (enrollment) | B7: SUSD Strategic Plan | C7: Shows growth is an explicit district goal.
