Workbook
Name ADM_Day_Select: Parameters_Public!C8
Name BaseAid_per_ADM: Parameters_Public!C18
Name Capex_ArtsHub: Parameters_Public!C28
Name Capex_in_MO_Toggle: Parameters_Public!C30
Name Capex_InnovHub: Parameters_Public!C29
Name Echo_ADM0: Parameters_Public!C10
Name EchoFixed_FY25_Total: Site_Fixed!C8
Name M_O_per_ADM_Audited: Parameters_Public!C14
Name Override_per_ADM_proxy: Parameters_Public!C19
Name Override_Percent: Parameters_Public!C17
Name Override_Toggle: Parameters_Public!C20
Name Pima_ADM0: Parameters_Public!C11
Name PimaFixed_FY25_Total: Site_Fixed!C15
Name TI_in_MO_Toggle: Parameters_Public!C26
Name TI_per_Site: Parameters_Public!C27

Sheet Parameters_Public
A1: Public Inputs — Audited Baselines and Overrides (Phase A)
A3: ADM (official) | C3: Values | E3: Notes
B4: Echo 40th | C4: 257 | D4: Use Day (40 or 100) | E4: Estimate used at this point; need to replace. Official 40th day ADM for Echo (enter audited)
B5: Echo 100th | C5: 257 | D5: Echo_ADM0 (selected) | E5: Estimate used at this point; need to replace. Official 100th day ADM for Echo (enter audited)
B6: Pima 40th | C6: 296 | D6: Pima_ADM0 (selected) | E6: Estimate used at this point; need to replace. Official 40th day ADM for Pima (enter audited)
B7: Pima 100th | C7: 296 | E7: Estimate used at this point; need to replace. Official 100th day ADM for Pima (enter audited)
B8: Use Day (40 or 100) | C8: 40 | E8: Choose which count the model uses (40 or 100).
B10: Echo_ADM0 (selected) | C10: =IF(C8=40,C4,C5) -> 257 | E10: Model‑read Echo_ADM0 selected based on 40/100 day switch.
B11: Pima_ADM0 (selected) | C11: =IF(C8=40,C6,C7) -> 296 | E11: Model‑read Pima_ADM0 selected based on 40/100 day switch.
A13: M&O/ADM (district), audited (ACFR)
B14: M_O_per_ADM_Audited | C14: 11589 | E14: Enter the audited districtwide Maintenance & Operations cost per ADM from the latest ACFR/Adopted Budget. Used as the FY25 base.
A16: Override — property‑tax override
B17: Override percent | C17: 0.15 | E17: Districtwide override percent (e.g., 15%).
B18: Base aid per ADM (proxy for RCL per pupil) | C18: 5013 | E18: Proxy base for calculating per‑ADM override; replace with RCL per pupil if available.
B19: Override per ADM (proxy) | C19: =C17*C18 -> 751.95 | E19: Computed per‑ADM amount used wherever the model needs a per‑student override term.
B20: Override toggle (1=on, 0=off) | C20: 1 | E20: Global on/off switch for including override in revenue calculations (future phase).
B22: Retention r — Echo (central) | C22: 0.6 | E22: Share of displaced Echo students re-enrolling in SUSD (0–1).
B23: Retention r — Pima (central) | C23: 0.85 | E23: Share of displaced Pima students re-enrolling in SUSD (0–1).
A24: Capital Treatment & Growth Capex (DRAFT placeholders)
B26: Include TI in Operating M&O? (0/1) | C26: 0 | E26: 0 = treat TI as capital (exclude from operating nets); 1 = include TI in Comparable_MO$
B27: TI per closed site (one-time) | C27: =BaselineCalc!$B$22 -> 1200000 | E27: DRAFT Ops TI: Mirrors BaselineCalc TI unit; replace with capital plan when available
B28: Growth Capex — Arts Hub (one-time) | C28: 800000 | E28: DRAFT placeholder; enter benchmarked capital required to enable Arts hub
B29: Growth Capex — Innovation Hub (one-time) | C29: 1200000 | E29: DRAFT placeholder; enter benchmarked capital required for Innovation hub
B30: Include Growth Capex in Operating? (0/1) | C30: 0 | E30: 0 = treat growth capex as capital (recommended); 1 = include in Comparable_MO$ (what‑if only)
B31: TI per closed site (lease case) | C31: 800000 | E31: DRAFT: lease TI placeholder; separate from ops TI (C27)
B32: Portable seat cost (capital $ per seat) | C32: 12000 | E32: DRAFT: per-seat portables or TI to add seats at receivers
B33: Spare K–5 seats across receivers (FY26) | C33: 300 | E33: User input: available elementary seats to absorb retained K–5
B34: Spare 6–8 seats across receivers (FY26) | C34: 150 | E34: User input: available middle seats to absorb retained 6–8
B36: Echo K–5 share of ADM | C36: 0.7 | E36: DRAFT: distribution of Echo ADM by grade band
B37: Echo 6–8 share of ADM | C37: 0.3
B38: Pima K–5 share of ADM | C38: 1
B39: Pima 6–8 share of ADM | C39: 0

Sheet Summary

Sheet Capital_Summary
A1: Capital Summary (TI & Growth Capex & Portables) — Cash, not Operating
A3: ScenarioKey | B3: Year | C3: ClosedSites | D3: TI_Cash$ | E3: GrowthCapex_Echo$ | F3: GrowthCapex_Pima$ | G3: Portables$ | H3: Total_Capital$
A4: =Scenarios!$A$2 -> D_CUSTOM1 | B4: FY2026 | C4: =INDEX(Scenarios!$D:$D, MATCH($A4, Scenarios!$A:$A, 0)) + INDEX(Scenarios!$E:$E, MATCH($A4, Scenarios!$A:$A, 0)) -> 0 | D4: =IF($B4="FY2026",$C4*IF(INDEX(Scenarios!$N:$N, MATCH($A4, Scenarios!$A:$A, 0))="lease", Parameters_Public!$C$31, Parameters_Public!$C$27),0) -> 0 | E4: =IF($B4="FY2026", IF(INDEX(Scenarios!$D:$D, MATCH($A4, Scenarios!$A:$A, 0))=0, IF(LEFT(INDEX(Scenarios!$O:$O, MATCH($A4, Scenarios!$A:$A, 0)),4)="Arts", Parameters_Public!$C$28, IF(LEFT(INDEX(Scenarios!$O:$O, MATCH($A4, Scenarios!$A:$A, 0)),5)="Innov", Parameters_Public!$C$29, 0)), 0), 0) -> 0 | F4: =IF($B4="FY2026", IF(INDEX(Scenarios!$E:$E, MATCH($A4, Scenarios!$A:$A, 0))=0, IF(LEFT(INDEX(Scenarios!$P:$P, MATCH($A4, Scenarios!$A:$A, 0)),4)="Arts", Parameters_Public!$C$28, IF(LEFT(INDEX(Scenarios!$P:$P, MATCH($A4, Scenarios!$A:$A, 0)),5)="Innov", Parameters_Public!$C$29, 0)), 0), 0) -> 0 | G4: =IF($B4="FY2026", INDEX(Receiving_Capacity!$L:$L, MATCH($A4, Receiving_Capacity!$A:$A, 0)), 0) -> 0 | H4: =SUM(D4:G4) -> 0
A5: =Scenarios!$A$2 -> D_CUSTOM1 | B5: FY2027 | C5: =INDEX(Scenarios!$D:$D, MATCH($A5, Scenarios!$A:$A, 0)) + INDEX(Scenarios!$E:$E, MATCH($A5, Scenarios!$A:$A, 0)) -> 0 | D5: =IF($B5="FY2026",$C5*IF(INDEX(Scenarios!$N:$N, MATCH($A5, Scenarios!$A:$A, 0))="lease", Parameters_Public!$C$31, Parameters_Public!$C$27),0) -> 0 | E5: =IF($B5="FY2026", IF(INDEX(Scenarios!$D:$D, MATCH($A5, Scenarios!$A:$A, 0))=0, IF(LEFT(INDEX(Scenarios!$O:$O, MATCH($A5, Scenarios!$A:$A, 0)),4)="Arts", Parameters_Public!$C$28, IF(LEFT(INDEX(Scenarios!$O:$O, MATCH($A5, Scenarios!$A:$A, 0)),5)="Innov", Parameters_Public!$C$29, 0)), 0), 0) -> 0 | F5: =IF($B5="FY2026", IF(INDEX(Scenarios!$E:$E, MATCH($A5, Scenarios!$A:$A, 0))=0, IF(LEFT(INDEX(Scenarios!$P:$P, MATCH($A5, Scenarios!$A:$A, 0)),4)="Arts", Parameters_Public!$C$28, IF(LEFT(INDEX(Scenarios!$P:$P, MATCH($A5, Scenarios!$A:$A, 0)),5)="Innov", Parameters_Public!$C$29, 0)), 0), 0) -> 0 | G5: =IF($B5="FY2026", INDEX(Receiving_Capacity!$L:$L, MATCH($A5, Receiving_Capacity!$A:$A, 0)), 0) -> 0 | H5: =SUM(D5:G5) -> 0
A6: =Scenarios!$A$2 -> D_CUSTOM1 | B6: FY2028 | C6: =INDEX(Scenarios!$D:$D, MATCH($A6, Scenarios!$A:$A, 0)) + INDEX(Scenarios!$E:$E, MATCH($A6, Scenarios!$A:$A, 0)) -> 0 | D6: =IF($B6="FY2026",$C6*IF(INDEX(Scenarios!$N:$N, MATCH($A6, Scenarios!$A:$A, 0))="lease", Parameters_Public!$C$31, Parameters_Public!$C$27),0) -> 0 | E6: =IF($B6="FY2026", IF(INDEX(Scenarios!$D:$D, MATCH($A6, Scenarios!$A:$A, 0))=0, IF(LEFT(INDEX(Scenarios!$O:$O, MATCH($A6, Scenarios!$A:$A, 0)),4)="Arts", Parameters_Public!$C$28, IF(LEFT(INDEX(Scenarios!$O:$O, MATCH($A6, Scenarios!$A:$A, 0)),5)="Innov", Parameters_Public!$C$29, 0)), 0), 0) -> 0 | F6: =IF($B6="FY2026", IF(INDEX(Scenarios!$E:$E, MATCH($A6, Scenarios!$A:$A, 0))=0, IF(LEFT(INDEX(Scenarios!$P:$P, MATCH($A6, Scenarios!$A:$A, 0)),4)="Arts", Parameters_Public!$C$28, IF(LEFT(INDEX(Scenarios!$P:$P, MATCH($A6, Scenarios!$A:$A, 0)),5)="Innov", Parameters_Public!$C$29, 0)), 0), 0) -> 0 | G6: =IF($B6="FY2026", INDEX(Receiving_Capacity!$L:$L, MATCH($A6, Receiving_Capacity!$A:$A, 0)), 0) -> 0 | H6: =SUM(D6:G6) -> 0
A7: =Scenarios!$A$2 -> D_CUSTOM1 | B7: FY2029 | C7: =INDEX(Scenarios!$D:$D, MATCH($A7, Scenarios!$A:$A, 0)) + INDEX(Scenarios!$E:$E, MATCH($A7, Scenarios!$A:$A, 0)) -> 0 | D7: =IF($B7="FY2026",$C7*IF(INDEX(Scenarios!$N:$N, MATCH($A7, Scenarios!$A:$A, 0))="lease", Parameters_Public!$C$31, Parameters_Public!$C$27),0) -> 0 | E7: =IF($B7="FY2026", IF(INDEX(Scenarios!$D:$D, MATCH($A7, Scenarios!$A:$A, 0))=0, IF(LEFT(INDEX(Scenarios!$O:$O, MATCH($A7, Scenarios!$A:$A, 0)),4)="Arts", Parameters_Public!$C$28, IF(LEFT(INDEX(Scenarios!$O:$O, MATCH($A7, Scenarios!$A:$A, 0)),5)="Innov", Parameters_Public!$C$29, 0)), 0), 0) -> 0 | F7: =IF($B7="FY2026", IF(INDEX(Scenarios!$E:$E, MATCH($A7, Scenarios!$A:$A, 0))=0, IF(LEFT(INDEX(Scenarios!$P:$P, MATCH($A7, Scenarios!$A:$A, 0)),4)="Arts", Parameters_Public!$C$28, IF(LEFT(INDEX(Scenarios!$P:$P, MATCH($A7, Scenarios!$A:$A, 0)),5)="Innov", Parameters_Public!$C$29, 0)), 0), 0) -> 0 | G7: =IF($B7="FY2026", INDEX(Receiving_Capacity!$L:$L, MATCH($A7, Receiving_Capacity!$A:$A, 0)), 0) -> 0 | H7: =SUM(D7:G7) -> 0
A8: =Scenarios!$A$2 -> D_CUSTOM1 | B8: FY2030 | C8: =INDEX(Scenarios!$D:$D, MATCH($A8, Scenarios!$A:$A, 0)) + INDEX(Scenarios!$E:$E, MATCH($A8, Scenarios!$A:$A, 0)) -> 0 | D8: =IF($B8="FY2026",$C8*IF(INDEX(Scenarios!$N:$N, MATCH($A8, Scenarios!$A:$A, 0))="lease", Parameters_Public!$C$31, Parameters_Public!$C$27),0) -> 0 | E8: =IF($B8="FY2026", IF(INDEX(Scenarios!$D:$D, MATCH($A8, Scenarios!$A:$A, 0))=0, IF(LEFT(INDEX(Scenarios!$O:$O, MATCH($A8, Scenarios!$A:$A, 0)),4)="Arts", Parameters_Public!$C$28, IF(LEFT(INDEX(Scenarios!$O:$O, MATCH($A8, Scenarios!$A:$A, 0)),5)="Innov", Parameters_Public!$C$29, 0)), 0), 0) -> 0 | F8: =IF($B8="FY2026", IF(INDEX(Scenarios!$E:$E, MATCH($A8, Scenarios!$A:$A, 0))=0, IF(LEFT(INDEX(Scenarios!$P:$P, MATCH($A8, Scenarios!$A:$A, 0)),4)="Arts", Parameters_Public!$C$28, IF(LEFT(INDEX(Scenarios!$P:$P, MATCH($A8, Scenarios!$A:$A, 0)),5)="Innov", Parameters_Public!$C$29, 0)), 0), 0) -> 0 | G8: =IF($B8="FY2026", INDEX(Receiving_Capacity!$L:$L, MATCH($A8, Receiving_Capacity!$A:$A, 0)), 0) -> 0 | H8: =SUM(D8:G8) -> 0
A9: =Scenarios!$A$3 -> E_StatusQuo_Targets | B9: FY2026 | C9: =INDEX(Scenarios!$D:$D, MATCH($A9, Scenarios!$A:$A, 0)) + INDEX(Scenarios!$E:$E, MATCH($A9, Scenarios!$A:$A, 0)) -> 0 | D9: =IF($B9="FY2026",$C9*IF(INDEX(Scenarios!$N:$N, MATCH($A9, Scenarios!$A:$A, 0))="lease", Parameters_Public!$C$31, Parameters_Public!$C$27),0) -> 0 | E9: =IF($B9="FY2026", IF(INDEX(Scenarios!$D:$D, MATCH($A9, Scenarios!$A:$A, 0))=0, IF(LEFT(INDEX(Scenarios!$O:$O, MATCH($A9, Scenarios!$A:$A, 0)),4)="Arts", Parameters_Public!$C$28, IF(LEFT(INDEX(Scenarios!$O:$O, MATCH($A9, Scenarios!$A:$A, 0)),5)="Innov", Parameters_Public!$C$29, 0)), 0), 0) -> 0 | F9: =IF($B9="FY2026", IF(INDEX(Scenarios!$E:$E, MATCH($A9, Scenarios!$A:$A, 0))=0, IF(LEFT(INDEX(Scenarios!$P:$P, MATCH($A9, Scenarios!$A:$A, 0)),4)="Arts", Parameters_Public!$C$28, IF(LEFT(INDEX(Scenarios!$P:$P, MATCH($A9, Scenarios!$A:$A, 0)),5)="Innov", Parameters_Public!$C$29, 0)), 0), 0) -> 0 | G9: =IF($B9="FY2026", INDEX(Receiving_Capacity!$L:$L, MATCH($A9, Receiving_Capacity!$A:$A, 0)), 0) -> 0 | H9: =SUM(D9:G9) -> 0
A10: =Scenarios!$A$3 -> E_StatusQuo_Targets | B10: FY2027 | C10: =INDEX(Scenarios!$D:$D, MATCH($A10, Scenarios!$A:$A, 0)) + INDEX(Scenarios!$E:$E, MATCH($A10, Scenarios!$A:$A, 0)) -> 0 | D10: =IF($B10="FY2026",$C10*IF(INDEX(Scenarios!$N:$N, MATCH($A10, Scenarios!$A:$A, 0))="lease", Parameters_Public!$C$31, Parameters_Public!$C$27),0) -> 0 | E10: =IF($B10="FY2026", IF(INDEX(Scenarios!$D:$D, MATCH($A10, Scenarios!$A:$A, 0))=0, IF(LEFT(INDEX(Scenarios!$O:$O, MATCH($A10, Scenarios!$A:$A, 0)),4)="Arts", Parameters_Public!$C$28, IF(LEFT(INDEX(Scenarios!$O:$O, MATCH($A10, Scenarios!$A:$A, 0)),5)="Innov", Parameters_Public!$C$29, 0)), 0), 0) -> 0 | F10: =IF($B10="FY2026", IF(INDEX(Scenarios!$E:$E, MATCH($A10, Scenarios!$A:$A, 0))=0, IF(LEFT(INDEX(Scenarios!$P:$P, MATCH($A10, Scenarios!$A:$A, 0)),4)="Arts", Parameters_Public!$C$28, IF(LEFT(INDEX(Scenarios!$P:$P, MATCH($A10, Scenarios!$A:$A, 0)),5)="Innov", Parameters_Public!$C$29, 0)), 0), 0) -> 0 | G10: =IF($B10="FY2026", INDEX(Receiving_Capacity!$L:$L, MATCH($A10, Receiving_Capacity!$A:$A, 0)), 0) -> 0 | H10: =SUM(D10:G10) -> 0
A11: =Scenarios!$A$3 -> E_StatusQuo_Targets | B11: FY2028 | C11: =INDEX(Scenarios!$D:$D, MATCH($A11, Scenarios!$A:$A, 0)) + INDEX(Scenarios!$E:$E, MATCH($A11, Scenarios!$A:$A, 0)) -> 0 | D11: =IF($B11="FY2026",$C11*IF(INDEX(Scenarios!$N:$N, MATCH($A11, Scenarios!$A:$A, 0))="lease", Parameters_Public!$C$31, Parameters_Public!$C$27),0) -> 0 | E11: =IF($B11="FY2026", IF(INDEX(Scenarios!$D:$D, MATCH($A11, Scenarios!$A:$A, 0))=0, IF(LEFT(INDEX(Scenarios!$O:$O, MATCH($A11, Scenarios!$A:$A, 0)),4)="Arts", Parameters_Public!$C$28, IF(LEFT(INDEX(Scenarios!$O:$O, MATCH($A11, Scenarios!$A:$A, 0)),5)="Innov", Parameters_Public!$C$29, 0)), 0), 0) -> 0 | F11: =IF($B11="FY2026", IF(INDEX(Scenarios!$E:$E, MATCH($A11, Scenarios!$A:$A, 0))=0, IF(LEFT(INDEX(Scenarios!$P:$P, MATCH($A11, Scenarios!$A:$A, 0)),4)="Arts", Parameters_Public!$C$28, IF(LEFT(INDEX(Scenarios!$P:$P, MATCH($A11, Scenarios!$A:$A, 0)),5)="Innov", Parameters_Public!$C$29, 0)), 0), 0) -> 0 | G11: =IF($B11="FY2026", INDEX(Receiving_Capacity!$L:$L, MATCH($A11, Receiving_Capacity!$A:$A, 0)), 0) -> 0 | H11: =SUM(D11:G11) -> 0
A12: =Scenarios!$A$3 -> E_StatusQuo_Targets | B12: FY2029 | C12: =INDEX(Scenarios!$D:$D, MATCH($A12, Scenarios!$A:$A, 0)) + INDEX(Scenarios!$E:$E, MATCH($A12, Scenarios!$A:$A, 0)) -> 0 | D12: =IF($B12="FY2026",$C12*IF(INDEX(Scenarios!$N:$N, MATCH($A12, Scenarios!$A:$A, 0))="lease", Parameters_Public!$C$31, Parameters_Public!$C$27),0) -> 0 | E12: =IF($B12="FY2026", IF(INDEX(Scenarios!$D:$D, MATCH($A12, Scenarios!$A:$A, 0))=0, IF(LEFT(INDEX(Scenarios!$O:$O, MATCH($A12, Scenarios!$A:$A, 0)),4)="Arts", Parameters_Public!$C$28, IF(LEFT(INDEX(Scenarios!$O:$O, MATCH($A12, Scenarios!$A:$A, 0)),5)="Innov", Parameters_Public!$C$29, 0)), 0), 0) -> 0 | F12: =IF($B12="FY2026", IF(INDEX(Scenarios!$E:$E, MATCH($A12, Scenarios!$A:$A, 0))=0, IF(LEFT(INDEX(Scenarios!$P:$P, MATCH($A12, Scenarios!$A:$A, 0)),4)="Arts", Parameters_Public!$C$28, IF(LEFT(INDEX(Scenarios!$P:$P, MATCH($A12, Scenarios!$A:$A, 0)),5)="Innov", Parameters_Public!$C$29, 0)), 0), 0) -> 0 | G12: =IF($B12="FY2026", INDEX(Receiving_Capacity!$L:$L, MATCH($A12, Receiving_Capacity!$A:$A, 0)), 0) -> 0 | H12: =SUM(D12:G12) -> 0
A13: =Scenarios!$A$3 -> E_StatusQuo_Targets | B13: FY2030 | C13: =INDEX(Scenarios!$D:$D, MATCH($A13, Scenarios!$A:$A, 0)) + INDEX(Scenarios!$E:$E, MATCH($A13, Scenarios!$A:$A, 0)) -> 0 | D13: =IF($B13="FY2026",$C13*IF(INDEX(Scenarios!$N:$N, MATCH($A13, Scenarios!$A:$A, 0))="lease", Parameters_Public!$C$31, Parameters_Public!$C$27),0) -> 0 | E13: =IF($B13="FY2026", IF(INDEX(Scenarios!$D:$D, MATCH($A13, Scenarios!$A:$A, 0))=0, IF(LEFT(INDEX(Scenarios!$O:$O, MATCH($A13, Scenarios!$A:$A, 0)),4)="Arts", Parameters_Public!$C$28, IF(LEFT(INDEX(Scenarios!$O:$O, MATCH($A13, Scenarios!$A:$A, 0)),5)="Innov", Parameters_Public!$C$29, 0)), 0), 0) -> 0 | F13: =IF($B13="FY2026", IF(INDEX(Scenarios!$E:$E, MATCH($A13, Scenarios!$A:$A, 0))=0, IF(LEFT(INDEX(Scenarios!$P:$P, MATCH($A13, Scenarios!$A:$A, 0)),4)="Arts", Parameters_Public!$C$28, IF(LEFT(INDEX(Scenarios!$P:$P, MATCH($A13, Scenarios!$A:$A, 0)),5)="Innov", Parameters_Public!$C$29, 0)), 0), 0) -> 0 | G13: =IF($B13="FY2026", INDEX(Receiving_Capacity!$L:$L, MATCH($A13, Receiving_Capacity!$A:$A, 0)), 0) -> 0 | H13: =SUM(D13:G13) -> 0
A14: =Scenarios!$A$4 -> F_CoLocation_Echo_Targets | B14: FY2026 | C14: =INDEX(Scenarios!$D:$D, MATCH($A14, Scenarios!$A:$A, 0)) + INDEX(Scenarios!$E:$E, MATCH($A14, Scenarios!$A:$A, 0)) -> 0 | D14: =IF($B14="FY2026",$C14*IF(INDEX(Scenarios!$N:$N, MATCH($A14, Scenarios!$A:$A, 0))="lease", Parameters_Public!$C$31, Parameters_Public!$C$27),0) -> 0 | E14: =IF($B14="FY2026", IF(INDEX(Scenarios!$D:$D, MATCH($A14, Scenarios!$A:$A, 0))=0, IF(LEFT(INDEX(Scenarios!$O:$O, MATCH($A14, Scenarios!$A:$A, 0)),4)="Arts", Parameters_Public!$C$28, IF(LEFT(INDEX(Scenarios!$O:$O, MATCH($A14, Scenarios!$A:$A, 0)),5)="Innov", Parameters_Public!$C$29, 0)), 0), 0) -> 0 | F14: =IF($B14="FY2026", IF(INDEX(Scenarios!$E:$E, MATCH($A14, Scenarios!$A:$A, 0))=0, IF(LEFT(INDEX(Scenarios!$P:$P, MATCH($A14, Scenarios!$A:$A, 0)),4)="Arts", Parameters_Public!$C$28, IF(LEFT(INDEX(Scenarios!$P:$P, MATCH($A14, Scenarios!$A:$A, 0)),5)="Innov", Parameters_Public!$C$29, 0)), 0), 0) -> 0 | G14: =IF($B14="FY2026", INDEX(Receiving_Capacity!$L:$L, MATCH($A14, Receiving_Capacity!$A:$A, 0)), 0) -> 0 | H14: =SUM(D14:G14) -> 0
A15: =Scenarios!$A$4 -> F_CoLocation_Echo_Targets | B15: FY2027 | C15: =INDEX(Scenarios!$D:$D, MATCH($A15, Scenarios!$A:$A, 0)) + INDEX(Scenarios!$E:$E, MATCH($A15, Scenarios!$A:$A, 0)) -> 0 | D15: =IF($B15="FY2026",$C15*IF(INDEX(Scenarios!$N:$N, MATCH($A15, Scenarios!$A:$A, 0))="lease", Parameters_Public!$C$31, Parameters_Public!$C$27),0) -> 0 | E15: =IF($B15="FY2026", IF(INDEX(Scenarios!$D:$D, MATCH($A15, Scenarios!$A:$A, 0))=0, IF(LEFT(INDEX(Scenarios!$O:$O, MATCH($A15, Scenarios!$A:$A, 0)),4)="Arts", Parameters_Public!$C$28, IF(LEFT(INDEX(Scenarios!$O:$O, MATCH($A15, Scenarios!$A:$A, 0)),5)="Innov", Parameters_Public!$C$29, 0)), 0), 0) -> 0 | F15: =IF($B15="FY2026", IF(INDEX(Scenarios!$E:$E, MATCH($A15, Scenarios!$A:$A, 0))=0, IF(LEFT(INDEX(Scenarios!$P:$P, MATCH($A15, Scenarios!$A:$A, 0)),4)="Arts", Parameters_Public!$C$28, IF(LEFT(INDEX(Scenarios!$P:$P, MATCH($A15, Scenarios!$A:$A, 0)),5)="Innov", Parameters_Public!$C$29, 0)), 0), 0) -> 0 | G15: =IF($B15="FY2026", INDEX(Receiving_Capacity!$L:$L, MATCH($A15, Receiving_Capacity!$A:$A, 0)), 0) -> 0 | H15: =SUM(D15:G15) -> 0
A16: =Scenarios!$A$4 -> F_CoLocation_Echo_Targets | B16: FY2028 | C16: =INDEX(Scenarios!$D:$D, MATCH($A16, Scenarios!$A:$A, 0)) + INDEX(Scenarios!$E:$E, MATCH($A16, Scenarios!$A:$A, 0)) -> 0 | D16: =IF($B16="FY2026",$C16*IF(INDEX(Scenarios!$N:$N, MATCH($A16, Scenarios!$A:$A, 0))="lease", Parameters_Public!$C$31, Parameters_Public!$C$27),0) -> 0 | E16: =IF($B16="FY2026", IF(INDEX(Scenarios!$D:$D, MATCH($A16, Scenarios!$A:$A, 0))=0, IF(LEFT(INDEX(Scenarios!$O:$O, MATCH($A16, Scenarios!$A:$A, 0)),4)="Arts", Parameters_Public!$C$28, IF(LEFT(INDEX(Scenarios!$O:$O, MATCH($A16, Scenarios!$A:$A, 0)),5)="Innov", Parameters_Public!$C$29, 0)), 0), 0) -> 0 | F16: =IF($B16="FY2026", IF(INDEX(Scenarios!$E:$E, MATCH($A16, Scenarios!$A:$A, 0))=0, IF(LEFT(INDEX(Scenarios!$P:$P, MATCH($A16, Scenarios!$A:$A, 0)),4)="Arts", Parameters_Public!$C$28, IF(LEFT(INDEX(Scenarios!$P:$P, MATCH($A16, Scenarios!$A:$A, 0)),5)="Innov", Parameters_Public!$C$29, 0)), 0), 0) -> 0 | G16: =IF($B16="FY2026", INDEX(Receiving_Capacity!$L:$L, MATCH($A16, Receiving_Capacity!$A:$A, 0)), 0) -> 0 | H16: =SUM(D16:G16) -> 0
A17: =Scenarios!$A$4 -> F_CoLocation_Echo_Targets | B17: FY2029 | C17: =INDEX(Scenarios!$D:$D, MATCH($A17, Scenarios!$A:$A, 0)) + INDEX(Scenarios!$E:$E, MATCH($A17, Scenarios!$A:$A, 0)) -> 0 | D17: =IF($B17="FY2026",$C17*IF(INDEX(Scenarios!$N:$N, MATCH($A17, Scenarios!$A:$A, 0))="lease", Parameters_Public!$C$31, Parameters_Public!$C$27),0) -> 0 | E17: =IF($B17="FY2026", IF(INDEX(Scenarios!$D:$D, MATCH($A17, Scenarios!$A:$A, 0))=0, IF(LEFT(INDEX(Scenarios!$O:$O, MATCH($A17, Scenarios!$A:$A, 0)),4)="Arts", Parameters_Public!$C$28, IF(LEFT(INDEX(Scenarios!$O:$O, MATCH($A17, Scenarios!$A:$A, 0)),5)="Innov", Parameters_Public!$C$29, 0)), 0), 0) -> 0 | F17: =IF($B17="FY2026", IF(INDEX(Scenarios!$E:$E, MATCH($A17, Scenarios!$A:$A, 0))=0, IF(LEFT(INDEX(Scenarios!$P:$P, MATCH($A17, Scenarios!$A:$A, 0)),4)="Arts", Parameters_Public!$C$28, IF(LEFT(INDEX(Scenarios!$P:$P, MATCH($A17, Scenarios!$A:$A, 0)),5)="Innov", Parameters_Public!$C$29, 0)), 0), 0) -> 0 | G17: =IF($B17="FY2026", INDEX(Receiving_Capacity!$L:$L, MATCH($A17, Receiving_Capacity!$A:$A, 0)), 0) -> 0 | H17: =SUM(D17:G17) -> 0
A18: =Scenarios!$A$4 -> F_CoLocation_Echo_Targets | B18: FY2030 | C18: =INDEX(Scenarios!$D:$D, MATCH($A18, Scenarios!$A:$A, 0)) + INDEX(Scenarios!$E:$E, MATCH($A18, Scenarios!$A:$A, 0)) -> 0 | D18: =IF($B18="FY2026",$C18*IF(INDEX(Scenarios!$N:$N, MATCH($A18, Scenarios!$A:$A, 0))="lease", Parameters_Public!$C$31, Parameters_Public!$C$27),0) -> 0 | E18: =IF($B18="FY2026", IF(INDEX(Scenarios!$D:$D, MATCH($A18, Scenarios!$A:$A, 0))=0, IF(LEFT(INDEX(Scenarios!$O:$O, MATCH($A18, Scenarios!$A:$A, 0)),4)="Arts", Parameters_Public!$C$28, IF(LEFT(INDEX(Scenarios!$O:$O, MATCH($A18, Scenarios!$A:$A, 0)),5)="Innov", Parameters_Public!$C$29, 0)), 0), 0) -> 0 | F18: =IF($B18="FY2026", IF(INDEX(Scenarios!$E:$E, MATCH($A18, Scenarios!$A:$A, 0))=0, IF(LEFT(INDEX(Scenarios!$P:$P, MATCH($A18, Scenarios!$A:$A, 0)),4)="Arts", Parameters_Public!$C$28, IF(LEFT(INDEX(Scenarios!$P:$P, MATCH($A18, Scenarios!$A:$A, 0)),5)="Innov", Parameters_Public!$C$29, 0)), 0), 0) -> 0 | G18: =IF($B18="FY2026", INDEX(Receiving_Capacity!$L:$L, MATCH($A18, Receiving_Capacity!$A:$A, 0)), 0) -> 0 | H18: =SUM(D18:G18) -> 0
A19: =Scenarios!$A$5 -> D_Grow_Both_Targets | B19: FY2026 | C19: =INDEX(Scenarios!$D:$D, MATCH($A19, Scenarios!$A:$A, 0)) + INDEX(Scenarios!$E:$E, MATCH($A19, Scenarios!$A:$A, 0)) -> 0 | D19: =IF($B19="FY2026",$C19*IF(INDEX(Scenarios!$N:$N, MATCH($A19, Scenarios!$A:$A, 0))="lease", Parameters_Public!$C$31, Parameters_Public!$C$27),0) -> 0 | E19: =IF($B19="FY2026", IF(INDEX(Scenarios!$D:$D, MATCH($A19, Scenarios!$A:$A, 0))=0, IF(LEFT(INDEX(Scenarios!$O:$O, MATCH($A19, Scenarios!$A:$A, 0)),4)="Arts", Parameters_Public!$C$28, IF(LEFT(INDEX(Scenarios!$O:$O, MATCH($A19, Scenarios!$A:$A, 0)),5)="Innov", Parameters_Public!$C$29, 0)), 0), 0) -> 1200000 | F19: =IF($B19="FY2026", IF(INDEX(Scenarios!$E:$E, MATCH($A19, Scenarios!$A:$A, 0))=0, IF(LEFT(INDEX(Scenarios!$P:$P, MATCH($A19, Scenarios!$A:$A, 0)),4)="Arts", Parameters_Public!$C$28, IF(LEFT(INDEX(Scenarios!$P:$P, MATCH($A19, Scenarios!$A:$A, 0)),5)="Innov", Parameters_Public!$C$29, 0)), 0), 0) -> 800000 | G19: =IF($B19="FY2026", INDEX(Receiving_Capacity!$L:$L, MATCH($A19, Receiving_Capacity!$A:$A, 0)), 0) -> 0 | H19: =SUM(D19:G19) -> 2000000
A20: =Scenarios!$A$5 -> D_Grow_Both_Targets | B20: FY2027 | C20: =INDEX(Scenarios!$D:$D, MATCH($A20, Scenarios!$A:$A, 0)) + INDEX(Scenarios!$E:$E, MATCH($A20, Scenarios!$A:$A, 0)) -> 0 | D20: =IF($B20="FY2026",$C20*IF(INDEX(Scenarios!$N:$N, MATCH($A20, Scenarios!$A:$A, 0))="lease", Parameters_Public!$C$31, Parameters_Public!$C$27),0) -> 0 | E20: =IF($B20="FY2026", IF(INDEX(Scenarios!$D:$D, MATCH($A20, Scenarios!$A:$A, 0))=0, IF(LEFT(INDEX(Scenarios!$O:$O, MATCH($A20, Scenarios!$A:$A, 0)),4)="Arts", Parameters_Public!$C$28, IF(LEFT(INDEX(Scenarios!$O:$O, MATCH($A20, Scenarios!$A:$A, 0)),5)="Innov", Parameters_Public!$C$29, 0)), 0), 0) -> 0 | F20: =IF($B20="FY2026", IF(INDEX(Scenarios!$E:$E, MATCH($A20, Scenarios!$A:$A, 0))=0, IF(LEFT(INDEX(Scenarios!$P:$P, MATCH($A20, Scenarios!$A:$A, 0)),4)="Arts", Parameters_Public!$C$28, IF(LEFT(INDEX(Scenarios!$P:$P, MATCH($A20, Scenarios!$A:$A, 0)),5)="Innov", Parameters_Public!$C$29, 0)), 0), 0) -> 0 | G20: =IF($B20="FY2026", INDEX(Receiving_Capacity!$L:$L, MATCH($A20, Receiving_Capacity!$A:$A, 0)), 0) -> 0 | H20: =SUM(D20:G20) -> 0
A21: =Scenarios!$A$5 -> D_Grow_Both_Targets | B21: FY2028 | C21: =INDEX(Scenarios!$D:$D, MATCH($A21, Scenarios!$A:$A, 0)) + INDEX(Scenarios!$E:$E, MATCH($A21, Scenarios!$A:$A, 0)) -> 0 | D21: =IF($B21="FY2026",$C21*IF(INDEX(Scenarios!$N:$N, MATCH($A21, Scenarios!$A:$A, 0))="lease", Parameters_Public!$C$31, Parameters_Public!$C$27),0) -> 0 | E21: =IF($B21="FY2026", IF(INDEX(Scenarios!$D:$D, MATCH($A21, Scenarios!$A:$A, 0))=0, IF(LEFT(INDEX(Scenarios!$O:$O, MATCH($A21, Scenarios!$A:$A, 0)),4)="Arts", Parameters_Public!$C$28, IF(LEFT(INDEX(Scenarios!$O:$O, MATCH($A21, Scenarios!$A:$A, 0)),5)="Innov", Parameters_Public!$C$29, 0)), 0), 0) -> 0 | F21: =IF($B21="FY2026", IF(INDEX(Scenarios!$E:$E, MATCH($A21, Scenarios!$A:$A, 0))=0, IF(LEFT(INDEX(Scenarios!$P:$P, MATCH($A21, Scenarios!$A:$A, 0)),4)="Arts", Parameters_Public!$C$28, IF(LEFT(INDEX(Scenarios!$P:$P, MATCH($A21, Scenarios!$A:$A, 0)),5)="Innov", Parameters_Public!$C$29, 0)), 0), 0) -> 0 | G21: =IF($B21="FY2026", INDEX(Receiving_Capacity!$L:$L, MATCH($A21, Receiving_Capacity!$A:$A, 0)), 0) -> 0 | H21: =SUM(D21:G21) -> 0
A22: =Scenarios!$A$5 -> D_Grow_Both_Targets | B22: FY2029 | C22: =INDEX(Scenarios!$D:$D, MATCH($A22, Scenarios!$A:$A, 0)) + INDEX(Scenarios!$E:$E, MATCH($A22, Scenarios!$A:$A, 0)) -> 0 | D22: =IF($B22="FY2026",$C22*IF(INDEX(Scenarios!$N:$N, MATCH($A22, Scenarios!$A:$A, 0))="lease", Parameters_Public!$C$31, Parameters_Public!$C$27),0) -> 0 | E22: =IF($B22="FY2026", IF(INDEX(Scenarios!$D:$D, MATCH($A22, Scenarios!$A:$A, 0))=0, IF(LEFT(INDEX(Scenarios!$O:$O, MATCH($A22, Scenarios!$A:$A, 0)),4)="Arts", Parameters_Public!$C$28, IF(LEFT(INDEX(Scenarios!$O:$O, MATCH($A22, Scenarios!$A:$A, 0)),5)="Innov", Parameters_Public!$C$29, 0)), 0), 0) -> 0 | F22: =IF($B22="FY2026", IF(INDEX(Scenarios!$E:$E, MATCH($A22, Scenarios!$A:$A, 0))=0, IF(LEFT(INDEX(Scenarios!$P:$P, MATCH($A22, Scenarios!$A:$A, 0)),4)="Arts", Parameters_Public!$C$28, IF(LEFT(INDEX(Scenarios!$P:$P, MATCH($A22, Scenarios!$A:$A, 0)),5)="Innov", Parameters_Public!$C$29, 0)), 0), 0) -> 0 | G22: =IF($B22="FY2026", INDEX(Receiving_Capacity!$L:$L, MATCH($A22, Receiving_Capacity!$A:$A, 0)), 0) -> 0 | H22: =SUM(D22:G22) -> 0
A23: =Scenarios!$A$5 -> D_Grow_Both_Targets | B23: FY2030 | C23: =INDEX(Scenarios!$D:$D, MATCH($A23, Scenarios!$A:$A, 0)) + INDEX(Scenarios!$E:$E, MATCH($A23, Scenarios!$A:$A, 0)) -> 0 | D23: =IF($B23="FY2026",$C23*IF(INDEX(Scenarios!$N:$N, MATCH($A23, Scenarios!$A:$A, 0))="lease", Parameters_Public!$C$31, Parameters_Public!$C$27),0) -> 0 | E23: =IF($B23="FY2026", IF(INDEX(Scenarios!$D:$D, MATCH($A23, Scenarios!$A:$A, 0))=0, IF(LEFT(INDEX(Scenarios!$O:$O, MATCH($A23, Scenarios!$A:$A, 0)),4)="Arts", Parameters_Public!$C$28, IF(LEFT(INDEX(Scenarios!$O:$O, MATCH($A23, Scenarios!$A:$A, 0)),5)="Innov", Parameters_Public!$C$29, 0)), 0), 0) -> 0 | F23: =IF($B23="FY2026", IF(INDEX(Scenarios!$E:$E, MATCH($A23, Scenarios!$A:$A, 0))=0, IF(LEFT(INDEX(Scenarios!$P:$P, MATCH($A23, Scenarios!$A:$A, 0)),4)="Arts", Parameters_Public!$C$28, IF(LEFT(INDEX(Scenarios!$P:$P, MATCH($A23, Scenarios!$A:$A, 0)),5)="Innov", Parameters_Public!$C$29, 0)), 0), 0) -> 0 | G23: =IF($B23="FY2026", INDEX(Receiving_Capacity!$L:$L, MATCH($A23, Receiving_Capacity!$A:$A, 0)), 0) -> 0 | H23: =SUM(D23:G23) -> 0
A24: =Scenarios!$A$6 -> D_CUSTOM2 | B24: FY2026 | C24: =INDEX(Scenarios!$D:$D, MATCH($A24, Scenarios!$A:$A, 0)) + INDEX(Scenarios!$E:$E, MATCH($A24, Scenarios!$A:$A, 0)) -> 0 | D24: =IF($B24="FY2026",$C24*IF(INDEX(Scenarios!$N:$N, MATCH($A24, Scenarios!$A:$A, 0))="lease", Parameters_Public!$C$31, Parameters_Public!$C$27),0) -> 0 | E24: =IF($B24="FY2026", IF(INDEX(Scenarios!$D:$D, MATCH($A24, Scenarios!$A:$A, 0))=0, IF(LEFT(INDEX(Scenarios!$O:$O, MATCH($A24, Scenarios!$A:$A, 0)),4)="Arts", Parameters_Public!$C$28, IF(LEFT(INDEX(Scenarios!$O:$O, MATCH($A24, Scenarios!$A:$A, 0)),5)="Innov", Parameters_Public!$C$29, 0)), 0), 0) -> 0 | F24: =IF($B24="FY2026", IF(INDEX(Scenarios!$E:$E, MATCH($A24, Scenarios!$A:$A, 0))=0, IF(LEFT(INDEX(Scenarios!$P:$P, MATCH($A24, Scenarios!$A:$A, 0)),4)="Arts", Parameters_Public!$C$28, IF(LEFT(INDEX(Scenarios!$P:$P, MATCH($A24, Scenarios!$A:$A, 0)),5)="Innov", Parameters_Public!$C$29, 0)), 0), 0) -> 0 | G24: =IF($B24="FY2026", INDEX(Receiving_Capacity!$L:$L, MATCH($A24, Receiving_Capacity!$A:$A, 0)), 0) -> 0 | H24: =SUM(D24:G24) -> 0
A25: =Scenarios!$A$6 -> D_CUSTOM2 | B25: FY2027 | C25: =INDEX(Scenarios!$D:$D, MATCH($A25, Scenarios!$A:$A, 0)) + INDEX(Scenarios!$E:$E, MATCH($A25, Scenarios!$A:$A, 0)) -> 0 | D25: =IF($B25="FY2026",$C25*IF(INDEX(Scenarios!$N:$N, MATCH($A25, Scenarios!$A:$A, 0))="lease", Parameters_Public!$C$31, Parameters_Public!$C$27),0) -> 0 | E25: =IF($B25="FY2026", IF(INDEX(Scenarios!$D:$D, MATCH($A25, Scenarios!$A:$A, 0))=0, IF(LEFT(INDEX(Scenarios!$O:$O, MATCH($A25, Scenarios!$A:$A, 0)),4)="Arts", Parameters_Public!$C$28, IF(LEFT(INDEX(Scenarios!$O:$O, MATCH($A25, Scenarios!$A:$A, 0)),5)="Innov", Parameters_Public!$C$29, 0)), 0), 0) -> 0 | F25: =IF($B25="FY2026", IF(INDEX(Scenarios!$E:$E, MATCH($A25, Scenarios!$A:$A, 0))=0, IF(LEFT(INDEX(Scenarios!$P:$P, MATCH($A25, Scenarios!$A:$A, 0)),4)="Arts", Parameters_Public!$C$28, IF(LEFT(INDEX(Scenarios!$P:$P, MATCH($A25, Scenarios!$A:$A, 0)),5)="Innov", Parameters_Public!$C$29, 0)), 0), 0) -> 0 | G25: =IF($B25="FY2026", INDEX(Receiving_Capacity!$L:$L, MATCH($A25, Receiving_Capacity!$A:$A, 0)), 0) -> 0 | H25: =SUM(D25:G25) -> 0
A26: =Scenarios!$A$6 -> D_CUSTOM2 | B26: FY2028 | C26: =INDEX(Scenarios!$D:$D, MATCH($A26, Scenarios!$A:$A, 0)) + INDEX(Scenarios!$E:$E, MATCH($A26, Scenarios!$A:$A, 0)) -> 0 | D26: =IF($B26="FY2026",$C26*IF(INDEX(Scenarios!$N:$N, MATCH($A26, Scenarios!$A:$A, 0))="lease", Parameters_Public!$C$31, Parameters_Public!$C$27),0) -> 0 | E26: =IF($B26="FY2026", IF(INDEX(Scenarios!$D:$D, MATCH($A26, Scenarios!$A:$A, 0))=0, IF(LEFT(INDEX(Scenarios!$O:$O, MATCH($A26, Scenarios!$A:$A, 0)),4)="Arts", Parameters_Public!$C$28, IF(LEFT(INDEX(Scenarios!$O:$O, MATCH($A26, Scenarios!$A:$A, 0)),5)="Innov", Parameters_Public!$C$29, 0)), 0), 0) -> 0 | F26: =IF($B26="FY2026", IF(INDEX(Scenarios!$E:$E, MATCH($A26, Scenarios!$A:$A, 0))=0, IF(LEFT(INDEX(Scenarios!$P:$P, MATCH($A26, Scenarios!$A:$A, 0)),4)="Arts", Parameters_Public!$C$28, IF(LEFT(INDEX(Scenarios!$P:$P, MATCH($A26, Scenarios!$A:$A, 0)),5)="Innov", Parameters_Public!$C$29, 0)), 0), 0) -> 0 | G26: =IF($B26="FY2026", INDEX(Receiving_Capacity!$L:$L, MATCH($A26, Receiving_Capacity!$A:$A, 0)), 0) -> 0 | H26: =SUM(D26:G26) -> 0
A27: =Scenarios!$A$6 -> D_CUSTOM2 | B27: FY2029 | C27: =INDEX(Scenarios!$D:$D, MATCH($A27, Scenarios!$A:$A, 0)) + INDEX(Scenarios!$E:$E, MATCH($A27, Scenarios!$A:$A, 0)) -> 0 | D27: =IF($B27="FY2026",$C27*IF(INDEX(Scenarios!$N:$N, MATCH($A27, Scenarios!$A:$A, 0))="lease", Parameters_Public!$C$31, Parameters_Public!$C$27),0) -> 0 | E27: =IF($B27="FY2026", IF(INDEX(Scenarios!$D:$D, MATCH($A27, Scenarios!$A:$A, 0))=0, IF(LEFT(INDEX(Scenarios!$O:$O, MATCH($A27, Scenarios!$A:$A, 0)),4)="Arts", Parameters_Public!$C$28, IF(LEFT(INDEX(Scenarios!$O:$O, MATCH($A27, Scenarios!$A:$A, 0)),5)="Innov", Parameters_Public!$C$29, 0)), 0), 0) -> 0 | F27: =IF($B27="FY2026", IF(INDEX(Scenarios!$E:$E, MATCH($A27, Scenarios!$A:$A, 0))=0, IF(LEFT(INDEX(Scenarios!$P:$P, MATCH($A27, Scenarios!$A:$A, 0)),4)="Arts", Parameters_Public!$C$28, IF(LEFT(INDEX(Scenarios!$P:$P, MATCH($A27, Scenarios!$A:$A, 0)),5)="Innov", Parameters_Public!$C$29, 0)), 0), 0) -> 0 | G27: =IF($B27="FY2026", INDEX(Receiving_Capacity!$L:$L, MATCH($A27, Receiving_Capacity!$A:$A, 0)), 0) -> 0 | H27: =SUM(D27:G27) -> 0
A28: =Scenarios!$A$6 -> D_CUSTOM2 | B28: FY2030 | C28: =INDEX(Scenarios!$D:$D, MATCH($A28, Scenarios!$A:$A, 0)) + INDEX(Scenarios!$E:$E, MATCH($A28, Scenarios!$A:$A, 0)) -> 0 | D28: =IF($B28="FY2026",$C28*IF(INDEX(Scenarios!$N:$N, MATCH($A28, Scenarios!$A:$A, 0))="lease", Parameters_Public!$C$31, Parameters_Public!$C$27),0) -> 0 | E28: =IF($B28="FY2026", IF(INDEX(Scenarios!$D:$D, MATCH($A28, Scenarios!$A:$A, 0))=0, IF(LEFT(INDEX(Scenarios!$O:$O, MATCH($A28, Scenarios!$A:$A, 0)),4)="Arts", Parameters_Public!$C$28, IF(LEFT(INDEX(Scenarios!$O:$O, MATCH($A28, Scenarios!$A:$A, 0)),5)="Innov", Parameters_Public!$C$29, 0)), 0), 0) -> 0 | F28: =IF($B28="FY2026", IF(INDEX(Scenarios!$E:$E, MATCH($A28, Scenarios!$A:$A, 0))=0, IF(LEFT(INDEX(Scenarios!$P:$P, MATCH($A28, Scenarios!$A:$A, 0)),4)="Arts", Parameters_Public!$C$28, IF(LEFT(INDEX(Scenarios!$P:$P, MATCH($A28, Scenarios!$A:$A, 0)),5)="Innov", Parameters_Public!$C$29, 0)), 0), 0) -> 0 | G28: =IF($B28="FY2026", INDEX(Receiving_Capacity!$L:$L, MATCH($A28, Receiving_Capacity!$A:$A, 0)), 0) -> 0 | H28: =SUM(D28:G28) -> 0
A29: =Scenarios!$A$7 -> G_EchoGHubRamp_PimaTargets | B29: FY2026 | C29: =INDEX(Scenarios!$D:$D, MATCH($A29, Scenarios!$A:$A, 0)) + INDEX(Scenarios!$E:$E, MATCH($A29, Scenarios!$A:$A, 0)) -> 0 | D29: =IF($B29="FY2026",$C29*IF(INDEX(Scenarios!$N:$N, MATCH($A29, Scenarios!$A:$A, 0))="lease", Parameters_Public!$C$31, Parameters_Public!$C$27),0) -> 0 | E29: =IF($B29="FY2026", IF(INDEX(Scenarios!$D:$D, MATCH($A29, Scenarios!$A:$A, 0))=0, IF(LEFT(INDEX(Scenarios!$O:$O, MATCH($A29, Scenarios!$A:$A, 0)),4)="Arts", Parameters_Public!$C$28, IF(LEFT(INDEX(Scenarios!$O:$O, MATCH($A29, Scenarios!$A:$A, 0)),5)="Innov", Parameters_Public!$C$29, 0)), 0), 0) -> 800000 | F29: =IF($B29="FY2026", IF(INDEX(Scenarios!$E:$E, MATCH($A29, Scenarios!$A:$A, 0))=0, IF(LEFT(INDEX(Scenarios!$P:$P, MATCH($A29, Scenarios!$A:$A, 0)),4)="Arts", Parameters_Public!$C$28, IF(LEFT(INDEX(Scenarios!$P:$P, MATCH($A29, Scenarios!$A:$A, 0)),5)="Innov", Parameters_Public!$C$29, 0)), 0), 0) -> 0 | G29: =IF($B29="FY2026", INDEX(Receiving_Capacity!$L:$L, MATCH($A29, Receiving_Capacity!$A:$A, 0)), 0) -> 0 | H29: =SUM(D29:G29) -> 800000
A30: =Scenarios!$A$7 -> G_EchoGHubRamp_PimaTargets | B30: FY2027 | C30: =INDEX(Scenarios!$D:$D, MATCH($A30, Scenarios!$A:$A, 0)) + INDEX(Scenarios!$E:$E, MATCH($A30, Scenarios!$A:$A, 0)) -> 0 | D30: =IF($B30="FY2026",$C30*IF(INDEX(Scenarios!$N:$N, MATCH($A30, Scenarios!$A:$A, 0))="lease", Parameters_Public!$C$31, Parameters_Public!$C$27),0) -> 0 | E30: =IF($B30="FY2026", IF(INDEX(Scenarios!$D:$D, MATCH($A30, Scenarios!$A:$A, 0))=0, IF(LEFT(INDEX(Scenarios!$O:$O, MATCH($A30, Scenarios!$A:$A, 0)),4)="Arts", Parameters_Public!$C$28, IF(LEFT(INDEX(Scenarios!$O:$O, MATCH($A30, Scenarios!$A:$A, 0)),5)="Innov", Parameters_Public!$C$29, 0)), 0), 0) -> 0 | F30: =IF($B30="FY2026", IF(INDEX(Scenarios!$E:$E, MATCH($A30, Scenarios!$A:$A, 0))=0, IF(LEFT(INDEX(Scenarios!$P:$P, MATCH($A30, Scenarios!$A:$A, 0)),4)="Arts", Parameters_Public!$C$28, IF(LEFT(INDEX(Scenarios!$P:$P, MATCH($A30, Scenarios!$A:$A, 0)),5)="Innov", Parameters_Public!$C$29, 0)), 0), 0) -> 0 | G30: =IF($B30="FY2026", INDEX(Receiving_Capacity!$L:$L, MATCH($A30, Receiving_Capacity!$A:$A, 0)), 0) -> 0 | H30: =SUM(D30:G30) -> 0
A31: =Scenarios!$A$7 -> G_EchoGHubRamp_PimaTargets | B31: FY2028 | C31: =INDEX(Scenarios!$D:$D, MATCH($A31, Scenarios!$A:$A, 0)) + INDEX(Scenarios!$E:$E, MATCH($A31, Scenarios!$A:$A, 0)) -> 0 | D31: =IF($B31="FY2026",$C31*IF(INDEX(Scenarios!$N:$N, MATCH($A31, Scenarios!$A:$A, 0))="lease", Parameters_Public!$C$31, Parameters_Public!$C$27),0) -> 0 | E31: =IF($B31="FY2026", IF(INDEX(Scenarios!$D:$D, MATCH($A31, Scenarios!$A:$A, 0))=0, IF(LEFT(INDEX(Scenarios!$O:$O, MATCH($A31, Scenarios!$A:$A, 0)),4)="Arts", Parameters_Public!$C$28, IF(LEFT(INDEX(Scenarios!$O:$O, MATCH($A31, Scenarios!$A:$A, 0)),5)="Innov", Parameters_Public!$C$29, 0)), 0), 0) -> 0 | F31: =IF($B31="FY2026", IF(INDEX(Scenarios!$E:$E, MATCH($A31, Scenarios!$A:$A, 0))=0, IF(LEFT(INDEX(Scenarios!$P:$P, MATCH($A31, Scenarios!$A:$A, 0)),4)="Arts", Parameters_Public!$C$28, IF(LEFT(INDEX(Scenarios!$P:$P, MATCH($A31, Scenarios!$A:$A, 0)),5)="Innov", Parameters_Public!$C$29, 0)), 0), 0) -> 0 | G31: =IF($B31="FY2026", INDEX(Receiving_Capacity!$L:$L, MATCH($A31, Receiving_Capacity!$A:$A, 0)), 0) -> 0 | H31: =SUM(D31:G31) -> 0
A32: =Scenarios!$A$7 -> G_EchoGHubRamp_PimaTargets | B32: FY2029 | C32: =INDEX(Scenarios!$D:$D, MATCH($A32, Scenarios!$A:$A, 0)) + INDEX(Scenarios!$E:$E, MATCH($A32, Scenarios!$A:$A, 0)) -> 0 | D32: =IF($B32="FY2026",$C32*IF(INDEX(Scenarios!$N:$N, MATCH($A32, Scenarios!$A:$A, 0))="lease", Parameters_Public!$C$31, Parameters_Public!$C$27),0) -> 0 | E32: =IF($B32="FY2026", IF(INDEX(Scenarios!$D:$D, MATCH($A32, Scenarios!$A:$A, 0))=0, IF(LEFT(INDEX(Scenarios!$O:$O, MATCH($A32, Scenarios!$A:$A, 0)),4)="Arts", Parameters_Public!$C$28, IF(LEFT(INDEX(Scenarios!$O:$O, MATCH($A32, Scenarios!$A:$A, 0)),5)="Innov", Parameters_Public!$C$29, 0)), 0), 0) -> 0 | F32: =IF($B32="FY2026", IF(INDEX(Scenarios!$E:$E, MATCH($A32, Scenarios!$A:$A, 0))=0, IF(LEFT(INDEX(Scenarios!$P:$P, MATCH($A32, Scenarios!$A:$A, 0)),4)="Arts", Parameters_Public!$C$28, IF(LEFT(INDEX(Scenarios!$P:$P, MATCH($A32, Scenarios!$A:$A, 0)),5)="Innov", Parameters_Public!$C$29, 0)), 0), 0) -> 0 | G32: =IF($B32="FY2026", INDEX(Receiving_Capacity!$L:$L, MATCH($A32, Receiving_Capacity!$A:$A, 0)), 0) -> 0 | H32: =SUM(D32:G32) -> 0
A33: =Scenarios!$A$7 -> G_EchoGHubRamp_PimaTargets | B33: FY2030 | C33: =INDEX(Scenarios!$D:$D, MATCH($A33, Scenarios!$A:$A, 0)) + INDEX(Scenarios!$E:$E, MATCH($A33, Scenarios!$A:$A, 0)) -> 0 | D33: =IF($B33="FY2026",$C33*IF(INDEX(Scenarios!$N:$N, MATCH($A33, Scenarios!$A:$A, 0))="lease", Parameters_Public!$C$31, Parameters_Public!$C$27),0) -> 0 | E33: =IF($B33="FY2026", IF(INDEX(Scenarios!$D:$D, MATCH($A33, Scenarios!$A:$A, 0))=0, IF(LEFT(INDEX(Scenarios!$O:$O, MATCH($A33, Scenarios!$A:$A, 0)),4)="Arts", Parameters_Public!$C$28, IF(LEFT(INDEX(Scenarios!$O:$O, MATCH($A33, Scenarios!$A:$A, 0)),5)="Innov", Parameters_Public!$C$29, 0)), 0), 0) -> 0 | F33: =IF($B33="FY2026", IF(INDEX(Scenarios!$E:$E, MATCH($A33, Scenarios!$A:$A, 0))=0, IF(LEFT(INDEX(Scenarios!$P:$P, MATCH($A33, Scenarios!$A:$A, 0)),4)="Arts", Parameters_Public!$C$28, IF(LEFT(INDEX(Scenarios!$P:$P, MATCH($A33, Scenarios!$A:$A, 0)),5)="Innov", Parameters_Public!$C$29, 0)), 0), 0) -> 0 | G33: =IF($B33="FY2026", INDEX(Receiving_Capacity!$L:$L, MATCH($A33, Receiving_Capacity!$A:$A, 0)), 0) -> 0 | H33: =SUM(D33:G33) -> 0
A34: =Scenarios!$A$8 -> A_Repurpose_Both_lease | B34: FY2026 | C34: =INDEX(Scenarios!$D:$D, MATCH($A34, Scenarios!$A:$A, 0)) + INDEX(Scenarios!$E:$E, MATCH($A34, Scenarios!$A:$A, 0)) -> 2 | D34: =IF($B34="FY2026",$C34*IF(INDEX(Scenarios!$N:$N, MATCH($A34, Scenarios!$A:$A, 0))="lease", Parameters_Public!$C$31, Parameters_Public!$C$27),0) -> 1600000 | E34: =IF($B34="FY2026", IF(INDEX(Scenarios!$D:$D, MATCH($A34, Scenarios!$A:$A, 0))=0, IF(LEFT(INDEX(Scenarios!$O:$O, MATCH($A34, Scenarios!$A:$A, 0)),4)="Arts", Parameters_Public!$C$28, IF(LEFT(INDEX(Scenarios!$O:$O, MATCH($A34, Scenarios!$A:$A, 0)),5)="Innov", Parameters_Public!$C$29, 0)), 0), 0) -> 0 | F34: =IF($B34="FY2026", IF(INDEX(Scenarios!$E:$E, MATCH($A34, Scenarios!$A:$A, 0))=0, IF(LEFT(INDEX(Scenarios!$P:$P, MATCH($A34, Scenarios!$A:$A, 0)),4)="Arts", Parameters_Public!$C$28, IF(LEFT(INDEX(Scenarios!$P:$P, MATCH($A34, Scenarios!$A:$A, 0)),5)="Innov", Parameters_Public!$C$29, 0)), 0), 0) -> 0 | G34: =IF($B34="FY2026", INDEX(Receiving_Capacity!$L:$L, MATCH($A34, Receiving_Capacity!$A:$A, 0)), 0) -> 714480 | H34: =SUM(D34:G34) -> 2314480
A35: =Scenarios!$A$8 -> A_Repurpose_Both_lease | B35: FY2027 | C35: =INDEX(Scenarios!$D:$D, MATCH($A35, Scenarios!$A:$A, 0)) + INDEX(Scenarios!$E:$E, MATCH($A35, Scenarios!$A:$A, 0)) -> 2 | D35: =IF($B35="FY2026",$C35*IF(INDEX(Scenarios!$N:$N, MATCH($A35, Scenarios!$A:$A, 0))="lease", Parameters_Public!$C$31, Parameters_Public!$C$27),0) -> 0 | E35: =IF($B35="FY2026", IF(INDEX(Scenarios!$D:$D, MATCH($A35, Scenarios!$A:$A, 0))=0, IF(LEFT(INDEX(Scenarios!$O:$O, MATCH($A35, Scenarios!$A:$A, 0)),4)="Arts", Parameters_Public!$C$28, IF(LEFT(INDEX(Scenarios!$O:$O, MATCH($A35, Scenarios!$A:$A, 0)),5)="Innov", Parameters_Public!$C$29, 0)), 0), 0) -> 0 | F35: =IF($B35="FY2026", IF(INDEX(Scenarios!$E:$E, MATCH($A35, Scenarios!$A:$A, 0))=0, IF(LEFT(INDEX(Scenarios!$P:$P, MATCH($A35, Scenarios!$A:$A, 0)),4)="Arts", Parameters_Public!$C$28, IF(LEFT(INDEX(Scenarios!$P:$P, MATCH($A35, Scenarios!$A:$A, 0)),5)="Innov", Parameters_Public!$C$29, 0)), 0), 0) -> 0 | G35: =IF($B35="FY2026", INDEX(Receiving_Capacity!$L:$L, MATCH($A35, Receiving_Capacity!$A:$A, 0)), 0) -> 0 | H35: =SUM(D35:G35) -> 0
A36: =Scenarios!$A$8 -> A_Repurpose_Both_lease | B36: FY2028 | C36: =INDEX(Scenarios!$D:$D, MATCH($A36, Scenarios!$A:$A, 0)) + INDEX(Scenarios!$E:$E, MATCH($A36, Scenarios!$A:$A, 0)) -> 2 | D36: =IF($B36="FY2026",$C36*IF(INDEX(Scenarios!$N:$N, MATCH($A36, Scenarios!$A:$A, 0))="lease", Parameters_Public!$C$31, Parameters_Public!$C$27),0) -> 0 | E36: =IF($B36="FY2026", IF(INDEX(Scenarios!$D:$D, MATCH($A36, Scenarios!$A:$A, 0))=0, IF(LEFT(INDEX(Scenarios!$O:$O, MATCH($A36, Scenarios!$A:$A, 0)),4)="Arts", Parameters_Public!$C$28, IF(LEFT(INDEX(Scenarios!$O:$O, MATCH($A36, Scenarios!$A:$A, 0)),5)="Innov", Parameters_Public!$C$29, 0)), 0), 0) -> 0 | F36: =IF($B36="FY2026", IF(INDEX(Scenarios!$E:$E, MATCH($A36, Scenarios!$A:$A, 0))=0, IF(LEFT(INDEX(Scenarios!$P:$P, MATCH($A36, Scenarios!$A:$A, 0)),4)="Arts", Parameters_Public!$C$28, IF(LEFT(INDEX(Scenarios!$P:$P, MATCH($A36, Scenarios!$A:$A, 0)),5)="Innov", Parameters_Public!$C$29, 0)), 0), 0) -> 0 | G36: =IF($B36="FY2026", INDEX(Receiving_Capacity!$L:$L, MATCH($A36, Receiving_Capacity!$A:$A, 0)), 0) -> 0 | H36: =SUM(D36:G36) -> 0
A37: =Scenarios!$A$8 -> A_Repurpose_Both_lease | B37: FY2029 | C37: =INDEX(Scenarios!$D:$D, MATCH($A37, Scenarios!$A:$A, 0)) + INDEX(Scenarios!$E:$E, MATCH($A37, Scenarios!$A:$A, 0)) -> 2 | D37: =IF($B37="FY2026",$C37*IF(INDEX(Scenarios!$N:$N, MATCH($A37, Scenarios!$A:$A, 0))="lease", Parameters_Public!$C$31, Parameters_Public!$C$27),0) -> 0 | E37: =IF($B37="FY2026", IF(INDEX(Scenarios!$D:$D, MATCH($A37, Scenarios!$A:$A, 0))=0, IF(LEFT(INDEX(Scenarios!$O:$O, MATCH($A37, Scenarios!$A:$A, 0)),4)="Arts", Parameters_Public!$C$28, IF(LEFT(INDEX(Scenarios!$O:$O, MATCH($A37, Scenarios!$A:$A, 0)),5)="Innov", Parameters_Public!$C$29, 0)), 0), 0) -> 0 | F37: =IF($B37="FY2026", IF(INDEX(Scenarios!$E:$E, MATCH($A37, Scenarios!$A:$A, 0))=0, IF(LEFT(INDEX(Scenarios!$P:$P, MATCH($A37, Scenarios!$A:$A, 0)),4)="Arts", Parameters_Public!$C$28, IF(LEFT(INDEX(Scenarios!$P:$P, MATCH($A37, Scenarios!$A:$A, 0)),5)="Innov", Parameters_Public!$C$29, 0)), 0), 0) -> 0 | G37: =IF($B37="FY2026", INDEX(Receiving_Capacity!$L:$L, MATCH($A37, Receiving_Capacity!$A:$A, 0)), 0) -> 0 | H37: =SUM(D37:G37) -> 0
A38: =Scenarios!$A$8 -> A_Repurpose_Both_lease | B38: FY2030 | C38: =INDEX(Scenarios!$D:$D, MATCH($A38, Scenarios!$A:$A, 0)) + INDEX(Scenarios!$E:$E, MATCH($A38, Scenarios!$A:$A, 0)) -> 2 | D38: =IF($B38="FY2026",$C38*IF(INDEX(Scenarios!$N:$N, MATCH($A38, Scenarios!$A:$A, 0))="lease", Parameters_Public!$C$31, Parameters_Public!$C$27),0) -> 0 | E38: =IF($B38="FY2026", IF(INDEX(Scenarios!$D:$D, MATCH($A38, Scenarios!$A:$A, 0))=0, IF(LEFT(INDEX(Scenarios!$O:$O, MATCH($A38, Scenarios!$A:$A, 0)),4)="Arts", Parameters_Public!$C$28, IF(LEFT(INDEX(Scenarios!$O:$O, MATCH($A38, Scenarios!$A:$A, 0)),5)="Innov", Parameters_Public!$C$29, 0)), 0), 0) -> 0 | F38: =IF($B38="FY2026", IF(INDEX(Scenarios!$E:$E, MATCH($A38, Scenarios!$A:$A, 0))=0, IF(LEFT(INDEX(Scenarios!$P:$P, MATCH($A38, Scenarios!$A:$A, 0)),4)="Arts", Parameters_Public!$C$28, IF(LEFT(INDEX(Scenarios!$P:$P, MATCH($A38, Scenarios!$A:$A, 0)),5)="Innov", Parameters_Public!$C$29, 0)), 0), 0) -> 0 | G38: =IF($B38="FY2026", INDEX(Receiving_Capacity!$L:$L, MATCH($A38, Receiving_Capacity!$A:$A, 0)), 0) -> 0 | H38: =SUM(D38:G38) -> 0
A39: =Scenarios!$A$9 -> A_Repurpose_Both_ops | B39: FY2026 | C39: =INDEX(Scenarios!$D:$D, MATCH($A39, Scenarios!$A:$A, 0)) + INDEX(Scenarios!$E:$E, MATCH($A39, Scenarios!$A:$A, 0)) -> 2 | D39: =IF($B39="FY2026",$C39*IF(INDEX(Scenarios!$N:$N, MATCH($A39, Scenarios!$A:$A, 0))="lease", Parameters_Public!$C$31, Parameters_Public!$C$27),0) -> 2400000 | E39: =IF($B39="FY2026", IF(INDEX(Scenarios!$D:$D, MATCH($A39, Scenarios!$A:$A, 0))=0, IF(LEFT(INDEX(Scenarios!$O:$O, MATCH($A39, Scenarios!$A:$A, 0)),4)="Arts", Parameters_Public!$C$28, IF(LEFT(INDEX(Scenarios!$O:$O, MATCH($A39, Scenarios!$A:$A, 0)),5)="Innov", Parameters_Public!$C$29, 0)), 0), 0) -> 0 | F39: =IF($B39="FY2026", IF(INDEX(Scenarios!$E:$E, MATCH($A39, Scenarios!$A:$A, 0))=0, IF(LEFT(INDEX(Scenarios!$P:$P, MATCH($A39, Scenarios!$A:$A, 0)),4)="Arts", Parameters_Public!$C$28, IF(LEFT(INDEX(Scenarios!$P:$P, MATCH($A39, Scenarios!$A:$A, 0)),5)="Innov", Parameters_Public!$C$29, 0)), 0), 0) -> 0 | G39: =IF($B39="FY2026", INDEX(Receiving_Capacity!$L:$L, MATCH($A39, Receiving_Capacity!$A:$A, 0)), 0) -> 714480 | H39: =SUM(D39:G39) -> 3114480
A40: =Scenarios!$A$9 -> A_Repurpose_Both_ops | B40: FY2027 | C40: =INDEX(Scenarios!$D:$D, MATCH($A40, Scenarios!$A:$A, 0)) + INDEX(Scenarios!$E:$E, MATCH($A40, Scenarios!$A:$A, 0)) -> 2 | D40: =IF($B40="FY2026",$C40*IF(INDEX(Scenarios!$N:$N, MATCH($A40, Scenarios!$A:$A, 0))="lease", Parameters_Public!$C$31, Parameters_Public!$C$27),0) -> 0 | E40: =IF($B40="FY2026", IF(INDEX(Scenarios!$D:$D, MATCH($A40, Scenarios!$A:$A, 0))=0, IF(LEFT(INDEX(Scenarios!$O:$O, MATCH($A40, Scenarios!$A:$A, 0)),4)="Arts", Parameters_Public!$C$28, IF(LEFT(INDEX(Scenarios!$O:$O, MATCH($A40, Scenarios!$A:$A, 0)),5)="Innov", Parameters_Public!$C$29, 0)), 0), 0) -> 0 | F40: =IF($B40="FY2026", IF(INDEX(Scenarios!$E:$E, MATCH($A40, Scenarios!$A:$A, 0))=0, IF(LEFT(INDEX(Scenarios!$P:$P, MATCH($A40, Scenarios!$A:$A, 0)),4)="Arts", Parameters_Public!$C$28, IF(LEFT(INDEX(Scenarios!$P:$P, MATCH($A40, Scenarios!$A:$A, 0)),5)="Innov", Parameters_Public!$C$29, 0)), 0), 0) -> 0 | G40: =IF($B40="FY2026", INDEX(Receiving_Capacity!$L:$L, MATCH($A40, Receiving_Capacity!$A:$A, 0)), 0) -> 0 | H40: =SUM(D40:G40) -> 0
A41: =Scenarios!$A$9 -> A_Repurpose_Both_ops | B41: FY2028 | C41: =INDEX(Scenarios!$D:$D, MATCH($A41, Scenarios!$A:$A, 0)) + INDEX(Scenarios!$E:$E, MATCH($A41, Scenarios!$A:$A, 0)) -> 2 | D41: =IF($B41="FY2026",$C41*IF(INDEX(Scenarios!$N:$N, MATCH($A41, Scenarios!$A:$A, 0))="lease", Parameters_Public!$C$31, Parameters_Public!$C$27),0) -> 0 | E41: =IF($B41="FY2026", IF(INDEX(Scenarios!$D:$D, MATCH($A41, Scenarios!$A:$A, 0))=0, IF(LEFT(INDEX(Scenarios!$O:$O, MATCH($A41, Scenarios!$A:$A, 0)),4)="Arts", Parameters_Public!$C$28, IF(LEFT(INDEX(Scenarios!$O:$O, MATCH($A41, Scenarios!$A:$A, 0)),5)="Innov", Parameters_Public!$C$29, 0)), 0), 0) -> 0 | F41: =IF($B41="FY2026", IF(INDEX(Scenarios!$E:$E, MATCH($A41, Scenarios!$A:$A, 0))=0, IF(LEFT(INDEX(Scenarios!$P:$P, MATCH($A41, Scenarios!$A:$A, 0)),4)="Arts", Parameters_Public!$C$28, IF(LEFT(INDEX(Scenarios!$P:$P, MATCH($A41, Scenarios!$A:$A, 0)),5)="Innov", Parameters_Public!$C$29, 0)), 0), 0) -> 0 | G41: =IF($B41="FY2026", INDEX(Receiving_Capacity!$L:$L, MATCH($A41, Receiving_Capacity!$A:$A, 0)), 0) -> 0 | H41: =SUM(D41:G41) -> 0
A42: =Scenarios!$A$9 -> A_Repurpose_Both_ops | B42: FY2029 | C42: =INDEX(Scenarios!$D:$D, MATCH($A42, Scenarios!$A:$A, 0)) + INDEX(Scenarios!$E:$E, MATCH($A42, Scenarios!$A:$A, 0)) -> 2 | D42: =IF($B42="FY2026",$C42*IF(INDEX(Scenarios!$N:$N, MATCH($A42, Scenarios!$A:$A, 0))="lease", Parameters_Public!$C$31, Parameters_Public!$C$27),0) -> 0 | E42: =IF($B42="FY2026", IF(INDEX(Scenarios!$D:$D, MATCH($A42, Scenarios!$A:$A, 0))=0, IF(LEFT(INDEX(Scenarios!$O:$O, MATCH($A42, Scenarios!$A:$A, 0)),4)="Arts", Parameters_Public!$C$28, IF(LEFT(INDEX(Scenarios!$O:$O, MATCH($A42, Scenarios!$A:$A, 0)),5)="Innov", Parameters_Public!$C$29, 0)), 0), 0) -> 0 | F42: =IF($B42="FY2026", IF(INDEX(Scenarios!$E:$E, MATCH($A42, Scenarios!$A:$A, 0))=0, IF(LEFT(INDEX(Scenarios!$P:$P, MATCH($A42, Scenarios!$A:$A, 0)),4)="Arts", Parameters_Public!$C$28, IF(LEFT(INDEX(Scenarios!$P:$P, MATCH($A42, Scenarios!$A:$A, 0)),5)="Innov", Parameters_Public!$C$29, 0)), 0), 0) -> 0 | G42: =IF($B42="FY2026", INDEX(Receiving_Capacity!$L:$L, MATCH($A42, Receiving_Capacity!$A:$A, 0)), 0) -> 0 | H42: =SUM(D42:G42) -> 0
A43: =Scenarios!$A$9 -> A_Repurpose_Both_ops | B43: FY2030 | C43: =INDEX(Scenarios!$D:$D, MATCH($A43, Scenarios!$A:$A, 0)) + INDEX(Scenarios!$E:$E, MATCH($A43, Scenarios!$A:$A, 0)) -> 2 | D43: =IF($B43="FY2026",$C43*IF(INDEX(Scenarios!$N:$N, MATCH($A43, Scenarios!$A:$A, 0))="lease", Parameters_Public!$C$31, Parameters_Public!$C$27),0) -> 0 | E43: =IF($B43="FY2026", IF(INDEX(Scenarios!$D:$D, MATCH($A43, Scenarios!$A:$A, 0))=0, IF(LEFT(INDEX(Scenarios!$O:$O, MATCH($A43, Scenarios!$A:$A, 0)),4)="Arts", Parameters_Public!$C$28, IF(LEFT(INDEX(Scenarios!$O:$O, MATCH($A43, Scenarios!$A:$A, 0)),5)="Innov", Parameters_Public!$C$29, 0)), 0), 0) -> 0 | F43: =IF($B43="FY2026", IF(INDEX(Scenarios!$E:$E, MATCH($A43, Scenarios!$A:$A, 0))=0, IF(LEFT(INDEX(Scenarios!$P:$P, MATCH($A43, Scenarios!$A:$A, 0)),4)="Arts", Parameters_Public!$C$28, IF(LEFT(INDEX(Scenarios!$P:$P, MATCH($A43, Scenarios!$A:$A, 0)),5)="Innov", Parameters_Public!$C$29, 0)), 0), 0) -> 0 | G43: =IF($B43="FY2026", INDEX(Receiving_Capacity!$L:$L, MATCH($A43, Receiving_Capacity!$A:$A, 0)), 0) -> 0 | H43: =SUM(D43:G43) -> 0
A44: =Scenarios!$A$10 -> B_Repurpose_Echo_lease_PimaTargets | B44: FY2026 | C44: =INDEX(Scenarios!$D:$D, MATCH($A44, Scenarios!$A:$A, 0)) + INDEX(Scenarios!$E:$E, MATCH($A44, Scenarios!$A:$A, 0)) -> 1 | D44: =IF($B44="FY2026",$C44*IF(INDEX(Scenarios!$N:$N, MATCH($A44, Scenarios!$A:$A, 0))="lease", Parameters_Public!$C$31, Parameters_Public!$C$27),0) -> 800000 | E44: =IF($B44="FY2026", IF(INDEX(Scenarios!$D:$D, MATCH($A44, Scenarios!$A:$A, 0))=0, IF(LEFT(INDEX(Scenarios!$O:$O, MATCH($A44, Scenarios!$A:$A, 0)),4)="Arts", Parameters_Public!$C$28, IF(LEFT(INDEX(Scenarios!$O:$O, MATCH($A44, Scenarios!$A:$A, 0)),5)="Innov", Parameters_Public!$C$29, 0)), 0), 0) -> 0 | F44: =IF($B44="FY2026", IF(INDEX(Scenarios!$E:$E, MATCH($A44, Scenarios!$A:$A, 0))=0, IF(LEFT(INDEX(Scenarios!$P:$P, MATCH($A44, Scenarios!$A:$A, 0)),4)="Arts", Parameters_Public!$C$28, IF(LEFT(INDEX(Scenarios!$P:$P, MATCH($A44, Scenarios!$A:$A, 0)),5)="Innov", Parameters_Public!$C$29, 0)), 0), 0) -> 0 | G44: =IF($B44="FY2026", INDEX(Receiving_Capacity!$L:$L, MATCH($A44, Receiving_Capacity!$A:$A, 0)), 0) -> 0 | H44: =SUM(D44:G44) -> 800000
A45: =Scenarios!$A$10 -> B_Repurpose_Echo_lease_PimaTargets | B45: FY2027 | C45: =INDEX(Scenarios!$D:$D, MATCH($A45, Scenarios!$A:$A, 0)) + INDEX(Scenarios!$E:$E, MATCH($A45, Scenarios!$A:$A, 0)) -> 1 | D45: =IF($B45="FY2026",$C45*IF(INDEX(Scenarios!$N:$N, MATCH($A45, Scenarios!$A:$A, 0))="lease", Parameters_Public!$C$31, Parameters_Public!$C$27),0) -> 0 | E45: =IF($B45="FY2026", IF(INDEX(Scenarios!$D:$D, MATCH($A45, Scenarios!$A:$A, 0))=0, IF(LEFT(INDEX(Scenarios!$O:$O, MATCH($A45, Scenarios!$A:$A, 0)),4)="Arts", Parameters_Public!$C$28, IF(LEFT(INDEX(Scenarios!$O:$O, MATCH($A45, Scenarios!$A:$A, 0)),5)="Innov", Parameters_Public!$C$29, 0)), 0), 0) -> 0 | F45: =IF($B45="FY2026", IF(INDEX(Scenarios!$E:$E, MATCH($A45, Scenarios!$A:$A, 0))=0, IF(LEFT(INDEX(Scenarios!$P:$P, MATCH($A45, Scenarios!$A:$A, 0)),4)="Arts", Parameters_Public!$C$28, IF(LEFT(INDEX(Scenarios!$P:$P, MATCH($A45, Scenarios!$A:$A, 0)),5)="Innov", Parameters_Public!$C$29, 0)), 0), 0) -> 0 | G45: =IF($B45="FY2026", INDEX(Receiving_Capacity!$L:$L, MATCH($A45, Receiving_Capacity!$A:$A, 0)), 0) -> 0 | H45: =SUM(D45:G45) -> 0
A46: =Scenarios!$A$10 -> B_Repurpose_Echo_lease_PimaTargets | B46: FY2028 | C46: =INDEX(Scenarios!$D:$D, MATCH($A46, Scenarios!$A:$A, 0)) + INDEX(Scenarios!$E:$E, MATCH($A46, Scenarios!$A:$A, 0)) -> 1 | D46: =IF($B46="FY2026",$C46*IF(INDEX(Scenarios!$N:$N, MATCH($A46, Scenarios!$A:$A, 0))="lease", Parameters_Public!$C$31, Parameters_Public!$C$27),0) -> 0 | E46: =IF($B46="FY2026", IF(INDEX(Scenarios!$D:$D, MATCH($A46, Scenarios!$A:$A, 0))=0, IF(LEFT(INDEX(Scenarios!$O:$O, MATCH($A46, Scenarios!$A:$A, 0)),4)="Arts", Parameters_Public!$C$28, IF(LEFT(INDEX(Scenarios!$O:$O, MATCH($A46, Scenarios!$A:$A, 0)),5)="Innov", Parameters_Public!$C$29, 0)), 0), 0) -> 0 | F46: =IF($B46="FY2026", IF(INDEX(Scenarios!$E:$E, MATCH($A46, Scenarios!$A:$A, 0))=0, IF(LEFT(INDEX(Scenarios!$P:$P, MATCH($A46, Scenarios!$A:$A, 0)),4)="Arts", Parameters_Public!$C$28, IF(LEFT(INDEX(Scenarios!$P:$P, MATCH($A46, Scenarios!$A:$A, 0)),5)="Innov", Parameters_Public!$C$29, 0)), 0), 0) -> 0 | G46: =IF($B46="FY2026", INDEX(Receiving_Capacity!$L:$L, MATCH($A46, Receiving_Capacity!$A:$A, 0)), 0) -> 0 | H46: =SUM(D46:G46) -> 0
A47: =Scenarios!$A$10 -> B_Repurpose_Echo_lease_PimaTargets | B47: FY2029 | C47: =INDEX(Scenarios!$D:$D, MATCH($A47, Scenarios!$A:$A, 0)) + INDEX(Scenarios!$E:$E, MATCH($A47, Scenarios!$A:$A, 0)) -> 1 | D47: =IF($B47="FY2026",$C47*IF(INDEX(Scenarios!$N:$N, MATCH($A47, Scenarios!$A:$A, 0))="lease", Parameters_Public!$C$31, Parameters_Public!$C$27),0) -> 0 | E47: =IF($B47="FY2026", IF(INDEX(Scenarios!$D:$D, MATCH($A47, Scenarios!$A:$A, 0))=0, IF(LEFT(INDEX(Scenarios!$O:$O, MATCH($A47, Scenarios!$A:$A, 0)),4)="Arts", Parameters_Public!$C$28, IF(LEFT(INDEX(Scenarios!$O:$O, MATCH($A47, Scenarios!$A:$A, 0)),5)="Innov", Parameters_Public!$C$29, 0)), 0), 0) -> 0 | F47: =IF($B47="FY2026", IF(INDEX(Scenarios!$E:$E, MATCH($A47, Scenarios!$A:$A, 0))=0, IF(LEFT(INDEX(Scenarios!$P:$P, MATCH($A47, Scenarios!$A:$A, 0)),4)="Arts", Parameters_Public!$C$28, IF(LEFT(INDEX(Scenarios!$P:$P, MATCH($A47, Scenarios!$A:$A, 0)),5)="Innov", Parameters_Public!$C$29, 0)), 0), 0) -> 0 | G47: =IF($B47="FY2026", INDEX(Receiving_Capacity!$L:$L, MATCH($A47, Receiving_Capacity!$A:$A, 0)), 0) -> 0 | H47: =SUM(D47:G47) -> 0
A48: =Scenarios!$A$10 -> B_Repurpose_Echo_lease_PimaTargets | B48: FY2030 | C48: =INDEX(Scenarios!$D:$D, MATCH($A48, Scenarios!$A:$A, 0)) + INDEX(Scenarios!$E:$E, MATCH($A48, Scenarios!$A:$A, 0)) -> 1 | D48: =IF($B48="FY2026",$C48*IF(INDEX(Scenarios!$N:$N, MATCH($A48, Scenarios!$A:$A, 0))="lease", Parameters_Public!$C$31, Parameters_Public!$C$27),0) -> 0 | E48: =IF($B48="FY2026", IF(INDEX(Scenarios!$D:$D, MATCH($A48, Scenarios!$A:$A, 0))=0, IF(LEFT(INDEX(Scenarios!$O:$O, MATCH($A48, Scenarios!$A:$A, 0)),4)="Arts", Parameters_Public!$C$28, IF(LEFT(INDEX(Scenarios!$O:$O, MATCH($A48, Scenarios!$A:$A, 0)),5)="Innov", Parameters_Public!$C$29, 0)), 0), 0) -> 0 | F48: =IF($B48="FY2026", IF(INDEX(Scenarios!$E:$E, MATCH($A48, Scenarios!$A:$A, 0))=0, IF(LEFT(INDEX(Scenarios!$P:$P, MATCH($A48, Scenarios!$A:$A, 0)),4)="Arts", Parameters_Public!$C$28, IF(LEFT(INDEX(Scenarios!$P:$P, MATCH($A48, Scenarios!$A:$A, 0)),5)="Innov", Parameters_Public!$C$29, 0)), 0), 0) -> 0 | G48: =IF($B48="FY2026", INDEX(Receiving_Capacity!$L:$L, MATCH($A48, Receiving_Capacity!$A:$A, 0)), 0) -> 0 | H48: =SUM(D48:G48) -> 0
A49: =Scenarios!$A$11 -> B_Repurpose_Echo_ops_PimaTargets | B49: FY2026 | C49: =INDEX(Scenarios!$D:$D, MATCH($A49, Scenarios!$A:$A, 0)) + INDEX(Scenarios!$E:$E, MATCH($A49, Scenarios!$A:$A, 0)) -> 1 | D49: =IF($B49="FY2026",$C49*IF(INDEX(Scenarios!$N:$N, MATCH($A49, Scenarios!$A:$A, 0))="lease", Parameters_Public!$C$31, Parameters_Public!$C$27),0) -> 1200000 | E49: =IF($B49="FY2026", IF(INDEX(Scenarios!$D:$D, MATCH($A49, Scenarios!$A:$A, 0))=0, IF(LEFT(INDEX(Scenarios!$O:$O, MATCH($A49, Scenarios!$A:$A, 0)),4)="Arts", Parameters_Public!$C$28, IF(LEFT(INDEX(Scenarios!$O:$O, MATCH($A49, Scenarios!$A:$A, 0)),5)="Innov", Parameters_Public!$C$29, 0)), 0), 0) -> 0 | F49: =IF($B49="FY2026", IF(INDEX(Scenarios!$E:$E, MATCH($A49, Scenarios!$A:$A, 0))=0, IF(LEFT(INDEX(Scenarios!$P:$P, MATCH($A49, Scenarios!$A:$A, 0)),4)="Arts", Parameters_Public!$C$28, IF(LEFT(INDEX(Scenarios!$P:$P, MATCH($A49, Scenarios!$A:$A, 0)),5)="Innov", Parameters_Public!$C$29, 0)), 0), 0) -> 0 | G49: =IF($B49="FY2026", INDEX(Receiving_Capacity!$L:$L, MATCH($A49, Receiving_Capacity!$A:$A, 0)), 0) -> 0 | H49: =SUM(D49:G49) -> 1200000
A50: =Scenarios!$A$11 -> B_Repurpose_Echo_ops_PimaTargets | B50: FY2027 | C50: =INDEX(Scenarios!$D:$D, MATCH($A50, Scenarios!$A:$A, 0)) + INDEX(Scenarios!$E:$E, MATCH($A50, Scenarios!$A:$A, 0)) -> 1 | D50: =IF($B50="FY2026",$C50*IF(INDEX(Scenarios!$N:$N, MATCH($A50, Scenarios!$A:$A, 0))="lease", Parameters_Public!$C$31, Parameters_Public!$C$27),0) -> 0 | E50: =IF($B50="FY2026", IF(INDEX(Scenarios!$D:$D, MATCH($A50, Scenarios!$A:$A, 0))=0, IF(LEFT(INDEX(Scenarios!$O:$O, MATCH($A50, Scenarios!$A:$A, 0)),4)="Arts", Parameters_Public!$C$28, IF(LEFT(INDEX(Scenarios!$O:$O, MATCH($A50, Scenarios!$A:$A, 0)),5)="Innov", Parameters_Public!$C$29, 0)), 0), 0) -> 0 | F50: =IF($B50="FY2026", IF(INDEX(Scenarios!$E:$E, MATCH($A50, Scenarios!$A:$A, 0))=0, IF(LEFT(INDEX(Scenarios!$P:$P, MATCH($A50, Scenarios!$A:$A, 0)),4)="Arts", Parameters_Public!$C$28, IF(LEFT(INDEX(Scenarios!$P:$P, MATCH($A50, Scenarios!$A:$A, 0)),5)="Innov", Parameters_Public!$C$29, 0)), 0), 0) -> 0 | G50: =IF($B50="FY2026", INDEX(Receiving_Capacity!$L:$L, MATCH($A50, Receiving_Capacity!$A:$A, 0)), 0) -> 0 | H50: =SUM(D50:G50) -> 0
A51: =Scenarios!$A$11 -> B_Repurpose_Echo_ops_PimaTargets | B51: FY2028 | C51: =INDEX(Scenarios!$D:$D, MATCH($A51, Scenarios!$A:$A, 0)) + INDEX(Scenarios!$E:$E, MATCH($A51, Scenarios!$A:$A, 0)) -> 1 | D51: =IF($B51="FY2026",$C51*IF(INDEX(Scenarios!$N:$N, MATCH($A51, Scenarios!$A:$A, 0))="lease", Parameters_Public!$C$31, Parameters_Public!$C$27),0) -> 0 | E51: =IF($B51="FY2026", IF(INDEX(Scenarios!$D:$D, MATCH($A51, Scenarios!$A:$A, 0))=0, IF(LEFT(INDEX(Scenarios!$O:$O, MATCH($A51, Scenarios!$A:$A, 0)),4)="Arts", Parameters_Public!$C$28, IF(LEFT(INDEX(Scenarios!$O:$O, MATCH($A51, Scenarios!$A:$A, 0)),5)="Innov", Parameters_Public!$C$29, 0)), 0), 0) -> 0 | F51: =IF($B51="FY2026", IF(INDEX(Scenarios!$E:$E, MATCH($A51, Scenarios!$A:$A, 0))=0, IF(LEFT(INDEX(Scenarios!$P:$P, MATCH($A51, Scenarios!$A:$A, 0)),4)="Arts", Parameters_Public!$C$28, IF(LEFT(INDEX(Scenarios!$P:$P, MATCH($A51, Scenarios!$A:$A, 0)),5)="Innov", Parameters_Public!$C$29, 0)), 0), 0) -> 0 | G51: =IF($B51="FY2026", INDEX(Receiving_Capacity!$L:$L, MATCH($A51, Receiving_Capacity!$A:$A, 0)), 0) -> 0 | H51: =SUM(D51:G51) -> 0
A52: =Scenarios!$A$11 -> B_Repurpose_Echo_ops_PimaTargets | B52: FY2029 | C52: =INDEX(Scenarios!$D:$D, MATCH($A52, Scenarios!$A:$A, 0)) + INDEX(Scenarios!$E:$E, MATCH($A52, Scenarios!$A:$A, 0)) -> 1 | D52: =IF($B52="FY2026",$C52*IF(INDEX(Scenarios!$N:$N, MATCH($A52, Scenarios!$A:$A, 0))="lease", Parameters_Public!$C$31, Parameters_Public!$C$27),0) -> 0 | E52: =IF($B52="FY2026", IF(INDEX(Scenarios!$D:$D, MATCH($A52, Scenarios!$A:$A, 0))=0, IF(LEFT(INDEX(Scenarios!$O:$O, MATCH($A52, Scenarios!$A:$A, 0)),4)="Arts", Parameters_Public!$C$28, IF(LEFT(INDEX(Scenarios!$O:$O, MATCH($A52, Scenarios!$A:$A, 0)),5)="Innov", Parameters_Public!$C$29, 0)), 0), 0) -> 0 | F52: =IF($B52="FY2026", IF(INDEX(Scenarios!$E:$E, MATCH($A52, Scenarios!$A:$A, 0))=0, IF(LEFT(INDEX(Scenarios!$P:$P, MATCH($A52, Scenarios!$A:$A, 0)),4)="Arts", Parameters_Public!$C$28, IF(LEFT(INDEX(Scenarios!$P:$P, MATCH($A52, Scenarios!$A:$A, 0)),5)="Innov", Parameters_Public!$C$29, 0)), 0), 0) -> 0 | G52: =IF($B52="FY2026", INDEX(Receiving_Capacity!$L:$L, MATCH($A52, Receiving_Capacity!$A:$A, 0)), 0) -> 0 | H52: =SUM(D52:G52) -> 0
A53: =Scenarios!$A$11 -> B_Repurpose_Echo_ops_PimaTargets | B53: FY2030 | C53: =INDEX(Scenarios!$D:$D, MATCH($A53, Scenarios!$A:$A, 0)) + INDEX(Scenarios!$E:$E, MATCH($A53, Scenarios!$A:$A, 0)) -> 1 | D53: =IF($B53="FY2026",$C53*IF(INDEX(Scenarios!$N:$N, MATCH($A53, Scenarios!$A:$A, 0))="lease", Parameters_Public!$C$31, Parameters_Public!$C$27),0) -> 0 | E53: =IF($B53="FY2026", IF(INDEX(Scenarios!$D:$D, MATCH($A53, Scenarios!$A:$A, 0))=0, IF(LEFT(INDEX(Scenarios!$O:$O, MATCH($A53, Scenarios!$A:$A, 0)),4)="Arts", Parameters_Public!$C$28, IF(LEFT(INDEX(Scenarios!$O:$O, MATCH($A53, Scenarios!$A:$A, 0)),5)="Innov", Parameters_Public!$C$29, 0)), 0), 0) -> 0 | F53: =IF($B53="FY2026", IF(INDEX(Scenarios!$E:$E, MATCH($A53, Scenarios!$A:$A, 0))=0, IF(LEFT(INDEX(Scenarios!$P:$P, MATCH($A53, Scenarios!$A:$A, 0)),4)="Arts", Parameters_Public!$C$28, IF(LEFT(INDEX(Scenarios!$P:$P, MATCH($A53, Scenarios!$A:$A, 0)),5)="Innov", Parameters_Public!$C$29, 0)), 0), 0) -> 0 | G53: =IF($B53="FY2026", INDEX(Receiving_Capacity!$L:$L, MATCH($A53, Receiving_Capacity!$A:$A, 0)), 0) -> 0 | H53: =SUM(D53:G53) -> 0
A54: =Scenarios!$A$12 -> C_Repurpose_Pima_lease_EchoGHub_EchoTargets | B54: FY2026 | C54: =INDEX(Scenarios!$D:$D, MATCH($A54, Scenarios!$A:$A, 0)) + INDEX(Scenarios!$E:$E, MATCH($A54, Scenarios!$A:$A, 0)) -> 1 | D54: =IF($B54="FY2026",$C54*IF(INDEX(Scenarios!$N:$N, MATCH($A54, Scenarios!$A:$A, 0))="lease", Parameters_Public!$C$31, Parameters_Public!$C$27),0) -> 800000 | E54: =IF($B54="FY2026", IF(INDEX(Scenarios!$D:$D, MATCH($A54, Scenarios!$A:$A, 0))=0, IF(LEFT(INDEX(Scenarios!$O:$O, MATCH($A54, Scenarios!$A:$A, 0)),4)="Arts", Parameters_Public!$C$28, IF(LEFT(INDEX(Scenarios!$O:$O, MATCH($A54, Scenarios!$A:$A, 0)),5)="Innov", Parameters_Public!$C$29, 0)), 0), 0) -> 800000 | F54: =IF($B54="FY2026", IF(INDEX(Scenarios!$E:$E, MATCH($A54, Scenarios!$A:$A, 0))=0, IF(LEFT(INDEX(Scenarios!$P:$P, MATCH($A54, Scenarios!$A:$A, 0)),4)="Arts", Parameters_Public!$C$28, IF(LEFT(INDEX(Scenarios!$P:$P, MATCH($A54, Scenarios!$A:$A, 0)),5)="Innov", Parameters_Public!$C$29, 0)), 0), 0) -> 0 | G54: =IF($B54="FY2026", INDEX(Receiving_Capacity!$L:$L, MATCH($A54, Receiving_Capacity!$A:$A, 0)), 0) -> 0 | H54: =SUM(D54:G54) -> 1600000
A55: =Scenarios!$A$12 -> C_Repurpose_Pima_lease_EchoGHub_EchoTargets | B55: FY2027 | C55: =INDEX(Scenarios!$D:$D, MATCH($A55, Scenarios!$A:$A, 0)) + INDEX(Scenarios!$E:$E, MATCH($A55, Scenarios!$A:$A, 0)) -> 1 | D55: =IF($B55="FY2026",$C55*IF(INDEX(Scenarios!$N:$N, MATCH($A55, Scenarios!$A:$A, 0))="lease", Parameters_Public!$C$31, Parameters_Public!$C$27),0) -> 0 | E55: =IF($B55="FY2026", IF(INDEX(Scenarios!$D:$D, MATCH($A55, Scenarios!$A:$A, 0))=0, IF(LEFT(INDEX(Scenarios!$O:$O, MATCH($A55, Scenarios!$A:$A, 0)),4)="Arts", Parameters_Public!$C$28, IF(LEFT(INDEX(Scenarios!$O:$O, MATCH($A55, Scenarios!$A:$A, 0)),5)="Innov", Parameters_Public!$C$29, 0)), 0), 0) -> 0 | F55: =IF($B55="FY2026", IF(INDEX(Scenarios!$E:$E, MATCH($A55, Scenarios!$A:$A, 0))=0, IF(LEFT(INDEX(Scenarios!$P:$P, MATCH($A55, Scenarios!$A:$A, 0)),4)="Arts", Parameters_Public!$C$28, IF(LEFT(INDEX(Scenarios!$P:$P, MATCH($A55, Scenarios!$A:$A, 0)),5)="Innov", Parameters_Public!$C$29, 0)), 0), 0) -> 0 | G55: =IF($B55="FY2026", INDEX(Receiving_Capacity!$L:$L, MATCH($A55, Receiving_Capacity!$A:$A, 0)), 0) -> 0 | H55: =SUM(D55:G55) -> 0
A56: =Scenarios!$A$12 -> C_Repurpose_Pima_lease_EchoGHub_EchoTargets | B56: FY2028 | C56: =INDEX(Scenarios!$D:$D, MATCH($A56, Scenarios!$A:$A, 0)) + INDEX(Scenarios!$E:$E, MATCH($A56, Scenarios!$A:$A, 0)) -> 1 | D56: =IF($B56="FY2026",$C56*IF(INDEX(Scenarios!$N:$N, MATCH($A56, Scenarios!$A:$A, 0))="lease", Parameters_Public!$C$31, Parameters_Public!$C$27),0) -> 0 | E56: =IF($B56="FY2026", IF(INDEX(Scenarios!$D:$D, MATCH($A56, Scenarios!$A:$A, 0))=0, IF(LEFT(INDEX(Scenarios!$O:$O, MATCH($A56, Scenarios!$A:$A, 0)),4)="Arts", Parameters_Public!$C$28, IF(LEFT(INDEX(Scenarios!$O:$O, MATCH($A56, Scenarios!$A:$A, 0)),5)="Innov", Parameters_Public!$C$29, 0)), 0), 0) -> 0 | F56: =IF($B56="FY2026", IF(INDEX(Scenarios!$E:$E, MATCH($A56, Scenarios!$A:$A, 0))=0, IF(LEFT(INDEX(Scenarios!$P:$P, MATCH($A56, Scenarios!$A:$A, 0)),4)="Arts", Parameters_Public!$C$28, IF(LEFT(INDEX(Scenarios!$P:$P, MATCH($A56, Scenarios!$A:$A, 0)),5)="Innov", Parameters_Public!$C$29, 0)), 0), 0) -> 0 | G56: =IF($B56="FY2026", INDEX(Receiving_Capacity!$L:$L, MATCH($A56, Receiving_Capacity!$A:$A, 0)), 0) -> 0 | H56: =SUM(D56:G56) -> 0
A57: =Scenarios!$A$12 -> C_Repurpose_Pima_lease_EchoGHub_EchoTargets | B57: FY2029 | C57: =INDEX(Scenarios!$D:$D, MATCH($A57, Scenarios!$A:$A, 0)) + INDEX(Scenarios!$E:$E, MATCH($A57, Scenarios!$A:$A, 0)) -> 1 | D57: =IF($B57="FY2026",$C57*IF(INDEX(Scenarios!$N:$N, MATCH($A57, Scenarios!$A:$A, 0))="lease", Parameters_Public!$C$31, Parameters_Public!$C$27),0) -> 0 | E57: =IF($B57="FY2026", IF(INDEX(Scenarios!$D:$D, MATCH($A57, Scenarios!$A:$A, 0))=0, IF(LEFT(INDEX(Scenarios!$O:$O, MATCH($A57, Scenarios!$A:$A, 0)),4)="Arts", Parameters_Public!$C$28, IF(LEFT(INDEX(Scenarios!$O:$O, MATCH($A57, Scenarios!$A:$A, 0)),5)="Innov", Parameters_Public!$C$29, 0)), 0), 0) -> 0 | F57: =IF($B57="FY2026", IF(INDEX(Scenarios!$E:$E, MATCH($A57, Scenarios!$A:$A, 0))=0, IF(LEFT(INDEX(Scenarios!$P:$P, MATCH($A57, Scenarios!$A:$A, 0)),4)="Arts", Parameters_Public!$C$28, IF(LEFT(INDEX(Scenarios!$P:$P, MATCH($A57, Scenarios!$A:$A, 0)),5)="Innov", Parameters_Public!$C$29, 0)), 0), 0) -> 0 | G57: =IF($B57="FY2026", INDEX(Receiving_Capacity!$L:$L, MATCH($A57, Receiving_Capacity!$A:$A, 0)), 0) -> 0 | H57: =SUM(D57:G57) -> 0
A58: =Scenarios!$A$12 -> C_Repurpose_Pima_lease_EchoGHub_EchoTargets | B58: FY2030 | C58: =INDEX(Scenarios!$D:$D, MATCH($A58, Scenarios!$A:$A, 0)) + INDEX(Scenarios!$E:$E, MATCH($A58, Scenarios!$A:$A, 0)) -> 1 | D58: =IF($B58="FY2026",$C58*IF(INDEX(Scenarios!$N:$N, MATCH($A58, Scenarios!$A:$A, 0))="lease", Parameters_Public!$C$31, Parameters_Public!$C$27),0) -> 0 | E58: =IF($B58="FY2026", IF(INDEX(Scenarios!$D:$D, MATCH($A58, Scenarios!$A:$A, 0))=0, IF(LEFT(INDEX(Scenarios!$O:$O, MATCH($A58, Scenarios!$A:$A, 0)),4)="Arts", Parameters_Public!$C$28, IF(LEFT(INDEX(Scenarios!$O:$O, MATCH($A58, Scenarios!$A:$A, 0)),5)="Innov", Parameters_Public!$C$29, 0)), 0), 0) -> 0 | F58: =IF($B58="FY2026", IF(INDEX(Scenarios!$E:$E, MATCH($A58, Scenarios!$A:$A, 0))=0, IF(LEFT(INDEX(Scenarios!$P:$P, MATCH($A58, Scenarios!$A:$A, 0)),4)="Arts", Parameters_Public!$C$28, IF(LEFT(INDEX(Scenarios!$P:$P, MATCH($A58, Scenarios!$A:$A, 0)),5)="Innov", Parameters_Public!$C$29, 0)), 0), 0) -> 0 | G58: =IF($B58="FY2026", INDEX(Receiving_Capacity!$L:$L, MATCH($A58, Receiving_Capacity!$A:$A, 0)), 0) -> 0 | H58: =SUM(D58:G58) -> 0
A59: =Scenarios!$A$13 -> C_Repurpose_Pima_ops_EchoGHub_EchoTargets | B59: FY2026 | C59: =INDEX(Scenarios!$D:$D, MATCH($A59, Scenarios!$A:$A, 0)) + INDEX(Scenarios!$E:$E, MATCH($A59, Scenarios!$A:$A, 0)) -> 1 | D59: =IF($B59="FY2026",$C59*IF(INDEX(Scenarios!$N:$N, MATCH($A59, Scenarios!$A:$A, 0))="lease", Parameters_Public!$C$31, Parameters_Public!$C$27),0) -> 1200000 | E59: =IF($B59="FY2026", IF(INDEX(Scenarios!$D:$D, MATCH($A59, Scenarios!$A:$A, 0))=0, IF(LEFT(INDEX(Scenarios!$O:$O, MATCH($A59, Scenarios!$A:$A, 0)),4)="Arts", Parameters_Public!$C$28, IF(LEFT(INDEX(Scenarios!$O:$O, MATCH($A59, Scenarios!$A:$A, 0)),5)="Innov", Parameters_Public!$C$29, 0)), 0), 0) -> 800000 | F59: =IF($B59="FY2026", IF(INDEX(Scenarios!$E:$E, MATCH($A59, Scenarios!$A:$A, 0))=0, IF(LEFT(INDEX(Scenarios!$P:$P, MATCH($A59, Scenarios!$A:$A, 0)),4)="Arts", Parameters_Public!$C$28, IF(LEFT(INDEX(Scenarios!$P:$P, MATCH($A59, Scenarios!$A:$A, 0)),5)="Innov", Parameters_Public!$C$29, 0)), 0), 0) -> 0 | G59: =IF($B59="FY2026", INDEX(Receiving_Capacity!$L:$L, MATCH($A59, Receiving_Capacity!$A:$A, 0)), 0) -> 0 | H59: =SUM(D59:G59) -> 2000000
A60: =Scenarios!$A$13 -> C_Repurpose_Pima_ops_EchoGHub_EchoTargets | B60: FY2027 | C60: =INDEX(Scenarios!$D:$D, MATCH($A60, Scenarios!$A:$A, 0)) + INDEX(Scenarios!$E:$E, MATCH($A60, Scenarios!$A:$A, 0)) -> 1 | D60: =IF($B60="FY2026",$C60*IF(INDEX(Scenarios!$N:$N, MATCH($A60, Scenarios!$A:$A, 0))="lease", Parameters_Public!$C$31, Parameters_Public!$C$27),0) -> 0 | E60: =IF($B60="FY2026", IF(INDEX(Scenarios!$D:$D, MATCH($A60, Scenarios!$A:$A, 0))=0, IF(LEFT(INDEX(Scenarios!$O:$O, MATCH($A60, Scenarios!$A:$A, 0)),4)="Arts", Parameters_Public!$C$28, IF(LEFT(INDEX(Scenarios!$O:$O, MATCH($A60, Scenarios!$A:$A, 0)),5)="Innov", Parameters_Public!$C$29, 0)), 0), 0) -> 0 | F60: =IF($B60="FY2026", IF(INDEX(Scenarios!$E:$E, MATCH($A60, Scenarios!$A:$A, 0))=0, IF(LEFT(INDEX(Scenarios!$P:$P, MATCH($A60, Scenarios!$A:$A, 0)),4)="Arts", Parameters_Public!$C$28, IF(LEFT(INDEX(Scenarios!$P:$P, MATCH($A60, Scenarios!$A:$A, 0)),5)="Innov", Parameters_Public!$C$29, 0)), 0), 0) -> 0 | G60: =IF($B60="FY2026", INDEX(Receiving_Capacity!$L:$L, MATCH($A60, Receiving_Capacity!$A:$A, 0)), 0) -> 0 | H60: =SUM(D60:G60) -> 0
A61: =Scenarios!$A$13 -> C_Repurpose_Pima_ops_EchoGHub_EchoTargets | B61: FY2028 | C61: =INDEX(Scenarios!$D:$D, MATCH($A61, Scenarios!$A:$A, 0)) + INDEX(Scenarios!$E:$E, MATCH($A61, Scenarios!$A:$A, 0)) -> 1 | D61: =IF($B61="FY2026",$C61*IF(INDEX(Scenarios!$N:$N, MATCH($A61, Scenarios!$A:$A, 0))="lease", Parameters_Public!$C$31, Parameters_Public!$C$27),0) -> 0 | E61: =IF($B61="FY2026", IF(INDEX(Scenarios!$D:$D, MATCH($A61, Scenarios!$A:$A, 0))=0, IF(LEFT(INDEX(Scenarios!$O:$O, MATCH($A61, Scenarios!$A:$A, 0)),4)="Arts", Parameters_Public!$C$28, IF(LEFT(INDEX(Scenarios!$O:$O, MATCH($A61, Scenarios!$A:$A, 0)),5)="Innov", Parameters_Public!$C$29, 0)), 0), 0) -> 0 | F61: =IF($B61="FY2026", IF(INDEX(Scenarios!$E:$E, MATCH($A61, Scenarios!$A:$A, 0))=0, IF(LEFT(INDEX(Scenarios!$P:$P, MATCH($A61, Scenarios!$A:$A, 0)),4)="Arts", Parameters_Public!$C$28, IF(LEFT(INDEX(Scenarios!$P:$P, MATCH($A61, Scenarios!$A:$A, 0)),5)="Innov", Parameters_Public!$C$29, 0)), 0), 0) -> 0 | G61: =IF($B61="FY2026", INDEX(Receiving_Capacity!$L:$L, MATCH($A61, Receiving_Capacity!$A:$A, 0)), 0) -> 0 | H61: =SUM(D61:G61) -> 0
A62: =Scenarios!$A$13 -> C_Repurpose_Pima_ops_EchoGHub_EchoTargets | B62: FY2029 | C62: =INDEX(Scenarios!$D:$D, MATCH($A62, Scenarios!$A:$A, 0)) + INDEX(Scenarios!$E:$E, MATCH($A62, Scenarios!$A:$A, 0)) -> 1 | D62: =IF($B62="FY2026",$C62*IF(INDEX(Scenarios!$N:$N, MATCH($A62, Scenarios!$A:$A, 0))="lease", Parameters_Public!$C$31, Parameters_Public!$C$27),0) -> 0 | E62: =IF($B62="FY2026", IF(INDEX(Scenarios!$D:$D, MATCH($A62, Scenarios!$A:$A, 0))=0, IF(LEFT(INDEX(Scenarios!$O:$O, MATCH($A62, Scenarios!$A:$A, 0)),4)="Arts", Parameters_Public!$C$28, IF(LEFT(INDEX(Scenarios!$O:$O, MATCH($A62, Scenarios!$A:$A, 0)),5)="Innov", Parameters_Public!$C$29, 0)), 0), 0) -> 0 | F62: =IF($B62="FY2026", IF(INDEX(Scenarios!$E:$E, MATCH($A62, Scenarios!$A:$A, 0))=0, IF(LEFT(INDEX(Scenarios!$P:$P, MATCH($A62, Scenarios!$A:$A, 0)),4)="Arts", Parameters_Public!$C$28, IF(LEFT(INDEX(Scenarios!$P:$P, MATCH($A62, Scenarios!$A:$A, 0)),5)="Innov", Parameters_Public!$C$29, 0)), 0), 0) -> 0 | G62: =IF($B62="FY2026", INDEX(Receiving_Capacity!$L:$L, MATCH($A62, Receiving_Capacity!$A:$A, 0)), 0) -> 0 | H62: =SUM(D62:G62) -> 0
A63: =Scenarios!$A$13 -> C_Repurpose_Pima_ops_EchoGHub_EchoTargets | B63: FY2030 | C63: =INDEX(Scenarios!$D:$D, MATCH($A63, Scenarios!$A:$A, 0)) + INDEX(Scenarios!$E:$E, MATCH($A63, Scenarios!$A:$A, 0)) -> 1 | D63: =IF($B63="FY2026",$C63*IF(INDEX(Scenarios!$N:$N, MATCH($A63, Scenarios!$A:$A, 0))="lease", Parameters_Public!$C$31, Parameters_Public!$C$27),0) -> 0 | E63: =IF($B63="FY2026", IF(INDEX(Scenarios!$D:$D, MATCH($A63, Scenarios!$A:$A, 0))=0, IF(LEFT(INDEX(Scenarios!$O:$O, MATCH($A63, Scenarios!$A:$A, 0)),4)="Arts", Parameters_Public!$C$28, IF(LEFT(INDEX(Scenarios!$O:$O, MATCH($A63, Scenarios!$A:$A, 0)),5)="Innov", Parameters_Public!$C$29, 0)), 0), 0) -> 0 | F63: =IF($B63="FY2026", IF(INDEX(Scenarios!$E:$E, MATCH($A63, Scenarios!$A:$A, 0))=0, IF(LEFT(INDEX(Scenarios!$P:$P, MATCH($A63, Scenarios!$A:$A, 0)),4)="Arts", Parameters_Public!$C$28, IF(LEFT(INDEX(Scenarios!$P:$P, MATCH($A63, Scenarios!$A:$A, 0)),5)="Innov", Parameters_Public!$C$29, 0)), 0), 0) -> 0 | G63: =IF($B63="FY2026", INDEX(Receiving_Capacity!$L:$L, MATCH($A63, Receiving_Capacity!$A:$A, 0)), 0) -> 0 | H63: =SUM(D63:G63) -> 0

Sheet Receiving_Capacity
A1: Receiving Capacity & Feasibility — FY2026 absorption of retained students (by grade band)
A3: ScenarioKey | B3: CloseEcho | C3: ClosePima | D3: Req_K5 | E3: Req_6_8 | G3: Spare_K5 | H3: Spare_6_8 | J3: Short_K5 | K3: Short_6_8 | L3: Portables$
A4: =Scenarios!$A$2 -> D_CUSTOM1 | B4: =INDEX(Scenarios!$D:$D, MATCH($A4, Scenarios!$A:$A, 0)) -> 0 | C4: =INDEX(Scenarios!$E:$E, MATCH($A4, Scenarios!$A:$A, 0)) -> 0 | D4: =INDEX(Scenarios!$D:$D, MATCH($A4, Scenarios!$A:$A, 0))*Parameters_Public!$C$22*Parameters_Public!$C$10*Parameters_Public!$C$36 + INDEX(Scenarios!$E:$E, MATCH($A4, Scenarios!$A:$A, 0))*Parameters_Public!$C$23*Parameters_Public!$C$11*Parameters_Public!$C$38 -> 0 | E4: =INDEX(Scenarios!$D:$D, MATCH($A4, Scenarios!$A:$A, 0))*Parameters_Public!$C$22*Parameters_Public!$C$10*Parameters_Public!$C$37 + INDEX(Scenarios!$E:$E, MATCH($A4, Scenarios!$A:$A, 0))*Parameters_Public!$C$23*Parameters_Public!$C$11*Parameters_Public!$C$39 -> 0 | G4: =Parameters_Public!$C$33 -> 300 | H4: =Parameters_Public!$C$34 -> 150 | J4: =MAX(0, D4-G4) -> 0 | K4: =MAX(0, E4-H4) -> 0 | L4: =(J4+K4)*Parameters_Public!$C$32 -> 0
A5: =Scenarios!$A$3 -> E_StatusQuo_Targets | B5: =INDEX(Scenarios!$D:$D, MATCH($A5, Scenarios!$A:$A, 0)) -> 0 | C5: =INDEX(Scenarios!$E:$E, MATCH($A5, Scenarios!$A:$A, 0)) -> 0 | D5: =INDEX(Scenarios!$D:$D, MATCH($A5, Scenarios!$A:$A, 0))*Parameters_Public!$C$22*Parameters_Public!$C$10*Parameters_Public!$C$36 + INDEX(Scenarios!$E:$E, MATCH($A5, Scenarios!$A:$A, 0))*Parameters_Public!$C$23*Parameters_Public!$C$11*Parameters_Public!$C$38 -> 0 | E5: =INDEX(Scenarios!$D:$D, MATCH($A5, Scenarios!$A:$A, 0))*Parameters_Public!$C$22*Parameters_Public!$C$10*Parameters_Public!$C$37 + INDEX(Scenarios!$E:$E, MATCH($A5, Scenarios!$A:$A, 0))*Parameters_Public!$C$23*Parameters_Public!$C$11*Parameters_Public!$C$39 -> 0 | G5: =Parameters_Public!$C$33 -> 300 | H5: =Parameters_Public!$C$34 -> 150 | J5: =MAX(0, D5-G5) -> 0 | K5: =MAX(0, E5-H5) -> 0 | L5: =(J5+K5)*Parameters_Public!$C$32 -> 0
A6: =Scenarios!$A$4 -> F_CoLocation_Echo_Targets | B6: =INDEX(Scenarios!$D:$D, MATCH($A6, Scenarios!$A:$A, 0)) -> 0 | C6: =INDEX(Scenarios!$E:$E, MATCH($A6, Scenarios!$A:$A, 0)) -> 0 | D6: =INDEX(Scenarios!$D:$D, MATCH($A6, Scenarios!$A:$A, 0))*Parameters_Public!$C$22*Parameters_Public!$C$10*Parameters_Public!$C$36 + INDEX(Scenarios!$E:$E, MATCH($A6, Scenarios!$A:$A, 0))*Parameters_Public!$C$23*Parameters_Public!$C$11*Parameters_Public!$C$38 -> 0 | E6: =INDEX(Scenarios!$D:$D, MATCH($A6, Scenarios!$A:$A, 0))*Parameters_Public!$C$22*Parameters_Public!$C$10*Parameters_Public!$C$37 + INDEX(Scenarios!$E:$E, MATCH($A6, Scenarios!$A:$A, 0))*Parameters_Public!$C$23*Parameters_Public!$C$11*Parameters_Public!$C$39 -> 0 | G6: =Parameters_Public!$C$33 -> 300 | H6: =Parameters_Public!$C$34 -> 150 | J6: =MAX(0, D6-G6) -> 0 | K6: =MAX(0, E6-H6) -> 0 | L6: =(J6+K6)*Parameters_Public!$C$32 -> 0
A7: =Scenarios!$A$5 -> D_Grow_Both_Targets | B7: =INDEX(Scenarios!$D:$D, MATCH($A7, Scenarios!$A:$A, 0)) -> 0 | C7: =INDEX(Scenarios!$E:$E, MATCH($A7, Scenarios!$A:$A, 0)) -> 0 | D7: =INDEX(Scenarios!$D:$D, MATCH($A7, Scenarios!$A:$A, 0))*Parameters_Public!$C$22*Parameters_Public!$C$10*Parameters_Public!$C$36 + INDEX(Scenarios!$E:$E, MATCH($A7, Scenarios!$A:$A, 0))*Parameters_Public!$C$23*Parameters_Public!$C$11*Parameters_Public!$C$38 -> 0 | E7: =INDEX(Scenarios!$D:$D, MATCH($A7, Scenarios!$A:$A, 0))*Parameters_Public!$C$22*Parameters_Public!$C$10*Parameters_Public!$C$37 + INDEX(Scenarios!$E:$E, MATCH($A7, Scenarios!$A:$A, 0))*Parameters_Public!$C$23*Parameters_Public!$C$11*Parameters_Public!$C$39 -> 0 | G7: =Parameters_Public!$C$33 -> 300 | H7: =Parameters_Public!$C$34 -> 150 | J7: =MAX(0, D7-G7) -> 0 | K7: =MAX(0, E7-H7) -> 0 | L7: =(J7+K7)*Parameters_Public!$C$32 -> 0
A8: =Scenarios!$A$6 -> D_CUSTOM2 | B8: =INDEX(Scenarios!$D:$D, MATCH($A8, Scenarios!$A:$A, 0)) -> 0 | C8: =INDEX(Scenarios!$E:$E, MATCH($A8, Scenarios!$A:$A, 0)) -> 0 | D8: =INDEX(Scenarios!$D:$D, MATCH($A8, Scenarios!$A:$A, 0))*Parameters_Public!$C$22*Parameters_Public!$C$10*Parameters_Public!$C$36 + INDEX(Scenarios!$E:$E, MATCH($A8, Scenarios!$A:$A, 0))*Parameters_Public!$C$23*Parameters_Public!$C$11*Parameters_Public!$C$38 -> 0 | E8: =INDEX(Scenarios!$D:$D, MATCH($A8, Scenarios!$A:$A, 0))*Parameters_Public!$C$22*Parameters_Public!$C$10*Parameters_Public!$C$37 + INDEX(Scenarios!$E:$E, MATCH($A8, Scenarios!$A:$A, 0))*Parameters_Public!$C$23*Parameters_Public!$C$11*Parameters_Public!$C$39 -> 0 | G8: =Parameters_Public!$C$33 -> 300 | H8: =Parameters_Public!$C$34 -> 150 | J8: =MAX(0, D8-G8) -> 0 | K8: =MAX(0, E8-H8) -> 0 | L8: =(J8+K8)*Parameters_Public!$C$32 -> 0
A9: =Scenarios!$A$7 -> G_EchoGHubRamp_PimaTargets | B9: =INDEX(Scenarios!$D:$D, MATCH($A9, Scenarios!$A:$A, 0)) -> 0 | C9: =INDEX(Scenarios!$E:$E, MATCH($A9, Scenarios!$A:$A, 0)) -> 0 | D9: =INDEX(Scenarios!$D:$D, MATCH($A9, Scenarios!$A:$A, 0))*Parameters_Public!$C$22*Parameters_Public!$C$10*Parameters_Public!$C$36 + INDEX(Scenarios!$E:$E, MATCH($A9, Scenarios!$A:$A, 0))*Parameters_Public!$C$23*Parameters_Public!$C$11*Parameters_Public!$C$38 -> 0 | E9: =INDEX(Scenarios!$D:$D, MATCH($A9, Scenarios!$A:$A, 0))*Parameters_Public!$C$22*Parameters_Public!$C$10*Parameters_Public!$C$37 + INDEX(Scenarios!$E:$E, MATCH($A9, Scenarios!$A:$A, 0))*Parameters_Public!$C$23*Parameters_Public!$C$11*Parameters_Public!$C$39 -> 0 | G9: =Parameters_Public!$C$33 -> 300 | H9: =Parameters_Public!$C$34 -> 150 | J9: =MAX(0, D9-G9) -> 0 | K9: =MAX(0, E9-H9) -> 0 | L9: =(J9+K9)*Parameters_Public!$C$32 -> 0
A10: =Scenarios!$A$8 -> A_Repurpose_Both_lease | B10: =INDEX(Scenarios!$D:$D, MATCH($A10, Scenarios!$A:$A, 0)) -> 1 | C10: =INDEX(Scenarios!$E:$E, MATCH($A10, Scenarios!$A:$A, 0)) -> 1 | D10: =INDEX(Scenarios!$D:$D, MATCH($A10, Scenarios!$A:$A, 0))*Parameters_Public!$C$22*Parameters_Public!$C$10*Parameters_Public!$C$36 + INDEX(Scenarios!$E:$E, MATCH($A10, Scenarios!$A:$A, 0))*Parameters_Public!$C$23*Parameters_Public!$C$11*Parameters_Public!$C$38 -> 359.54 | E10: =INDEX(Scenarios!$D:$D, MATCH($A10, Scenarios!$A:$A, 0))*Parameters_Public!$C$22*Parameters_Public!$C$10*Parameters_Public!$C$37 + INDEX(Scenarios!$E:$E, MATCH($A10, Scenarios!$A:$A, 0))*Parameters_Public!$C$23*Parameters_Public!$C$11*Parameters_Public!$C$39 -> 46.26 | G10: =Parameters_Public!$C$33 -> 300 | H10: =Parameters_Public!$C$34 -> 150 | J10: =MAX(0, D10-G10) -> 59.54 | K10: =MAX(0, E10-H10) -> 0 | L10: =(J10+K10)*Parameters_Public!$C$32 -> 714480
A11: =Scenarios!$A$9 -> A_Repurpose_Both_ops | B11: =INDEX(Scenarios!$D:$D, MATCH($A11, Scenarios!$A:$A, 0)) -> 1 | C11: =INDEX(Scenarios!$E:$E, MATCH($A11, Scenarios!$A:$A, 0)) -> 1 | D11: =INDEX(Scenarios!$D:$D, MATCH($A11, Scenarios!$A:$A, 0))*Parameters_Public!$C$22*Parameters_Public!$C$10*Parameters_Public!$C$36 + INDEX(Scenarios!$E:$E, MATCH($A11, Scenarios!$A:$A, 0))*Parameters_Public!$C$23*Parameters_Public!$C$11*Parameters_Public!$C$38 -> 359.54 | E11: =INDEX(Scenarios!$D:$D, MATCH($A11, Scenarios!$A:$A, 0))*Parameters_Public!$C$22*Parameters_Public!$C$10*Parameters_Public!$C$37 + INDEX(Scenarios!$E:$E, MATCH($A11, Scenarios!$A:$A, 0))*Parameters_Public!$C$23*Parameters_Public!$C$11*Parameters_Public!$C$39 -> 46.26 | G11: =Parameters_Public!$C$33 -> 300 | H11: =Parameters_Public!$C$34 -> 150 | J11: =MAX(0, D11-G11) -> 59.54 | K11: =MAX(0, E11-H11) -> 0 | L11: =(J11+K11)*Parameters_Public!$C$32 -> 714480
A12: =Scenarios!$A$10 -> B_Repurpose_Echo_lease_PimaTargets | B12: =INDEX(Scenarios!$D:$D, MATCH($A12, Scenarios!$A:$A, 0)) -> 1 | C12: =INDEX(Scenarios!$E:$E, MATCH($A12, Scenarios!$A:$A, 0)) -> 0 | D12: =INDEX(Scenarios!$D:$D, MATCH($A12, Scenarios!$A:$A, 0))*Parameters_Public!$C$22*Parameters_Public!$C$10*Parameters_Public!$C$36 + INDEX(Scenarios!$E:$E, MATCH($A12, Scenarios!$A:$A, 0))*Parameters_Public!$C$23*Parameters_Public!$C$11*Parameters_Public!$C$38 -> 107.94 | E12: =INDEX(Scenarios!$D:$D, MATCH($A12, Scenarios!$A:$A, 0))*Parameters_Public!$C$22*Parameters_Public!$C$10*Parameters_Public!$C$37 + INDEX(Scenarios!$E:$E, MATCH($A12, Scenarios!$A:$A, 0))*Parameters_Public!$C$23*Parameters_Public!$C$11*Parameters_Public!$C$39 -> 46.26 | G12: =Parameters_Public!$C$33 -> 300 | H12: =Parameters_Public!$C$34 -> 150 | J12: =MAX(0, D12-G12) -> 0 | K12: =MAX(0, E12-H12) -> 0 | L12: =(J12+K12)*Parameters_Public!$C$32 -> 0
A13: =Scenarios!$A$11 -> B_Repurpose_Echo_ops_PimaTargets | B13: =INDEX(Scenarios!$D:$D, MATCH($A13, Scenarios!$A:$A, 0)) -> 1 | C13: =INDEX(Scenarios!$E:$E, MATCH($A13, Scenarios!$A:$A, 0)) -> 0 | D13: =INDEX(Scenarios!$D:$D, MATCH($A13, Scenarios!$A:$A, 0))*Parameters_Public!$C$22*Parameters_Public!$C$10*Parameters_Public!$C$36 + INDEX(Scenarios!$E:$E, MATCH($A13, Scenarios!$A:$A, 0))*Parameters_Public!$C$23*Parameters_Public!$C$11*Parameters_Public!$C$38 -> 107.94 | E13: =INDEX(Scenarios!$D:$D, MATCH($A13, Scenarios!$A:$A, 0))*Parameters_Public!$C$22*Parameters_Public!$C$10*Parameters_Public!$C$37 + INDEX(Scenarios!$E:$E, MATCH($A13, Scenarios!$A:$A, 0))*Parameters_Public!$C$23*Parameters_Public!$C$11*Parameters_Public!$C$39 -> 46.26 | G13: =Parameters_Public!$C$33 -> 300 | H13: =Parameters_Public!$C$34 -> 150 | J13: =MAX(0, D13-G13) -> 0 | K13: =MAX(0, E13-H13) -> 0 | L13: =(J13+K13)*Parameters_Public!$C$32 -> 0
A14: =Scenarios!$A$12 -> C_Repurpose_Pima_lease_EchoGHub_EchoTargets | B14: =INDEX(Scenarios!$D:$D, MATCH($A14, Scenarios!$A:$A, 0)) -> 0 | C14: =INDEX(Scenarios!$E:$E, MATCH($A14, Scenarios!$A:$A, 0)) -> 1 | D14: =INDEX(Scenarios!$D:$D, MATCH($A14, Scenarios!$A:$A, 0))*Parameters_Public!$C$22*Parameters_Public!$C$10*Parameters_Public!$C$36 + INDEX(Scenarios!$E:$E, MATCH($A14, Scenarios!$A:$A, 0))*Parameters_Public!$C$23*Parameters_Public!$C$11*Parameters_Public!$C$38 -> 251.6 | E14: =INDEX(Scenarios!$D:$D, MATCH($A14, Scenarios!$A:$A, 0))*Parameters_Public!$C$22*Parameters_Public!$C$10*Parameters_Public!$C$37 + INDEX(Scenarios!$E:$E, MATCH($A14, Scenarios!$A:$A, 0))*Parameters_Public!$C$23*Parameters_Public!$C$11*Parameters_Public!$C$39 -> 0 | G14: =Parameters_Public!$C$33 -> 300 | H14: =Parameters_Public!$C$34 -> 150 | J14: =MAX(0, D14-G14) -> 0 | K14: =MAX(0, E14-H14) -> 0 | L14: =(J14+K14)*Parameters_Public!$C$32 -> 0
A15: =Scenarios!$A$13 -> C_Repurpose_Pima_ops_EchoGHub_EchoTargets | B15: =INDEX(Scenarios!$D:$D, MATCH($A15, Scenarios!$A:$A, 0)) -> 0 | C15: =INDEX(Scenarios!$E:$E, MATCH($A15, Scenarios!$A:$A, 0)) -> 1 | D15: =INDEX(Scenarios!$D:$D, MATCH($A15, Scenarios!$A:$A, 0))*Parameters_Public!$C$22*Parameters_Public!$C$10*Parameters_Public!$C$36 + INDEX(Scenarios!$E:$E, MATCH($A15, Scenarios!$A:$A, 0))*Parameters_Public!$C$23*Parameters_Public!$C$11*Parameters_Public!$C$38 -> 251.6 | E15: =INDEX(Scenarios!$D:$D, MATCH($A15, Scenarios!$A:$A, 0))*Parameters_Public!$C$22*Parameters_Public!$C$10*Parameters_Public!$C$37 + INDEX(Scenarios!$E:$E, MATCH($A15, Scenarios!$A:$A, 0))*Parameters_Public!$C$23*Parameters_Public!$C$11*Parameters_Public!$C$39 -> 0 | G15: =Parameters_Public!$C$33 -> 300 | H15: =Parameters_Public!$C$34 -> 150 | J15: =MAX(0, D15-G15) -> 0 | K15: =MAX(0, E15-H15) -> 0 | L15: =(J15+K15)*Parameters_Public!$C$32 -> 0
D18: =INDEX(Scenarios!$D:$D, MATCH($A4, Scenarios!$A:$A, 0))*Parameters_Public!$C$22*Echo_ADM0*Parameters_Public!$C$36 + INDEX(Scenarios!$E:$E, MATCH($A4, Scenarios!$A:$A, 0))*Parameters_Public!$C$23*Pima_ADM0*Parameters_Public!$C$38 -> 0

Sheet Control_Center
A1: Control center - yellow shaded fields are editable inputs
A3: Foundational inputs
B5: Parameter | C5: Value | H5: Notes
B6: MO inflation | C6: 0.025 | H6: Annual inflation factor.
B7: Base MO per ADM (FY25) | C7: 9936 | H7: "MO" = xx. Working base for FY25. Calculated from reported budget data and enrollment estimates - as relates to Echo Canyon and Pima only.
B8: Fixed share of MO | C8: 0.46 | H8: Share of MO treated as semi‑fixed (plant/insurance).
B9: Base State Aid per ADM (FY26) | C9: 5013 | H9: Editable; ADE base aid.
B10: Ops savings (keep‑open) | C10: 0.007 | H10: Light discipline if sites remain open (not used here).
B11: Extra savings (Co‑location) | C11: 0.015 | H11: Incremental savings for co‑location (not used here).
B12: Echo base ADM | C12: 257 | H12: "ADM" = average daily membership; roughly equivalent to enrollment. Approximate current Echo enrollment
B13: Pima base ADM | C13: 296 | H13: Approximate current Pima enrollment
B14: Total base ADM | C14: =C12+C13 -> 553 | H14: Echo base ADM + Pima base ADM
B15: Repurpose TI per closed site (FY26) | C15: 1200000 | H15: Research suggests a xx
B16: Retention r (in case of repurpose) | C16: 0.75 | H16: Research suggests a range in the 0.5-0.8 range. Since Echo is a choice school with high % of families from out of district, reality might be lower?
B17: MarginalFactor_for_Overlay | C17: 0.4 | H17: Assuming there is a reduced marginal cost of adding new (growth) students, especially when the schools (Echo and Pima) have capacity. In reality this is probably a complicated step function, but we can approximate.
A19: Repurpose trajectory assumptions
B21: Year | C21: h | D21: f_lease | E21: f_ops
B22: FY2026 | C22: 1000 | D22: 0.4 | E22: 0.5 | H22: (For 'h') Research suggests an incremental transition cost (largely related to bus transportation) that can start higher than $1000. Assumption is this is managed down over time
B23: FY2027 | C23: 800 | D23: 0.3 | E23: 0.4 | H23: (For 'f_lease') Assuming repurpose = lease… depending on lease timing and type / arrangement (e.g. triple net?), district will carry some percentage of fixed and semi-fixed costs for a certain period of time
B24: FY2028 | C24: 600 | D24: 0.2 | E24: 0.35 | H24: (For 'f_ops') Assuming repurpose = some operational repurpose (not lease or sale)… depending on timing and type of repurpose, district will still carry some percentage of fixed and semi-fixed costs
B25: FY2029 | C25: 500 | D25: 0.1 | E25: 0.3
B26: FY2030 | C26: 300 | D26: 0.1 | E26: 0.3
A28: Scenario assumptions
A30: (Reference) | B30: Scenario title | C30: TargetGrowth (#) | D30: CloseEcho (0 or 1) | E30: ClosePima (0 or 1) | F30: EchoShareGrowth (ratio) | G30: ExtraOpSavings (ratio)
A31: D. Grow Both (Overlay 0) | B31: CUSTOM_KeepOpen_v1 | C31: 0 | D31: 0 | E31: 0 | F31: 0.5 | G31: 0
A32: E. Status‑Quo + Targets (0) | B32: Status‑Quo + Op Growth Targets | C32: 150 | D32: 0 | E32: 0 | F32: 0.5 | G32: 0 | H32: Echo and Pima remain open; uplift warm handoff effort (intra-SUSD) and implement cross-district marketing initiative (e.g. capture ~10% of Kyrene's displaced families?)
A33: F. Co‑Location @ Echo (0) | B33: Co‑Location @ Echo + Op Growth Targets | C33: 150 | D33: 0 | E33: 0 | F33: 0.5 | G33: 0.05
A34: D. Grow Both (Overlay 100) | B34: Grow Both + Op Growth Targets | C34: 250 | D34: 0 | E34: 0 | F34: 0.5 | G34: 0
A35: D. Grow Both (Overlay 150) | B35: CUSTOM_KeepOpen_v2 | C35: 0 | D35: 0 | E35: 0 | F35: 0.5 | G35: 0
A36: G. D‑Hub @ Echo (Ramp 50→100→150) | B36: Growth Hub @ Echo + Status-Quo Pima + Op Growth Targets | C36: 150 | D36: 0 | E36: 0 | F36: 0.7 | G36: 0
A37: A. Repurpose BOTH (lease) | B37: Repurpose BOTH (lease) | C37: 0 | D37: 1 | E37: 1 | F37: 0.5 | G37: 0
A38: A. Repurpose BOTH (ops) | B38: Repurpose BOTH (ops) | C38: 0 | D38: 1 | E38: 1 | F38: 0.5 | G38: 0
A39: B. Repurpose ECHO (lease) | B39: Repurpose ECHO (lease) + Status-Quo Pima + Pima Op Growth Targets | C39: 0 | D39: 1 | E39: 0 | F39: 0 | G39: 0
A40: B. Repurpose ECHO (ops) | B40: Repurpose ECHO (ops) + Status-Quo Pima + Pima Op Growth Targets | C40: 150 | D40: 1 | E40: 0 | F40: 0 | G40: 0
A41: C. Repurpose PIMA (lease) | B41: Repurpose PIMA (lease) + Growth Hub @ Echo + Echo Op Growth Targets | C41: 0 | D41: 0 | E41: 1 | F41: 1 | G41: 0
A42: C. Repurpose PIMA (ops) | B42: Repurpose PIMA (ops) + Growth Hub @ Echo + Echo Op Growth Targets | C42: 200 | D42: 0 | E42: 1 | F42: 1 | G42: 0
A44: Qualitative assessment
B46: Scenario title | C46: Distinctiveness | D46: Reversibility | H46: Example qualitative metrics to consider. Possibly interesting as part of overall story.
B47: CUSTOM1 | C47: + | D47: Med
B48: Status‑Quo + Op Growth Targets | C48: o | D48: High
B49: Co‑Location @ Echo + Op Growth Targets | C49: ++ | D49: Med
B50: Grow Both + Op Growth Targets | C50: ++ | D50: Med
B51: CUSTOM2 | C51: + | D51: Med
B52: Growth Hub @ Echo + Status-Quo Pima + Op Growth Targets | C52: ++ | D52: Med
B53: Repurpose BOTH (lease) | C53: -- | D53: Low
B54: Repurpose BOTH (ops) | C54: - | D54: Low-Med
B55: Repurpose ECHO (lease) + Status-Quo Pima + Pima Op Growth Targets | C55: - | D55: Low-Med
B56: Repurpose ECHO (ops) + Status-Quo Pima + Pima Op Growth Targets | C56: o | D56: Low-Med
B57: Repurpose PIMA (lease) + Growth Hub @ Echo + Echo Op Growth Targets | C57: - | D57: Low-Med
B58: Repurpose PIMA (ops) + Growth Hub @ Echo + Echo Op Growth Targets | C58: o | D58: Low-Med

Sheet Dashboard
G1: Operational | I1: Qualitative | K1: Net figures ('revenue' - 'cost') | O1: Scenario net figures vs. Repurpose both (ops)
B2: ScenarioKey | C2: FY2028 Comparable $/Student | D2: FY2030 Comparable $/Student | E2: 3‑yr Avg Comparable $/Student (FY26–FY28) | F2: 5‑yr Avg Comparable $/Student (FY26–FY30) | G2: # Students displaced | H2: FY2030 # students served (open & retained) | I2: =Control_Center!C46 -> Distinctiveness | J2: =Control_Center!D46 -> Reversibility | K2: FY2028 Net ($) | L2: FY2030 Net ($) | M2: 5-yr Net Avg ($) | N2: (Ref) Control center labels | O2: Δ FY2030 Net ($) vs Repurpose BOTH (ops) | P2: Δ 5-yr Avg Net ($) vs Repurpose BOTH (ops)
B3: =Scenarios!A8 -> A_Repurpose_Both_lease | C3: =INDEX(MultiYear_ProForma!$X$2:$X$61, MATCH(Scenarios!A8&"|FY2028", MultiYear_ProForma!$AG$2:$AG$61, 0)) -> 8892.9481 | D3: =INDEX(MultiYear_ProForma!$X$2:$X$61, MATCH(Scenarios!A8&"|FY2030", MultiYear_ProForma!$AG$2:$AG$61, 0)) -> 8196.5996 | E3: =AVERAGE(INDEX(MultiYear_ProForma!$X$2:$X$61, MATCH(Scenarios!A8&"|FY2026", MultiYear_ProForma!$AG$2:$AG$61, 0)),INDEX(MultiYear_ProForma!$X$2:$X$61, MATCH(Scenarios!A8&"|FY2027", MultiYear_ProForma!$AG$2:$AG$61, 0)),INDEX(MultiYear_ProForma!$X$2:$X$61, MATCH(Scenarios!A8&"|FY2028", MultiYear_ProForma!$AG$2:$AG$61, 0))) -> 9637.9053 | F3: =AVERAGE(INDEX(MultiYear_ProForma!$X$2:$X$61, MATCH(Scenarios!A8&"|FY2026", MultiYear_ProForma!$AG$2:$AG$61, 0)),INDEX(MultiYear_ProForma!$X$2:$X$61, MATCH(Scenarios!A8&"|FY2027", MultiYear_ProForma!$AG$2:$AG$61, 0)),INDEX(MultiYear_ProForma!$X$2:$X$61, MATCH(Scenarios!A8&"|FY2028", MultiYear_ProForma!$AG$2:$AG$61, 0)),INDEX(MultiYear_ProForma!$X$2:$X$61, MATCH(Scenarios!A8&"|FY2029", MultiYear_ProForma!$AG$2:$AG$61, 0)),INDEX(MultiYear_ProForma!$X$2:$X$61, MATCH(Scenarios!A8&"|FY2030", MultiYear_ProForma!$AG$2:$AG$61, 0))) -> 9062.863 | G3: =IFERROR(VLOOKUP($B3&"|FY2026", MultiYear_ProForma!$A:$AG, 14, FALSE), "") -> 553 | H3: =IFERROR(VLOOKUP($B3&"|FY2030", MultiYear_ProForma!$A:$AG, 6, FALSE) + VLOOKUP($B3&"|FY2030", MultiYear_ProForma!$A:$AG, 15, FALSE), "") -> 405.8 | I3: =Control_Center!C48 -> o | J3: =Control_Center!D48 -> High | K3: =SUMIFS(MultiYear_ProForma!$AF:$AF, MultiYear_ProForma!$B:$B, $B3, MultiYear_ProForma!$C:$C, "FY2028") -> -1187156.9 | L3: =SUMIFS(MultiYear_ProForma!$AF:$AF, MultiYear_ProForma!$B:$B, $B3, MultiYear_ProForma!$C:$C, "FY2030") -> -819073.68 | M3: =(SUMIFS(MultiYear_ProForma!$AF:$AF, MultiYear_ProForma!$B:$B, $B3, MultiYear_ProForma!$C:$C, "FY2026")+SUMIFS(MultiYear_ProForma!$AF:$AF, MultiYear_ProForma!$B:$B, $B3, MultiYear_ProForma!$C:$C, "FY2027")+SUMIFS(MultiYear_ProForma!$AF:$AF, MultiYear_ProForma!$B:$B, $B3, MultiYear_ProForma!$C:$C, "FY2028")+SUMIFS(MultiYear_ProForma!$AF:$AF, MultiYear_ProForma!$B:$B, $B3, MultiYear_ProForma!$C:$C, "FY2029")+SUMIFS(MultiYear_ProForma!$AF:$AF, MultiYear_ProForma!$B:$B, $B3, MultiYear_ProForma!$C:$C, "FY2030"))/5 -> -1255278.3 | N3: =Control_Center!B37 -> Repurpose BOTH (lease) | O3: =L3 - INDEX(L:L, MATCH("A_Repurpose_Both_ops", $B:$B, 0)) -> 662410.94 | P3: =M3 - INDEX(M:M, MATCH("A_Repurpose_Both_ops", $B:$B, 0)) -> 477829.55
B4: =Scenarios!A13 -> C_Repurpose_Pima_ops_EchoGHub_EchoTargets | C4: =INDEX(MultiYear_ProForma!$X$2:$X$61, MATCH(Scenarios!A13&"|FY2028", MultiYear_ProForma!$AG$2:$AG$61, 0)) -> 9822.8713 | D4: =INDEX(MultiYear_ProForma!$X$2:$X$61, MATCH(Scenarios!A13&"|FY2030", MultiYear_ProForma!$AG$2:$AG$61, 0)) -> 10077.756 | E4: =AVERAGE(INDEX(MultiYear_ProForma!$X$2:$X$61, MATCH(Scenarios!A13&"|FY2026", MultiYear_ProForma!$AG$2:$AG$61, 0)),INDEX(MultiYear_ProForma!$X$2:$X$61, MATCH(Scenarios!A13&"|FY2027", MultiYear_ProForma!$AG$2:$AG$61, 0)),INDEX(MultiYear_ProForma!$X$2:$X$61, MATCH(Scenarios!A13&"|FY2028", MultiYear_ProForma!$AG$2:$AG$61, 0))) -> 9813.4525 | F4: =AVERAGE(INDEX(MultiYear_ProForma!$X$2:$X$61, MATCH(Scenarios!A13&"|FY2026", MultiYear_ProForma!$AG$2:$AG$61, 0)),INDEX(MultiYear_ProForma!$X$2:$X$61, MATCH(Scenarios!A13&"|FY2027", MultiYear_ProForma!$AG$2:$AG$61, 0)),INDEX(MultiYear_ProForma!$X$2:$X$61, MATCH(Scenarios!A13&"|FY2028", MultiYear_ProForma!$AG$2:$AG$61, 0)),INDEX(MultiYear_ProForma!$X$2:$X$61, MATCH(Scenarios!A13&"|FY2029", MultiYear_ProForma!$AG$2:$AG$61, 0)),INDEX(MultiYear_ProForma!$X$2:$X$61, MATCH(Scenarios!A13&"|FY2030", MultiYear_ProForma!$AG$2:$AG$61, 0))) -> 9884.7364 | G4: =IFERROR(VLOOKUP($B4&"|FY2026", MultiYear_ProForma!$A:$AG, 14, FALSE), "") -> 296 | H4: =IFERROR(VLOOKUP($B4&"|FY2030", MultiYear_ProForma!$A:$AG, 6, FALSE) + VLOOKUP($B4&"|FY2030", MultiYear_ProForma!$A:$AG, 15, FALSE), "") -> 708.6 | I4: =Control_Center!C47 -> + | J4: =Control_Center!D47 -> Med | K4: =SUMIFS(MultiYear_ProForma!$AF:$AF, MultiYear_ProForma!$B:$B, $B4, MultiYear_ProForma!$C:$C, "FY2028") -> -1928885.1 | L4: =SUMIFS(MultiYear_ProForma!$AF:$AF, MultiYear_ProForma!$B:$B, $B4, MultiYear_ProForma!$C:$C, "FY2030") -> -1919535 | M4: =(SUMIFS(MultiYear_ProForma!$AF:$AF, MultiYear_ProForma!$B:$B, $B4, MultiYear_ProForma!$C:$C, "FY2026")+SUMIFS(MultiYear_ProForma!$AF:$AF, MultiYear_ProForma!$B:$B, $B4, MultiYear_ProForma!$C:$C, "FY2027")+SUMIFS(MultiYear_ProForma!$AF:$AF, MultiYear_ProForma!$B:$B, $B4, MultiYear_ProForma!$C:$C, "FY2028")+SUMIFS(MultiYear_ProForma!$AF:$AF, MultiYear_ProForma!$B:$B, $B4, MultiYear_ProForma!$C:$C, "FY2029")+SUMIFS(MultiYear_ProForma!$AF:$AF, MultiYear_ProForma!$B:$B, $B4, MultiYear_ProForma!$C:$C, "FY2030"))/5 -> -1970783.6 | N4: =Control_Center!B42 -> Repurpose PIMA (ops) + Growth Hub @ Echo + Echo Op Growth Targets | O4: =L4 - INDEX(L:L, MATCH("A_Repurpose_Both_ops", $B:$B, 0)) -> -438050.41 | P4: =M4 - INDEX(M:M, MATCH("A_Repurpose_Both_ops", $B:$B, 0)) -> -237675.71
B5: =Scenarios!A4 -> F_CoLocation_Echo_Targets | C5: =INDEX(MultiYear_ProForma!$X$2:$X$61, MATCH(Scenarios!A4&"|FY2028", MultiYear_ProForma!$AG$2:$AG$61, 0)) -> 10617.551 | D5: =INDEX(MultiYear_ProForma!$X$2:$X$61, MATCH(Scenarios!A4&"|FY2030", MultiYear_ProForma!$AG$2:$AG$61, 0)) -> 11155.064 | E5: =AVERAGE(INDEX(MultiYear_ProForma!$X$2:$X$61, MATCH(Scenarios!A4&"|FY2026", MultiYear_ProForma!$AG$2:$AG$61, 0)),INDEX(MultiYear_ProForma!$X$2:$X$61, MATCH(Scenarios!A4&"|FY2027", MultiYear_ProForma!$AG$2:$AG$61, 0)),INDEX(MultiYear_ProForma!$X$2:$X$61, MATCH(Scenarios!A4&"|FY2028", MultiYear_ProForma!$AG$2:$AG$61, 0))) -> 10360.692 | F5: =AVERAGE(INDEX(MultiYear_ProForma!$X$2:$X$61, MATCH(Scenarios!A4&"|FY2026", MultiYear_ProForma!$AG$2:$AG$61, 0)),INDEX(MultiYear_ProForma!$X$2:$X$61, MATCH(Scenarios!A4&"|FY2027", MultiYear_ProForma!$AG$2:$AG$61, 0)),INDEX(MultiYear_ProForma!$X$2:$X$61, MATCH(Scenarios!A4&"|FY2028", MultiYear_ProForma!$AG$2:$AG$61, 0)),INDEX(MultiYear_ProForma!$X$2:$X$61, MATCH(Scenarios!A4&"|FY2029", MultiYear_ProForma!$AG$2:$AG$61, 0)),INDEX(MultiYear_ProForma!$X$2:$X$61, MATCH(Scenarios!A4&"|FY2030", MultiYear_ProForma!$AG$2:$AG$61, 0))) -> 10624.026 | G5: =IFERROR(VLOOKUP($B5&"|FY2026", MultiYear_ProForma!$A:$AG, 14, FALSE), "") -> 0 | H5: =IFERROR(VLOOKUP($B5&"|FY2030", MultiYear_ProForma!$A:$AG, 6, FALSE) + VLOOKUP($B5&"|FY2030", MultiYear_ProForma!$A:$AG, 15, FALSE), "") -> 703 | I5: =Control_Center!C50 -> ++ | J5: =Control_Center!D50 -> Med | K5: =SUMIFS(MultiYear_ProForma!$AF:$AF, MultiYear_ProForma!$B:$B, $B5, MultiYear_ProForma!$C:$C, "FY2028") -> -2696831 | L5: =SUMIFS(MultiYear_ProForma!$AF:$AF, MultiYear_ProForma!$B:$B, $B5, MultiYear_ProForma!$C:$C, "FY2030") -> -2897609.6 | M5: =(SUMIFS(MultiYear_ProForma!$AF:$AF, MultiYear_ProForma!$B:$B, $B5, MultiYear_ProForma!$C:$C, "FY2026")+SUMIFS(MultiYear_ProForma!$AF:$AF, MultiYear_ProForma!$B:$B, $B5, MultiYear_ProForma!$C:$C, "FY2027")+SUMIFS(MultiYear_ProForma!$AF:$AF, MultiYear_ProForma!$B:$B, $B5, MultiYear_ProForma!$C:$C, "FY2028")+SUMIFS(MultiYear_ProForma!$AF:$AF, MultiYear_ProForma!$B:$B, $B5, MultiYear_ProForma!$C:$C, "FY2029")+SUMIFS(MultiYear_ProForma!$AF:$AF, MultiYear_ProForma!$B:$B, $B5, MultiYear_ProForma!$C:$C, "FY2030"))/5 -> -2699596 | N5: =Control_Center!B33 -> Co‑Location @ Echo + Op Growth Targets | O5: =L5 - INDEX(L:L, MATCH("A_Repurpose_Both_ops", $B:$B, 0)) -> -1416125 | P5: =M5 - INDEX(M:M, MATCH("A_Repurpose_Both_ops", $B:$B, 0)) -> -966488.1
B6: =Scenarios!A9 -> A_Repurpose_Both_ops | C6: =INDEX(MultiYear_ProForma!$X$2:$X$61, MATCH(Scenarios!A9&"|FY2028", MultiYear_ProForma!$AG$2:$AG$61, 0)) -> 10058.225 | D6: =INDEX(MultiYear_ProForma!$X$2:$X$61, MATCH(Scenarios!A9&"|FY2030", MultiYear_ProForma!$AG$2:$AG$61, 0)) -> 9828.9577 | E6: =AVERAGE(INDEX(MultiYear_ProForma!$X$2:$X$61, MATCH(Scenarios!A9&"|FY2026", MultiYear_ProForma!$AG$2:$AG$61, 0)),INDEX(MultiYear_ProForma!$X$2:$X$61, MATCH(Scenarios!A9&"|FY2027", MultiYear_ProForma!$AG$2:$AG$61, 0)),INDEX(MultiYear_ProForma!$X$2:$X$61, MATCH(Scenarios!A9&"|FY2028", MultiYear_ProForma!$AG$2:$AG$61, 0))) -> 10525.438 | F6: =AVERAGE(INDEX(MultiYear_ProForma!$X$2:$X$61, MATCH(Scenarios!A9&"|FY2026", MultiYear_ProForma!$AG$2:$AG$61, 0)),INDEX(MultiYear_ProForma!$X$2:$X$61, MATCH(Scenarios!A9&"|FY2027", MultiYear_ProForma!$AG$2:$AG$61, 0)),INDEX(MultiYear_ProForma!$X$2:$X$61, MATCH(Scenarios!A9&"|FY2028", MultiYear_ProForma!$AG$2:$AG$61, 0)),INDEX(MultiYear_ProForma!$X$2:$X$61, MATCH(Scenarios!A9&"|FY2029", MultiYear_ProForma!$AG$2:$AG$61, 0)),INDEX(MultiYear_ProForma!$X$2:$X$61, MATCH(Scenarios!A9&"|FY2030", MultiYear_ProForma!$AG$2:$AG$61, 0))) -> 10240.363 | G6: =IFERROR(VLOOKUP($B6&"|FY2026", MultiYear_ProForma!$A:$AG, 14, FALSE), "") -> 553 | H6: =IFERROR(VLOOKUP($B6&"|FY2030", MultiYear_ProForma!$A:$AG, 6, FALSE) + VLOOKUP($B6&"|FY2030", MultiYear_ProForma!$A:$AG, 15, FALSE), "") -> 405.8 | I6: =Control_Center!C52 -> ++ | J6: =Control_Center!D52 -> Med | K6: =SUMIFS(MultiYear_ProForma!$AF:$AF, MultiYear_ProForma!$B:$B, $B6, MultiYear_ProForma!$C:$C, "FY2028") -> -1660026.1 | L6: =SUMIFS(MultiYear_ProForma!$AF:$AF, MultiYear_ProForma!$B:$B, $B6, MultiYear_ProForma!$C:$C, "FY2030") -> -1481484.6 | M6: =(SUMIFS(MultiYear_ProForma!$AF:$AF, MultiYear_ProForma!$B:$B, $B6, MultiYear_ProForma!$C:$C, "FY2026")+SUMIFS(MultiYear_ProForma!$AF:$AF, MultiYear_ProForma!$B:$B, $B6, MultiYear_ProForma!$C:$C, "FY2027")+SUMIFS(MultiYear_ProForma!$AF:$AF, MultiYear_ProForma!$B:$B, $B6, MultiYear_ProForma!$C:$C, "FY2028")+SUMIFS(MultiYear_ProForma!$AF:$AF, MultiYear_ProForma!$B:$B, $B6, MultiYear_ProForma!$C:$C, "FY2029")+SUMIFS(MultiYear_ProForma!$AF:$AF, MultiYear_ProForma!$B:$B, $B6, MultiYear_ProForma!$C:$C, "FY2030"))/5 -> -1733107.9 | N6: =Control_Center!B38 -> Repurpose BOTH (ops) | O6: =L6 - INDEX(L:L, MATCH("A_Repurpose_Both_ops", $B:$B, 0)) -> 0 | P6: =M6 - INDEX(M:M, MATCH("A_Repurpose_Both_ops", $B:$B, 0)) -> 0
B7: =Scenarios!A11 -> B_Repurpose_Echo_ops_PimaTargets | C7: =INDEX(MultiYear_ProForma!$X$2:$X$61, MATCH(Scenarios!A11&"|FY2028", MultiYear_ProForma!$AG$2:$AG$61, 0)) -> 10524.063 | D7: =INDEX(MultiYear_ProForma!$X$2:$X$61, MATCH(Scenarios!A11&"|FY2030", MultiYear_ProForma!$AG$2:$AG$61, 0)) -> 10843.739 | E7: =AVERAGE(INDEX(MultiYear_ProForma!$X$2:$X$61, MATCH(Scenarios!A11&"|FY2026", MultiYear_ProForma!$AG$2:$AG$61, 0)),INDEX(MultiYear_ProForma!$X$2:$X$61, MATCH(Scenarios!A11&"|FY2027", MultiYear_ProForma!$AG$2:$AG$61, 0)),INDEX(MultiYear_ProForma!$X$2:$X$61, MATCH(Scenarios!A11&"|FY2028", MultiYear_ProForma!$AG$2:$AG$61, 0))) -> 10480.436 | F7: =AVERAGE(INDEX(MultiYear_ProForma!$X$2:$X$61, MATCH(Scenarios!A11&"|FY2026", MultiYear_ProForma!$AG$2:$AG$61, 0)),INDEX(MultiYear_ProForma!$X$2:$X$61, MATCH(Scenarios!A11&"|FY2027", MultiYear_ProForma!$AG$2:$AG$61, 0)),INDEX(MultiYear_ProForma!$X$2:$X$61, MATCH(Scenarios!A11&"|FY2028", MultiYear_ProForma!$AG$2:$AG$61, 0)),INDEX(MultiYear_ProForma!$X$2:$X$61, MATCH(Scenarios!A11&"|FY2029", MultiYear_ProForma!$AG$2:$AG$61, 0)),INDEX(MultiYear_ProForma!$X$2:$X$61, MATCH(Scenarios!A11&"|FY2030", MultiYear_ProForma!$AG$2:$AG$61, 0))) -> 10583.513 | G7: =IFERROR(VLOOKUP($B7&"|FY2026", MultiYear_ProForma!$A:$AG, 14, FALSE), "") -> 257 | H7: =IFERROR(VLOOKUP($B7&"|FY2030", MultiYear_ProForma!$A:$AG, 6, FALSE) + VLOOKUP($B7&"|FY2030", MultiYear_ProForma!$A:$AG, 15, FALSE), "") -> 600.2 | I7: =Control_Center!C49 -> ++ | J7: =Control_Center!D49 -> Med | K7: =SUMIFS(MultiYear_ProForma!$AF:$AF, MultiYear_ProForma!$B:$B, $B7, MultiYear_ProForma!$C:$C, "FY2028") -> -2132577.8 | L7: =SUMIFS(MultiYear_ProForma!$AF:$AF, MultiYear_ProForma!$B:$B, $B7, MultiYear_ProForma!$C:$C, "FY2030") -> -2167489.8 | M7: =(SUMIFS(MultiYear_ProForma!$AF:$AF, MultiYear_ProForma!$B:$B, $B7, MultiYear_ProForma!$C:$C, "FY2026")+SUMIFS(MultiYear_ProForma!$AF:$AF, MultiYear_ProForma!$B:$B, $B7, MultiYear_ProForma!$C:$C, "FY2027")+SUMIFS(MultiYear_ProForma!$AF:$AF, MultiYear_ProForma!$B:$B, $B7, MultiYear_ProForma!$C:$C, "FY2028")+SUMIFS(MultiYear_ProForma!$AF:$AF, MultiYear_ProForma!$B:$B, $B7, MultiYear_ProForma!$C:$C, "FY2029")+SUMIFS(MultiYear_ProForma!$AF:$AF, MultiYear_ProForma!$B:$B, $B7, MultiYear_ProForma!$C:$C, "FY2030"))/5 -> -2166664.6 | N7: =Control_Center!B40 -> Repurpose ECHO (ops) + Status-Quo Pima + Pima Op Growth Targets | O7: =L7 - INDEX(L:L, MATCH("A_Repurpose_Both_ops", $B:$B, 0)) -> -686005.22 | P7: =M7 - INDEX(M:M, MATCH("A_Repurpose_Both_ops", $B:$B, 0)) -> -433556.71
B8: =Scenarios!A5 -> D_Grow_Both_Targets | C8: =INDEX(MultiYear_ProForma!$X$2:$X$61, MATCH(Scenarios!A5&"|FY2028", MultiYear_ProForma!$AG$2:$AG$61, 0)) -> 10617.926 | D8: =INDEX(MultiYear_ProForma!$X$2:$X$61, MATCH(Scenarios!A5&"|FY2030", MultiYear_ProForma!$AG$2:$AG$61, 0)) -> 11155.459 | E8: =AVERAGE(INDEX(MultiYear_ProForma!$X$2:$X$61, MATCH(Scenarios!A5&"|FY2026", MultiYear_ProForma!$AG$2:$AG$61, 0)),INDEX(MultiYear_ProForma!$X$2:$X$61, MATCH(Scenarios!A5&"|FY2027", MultiYear_ProForma!$AG$2:$AG$61, 0)),INDEX(MultiYear_ProForma!$X$2:$X$61, MATCH(Scenarios!A5&"|FY2028", MultiYear_ProForma!$AG$2:$AG$61, 0))) -> 10361.058 | F8: =AVERAGE(INDEX(MultiYear_ProForma!$X$2:$X$61, MATCH(Scenarios!A5&"|FY2026", MultiYear_ProForma!$AG$2:$AG$61, 0)),INDEX(MultiYear_ProForma!$X$2:$X$61, MATCH(Scenarios!A5&"|FY2027", MultiYear_ProForma!$AG$2:$AG$61, 0)),INDEX(MultiYear_ProForma!$X$2:$X$61, MATCH(Scenarios!A5&"|FY2028", MultiYear_ProForma!$AG$2:$AG$61, 0)),INDEX(MultiYear_ProForma!$X$2:$X$61, MATCH(Scenarios!A5&"|FY2029", MultiYear_ProForma!$AG$2:$AG$61, 0)),INDEX(MultiYear_ProForma!$X$2:$X$61, MATCH(Scenarios!A5&"|FY2030", MultiYear_ProForma!$AG$2:$AG$61, 0))) -> 10624.401 | G8: =IFERROR(VLOOKUP($B8&"|FY2026", MultiYear_ProForma!$A:$AG, 14, FALSE), "") -> 0 | H8: =IFERROR(VLOOKUP($B8&"|FY2030", MultiYear_ProForma!$A:$AG, 6, FALSE) + VLOOKUP($B8&"|FY2030", MultiYear_ProForma!$A:$AG, 15, FALSE), "") -> 803 | I8: =Control_Center!C56 -> o | J8: =Control_Center!D56 -> Low-Med | K8: =SUMIFS(MultiYear_ProForma!$AF:$AF, MultiYear_ProForma!$B:$B, $B8, MultiYear_ProForma!$C:$C, "FY2028") -> -2730501.4 | L8: =SUMIFS(MultiYear_ProForma!$AF:$AF, MultiYear_ProForma!$B:$B, $B8, MultiYear_ProForma!$C:$C, "FY2030") -> -2942124.2 | M8: =(SUMIFS(MultiYear_ProForma!$AF:$AF, MultiYear_ProForma!$B:$B, $B8, MultiYear_ProForma!$C:$C, "FY2026")+SUMIFS(MultiYear_ProForma!$AF:$AF, MultiYear_ProForma!$B:$B, $B8, MultiYear_ProForma!$C:$C, "FY2027")+SUMIFS(MultiYear_ProForma!$AF:$AF, MultiYear_ProForma!$B:$B, $B8, MultiYear_ProForma!$C:$C, "FY2028")+SUMIFS(MultiYear_ProForma!$AF:$AF, MultiYear_ProForma!$B:$B, $B8, MultiYear_ProForma!$C:$C, "FY2029")+SUMIFS(MultiYear_ProForma!$AF:$AF, MultiYear_ProForma!$B:$B, $B8, MultiYear_ProForma!$C:$C, "FY2030"))/5 -> -2733446.3 | N8: =Control_Center!B34 -> Grow Both + Op Growth Targets | O8: =L8 - INDEX(L:L, MATCH("A_Repurpose_Both_ops", $B:$B, 0)) -> -1460639.6 | P8: =M8 - INDEX(M:M, MATCH("A_Repurpose_Both_ops", $B:$B, 0)) -> -1000338.4
B9: =Scenarios!A12 -> C_Repurpose_Pima_lease_EchoGHub_EchoTargets | C9: =INDEX(MultiYear_ProForma!$X$2:$X$61, MATCH(Scenarios!A12&"|FY2028", MultiYear_ProForma!$AG$2:$AG$61, 0)) -> 10556.357 | D9: =INDEX(MultiYear_ProForma!$X$2:$X$61, MATCH(Scenarios!A12&"|FY2030", MultiYear_ProForma!$AG$2:$AG$61, 0)) -> 10578.771 | E9: =AVERAGE(INDEX(MultiYear_ProForma!$X$2:$X$61, MATCH(Scenarios!A12&"|FY2026", MultiYear_ProForma!$AG$2:$AG$61, 0)),INDEX(MultiYear_ProForma!$X$2:$X$61, MATCH(Scenarios!A12&"|FY2027", MultiYear_ProForma!$AG$2:$AG$61, 0)),INDEX(MultiYear_ProForma!$X$2:$X$61, MATCH(Scenarios!A12&"|FY2028", MultiYear_ProForma!$AG$2:$AG$61, 0))) -> 10725.514 | F9: =AVERAGE(INDEX(MultiYear_ProForma!$X$2:$X$61, MATCH(Scenarios!A12&"|FY2026", MultiYear_ProForma!$AG$2:$AG$61, 0)),INDEX(MultiYear_ProForma!$X$2:$X$61, MATCH(Scenarios!A12&"|FY2027", MultiYear_ProForma!$AG$2:$AG$61, 0)),INDEX(MultiYear_ProForma!$X$2:$X$61, MATCH(Scenarios!A12&"|FY2028", MultiYear_ProForma!$AG$2:$AG$61, 0)),INDEX(MultiYear_ProForma!$X$2:$X$61, MATCH(Scenarios!A12&"|FY2029", MultiYear_ProForma!$AG$2:$AG$61, 0)),INDEX(MultiYear_ProForma!$X$2:$X$61, MATCH(Scenarios!A12&"|FY2030", MultiYear_ProForma!$AG$2:$AG$61, 0))) -> 10635.725 | G9: =IFERROR(VLOOKUP($B9&"|FY2026", MultiYear_ProForma!$A:$AG, 14, FALSE), "") -> 296 | H9: =IFERROR(VLOOKUP($B9&"|FY2030", MultiYear_ProForma!$A:$AG, 6, FALSE) + VLOOKUP($B9&"|FY2030", MultiYear_ProForma!$A:$AG, 15, FALSE), "") -> 508.6 | I9: =Control_Center!C53 -> -- | J9: =Control_Center!D53 -> Low | K9: =SUMIFS(MultiYear_ProForma!$AF:$AF, MultiYear_ProForma!$B:$B, $B9, MultiYear_ProForma!$C:$C, "FY2028") -> -2333905.4 | L9: =SUMIFS(MultiYear_ProForma!$AF:$AF, MultiYear_ProForma!$B:$B, $B9, MultiYear_ProForma!$C:$C, "FY2030") -> -2238139.4 | M9: =(SUMIFS(MultiYear_ProForma!$AF:$AF, MultiYear_ProForma!$B:$B, $B9, MultiYear_ProForma!$C:$C, "FY2026")+SUMIFS(MultiYear_ProForma!$AF:$AF, MultiYear_ProForma!$B:$B, $B9, MultiYear_ProForma!$C:$C, "FY2027")+SUMIFS(MultiYear_ProForma!$AF:$AF, MultiYear_ProForma!$B:$B, $B9, MultiYear_ProForma!$C:$C, "FY2028")+SUMIFS(MultiYear_ProForma!$AF:$AF, MultiYear_ProForma!$B:$B, $B9, MultiYear_ProForma!$C:$C, "FY2029")+SUMIFS(MultiYear_ProForma!$AF:$AF, MultiYear_ProForma!$B:$B, $B9, MultiYear_ProForma!$C:$C, "FY2030"))/5 -> -2373231.4 | N9: =Control_Center!B41 -> Repurpose PIMA (lease) + Growth Hub @ Echo + Echo Op Growth Targets | O9: =L9 - INDEX(L:L, MATCH("A_Repurpose_Both_ops", $B:$B, 0)) -> -756654.75 | P9: =M9 - INDEX(M:M, MATCH("A_Repurpose_Both_ops", $B:$B, 0)) -> -640123.55
B10: =Scenarios!A10 -> B_Repurpose_Echo_lease_PimaTargets | C10: =INDEX(MultiYear_ProForma!$X$2:$X$61, MATCH(Scenarios!A10&"|FY2028", MultiYear_ProForma!$AG$2:$AG$61, 0)) -> 11312.687 | D10: =INDEX(MultiYear_ProForma!$X$2:$X$61, MATCH(Scenarios!A10&"|FY2030", MultiYear_ProForma!$AG$2:$AG$61, 0)) -> 11430.333 | E10: =AVERAGE(INDEX(MultiYear_ProForma!$X$2:$X$61, MATCH(Scenarios!A10&"|FY2026", MultiYear_ProForma!$AG$2:$AG$61, 0)),INDEX(MultiYear_ProForma!$X$2:$X$61, MATCH(Scenarios!A10&"|FY2027", MultiYear_ProForma!$AG$2:$AG$61, 0)),INDEX(MultiYear_ProForma!$X$2:$X$61, MATCH(Scenarios!A10&"|FY2028", MultiYear_ProForma!$AG$2:$AG$61, 0))) -> 11424.812 | F10: =AVERAGE(INDEX(MultiYear_ProForma!$X$2:$X$61, MATCH(Scenarios!A10&"|FY2026", MultiYear_ProForma!$AG$2:$AG$61, 0)),INDEX(MultiYear_ProForma!$X$2:$X$61, MATCH(Scenarios!A10&"|FY2027", MultiYear_ProForma!$AG$2:$AG$61, 0)),INDEX(MultiYear_ProForma!$X$2:$X$61, MATCH(Scenarios!A10&"|FY2028", MultiYear_ProForma!$AG$2:$AG$61, 0)),INDEX(MultiYear_ProForma!$X$2:$X$61, MATCH(Scenarios!A10&"|FY2029", MultiYear_ProForma!$AG$2:$AG$61, 0)),INDEX(MultiYear_ProForma!$X$2:$X$61, MATCH(Scenarios!A10&"|FY2030", MultiYear_ProForma!$AG$2:$AG$61, 0))) -> 11385.465 | G10: =IFERROR(VLOOKUP($B10&"|FY2026", MultiYear_ProForma!$A:$AG, 14, FALSE), "") -> 257 | H10: =IFERROR(VLOOKUP($B10&"|FY2030", MultiYear_ProForma!$A:$AG, 6, FALSE) + VLOOKUP($B10&"|FY2030", MultiYear_ProForma!$A:$AG, 15, FALSE), "") -> 450.2 | I10: =Control_Center!C54 -> - | J10: =Control_Center!D54 -> Low-Med | K10: =SUMIFS(MultiYear_ProForma!$AF:$AF, MultiYear_ProForma!$B:$B, $B10, MultiYear_ProForma!$C:$C, "FY2028") -> -2406414.6 | L10: =SUMIFS(MultiYear_ProForma!$AF:$AF, MultiYear_ProForma!$B:$B, $B10, MultiYear_ProForma!$C:$C, "FY2030") -> -2364518.4 | M10: =(SUMIFS(MultiYear_ProForma!$AF:$AF, MultiYear_ProForma!$B:$B, $B10, MultiYear_ProForma!$C:$C, "FY2026")+SUMIFS(MultiYear_ProForma!$AF:$AF, MultiYear_ProForma!$B:$B, $B10, MultiYear_ProForma!$C:$C, "FY2027")+SUMIFS(MultiYear_ProForma!$AF:$AF, MultiYear_ProForma!$B:$B, $B10, MultiYear_ProForma!$C:$C, "FY2028")+SUMIFS(MultiYear_ProForma!$AF:$AF, MultiYear_ProForma!$B:$B, $B10, MultiYear_ProForma!$C:$C, "FY2029")+SUMIFS(MultiYear_ProForma!$AF:$AF, MultiYear_ProForma!$B:$B, $B10, MultiYear_ProForma!$C:$C, "FY2030"))/5 -> -2438258.1 | N10: =Control_Center!B39 -> Repurpose ECHO (lease) + Status-Quo Pima + Pima Op Growth Targets | O10: =L10 - INDEX(L:L, MATCH("A_Repurpose_Both_ops", $B:$B, 0)) -> -883033.74 | P10: =M10 - INDEX(M:M, MATCH("A_Repurpose_Both_ops", $B:$B, 0)) -> -705150.21
B11: =Scenarios!A3 -> E_StatusQuo_Targets | C11: =INDEX(MultiYear_ProForma!$X$2:$X$61, MATCH(Scenarios!A3&"|FY2028", MultiYear_ProForma!$AG$2:$AG$61, 0)) -> 11176.369 | D11: =INDEX(MultiYear_ProForma!$X$2:$X$61, MATCH(Scenarios!A3&"|FY2030", MultiYear_ProForma!$AG$2:$AG$61, 0)) -> 11742.173 | E11: =AVERAGE(INDEX(MultiYear_ProForma!$X$2:$X$61, MATCH(Scenarios!A3&"|FY2026", MultiYear_ProForma!$AG$2:$AG$61, 0)),INDEX(MultiYear_ProForma!$X$2:$X$61, MATCH(Scenarios!A3&"|FY2027", MultiYear_ProForma!$AG$2:$AG$61, 0)),INDEX(MultiYear_ProForma!$X$2:$X$61, MATCH(Scenarios!A3&"|FY2028", MultiYear_ProForma!$AG$2:$AG$61, 0))) -> 10905.991 | F11: =AVERAGE(INDEX(MultiYear_ProForma!$X$2:$X$61, MATCH(Scenarios!A3&"|FY2026", MultiYear_ProForma!$AG$2:$AG$61, 0)),INDEX(MultiYear_ProForma!$X$2:$X$61, MATCH(Scenarios!A3&"|FY2027", MultiYear_ProForma!$AG$2:$AG$61, 0)),INDEX(MultiYear_ProForma!$X$2:$X$61, MATCH(Scenarios!A3&"|FY2028", MultiYear_ProForma!$AG$2:$AG$61, 0)),INDEX(MultiYear_ProForma!$X$2:$X$61, MATCH(Scenarios!A3&"|FY2029", MultiYear_ProForma!$AG$2:$AG$61, 0)),INDEX(MultiYear_ProForma!$X$2:$X$61, MATCH(Scenarios!A3&"|FY2030", MultiYear_ProForma!$AG$2:$AG$61, 0))) -> 11183.185 | G11: =IFERROR(VLOOKUP($B11&"|FY2026", MultiYear_ProForma!$A:$AG, 14, FALSE), "") -> 0 | H11: =IFERROR(VLOOKUP($B11&"|FY2030", MultiYear_ProForma!$A:$AG, 6, FALSE) + VLOOKUP($B11&"|FY2030", MultiYear_ProForma!$A:$AG, 15, FALSE), "") -> 703 | I11: =Control_Center!C58 -> o | J11: =Control_Center!D58 -> Low-Med | K11: =SUMIFS(MultiYear_ProForma!$AF:$AF, MultiYear_ProForma!$B:$B, $B11, MultiYear_ProForma!$C:$C, "FY2028") -> -3059566.1 | L11: =SUMIFS(MultiYear_ProForma!$AF:$AF, MultiYear_ProForma!$B:$B, $B11, MultiYear_ProForma!$C:$C, "FY2030") -> -3278708.1 | M11: =(SUMIFS(MultiYear_ProForma!$AF:$AF, MultiYear_ProForma!$B:$B, $B11, MultiYear_ProForma!$C:$C, "FY2026")+SUMIFS(MultiYear_ProForma!$AF:$AF, MultiYear_ProForma!$B:$B, $B11, MultiYear_ProForma!$C:$C, "FY2027")+SUMIFS(MultiYear_ProForma!$AF:$AF, MultiYear_ProForma!$B:$B, $B11, MultiYear_ProForma!$C:$C, "FY2028")+SUMIFS(MultiYear_ProForma!$AF:$AF, MultiYear_ProForma!$B:$B, $B11, MultiYear_ProForma!$C:$C, "FY2029")+SUMIFS(MultiYear_ProForma!$AF:$AF, MultiYear_ProForma!$B:$B, $B11, MultiYear_ProForma!$C:$C, "FY2030"))/5 -> -3062552.2 | N11: =Control_Center!B32 -> Status‑Quo + Op Growth Targets | O11: =L11 - INDEX(L:L, MATCH("A_Repurpose_Both_ops", $B:$B, 0)) -> -1797223.5 | P11: =M11 - INDEX(M:M, MATCH("A_Repurpose_Both_ops", $B:$B, 0)) -> -1329444.4
B12: =Scenarios!A7 -> G_EchoGHubRamp_PimaTargets | C12: =INDEX(MultiYear_ProForma!$X$2:$X$61, MATCH(Scenarios!A7&"|FY2028", MultiYear_ProForma!$AG$2:$AG$61, 0)) -> 11176.369 | D12: =INDEX(MultiYear_ProForma!$X$2:$X$61, MATCH(Scenarios!A7&"|FY2030", MultiYear_ProForma!$AG$2:$AG$61, 0)) -> 11742.173 | E12: =AVERAGE(INDEX(MultiYear_ProForma!$X$2:$X$61, MATCH(Scenarios!A7&"|FY2026", MultiYear_ProForma!$AG$2:$AG$61, 0)),INDEX(MultiYear_ProForma!$X$2:$X$61, MATCH(Scenarios!A7&"|FY2027", MultiYear_ProForma!$AG$2:$AG$61, 0)),INDEX(MultiYear_ProForma!$X$2:$X$61, MATCH(Scenarios!A7&"|FY2028", MultiYear_ProForma!$AG$2:$AG$61, 0))) -> 11253.597 | F12: =AVERAGE(INDEX(MultiYear_ProForma!$X$2:$X$61, MATCH(Scenarios!A7&"|FY2026", MultiYear_ProForma!$AG$2:$AG$61, 0)),INDEX(MultiYear_ProForma!$X$2:$X$61, MATCH(Scenarios!A7&"|FY2027", MultiYear_ProForma!$AG$2:$AG$61, 0)),INDEX(MultiYear_ProForma!$X$2:$X$61, MATCH(Scenarios!A7&"|FY2028", MultiYear_ProForma!$AG$2:$AG$61, 0)),INDEX(MultiYear_ProForma!$X$2:$X$61, MATCH(Scenarios!A7&"|FY2029", MultiYear_ProForma!$AG$2:$AG$61, 0)),INDEX(MultiYear_ProForma!$X$2:$X$61, MATCH(Scenarios!A7&"|FY2030", MultiYear_ProForma!$AG$2:$AG$61, 0))) -> 11391.748 | G12: =IFERROR(VLOOKUP($B12&"|FY2026", MultiYear_ProForma!$A:$AG, 14, FALSE), "") -> 0 | H12: =IFERROR(VLOOKUP($B12&"|FY2030", MultiYear_ProForma!$A:$AG, 6, FALSE) + VLOOKUP($B12&"|FY2030", MultiYear_ProForma!$A:$AG, 15, FALSE), "") -> 703 | I12: =Control_Center!C55 -> - | J12: =Control_Center!D55 -> Low-Med | K12: =SUMIFS(MultiYear_ProForma!$AF:$AF, MultiYear_ProForma!$B:$B, $B12, MultiYear_ProForma!$C:$C, "FY2028") -> -3059566.1 | L12: =SUMIFS(MultiYear_ProForma!$AF:$AF, MultiYear_ProForma!$B:$B, $B12, MultiYear_ProForma!$C:$C, "FY2030") -> -3278708.1 | M12: =(SUMIFS(MultiYear_ProForma!$AF:$AF, MultiYear_ProForma!$B:$B, $B12, MultiYear_ProForma!$C:$C, "FY2026")+SUMIFS(MultiYear_ProForma!$AF:$AF, MultiYear_ProForma!$B:$B, $B12, MultiYear_ProForma!$C:$C, "FY2027")+SUMIFS(MultiYear_ProForma!$AF:$AF, MultiYear_ProForma!$B:$B, $B12, MultiYear_ProForma!$C:$C, "FY2028")+SUMIFS(MultiYear_ProForma!$AF:$AF, MultiYear_ProForma!$B:$B, $B12, MultiYear_ProForma!$C:$C, "FY2029")+SUMIFS(MultiYear_ProForma!$AF:$AF, MultiYear_ProForma!$B:$B, $B12, MultiYear_ProForma!$C:$C, "FY2030"))/5 -> -3159431.1 | N12: =Control_Center!B36 -> Growth Hub @ Echo + Status-Quo Pima + Op Growth Targets | O12: =L12 - INDEX(L:L, MATCH("A_Repurpose_Both_ops", $B:$B, 0)) -> -1797223.5 | P12: =M12 - INDEX(M:M, MATCH("A_Repurpose_Both_ops", $B:$B, 0)) -> -1426323.2
B13: =Scenarios!A6 -> D_CUSTOM2 | C13: =INDEX(MultiYear_ProForma!$X$2:$X$61, MATCH(Scenarios!A6&"|FY2028", MultiYear_ProForma!$AG$2:$AG$61, 0)) -> 12392.725 | D13: =INDEX(MultiYear_ProForma!$X$2:$X$61, MATCH(Scenarios!A6&"|FY2030", MultiYear_ProForma!$AG$2:$AG$61, 0)) -> 13020.107 | E13: =AVERAGE(INDEX(MultiYear_ProForma!$X$2:$X$61, MATCH(Scenarios!A6&"|FY2026", MultiYear_ProForma!$AG$2:$AG$61, 0)),INDEX(MultiYear_ProForma!$X$2:$X$61, MATCH(Scenarios!A6&"|FY2027", MultiYear_ProForma!$AG$2:$AG$61, 0)),INDEX(MultiYear_ProForma!$X$2:$X$61, MATCH(Scenarios!A6&"|FY2028", MultiYear_ProForma!$AG$2:$AG$61, 0))) -> 12092.921 | F13: =AVERAGE(INDEX(MultiYear_ProForma!$X$2:$X$61, MATCH(Scenarios!A6&"|FY2026", MultiYear_ProForma!$AG$2:$AG$61, 0)),INDEX(MultiYear_ProForma!$X$2:$X$61, MATCH(Scenarios!A6&"|FY2027", MultiYear_ProForma!$AG$2:$AG$61, 0)),INDEX(MultiYear_ProForma!$X$2:$X$61, MATCH(Scenarios!A6&"|FY2028", MultiYear_ProForma!$AG$2:$AG$61, 0)),INDEX(MultiYear_ProForma!$X$2:$X$61, MATCH(Scenarios!A6&"|FY2029", MultiYear_ProForma!$AG$2:$AG$61, 0)),INDEX(MultiYear_ProForma!$X$2:$X$61, MATCH(Scenarios!A6&"|FY2030", MultiYear_ProForma!$AG$2:$AG$61, 0))) -> 12400.282 | G13: =IFERROR(VLOOKUP($B13&"|FY2026", MultiYear_ProForma!$A:$AG, 14, FALSE), "") -> 0 | H13: =IFERROR(VLOOKUP($B13&"|FY2030", MultiYear_ProForma!$A:$AG, 6, FALSE) + VLOOKUP($B13&"|FY2030", MultiYear_ProForma!$A:$AG, 15, FALSE), "") -> 553 | I13: =Control_Center!C51 -> + | J13: =Control_Center!D51 -> Med | K13: =SUMIFS(MultiYear_ProForma!$AF:$AF, MultiYear_ProForma!$B:$B, $B13, MultiYear_ProForma!$C:$C, "FY2028") -> -3553163.1 | L13: =SUMIFS(MultiYear_ProForma!$AF:$AF, MultiYear_ProForma!$B:$B, $B13, MultiYear_ProForma!$C:$C, "FY2030") -> -3783584 | M13: =(SUMIFS(MultiYear_ProForma!$AF:$AF, MultiYear_ProForma!$B:$B, $B13, MultiYear_ProForma!$C:$C, "FY2026")+SUMIFS(MultiYear_ProForma!$AF:$AF, MultiYear_ProForma!$B:$B, $B13, MultiYear_ProForma!$C:$C, "FY2027")+SUMIFS(MultiYear_ProForma!$AF:$AF, MultiYear_ProForma!$B:$B, $B13, MultiYear_ProForma!$C:$C, "FY2028")+SUMIFS(MultiYear_ProForma!$AF:$AF, MultiYear_ProForma!$B:$B, $B13, MultiYear_ProForma!$C:$C, "FY2029")+SUMIFS(MultiYear_ProForma!$AF:$AF, MultiYear_ProForma!$B:$B, $B13, MultiYear_ProForma!$C:$C, "FY2030"))/5 -> -3556211.2 | N13: =Control_Center!B35 -> CUSTOM_KeepOpen_v2 | O13: =L13 - INDEX(L:L, MATCH("A_Repurpose_Both_ops", $B:$B, 0)) -> -2302099.4 | P13: =M13 - INDEX(M:M, MATCH("A_Repurpose_Both_ops", $B:$B, 0)) -> -1823103.3
B14: =Scenarios!A2 -> D_CUSTOM1 | C14: =INDEX(MultiYear_ProForma!$X$2:$X$61, MATCH(Scenarios!A2&"|FY2028", MultiYear_ProForma!$AG$2:$AG$61, 0)) -> 12392.725 | D14: =INDEX(MultiYear_ProForma!$X$2:$X$61, MATCH(Scenarios!A2&"|FY2030", MultiYear_ProForma!$AG$2:$AG$61, 0)) -> 13020.107 | E14: =AVERAGE(INDEX(MultiYear_ProForma!$X$2:$X$61, MATCH(Scenarios!A2&"|FY2026", MultiYear_ProForma!$AG$2:$AG$61, 0)),INDEX(MultiYear_ProForma!$X$2:$X$61, MATCH(Scenarios!A2&"|FY2027", MultiYear_ProForma!$AG$2:$AG$61, 0)),INDEX(MultiYear_ProForma!$X$2:$X$61, MATCH(Scenarios!A2&"|FY2028", MultiYear_ProForma!$AG$2:$AG$61, 0))) -> 12092.921 | F14: =AVERAGE(INDEX(MultiYear_ProForma!$X$2:$X$61, MATCH(Scenarios!A2&"|FY2026", MultiYear_ProForma!$AG$2:$AG$61, 0)),INDEX(MultiYear_ProForma!$X$2:$X$61, MATCH(Scenarios!A2&"|FY2027", MultiYear_ProForma!$AG$2:$AG$61, 0)),INDEX(MultiYear_ProForma!$X$2:$X$61, MATCH(Scenarios!A2&"|FY2028", MultiYear_ProForma!$AG$2:$AG$61, 0)),INDEX(MultiYear_ProForma!$X$2:$X$61, MATCH(Scenarios!A2&"|FY2029", MultiYear_ProForma!$AG$2:$AG$61, 0)),INDEX(MultiYear_ProForma!$X$2:$X$61, MATCH(Scenarios!A2&"|FY2030", MultiYear_ProForma!$AG$2:$AG$61, 0))) -> 12400.282 | G14: =IFERROR(VLOOKUP($B14&"|FY2026", MultiYear_ProForma!$A:$AG, 14, FALSE), "") -> 0 | H14: =IFERROR(VLOOKUP($B14&"|FY2030", MultiYear_ProForma!$A:$AG, 6, FALSE) + VLOOKUP($B14&"|FY2030", MultiYear_ProForma!$A:$AG, 15, FALSE), "") -> 553 | I14: =Control_Center!C57 -> - | J14: =Control_Center!D57 -> Low-Med | K14: =SUMIFS(MultiYear_ProForma!$AF:$AF, MultiYear_ProForma!$B:$B, $B14, MultiYear_ProForma!$C:$C, "FY2028") -> -3553163.1 | L14: =SUMIFS(MultiYear_ProForma!$AF:$AF, MultiYear_ProForma!$B:$B, $B14, MultiYear_ProForma!$C:$C, "FY2030") -> -3783584 | M14: =(SUMIFS(MultiYear_ProForma!$AF:$AF, MultiYear_ProForma!$B:$B, $B14, MultiYear_ProForma!$C:$C, "FY2026")+SUMIFS(MultiYear_ProForma!$AF:$AF, MultiYear_ProForma!$B:$B, $B14, MultiYear_ProForma!$C:$C, "FY2027")+SUMIFS(MultiYear_ProForma!$AF:$AF, MultiYear_ProForma!$B:$B, $B14, MultiYear_ProForma!$C:$C, "FY2028")+SUMIFS(MultiYear_ProForma!$AF:$AF, MultiYear_ProForma!$B:$B, $B14, MultiYear_ProForma!$C:$C, "FY2029")+SUMIFS(MultiYear_ProForma!$AF:$AF, MultiYear_ProForma!$B:$B, $B14, MultiYear_ProForma!$C:$C, "FY2030"))/5 -> -3556211.2 | N14: =Control_Center!B31 -> CUSTOM_KeepOpen_v1 | O14: =L14 - INDEX(L:L, MATCH("A_Repurpose_Both_ops", $B:$B, 0)) -> -2302099.4 | P14: =M14 - INDEX(M:M, MATCH("A_Repurpose_Both_ops", $B:$B, 0)) -> -1823103.3

Sheet Definitions_Sources
B2: Parameter / input | C2: Description / how we used it | D2: Public source & how derived | E2: What to request to confirm / refine
B3: ADM | C3: ADM stands for Average Daily Membership. It is the primary metric used by the state of Arizona to determine funding for a school district. What it is: ADM is essentially the official student count. It is not based on how many students are present on any single day (that would be average daily attendance), but rather on how many students are officially enrolled in the district. | D3: How it's calculated: The state uses enrollment data from specific points in the school year to generate an average. This average, the ADM, becomes the official "student count" for that fiscal year. Why it matters: Nearly all state funding is allocated on a per-student basis using ADM. This number is multiplied by various weights (e.g., for high school students, special education, etc.) to create a "weighted student count," which is the foundational number for calculating the district's total state aid. An audit of SUSD's ADM, for example, is a check to ensure the district reported its enrollment correctly and received the proper amount of funding.
B4: M&O | C4: M&O stands for Maintenance and Operations. This is the largest and most important part of a school district's budget. What it is: The M&O budget is the "bucket" of money that pays for all the day-to-day, non-capital expenses of running the school district. It is the district's operating budget. | D4: What it pays for: Salaries and benefits for all employees (teachers, principals, support staff, administrators) Classroom supplies (textbooks, software, paper, etc.) Utilities (electricity, water, gas) Transportation (bus fuel and maintenance) Student services and athletics
B5: Base state aid per pupil (FY2025) | C5: Revenue per ADM in “Aid per ADM” line; grown by CPI in out‑years (model uses a placeholder near $5.1k) | D5: Arizona FY2025 budget bill (HB 2906) sets the base level per pupil at $5,013 for FY2025. Arizona Senate Issue Brief – K‑12 School Finance (official, widely used reference). Shows the Base Level Amount (FY 2024‑25 = $5,013.33), the factor that (with district weights) drives state aid. ADE lists the same figure in its finance materials. | E5: ADE School Finance memo for FY2025 base level (final), plus any FY2026 update; SUSD’s per‑pupil revenue schedule (by weight) if you want to add K‑8 weights locally.
B6: Echo Canyon base ADM (≈257) | C6: Baseline students “served” in keep‑open scenarios | D6: ADE School Report Cards / Arizona Education Profiles (school pages) + SUSD 40th‑day board reports for Echo Canyon’s latest K‑8 enrollment ADE school page data used. | E6: SUSD October (40th‑day) ADM sheet listing Echo Canyon K‑8 ADM (most recent year) and the same for the prior 3 years.
B7: Pima base ADM (≈296) | C7: Baseline students “served” in keep‑open scenarios | D7: ADE School Report Cards page for Pima Traditional (enrollment tile). The “Enrollment” 🛈 on that page for the specific year has enrollment data. | E7: Same 40th‑day ADM sheet as above, for Pima K‑8.
B8: District M&O (Fund 001) context | C8: Grounds the “M&O per ADM” baseline used in comparable $/student | D8: Scottsdale USD ACFR FY2024 (annual comprehensive financial report) — Fund statements and notes establish M&O (Fund 001) totals and function splits (instruction, plant ops, admin, etc.). We used it to sanity‑check the order of magnitude for per‑pupil operating cost. (Scottsdale Unified School District) | E8: From ACFR or adopted budget: Fund 001 totals and function detail by object/function; district ADM used in budget; site‑level M&O if available.
B9: “Fixed‑like” share of M&O ≈ 30–40% (used 30% as a conservative placeholder) | C9: Splits total M&O into “semi‑fixed” (plant ops, insurance, admin, central) vs “variable” (classroom sections, supplies, a slice of transport) to compute EchoFixed$ and PimaFixed$ | D9: Arizona Auditor General – Arizona School District Spending – FY2024 portal (official statewide analysis). The Overview and category definitions show the functional buckets (instruction, administration, plant operations & maintenance, student support, etc.) districts report and that we treat as the “more fixed‑like” categories. (sdspending.azauditor.gov) | E9: SUSD site‑level: plant ops/maintenance, insurance, utilities, admin FTE & benefits at Echo/Pima. Use that to replace the 30% proxy with real fixed amounts. The file allocates the fixed share across the two schools pro‑rata (by base ADM) as a temporary step. Replace with the actual plant ops/insurance/utilities/admin for each site from Fund 001 to remove that simplification.
B10: M&O Inflation
B11: AID inflation
B12: Overlay | C12: Using this term in the spreadsheet to mean growth of new students | D12: Not an official district term; just using in this spreadsheet
B13: Variable unit cost (VarUnit$) | C13: $ per student applied to “served ADM,” plus marginal‑cost factor on overlay seats | D13: Assumption derived from Fund 001 minus fixed share, divided by total ADM; then Marginal factor (see below) reduces cost for overlay seats. | E13: SUSD staffing ratios & actual sectioning at K–8; confirm what portion of M&O truly scales with added sections (teachers, aides, supplies, a slice of transport).
B14: Marginal‑cost factor for overlay seats (0.50) | C14: Applies only to overlay growth students in keep‑open scenarios; models that not every dollar is average cost | D14: Assumption w/ rationale: Roughly half of per‑pupil cost is staffing/supplies/transport that scale with sections; the remainder is semi‑fixed plant/admin. This aligns with Auditor General function splits and is intentionally conservative. We’ll replace with SUSD’s staffing & plant data if provided. (Sun Devil Central) | E14: SUSD’s teacher‑section & aide staffing rules, average class sizes, and any marginal staffing adders at K–8 (arts, specialists).
B15: Receiving overhead “h” (FY26 $1,000 → FY30 $300) | C15: Per retained student transition/route/admin cost added when a site is repurposed; tapers as routes stabilize | D15: Assumption with AZ context: AZ districts’ transport spend per rider is often $2k–$3k (statewide average $2,862 cited in a district budget narrative), so $1,000 tapering to $300 is a conservative placeholder for incremental cost, not full bus cost. | E15: SUSD transportation cost per route-hour, average riders per route, and the specific route changes proposed in the repurpose option. | F15: Transportation / receiving overhead order‑of‑magnitude | G15: Our h parameter adds incremental per‑retained‑student cost (routing/transition/admin) only when a repurpose occurs, tapering as routes stabilize | H15: AAG district audits show cost per rider varies (several audited districts fall near $900–$1,100 per rider; others higher depending on geography), demonstrating the right order of magnitude for incremental routing burden. Examples: Safford USD 2022 $893 per rider; Snowflake USD 2023 $1,008 per rider. | I15: Keeping h = $1,000 → $300 (FY26→FY30) is defensible as incremental overhead, not full bus cost. Leave Parameters!h_FY values editable; note they should be zero in keep‑open scenarios (no forced transfers).
B16: Retention rate “r” (central 0.75; sensitivities 0.65–0.85) | C16: Share of displaced Echo+Pima students who remain in SUSD (the rest leave to charters/other districts) | D16: Assumption, benchmarked to closure research: large‑district closure work (e.g., Chicago) shows most students remain in‑district the next year (CPS analyses place that figure well above half); retention varies with hand‑off quality and distance. We model 65–85% to bracket. (UChicago Consortium on School Research) Large‑district evidence: UChicago Consortium’s analyses of the 2013 CPS closures found most displaced students remained in district the next year; outcomes varied with the quality and distance of receiving schools. That supports using a central r ~ 0.75 with a band. UChicago Consortium on School Research What we could not find in AZ: districts rarely publish explicit post‑closure retention; you can proxy from post‑closure enrollment by receiving schools if SUSD shares it. Echo nuance: Because Echo is open‑enrollment and draws many out‑of‑district students, those families may be less likely to follow to a different SUSD school after a closure (they already cross a boundary by choice). That argues for running a lower Echo‑weighted r scenario (e.g., 0.55–0.65) in addition to the district‑wide 0.65–0.85 band. Make that explicit in the dashboard and in the sensitivity mini‑cards. | E16: SUSD post‑closure enrollment tracking (where displaced students re‑enroll), by receiving school; use that to set “r” from observed data.
B17: Carry fractions f_ops / f_lease (e.g., 0.40 → 0 by FY30) | C17: Share of each site’s fixed costs that persist after repurpose under ops mothball vs lease/sale | D17: Assumption pending facilities plan. The glide‑path (e.g., 40%→30%→20%→10%→0%) reflects how fast plant/insurance/utilities can be retired or passed to a tenant. | E17: SUSD facilities memo: timeline to partial/full mothball, target lease/sale timing, and which cost lines truly zero out under each scenario.
B18: TI / one‑time repurpose costs (e.g., $2.4M) | C18: “TI_adds$” in the pro‑forma for the first 1–2 years. Why “Repurpose TI per closed site (FY26) = $1.2M”? What is “one‑time carry/TI”? “TI” = tenant improvements / transition investments needed to convert a K‑8 to a different use (early learning, admin consolidation) and carry costs in year one (e.g., abatement, doors/security, low‑voltage re‑work, furniture, swing space). A light‑touch repurpose can easily run $10–$20/sq‑ft; Echo’s plant is ~77k sq ft, so $1.2M is a reasonable placeholder (we are not assuming a gut remodel). We’ll replace this with SUSD’s scope/estimate if they have one. | D18: Assumption (placeholder). | E18: SUSD engineering estimate for tenant improvements or district reconfiguration (scope, cost, which fund, and amortization).
B19: Extra cost savings for co-location scenario | C19: Why “Extra savings (co‑location) = 0.015 (1.5%)”? This reflects incremental savings from consolidating some services on one campus (custodial/grounds/partial routing). Again kept small and conservative; we’ll swap in real custodial (sq‑ft), grounds and route deltas when we get them.
B20: Ops savings (for keep-open scenarios) | C20: Ops savings (keep‑open) = 0.007 (0.7%)”? This represents “light discipline” (utilities/purchasing tweaks, route smoothing) that does not depend on closing a site. I set it very low on purpose so it doesn’t drive results. We’ll calibrate with SUSD data (e.g., last year’s utility audits) if provided.
B22: Scenario overlays (+0 / +100 / +150 / +200) | C22: Size of growth push in keep‑open options (D, F, G) | D22: Assumption based on capacity headroom + practical recruitment targets. | E22: SUSD SFB capacity for Echo/Pima and neighboring receiving schools; actual classroom/wing availability by grade band.
B23: K–8 capacity / square footage | C23: Context for “utilization” and whether overlay targets are feasible | D23: Not yet populated; to be anchored to SFB (AZ School Facilities Board) capacity files and SUSD construction docs. | E23: SUSD/SFB: design capacity and current utilization for Echo & Pima (post‑rebuild specs for Pima).
B24: Pre‑K contribution | C24: Excluded from ADM and revenue in the model (unless tuition/lease modeled) | D24: Supported by statute & ADE finance practice—general Pre‑K does not generate state ADM (exception: SPED preschool). (Arizona Department of Education) | E24: If SUSD intends district‑operated tuition Pre‑K on site, request pro forma for net contribution (tuition – staffing – TI).
B25: ADM definition (what “counts”) | C25: Explains why Pre‑K is excluded and why K can count at 0.5; supports “served” math | D25: A.R.S. §15‑901 and legislative fact sheet: Kindergarten generates 0.5 ADM unless full‑time; ADM is a statutory count, and preschool is generally not included in ADM (except some SPED programs). (LegiScan) | E25: SUSD’s 40th‑day and 100th‑day ADM certification for Echo and Pima (K–8 breakouts).
B28: Model input / claim | C28: How we’re using it in the model | D28: Public source to cite (what to grab) | E28: How to apply in the file
B32: Parameter / Input | C32: Description | D32: Where it lives | E32: Notes on logic / calculation | F32: Source to use for final vetting
B33: Base MO per ADM (FY25) | C33: Working average M&O per student at FY25 | D33: BaselineCalc | E33: Drives Base total MO = Total ADM × Base MO/ADM | F33: Replace with SUSD ACFR/Adopted Budget (FY24–FY25) for precision
B34: Fixed share of MO | C34: Semi‑fixed share (plant ops, admin, insurance, custodial) | D34: BaselineCalc | E34: Fixed MO = Base total MO × Fixed share | F34: Validate vs ACFR function split (% Plant/Admin/Insurance) | G34: Notes on Pima & Echo fixed $ placeholders: The file allocates the fixed share across the two schools pro‑rata (by base ADM) as a temporary step. Replace with the actual plant ops/insurance/utilities/admin for each site from Fund 001 to remove that simplification.
B35: Var per student (FY25) | C35: Derived variable cost per student | D35: BaselineCalc | E35: (Base total – Fixed) ÷ total ADM | F35: Derived
B36: MO inflation | C36: Annual inflation on M&O lines | D36: BaselineCalc | E36: Inflates VarUnit$ across YearMap | F36: Use district inflation guidance
B37: Echo/Pima base ADM | C37: Starting enrollment | D37: BaselineCalc | E37: Builds Total base ADM = Echo + Pima | F37: District official
B38: YearMap VarUnit$ (FY26–FY30) | C38: Inflated variable per‑student cost | D38: YearMap | E38: Starts from BaselineCalc Var$ then inflation | F38: Derived
B39: Aid$ per ADM (FY26–FY30) | C39: State equalization aid per student | D39: YearMap | E39: Used to net out revenue: Net_MO_after_aid$ / Served_ADM | F39: Replace with ADE equalization worksheets for those years
B40: h (FY26–FY30) | C40: Receiving overhead per retained student | D40: YearMap | E40: Added for transition: routes, scheduling, admin | F40: Calibrate with transpo/admin data
B41: f_ops (FY26–FY30) | C41: Fixed‑carry fraction under mothball path | D41: YearMap | E41: Carry$ = f_ops × site fixed costs | F41: Needs calibration vs plant ops/insurance
B42: f_lease (FY26–FY30) | C42: Fixed‑carry fraction under lease/sale | D42: YearMap | E42: Carry$ = f_lease × site fixed costs (→0 by FY30) | F42: Requires credible lease/sale timeline
B43: MarginalFactor_for_Overlay | C43: Share of VarUnit$ applied to overlay seats | D43: Other_Parameters (v6 = 0.30) | E43: Keeps growth seats from carrying full average M&O | F43: Documented below (why 0.30)
B44: Scenario controls | C44: Overlay amounts by year; closures; co‑location flag; hub ramp | D44: Scenarios | E44: Dashboard pulls one comparator vs baseline | F44: Scenario definitions are transparent on the Scenarios tab

Sheet Q&A

Sheet MultiYear_ProForma
A1: =AG1 -> Key | B1: ScenarioKey | C1: Year | D1: Echo_ADM | E1: Pima_ADM | F1: Total_ADM | G1: VarUnit$ | H1: EchoFixed$ | I1: PimaFixed$ | J1: OpsFactor | K1: ExtraSave | L1: EchoPotential_ADM | M1: PimaPotential_ADM | N1: Displaced_ADM | O1: Retained_ADM | P1: h | Q1: CarryFrac | R1: EchoFixedEff$ | S1: PimaFixedEff$ | T1: TI_adds$ | U1: SiteCost$ | V1: RetainedSvc$ | W1: Comparable_MO$ | X1: Comparable_per_Student$ | Y1: Aid_per_ADM | Z1: Net_MO_after_aid$ | AA1: Net_per_served$ | AB1: Overlay_ADM | AC1: Served_ADM | AD1: Revenue$ | AE1: Adj_MO$ | AF1: Net$ | AG1: Key
A2: =AG2 -> D_CUSTOM1|FY2026 | B2: =Scenarios!A2 -> D_CUSTOM1 | C2: FY2026 | D2: =IF(Scenarios!D2=1,0, L2) -> 257 | E2: =IF(Scenarios!E2=1,0, M2) -> 296 | F2: =D2+E2 -> 553 | G2: =YearMap!B2 -> 6414.5115 | H2: =YearMap!C2 -> 1404302.9 | I2: =YearMap!D2 -> 1617407.2 | J2: =1-BaselineCalc!$B$5 -> 0.993 | K2: =Scenarios!G2 -> 0 | L2: =BaselineCalc!$B$7 + ROUND(Scenarios!I2*Scenarios!F2,0) -> 257 | M2: =BaselineCalc!$B$8 + Scenarios!I2 - ROUND(Scenarios!I2*Scenarios!F2,0) -> 296 | N2: =(L2-D2) + (M2-E2) -> 0 | O2: =(Parameters_Public!$C$22*(L2-D2)+Parameters_Public!$C$23*(M2-E2)) -> 0 | P2: =YearMap!E2 -> 1000 | Q2: =IF(Scenarios!N2="lease", YearMap!F2, YearMap!G2) -> 0.5 | R2: =IF(Scenarios!D2=1, Q2*H2, H2) -> 1404302.9 | S2: =IF(Scenarios!E2=1, Q2*I2, I2) -> 1617407.2 | T2: =IF(C2="FY2026", (Scenarios!D2+Scenarios!E2)*BaselineCalc!$B$22, 0) -> 0 | U2: =(R2+S2+G2*F2)*J2*(1-K2) -> 6522952.4 | V2: =O2*(G2+P2) -> 0 | W2: =U2+V2+IF(Parameters_Public!$C$26=1, T2, 0) -> 6522952.4 | X2: =IF(F2+O2>0, W2/(F2+O2),"") -> 11795.574 | Y2: =INDEX(YearMap!$I$2:$I$6, MATCH(C2, YearMap!$A$2:$A$6, 0)) -> 5013 | Z2: =W2 - ((Y2 + IF(Parameters_Public!$C$20=1, Parameters_Public!$C$19, 0))*AC2) -> 3334935 | AA2: =IF($AC2>0, $Z2/$AC2, 0) -> 6030.6239 | AB2: =MAX(0, (MAX(0, $D2-BaselineCalc!$B$7) + MAX(0, $E2-BaselineCalc!$B$8))) -> 0 | AC2: =IF(LEFT($B2,2)="A_", $O2, IF(LEFT($B2,2)="B_", $M2+$O2, IF(LEFT($B2,2)="C_", $L2+$O2, $F2))) -> 553 | AD2: =(Y2 + IF(Parameters_Public!$C$20=1, Parameters_Public!$C$19, 0))*AC2 -> 3188017.4 | AE2: =W2 - (1-Other_Parameters!$B$2)*$G2*$AB2*$J2*(1-$K2) -> 6522952.4 | AF2: =AD2-AE2 -> -3334935 | AG2: =B2&"|"&C2 -> D_CUSTOM1|FY2026
A3: =AG3 -> D_CUSTOM1|FY2027 | B3: =Scenarios!A2 -> D_CUSTOM1 | C3: FY2027 | D3: =IF(Scenarios!D2=1,0, L3) -> 257 | E3: =IF(Scenarios!E2=1,0, M3) -> 296 | F3: =D3+E3 -> 553 | G3: =YearMap!B3 -> 6574.8743 | H3: =YearMap!C3 -> 1439410.4 | I3: =YearMap!D3 -> 1657842.4 | J3: =1-BaselineCalc!$B$5 -> 0.993 | K3: =Scenarios!G2 -> 0 | L3: =BaselineCalc!$B$7 + ROUND(Scenarios!J2*Scenarios!F2,0) -> 257 | M3: =BaselineCalc!$B$8 + Scenarios!J2 - ROUND(Scenarios!J2*Scenarios!F2,0) -> 296 | N3: =(L3-D3) + (M3-E3) -> 0 | O3: =(Parameters_Public!$C$22*(L3-D3)+Parameters_Public!$C$23*(M3-E3)) -> 0 | P3: =YearMap!E3 -> 800 | Q3: =IF(Scenarios!N2="lease", YearMap!F3, YearMap!G3) -> 0.4 | R3: =IF(Scenarios!D2=1, Q3*H3, H3) -> 1439410.4 | S3: =IF(Scenarios!E2=1, Q3*I3, I3) -> 1657842.4 | T3: =IF(C3="FY2026", (Scenarios!D2+Scenarios!E2)*BaselineCalc!$B$22, 0) -> 0 | U3: =(R3+S3+G3*F3)*J3*(1-K3) -> 6686026.2 | V3: =O3*(G3+P3) -> 0 | W3: =U3+V3+IF(Parameters_Public!$C$26=1, T3, 0) -> 6686026.2 | X3: =IF(F3+O3>0, W3/(F3+O3),"") -> 12090.463 | Y3: =INDEX(YearMap!$I$2:$I$6, MATCH(C3, YearMap!$A$2:$A$6, 0)) -> 5113.26 | Z3: =W3 - ((Y3 + IF(Parameters_Public!$C$20=1, Parameters_Public!$C$19, 0))*AC3) -> 3442565.1 | AA3: =IF($AC3>0, $Z3/$AC3, 0) -> 6225.2533 | AB3: =MAX(0, (MAX(0, $D3-BaselineCalc!$B$7) + MAX(0, $E3-BaselineCalc!$B$8))) -> 0 | AC3: =IF(LEFT($B3,2)="A_", $O3, IF(LEFT($B3,2)="B_", $M3+$O3, IF(LEFT($B3,2)="C_", $L3+$O3, $F3))) -> 553 | AD3: =(Y3 + IF(Parameters_Public!$C$20=1, Parameters_Public!$C$19, 0))*AC3 -> 3243461.1 | AE3: =W3 - (1-Other_Parameters!$B$2)*$G3*$AB3*$J3*(1-$K3) -> 6686026.2 | AF3: =AD3-AE3 -> -3442565.1 | AG3: =B3&"|"&C3 -> D_CUSTOM1|FY2027
A4: =AG4 -> D_CUSTOM1|FY2028 | B4: =Scenarios!A2 -> D_CUSTOM1 | C4: FY2028 | D4: =IF(Scenarios!D2=1,0, L4) -> 257 | E4: =IF(Scenarios!E2=1,0, M4) -> 296 | F4: =D4+E4 -> 553 | G4: =YearMap!B4 -> 6739.2461 | H4: =YearMap!C4 -> 1475395.7 | I4: =YearMap!D4 -> 1699288.4 | J4: =1-BaselineCalc!$B$5 -> 0.993 | K4: =Scenarios!G2 -> 0 | L4: =BaselineCalc!$B$7 + ROUND(Scenarios!K2*Scenarios!F2,0) -> 257 | M4: =BaselineCalc!$B$8 + Scenarios!K2 - ROUND(Scenarios!K2*Scenarios!F2,0) -> 296 | N4: =(L4-D4) + (M4-E4) -> 0 | O4: =(Parameters_Public!$C$22*(L4-D4)+Parameters_Public!$C$23*(M4-E4)) -> 0 | P4: =YearMap!E4 -> 600 | Q4: =IF(Scenarios!N2="lease", YearMap!F4, YearMap!G4) -> 0.35 | R4: =IF(Scenarios!D2=1, Q4*H4, H4) -> 1475395.7 | S4: =IF(Scenarios!E2=1, Q4*I4, I4) -> 1699288.4 | T4: =IF(C4="FY2026", (Scenarios!D2+Scenarios!E2)*BaselineCalc!$B$22, 0) -> 0 | U4: =(R4+S4+G4*F4)*J4*(1-K4) -> 6853176.8 | V4: =O4*(G4+P4) -> 0 | W4: =U4+V4+IF(Parameters_Public!$C$26=1, T4, 0) -> 6853176.8 | X4: =IF(F4+O4>0, W4/(F4+O4),"") -> 12392.725 | Y4: =INDEX(YearMap!$I$2:$I$6, MATCH(C4, YearMap!$A$2:$A$6, 0)) -> 5215.5252 | Z4: =W4 - ((Y4 + IF(Parameters_Public!$C$20=1, Parameters_Public!$C$19, 0))*AC4) -> 3553163.1 | AA4: =IF($AC4>0, $Z4/$AC4, 0) -> 6425.2497 | AB4: =MAX(0, (MAX(0, $D4-BaselineCalc!$B$7) + MAX(0, $E4-BaselineCalc!$B$8))) -> 0 | AC4: =IF(LEFT($B4,2)="A_", $O4, IF(LEFT($B4,2)="B_", $M4+$O4, IF(LEFT($B4,2)="C_", $L4+$O4, $F4))) -> 553 | AD4: =(Y4 + IF(Parameters_Public!$C$20=1, Parameters_Public!$C$19, 0))*AC4 -> 3300013.8 | AE4: =W4 - (1-Other_Parameters!$B$2)*$G4*$AB4*$J4*(1-$K4) -> 6853176.8 | AF4: =AD4-AE4 -> -3553163.1 | AG4: =B4&"|"&C4 -> D_CUSTOM1|FY2028
A5: =AG5 -> D_CUSTOM1|FY2029 | B5: =Scenarios!A2 -> D_CUSTOM1 | C5: FY2029 | D5: =IF(Scenarios!D2=1,0, L5) -> 257 | E5: =IF(Scenarios!E2=1,0, M5) -> 296 | F5: =D5+E5 -> 553 | G5: =YearMap!B5 -> 6907.7273 | H5: =YearMap!C5 -> 1512280.6 | I5: =YearMap!D5 -> 1741770.6 | J5: =1-BaselineCalc!$B$5 -> 0.993 | K5: =Scenarios!G2 -> 0 | L5: =BaselineCalc!$B$7 + ROUND(Scenarios!L2*Scenarios!F2,0) -> 257 | M5: =BaselineCalc!$B$8 + Scenarios!L2 - ROUND(Scenarios!L2*Scenarios!F2,0) -> 296 | N5: =(L5-D5) + (M5-E5) -> 0 | O5: =(Parameters_Public!$C$22*(L5-D5)+Parameters_Public!$C$23*(M5-E5)) -> 0 | P5: =YearMap!E5 -> 500 | Q5: =IF(Scenarios!N2="lease", YearMap!F5, YearMap!G5) -> 0.3 | R5: =IF(Scenarios!D2=1, Q5*H5, H5) -> 1512280.6 | S5: =IF(Scenarios!E2=1, Q5*I5, I5) -> 1741770.6 | T5: =IF(C5="FY2026", (Scenarios!D2+Scenarios!E2)*BaselineCalc!$B$22, 0) -> 0 | U5: =(R5+S5+G5*F5)*J5*(1-K5) -> 7024506.3 | V5: =O5*(G5+P5) -> 0 | W5: =U5+V5+IF(Parameters_Public!$C$26=1, T5, 0) -> 7024506.3 | X5: =IF(F5+O5>0, W5/(F5+O5),"") -> 12702.543 | Y5: =INDEX(YearMap!$I$2:$I$6, MATCH(C5, YearMap!$A$2:$A$6, 0)) -> 5319.8357 | Z5: =W5 - ((Y5 + IF(Parameters_Public!$C$20=1, Parameters_Public!$C$19, 0))*AC5) -> 3666808.8 | AA5: =IF($AC5>0, $Z5/$AC5, 0) -> 6630.7573 | AB5: =MAX(0, (MAX(0, $D5-BaselineCalc!$B$7) + MAX(0, $E5-BaselineCalc!$B$8))) -> 0 | AC5: =IF(LEFT($B5,2)="A_", $O5, IF(LEFT($B5,2)="B_", $M5+$O5, IF(LEFT($B5,2)="C_", $L5+$O5, $F5))) -> 553 | AD5: =(Y5 + IF(Parameters_Public!$C$20=1, Parameters_Public!$C$19, 0))*AC5 -> 3357697.5 | AE5: =W5 - (1-Other_Parameters!$B$2)*$G5*$AB5*$J5*(1-$K5) -> 7024506.3 | AF5: =AD5-AE5 -> -3666808.8 | AG5: =B5&"|"&C5 -> D_CUSTOM1|FY2029
A6: =AG6 -> D_CUSTOM1|FY2030 | B6: =Scenarios!A2 -> D_CUSTOM1 | C6: FY2030 | D6: =IF(Scenarios!D2=1,0, L6) -> 257 | E6: =IF(Scenarios!E2=1,0, M6) -> 296 | F6: =D6+E6 -> 553 | G6: =YearMap!B6 -> 7080.4205 | H6: =YearMap!C6 -> 1550087.6 | I6: =YearMap!D6 -> 1785314.9 | J6: =1-BaselineCalc!$B$5 -> 0.993 | K6: =Scenarios!G2 -> 0 | L6: =BaselineCalc!$B$7 + ROUND(Scenarios!M2*Scenarios!F2,0) -> 257 | M6: =BaselineCalc!$B$8 + Scenarios!M2 - ROUND(Scenarios!M2*Scenarios!F2,0) -> 296 | N6: =(L6-D6) + (M6-E6) -> 0 | O6: =(Parameters_Public!$C$22*(L6-D6)+Parameters_Public!$C$23*(M6-E6)) -> 0 | P6: =YearMap!E6 -> 300 | Q6: =IF(Scenarios!N2="lease", YearMap!F6, YearMap!G6) -> 0.3 | R6: =IF(Scenarios!D2=1, Q6*H6, H6) -> 1550087.6 | S6: =IF(Scenarios!E2=1, Q6*I6, I6) -> 1785314.9 | T6: =IF(C6="FY2026", (Scenarios!D2+Scenarios!E2)*BaselineCalc!$B$22, 0) -> 0 | U6: =(R6+S6+G6*F6)*J6*(1-K6) -> 7200118.9 | V6: =O6*(G6+P6) -> 0 | W6: =U6+V6+IF(Parameters_Public!$C$26=1, T6, 0) -> 7200118.9 | X6: =IF(F6+O6>0, W6/(F6+O6),"") -> 13020.107 | Y6: =INDEX(YearMap!$I$2:$I$6, MATCH(C6, YearMap!$A$2:$A$6, 0)) -> 5426.2324 | Z6: =W6 - ((Y6 + IF(Parameters_Public!$C$20=1, Parameters_Public!$C$19, 0))*AC6) -> 3783584 | AA6: =IF($AC6>0, $Z6/$AC6, 0) -> 6841.9241 | AB6: =MAX(0, (MAX(0, $D6-BaselineCalc!$B$7) + MAX(0, $E6-BaselineCalc!$B$8))) -> 0 | AC6: =IF(LEFT($B6,2)="A_", $O6, IF(LEFT($B6,2)="B_", $M6+$O6, IF(LEFT($B6,2)="C_", $L6+$O6, $F6))) -> 553 | AD6: =(Y6 + IF(Parameters_Public!$C$20=1, Parameters_Public!$C$19, 0))*AC6 -> 3416534.9 | AE6: =W6 - (1-Other_Parameters!$B$2)*$G6*$AB6*$J6*(1-$K6) -> 7200118.9 | AF6: =AD6-AE6 -> -3783584 | AG6: =B6&"|"&C6 -> D_CUSTOM1|FY2030
A7: =AG7 -> E_StatusQuo_Targets|FY2026 | B7: =Scenarios!A3 -> E_StatusQuo_Targets | C7: FY2026 | D7: =IF(Scenarios!D3=1,0, L7) -> 332 | E7: =IF(Scenarios!E3=1,0, M7) -> 371 | F7: =D7+E7 -> 703 | G7: =YearMap!B2 -> 6414.5115 | H7: =YearMap!C2 -> 1404302.9 | I7: =YearMap!D2 -> 1617407.2 | J7: =1-BaselineCalc!$B$5 -> 0.993 | K7: =Scenarios!G3 -> 0 | L7: =BaselineCalc!$B$7 + ROUND(Scenarios!I3*Scenarios!F3,0) -> 332 | M7: =BaselineCalc!$B$8 + Scenarios!I3 - ROUND(Scenarios!J3*Scenarios!F3,0) -> 371 | N7: =(L7-D7) + (M7-E7) -> 0 | O7: =(Parameters_Public!$C$22*(L7-D7)+Parameters_Public!$C$23*(M7-E7)) -> 0 | P7: =YearMap!E2 -> 1000 | Q7: =IF(Scenarios!N3="lease", YearMap!F2, YearMap!G2) -> 0.5 | R7: =IF(Scenarios!D3=1, Q7*H7, H7) -> 1404302.9 | S7: =IF(Scenarios!E3=1, Q7*I7, I7) -> 1617407.2 | T7: =IF(C7="FY2026", (Scenarios!D3+Scenarios!E3)*BaselineCalc!$B$22, 0) -> 0 | U7: =(R7+S7+G7*F7)*J7*(1-K7) -> 7478393.9 | V7: =O7*(G7+P7) -> 0 | W7: =U7+V7+IF(Parameters_Public!$C$26=1, T7, 0) -> 7478393.9 | X7: =IF(F7+O7>0, W7/(F7+O7),"") -> 10637.829 | Y7: =INDEX(YearMap!$I$2:$I$6, MATCH(C7, YearMap!$A$2:$A$6, 0)) -> 5013 | Z7: =W7 - ((Y7 + IF(Parameters_Public!$C$20=1, Parameters_Public!$C$19, 0))*AC7) -> 3425634 | AA7: =IF($AC7>0, $Z7/$AC7, 0) -> 4872.8791 | AB7: =MAX(0, (MAX(0, $D7-BaselineCalc!$B$7) + MAX(0, $E7-BaselineCalc!$B$8))) -> 150 | AC7: =IF(LEFT($B7,2)="A_", $O7, IF(LEFT($B7,2)="B_", $M7+$O7, IF(LEFT($B7,2)="C_", $L7+$O7, $F7))) -> 703 | AD7: =(Y7 + IF(Parameters_Public!$C$20=1, Parameters_Public!$C$19, 0))*AC7 -> 4052759.9 | AE7: =W7 - (1-Other_Parameters!$B$2)*$G7*$AB7*$J7*(1-$K7) -> 6905129 | AF7: =AD7-AE7 -> -2852369.1 | AG7: =B7&"|"&C7 -> E_StatusQuo_Targets|FY2026
A8: =AG8 -> E_StatusQuo_Targets|FY2027 | B8: =Scenarios!A3 -> E_StatusQuo_Targets | C8: FY2027 | D8: =IF(Scenarios!D3=1,0, L8) -> 332 | E8: =IF(Scenarios!E3=1,0, M8) -> 371 | F8: =D8+E8 -> 703 | G8: =YearMap!B3 -> 6574.8743 | H8: =YearMap!C3 -> 1439410.4 | I8: =YearMap!D3 -> 1657842.4 | J8: =1-BaselineCalc!$B$5 -> 0.993 | K8: =Scenarios!G3 -> 0 | L8: =BaselineCalc!$B$7 + ROUND(Scenarios!J3*Scenarios!F3,0) -> 332 | M8: =BaselineCalc!$B$8 + Scenarios!J3 - ROUND(Scenarios!J3*Scenarios!F3,0) -> 371 | N8: =(L8-D8) + (M8-E8) -> 0 | O8: =(Parameters_Public!$C$22*(L8-D8)+Parameters_Public!$C$23*(M8-E8)) -> 0 | P8: =YearMap!E3 -> 800 | Q8: =IF(Scenarios!N3="lease", YearMap!F3, YearMap!G3) -> 0.4 | R8: =IF(Scenarios!D3=1, Q8*H8, H8) -> 1439410.4 | S8: =IF(Scenarios!E3=1, Q8*I8, I8) -> 1657842.4 | T8: =IF(C8="FY2026", (Scenarios!D3+Scenarios!E3)*BaselineCalc!$B$22, 0) -> 0 | U8: =(R8+S8+G8*F8)*J8*(1-K8) -> 7665353.7 | V8: =O8*(G8+P8) -> 0 | W8: =U8+V8+IF(Parameters_Public!$C$26=1, T8, 0) -> 7665353.7 | X8: =IF(F8+O8>0, W8/(F8+O8),"") -> 10903.775 | Y8: =INDEX(YearMap!$I$2:$I$6, MATCH(C8, YearMap!$A$2:$A$6, 0)) -> 5113.26 | Z8: =W8 - ((Y8 + IF(Parameters_Public!$C$20=1, Parameters_Public!$C$19, 0))*AC8) -> 3542111.1 | AA8: =IF($AC8>0, $Z8/$AC8, 0) -> 5038.5648 | AB8: =MAX(0, (MAX(0, $D8-BaselineCalc!$B$7) + MAX(0, $E8-BaselineCalc!$B$8))) -> 150 | AC8: =IF(LEFT($B8,2)="A_", $O8, IF(LEFT($B8,2)="B_", $M8+$O8, IF(LEFT($B8,2)="C_", $L8+$O8, $F8))) -> 703 | AD8: =(Y8 + IF(Parameters_Public!$C$20=1, Parameters_Public!$C$19, 0))*AC8 -> 4123242.6 | AE8: =W8 - (1-Other_Parameters!$B$2)*$G8*$AB8*$J8*(1-$K8) -> 7077757.2 | AF8: =AD8-AE8 -> -2954514.6 | AG8: =B8&"|"&C8 -> E_StatusQuo_Targets|FY2027
A9: =AG9 -> E_StatusQuo_Targets|FY2028 | B9: =Scenarios!A3 -> E_StatusQuo_Targets | C9: FY2028 | D9: =IF(Scenarios!D3=1,0, L9) -> 332 | E9: =IF(Scenarios!E3=1,0, M9) -> 371 | F9: =D9+E9 -> 703 | G9: =YearMap!B4 -> 6739.2461 | H9: =YearMap!C4 -> 1475395.7 | I9: =YearMap!D4 -> 1699288.4 | J9: =1-BaselineCalc!$B$5 -> 0.993 | K9: =Scenarios!G3 -> 0 | L9: =BaselineCalc!$B$7 + ROUND(Scenarios!K3*Scenarios!F3,0) -> 332 | M9: =BaselineCalc!$B$8 + Scenarios!K3 - ROUND(Scenarios!K3*Scenarios!F3,0) -> 371 | N9: =(L9-D9) + (M9-E9) -> 0 | O9: =(Parameters_Public!$C$22*(L9-D9)+Parameters_Public!$C$23*(M9-E9)) -> 0 | P9: =YearMap!E4 -> 600 | Q9: =IF(Scenarios!N3="lease", YearMap!F4, YearMap!G4) -> 0.35 | R9: =IF(Scenarios!D3=1, Q9*H9, H9) -> 1475395.7 | S9: =IF(Scenarios!E3=1, Q9*I9, I9) -> 1699288.4 | T9: =IF(C9="FY2026", (Scenarios!D3+Scenarios!E3)*BaselineCalc!$B$22, 0) -> 0 | U9: =(R9+S9+G9*F9)*J9*(1-K9) -> 7856987.6 | V9: =O9*(G9+P9) -> 0 | W9: =U9+V9+IF(Parameters_Public!$C$26=1, T9, 0) -> 7856987.6 | X9: =IF(F9+O9>0, W9/(F9+O9),"") -> 11176.369 | Y9: =INDEX(YearMap!$I$2:$I$6, MATCH(C9, YearMap!$A$2:$A$6, 0)) -> 5215.5252 | Z9: =W9 - ((Y9 + IF(Parameters_Public!$C$20=1, Parameters_Public!$C$19, 0))*AC9) -> 3661852.5 | AA9: =IF($AC9>0, $Z9/$AC9, 0) -> 5208.894 | AB9: =MAX(0, (MAX(0, $D9-BaselineCalc!$B$7) + MAX(0, $E9-BaselineCalc!$B$8))) -> 150 | AC9: =IF(LEFT($B9,2)="A_", $O9, IF(LEFT($B9,2)="B_", $M9+$O9, IF(LEFT($B9,2)="C_", $L9+$O9, $F9))) -> 703 | AD9: =(Y9 + IF(Parameters_Public!$C$20=1, Parameters_Public!$C$19, 0))*AC9 -> 4195135.1 | AE9: =W9 - (1-Other_Parameters!$B$2)*$G9*$AB9*$J9*(1-$K9) -> 7254701.1 | AF9: =AD9-AE9 -> -3059566.1 | AG9: =B9&"|"&C9 -> E_StatusQuo_Targets|FY2028
A10: =AG10 -> E_StatusQuo_Targets|FY2029 | B10: =Scenarios!A3 -> E_StatusQuo_Targets | C10: FY2029 | D10: =IF(Scenarios!D3=1,0, L10) -> 332 | E10: =IF(Scenarios!E3=1,0, M10) -> 371 | F10: =D10+E10 -> 703 | G10: =YearMap!B5 -> 6907.7273 | H10: =YearMap!C5 -> 1512280.6 | I10: =YearMap!D5 -> 1741770.6 | J10: =1-BaselineCalc!$B$5 -> 0.993 | K10: =Scenarios!G3 -> 0 | L10: =BaselineCalc!$B$7 + ROUND(Scenarios!L3*Scenarios!F3,0) -> 332 | M10: =BaselineCalc!$B$8 + Scenarios!L3 - ROUND(Scenarios!L3*Scenarios!F3,0) -> 371 | N10: =(L10-D10) + (M10-E10) -> 0 | O10: =(Parameters_Public!$C$22*(L10-D10)+Parameters_Public!$C$23*(M10-E10)) -> 0 | P10: =YearMap!E5 -> 500 | Q10: =IF(Scenarios!N3="lease", YearMap!F5, YearMap!G5) -> 0.3 | R10: =IF(Scenarios!D3=1, Q10*H10, H10) -> 1512280.6 | S10: =IF(Scenarios!E3=1, Q10*I10, I10) -> 1741770.6 | T10: =IF(C10="FY2026", (Scenarios!D3+Scenarios!E3)*BaselineCalc!$B$22, 0) -> 0 | U10: =(R10+S10+G10*F10)*J10*(1-K10) -> 8053412.2 | V10: =O10*(G10+P10) -> 0 | W10: =U10+V10+IF(Parameters_Public!$C$26=1, T10, 0) -> 8053412.2 | X10: =IF(F10+O10>0, W10/(F10+O10),"") -> 11455.778 | Y10: =INDEX(YearMap!$I$2:$I$6, MATCH(C10, YearMap!$A$2:$A$6, 0)) -> 5319.8357 | Z10: =W10 - ((Y10 + IF(Parameters_Public!$C$20=1, Parameters_Public!$C$19, 0))*AC10) -> 3784946.9 | AA10: =IF($AC10>0, $Z10/$AC10, 0) -> 5383.9927 | AB10: =MAX(0, (MAX(0, $D10-BaselineCalc!$B$7) + MAX(0, $E10-BaselineCalc!$B$8))) -> 150 | AC10: =IF(LEFT($B10,2)="A_", $O10, IF(LEFT($B10,2)="B_", $M10+$O10, IF(LEFT($B10,2)="C_", $L10+$O10, $F10))) -> 703 | AD10: =(Y10 + IF(Parameters_Public!$C$20=1, Parameters_Public!$C$19, 0))*AC10 -> 4268465.3 | AE10: =W10 - (1-Other_Parameters!$B$2)*$G10*$AB10*$J10*(1-$K10) -> 7436068.7 | AF10: =AD10-AE10 -> -3167603.3 | AG10: =B10&"|"&C10 -> E_StatusQuo_Targets|FY2029
A11: =AG11 -> E_StatusQuo_Targets|FY2030 | B11: =Scenarios!A3 -> E_StatusQuo_Targets | C11: FY2030 | D11: =IF(Scenarios!D3=1,0, L11) -> 332 | E11: =IF(Scenarios!E3=1,0, M11) -> 371 | F11: =D11+E11 -> 703 | G11: =YearMap!B6 -> 7080.4205 | H11: =YearMap!C6 -> 1550087.6 | I11: =YearMap!D6 -> 1785314.9 | J11: =1-BaselineCalc!$B$5 -> 0.993 | K11: =Scenarios!G3 -> 0 | L11: =BaselineCalc!$B$7 + ROUND(Scenarios!M3*Scenarios!F3,0) -> 332 | M11: =BaselineCalc!$B$8 + Scenarios!M3 - ROUND(Scenarios!M3*Scenarios!F3,0) -> 371 | N11: =(L11-D11) + (M11-E11) -> 0 | O11: =(Parameters_Public!$C$22*(L11-D11)+Parameters_Public!$C$23*(M11-E11)) -> 0 | P11: =YearMap!E6 -> 300 | Q11: =IF(Scenarios!N3="lease", YearMap!F6, YearMap!G6) -> 0.3 | R11: =IF(Scenarios!D3=1, Q11*H11, H11) -> 1550087.6 | S11: =IF(Scenarios!E3=1, Q11*I11, I11) -> 1785314.9 | T11: =IF(C11="FY2026", (Scenarios!D3+Scenarios!E3)*BaselineCalc!$B$22, 0) -> 0 | U11: =(R11+S11+G11*F11)*J11*(1-K11) -> 8254747.6 | V11: =O11*(G11+P11) -> 0 | W11: =U11+V11+IF(Parameters_Public!$C$26=1, T11, 0) -> 8254747.6 | X11: =IF(F11+O11>0, W11/(F11+O11),"") -> 11742.173 | Y11: =INDEX(YearMap!$I$2:$I$6, MATCH(C11, YearMap!$A$2:$A$6, 0)) -> 5426.2324 | Z11: =W11 - ((Y11 + IF(Parameters_Public!$C$20=1, Parameters_Public!$C$19, 0))*AC11) -> 3911485.3 | AA11: =IF($AC11>0, $Z11/$AC11, 0) -> 5563.9905 | AB11: =MAX(0, (MAX(0, $D11-BaselineCalc!$B$7) + MAX(0, $E11-BaselineCalc!$B$8))) -> 150 | AC11: =IF(LEFT($B11,2)="A_", $O11, IF(LEFT($B11,2)="B_", $M11+$O11, IF(LEFT($B11,2)="C_", $L11+$O11, $F11))) -> 703 | AD11: =(Y11 + IF(Parameters_Public!$C$20=1, Parameters_Public!$C$19, 0))*AC11 -> 4343262.2 | AE11: =W11 - (1-Other_Parameters!$B$2)*$G11*$AB11*$J11*(1-$K11) -> 7621970.4 | AF11: =AD11-AE11 -> -3278708.1 | AG11: =B11&"|"&C11 -> E_StatusQuo_Targets|FY2030
A12: =AG12 -> F_CoLocation_Echo_Targets|FY2026 | B12: =Scenarios!A4 -> F_CoLocation_Echo_Targets | C12: FY2026 | D12: =IF(Scenarios!D4=1,0, L12) -> 332 | E12: =IF(Scenarios!E4=1,0, M12) -> 371 | F12: =D12+E12 -> 703 | G12: =YearMap!B2 -> 6414.5115 | H12: =YearMap!C2 -> 1404302.9 | I12: =YearMap!D2 -> 1617407.2 | J12: =1-BaselineCalc!$B$5 -> 0.993 | K12: =Scenarios!G4 -> 0.05 | L12: =BaselineCalc!$B$7 + ROUND(Scenarios!I4*Scenarios!F4,0) -> 332 | M12: =BaselineCalc!$B$8 + Scenarios!I4 - ROUND(Scenarios!I4*Scenarios!F4,0) -> 371 | N12: =(L12-D12) + (M12-E12) -> 0 | O12: =(Parameters_Public!$C$22*(L12-D12)+Parameters_Public!$C$23*(M12-E12)) -> 0 | P12: =YearMap!E2 -> 1000 | Q12: =IF(Scenarios!N4="lease", YearMap!F2, YearMap!G2) -> 0.5 | R12: =IF(Scenarios!D4=1, Q12*H12, H12) -> 1404302.9 | S12: =IF(Scenarios!E4=1, Q12*I12, I12) -> 1617407.2 | T12: =IF(C12="FY2026", (Scenarios!D4+Scenarios!E4)*BaselineCalc!$B$22, 0) -> 0 | U12: =(R12+S12+G12*F12)*J12*(1-K12) -> 7104474.2 | V12: =O12*(G12+P12) -> 0 | W12: =U12+V12+IF(Parameters_Public!$C$26=1, T12, 0) -> 7104474.2 | X12: =IF(F12+O12>0, W12/(F12+O12),"") -> 10105.938 | Y12: =INDEX(YearMap!$I$2:$I$6, MATCH(C12, YearMap!$A$2:$A$6, 0)) -> 5013 | Z12: =W12 - ((Y12 + IF(Parameters_Public!$C$20=1, Parameters_Public!$C$19, 0))*AC12) -> 3051714.3 | AA12: =IF($AC12>0, $Z12/$AC12, 0) -> 4340.9877 | AB12: =MAX(0, (MAX(0, $D12-BaselineCalc!$B$7) + MAX(0, $E12-BaselineCalc!$B$8))) -> 150 | AC12: =IF(LEFT($B12,2)="A_", $O12, IF(LEFT($B12,2)="B_", $M12+$O12, IF(LEFT($B12,2)="C_", $L12+$O12, $F12))) -> 703 | AD12: =(Y12 + IF(Parameters_Public!$C$20=1, Parameters_Public!$C$19, 0))*AC12 -> 4052759.9 | AE12: =W12 - (1-Other_Parameters!$B$2)*$G12*$AB12*$J12*(1-$K12) -> 6559872.5 | AF12: =AD12-AE12 -> -2507112.7 | AG12: =B12&"|"&C12 -> F_CoLocation_Echo_Targets|FY2026
A13: =AG13 -> F_CoLocation_Echo_Targets|FY2027 | B13: =Scenarios!A4 -> F_CoLocation_Echo_Targets | C13: FY2027 | D13: =IF(Scenarios!D4=1,0, L13) -> 332 | E13: =IF(Scenarios!E4=1,0, M13) -> 371 | F13: =D13+E13 -> 703 | G13: =YearMap!B3 -> 6574.8743 | H13: =YearMap!C3 -> 1439410.4 | I13: =YearMap!D3 -> 1657842.4 | J13: =1-BaselineCalc!$B$5 -> 0.993 | K13: =Scenarios!G4 -> 0.05 | L13: =BaselineCalc!$B$7 + ROUND(Scenarios!J4*Scenarios!F4,0) -> 332 | M13: =BaselineCalc!$B$8 + Scenarios!J4 - ROUND(Scenarios!J4*Scenarios!F4,0) -> 371 | N13: =(L13-D13) + (M13-E13) -> 0 | O13: =(Parameters_Public!$C$22*(L13-D13)+Parameters_Public!$C$23*(M13-E13)) -> 0 | P13: =YearMap!E3 -> 800 | Q13: =IF(Scenarios!N4="lease", YearMap!F3, YearMap!G3) -> 0.4 | R13: =IF(Scenarios!D4=1, Q13*H13, H13) -> 1439410.4 | S13: =IF(Scenarios!E4=1, Q13*I13, I13) -> 1657842.4 | T13: =IF(C13="FY2026", (Scenarios!D4+Scenarios!E4)*BaselineCalc!$B$22, 0) -> 0 | U13: =(R13+S13+G13*F13)*J13*(1-K13) -> 7282086 | V13: =O13*(G13+P13) -> 0 | W13: =U13+V13+IF(Parameters_Public!$C$26=1, T13, 0) -> 7282086 | X13: =IF(F13+O13>0, W13/(F13+O13),"") -> 10358.586 | Y13: =INDEX(YearMap!$I$2:$I$6, MATCH(C13, YearMap!$A$2:$A$6, 0)) -> 5113.26 | Z13: =W13 - ((Y13 + IF(Parameters_Public!$C$20=1, Parameters_Public!$C$19, 0))*AC13) -> 3158843.4 | AA13: =IF($AC13>0, $Z13/$AC13, 0) -> 4493.3761 | AB13: =MAX(0, (MAX(0, $D13-BaselineCalc!$B$7) + MAX(0, $E13-BaselineCalc!$B$8))) -> 150 | AC13: =IF(LEFT($B13,2)="A_", $O13, IF(LEFT($B13,2)="B_", $M13+$O13, IF(LEFT($B13,2)="C_", $L13+$O13, $F13))) -> 703 | AD13: =(Y13 + IF(Parameters_Public!$C$20=1, Parameters_Public!$C$19, 0))*AC13 -> 4123242.6 | AE13: =W13 - (1-Other_Parameters!$B$2)*$G13*$AB13*$J13*(1-$K13) -> 6723869.3 | AF13: =AD13-AE13 -> -2600626.7 | AG13: =B13&"|"&C13 -> F_CoLocation_Echo_Targets|FY2027
A14: =AG14 -> F_CoLocation_Echo_Targets|FY2028 | B14: =Scenarios!A4 -> F_CoLocation_Echo_Targets | C14: FY2028 | D14: =IF(Scenarios!D4=1,0, L14) -> 332 | E14: =IF(Scenarios!E4=1,0, M14) -> 371 | F14: =D14+E14 -> 703 | G14: =YearMap!B4 -> 6739.2461 | H14: =YearMap!C4 -> 1475395.7 | I14: =YearMap!D4 -> 1699288.4 | J14: =1-BaselineCalc!$B$5 -> 0.993 | K14: =Scenarios!G4 -> 0.05 | L14: =BaselineCalc!$B$7 + ROUND(Scenarios!K4*Scenarios!F4,0) -> 332 | M14: =BaselineCalc!$B$8 + Scenarios!K4 - ROUND(Scenarios!K4*Scenarios!F4,0) -> 371 | N14: =(L14-D14) + (M14-E14) -> 0 | O14: =(Parameters_Public!$C$22*(L14-D14)+Parameters_Public!$C$23*(M14-E14)) -> 0 | P14: =YearMap!E4 -> 600 | Q14: =IF(Scenarios!N4="lease", YearMap!F4, YearMap!G4) -> 0.35 | R14: =IF(Scenarios!D4=1, Q14*H14, H14) -> 1475395.7 | S14: =IF(Scenarios!E4=1, Q14*I14, I14) -> 1699288.4 | T14: =IF(C14="FY2026", (Scenarios!D4+Scenarios!E4)*BaselineCalc!$B$22, 0) -> 0 | U14: =(R14+S14+G14*F14)*J14*(1-K14) -> 7464138.2 | V14: =O14*(G14+P14) -> 0 | W14: =U14+V14+IF(Parameters_Public!$C$26=1, T14, 0) -> 7464138.2 | X14: =IF(F14+O14>0, W14/(F14+O14),"") -> 10617.551 | Y14: =INDEX(YearMap!$I$2:$I$6, MATCH(C14, YearMap!$A$2:$A$6, 0)) -> 5215.5252 | Z14: =W14 - ((Y14 + IF(Parameters_Public!$C$20=1, Parameters_Public!$C$19, 0))*AC14) -> 3269003.1 | AA14: =IF($AC14>0, $Z14/$AC14, 0) -> 4650.0756 | AB14: =MAX(0, (MAX(0, $D14-BaselineCalc!$B$7) + MAX(0, $E14-BaselineCalc!$B$8))) -> 150 | AC14: =IF(LEFT($B14,2)="A_", $O14, IF(LEFT($B14,2)="B_", $M14+$O14, IF(LEFT($B14,2)="C_", $L14+$O14, $F14))) -> 703 | AD14: =(Y14 + IF(Parameters_Public!$C$20=1, Parameters_Public!$C$19, 0))*AC14 -> 4195135.1 | AE14: =W14 - (1-Other_Parameters!$B$2)*$G14*$AB14*$J14*(1-$K14) -> 6891966.1 | AF14: =AD14-AE14 -> -2696831 | AG14: =B14&"|"&C14 -> F_CoLocation_Echo_Targets|FY2028
A15: =AG15 -> F_CoLocation_Echo_Targets|FY2029 | B15: =Scenarios!A4 -> F_CoLocation_Echo_Targets | C15: FY2029 | D15: =IF(Scenarios!D4=1,0, L15) -> 332 | E15: =IF(Scenarios!E4=1,0, M15) -> 371 | F15: =D15+E15 -> 703 | G15: =YearMap!B5 -> 6907.7273 | H15: =YearMap!C5 -> 1512280.6 | I15: =YearMap!D5 -> 1741770.6 | J15: =1-BaselineCalc!$B$5 -> 0.993 | K15: =Scenarios!G4 -> 0.05 | L15: =BaselineCalc!$B$7 + ROUND(Scenarios!L4*Scenarios!F4,0) -> 332 | M15: =BaselineCalc!$B$8 + Scenarios!L4 - ROUND(Scenarios!L4*Scenarios!F4,0) -> 371 | N15: =(L15-D15) + (M15-E15) -> 0 | O15: =(Parameters_Public!$C$22*(L15-D15)+Parameters_Public!$C$23*(M15-E15)) -> 0 | P15: =YearMap!E5 -> 500 | Q15: =IF(Scenarios!N4="lease", YearMap!F5, YearMap!G5) -> 0.3 | R15: =IF(Scenarios!D4=1, Q15*H15, H15) -> 1512280.6 | S15: =IF(Scenarios!E4=1, Q15*I15, I15) -> 1741770.6 | T15: =IF(C15="FY2026", (Scenarios!D4+Scenarios!E4)*BaselineCalc!$B$22, 0) -> 0 | U15: =(R15+S15+G15*F15)*J15*(1-K15) -> 7650741.6 | V15: =O15*(G15+P15) -> 0 | W15: =U15+V15+IF(Parameters_Public!$C$26=1, T15, 0) -> 7650741.6 | X15: =IF(F15+O15>0, W15/(F15+O15),"") -> 10882.99 | Y15: =INDEX(YearMap!$I$2:$I$6, MATCH(C15, YearMap!$A$2:$A$6, 0)) -> 5319.8357 | Z15: =W15 - ((Y15 + IF(Parameters_Public!$C$20=1, Parameters_Public!$C$19, 0))*AC15) -> 3382276.3 | AA15: =IF($AC15>0, $Z15/$AC15, 0) -> 4811.2038 | AB15: =MAX(0, (MAX(0, $D15-BaselineCalc!$B$7) + MAX(0, $E15-BaselineCalc!$B$8))) -> 150 | AC15: =IF(LEFT($B15,2)="A_", $O15, IF(LEFT($B15,2)="B_", $M15+$O15, IF(LEFT($B15,2)="C_", $L15+$O15, $F15))) -> 703 | AD15: =(Y15 + IF(Parameters_Public!$C$20=1, Parameters_Public!$C$19, 0))*AC15 -> 4268465.3 | AE15: =W15 - (1-Other_Parameters!$B$2)*$G15*$AB15*$J15*(1-$K15) -> 7064265.2 | AF15: =AD15-AE15 -> -2795799.9 | AG15: =B15&"|"&C15 -> F_CoLocation_Echo_Targets|FY2029
A16: =AG16 -> F_CoLocation_Echo_Targets|FY2030 | B16: =Scenarios!A4 -> F_CoLocation_Echo_Targets | C16: FY2030 | D16: =IF(Scenarios!D4=1,0, L16) -> 332 | E16: =IF(Scenarios!E4=1,0, M16) -> 371 | F16: =D16+E16 -> 703 | G16: =YearMap!B6 -> 7080.4205 | H16: =YearMap!C6 -> 1550087.6 | I16: =YearMap!D6 -> 1785314.9 | J16: =1-BaselineCalc!$B$5 -> 0.993 | K16: =Scenarios!G4 -> 0.05 | L16: =BaselineCalc!$B$7 + ROUND(Scenarios!M4*Scenarios!F4,0) -> 332 | M16: =BaselineCalc!$B$8 + Scenarios!M4 - ROUND(Scenarios!M4*Scenarios!F4,0) -> 371 | N16: =(L16-D16) + (M16-E16) -> 0 | O16: =(Parameters_Public!$C$22*(L16-D16)+Parameters_Public!$C$23*(M16-E16)) -> 0 | P16: =YearMap!E6 -> 300 | Q16: =IF(Scenarios!N4="lease", YearMap!F6, YearMap!G6) -> 0.3 | R16: =IF(Scenarios!D4=1, Q16*H16, H16) -> 1550087.6 | S16: =IF(Scenarios!E4=1, Q16*I16, I16) -> 1785314.9 | T16: =IF(C16="FY2026", (Scenarios!D4+Scenarios!E4)*BaselineCalc!$B$22, 0) -> 0 | U16: =(R16+S16+G16*F16)*J16*(1-K16) -> 7842010.2 | V16: =O16*(G16+P16) -> 0 | W16: =U16+V16+IF(Parameters_Public!$C$26=1, T16, 0) -> 7842010.2 | X16: =IF(F16+O16>0, W16/(F16+O16),"") -> 11155.064 | Y16: =INDEX(YearMap!$I$2:$I$6, MATCH(C16, YearMap!$A$2:$A$6, 0)) -> 5426.2324 | Z16: =W16 - ((Y16 + IF(Parameters_Public!$C$20=1, Parameters_Public!$C$19, 0))*AC16) -> 3498747.9 | AA16: =IF($AC16>0, $Z16/$AC16, 0) -> 4976.8818 | AB16: =MAX(0, (MAX(0, $D16-BaselineCalc!$B$7) + MAX(0, $E16-BaselineCalc!$B$8))) -> 150 | AC16: =IF(LEFT($B16,2)="A_", $O16, IF(LEFT($B16,2)="B_", $M16+$O16, IF(LEFT($B16,2)="C_", $L16+$O16, $F16))) -> 703 | AD16: =(Y16 + IF(Parameters_Public!$C$20=1, Parameters_Public!$C$19, 0))*AC16 -> 4343262.2 | AE16: =W16 - (1-Other_Parameters!$B$2)*$G16*$AB16*$J16*(1-$K16) -> 7240871.9 | AF16: =AD16-AE16 -> -2897609.6 | AG16: =B16&"|"&C16 -> F_CoLocation_Echo_Targets|FY2030
A17: =AG17 -> D_Grow_Both_Targets|FY2026 | B17: =Scenarios!A5 -> D_Grow_Both_Targets | C17: FY2026 | D17: =IF(Scenarios!D5=1,0, L17) -> 382 | E17: =IF(Scenarios!E5=1,0, M17) -> 421 | F17: =D17+E17 -> 803 | G17: =YearMap!B2 -> 6414.5115 | H17: =YearMap!C2 -> 1404302.9 | I17: =YearMap!D2 -> 1617407.2 | J17: =1-BaselineCalc!$B$5 -> 0.993 | K17: =Scenarios!G5 -> 0 | L17: =BaselineCalc!$B$7 + ROUND(Scenarios!I5*Scenarios!F5,0) -> 382 | M17: =BaselineCalc!$B$8 + Scenarios!I5 - ROUND(Scenarios!I5*Scenarios!F5,0) -> 421 | N17: =(L17-D17) + (M17-E17) -> 0 | O17: =(Parameters_Public!$C$22*(L17-D17)+Parameters_Public!$C$23*(M17-E17)) -> 0 | P17: =YearMap!E2 -> 1000 | Q17: =IF(Scenarios!N5="lease", YearMap!F2, YearMap!G2) -> 0.5 | R17: =IF(Scenarios!D5=1, Q17*H17, H17) -> 1404302.9 | S17: =IF(Scenarios!E5=1, Q17*I17, I17) -> 1617407.2 | T17: =IF(C17="FY2026", (Scenarios!D5+Scenarios!E5)*BaselineCalc!$B$22, 0) -> 0 | U17: =(R17+S17+G17*F17)*J17*(1-K17) -> 8115354.9 | V17: =O17*(G17+P17) -> 0 | W17: =U17+V17+IF(Parameters_Public!$C$26=1, T17, 0) -> 8115354.9 | X17: =IF(F17+O17>0, W17/(F17+O17),"") -> 10106.295 | Y17: =INDEX(YearMap!$I$2:$I$6, MATCH(C17, YearMap!$A$2:$A$6, 0)) -> 5013 | Z17: =W17 - ((Y17 + IF(Parameters_Public!$C$20=1, Parameters_Public!$C$19, 0))*AC17) -> 3486100 | AA17: =IF($AC17>0, $Z17/$AC17, 0) -> 4341.345 | AB17: =MAX(0, (MAX(0, $D17-BaselineCalc!$B$7) + MAX(0, $E17-BaselineCalc!$B$8))) -> 250 | AC17: =IF(LEFT($B17,2)="A_", $O17, IF(LEFT($B17,2)="B_", $M17+$O17, IF(LEFT($B17,2)="C_", $L17+$O17, $F17))) -> 803 | AD17: =(Y17 + IF(Parameters_Public!$C$20=1, Parameters_Public!$C$19, 0))*AC17 -> 4629254.8 | AE17: =W17 - (1-Other_Parameters!$B$2)*$G17*$AB17*$J17*(1-$K17) -> 7159913.4 | AF17: =AD17-AE17 -> -2530658.5 | AG17: =B17&"|"&C17 -> D_Grow_Both_Targets|FY2026
A18: =AG18 -> D_Grow_Both_Targets|FY2027 | B18: =Scenarios!A5 -> D_Grow_Both_Targets | C18: FY2027 | D18: =IF(Scenarios!D5=1,0, L18) -> 382 | E18: =IF(Scenarios!E5=1,0, M18) -> 421 | F18: =D18+E18 -> 803 | G18: =YearMap!B3 -> 6574.8743 | H18: =YearMap!C3 -> 1439410.4 | I18: =YearMap!D3 -> 1657842.4 | J18: =1-BaselineCalc!$B$5 -> 0.993 | K18: =Scenarios!G5 -> 0 | L18: =BaselineCalc!$B$7 + ROUND(Scenarios!J5*Scenarios!F5,0) -> 382 | M18: =BaselineCalc!$B$8 + Scenarios!J5 - ROUND(Scenarios!J5*Scenarios!F5,0) -> 421 | N18: =(L18-D18) + (M18-E18) -> 0 | O18: =(Parameters_Public!$C$22*(L18-D18)+Parameters_Public!$C$23*(M18-E18)) -> 0 | P18: =YearMap!E3 -> 800 | Q18: =IF(Scenarios!N5="lease", YearMap!F3, YearMap!G3) -> 0.4 | R18: =IF(Scenarios!D5=1, Q18*H18, H18) -> 1439410.4 | S18: =IF(Scenarios!E5=1, Q18*I18, I18) -> 1657842.4 | T18: =IF(C18="FY2026", (Scenarios!D5+Scenarios!E5)*BaselineCalc!$B$22, 0) -> 0 | U18: =(R18+S18+G18*F18)*J18*(1-K18) -> 8318238.7 | V18: =O18*(G18+P18) -> 0 | W18: =U18+V18+IF(Parameters_Public!$C$26=1, T18, 0) -> 8318238.7 | X18: =IF(F18+O18>0, W18/(F18+O18),"") -> 10358.952 | Y18: =INDEX(YearMap!$I$2:$I$6, MATCH(C18, YearMap!$A$2:$A$6, 0)) -> 5113.26 | Z18: =W18 - ((Y18 + IF(Parameters_Public!$C$20=1, Parameters_Public!$C$19, 0))*AC18) -> 3608475.1 | AA18: =IF($AC18>0, $Z18/$AC18, 0) -> 4493.7423 | AB18: =MAX(0, (MAX(0, $D18-BaselineCalc!$B$7) + MAX(0, $E18-BaselineCalc!$B$8))) -> 250 | AC18: =IF(LEFT($B18,2)="A_", $O18, IF(LEFT($B18,2)="B_", $M18+$O18, IF(LEFT($B18,2)="C_", $L18+$O18, $F18))) -> 803 | AD18: =(Y18 + IF(Parameters_Public!$C$20=1, Parameters_Public!$C$19, 0))*AC18 -> 4709763.6 | AE18: =W18 - (1-Other_Parameters!$B$2)*$G18*$AB18*$J18*(1-$K18) -> 7338911.2 | AF18: =AD18-AE18 -> -2629147.6 | AG18: =B18&"|"&C18 -> D_Grow_Both_Targets|FY2027
A19: =AG19 -> D_Grow_Both_Targets|FY2028 | B19: =Scenarios!A5 -> D_Grow_Both_Targets | C19: FY2028 | D19: =IF(Scenarios!D5=1,0, L19) -> 382 | E19: =IF(Scenarios!E5=1,0, M19) -> 421 | F19: =D19+E19 -> 803 | G19: =YearMap!B4 -> 6739.2461 | H19: =YearMap!C4 -> 1475395.7 | I19: =YearMap!D4 -> 1699288.4 | J19: =1-BaselineCalc!$B$5 -> 0.993 | K19: =Scenarios!G5 -> 0 | L19: =BaselineCalc!$B$7 + ROUND(Scenarios!K5*Scenarios!F5,0) -> 382 | M19: =BaselineCalc!$B$8 + Scenarios!K5 - ROUND(Scenarios!K5*Scenarios!F5,0) -> 421 | N19: =(L19-D19) + (M19-E19) -> 0 | O19: =(Parameters_Public!$C$22*(L19-D19)+Parameters_Public!$C$23*(M19-E19)) -> 0 | P19: =YearMap!E4 -> 600 | Q19: =IF(Scenarios!N5="lease", YearMap!F4, YearMap!G4) -> 0.35 | R19: =IF(Scenarios!D5=1, Q19*H19, H19) -> 1475395.7 | S19: =IF(Scenarios!E5=1, Q19*I19, I19) -> 1699288.4 | T19: =IF(C19="FY2026", (Scenarios!D5+Scenarios!E5)*BaselineCalc!$B$22, 0) -> 0 | U19: =(R19+S19+G19*F19)*J19*(1-K19) -> 8526194.7 | V19: =O19*(G19+P19) -> 0 | W19: =U19+V19+IF(Parameters_Public!$C$26=1, T19, 0) -> 8526194.7 | X19: =IF(F19+O19>0, W19/(F19+O19),"") -> 10617.926 | Y19: =INDEX(YearMap!$I$2:$I$6, MATCH(C19, YearMap!$A$2:$A$6, 0)) -> 5215.5252 | Z19: =W19 - ((Y19 + IF(Parameters_Public!$C$20=1, Parameters_Public!$C$19, 0))*AC19) -> 3734312.1 | AA19: =IF($AC19>0, $Z19/$AC19, 0) -> 4650.451 | AB19: =MAX(0, (MAX(0, $D19-BaselineCalc!$B$7) + MAX(0, $E19-BaselineCalc!$B$8))) -> 250 | AC19: =IF(LEFT($B19,2)="A_", $O19, IF(LEFT($B19,2)="B_", $M19+$O19, IF(LEFT($B19,2)="C_", $L19+$O19, $F19))) -> 803 | AD19: =(Y19 + IF(Parameters_Public!$C$20=1, Parameters_Public!$C$19, 0))*AC19 -> 4791882.6 | AE19: =W19 - (1-Other_Parameters!$B$2)*$G19*$AB19*$J19*(1-$K19) -> 7522384 | AF19: =AD19-AE19 -> -2730501.4 | AG19: =B19&"|"&C19 -> D_Grow_Both_Targets|FY2028
A20: =AG20 -> D_Grow_Both_Targets|FY2029 | B20: =Scenarios!A5 -> D_Grow_Both_Targets | C20: FY2029 | D20: =IF(Scenarios!D5=1,0, L20) -> 382 | E20: =IF(Scenarios!E5=1,0, M20) -> 421 | F20: =D20+E20 -> 803 | G20: =YearMap!B5 -> 6907.7273 | H20: =YearMap!C5 -> 1512280.6 | I20: =YearMap!D5 -> 1741770.6 | J20: =1-BaselineCalc!$B$5 -> 0.993 | K20: =Scenarios!G5 -> 0 | L20: =BaselineCalc!$B$7 + ROUND(Scenarios!L5*Scenarios!F5,0) -> 382 | M20: =BaselineCalc!$B$8 + Scenarios!L5 - ROUND(Scenarios!L5*Scenarios!F5,0) -> 421 | N20: =(L20-D20) + (M20-E20) -> 0 | O20: =(Parameters_Public!$C$22*(L20-D20)+Parameters_Public!$C$23*(M20-E20)) -> 0 | P20: =YearMap!E5 -> 500 | Q20: =IF(Scenarios!N5="lease", YearMap!F5, YearMap!G5) -> 0.3 | R20: =IF(Scenarios!D5=1, Q20*H20, H20) -> 1512280.6 | S20: =IF(Scenarios!E5=1, Q20*I20, I20) -> 1741770.6 | T20: =IF(C20="FY2026", (Scenarios!D5+Scenarios!E5)*BaselineCalc!$B$22, 0) -> 0 | U20: =(R20+S20+G20*F20)*J20*(1-K20) -> 8739349.6 | V20: =O20*(G20+P20) -> 0 | W20: =U20+V20+IF(Parameters_Public!$C$26=1, T20, 0) -> 8739349.6 | X20: =IF(F20+O20>0, W20/(F20+O20),"") -> 10883.374 | Y20: =INDEX(YearMap!$I$2:$I$6, MATCH(C20, YearMap!$A$2:$A$6, 0)) -> 5319.8357 | Z20: =W20 - ((Y20 + IF(Parameters_Public!$C$20=1, Parameters_Public!$C$19, 0))*AC20) -> 3863705.6 | AA20: =IF($AC20>0, $Z20/$AC20, 0) -> 4811.5886 | AB20: =MAX(0, (MAX(0, $D20-BaselineCalc!$B$7) + MAX(0, $E20-BaselineCalc!$B$8))) -> 250 | AC20: =IF(LEFT($B20,2)="A_", $O20, IF(LEFT($B20,2)="B_", $M20+$O20, IF(LEFT($B20,2)="C_", $L20+$O20, $F20))) -> 803 | AD20: =(Y20 + IF(Parameters_Public!$C$20=1, Parameters_Public!$C$19, 0))*AC20 -> 4875643.9 | AE20: =W20 - (1-Other_Parameters!$B$2)*$G20*$AB20*$J20*(1-$K20) -> 7710443.6 | AF20: =AD20-AE20 -> -2834799.7 | AG20: =B20&"|"&C20 -> D_Grow_Both_Targets|FY2029
A21: =AG21 -> D_Grow_Both_Targets|FY2030 | B21: =Scenarios!A5 -> D_Grow_Both_Targets | C21: FY2030 | D21: =IF(Scenarios!D5=1,0, L21) -> 382 | E21: =IF(Scenarios!E5=1,0, M21) -> 421 | F21: =D21+E21 -> 803 | G21: =YearMap!B6 -> 7080.4205 | H21: =YearMap!C6 -> 1550087.6 | I21: =YearMap!D6 -> 1785314.9 | J21: =1-BaselineCalc!$B$5 -> 0.993 | K21: =Scenarios!G5 -> 0 | L21: =BaselineCalc!$B$7 + ROUND(Scenarios!M5*Scenarios!F5,0) -> 382 | M21: =BaselineCalc!$B$8 + Scenarios!M5 - ROUND(Scenarios!M5*Scenarios!F5,0) -> 421 | N21: =(L21-D21) + (M21-E21) -> 0 | O21: =(Parameters_Public!$C$22*(L21-D21)+Parameters_Public!$C$23*(M21-E21)) -> 0 | P21: =YearMap!E6 -> 300 | Q21: =IF(Scenarios!N5="lease", YearMap!F6, YearMap!G6) -> 0.3 | R21: =IF(Scenarios!D5=1, Q21*H21, H21) -> 1550087.6 | S21: =IF(Scenarios!E5=1, Q21*I21, I21) -> 1785314.9 | T21: =IF(C21="FY2026", (Scenarios!D5+Scenarios!E5)*BaselineCalc!$B$22, 0) -> 0 | U21: =(R21+S21+G21*F21)*J21*(1-K21) -> 8957833.3 | V21: =O21*(G21+P21) -> 0 | W21: =U21+V21+IF(Parameters_Public!$C$26=1, T21, 0) -> 8957833.3 | X21: =IF(F21+O21>0, W21/(F21+O21),"") -> 11155.459 | Y21: =INDEX(YearMap!$I$2:$I$6, MATCH(C21, YearMap!$A$2:$A$6, 0)) -> 5426.2324 | Z21: =W21 - ((Y21 + IF(Parameters_Public!$C$20=1, Parameters_Public!$C$19, 0))*AC21) -> 3996752.8 | AA21: =IF($AC21>0, $Z21/$AC21, 0) -> 4977.2762 | AB21: =MAX(0, (MAX(0, $D21-BaselineCalc!$B$7) + MAX(0, $E21-BaselineCalc!$B$8))) -> 250 | AC21: =IF(LEFT($B21,2)="A_", $O21, IF(LEFT($B21,2)="B_", $M21+$O21, IF(LEFT($B21,2)="C_", $L21+$O21, $F21))) -> 803 | AD21: =(Y21 + IF(Parameters_Public!$C$20=1, Parameters_Public!$C$19, 0))*AC21 -> 4961080.5 | AE21: =W21 - (1-Other_Parameters!$B$2)*$G21*$AB21*$J21*(1-$K21) -> 7903204.7 | AF21: =AD21-AE21 -> -2942124.2 | AG21: =B21&"|"&C21 -> D_Grow_Both_Targets|FY2030
A22: =AG22 -> D_CUSTOM2|FY2026 | B22: =Scenarios!A6 -> D_CUSTOM2 | C22: FY2026 | D22: =IF(Scenarios!D6=1,0, L22) -> 257 | E22: =IF(Scenarios!E6=1,0, M22) -> 296 | F22: =D22+E22 -> 553 | G22: =YearMap!B2 -> 6414.5115 | H22: =YearMap!C2 -> 1404302.9 | I22: =YearMap!D2 -> 1617407.2 | J22: =1-BaselineCalc!$B$5 -> 0.993 | K22: =Scenarios!G6 -> 0 | L22: =BaselineCalc!$B$7 + ROUND(Scenarios!I6*Scenarios!F6,0) -> 257 | M22: =BaselineCalc!$B$8 + Scenarios!I6 - ROUND(Scenarios!I6*Scenarios!F6,0) -> 296 | N22: =(L22-D22) + (M22-E22) -> 0 | O22: =(Parameters_Public!$C$22*(L22-D22)+Parameters_Public!$C$23*(M22-E22)) -> 0 | P22: =YearMap!E2 -> 1000 | Q22: =IF(Scenarios!N6="lease", YearMap!F2, YearMap!G2) -> 0.5 | R22: =IF(Scenarios!D6=1, Q22*H22, H22) -> 1404302.9 | S22: =IF(Scenarios!E6=1, Q22*I22, I22) -> 1617407.2 | T22: =IF(C22="FY2026", (Scenarios!D6+Scenarios!E6)*BaselineCalc!$B$22, 0) -> 0 | U22: =(R22+S22+G22*F22)*J22*(1-K22) -> 6522952.4 | V22: =O22*(G22+P22) -> 0 | W22: =U22+V22+IF(Parameters_Public!$C$26=1, T22, 0) -> 6522952.4 | X22: =IF(F22+O22>0, W22/(F22+O22),"") -> 11795.574 | Y22: =INDEX(YearMap!$I$2:$I$6, MATCH(C22, YearMap!$A$2:$A$6, 0)) -> 5013 | Z22: =W22 - ((Y22 + IF(Parameters_Public!$C$20=1, Parameters_Public!$C$19, 0))*AC22) -> 3334935 | AA22: =IF($AC22>0, $Z22/$AC22, 0) -> 6030.6239 | AB22: =MAX(0, (MAX(0, $D22-BaselineCalc!$B$7) + MAX(0, $E22-BaselineCalc!$B$8))) -> 0 | AC22: =IF(LEFT($B22,2)="A_", $O22, IF(LEFT($B22,2)="B_", $M22+$O22, IF(LEFT($B22,2)="C_", $L22+$O22, $F22))) -> 553 | AD22: =(Y22 + IF(Parameters_Public!$C$20=1, Parameters_Public!$C$19, 0))*AC22 -> 3188017.4 | AE22: =W22 - (1-Other_Parameters!$B$2)*$G22*$AB22*$J22*(1-$K22) -> 6522952.4 | AF22: =AD22-AE22 -> -3334935 | AG22: =B22&"|"&C22 -> D_CUSTOM2|FY2026
A23: =AG23 -> D_CUSTOM2|FY2027 | B23: =Scenarios!A6 -> D_CUSTOM2 | C23: FY2027 | D23: =IF(Scenarios!D6=1,0, L23) -> 257 | E23: =IF(Scenarios!E6=1,0, M23) -> 296 | F23: =D23+E23 -> 553 | G23: =YearMap!B3 -> 6574.8743 | H23: =YearMap!C3 -> 1439410.4 | I23: =YearMap!D3 -> 1657842.4 | J23: =1-BaselineCalc!$B$5 -> 0.993 | K23: =Scenarios!G6 -> 0 | L23: =BaselineCalc!$B$7 + ROUND(Scenarios!J6*Scenarios!F6,0) -> 257 | M23: =BaselineCalc!$B$8 + Scenarios!J6 - ROUND(Scenarios!J6*Scenarios!F6,0) -> 296 | N23: =(L23-D23) + (M23-E23) -> 0 | O23: =(Parameters_Public!$C$22*(L23-D23)+Parameters_Public!$C$23*(M23-E23)) -> 0 | P23: =YearMap!E3 -> 800 | Q23: =IF(Scenarios!N6="lease", YearMap!F3, YearMap!G3) -> 0.4 | R23: =IF(Scenarios!D6=1, Q23*H23, H23) -> 1439410.4 | S23: =IF(Scenarios!E6=1, Q23*I23, I23) -> 1657842.4 | T23: =IF(C23="FY2026", (Scenarios!D6+Scenarios!E6)*BaselineCalc!$B$22, 0) -> 0 | U23: =(R23+S23+G23*F23)*J23*(1-K23) -> 6686026.2 | V23: =O23*(G23+P23) -> 0 | W23: =U23+V23+IF(Parameters_Public!$C$26=1, T23, 0) -> 6686026.2 | X23: =IF(F23+O23>0, W23/(F23+O23),"") -> 12090.463 | Y23: =INDEX(YearMap!$I$2:$I$6, MATCH(C23, YearMap!$A$2:$A$6, 0)) -> 5113.26 | Z23: =W23 - ((Y23 + IF(Parameters_Public!$C$20=1, Parameters_Public!$C$19, 0))*AC23) -> 3442565.1 | AA23: =IF($AC23>0, $Z23/$AC23, 0) -> 6225.2533 | AB23: =MAX(0, (MAX(0, $D23-BaselineCalc!$B$7) + MAX(0, $E23-BaselineCalc!$B$8))) -> 0 | AC23: =IF(LEFT($B23,2)="A_", $O23, IF(LEFT($B23,2)="B_", $M23+$O23, IF(LEFT($B23,2)="C_", $L23+$O23, $F23))) -> 553 | AD23: =(Y23 + IF(Parameters_Public!$C$20=1, Parameters_Public!$C$19, 0))*AC23 -> 3243461.1 | AE23: =W23 - (1-Other_Parameters!$B$2)*$G23*$AB23*$J23*(1-$K23) -> 6686026.2 | AF23: =AD23-AE23 -> -3442565.1 | AG23: =B23&"|"&C23 -> D_CUSTOM2|FY2027
A24: =AG24 -> D_CUSTOM2|FY2028 | B24: =Scenarios!A6 -> D_CUSTOM2 | C24: FY2028 | D24: =IF(Scenarios!D6=1,0, L24) -> 257 | E24: =IF(Scenarios!E6=1,0, M24) -> 296 | F24: =D24+E24 -> 553 | G24: =YearMap!B4 -> 6739.2461 | H24: =YearMap!C4 -> 1475395.7 | I24: =YearMap!D4 -> 1699288.4 | J24: =1-BaselineCalc!$B$5 -> 0.993 | K24: =Scenarios!G6 -> 0 | L24: =BaselineCalc!$B$7 + ROUND(Scenarios!K6*Scenarios!F6,0) -> 257 | M24: =BaselineCalc!$B$8 + Scenarios!K6 - ROUND(Scenarios!K6*Scenarios!F6,0) -> 296 | N24: =(L24-D24) + (M24-E24) -> 0 | O24: =(Parameters_Public!$C$22*(L24-D24)+Parameters_Public!$C$23*(M24-E24)) -> 0 | P24: =YearMap!E4 -> 600 | Q24: =IF(Scenarios!N6="lease", YearMap!F4, YearMap!G4) -> 0.35 | R24: =IF(Scenarios!D6=1, Q24*H24, H24) -> 1475395.7 | S24: =IF(Scenarios!E6=1, Q24*I24, I24) -> 1699288.4 | T24: =IF(C24="FY2026", (Scenarios!D6+Scenarios!E6)*BaselineCalc!$B$22, 0) -> 0 | U24: =(R24+S24+G24*F24)*J24*(1-K24) -> 6853176.8 | V24: =O24*(G24+P24) -> 0 | W24: =U24+V24+IF(Parameters_Public!$C$26=1, T24, 0) -> 6853176.8 | X24: =IF(F24+O24>0, W24/(F24+O24),"") -> 12392.725 | Y24: =INDEX(YearMap!$I$2:$I$6, MATCH(C24, YearMap!$A$2:$A$6, 0)) -> 5215.5252 | Z24: =W24 - ((Y24 + IF(Parameters_Public!$C$20=1, Parameters_Public!$C$19, 0))*AC24) -> 3553163.1 | AA24: =IF($AC24>0, $Z24/$AC24, 0) -> 6425.2497 | AB24: =MAX(0, (MAX(0, $D24-BaselineCalc!$B$7) + MAX(0, $E24-BaselineCalc!$B$8))) -> 0 | AC24: =IF(LEFT($B24,2)="A_", $O24, IF(LEFT($B24,2)="B_", $M24+$O24, IF(LEFT($B24,2)="C_", $L24+$O24, $F24))) -> 553 | AD24: =(Y24 + IF(Parameters_Public!$C$20=1, Parameters_Public!$C$19, 0))*AC24 -> 3300013.8 | AE24: =W24 - (1-Other_Parameters!$B$2)*$G24*$AB24*$J24*(1-$K24) -> 6853176.8 | AF24: =AD24-AE24 -> -3553163.1 | AG24: =B24&"|"&C24 -> D_CUSTOM2|FY2028
A25: =AG25 -> D_CUSTOM2|FY2029 | B25: =Scenarios!A6 -> D_CUSTOM2 | C25: FY2029 | D25: =IF(Scenarios!D6=1,0, L25) -> 257 | E25: =IF(Scenarios!E6=1,0, M25) -> 296 | F25: =D25+E25 -> 553 | G25: =YearMap!B5 -> 6907.7273 | H25: =YearMap!C5 -> 1512280.6 | I25: =YearMap!D5 -> 1741770.6 | J25: =1-BaselineCalc!$B$5 -> 0.993 | K25: =Scenarios!G6 -> 0 | L25: =BaselineCalc!$B$7 + ROUND(Scenarios!L6*Scenarios!F6,0) -> 257 | M25: =BaselineCalc!$B$8 + Scenarios!L6 - ROUND(Scenarios!L6*Scenarios!F6,0) -> 296 | N25: =(L25-D25) + (M25-E25) -> 0 | O25: =(Parameters_Public!$C$22*(L25-D25)+Parameters_Public!$C$23*(M25-E25)) -> 0 | P25: =YearMap!E5 -> 500 | Q25: =IF(Scenarios!N6="lease", YearMap!F5, YearMap!G5) -> 0.3 | R25: =IF(Scenarios!D6=1, Q25*H25, H25) -> 1512280.6 | S25: =IF(Scenarios!E6=1, Q25*I25, I25) -> 1741770.6 | T25: =IF(C25="FY2026", (Scenarios!D6+Scenarios!E6)*BaselineCalc!$B$22, 0) -> 0 | U25: =(R25+S25+G25*F25)*J25*(1-K25) -> 7024506.3 | V25: =O25*(G25+P25) -> 0 | W25: =U25+V25+IF(Parameters_Public!$C$26=1, T25, 0) -> 7024506.3 | X25: =IF(F25+O25>0, W25/(F25+O25),"") -> 12702.543 | Y25: =INDEX(YearMap!$I$2:$I$6, MATCH(C25, YearMap!$A$2:$A$6, 0)) -> 5319.8357 | Z25: =W25 - ((Y25 + IF(Parameters_Public!$C$20=1, Parameters_Public!$C$19, 0))*AC25) -> 3666808.8 | AA25: =IF($AC25>0, $Z25/$AC25, 0) -> 6630.7573 | AB25: =MAX(0, (MAX(0, $D25-BaselineCalc!$B$7) + MAX(0, $E25-BaselineCalc!$B$8))) -> 0 | AC25: =IF(LEFT($B25,2)="A_", $O25, IF(LEFT($B25,2)="B_", $M25+$O25, IF(LEFT($B25,2)="C_", $L25+$O25, $F25))) -> 553 | AD25: =(Y25 + IF(Parameters_Public!$C$20=1, Parameters_Public!$C$19, 0))*AC25 -> 3357697.5 | AE25: =W25 - (1-Other_Parameters!$B$2)*$G25*$AB25*$J25*(1-$K25) -> 7024506.3 | AF25: =AD25-AE25 -> -3666808.8 | AG25: =B25&"|"&C25 -> D_CUSTOM2|FY2029
A26: =AG26 -> D_CUSTOM2|FY2030 | B26: =Scenarios!A6 -> D_CUSTOM2 | C26: FY2030 | D26: =IF(Scenarios!D6=1,0, L26) -> 257 | E26: =IF(Scenarios!E6=1,0, M26) -> 296 | F26: =D26+E26 -> 553 | G26: =YearMap!B6 -> 7080.4205 | H26: =YearMap!C6 -> 1550087.6 | I26: =YearMap!D6 -> 1785314.9 | J26: =1-BaselineCalc!$B$5 -> 0.993 | K26: =Scenarios!G6 -> 0 | L26: =BaselineCalc!$B$7 + ROUND(Scenarios!M6*Scenarios!F6,0) -> 257 | M26: =BaselineCalc!$B$8 + Scenarios!M6 - ROUND(Scenarios!M6*Scenarios!F6,0) -> 296 | N26: =(L26-D26) + (M26-E26) -> 0 | O26: =(Parameters_Public!$C$22*(L26-D26)+Parameters_Public!$C$23*(M26-E26)) -> 0 | P26: =YearMap!E6 -> 300 | Q26: =IF(Scenarios!N6="lease", YearMap!F6, YearMap!G6) -> 0.3 | R26: =IF(Scenarios!D6=1, Q26*H26, H26) -> 1550087.6 | S26: =IF(Scenarios!E6=1, Q26*I26, I26) -> 1785314.9 | T26: =IF(C26="FY2026", (Scenarios!D6+Scenarios!E6)*BaselineCalc!$B$22, 0) -> 0 | U26: =(R26+S26+G26*F26)*J26*(1-K26) -> 7200118.9 | V26: =O26*(G26+P26) -> 0 | W26: =U26+V26+IF(Parameters_Public!$C$26=1, T26, 0) -> 7200118.9 | X26: =IF(F26+O26>0, W26/(F26+O26),"") -> 13020.107 | Y26: =INDEX(YearMap!$I$2:$I$6, MATCH(C26, YearMap!$A$2:$A$6, 0)) -> 5426.2324 | Z26: =W26 - ((Y26 + IF(Parameters_Public!$C$20=1, Parameters_Public!$C$19, 0))*AC26) -> 3783584 | AA26: =IF($AC26>0, $Z26/$AC26, 0) -> 6841.9241 | AB26: =MAX(0, (MAX(0, $D26-BaselineCalc!$B$7) + MAX(0, $E26-BaselineCalc!$B$8))) -> 0 | AC26: =IF(LEFT($B26,2)="A_", $O26, IF(LEFT($B26,2)="B_", $M26+$O26, IF(LEFT($B26,2)="C_", $L26+$O26, $F26))) -> 553 | AD26: =(Y26 + IF(Parameters_Public!$C$20=1, Parameters_Public!$C$19, 0))*AC26 -> 3416534.9 | AE26: =W26 - (1-Other_Parameters!$B$2)*$G26*$AB26*$J26*(1-$K26) -> 7200118.9 | AF26: =AD26-AE26 -> -3783584 | AG26: =B26&"|"&C26 -> D_CUSTOM2|FY2030
A27: =AG27 -> G_EchoGHubRamp_PimaTargets|FY2026 | B27: =Scenarios!A7 -> G_EchoGHubRamp_PimaTargets | C27: FY2026 | D27: =IF(Scenarios!D7=1,0, L27) -> 292 | E27: =IF(Scenarios!E7=1,0, M27) -> 311 | F27: =D27+E27 -> 603 | G27: =YearMap!B2 -> 6414.5115 | H27: =YearMap!C2 -> 1404302.9 | I27: =YearMap!D2 -> 1617407.2 | J27: =1-BaselineCalc!$B$5 -> 0.993 | K27: =Scenarios!G7 -> 0 | L27: =BaselineCalc!$B$7 + ROUND(Scenarios!I7*Scenarios!F7,0) -> 292 | M27: =BaselineCalc!$B$8 + Scenarios!I7 - ROUND(Scenarios!I7*Scenarios!F7,0) -> 311 | N27: =(L27-D27) + (M27-E27) -> 0 | O27: =(Parameters_Public!$C$22*(L27-D27)+Parameters_Public!$C$23*(M27-E27)) -> 0 | P27: =YearMap!E2 -> 1000 | Q27: =IF(Scenarios!N7="lease", YearMap!F2, YearMap!G2) -> 0.5 | R27: =IF(Scenarios!D7=1, Q27*H27, H27) -> 1404302.9 | S27: =IF(Scenarios!E7=1, Q27*I27, I27) -> 1617407.2 | T27: =IF(C27="FY2026", (Scenarios!D7+Scenarios!E7)*BaselineCalc!$B$22, 0) -> 0 | U27: =(R27+S27+G27*F27)*J27*(1-K27) -> 6841432.9 | V27: =O27*(G27+P27) -> 0 | W27: =U27+V27+IF(Parameters_Public!$C$26=1, T27, 0) -> 6841432.9 | X27: =IF(F27+O27>0, W27/(F27+O27),"") -> 11345.66 | Y27: =INDEX(YearMap!$I$2:$I$6, MATCH(C27, YearMap!$A$2:$A$6, 0)) -> 5013 | Z27: =W27 - ((Y27 + IF(Parameters_Public!$C$20=1, Parameters_Public!$C$19, 0))*AC27) -> 3365168 | AA27: =IF($AC27>0, $Z27/$AC27, 0) -> 5580.7098 | AB27: =MAX(0, (MAX(0, $D27-BaselineCalc!$B$7) + MAX(0, $E27-BaselineCalc!$B$8))) -> 50 | AC27: =IF(LEFT($B27,2)="A_", $O27, IF(LEFT($B27,2)="B_", $M27+$O27, IF(LEFT($B27,2)="C_", $L27+$O27, $F27))) -> 603 | AD27: =(Y27 + IF(Parameters_Public!$C$20=1, Parameters_Public!$C$19, 0))*AC27 -> 3476264.9 | AE27: =W27 - (1-Other_Parameters!$B$2)*$G27*$AB27*$J27*(1-$K27) -> 6650344.6 | AF27: =AD27-AE27 -> -3174079.7 | AG27: =B27&"|"&C27 -> G_EchoGHubRamp_PimaTargets|FY2026
A28: =AG28 -> G_EchoGHubRamp_PimaTargets|FY2027 | B28: =Scenarios!A7 -> G_EchoGHubRamp_PimaTargets | C28: FY2027 | D28: =IF(Scenarios!D7=1,0, L28) -> 327 | E28: =IF(Scenarios!E7=1,0, M28) -> 326 | F28: =D28+E28 -> 653 | G28: =YearMap!B3 -> 6574.8743 | H28: =YearMap!C3 -> 1439410.4 | I28: =YearMap!D3 -> 1657842.4 | J28: =1-BaselineCalc!$B$5 -> 0.993 | K28: =Scenarios!G7 -> 0 | L28: =BaselineCalc!$B$7 + ROUND(Scenarios!J7*Scenarios!F7,0) -> 327 | M28: =BaselineCalc!$B$8 + Scenarios!J7 - ROUND(Scenarios!J7*Scenarios!F7,0) -> 326 | N28: =(L28-D28) + (M28-E28) -> 0 | O28: =(Parameters_Public!$C$22*(L28-D28)+Parameters_Public!$C$23*(M28-E28)) -> 0 | P28: =YearMap!E3 -> 800 | Q28: =IF(Scenarios!N7="lease", YearMap!F3, YearMap!G3) -> 0.4 | R28: =IF(Scenarios!D7=1, Q28*H28, H28) -> 1439410.4 | S28: =IF(Scenarios!E7=1, Q28*I28, I28) -> 1657842.4 | T28: =IF(C28="FY2026", (Scenarios!D7+Scenarios!E7)*BaselineCalc!$B$22, 0) -> 0 | U28: =(R28+S28+G28*F28)*J28*(1-K28) -> 7338911.2 | V28: =O28*(G28+P28) -> 0 | W28: =U28+V28+IF(Parameters_Public!$C$26=1, T28, 0) -> 7338911.2 | X28: =IF(F28+O28>0, W28/(F28+O28),"") -> 11238.761 | Y28: =INDEX(YearMap!$I$2:$I$6, MATCH(C28, YearMap!$A$2:$A$6, 0)) -> 5113.26 | Z28: =W28 - ((Y28 + IF(Parameters_Public!$C$20=1, Parameters_Public!$C$19, 0))*AC28) -> 3508929.1 | AA28: =IF($AC28>0, $Z28/$AC28, 0) -> 5373.5514 | AB28: =MAX(0, (MAX(0, $D28-BaselineCalc!$B$7) + MAX(0, $E28-BaselineCalc!$B$8))) -> 100 | AC28: =IF(LEFT($B28,2)="A_", $O28, IF(LEFT($B28,2)="B_", $M28+$O28, IF(LEFT($B28,2)="C_", $L28+$O28, $F28))) -> 653 | AD28: =(Y28 + IF(Parameters_Public!$C$20=1, Parameters_Public!$C$19, 0))*AC28 -> 3829982.1 | AE28: =W28 - (1-Other_Parameters!$B$2)*$G28*$AB28*$J28*(1-$K28) -> 6947180.2 | AF28: =AD28-AE28 -> -3117198.1 | AG28: =B28&"|"&C28 -> G_EchoGHubRamp_PimaTargets|FY2027
A29: =AG29 -> G_EchoGHubRamp_PimaTargets|FY2028 | B29: =Scenarios!A7 -> G_EchoGHubRamp_PimaTargets | C29: FY2028 | D29: =IF(Scenarios!D7=1,0, L29) -> 362 | E29: =IF(Scenarios!E7=1,0, M29) -> 341 | F29: =D29+E29 -> 703 | G29: =YearMap!B4 -> 6739.2461 | H29: =YearMap!C4 -> 1475395.7 | I29: =YearMap!D4 -> 1699288.4 | J29: =1-BaselineCalc!$B$5 -> 0.993 | K29: =Scenarios!G7 -> 0 | L29: =BaselineCalc!$B$7 + ROUND(Scenarios!K7*Scenarios!F7,0) -> 362 | M29: =BaselineCalc!$B$8 + Scenarios!K7 - ROUND(Scenarios!K7*Scenarios!F7,0) -> 341 | N29: =(L29-D29) + (M29-E29) -> 0 | O29: =(Parameters_Public!$C$22*(L29-D29)+Parameters_Public!$C$23*(M29-E29)) -> 0 | P29: =YearMap!E4 -> 600 | Q29: =IF(Scenarios!N7="lease", YearMap!F4, YearMap!G4) -> 0.35 | R29: =IF(Scenarios!D7=1, Q29*H29, H29) -> 1475395.7 | S29: =IF(Scenarios!E7=1, Q29*I29, I29) -> 1699288.4 | T29: =IF(C29="FY2026", (Scenarios!D7+Scenarios!E7)*BaselineCalc!$B$22, 0) -> 0 | U29: =(R29+S29+G29*F29)*J29*(1-K29) -> 7856987.6 | V29: =O29*(G29+P29) -> 0 | W29: =U29+V29+IF(Parameters_Public!$C$26=1, T29, 0) -> 7856987.6 | X29: =IF(F29+O29>0, W29/(F29+O29),"") -> 11176.369 | Y29: =INDEX(YearMap!$I$2:$I$6, MATCH(C29, YearMap!$A$2:$A$6, 0)) -> 5215.5252 | Z29: =W29 - ((Y29 + IF(Parameters_Public!$C$20=1, Parameters_Public!$C$19, 0))*AC29) -> 3661852.5 | AA29: =IF($AC29>0, $Z29/$AC29, 0) -> 5208.894 | AB29: =MAX(0, (MAX(0, $D29-BaselineCalc!$B$7) + MAX(0, $E29-BaselineCalc!$B$8))) -> 150 | AC29: =IF(LEFT($B29,2)="A_", $O29, IF(LEFT($B29,2)="B_", $M29+$O29, IF(LEFT($B29,2)="C_", $L29+$O29, $F29))) -> 703 | AD29: =(Y29 + IF(Parameters_Public!$C$20=1, Parameters_Public!$C$19, 0))*AC29 -> 4195135.1 | AE29: =W29 - (1-Other_Parameters!$B$2)*$G29*$AB29*$J29*(1-$K29) -> 7254701.1 | AF29: =AD29-AE29 -> -3059566.1 | AG29: =B29&"|"&C29 -> G_EchoGHubRamp_PimaTargets|FY2028
A30: =AG30 -> G_EchoGHubRamp_PimaTargets|FY2029 | B30: =Scenarios!A7 -> G_EchoGHubRamp_PimaTargets | C30: FY2029 | D30: =IF(Scenarios!D7=1,0, L30) -> 362 | E30: =IF(Scenarios!E7=1,0, M30) -> 341 | F30: =D30+E30 -> 703 | G30: =YearMap!B5 -> 6907.7273 | H30: =YearMap!C5 -> 1512280.6 | I30: =YearMap!D5 -> 1741770.6 | J30: =1-BaselineCalc!$B$5 -> 0.993 | K30: =Scenarios!G7 -> 0 | L30: =BaselineCalc!$B$7 + ROUND(Scenarios!L7*Scenarios!F7,0) -> 362 | M30: =BaselineCalc!$B$8 + Scenarios!L7 - ROUND(Scenarios!L7*Scenarios!F7,0) -> 341 | N30: =(L30-D30) + (M30-E30) -> 0 | O30: =(Parameters_Public!$C$22*(L30-D30)+Parameters_Public!$C$23*(M30-E30)) -> 0 | P30: =YearMap!E5 -> 500 | Q30: =IF(Scenarios!N7="lease", YearMap!F5, YearMap!G5) -> 0.3 | R30: =IF(Scenarios!D7=1, Q30*H30, H30) -> 1512280.6 | S30: =IF(Scenarios!E7=1, Q30*I30, I30) -> 1741770.6 | T30: =IF(C30="FY2026", (Scenarios!D7+Scenarios!E7)*BaselineCalc!$B$22, 0) -> 0 | U30: =(R30+S30+G30*F30)*J30*(1-K30) -> 8053412.2 | V30: =O30*(G30+P30) -> 0 | W30: =U30+V30+IF(Parameters_Public!$C$26=1, T30, 0) -> 8053412.2 | X30: =IF(F30+O30>0, W30/(F30+O30),"") -> 11455.778 | Y30: =INDEX(YearMap!$I$2:$I$6, MATCH(C30, YearMap!$A$2:$A$6, 0)) -> 5319.8357 | Z30: =W30 - ((Y30 + IF(Parameters_Public!$C$20=1, Parameters_Public!$C$19, 0))*AC30) -> 3784946.9 | AA30: =IF($AC30>0, $Z30/$AC30, 0) -> 5383.9927 | AB30: =MAX(0, (MAX(0, $D30-BaselineCalc!$B$7) + MAX(0, $E30-BaselineCalc!$B$8))) -> 150 | AC30: =IF(LEFT($B30,2)="A_", $O30, IF(LEFT($B30,2)="B_", $M30+$O30, IF(LEFT($B30,2)="C_", $L30+$O30, $F30))) -> 703 | AD30: =(Y30 + IF(Parameters_Public!$C$20=1, Parameters_Public!$C$19, 0))*AC30 -> 4268465.3 | AE30: =W30 - (1-Other_Parameters!$B$2)*$G30*$AB30*$J30*(1-$K30) -> 7436068.7 | AF30: =AD30-AE30 -> -3167603.3 | AG30: =B30&"|"&C30 -> G_EchoGHubRamp_PimaTargets|FY2029
A31: =AG31 -> G_EchoGHubRamp_PimaTargets|FY2030 | B31: =Scenarios!A7 -> G_EchoGHubRamp_PimaTargets | C31: FY2030 | D31: =IF(Scenarios!D7=1,0, L31) -> 362 | E31: =IF(Scenarios!E7=1,0, M31) -> 341 | F31: =D31+E31 -> 703 | G31: =YearMap!B6 -> 7080.4205 | H31: =YearMap!C6 -> 1550087.6 | I31: =YearMap!D6 -> 1785314.9 | J31: =1-BaselineCalc!$B$5 -> 0.993 | K31: =Scenarios!G7 -> 0 | L31: =BaselineCalc!$B$7 + ROUND(Scenarios!M7*Scenarios!F7,0) -> 362 | M31: =BaselineCalc!$B$8 + Scenarios!M7 - ROUND(Scenarios!M7*Scenarios!F7,0) -> 341 | N31: =(L31-D31) + (M31-E31) -> 0 | O31: =(Parameters_Public!$C$22*(L31-D31)+Parameters_Public!$C$23*(M31-E31)) -> 0 | P31: =YearMap!E6 -> 300 | Q31: =IF(Scenarios!N7="lease", YearMap!F6, YearMap!G6) -> 0.3 | R31: =IF(Scenarios!D7=1, Q31*H31, H31) -> 1550087.6 | S31: =IF(Scenarios!E7=1, Q31*I31, I31) -> 1785314.9 | T31: =IF(C31="FY2026", (Scenarios!D7+Scenarios!E7)*BaselineCalc!$B$22, 0) -> 0 | U31: =(R31+S31+G31*F31)*J31*(1-K31) -> 8254747.6 | V31: =O31*(G31+P31) -> 0 | W31: =U31+V31+IF(Parameters_Public!$C$26=1, T31, 0) -> 8254747.6 | X31: =IF(F31+O31>0, W31/(F31+O31),"") -> 11742.173 | Y31: =INDEX(YearMap!$I$2:$I$6, MATCH(C31, YearMap!$A$2:$A$6, 0)) -> 5426.2324 | Z31: =W31 - ((Y31 + IF(Parameters_Public!$C$20=1, Parameters_Public!$C$19, 0))*AC31) -> 3911485.3 | AA31: =IF($AC31>0, $Z31/$AC31, 0) -> 5563.9905 | AB31: =MAX(0, (MAX(0, $D31-BaselineCalc!$B$7) + MAX(0, $E31-BaselineCalc!$B$8))) -> 150 | AC31: =IF(LEFT($B31,2)="A_", $O31, IF(LEFT($B31,2)="B_", $M31+$O31, IF(LEFT($B31,2)="C_", $L31+$O31, $F31))) -> 703 | AD31: =(Y31 + IF(Parameters_Public!$C$20=1, Parameters_Public!$C$19, 0))*AC31 -> 4343262.2 | AE31: =W31 - (1-Other_Parameters!$B$2)*$G31*$AB31*$J31*(1-$K31) -> 7621970.4 | AF31: =AD31-AE31 -> -3278708.1 | AG31: =B31&"|"&C31 -> G_EchoGHubRamp_PimaTargets|FY2030
A32: =AG32 -> A_Repurpose_Both_lease|FY2026 | B32: =Scenarios!A8 -> A_Repurpose_Both_lease | C32: FY2026 | D32: =IF(Scenarios!D8=1,0, L32) -> 0 | E32: =IF(Scenarios!E8=1,0, M32) -> 0 | F32: =D32+E32 -> 0 | G32: =YearMap!B2 -> 6414.5115 | H32: =YearMap!C2 -> 1404302.9 | I32: =YearMap!D2 -> 1617407.2 | J32: =1-BaselineCalc!$B$5 -> 0.993 | K32: =Scenarios!G8 -> 0 | L32: =BaselineCalc!$B$7 + ROUND(Scenarios!I8*Scenarios!F8,0) -> 257 | M32: =BaselineCalc!$B$8 + Scenarios!I8 - ROUND(Scenarios!I8*Scenarios!F8,0) -> 296 | N32: =(L32-D32) + (M32-E32) -> 553 | O32: =(Parameters_Public!$C$22*(L32-D32)+Parameters_Public!$C$23*(M32-E32)) -> 405.8 | P32: =YearMap!E2 -> 1000 | Q32: =IF(Scenarios!N8="lease", YearMap!F2, YearMap!G2) -> 0.4 | R32: =IF(Scenarios!D8=1, Q32*H32, H32) -> 561721.15 | S32: =IF(Scenarios!E8=1, Q32*I32, I32) -> 646962.88 | T32: =IF(C32="FY2026", (Scenarios!D8+Scenarios!E8)*BaselineCalc!$B$22, 0) -> 2400000 | U32: =(R32+S32+G32*F32)*J32*(1-K32) -> 1200223.2 | V32: =O32*(G32+P32) -> 3008808.8 | W32: =U32+V32+IF(Parameters_Public!$C$26=1, T32, 0) -> 4209032 | X32: =IF(F32+O32>0, W32/(F32+O32),"") -> 10372.183 | Y32: =INDEX(YearMap!$I$2:$I$6, MATCH(C32, YearMap!$A$2:$A$6, 0)) -> 5013 | Z32: =W32 - ((Y32 + IF(Parameters_Public!$C$20=1, Parameters_Public!$C$19, 0))*AC32) -> 1869615.3 | AA32: =IF($AC32>0, $Z32/$AC32, 0) -> 4607.2334 | AB32: =MAX(0, (MAX(0, $D32-BaselineCalc!$B$7) + MAX(0, $E32-BaselineCalc!$B$8))) -> 0 | AC32: =IF(LEFT($B32,2)="A_", $O32, IF(LEFT($B32,2)="B_", $M32+$O32, IF(LEFT($B32,2)="C_", $L32+$O32, $F32))) -> 405.8 | AD32: =(Y32 + IF(Parameters_Public!$C$20=1, Parameters_Public!$C$19, 0))*AC32 -> 2339416.7 | AE32: =W32 - (1-Other_Parameters!$B$2)*$G32*$AB32*$J32*(1-$K32) -> 4209032 | AF32: =AD32-AE32 -> -1869615.3 | AG32: =B32&"|"&C32 -> A_Repurpose_Both_lease|FY2026
A33: =AG33 -> A_Repurpose_Both_lease|FY2027 | B33: =Scenarios!A8 -> A_Repurpose_Both_lease | C33: FY2027 | D33: =IF(Scenarios!D8=1,0, L33) -> 0 | E33: =IF(Scenarios!E8=1,0, M33) -> 0 | F33: =D33+E33 -> 0 | G33: =YearMap!B3 -> 6574.8743 | H33: =YearMap!C3 -> 1439410.4 | I33: =YearMap!D3 -> 1657842.4 | J33: =1-BaselineCalc!$B$5 -> 0.993 | K33: =Scenarios!G8 -> 0 | L33: =BaselineCalc!$B$7 + ROUND(Scenarios!J8*Scenarios!F8,0) -> 257 | M33: =BaselineCalc!$B$8 + Scenarios!J8 - ROUND(Scenarios!J8*Scenarios!F8,0) -> 296 | N33: =(L33-D33) + (M33-E33) -> 553 | O33: =(Parameters_Public!$C$22*(L33-D33)+Parameters_Public!$C$23*(M33-E33)) -> 405.8 | P33: =YearMap!E3 -> 800 | Q33: =IF(Scenarios!N8="lease", YearMap!F3, YearMap!G3) -> 0.3 | R33: =IF(Scenarios!D8=1, Q33*H33, H33) -> 431823.13 | S33: =IF(Scenarios!E8=1, Q33*I33, I33) -> 497352.71 | T33: =IF(C33="FY2026", (Scenarios!D8+Scenarios!E8)*BaselineCalc!$B$22, 0) -> 0 | U33: =(R33+S33+G33*F33)*J33*(1-K33) -> 922671.61 | V33: =O33*(G33+P33) -> 2992724 | W33: =U33+V33+IF(Parameters_Public!$C$26=1, T33, 0) -> 3915395.6 | X33: =IF(F33+O33>0, W33/(F33+O33),"") -> 9648.5845 | Y33: =INDEX(YearMap!$I$2:$I$6, MATCH(C33, YearMap!$A$2:$A$6, 0)) -> 5113.26 | Z33: =W33 - ((Y33 + IF(Parameters_Public!$C$20=1, Parameters_Public!$C$19, 0))*AC33) -> 1535293.4 | AA33: =IF($AC33>0, $Z33/$AC33, 0) -> 3783.3745 | AB33: =MAX(0, (MAX(0, $D33-BaselineCalc!$B$7) + MAX(0, $E33-BaselineCalc!$B$8))) -> 0 | AC33: =IF(LEFT($B33,2)="A_", $O33, IF(LEFT($B33,2)="B_", $M33+$O33, IF(LEFT($B33,2)="C_", $L33+$O33, $F33))) -> 405.8 | AD33: =(Y33 + IF(Parameters_Public!$C$20=1, Parameters_Public!$C$19, 0))*AC33 -> 2380102.2 | AE33: =W33 - (1-Other_Parameters!$B$2)*$G33*$AB33*$J33*(1-$K33) -> 3915395.6 | AF33: =AD33-AE33 -> -1535293.4 | AG33: =B33&"|"&C33 -> A_Repurpose_Both_lease|FY2027
A34: =AG34 -> A_Repurpose_Both_lease|FY2028 | B34: =Scenarios!A8 -> A_Repurpose_Both_lease | C34: FY2028 | D34: =IF(Scenarios!D8=1,0, L34) -> 0 | E34: =IF(Scenarios!E8=1,0, M34) -> 0 | F34: =D34+E34 -> 0 | G34: =YearMap!B4 -> 6739.2461 | H34: =YearMap!C4 -> 1475395.7 | I34: =YearMap!D4 -> 1699288.4 | J34: =1-BaselineCalc!$B$5 -> 0.993 | K34: =Scenarios!G8 -> 0 | L34: =BaselineCalc!$B$7 + ROUND(Scenarios!K8*Scenarios!F8,0) -> 257 | M34: =BaselineCalc!$B$8 + Scenarios!K8 - ROUND(Scenarios!K8*Scenarios!F8,0) -> 296 | N34: =(L34-D34) + (M34-E34) -> 553 | O34: =(Parameters_Public!$C$22*(L34-D34)+Parameters_Public!$C$23*(M34-E34)) -> 405.8 | P34: =YearMap!E4 -> 600 | Q34: =IF(Scenarios!N8="lease", YearMap!F4, YearMap!G4) -> 0.2 | R34: =IF(Scenarios!D8=1, Q34*H34, H34) -> 295079.14 | S34: =IF(Scenarios!E8=1, Q34*I34, I34) -> 339857.69 | T34: =IF(C34="FY2026", (Scenarios!D8+Scenarios!E8)*BaselineCalc!$B$22, 0) -> 0 | U34: =(R34+S34+G34*F34)*J34*(1-K34) -> 630492.27 | V34: =O34*(G34+P34) -> 2978266.1 | W34: =U34+V34+IF(Parameters_Public!$C$26=1, T34, 0) -> 3608758.4 | X34: =IF(F34+O34>0, W34/(F34+O34),"") -> 8892.9481 | Y34: =INDEX(YearMap!$I$2:$I$6, MATCH(C34, YearMap!$A$2:$A$6, 0)) -> 5215.5252 | Z34: =W34 - ((Y34 + IF(Parameters_Public!$C$20=1, Parameters_Public!$C$19, 0))*AC34) -> 1187156.9 | AA34: =IF($AC34>0, $Z34/$AC34, 0) -> 2925.4729 | AB34: =MAX(0, (MAX(0, $D34-BaselineCalc!$B$7) + MAX(0, $E34-BaselineCalc!$B$8))) -> 0 | AC34: =IF(LEFT($B34,2)="A_", $O34, IF(LEFT($B34,2)="B_", $M34+$O34, IF(LEFT($B34,2)="C_", $L34+$O34, $F34))) -> 405.8 | AD34: =(Y34 + IF(Parameters_Public!$C$20=1, Parameters_Public!$C$19, 0))*AC34 -> 2421601.4 | AE34: =W34 - (1-Other_Parameters!$B$2)*$G34*$AB34*$J34*(1-$K34) -> 3608758.4 | AF34: =AD34-AE34 -> -1187156.9 | AG34: =B34&"|"&C34 -> A_Repurpose_Both_lease|FY2028
A35: =AG35 -> A_Repurpose_Both_lease|FY2029 | B35: =Scenarios!A8 -> A_Repurpose_Both_lease | C35: FY2029 | D35: =IF(Scenarios!D8=1,0, L35) -> 0 | E35: =IF(Scenarios!E8=1,0, M35) -> 0 | F35: =D35+E35 -> 0 | G35: =YearMap!B5 -> 6907.7273 | H35: =YearMap!C5 -> 1512280.6 | I35: =YearMap!D5 -> 1741770.6 | J35: =1-BaselineCalc!$B$5 -> 0.993 | K35: =Scenarios!G8 -> 0 | L35: =BaselineCalc!$B$7 + ROUND(Scenarios!L8*Scenarios!F8,0) -> 257 | M35: =BaselineCalc!$B$8 + Scenarios!L8 - ROUND(Scenarios!L8*Scenarios!F8,0) -> 296 | N35: =(L35-D35) + (M35-E35) -> 553 | O35: =(Parameters_Public!$C$22*(L35-D35)+Parameters_Public!$C$23*(M35-E35)) -> 405.8 | P35: =YearMap!E5 -> 500 | Q35: =IF(Scenarios!N8="lease", YearMap!F5, YearMap!G5) -> 0.1 | R35: =IF(Scenarios!D8=1, Q35*H35, H35) -> 151228.06 | S35: =IF(Scenarios!E8=1, Q35*I35, I35) -> 174177.06 | T35: =IF(C35="FY2026", (Scenarios!D8+Scenarios!E8)*BaselineCalc!$B$22, 0) -> 0 | U35: =(R35+S35+G35*F35)*J35*(1-K35) -> 323127.29 | V35: =O35*(G35+P35) -> 3006055.7 | W35: =U35+V35+IF(Parameters_Public!$C$26=1, T35, 0) -> 3329183 | X35: =IF(F35+O35>0, W35/(F35+O35),"") -> 8203.9996 | Y35: =INDEX(YearMap!$I$2:$I$6, MATCH(C35, YearMap!$A$2:$A$6, 0)) -> 5319.8357 | Z35: =W35 - ((Y35 + IF(Parameters_Public!$C$20=1, Parameters_Public!$C$19, 0))*AC35) -> 865252.39 | AA35: =IF($AC35>0, $Z35/$AC35, 0) -> 2132.2139 | AB35: =MAX(0, (MAX(0, $D35-BaselineCalc!$B$7) + MAX(0, $E35-BaselineCalc!$B$8))) -> 0 | AC35: =IF(LEFT($B35,2)="A_", $O35, IF(LEFT($B35,2)="B_", $M35+$O35, IF(LEFT($B35,2)="C_", $L35+$O35, $F35))) -> 405.8 | AD35: =(Y35 + IF(Parameters_Public!$C$20=1, Parameters_Public!$C$19, 0))*AC35 -> 2463930.6 | AE35: =W35 - (1-Other_Parameters!$B$2)*$G35*$AB35*$J35*(1-$K35) -> 3329183 | AF35: =AD35-AE35 -> -865252.39 | AG35: =B35&"|"&C35 -> A_Repurpose_Both_lease|FY2029
A36: =AG36 -> A_Repurpose_Both_lease|FY2030 | B36: =Scenarios!A8 -> A_Repurpose_Both_lease | C36: FY2030 | D36: =IF(Scenarios!D8=1,0, L36) -> 0 | E36: =IF(Scenarios!E8=1,0, M36) -> 0 | F36: =D36+E36 -> 0 | G36: =YearMap!B6 -> 7080.4205 | H36: =YearMap!C6 -> 1550087.6 | I36: =YearMap!D6 -> 1785314.9 | J36: =1-BaselineCalc!$B$5 -> 0.993 | K36: =Scenarios!G8 -> 0 | L36: =BaselineCalc!$B$7 + ROUND(Scenarios!M8*Scenarios!F8,0) -> 257 | M36: =BaselineCalc!$B$8 + Scenarios!M8 - ROUND(Scenarios!M8*Scenarios!F8,0) -> 296 | N36: =(L36-D36) + (M36-E36) -> 553 | O36: =(Parameters_Public!$C$22*(L36-D36)+Parameters_Public!$C$23*(M36-E36)) -> 405.8 | P36: =YearMap!E6 -> 300 | Q36: =IF(Scenarios!N8="lease", YearMap!F6, YearMap!G6) -> 0.1 | R36: =IF(Scenarios!D8=1, Q36*H36, H36) -> 155008.76 | S36: =IF(Scenarios!E8=1, Q36*I36, I36) -> 178531.49 | T36: =IF(C36="FY2026", (Scenarios!D8+Scenarios!E8)*BaselineCalc!$B$22, 0) -> 0 | U36: =(R36+S36+G36*F36)*J36*(1-K36) -> 331205.47 | V36: =O36*(G36+P36) -> 2994974.6 | W36: =U36+V36+IF(Parameters_Public!$C$26=1, T36, 0) -> 3326180.1 | X36: =IF(F36+O36>0, W36/(F36+O36),"") -> 8196.5996 | Y36: =INDEX(YearMap!$I$2:$I$6, MATCH(C36, YearMap!$A$2:$A$6, 0)) -> 5426.2324 | Z36: =W36 - ((Y36 + IF(Parameters_Public!$C$20=1, Parameters_Public!$C$19, 0))*AC36) -> 819073.68 | AA36: =IF($AC36>0, $Z36/$AC36, 0) -> 2018.4171 | AB36: =MAX(0, (MAX(0, $D36-BaselineCalc!$B$7) + MAX(0, $E36-BaselineCalc!$B$8))) -> 0 | AC36: =IF(LEFT($B36,2)="A_", $O36, IF(LEFT($B36,2)="B_", $M36+$O36, IF(LEFT($B36,2)="C_", $L36+$O36, $F36))) -> 405.8 | AD36: =(Y36 + IF(Parameters_Public!$C$20=1, Parameters_Public!$C$19, 0))*AC36 -> 2507106.4 | AE36: =W36 - (1-Other_Parameters!$B$2)*$G36*$AB36*$J36*(1-$K36) -> 3326180.1 | AF36: =AD36-AE36 -> -819073.68 | AG36: =B36&"|"&C36 -> A_Repurpose_Both_lease|FY2030
A37: =AG37 -> A_Repurpose_Both_ops|FY2026 | B37: =Scenarios!A9 -> A_Repurpose_Both_ops | C37: FY2026 | D37: =IF(Scenarios!D9=1,0, L37) -> 0 | E37: =IF(Scenarios!E9=1,0, M37) -> 0 | F37: =D37+E37 -> 0 | G37: =YearMap!B2 -> 6414.5115 | H37: =YearMap!C2 -> 1404302.9 | I37: =YearMap!D2 -> 1617407.2 | J37: =1-BaselineCalc!$B$5 -> 0.993 | K37: =Scenarios!G9 -> 0 | L37: =BaselineCalc!$B$7 + ROUND(Scenarios!I9*Scenarios!F9,0) -> 257 | M37: =BaselineCalc!$B$8 + Scenarios!I9 - ROUND(Scenarios!I9*Scenarios!F9,0) -> 296 | N37: =(L37-D37) + (M37-E37) -> 553 | O37: =(Parameters_Public!$C$22*(L37-D37)+Parameters_Public!$C$23*(M37-E37)) -> 405.8 | P37: =YearMap!E2 -> 1000 | Q37: =IF(Scenarios!N9="lease", YearMap!F2, YearMap!G2) -> 0.5 | R37: =IF(Scenarios!D9=1, Q37*H37, H37) -> 702151.43 | S37: =IF(Scenarios!E9=1, Q37*I37, I37) -> 808703.6 | T37: =IF(C37="FY2026", (Scenarios!D9+Scenarios!E9)*BaselineCalc!$B$22, 0) -> 2400000 | U37: =(R37+S37+G37*F37)*J37*(1-K37) -> 1500279 | V37: =O37*(G37+P37) -> 3008808.8 | W37: =U37+V37+IF(Parameters_Public!$C$26=1, T37, 0) -> 4509087.8 | X37: =IF(F37+O37>0, W37/(F37+O37),"") -> 11111.601 | Y37: =INDEX(YearMap!$I$2:$I$6, MATCH(C37, YearMap!$A$2:$A$6, 0)) -> 5013 | Z37: =W37 - ((Y37 + IF(Parameters_Public!$C$20=1, Parameters_Public!$C$19, 0))*AC37) -> 2169671.1 | AA37: =IF($AC37>0, $Z37/$AC37, 0) -> 5346.6513 | AB37: =MAX(0, (MAX(0, $D37-BaselineCalc!$B$7) + MAX(0, $E37-BaselineCalc!$B$8))) -> 0 | AC37: =IF(LEFT($B37,2)="A_", $O37, IF(LEFT($B37,2)="B_", $M37+$O37, IF(LEFT($B37,2)="C_", $L37+$O37, $F37))) -> 405.8 | AD37: =(Y37 + IF(Parameters_Public!$C$20=1, Parameters_Public!$C$19, 0))*AC37 -> 2339416.7 | AE37: =W37 - (1-Other_Parameters!$B$2)*$G37*$AB37*$J37*(1-$K37) -> 4509087.8 | AF37: =AD37-AE37 -> -2169671.1 | AG37: =B37&"|"&C37 -> A_Repurpose_Both_ops|FY2026
A38: =AG38 -> A_Repurpose_Both_ops|FY2027 | B38: =Scenarios!A9 -> A_Repurpose_Both_ops | C38: FY2027 | D38: =IF(Scenarios!D9=1,0, L38) -> 0 | E38: =IF(Scenarios!E9=1,0, M38) -> 0 | F38: =D38+E38 -> 0 | G38: =YearMap!B3 -> 6574.8743 | H38: =YearMap!C3 -> 1439410.4 | I38: =YearMap!D3 -> 1657842.4 | J38: =1-BaselineCalc!$B$5 -> 0.993 | K38: =Scenarios!G9 -> 0 | L38: =BaselineCalc!$B$7 + ROUND(Scenarios!J9*Scenarios!F9,0) -> 257 | M38: =BaselineCalc!$B$8 + Scenarios!J9 - ROUND(Scenarios!J9*Scenarios!F9,0) -> 296 | N38: =(L38-D38) + (M38-E38) -> 553 | O38: =(Parameters_Public!$C$22*(L38-D38)+Parameters_Public!$C$23*(M38-E38)) -> 405.8 | P38: =YearMap!E3 -> 800 | Q38: =IF(Scenarios!N9="lease", YearMap!F3, YearMap!G3) -> 0.4 | R38: =IF(Scenarios!D9=1, Q38*H38, H38) -> 575764.18 | S38: =IF(Scenarios!E9=1, Q38*I38, I38) -> 663136.95 | T38: =IF(C38="FY2026", (Scenarios!D9+Scenarios!E9)*BaselineCalc!$B$22, 0) -> 0 | U38: =(R38+S38+G38*F38)*J38*(1-K38) -> 1230228.8 | V38: =O38*(G38+P38) -> 2992724 | W38: =U38+V38+IF(Parameters_Public!$C$26=1, T38, 0) -> 4222952.8 | X38: =IF(F38+O38>0, W38/(F38+O38),"") -> 10406.488 | Y38: =INDEX(YearMap!$I$2:$I$6, MATCH(C38, YearMap!$A$2:$A$6, 0)) -> 5113.26 | Z38: =W38 - ((Y38 + IF(Parameters_Public!$C$20=1, Parameters_Public!$C$19, 0))*AC38) -> 1842850.6 | AA38: =IF($AC38>0, $Z38/$AC38, 0) -> 4541.2779 | AB38: =MAX(0, (MAX(0, $D38-BaselineCalc!$B$7) + MAX(0, $E38-BaselineCalc!$B$8))) -> 0 | AC38: =IF(LEFT($B38,2)="A_", $O38, IF(LEFT($B38,2)="B_", $M38+$O38, IF(LEFT($B38,2)="C_", $L38+$O38, $F38))) -> 405.8 | AD38: =(Y38 + IF(Parameters_Public!$C$20=1, Parameters_Public!$C$19, 0))*AC38 -> 2380102.2 | AE38: =W38 - (1-Other_Parameters!$B$2)*$G38*$AB38*$J38*(1-$K38) -> 4222952.8 | AF38: =AD38-AE38 -> -1842850.6 | AG38: =B38&"|"&C38 -> A_Repurpose_Both_ops|FY2027
