Workbook

Sheet BaselineCalc
A1: Parameter | B1: Value | C1: Notes
A2: MO inflation | B2: 0.025 | C2: Annual inflation factor.
A3: Base MO per ADM (FY25) | B3: 9936 | C3: Working base for FY25.
A4: Fixed share of MO | B4: 0.3 | C4: Share treated as semi‑fixed (plant/insurance).
A5: Ops savings (keep‑open) | B5: 0.007 | C5: Light discipline if sites remain open (not used here).
A6: Extra savings (Co‑location) | B6: 0.015 | C6: Incremental savings for co‑location (not used here).
A7: Echo base ADM | B7: 257
A8: Pima base ADM | B8: 296
A9: Total base ADM | B9: =B7+B8 -> 553 | C9: Echo base ADM + Pima base ADM
A12: Helper / Derivation | B12: FY26 | C12: FY27 | D12: FY28 | E12: FY29 | F12: FY30 | G12: Notes
A13: Base total MO (FY25) | B13: =B9*B3 -> 5494608 | C13: =C14/$B$4 -> 5631973.2 | D13: =D14/$B$4 -> 5772772.5 | E13: =E14/$B$4 -> 5917091.8 | F13: =F14/$B$4 -> 6065019.1 | G13: Total ADM × Base MO/ADM | K13: B13 = B9*B3 (Base total MO, FY25)
A14: Fixed MO (FY25) | B14: =B13*B4 -> 1648382.4 | C14: =B17 -> 1689592 | D14: =C17 -> 1731831.8 | E14: =D17 -> 1775127.6 | F14: =E17 -> 1819505.7 | G14: Fixed = Base total × Fixed share | K14: B14 = B13*B4 (Fixed MO, FY25)
A15: Var per student (FY25) | B15: =(B13-B14)/B9 -> 6955.2 | C15: =B18 -> 7129.08 | D15: =C18 -> 7307.307 | E15: =D18 -> 7489.9897 | F15: =E18 -> 7677.2394 | G15: Variable = (Base total − Fixed)/Total ADM | K15: B15 = (B13–B14)/B9 (Variable $/student, FY25)
A17: Fixed total ($) | B17: =$B$14*(1+$B$2)^1 -> 1689592 | C17: =$B$14*(1+$B$2)^2 -> 1731831.8 | D17: =$B$14*(1+$B$2)^3 -> 1775127.6 | E17: =$B$14*(1+$B$2)^4 -> 1819505.7 | F17: =$B$14*(1+$B$2)^5 -> 1864993.4
A18: Var unit ($/student) | B18: =$B$15*(1+$B$2)^1 -> 7129.08 | C18: =$B$15*(1+$B$2)^2 -> 7307.307 | D18: =$B$15*(1+$B$2)^3 -> 7489.9897 | E18: =$B$15*(1+$B$2)^4 -> 7677.2394 | F18: =$B$15*(1+$B$2)^5 -> 7869.1704
A19: Echo fixed ($) | B19: =B17*($B$7/$B$9) -> 785217.24 | C19: =C17*($B$7/$B$9) -> 804847.67 | D19: =D17*($B$7/$B$9) -> 824968.86 | E19: =E17*($B$7/$B$9) -> 845593.08 | F19: =F17*($B$7/$B$9) -> 866732.91
A20: Pima fixed ($) | B20: =B17*($B$8/$B$9) -> 904374.72 | C20: =C17*($B$8/$B$9) -> 926984.09 | D20: =D17*($B$8/$B$9) -> 950158.69 | E20: =E17*($B$8/$B$9) -> 973912.66 | F20: =F17*($B$8/$B$9) -> 998260.47
A22: Notes
A23: All formulas are same‑sheet and reference the Parameter cells above.

Sheet YearMap
A1: Year | B1: VarUnit$ | C1: EchoFixed$ | D1: PimaFixed$ | E1: h | F1: f_lease | G1: f_ops
A2: FY2026 | B2: =BaselineCalc!B18 -> 7129.08 | C2: =BaselineCalc!B19 -> 785217.24 | D2: =BaselineCalc!B20 -> 904374.72 | E2: 1000 | F2: 0.4 | G2: 0.4
A3: FY2027 | B3: =BaselineCalc!C18 -> 7307.307 | C3: =BaselineCalc!C19 -> 804847.67 | D3: =BaselineCalc!C20 -> 926984.09 | E3: 800 | F3: 0.3 | G3: 0.35
A4: FY2028 | B4: =BaselineCalc!D18 -> 7489.9897 | C4: =BaselineCalc!D19 -> 824968.86 | D4: =BaselineCalc!D20 -> 950158.69 | E4: 600 | F4: 0.2 | G4: 0.3
A5: FY2029 | B5: =BaselineCalc!E18 -> 7677.2394 | C5: =BaselineCalc!E19 -> 845593.08 | D5: =BaselineCalc!E20 -> 973912.66 | E5: 400 | F5: 0.1 | G5: 0.25
A6: FY2030 | B6: =BaselineCalc!F18 -> 7869.1704 | C6: =BaselineCalc!F19 -> 866732.91 | D6: =BaselineCalc!F20 -> 998260.47 | E6: 300 | F6: 0 | G6: 0.2

Sheet Scenarios
A1: ScenarioKey | B1: Label | C1: Overlay | D1: CloseEcho | E1: ClosePima | F1: EchoShareDist | G1: ExtraSave | H1: Notes
A2: D_Grow_Both_0 | B2: D. Grow Both (Overlay 0) | C2: 0 | D2: 0 | E2: 0 | F2: 0.5 | G2: 0 | H2: Baseline + outreach; no closures
A3: E_StatusQuo_Targets_0 | B3: E. Status‑Quo + Targets (0) | C3: 0 | D3: 0 | E3: 0 | F3: 0.5 | G3: 0 | H3: Baseline + targets; no closures
A4: F_CoLocation_Echo_0 | B4: F. Co‑Location @ Echo (0) | C4: 0 | D4: 0 | E4: 0 | F4: 0.7 | G4: 0.0015 | H4: Shared‑use efficiencies later (no closure)
A6: ScenarioKey | B6: Year | C6: Echo_ADM | D6: Pima_ADM | E6: Total_ADM | F6: VarUnit$ | G6: EchoFixed$ | H6: PimaFixed$ | I6: Key
A7: =A2 -> D_Grow_Both_0 | B7: FY2026 | C7: =IF(D2=1,0, BaselineCalc!$B$7 + ROUND(C2*F2,0)) -> 257 | D7: =IF(E2=1,0, BaselineCalc!$B$8 + C2 - ROUND(C2*F2,0)) -> 296 | E7: =C7+D7 -> 553 | F7: =VLOOKUP(B7,YearMap!$A$2:$B$6,2,FALSE) -> 7129.08 | G7: =VLOOKUP(B7,YearMap!$A$2:$C$6,3,FALSE) -> 785217.24 | H7: =VLOOKUP(B7,YearMap!$A$2:$D$6,4,FALSE) -> 904374.72 | I7: =A7&"|"&B7 -> D_Grow_Both_0|FY2026
A8: =A2 -> D_Grow_Both_0 | B8: FY2027 | C8: =IF(D2=1,0, BaselineCalc!$B$7 + ROUND(C2*F2,0)) -> 257 | D8: =IF(E2=1,0, BaselineCalc!$B$8 + C2 - ROUND(C2*F2,0)) -> 296 | E8: =C8+D8 -> 553 | F8: =VLOOKUP(B8,YearMap!$A$2:$B$6,2,FALSE) -> 7307.307 | G8: =VLOOKUP(B8,YearMap!$A$2:$C$6,3,FALSE) -> 804847.67 | H8: =VLOOKUP(B8,YearMap!$A$2:$D$6,4,FALSE) -> 926984.09 | I8: =A8&"|"&B8 -> D_Grow_Both_0|FY2027
A9: =A2 -> D_Grow_Both_0 | B9: FY2028 | C9: =IF(D2=1,0, BaselineCalc!$B$7 + ROUND(C2*F2,0)) -> 257 | D9: =IF(E2=1,0, BaselineCalc!$B$8 + C2 - ROUND(C2*F2,0)) -> 296 | E9: =C9+D9 -> 553 | F9: =VLOOKUP(B9,YearMap!$A$2:$B$6,2,FALSE) -> 7489.9897 | G9: =VLOOKUP(B9,YearMap!$A$2:$C$6,3,FALSE) -> 824968.86 | H9: =VLOOKUP(B9,YearMap!$A$2:$D$6,4,FALSE) -> 950158.69 | I9: =A9&"|"&B9 -> D_Grow_Both_0|FY2028
A10: =A2 -> D_Grow_Both_0 | B10: FY2029 | C10: =IF(D2=1,0, BaselineCalc!$B$7 + ROUND(C2*F2,0)) -> 257 | D10: =IF(E2=1,0, BaselineCalc!$B$8 + C2 - ROUND(C2*F2,0)) -> 296 | E10: =C10+D10 -> 553 | F10: =VLOOKUP(B10,YearMap!$A$2:$B$6,2,FALSE) -> 7677.2394 | G10: =VLOOKUP(B10,YearMap!$A$2:$C$6,3,FALSE) -> 845593.08 | H10: =VLOOKUP(B10,YearMap!$A$2:$D$6,4,FALSE) -> 973912.66 | I10: =A10&"|"&B10 -> D_Grow_Both_0|FY2029
A11: =A2 -> D_Grow_Both_0 | B11: FY2030 | C11: =IF(D2=1,0, BaselineCalc!$B$7 + ROUND(C2*F2,0)) -> 257 | D11: =IF(E2=1,0, BaselineCalc!$B$8 + C2 - ROUND(C2*F2,0)) -> 296 | E11: =C11+D11 -> 553 | F11: =VLOOKUP(B11,YearMap!$A$2:$B$6,2,FALSE) -> 7869.1704 | G11: =VLOOKUP(B11,YearMap!$A$2:$C$6,3,FALSE) -> 866732.91 | H11: =VLOOKUP(B11,YearMap!$A$2:$D$6,4,FALSE) -> 998260.47 | I11: =A11&"|"&B11 -> D_Grow_Both_0|FY2030
A12: =A3 -> E_StatusQuo_Targets_0 | B12: FY2026 | C12: =IF(D3=1,0, BaselineCalc!$B$7 + ROUND(C3*F3,0)) -> 257 | D12: =IF(E3=1,0, BaselineCalc!$B$8 + C3 - ROUND(C3*F3,0)) -> 296 | E12: =C12+D12 -> 553 | F12: =VLOOKUP(B12,YearMap!$A$2:$B$6,2,FALSE) -> 7129.08 | G12: =VLOOKUP(B12,YearMap!$A$2:$C$6,3,FALSE) -> 785217.24 | H12: =VLOOKUP(B12,YearMap!$A$2:$D$6,4,FALSE) -> 904374.72 | I12: =A12&"|"&B12 -> E_StatusQuo_Targets_0|FY2026
A13: =A3 -> E_StatusQuo_Targets_0 | B13: FY2027 | C13: =IF(D3=1,0, BaselineCalc!$B$7 + ROUND(C3*F3,0)) -> 257 | D13: =IF(E3=1,0, BaselineCalc!$B$8 + C3 - ROUND(C3*F3,0)) -> 296 | E13: =C13+D13 -> 553 | F13: =VLOOKUP(B13,YearMap!$A$2:$B$6,2,FALSE) -> 7307.307 | G13: =VLOOKUP(B13,YearMap!$A$2:$C$6,3,FALSE) -> 804847.67 | H13: =VLOOKUP(B13,YearMap!$A$2:$D$6,4,FALSE) -> 926984.09 | I13: =A13&"|"&B13 -> E_StatusQuo_Targets_0|FY2027
A14: =A3 -> E_StatusQuo_Targets_0 | B14: FY2028 | C14: =IF(D3=1,0, BaselineCalc!$B$7 + ROUND(C3*F3,0)) -> 257 | D14: =IF(E3=1,0, BaselineCalc!$B$8 + C3 - ROUND(C3*F3,0)) -> 296 | E14: =C14+D14 -> 553 | F14: =VLOOKUP(B14,YearMap!$A$2:$B$6,2,FALSE) -> 7489.9897 | G14: =VLOOKUP(B14,YearMap!$A$2:$C$6,3,FALSE) -> 824968.86 | H14: =VLOOKUP(B14,YearMap!$A$2:$D$6,4,FALSE) -> 950158.69 | I14: =A14&"|"&B14 -> E_StatusQuo_Targets_0|FY2028
A15: =A3 -> E_StatusQuo_Targets_0 | B15: FY2029 | C15: =IF(D3=1,0, BaselineCalc!$B$7 + ROUND(C3*F3,0)) -> 257 | D15: =IF(E3=1,0, BaselineCalc!$B$8 + C3 - ROUND(C3*F3,0)) -> 296 | E15: =C15+D15 -> 553 | F15: =VLOOKUP(B15,YearMap!$A$2:$B$6,2,FALSE) -> 7677.2394 | G15: =VLOOKUP(B15,YearMap!$A$2:$C$6,3,FALSE) -> 845593.08 | H15: =VLOOKUP(B15,YearMap!$A$2:$D$6,4,FALSE) -> 973912.66 | I15: =A15&"|"&B15 -> E_StatusQuo_Targets_0|FY2029
A16: =A3 -> E_StatusQuo_Targets_0 | B16: FY2030 | C16: =IF(D3=1,0, BaselineCalc!$B$7 + ROUND(C3*F3,0)) -> 257 | D16: =IF(E3=1,0, BaselineCalc!$B$8 + C3 - ROUND(C3*F3,0)) -> 296 | E16: =C16+D16 -> 553 | F16: =VLOOKUP(B16,YearMap!$A$2:$B$6,2,FALSE) -> 7869.1704 | G16: =VLOOKUP(B16,YearMap!$A$2:$C$6,3,FALSE) -> 866732.91 | H16: =VLOOKUP(B16,YearMap!$A$2:$D$6,4,FALSE) -> 998260.47 | I16: =A16&"|"&B16 -> E_StatusQuo_Targets_0|FY2030
A17: =A4 -> F_CoLocation_Echo_0 | B17: FY2026 | C17: =IF(D4=1,0, BaselineCalc!$B$7 + ROUND(C4*F4,0)) -> 257 | D17: =IF(E4=1,0, BaselineCalc!$B$8 + C4 - ROUND(C4*F4,0)) -> 296 | E17: =C17+D17 -> 553 | F17: =VLOOKUP(B17,YearMap!$A$2:$B$6,2,FALSE) -> 7129.08 | G17: =VLOOKUP(B17,YearMap!$A$2:$C$6,3,FALSE) -> 785217.24 | H17: =VLOOKUP(B17,YearMap!$A$2:$D$6,4,FALSE) -> 904374.72 | I17: =A17&"|"&B17 -> F_CoLocation_Echo_0|FY2026
A18: =A4 -> F_CoLocation_Echo_0 | B18: FY2027 | C18: =IF(D4=1,0, BaselineCalc!$B$7 + ROUND(C4*F4,0)) -> 257 | D18: =IF(E4=1,0, BaselineCalc!$B$8 + C4 - ROUND(C4*F4,0)) -> 296 | E18: =C18+D18 -> 553 | F18: =VLOOKUP(B18,YearMap!$A$2:$B$6,2,FALSE) -> 7307.307 | G18: =VLOOKUP(B18,YearMap!$A$2:$C$6,3,FALSE) -> 804847.67 | H18: =VLOOKUP(B18,YearMap!$A$2:$D$6,4,FALSE) -> 926984.09 | I18: =A18&"|"&B18 -> F_CoLocation_Echo_0|FY2027
A19: =A4 -> F_CoLocation_Echo_0 | B19: FY2028 | C19: =IF(D4=1,0, BaselineCalc!$B$7 + ROUND(C4*F4,0)) -> 257 | D19: =IF(E4=1,0, BaselineCalc!$B$8 + C4 - ROUND(C4*F4,0)) -> 296 | E19: =C19+D19 -> 553 | F19: =VLOOKUP(B19,YearMap!$A$2:$B$6,2,FALSE) -> 7489.9897 | G19: =VLOOKUP(B19,YearMap!$A$2:$C$6,3,FALSE) -> 824968.86 | H19: =VLOOKUP(B19,YearMap!$A$2:$D$6,4,FALSE) -> 950158.69 | I19: =A19&"|"&B19 -> F_CoLocation_Echo_0|FY2028
A20: =A4 -> F_CoLocation_Echo_0 | B20: FY2029 | C20: =IF(D4=1,0, BaselineCalc!$B$7 + ROUND(C4*F4,0)) -> 257 | D20: =IF(E4=1,0, BaselineCalc!$B$8 + C4 - ROUND(C4*F4,0)) -> 296 | E20: =C20+D20 -> 553 | F20: =VLOOKUP(B20,YearMap!$A$2:$B$6,2,FALSE) -> 7677.2394 | G20: =VLOOKUP(B20,YearMap!$A$2:$C$6,3,FALSE) -> 845593.08 | H20: =VLOOKUP(B20,YearMap!$A$2:$D$6,4,FALSE) -> 973912.66 | I20: =A20&"|"&B20 -> F_CoLocation_Echo_0|FY2029
A21: =A4 -> F_CoLocation_Echo_0 | B21: FY2030 | C21: =IF(D4=1,0, BaselineCalc!$B$7 + ROUND(C4*F4,0)) -> 257 | D21: =IF(E4=1,0, BaselineCalc!$B$8 + C4 - ROUND(C4*F4,0)) -> 296 | E21: =C21+D21 -> 553 | F21: =VLOOKUP(B21,YearMap!$A$2:$B$6,2,FALSE) -> 7869.1704 | G21: =VLOOKUP(B21,YearMap!$A$2:$C$6,3,FALSE) -> 866732.91 | H21: =VLOOKUP(B21,YearMap!$A$2:$D$6,4,FALSE) -> 998260.47 | I21: =A21&"|"&B21 -> F_CoLocation_Echo_0|FY2030

Sheet Notes
A1: FAQs
B2: Why “Fixed share of M&O = 0.30”?
B3: District M&O typically has a sizable semi‑fixed component (plant ops/custodial/insurance/admin overhead). Without site‑level detail yet, 30% is a conservative placeholder in the middle of the 25–40% range many K‑12 systems sit in. We will replace it with SUSD plant ops + insurance shares when available.
B5: Why “Ops savings (keep‑open) = 0.007 (0.7%)”?
B6: This represents “light discipline” (utilities/purchasing tweaks, route smoothing) that does not depend on closing a site. I set it very low on purpose so it doesn’t drive results. We’ll calibrate with SUSD data (e.g., last year’s utility audits) if provided.
B8: Why “Extra savings (co‑location) = 0.015 (1.5%)”?
B9: This reflects incremental savings from consolidating some services on one campus (custodial/grounds/partial routing). Again kept small and conservative; we’ll swap in real custodial (sq‑ft), grounds and route deltas when we get them.
B11: Why “Repurpose TI per closed site (FY26) = $1.2M”? What is “one‑time carry/TI”?
B12: “TI” = tenant improvements / transition investments needed to convert a K‑8 to a different use (early learning, admin consolidation) and carry costs in year one (e.g., abatement, doors/security, low‑voltage re‑work, furniture, swing space). A light‑touch repurpose can easily run $10–$20/sq‑ft; Echo’s plant is ~77k sq ft, so $1.2M is a reasonable placeholder (we are not assuming a gut remodel). We’ll replace this with SUSD’s scope/estimate if they have one.
A17: Definitions
B18: MO inflation
B19: Base MO per ADM (FY25)
B20: Fixed share of MO
B21: Ops savings (keep‑open)
B22: Extra savings (Co‑location)
B23: Echo base ADM
B24: Pima base ADM
B25: Total base ADM
