Workbook

Sheet Parameters
A1: Parameter | B1: Value | C1: Notes
A2: MO inflation | B2: 0.025 | C2: Annual inflation applied to M&O components
A3: Base MO per ADM (FY25) | B3: 9936 | C3: Auditor General/ACFR context; working base
A4: Fixed share of MO | B4: 0.3 | C4: Share of M&O treated as fixed plant/insurance
A5: Ops savings (keep-open) | B5: 0.007 | C5: Light ops discipline applied to keep-open scenarios
A6: Extra savings (Co-location) | B6: 0.015 | C6: Additional savings for F (co-location)
A7: Echo base ADM | B7: 257
A8: Pima base ADM | B8: 296
A9: Total base ADM | B9: 553 | C9: =B6+B7 -> 257.015
A10: Repurpose TI per closed site (FY26) | B10: 1200000 | C10: One-time tenant improvement/carry add in FY26
A13: Receiving overhead taper (h $/retained student) | B13: FY2026 | C13: FY2027 | D13: FY2028 | E13: FY2029 | F13: FY2030
A14: h | B14: 1000 | C14: 800 | D14: 600 | E14: 400 | F14: 300
A16: Fixed-carry path - Lease/Sale (f) | B16: FY2026 | C16: FY2027 | D16: FY2028 | E16: FY2029 | F16: FY2030
A17: f_lease | B17: 0.4 | C17: 0.3 | D17: 0.2 | E17: 0.1 | F17: 0
A19: Fixed-carry path - Ops Repurpose (f) | B19: FY2026 | C19: FY2027 | D19: FY2028 | E19: FY2029 | F19: FY2030
A20: f_ops | B20: 0.4 | C20: 0.35 | D20: 0.3 | E20: 0.25 | F20: 0.2

Sheet Calc
A1: Helper | B1: FY26 | C1: FY27 | D1: FY28 | E1: FY29 | F1: FY30
A2: Fixed total ($) | B2: 1689592 | C2: 1731831.8 | D2: 1775127.6 | E2: 1819505.7 | F2: 1864993.4
A3: Var unit ($/student) | B3: 7129.08 | C3: 7307.307 | D3: 7489.9897 | E3: 7677.2394 | F3: 7869.1704
A4: Echo fixed ($) | B4: 785217.24 | C4: 804847.67 | D4: 824968.86 | E4: 845593.08 | F4: 866732.91
A5: Pima fixed ($) | B5: 904374.72 | C5: 926984.09 | D5: 950158.69 | E5: 973912.66 | F5: 998260.47
A7: Receiving overhead h ($/retained) | B7: 1000 | C7: 800 | D7: 600 | E7: 400 | F7: 300
A8: Lease f (fraction) | B8: 0.4 | C8: 0.3 | D8: 0.2 | E8: 0.1 | F8: 0
A9: Ops f (fraction) | B9: 0.4 | C9: 0.35 | D9: 0.3 | E9: 0.25 | F9: 0.2
A11: Total base ADM | B11: 553

Sheet Scenarios
A1: ScenarioKey | B1: Label | C1: Overlay | D1: CloseEcho | E1: ClosePima | F1: EchoShareDist | G1: ExtraSave | H1: Ramp | I1: Umbrella
A2: A_Repurpose_Both_lease | B2: A. Repurpose Both (Lease/Sale) | C2: 0 | D2: 1 | E2: 1 | F2: 0.5 | G2: 0 | H2: 0 | I2: lease
A3: A_Repurpose_Both_ops | B3: A. Repurpose Both (Ops) | C3: 0 | D3: 1 | E3: 1 | F3: 0.5 | G3: 0 | H3: 0 | I3: ops
A4: B_Repurpose_Echo_Grow_Pima_lease | B4: B. Repurpose Echo; Grow Pima (Lease) | C4: 0 | D4: 1 | E4: 0 | F4: 0.5 | G4: 0 | H4: 0 | I4: lease
A5: B_Repurpose_Echo_Grow_Pima_ops | B5: B. Repurpose Echo; Grow Pima (Ops) | C5: 0 | D5: 1 | E5: 0 | F5: 0.5 | G5: 0 | H5: 0 | I5: ops
A6: C_Repurpose_Pima_Grow_Echo_lease | B6: C. Repurpose Pima; Grow Echo (Lease) | C6: 0 | D6: 0 | E6: 1 | F6: 0.5 | G6: 0 | H6: 0 | I6: lease
A7: C_Repurpose_Pima_Grow_Echo_ops | B7: C. Repurpose Pima; Grow Echo (Ops) | C7: 0 | D7: 0 | E7: 1 | F7: 0.5 | G7: 0 | H7: 0 | I7: ops
A8: D_Grow_Both_0 | B8: D. Grow Both (Overlay 0) | C8: 0 | D8: 0 | E8: 0 | F8: 0.5 | G8: 0 | H8: 0
A9: D_Grow_Both_100 | B9: D. Grow Both (Overlay 100) | C9: 100 | D9: 0 | E9: 0 | F9: 0.5 | G9: 0 | H9: 0
A10: D_Grow_Both_150 | B10: D. Grow Both (Overlay 150) | C10: 150 | D10: 0 | E10: 0 | F10: 0.5 | G10: 0 | H10: 0
A11: E_StatusQuo_Targets_0 | B11: E. Status-Quo + Targets (0) | C11: 0 | D11: 0 | E11: 0 | F11: 0.5 | G11: 0 | H11: 0
A12: E_StatusQuo_Targets_100 | B12: E. Status-Quo + Targets (100) | C12: 100 | D12: 0 | E12: 0 | F12: 0.5 | G12: 0 | H12: 0
A13: E_StatusQuo_Targets_150 | B13: E. Status-Quo + Targets (150) | C13: 150 | D13: 0 | E13: 0 | F13: 0.5 | G13: 0 | H13: 0
A14: F_CoLocation_Echo_0 | B14: F. Co-Location @ Echo (0) | C14: 0 | D14: 0 | E14: 0 | F14: 0.7 | G14: 0.015 | H14: 0
A15: F_CoLocation_Echo_100 | B15: F. Co-Location @ Echo (100) | C15: 100 | D15: 0 | E15: 0 | F15: 0.7 | G15: 0.015 | H15: 0
A16: F_CoLocation_Echo_150 | B16: F. Co-Location @ Echo (150) | C16: 150 | D16: 0 | E16: 0 | F16: 0.7 | G16: 0.015 | H16: 0
A17: G_DHub_EchoRamp | B17: G. D-Hub @ Echo (Ramp 70/30) | C17: 150 | D17: 0 | E17: 0 | F17: 0.7 | G17: 0 | H17: 1

Sheet MultiYear_ProForma
A1: ScenarioKey | B1: Year | C1: Overlay | D1: Echo_ADM | E1: Pima_ADM | F1: Total_ADM | G1: EchoFixed$ | H1: PimaFixed$ | I1: VarUnit$ | J1: TI_add$ | K1: OpsFactor | L1: ExtraSave | M1: Total_MO$ | N1: MO_per_ADM$
A2: =Scenarios!A2 -> A_Repurpose_Both_lease | B2: FY2026 | C2: =Scenarios!C2 -> 0 | F2: =D2+E2 -> 0 | G2: =IF(Scenarios!D2=1, IF(Scenarios!I2="lease", INDEX(Calc!B4:F4,1,1)*INDEX(Calc!B8:F8,1,1), INDEX(Calc!B4:F4,1,1)*INDEX(Calc!B9:F9,1,1)), INDEX(Calc!B4:F4,1,1)) -> 314086.9 | H2: =IF(Scenarios!E2=1, IF(Scenarios!I2="lease", INDEX(Calc!B5:F5,1,1)*INDEX(Calc!B8:F8,1,1), INDEX(Calc!B5:F5,1,1)*INDEX(Calc!B9:F9,1,1)), INDEX(Calc!B5:F5,1,1)) -> 361749.89 | I2: =INDEX(Calc!B3:F3,1,1) -> 7129.08 | J2: =IF("FY2026"="FY2026", (IF(Scenarios!D2=1, Parameters!B9,0) + IF(Scenarios!E2=1, Parameters!B9,0)), 0) -> 1106 | K2: =1-Parameters!B4 -> 0.7 | L2: =Scenarios!G2 -> 0 | N2: =IF(F2>0, L2/F2, NA()) -> #N/A
A3: =Scenarios!A2 -> A_Repurpose_Both_lease | B3: FY2027 | C3: =Scenarios!C2 -> 0 | F3: =D3+E3 -> 0 | G3: =IF(Scenarios!D2=1, IF(Scenarios!I2="lease", INDEX(Calc!B4:F4,1,2)*INDEX(Calc!B8:F8,1,2), INDEX(Calc!B4:F4,1,2)*INDEX(Calc!B9:F9,1,2)), INDEX(Calc!B4:F4,1,2)) -> 241454.3 | H3: =IF(Scenarios!E2=1, IF(Scenarios!I2="lease", INDEX(Calc!B5:F5,1,2)*INDEX(Calc!B8:F8,1,2), INDEX(Calc!B5:F5,1,2)*INDEX(Calc!B9:F9,1,2)), INDEX(Calc!B5:F5,1,2)) -> 278095.23 | I3: =INDEX(Calc!B3:F3,1,2) -> 7307.307 | J3: =IF("FY2027"="FY2026", (IF(Scenarios!D2=1, Parameters!B9,0) + IF(Scenarios!E2=1, Parameters!B9,0)), 0) -> 0 | K3: =1-Parameters!B4 -> 0.7 | L3: =Scenarios!G2 -> 0 | N3: =IF(F3>0, L3/F3, NA()) -> #N/A
A4: =Scenarios!A2 -> A_Repurpose_Both_lease | B4: FY2028 | C4: =Scenarios!C2 -> 0 | F4: =D4+E4 -> 0 | G4: =IF(Scenarios!D2=1, IF(Scenarios!I2="lease", INDEX(Calc!B4:F4,1,3)*INDEX(Calc!B8:F8,1,3), INDEX(Calc!B4:F4,1,3)*INDEX(Calc!B9:F9,1,3)), INDEX(Calc!B4:F4,1,3)) -> 164993.77 | H4: =IF(Scenarios!E2=1, IF(Scenarios!I2="lease", INDEX(Calc!B5:F5,1,3)*INDEX(Calc!B8:F8,1,3), INDEX(Calc!B5:F5,1,3)*INDEX(Calc!B9:F9,1,3)), INDEX(Calc!B5:F5,1,3)) -> 190031.74 | I4: =INDEX(Calc!B3:F3,1,3) -> 7489.9897 | J4: =IF("FY2028"="FY2026", (IF(Scenarios!D2=1, Parameters!B9,0) + IF(Scenarios!E2=1, Parameters!B9,0)), 0) -> 0 | K4: =1-Parameters!B4 -> 0.7 | L4: =Scenarios!G2 -> 0 | N4: =IF(F4>0, L4/F4, NA()) -> #N/A
A5: =Scenarios!A2 -> A_Repurpose_Both_lease | B5: FY2029 | C5: =Scenarios!C2 -> 0 | F5: =D5+E5 -> 0 | G5: =IF(Scenarios!D2=1, IF(Scenarios!I2="lease", INDEX(Calc!B4:F4,1,4)*INDEX(Calc!B8:F8,1,4), INDEX(Calc!B4:F4,1,4)*INDEX(Calc!B9:F9,1,4)), INDEX(Calc!B4:F4,1,4)) -> 84559.308 | H5: =IF(Scenarios!E2=1, IF(Scenarios!I2="lease", INDEX(Calc!B5:F5,1,4)*INDEX(Calc!B8:F8,1,4), INDEX(Calc!B5:F5,1,4)*INDEX(Calc!B9:F9,1,4)), INDEX(Calc!B5:F5,1,4)) -> 97391.266 | I5: =INDEX(Calc!B3:F3,1,4) -> 7677.2394 | J5: =IF("FY2029"="FY2026", (IF(Scenarios!D2=1, Parameters!B9,0) + IF(Scenarios!E2=1, Parameters!B9,0)), 0) -> 0 | K5: =1-Parameters!B4 -> 0.7 | L5: =Scenarios!G2 -> 0 | N5: =IF(F5>0, L5/F5, NA()) -> #N/A
A6: =Scenarios!A2 -> A_Repurpose_Both_lease | B6: FY2030 | C6: =Scenarios!C2 -> 0 | F6: =D6+E6 -> 0 | G6: =IF(Scenarios!D2=1, IF(Scenarios!I2="lease", INDEX(Calc!B4:F4,1,5)*INDEX(Calc!B8:F8,1,5), INDEX(Calc!B4:F4,1,5)*INDEX(Calc!B9:F9,1,5)), INDEX(Calc!B4:F4,1,5)) -> 0 | H6: =IF(Scenarios!E2=1, IF(Scenarios!I2="lease", INDEX(Calc!B5:F5,1,5)*INDEX(Calc!B8:F8,1,5), INDEX(Calc!B5:F5,1,5)*INDEX(Calc!B9:F9,1,5)), INDEX(Calc!B5:F5,1,5)) -> 0 | I6: =INDEX(Calc!B3:F3,1,5) -> 7869.1704 | J6: =IF("FY2030"="FY2026", (IF(Scenarios!D2=1, Parameters!B9,0) + IF(Scenarios!E2=1, Parameters!B9,0)), 0) -> 0 | K6: =1-Parameters!B4 -> 0.7 | L6: =Scenarios!G2 -> 0 | N6: =IF(F6>0, L6/F6, NA()) -> #N/A
A7: =Scenarios!A3 -> A_Repurpose_Both_ops | B7: FY2026 | C7: =Scenarios!C3 -> 0 | F7: =D7+E7 -> 0 | G7: =IF(Scenarios!D3=1, IF(Scenarios!I3="lease", INDEX(Calc!B4:F4,1,1)*INDEX(Calc!B8:F8,1,1), INDEX(Calc!B4:F4,1,1)*INDEX(Calc!B9:F9,1,1)), INDEX(Calc!B4:F4,1,1)) -> 314086.9 | H7: =IF(Scenarios!E3=1, IF(Scenarios!I3="lease", INDEX(Calc!B5:F5,1,1)*INDEX(Calc!B8:F8,1,1), INDEX(Calc!B5:F5,1,1)*INDEX(Calc!B9:F9,1,1)), INDEX(Calc!B5:F5,1,1)) -> 361749.89 | I7: =INDEX(Calc!B3:F3,1,1) -> 7129.08 | J7: =IF("FY2026"="FY2026", (IF(Scenarios!D3=1, Parameters!B9,0) + IF(Scenarios!E3=1, Parameters!B9,0)), 0) -> 1106 | K7: =1-Parameters!B4 -> 0.7 | L7: =Scenarios!G3 -> 0 | N7: =IF(F7>0, L7/F7, NA()) -> #N/A
A8: =Scenarios!A3 -> A_Repurpose_Both_ops | B8: FY2027 | C8: =Scenarios!C3 -> 0 | F8: =D8+E8 -> 0 | G8: =IF(Scenarios!D3=1, IF(Scenarios!I3="lease", INDEX(Calc!B4:F4,1,2)*INDEX(Calc!B8:F8,1,2), INDEX(Calc!B4:F4,1,2)*INDEX(Calc!B9:F9,1,2)), INDEX(Calc!B4:F4,1,2)) -> 281696.68 | H8: =IF(Scenarios!E3=1, IF(Scenarios!I3="lease", INDEX(Calc!B5:F5,1,2)*INDEX(Calc!B8:F8,1,2), INDEX(Calc!B5:F5,1,2)*INDEX(Calc!B9:F9,1,2)), INDEX(Calc!B5:F5,1,2)) -> 324444.43 | I8: =INDEX(Calc!B3:F3,1,2) -> 7307.307 | J8: =IF("FY2027"="FY2026", (IF(Scenarios!D3=1, Parameters!B9,0) + IF(Scenarios!E3=1, Parameters!B9,0)), 0) -> 0 | K8: =1-Parameters!B4 -> 0.7 | L8: =Scenarios!G3 -> 0 | N8: =IF(F8>0, L8/F8, NA()) -> #N/A
A9: =Scenarios!A3 -> A_Repurpose_Both_ops | B9: FY2028 | C9: =Scenarios!C3 -> 0 | F9: =D9+E9 -> 0 | G9: =IF(Scenarios!D3=1, IF(Scenarios!I3="lease", INDEX(Calc!B4:F4,1,3)*INDEX(Calc!B8:F8,1,3), INDEX(Calc!B4:F4,1,3)*INDEX(Calc!B9:F9,1,3)), INDEX(Calc!B4:F4,1,3)) -> 247490.66 | H9: =IF(Scenarios!E3=1, IF(Scenarios!I3="lease", INDEX(Calc!B5:F5,1,3)*INDEX(Calc!B8:F8,1,3), INDEX(Calc!B5:F5,1,3)*INDEX(Calc!B9:F9,1,3)), INDEX(Calc!B5:F5,1,3)) -> 285047.61 | I9: =INDEX(Calc!B3:F3,1,3) -> 7489.9897 | J9: =IF("FY2028"="FY2026", (IF(Scenarios!D3=1, Parameters!B9,0) + IF(Scenarios!E3=1, Parameters!B9,0)), 0) -> 0 | K9: =1-Parameters!B4 -> 0.7 | L9: =Scenarios!G3 -> 0 | N9: =IF(F9>0, L9/F9, NA()) -> #N/A
A10: =Scenarios!A3 -> A_Repurpose_Both_ops | B10: FY2029 | C10: =Scenarios!C3 -> 0 | F10: =D10+E10 -> 0 | G10: =IF(Scenarios!D3=1, IF(Scenarios!I3="lease", INDEX(Calc!B4:F4,1,4)*INDEX(Calc!B8:F8,1,4), INDEX(Calc!B4:F4,1,4)*INDEX(Calc!B9:F9,1,4)), INDEX(Calc!B4:F4,1,4)) -> 211398.27 | H10: =IF(Scenarios!E3=1, IF(Scenarios!I3="lease", INDEX(Calc!B5:F5,1,4)*INDEX(Calc!B8:F8,1,4), INDEX(Calc!B5:F5,1,4)*INDEX(Calc!B9:F9,1,4)), INDEX(Calc!B5:F5,1,4)) -> 243478.16 | I10: =INDEX(Calc!B3:F3,1,4) -> 7677.2394 | J10: =IF("FY2029"="FY2026", (IF(Scenarios!D3=1, Parameters!B9,0) + IF(Scenarios!E3=1, Parameters!B9,0)), 0) -> 0 | K10: =1-Parameters!B4 -> 0.7 | L10: =Scenarios!G3 -> 0 | N10: =IF(F10>0, L10/F10, NA()) -> #N/A
A11: =Scenarios!A3 -> A_Repurpose_Both_ops | B11: FY2030 | C11: =Scenarios!C3 -> 0 | F11: =D11+E11 -> 0 | G11: =IF(Scenarios!D3=1, IF(Scenarios!I3="lease", INDEX(Calc!B4:F4,1,5)*INDEX(Calc!B8:F8,1,5), INDEX(Calc!B4:F4,1,5)*INDEX(Calc!B9:F9,1,5)), INDEX(Calc!B4:F4,1,5)) -> 173346.58 | H11: =IF(Scenarios!E3=1, IF(Scenarios!I3="lease", INDEX(Calc!B5:F5,1,5)*INDEX(Calc!B8:F8,1,5), INDEX(Calc!B5:F5,1,5)*INDEX(Calc!B9:F9,1,5)), INDEX(Calc!B5:F5,1,5)) -> 199652.09 | I11: =INDEX(Calc!B3:F3,1,5) -> 7869.1704 | J11: =IF("FY2030"="FY2026", (IF(Scenarios!D3=1, Parameters!B9,0) + IF(Scenarios!E3=1, Parameters!B9,0)), 0) -> 0 | K11: =1-Parameters!B4 -> 0.7 | L11: =Scenarios!G3 -> 0 | N11: =IF(F11>0, L11/F11, NA()) -> #N/A
A12: =Scenarios!A4 -> B_Repurpose_Echo_Grow_Pima_lease | B12: FY2026 | C12: =Scenarios!C4 -> 0 | F12: =D12+E12 -> 0 | G12: =IF(Scenarios!D4=1, IF(Scenarios!I4="lease", INDEX(Calc!B4:F4,1,1)*INDEX(Calc!B8:F8,1,1), INDEX(Calc!B4:F4,1,1)*INDEX(Calc!B9:F9,1,1)), INDEX(Calc!B4:F4,1,1)) -> 314086.9 | H12: =IF(Scenarios!E4=1, IF(Scenarios!I4="lease", INDEX(Calc!B5:F5,1,1)*INDEX(Calc!B8:F8,1,1), INDEX(Calc!B5:F5,1,1)*INDEX(Calc!B9:F9,1,1)), INDEX(Calc!B5:F5,1,1)) -> 904374.72 | I12: =INDEX(Calc!B3:F3,1,1) -> 7129.08 | J12: =IF("FY2026"="FY2026", (IF(Scenarios!D4=1, Parameters!B9,0) + IF(Scenarios!E4=1, Parameters!B9,0)), 0) -> 553 | K12: =1-Parameters!B4 -> 0.7 | L12: =Scenarios!G4 -> 0 | N12: =IF(F12>0, L12/F12, NA()) -> #N/A
A13: =Scenarios!A4 -> B_Repurpose_Echo_Grow_Pima_lease | B13: FY2027 | C13: =Scenarios!C4 -> 0 | F13: =D13+E13 -> 0 | G13: =IF(Scenarios!D4=1, IF(Scenarios!I4="lease", INDEX(Calc!B4:F4,1,2)*INDEX(Calc!B8:F8,1,2), INDEX(Calc!B4:F4,1,2)*INDEX(Calc!B9:F9,1,2)), INDEX(Calc!B4:F4,1,2)) -> 241454.3 | H13: =IF(Scenarios!E4=1, IF(Scenarios!I4="lease", INDEX(Calc!B5:F5,1,2)*INDEX(Calc!B8:F8,1,2), INDEX(Calc!B5:F5,1,2)*INDEX(Calc!B9:F9,1,2)), INDEX(Calc!B5:F5,1,2)) -> 926984.09 | I13: =INDEX(Calc!B3:F3,1,2) -> 7307.307 | J13: =IF("FY2027"="FY2026", (IF(Scenarios!D4=1, Parameters!B9,0) + IF(Scenarios!E4=1, Parameters!B9,0)), 0) -> 0 | K13: =1-Parameters!B4 -> 0.7 | L13: =Scenarios!G4 -> 0 | N13: =IF(F13>0, L13/F13, NA()) -> #N/A
A14: =Scenarios!A4 -> B_Repurpose_Echo_Grow_Pima_lease | B14: FY2028 | C14: =Scenarios!C4 -> 0 | F14: =D14+E14 -> 0 | G14: =IF(Scenarios!D4=1, IF(Scenarios!I4="lease", INDEX(Calc!B4:F4,1,3)*INDEX(Calc!B8:F8,1,3), INDEX(Calc!B4:F4,1,3)*INDEX(Calc!B9:F9,1,3)), INDEX(Calc!B4:F4,1,3)) -> 164993.77 | H14: =IF(Scenarios!E4=1, IF(Scenarios!I4="lease", INDEX(Calc!B5:F5,1,3)*INDEX(Calc!B8:F8,1,3), INDEX(Calc!B5:F5,1,3)*INDEX(Calc!B9:F9,1,3)), INDEX(Calc!B5:F5,1,3)) -> 950158.69 | I14: =INDEX(Calc!B3:F3,1,3) -> 7489.9897 | J14: =IF("FY2028"="FY2026", (IF(Scenarios!D4=1, Parameters!B9,0) + IF(Scenarios!E4=1, Parameters!B9,0)), 0) -> 0 | K14: =1-Parameters!B4 -> 0.7 | L14: =Scenarios!G4 -> 0 | N14: =IF(F14>0, L14/F14, NA()) -> #N/A
A15: =Scenarios!A4 -> B_Repurpose_Echo_Grow_Pima_lease | B15: FY2029 | C15: =Scenarios!C4 -> 0 | F15: =D15+E15 -> 0 | G15: =IF(Scenarios!D4=1, IF(Scenarios!I4="lease", INDEX(Calc!B4:F4,1,4)*INDEX(Calc!B8:F8,1,4), INDEX(Calc!B4:F4,1,4)*INDEX(Calc!B9:F9,1,4)), INDEX(Calc!B4:F4,1,4)) -> 84559.308 | H15: =IF(Scenarios!E4=1, IF(Scenarios!I4="lease", INDEX(Calc!B5:F5,1,4)*INDEX(Calc!B8:F8,1,4), INDEX(Calc!B5:F5,1,4)*INDEX(Calc!B9:F9,1,4)), INDEX(Calc!B5:F5,1,4)) -> 973912.66 | I15: =INDEX(Calc!B3:F3,1,4) -> 7677.2394 | J15: =IF("FY2029"="FY2026", (IF(Scenarios!D4=1, Parameters!B9,0) + IF(Scenarios!E4=1, Parameters!B9,0)), 0) -> 0 | K15: =1-Parameters!B4 -> 0.7 | L15: =Scenarios!G4 -> 0 | N15: =IF(F15>0, L15/F15, NA()) -> #N/A
A16: =Scenarios!A4 -> B_Repurpose_Echo_Grow_Pima_lease | B16: FY2030 | C16: =Scenarios!C4 -> 0 | F16: =D16+E16 -> 0 | G16: =IF(Scenarios!D4=1, IF(Scenarios!I4="lease", INDEX(Calc!B4:F4,1,5)*INDEX(Calc!B8:F8,1,5), INDEX(Calc!B4:F4,1,5)*INDEX(Calc!B9:F9,1,5)), INDEX(Calc!B4:F4,1,5)) -> 0 | H16: =IF(Scenarios!E4=1, IF(Scenarios!I4="lease", INDEX(Calc!B5:F5,1,5)*INDEX(Calc!B8:F8,1,5), INDEX(Calc!B5:F5,1,5)*INDEX(Calc!B9:F9,1,5)), INDEX(Calc!B5:F5,1,5)) -> 998260.47 | I16: =INDEX(Calc!B3:F3,1,5) -> 7869.1704 | J16: =IF("FY2030"="FY2026", (IF(Scenarios!D4=1, Parameters!B9,0) + IF(Scenarios!E4=1, Parameters!B9,0)), 0) -> 0 | K16: =1-Parameters!B4 -> 0.7 | L16: =Scenarios!G4 -> 0 | N16: =IF(F16>0, L16/F16, NA()) -> #N/A
A17: =Scenarios!A5 -> B_Repurpose_Echo_Grow_Pima_ops | B17: FY2026 | C17: =Scenarios!C5 -> 0 | F17: =D17+E17 -> 0 | G17: =IF(Scenarios!D5=1, IF(Scenarios!I5="lease", INDEX(Calc!B4:F4,1,1)*INDEX(Calc!B8:F8,1,1), INDEX(Calc!B4:F4,1,1)*INDEX(Calc!B9:F9,1,1)), INDEX(Calc!B4:F4,1,1)) -> 314086.9 | H17: =IF(Scenarios!E5=1, IF(Scenarios!I5="lease", INDEX(Calc!B5:F5,1,1)*INDEX(Calc!B8:F8,1,1), INDEX(Calc!B5:F5,1,1)*INDEX(Calc!B9:F9,1,1)), INDEX(Calc!B5:F5,1,1)) -> 904374.72 | I17: =INDEX(Calc!B3:F3,1,1) -> 7129.08 | J17: =IF("FY2026"="FY2026", (IF(Scenarios!D5=1, Parameters!B9,0) + IF(Scenarios!E5=1, Parameters!B9,0)), 0) -> 553 | K17: =1-Parameters!B4 -> 0.7 | L17: =Scenarios!G5 -> 0 | N17: =IF(F17>0, L17/F17, NA()) -> #N/A
A18: =Scenarios!A5 -> B_Repurpose_Echo_Grow_Pima_ops | B18: FY2027 | C18: =Scenarios!C5 -> 0 | F18: =D18+E18 -> 0 | G18: =IF(Scenarios!D5=1, IF(Scenarios!I5="lease", INDEX(Calc!B4:F4,1,2)*INDEX(Calc!B8:F8,1,2), INDEX(Calc!B4:F4,1,2)*INDEX(Calc!B9:F9,1,2)), INDEX(Calc!B4:F4,1,2)) -> 281696.68 | H18: =IF(Scenarios!E5=1, IF(Scenarios!I5="lease", INDEX(Calc!B5:F5,1,2)*INDEX(Calc!B8:F8,1,2), INDEX(Calc!B5:F5,1,2)*INDEX(Calc!B9:F9,1,2)), INDEX(Calc!B5:F5,1,2)) -> 926984.09 | I18: =INDEX(Calc!B3:F3,1,2) -> 7307.307 | J18: =IF("FY2027"="FY2026", (IF(Scenarios!D5=1, Parameters!B9,0) + IF(Scenarios!E5=1, Parameters!B9,0)), 0) -> 0 | K18: =1-Parameters!B4 -> 0.7 | L18: =Scenarios!G5 -> 0 | N18: =IF(F18>0, L18/F18, NA()) -> #N/A
A19: =Scenarios!A5 -> B_Repurpose_Echo_Grow_Pima_ops | B19: FY2028 | C19: =Scenarios!C5 -> 0 | F19: =D19+E19 -> 0 | G19: =IF(Scenarios!D5=1, IF(Scenarios!I5="lease", INDEX(Calc!B4:F4,1,3)*INDEX(Calc!B8:F8,1,3), INDEX(Calc!B4:F4,1,3)*INDEX(Calc!B9:F9,1,3)), INDEX(Calc!B4:F4,1,3)) -> 247490.66 | H19: =IF(Scenarios!E5=1, IF(Scenarios!I5="lease", INDEX(Calc!B5:F5,1,3)*INDEX(Calc!B8:F8,1,3), INDEX(Calc!B5:F5,1,3)*INDEX(Calc!B9:F9,1,3)), INDEX(Calc!B5:F5,1,3)) -> 950158.69 | I19: =INDEX(Calc!B3:F3,1,3) -> 7489.9897 | J19: =IF("FY2028"="FY2026", (IF(Scenarios!D5=1, Parameters!B9,0) + IF(Scenarios!E5=1, Parameters!B9,0)), 0) -> 0 | K19: =1-Parameters!B4 -> 0.7 | L19: =Scenarios!G5 -> 0 | N19: =IF(F19>0, L19/F19, NA()) -> #N/A
A20: =Scenarios!A5 -> B_Repurpose_Echo_Grow_Pima_ops | B20: FY2029 | C20: =Scenarios!C5 -> 0 | F20: =D20+E20 -> 0 | G20: =IF(Scenarios!D5=1, IF(Scenarios!I5="lease", INDEX(Calc!B4:F4,1,4)*INDEX(Calc!B8:F8,1,4), INDEX(Calc!B4:F4,1,4)*INDEX(Calc!B9:F9,1,4)), INDEX(Calc!B4:F4,1,4)) -> 211398.27 | H20: =IF(Scenarios!E5=1, IF(Scenarios!I5="lease", INDEX(Calc!B5:F5,1,4)*INDEX(Calc!B8:F8,1,4), INDEX(Calc!B5:F5,1,4)*INDEX(Calc!B9:F9,1,4)), INDEX(Calc!B5:F5,1,4)) -> 973912.66 | I20: =INDEX(Calc!B3:F3,1,4) -> 7677.2394 | J20: =IF("FY2029"="FY2026", (IF(Scenarios!D5=1, Parameters!B9,0) + IF(Scenarios!E5=1, Parameters!B9,0)), 0) -> 0 | K20: =1-Parameters!B4 -> 0.7 | L20: =Scenarios!G5 -> 0 | N20: =IF(F20>0, L20/F20, NA()) -> #N/A
A21: =Scenarios!A5 -> B_Repurpose_Echo_Grow_Pima_ops | B21: FY2030 | C21: =Scenarios!C5 -> 0 | F21: =D21+E21 -> 0 | G21: =IF(Scenarios!D5=1, IF(Scenarios!I5="lease", INDEX(Calc!B4:F4,1,5)*INDEX(Calc!B8:F8,1,5), INDEX(Calc!B4:F4,1,5)*INDEX(Calc!B9:F9,1,5)), INDEX(Calc!B4:F4,1,5)) -> 173346.58 | H21: =IF(Scenarios!E5=1, IF(Scenarios!I5="lease", INDEX(Calc!B5:F5,1,5)*INDEX(Calc!B8:F8,1,5), INDEX(Calc!B5:F5,1,5)*INDEX(Calc!B9:F9,1,5)), INDEX(Calc!B5:F5,1,5)) -> 998260.47 | I21: =INDEX(Calc!B3:F3,1,5) -> 7869.1704 | J21: =IF("FY2030"="FY2026", (IF(Scenarios!D5=1, Parameters!B9,0) + IF(Scenarios!E5=1, Parameters!B9,0)), 0) -> 0 | K21: =1-Parameters!B4 -> 0.7 | L21: =Scenarios!G5 -> 0 | N21: =IF(F21>0, L21/F21, NA()) -> #N/A
A22: =Scenarios!A6 -> C_Repurpose_Pima_Grow_Echo_lease | B22: FY2026 | C22: =Scenarios!C6 -> 0 | F22: =D22+E22 -> 0 | G22: =IF(Scenarios!D6=1, IF(Scenarios!I6="lease", INDEX(Calc!B4:F4,1,1)*INDEX(Calc!B8:F8,1,1), INDEX(Calc!B4:F4,1,1)*INDEX(Calc!B9:F9,1,1)), INDEX(Calc!B4:F4,1,1)) -> 785217.24 | H22: =IF(Scenarios!E6=1, IF(Scenarios!I6="lease", INDEX(Calc!B5:F5,1,1)*INDEX(Calc!B8:F8,1,1), INDEX(Calc!B5:F5,1,1)*INDEX(Calc!B9:F9,1,1)), INDEX(Calc!B5:F5,1,1)) -> 361749.89 | I22: =INDEX(Calc!B3:F3,1,1) -> 7129.08 | J22: =IF("FY2026"="FY2026", (IF(Scenarios!D6=1, Parameters!B9,0) + IF(Scenarios!E6=1, Parameters!B9,0)), 0) -> 553 | K22: =1-Parameters!B4 -> 0.7 | L22: =Scenarios!G6 -> 0 | N22: =IF(F22>0, L22/F22, NA()) -> #N/A
A23: =Scenarios!A6 -> C_Repurpose_Pima_Grow_Echo_lease | B23: FY2027 | C23: =Scenarios!C6 -> 0 | F23: =D23+E23 -> 0 | G23: =IF(Scenarios!D6=1, IF(Scenarios!I6="lease", INDEX(Calc!B4:F4,1,2)*INDEX(Calc!B8:F8,1,2), INDEX(Calc!B4:F4,1,2)*INDEX(Calc!B9:F9,1,2)), INDEX(Calc!B4:F4,1,2)) -> 804847.67 | H23: =IF(Scenarios!E6=1, IF(Scenarios!I6="lease", INDEX(Calc!B5:F5,1,2)*INDEX(Calc!B8:F8,1,2), INDEX(Calc!B5:F5,1,2)*INDEX(Calc!B9:F9,1,2)), INDEX(Calc!B5:F5,1,2)) -> 278095.23 | I23: =INDEX(Calc!B3:F3,1,2) -> 7307.307 | J23: =IF("FY2027"="FY2026", (IF(Scenarios!D6=1, Parameters!B9,0) + IF(Scenarios!E6=1, Parameters!B9,0)), 0) -> 0 | K23: =1-Parameters!B4 -> 0.7 | L23: =Scenarios!G6 -> 0 | N23: =IF(F23>0, L23/F23, NA()) -> #N/A
A24: =Scenarios!A6 -> C_Repurpose_Pima_Grow_Echo_lease | B24: FY2028 | C24: =Scenarios!C6 -> 0 | F24: =D24+E24 -> 0 | G24: =IF(Scenarios!D6=1, IF(Scenarios!I6="lease", INDEX(Calc!B4:F4,1,3)*INDEX(Calc!B8:F8,1,3), INDEX(Calc!B4:F4,1,3)*INDEX(Calc!B9:F9,1,3)), INDEX(Calc!B4:F4,1,3)) -> 824968.86 | H24: =IF(Scenarios!E6=1, IF(Scenarios!I6="lease", INDEX(Calc!B5:F5,1,3)*INDEX(Calc!B8:F8,1,3), INDEX(Calc!B5:F5,1,3)*INDEX(Calc!B9:F9,1,3)), INDEX(Calc!B5:F5,1,3)) -> 190031.74 | I24: =INDEX(Calc!B3:F3,1,3) -> 7489.9897 | J24: =IF("FY2028"="FY2026", (IF(Scenarios!D6=1, Parameters!B9,0) + IF(Scenarios!E6=1, Parameters!B9,0)), 0) -> 0 | K24: =1-Parameters!B4 -> 0.7 | L24: =Scenarios!G6 -> 0 | N24: =IF(F24>0, L24/F24, NA()) -> #N/A
A25: =Scenarios!A6 -> C_Repurpose_Pima_Grow_Echo_lease | B25: FY2029 | C25: =Scenarios!C6 -> 0 | F25: =D25+E25 -> 0 | G25: =IF(Scenarios!D6=1, IF(Scenarios!I6="lease", INDEX(Calc!B4:F4,1,4)*INDEX(Calc!B8:F8,1,4), INDEX(Calc!B4:F4,1,4)*INDEX(Calc!B9:F9,1,4)), INDEX(Calc!B4:F4,1,4)) -> 845593.08 | H25: =IF(Scenarios!E6=1, IF(Scenarios!I6="lease", INDEX(Calc!B5:F5,1,4)*INDEX(Calc!B8:F8,1,4), INDEX(Calc!B5:F5,1,4)*INDEX(Calc!B9:F9,1,4)), INDEX(Calc!B5:F5,1,4)) -> 97391.266 | I25: =INDEX(Calc!B3:F3,1,4) -> 7677.2394 | J25: =IF("FY2029"="FY2026", (IF(Scenarios!D6=1, Parameters!B9,0) + IF(Scenarios!E6=1, Parameters!B9,0)), 0) -> 0 | K25: =1-Parameters!B4 -> 0.7 | L25: =Scenarios!G6 -> 0 | N25: =IF(F25>0, L25/F25, NA()) -> #N/A
A26: =Scenarios!A6 -> C_Repurpose_Pima_Grow_Echo_lease | B26: FY2030 | C26: =Scenarios!C6 -> 0 | F26: =D26+E26 -> 0 | G26: =IF(Scenarios!D6=1, IF(Scenarios!I6="lease", INDEX(Calc!B4:F4,1,5)*INDEX(Calc!B8:F8,1,5), INDEX(Calc!B4:F4,1,5)*INDEX(Calc!B9:F9,1,5)), INDEX(Calc!B4:F4,1,5)) -> 866732.91 | H26: =IF(Scenarios!E6=1, IF(Scenarios!I6="lease", INDEX(Calc!B5:F5,1,5)*INDEX(Calc!B8:F8,1,5), INDEX(Calc!B5:F5,1,5)*INDEX(Calc!B9:F9,1,5)), INDEX(Calc!B5:F5,1,5)) -> 0 | I26: =INDEX(Calc!B3:F3,1,5) -> 7869.1704 | J26: =IF("FY2030"="FY2026", (IF(Scenarios!D6=1, Parameters!B9,0) + IF(Scenarios!E6=1, Parameters!B9,0)), 0) -> 0 | K26: =1-Parameters!B4 -> 0.7 | L26: =Scenarios!G6 -> 0 | N26: =IF(F26>0, L26/F26, NA()) -> #N/A
A27: =Scenarios!A7 -> C_Repurpose_Pima_Grow_Echo_ops | B27: FY2026 | C27: =Scenarios!C7 -> 0 | F27: =D27+E27 -> 0 | G27: =IF(Scenarios!D7=1, IF(Scenarios!I7="lease", INDEX(Calc!B4:F4,1,1)*INDEX(Calc!B8:F8,1,1), INDEX(Calc!B4:F4,1,1)*INDEX(Calc!B9:F9,1,1)), INDEX(Calc!B4:F4,1,1)) -> 785217.24 | H27: =IF(Scenarios!E7=1, IF(Scenarios!I7="lease", INDEX(Calc!B5:F5,1,1)*INDEX(Calc!B8:F8,1,1), INDEX(Calc!B5:F5,1,1)*INDEX(Calc!B9:F9,1,1)), INDEX(Calc!B5:F5,1,1)) -> 361749.89 | I27: =INDEX(Calc!B3:F3,1,1) -> 7129.08 | J27: =IF("FY2026"="FY2026", (IF(Scenarios!D7=1, Parameters!B9,0) + IF(Scenarios!E7=1, Parameters!B9,0)), 0) -> 553 | K27: =1-Parameters!B4 -> 0.7 | L27: =Scenarios!G7 -> 0 | N27: =IF(F27>0, L27/F27, NA()) -> #N/A
A28: =Scenarios!A7 -> C_Repurpose_Pima_Grow_Echo_ops | B28: FY2027 | C28: =Scenarios!C7 -> 0 | F28: =D28+E28 -> 0 | G28: =IF(Scenarios!D7=1, IF(Scenarios!I7="lease", INDEX(Calc!B4:F4,1,2)*INDEX(Calc!B8:F8,1,2), INDEX(Calc!B4:F4,1,2)*INDEX(Calc!B9:F9,1,2)), INDEX(Calc!B4:F4,1,2)) -> 804847.67 | H28: =IF(Scenarios!E7=1, IF(Scenarios!I7="lease", INDEX(Calc!B5:F5,1,2)*INDEX(Calc!B8:F8,1,2), INDEX(Calc!B5:F5,1,2)*INDEX(Calc!B9:F9,1,2)), INDEX(Calc!B5:F5,1,2)) -> 324444.43 | I28: =INDEX(Calc!B3:F3,1,2) -> 7307.307 | J28: =IF("FY2027"="FY2026", (IF(Scenarios!D7=1, Parameters!B9,0) + IF(Scenarios!E7=1, Parameters!B9,0)), 0) -> 0 | K28: =1-Parameters!B4 -> 0.7 | L28: =Scenarios!G7 -> 0 | N28: =IF(F28>0, L28/F28, NA()) -> #N/A
A29: =Scenarios!A7 -> C_Repurpose_Pima_Grow_Echo_ops | B29: FY2028 | C29: =Scenarios!C7 -> 0 | F29: =D29+E29 -> 0 | G29: =IF(Scenarios!D7=1, IF(Scenarios!I7="lease", INDEX(Calc!B4:F4,1,3)*INDEX(Calc!B8:F8,1,3), INDEX(Calc!B4:F4,1,3)*INDEX(Calc!B9:F9,1,3)), INDEX(Calc!B4:F4,1,3)) -> 824968.86 | H29: =IF(Scenarios!E7=1, IF(Scenarios!I7="lease", INDEX(Calc!B5:F5,1,3)*INDEX(Calc!B8:F8,1,3), INDEX(Calc!B5:F5,1,3)*INDEX(Calc!B9:F9,1,3)), INDEX(Calc!B5:F5,1,3)) -> 285047.61 | I29: =INDEX(Calc!B3:F3,1,3) -> 7489.9897 | J29: =IF("FY2028"="FY2026", (IF(Scenarios!D7=1, Parameters!B9,0) + IF(Scenarios!E7=1, Parameters!B9,0)), 0) -> 0 | K29: =1-Parameters!B4 -> 0.7 | L29: =Scenarios!G7 -> 0 | N29: =IF(F29>0, L29/F29, NA()) -> #N/A
A30: =Scenarios!A7 -> C_Repurpose_Pima_Grow_Echo_ops | B30: FY2029 | C30: =Scenarios!C7 -> 0 | F30: =D30+E30 -> 0 | G30: =IF(Scenarios!D7=1, IF(Scenarios!I7="lease", INDEX(Calc!B4:F4,1,4)*INDEX(Calc!B8:F8,1,4), INDEX(Calc!B4:F4,1,4)*INDEX(Calc!B9:F9,1,4)), INDEX(Calc!B4:F4,1,4)) -> 845593.08 | H30: =IF(Scenarios!E7=1, IF(Scenarios!I7="lease", INDEX(Calc!B5:F5,1,4)*INDEX(Calc!B8:F8,1,4), INDEX(Calc!B5:F5,1,4)*INDEX(Calc!B9:F9,1,4)), INDEX(Calc!B5:F5,1,4)) -> 243478.16 | I30: =INDEX(Calc!B3:F3,1,4) -> 7677.2394 | J30: =IF("FY2029"="FY2026", (IF(Scenarios!D7=1, Parameters!B9,0) + IF(Scenarios!E7=1, Parameters!B9,0)), 0) -> 0 | K30: =1-Parameters!B4 -> 0.7 | L30: =Scenarios!G7 -> 0 | N30: =IF(F30>0, L30/F30, NA()) -> #N/A
A31: =Scenarios!A7 -> C_Repurpose_Pima_Grow_Echo_ops | B31: FY2030 | C31: =Scenarios!C7 -> 0 | F31: =D31+E31 -> 0 | G31: =IF(Scenarios!D7=1, IF(Scenarios!I7="lease", INDEX(Calc!B4:F4,1,5)*INDEX(Calc!B8:F8,1,5), INDEX(Calc!B4:F4,1,5)*INDEX(Calc!B9:F9,1,5)), INDEX(Calc!B4:F4,1,5)) -> 866732.91 | H31: =IF(Scenarios!E7=1, IF(Scenarios!I7="lease", INDEX(Calc!B5:F5,1,5)*INDEX(Calc!B8:F8,1,5), INDEX(Calc!B5:F5,1,5)*INDEX(Calc!B9:F9,1,5)), INDEX(Calc!B5:F5,1,5)) -> 199652.09 | I31: =INDEX(Calc!B3:F3,1,5) -> 7869.1704 | J31: =IF("FY2030"="FY2026", (IF(Scenarios!D7=1, Parameters!B9,0) + IF(Scenarios!E7=1, Parameters!B9,0)), 0) -> 0 | K31: =1-Parameters!B4 -> 0.7 | L31: =Scenarios!G7 -> 0 | N31: =IF(F31>0, L31/F31, NA()) -> #N/A
A32: =Scenarios!A8 -> D_Grow_Both_0 | B32: FY2026 | C32: =Scenarios!C8 -> 0 | F32: =D32+E32 -> 0 | G32: =IF(Scenarios!D8=1, IF(Scenarios!I8="lease", INDEX(Calc!B4:F4,1,1)*INDEX(Calc!B8:F8,1,1), INDEX(Calc!B4:F4,1,1)*INDEX(Calc!B9:F9,1,1)), INDEX(Calc!B4:F4,1,1)) -> 785217.24 | H32: =IF(Scenarios!E8=1, IF(Scenarios!I8="lease", INDEX(Calc!B5:F5,1,1)*INDEX(Calc!B8:F8,1,1), INDEX(Calc!B5:F5,1,1)*INDEX(Calc!B9:F9,1,1)), INDEX(Calc!B5:F5,1,1)) -> 904374.72 | I32: =INDEX(Calc!B3:F3,1,1) -> 7129.08 | J32: =IF("FY2026"="FY2026", (IF(Scenarios!D8=1, Parameters!B9,0) + IF(Scenarios!E8=1, Parameters!B9,0)), 0) -> 0 | K32: =1-Parameters!B4 -> 0.7 | L32: =Scenarios!G8 -> 0 | N32: =IF(F32>0, L32/F32, NA()) -> #N/A
A33: =Scenarios!A8 -> D_Grow_Both_0 | B33: FY2027 | C33: =Scenarios!C8 -> 0 | F33: =D33+E33 -> 0 | G33: =IF(Scenarios!D8=1, IF(Scenarios!I8="lease", INDEX(Calc!B4:F4,1,2)*INDEX(Calc!B8:F8,1,2), INDEX(Calc!B4:F4,1,2)*INDEX(Calc!B9:F9,1,2)), INDEX(Calc!B4:F4,1,2)) -> 804847.67 | H33: =IF(Scenarios!E8=1, IF(Scenarios!I8="lease", INDEX(Calc!B5:F5,1,2)*INDEX(Calc!B8:F8,1,2), INDEX(Calc!B5:F5,1,2)*INDEX(Calc!B9:F9,1,2)), INDEX(Calc!B5:F5,1,2)) -> 926984.09 | I33: =INDEX(Calc!B3:F3,1,2) -> 7307.307 | J33: =IF("FY2027"="FY2026", (IF(Scenarios!D8=1, Parameters!B9,0) + IF(Scenarios!E8=1, Parameters!B9,0)), 0) -> 0 | K33: =1-Parameters!B4 -> 0.7 | L33: =Scenarios!G8 -> 0 | N33: =IF(F33>0, L33/F33, NA()) -> #N/A
A34: =Scenarios!A8 -> D_Grow_Both_0 | B34: FY2028 | C34: =Scenarios!C8 -> 0 | F34: =D34+E34 -> 0 | G34: =IF(Scenarios!D8=1, IF(Scenarios!I8="lease", INDEX(Calc!B4:F4,1,3)*INDEX(Calc!B8:F8,1,3), INDEX(Calc!B4:F4,1,3)*INDEX(Calc!B9:F9,1,3)), INDEX(Calc!B4:F4,1,3)) -> 824968.86 | H34: =IF(Scenarios!E8=1, IF(Scenarios!I8="lease", INDEX(Calc!B5:F5,1,3)*INDEX(Calc!B8:F8,1,3), INDEX(Calc!B5:F5,1,3)*INDEX(Calc!B9:F9,1,3)), INDEX(Calc!B5:F5,1,3)) -> 950158.69 | I34: =INDEX(Calc!B3:F3,1,3) -> 7489.9897 | J34: =IF("FY2028"="FY2026", (IF(Scenarios!D8=1, Parameters!B9,0) + IF(Scenarios!E8=1, Parameters!B9,0)), 0) -> 0 | K34: =1-Parameters!B4 -> 0.7 | L34: =Scenarios!G8 -> 0 | N34: =IF(F34>0, L34/F34, NA()) -> #N/A
A35: =Scenarios!A8 -> D_Grow_Both_0 | B35: FY2029 | C35: =Scenarios!C8 -> 0 | F35: =D35+E35 -> 0 | G35: =IF(Scenarios!D8=1, IF(Scenarios!I8="lease", INDEX(Calc!B4:F4,1,4)*INDEX(Calc!B8:F8,1,4), INDEX(Calc!B4:F4,1,4)*INDEX(Calc!B9:F9,1,4)), INDEX(Calc!B4:F4,1,4)) -> 845593.08 | H35: =IF(Scenarios!E8=1, IF(Scenarios!I8="lease", INDEX(Calc!B5:F5,1,4)*INDEX(Calc!B8:F8,1,4), INDEX(Calc!B5:F5,1,4)*INDEX(Calc!B9:F9,1,4)), INDEX(Calc!B5:F5,1,4)) -> 973912.66 | I35: =INDEX(Calc!B3:F3,1,4) -> 7677.2394 | J35: =IF("FY2029"="FY2026", (IF(Scenarios!D8=1, Parameters!B9,0) + IF(Scenarios!E8=1, Parameters!B9,0)), 0) -> 0 | K35: =1-Parameters!B4 -> 0.7 | L35: =Scenarios!G8 -> 0 | N35: =IF(F35>0, L35/F35, NA()) -> #N/A
A36: =Scenarios!A8 -> D_Grow_Both_0 | B36: FY2030 | C36: =Scenarios!C8 -> 0 | F36: =D36+E36 -> 0 | G36: =IF(Scenarios!D8=1, IF(Scenarios!I8="lease", INDEX(Calc!B4:F4,1,5)*INDEX(Calc!B8:F8,1,5), INDEX(Calc!B4:F4,1,5)*INDEX(Calc!B9:F9,1,5)), INDEX(Calc!B4:F4,1,5)) -> 866732.91 | H36: =IF(Scenarios!E8=1, IF(Scenarios!I8="lease", INDEX(Calc!B5:F5,1,5)*INDEX(Calc!B8:F8,1,5), INDEX(Calc!B5:F5,1,5)*INDEX(Calc!B9:F9,1,5)), INDEX(Calc!B5:F5,1,5)) -> 998260.47 | I36: =INDEX(Calc!B3:F3,1,5) -> 7869.1704 | J36: =IF("FY2030"="FY2026", (IF(Scenarios!D8=1, Parameters!B9,0) + IF(Scenarios!E8=1, Parameters!B9,0)), 0) -> 0 | K36: =1-Parameters!B4 -> 0.7 | L36: =Scenarios!G8 -> 0 | N36: =IF(F36>0, L36/F36, NA()) -> #N/A
A37: =Scenarios!A9 -> D_Grow_Both_100 | B37: FY2026 | C37: =Scenarios!C9 -> 100 | F37: =D37+E37 -> 0 | G37: =IF(Scenarios!D9=1, IF(Scenarios!I9="lease", INDEX(Calc!B4:F4,1,1)*INDEX(Calc!B8:F8,1,1), INDEX(Calc!B4:F4,1,1)*INDEX(Calc!B9:F9,1,1)), INDEX(Calc!B4:F4,1,1)) -> 785217.24 | H37: =IF(Scenarios!E9=1, IF(Scenarios!I9="lease", INDEX(Calc!B5:F5,1,1)*INDEX(Calc!B8:F8,1,1), INDEX(Calc!B5:F5,1,1)*INDEX(Calc!B9:F9,1,1)), INDEX(Calc!B5:F5,1,1)) -> 904374.72 | I37: =INDEX(Calc!B3:F3,1,1) -> 7129.08 | J37: =IF("FY2026"="FY2026", (IF(Scenarios!D9=1, Parameters!B9,0) + IF(Scenarios!E9=1, Parameters!B9,0)), 0) -> 0 | K37: =1-Parameters!B4 -> 0.7 | L37: =Scenarios!G9 -> 0 | N37: =IF(F37>0, L37/F37, NA()) -> #N/A
A38: =Scenarios!A9 -> D_Grow_Both_100 | B38: FY2027 | C38: =Scenarios!C9 -> 100 | F38: =D38+E38 -> 0 | G38: =IF(Scenarios!D9=1, IF(Scenarios!I9="lease", INDEX(Calc!B4:F4,1,2)*INDEX(Calc!B8:F8,1,2), INDEX(Calc!B4:F4,1,2)*INDEX(Calc!B9:F9,1,2)), INDEX(Calc!B4:F4,1,2)) -> 804847.67 | H38: =IF(Scenarios!E9=1, IF(Scenarios!I9="lease", INDEX(Calc!B5:F5,1,2)*INDEX(Calc!B8:F8,1,2), INDEX(Calc!B5:F5,1,2)*INDEX(Calc!B9:F9,1,2)), INDEX(Calc!B5:F5,1,2)) -> 926984.09 | I38: =INDEX(Calc!B3:F3,1,2) -> 7307.307 | J38: =IF("FY2027"="FY2026", (IF(Scenarios!D9=1, Parameters!B9,0) + IF(Scenarios!E9=1, Parameters!B9,0)), 0) -> 0 | K38: =1-Parameters!B4 -> 0.7 | L38: =Scenarios!G9 -> 0 | N38: =IF(F38>0, L38/F38, NA()) -> #N/A
A39: =Scenarios!A9 -> D_Grow_Both_100 | B39: FY2028 | C39: =Scenarios!C9 -> 100 | F39: =D39+E39 -> 0 | G39: =IF(Scenarios!D9=1, IF(Scenarios!I9="lease", INDEX(Calc!B4:F4,1,3)*INDEX(Calc!B8:F8,1,3), INDEX(Calc!B4:F4,1,3)*INDEX(Calc!B9:F9,1,3)), INDEX(Calc!B4:F4,1,3)) -> 824968.86 | H39: =IF(Scenarios!E9=1, IF(Scenarios!I9="lease", INDEX(Calc!B5:F5,1,3)*INDEX(Calc!B8:F8,1,3), INDEX(Calc!B5:F5,1,3)*INDEX(Calc!B9:F9,1,3)), INDEX(Calc!B5:F5,1,3)) -> 950158.69 | I39: =INDEX(Calc!B3:F3,1,3) -> 7489.9897 | J39: =IF("FY2028"="FY2026", (IF(Scenarios!D9=1, Parameters!B9,0) + IF(Scenarios!E9=1, Parameters!B9,0)), 0) -> 0 | K39: =1-Parameters!B4 -> 0.7 | L39: =Scenarios!G9 -> 0 | N39: =IF(F39>0, L39/F39, NA()) -> #N/A
A40: =Scenarios!A9 -> D_Grow_Both_100 | B40: FY2029 | C40: =Scenarios!C9 -> 100 | F40: =D40+E40 -> 0 | G40: =IF(Scenarios!D9=1, IF(Scenarios!I9="lease", INDEX(Calc!B4:F4,1,4)*INDEX(Calc!B8:F8,1,4), INDEX(Calc!B4:F4,1,4)*INDEX(Calc!B9:F9,1,4)), INDEX(Calc!B4:F4,1,4)) -> 845593.08 | H40: =IF(Scenarios!E9=1, IF(Scenarios!I9="lease", INDEX(Calc!B5:F5,1,4)*INDEX(Calc!B8:F8,1,4), INDEX(Calc!B5:F5,1,4)*INDEX(Calc!B9:F9,1,4)), INDEX(Calc!B5:F5,1,4)) -> 973912.66 | I40: =INDEX(Calc!B3:F3,1,4) -> 7677.2394 | J40: =IF("FY2029"="FY2026", (IF(Scenarios!D9=1, Parameters!B9,0) + IF(Scenarios!E9=1, Parameters!B9,0)), 0) -> 0 | K40: =1-Parameters!B4 -> 0.7 | L40: =Scenarios!G9 -> 0 | N40: =IF(F40>0, L40/F40, NA()) -> #N/A
A41: =Scenarios!A9 -> D_Grow_Both_100 | B41: FY2030 | C41: =Scenarios!C9 -> 100 | F41: =D41+E41 -> 0 | G41: =IF(Scenarios!D9=1, IF(Scenarios!I9="lease", INDEX(Calc!B4:F4,1,5)*INDEX(Calc!B8:F8,1,5), INDEX(Calc!B4:F4,1,5)*INDEX(Calc!B9:F9,1,5)), INDEX(Calc!B4:F4,1,5)) -> 866732.91 | H41: =IF(Scenarios!E9=1, IF(Scenarios!I9="lease", INDEX(Calc!B5:F5,1,5)*INDEX(Calc!B8:F8,1,5), INDEX(Calc!B5:F5,1,5)*INDEX(Calc!B9:F9,1,5)), INDEX(Calc!B5:F5,1,5)) -> 998260.47 | I41: =INDEX(Calc!B3:F3,1,5) -> 7869.1704 | J41: =IF("FY2030"="FY2026", (IF(Scenarios!D9=1, Parameters!B9,0) + IF(Scenarios!E9=1, Parameters!B9,0)), 0) -> 0 | K41: =1-Parameters!B4 -> 0.7 | L41: =Scenarios!G9 -> 0 | N41: =IF(F41>0, L41/F41, NA()) -> #N/A
A42: =Scenarios!A10 -> D_Grow_Both_150 | B42: FY2026 | C42: =Scenarios!C10 -> 150 | F42: =D42+E42 -> 0 | G42: =IF(Scenarios!D10=1, IF(Scenarios!I10="lease", INDEX(Calc!B4:F4,1,1)*INDEX(Calc!B8:F8,1,1), INDEX(Calc!B4:F4,1,1)*INDEX(Calc!B9:F9,1,1)), INDEX(Calc!B4:F4,1,1)) -> 785217.24 | H42: =IF(Scenarios!E10=1, IF(Scenarios!I10="lease", INDEX(Calc!B5:F5,1,1)*INDEX(Calc!B8:F8,1,1), INDEX(Calc!B5:F5,1,1)*INDEX(Calc!B9:F9,1,1)), INDEX(Calc!B5:F5,1,1)) -> 904374.72 | I42: =INDEX(Calc!B3:F3,1,1) -> 7129.08 | J42: =IF("FY2026"="FY2026", (IF(Scenarios!D10=1, Parameters!B9,0) + IF(Scenarios!E10=1, Parameters!B9,0)), 0) -> 0 | K42: =1-Parameters!B4 -> 0.7 | L42: =Scenarios!G10 -> 0 | N42: =IF(F42>0, L42/F42, NA()) -> #N/A
A43: =Scenarios!A10 -> D_Grow_Both_150 | B43: FY2027 | C43: =Scenarios!C10 -> 150 | F43: =D43+E43 -> 0 | G43: =IF(Scenarios!D10=1, IF(Scenarios!I10="lease", INDEX(Calc!B4:F4,1,2)*INDEX(Calc!B8:F8,1,2), INDEX(Calc!B4:F4,1,2)*INDEX(Calc!B9:F9,1,2)), INDEX(Calc!B4:F4,1,2)) -> 804847.67 | H43: =IF(Scenarios!E10=1, IF(Scenarios!I10="lease", INDEX(Calc!B5:F5,1,2)*INDEX(Calc!B8:F8,1,2), INDEX(Calc!B5:F5,1,2)*INDEX(Calc!B9:F9,1,2)), INDEX(Calc!B5:F5,1,2)) -> 926984.09 | I43: =INDEX(Calc!B3:F3,1,2) -> 7307.307 | J43: =IF("FY2027"="FY2026", (IF(Scenarios!D10=1, Parameters!B9,0) + IF(Scenarios!E10=1, Parameters!B9,0)), 0) -> 0 | K43: =1-Parameters!B4 -> 0.7 | L43: =Scenarios!G10 -> 0 | N43: =IF(F43>0, L43/F43, NA()) -> #N/A
A44: =Scenarios!A10 -> D_Grow_Both_150 | B44: FY2028 | C44: =Scenarios!C10 -> 150 | F44: =D44+E44 -> 0 | G44: =IF(Scenarios!D10=1, IF(Scenarios!I10="lease", INDEX(Calc!B4:F4,1,3)*INDEX(Calc!B8:F8,1,3), INDEX(Calc!B4:F4,1,3)*INDEX(Calc!B9:F9,1,3)), INDEX(Calc!B4:F4,1,3)) -> 824968.86 | H44: =IF(Scenarios!E10=1, IF(Scenarios!I10="lease", INDEX(Calc!B5:F5,1,3)*INDEX(Calc!B8:F8,1,3), INDEX(Calc!B5:F5,1,3)*INDEX(Calc!B9:F9,1,3)), INDEX(Calc!B5:F5,1,3)) -> 950158.69 | I44: =INDEX(Calc!B3:F3,1,3) -> 7489.9897 | J44: =IF("FY2028"="FY2026", (IF(Scenarios!D10=1, Parameters!B9,0) + IF(Scenarios!E10=1, Parameters!B9,0)), 0) -> 0 | K44: =1-Parameters!B4 -> 0.7 | L44: =Scenarios!G10 -> 0 | N44: =IF(F44>0, L44/F44, NA()) -> #N/A
A45: =Scenarios!A10 -> D_Grow_Both_150 | B45: FY2029 | C45: =Scenarios!C10 -> 150 | F45: =D45+E45 -> 0 | G45: =IF(Scenarios!D10=1, IF(Scenarios!I10="lease", INDEX(Calc!B4:F4,1,4)*INDEX(Calc!B8:F8,1,4), INDEX(Calc!B4:F4,1,4)*INDEX(Calc!B9:F9,1,4)), INDEX(Calc!B4:F4,1,4)) -> 845593.08 | H45: =IF(Scenarios!E10=1, IF(Scenarios!I10="lease", INDEX(Calc!B5:F5,1,4)*INDEX(Calc!B8:F8,1,4), INDEX(Calc!B5:F5,1,4)*INDEX(Calc!B9:F9,1,4)), INDEX(Calc!B5:F5,1,4)) -> 973912.66 | I45: =INDEX(Calc!B3:F3,1,4) -> 7677.2394 | J45: =IF("FY2029"="FY2026", (IF(Scenarios!D10=1, Parameters!B9,0) + IF(Scenarios!E10=1, Parameters!B9,0)), 0) -> 0 | K45: =1-Parameters!B4 -> 0.7 | L45: =Scenarios!G10 -> 0 | N45: =IF(F45>0, L45/F45, NA()) -> #N/A
A46: =Scenarios!A10 -> D_Grow_Both_150 | B46: FY2030 | C46: =Scenarios!C10 -> 150 | F46: =D46+E46 -> 0 | G46: =IF(Scenarios!D10=1, IF(Scenarios!I10="lease", INDEX(Calc!B4:F4,1,5)*INDEX(Calc!B8:F8,1,5), INDEX(Calc!B4:F4,1,5)*INDEX(Calc!B9:F9,1,5)), INDEX(Calc!B4:F4,1,5)) -> 866732.91 | H46: =IF(Scenarios!E10=1, IF(Scenarios!I10="lease", INDEX(Calc!B5:F5,1,5)*INDEX(Calc!B8:F8,1,5), INDEX(Calc!B5:F5,1,5)*INDEX(Calc!B9:F9,1,5)), INDEX(Calc!B5:F5,1,5)) -> 998260.47 | I46: =INDEX(Calc!B3:F3,1,5) -> 7869.1704 | J46: =IF("FY2030"="FY2026", (IF(Scenarios!D10=1, Parameters!B9,0) + IF(Scenarios!E10=1, Parameters!B9,0)), 0) -> 0 | K46: =1-Parameters!B4 -> 0.7 | L46: =Scenarios!G10 -> 0 | N46: =IF(F46>0, L46/F46, NA()) -> #N/A
A47: =Scenarios!A11 -> E_StatusQuo_Targets_0 | B47: FY2026 | C47: =Scenarios!C11 -> 0 | F47: =D47+E47 -> 0 | G47: =IF(Scenarios!D11=1, IF(Scenarios!I11="lease", INDEX(Calc!B4:F4,1,1)*INDEX(Calc!B8:F8,1,1), INDEX(Calc!B4:F4,1,1)*INDEX(Calc!B9:F9,1,1)), INDEX(Calc!B4:F4,1,1)) -> 785217.24 | H47: =IF(Scenarios!E11=1, IF(Scenarios!I11="lease", INDEX(Calc!B5:F5,1,1)*INDEX(Calc!B8:F8,1,1), INDEX(Calc!B5:F5,1,1)*INDEX(Calc!B9:F9,1,1)), INDEX(Calc!B5:F5,1,1)) -> 904374.72 | I47: =INDEX(Calc!B3:F3,1,1) -> 7129.08 | J47: =IF("FY2026"="FY2026", (IF(Scenarios!D11=1, Parameters!B9,0) + IF(Scenarios!E11=1, Parameters!B9,0)), 0) -> 0 | K47: =1-Parameters!B4 -> 0.7 | L47: =Scenarios!G11 -> 0 | N47: =IF(F47>0, L47/F47, NA()) -> #N/A
A48: =Scenarios!A11 -> E_StatusQuo_Targets_0 | B48: FY2027 | C48: =Scenarios!C11 -> 0 | F48: =D48+E48 -> 0 | G48: =IF(Scenarios!D11=1, IF(Scenarios!I11="lease", INDEX(Calc!B4:F4,1,2)*INDEX(Calc!B8:F8,1,2), INDEX(Calc!B4:F4,1,2)*INDEX(Calc!B9:F9,1,2)), INDEX(Calc!B4:F4,1,2)) -> 804847.67 | H48: =IF(Scenarios!E11=1, IF(Scenarios!I11="lease", INDEX(Calc!B5:F5,1,2)*INDEX(Calc!B8:F8,1,2), INDEX(Calc!B5:F5,1,2)*INDEX(Calc!B9:F9,1,2)), INDEX(Calc!B5:F5,1,2)) -> 926984.09 | I48: =INDEX(Calc!B3:F3,1,2) -> 7307.307 | J48: =IF("FY2027"="FY2026", (IF(Scenarios!D11=1, Parameters!B9,0) + IF(Scenarios!E11=1, Parameters!B9,0)), 0) -> 0 | K48: =1-Parameters!B4 -> 0.7 | L48: =Scenarios!G11 -> 0 | N48: =IF(F48>0, L48/F48, NA()) -> #N/A
A49: =Scenarios!A11 -> E_StatusQuo_Targets_0 | B49: FY2028 | C49: =Scenarios!C11 -> 0 | F49: =D49+E49 -> 0 | G49: =IF(Scenarios!D11=1, IF(Scenarios!I11="lease", INDEX(Calc!B4:F4,1,3)*INDEX(Calc!B8:F8,1,3), INDEX(Calc!B4:F4,1,3)*INDEX(Calc!B9:F9,1,3)), INDEX(Calc!B4:F4,1,3)) -> 824968.86 | H49: =IF(Scenarios!E11=1, IF(Scenarios!I11="lease", INDEX(Calc!B5:F5,1,3)*INDEX(Calc!B8:F8,1,3), INDEX(Calc!B5:F5,1,3)*INDEX(Calc!B9:F9,1,3)), INDEX(Calc!B5:F5,1,3)) -> 950158.69 | I49: =INDEX(Calc!B3:F3,1,3) -> 7489.9897 | J49: =IF("FY2028"="FY2026", (IF(Scenarios!D11=1, Parameters!B9,0) + IF(Scenarios!E11=1, Parameters!B9,0)), 0) -> 0 | K49: =1-Parameters!B4 -> 0.7 | L49: =Scenarios!G11 -> 0 | N49: =IF(F49>0, L49/F49, NA()) -> #N/A
A50: =Scenarios!A11 -> E_StatusQuo_Targets_0 | B50: FY2029 | C50: =Scenarios!C11 -> 0 | F50: =D50+E50 -> 0 | G50: =IF(Scenarios!D11=1, IF(Scenarios!I11="lease", INDEX(Calc!B4:F4,1,4)*INDEX(Calc!B8:F8,1,4), INDEX(Calc!B4:F4,1,4)*INDEX(Calc!B9:F9,1,4)), INDEX(Calc!B4:F4,1,4)) -> 845593.08 | H50: =IF(Scenarios!E11=1, IF(Scenarios!I11="lease", INDEX(Calc!B5:F5,1,4)*INDEX(Calc!B8:F8,1,4), INDEX(Calc!B5:F5,1,4)*INDEX(Calc!B9:F9,1,4)), INDEX(Calc!B5:F5,1,4)) -> 973912.66 | I50: =INDEX(Calc!B3:F3,1,4) -> 7677.2394 | J50: =IF("FY2029"="FY2026", (IF(Scenarios!D11=1, Parameters!B9,0) + IF(Scenarios!E11=1, Parameters!B9,0)), 0) -> 0 | K50: =1-Parameters!B4 -> 0.7 | L50: =Scenarios!G11 -> 0 | N50: =IF(F50>0, L50/F50, NA()) -> #N/A
A51: =Scenarios!A11 -> E_StatusQuo_Targets_0 | B51: FY2030 | C51: =Scenarios!C11 -> 0 | F51: =D51+E51 -> 0 | G51: =IF(Scenarios!D11=1, IF(Scenarios!I11="lease", INDEX(Calc!B4:F4,1,5)*INDEX(Calc!B8:F8,1,5), INDEX(Calc!B4:F4,1,5)*INDEX(Calc!B9:F9,1,5)), INDEX(Calc!B4:F4,1,5)) -> 866732.91 | H51: =IF(Scenarios!E11=1, IF(Scenarios!I11="lease", INDEX(Calc!B5:F5,1,5)*INDEX(Calc!B8:F8,1,5), INDEX(Calc!B5:F5,1,5)*INDEX(Calc!B9:F9,1,5)), INDEX(Calc!B5:F5,1,5)) -> 998260.47 | I51: =INDEX(Calc!B3:F3,1,5) -> 7869.1704 | J51: =IF("FY2030"="FY2026", (IF(Scenarios!D11=1, Parameters!B9,0) + IF(Scenarios!E11=1, Parameters!B9,0)), 0) -> 0 | K51: =1-Parameters!B4 -> 0.7 | L51: =Scenarios!G11 -> 0 | N51: =IF(F51>0, L51/F51, NA()) -> #N/A
A52: =Scenarios!A12 -> E_StatusQuo_Targets_100 | B52: FY2026 | C52: =Scenarios!C12 -> 100 | F52: =D52+E52 -> 0 | G52: =IF(Scenarios!D12=1, IF(Scenarios!I12="lease", INDEX(Calc!B4:F4,1,1)*INDEX(Calc!B8:F8,1,1), INDEX(Calc!B4:F4,1,1)*INDEX(Calc!B9:F9,1,1)), INDEX(Calc!B4:F4,1,1)) -> 785217.24 | H52: =IF(Scenarios!E12=1, IF(Scenarios!I12="lease", INDEX(Calc!B5:F5,1,1)*INDEX(Calc!B8:F8,1,1), INDEX(Calc!B5:F5,1,1)*INDEX(Calc!B9:F9,1,1)), INDEX(Calc!B5:F5,1,1)) -> 904374.72 | I52: =INDEX(Calc!B3:F3,1,1) -> 7129.08 | J52: =IF("FY2026"="FY2026", (IF(Scenarios!D12=1, Parameters!B9,0) + IF(Scenarios!E12=1, Parameters!B9,0)), 0) -> 0 | K52: =1-Parameters!B4 -> 0.7 | L52: =Scenarios!G12 -> 0 | N52: =IF(F52>0, L52/F52, NA()) -> #N/A
A53: =Scenarios!A12 -> E_StatusQuo_Targets_100 | B53: FY2027 | C53: =Scenarios!C12 -> 100 | F53: =D53+E53 -> 0 | G53: =IF(Scenarios!D12=1, IF(Scenarios!I12="lease", INDEX(Calc!B4:F4,1,2)*INDEX(Calc!B8:F8,1,2), INDEX(Calc!B4:F4,1,2)*INDEX(Calc!B9:F9,1,2)), INDEX(Calc!B4:F4,1,2)) -> 804847.67 | H53: =IF(Scenarios!E12=1, IF(Scenarios!I12="lease", INDEX(Calc!B5:F5,1,2)*INDEX(Calc!B8:F8,1,2), INDEX(Calc!B5:F5,1,2)*INDEX(Calc!B9:F9,1,2)), INDEX(Calc!B5:F5,1,2)) -> 926984.09 | I53: =INDEX(Calc!B3:F3,1,2) -> 7307.307 | J53: =IF("FY2027"="FY2026", (IF(Scenarios!D12=1, Parameters!B9,0) + IF(Scenarios!E12=1, Parameters!B9,0)), 0) -> 0 | K53: =1-Parameters!B4 -> 0.7 | L53: =Scenarios!G12 -> 0 | N53: =IF(F53>0, L53/F53, NA()) -> #N/A
A54: =Scenarios!A12 -> E_StatusQuo_Targets_100 | B54: FY2028 | C54: =Scenarios!C12 -> 100 | F54: =D54+E54 -> 0 | G54: =IF(Scenarios!D12=1, IF(Scenarios!I12="lease", INDEX(Calc!B4:F4,1,3)*INDEX(Calc!B8:F8,1,3), INDEX(Calc!B4:F4,1,3)*INDEX(Calc!B9:F9,1,3)), INDEX(Calc!B4:F4,1,3)) -> 824968.86 | H54: =IF(Scenarios!E12=1, IF(Scenarios!I12="lease", INDEX(Calc!B5:F5,1,3)*INDEX(Calc!B8:F8,1,3), INDEX(Calc!B5:F5,1,3)*INDEX(Calc!B9:F9,1,3)), INDEX(Calc!B5:F5,1,3)) -> 950158.69 | I54: =INDEX(Calc!B3:F3,1,3) -> 7489.9897 | J54: =IF("FY2028"="FY2026", (IF(Scenarios!D12=1, Parameters!B9,0) + IF(Scenarios!E12=1, Parameters!B9,0)), 0) -> 0 | K54: =1-Parameters!B4 -> 0.7 | L54: =Scenarios!G12 -> 0 | N54: =IF(F54>0, L54/F54, NA()) -> #N/A
A55: =Scenarios!A12 -> E_StatusQuo_Targets_100 | B55: FY2029 | C55: =Scenarios!C12 -> 100 | F55: =D55+E55 -> 0 | G55: =IF(Scenarios!D12=1, IF(Scenarios!I12="lease", INDEX(Calc!B4:F4,1,4)*INDEX(Calc!B8:F8,1,4), INDEX(Calc!B4:F4,1,4)*INDEX(Calc!B9:F9,1,4)), INDEX(Calc!B4:F4,1,4)) -> 845593.08 | H55: =IF(Scenarios!E12=1, IF(Scenarios!I12="lease", INDEX(Calc!B5:F5,1,4)*INDEX(Calc!B8:F8,1,4), INDEX(Calc!B5:F5,1,4)*INDEX(Calc!B9:F9,1,4)), INDEX(Calc!B5:F5,1,4)) -> 973912.66 | I55: =INDEX(Calc!B3:F3,1,4) -> 7677.2394 | J55: =IF("FY2029"="FY2026", (IF(Scenarios!D12=1, Parameters!B9,0) + IF(Scenarios!E12=1, Parameters!B9,0)), 0) -> 0 | K55: =1-Parameters!B4 -> 0.7 | L55: =Scenarios!G12 -> 0 | N55: =IF(F55>0, L55/F55, NA()) -> #N/A
A56: =Scenarios!A12 -> E_StatusQuo_Targets_100 | B56: FY2030 | C56: =Scenarios!C12 -> 100 | F56: =D56+E56 -> 0 | G56: =IF(Scenarios!D12=1, IF(Scenarios!I12="lease", INDEX(Calc!B4:F4,1,5)*INDEX(Calc!B8:F8,1,5), INDEX(Calc!B4:F4,1,5)*INDEX(Calc!B9:F9,1,5)), INDEX(Calc!B4:F4,1,5)) -> 866732.91 | H56: =IF(Scenarios!E12=1, IF(Scenarios!I12="lease", INDEX(Calc!B5:F5,1,5)*INDEX(Calc!B8:F8,1,5), INDEX(Calc!B5:F5,1,5)*INDEX(Calc!B9:F9,1,5)), INDEX(Calc!B5:F5,1,5)) -> 998260.47 | I56: =INDEX(Calc!B3:F3,1,5) -> 7869.1704 | J56: =IF("FY2030"="FY2026", (IF(Scenarios!D12=1, Parameters!B9,0) + IF(Scenarios!E12=1, Parameters!B9,0)), 0) -> 0 | K56: =1-Parameters!B4 -> 0.7 | L56: =Scenarios!G12 -> 0 | N56: =IF(F56>0, L56/F56, NA()) -> #N/A
A57: =Scenarios!A13 -> E_StatusQuo_Targets_150 | B57: FY2026 | C57: =Scenarios!C13 -> 150 | F57: =D57+E57 -> 0 | G57: =IF(Scenarios!D13=1, IF(Scenarios!I13="lease", INDEX(Calc!B4:F4,1,1)*INDEX(Calc!B8:F8,1,1), INDEX(Calc!B4:F4,1,1)*INDEX(Calc!B9:F9,1,1)), INDEX(Calc!B4:F4,1,1)) -> 785217.24 | H57: =IF(Scenarios!E13=1, IF(Scenarios!I13="lease", INDEX(Calc!B5:F5,1,1)*INDEX(Calc!B8:F8,1,1), INDEX(Calc!B5:F5,1,1)*INDEX(Calc!B9:F9,1,1)), INDEX(Calc!B5:F5,1,1)) -> 904374.72 | I57: =INDEX(Calc!B3:F3,1,1) -> 7129.08 | J57: =IF("FY2026"="FY2026", (IF(Scenarios!D13=1, Parameters!B9,0) + IF(Scenarios!E13=1, Parameters!B9,0)), 0) -> 0 | K57: =1-Parameters!B4 -> 0.7 | L57: =Scenarios!G13 -> 0 | N57: =IF(F57>0, L57/F57, NA()) -> #N/A
A58: =Scenarios!A13 -> E_StatusQuo_Targets_150 | B58: FY2027 | C58: =Scenarios!C13 -> 150 | F58: =D58+E58 -> 0 | G58: =IF(Scenarios!D13=1, IF(Scenarios!I13="lease", INDEX(Calc!B4:F4,1,2)*INDEX(Calc!B8:F8,1,2), INDEX(Calc!B4:F4,1,2)*INDEX(Calc!B9:F9,1,2)), INDEX(Calc!B4:F4,1,2)) -> 804847.67 | H58: =IF(Scenarios!E13=1, IF(Scenarios!I13="lease", INDEX(Calc!B5:F5,1,2)*INDEX(Calc!B8:F8,1,2), INDEX(Calc!B5:F5,1,2)*INDEX(Calc!B9:F9,1,2)), INDEX(Calc!B5:F5,1,2)) -> 926984.09 | I58: =INDEX(Calc!B3:F3,1,2) -> 7307.307 | J58: =IF("FY2027"="FY2026", (IF(Scenarios!D13=1, Parameters!B9,0) + IF(Scenarios!E13=1, Parameters!B9,0)), 0) -> 0 | K58: =1-Parameters!B4 -> 0.7 | L58: =Scenarios!G13 -> 0 | N58: =IF(F58>0, L58/F58, NA()) -> #N/A
A59: =Scenarios!A13 -> E_StatusQuo_Targets_150 | B59: FY2028 | C59: =Scenarios!C13 -> 150 | F59: =D59+E59 -> 0 | G59: =IF(Scenarios!D13=1, IF(Scenarios!I13="lease", INDEX(Calc!B4:F4,1,3)*INDEX(Calc!B8:F8,1,3), INDEX(Calc!B4:F4,1,3)*INDEX(Calc!B9:F9,1,3)), INDEX(Calc!B4:F4,1,3)) -> 824968.86 | H59: =IF(Scenarios!E13=1, IF(Scenarios!I13="lease", INDEX(Calc!B5:F5,1,3)*INDEX(Calc!B8:F8,1,3), INDEX(Calc!B5:F5,1,3)*INDEX(Calc!B9:F9,1,3)), INDEX(Calc!B5:F5,1,3)) -> 950158.69 | I59: =INDEX(Calc!B3:F3,1,3) -> 7489.9897 | J59: =IF("FY2028"="FY2026", (IF(Scenarios!D13=1, Parameters!B9,0) + IF(Scenarios!E13=1, Parameters!B9,0)), 0) -> 0 | K59: =1-Parameters!B4 -> 0.7 | L59: =Scenarios!G13 -> 0 | N59: =IF(F59>0, L59/F59, NA()) -> #N/A
A60: =Scenarios!A13 -> E_StatusQuo_Targets_150 | B60: FY2029 | C60: =Scenarios!C13 -> 150 | F60: =D60+E60 -> 0 | G60: =IF(Scenarios!D13=1, IF(Scenarios!I13="lease", INDEX(Calc!B4:F4,1,4)*INDEX(Calc!B8:F8,1,4), INDEX(Calc!B4:F4,1,4)*INDEX(Calc!B9:F9,1,4)), INDEX(Calc!B4:F4,1,4)) -> 845593.08 | H60: =IF(Scenarios!E13=1, IF(Scenarios!I13="lease", INDEX(Calc!B5:F5,1,4)*INDEX(Calc!B8:F8,1,4), INDEX(Calc!B5:F5,1,4)*INDEX(Calc!B9:F9,1,4)), INDEX(Calc!B5:F5,1,4)) -> 973912.66 | I60: =INDEX(Calc!B3:F3,1,4) -> 7677.2394 | J60: =IF("FY2029"="FY2026", (IF(Scenarios!D13=1, Parameters!B9,0) + IF(Scenarios!E13=1, Parameters!B9,0)), 0) -> 0 | K60: =1-Parameters!B4 -> 0.7 | L60: =Scenarios!G13 -> 0 | N60: =IF(F60>0, L60/F60, NA()) -> #N/A
A61: =Scenarios!A13 -> E_StatusQuo_Targets_150 | B61: FY2030 | C61: =Scenarios!C13 -> 150 | F61: =D61+E61 -> 0 | G61: =IF(Scenarios!D13=1, IF(Scenarios!I13="lease", INDEX(Calc!B4:F4,1,5)*INDEX(Calc!B8:F8,1,5), INDEX(Calc!B4:F4,1,5)*INDEX(Calc!B9:F9,1,5)), INDEX(Calc!B4:F4,1,5)) -> 866732.91 | H61: =IF(Scenarios!E13=1, IF(Scenarios!I13="lease", INDEX(Calc!B5:F5,1,5)*INDEX(Calc!B8:F8,1,5), INDEX(Calc!B5:F5,1,5)*INDEX(Calc!B9:F9,1,5)), INDEX(Calc!B5:F5,1,5)) -> 998260.47 | I61: =INDEX(Calc!B3:F3,1,5) -> 7869.1704 | J61: =IF("FY2030"="FY2026", (IF(Scenarios!D13=1, Parameters!B9,0) + IF(Scenarios!E13=1, Parameters!B9,0)), 0) -> 0 | K61: =1-Parameters!B4 -> 0.7 | L61: =Scenarios!G13 -> 0 | N61: =IF(F61>0, L61/F61, NA()) -> #N/A
A62: =Scenarios!A14 -> F_CoLocation_Echo_0 | B62: FY2026 | C62: =Scenarios!C14 -> 0 | F62: =D62+E62 -> 0 | G62: =IF(Scenarios!D14=1, IF(Scenarios!I14="lease", INDEX(Calc!B4:F4,1,1)*INDEX(Calc!B8:F8,1,1), INDEX(Calc!B4:F4,1,1)*INDEX(Calc!B9:F9,1,1)), INDEX(Calc!B4:F4,1,1)) -> 785217.24 | H62: =IF(Scenarios!E14=1, IF(Scenarios!I14="lease", INDEX(Calc!B5:F5,1,1)*INDEX(Calc!B8:F8,1,1), INDEX(Calc!B5:F5,1,1)*INDEX(Calc!B9:F9,1,1)), INDEX(Calc!B5:F5,1,1)) -> 904374.72 | I62: =INDEX(Calc!B3:F3,1,1) -> 7129.08 | J62: =IF("FY2026"="FY2026", (IF(Scenarios!D14=1, Parameters!B9,0) + IF(Scenarios!E14=1, Parameters!B9,0)), 0) -> 0 | K62: =1-Parameters!B4 -> 0.7 | L62: =Scenarios!G14 -> 0.015 | N62: =IF(F62>0, L62/F62, NA()) -> #N/A
A63: =Scenarios!A14 -> F_CoLocation_Echo_0 | B63: FY2027 | C63: =Scenarios!C14 -> 0 | F63: =D63+E63 -> 0 | G63: =IF(Scenarios!D14=1, IF(Scenarios!I14="lease", INDEX(Calc!B4:F4,1,2)*INDEX(Calc!B8:F8,1,2), INDEX(Calc!B4:F4,1,2)*INDEX(Calc!B9:F9,1,2)), INDEX(Calc!B4:F4,1,2)) -> 804847.67 | H63: =IF(Scenarios!E14=1, IF(Scenarios!I14="lease", INDEX(Calc!B5:F5,1,2)*INDEX(Calc!B8:F8,1,2), INDEX(Calc!B5:F5,1,2)*INDEX(Calc!B9:F9,1,2)), INDEX(Calc!B5:F5,1,2)) -> 926984.09 | I63: =INDEX(Calc!B3:F3,1,2) -> 7307.307 | J63: =IF("FY2027"="FY2026", (IF(Scenarios!D14=1, Parameters!B9,0) + IF(Scenarios!E14=1, Parameters!B9,0)), 0) -> 0 | K63: =1-Parameters!B4 -> 0.7 | L63: =Scenarios!G14 -> 0.015 | N63: =IF(F63>0, L63/F63, NA()) -> #N/A
A64: =Scenarios!A14 -> F_CoLocation_Echo_0 | B64: FY2028 | C64: =Scenarios!C14 -> 0 | F64: =D64+E64 -> 0 | G64: =IF(Scenarios!D14=1, IF(Scenarios!I14="lease", INDEX(Calc!B4:F4,1,3)*INDEX(Calc!B8:F8,1,3), INDEX(Calc!B4:F4,1,3)*INDEX(Calc!B9:F9,1,3)), INDEX(Calc!B4:F4,1,3)) -> 824968.86 | H64: =IF(Scenarios!E14=1, IF(Scenarios!I14="lease", INDEX(Calc!B5:F5,1,3)*INDEX(Calc!B8:F8,1,3), INDEX(Calc!B5:F5,1,3)*INDEX(Calc!B9:F9,1,3)), INDEX(Calc!B5:F5,1,3)) -> 950158.69 | I64: =INDEX(Calc!B3:F3,1,3) -> 7489.9897 | J64: =IF("FY2028"="FY2026", (IF(Scenarios!D14=1, Parameters!B9,0) + IF(Scenarios!E14=1, Parameters!B9,0)), 0) -> 0 | K64: =1-Parameters!B4 -> 0.7 | L64: =Scenarios!G14 -> 0.015 | N64: =IF(F64>0, L64/F64, NA()) -> #N/A
A65: =Scenarios!A14 -> F_CoLocation_Echo_0 | B65: FY2029 | C65: =Scenarios!C14 -> 0 | F65: =D65+E65 -> 0 | G65: =IF(Scenarios!D14=1, IF(Scenarios!I14="lease", INDEX(Calc!B4:F4,1,4)*INDEX(Calc!B8:F8,1,4), INDEX(Calc!B4:F4,1,4)*INDEX(Calc!B9:F9,1,4)), INDEX(Calc!B4:F4,1,4)) -> 845593.08 | H65: =IF(Scenarios!E14=1, IF(Scenarios!I14="lease", INDEX(Calc!B5:F5,1,4)*INDEX(Calc!B8:F8,1,4), INDEX(Calc!B5:F5,1,4)*INDEX(Calc!B9:F9,1,4)), INDEX(Calc!B5:F5,1,4)) -> 973912.66 | I65: =INDEX(Calc!B3:F3,1,4) -> 7677.2394 | J65: =IF("FY2029"="FY2026", (IF(Scenarios!D14=1, Parameters!B9,0) + IF(Scenarios!E14=1, Parameters!B9,0)), 0) -> 0 | K65: =1-Parameters!B4 -> 0.7 | L65: =Scenarios!G14 -> 0.015 | N65: =IF(F65>0, L65/F65, NA()) -> #N/A
A66: =Scenarios!A14 -> F_CoLocation_Echo_0 | B66: FY2030 | C66: =Scenarios!C14 -> 0 | F66: =D66+E66 -> 0 | G66: =IF(Scenarios!D14=1, IF(Scenarios!I14="lease", INDEX(Calc!B4:F4,1,5)*INDEX(Calc!B8:F8,1,5), INDEX(Calc!B4:F4,1,5)*INDEX(Calc!B9:F9,1,5)), INDEX(Calc!B4:F4,1,5)) -> 866732.91 | H66: =IF(Scenarios!E14=1, IF(Scenarios!I14="lease", INDEX(Calc!B5:F5,1,5)*INDEX(Calc!B8:F8,1,5), INDEX(Calc!B5:F5,1,5)*INDEX(Calc!B9:F9,1,5)), INDEX(Calc!B5:F5,1,5)) -> 998260.47 | I66: =INDEX(Calc!B3:F3,1,5) -> 7869.1704 | J66: =IF("FY2030"="FY2026", (IF(Scenarios!D14=1, Parameters!B9,0) + IF(Scenarios!E14=1, Parameters!B9,0)), 0) -> 0 | K66: =1-Parameters!B4 -> 0.7 | L66: =Scenarios!G14 -> 0.015 | N66: =IF(F66>0, L66/F66, NA()) -> #N/A
A67: =Scenarios!A15 -> F_CoLocation_Echo_100 | B67: FY2026 | C67: =Scenarios!C15 -> 100 | F67: =D67+E67 -> 0 | G67: =IF(Scenarios!D15=1, IF(Scenarios!I15="lease", INDEX(Calc!B4:F4,1,1)*INDEX(Calc!B8:F8,1,1), INDEX(Calc!B4:F4,1,1)*INDEX(Calc!B9:F9,1,1)), INDEX(Calc!B4:F4,1,1)) -> 785217.24 | H67: =IF(Scenarios!E15=1, IF(Scenarios!I15="lease", INDEX(Calc!B5:F5,1,1)*INDEX(Calc!B8:F8,1,1), INDEX(Calc!B5:F5,1,1)*INDEX(Calc!B9:F9,1,1)), INDEX(Calc!B5:F5,1,1)) -> 904374.72 | I67: =INDEX(Calc!B3:F3,1,1) -> 7129.08 | J67: =IF("FY2026"="FY2026", (IF(Scenarios!D15=1, Parameters!B9,0) + IF(Scenarios!E15=1, Parameters!B9,0)), 0) -> 0 | K67: =1-Parameters!B4 -> 0.7 | L67: =Scenarios!G15 -> 0.015 | N67: =IF(F67>0, L67/F67, NA()) -> #N/A
A68: =Scenarios!A15 -> F_CoLocation_Echo_100 | B68: FY2027 | C68: =Scenarios!C15 -> 100 | F68: =D68+E68 -> 0 | G68: =IF(Scenarios!D15=1, IF(Scenarios!I15="lease", INDEX(Calc!B4:F4,1,2)*INDEX(Calc!B8:F8,1,2), INDEX(Calc!B4:F4,1,2)*INDEX(Calc!B9:F9,1,2)), INDEX(Calc!B4:F4,1,2)) -> 804847.67 | H68: =IF(Scenarios!E15=1, IF(Scenarios!I15="lease", INDEX(Calc!B5:F5,1,2)*INDEX(Calc!B8:F8,1,2), INDEX(Calc!B5:F5,1,2)*INDEX(Calc!B9:F9,1,2)), INDEX(Calc!B5:F5,1,2)) -> 926984.09 | I68: =INDEX(Calc!B3:F3,1,2) -> 7307.307 | J68: =IF("FY2027"="FY2026", (IF(Scenarios!D15=1, Parameters!B9,0) + IF(Scenarios!E15=1, Parameters!B9,0)), 0) -> 0 | K68: =1-Parameters!B4 -> 0.7 | L68: =Scenarios!G15 -> 0.015 | N68: =IF(F68>0, L68/F68, NA()) -> #N/A
A69: =Scenarios!A15 -> F_CoLocation_Echo_100 | B69: FY2028 | C69: =Scenarios!C15 -> 100 | F69: =D69+E69 -> 0 | G69: =IF(Scenarios!D15=1, IF(Scenarios!I15="lease", INDEX(Calc!B4:F4,1,3)*INDEX(Calc!B8:F8,1,3), INDEX(Calc!B4:F4,1,3)*INDEX(Calc!B9:F9,1,3)), INDEX(Calc!B4:F4,1,3)) -> 824968.86 | H69: =IF(Scenarios!E15=1, IF(Scenarios!I15="lease", INDEX(Calc!B5:F5,1,3)*INDEX(Calc!B8:F8,1,3), INDEX(Calc!B5:F5,1,3)*INDEX(Calc!B9:F9,1,3)), INDEX(Calc!B5:F5,1,3)) -> 950158.69 | I69: =INDEX(Calc!B3:F3,1,3) -> 7489.9897 | J69: =IF("FY2028"="FY2026", (IF(Scenarios!D15=1, Parameters!B9,0) + IF(Scenarios!E15=1, Parameters!B9,0)), 0) -> 0 | K69: =1-Parameters!B4 -> 0.7 | L69: =Scenarios!G15 -> 0.015 | N69: =IF(F69>0, L69/F69, NA()) -> #N/A
A70: =Scenarios!A15 -> F_CoLocation_Echo_100 | B70: FY2029 | C70: =Scenarios!C15 -> 100 | F70: =D70+E70 -> 0 | G70: =IF(Scenarios!D15=1, IF(Scenarios!I15="lease", INDEX(Calc!B4:F4,1,4)*INDEX(Calc!B8:F8,1,4), INDEX(Calc!B4:F4,1,4)*INDEX(Calc!B9:F9,1,4)), INDEX(Calc!B4:F4,1,4)) -> 845593.08 | H70: =IF(Scenarios!E15=1, IF(Scenarios!I15="lease", INDEX(Calc!B5:F5,1,4)*INDEX(Calc!B8:F8,1,4), INDEX(Calc!B5:F5,1,4)*INDEX(Calc!B9:F9,1,4)), INDEX(Calc!B5:F5,1,4)) -> 973912.66 | I70: =INDEX(Calc!B3:F3,1,4) -> 7677.2394 | J70: =IF("FY2029"="FY2026", (IF(Scenarios!D15=1, Parameters!B9,0) + IF(Scenarios!E15=1, Parameters!B9,0)), 0) -> 0 | K70: =1-Parameters!B4 -> 0.7 | L70: =Scenarios!G15 -> 0.015 | N70: =IF(F70>0, L70/F70, NA()) -> #N/A
A71: =Scenarios!A15 -> F_CoLocation_Echo_100 | B71: FY2030 | C71: =Scenarios!C15 -> 100 | F71: =D71+E71 -> 0 | G71: =IF(Scenarios!D15=1, IF(Scenarios!I15="lease", INDEX(Calc!B4:F4,1,5)*INDEX(Calc!B8:F8,1,5), INDEX(Calc!B4:F4,1,5)*INDEX(Calc!B9:F9,1,5)), INDEX(Calc!B4:F4,1,5)) -> 866732.91 | H71: =IF(Scenarios!E15=1, IF(Scenarios!I15="lease", INDEX(Calc!B5:F5,1,5)*INDEX(Calc!B8:F8,1,5), INDEX(Calc!B5:F5,1,5)*INDEX(Calc!B9:F9,1,5)), INDEX(Calc!B5:F5,1,5)) -> 998260.47 | I71: =INDEX(Calc!B3:F3,1,5) -> 7869.1704 | J71: =IF("FY2030"="FY2026", (IF(Scenarios!D15=1, Parameters!B9,0) + IF(Scenarios!E15=1, Parameters!B9,0)), 0) -> 0 | K71: =1-Parameters!B4 -> 0.7 | L71: =Scenarios!G15 -> 0.015 | N71: =IF(F71>0, L71/F71, NA()) -> #N/A
A72: =Scenarios!A16 -> F_CoLocation_Echo_150 | B72: FY2026 | C72: =Scenarios!C16 -> 150 | F72: =D72+E72 -> 0 | G72: =IF(Scenarios!D16=1, IF(Scenarios!I16="lease", INDEX(Calc!B4:F4,1,1)*INDEX(Calc!B8:F8,1,1), INDEX(Calc!B4:F4,1,1)*INDEX(Calc!B9:F9,1,1)), INDEX(Calc!B4:F4,1,1)) -> 785217.24 | H72: =IF(Scenarios!E16=1, IF(Scenarios!I16="lease", INDEX(Calc!B5:F5,1,1)*INDEX(Calc!B8:F8,1,1), INDEX(Calc!B5:F5,1,1)*INDEX(Calc!B9:F9,1,1)), INDEX(Calc!B5:F5,1,1)) -> 904374.72 | I72: =INDEX(Calc!B3:F3,1,1) -> 7129.08 | J72: =IF("FY2026"="FY2026", (IF(Scenarios!D16=1, Parameters!B9,0) + IF(Scenarios!E16=1, Parameters!B9,0)), 0) -> 0 | K72: =1-Parameters!B4 -> 0.7 | L72: =Scenarios!G16 -> 0.015 | N72: =IF(F72>0, L72/F72, NA()) -> #N/A
A73: =Scenarios!A16 -> F_CoLocation_Echo_150 | B73: FY2027 | C73: =Scenarios!C16 -> 150 | F73: =D73+E73 -> 0 | G73: =IF(Scenarios!D16=1, IF(Scenarios!I16="lease", INDEX(Calc!B4:F4,1,2)*INDEX(Calc!B8:F8,1,2), INDEX(Calc!B4:F4,1,2)*INDEX(Calc!B9:F9,1,2)), INDEX(Calc!B4:F4,1,2)) -> 804847.67 | H73: =IF(Scenarios!E16=1, IF(Scenarios!I16="lease", INDEX(Calc!B5:F5,1,2)*INDEX(Calc!B8:F8,1,2), INDEX(Calc!B5:F5,1,2)*INDEX(Calc!B9:F9,1,2)), INDEX(Calc!B5:F5,1,2)) -> 926984.09 | I73: =INDEX(Calc!B3:F3,1,2) -> 7307.307 | J73: =IF("FY2027"="FY2026", (IF(Scenarios!D16=1, Parameters!B9,0) + IF(Scenarios!E16=1, Parameters!B9,0)), 0) -> 0 | K73: =1-Parameters!B4 -> 0.7 | L73: =Scenarios!G16 -> 0.015 | N73: =IF(F73>0, L73/F73, NA()) -> #N/A
A74: =Scenarios!A16 -> F_CoLocation_Echo_150 | B74: FY2028 | C74: =Scenarios!C16 -> 150 | F74: =D74+E74 -> 0 | G74: =IF(Scenarios!D16=1, IF(Scenarios!I16="lease", INDEX(Calc!B4:F4,1,3)*INDEX(Calc!B8:F8,1,3), INDEX(Calc!B4:F4,1,3)*INDEX(Calc!B9:F9,1,3)), INDEX(Calc!B4:F4,1,3)) -> 824968.86 | H74: =IF(Scenarios!E16=1, IF(Scenarios!I16="lease", INDEX(Calc!B5:F5,1,3)*INDEX(Calc!B8:F8,1,3), INDEX(Calc!B5:F5,1,3)*INDEX(Calc!B9:F9,1,3)), INDEX(Calc!B5:F5,1,3)) -> 950158.69 | I74: =INDEX(Calc!B3:F3,1,3) -> 7489.9897 | J74: =IF("FY2028"="FY2026", (IF(Scenarios!D16=1, Parameters!B9,0) + IF(Scenarios!E16=1, Parameters!B9,0)), 0) -> 0 | K74: =1-Parameters!B4 -> 0.7 | L74: =Scenarios!G16 -> 0.015 | N74: =IF(F74>0, L74/F74, NA()) -> #N/A
A75: =Scenarios!A16 -> F_CoLocation_Echo_150 | B75: FY2029 | C75: =Scenarios!C16 -> 150 | F75: =D75+E75 -> 0 | G75: =IF(Scenarios!D16=1, IF(Scenarios!I16="lease", INDEX(Calc!B4:F4,1,4)*INDEX(Calc!B8:F8,1,4), INDEX(Calc!B4:F4,1,4)*INDEX(Calc!B9:F9,1,4)), INDEX(Calc!B4:F4,1,4)) -> 845593.08 | H75: =IF(Scenarios!E16=1, IF(Scenarios!I16="lease", INDEX(Calc!B5:F5,1,4)*INDEX(Calc!B8:F8,1,4), INDEX(Calc!B5:F5,1,4)*INDEX(Calc!B9:F9,1,4)), INDEX(Calc!B5:F5,1,4)) -> 973912.66 | I75: =INDEX(Calc!B3:F3,1,4) -> 7677.2394 | J75: =IF("FY2029"="FY2026", (IF(Scenarios!D16=1, Parameters!B9,0) + IF(Scenarios!E16=1, Parameters!B9,0)), 0) -> 0 | K75: =1-Parameters!B4 -> 0.7 | L75: =Scenarios!G16 -> 0.015 | N75: =IF(F75>0, L75/F75, NA()) -> #N/A
A76: =Scenarios!A16 -> F_CoLocation_Echo_150 | B76: FY2030 | C76: =Scenarios!C16 -> 150 | F76: =D76+E76 -> 0 | G76: =IF(Scenarios!D16=1, IF(Scenarios!I16="lease", INDEX(Calc!B4:F4,1,5)*INDEX(Calc!B8:F8,1,5), INDEX(Calc!B4:F4,1,5)*INDEX(Calc!B9:F9,1,5)), INDEX(Calc!B4:F4,1,5)) -> 866732.91 | H76: =IF(Scenarios!E16=1, IF(Scenarios!I16="lease", INDEX(Calc!B5:F5,1,5)*INDEX(Calc!B8:F8,1,5), INDEX(Calc!B5:F5,1,5)*INDEX(Calc!B9:F9,1,5)), INDEX(Calc!B5:F5,1,5)) -> 998260.47 | I76: =INDEX(Calc!B3:F3,1,5) -> 7869.1704 | J76: =IF("FY2030"="FY2026", (IF(Scenarios!D16=1, Parameters!B9,0) + IF(Scenarios!E16=1, Parameters!B9,0)), 0) -> 0 | K76: =1-Parameters!B4 -> 0.7 | L76: =Scenarios!G16 -> 0.015 | N76: =IF(F76>0, L76/F76, NA()) -> #N/A
A77: =Scenarios!A17 -> G_DHub_EchoRamp | B77: FY2026 | C77: =Scenarios!C17 -> 150 | F77: =D77+E77 -> 0 | G77: =IF(Scenarios!D17=1, IF(Scenarios!I17="lease", INDEX(Calc!B4:F4,1,1)*INDEX(Calc!B8:F8,1,1), INDEX(Calc!B4:F4,1,1)*INDEX(Calc!B9:F9,1,1)), INDEX(Calc!B4:F4,1,1)) -> 785217.24 | H77: =IF(Scenarios!E17=1, IF(Scenarios!I17="lease", INDEX(Calc!B5:F5,1,1)*INDEX(Calc!B8:F8,1,1), INDEX(Calc!B5:F5,1,1)*INDEX(Calc!B9:F9,1,1)), INDEX(Calc!B5:F5,1,1)) -> 904374.72 | I77: =INDEX(Calc!B3:F3,1,1) -> 7129.08 | J77: =IF("FY2026"="FY2026", (IF(Scenarios!D17=1, Parameters!B9,0) + IF(Scenarios!E17=1, Parameters!B9,0)), 0) -> 0 | K77: =1-Parameters!B4 -> 0.7 | L77: =Scenarios!G17 -> 0 | N77: =IF(F77>0, L77/F77, NA()) -> #N/A
A78: =Scenarios!A17 -> G_DHub_EchoRamp | B78: FY2027 | C78: =Scenarios!C17 -> 150 | F78: =D78+E78 -> 0 | G78: =IF(Scenarios!D17=1, IF(Scenarios!I17="lease", INDEX(Calc!B4:F4,1,2)*INDEX(Calc!B8:F8,1,2), INDEX(Calc!B4:F4,1,2)*INDEX(Calc!B9:F9,1,2)), INDEX(Calc!B4:F4,1,2)) -> 804847.67 | H78: =IF(Scenarios!E17=1, IF(Scenarios!I17="lease", INDEX(Calc!B5:F5,1,2)*INDEX(Calc!B8:F8,1,2), INDEX(Calc!B5:F5,1,2)*INDEX(Calc!B9:F9,1,2)), INDEX(Calc!B5:F5,1,2)) -> 926984.09 | I78: =INDEX(Calc!B3:F3,1,2) -> 7307.307 | J78: =IF("FY2027"="FY2026", (IF(Scenarios!D17=1, Parameters!B9,0) + IF(Scenarios!E17=1, Parameters!B9,0)), 0) -> 0 | K78: =1-Parameters!B4 -> 0.7 | L78: =Scenarios!G17 -> 0 | N78: =IF(F78>0, L78/F78, NA()) -> #N/A
A79: =Scenarios!A17 -> G_DHub_EchoRamp | B79: FY2028 | C79: =Scenarios!C17 -> 150 | F79: =D79+E79 -> 0 | G79: =IF(Scenarios!D17=1, IF(Scenarios!I17="lease", INDEX(Calc!B4:F4,1,3)*INDEX(Calc!B8:F8,1,3), INDEX(Calc!B4:F4,1,3)*INDEX(Calc!B9:F9,1,3)), INDEX(Calc!B4:F4,1,3)) -> 824968.86 | H79: =IF(Scenarios!E17=1, IF(Scenarios!I17="lease", INDEX(Calc!B5:F5,1,3)*INDEX(Calc!B8:F8,1,3), INDEX(Calc!B5:F5,1,3)*INDEX(Calc!B9:F9,1,3)), INDEX(Calc!B5:F5,1,3)) -> 950158.69 | I79: =INDEX(Calc!B3:F3,1,3) -> 7489.9897 | J79: =IF("FY2028"="FY2026", (IF(Scenarios!D17=1, Parameters!B9,0) + IF(Scenarios!E17=1, Parameters!B9,0)), 0) -> 0 | K79: =1-Parameters!B4 -> 0.7 | L79: =Scenarios!G17 -> 0 | N79: =IF(F79>0, L79/F79, NA()) -> #N/A
A80: =Scenarios!A17 -> G_DHub_EchoRamp | B80: FY2029 | C80: =Scenarios!C17 -> 150 | F80: =D80+E80 -> 0 | G80: =IF(Scenarios!D17=1, IF(Scenarios!I17="lease", INDEX(Calc!B4:F4,1,4)*INDEX(Calc!B8:F8,1,4), INDEX(Calc!B4:F4,1,4)*INDEX(Calc!B9:F9,1,4)), INDEX(Calc!B4:F4,1,4)) -> 845593.08 | H80: =IF(Scenarios!E17=1, IF(Scenarios!I17="lease", INDEX(Calc!B5:F5,1,4)*INDEX(Calc!B8:F8,1,4), INDEX(Calc!B5:F5,1,4)*INDEX(Calc!B9:F9,1,4)), INDEX(Calc!B5:F5,1,4)) -> 973912.66 | I80: =INDEX(Calc!B3:F3,1,4) -> 7677.2394 | J80: =IF("FY2029"="FY2026", (IF(Scenarios!D17=1, Parameters!B9,0) + IF(Scenarios!E17=1, Parameters!B9,0)), 0) -> 0 | K80: =1-Parameters!B4 -> 0.7 | L80: =Scenarios!G17 -> 0 | N80: =IF(F80>0, L80/F80, NA()) -> #N/A
A81: =Scenarios!A17 -> G_DHub_EchoRamp | B81: FY2030 | C81: =Scenarios!C17 -> 150 | F81: =D81+E81 -> 0 | G81: =IF(Scenarios!D17=1, IF(Scenarios!I17="lease", INDEX(Calc!B4:F4,1,5)*INDEX(Calc!B8:F8,1,5), INDEX(Calc!B4:F4,1,5)*INDEX(Calc!B9:F9,1,5)), INDEX(Calc!B4:F4,1,5)) -> 866732.91 | H81: =IF(Scenarios!E17=1, IF(Scenarios!I17="lease", INDEX(Calc!B5:F5,1,5)*INDEX(Calc!B8:F8,1,5), INDEX(Calc!B5:F5,1,5)*INDEX(Calc!B9:F9,1,5)), INDEX(Calc!B5:F5,1,5)) -> 998260.47 | I81: =INDEX(Calc!B3:F3,1,5) -> 7869.1704 | J81: =IF("FY2030"="FY2026", (IF(Scenarios!D17=1, Parameters!B9,0) + IF(Scenarios!E17=1, Parameters!B9,0)), 0) -> 0 | K81: =1-Parameters!B4 -> 0.7 | L81: =Scenarios!G17 -> 0 | N81: =IF(F81>0, L81/F81, NA()) -> #N/A

Sheet Summary_Costs
A1: ScenarioKey | B1: Overlay | C1: Key | D1: Comparable_$FY2028 | E1: Comparable_$FY2030 | F1: Comparable_3yrAvg_$ | G1: NPV5_MO_$
A2: A_Repurpose_Both_lease | B2: 0 | C2: A_Repurpose_Both_lease|0 | D2: =IFERROR( (SUMPRODUCT((MultiYear_ProForma!$A:$A="A_Repurpose_Both_lease")*(MultiYear_ProForma!$B:$B="FY2028")*(MultiYear_ProForma!$L:$L)) + (IFERROR(VLOOKUP("A_Repurpose_Both_lease",$H$4:$I$9,2,FALSE),0)*$I$19*(VLOOKUP("FY2028",$H$11:$J$15,3,TRUE)+VLOOKUP("FY2028",$H$11:$J$15,2,TRUE))) ) / ( SUMPRODUCT((MultiYear_ProForma!$A:$A="A_Repurpose_Both_lease")*(MultiYear_ProForma!$B:$B="FY2028")*(MultiYear_ProForma!$F:$F)) + IFERROR(VLOOKUP("A_Repurpose_Both_lease",$H$4:$I$9,2,FALSE),0)*$I$19 ), "") | E2: =IFERROR( (SUMPRODUCT((MultiYear_ProForma!$A:$A="A_Repurpose_Both_lease")*(MultiYear_ProForma!$B:$B="FY2030")*(MultiYear_ProForma!$L:$L)) + (IFERROR(VLOOKUP("A_Repurpose_Both_lease",$H$4:$I$9,2,FALSE),0)*$I$19*(VLOOKUP("FY2030",$H$11:$J$15,3,TRUE)+VLOOKUP("FY2030",$H$11:$J$15,2,TRUE))) ) / ( SUMPRODUCT((MultiYear_ProForma!$A:$A="A_Repurpose_Both_lease")*(MultiYear_ProForma!$B:$B="FY2030")*(MultiYear_ProForma!$F:$F)) + IFERROR(VLOOKUP("A_Repurpose_Both_lease",$H$4:$I$9,2,FALSE),0)*$I$19 ), "") | F2: =AVERAGE(IFERROR( (SUMPRODUCT((MultiYear_ProForma!$A:$A="A_Repurpose_Both_lease")*(MultiYear_ProForma!$B:$B="FY2026")*(MultiYear_ProForma!$L:$L)) + (IFERROR(VLOOKUP("A_Repurpose_Both_lease",$H$4:$I$9,2,FALSE),0)*$I$19*(VLOOKUP("FY2026",$H$11:$J$15,3,TRUE)+VLOOKUP("FY2026",$H$11:$J$15,2,TRUE))) ) / ( SUMPRODUCT((MultiYear_ProForma!$A:$A="A_Repurpose_Both_lease")*(MultiYear_ProForma!$B:$B="FY2026")*(MultiYear_ProForma!$F:$F)) + IFERROR(VLOOKUP("A_Repurpose_Both_lease",$H$4:$I$9,2,FALSE),0)*$I$19 ), ""),IFERROR( (SUMPRODUCT((MultiYear_ProForma!$A:$A="A_Repurpose_Both_lease")*(MultiYear_ProForma!$B:$B="FY2027")*(MultiYear_ProForma!$L:$L)) + (IFERROR(VLOOKUP("A_Repurpose_Both_lease",$H$4:$I$9,2,FALSE),0)*$I$19*(VLOOKUP("FY2027",$H$11:$J$15,3,TRUE)+VLOOKUP("FY2027",$H$11:$J$15,2,TRUE))) ) / ( SUMPRODUCT((MultiYear_ProForma!$A:$A="A_Repurpose_Both_lease")*(MultiYear_ProForma!$B:$B="FY2027")*(MultiYear_ProForma!$F:$F)) + IFERROR(VLOOKUP("A_Repurpose_Both_lease",$H$4:$I$9,2,FALSE),0)*$I$19 ), ""),IFERROR( (SUMPRODUCT((MultiYear_ProForma!$A:$A="A_Repurpose_Both_lease")*(MultiYear_ProForma!$B:$B="FY2028")*(MultiYear_ProForma!$L:$L)) + (IFERROR(VLOOKUP("A_Repurpose_Both_lease",$H$4:$I$9,2,FALSE),0)*$I$19*(VLOOKUP("FY2028",$H$11:$J$15,3,TRUE)+VLOOKUP("FY2028",$H$11:$J$15,2,TRUE))) ) / ( SUMPRODUCT((MultiYear_ProForma!$A:$A="A_Repurpose_Both_lease")*(MultiYear_ProForma!$B:$B="FY2028")*(MultiYear_ProForma!$F:$F)) + IFERROR(VLOOKUP("A_Repurpose_Both_lease",$H$4:$I$9,2,FALSE),0)*$I$19 ), "")) -> #VALUE!
A3: A_Repurpose_Both_ops | B3: 0 | C3: A_Repurpose_Both_ops|0 | D3: =IFERROR( (SUMPRODUCT((MultiYear_ProForma!$A:$A="A_Repurpose_Both_ops")*(MultiYear_ProForma!$B:$B="FY2028")*(MultiYear_ProForma!$L:$L)) + (IFERROR(VLOOKUP("A_Repurpose_Both_ops",$H$4:$I$9,2,FALSE),0)*$I$19*(VLOOKUP("FY2028",$H$11:$J$15,3,TRUE)+VLOOKUP("FY2028",$H$11:$J$15,2,TRUE))) ) / ( SUMPRODUCT((MultiYear_ProForma!$A:$A="A_Repurpose_Both_ops")*(MultiYear_ProForma!$B:$B="FY2028")*(MultiYear_ProForma!$F:$F)) + IFERROR(VLOOKUP("A_Repurpose_Both_ops",$H$4:$I$9,2,FALSE),0)*$I$19 ), "") | E3: =IFERROR( (SUMPRODUCT((MultiYear_ProForma!$A:$A="A_Repurpose_Both_ops")*(MultiYear_ProForma!$B:$B="FY2030")*(MultiYear_ProForma!$L:$L)) + (IFERROR(VLOOKUP("A_Repurpose_Both_ops",$H$4:$I$9,2,FALSE),0)*$I$19*(VLOOKUP("FY2030",$H$11:$J$15,3,TRUE)+VLOOKUP("FY2030",$H$11:$J$15,2,TRUE))) ) / ( SUMPRODUCT((MultiYear_ProForma!$A:$A="A_Repurpose_Both_ops")*(MultiYear_ProForma!$B:$B="FY2030")*(MultiYear_ProForma!$F:$F)) + IFERROR(VLOOKUP("A_Repurpose_Both_ops",$H$4:$I$9,2,FALSE),0)*$I$19 ), "") | F3: =AVERAGE(IFERROR( (SUMPRODUCT((MultiYear_ProForma!$A:$A="A_Repurpose_Both_ops")*(MultiYear_ProForma!$B:$B="FY2026")*(MultiYear_ProForma!$L:$L)) + (IFERROR(VLOOKUP("A_Repurpose_Both_ops",$H$4:$I$9,2,FALSE),0)*$I$19*(VLOOKUP("FY2026",$H$11:$J$15,3,TRUE)+VLOOKUP("FY2026",$H$11:$J$15,2,TRUE))) ) / ( SUMPRODUCT((MultiYear_ProForma!$A:$A="A_Repurpose_Both_ops")*(MultiYear_ProForma!$B:$B="FY2026")*(MultiYear_ProForma!$F:$F)) + IFERROR(VLOOKUP("A_Repurpose_Both_ops",$H$4:$I$9,2,FALSE),0)*$I$19 ), ""),IFERROR( (SUMPRODUCT((MultiYear_ProForma!$A:$A="A_Repurpose_Both_ops")*(MultiYear_ProForma!$B:$B="FY2027")*(MultiYear_ProForma!$L:$L)) + (IFERROR(VLOOKUP("A_Repurpose_Both_ops",$H$4:$I$9,2,FALSE),0)*$I$19*(VLOOKUP("FY2027",$H$11:$J$15,3,TRUE)+VLOOKUP("FY2027",$H$11:$J$15,2,TRUE))) ) / ( SUMPRODUCT((MultiYear_ProForma!$A:$A="A_Repurpose_Both_ops")*(MultiYear_ProForma!$B:$B="FY2027")*(MultiYear_ProForma!$F:$F)) + IFERROR(VLOOKUP("A_Repurpose_Both_ops",$H$4:$I$9,2,FALSE),0)*$I$19 ), ""),IFERROR( (SUMPRODUCT((MultiYear_ProForma!$A:$A="A_Repurpose_Both_ops")*(MultiYear_ProForma!$B:$B="FY2028")*(MultiYear_ProForma!$L:$L)) + (IFERROR(VLOOKUP("A_Repurpose_Both_ops",$H$4:$I$9,2,FALSE),0)*$I$19*(VLOOKUP("FY2028",$H$11:$J$15,3,TRUE)+VLOOKUP("FY2028",$H$11:$J$15,2,TRUE))) ) / ( SUMPRODUCT((MultiYear_ProForma!$A:$A="A_Repurpose_Both_ops")*(MultiYear_ProForma!$B:$B="FY2028")*(MultiYear_ProForma!$F:$F)) + IFERROR(VLOOKUP("A_Repurpose_Both_ops",$H$4:$I$9,2,FALSE),0)*$I$19 ), "")) -> #VALUE! | I3: Helper: displaced by scenario (Echo+Pima)
A4: B_Repurpose_Echo_Grow_Pima_lease | B4: 0 | C4: B_Repurpose_Echo_Grow_Pima_lease|0 | D4: =IFERROR( (SUMPRODUCT((MultiYear_ProForma!$A:$A="B_Repurpose_Echo_Grow_Pima_lease")*(MultiYear_ProForma!$B:$B="FY2028")*(MultiYear_ProForma!$L:$L)) + (IFERROR(VLOOKUP("B_Repurpose_Echo_Grow_Pima_lease",$H$4:$I$9,2,FALSE),0)*$I$19*(VLOOKUP("FY2028",$H$11:$J$15,3,TRUE)+VLOOKUP("FY2028",$H$11:$J$15,2,TRUE))) ) / ( SUMPRODUCT((MultiYear_ProForma!$A:$A="B_Repurpose_Echo_Grow_Pima_lease")*(MultiYear_ProForma!$B:$B="FY2028")*(MultiYear_ProForma!$F:$F)) + IFERROR(VLOOKUP("B_Repurpose_Echo_Grow_Pima_lease",$H$4:$I$9,2,FALSE),0)*$I$19 ), "") | E4: =IFERROR( (SUMPRODUCT((MultiYear_ProForma!$A:$A="B_Repurpose_Echo_Grow_Pima_lease")*(MultiYear_ProForma!$B:$B="FY2030")*(MultiYear_ProForma!$L:$L)) + (IFERROR(VLOOKUP("B_Repurpose_Echo_Grow_Pima_lease",$H$4:$I$9,2,FALSE),0)*$I$19*(VLOOKUP("FY2030",$H$11:$J$15,3,TRUE)+VLOOKUP("FY2030",$H$11:$J$15,2,TRUE))) ) / ( SUMPRODUCT((MultiYear_ProForma!$A:$A="B_Repurpose_Echo_Grow_Pima_lease")*(MultiYear_ProForma!$B:$B="FY2030")*(MultiYear_ProForma!$F:$F)) + IFERROR(VLOOKUP("B_Repurpose_Echo_Grow_Pima_lease",$H$4:$I$9,2,FALSE),0)*$I$19 ), "") | F4: =AVERAGE(IFERROR( (SUMPRODUCT((MultiYear_ProForma!$A:$A="B_Repurpose_Echo_Grow_Pima_lease")*(MultiYear_ProForma!$B:$B="FY2026")*(MultiYear_ProForma!$L:$L)) + (IFERROR(VLOOKUP("B_Repurpose_Echo_Grow_Pima_lease",$H$4:$I$9,2,FALSE),0)*$I$19*(VLOOKUP("FY2026",$H$11:$J$15,3,TRUE)+VLOOKUP("FY2026",$H$11:$J$15,2,TRUE))) ) / ( SUMPRODUCT((MultiYear_ProForma!$A:$A="B_Repurpose_Echo_Grow_Pima_lease")*(MultiYear_ProForma!$B:$B="FY2026")*(MultiYear_ProForma!$F:$F)) + IFERROR(VLOOKUP("B_Repurpose_Echo_Grow_Pima_lease",$H$4:$I$9,2,FALSE),0)*$I$19 ), ""),IFERROR( (SUMPRODUCT((MultiYear_ProForma!$A:$A="B_Repurpose_Echo_Grow_Pima_lease")*(MultiYear_ProForma!$B:$B="FY2027")*(MultiYear_ProForma!$L:$L)) + (IFERROR(VLOOKUP("B_Repurpose_Echo_Grow_Pima_lease",$H$4:$I$9,2,FALSE),0)*$I$19*(VLOOKUP("FY2027",$H$11:$J$15,3,TRUE)+VLOOKUP("FY2027",$H$11:$J$15,2,TRUE))) ) / ( SUMPRODUCT((MultiYear_ProForma!$A:$A="B_Repurpose_Echo_Grow_Pima_lease")*(MultiYear_ProForma!$B:$B="FY2027")*(MultiYear_ProForma!$F:$F)) + IFERROR(VLOOKUP("B_Repurpose_Echo_Grow_Pima_lease",$H$4:$I$9,2,FALSE),0)*$I$19 ), ""),IFERROR( (SUMPRODUCT((MultiYear_ProForma!$A:$A="B_Repurpose_Echo_Grow_Pima_lease")*(MultiYear_ProForma!$B:$B="FY2028")*(MultiYear_ProForma!$L:$L)) + (IFERROR(VLOOKUP("B_Repurpose_Echo_Grow_Pima_lease",$H$4:$I$9,2,FALSE),0)*$I$19*(VLOOKUP("FY2028",$H$11:$J$15,3,TRUE)+VLOOKUP("FY2028",$H$11:$J$15,2,TRUE))) ) / ( SUMPRODUCT((MultiYear_ProForma!$A:$A="B_Repurpose_Echo_Grow_Pima_lease")*(MultiYear_ProForma!$B:$B="FY2028")*(MultiYear_ProForma!$F:$F)) + IFERROR(VLOOKUP("B_Repurpose_Echo_Grow_Pima_lease",$H$4:$I$9,2,FALSE),0)*$I$19 ), "")) -> #VALUE! | I4: ScenarioKey | J4: Displaced_T
A5: B_Repurpose_Echo_Grow_Pima_ops | B5: 0 | C5: B_Repurpose_Echo_Grow_Pima_ops|0 | D5: =IFERROR( (SUMPRODUCT((MultiYear_ProForma!$A:$A="B_Repurpose_Echo_Grow_Pima_ops")*(MultiYear_ProForma!$B:$B="FY2028")*(MultiYear_ProForma!$L:$L)) + (IFERROR(VLOOKUP("B_Repurpose_Echo_Grow_Pima_ops",$H$4:$I$9,2,FALSE),0)*$I$19*(VLOOKUP("FY2028",$H$11:$J$15,3,TRUE)+VLOOKUP("FY2028",$H$11:$J$15,2,TRUE))) ) / ( SUMPRODUCT((MultiYear_ProForma!$A:$A="B_Repurpose_Echo_Grow_Pima_ops")*(MultiYear_ProForma!$B:$B="FY2028")*(MultiYear_ProForma!$F:$F)) + IFERROR(VLOOKUP("B_Repurpose_Echo_Grow_Pima_ops",$H$4:$I$9,2,FALSE),0)*$I$19 ), "") | E5: =IFERROR( (SUMPRODUCT((MultiYear_ProForma!$A:$A="B_Repurpose_Echo_Grow_Pima_ops")*(MultiYear_ProForma!$B:$B="FY2030")*(MultiYear_ProForma!$L:$L)) + (IFERROR(VLOOKUP("B_Repurpose_Echo_Grow_Pima_ops",$H$4:$I$9,2,FALSE),0)*$I$19*(VLOOKUP("FY2030",$H$11:$J$15,3,TRUE)+VLOOKUP("FY2030",$H$11:$J$15,2,TRUE))) ) / ( SUMPRODUCT((MultiYear_ProForma!$A:$A="B_Repurpose_Echo_Grow_Pima_ops")*(MultiYear_ProForma!$B:$B="FY2030")*(MultiYear_ProForma!$F:$F)) + IFERROR(VLOOKUP("B_Repurpose_Echo_Grow_Pima_ops",$H$4:$I$9,2,FALSE),0)*$I$19 ), "") | F5: =AVERAGE(IFERROR( (SUMPRODUCT((MultiYear_ProForma!$A:$A="B_Repurpose_Echo_Grow_Pima_ops")*(MultiYear_ProForma!$B:$B="FY2026")*(MultiYear_ProForma!$L:$L)) + (IFERROR(VLOOKUP("B_Repurpose_Echo_Grow_Pima_ops",$H$4:$I$9,2,FALSE),0)*$I$19*(VLOOKUP("FY2026",$H$11:$J$15,3,TRUE)+VLOOKUP("FY2026",$H$11:$J$15,2,TRUE))) ) / ( SUMPRODUCT((MultiYear_ProForma!$A:$A="B_Repurpose_Echo_Grow_Pima_ops")*(MultiYear_ProForma!$B:$B="FY2026")*(MultiYear_ProForma!$F:$F)) + IFERROR(VLOOKUP("B_Repurpose_Echo_Grow_Pima_ops",$H$4:$I$9,2,FALSE),0)*$I$19 ), ""),IFERROR( (SUMPRODUCT((MultiYear_ProForma!$A:$A="B_Repurpose_Echo_Grow_Pima_ops")*(MultiYear_ProForma!$B:$B="FY2027")*(MultiYear_ProForma!$L:$L)) + (IFERROR(VLOOKUP("B_Repurpose_Echo_Grow_Pima_ops",$H$4:$I$9,2,FALSE),0)*$I$19*(VLOOKUP("FY2027",$H$11:$J$15,3,TRUE)+VLOOKUP("FY2027",$H$11:$J$15,2,TRUE))) ) / ( SUMPRODUCT((MultiYear_ProForma!$A:$A="B_Repurpose_Echo_Grow_Pima_ops")*(MultiYear_ProForma!$B:$B="FY2027")*(MultiYear_ProForma!$F:$F)) + IFERROR(VLOOKUP("B_Repurpose_Echo_Grow_Pima_ops",$H$4:$I$9,2,FALSE),0)*$I$19 ), ""),IFERROR( (SUMPRODUCT((MultiYear_ProForma!$A:$A="B_Repurpose_Echo_Grow_Pima_ops")*(MultiYear_ProForma!$B:$B="FY2028")*(MultiYear_ProForma!$L:$L)) + (IFERROR(VLOOKUP("B_Repurpose_Echo_Grow_Pima_ops",$H$4:$I$9,2,FALSE),0)*$I$19*(VLOOKUP("FY2028",$H$11:$J$15,3,TRUE)+VLOOKUP("FY2028",$H$11:$J$15,2,TRUE))) ) / ( SUMPRODUCT((MultiYear_ProForma!$A:$A="B_Repurpose_Echo_Grow_Pima_ops")*(MultiYear_ProForma!$B:$B="FY2028")*(MultiYear_ProForma!$F:$F)) + IFERROR(VLOOKUP("B_Repurpose_Echo_Grow_Pima_ops",$H$4:$I$9,2,FALSE),0)*$I$19 ), "")) -> #VALUE! | I5: A_Repurpose_Both_lease | J5: 553
A6: C_Repurpose_Pima_Grow_Echo_lease | B6: 0 | C6: C_Repurpose_Pima_Grow_Echo_lease|0 | D6: =IFERROR( (SUMPRODUCT((MultiYear_ProForma!$A:$A="C_Repurpose_Pima_Grow_Echo_lease")*(MultiYear_ProForma!$B:$B="FY2028")*(MultiYear_ProForma!$L:$L)) + (IFERROR(VLOOKUP("C_Repurpose_Pima_Grow_Echo_lease",$H$4:$I$9,2,FALSE),0)*$I$19*(VLOOKUP("FY2028",$H$11:$J$15,3,TRUE)+VLOOKUP("FY2028",$H$11:$J$15,2,TRUE))) ) / ( SUMPRODUCT((MultiYear_ProForma!$A:$A="C_Repurpose_Pima_Grow_Echo_lease")*(MultiYear_ProForma!$B:$B="FY2028")*(MultiYear_ProForma!$F:$F)) + IFERROR(VLOOKUP("C_Repurpose_Pima_Grow_Echo_lease",$H$4:$I$9,2,FALSE),0)*$I$19 ), "") | E6: =IFERROR( (SUMPRODUCT((MultiYear_ProForma!$A:$A="C_Repurpose_Pima_Grow_Echo_lease")*(MultiYear_ProForma!$B:$B="FY2030")*(MultiYear_ProForma!$L:$L)) + (IFERROR(VLOOKUP("C_Repurpose_Pima_Grow_Echo_lease",$H$4:$I$9,2,FALSE),0)*$I$19*(VLOOKUP("FY2030",$H$11:$J$15,3,TRUE)+VLOOKUP("FY2030",$H$11:$J$15,2,TRUE))) ) / ( SUMPRODUCT((MultiYear_ProForma!$A:$A="C_Repurpose_Pima_Grow_Echo_lease")*(MultiYear_ProForma!$B:$B="FY2030")*(MultiYear_ProForma!$F:$F)) + IFERROR(VLOOKUP("C_Repurpose_Pima_Grow_Echo_lease",$H$4:$I$9,2,FALSE),0)*$I$19 ), "") | F6: =AVERAGE(IFERROR( (SUMPRODUCT((MultiYear_ProForma!$A:$A="C_Repurpose_Pima_Grow_Echo_lease")*(MultiYear_ProForma!$B:$B="FY2026")*(MultiYear_ProForma!$L:$L)) + (IFERROR(VLOOKUP("C_Repurpose_Pima_Grow_Echo_lease",$H$4:$I$9,2,FALSE),0)*$I$19*(VLOOKUP("FY2026",$H$11:$J$15,3,TRUE)+VLOOKUP("FY2026",$H$11:$J$15,2,TRUE))) ) / ( SUMPRODUCT((MultiYear_ProForma!$A:$A="C_Repurpose_Pima_Grow_Echo_lease")*(MultiYear_ProForma!$B:$B="FY2026")*(MultiYear_ProForma!$F:$F)) + IFERROR(VLOOKUP("C_Repurpose_Pima_Grow_Echo_lease",$H$4:$I$9,2,FALSE),0)*$I$19 ), ""),IFERROR( (SUMPRODUCT((MultiYear_ProForma!$A:$A="C_Repurpose_Pima_Grow_Echo_lease")*(MultiYear_ProForma!$B:$B="FY2027")*(MultiYear_ProForma!$L:$L)) + (IFERROR(VLOOKUP("C_Repurpose_Pima_Grow_Echo_lease",$H$4:$I$9,2,FALSE),0)*$I$19*(VLOOKUP("FY2027",$H$11:$J$15,3,TRUE)+VLOOKUP("FY2027",$H$11:$J$15,2,TRUE))) ) / ( SUMPRODUCT((MultiYear_ProForma!$A:$A="C_Repurpose_Pima_Grow_Echo_lease")*(MultiYear_ProForma!$B:$B="FY2027")*(MultiYear_ProForma!$F:$F)) + IFERROR(VLOOKUP("C_Repurpose_Pima_Grow_Echo_lease",$H$4:$I$9,2,FALSE),0)*$I$19 ), ""),IFERROR( (SUMPRODUCT((MultiYear_ProForma!$A:$A="C_Repurpose_Pima_Grow_Echo_lease")*(MultiYear_ProForma!$B:$B="FY2028")*(MultiYear_ProForma!$L:$L)) + (IFERROR(VLOOKUP("C_Repurpose_Pima_Grow_Echo_lease",$H$4:$I$9,2,FALSE),0)*$I$19*(VLOOKUP("FY2028",$H$11:$J$15,3,TRUE)+VLOOKUP("FY2028",$H$11:$J$15,2,TRUE))) ) / ( SUMPRODUCT((MultiYear_ProForma!$A:$A="C_Repurpose_Pima_Grow_Echo_lease")*(MultiYear_ProForma!$B:$B="FY2028")*(MultiYear_ProForma!$F:$F)) + IFERROR(VLOOKUP("C_Repurpose_Pima_Grow_Echo_lease",$H$4:$I$9,2,FALSE),0)*$I$19 ), "")) -> #VALUE! | I6: A_Repurpose_Both_ops | J6: 553
A7: C_Repurpose_Pima_Grow_Echo_ops | B7: 0 | C7: C_Repurpose_Pima_Grow_Echo_ops|0 | D7: =IFERROR( (SUMPRODUCT((MultiYear_ProForma!$A:$A="C_Repurpose_Pima_Grow_Echo_ops")*(MultiYear_ProForma!$B:$B="FY2028")*(MultiYear_ProForma!$L:$L)) + (IFERROR(VLOOKUP("C_Repurpose_Pima_Grow_Echo_ops",$H$4:$I$9,2,FALSE),0)*$I$19*(VLOOKUP("FY2028",$H$11:$J$15,3,TRUE)+VLOOKUP("FY2028",$H$11:$J$15,2,TRUE))) ) / ( SUMPRODUCT((MultiYear_ProForma!$A:$A="C_Repurpose_Pima_Grow_Echo_ops")*(MultiYear_ProForma!$B:$B="FY2028")*(MultiYear_ProForma!$F:$F)) + IFERROR(VLOOKUP("C_Repurpose_Pima_Grow_Echo_ops",$H$4:$I$9,2,FALSE),0)*$I$19 ), "") | E7: =IFERROR( (SUMPRODUCT((MultiYear_ProForma!$A:$A="C_Repurpose_Pima_Grow_Echo_ops")*(MultiYear_ProForma!$B:$B="FY2030")*(MultiYear_ProForma!$L:$L)) + (IFERROR(VLOOKUP("C_Repurpose_Pima_Grow_Echo_ops",$H$4:$I$9,2,FALSE),0)*$I$19*(VLOOKUP("FY2030",$H$11:$J$15,3,TRUE)+VLOOKUP("FY2030",$H$11:$J$15,2,TRUE))) ) / ( SUMPRODUCT((MultiYear_ProForma!$A:$A="C_Repurpose_Pima_Grow_Echo_ops")*(MultiYear_ProForma!$B:$B="FY2030")*(MultiYear_ProForma!$F:$F)) + IFERROR(VLOOKUP("C_Repurpose_Pima_Grow_Echo_ops",$H$4:$I$9,2,FALSE),0)*$I$19 ), "") | F7: =AVERAGE(IFERROR( (SUMPRODUCT((MultiYear_ProForma!$A:$A="C_Repurpose_Pima_Grow_Echo_ops")*(MultiYear_ProForma!$B:$B="FY2026")*(MultiYear_ProForma!$L:$L)) + (IFERROR(VLOOKUP("C_Repurpose_Pima_Grow_Echo_ops",$H$4:$I$9,2,FALSE),0)*$I$19*(VLOOKUP("FY2026",$H$11:$J$15,3,TRUE)+VLOOKUP("FY2026",$H$11:$J$15,2,TRUE))) ) / ( SUMPRODUCT((MultiYear_ProForma!$A:$A="C_Repurpose_Pima_Grow_Echo_ops")*(MultiYear_ProForma!$B:$B="FY2026")*(MultiYear_ProForma!$F:$F)) + IFERROR(VLOOKUP("C_Repurpose_Pima_Grow_Echo_ops",$H$4:$I$9,2,FALSE),0)*$I$19 ), ""),IFERROR( (SUMPRODUCT((MultiYear_ProForma!$A:$A="C_Repurpose_Pima_Grow_Echo_ops")*(MultiYear_ProForma!$B:$B="FY2027")*(MultiYear_ProForma!$L:$L)) + (IFERROR(VLOOKUP("C_Repurpose_Pima_Grow_Echo_ops",$H$4:$I$9,2,FALSE),0)*$I$19*(VLOOKUP("FY2027",$H$11:$J$15,3,TRUE)+VLOOKUP("FY2027",$H$11:$J$15,2,TRUE))) ) / ( SUMPRODUCT((MultiYear_ProForma!$A:$A="C_Repurpose_Pima_Grow_Echo_ops")*(MultiYear_ProForma!$B:$B="FY2027")*(MultiYear_ProForma!$F:$F)) + IFERROR(VLOOKUP("C_Repurpose_Pima_Grow_Echo_ops",$H$4:$I$9,2,FALSE),0)*$I$19 ), ""),IFERROR( (SUMPRODUCT((MultiYear_ProForma!$A:$A="C_Repurpose_Pima_Grow_Echo_ops")*(MultiYear_ProForma!$B:$B="FY2028")*(MultiYear_ProForma!$L:$L)) + (IFERROR(VLOOKUP("C_Repurpose_Pima_Grow_Echo_ops",$H$4:$I$9,2,FALSE),0)*$I$19*(VLOOKUP("FY2028",$H$11:$J$15,3,TRUE)+VLOOKUP("FY2028",$H$11:$J$15,2,TRUE))) ) / ( SUMPRODUCT((MultiYear_ProForma!$A:$A="C_Repurpose_Pima_Grow_Echo_ops")*(MultiYear_ProForma!$B:$B="FY2028")*(MultiYear_ProForma!$F:$F)) + IFERROR(VLOOKUP("C_Repurpose_Pima_Grow_Echo_ops",$H$4:$I$9,2,FALSE),0)*$I$19 ), "")) -> #VALUE! | I7: B_Repurpose_Echo_Grow_Pima_lease | J7: 257
A8: D_Grow_Both_0 | B8: 0 | C8: D_Grow_Both_0|0 | D8: =IFERROR( (SUMPRODUCT((MultiYear_ProForma!$A:$A="D_Grow_Both_0")*(MultiYear_ProForma!$B:$B="FY2028")*(MultiYear_ProForma!$L:$L)) + (IFERROR(VLOOKUP("D_Grow_Both_0",$H$4:$I$9,2,FALSE),0)*$I$19*(VLOOKUP("FY2028",$H$11:$J$15,3,TRUE)+VLOOKUP("FY2028",$H$11:$J$15,2,TRUE))) ) / ( SUMPRODUCT((MultiYear_ProForma!$A:$A="D_Grow_Both_0")*(MultiYear_ProForma!$B:$B="FY2028")*(MultiYear_ProForma!$F:$F)) + IFERROR(VLOOKUP("D_Grow_Both_0",$H$4:$I$9,2,FALSE),0)*$I$19 ), "") | E8: =IFERROR( (SUMPRODUCT((MultiYear_ProForma!$A:$A="D_Grow_Both_0")*(MultiYear_ProForma!$B:$B="FY2030")*(MultiYear_ProForma!$L:$L)) + (IFERROR(VLOOKUP("D_Grow_Both_0",$H$4:$I$9,2,FALSE),0)*$I$19*(VLOOKUP("FY2030",$H$11:$J$15,3,TRUE)+VLOOKUP("FY2030",$H$11:$J$15,2,TRUE))) ) / ( SUMPRODUCT((MultiYear_ProForma!$A:$A="D_Grow_Both_0")*(MultiYear_ProForma!$B:$B="FY2030")*(MultiYear_ProForma!$F:$F)) + IFERROR(VLOOKUP("D_Grow_Both_0",$H$4:$I$9,2,FALSE),0)*$I$19 ), "") | F8: =AVERAGE(IFERROR( (SUMPRODUCT((MultiYear_ProForma!$A:$A="D_Grow_Both_0")*(MultiYear_ProForma!$B:$B="FY2026")*(MultiYear_ProForma!$L:$L)) + (IFERROR(VLOOKUP("D_Grow_Both_0",$H$4:$I$9,2,FALSE),0)*$I$19*(VLOOKUP("FY2026",$H$11:$J$15,3,TRUE)+VLOOKUP("FY2026",$H$11:$J$15,2,TRUE))) ) / ( SUMPRODUCT((MultiYear_ProForma!$A:$A="D_Grow_Both_0")*(MultiYear_ProForma!$B:$B="FY2026")*(MultiYear_ProForma!$F:$F)) + IFERROR(VLOOKUP("D_Grow_Both_0",$H$4:$I$9,2,FALSE),0)*$I$19 ), ""),IFERROR( (SUMPRODUCT((MultiYear_ProForma!$A:$A="D_Grow_Both_0")*(MultiYear_ProForma!$B:$B="FY2027")*(MultiYear_ProForma!$L:$L)) + (IFERROR(VLOOKUP("D_Grow_Both_0",$H$4:$I$9,2,FALSE),0)*$I$19*(VLOOKUP("FY2027",$H$11:$J$15,3,TRUE)+VLOOKUP("FY2027",$H$11:$J$15,2,TRUE))) ) / ( SUMPRODUCT((MultiYear_ProForma!$A:$A="D_Grow_Both_0")*(MultiYear_ProForma!$B:$B="FY2027")*(MultiYear_ProForma!$F:$F)) + IFERROR(VLOOKUP("D_Grow_Both_0",$H$4:$I$9,2,FALSE),0)*$I$19 ), ""),IFERROR( (SUMPRODUCT((MultiYear_ProForma!$A:$A="D_Grow_Both_0")*(MultiYear_ProForma!$B:$B="FY2028")*(MultiYear_ProForma!$L:$L)) + (IFERROR(VLOOKUP("D_Grow_Both_0",$H$4:$I$9,2,FALSE),0)*$I$19*(VLOOKUP("FY2028",$H$11:$J$15,3,TRUE)+VLOOKUP("FY2028",$H$11:$J$15,2,TRUE))) ) / ( SUMPRODUCT((MultiYear_ProForma!$A:$A="D_Grow_Both_0")*(MultiYear_ProForma!$B:$B="FY2028")*(MultiYear_ProForma!$F:$F)) + IFERROR(VLOOKUP("D_Grow_Both_0",$H$4:$I$9,2,FALSE),0)*$I$19 ), "")) -> #VALUE! | I8: B_Repurpose_Echo_Grow_Pima_ops | J8: 257
A9: D_Grow_Both_100 | B9: 100 | C9: D_Grow_Both_100|100 | D9: =IFERROR( (SUMPRODUCT((MultiYear_ProForma!$A:$A="D_Grow_Both_100")*(MultiYear_ProForma!$B:$B="FY2028")*(MultiYear_ProForma!$L:$L)) + (IFERROR(VLOOKUP("D_Grow_Both_100",$H$4:$I$9,2,FALSE),0)*$I$19*(VLOOKUP("FY2028",$H$11:$J$15,3,TRUE)+VLOOKUP("FY2028",$H$11:$J$15,2,TRUE))) ) / ( SUMPRODUCT((MultiYear_ProForma!$A:$A="D_Grow_Both_100")*(MultiYear_ProForma!$B:$B="FY2028")*(MultiYear_ProForma!$F:$F)) + IFERROR(VLOOKUP("D_Grow_Both_100",$H$4:$I$9,2,FALSE),0)*$I$19 ), "") | E9: =IFERROR( (SUMPRODUCT((MultiYear_ProForma!$A:$A="D_Grow_Both_100")*(MultiYear_ProForma!$B:$B="FY2030")*(MultiYear_ProForma!$L:$L)) + (IFERROR(VLOOKUP("D_Grow_Both_100",$H$4:$I$9,2,FALSE),0)*$I$19*(VLOOKUP("FY2030",$H$11:$J$15,3,TRUE)+VLOOKUP("FY2030",$H$11:$J$15,2,TRUE))) ) / ( SUMPRODUCT((MultiYear_ProForma!$A:$A="D_Grow_Both_100")*(MultiYear_ProForma!$B:$B="FY2030")*(MultiYear_ProForma!$F:$F)) + IFERROR(VLOOKUP("D_Grow_Both_100",$H$4:$I$9,2,FALSE),0)*$I$19 ), "") | F9: =AVERAGE(IFERROR( (SUMPRODUCT((MultiYear_ProForma!$A:$A="D_Grow_Both_100")*(MultiYear_ProForma!$B:$B="FY2026")*(MultiYear_ProForma!$L:$L)) + (IFERROR(VLOOKUP("D_Grow_Both_100",$H$4:$I$9,2,FALSE),0)*$I$19*(VLOOKUP("FY2026",$H$11:$J$15,3,TRUE)+VLOOKUP("FY2026",$H$11:$J$15,2,TRUE))) ) / ( SUMPRODUCT((MultiYear_ProForma!$A:$A="D_Grow_Both_100")*(MultiYear_ProForma!$B:$B="FY2026")*(MultiYear_ProForma!$F:$F)) + IFERROR(VLOOKUP("D_Grow_Both_100",$H$4:$I$9,2,FALSE),0)*$I$19 ), ""),IFERROR( (SUMPRODUCT((MultiYear_ProForma!$A:$A="D_Grow_Both_100")*(MultiYear_ProForma!$B:$B="FY2027")*(MultiYear_ProForma!$L:$L)) + (IFERROR(VLOOKUP("D_Grow_Both_100",$H$4:$I$9,2,FALSE),0)*$I$19*(VLOOKUP("FY2027",$H$11:$J$15,3,TRUE)+VLOOKUP("FY2027",$H$11:$J$15,2,TRUE))) ) / ( SUMPRODUCT((MultiYear_ProForma!$A:$A="D_Grow_Both_100")*(MultiYear_ProForma!$B:$B="FY2027")*(MultiYear_ProForma!$F:$F)) + IFERROR(VLOOKUP("D_Grow_Both_100",$H$4:$I$9,2,FALSE),0)*$I$19 ), ""),IFERROR( (SUMPRODUCT((MultiYear_ProForma!$A:$A="D_Grow_Both_100")*(MultiYear_ProForma!$B:$B="FY2028")*(MultiYear_ProForma!$L:$L)) + (IFERROR(VLOOKUP("D_Grow_Both_100",$H$4:$I$9,2,FALSE),0)*$I$19*(VLOOKUP("FY2028",$H$11:$J$15,3,TRUE)+VLOOKUP("FY2028",$H$11:$J$15,2,TRUE))) ) / ( SUMPRODUCT((MultiYear_ProForma!$A:$A="D_Grow_Both_100")*(MultiYear_ProForma!$B:$B="FY2028")*(MultiYear_ProForma!$F:$F)) + IFERROR(VLOOKUP("D_Grow_Both_100",$H$4:$I$9,2,FALSE),0)*$I$19 ), "")) -> #VALUE! | I9: C_Repurpose_Pima_Grow_Echo_lease | J9: 296
A10: D_Grow_Both_150 | B10: 150 | C10: D_Grow_Both_150|150 | D10: =IFERROR( (SUMPRODUCT((MultiYear_ProForma!$A:$A="D_Grow_Both_150")*(MultiYear_ProForma!$B:$B="FY2028")*(MultiYear_ProForma!$L:$L)) + (IFERROR(VLOOKUP("D_Grow_Both_150",$H$4:$I$9,2,FALSE),0)*$I$19*(VLOOKUP("FY2028",$H$11:$J$15,3,TRUE)+VLOOKUP("FY2028",$H$11:$J$15,2,TRUE))) ) / ( SUMPRODUCT((MultiYear_ProForma!$A:$A="D_Grow_Both_150")*(MultiYear_ProForma!$B:$B="FY2028")*(MultiYear_ProForma!$F:$F)) + IFERROR(VLOOKUP("D_Grow_Both_150",$H$4:$I$9,2,FALSE),0)*$I$19 ), "") | E10: =IFERROR( (SUMPRODUCT((MultiYear_ProForma!$A:$A="D_Grow_Both_150")*(MultiYear_ProForma!$B:$B="FY2030")*(MultiYear_ProForma!$L:$L)) + (IFERROR(VLOOKUP("D_Grow_Both_150",$H$4:$I$9,2,FALSE),0)*$I$19*(VLOOKUP("FY2030",$H$11:$J$15,3,TRUE)+VLOOKUP("FY2030",$H$11:$J$15,2,TRUE))) ) / ( SUMPRODUCT((MultiYear_ProForma!$A:$A="D_Grow_Both_150")*(MultiYear_ProForma!$B:$B="FY2030")*(MultiYear_ProForma!$F:$F)) + IFERROR(VLOOKUP("D_Grow_Both_150",$H$4:$I$9,2,FALSE),0)*$I$19 ), "") | F10: =AVERAGE(IFERROR( (SUMPRODUCT((MultiYear_ProForma!$A:$A="D_Grow_Both_150")*(MultiYear_ProForma!$B:$B="FY2026")*(MultiYear_ProForma!$L:$L)) + (IFERROR(VLOOKUP("D_Grow_Both_150",$H$4:$I$9,2,FALSE),0)*$I$19*(VLOOKUP("FY2026",$H$11:$J$15,3,TRUE)+VLOOKUP("FY2026",$H$11:$J$15,2,TRUE))) ) / ( SUMPRODUCT((MultiYear_ProForma!$A:$A="D_Grow_Both_150")*(MultiYear_ProForma!$B:$B="FY2026")*(MultiYear_ProForma!$F:$F)) + IFERROR(VLOOKUP("D_Grow_Both_150",$H$4:$I$9,2,FALSE),0)*$I$19 ), ""),IFERROR( (SUMPRODUCT((MultiYear_ProForma!$A:$A="D_Grow_Both_150")*(MultiYear_ProForma!$B:$B="FY2027")*(MultiYear_ProForma!$L:$L)) + (IFERROR(VLOOKUP("D_Grow_Both_150",$H$4:$I$9,2,FALSE),0)*$I$19*(VLOOKUP("FY2027",$H$11:$J$15,3,TRUE)+VLOOKUP("FY2027",$H$11:$J$15,2,TRUE))) ) / ( SUMPRODUCT((MultiYear_ProForma!$A:$A="D_Grow_Both_150")*(MultiYear_ProForma!$B:$B="FY2027")*(MultiYear_ProForma!$F:$F)) + IFERROR(VLOOKUP("D_Grow_Both_150",$H$4:$I$9,2,FALSE),0)*$I$19 ), ""),IFERROR( (SUMPRODUCT((MultiYear_ProForma!$A:$A="D_Grow_Both_150")*(MultiYear_ProForma!$B:$B="FY2028")*(MultiYear_ProForma!$L:$L)) + (IFERROR(VLOOKUP("D_Grow_Both_150",$H$4:$I$9,2,FALSE),0)*$I$19*(VLOOKUP("FY2028",$H$11:$J$15,3,TRUE)+VLOOKUP("FY2028",$H$11:$J$15,2,TRUE))) ) / ( SUMPRODUCT((MultiYear_ProForma!$A:$A="D_Grow_Both_150")*(MultiYear_ProForma!$B:$B="FY2028")*(MultiYear_ProForma!$F:$F)) + IFERROR(VLOOKUP("D_Grow_Both_150",$H$4:$I$9,2,FALSE),0)*$I$19 ), "")) -> #VALUE! | I10: C_Repurpose_Pima_Grow_Echo_ops | J10: 296
A11: E_StatusQuo_Targets_0 | B11: 0 | C11: E_StatusQuo_Targets_0|0 | D11: =IFERROR( (SUMPRODUCT((MultiYear_ProForma!$A:$A="E_StatusQuo_Targets_0")*(MultiYear_ProForma!$B:$B="FY2028")*(MultiYear_ProForma!$L:$L)) + (IFERROR(VLOOKUP("E_StatusQuo_Targets_0",$H$4:$I$9,2,FALSE),0)*$I$19*(VLOOKUP("FY2028",$H$11:$J$15,3,TRUE)+VLOOKUP("FY2028",$H$11:$J$15,2,TRUE))) ) / ( SUMPRODUCT((MultiYear_ProForma!$A:$A="E_StatusQuo_Targets_0")*(MultiYear_ProForma!$B:$B="FY2028")*(MultiYear_ProForma!$F:$F)) + IFERROR(VLOOKUP("E_StatusQuo_Targets_0",$H$4:$I$9,2,FALSE),0)*$I$19 ), "") | E11: =IFERROR( (SUMPRODUCT((MultiYear_ProForma!$A:$A="E_StatusQuo_Targets_0")*(MultiYear_ProForma!$B:$B="FY2030")*(MultiYear_ProForma!$L:$L)) + (IFERROR(VLOOKUP("E_StatusQuo_Targets_0",$H$4:$I$9,2,FALSE),0)*$I$19*(VLOOKUP("FY2030",$H$11:$J$15,3,TRUE)+VLOOKUP("FY2030",$H$11:$J$15,2,TRUE))) ) / ( SUMPRODUCT((MultiYear_ProForma!$A:$A="E_StatusQuo_Targets_0")*(MultiYear_ProForma!$B:$B="FY2030")*(MultiYear_ProForma!$F:$F)) + IFERROR(VLOOKUP("E_StatusQuo_Targets_0",$H$4:$I$9,2,FALSE),0)*$I$19 ), "") | F11: =AVERAGE(IFERROR( (SUMPRODUCT((MultiYear_ProForma!$A:$A="E_StatusQuo_Targets_0")*(MultiYear_ProForma!$B:$B="FY2026")*(MultiYear_ProForma!$L:$L)) + (IFERROR(VLOOKUP("E_StatusQuo_Targets_0",$H$4:$I$9,2,FALSE),0)*$I$19*(VLOOKUP("FY2026",$H$11:$J$15,3,TRUE)+VLOOKUP("FY2026",$H$11:$J$15,2,TRUE))) ) / ( SUMPRODUCT((MultiYear_ProForma!$A:$A="E_StatusQuo_Targets_0")*(MultiYear_ProForma!$B:$B="FY2026")*(MultiYear_ProForma!$F:$F)) + IFERROR(VLOOKUP("E_StatusQuo_Targets_0",$H$4:$I$9,2,FALSE),0)*$I$19 ), ""),IFERROR( (SUMPRODUCT((MultiYear_ProForma!$A:$A="E_StatusQuo_Targets_0")*(MultiYear_ProForma!$B:$B="FY2027")*(MultiYear_ProForma!$L:$L)) + (IFERROR(VLOOKUP("E_StatusQuo_Targets_0",$H$4:$I$9,2,FALSE),0)*$I$19*(VLOOKUP("FY2027",$H$11:$J$15,3,TRUE)+VLOOKUP("FY2027",$H$11:$J$15,2,TRUE))) ) / ( SUMPRODUCT((MultiYear_ProForma!$A:$A="E_StatusQuo_Targets_0")*(MultiYear_ProForma!$B:$B="FY2027")*(MultiYear_ProForma!$F:$F)) + IFERROR(VLOOKUP("E_StatusQuo_Targets_0",$H$4:$I$9,2,FALSE),0)*$I$19 ), ""),IFERROR( (SUMPRODUCT((MultiYear_ProForma!$A:$A="E_StatusQuo_Targets_0")*(MultiYear_ProForma!$B:$B="FY2028")*(MultiYear_ProForma!$L:$L)) + (IFERROR(VLOOKUP("E_StatusQuo_Targets_0",$H$4:$I$9,2,FALSE),0)*$I$19*(VLOOKUP("FY2028",$H$11:$J$15,3,TRUE)+VLOOKUP("FY2028",$H$11:$J$15,2,TRUE))) ) / ( SUMPRODUCT((MultiYear_ProForma!$A:$A="E_StatusQuo_Targets_0")*(MultiYear_ProForma!$B:$B="FY2028")*(MultiYear_ProForma!$F:$F)) + IFERROR(VLOOKUP("E_StatusQuo_Targets_0",$H$4:$I$9,2,FALSE),0)*$I$19 ), "")) -> #VALUE! | I11: FY | J11: h | K11: var_unit
A12: E_StatusQuo_Targets_100 | B12: 100 | C12: E_StatusQuo_Targets_100|100 | D12: =IFERROR( (SUMPRODUCT((MultiYear_ProForma!$A:$A="E_StatusQuo_Targets_100")*(MultiYear_ProForma!$B:$B="FY2028")*(MultiYear_ProForma!$L:$L)) + (IFERROR(VLOOKUP("E_StatusQuo_Targets_100",$H$4:$I$9,2,FALSE),0)*$I$19*(VLOOKUP("FY2028",$H$11:$J$15,3,TRUE)+VLOOKUP("FY2028",$H$11:$J$15,2,TRUE))) ) / ( SUMPRODUCT((MultiYear_ProForma!$A:$A="E_StatusQuo_Targets_100")*(MultiYear_ProForma!$B:$B="FY2028")*(MultiYear_ProForma!$F:$F)) + IFERROR(VLOOKUP("E_StatusQuo_Targets_100",$H$4:$I$9,2,FALSE),0)*$I$19 ), "") | E12: =IFERROR( (SUMPRODUCT((MultiYear_ProForma!$A:$A="E_StatusQuo_Targets_100")*(MultiYear_ProForma!$B:$B="FY2030")*(MultiYear_ProForma!$L:$L)) + (IFERROR(VLOOKUP("E_StatusQuo_Targets_100",$H$4:$I$9,2,FALSE),0)*$I$19*(VLOOKUP("FY2030",$H$11:$J$15,3,TRUE)+VLOOKUP("FY2030",$H$11:$J$15,2,TRUE))) ) / ( SUMPRODUCT((MultiYear_ProForma!$A:$A="E_StatusQuo_Targets_100")*(MultiYear_ProForma!$B:$B="FY2030")*(MultiYear_ProForma!$F:$F)) + IFERROR(VLOOKUP("E_StatusQuo_Targets_100",$H$4:$I$9,2,FALSE),0)*$I$19 ), "") | F12: =AVERAGE(IFERROR( (SUMPRODUCT((MultiYear_ProForma!$A:$A="E_StatusQuo_Targets_100")*(MultiYear_ProForma!$B:$B="FY2026")*(MultiYear_ProForma!$L:$L)) + (IFERROR(VLOOKUP("E_StatusQuo_Targets_100",$H$4:$I$9,2,FALSE),0)*$I$19*(VLOOKUP("FY2026",$H$11:$J$15,3,TRUE)+VLOOKUP("FY2026",$H$11:$J$15,2,TRUE))) ) / ( SUMPRODUCT((MultiYear_ProForma!$A:$A="E_StatusQuo_Targets_100")*(MultiYear_ProForma!$B:$B="FY2026")*(MultiYear_ProForma!$F:$F)) + IFERROR(VLOOKUP("E_StatusQuo_Targets_100",$H$4:$I$9,2,FALSE),0)*$I$19 ), ""),IFERROR( (SUMPRODUCT((MultiYear_ProForma!$A:$A="E_StatusQuo_Targets_100")*(MultiYear_ProForma!$B:$B="FY2027")*(MultiYear_ProForma!$L:$L)) + (IFERROR(VLOOKUP("E_StatusQuo_Targets_100",$H$4:$I$9,2,FALSE),0)*$I$19*(VLOOKUP("FY2027",$H$11:$J$15,3,TRUE)+VLOOKUP("FY2027",$H$11:$J$15,2,TRUE))) ) / ( SUMPRODUCT((MultiYear_ProForma!$A:$A="E_StatusQuo_Targets_100")*(MultiYear_ProForma!$B:$B="FY2027")*(MultiYear_ProForma!$F:$F)) + IFERROR(VLOOKUP("E_StatusQuo_Targets_100",$H$4:$I$9,2,FALSE),0)*$I$19 ), ""),IFERROR( (SUMPRODUCT((MultiYear_ProForma!$A:$A="E_StatusQuo_Targets_100")*(MultiYear_ProForma!$B:$B="FY2028")*(MultiYear_ProForma!$L:$L)) + (IFERROR(VLOOKUP("E_StatusQuo_Targets_100",$H$4:$I$9,2,FALSE),0)*$I$19*(VLOOKUP("FY2028",$H$11:$J$15,3,TRUE)+VLOOKUP("FY2028",$H$11:$J$15,2,TRUE))) ) / ( SUMPRODUCT((MultiYear_ProForma!$A:$A="E_StatusQuo_Targets_100")*(MultiYear_ProForma!$B:$B="FY2028")*(MultiYear_ProForma!$F:$F)) + IFERROR(VLOOKUP("E_StatusQuo_Targets_100",$H$4:$I$9,2,FALSE),0)*$I$19 ), "")) -> #VALUE! | I12: FY2026 | J12: 1000 | K12: 7129.08
A13: E_StatusQuo_Targets_150 | B13: 150 | C13: E_StatusQuo_Targets_150|150 | D13: =IFERROR( (SUMPRODUCT((MultiYear_ProForma!$A:$A="E_StatusQuo_Targets_150")*(MultiYear_ProForma!$B:$B="FY2028")*(MultiYear_ProForma!$L:$L)) + (IFERROR(VLOOKUP("E_StatusQuo_Targets_150",$H$4:$I$9,2,FALSE),0)*$I$19*(VLOOKUP("FY2028",$H$11:$J$15,3,TRUE)+VLOOKUP("FY2028",$H$11:$J$15,2,TRUE))) ) / ( SUMPRODUCT((MultiYear_ProForma!$A:$A="E_StatusQuo_Targets_150")*(MultiYear_ProForma!$B:$B="FY2028")*(MultiYear_ProForma!$F:$F)) + IFERROR(VLOOKUP("E_StatusQuo_Targets_150",$H$4:$I$9,2,FALSE),0)*$I$19 ), "") | E13: =IFERROR( (SUMPRODUCT((MultiYear_ProForma!$A:$A="E_StatusQuo_Targets_150")*(MultiYear_ProForma!$B:$B="FY2030")*(MultiYear_ProForma!$L:$L)) + (IFERROR(VLOOKUP("E_StatusQuo_Targets_150",$H$4:$I$9,2,FALSE),0)*$I$19*(VLOOKUP("FY2030",$H$11:$J$15,3,TRUE)+VLOOKUP("FY2030",$H$11:$J$15,2,TRUE))) ) / ( SUMPRODUCT((MultiYear_ProForma!$A:$A="E_StatusQuo_Targets_150")*(MultiYear_ProForma!$B:$B="FY2030")*(MultiYear_ProForma!$F:$F)) + IFERROR(VLOOKUP("E_StatusQuo_Targets_150",$H$4:$I$9,2,FALSE),0)*$I$19 ), "") | F13: =AVERAGE(IFERROR( (SUMPRODUCT((MultiYear_ProForma!$A:$A="E_StatusQuo_Targets_150")*(MultiYear_ProForma!$B:$B="FY2026")*(MultiYear_ProForma!$L:$L)) + (IFERROR(VLOOKUP("E_StatusQuo_Targets_150",$H$4:$I$9,2,FALSE),0)*$I$19*(VLOOKUP("FY2026",$H$11:$J$15,3,TRUE)+VLOOKUP("FY2026",$H$11:$J$15,2,TRUE))) ) / ( SUMPRODUCT((MultiYear_ProForma!$A:$A="E_StatusQuo_Targets_150")*(MultiYear_ProForma!$B:$B="FY2026")*(MultiYear_ProForma!$F:$F)) + IFERROR(VLOOKUP("E_StatusQuo_Targets_150",$H$4:$I$9,2,FALSE),0)*$I$19 ), ""),IFERROR( (SUMPRODUCT((MultiYear_ProForma!$A:$A="E_StatusQuo_Targets_150")*(MultiYear_ProForma!$B:$B="FY2027")*(MultiYear_ProForma!$L:$L)) + (IFERROR(VLOOKUP("E_StatusQuo_Targets_150",$H$4:$I$9,2,FALSE),0)*$I$19*(VLOOKUP("FY2027",$H$11:$J$15,3,TRUE)+VLOOKUP("FY2027",$H$11:$J$15,2,TRUE))) ) / ( SUMPRODUCT((MultiYear_ProForma!$A:$A="E_StatusQuo_Targets_150")*(MultiYear_ProForma!$B:$B="FY2027")*(MultiYear_ProForma!$F:$F)) + IFERROR(VLOOKUP("E_StatusQuo_Targets_150",$H$4:$I$9,2,FALSE),0)*$I$19 ), ""),IFERROR( (SUMPRODUCT((MultiYear_ProForma!$A:$A="E_StatusQuo_Targets_150")*(MultiYear_ProForma!$B:$B="FY2028")*(MultiYear_ProForma!$L:$L)) + (IFERROR(VLOOKUP("E_StatusQuo_Targets_150",$H$4:$I$9,2,FALSE),0)*$I$19*(VLOOKUP("FY2028",$H$11:$J$15,3,TRUE)+VLOOKUP("FY2028",$H$11:$J$15,2,TRUE))) ) / ( SUMPRODUCT((MultiYear_ProForma!$A:$A="E_StatusQuo_Targets_150")*(MultiYear_ProForma!$B:$B="FY2028")*(MultiYear_ProForma!$F:$F)) + IFERROR(VLOOKUP("E_StatusQuo_Targets_150",$H$4:$I$9,2,FALSE),0)*$I$19 ), "")) -> #VALUE! | I13: FY2027 | J13: 800 | K13: 7307.307
A14: F_CoLocation_Echo_0 | B14: 0 | C14: F_CoLocation_Echo_0|0 | D14: =IFERROR( (SUMPRODUCT((MultiYear_ProForma!$A:$A="F_CoLocation_Echo_0")*(MultiYear_ProForma!$B:$B="FY2028")*(MultiYear_ProForma!$L:$L)) + (IFERROR(VLOOKUP("F_CoLocation_Echo_0",$H$4:$I$9,2,FALSE),0)*$I$19*(VLOOKUP("FY2028",$H$11:$J$15,3,TRUE)+VLOOKUP("FY2028",$H$11:$J$15,2,TRUE))) ) / ( SUMPRODUCT((MultiYear_ProForma!$A:$A="F_CoLocation_Echo_0")*(MultiYear_ProForma!$B:$B="FY2028")*(MultiYear_ProForma!$F:$F)) + IFERROR(VLOOKUP("F_CoLocation_Echo_0",$H$4:$I$9,2,FALSE),0)*$I$19 ), "") | E14: =IFERROR( (SUMPRODUCT((MultiYear_ProForma!$A:$A="F_CoLocation_Echo_0")*(MultiYear_ProForma!$B:$B="FY2030")*(MultiYear_ProForma!$L:$L)) + (IFERROR(VLOOKUP("F_CoLocation_Echo_0",$H$4:$I$9,2,FALSE),0)*$I$19*(VLOOKUP("FY2030",$H$11:$J$15,3,TRUE)+VLOOKUP("FY2030",$H$11:$J$15,2,TRUE))) ) / ( SUMPRODUCT((MultiYear_ProForma!$A:$A="F_CoLocation_Echo_0")*(MultiYear_ProForma!$B:$B="FY2030")*(MultiYear_ProForma!$F:$F)) + IFERROR(VLOOKUP("F_CoLocation_Echo_0",$H$4:$I$9,2,FALSE),0)*$I$19 ), "") | F14: =AVERAGE(IFERROR( (SUMPRODUCT((MultiYear_ProForma!$A:$A="F_CoLocation_Echo_0")*(MultiYear_ProForma!$B:$B="FY2026")*(MultiYear_ProForma!$L:$L)) + (IFERROR(VLOOKUP("F_CoLocation_Echo_0",$H$4:$I$9,2,FALSE),0)*$I$19*(VLOOKUP("FY2026",$H$11:$J$15,3,TRUE)+VLOOKUP("FY2026",$H$11:$J$15,2,TRUE))) ) / ( SUMPRODUCT((MultiYear_ProForma!$A:$A="F_CoLocation_Echo_0")*(MultiYear_ProForma!$B:$B="FY2026")*(MultiYear_ProForma!$F:$F)) + IFERROR(VLOOKUP("F_CoLocation_Echo_0",$H$4:$I$9,2,FALSE),0)*$I$19 ), ""),IFERROR( (SUMPRODUCT((MultiYear_ProForma!$A:$A="F_CoLocation_Echo_0")*(MultiYear_ProForma!$B:$B="FY2027")*(MultiYear_ProForma!$L:$L)) + (IFERROR(VLOOKUP("F_CoLocation_Echo_0",$H$4:$I$9,2,FALSE),0)*$I$19*(VLOOKUP("FY2027",$H$11:$J$15,3,TRUE)+VLOOKUP("FY2027",$H$11:$J$15,2,TRUE))) ) / ( SUMPRODUCT((MultiYear_ProForma!$A:$A="F_CoLocation_Echo_0")*(MultiYear_ProForma!$B:$B="FY2027")*(MultiYear_ProForma!$F:$F)) + IFERROR(VLOOKUP("F_CoLocation_Echo_0",$H$4:$I$9,2,FALSE),0)*$I$19 ), ""),IFERROR( (SUMPRODUCT((MultiYear_ProForma!$A:$A="F_CoLocation_Echo_0")*(MultiYear_ProForma!$B:$B="FY2028")*(MultiYear_ProForma!$L:$L)) + (IFERROR(VLOOKUP("F_CoLocation_Echo_0",$H$4:$I$9,2,FALSE),0)*$I$19*(VLOOKUP("FY2028",$H$11:$J$15,3,TRUE)+VLOOKUP("FY2028",$H$11:$J$15,2,TRUE))) ) / ( SUMPRODUCT((MultiYear_ProForma!$A:$A="F_CoLocation_Echo_0")*(MultiYear_ProForma!$B:$B="FY2028")*(MultiYear_ProForma!$F:$F)) + IFERROR(VLOOKUP("F_CoLocation_Echo_0",$H$4:$I$9,2,FALSE),0)*$I$19 ), "")) -> #VALUE! | I14: FY2028 | J14: 600 | K14: 7489.9897
A15: F_CoLocation_Echo_100 | B15: 100 | C15: F_CoLocation_Echo_100|100 | D15: =IFERROR( (SUMPRODUCT((MultiYear_ProForma!$A:$A="F_CoLocation_Echo_100")*(MultiYear_ProForma!$B:$B="FY2028")*(MultiYear_ProForma!$L:$L)) + (IFERROR(VLOOKUP("F_CoLocation_Echo_100",$H$4:$I$9,2,FALSE),0)*$I$19*(VLOOKUP("FY2028",$H$11:$J$15,3,TRUE)+VLOOKUP("FY2028",$H$11:$J$15,2,TRUE))) ) / ( SUMPRODUCT((MultiYear_ProForma!$A:$A="F_CoLocation_Echo_100")*(MultiYear_ProForma!$B:$B="FY2028")*(MultiYear_ProForma!$F:$F)) + IFERROR(VLOOKUP("F_CoLocation_Echo_100",$H$4:$I$9,2,FALSE),0)*$I$19 ), "") | E15: =IFERROR( (SUMPRODUCT((MultiYear_ProForma!$A:$A="F_CoLocation_Echo_100")*(MultiYear_ProForma!$B:$B="FY2030")*(MultiYear_ProForma!$L:$L)) + (IFERROR(VLOOKUP("F_CoLocation_Echo_100",$H$4:$I$9,2,FALSE),0)*$I$19*(VLOOKUP("FY2030",$H$11:$J$15,3,TRUE)+VLOOKUP("FY2030",$H$11:$J$15,2,TRUE))) ) / ( SUMPRODUCT((MultiYear_ProForma!$A:$A="F_CoLocation_Echo_100")*(MultiYear_ProForma!$B:$B="FY2030")*(MultiYear_ProForma!$F:$F)) + IFERROR(VLOOKUP("F_CoLocation_Echo_100",$H$4:$I$9,2,FALSE),0)*$I$19 ), "") | F15: =AVERAGE(IFERROR( (SUMPRODUCT((MultiYear_ProForma!$A:$A="F_CoLocation_Echo_100")*(MultiYear_ProForma!$B:$B="FY2026")*(MultiYear_ProForma!$L:$L)) + (IFERROR(VLOOKUP("F_CoLocation_Echo_100",$H$4:$I$9,2,FALSE),0)*$I$19*(VLOOKUP("FY2026",$H$11:$J$15,3,TRUE)+VLOOKUP("FY2026",$H$11:$J$15,2,TRUE))) ) / ( SUMPRODUCT((MultiYear_ProForma!$A:$A="F_CoLocation_Echo_100")*(MultiYear_ProForma!$B:$B="FY2026")*(MultiYear_ProForma!$F:$F)) + IFERROR(VLOOKUP("F_CoLocation_Echo_100",$H$4:$I$9,2,FALSE),0)*$I$19 ), ""),IFERROR( (SUMPRODUCT((MultiYear_ProForma!$A:$A="F_CoLocation_Echo_100")*(MultiYear_ProForma!$B:$B="FY2027")*(MultiYear_ProForma!$L:$L)) + (IFERROR(VLOOKUP("F_CoLocation_Echo_100",$H$4:$I$9,2,FALSE),0)*$I$19*(VLOOKUP("FY2027",$H$11:$J$15,3,TRUE)+VLOOKUP("FY2027",$H$11:$J$15,2,TRUE))) ) / ( SUMPRODUCT((MultiYear_ProForma!$A:$A="F_CoLocation_Echo_100")*(MultiYear_ProForma!$B:$B="FY2027")*(MultiYear_ProForma!$F:$F)) + IFERROR(VLOOKUP("F_CoLocation_Echo_100",$H$4:$I$9,2,FALSE),0)*$I$19 ), ""),IFERROR( (SUMPRODUCT((MultiYear_ProForma!$A:$A="F_CoLocation_Echo_100")*(MultiYear_ProForma!$B:$B="FY2028")*(MultiYear_ProForma!$L:$L)) + (IFERROR(VLOOKUP("F_CoLocation_Echo_100",$H$4:$I$9,2,FALSE),0)*$I$19*(VLOOKUP("FY2028",$H$11:$J$15,3,TRUE)+VLOOKUP("FY2028",$H$11:$J$15,2,TRUE))) ) / ( SUMPRODUCT((MultiYear_ProForma!$A:$A="F_CoLocation_Echo_100")*(MultiYear_ProForma!$B:$B="FY2028")*(MultiYear_ProForma!$F:$F)) + IFERROR(VLOOKUP("F_CoLocation_Echo_100",$H$4:$I$9,2,FALSE),0)*$I$19 ), "")) -> #VALUE! | I15: FY2029 | J15: 400 | K15: 7677.2394
A16: F_CoLocation_Echo_150 | B16: 150 | C16: F_CoLocation_Echo_150|150 | D16: =IFERROR( (SUMPRODUCT((MultiYear_ProForma!$A:$A="F_CoLocation_Echo_150")*(MultiYear_ProForma!$B:$B="FY2028")*(MultiYear_ProForma!$L:$L)) + (IFERROR(VLOOKUP("F_CoLocation_Echo_150",$H$4:$I$9,2,FALSE),0)*$I$19*(VLOOKUP("FY2028",$H$11:$J$15,3,TRUE)+VLOOKUP("FY2028",$H$11:$J$15,2,TRUE))) ) / ( SUMPRODUCT((MultiYear_ProForma!$A:$A="F_CoLocation_Echo_150")*(MultiYear_ProForma!$B:$B="FY2028")*(MultiYear_ProForma!$F:$F)) + IFERROR(VLOOKUP("F_CoLocation_Echo_150",$H$4:$I$9,2,FALSE),0)*$I$19 ), "") | E16: =IFERROR( (SUMPRODUCT((MultiYear_ProForma!$A:$A="F_CoLocation_Echo_150")*(MultiYear_ProForma!$B:$B="FY2030")*(MultiYear_ProForma!$L:$L)) + (IFERROR(VLOOKUP("F_CoLocation_Echo_150",$H$4:$I$9,2,FALSE),0)*$I$19*(VLOOKUP("FY2030",$H$11:$J$15,3,TRUE)+VLOOKUP("FY2030",$H$11:$J$15,2,TRUE))) ) / ( SUMPRODUCT((MultiYear_ProForma!$A:$A="F_CoLocation_Echo_150")*(MultiYear_ProForma!$B:$B="FY2030")*(MultiYear_ProForma!$F:$F)) + IFERROR(VLOOKUP("F_CoLocation_Echo_150",$H$4:$I$9,2,FALSE),0)*$I$19 ), "") | F16: =AVERAGE(IFERROR( (SUMPRODUCT((MultiYear_ProForma!$A:$A="F_CoLocation_Echo_150")*(MultiYear_ProForma!$B:$B="FY2026")*(MultiYear_ProForma!$L:$L)) + (IFERROR(VLOOKUP("F_CoLocation_Echo_150",$H$4:$I$9,2,FALSE),0)*$I$19*(VLOOKUP("FY2026",$H$11:$J$15,3,TRUE)+VLOOKUP("FY2026",$H$11:$J$15,2,TRUE))) ) / ( SUMPRODUCT((MultiYear_ProForma!$A:$A="F_CoLocation_Echo_150")*(MultiYear_ProForma!$B:$B="FY2026")*(MultiYear_ProForma!$F:$F)) + IFERROR(VLOOKUP("F_CoLocation_Echo_150",$H$4:$I$9,2,FALSE),0)*$I$19 ), ""),IFERROR( (SUMPRODUCT((MultiYear_ProForma!$A:$A="F_CoLocation_Echo_150")*(MultiYear_ProForma!$B:$B="FY2027")*(MultiYear_ProForma!$L:$L)) + (IFERROR(VLOOKUP("F_CoLocation_Echo_150",$H$4:$I$9,2,FALSE),0)*$I$19*(VLOOKUP("FY2027",$H$11:$J$15,3,TRUE)+VLOOKUP("FY2027",$H$11:$J$15,2,TRUE))) ) / ( SUMPRODUCT((MultiYear_ProForma!$A:$A="F_CoLocation_Echo_150")*(MultiYear_ProForma!$B:$B="FY2027")*(MultiYear_ProForma!$F:$F)) + IFERROR(VLOOKUP("F_CoLocation_Echo_150",$H$4:$I$9,2,FALSE),0)*$I$19 ), ""),IFERROR( (SUMPRODUCT((MultiYear_ProForma!$A:$A="F_CoLocation_Echo_150")*(MultiYear_ProForma!$B:$B="FY2028")*(MultiYear_ProForma!$L:$L)) + (IFERROR(VLOOKUP("F_CoLocation_Echo_150",$H$4:$I$9,2,FALSE),0)*$I$19*(VLOOKUP("FY2028",$H$11:$J$15,3,TRUE)+VLOOKUP("FY2028",$H$11:$J$15,2,TRUE))) ) / ( SUMPRODUCT((MultiYear_ProForma!$A:$A="F_CoLocation_Echo_150")*(MultiYear_ProForma!$B:$B="FY2028")*(MultiYear_ProForma!$F:$F)) + IFERROR(VLOOKUP("F_CoLocation_Echo_150",$H$4:$I$9,2,FALSE),0)*$I$19 ), "")) -> #VALUE! | I16: FY2030 | J16: 300 | K16: 7869.1704
A17: G_DHub_EchoRamp | B17: 150 | C17: G_DHub_EchoRamp|150 | D17: =IFERROR( (SUMPRODUCT((MultiYear_ProForma!$A:$A="G_DHub_EchoRamp")*(MultiYear_ProForma!$B:$B="FY2028")*(MultiYear_ProForma!$L:$L)) + (IFERROR(VLOOKUP("G_DHub_EchoRamp",$H$4:$I$9,2,FALSE),0)*$I$19*(VLOOKUP("FY2028",$H$11:$J$15,3,TRUE)+VLOOKUP("FY2028",$H$11:$J$15,2,TRUE))) ) / ( SUMPRODUCT((MultiYear_ProForma!$A:$A="G_DHub_EchoRamp")*(MultiYear_ProForma!$B:$B="FY2028")*(MultiYear_ProForma!$F:$F)) + IFERROR(VLOOKUP("G_DHub_EchoRamp",$H$4:$I$9,2,FALSE),0)*$I$19 ), "") | E17: =IFERROR( (SUMPRODUCT((MultiYear_ProForma!$A:$A="G_DHub_EchoRamp")*(MultiYear_ProForma!$B:$B="FY2030")*(MultiYear_ProForma!$L:$L)) + (IFERROR(VLOOKUP("G_DHub_EchoRamp",$H$4:$I$9,2,FALSE),0)*$I$19*(VLOOKUP("FY2030",$H$11:$J$15,3,TRUE)+VLOOKUP("FY2030",$H$11:$J$15,2,TRUE))) ) / ( SUMPRODUCT((MultiYear_ProForma!$A:$A="G_DHub_EchoRamp")*(MultiYear_ProForma!$B:$B="FY2030")*(MultiYear_ProForma!$F:$F)) + IFERROR(VLOOKUP("G_DHub_EchoRamp",$H$4:$I$9,2,FALSE),0)*$I$19 ), "") | F17: =AVERAGE(IFERROR( (SUMPRODUCT((MultiYear_ProForma!$A:$A="G_DHub_EchoRamp")*(MultiYear_ProForma!$B:$B="FY2026")*(MultiYear_ProForma!$L:$L)) + (IFERROR(VLOOKUP("G_DHub_EchoRamp",$H$4:$I$9,2,FALSE),0)*$I$19*(VLOOKUP("FY2026",$H$11:$J$15,3,TRUE)+VLOOKUP("FY2026",$H$11:$J$15,2,TRUE))) ) / ( SUMPRODUCT((MultiYear_ProForma!$A:$A="G_DHub_EchoRamp")*(MultiYear_ProForma!$B:$B="FY2026")*(MultiYear_ProForma!$F:$F)) + IFERROR(VLOOKUP("G_DHub_EchoRamp",$H$4:$I$9,2,FALSE),0)*$I$19 ), ""),IFERROR( (SUMPRODUCT((MultiYear_ProForma!$A:$A="G_DHub_EchoRamp")*(MultiYear_ProForma!$B:$B="FY2027")*(MultiYear_ProForma!$L:$L)) + (IFERROR(VLOOKUP("G_DHub_EchoRamp",$H$4:$I$9,2,FALSE),0)*$I$19*(VLOOKUP("FY2027",$H$11:$J$15,3,TRUE)+VLOOKUP("FY2027",$H$11:$J$15,2,TRUE))) ) / ( SUMPRODUCT((MultiYear_ProForma!$A:$A="G_DHub_EchoRamp")*(MultiYear_ProForma!$B:$B="FY2027")*(MultiYear_ProForma!$F:$F)) + IFERROR(VLOOKUP("G_DHub_EchoRamp",$H$4:$I$9,2,FALSE),0)*$I$19 ), ""),IFERROR( (SUMPRODUCT((MultiYear_ProForma!$A:$A="G_DHub_EchoRamp")*(MultiYear_ProForma!$B:$B="FY2028")*(MultiYear_ProForma!$L:$L)) + (IFERROR(VLOOKUP("G_DHub_EchoRamp",$H$4:$I$9,2,FALSE),0)*$I$19*(VLOOKUP("FY2028",$H$11:$J$15,3,TRUE)+VLOOKUP("FY2028",$H$11:$J$15,2,TRUE))) ) / ( SUMPRODUCT((MultiYear_ProForma!$A:$A="G_DHub_EchoRamp")*(MultiYear_ProForma!$B:$B="FY2028")*(MultiYear_ProForma!$F:$F)) + IFERROR(VLOOKUP("G_DHub_EchoRamp",$H$4:$I$9,2,FALSE),0)*$I$19 ), "")) -> #VALUE!
C18: None|None
C19: None|None | I19: Retention (r) used for Summary | J19: 0.75

Sheet BreakEven_Calc
A1: Helper | B1: FY28 | C1: FY30
A2: Fixed_total ($) | B2: =Calc!B2 -> 1689592 | C2: =Calc!F2 -> 1864993.4
A3: Var_unit ($/student) | B3: =Calc!B3 -> 7129.08 | C3: =Calc!F3 -> 7869.1704
A4: Total base ADM | B4: =Calc!B11 -> 553 | C4: =Calc!B11 -> 553
A6: Select target scenario | B6: D_Grow_Both
A7: Select overlay (0/100/150) | B7: 150
A8: Select year (2028 or 2030) | B8: 2030
A9: Receiving overhead h ($) | B9: 300
A10: Fixed-carry f (fraction) | B10: 0.2
A12: C_target (Comparable $/student)
B13: =IF($B$8="2028", INDEX(Summary_Costs!$D:$D, MATCH($B$6&"|"&$B$7, Summary_Costs!$C:$C,0)), INDEX(Summary_Costs!$E:$E, MATCH($B$6&"|"&$B$7, Summary_Costs!$C:$C,0))) -> #N/A
A15: Break‑even retention r*
B16: =IF($B$8="2028", ($B$10*$B$2)/( $B$4 * ($B$13 - ($B$3 + $B$8)) ), ($B$10*$C$2)/( $B$4 * ($B$13 - ($C$3 + $B$8)) )) -> #N/A
A18: How to use | B18: 1) Select target/overlay/year; 2) Enter overhead h and fixed‑carry f; 3) Read r*; 4) Grid sweeps f across h bands. Positive r* means minimum retention for A to break even with target. If r* ≤ 0, A is already cheaper at those assumptions; if r* > 1, A cannot break even under those assumptions.
A20: Grid: r* vs f (rows) by h (cols)
A21: f \ h | B21: 200 | C21: 300 | D21: 400 | E21: 600 | F21: 800 | G21: 1000 | H21: 1200 | I21: 1500
A22: 0 | B22: =IF($B$8="2028", (0*$B$2)/($B$4*($B$13-($B$3+200))), (0*$C$2)/($B$4*($B$13-($C$3+200)))) -> #N/A | C22: =IF($B$8="2028", (0*$B$2)/($B$4*($B$13-($B$3+300))), (0*$C$2)/($B$4*($B$13-($C$3+300)))) -> #N/A | D22: =IF($B$8="2028", (0*$B$2)/($B$4*($B$13-($B$3+400))), (0*$C$2)/($B$4*($B$13-($C$3+400)))) -> #N/A | E22: =IF($B$8="2028", (0*$B$2)/($B$4*($B$13-($B$3+600))), (0*$C$2)/($B$4*($B$13-($C$3+600)))) -> #N/A | F22: =IF($B$8="2028", (0*$B$2)/($B$4*($B$13-($B$3+800))), (0*$C$2)/($B$4*($B$13-($C$3+800)))) -> #N/A | G22: =IF($B$8="2028", (0*$B$2)/($B$4*($B$13-($B$3+1000))), (0*$C$2)/($B$4*($B$13-($C$3+1000)))) -> #N/A | H22: =IF($B$8="2028", (0*$B$2)/($B$4*($B$13-($B$3+1200))), (0*$C$2)/($B$4*($B$13-($C$3+1200)))) -> #N/A | I22: =IF($B$8="2028", (0*$B$2)/($B$4*($B$13-($B$3+1500))), (0*$C$2)/($B$4*($B$13-($C$3+1500)))) -> #N/A
A23: 0.05 | B23: =IF($B$8="2028", (0.05*$B$2)/($B$4*($B$13-($B$3+200))), (0.05*$C$2)/($B$4*($B$13-($C$3+200)))) -> #N/A | C23: =IF($B$8="2028", (0.05*$B$2)/($B$4*($B$13-($B$3+300))), (0.05*$C$2)/($B$4*($B$13-($C$3+300)))) -> #N/A | D23: =IF($B$8="2028", (0.05*$B$2)/($B$4*($B$13-($B$3+400))), (0.05*$C$2)/($B$4*($B$13-($C$3+400)))) -> #N/A | E23: =IF($B$8="2028", (0.05*$B$2)/($B$4*($B$13-($B$3+600))), (0.05*$C$2)/($B$4*($B$13-($C$3+600)))) -> #N/A | F23: =IF($B$8="2028", (0.05*$B$2)/($B$4*($B$13-($B$3+800))), (0.05*$C$2)/($B$4*($B$13-($C$3+800)))) -> #N/A | G23: =IF($B$8="2028", (0.05*$B$2)/($B$4*($B$13-($B$3+1000))), (0.05*$C$2)/($B$4*($B$13-($C$3+1000)))) -> #N/A | H23: =IF($B$8="2028", (0.05*$B$2)/($B$4*($B$13-($B$3+1200))), (0.05*$C$2)/($B$4*($B$13-($C$3+1200)))) -> #N/A | I23: =IF($B$8="2028", (0.05*$B$2)/($B$4*($B$13-($B$3+1500))), (0.05*$C$2)/($B$4*($B$13-($C$3+1500)))) -> #N/A
A24: 0.1 | B24: =IF($B$8="2028", (0.1*$B$2)/($B$4*($B$13-($B$3+200))), (0.1*$C$2)/($B$4*($B$13-($C$3+200)))) -> #N/A | C24: =IF($B$8="2028", (0.1*$B$2)/($B$4*($B$13-($B$3+300))), (0.1*$C$2)/($B$4*($B$13-($C$3+300)))) -> #N/A | D24: =IF($B$8="2028", (0.1*$B$2)/($B$4*($B$13-($B$3+400))), (0.1*$C$2)/($B$4*($B$13-($C$3+400)))) -> #N/A | E24: =IF($B$8="2028", (0.1*$B$2)/($B$4*($B$13-($B$3+600))), (0.1*$C$2)/($B$4*($B$13-($C$3+600)))) -> #N/A | F24: =IF($B$8="2028", (0.1*$B$2)/($B$4*($B$13-($B$3+800))), (0.1*$C$2)/($B$4*($B$13-($C$3+800)))) -> #N/A | G24: =IF($B$8="2028", (0.1*$B$2)/($B$4*($B$13-($B$3+1000))), (0.1*$C$2)/($B$4*($B$13-($C$3+1000)))) -> #N/A | H24: =IF($B$8="2028", (0.1*$B$2)/($B$4*($B$13-($B$3+1200))), (0.1*$C$2)/($B$4*($B$13-($C$3+1200)))) -> #N/A | I24: =IF($B$8="2028", (0.1*$B$2)/($B$4*($B$13-($B$3+1500))), (0.1*$C$2)/($B$4*($B$13-($C$3+1500)))) -> #N/A
A25: 0.15 | B25: =IF($B$8="2028", (0.15*$B$2)/($B$4*($B$13-($B$3+200))), (0.15*$C$2)/($B$4*($B$13-($C$3+200)))) -> #N/A | C25: =IF($B$8="2028", (0.15*$B$2)/($B$4*($B$13-($B$3+300))), (0.15*$C$2)/($B$4*($B$13-($C$3+300)))) -> #N/A | D25: =IF($B$8="2028", (0.15*$B$2)/($B$4*($B$13-($B$3+400))), (0.15*$C$2)/($B$4*($B$13-($C$3+400)))) -> #N/A | E25: =IF($B$8="2028", (0.15*$B$2)/($B$4*($B$13-($B$3+600))), (0.15*$C$2)/($B$4*($B$13-($C$3+600)))) -> #N/A | F25: =IF($B$8="2028", (0.15*$B$2)/($B$4*($B$13-($B$3+800))), (0.15*$C$2)/($B$4*($B$13-($C$3+800)))) -> #N/A | G25: =IF($B$8="2028", (0.15*$B$2)/($B$4*($B$13-($B$3+1000))), (0.15*$C$2)/($B$4*($B$13-($C$3+1000)))) -> #N/A | H25: =IF($B$8="2028", (0.15*$B$2)/($B$4*($B$13-($B$3+1200))), (0.15*$C$2)/($B$4*($B$13-($C$3+1200)))) -> #N/A | I25: =IF($B$8="2028", (0.15*$B$2)/($B$4*($B$13-($B$3+1500))), (0.15*$C$2)/($B$4*($B$13-($C$3+1500)))) -> #N/A
A26: 0.2 | B26: =IF($B$8="2028", (0.2*$B$2)/($B$4*($B$13-($B$3+200))), (0.2*$C$2)/($B$4*($B$13-($C$3+200)))) -> #N/A | C26: =IF($B$8="2028", (0.2*$B$2)/($B$4*($B$13-($B$3+300))), (0.2*$C$2)/($B$4*($B$13-($C$3+300)))) -> #N/A | D26: =IF($B$8="2028", (0.2*$B$2)/($B$4*($B$13-($B$3+400))), (0.2*$C$2)/($B$4*($B$13-($C$3+400)))) -> #N/A | E26: =IF($B$8="2028", (0.2*$B$2)/($B$4*($B$13-($B$3+600))), (0.2*$C$2)/($B$4*($B$13-($C$3+600)))) -> #N/A | F26: =IF($B$8="2028", (0.2*$B$2)/($B$4*($B$13-($B$3+800))), (0.2*$C$2)/($B$4*($B$13-($C$3+800)))) -> #N/A | G26: =IF($B$8="2028", (0.2*$B$2)/($B$4*($B$13-($B$3+1000))), (0.2*$C$2)/($B$4*($B$13-($C$3+1000)))) -> #N/A | H26: =IF($B$8="2028", (0.2*$B$2)/($B$4*($B$13-($B$3+1200))), (0.2*$C$2)/($B$4*($B$13-($C$3+1200)))) -> #N/A | I26: =IF($B$8="2028", (0.2*$B$2)/($B$4*($B$13-($B$3+1500))), (0.2*$C$2)/($B$4*($B$13-($C$3+1500)))) -> #N/A
A27: 0.25 | B27: =IF($B$8="2028", (0.25*$B$2)/($B$4*($B$13-($B$3+200))), (0.25*$C$2)/($B$4*($B$13-($C$3+200)))) -> #N/A | C27: =IF($B$8="2028", (0.25*$B$2)/($B$4*($B$13-($B$3+300))), (0.25*$C$2)/($B$4*($B$13-($C$3+300)))) -> #N/A | D27: =IF($B$8="2028", (0.25*$B$2)/($B$4*($B$13-($B$3+400))), (0.25*$C$2)/($B$4*($B$13-($C$3+400)))) -> #N/A | E27: =IF($B$8="2028", (0.25*$B$2)/($B$4*($B$13-($B$3+600))), (0.25*$C$2)/($B$4*($B$13-($C$3+600)))) -> #N/A | F27: =IF($B$8="2028", (0.25*$B$2)/($B$4*($B$13-($B$3+800))), (0.25*$C$2)/($B$4*($B$13-($C$3+800)))) -> #N/A | G27: =IF($B$8="2028", (0.25*$B$2)/($B$4*($B$13-($B$3+1000))), (0.25*$C$2)/($B$4*($B$13-($C$3+1000)))) -> #N/A | H27: =IF($B$8="2028", (0.25*$B$2)/($B$4*($B$13-($B$3+1200))), (0.25*$C$2)/($B$4*($B$13-($C$3+1200)))) -> #N/A | I27: =IF($B$8="2028", (0.25*$B$2)/($B$4*($B$13-($B$3+1500))), (0.25*$C$2)/($B$4*($B$13-($C$3+1500)))) -> #N/A
A28: 0.3 | B28: =IF($B$8="2028", (0.3*$B$2)/($B$4*($B$13-($B$3+200))), (0.3*$C$2)/($B$4*($B$13-($C$3+200)))) -> #N/A | C28: =IF($B$8="2028", (0.3*$B$2)/($B$4*($B$13-($B$3+300))), (0.3*$C$2)/($B$4*($B$13-($C$3+300)))) -> #N/A | D28: =IF($B$8="2028", (0.3*$B$2)/($B$4*($B$13-($B$3+400))), (0.3*$C$2)/($B$4*($B$13-($C$3+400)))) -> #N/A | E28: =IF($B$8="2028", (0.3*$B$2)/($B$4*($B$13-($B$3+600))), (0.3*$C$2)/($B$4*($B$13-($C$3+600)))) -> #N/A | F28: =IF($B$8="2028", (0.3*$B$2)/($B$4*($B$13-($B$3+800))), (0.3*$C$2)/($B$4*($B$13-($C$3+800)))) -> #N/A | G28: =IF($B$8="2028", (0.3*$B$2)/($B$4*($B$13-($B$3+1000))), (0.3*$C$2)/($B$4*($B$13-($C$3+1000)))) -> #N/A | H28: =IF($B$8="2028", (0.3*$B$2)/($B$4*($B$13-($B$3+1200))), (0.3*$C$2)/($B$4*($B$13-($C$3+1200)))) -> #N/A | I28: =IF($B$8="2028", (0.3*$B$2)/($B$4*($B$13-($B$3+1500))), (0.3*$C$2)/($B$4*($B$13-($C$3+1500)))) -> #N/A
A29: 0.35 | B29: =IF($B$8="2028", (0.35*$B$2)/($B$4*($B$13-($B$3+200))), (0.35*$C$2)/($B$4*($B$13-($C$3+200)))) -> #N/A | C29: =IF($B$8="2028", (0.35*$B$2)/($B$4*($B$13-($B$3+300))), (0.35*$C$2)/($B$4*($B$13-($C$3+300)))) -> #N/A | D29: =IF($B$8="2028", (0.35*$B$2)/($B$4*($B$13-($B$3+400))), (0.35*$C$2)/($B$4*($B$13-($C$3+400)))) -> #N/A | E29: =IF($B$8="2028", (0.35*$B$2)/($B$4*($B$13-($B$3+600))), (0.35*$C$2)/($B$4*($B$13-($C$3+600)))) -> #N/A | F29: =IF($B$8="2028", (0.35*$B$2)/($B$4*($B$13-($B$3+800))), (0.35*$C$2)/($B$4*($B$13-($C$3+800)))) -> #N/A | G29: =IF($B$8="2028", (0.35*$B$2)/($B$4*($B$13-($B$3+1000))), (0.35*$C$2)/($B$4*($B$13-($C$3+1000)))) -> #N/A | H29: =IF($B$8="2028", (0.35*$B$2)/($B$4*($B$13-($B$3+1200))), (0.35*$C$2)/($B$4*($B$13-($C$3+1200)))) -> #N/A | I29: =IF($B$8="2028", (0.35*$B$2)/($B$4*($B$13-($B$3+1500))), (0.35*$C$2)/($B$4*($B$13-($C$3+1500)))) -> #N/A
A30: 0.4 | B30: =IF($B$8="2028", (0.4*$B$2)/($B$4*($B$13-($B$3+200))), (0.4*$C$2)/($B$4*($B$13-($C$3+200)))) -> #N/A | C30: =IF($B$8="2028", (0.4*$B$2)/($B$4*($B$13-($B$3+300))), (0.4*$C$2)/($B$4*($B$13-($C$3+300)))) -> #N/A | D30: =IF($B$8="2028", (0.4*$B$2)/($B$4*($B$13-($B$3+400))), (0.4*$C$2)/($B$4*($B$13-($C$3+400)))) -> #N/A | E30: =IF($B$8="2028", (0.4*$B$2)/($B$4*($B$13-($B$3+600))), (0.4*$C$2)/($B$4*($B$13-($C$3+600)))) -> #N/A | F30: =IF($B$8="2028", (0.4*$B$2)/($B$4*($B$13-($B$3+800))), (0.4*$C$2)/($B$4*($B$13-($C$3+800)))) -> #N/A | G30: =IF($B$8="2028", (0.4*$B$2)/($B$4*($B$13-($B$3+1000))), (0.4*$C$2)/($B$4*($B$13-($C$3+1000)))) -> #N/A | H30: =IF($B$8="2028", (0.4*$B$2)/($B$4*($B$13-($B$3+1200))), (0.4*$C$2)/($B$4*($B$13-($C$3+1200)))) -> #N/A | I30: =IF($B$8="2028", (0.4*$B$2)/($B$4*($B$13-($B$3+1500))), (0.4*$C$2)/($B$4*($B$13-($C$3+1500)))) -> #N/A

Sheet Sources
A1: Topic | B1: Source / Link | C1: What we used it for
A2: SUSD ACFR (fund structure; M&O vs Debt Service) | B2: SUSD Annual Comprehensive Financial Report (latest) | C2: To confirm M&O/plant carry and that debt service is separate; closures don’t erase plant/insurance without lease/sale.
A3: AZ Auditor General—transport benchmarks | B3: Arizona Auditor General transportation cost per rider and efficiency reports | C3: To anchor receiving overhead h bands ($500–$1,500).
A4: Chicago 2013 closures—retention/outcomes | B4: UChicago Consortium on School Research (2015) | C4: Retention and outcome context; informs 65–85% retention bands.
A5: Denver closures—charter capture & pause | B5: Chalkbeat/Denverite reporting (2024–2025) | C5: Demonstrates choice‑market retention risk and the case for iterative right‑sizing.
A6: Kyrene revision (9 → 7) | B6: Kyrene ESD public materials | C6: Local example of phased iteration.
