Workbook
Name ADM_Day_Select: Parameters_Public!C8
Name BaseAid_per_ADM: Parameters_Public!C18
Name Capex_ArtsHub: Parameters_Public!C28
Name Capex_in_MO_Toggle: Parameters_Public!C30
Name Capex_InnovHub: Parameters_Public!C29
Name Echo_ADM0: Parameters_Public!C10
Name EchoFixed_FY25_Total: Site_Fixed!C8
Name M_O_per_ADM_Audited: Parameters_Public!C14
Name Override_per_ADM_proxy: Parameters_Public!C19
Name Override_Percent: Parameters_Public!C17
Name Override_Toggle: Parameters_Public!C20
Name Pima_ADM0: Parameters_Public!C11
Name PimaFixed_FY25_Total: Site_Fixed!C15
Name TI_in_MO_Toggle: Parameters_Public!C26
Name TI_per_Site: Parameters_Public!C27

Sheet Workbook_Purpose_Overview

Sheet Summary_Figures
A1: Base (for comparison) | B1: H_StatusQuo_Decline | M1: Chart title
M2: ="Change in ops net $ by scenario compared to "&B1&" (Positive = savings)" -> Change in ops net $ by scenario compared to H_StatusQuo_Decline (Positive = savings)
A4: Scenario | B4: One-time Capital (FY26) | C4: NET2026 | D4: NET2028 | E4: NET2030 | F4: AVG5 | G4: DISP | H4: SRV2030 | I4: Δ vs Base (FY2030 Net) | J4: Δ vs Base (5-yr Avg Net)
A5: D_CUSTOM1 | B5: =SUMIFS(Capital_Summary!$H$4:$H$83, Capital_Summary!$A$4:$A$83, A5, Capital_Summary!$B$4:$B$83, "FY2026") -> 0 | C5: =SUMIFS(MultiYear_ProForma!$AF$2:$AF$66, MultiYear_ProForma!$B$2:$B$66, A5, MultiYear_ProForma!$C$2:$C$66, "FY2026") -> -459335.03 | D5: =SUMIFS(MultiYear_ProForma!$AF$2:$AF$66, MultiYear_ProForma!$B$2:$B$66, A5, MultiYear_ProForma!$C$2:$C$66, "FY2028") -> -482588.87 | E5: =SUMIFS(MultiYear_ProForma!$AF$2:$AF$66, MultiYear_ProForma!$B$2:$B$66, A5, MultiYear_ProForma!$C$2:$C$66, "FY2030") -> -507019.93 | F5: =(SUMIFS(MultiYear_ProForma!$AF$2:$AF$66, MultiYear_ProForma!$B$2:$B$66, A5, MultiYear_ProForma!$C$2:$C$66, "FY2026")+SUMIFS(MultiYear_ProForma!$AF$2:$AF$66, MultiYear_ProForma!$B$2:$B$66, A5, MultiYear_ProForma!$C$2:$C$66, "FY2027")+SUMIFS(MultiYear_ProForma!$AF$2:$AF$66, MultiYear_ProForma!$B$2:$B$66, A5, MultiYear_ProForma!$C$2:$C$66, "FY2028")+SUMIFS(MultiYear_ProForma!$AF$2:$AF$66, MultiYear_ProForma!$B$2:$B$66, A5, MultiYear_ProForma!$C$2:$C$66, "FY2029")+SUMIFS(MultiYear_ProForma!$AF$2:$AF$66, MultiYear_ProForma!$B$2:$B$66, A5, MultiYear_ProForma!$C$2:$C$66, "FY2030"))/5 -> -482883.16 | G5: =SUMIFS(MultiYear_ProForma!$N$2:$N$66, MultiYear_ProForma!$B$2:$B$66, A5, MultiYear_ProForma!$C$2:$C$66, "FY2026") -> 0 | H5: =SUMIFS(MultiYear_ProForma!$AC$2:$AC$66, MultiYear_ProForma!$B$2:$B$66, A5, MultiYear_ProForma!$C$2:$C$66, "FY2030") -> 553 | I5: =E5-(VLOOKUP($B$1,$A$5:$F$17,5, 0)) -> 217760.01 | J5: =F5-(VLOOKUP($B$1,$A$5:$H$17,6, 0)) -> 107303.43
A6: E_StatusQuo_Targets | B6: =SUMIFS(Capital_Summary!$H$4:$H$83, Capital_Summary!$A$4:$A$83, A6, Capital_Summary!$B$4:$B$83, "FY2026") -> 0 | C6: =SUMIFS(MultiYear_ProForma!$AF$2:$AF$66, MultiYear_ProForma!$B$2:$B$66, A6, MultiYear_ProForma!$C$2:$C$66, "FY2030") -> 703305.39 | D6: =SUMIFS(MultiYear_ProForma!$AF$2:$AF$66, MultiYear_ProForma!$B$2:$B$66, A6, MultiYear_ProForma!$C$2:$C$66, "FY2028") -> 669416.19 | E6: =SUMIFS(MultiYear_ProForma!$AF$2:$AF$66, MultiYear_ProForma!$B$2:$B$66, A6, MultiYear_ProForma!$C$2:$C$66, "FY2030") -> 703305.39 | F6: =(SUMIFS(MultiYear_ProForma!$AF$2:$AF$66, MultiYear_ProForma!$B$2:$B$66, A6, MultiYear_ProForma!$C$2:$C$66, "FY2026")+SUMIFS(MultiYear_ProForma!$AF$2:$AF$66, MultiYear_ProForma!$B$2:$B$66, A6, MultiYear_ProForma!$C$2:$C$66, "FY2027")+SUMIFS(MultiYear_ProForma!$AF$2:$AF$66, MultiYear_ProForma!$B$2:$B$66, A6, MultiYear_ProForma!$C$2:$C$66, "FY2028")+SUMIFS(MultiYear_ProForma!$AF$2:$AF$66, MultiYear_ProForma!$B$2:$B$66, A6, MultiYear_ProForma!$C$2:$C$66, "FY2029")+SUMIFS(MultiYear_ProForma!$AF$2:$AF$66, MultiYear_ProForma!$B$2:$B$66, A6, MultiYear_ProForma!$C$2:$C$66, "FY2030"))/5 -> 448697.93 | G6: =SUMIFS(MultiYear_ProForma!$N$2:$N$66, MultiYear_ProForma!$B$2:$B$66, A6, MultiYear_ProForma!$C$2:$C$66, "FY2026") -> 0 | H6: =SUMIFS(MultiYear_ProForma!$AC$2:$AC$66, MultiYear_ProForma!$B$2:$B$66, A6, MultiYear_ProForma!$C$2:$C$66, "FY2030") -> 653 | I6: =E6-(VLOOKUP($B$1,$A$5:$F$17,5, 0)) -> 1428085.3 | J6: =F6-(VLOOKUP($B$1,$A$5:$H$17,6, 0)) -> 1038884.5
A7: F_CoLocation_Echo_Targets | B7: =SUMIFS(Capital_Summary!$H$4:$H$83, Capital_Summary!$A$4:$A$83, A7, Capital_Summary!$B$4:$B$83, "FY2026") -> 0 | C7: =SUMIFS(MultiYear_ProForma!$AF$2:$AF$66, MultiYear_ProForma!$B$2:$B$66, A7, MultiYear_ProForma!$C$2:$C$66, "FY2030") -> 1063311.3 | D7: =SUMIFS(MultiYear_ProForma!$AF$2:$AF$66, MultiYear_ProForma!$B$2:$B$66, A7, MultiYear_ProForma!$C$2:$C$66, "FY2028") -> 1012075 | E7: =SUMIFS(MultiYear_ProForma!$AF$2:$AF$66, MultiYear_ProForma!$B$2:$B$66, A7, MultiYear_ProForma!$C$2:$C$66, "FY2030") -> 1063311.3 | F7: =(SUMIFS(MultiYear_ProForma!$AF$2:$AF$66, MultiYear_ProForma!$B$2:$B$66, A7, MultiYear_ProForma!$C$2:$C$66, "FY2026")+SUMIFS(MultiYear_ProForma!$AF$2:$AF$66, MultiYear_ProForma!$B$2:$B$66, A7, MultiYear_ProForma!$C$2:$C$66, "FY2027")+SUMIFS(MultiYear_ProForma!$AF$2:$AF$66, MultiYear_ProForma!$B$2:$B$66, A7, MultiYear_ProForma!$C$2:$C$66, "FY2028")+SUMIFS(MultiYear_ProForma!$AF$2:$AF$66, MultiYear_ProForma!$B$2:$B$66, A7, MultiYear_ProForma!$C$2:$C$66, "FY2029")+SUMIFS(MultiYear_ProForma!$AF$2:$AF$66, MultiYear_ProForma!$B$2:$B$66, A7, MultiYear_ProForma!$C$2:$C$66, "FY2030"))/5 -> 791565.74 | G7: =SUMIFS(MultiYear_ProForma!$N$2:$N$66, MultiYear_ProForma!$B$2:$B$66, A7, MultiYear_ProForma!$C$2:$C$66, "FY2026") -> 0 | H7: =SUMIFS(MultiYear_ProForma!$AC$2:$AC$66, MultiYear_ProForma!$B$2:$B$66, A7, MultiYear_ProForma!$C$2:$C$66, "FY2030") -> 653 | I7: =E7-(VLOOKUP($B$1,$A$5:$F$17,5, 0)) -> 1788091.3 | J7: =F7-(VLOOKUP($B$1,$A$5:$H$17,6, 0)) -> 1381752.3
A8: D_Grow_Both_Targets | B8: =SUMIFS(Capital_Summary!$H$4:$H$83, Capital_Summary!$A$4:$A$83, A8, Capital_Summary!$B$4:$B$83, "FY2026") -> 1200000 | C8: =SUMIFS(MultiYear_ProForma!$AF$2:$AF$66, MultiYear_ProForma!$B$2:$B$66, A8, MultiYear_ProForma!$C$2:$C$66, "FY2030") -> 1913630.7 | D8: =SUMIFS(MultiYear_ProForma!$AF$2:$AF$66, MultiYear_ProForma!$B$2:$B$66, A8, MultiYear_ProForma!$C$2:$C$66, "FY2028") -> 1821421.3 | E8: =SUMIFS(MultiYear_ProForma!$AF$2:$AF$66, MultiYear_ProForma!$B$2:$B$66, A8, MultiYear_ProForma!$C$2:$C$66, "FY2030") -> 1913630.7 | F8: =(SUMIFS(MultiYear_ProForma!$AF$2:$AF$66, MultiYear_ProForma!$B$2:$B$66, A8, MultiYear_ProForma!$C$2:$C$66, "FY2026")+SUMIFS(MultiYear_ProForma!$AF$2:$AF$66, MultiYear_ProForma!$B$2:$B$66, A8, MultiYear_ProForma!$C$2:$C$66, "FY2027")+SUMIFS(MultiYear_ProForma!$AF$2:$AF$66, MultiYear_ProForma!$B$2:$B$66, A8, MultiYear_ProForma!$C$2:$C$66, "FY2028")+SUMIFS(MultiYear_ProForma!$AF$2:$AF$66, MultiYear_ProForma!$B$2:$B$66, A8, MultiYear_ProForma!$C$2:$C$66, "FY2029")+SUMIFS(MultiYear_ProForma!$AF$2:$AF$66, MultiYear_ProForma!$B$2:$B$66, A8, MultiYear_ProForma!$C$2:$C$66, "FY2030"))/5 -> 1380279 | G8: =SUMIFS(MultiYear_ProForma!$N$2:$N$66, MultiYear_ProForma!$B$2:$B$66, A8, MultiYear_ProForma!$C$2:$C$66, "FY2026") -> 0 | H8: =SUMIFS(MultiYear_ProForma!$AC$2:$AC$66, MultiYear_ProForma!$B$2:$B$66, A8, MultiYear_ProForma!$C$2:$C$66, "FY2030") -> 753 | I8: =E8-(VLOOKUP($B$1,$A$5:$F$17,5, 0)) -> 2638410.6 | J8: =F8-(VLOOKUP($B$1,$A$5:$H$17,6, 0)) -> 1970465.6
A9: D_CUSTOM2 | B9: =SUMIFS(Capital_Summary!$H$4:$H$83, Capital_Summary!$A$4:$A$83, A9, Capital_Summary!$B$4:$B$83, "FY2026") -> 0 | C9: =SUMIFS(MultiYear_ProForma!$AF$2:$AF$66, MultiYear_ProForma!$B$2:$B$66, A9, MultiYear_ProForma!$C$2:$C$66, "FY2030") -> -507019.93 | D9: =SUMIFS(MultiYear_ProForma!$AF$2:$AF$66, MultiYear_ProForma!$B$2:$B$66, A9, MultiYear_ProForma!$C$2:$C$66, "FY2028") -> -482588.87 | E9: =SUMIFS(MultiYear_ProForma!$AF$2:$AF$66, MultiYear_ProForma!$B$2:$B$66, A9, MultiYear_ProForma!$C$2:$C$66, "FY2030") -> -507019.93 | F9: =(SUMIFS(MultiYear_ProForma!$AF$2:$AF$66, MultiYear_ProForma!$B$2:$B$66, A9, MultiYear_ProForma!$C$2:$C$66, "FY2026")+SUMIFS(MultiYear_ProForma!$AF$2:$AF$66, MultiYear_ProForma!$B$2:$B$66, A9, MultiYear_ProForma!$C$2:$C$66, "FY2027")+SUMIFS(MultiYear_ProForma!$AF$2:$AF$66, MultiYear_ProForma!$B$2:$B$66, A9, MultiYear_ProForma!$C$2:$C$66, "FY2028")+SUMIFS(MultiYear_ProForma!$AF$2:$AF$66, MultiYear_ProForma!$B$2:$B$66, A9, MultiYear_ProForma!$C$2:$C$66, "FY2029")+SUMIFS(MultiYear_ProForma!$AF$2:$AF$66, MultiYear_ProForma!$B$2:$B$66, A9, MultiYear_ProForma!$C$2:$C$66, "FY2030"))/5 -> -482883.16 | G9: =SUMIFS(MultiYear_ProForma!$N$2:$N$66, MultiYear_ProForma!$B$2:$B$66, A9, MultiYear_ProForma!$C$2:$C$66, "FY2026") -> 0 | H9: =SUMIFS(MultiYear_ProForma!$AC$2:$AC$66, MultiYear_ProForma!$B$2:$B$66, A9, MultiYear_ProForma!$C$2:$C$66, "FY2030") -> 553 | I9: =E9-(VLOOKUP($B$1,$A$5:$F$17,5, 0)) -> 217760.01 | J9: =F9-(VLOOKUP($B$1,$A$5:$H$17,6, 0)) -> 107303.43
A10: G_EchoGHubRamp_PimaTargets | B10: =SUMIFS(Capital_Summary!$H$4:$H$83, Capital_Summary!$A$4:$A$83, A10, Capital_Summary!$B$4:$B$83, "FY2026") -> 0 | C10: =SUMIFS(MultiYear_ProForma!$AF$2:$AF$66, MultiYear_ProForma!$B$2:$B$66, A10, MultiYear_ProForma!$C$2:$C$66, "FY2030") -> 1308468 | D10: =SUMIFS(MultiYear_ProForma!$AF$2:$AF$66, MultiYear_ProForma!$B$2:$B$66, A10, MultiYear_ProForma!$C$2:$C$66, "FY2028") -> 1245418.7 | E10: =SUMIFS(MultiYear_ProForma!$AF$2:$AF$66, MultiYear_ProForma!$B$2:$B$66, A10, MultiYear_ProForma!$C$2:$C$66, "FY2030") -> 1308468 | F10: =(SUMIFS(MultiYear_ProForma!$AF$2:$AF$66, MultiYear_ProForma!$B$2:$B$66, A10, MultiYear_ProForma!$C$2:$C$66, "FY2026")+SUMIFS(MultiYear_ProForma!$AF$2:$AF$66, MultiYear_ProForma!$B$2:$B$66, A10, MultiYear_ProForma!$C$2:$C$66, "FY2027")+SUMIFS(MultiYear_ProForma!$AF$2:$AF$66, MultiYear_ProForma!$B$2:$B$66, A10, MultiYear_ProForma!$C$2:$C$66, "FY2028")+SUMIFS(MultiYear_ProForma!$AF$2:$AF$66, MultiYear_ProForma!$B$2:$B$66, A10, MultiYear_ProForma!$C$2:$C$66, "FY2029")+SUMIFS(MultiYear_ProForma!$AF$2:$AF$66, MultiYear_ProForma!$B$2:$B$66, A10, MultiYear_ProForma!$C$2:$C$66, "FY2030"))/5 -> 914488.48 | G10: =SUMIFS(MultiYear_ProForma!$N$2:$N$66, MultiYear_ProForma!$B$2:$B$66, A10, MultiYear_ProForma!$C$2:$C$66, "FY2026") -> 0 | H10: =SUMIFS(MultiYear_ProForma!$AC$2:$AC$66, MultiYear_ProForma!$B$2:$B$66, A10, MultiYear_ProForma!$C$2:$C$66, "FY2030") -> 703 | I10: =E10-(VLOOKUP($B$1,$A$5:$F$17,5, 0)) -> 2033248 | J10: =F10-(VLOOKUP($B$1,$A$5:$H$17,6, 0)) -> 1504675.1
A11: A_Repurpose_Both_lease | B11: =SUMIFS(Capital_Summary!$H$4:$H$83, Capital_Summary!$A$4:$A$83, A11, Capital_Summary!$B$4:$B$83, "FY2026") -> 2400000 | C11: =SUMIFS(MultiYear_ProForma!$AF$2:$AF$66, MultiYear_ProForma!$B$2:$B$66, A11, MultiYear_ProForma!$C$2:$C$66, "FY2030") -> 537913.81 | D11: =SUMIFS(MultiYear_ProForma!$AF$2:$AF$66, MultiYear_ProForma!$B$2:$B$66, A11, MultiYear_ProForma!$C$2:$C$66, "FY2028") -> 138880.27 | E11: =SUMIFS(MultiYear_ProForma!$AF$2:$AF$66, MultiYear_ProForma!$B$2:$B$66, A11, MultiYear_ProForma!$C$2:$C$66, "FY2030") -> 537913.81 | F11: =(SUMIFS(MultiYear_ProForma!$AF$2:$AF$66, MultiYear_ProForma!$B$2:$B$66, A11, MultiYear_ProForma!$C$2:$C$66, "FY2026")+SUMIFS(MultiYear_ProForma!$AF$2:$AF$66, MultiYear_ProForma!$B$2:$B$66, A11, MultiYear_ProForma!$C$2:$C$66, "FY2027")+SUMIFS(MultiYear_ProForma!$AF$2:$AF$66, MultiYear_ProForma!$B$2:$B$66, A11, MultiYear_ProForma!$C$2:$C$66, "FY2028")+SUMIFS(MultiYear_ProForma!$AF$2:$AF$66, MultiYear_ProForma!$B$2:$B$66, A11, MultiYear_ProForma!$C$2:$C$66, "FY2029")+SUMIFS(MultiYear_ProForma!$AF$2:$AF$66, MultiYear_ProForma!$B$2:$B$66, A11, MultiYear_ProForma!$C$2:$C$66, "FY2030"))/5 -> 81004.084 | G11: =SUMIFS(MultiYear_ProForma!$N$2:$N$66, MultiYear_ProForma!$B$2:$B$66, A11, MultiYear_ProForma!$C$2:$C$66, "FY2026") -> 553 | H11: =SUMIFS(MultiYear_ProForma!$AC$2:$AC$66, MultiYear_ProForma!$B$2:$B$66, A11, MultiYear_ProForma!$C$2:$C$66, "FY2030") -> 184.025 | I11: =E11-(VLOOKUP($B$1,$A$5:$F$17,5, 0)) -> 1262693.8 | J11: =F11-(VLOOKUP($B$1,$A$5:$H$17,6, 0)) -> 671190.68
A12: A_Repurpose_Both_ops | B12: =SUMIFS(Capital_Summary!$H$4:$H$83, Capital_Summary!$A$4:$A$83, A12, Capital_Summary!$B$4:$B$83, "FY2026") -> 0 | C12: =SUMIFS(MultiYear_ProForma!$AF$2:$AF$66, MultiYear_ProForma!$B$2:$B$66, A12, MultiYear_ProForma!$C$2:$C$66, "FY2030") -> -124497.13 | D12: =SUMIFS(MultiYear_ProForma!$AF$2:$AF$66, MultiYear_ProForma!$B$2:$B$66, A12, MultiYear_ProForma!$C$2:$C$66, "FY2028") -> -333988.93 | E12: =SUMIFS(MultiYear_ProForma!$AF$2:$AF$66, MultiYear_ProForma!$B$2:$B$66, A12, MultiYear_ProForma!$C$2:$C$66, "FY2030") -> -124497.13 | F12: =(SUMIFS(MultiYear_ProForma!$AF$2:$AF$66, MultiYear_ProForma!$B$2:$B$66, A12, MultiYear_ProForma!$C$2:$C$66, "FY2026")+SUMIFS(MultiYear_ProForma!$AF$2:$AF$66, MultiYear_ProForma!$B$2:$B$66, A12, MultiYear_ProForma!$C$2:$C$66, "FY2027")+SUMIFS(MultiYear_ProForma!$AF$2:$AF$66, MultiYear_ProForma!$B$2:$B$66, A12, MultiYear_ProForma!$C$2:$C$66, "FY2028")+SUMIFS(MultiYear_ProForma!$AF$2:$AF$66, MultiYear_ProForma!$B$2:$B$66, A12, MultiYear_ProForma!$C$2:$C$66, "FY2029")+SUMIFS(MultiYear_ProForma!$AF$2:$AF$66, MultiYear_ProForma!$B$2:$B$66, A12, MultiYear_ProForma!$C$2:$C$66, "FY2030"))/5 -> -396825.46 | G12: =SUMIFS(MultiYear_ProForma!$N$2:$N$66, MultiYear_ProForma!$B$2:$B$66, A12, MultiYear_ProForma!$C$2:$C$66, "FY2026") -> 553 | H12: =SUMIFS(MultiYear_ProForma!$AC$2:$AC$66, MultiYear_ProForma!$B$2:$B$66, A12, MultiYear_ProForma!$C$2:$C$66, "FY2030") -> 184.025 | I12: =E12-(VLOOKUP($B$1,$A$5:$F$17,5, 0)) -> 600282.81 | J12: =F12-(VLOOKUP($B$1,$A$5:$H$17,6, 0)) -> 193361.13
A13: B_Repurpose_Echo_lease_PimaTargets | B13: =SUMIFS(Capital_Summary!$H$4:$H$83, Capital_Summary!$A$4:$A$83, A13, Capital_Summary!$B$4:$B$83, "FY2026") -> 1200000 | C13: =SUMIFS(MultiYear_ProForma!$AF$2:$AF$66, MultiYear_ProForma!$B$2:$B$66, A13, MultiYear_ProForma!$C$2:$C$66, "FY2030") -> -394968.1 | D13: =SUMIFS(MultiYear_ProForma!$AF$2:$AF$66, MultiYear_ProForma!$B$2:$B$66, A13, MultiYear_ProForma!$C$2:$C$66, "FY2028") -> -524463.5 | E13: =SUMIFS(MultiYear_ProForma!$AF$2:$AF$66, MultiYear_ProForma!$B$2:$B$66, A13, MultiYear_ProForma!$C$2:$C$66, "FY2030") -> -394968.1 | F13: =(SUMIFS(MultiYear_ProForma!$AF$2:$AF$66, MultiYear_ProForma!$B$2:$B$66, A13, MultiYear_ProForma!$C$2:$C$66, "FY2026")+SUMIFS(MultiYear_ProForma!$AF$2:$AF$66, MultiYear_ProForma!$B$2:$B$66, A13, MultiYear_ProForma!$C$2:$C$66, "FY2027")+SUMIFS(MultiYear_ProForma!$AF$2:$AF$66, MultiYear_ProForma!$B$2:$B$66, A13, MultiYear_ProForma!$C$2:$C$66, "FY2028")+SUMIFS(MultiYear_ProForma!$AF$2:$AF$66, MultiYear_ProForma!$B$2:$B$66, A13, MultiYear_ProForma!$C$2:$C$66, "FY2029")+SUMIFS(MultiYear_ProForma!$AF$2:$AF$66, MultiYear_ProForma!$B$2:$B$66, A13, MultiYear_ProForma!$C$2:$C$66, "FY2030"))/5 -> -548584.95 | G13: =SUMIFS(MultiYear_ProForma!$N$2:$N$66, MultiYear_ProForma!$B$2:$B$66, A13, MultiYear_ProForma!$C$2:$C$66, "FY2026") -> 257 | H13: =SUMIFS(MultiYear_ProForma!$AC$2:$AC$66, MultiYear_ProForma!$B$2:$B$66, A13, MultiYear_ProForma!$C$2:$C$66, "FY2030") -> 302.425 | I13: =E13-(VLOOKUP($B$1,$A$5:$F$17,5, 0)) -> 329811.83 | J13: =F13-(VLOOKUP($B$1,$A$5:$H$17,6, 0)) -> 41601.641
A14: B_Repurpose_Echo_ops_PimaTargets | B14: =SUMIFS(Capital_Summary!$H$4:$H$83, Capital_Summary!$A$4:$A$83, A14, Capital_Summary!$B$4:$B$83, "FY2026") -> 0 | C14: =SUMIFS(MultiYear_ProForma!$AF$2:$AF$66, MultiYear_ProForma!$B$2:$B$66, A14, MultiYear_ProForma!$C$2:$C$66, "FY2030") -> -97652.846 | D14: =SUMIFS(MultiYear_ProForma!$AF$2:$AF$66, MultiYear_ProForma!$B$2:$B$66, A14, MultiYear_ProForma!$C$2:$C$66, "FY2028") -> -168221.16 | E14: =SUMIFS(MultiYear_ProForma!$AF$2:$AF$66, MultiYear_ProForma!$B$2:$B$66, A14, MultiYear_ProForma!$C$2:$C$66, "FY2030") -> -97652.846 | F14: =(SUMIFS(MultiYear_ProForma!$AF$2:$AF$66, MultiYear_ProForma!$B$2:$B$66, A14, MultiYear_ProForma!$C$2:$C$66, "FY2026")+SUMIFS(MultiYear_ProForma!$AF$2:$AF$66, MultiYear_ProForma!$B$2:$B$66, A14, MultiYear_ProForma!$C$2:$C$66, "FY2027")+SUMIFS(MultiYear_ProForma!$AF$2:$AF$66, MultiYear_ProForma!$B$2:$B$66, A14, MultiYear_ProForma!$C$2:$C$66, "FY2028")+SUMIFS(MultiYear_ProForma!$AF$2:$AF$66, MultiYear_ProForma!$B$2:$B$66, A14, MultiYear_ProForma!$C$2:$C$66, "FY2029")+SUMIFS(MultiYear_ProForma!$AF$2:$AF$66, MultiYear_ProForma!$B$2:$B$66, A14, MultiYear_ProForma!$C$2:$C$66, "FY2030"))/5 -> -304859.85 | G14: =SUMIFS(MultiYear_ProForma!$N$2:$N$66, MultiYear_ProForma!$B$2:$B$66, A14, MultiYear_ProForma!$C$2:$C$66, "FY2026") -> 257 | H14: =SUMIFS(MultiYear_ProForma!$AC$2:$AC$66, MultiYear_ProForma!$B$2:$B$66, A14, MultiYear_ProForma!$C$2:$C$66, "FY2030") -> 352.425 | I14: =E14-(VLOOKUP($B$1,$A$5:$F$17,5, 0)) -> 627127.09 | J14: =F14-(VLOOKUP($B$1,$A$5:$H$17,6, 0)) -> 285326.74
A15: C_Repurpose_Pima_lease_EchoGHub_EchoTargets | B15: =SUMIFS(Capital_Summary!$H$4:$H$83, Capital_Summary!$A$4:$A$83, A15, Capital_Summary!$B$4:$B$83, "FY2026") -> 1200000 | C15: =SUMIFS(MultiYear_ProForma!$AF$2:$AF$66, MultiYear_ProForma!$B$2:$B$66, A15, MultiYear_ProForma!$C$2:$C$66, "FY2030") -> 425861.99 | D15: =SUMIFS(MultiYear_ProForma!$AF$2:$AF$66, MultiYear_ProForma!$B$2:$B$66, A15, MultiYear_ProForma!$C$2:$C$66, "FY2028") -> 180754.9 | E15: =SUMIFS(MultiYear_ProForma!$AF$2:$AF$66, MultiYear_ProForma!$B$2:$B$66, A15, MultiYear_ProForma!$C$2:$C$66, "FY2030") -> 425861.99 | F15: =(SUMIFS(MultiYear_ProForma!$AF$2:$AF$66, MultiYear_ProForma!$B$2:$B$66, A15, MultiYear_ProForma!$C$2:$C$66, "FY2026")+SUMIFS(MultiYear_ProForma!$AF$2:$AF$66, MultiYear_ProForma!$B$2:$B$66, A15, MultiYear_ProForma!$C$2:$C$66, "FY2027")+SUMIFS(MultiYear_ProForma!$AF$2:$AF$66, MultiYear_ProForma!$B$2:$B$66, A15, MultiYear_ProForma!$C$2:$C$66, "FY2028")+SUMIFS(MultiYear_ProForma!$AF$2:$AF$66, MultiYear_ProForma!$B$2:$B$66, A15, MultiYear_ProForma!$C$2:$C$66, "FY2029")+SUMIFS(MultiYear_ProForma!$AF$2:$AF$66, MultiYear_ProForma!$B$2:$B$66, A15, MultiYear_ProForma!$C$2:$C$66, "FY2030"))/5 -> 146705.87 | G15: =SUMIFS(MultiYear_ProForma!$N$2:$N$66, MultiYear_ProForma!$B$2:$B$66, A15, MultiYear_ProForma!$C$2:$C$66, "FY2026") -> 296 | H15: =SUMIFS(MultiYear_ProForma!$AC$2:$AC$66, MultiYear_ProForma!$B$2:$B$66, A15, MultiYear_ProForma!$C$2:$C$66, "FY2030") -> 434.6 | I15: =E15-(VLOOKUP($B$1,$A$5:$F$17,5, 0)) -> 1150641.9 | J15: =F15-(VLOOKUP($B$1,$A$5:$H$17,6, 0)) -> 736892.46
A16: C_Repurpose_Pima_ops_EchoGHub_EchoTargets | B16: =SUMIFS(Capital_Summary!$H$4:$H$83, Capital_Summary!$A$4:$A$83, A16, Capital_Summary!$B$4:$B$83, "FY2026") -> 0 | C16: =SUMIFS(MultiYear_ProForma!$AF$2:$AF$66, MultiYear_ProForma!$B$2:$B$66, A16, MultiYear_ProForma!$C$2:$C$66, "FY2030") -> 1281623.8 | D16: =SUMIFS(MultiYear_ProForma!$AF$2:$AF$66, MultiYear_ProForma!$B$2:$B$66, A16, MultiYear_ProForma!$C$2:$C$66, "FY2028") -> 1079650.9 | E16: =SUMIFS(MultiYear_ProForma!$AF$2:$AF$66, MultiYear_ProForma!$B$2:$B$66, A16, MultiYear_ProForma!$C$2:$C$66, "FY2030") -> 1281623.8 | F16: =(SUMIFS(MultiYear_ProForma!$AF$2:$AF$66, MultiYear_ProForma!$B$2:$B$66, A16, MultiYear_ProForma!$C$2:$C$66, "FY2026")+SUMIFS(MultiYear_ProForma!$AF$2:$AF$66, MultiYear_ProForma!$B$2:$B$66, A16, MultiYear_ProForma!$C$2:$C$66, "FY2027")+SUMIFS(MultiYear_ProForma!$AF$2:$AF$66, MultiYear_ProForma!$B$2:$B$66, A16, MultiYear_ProForma!$C$2:$C$66, "FY2028")+SUMIFS(MultiYear_ProForma!$AF$2:$AF$66, MultiYear_ProForma!$B$2:$B$66, A16, MultiYear_ProForma!$C$2:$C$66, "FY2029")+SUMIFS(MultiYear_ProForma!$AF$2:$AF$66, MultiYear_ProForma!$B$2:$B$66, A16, MultiYear_ProForma!$C$2:$C$66, "FY2030"))/5 -> 822528.59 | G16: =SUMIFS(MultiYear_ProForma!$N$2:$N$66, MultiYear_ProForma!$B$2:$B$66, A16, MultiYear_ProForma!$C$2:$C$66, "FY2026") -> 296.33333 | H16: =SUMIFS(MultiYear_ProForma!$AC$2:$AC$66, MultiYear_ProForma!$B$2:$B$66, A16, MultiYear_ProForma!$C$2:$C$66, "FY2030") -> 534.6 | I16: =E16-(VLOOKUP($B$1,$A$5:$F$17,5, 0)) -> 2006403.7 | J16: =F16-(VLOOKUP($B$1,$A$5:$H$17,6, 0)) -> 1412715.2
A17: H_StatusQuo_Decline | B17: =SUMIFS(Capital_Summary!$H$4:$H$83, Capital_Summary!$A$4:$A$83, A17, Capital_Summary!$B$4:$B$83, "FY2026") -> 0 | C17: =SUMIFS(MultiYear_ProForma!$AF$2:$AF$66, MultiYear_ProForma!$B$2:$B$66, A17, MultiYear_ProForma!$C$2:$C$66, "FY2030") -> -724779.94 | D17: =SUMIFS(MultiYear_ProForma!$AF$2:$AF$66, MultiYear_ProForma!$B$2:$B$66, A17, MultiYear_ProForma!$C$2:$C$66, "FY2028") -> -588315.82 | E17: =SUMIFS(MultiYear_ProForma!$AF$2:$AF$66, MultiYear_ProForma!$B$2:$B$66, A17, MultiYear_ProForma!$C$2:$C$66, "FY2030") -> -724779.94 | F17: =(SUMIFS(MultiYear_ProForma!$AF$2:$AF$66, MultiYear_ProForma!$B$2:$B$66, A17, MultiYear_ProForma!$C$2:$C$66, "FY2026")+SUMIFS(MultiYear_ProForma!$AF$2:$AF$66, MultiYear_ProForma!$B$2:$B$66, A17, MultiYear_ProForma!$C$2:$C$66, "FY2027")+SUMIFS(MultiYear_ProForma!$AF$2:$AF$66, MultiYear_ProForma!$B$2:$B$66, A17, MultiYear_ProForma!$C$2:$C$66, "FY2028")+SUMIFS(MultiYear_ProForma!$AF$2:$AF$66, MultiYear_ProForma!$B$2:$B$66, A17, MultiYear_ProForma!$C$2:$C$66, "FY2029")+SUMIFS(MultiYear_ProForma!$AF$2:$AF$66, MultiYear_ProForma!$B$2:$B$66, A17, MultiYear_ProForma!$C$2:$C$66, "FY2030"))/5 -> -590186.59 | G17: =SUMIFS(MultiYear_ProForma!$N$2:$N$66, MultiYear_ProForma!$B$2:$B$66, A17, MultiYear_ProForma!$C$2:$C$66, "FY2026") -> 0 | H17: =SUMIFS(MultiYear_ProForma!$AC$2:$AC$66, MultiYear_ProForma!$B$2:$B$66, A17, MultiYear_ProForma!$C$2:$C$66, "FY2030") -> 510.06959 | I17: =E17-(VLOOKUP($B$1,$A$5:$F$17,5, 0)) -> 0 | J17: =F17-(VLOOKUP($B$1,$A$5:$H$17,6, 0)) -> 0
A19: Note: Displaced = FY26; Served = FY30. Net = M&O − (Aid + Override + Uplift)

Sheet Board_OnePager
A1: Echo & Pima — Baseline vs Comparator (Operating Net, FY26–FY30)
A3: Baseline (Base) | B3: A_Repurpose_Both_lease
A4: Comparator | B4: H_StatusQuo_Decline
A6: Year | B6: Operating Net$ (Base) | C6: Operating Net$ (Comparator)
A7: FY2026 | B7: =SUMIFS(MultiYear_ProForma!$AF$2:$AF$66, MultiYear_ProForma!$B$2:$B$66, $B$3, MultiYear_ProForma!$C$2:$C$66, "FY2026") -> -546853.79 | C7: =SUMIFS(MultiYear_ProForma!$AF$2:$AF$66, MultiYear_ProForma!$B$2:$B$66, $B$4, MultiYear_ProForma!$C$2:$C$66, "FY2026") -> -459335.03
A8: FY2027 | B8: =SUMIFS(MultiYear_ProForma!$AF$2:$AF$66, MultiYear_ProForma!$B$2:$B$66, $B$3, MultiYear_ProForma!$C$2:$C$66, "FY2027") -> -211562.31 | C8: =SUMIFS(MultiYear_ProForma!$AF$2:$AF$66, MultiYear_ProForma!$B$2:$B$66, $B$4, MultiYear_ProForma!$C$2:$C$66, "FY2027") -> -522913.48
A9: FY2028 | B9: =SUMIFS(MultiYear_ProForma!$AF$2:$AF$66, MultiYear_ProForma!$B$2:$B$66, $B$3, MultiYear_ProForma!$C$2:$C$66, "FY2028") -> 138880.27 | C9: =SUMIFS(MultiYear_ProForma!$AF$2:$AF$66, MultiYear_ProForma!$B$2:$B$66, $B$4, MultiYear_ProForma!$C$2:$C$66, "FY2028") -> -588315.82
A10: FY2029 | B10: =SUMIFS(MultiYear_ProForma!$AF$2:$AF$66, MultiYear_ProForma!$B$2:$B$66, $B$3, MultiYear_ProForma!$C$2:$C$66, "FY2029") -> 486642.44 | C10: =SUMIFS(MultiYear_ProForma!$AF$2:$AF$66, MultiYear_ProForma!$B$2:$B$66, $B$4, MultiYear_ProForma!$C$2:$C$66, "FY2029") -> -655588.7
A11: FY2030 | B11: =SUMIFS(MultiYear_ProForma!$AF$2:$AF$66, MultiYear_ProForma!$B$2:$B$66, $B$3, MultiYear_ProForma!$C$2:$C$66, "FY2030") -> 537913.81 | C11: =SUMIFS(MultiYear_ProForma!$AF$2:$AF$66, MultiYear_ProForma!$B$2:$B$66, $B$4, MultiYear_ProForma!$C$2:$C$66, "FY2030") -> -724779.94
A16: Notes: No receiving site exceeds spare seats + portables; assumptions reflect: r, override, marginal factor, trend flags; h tapers yearly
A18: FY2030 Net (Base) | B18: =SUMIFS(MultiYear_ProForma!$AF$2:$AF$66, MultiYear_ProForma!$B$2:$B$66, $B$3, MultiYear_ProForma!$C$2:$C$66, "FY2030") -> 537913.81
A19: FY2030 Net (Comparator) | B19: =SUMIFS(MultiYear_ProForma!$AF$2:$AF$66, MultiYear_ProForma!$B$2:$B$66, $B$4, MultiYear_ProForma!$C$2:$C$66, "FY2030") -> -724779.94
A20: Δ vs Base (FY2030) | B20: =B19-B18 -> -1262693.8
A22: Avg Net (FY26–30) (Base) | B22: =(SUMIFS(MultiYear_ProForma!$AF$2:$AF$66, MultiYear_ProForma!$B$2:$B$66, $B$3, MultiYear_ProForma!$C$2:$C$66, "FY2026")+SUMIFS(MultiYear_ProForma!$AF$2:$AF$66, MultiYear_ProForma!$B$2:$B$66, $B$3, MultiYear_ProForma!$C$2:$C$66, "FY2027")+SUMIFS(MultiYear_ProForma!$AF$2:$AF$66, MultiYear_ProForma!$B$2:$B$66, $B$3, MultiYear_ProForma!$C$2:$C$66, "FY2028")+SUMIFS(MultiYear_ProForma!$AF$2:$AF$66, MultiYear_ProForma!$B$2:$B$66, $B$3, MultiYear_ProForma!$C$2:$C$66, "FY2029")+SUMIFS(MultiYear_ProForma!$AF$2:$AF$66, MultiYear_ProForma!$B$2:$B$66, $B$3, MultiYear_ProForma!$C$2:$C$66, "FY2030"))/5 -> 81004.084
A23: Avg Net (FY26–30) (Comparator) | B23: =(SUMIFS(MultiYear_ProForma!$AF$2:$AF$66, MultiYear_ProForma!$B$2:$B$66, $B$4, MultiYear_ProForma!$C$2:$C$66, "FY2026")+SUMIFS(MultiYear_ProForma!$AF$2:$AF$66, MultiYear_ProForma!$B$2:$B$66, $B$4, MultiYear_ProForma!$C$2:$C$66, "FY2027")+SUMIFS(MultiYear_ProForma!$AF$2:$AF$66, MultiYear_ProForma!$B$2:$B$66, $B$4, MultiYear_ProForma!$C$2:$C$66, "FY2028")+SUMIFS(MultiYear_ProForma!$AF$2:$AF$66, MultiYear_ProForma!$B$2:$B$66, $B$4, MultiYear_ProForma!$C$2:$C$66, "FY2029")+SUMIFS(MultiYear_ProForma!$AF$2:$AF$66, MultiYear_ProForma!$B$2:$B$66, $B$4, MultiYear_ProForma!$C$2:$C$66, "FY2030"))/5 -> -590186.59
A24: Δ vs Base (Avg FY26–30) | B24: =B23-B22 -> -671190.68
A26: Displaced (FY26) (Base) | B26: =SUMIFS(MultiYear_ProForma!$N$2:$N$66, MultiYear_ProForma!$B$2:$B$66, $B$3, MultiYear_ProForma!$C$2:$C$66, "FY2026") -> 553
A27: Displaced (FY26) (Comparator) | B27: =SUMIFS(MultiYear_ProForma!$N$2:$N$66, MultiYear_ProForma!$B$2:$B$66, $B$4, MultiYear_ProForma!$C$2:$C$66, "FY2026") -> 0
A29: Served (FY2030) (Base) | B29: =SUMIFS(MultiYear_ProForma!$AC$2:$AC$66, MultiYear_ProForma!$B$2:$B$66, $B$3, MultiYear_ProForma!$C$2:$C$66, "FY2030") -> 184.025
A30: Served (FY2030) (Comparator) | B30: =SUMIFS(MultiYear_ProForma!$AC$2:$AC$66, MultiYear_ProForma!$B$2:$B$66, $B$4, MultiYear_ProForma!$C$2:$C$66, "FY2030") -> 510.06959
A32: One-time Capital FY 2026 (Base) | B32: =SUMIFS(Capital_Summary!$H$4:$H$83, Capital_Summary!$A$4:$A$83, B3, Capital_Summary!$B$4:$B$83, "FY2026") -> 2400000
A33: One-time Capital FY 2026 (Comparator) | B33: =SUMIFS(Capital_Summary!$H$4:$H$83, Capital_Summary!$A$4:$A$83, B4, Capital_Summary!$B$4:$B$83, "FY2026") -> 0

Sheet One_to_One_Comparison
A1: Echo & Pima Decision Dashboard — one comparator vs A_Repurpose_Both_ops
D2: OPERATING | K2: CAPITAL — FY2026 only
D3: FY2030 Net ($) | E3: 5-yr Avg Net ($) | F3: Δ vs Base (FY2030 Net) | G3: Δ vs Base (5-yr Avg Net) | H3: Students displaced | I3: FY2030 students served | K3: FY2026 Capital ($) | L3: Δ vs Base
A4: Baseline (Base) | B4: H_StatusQuo_Decline | D4: =INDEX(Summary_Figures!$E$5:$E$17, MATCH($B$4, Summary_Figures!$A$5:$A$17, 0)) -> -724779.94 | E4: =INDEX(Summary_Figures!$F$5:$F$17, MATCH($B$4, Summary_Figures!$A$5:$A$17, 0)) -> -590186.59 | H4: =INDEX(Summary_Figures!$G$5:$G$17, MATCH($B$4, Summary_Figures!$A$5:$A$17, 0)) -> 0 | I4: =INDEX(Summary_Figures!$H$5:$H$17, MATCH($B$4, Summary_Figures!$A$5:$A$17, 0)) -> 510.06959 | K4: =SUMIFS(Capital_Summary!$H$4:$H$63, Capital_Summary!$A$4:$A$63, $B$4, Capital_Summary!$B$4:$B$63, "FY2026") -> 0
A5: Comparator (ScenarioKey) | B5: A_Repurpose_Both_lease | D5: =INDEX(Summary_Figures!$E$5:$E$17, MATCH($B$5, Summary_Figures!$A$5:$A$17, 0)) -> 537913.81 | E5: =INDEX(Summary_Figures!$F$5:$F$17, MATCH($B$5, Summary_Figures!$A$5:$A$17, 0)) -> 81004.084 | F5: =D5-D4 -> 1262693.8 | G5: =E5-E4 -> 671190.68 | H5: =INDEX(Summary_Figures!$G$5:$G$17, MATCH($B$5, Summary_Figures!$A$5:$A$17, 0)) -> 553 | I5: =INDEX(Summary_Figures!$H$5:$H$17, MATCH($B$5, Summary_Figures!$A$5:$A$17, 0)) -> 184.025 | K5: =SUMIFS(Capital_Summary!$H$4:$H$63, Capital_Summary!$A$4:$A$63, $B$5, Capital_Summary!$B$4:$B$63, "FY2026") -> 2400000 | L5: =K5-K4 -> 2400000
A7: Assumptions (from Parameters_Public / Control_Center)
A8: Retention r (Echo central) | B8: =Parameters_Public!C22 -> 0.025
A9: Retention r (Pima central) | B9: =Parameters_Public!C23 -> 0.6
A10: MarginalFactor_for_Overlay | B10: =Parameters_Public!$C42 -> 0
A11: Override % | B11: =Parameters_Public!C17 -> 0.15
A12: Override toggle (0/1) | B12: =Parameters_Public!C20 -> 1
A14: Assumption notes:
A15: • Routing/admin overhead h tapers by year (see YearMap). Try ±20% sensitivity when routing assumptions are uncertain.
A16: • Keep-open ops savings (fraction of MO): | B16: =Control_Center!C10 -> 0.007
A17: • Extra savings for co-location (fraction of MO): | B17: =Control_Center!C11 -> 0.015

Sheet Scenarios
A1: ScenarioKey | B1: Label | C1: Overlay | D1: CloseEcho | E1: ClosePima | F1: EchoShareDist | G1: ExtraSave | H1: Notes | I1: Overlay_FY26 | J1: Overlay_FY27 | K1: Overlay_FY28 | L1: Overlay_FY29 | M1: Overlay_FY30 | N1: Carry | O1: Growth_Echo | P1: Growth_Pima | Q1: Apply_Echo_Trend | R1: Apply_Pima_Trend
A2: D_CUSTOM1 | B2: =Control_Center!B31 -> CUSTOM_KeepOpen_v1 | C2: =Control_Center!C31 -> 0 | D2: =Control_Center!D31 -> 0 | E2: =Control_Center!E31 -> 0 | F2: =Control_Center!F31 -> 0.5 | G2: =Control_Center!G31 -> 0 | H2: Baseline + outreach; no closures | I2: =C2/3 -> 0 | J2: =I2+C2/3 -> 0 | K2: =J2+C2/3 -> 0 | L2: =C2 -> 0 | M2: =C2 -> 0 | O2: None | P2: None | Q2: 0 | R2: 0
A3: E_StatusQuo_Targets | B3: =Control_Center!B32 -> Status‑Quo + Op Growth Targets | C3: =Control_Center!C32 -> 100 | D3: =Control_Center!D32 -> 0 | E3: =Control_Center!E32 -> 0 | F3: =Control_Center!F32 -> 0.5 | G3: =Control_Center!G32 -> 0 | H3: Baseline + targets; no closures | I3: =C3/3 -> 33.333333 | J3: =I3+C3/3 -> 66.666667 | K3: =J3+C3/3 -> 100 | L3: =C3 -> 100 | M3: =C3 -> 100 | O3: None | P3: None | Q3: 0 | R3: 0
A4: F_CoLocation_Echo_Targets | B4: =Control_Center!B33 -> Co‑Location @ Echo + Op Growth Targets | C4: =Control_Center!C33 -> 100 | D4: =Control_Center!D33 -> 0 | E4: =Control_Center!E33 -> 0 | F4: =Control_Center!F33 -> 0.5 | G4: =Control_Center!G33 -> 0.05 | H4: Shared‑use efficiencies later (no closure) | I4: =C4/3 -> 33.333333 | J4: =I4+C4/3 -> 66.666667 | K4: =J4+C4/3 -> 100 | L4: =C4 -> 100 | M4: =C4 -> 100 | O4: None | P4: None | Q4: 0 | R4: 0
A5: D_Grow_Both_Targets | B5: =Control_Center!B34 -> Grow Both + Op Growth Targets | C5: =Control_Center!C34 -> 200 | D5: =Control_Center!D34 -> 0 | E5: =Control_Center!E34 -> 0 | F5: =Control_Center!F34 -> 0.5 | G5: =Control_Center!G34 -> 0 | H5: Baseline +100 overlay | I5: =C5/3 -> 66.666667 | J5: =I5+C5/3 -> 133.33333 | K5: =J5+C5/3 -> 200 | L5: =C5 -> 200 | M5: =C5 -> 200 | O5: Innov | P5: Arts | Q5: 0 | R5: 0
A6: D_CUSTOM2 | B6: =Control_Center!B35 -> CUSTOM_KeepOpen_v2 | C6: =Control_Center!C35 -> 0 | D6: =Control_Center!D35 -> 0 | E6: =Control_Center!E35 -> 0 | F6: =Control_Center!F35 -> 0.5 | G6: =Control_Center!G35 -> 0 | H6: Baseline +150 overlay | I6: =C6/3 -> 0 | J6: =I6+C6/3 -> 0 | K6: =J6+C6/3 -> 0 | L6: =C6 -> 0 | M6: =C6 -> 0 | O6: None | P6: None | Q6: 0 | R6: 0
A7: G_EchoGHubRamp_PimaTargets | B7: =Control_Center!B36 -> Growth Hub @ Echo + Status-Quo Pima + Op Growth Targets | C7: =Control_Center!C36 -> 150 | D7: =Control_Center!D36 -> 0 | E7: =Control_Center!E36 -> 0 | F7: =Control_Center!F36 -> 0.7 | G7: =Control_Center!G36 -> 0 | H7: Time‑phased ramp (+50,+100,+150 years 1–3) | I7: =C7/3 -> 50 | J7: =I7+C7/3 -> 100 | K7: =J7+C7/3 -> 150 | L7: =C7 -> 150 | M7: =C7 -> 150 | O7: Arts | P7: None | Q7: 0 | R7: 0
A8: A_Repurpose_Both_lease | B8: =Control_Center!B37 -> Repurpose BOTH (lease) | C8: =Control_Center!C37 -> 0 | D8: =Control_Center!D37 -> 1 | E8: =Control_Center!E37 -> 1 | F8: =Control_Center!F37 -> 0.5 | G8: =Control_Center!G37 -> 0 | H8: Repurpose both; lease/sale glide | I8: =C8/3 -> 0 | J8: =I8+C8/3 -> 0 | K8: =J8+C8/3 -> 0 | L8: =C8 -> 0 | M8: =C8 -> 0 | N8: lease | O8: None | P8: None | Q8: 0 | R8: 0
A9: A_Repurpose_Both_ops | B9: =Control_Center!B38 -> Repurpose BOTH (ops) | C9: =Control_Center!C38 -> 0 | D9: =Control_Center!D38 -> 1 | E9: =Control_Center!E38 -> 1 | F9: =Control_Center!F38 -> 0.5 | G9: =Control_Center!G38 -> 0 | H9: Repurpose both; operations carry | I9: =C9/3 -> 0 | J9: =I9+C9/3 -> 0 | K9: =J9+C9/3 -> 0 | L9: =C9 -> 0 | M9: =C9 -> 0 | N9: ops | O9: None | P9: None | Q9: 0 | R9: 0
A10: B_Repurpose_Echo_lease_PimaTargets | B10: =Control_Center!B39 -> Repurpose ECHO (lease) + Status-Quo Pima + Pima Op Growth Targets | C10: =Control_Center!C39 -> 0 | D10: =Control_Center!D39 -> 1 | E10: =Control_Center!E39 -> 0 | F10: =Control_Center!F39 -> 0 | G10: =Control_Center!G39 -> 0 | H10: Repurpose Echo only; lease glide | I10: =C10/3 -> 0 | J10: =I10+C10/3 -> 0 | K10: =J10+C10/3 -> 0 | L10: =C10 -> 0 | M10: =C10 -> 0 | N10: lease | O10: None | P10: None | Q10: 0 | R10: 0
A11: B_Repurpose_Echo_ops_PimaTargets | B11: =Control_Center!B40 -> Repurpose ECHO (ops) + Status-Quo Pima + Pima Op Growth Targets | C11: =Control_Center!C40 -> 50 | D11: =Control_Center!D40 -> 1 | E11: =Control_Center!E40 -> 0 | F11: =Control_Center!F40 -> 0 | G11: =Control_Center!G40 -> 0 | H11: Repurpose Echo only; ops carry | I11: =C11/3 -> 16.666667 | J11: =I11+C11/3 -> 33.333333 | K11: =J11+C11/3 -> 50 | L11: =C11 -> 50 | M11: =C11 -> 50 | N11: ops | O11: None | P11: None | Q11: 0 | R11: 0
A12: C_Repurpose_Pima_lease_EchoGHub_EchoTargets | B12: =Control_Center!B41 -> Repurpose PIMA (lease) + Growth Hub @ Echo + Echo Op Growth Targets | C12: =Control_Center!C41 -> 0 | D12: =Control_Center!D41 -> 0 | E12: =Control_Center!E41 -> 1 | F12: =Control_Center!F41 -> 1 | G12: =Control_Center!G41 -> 0 | H12: Repurpose Pima only; lease glide | I12: =C12/3 -> 0 | J12: =I12+C12/3 -> 0 | K12: =J12+C12/3 -> 0 | L12: =C12 -> 0 | M12: =C12 -> 0 | N12: lease | O12: Arts | P12: None | Q12: 0 | R12: 0
A13: C_Repurpose_Pima_ops_EchoGHub_EchoTargets | B13: =Control_Center!B42 -> Repurpose PIMA (ops) + Growth Hub @ Echo + Echo Op Growth Targets | C13: =Control_Center!C42 -> 100 | D13: =Control_Center!D42 -> 0 | E13: =Control_Center!E42 -> 1 | F13: =Control_Center!F42 -> 1 | G13: =Control_Center!G42 -> 0 | H13: Repurpose Pima only; ops carry | I13: =C13/3 -> 33.333333 | J13: =I13+C13/3 -> 66.666667 | K13: =J13+C13/3 -> 100 | L13: =C13 -> 100 | M13: =C13 -> 100 | N13: ops | O13: Arts | P13: None | Q13: 0 | R13: 0
A14: H_StatusQuo_Decline | B14: Status-Quo + DeclineTrend | C14: 0 | D14: 0 | E14: 0 | F14: 0 | G14: 0 | H14: Keep open but decline per district forecast | I14: =C14/3 -> 0 | J14: =I14+C14/3 -> 0 | K14: =J14+C14/3 -> 0 | L14: =C14 -> 0 | M14: =C14 -> 0 | O14: None | P14: None | Q14: 1 | R14: 1
A16: ScenarioKey | B16: Year | C16: Echo_ADM | D16: Pima_ADM | E16: Total_ADM | F16: VarUnit$ | G16: EchoFixed$ | H16: PimaFixed$ | I16: Key | O16: None | P16: None
A17: =A2 -> D_CUSTOM1 | B17: FY2026 | C17: =IF(D2=1,0, BaselineCalc!$B$7 + ROUND(I2*F2,0)) -> 257 | D17: =IF(E2=1,0, BaselineCalc!$B$8 + I2 - ROUND(I2*F2,0)) -> 296 | E17: =C17+D17 -> 553 | F17: =YearMap!B2 -> 6414.5115 | G17: =YearMap!C2 -> 1404302.9 | H17: =YearMap!D2 -> 1617407.2 | I17: =A17&"|"&B17 -> D_CUSTOM1|FY2026 | O17: None | P17: None
A18: =A2 -> D_CUSTOM1 | B18: FY2027 | C18: =IF(D2=1,0, BaselineCalc!$B$7 + ROUND(J2*F2,0)) -> 257 | D18: =IF(E2=1,0, BaselineCalc!$B$8 + J2 - ROUND(J2*F2,0)) -> 296 | E18: =C18+D18 -> 553 | F18: =YearMap!B3 -> 6574.8743 | G18: =YearMap!C3 -> 1439410.4 | H18: =YearMap!D3 -> 1657842.4 | I18: =A18&"|"&B18 -> D_CUSTOM1|FY2027 | O18: None | P18: None
A19: =A2 -> D_CUSTOM1 | B19: FY2028 | C19: =IF(D2=1,0, BaselineCalc!$B$7 + ROUND(K2*F2,0)) -> 257 | D19: =IF(E2=1,0, BaselineCalc!$B$8 + K2 - ROUND(K2*F2,0)) -> 296 | E19: =C19+D19 -> 553 | F19: =YearMap!B4 -> 6739.2461 | G19: =YearMap!C4 -> 1475395.7 | H19: =YearMap!D4 -> 1699288.4 | I19: =A19&"|"&B19 -> D_CUSTOM1|FY2028 | O19: None | P19: None
A20: =A2 -> D_CUSTOM1 | B20: FY2029 | C20: =IF(D2=1,0, BaselineCalc!$B$7 + ROUND(L2*F2,0)) -> 257 | D20: =IF(E2=1,0, BaselineCalc!$B$8 + L2 - ROUND(L2*F2,0)) -> 296 | E20: =C20+D20 -> 553 | F20: =YearMap!B5 -> 6907.7273 | G20: =YearMap!C5 -> 1512280.6 | H20: =YearMap!D5 -> 1741770.6 | I20: =A20&"|"&B20 -> D_CUSTOM1|FY2029 | O20: None | P20: None
A21: =A2 -> D_CUSTOM1 | B21: FY2030 | C21: =IF(D2=1,0, BaselineCalc!$B$7 + ROUND(M2*F2,0)) -> 257 | D21: =IF(E2=1,0, BaselineCalc!$B$8 + M2 - ROUND(M2*F2,0)) -> 296 | E21: =C21+D21 -> 553 | F21: =YearMap!B6 -> 7080.4205 | G21: =YearMap!C6 -> 1550087.6 | H21: =YearMap!D6 -> 1785314.9 | I21: =A21&"|"&B21 -> D_CUSTOM1|FY2030 | O21: None | P21: None
A22: =A3 -> E_StatusQuo_Targets | B22: FY2026 | C22: =IF(D3=1,0, BaselineCalc!$B$7 + ROUND(I3*F3,0)) -> 274 | D22: =IF(E3=1,0, BaselineCalc!$B$8 + I3 - ROUND(I3*F3,0)) -> 312.33333 | E22: =C22+D22 -> 586.33333 | F22: =YearMap!B2 -> 6414.5115 | G22: =YearMap!C2 -> 1404302.9 | H22: =YearMap!D2 -> 1617407.2 | I22: =A22&"|"&B22 -> E_StatusQuo_Targets|FY2026 | O22: None | P22: None
A23: =A3 -> E_StatusQuo_Targets | B23: FY2027 | C23: =IF(D3=1,0, BaselineCalc!$B$7 + ROUND(J3*F3,0)) -> 290 | D23: =IF(E3=1,0, BaselineCalc!$B$8 + J3 - ROUND(J3*F3,0)) -> 329.66667 | E23: =C23+D23 -> 619.66667 | F23: =YearMap!B3 -> 6574.8743 | G23: =YearMap!C3 -> 1439410.4 | H23: =YearMap!D3 -> 1657842.4 | I23: =A23&"|"&B23 -> E_StatusQuo_Targets|FY2027 | O23: None | P23: None
A24: =A3 -> E_StatusQuo_Targets | B24: FY2028 | C24: =IF(D3=1,0, BaselineCalc!$B$7 + ROUND(K3*F3,0)) -> 307 | D24: =IF(E3=1,0, BaselineCalc!$B$8 + K3 - ROUND(K3*F3,0)) -> 346 | E24: =C24+D24 -> 653 | F24: =YearMap!B4 -> 6739.2461 | G24: =YearMap!C4 -> 1475395.7 | H24: =YearMap!D4 -> 1699288.4 | I24: =A24&"|"&B24 -> E_StatusQuo_Targets|FY2028 | O24: None | P24: None
A25: =A3 -> E_StatusQuo_Targets | B25: FY2029 | C25: =IF(D3=1,0, BaselineCalc!$B$7 + ROUND(L3*F3,0)) -> 307 | D25: =IF(E3=1,0, BaselineCalc!$B$8 + L3 - ROUND(L3*F3,0)) -> 346 | E25: =C25+D25 -> 653 | F25: =YearMap!B5 -> 6907.7273 | G25: =YearMap!C5 -> 1512280.6 | H25: =YearMap!D5 -> 1741770.6 | I25: =A25&"|"&B25 -> E_StatusQuo_Targets|FY2029 | O25: None | P25: None
A26: =A3 -> E_StatusQuo_Targets | B26: FY2030 | C26: =IF(D3=1,0, BaselineCalc!$B$7 + ROUND(M3*F3,0)) -> 307 | D26: =IF(E3=1,0, BaselineCalc!$B$8 + M3 - ROUND(M3*F3,0)) -> 346 | E26: =C26+D26 -> 653 | F26: =YearMap!B6 -> 7080.4205 | G26: =YearMap!C6 -> 1550087.6 | H26: =YearMap!D6 -> 1785314.9 | I26: =A26&"|"&B26 -> E_StatusQuo_Targets|FY2030 | O26: None | P26: None
A27: =A4 -> F_CoLocation_Echo_Targets | B27: FY2026 | C27: =IF(D4=1,0, BaselineCalc!$B$7 + ROUND(I4*F4,0)) -> 274 | D27: =IF(E4=1,0, BaselineCalc!$B$8 + I4 - ROUND(I4*F4,0)) -> 312.33333 | E27: =C27+D27 -> 586.33333 | F27: =YearMap!B2 -> 6414.5115 | G27: =YearMap!C2 -> 1404302.9 | H27: =YearMap!D2 -> 1617407.2 | I27: =A27&"|"&B27 -> F_CoLocation_Echo_Targets|FY2026 | O27: None | P27: None
A28: =A4 -> F_CoLocation_Echo_Targets | B28: FY2027 | C28: =IF(D4=1,0, BaselineCalc!$B$7 + ROUND(J4*F4,0)) -> 290 | D28: =IF(E4=1,0, BaselineCalc!$B$8 + J4 - ROUND(J4*F4,0)) -> 329.66667 | E28: =C28+D28 -> 619.66667 | F28: =YearMap!B3 -> 6574.8743 | G28: =YearMap!C3 -> 1439410.4 | H28: =YearMap!D3 -> 1657842.4 | I28: =A28&"|"&B28 -> F_CoLocation_Echo_Targets|FY2027 | O28: None | P28: None
A29: =A4 -> F_CoLocation_Echo_Targets | B29: FY2028 | C29: =IF(D4=1,0, BaselineCalc!$B$7 + ROUND(K4*F4,0)) -> 307 | D29: =IF(E4=1,0, BaselineCalc!$B$8 + K4 - ROUND(K4*F4,0)) -> 346 | E29: =C29+D29 -> 653 | F29: =YearMap!B4 -> 6739.2461 | G29: =YearMap!C4 -> 1475395.7 | H29: =YearMap!D4 -> 1699288.4 | I29: =A29&"|"&B29 -> F_CoLocation_Echo_Targets|FY2028 | O29: None | P29: None
A30: =A4 -> F_CoLocation_Echo_Targets | B30: FY2029 | C30: =IF(D4=1,0, BaselineCalc!$B$7 + ROUND(L4*F4,0)) -> 307 | D30: =IF(E4=1,0, BaselineCalc!$B$8 + L4 - ROUND(L4*F4,0)) -> 346 | E30: =C30+D30 -> 653 | F30: =YearMap!B5 -> 6907.7273 | G30: =YearMap!C5 -> 1512280.6 | H30: =YearMap!D5 -> 1741770.6 | I30: =A30&"|"&B30 -> F_CoLocation_Echo_Targets|FY2029 | O30: None | P30: None
A31: =A4 -> F_CoLocation_Echo_Targets | B31: FY2030 | C31: =IF(D4=1,0, BaselineCalc!$B$7 + ROUND(M4*F4,0)) -> 307 | D31: =IF(E4=1,0, BaselineCalc!$B$8 + M4 - ROUND(M4*F4,0)) -> 346 | E31: =C31+D31 -> 653 | F31: =YearMap!B6 -> 7080.4205 | G31: =YearMap!C6 -> 1550087.6 | H31: =YearMap!D6 -> 1785314.9 | I31: =A31&"|"&B31 -> F_CoLocation_Echo_Targets|FY2030 | O31: None | P31: None
A32: =A5 -> D_Grow_Both_Targets | B32: FY2026 | C32: =IF(D5=1,0, BaselineCalc!$B$7 + ROUND(I5*F5,0)) -> 290 | D32: =IF(E5=1,0, BaselineCalc!$B$8 + I5 - ROUND(I5*F5,0)) -> 329.66667 | E32: =C32+D32 -> 619.66667 | F32: =YearMap!B2 -> 6414.5115 | G32: =YearMap!C2 -> 1404302.9 | H32: =YearMap!D2 -> 1617407.2 | I32: =A32&"|"&B32 -> D_Grow_Both_Targets|FY2026 | O32: None | P32: None
A33: =A5 -> D_Grow_Both_Targets | B33: FY2027 | C33: =IF(D5=1,0, BaselineCalc!$B$7 + ROUND(J5*F5,0)) -> 324 | D33: =IF(E5=1,0, BaselineCalc!$B$8 + J5 - ROUND(J5*F5,0)) -> 362.33333 | E33: =C33+D33 -> 686.33333 | F33: =YearMap!B3 -> 6574.8743 | G33: =YearMap!C3 -> 1439410.4 | H33: =YearMap!D3 -> 1657842.4 | I33: =A33&"|"&B33 -> D_Grow_Both_Targets|FY2027 | O33: None | P33: None
A34: =A5 -> D_Grow_Both_Targets | B34: FY2028 | C34: =IF(D5=1,0, BaselineCalc!$B$7 + ROUND(K5*F5,0)) -> 357 | D34: =IF(E5=1,0, BaselineCalc!$B$8 + K5 - ROUND(K5*F5,0)) -> 396 | E34: =C34+D34 -> 753 | F34: =YearMap!B4 -> 6739.2461 | G34: =YearMap!C4 -> 1475395.7 | H34: =YearMap!D4 -> 1699288.4 | I34: =A34&"|"&B34 -> D_Grow_Both_Targets|FY2028 | O34: None | P34: None
A35: =A5 -> D_Grow_Both_Targets | B35: FY2029 | C35: =IF(D5=1,0, BaselineCalc!$B$7 + ROUND(L5*F5,0)) -> 357 | D35: =IF(E5=1,0, BaselineCalc!$B$8 + L5 - ROUND(L5*F5,0)) -> 396 | E35: =C35+D35 -> 753 | F35: =YearMap!B5 -> 6907.7273 | G35: =YearMap!C5 -> 1512280.6 | H35: =YearMap!D5 -> 1741770.6 | I35: =A35&"|"&B35 -> D_Grow_Both_Targets|FY2029 | O35: None | P35: None
A36: =A5 -> D_Grow_Both_Targets | B36: FY2030 | C36: =IF(D5=1,0, BaselineCalc!$B$7 + ROUND(M5*F5,0)) -> 357 | D36: =IF(E5=1,0, BaselineCalc!$B$8 + M5 - ROUND(M5*F5,0)) -> 396 | E36: =C36+D36 -> 753 | F36: =YearMap!B6 -> 7080.4205 | G36: =YearMap!C6 -> 1550087.6 | H36: =YearMap!D6 -> 1785314.9 | I36: =A36&"|"&B36 -> D_Grow_Both_Targets|FY2030 | O36: None | P36: None
A37: =A6 -> D_CUSTOM2 | B37: FY2026 | C37: =IF(D6=1,0, BaselineCalc!$B$7 + ROUND(I6*F6,0)) -> 257 | D37: =IF(E6=1,0, BaselineCalc!$B$8 + I6 - ROUND(I6*F6,0)) -> 296 | E37: =C37+D37 -> 553 | F37: =YearMap!B2 -> 6414.5115 | G37: =YearMap!C2 -> 1404302.9 | H37: =YearMap!D2 -> 1617407.2 | I37: =A37&"|"&B37 -> D_CUSTOM2|FY2026 | O37: None | P37: None
A38: =A6 -> D_CUSTOM2 | B38: FY2027 | C38: =IF(D6=1,0, BaselineCalc!$B$7 + ROUND(J6*F6,0)) -> 257 | D38: =IF(E6=1,0, BaselineCalc!$B$8 + J6 - ROUND(J6*F6,0)) -> 296 | E38: =C38+D38 -> 553 | F38: =YearMap!B3 -> 6574.8743 | G38: =YearMap!C3 -> 1439410.4 | H38: =YearMap!D3 -> 1657842.4 | I38: =A38&"|"&B38 -> D_CUSTOM2|FY2027 | O38: None | P38: None
A39: =A6 -> D_CUSTOM2 | B39: FY2028 | C39: =IF(D6=1,0, BaselineCalc!$B$7 + ROUND(K6*F6,0)) -> 257 | D39: =IF(E6=1,0, BaselineCalc!$B$8 + K6 - ROUND(K6*F6,0)) -> 296 | E39: =C39+D39 -> 553 | F39: =YearMap!B4 -> 6739.2461 | G39: =YearMap!C4 -> 1475395.7 | H39: =YearMap!D4 -> 1699288.4 | I39: =A39&"|"&B39 -> D_CUSTOM2|FY2028 | O39: None | P39: None
A40: =A6 -> D_CUSTOM2 | B40: FY2029 | C40: =IF(D6=1,0, BaselineCalc!$B$7 + ROUND(L6*F6,0)) -> 257 | D40: =IF(E6=1,0, BaselineCalc!$B$8 + L6 - ROUND(L6*F6,0)) -> 296 | E40: =C40+D40 -> 553 | F40: =YearMap!B5 -> 6907.7273 | G40: =YearMap!C5 -> 1512280.6 | H40: =YearMap!D5 -> 1741770.6 | I40: =A40&"|"&B40 -> D_CUSTOM2|FY2029 | O40: None | P40: None
A41: =A6 -> D_CUSTOM2 | B41: FY2030 | C41: =IF(D6=1,0, BaselineCalc!$B$7 + ROUND(M6*F6,0)) -> 257 | D41: =IF(E6=1,0, BaselineCalc!$B$8 + M6 - ROUND(M6*F6,0)) -> 296 | E41: =C41+D41 -> 553 | F41: =YearMap!B6 -> 7080.4205 | G41: =YearMap!C6 -> 1550087.6 | H41: =YearMap!D6 -> 1785314.9 | I41: =A41&"|"&B41 -> D_CUSTOM2|FY2030 | O41: None | P41: None
A42: =A7 -> G_EchoGHubRamp_PimaTargets | B42: FY2026 | C42: =IF(D7=1,0, BaselineCalc!$B$7 + ROUND(I7*F7,0)) -> 292 | D42: =IF(E7=1,0, BaselineCalc!$B$8 + I7 - ROUND(I7*F7,0)) -> 311 | E42: =C42+D42 -> 603 | F42: =YearMap!B2 -> 6414.5115 | G42: =YearMap!C2 -> 1404302.9 | H42: =YearMap!D2 -> 1617407.2 | I42: =A42&"|"&B42 -> G_EchoGHubRamp_PimaTargets|FY2026 | O42: None | P42: None
A43: =A7 -> G_EchoGHubRamp_PimaTargets | B43: FY2027 | C43: =IF(D7=1,0, BaselineCalc!$B$7 + ROUND(J7*F7,0)) -> 327 | D43: =IF(E7=1,0, BaselineCalc!$B$8 + J7 - ROUND(J7*F7,0)) -> 326 | E43: =C43+D43 -> 653 | F43: =YearMap!B3 -> 6574.8743 | G43: =YearMap!C3 -> 1439410.4 | H43: =YearMap!D3 -> 1657842.4 | I43: =A43&"|"&B43 -> G_EchoGHubRamp_PimaTargets|FY2027 | O43: None | P43: None
A44: =A7 -> G_EchoGHubRamp_PimaTargets | B44: FY2028 | C44: =IF(D7=1,0, BaselineCalc!$B$7 + ROUND(K7*F7,0)) -> 362 | D44: =IF(E7=1,0, BaselineCalc!$B$8 + K7 - ROUND(K7*F7,0)) -> 341 | E44: =C44+D44 -> 703 | F44: =YearMap!B4 -> 6739.2461 | G44: =YearMap!C4 -> 1475395.7 | H44: =YearMap!D4 -> 1699288.4 | I44: =A44&"|"&B44 -> G_EchoGHubRamp_PimaTargets|FY2028 | O44: None | P44: None
A45: =A7 -> G_EchoGHubRamp_PimaTargets | B45: FY2029 | C45: =IF(D7=1,0, BaselineCalc!$B$7 + ROUND(L7*F7,0)) -> 362 | D45: =IF(E7=1,0, BaselineCalc!$B$8 + L7 - ROUND(L7*F7,0)) -> 341 | E45: =C45+D45 -> 703 | F45: =YearMap!B5 -> 6907.7273 | G45: =YearMap!C5 -> 1512280.6 | H45: =YearMap!D5 -> 1741770.6 | I45: =A45&"|"&B45 -> G_EchoGHubRamp_PimaTargets|FY2029 | O45: None | P45: None
A46: =A7 -> G_EchoGHubRamp_PimaTargets | B46: FY2030 | C46: =IF(D7=1,0, BaselineCalc!$B$7 + ROUND(M7*F7,0)) -> 362 | D46: =IF(E7=1,0, BaselineCalc!$B$8 + M7 - ROUND(M7*F7,0)) -> 341 | E46: =C46+D46 -> 703 | F46: =YearMap!B6 -> 7080.4205 | G46: =YearMap!C6 -> 1550087.6 | H46: =YearMap!D6 -> 1785314.9 | I46: =A46&"|"&B46 -> G_EchoGHubRamp_PimaTargets|FY2030 | O46: None | P46: None
A47: =A8 -> A_Repurpose_Both_lease | B47: FY2026 | C47: =IF(D8=1,0, BaselineCalc!$B$7 + ROUND(I8*F8,0)) -> 0 | D47: =IF(E8=1,0, BaselineCalc!$B$8 + I8 - ROUND(I8*F8,0)) -> 0 | E47: =C47+D47 -> 0 | F47: =YearMap!B2 -> 6414.5115 | G47: =YearMap!C2 -> 1404302.9 | H47: =YearMap!D2 -> 1617407.2 | I47: =A47&"|"&B47 -> A_Repurpose_Both_lease|FY2026 | O47: None | P47: None
A48: =A8 -> A_Repurpose_Both_lease | B48: FY2027 | C48: =IF(D8=1,0, BaselineCalc!$B$7 + ROUND(J8*F8,0)) -> 0 | D48: =IF(E8=1,0, BaselineCalc!$B$8 + J8 - ROUND(J8*F8,0)) -> 0 | E48: =C48+D48 -> 0 | F48: =YearMap!B3 -> 6574.8743 | G48: =YearMap!C3 -> 1439410.4 | H48: =YearMap!D3 -> 1657842.4 | I48: =A48&"|"&B48 -> A_Repurpose_Both_lease|FY2027 | O48: None | P48: None
A49: =A8 -> A_Repurpose_Both_lease | B49: FY2028 | C49: =IF(D8=1,0, BaselineCalc!$B$7 + ROUND(K8*F8,0)) -> 0 | D49: =IF(E8=1,0, BaselineCalc!$B$8 + K8 - ROUND(K8*F8,0)) -> 0 | E49: =C49+D49 -> 0 | F49: =YearMap!B4 -> 6739.2461 | G49: =YearMap!C4 -> 1475395.7 | H49: =YearMap!D4 -> 1699288.4 | I49: =A49&"|"&B49 -> A_Repurpose_Both_lease|FY2028 | O49: None | P49: None
A50: =A8 -> A_Repurpose_Both_lease | B50: FY2029 | C50: =IF(D8=1,0, BaselineCalc!$B$7 + ROUND(L8*F8,0)) -> 0 | D50: =IF(E8=1,0, BaselineCalc!$B$8 + L8 - ROUND(L8*F8,0)) -> 0 | E50: =C50+D50 -> 0 | F50: =YearMap!B5 -> 6907.7273 | G50: =YearMap!C5 -> 1512280.6 | H50: =YearMap!D5 -> 1741770.6 | I50: =A50&"|"&B50 -> A_Repurpose_Both_lease|FY2029 | O50: None | P50: None
A51: =A8 -> A_Repurpose_Both_lease | B51: FY2030 | C51: =IF(D8=1,0, BaselineCalc!$B$7 + ROUND(M8*F8,0)) -> 0 | D51: =IF(E8=1,0, BaselineCalc!$B$8 + M8 - ROUND(M8*F8,0)) -> 0 | E51: =C51+D51 -> 0 | F51: =YearMap!B6 -> 7080.4205 | G51: =YearMap!C6 -> 1550087.6 | H51: =YearMap!D6 -> 1785314.9 | I51: =A51&"|"&B51 -> A_Repurpose_Both_lease|FY2030 | O51: None | P51: None
A52: =A9 -> A_Repurpose_Both_ops | B52: FY2026 | C52: =IF(D9=1,0, BaselineCalc!$B$7 + ROUND(I9*F9,0)) -> 0 | D52: =IF(E9=1,0, BaselineCalc!$B$8 + I9 - ROUND(I9*F9,0)) -> 0 | E52: =C52+D52 -> 0 | F52: =YearMap!B2 -> 6414.5115 | G52: =YearMap!C2 -> 1404302.9 | H52: =YearMap!D2 -> 1617407.2 | I52: =A52&"|"&B52 -> A_Repurpose_Both_ops|FY2026 | O52: None | P52: None
A53: =A9 -> A_Repurpose_Both_ops | B53: FY2027 | C53: =IF(D9=1,0, BaselineCalc!$B$7 + ROUND(J9*F9,0)) -> 0 | D53: =IF(E9=1,0, BaselineCalc!$B$8 + J9 - ROUND(J9*F9,0)) -> 0 | E53: =C53+D53 -> 0 | F53: =YearMap!B3 -> 6574.8743 | G53: =YearMap!C3 -> 1439410.4 | H53: =YearMap!D3 -> 1657842.4 | I53: =A53&"|"&B53 -> A_Repurpose_Both_ops|FY2027 | O53: None | P53: None
A54: =A9 -> A_Repurpose_Both_ops | B54: FY2028 | C54: =IF(D9=1,0, BaselineCalc!$B$7 + ROUND(K9*F9,0)) -> 0 | D54: =IF(E9=1,0, BaselineCalc!$B$8 + K9 - ROUND(K9*F9,0)) -> 0 | E54: =C54+D54 -> 0 | F54: =YearMap!B4 -> 6739.2461 | G54: =YearMap!C4 -> 1475395.7 | H54: =YearMap!D4 -> 1699288.4 | I54: =A54&"|"&B54 -> A_Repurpose_Both_ops|FY2028 | O54: None | P54: None
A55: =A9 -> A_Repurpose_Both_ops | B55: FY2029 | C55: =IF(D9=1,0, BaselineCalc!$B$7 + ROUND(L9*F9,0)) -> 0 | D55: =IF(E9=1,0, BaselineCalc!$B$8 + L9 - ROUND(L9*F9,0)) -> 0 | E55: =C55+D55 -> 0 | F55: =YearMap!B5 -> 6907.7273 | G55: =YearMap!C5 -> 1512280.6 | H55: =YearMap!D5 -> 1741770.6 | I55: =A55&"|"&B55 -> A_Repurpose_Both_ops|FY2029 | O55: None | P55: None
A56: =A9 -> A_Repurpose_Both_ops | B56: FY2030 | C56: =IF(D9=1,0, BaselineCalc!$B$7 + ROUND(M9*F9,0)) -> 0 | D56: =IF(E9=1,0, BaselineCalc!$B$8 + M9 - ROUND(M9*F9,0)) -> 0 | E56: =C56+D56 -> 0 | F56: =YearMap!B6 -> 7080.4205 | G56: =YearMap!C6 -> 1550087.6 | H56: =YearMap!D6 -> 1785314.9 | I56: =A56&"|"&B56 -> A_Repurpose_Both_ops|FY2030 | O56: None | P56: None
A57: =A10 -> B_Repurpose_Echo_lease_PimaTargets | B57: FY2026 | C57: =IF(D10=1,0, BaselineCalc!$B$7 + ROUND(I10*F10,0)) -> 0 | D57: =IF(E10=1,0, BaselineCalc!$B$8 + I10 - ROUND(I10*F10,0)) -> 296 | E57: =C57+D57 -> 296 | F57: =YearMap!B2 -> 6414.5115 | G57: =YearMap!C2 -> 1404302.9 | H57: =YearMap!D2 -> 1617407.2 | I57: =A57&"|"&B57 -> B_Repurpose_Echo_lease_PimaTargets|FY2026 | O57: None | P57: None
A58: =A10 -> B_Repurpose_Echo_lease_PimaTargets | B58: FY2027 | C58: =IF(D10=1,0, BaselineCalc!$B$7 + ROUND(J10*F10,0)) -> 0 | D58: =IF(E10=1,0, BaselineCalc!$B$8 + J10 - ROUND(J10*F10,0)) -> 296 | E58: =C58+D58 -> 296 | F58: =YearMap!B3 -> 6574.8743 | G58: =YearMap!C3 -> 1439410.4 | H58: =YearMap!D3 -> 1657842.4 | I58: =A58&"|"&B58 -> B_Repurpose_Echo_lease_PimaTargets|FY2027 | O58: None | P58: None
A59: =A10 -> B_Repurpose_Echo_lease_PimaTargets | B59: FY2028 | C59: =IF(D10=1,0, BaselineCalc!$B$7 + ROUND(K10*F10,0)) -> 0 | D59: =IF(E10=1,0, BaselineCalc!$B$8 + K10 - ROUND(K10*F10,0)) -> 296 | E59: =C59+D59 -> 296 | F59: =YearMap!B4 -> 6739.2461 | G59: =YearMap!C4 -> 1475395.7 | H59: =YearMap!D4 -> 1699288.4 | I59: =A59&"|"&B59 -> B_Repurpose_Echo_lease_PimaTargets|FY2028 | O59: None | P59: None
A60: =A10 -> B_Repurpose_Echo_lease_PimaTargets | B60: FY2029 | C60: =IF(D10=1,0, BaselineCalc!$B$7 + ROUND(L10*F10,0)) -> 0 | D60: =IF(E10=1,0, BaselineCalc!$B$8 + L10 - ROUND(L10*F10,0)) -> 296 | E60: =C60+D60 -> 296 | F60: =YearMap!B5 -> 6907.7273 | G60: =YearMap!C5 -> 1512280.6 | H60: =YearMap!D5 -> 1741770.6 | I60: =A60&"|"&B60 -> B_Repurpose_Echo_lease_PimaTargets|FY2029 | O60: None | P60: None
A61: =A10 -> B_Repurpose_Echo_lease_PimaTargets | B61: FY2030 | C61: =IF(D10=1,0, BaselineCalc!$B$7 + ROUND(M10*F10,0)) -> 0 | D61: =IF(E10=1,0, BaselineCalc!$B$8 + M10 - ROUND(M10*F10,0)) -> 296 | E61: =C61+D61 -> 296 | F61: =YearMap!B6 -> 7080.4205 | G61: =YearMap!C6 -> 1550087.6 | H61: =YearMap!D6 -> 1785314.9 | I61: =A61&"|"&B61 -> B_Repurpose_Echo_lease_PimaTargets|FY2030 | O61: None | P61: None
A62: =A11 -> B_Repurpose_Echo_ops_PimaTargets | B62: FY2026 | C62: =IF(D11=1,0, BaselineCalc!$B$7 + ROUND(I11*F11,0)) -> 0 | D62: =IF(E11=1,0, BaselineCalc!$B$8 + I11 - ROUND(I11*F11,0)) -> 312.66667 | E62: =C62+D62 -> 312.66667 | F62: =YearMap!B2 -> 6414.5115 | G62: =YearMap!C2 -> 1404302.9 | H62: =YearMap!D2 -> 1617407.2 | I62: =A62&"|"&B62 -> B_Repurpose_Echo_ops_PimaTargets|FY2026 | O62: None | P62: None
A63: =A11 -> B_Repurpose_Echo_ops_PimaTargets | B63: FY2027 | C63: =IF(D11=1,0, BaselineCalc!$B$7 + ROUND(J11*F11,0)) -> 0 | D63: =IF(E11=1,0, BaselineCalc!$B$8 + J11 - ROUND(J11*F11,0)) -> 329.33333 | E63: =C63+D63 -> 329.33333 | F63: =YearMap!B3 -> 6574.8743 | G63: =YearMap!C3 -> 1439410.4 | H63: =YearMap!D3 -> 1657842.4 | I63: =A63&"|"&B63 -> B_Repurpose_Echo_ops_PimaTargets|FY2027 | O63: None | P63: None
A64: =A11 -> B_Repurpose_Echo_ops_PimaTargets | B64: FY2028 | C64: =IF(D11=1,0, BaselineCalc!$B$7 + ROUND(K11*F11,0)) -> 0 | D64: =IF(E11=1,0, BaselineCalc!$B$8 + K11 - ROUND(K11*F11,0)) -> 346 | E64: =C64+D64 -> 346 | F64: =YearMap!B4 -> 6739.2461 | G64: =YearMap!C4 -> 1475395.7 | H64: =YearMap!D4 -> 1699288.4 | I64: =A64&"|"&B64 -> B_Repurpose_Echo_ops_PimaTargets|FY2028 | O64: None | P64: None
A65: =A11 -> B_Repurpose_Echo_ops_PimaTargets | B65: FY2029 | C65: =IF(D11=1,0, BaselineCalc!$B$7 + ROUND(L11*F11,0)) -> 0 | D65: =IF(E11=1,0, BaselineCalc!$B$8 + L11 - ROUND(L11*F11,0)) -> 346 | E65: =C65+D65 -> 346 | F65: =YearMap!B5 -> 6907.7273 | G65: =YearMap!C5 -> 1512280.6 | H65: =YearMap!D5 -> 1741770.6 | I65: =A65&"|"&B65 -> B_Repurpose_Echo_ops_PimaTargets|FY2029 | O65: None | P65: None
A66: =A11 -> B_Repurpose_Echo_ops_PimaTargets | B66: FY2030 | C66: =IF(D11=1,0, BaselineCalc!$B$7 + ROUND(M11*F11,0)) -> 0 | D66: =IF(E11=1,0, BaselineCalc!$B$8 + M11 - ROUND(M11*F11,0)) -> 346 | E66: =C66+D66 -> 346 | F66: =YearMap!B6 -> 7080.4205 | G66: =YearMap!C6 -> 1550087.6 | H66: =YearMap!D6 -> 1785314.9 | I66: =A66&"|"&B66 -> B_Repurpose_Echo_ops_PimaTargets|FY2030 | O66: None | P66: None
A67: =A12 -> C_Repurpose_Pima_lease_EchoGHub_EchoTargets | B67: FY2026 | C67: =IF(D12=1,0, BaselineCalc!$B$7 + ROUND(I12*F12,0)) -> 257 | D67: =IF(E12=1,0, BaselineCalc!$B$8 + I12 - ROUND(I12*F12,0)) -> 0 | E67: =C67+D67 -> 257 | F67: =YearMap!B2 -> 6414.5115 | G67: =YearMap!C2 -> 1404302.9 | H67: =YearMap!D2 -> 1617407.2 | I67: =A67&"|"&B67 -> C_Repurpose_Pima_lease_EchoGHub_EchoTargets|FY2026 | O67: None | P67: None
A68: =A12 -> C_Repurpose_Pima_lease_EchoGHub_EchoTargets | B68: FY2027 | C68: =IF(D12=1,0, BaselineCalc!$B$7 + ROUND(J12*F12,0)) -> 257 | D68: =IF(E12=1,0, BaselineCalc!$B$8 + J12 - ROUND(J12*F12,0)) -> 0 | E68: =C68+D68 -> 257 | F68: =YearMap!B3 -> 6574.8743 | G68: =YearMap!C3 -> 1439410.4 | H68: =YearMap!D3 -> 1657842.4 | I68: =A68&"|"&B68 -> C_Repurpose_Pima_lease_EchoGHub_EchoTargets|FY2027 | O68: None | P68: None
A69: =A12 -> C_Repurpose_Pima_lease_EchoGHub_EchoTargets | B69: FY2028 | C69: =IF(D12=1,0, BaselineCalc!$B$7 + ROUND(K12*F12,0)) -> 257 | D69: =IF(E12=1,0, BaselineCalc!$B$8 + K12 - ROUND(K12*F12,0)) -> 0 | E69: =C69+D69 -> 257 | F69: =YearMap!B4 -> 6739.2461 | G69: =YearMap!C4 -> 1475395.7 | H69: =YearMap!D4 -> 1699288.4 | I69: =A69&"|"&B69 -> C_Repurpose_Pima_lease_EchoGHub_EchoTargets|FY2028 | O69: None | P69: None
A70: =A12 -> C_Repurpose_Pima_lease_EchoGHub_EchoTargets | B70: FY2029 | C70: =IF(D12=1,0, BaselineCalc!$B$7 + ROUND(L12*F12,0)) -> 257 | D70: =IF(E12=1,0, BaselineCalc!$B$8 + L12 - ROUND(L12*F12,0)) -> 0 | E70: =C70+D70 -> 257 | F70: =YearMap!B5 -> 6907.7273 | G70: =YearMap!C5 -> 1512280.6 | H70: =YearMap!D5 -> 1741770.6 | I70: =A70&"|"&B70 -> C_Repurpose_Pima_lease_EchoGHub_EchoTargets|FY2029 | O70: None | P70: None
A71: =A12 -> C_Repurpose_Pima_lease_EchoGHub_EchoTargets | B71: FY2030 | C71: =IF(D12=1,0, BaselineCalc!$B$7 + ROUND(M12*F12,0)) -> 257 | D71: =IF(E12=1,0, BaselineCalc!$B$8 + M12 - ROUND(M12*F12,0)) -> 0 | E71: =C71+D71 -> 257 | F71: =YearMap!B6 -> 7080.4205 | G71: =YearMap!C6 -> 1550087.6 | H71: =YearMap!D6 -> 1785314.9 | I71: =A71&"|"&B71 -> C_Repurpose_Pima_lease_EchoGHub_EchoTargets|FY2030 | O71: None | P71: None
A72: =A13 -> C_Repurpose_Pima_ops_EchoGHub_EchoTargets | B72: FY2026 | C72: =IF(D13=1,0, BaselineCalc!$B$7 + ROUND(I13*F13,0)) -> 290 | D72: =IF(E13=1,0, BaselineCalc!$B$8 + I13 - ROUND(I13*F13,0)) -> 0 | E72: =C72+D72 -> 290 | F72: =YearMap!B2 -> 6414.5115 | G72: =YearMap!C2 -> 1404302.9 | H72: =YearMap!D2 -> 1617407.2 | I72: =A72&"|"&B72 -> C_Repurpose_Pima_ops_EchoGHub_EchoTargets|FY2026 | O72: None | P72: None
A73: =A13 -> C_Repurpose_Pima_ops_EchoGHub_EchoTargets | B73: FY2027 | C73: =IF(D13=1,0, BaselineCalc!$B$7 + ROUND(J13*F13,0)) -> 324 | D73: =IF(E13=1,0, BaselineCalc!$B$8 + J13 - ROUND(J13*F13,0)) -> 0 | E73: =C73+D73 -> 324 | F73: =YearMap!B3 -> 6574.8743 | G73: =YearMap!C3 -> 1439410.4 | H73: =YearMap!D3 -> 1657842.4 | I73: =A73&"|"&B73 -> C_Repurpose_Pima_ops_EchoGHub_EchoTargets|FY2027 | O73: None | P73: None
A74: =A13 -> C_Repurpose_Pima_ops_EchoGHub_EchoTargets | B74: FY2028 | C74: =IF(D13=1,0, BaselineCalc!$B$7 + ROUND(K13*F13,0)) -> 357 | D74: =IF(E13=1,0, BaselineCalc!$B$8 + K13 - ROUND(K13*F13,0)) -> 0 | E74: =C74+D74 -> 357 | F74: =YearMap!B4 -> 6739.2461 | G74: =YearMap!C4 -> 1475395.7 | H74: =YearMap!D4 -> 1699288.4 | I74: =A74&"|"&B74 -> C_Repurpose_Pima_ops_EchoGHub_EchoTargets|FY2028 | O74: None | P74: None
A75: =A13 -> C_Repurpose_Pima_ops_EchoGHub_EchoTargets | B75: FY2029 | C75: =IF(D13=1,0, BaselineCalc!$B$7 + ROUND(L13*F13,0)) -> 357 | D75: =IF(E13=1,0, BaselineCalc!$B$8 + L13 - ROUND(L13*F13,0)) -> 0 | E75: =C75+D75 -> 357 | F75: =YearMap!B5 -> 6907.7273 | G75: =YearMap!C5 -> 1512280.6 | H75: =YearMap!D5 -> 1741770.6 | I75: =A75&"|"&B75 -> C_Repurpose_Pima_ops_EchoGHub_EchoTargets|FY2029 | O75: None | P75: None
A76: =A13 -> C_Repurpose_Pima_ops_EchoGHub_EchoTargets | B76: FY2030 | C76: =IF(D13=1,0, BaselineCalc!$B$7 + ROUND(M13*F13,0)) -> 357 | D76: =IF(E13=1,0, BaselineCalc!$B$8 + M13 - ROUND(M13*F13,0)) -> 0 | E76: =C76+D76 -> 357 | F76: =YearMap!B6 -> 7080.4205 | G76: =YearMap!C6 -> 1550087.6 | H76: =YearMap!D6 -> 1785314.9 | I76: =A76&"|"&B76 -> C_Repurpose_Pima_ops_EchoGHub_EchoTargets|FY2030 | O76: None | P76: None

Sheet MultiYear_ProForma
A1: =AG1 -> Key | B1: ScenarioKey | C1: Year | D1: Echo_ADM | E1: Pima_ADM | F1: Total_ADM | G1: VarUnit$ | H1: EchoFixed$ | I1: PimaFixed$ | J1: OpsFactor | K1: ExtraSave | L1: EchoPotential_ADM | M1: PimaPotential_ADM | N1: Displaced_ADM | O1: Retained_ADM | P1: h | Q1: CarryFrac | R1: EchoFixedEff$ | S1: PimaFixedEff$ | T1: TI_adds$ | U1: SiteCost$ | V1: RetainedSvc$ | W1: Comparable_MO$ | X1: Comparable_per_Student$ | Y1: Aid_per_ADM | Z1: Net_MO_after_aid$ | AA1: Net_per_served$ | AB1: Overlay_ADM | AC1: Served_ADM | AD1: Revenue$ | AE1: Adj_MO$ | AF1: Net$ | AG1: Key
A2: =AG2 -> D_CUSTOM1|FY2026 | B2: =Scenarios!A2 -> D_CUSTOM1 | C2: FY2026 | D2: =IF(Scenarios!D2=1,0, L2) -> 257 | E2: =IF(Scenarios!E2=1,0, M2) -> 296 | F2: =D2+E2 -> 553 | G2: =YearMap!B2 -> 6414.5115 | H2: =YearMap!C2 -> 1404302.9 | I2: =YearMap!D2 -> 1617407.2 | J2: =1-BaselineCalc!$B$5 -> 0.993 | K2: =Scenarios!G2 -> 0 | L2: =IF(Scenarios!$Q2=1,BaselineCalc!$B$7*(1+Parameters_Public!$C44)^(IF($C2="FY2026",0,IF($C2="FY2027",1,IF($C2="FY2028",2,IF($C2="FY2029",3,IF($C2="FY2030",4,0))))))+ROUND(Scenarios!I2*Scenarios!$F2,0),BaselineCalc!$B$7+ROUND(Scenarios!I2*Scenarios!$F2,0)) -> 257 | M2: =IF(Scenarios!$R2=1,BaselineCalc!$B$8*(1+Parameters_Public!$C45)^(IF($C2="FY2026",0,IF($C2="FY2027",1,IF($C2="FY2028",2,IF($C2="FY2029",3,IF($C2="FY2030",4,0))))))+Scenarios!I2-ROUND(Scenarios!I2*Scenarios!$F2,0),BaselineCalc!$B$8+Scenarios!I2-ROUND(Scenarios!I2*Scenarios!$F2,0)) -> 296 | N2: =(L2-D2) + (M2-E2) -> 0 | O2: =(Parameters_Public!$C$22*(L2-D2)+Parameters_Public!$C$23*(M2-E2)) -> 0 | P2: =YearMap!E2 -> 1000 | Q2: =IF(Scenarios!N2="lease", YearMap!F2, YearMap!G2) -> 0.5 | R2: =IF(Scenarios!D2=1, Q2*H2, H2) -> 1404302.9 | S2: =IF(Scenarios!E2=1, Q2*I2, I2) -> 1617407.2 | T2: =IF(C2="FY2026", (Scenarios!D2+Scenarios!E2)*BaselineCalc!$B$22, 0) -> 0 | U2: =(R2+S2+G2*F2)*J2*(1-K2) -> 6522952.4 | V2: =O2*(G2+P2) -> 0 | W2: =U2+V2+IF(Parameters_Public!$C$26=1, T2, 0) -> 6522952.4 | X2: =IF(F2+O2>0, W2/(F2+O2),"") -> 11795.574 | Y2: =INDEX(YearMap!$I$2:$I$6, MATCH(C2, YearMap!$A$2:$A$6, 0)) -> 5013 | Z2: =W2 - ((Y2 + IF(Parameters_Public!$C$20=1, Parameters_Public!$C$19, 0))*AC2) -> 3334935 | AA2: =IF($AC2>0, $Z2/$AC2, 0) -> 6030.6239 | AB2: =MAX(0, (MAX(0, $D2-BaselineCalc!$B$7) + MAX(0, $E2-BaselineCalc!$B$8))) -> 0 | AC2: =IF(LEFT($B2,2)="A_", $O2, IF(LEFT($B2,2)="B_", $M2+$O2, IF(LEFT($B2,2)="C_", $L2+$O2, $F2))) -> 553 | AD2: =((Y2 + IF(Parameters_Public!$C$20=1, INDEX(YearMap!$O$2:$O$6, MATCH(C2, YearMap!$A$2:$A$6, 0)), 0))*AC2) + AC2*INDEX(YearMap!$P$2:$P$6, MATCH(C2, YearMap!$A$2:$A$6, 0)) -> 6063617.3 | AE2: =W2 - (1-Parameters_Public!$C42)*$G2*$AB2*$J2*(1-$K2) -> 6522952.4 | AF2: =AD2-AE2 -> -459335.03 | AG2: =B2&"|"&C2 -> D_CUSTOM1|FY2026
A3: =AG3 -> D_CUSTOM1|FY2027 | B3: =Scenarios!A2 -> D_CUSTOM1 | C3: FY2027 | D3: =IF(Scenarios!D2=1,0, L3) -> 257 | E3: =IF(Scenarios!E2=1,0, M3) -> 296 | F3: =D3+E3 -> 553 | G3: =YearMap!B3 -> 6574.8743 | H3: =YearMap!C3 -> 1439410.4 | I3: =YearMap!D3 -> 1657842.4 | J3: =1-BaselineCalc!$B$5 -> 0.993 | K3: =Scenarios!G2 -> 0 | L3: =IF(Scenarios!$Q2=1,BaselineCalc!$B$7*(1+Parameters_Public!$C44)^(IF($C3="FY2026",0,IF($C3="FY2027",1,IF($C3="FY2028",2,IF($C3="FY2029",3,IF($C3="FY2030",4,0))))))+ROUND(Scenarios!J2*Scenarios!$F2,0),BaselineCalc!$B$7+ROUND(Scenarios!J2*Scenarios!$F2,0)) -> 257 | M3: =IF(Scenarios!$R2=1,BaselineCalc!$B$8*(1+Parameters_Public!$C45)^(IF($C3="FY2026",0,IF($C3="FY2027",1,IF($C3="FY2028",2,IF($C3="FY2029",3,IF($C3="FY2030",4,0))))))+Scenarios!J2-ROUND(Scenarios!J2*Scenarios!$F2,0),BaselineCalc!$B$8+Scenarios!J2-ROUND(Scenarios!J2*Scenarios!$F2,0)) -> 296 | N3: =(L3-D3) + (M3-E3) -> 0 | O3: =(Parameters_Public!$C$22*(L3-D3)+Parameters_Public!$C$23*(M3-E3)) -> 0 | P3: =YearMap!E3 -> 800 | Q3: =IF(Scenarios!N2="lease", YearMap!F3, YearMap!G3) -> 0.4 | R3: =IF(Scenarios!D2=1, Q3*H3, H3) -> 1439410.4 | S3: =IF(Scenarios!E2=1, Q3*I3, I3) -> 1657842.4 | T3: =IF(C3="FY2026", (Scenarios!D2+Scenarios!E2)*BaselineCalc!$B$22, 0) -> 0 | U3: =(R3+S3+G3*F3)*J3*(1-K3) -> 6686026.2 | V3: =O3*(G3+P3) -> 0 | W3: =U3+V3+IF(Parameters_Public!$C$26=1, T3, 0) -> 6686026.2 | X3: =IF(F3+O3>0, W3/(F3+O3),"") -> 12090.463 | Y3: =INDEX(YearMap!$I$2:$I$6, MATCH(C3, YearMap!$A$2:$A$6, 0)) -> 5138.325 | Z3: =W3 - ((Y3 + IF(Parameters_Public!$C$20=1, Parameters_Public!$C$19, 0))*AC3) -> 3428704.1 | AA3: =IF($AC3>0, $Z3/$AC3, 0) -> 6200.1883 | AB3: =MAX(0, (MAX(0, $D3-BaselineCalc!$B$7) + MAX(0, $E3-BaselineCalc!$B$8))) -> 0 | AC3: =IF(LEFT($B3,2)="A_", $O3, IF(LEFT($B3,2)="B_", $M3+$O3, IF(LEFT($B3,2)="C_", $L3+$O3, $F3))) -> 553 | AD3: =((Y3 + IF(Parameters_Public!$C$20=1, INDEX(YearMap!$O$2:$O$6, MATCH(C3, YearMap!$A$2:$A$6, 0)), 0))*AC3) + AC3*INDEX(YearMap!$P$2:$P$6, MATCH(C3, YearMap!$A$2:$A$6, 0)) -> 6215207.8 | AE3: =W3 - (1-Parameters_Public!$C42)*$G3*$AB3*$J3*(1-$K3) -> 6686026.2 | AF3: =AD3-AE3 -> -470818.41 | AG3: =B3&"|"&C3 -> D_CUSTOM1|FY2027
A4: =AG4 -> D_CUSTOM1|FY2028 | B4: =Scenarios!A2 -> D_CUSTOM1 | C4: FY2028 | D4: =IF(Scenarios!D2=1,0, L4) -> 257 | E4: =IF(Scenarios!E2=1,0, M4) -> 296 | F4: =D4+E4 -> 553 | G4: =YearMap!B4 -> 6739.2461 | H4: =YearMap!C4 -> 1475395.7 | I4: =YearMap!D4 -> 1699288.4 | J4: =1-BaselineCalc!$B$5 -> 0.993 | K4: =Scenarios!G2 -> 0 | L4: =IF(Scenarios!$Q2=1,BaselineCalc!$B$7*(1+Parameters_Public!$C44)^(IF($C4="FY2026",0,IF($C4="FY2027",1,IF($C4="FY2028",2,IF($C4="FY2029",3,IF($C4="FY2030",4,0))))))+ROUND(Scenarios!K2*Scenarios!$F2,0),BaselineCalc!$B$7+ROUND(Scenarios!K2*Scenarios!$F2,0)) -> 257 | M4: =IF(Scenarios!$R2=1,BaselineCalc!$B$8*(1+Parameters_Public!$C45)^(IF($C4="FY2026",0,IF($C4="FY2027",1,IF($C4="FY2028",2,IF($C4="FY2029",3,IF($C4="FY2030",4,0))))))+Scenarios!K2-ROUND(Scenarios!K2*Scenarios!$F2,0),BaselineCalc!$B$8+Scenarios!K2-ROUND(Scenarios!K2*Scenarios!$F2,0)) -> 296 | N4: =(L4-D4) + (M4-E4) -> 0 | O4: =(Parameters_Public!$C$22*(L4-D4)+Parameters_Public!$C$23*(M4-E4)) -> 0 | P4: =YearMap!E4 -> 600 | Q4: =IF(Scenarios!N2="lease", YearMap!F4, YearMap!G4) -> 0.35 | R4: =IF(Scenarios!D2=1, Q4*H4, H4) -> 1475395.7 | S4: =IF(Scenarios!E2=1, Q4*I4, I4) -> 1699288.4 | T4: =IF(C4="FY2026", (Scenarios!D2+Scenarios!E2)*BaselineCalc!$B$22, 0) -> 0 | U4: =(R4+S4+G4*F4)*J4*(1-K4) -> 6853176.8 | V4: =O4*(G4+P4) -> 0 | W4: =U4+V4+IF(Parameters_Public!$C$26=1, T4, 0) -> 6853176.8 | X4: =IF(F4+O4>0, W4/(F4+O4),"") -> 12392.725 | Y4: =INDEX(YearMap!$I$2:$I$6, MATCH(C4, YearMap!$A$2:$A$6, 0)) -> 5266.7831 | Z4: =W4 - ((Y4 + IF(Parameters_Public!$C$20=1, Parameters_Public!$C$19, 0))*AC4) -> 3524817.4 | AA4: =IF($AC4>0, $Z4/$AC4, 0) -> 6373.9917 | AB4: =MAX(0, (MAX(0, $D4-BaselineCalc!$B$7) + MAX(0, $E4-BaselineCalc!$B$8))) -> 0 | AC4: =IF(LEFT($B4,2)="A_", $O4, IF(LEFT($B4,2)="B_", $M4+$O4, IF(LEFT($B4,2)="C_", $L4+$O4, $F4))) -> 553 | AD4: =((Y4 + IF(Parameters_Public!$C$20=1, INDEX(YearMap!$O$2:$O$6, MATCH(C4, YearMap!$A$2:$A$6, 0)), 0))*AC4) + AC4*INDEX(YearMap!$P$2:$P$6, MATCH(C4, YearMap!$A$2:$A$6, 0)) -> 6370588 | AE4: =W4 - (1-Parameters_Public!$C42)*$G4*$AB4*$J4*(1-$K4) -> 6853176.8 | AF4: =AD4-AE4 -> -482588.87 | AG4: =B4&"|"&C4 -> D_CUSTOM1|FY2028
A5: =AG5 -> D_CUSTOM1|FY2029 | B5: =Scenarios!A2 -> D_CUSTOM1 | C5: FY2029 | D5: =IF(Scenarios!D2=1,0, L5) -> 257 | E5: =IF(Scenarios!E2=1,0, M5) -> 296 | F5: =D5+E5 -> 553 | G5: =YearMap!B5 -> 6907.7273 | H5: =YearMap!C5 -> 1512280.6 | I5: =YearMap!D5 -> 1741770.6 | J5: =1-BaselineCalc!$B$5 -> 0.993 | K5: =Scenarios!G2 -> 0 | L5: =IF(Scenarios!$Q2=1,BaselineCalc!$B$7*(1+Parameters_Public!$C44)^(IF($C5="FY2026",0,IF($C5="FY2027",1,IF($C5="FY2028",2,IF($C5="FY2029",3,IF($C5="FY2030",4,0))))))+ROUND(Scenarios!L2*Scenarios!$F2,0),BaselineCalc!$B$7+ROUND(Scenarios!L2*Scenarios!$F2,0)) -> 257 | M5: =IF(Scenarios!$R2=1,BaselineCalc!$B$8*(1+Parameters_Public!$C45)^(IF($C5="FY2026",0,IF($C5="FY2027",1,IF($C5="FY2028",2,IF($C5="FY2029",3,IF($C5="FY2030",4,0))))))+Scenarios!L2-ROUND(Scenarios!L2*Scenarios!$F2,0),BaselineCalc!$B$8+Scenarios!L2-ROUND(Scenarios!L2*Scenarios!$F2,0)) -> 296 | N5: =(L5-D5) + (M5-E5) -> 0 | O5: =(Parameters_Public!$C$22*(L5-D5)+Parameters_Public!$C$23*(M5-E5)) -> 0 | P5: =YearMap!E5 -> 500 | Q5: =IF(Scenarios!N2="lease", YearMap!F5, YearMap!G5) -> 0.3 | R5: =IF(Scenarios!D2=1, Q5*H5, H5) -> 1512280.6 | S5: =IF(Scenarios!E2=1, Q5*I5, I5) -> 1741770.6 | T5: =IF(C5="FY2026", (Scenarios!D2+Scenarios!E2)*BaselineCalc!$B$22, 0) -> 0 | U5: =(R5+S5+G5*F5)*J5*(1-K5) -> 7024506.3 | V5: =O5*(G5+P5) -> 0 | W5: =U5+V5+IF(Parameters_Public!$C$26=1, T5, 0) -> 7024506.3 | X5: =IF(F5+O5>0, W5/(F5+O5),"") -> 12702.543 | Y5: =INDEX(YearMap!$I$2:$I$6, MATCH(C5, YearMap!$A$2:$A$6, 0)) -> 5398.4527 | Z5: =W5 - ((Y5 + IF(Parameters_Public!$C$20=1, Parameters_Public!$C$19, 0))*AC5) -> 3623333.6 | AA5: =IF($AC5>0, $Z5/$AC5, 0) -> 6552.1403 | AB5: =MAX(0, (MAX(0, $D5-BaselineCalc!$B$7) + MAX(0, $E5-BaselineCalc!$B$8))) -> 0 | AC5: =IF(LEFT($B5,2)="A_", $O5, IF(LEFT($B5,2)="B_", $M5+$O5, IF(LEFT($B5,2)="C_", $L5+$O5, $F5))) -> 553 | AD5: =((Y5 + IF(Parameters_Public!$C$20=1, INDEX(YearMap!$O$2:$O$6, MATCH(C5, YearMap!$A$2:$A$6, 0)), 0))*AC5) + AC5*INDEX(YearMap!$P$2:$P$6, MATCH(C5, YearMap!$A$2:$A$6, 0)) -> 6529852.7 | AE5: =W5 - (1-Parameters_Public!$C42)*$G5*$AB5*$J5*(1-$K5) -> 7024506.3 | AF5: =AD5-AE5 -> -494653.59 | AG5: =B5&"|"&C5 -> D_CUSTOM1|FY2029
A6: =AG6 -> D_CUSTOM1|FY2030 | B6: =Scenarios!A2 -> D_CUSTOM1 | C6: FY2030 | D6: =IF(Scenarios!D2=1,0, L6) -> 257 | E6: =IF(Scenarios!E2=1,0, M6) -> 296 | F6: =D6+E6 -> 553 | G6: =YearMap!B6 -> 7080.4205 | H6: =YearMap!C6 -> 1550087.6 | I6: =YearMap!D6 -> 1785314.9 | J6: =1-BaselineCalc!$B$5 -> 0.993 | K6: =Scenarios!G2 -> 0 | L6: =IF(Scenarios!$Q2=1,BaselineCalc!$B$7*(1+Parameters_Public!$C44)^(IF($C6="FY2026",0,IF($C6="FY2027",1,IF($C6="FY2028",2,IF($C6="FY2029",3,IF($C6="FY2030",4,0))))))+ROUND(Scenarios!M2*Scenarios!$F2,0),BaselineCalc!$B$7+ROUND(Scenarios!M2*Scenarios!$F2,0)) -> 257 | M6: =IF(Scenarios!$R2=1,BaselineCalc!$B$8*(1+Parameters_Public!$C45)^(IF($C6="FY2026",0,IF($C6="FY2027",1,IF($C6="FY2028",2,IF($C6="FY2029",3,IF($C6="FY2030",4,0))))))+Scenarios!M2-ROUND(Scenarios!M2*Scenarios!$F2,0),BaselineCalc!$B$8+Scenarios!M2-ROUND(Scenarios!M2*Scenarios!$F2,0)) -> 296 | N6: =(L6-D6) + (M6-E6) -> 0 | O6: =(Parameters_Public!$C$22*(L6-D6)+Parameters_Public!$C$23*(M6-E6)) -> 0 | P6: =YearMap!E6 -> 300 | Q6: =IF(Scenarios!N2="lease", YearMap!F6, YearMap!G6) -> 0.3 | R6: =IF(Scenarios!D2=1, Q6*H6, H6) -> 1550087.6 | S6: =IF(Scenarios!E2=1, Q6*I6, I6) -> 1785314.9 | T6: =IF(C6="FY2026", (Scenarios!D2+Scenarios!E2)*BaselineCalc!$B$22, 0) -> 0 | U6: =(R6+S6+G6*F6)*J6*(1-K6) -> 7200118.9 | V6: =O6*(G6+P6) -> 0 | W6: =U6+V6+IF(Parameters_Public!$C$26=1, T6, 0) -> 7200118.9 | X6: =IF(F6+O6>0, W6/(F6+O6),"") -> 13020.107 | Y6: =INDEX(YearMap!$I$2:$I$6, MATCH(C6, YearMap!$A$2:$A$6, 0)) -> 5533.414 | Z6: =W6 - ((Y6 + IF(Parameters_Public!$C$20=1, Parameters_Public!$C$19, 0))*AC6) -> 3724312.6 | AA6: =IF($AC6>0, $Z6/$AC6, 0) -> 6734.7425 | AB6: =MAX(0, (MAX(0, $D6-BaselineCalc!$B$7) + MAX(0, $E6-BaselineCalc!$B$8))) -> 0 | AC6: =IF(LEFT($B6,2)="A_", $O6, IF(LEFT($B6,2)="B_", $M6+$O6, IF(LEFT($B6,2)="C_", $L6+$O6, $F6))) -> 553 | AD6: =((Y6 + IF(Parameters_Public!$C$20=1, INDEX(YearMap!$O$2:$O$6, MATCH(C6, YearMap!$A$2:$A$6, 0)), 0))*AC6) + AC6*INDEX(YearMap!$P$2:$P$6, MATCH(C6, YearMap!$A$2:$A$6, 0)) -> 6693099 | AE6: =W6 - (1-Parameters_Public!$C42)*$G6*$AB6*$J6*(1-$K6) -> 7200118.9 | AF6: =AD6-AE6 -> -507019.93 | AG6: =B6&"|"&C6 -> D_CUSTOM1|FY2030
A7: =AG7 -> E_StatusQuo_Targets|FY2026 | B7: =Scenarios!A3 -> E_StatusQuo_Targets | C7: FY2026 | D7: =IF(Scenarios!D3=1,0, L7) -> 274 | E7: =IF(Scenarios!E3=1,0, M7) -> 312.33333 | F7: =D7+E7 -> 586.33333 | G7: =YearMap!B2 -> 6414.5115 | H7: =YearMap!C2 -> 1404302.9 | I7: =YearMap!D2 -> 1617407.2 | J7: =1-BaselineCalc!$B$5 -> 0.993 | K7: =Scenarios!G3 -> 0 | L7: =IF(Scenarios!$Q3=1,BaselineCalc!$B$7*(1+Parameters_Public!$C44)^(IF($C7="FY2026",0,IF($C7="FY2027",1,IF($C7="FY2028",2,IF($C7="FY2029",3,IF($C7="FY2030",4,0))))))+ROUND(Scenarios!I3*Scenarios!$F3,0),BaselineCalc!$B$7+ROUND(Scenarios!I3*Scenarios!$F3,0)) -> 274 | M7: =IF(Scenarios!$R3=1,BaselineCalc!$B$8*(1+Parameters_Public!$C45)^(IF($C7="FY2026",0,IF($C7="FY2027",1,IF($C7="FY2028",2,IF($C7="FY2029",3,IF($C7="FY2030",4,0))))))+Scenarios!I3-ROUND(Scenarios!I3*Scenarios!$F3,0),BaselineCalc!$B$8+Scenarios!I3-ROUND(Scenarios!I3*Scenarios!$F3,0)) -> 312.33333 | N7: =(L7-D7) + (M7-E7) -> 0 | O7: =(Parameters_Public!$C$22*(L7-D7)+Parameters_Public!$C$23*(M7-E7)) -> 0 | P7: =YearMap!E2 -> 1000 | Q7: =IF(Scenarios!N3="lease", YearMap!F2, YearMap!G2) -> 0.5 | R7: =IF(Scenarios!D3=1, Q7*H7, H7) -> 1404302.9 | S7: =IF(Scenarios!E3=1, Q7*I7, I7) -> 1617407.2 | T7: =IF(C7="FY2026", (Scenarios!D3+Scenarios!E3)*BaselineCalc!$B$22, 0) -> 0 | U7: =(R7+S7+G7*F7)*J7*(1-K7) -> 6735272.7 | V7: =O7*(G7+P7) -> 0 | W7: =U7+V7+IF(Parameters_Public!$C$26=1, T7, 0) -> 6735272.7 | X7: =IF(F7+O7>0, W7/(F7+O7),"") -> 11487.105 | Y7: =INDEX(YearMap!$I$2:$I$6, MATCH(C7, YearMap!$A$2:$A$6, 0)) -> 5013 | Z7: =W7 - ((Y7 + IF(Parameters_Public!$C$20=1, Parameters_Public!$C$19, 0))*AC7) -> 3355090.4 | AA7: =IF($AC7>0, $Z7/$AC7, 0) -> 5722.1552 | AB7: =MAX(0, (MAX(0, $D7-BaselineCalc!$B$7) + MAX(0, $E7-BaselineCalc!$B$8))) -> 33.333333 | AC7: =IF(LEFT($B7,2)="A_", $O7, IF(LEFT($B7,2)="B_", $M7+$O7, IF(LEFT($B7,2)="C_", $L7+$O7, $F7))) -> 586.33333 | AD7: =((Y7 + IF(Parameters_Public!$C$20=1, INDEX(YearMap!$O$2:$O$6, MATCH(C7, YearMap!$A$2:$A$6, 0)), 0))*AC7) + AC7*INDEX(YearMap!$P$2:$P$6, MATCH(C7, YearMap!$A$2:$A$6, 0)) -> 6429115.7 | AE7: =W7 - (1-Parameters_Public!$C42)*$G7*$AB7*$J7*(1-$K7) -> 6522952.4 | AF7: =AD7-AE7 -> -93836.697 | AG7: =B7&"|"&C7 -> E_StatusQuo_Targets|FY2026
A8: =AG8 -> E_StatusQuo_Targets|FY2027 | B8: =Scenarios!A3 -> E_StatusQuo_Targets | C8: FY2027 | D8: =IF(Scenarios!D3=1,0, L8) -> 290 | E8: =IF(Scenarios!E3=1,0, M8) -> 329.66667 | F8: =D8+E8 -> 619.66667 | G8: =YearMap!B3 -> 6574.8743 | H8: =YearMap!C3 -> 1439410.4 | I8: =YearMap!D3 -> 1657842.4 | J8: =1-BaselineCalc!$B$5 -> 0.993 | K8: =Scenarios!G3 -> 0 | L8: =IF(Scenarios!$Q3=1,BaselineCalc!$B$7*(1+Parameters_Public!$C44)^(IF($C8="FY2026",0,IF($C8="FY2027",1,IF($C8="FY2028",2,IF($C8="FY2029",3,IF($C8="FY2030",4,0))))))+ROUND(Scenarios!J3*Scenarios!$F3,0),BaselineCalc!$B$7+ROUND(Scenarios!J3*Scenarios!$F3,0)) -> 290 | M8: =IF(Scenarios!$R3=1,BaselineCalc!$B$8*(1+Parameters_Public!$C45)^(IF($C8="FY2026",0,IF($C8="FY2027",1,IF($C8="FY2028",2,IF($C8="FY2029",3,IF($C8="FY2030",4,0))))))+Scenarios!J3-ROUND(Scenarios!J3*Scenarios!$F3,0),BaselineCalc!$B$8+Scenarios!J3-ROUND(Scenarios!J3*Scenarios!$F3,0)) -> 329.66667 | N8: =(L8-D8) + (M8-E8) -> 0 | O8: =(Parameters_Public!$C$22*(L8-D8)+Parameters_Public!$C$23*(M8-E8)) -> 0 | P8: =YearMap!E3 -> 800 | Q8: =IF(Scenarios!N3="lease", YearMap!F3, YearMap!G3) -> 0.4 | R8: =IF(Scenarios!D3=1, Q8*H8, H8) -> 1439410.4 | S8: =IF(Scenarios!E3=1, Q8*I8, I8) -> 1657842.4 | T8: =IF(C8="FY2026", (Scenarios!D3+Scenarios!E3)*BaselineCalc!$B$22, 0) -> 0 | U8: =(R8+S8+G8*F8)*J8*(1-K8) -> 7121282.9 | V8: =O8*(G8+P8) -> 0 | W8: =U8+V8+IF(Parameters_Public!$C$26=1, T8, 0) -> 7121282.9 | X8: =IF(F8+O8>0, W8/(F8+O8),"") -> 11492.119 | Y8: =INDEX(YearMap!$I$2:$I$6, MATCH(C8, YearMap!$A$2:$A$6, 0)) -> 5138.325 | Z8: =W8 - ((Y8 + IF(Parameters_Public!$C$20=1, Parameters_Public!$C$19, 0))*AC8) -> 3471275.8 | AA8: =IF($AC8>0, $Z8/$AC8, 0) -> 5601.8437 | AB8: =MAX(0, (MAX(0, $D8-BaselineCalc!$B$7) + MAX(0, $E8-BaselineCalc!$B$8))) -> 66.666667 | AC8: =IF(LEFT($B8,2)="A_", $O8, IF(LEFT($B8,2)="B_", $M8+$O8, IF(LEFT($B8,2)="C_", $L8+$O8, $F8))) -> 619.66667 | AD8: =((Y8 + IF(Parameters_Public!$C$20=1, INDEX(YearMap!$O$2:$O$6, MATCH(C8, YearMap!$A$2:$A$6, 0)), 0))*AC8) + AC8*INDEX(YearMap!$P$2:$P$6, MATCH(C8, YearMap!$A$2:$A$6, 0)) -> 6964479.4 | AE8: =W8 - (1-Parameters_Public!$C42)*$G8*$AB8*$J8*(1-$K8) -> 6686026.2 | AF8: =AD8-AE8 -> 278453.18 | AG8: =B8&"|"&C8 -> E_StatusQuo_Targets|FY2027
A9: =AG9 -> E_StatusQuo_Targets|FY2028 | B9: =Scenarios!A3 -> E_StatusQuo_Targets | C9: FY2028 | D9: =IF(Scenarios!D3=1,0, L9) -> 307 | E9: =IF(Scenarios!E3=1,0, M9) -> 346 | F9: =D9+E9 -> 653 | G9: =YearMap!B4 -> 6739.2461 | H9: =YearMap!C4 -> 1475395.7 | I9: =YearMap!D4 -> 1699288.4 | J9: =1-BaselineCalc!$B$5 -> 0.993 | K9: =Scenarios!G3 -> 0 | L9: =IF(Scenarios!$Q3=1,BaselineCalc!$B$7*(1+Parameters_Public!$C44)^(IF($C9="FY2026",0,IF($C9="FY2027",1,IF($C9="FY2028",2,IF($C9="FY2029",3,IF($C9="FY2030",4,0))))))+ROUND(Scenarios!K3*Scenarios!$F3,0),BaselineCalc!$B$7+ROUND(Scenarios!K3*Scenarios!$F3,0)) -> 307 | M9: =IF(Scenarios!$R3=1,BaselineCalc!$B$8*(1+Parameters_Public!$C45)^(IF($C9="FY2026",0,IF($C9="FY2027",1,IF($C9="FY2028",2,IF($C9="FY2029",3,IF($C9="FY2030",4,0))))))+Scenarios!K3-ROUND(Scenarios!K3*Scenarios!$F3,0),BaselineCalc!$B$8+Scenarios!K3-ROUND(Scenarios!K3*Scenarios!$F3,0)) -> 346 | N9: =(L9-D9) + (M9-E9) -> 0 | O9: =(Parameters_Public!$C$22*(L9-D9)+Parameters_Public!$C$23*(M9-E9)) -> 0 | P9: =YearMap!E4 -> 600 | Q9: =IF(Scenarios!N3="lease", YearMap!F4, YearMap!G4) -> 0.35 | R9: =IF(Scenarios!D3=1, Q9*H9, H9) -> 1475395.7 | S9: =IF(Scenarios!E3=1, Q9*I9, I9) -> 1699288.4 | T9: =IF(C9="FY2026", (Scenarios!D3+Scenarios!E3)*BaselineCalc!$B$22, 0) -> 0 | U9: =(R9+S9+G9*F9)*J9*(1-K9) -> 7522384 | V9: =O9*(G9+P9) -> 0 | W9: =U9+V9+IF(Parameters_Public!$C$26=1, T9, 0) -> 7522384 | X9: =IF(F9+O9>0, W9/(F9+O9),"") -> 11519.73 | Y9: =INDEX(YearMap!$I$2:$I$6, MATCH(C9, YearMap!$A$2:$A$6, 0)) -> 5266.7831 | Z9: =W9 - ((Y9 + IF(Parameters_Public!$C$20=1, Parameters_Public!$C$19, 0))*AC9) -> 3592151.3 | AA9: =IF($AC9>0, $Z9/$AC9, 0) -> 5500.9973 | AB9: =MAX(0, (MAX(0, $D9-BaselineCalc!$B$7) + MAX(0, $E9-BaselineCalc!$B$8))) -> 100 | AC9: =IF(LEFT($B9,2)="A_", $O9, IF(LEFT($B9,2)="B_", $M9+$O9, IF(LEFT($B9,2)="C_", $L9+$O9, $F9))) -> 653 | AD9: =((Y9 + IF(Parameters_Public!$C$20=1, INDEX(YearMap!$O$2:$O$6, MATCH(C9, YearMap!$A$2:$A$6, 0)), 0))*AC9) + AC9*INDEX(YearMap!$P$2:$P$6, MATCH(C9, YearMap!$A$2:$A$6, 0)) -> 7522593 | AE9: =W9 - (1-Parameters_Public!$C42)*$G9*$AB9*$J9*(1-$K9) -> 6853176.8 | AF9: =AD9-AE9 -> 669416.19 | AG9: =B9&"|"&C9 -> E_StatusQuo_Targets|FY2028
A10: =AG10 -> E_StatusQuo_Targets|FY2029 | B10: =Scenarios!A3 -> E_StatusQuo_Targets | C10: FY2029 | D10: =IF(Scenarios!D3=1,0, L10) -> 307 | E10: =IF(Scenarios!E3=1,0, M10) -> 346 | F10: =D10+E10 -> 653 | G10: =YearMap!B5 -> 6907.7273 | H10: =YearMap!C5 -> 1512280.6 | I10: =YearMap!D5 -> 1741770.6 | J10: =1-BaselineCalc!$B$5 -> 0.993 | K10: =Scenarios!G3 -> 0 | L10: =IF(Scenarios!$Q3=1,BaselineCalc!$B$7*(1+Parameters_Public!$C44)^(IF($C10="FY2026",0,IF($C10="FY2027",1,IF($C10="FY2028",2,IF($C10="FY2029",3,IF($C10="FY2030",4,0))))))+ROUND(Scenarios!L3*Scenarios!$F3,0),BaselineCalc!$B$7+ROUND(Scenarios!L3*Scenarios!$F3,0)) -> 307 | M10: =IF(Scenarios!$R3=1,BaselineCalc!$B$8*(1+Parameters_Public!$C45)^(IF($C10="FY2026",0,IF($C10="FY2027",1,IF($C10="FY2028",2,IF($C10="FY2029",3,IF($C10="FY2030",4,0))))))+Scenarios!L3-ROUND(Scenarios!L3*Scenarios!$F3,0),BaselineCalc!$B$8+Scenarios!L3-ROUND(Scenarios!L3*Scenarios!$F3,0)) -> 346 | N10: =(L10-D10) + (M10-E10) -> 0 | O10: =(Parameters_Public!$C$22*(L10-D10)+Parameters_Public!$C$23*(M10-E10)) -> 0 | P10: =YearMap!E5 -> 500 | Q10: =IF(Scenarios!N3="lease", YearMap!F5, YearMap!G5) -> 0.3 | R10: =IF(Scenarios!D3=1, Q10*H10, H10) -> 1512280.6 | S10: =IF(Scenarios!E3=1, Q10*I10, I10) -> 1741770.6 | T10: =IF(C10="FY2026", (Scenarios!D3+Scenarios!E3)*BaselineCalc!$B$22, 0) -> 0 | U10: =(R10+S10+G10*F10)*J10*(1-K10) -> 7710443.6 | V10: =O10*(G10+P10) -> 0 | W10: =U10+V10+IF(Parameters_Public!$C$26=1, T10, 0) -> 7710443.6 | X10: =IF(F10+O10>0, W10/(F10+O10),"") -> 11807.724 | Y10: =INDEX(YearMap!$I$2:$I$6, MATCH(C10, YearMap!$A$2:$A$6, 0)) -> 5398.4527 | Z10: =W10 - ((Y10 + IF(Parameters_Public!$C$20=1, Parameters_Public!$C$19, 0))*AC10) -> 3694230.6 | AA10: =IF($AC10>0, $Z10/$AC10, 0) -> 5657.321 | AB10: =MAX(0, (MAX(0, $D10-BaselineCalc!$B$7) + MAX(0, $E10-BaselineCalc!$B$8))) -> 100 | AC10: =IF(LEFT($B10,2)="A_", $O10, IF(LEFT($B10,2)="B_", $M10+$O10, IF(LEFT($B10,2)="C_", $L10+$O10, $F10))) -> 653 | AD10: =((Y10 + IF(Parameters_Public!$C$20=1, INDEX(YearMap!$O$2:$O$6, MATCH(C10, YearMap!$A$2:$A$6, 0)), 0))*AC10) + AC10*INDEX(YearMap!$P$2:$P$6, MATCH(C10, YearMap!$A$2:$A$6, 0)) -> 7710657.9 | AE10: =W10 - (1-Parameters_Public!$C42)*$G10*$AB10*$J10*(1-$K10) -> 7024506.3 | AF10: =AD10-AE10 -> 686151.6 | AG10: =B10&"|"&C10 -> E_StatusQuo_Targets|FY2029
A11: =AG11 -> E_StatusQuo_Targets|FY2030 | B11: =Scenarios!A3 -> E_StatusQuo_Targets | C11: FY2030 | D11: =IF(Scenarios!D3=1,0, L11) -> 307 | E11: =IF(Scenarios!E3=1,0, M11) -> 346 | F11: =D11+E11 -> 653 | G11: =YearMap!B6 -> 7080.4205 | H11: =YearMap!C6 -> 1550087.6 | I11: =YearMap!D6 -> 1785314.9 | J11: =1-BaselineCalc!$B$5 -> 0.993 | K11: =Scenarios!G3 -> 0 | L11: =IF(Scenarios!$Q3=1,BaselineCalc!$B$7*(1+Parameters_Public!$C44)^(IF($C11="FY2026",0,IF($C11="FY2027",1,IF($C11="FY2028",2,IF($C11="FY2029",3,IF($C11="FY2030",4,0))))))+ROUND(Scenarios!M3*Scenarios!$F3,0),BaselineCalc!$B$7+ROUND(Scenarios!M3*Scenarios!$F3,0)) -> 307 | M11: =IF(Scenarios!$R3=1,BaselineCalc!$B$8*(1+Parameters_Public!$C45)^(IF($C11="FY2026",0,IF($C11="FY2027",1,IF($C11="FY2028",2,IF($C11="FY2029",3,IF($C11="FY2030",4,0))))))+Scenarios!M3-ROUND(Scenarios!M3*Scenarios!$F3,0),BaselineCalc!$B$8+Scenarios!M3-ROUND(Scenarios!M3*Scenarios!$F3,0)) -> 346 | N11: =(L11-D11) + (M11-E11) -> 0 | O11: =(Parameters_Public!$C$22*(L11-D11)+Parameters_Public!$C$23*(M11-E11)) -> 0 | P11: =YearMap!E6 -> 300 | Q11: =IF(Scenarios!N3="lease", YearMap!F6, YearMap!G6) -> 0.3 | R11: =IF(Scenarios!D3=1, Q11*H11, H11) -> 1550087.6 | S11: =IF(Scenarios!E3=1, Q11*I11, I11) -> 1785314.9 | T11: =IF(C11="FY2026", (Scenarios!D3+Scenarios!E3)*BaselineCalc!$B$22, 0) -> 0 | U11: =(R11+S11+G11*F11)*J11*(1-K11) -> 7903204.7 | V11: =O11*(G11+P11) -> 0 | W11: =U11+V11+IF(Parameters_Public!$C$26=1, T11, 0) -> 7903204.7 | X11: =IF(F11+O11>0, W11/(F11+O11),"") -> 12102.917 | Y11: =INDEX(YearMap!$I$2:$I$6, MATCH(C11, YearMap!$A$2:$A$6, 0)) -> 5533.414 | Z11: =W11 - ((Y11 + IF(Parameters_Public!$C$20=1, Parameters_Public!$C$19, 0))*AC11) -> 3798862 | AA11: =IF($AC11>0, $Z11/$AC11, 0) -> 5817.5528 | AB11: =MAX(0, (MAX(0, $D11-BaselineCalc!$B$7) + MAX(0, $E11-BaselineCalc!$B$8))) -> 100 | AC11: =IF(LEFT($B11,2)="A_", $O11, IF(LEFT($B11,2)="B_", $M11+$O11, IF(LEFT($B11,2)="C_", $L11+$O11, $F11))) -> 653 | AD11: =((Y11 + IF(Parameters_Public!$C$20=1, INDEX(YearMap!$O$2:$O$6, MATCH(C11, YearMap!$A$2:$A$6, 0)), 0))*AC11) + AC11*INDEX(YearMap!$P$2:$P$6, MATCH(C11, YearMap!$A$2:$A$6, 0)) -> 7903424.3 | AE11: =W11 - (1-Parameters_Public!$C42)*$G11*$AB11*$J11*(1-$K11) -> 7200118.9 | AF11: =AD11-AE11 -> 703305.39 | AG11: =B11&"|"&C11 -> E_StatusQuo_Targets|FY2030
A12: =AG12 -> F_CoLocation_Echo_Targets|FY2026 | B12: =Scenarios!A4 -> F_CoLocation_Echo_Targets | C12: FY2026 | D12: =IF(Scenarios!D4=1,0, L12) -> 274 | E12: =IF(Scenarios!E4=1,0, M12) -> 312.33333 | F12: =D12+E12 -> 586.33333 | G12: =YearMap!B2 -> 6414.5115 | H12: =YearMap!C2 -> 1404302.9 | I12: =YearMap!D2 -> 1617407.2 | J12: =1-BaselineCalc!$B$5 -> 0.993 | K12: =Scenarios!G4 -> 0.05 | L12: =IF(Scenarios!$Q4=1,BaselineCalc!$B$7*(1+Parameters_Public!$C44)^(IF($C12="FY2026",0,IF($C12="FY2027",1,IF($C12="FY2028",2,IF($C12="FY2029",3,IF($C12="FY2030",4,0))))))+ROUND(Scenarios!I4*Scenarios!$F4,0),BaselineCalc!$B$7+ROUND(Scenarios!I4*Scenarios!$F4,0)) -> 274 | M12: =IF(Scenarios!$R4=1,BaselineCalc!$B$8*(1+Parameters_Public!$C45)^(IF($C12="FY2026",0,IF($C12="FY2027",1,IF($C12="FY2028",2,IF($C12="FY2029",3,IF($C12="FY2030",4,0))))))+Scenarios!I4-ROUND(Scenarios!I4*Scenarios!$F4,0),BaselineCalc!$B$8+Scenarios!I4-ROUND(Scenarios!I4*Scenarios!$F4,0)) -> 312.33333 | N12: =(L12-D12) + (M12-E12) -> 0 | O12: =(Parameters_Public!$C$22*(L12-D12)+Parameters_Public!$C$23*(M12-E12)) -> 0 | P12: =YearMap!E2 -> 1000 | Q12: =IF(Scenarios!N4="lease", YearMap!F2, YearMap!G2) -> 0.5 | R12: =IF(Scenarios!D4=1, Q12*H12, H12) -> 1404302.9 | S12: =IF(Scenarios!E4=1, Q12*I12, I12) -> 1617407.2 | T12: =IF(C12="FY2026", (Scenarios!D4+Scenarios!E4)*BaselineCalc!$B$22, 0) -> 0 | U12: =(R12+S12+G12*F12)*J12*(1-K12) -> 6398509.1 | V12: =O12*(G12+P12) -> 0 | W12: =U12+V12+IF(Parameters_Public!$C$26=1, T12, 0) -> 6398509.1 | X12: =IF(F12+O12>0, W12/(F12+O12),"") -> 10912.75 | Y12: =INDEX(YearMap!$I$2:$I$6, MATCH(C12, YearMap!$A$2:$A$6, 0)) -> 5013 | Z12: =W12 - ((Y12 + IF(Parameters_Public!$C$20=1, Parameters_Public!$C$19, 0))*AC12) -> 3018326.7 | AA12: =IF($AC12>0, $Z12/$AC12, 0) -> 5147.8 | AB12: =MAX(0, (MAX(0, $D12-BaselineCalc!$B$7) + MAX(0, $E12-BaselineCalc!$B$8))) -> 33.333333 | AC12: =IF(LEFT($B12,2)="A_", $O12, IF(LEFT($B12,2)="B_", $M12+$O12, IF(LEFT($B12,2)="C_", $L12+$O12, $F12))) -> 586.33333 | AD12: =((Y12 + IF(Parameters_Public!$C$20=1, INDEX(YearMap!$O$2:$O$6, MATCH(C12, YearMap!$A$2:$A$6, 0)), 0))*AC12) + AC12*INDEX(YearMap!$P$2:$P$6, MATCH(C12, YearMap!$A$2:$A$6, 0)) -> 6429115.7 | AE12: =W12 - (1-Parameters_Public!$C42)*$G12*$AB12*$J12*(1-$K12) -> 6196804.8 | AF12: =AD12-AE12 -> 232310.92 | AG12: =B12&"|"&C12 -> F_CoLocation_Echo_Targets|FY2026
A13: =AG13 -> F_CoLocation_Echo_Targets|FY2027 | B13: =Scenarios!A4 -> F_CoLocation_Echo_Targets | C13: FY2027 | D13: =IF(Scenarios!D4=1,0, L13) -> 290 | E13: =IF(Scenarios!E4=1,0, M13) -> 329.66667 | F13: =D13+E13 -> 619.66667 | G13: =YearMap!B3 -> 6574.8743 | H13: =YearMap!C3 -> 1439410.4 | I13: =YearMap!D3 -> 1657842.4 | J13: =1-BaselineCalc!$B$5 -> 0.993 | K13: =Scenarios!G4 -> 0.05 | L13: =IF(Scenarios!$Q4=1,BaselineCalc!$B$7*(1+Parameters_Public!$C44)^(IF($C13="FY2026",0,IF($C13="FY2027",1,IF($C13="FY2028",2,IF($C13="FY2029",3,IF($C13="FY2030",4,0))))))+ROUND(Scenarios!J4*Scenarios!$F4,0),BaselineCalc!$B$7+ROUND(Scenarios!J4*Scenarios!$F4,0)) -> 290 | M13: =IF(Scenarios!$R4=1,BaselineCalc!$B$8*(1+Parameters_Public!$C45)^(IF($C13="FY2026",0,IF($C13="FY2027",1,IF($C13="FY2028",2,IF($C13="FY2029",3,IF($C13="FY2030",4,0))))))+Scenarios!J4-ROUND(Scenarios!J4*Scenarios!$F4,0),BaselineCalc!$B$8+Scenarios!J4-ROUND(Scenarios!J4*Scenarios!$F4,0)) -> 329.66667 | N13: =(L13-D13) + (M13-E13) -> 0 | O13: =(Parameters_Public!$C$22*(L13-D13)+Parameters_Public!$C$23*(M13-E13)) -> 0 | P13: =YearMap!E3 -> 800 | Q13: =IF(Scenarios!N4="lease", YearMap!F3, YearMap!G3) -> 0.4 | R13: =IF(Scenarios!D4=1, Q13*H13, H13) -> 1439410.4 | S13: =IF(Scenarios!E4=1, Q13*I13, I13) -> 1657842.4 | T13: =IF(C13="FY2026", (Scenarios!D4+Scenarios!E4)*BaselineCalc!$B$22, 0) -> 0 | U13: =(R13+S13+G13*F13)*J13*(1-K13) -> 6765218.7 | V13: =O13*(G13+P13) -> 0 | W13: =U13+V13+IF(Parameters_Public!$C$26=1, T13, 0) -> 6765218.7 | X13: =IF(F13+O13>0, W13/(F13+O13),"") -> 10917.513 | Y13: =INDEX(YearMap!$I$2:$I$6, MATCH(C13, YearMap!$A$2:$A$6, 0)) -> 5138.325 | Z13: =W13 - ((Y13 + IF(Parameters_Public!$C$20=1, Parameters_Public!$C$19, 0))*AC13) -> 3115211.6 | AA13: =IF($AC13>0, $Z13/$AC13, 0) -> 5027.2377 | AB13: =MAX(0, (MAX(0, $D13-BaselineCalc!$B$7) + MAX(0, $E13-BaselineCalc!$B$8))) -> 66.666667 | AC13: =IF(LEFT($B13,2)="A_", $O13, IF(LEFT($B13,2)="B_", $M13+$O13, IF(LEFT($B13,2)="C_", $L13+$O13, $F13))) -> 619.66667 | AD13: =((Y13 + IF(Parameters_Public!$C$20=1, INDEX(YearMap!$O$2:$O$6, MATCH(C13, YearMap!$A$2:$A$6, 0)), 0))*AC13) + AC13*INDEX(YearMap!$P$2:$P$6, MATCH(C13, YearMap!$A$2:$A$6, 0)) -> 6964479.4 | AE13: =W13 - (1-Parameters_Public!$C42)*$G13*$AB13*$J13*(1-$K13) -> 6351724.9 | AF13: =AD13-AE13 -> 612754.49 | AG13: =B13&"|"&C13 -> F_CoLocation_Echo_Targets|FY2027
A14: =AG14 -> F_CoLocation_Echo_Targets|FY2028 | B14: =Scenarios!A4 -> F_CoLocation_Echo_Targets | C14: FY2028 | D14: =IF(Scenarios!D4=1,0, L14) -> 307 | E14: =IF(Scenarios!E4=1,0, M14) -> 346 | F14: =D14+E14 -> 653 | G14: =YearMap!B4 -> 6739.2461 | H14: =YearMap!C4 -> 1475395.7 | I14: =YearMap!D4 -> 1699288.4 | J14: =1-BaselineCalc!$B$5 -> 0.993 | K14: =Scenarios!G4 -> 0.05 | L14: =IF(Scenarios!$Q4=1,BaselineCalc!$B$7*(1+Parameters_Public!$C44)^(IF($C14="FY2026",0,IF($C14="FY2027",1,IF($C14="FY2028",2,IF($C14="FY2029",3,IF($C14="FY2030",4,0))))))+ROUND(Scenarios!K4*Scenarios!$F4,0),BaselineCalc!$B$7+ROUND(Scenarios!K4*Scenarios!$F4,0)) -> 307 | M14: =IF(Scenarios!$R4=1,BaselineCalc!$B$8*(1+Parameters_Public!$C45)^(IF($C14="FY2026",0,IF($C14="FY2027",1,IF($C14="FY2028",2,IF($C14="FY2029",3,IF($C14="FY2030",4,0))))))+Scenarios!K4-ROUND(Scenarios!K4*Scenarios!$F4,0),BaselineCalc!$B$8+Scenarios!K4-ROUND(Scenarios!K4*Scenarios!$F4,0)) -> 346 | N14: =(L14-D14) + (M14-E14) -> 0 | O14: =(Parameters_Public!$C$22*(L14-D14)+Parameters_Public!$C$23*(M14-E14)) -> 0 | P14: =YearMap!E4 -> 600 | Q14: =IF(Scenarios!N4="lease", YearMap!F4, YearMap!G4) -> 0.35 | R14: =IF(Scenarios!D4=1, Q14*H14, H14) -> 1475395.7 | S14: =IF(Scenarios!E4=1, Q14*I14, I14) -> 1699288.4 | T14: =IF(C14="FY2026", (Scenarios!D4+Scenarios!E4)*BaselineCalc!$B$22, 0) -> 0 | U14: =(R14+S14+G14*F14)*J14*(1-K14) -> 7146264.8 | V14: =O14*(G14+P14) -> 0 | W14: =U14+V14+IF(Parameters_Public!$C$26=1, T14, 0) -> 7146264.8 | X14: =IF(F14+O14>0, W14/(F14+O14),"") -> 10943.744 | Y14: =INDEX(YearMap!$I$2:$I$6, MATCH(C14, YearMap!$A$2:$A$6, 0)) -> 5266.7831 | Z14: =W14 - ((Y14 + IF(Parameters_Public!$C$20=1, Parameters_Public!$C$19, 0))*AC14) -> 3216032.1 | AA14: =IF($AC14>0, $Z14/$AC14, 0) -> 4925.0108 | AB14: =MAX(0, (MAX(0, $D14-BaselineCalc!$B$7) + MAX(0, $E14-BaselineCalc!$B$8))) -> 100 | AC14: =IF(LEFT($B14,2)="A_", $O14, IF(LEFT($B14,2)="B_", $M14+$O14, IF(LEFT($B14,2)="C_", $L14+$O14, $F14))) -> 653 | AD14: =((Y14 + IF(Parameters_Public!$C$20=1, INDEX(YearMap!$O$2:$O$6, MATCH(C14, YearMap!$A$2:$A$6, 0)), 0))*AC14) + AC14*INDEX(YearMap!$P$2:$P$6, MATCH(C14, YearMap!$A$2:$A$6, 0)) -> 7522593 | AE14: =W14 - (1-Parameters_Public!$C42)*$G14*$AB14*$J14*(1-$K14) -> 6510518 | AF14: =AD14-AE14 -> 1012075 | AG14: =B14&"|"&C14 -> F_CoLocation_Echo_Targets|FY2028
A15: =AG15 -> F_CoLocation_Echo_Targets|FY2029 | B15: =Scenarios!A4 -> F_CoLocation_Echo_Targets | C15: FY2029 | D15: =IF(Scenarios!D4=1,0, L15) -> 307 | E15: =IF(Scenarios!E4=1,0, M15) -> 346 | F15: =D15+E15 -> 653 | G15: =YearMap!B5 -> 6907.7273 | H15: =YearMap!C5 -> 1512280.6 | I15: =YearMap!D5 -> 1741770.6 | J15: =1-BaselineCalc!$B$5 -> 0.993 | K15: =Scenarios!G4 -> 0.05 | L15: =IF(Scenarios!$Q4=1,BaselineCalc!$B$7*(1+Parameters_Public!$C44)^(IF($C15="FY2026",0,IF($C15="FY2027",1,IF($C15="FY2028",2,IF($C15="FY2029",3,IF($C15="FY2030",4,0))))))+ROUND(Scenarios!L4*Scenarios!$F4,0),BaselineCalc!$B$7+ROUND(Scenarios!L4*Scenarios!$F4,0)) -> 307 | M15: =IF(Scenarios!$R4=1,BaselineCalc!$B$8*(1+Parameters_Public!$C45)^(IF($C15="FY2026",0,IF($C15="FY2027",1,IF($C15="FY2028",2,IF($C15="FY2029",3,IF($C15="FY2030",4,0))))))+Scenarios!L4-ROUND(Scenarios!L4*Scenarios!$F4,0),BaselineCalc!$B$8+Scenarios!L4-ROUND(Scenarios!L4*Scenarios!$F4,0)) -> 346 | N15: =(L15-D15) + (M15-E15) -> 0 | O15: =(Parameters_Public!$C$22*(L15-D15)+Parameters_Public!$C$23*(M15-E15)) -> 0 | P15: =YearMap!E5 -> 500 | Q15: =IF(Scenarios!N4="lease", YearMap!F5, YearMap!G5) -> 0.3 | R15: =IF(Scenarios!D4=1, Q15*H15, H15) -> 1512280.6 | S15: =IF(Scenarios!E4=1, Q15*I15, I15) -> 1741770.6 | T15: =IF(C15="FY2026", (Scenarios!D4+Scenarios!E4)*BaselineCalc!$B$22, 0) -> 0 | U15: =(R15+S15+G15*F15)*J15*(1-K15) -> 7324921.4 | V15: =O15*(G15+P15) -> 0 | W15: =U15+V15+IF(Parameters_Public!$C$26=1, T15, 0) -> 7324921.4 | X15: =IF(F15+O15>0, W15/(F15+O15),"") -> 11217.338 | Y15: =INDEX(YearMap!$I$2:$I$6, MATCH(C15, YearMap!$A$2:$A$6, 0)) -> 5398.4527 | Z15: =W15 - ((Y15 + IF(Parameters_Public!$C$20=1, Parameters_Public!$C$19, 0))*AC15) -> 3308708.4 | AA15: =IF($AC15>0, $Z15/$AC15, 0) -> 5066.9348 | AB15: =MAX(0, (MAX(0, $D15-BaselineCalc!$B$7) + MAX(0, $E15-BaselineCalc!$B$8))) -> 100 | AC15: =IF(LEFT($B15,2)="A_", $O15, IF(LEFT($B15,2)="B_", $M15+$O15, IF(LEFT($B15,2)="C_", $L15+$O15, $F15))) -> 653 | AD15: =((Y15 + IF(Parameters_Public!$C$20=1, INDEX(YearMap!$O$2:$O$6, MATCH(C15, YearMap!$A$2:$A$6, 0)), 0))*AC15) + AC15*INDEX(YearMap!$P$2:$P$6, MATCH(C15, YearMap!$A$2:$A$6, 0)) -> 7710657.9 | AE15: =W15 - (1-Parameters_Public!$C42)*$G15*$AB15*$J15*(1-$K15) -> 6673281 | AF15: =AD15-AE15 -> 1037376.9 | AG15: =B15&"|"&C15 -> F_CoLocation_Echo_Targets|FY2029
A16: =AG16 -> F_CoLocation_Echo_Targets|FY2030 | B16: =Scenarios!A4 -> F_CoLocation_Echo_Targets | C16: FY2030 | D16: =IF(Scenarios!D4=1,0, L16) -> 307 | E16: =IF(Scenarios!E4=1,0, M16) -> 346 | F16: =D16+E16 -> 653 | G16: =YearMap!B6 -> 7080.4205 | H16: =YearMap!C6 -> 1550087.6 | I16: =YearMap!D6 -> 1785314.9 | J16: =1-BaselineCalc!$B$5 -> 0.993 | K16: =Scenarios!G4 -> 0.05 | L16: =IF(Scenarios!$Q4=1,BaselineCalc!$B$7*(1+Parameters_Public!$C44)^(IF($C16="FY2026",0,IF($C16="FY2027",1,IF($C16="FY2028",2,IF($C16="FY2029",3,IF($C16="FY2030",4,0))))))+ROUND(Scenarios!M4*Scenarios!$F4,0),BaselineCalc!$B$7+ROUND(Scenarios!M4*Scenarios!$F4,0)) -> 307 | M16: =IF(Scenarios!$R4=1,BaselineCalc!$B$8*(1+Parameters_Public!$C45)^(IF($C16="FY2026",0,IF($C16="FY2027",1,IF($C16="FY2028",2,IF($C16="FY2029",3,IF($C16="FY2030",4,0))))))+Scenarios!M4-ROUND(Scenarios!M4*Scenarios!$F4,0),BaselineCalc!$B$8+Scenarios!M4-ROUND(Scenarios!M4*Scenarios!$F4,0)) -> 346 | N16: =(L16-D16) + (M16-E16) -> 0 | O16: =(Parameters_Public!$C$22*(L16-D16)+Parameters_Public!$C$23*(M16-E16)) -> 0 | P16: =YearMap!E6 -> 300 | Q16: =IF(Scenarios!N4="lease", YearMap!F6, YearMap!G6) -> 0.3 | R16: =IF(Scenarios!D4=1, Q16*H16, H16) -> 1550087.6 | S16: =IF(Scenarios!E4=1, Q16*I16, I16) -> 1785314.9 | T16: =IF(C16="FY2026", (Scenarios!D4+Scenarios!E4)*BaselineCalc!$B$22, 0) -> 0 | U16: =(R16+S16+G16*F16)*J16*(1-K16) -> 7508044.4 | V16: =O16*(G16+P16) -> 0 | W16: =U16+V16+IF(Parameters_Public!$C$26=1, T16, 0) -> 7508044.4 | X16: =IF(F16+O16>0, W16/(F16+O16),"") -> 11497.771 | Y16: =INDEX(YearMap!$I$2:$I$6, MATCH(C16, YearMap!$A$2:$A$6, 0)) -> 5533.414 | Z16: =W16 - ((Y16 + IF(Parameters_Public!$C$20=1, Parameters_Public!$C$19, 0))*AC16) -> 3403701.7 | AA16: =IF($AC16>0, $Z16/$AC16, 0) -> 5212.4069 | AB16: =MAX(0, (MAX(0, $D16-BaselineCalc!$B$7) + MAX(0, $E16-BaselineCalc!$B$8))) -> 100 | AC16: =IF(LEFT($B16,2)="A_", $O16, IF(LEFT($B16,2)="B_", $M16+$O16, IF(LEFT($B16,2)="C_", $L16+$O16, $F16))) -> 653 | AD16: =((Y16 + IF(Parameters_Public!$C$20=1, INDEX(YearMap!$O$2:$O$6, MATCH(C16, YearMap!$A$2:$A$6, 0)), 0))*AC16) + AC16*INDEX(YearMap!$P$2:$P$6, MATCH(C16, YearMap!$A$2:$A$6, 0)) -> 7903424.3 | AE16: =W16 - (1-Parameters_Public!$C42)*$G16*$AB16*$J16*(1-$K16) -> 6840113 | AF16: =AD16-AE16 -> 1063311.3 | AG16: =B16&"|"&C16 -> F_CoLocation_Echo_Targets|FY2030
A17: =AG17 -> D_Grow_Both_Targets|FY2026 | B17: =Scenarios!A5 -> D_Grow_Both_Targets | C17: FY2026 | D17: =IF(Scenarios!D5=1,0, L17) -> 290 | E17: =IF(Scenarios!E5=1,0, M17) -> 329.66667 | F17: =D17+E17 -> 619.66667 | G17: =YearMap!B2 -> 6414.5115 | H17: =YearMap!C2 -> 1404302.9 | I17: =YearMap!D2 -> 1617407.2 | J17: =1-BaselineCalc!$B$5 -> 0.993 | K17: =Scenarios!G5 -> 0 | L17: =IF(Scenarios!$Q5=1,BaselineCalc!$B$7*(1+Parameters_Public!$C44)^(IF($C17="FY2026",0,IF($C17="FY2027",1,IF($C17="FY2028",2,IF($C17="FY2029",3,IF($C17="FY2030",4,0))))))+ROUND(Scenarios!I5*Scenarios!$F5,0),BaselineCalc!$B$7+ROUND(Scenarios!I5*Scenarios!$F5,0)) -> 290 | M17: =IF(Scenarios!$R5=1,BaselineCalc!$B$8*(1+Parameters_Public!$C45)^(IF($C17="FY2026",0,IF($C17="FY2027",1,IF($C17="FY2028",2,IF($C17="FY2029",3,IF($C17="FY2030",4,0))))))+Scenarios!I5-ROUND(Scenarios!I5*Scenarios!$F5,0),BaselineCalc!$B$8+Scenarios!I5-ROUND(Scenarios!I5*Scenarios!$F5,0)) -> 329.66667 | N17: =(L17-D17) + (M17-E17) -> 0 | O17: =(Parameters_Public!$C$22*(L17-D17)+Parameters_Public!$C$23*(M17-E17)) -> 0 | P17: =YearMap!E2 -> 1000 | Q17: =IF(Scenarios!N5="lease", YearMap!F2, YearMap!G2) -> 0.5 | R17: =IF(Scenarios!D5=1, Q17*H17, H17) -> 1404302.9 | S17: =IF(Scenarios!E5=1, Q17*I17, I17) -> 1617407.2 | T17: =IF(C17="FY2026", (Scenarios!D5+Scenarios!E5)*BaselineCalc!$B$22, 0) -> 0 | U17: =(R17+S17+G17*F17)*J17*(1-K17) -> 6947593 | V17: =O17*(G17+P17) -> 0 | W17: =U17+V17+IF(Parameters_Public!$C$26=1, T17, 0) -> 6947593 | X17: =IF(F17+O17>0, W17/(F17+O17),"") -> 11211.823 | Y17: =INDEX(YearMap!$I$2:$I$6, MATCH(C17, YearMap!$A$2:$A$6, 0)) -> 5013 | Z17: =W17 - ((Y17 + IF(Parameters_Public!$C$20=1, Parameters_Public!$C$19, 0))*AC17) -> 3375245.7 | AA17: =IF($AC17>0, $Z17/$AC17, 0) -> 5446.8731 | AB17: =MAX(0, (MAX(0, $D17-BaselineCalc!$B$7) + MAX(0, $E17-BaselineCalc!$B$8))) -> 66.666667 | AC17: =IF(LEFT($B17,2)="A_", $O17, IF(LEFT($B17,2)="B_", $M17+$O17, IF(LEFT($B17,2)="C_", $L17+$O17, $F17))) -> 619.66667 | AD17: =((Y17 + IF(Parameters_Public!$C$20=1, INDEX(YearMap!$O$2:$O$6, MATCH(C17, YearMap!$A$2:$A$6, 0)), 0))*AC17) + AC17*INDEX(YearMap!$P$2:$P$6, MATCH(C17, YearMap!$A$2:$A$6, 0)) -> 6794614 | AE17: =W17 - (1-Parameters_Public!$C42)*$G17*$AB17*$J17*(1-$K17) -> 6522952.4 | AF17: =AD17-AE17 -> 271661.64 | AG17: =B17&"|"&C17 -> D_Grow_Both_Targets|FY2026
A18: =AG18 -> D_Grow_Both_Targets|FY2027 | B18: =Scenarios!A5 -> D_Grow_Both_Targets | C18: FY2027 | D18: =IF(Scenarios!D5=1,0, L18) -> 324 | E18: =IF(Scenarios!E5=1,0, M18) -> 362.33333 | F18: =D18+E18 -> 686.33333 | G18: =YearMap!B3 -> 6574.8743 | H18: =YearMap!C3 -> 1439410.4 | I18: =YearMap!D3 -> 1657842.4 | J18: =1-BaselineCalc!$B$5 -> 0.993 | K18: =Scenarios!G5 -> 0 | L18: =IF(Scenarios!$Q5=1,BaselineCalc!$B$7*(1+Parameters_Public!$C44)^(IF($C18="FY2026",0,IF($C18="FY2027",1,IF($C18="FY2028",2,IF($C18="FY2029",3,IF($C18="FY2030",4,0))))))+ROUND(Scenarios!J5*Scenarios!$F5,0),BaselineCalc!$B$7+ROUND(Scenarios!J5*Scenarios!$F5,0)) -> 324 | M18: =IF(Scenarios!$R5=1,BaselineCalc!$B$8*(1+Parameters_Public!$C45)^(IF($C18="FY2026",0,IF($C18="FY2027",1,IF($C18="FY2028",2,IF($C18="FY2029",3,IF($C18="FY2030",4,0))))))+Scenarios!J5-ROUND(Scenarios!J5*Scenarios!$F5,0),BaselineCalc!$B$8+Scenarios!J5-ROUND(Scenarios!J5*Scenarios!$F5,0)) -> 362.33333 | N18: =(L18-D18) + (M18-E18) -> 0 | O18: =(Parameters_Public!$C$22*(L18-D18)+Parameters_Public!$C$23*(M18-E18)) -> 0 | P18: =YearMap!E3 -> 800 | Q18: =IF(Scenarios!N5="lease", YearMap!F3, YearMap!G3) -> 0.4 | R18: =IF(Scenarios!D5=1, Q18*H18, H18) -> 1439410.4 | S18: =IF(Scenarios!E5=1, Q18*I18, I18) -> 1657842.4 | T18: =IF(C18="FY2026", (Scenarios!D5+Scenarios!E5)*BaselineCalc!$B$22, 0) -> 0 | U18: =(R18+S18+G18*F18)*J18*(1-K18) -> 7556539.5 | V18: =O18*(G18+P18) -> 0 | W18: =U18+V18+IF(Parameters_Public!$C$26=1, T18, 0) -> 7556539.5 | X18: =IF(F18+O18>0, W18/(F18+O18),"") -> 11010.014 | Y18: =INDEX(YearMap!$I$2:$I$6, MATCH(C18, YearMap!$A$2:$A$6, 0)) -> 5138.325 | Z18: =W18 - ((Y18 + IF(Parameters_Public!$C$20=1, Parameters_Public!$C$19, 0))*AC18) -> 3513847.5 | AA18: =IF($AC18>0, $Z18/$AC18, 0) -> 5119.7389 | AB18: =MAX(0, (MAX(0, $D18-BaselineCalc!$B$7) + MAX(0, $E18-BaselineCalc!$B$8))) -> 133.33333 | AC18: =IF(LEFT($B18,2)="A_", $O18, IF(LEFT($B18,2)="B_", $M18+$O18, IF(LEFT($B18,2)="C_", $L18+$O18, $F18))) -> 686.33333 | AD18: =((Y18 + IF(Parameters_Public!$C$20=1, INDEX(YearMap!$O$2:$O$6, MATCH(C18, YearMap!$A$2:$A$6, 0)), 0))*AC18) + AC18*INDEX(YearMap!$P$2:$P$6, MATCH(C18, YearMap!$A$2:$A$6, 0)) -> 7713751 | AE18: =W18 - (1-Parameters_Public!$C42)*$G18*$AB18*$J18*(1-$K18) -> 6686026.2 | AF18: =AD18-AE18 -> 1027724.8 | AG18: =B18&"|"&C18 -> D_Grow_Both_Targets|FY2027
A19: =AG19 -> D_Grow_Both_Targets|FY2028 | B19: =Scenarios!A5 -> D_Grow_Both_Targets | C19: FY2028 | D19: =IF(Scenarios!D5=1,0, L19) -> 357 | E19: =IF(Scenarios!E5=1,0, M19) -> 396 | F19: =D19+E19 -> 753 | G19: =YearMap!B4 -> 6739.2461 | H19: =YearMap!C4 -> 1475395.7 | I19: =YearMap!D4 -> 1699288.4 | J19: =1-BaselineCalc!$B$5 -> 0.993 | K19: =Scenarios!G5 -> 0 | L19: =IF(Scenarios!$Q5=1,BaselineCalc!$B$7*(1+Parameters_Public!$C44)^(IF($C19="FY2026",0,IF($C19="FY2027",1,IF($C19="FY2028",2,IF($C19="FY2029",3,IF($C19="FY2030",4,0))))))+ROUND(Scenarios!K5*Scenarios!$F5,0),BaselineCalc!$B$7+ROUND(Scenarios!K5*Scenarios!$F5,0)) -> 357 | M19: =IF(Scenarios!$R5=1,BaselineCalc!$B$8*(1+Parameters_Public!$C45)^(IF($C19="FY2026",0,IF($C19="FY2027",1,IF($C19="FY2028",2,IF($C19="FY2029",3,IF($C19="FY2030",4,0))))))+Scenarios!K5-ROUND(Scenarios!K5*Scenarios!$F5,0),BaselineCalc!$B$8+Scenarios!K5-ROUND(Scenarios!K5*Scenarios!$F5,0)) -> 396 | N19: =(L19-D19) + (M19-E19) -> 0 | O19: =(Parameters_Public!$C$22*(L19-D19)+Parameters_Public!$C$23*(M19-E19)) -> 0 | P19: =YearMap!E4 -> 600 | Q19: =IF(Scenarios!N5="lease", YearMap!F4, YearMap!G4) -> 0.35 | R19: =IF(Scenarios!D5=1, Q19*H19, H19) -> 1475395.7 | S19: =IF(Scenarios!E5=1, Q19*I19, I19) -> 1699288.4 | T19: =IF(C19="FY2026", (Scenarios!D5+Scenarios!E5)*BaselineCalc!$B$22, 0) -> 0 | U19: =(R19+S19+G19*F19)*J19*(1-K19) -> 8191591.1 | V19: =O19*(G19+P19) -> 0 | W19: =U19+V19+IF(Parameters_Public!$C$26=1, T19, 0) -> 8191591.1 | X19: =IF(F19+O19>0, W19/(F19+O19),"") -> 10878.607 | Y19: =INDEX(YearMap!$I$2:$I$6, MATCH(C19, YearMap!$A$2:$A$6, 0)) -> 5266.7831 | Z19: =W19 - ((Y19 + IF(Parameters_Public!$C$20=1, Parameters_Public!$C$19, 0))*AC19) -> 3659485.1 | AA19: =IF($AC19>0, $Z19/$AC19, 0) -> 4859.874 | AB19: =MAX(0, (MAX(0, $D19-BaselineCalc!$B$7) + MAX(0, $E19-BaselineCalc!$B$8))) -> 200 | AC19: =IF(LEFT($B19,2)="A_", $O19, IF(LEFT($B19,2)="B_", $M19+$O19, IF(LEFT($B19,2)="C_", $L19+$O19, $F19))) -> 753 | AD19: =((Y19 + IF(Parameters_Public!$C$20=1, INDEX(YearMap!$O$2:$O$6, MATCH(C19, YearMap!$A$2:$A$6, 0)), 0))*AC19) + AC19*INDEX(YearMap!$P$2:$P$6, MATCH(C19, YearMap!$A$2:$A$6, 0)) -> 8674598.1 | AE19: =W19 - (1-Parameters_Public!$C42)*$G19*$AB19*$J19*(1-$K19) -> 6853176.8 | AF19: =AD19-AE19 -> 1821421.3 | AG19: =B19&"|"&C19 -> D_Grow_Both_Targets|FY2028
A20: =AG20 -> D_Grow_Both_Targets|FY2029 | B20: =Scenarios!A5 -> D_Grow_Both_Targets | C20: FY2029 | D20: =IF(Scenarios!D5=1,0, L20) -> 357 | E20: =IF(Scenarios!E5=1,0, M20) -> 396 | F20: =D20+E20 -> 753 | G20: =YearMap!B5 -> 6907.7273 | H20: =YearMap!C5 -> 1512280.6 | I20: =YearMap!D5 -> 1741770.6 | J20: =1-BaselineCalc!$B$5 -> 0.993 | K20: =Scenarios!G5 -> 0 | L20: =IF(Scenarios!$Q5=1,BaselineCalc!$B$7*(1+Parameters_Public!$C44)^(IF($C20="FY2026",0,IF($C20="FY2027",1,IF($C20="FY2028",2,IF($C20="FY2029",3,IF($C20="FY2030",4,0))))))+ROUND(Scenarios!L5*Scenarios!$F5,0),BaselineCalc!$B$7+ROUND(Scenarios!L5*Scenarios!$F5,0)) -> 357 | M20: =IF(Scenarios!$R5=1,BaselineCalc!$B$8*(1+Parameters_Public!$C45)^(IF($C20="FY2026",0,IF($C20="FY2027",1,IF($C20="FY2028",2,IF($C20="FY2029",3,IF($C20="FY2030",4,0))))))+Scenarios!L5-ROUND(Scenarios!L5*Scenarios!$F5,0),BaselineCalc!$B$8+Scenarios!L5-ROUND(Scenarios!L5*Scenarios!$F5,0)) -> 396 | N20: =(L20-D20) + (M20-E20) -> 0 | O20: =(Parameters_Public!$C$22*(L20-D20)+Parameters_Public!$C$23*(M20-E20)) -> 0 | P20: =YearMap!E5 -> 500 | Q20: =IF(Scenarios!N5="lease", YearMap!F5, YearMap!G5) -> 0.3 | R20: =IF(Scenarios!D5=1, Q20*H20, H20) -> 1512280.6 | S20: =IF(Scenarios!E5=1, Q20*I20, I20) -> 1741770.6 | T20: =IF(C20="FY2026", (Scenarios!D5+Scenarios!E5)*BaselineCalc!$B$22, 0) -> 0 | U20: =(R20+S20+G20*F20)*J20*(1-K20) -> 8396380.9 | V20: =O20*(G20+P20) -> 0 | W20: =U20+V20+IF(Parameters_Public!$C$26=1, T20, 0) -> 8396380.9 | X20: =IF(F20+O20>0, W20/(F20+O20),"") -> 11150.572 | Y20: =INDEX(YearMap!$I$2:$I$6, MATCH(C20, YearMap!$A$2:$A$6, 0)) -> 5398.4527 | Z20: =W20 - ((Y20 + IF(Parameters_Public!$C$20=1, Parameters_Public!$C$19, 0))*AC20) -> 3765127.7 | AA20: =IF($AC20>0, $Z20/$AC20, 0) -> 5000.1696 | AB20: =MAX(0, (MAX(0, $D20-BaselineCalc!$B$7) + MAX(0, $E20-BaselineCalc!$B$8))) -> 200 | AC20: =IF(LEFT($B20,2)="A_", $O20, IF(LEFT($B20,2)="B_", $M20+$O20, IF(LEFT($B20,2)="C_", $L20+$O20, $F20))) -> 753 | AD20: =((Y20 + IF(Parameters_Public!$C$20=1, INDEX(YearMap!$O$2:$O$6, MATCH(C20, YearMap!$A$2:$A$6, 0)), 0))*AC20) + AC20*INDEX(YearMap!$P$2:$P$6, MATCH(C20, YearMap!$A$2:$A$6, 0)) -> 8891463 | AE20: =W20 - (1-Parameters_Public!$C42)*$G20*$AB20*$J20*(1-$K20) -> 7024506.3 | AF20: =AD20-AE20 -> 1866956.8 | AG20: =B20&"|"&C20 -> D_Grow_Both_Targets|FY2029
A21: =AG21 -> D_Grow_Both_Targets|FY2030 | B21: =Scenarios!A5 -> D_Grow_Both_Targets | C21: FY2030 | D21: =IF(Scenarios!D5=1,0, L21) -> 357 | E21: =IF(Scenarios!E5=1,0, M21) -> 396 | F21: =D21+E21 -> 753 | G21: =YearMap!B6 -> 7080.4205 | H21: =YearMap!C6 -> 1550087.6 | I21: =YearMap!D6 -> 1785314.9 | J21: =1-BaselineCalc!$B$5 -> 0.993 | K21: =Scenarios!G5 -> 0 | L21: =IF(Scenarios!$Q5=1,BaselineCalc!$B$7*(1+Parameters_Public!$C44)^(IF($C21="FY2026",0,IF($C21="FY2027",1,IF($C21="FY2028",2,IF($C21="FY2029",3,IF($C21="FY2030",4,0))))))+ROUND(Scenarios!M5*Scenarios!$F5,0),BaselineCalc!$B$7+ROUND(Scenarios!M5*Scenarios!$F5,0)) -> 357 | M21: =IF(Scenarios!$R5=1,BaselineCalc!$B$8*(1+Parameters_Public!$C45)^(IF($C21="FY2026",0,IF($C21="FY2027",1,IF($C21="FY2028",2,IF($C21="FY2029",3,IF($C21="FY2030",4,0))))))+Scenarios!M5-ROUND(Scenarios!M5*Scenarios!$F5,0),BaselineCalc!$B$8+Scenarios!M5-ROUND(Scenarios!M5*Scenarios!$F5,0)) -> 396 | N21: =(L21-D21) + (M21-E21) -> 0 | O21: =(Parameters_Public!$C$22*(L21-D21)+Parameters_Public!$C$23*(M21-E21)) -> 0 | P21: =YearMap!E6 -> 300 | Q21: =IF(Scenarios!N5="lease", YearMap!F6, YearMap!G6) -> 0.3 | R21: =IF(Scenarios!D5=1, Q21*H21, H21) -> 1550087.6 | S21: =IF(Scenarios!E5=1, Q21*I21, I21) -> 1785314.9 | T21: =IF(C21="FY2026", (Scenarios!D5+Scenarios!E5)*BaselineCalc!$B$22, 0) -> 0 | U21: =(R21+S21+G21*F21)*J21*(1-K21) -> 8606290.4 | V21: =O21*(G21+P21) -> 0 | W21: =U21+V21+IF(Parameters_Public!$C$26=1, T21, 0) -> 8606290.4 | X21: =IF(F21+O21>0, W21/(F21+O21),"") -> 11429.337 | Y21: =INDEX(YearMap!$I$2:$I$6, MATCH(C21, YearMap!$A$2:$A$6, 0)) -> 5533.414 | Z21: =W21 - ((Y21 + IF(Parameters_Public!$C$20=1, Parameters_Public!$C$19, 0))*AC21) -> 3873411.3 | AA21: =IF($AC21>0, $Z21/$AC21, 0) -> 5143.9725 | AB21: =MAX(0, (MAX(0, $D21-BaselineCalc!$B$7) + MAX(0, $E21-BaselineCalc!$B$8))) -> 200 | AC21: =IF(LEFT($B21,2)="A_", $O21, IF(LEFT($B21,2)="B_", $M21+$O21, IF(LEFT($B21,2)="C_", $L21+$O21, $F21))) -> 753 | AD21: =((Y21 + IF(Parameters_Public!$C$20=1, INDEX(YearMap!$O$2:$O$6, MATCH(C21, YearMap!$A$2:$A$6, 0)), 0))*AC21) + AC21*INDEX(YearMap!$P$2:$P$6, MATCH(C21, YearMap!$A$2:$A$6, 0)) -> 9113749.6 | AE21: =W21 - (1-Parameters_Public!$C42)*$G21*$AB21*$J21*(1-$K21) -> 7200118.9 | AF21: =AD21-AE21 -> 1913630.7 | AG21: =B21&"|"&C21 -> D_Grow_Both_Targets|FY2030
A22: =AG22 -> D_CUSTOM2|FY2026 | B22: =Scenarios!A6 -> D_CUSTOM2 | C22: FY2026 | D22: =IF(Scenarios!D6=1,0, L22) -> 257 | E22: =IF(Scenarios!E6=1,0, M22) -> 296 | F22: =D22+E22 -> 553 | G22: =YearMap!B2 -> 6414.5115 | H22: =YearMap!C2 -> 1404302.9 | I22: =YearMap!D2 -> 1617407.2 | J22: =1-BaselineCalc!$B$5 -> 0.993 | K22: =Scenarios!G6 -> 0 | L22: =IF(Scenarios!$Q6=1,BaselineCalc!$B$7*(1+Parameters_Public!$C44)^(IF($C22="FY2026",0,IF($C22="FY2027",1,IF($C22="FY2028",2,IF($C22="FY2029",3,IF($C22="FY2030",4,0))))))+ROUND(Scenarios!I6*Scenarios!$F6,0),BaselineCalc!$B$7+ROUND(Scenarios!I6*Scenarios!$F6,0)) -> 257 | M22: =IF(Scenarios!$R6=1,BaselineCalc!$B$8*(1+Parameters_Public!$C45)^(IF($C22="FY2026",0,IF($C22="FY2027",1,IF($C22="FY2028",2,IF($C22="FY2029",3,IF($C22="FY2030",4,0))))))+Scenarios!I6-ROUND(Scenarios!I6*Scenarios!$F6,0),BaselineCalc!$B$8+Scenarios!I6-ROUND(Scenarios!I6*Scenarios!$F6,0)) -> 296 | N22: =(L22-D22) + (M22-E22) -> 0 | O22: =(Parameters_Public!$C$22*(L22-D22)+Parameters_Public!$C$23*(M22-E22)) -> 0 | P22: =YearMap!E2 -> 1000 | Q22: =IF(Scenarios!N6="lease", YearMap!F2, YearMap!G2) -> 0.5 | R22: =IF(Scenarios!D6=1, Q22*H22, H22) -> 1404302.9 | S22: =IF(Scenarios!E6=1, Q22*I22, I22) -> 1617407.2 | T22: =IF(C22="FY2026", (Scenarios!D6+Scenarios!E6)*BaselineCalc!$B$22, 0) -> 0 | U22: =(R22+S22+G22*F22)*J22*(1-K22) -> 6522952.4 | V22: =O22*(G22+P22) -> 0 | W22: =U22+V22+IF(Parameters_Public!$C$26=1, T22, 0) -> 6522952.4 | X22: =IF(F22+O22>0, W22/(F22+O22),"") -> 11795.574 | Y22: =INDEX(YearMap!$I$2:$I$6, MATCH(C22, YearMap!$A$2:$A$6, 0)) -> 5013 | Z22: =W22 - ((Y22 + IF(Parameters_Public!$C$20=1, Parameters_Public!$C$19, 0))*AC22) -> 3334935 | AA22: =IF($AC22>0, $Z22/$AC22, 0) -> 6030.6239 | AB22: =MAX(0, (MAX(0, $D22-BaselineCalc!$B$7) + MAX(0, $E22-BaselineCalc!$B$8))) -> 0 | AC22: =IF(LEFT($B22,2)="A_", $O22, IF(LEFT($B22,2)="B_", $M22+$O22, IF(LEFT($B22,2)="C_", $L22+$O22, $F22))) -> 553 | AD22: =((Y22 + IF(Parameters_Public!$C$20=1, INDEX(YearMap!$O$2:$O$6, MATCH(C22, YearMap!$A$2:$A$6, 0)), 0))*AC22) + AC22*INDEX(YearMap!$P$2:$P$6, MATCH(C22, YearMap!$A$2:$A$6, 0)) -> 6063617.3 | AE22: =W22 - (1-Parameters_Public!$C42)*$G22*$AB22*$J22*(1-$K22) -> 6522952.4 | AF22: =AD22-AE22 -> -459335.03 | AG22: =B22&"|"&C22 -> D_CUSTOM2|FY2026
A23: =AG23 -> D_CUSTOM2|FY2027 | B23: =Scenarios!A6 -> D_CUSTOM2 | C23: FY2027 | D23: =IF(Scenarios!D6=1,0, L23) -> 257 | E23: =IF(Scenarios!E6=1,0, M23) -> 296 | F23: =D23+E23 -> 553 | G23: =YearMap!B3 -> 6574.8743 | H23: =YearMap!C3 -> 1439410.4 | I23: =YearMap!D3 -> 1657842.4 | J23: =1-BaselineCalc!$B$5 -> 0.993 | K23: =Scenarios!G6 -> 0 | L23: =IF(Scenarios!$Q6=1,BaselineCalc!$B$7*(1+Parameters_Public!$C44)^(IF($C23="FY2026",0,IF($C23="FY2027",1,IF($C23="FY2028",2,IF($C23="FY2029",3,IF($C23="FY2030",4,0))))))+ROUND(Scenarios!J6*Scenarios!$F6,0),BaselineCalc!$B$7+ROUND(Scenarios!J6*Scenarios!$F6,0)) -> 257 | M23: =IF(Scenarios!$R6=1,BaselineCalc!$B$8*(1+Parameters_Public!$C45)^(IF($C23="FY2026",0,IF($C23="FY2027",1,IF($C23="FY2028",2,IF($C23="FY2029",3,IF($C23="FY2030",4,0))))))+Scenarios!J6-ROUND(Scenarios!J6*Scenarios!$F6,0),BaselineCalc!$B$8+Scenarios!J6-ROUND(Scenarios!J6*Scenarios!$F6,0)) -> 296 | N23: =(L23-D23) + (M23-E23) -> 0 | O23: =(Parameters_Public!$C$22*(L23-D23)+Parameters_Public!$C$23*(M23-E23)) -> 0 | P23: =YearMap!E3 -> 800 | Q23: =IF(Scenarios!N6="lease", YearMap!F3, YearMap!G3) -> 0.4 | R23: =IF(Scenarios!D6=1, Q23*H23, H23) -> 1439410.4 | S23: =IF(Scenarios!E6=1, Q23*I23, I23) -> 1657842.4 | T23: =IF(C23="FY2026", (Scenarios!D6+Scenarios!E6)*BaselineCalc!$B$22, 0) -> 0 | U23: =(R23+S23+G23*F23)*J23*(1-K23) -> 6686026.2 | V23: =O23*(G23+P23) -> 0 | W23: =U23+V23+IF(Parameters_Public!$C$26=1, T23, 0) -> 6686026.2 | X23: =IF(F23+O23>0, W23/(F23+O23),"") -> 12090.463 | Y23: =INDEX(YearMap!$I$2:$I$6, MATCH(C23, YearMap!$A$2:$A$6, 0)) -> 5138.325 | Z23: =W23 - ((Y23 + IF(Parameters_Public!$C$20=1, Parameters_Public!$C$19, 0))*AC23) -> 3428704.1 | AA23: =IF($AC23>0, $Z23/$AC23, 0) -> 6200.1883 | AB23: =MAX(0, (MAX(0, $D23-BaselineCalc!$B$7) + MAX(0, $E23-BaselineCalc!$B$8))) -> 0 | AC23: =IF(LEFT($B23,2)="A_", $O23, IF(LEFT($B23,2)="B_", $M23+$O23, IF(LEFT($B23,2)="C_", $L23+$O23, $F23))) -> 553 | AD23: =((Y23 + IF(Parameters_Public!$C$20=1, INDEX(YearMap!$O$2:$O$6, MATCH(C23, YearMap!$A$2:$A$6, 0)), 0))*AC23) + AC23*INDEX(YearMap!$P$2:$P$6, MATCH(C23, YearMap!$A$2:$A$6, 0)) -> 6215207.8 | AE23: =W23 - (1-Parameters_Public!$C42)*$G23*$AB23*$J23*(1-$K23) -> 6686026.2 | AF23: =AD23-AE23 -> -470818.41 | AG23: =B23&"|"&C23 -> D_CUSTOM2|FY2027
A24: =AG24 -> D_CUSTOM2|FY2028 | B24: =Scenarios!A6 -> D_CUSTOM2 | C24: FY2028 | D24: =IF(Scenarios!D6=1,0, L24) -> 257 | E24: =IF(Scenarios!E6=1,0, M24) -> 296 | F24: =D24+E24 -> 553 | G24: =YearMap!B4 -> 6739.2461 | H24: =YearMap!C4 -> 1475395.7 | I24: =YearMap!D4 -> 1699288.4 | J24: =1-BaselineCalc!$B$5 -> 0.993 | K24: =Scenarios!G6 -> 0 | L24: =IF(Scenarios!$Q6=1,BaselineCalc!$B$7*(1+Parameters_Public!$C44)^(IF($C24="FY2026",0,IF($C24="FY2027",1,IF($C24="FY2028",2,IF($C24="FY2029",3,IF($C24="FY2030",4,0))))))+ROUND(Scenarios!K6*Scenarios!$F6,0),BaselineCalc!$B$7+ROUND(Scenarios!K6*Scenarios!$F6,0)) -> 257 | M24: =IF(Scenarios!$R6=1,BaselineCalc!$B$8*(1+Parameters_Public!$C45)^(IF($C24="FY2026",0,IF($C24="FY2027",1,IF($C24="FY2028",2,IF($C24="FY2029",3,IF($C24="FY2030",4,0))))))+Scenarios!K6-ROUND(Scenarios!K6*Scenarios!$F6,0),BaselineCalc!$B$8+Scenarios!K6-ROUND(Scenarios!K6*Scenarios!$F6,0)) -> 296 | N24: =(L24-D24) + (M24-E24) -> 0 | O24: =(Parameters_Public!$C$22*(L24-D24)+Parameters_Public!$C$23*(M24-E24)) -> 0 | P24: =YearMap!E4 -> 600 | Q24: =IF(Scenarios!N6="lease", YearMap!F4, YearMap!G4) -> 0.35 | R24: =IF(Scenarios!D6=1, Q24*H24, H24) -> 1475395.7 | S24: =IF(Scenarios!E6=1, Q24*I24, I24) -> 1699288.4 | T24: =IF(C24="FY2026", (Scenarios!D6+Scenarios!E6)*BaselineCalc!$B$22, 0) -> 0 | U24: =(R24+S24+G24*F24)*J24*(1-K24) -> 6853176.8 | V24: =O24*(G24+P24) -> 0 | W24: =U24+V24+IF(Parameters_Public!$C$26=1, T24, 0) -> 6853176.8 | X24: =IF(F24+O24>0, W24/(F24+O24),"") -> 12392.725 | Y24: =INDEX(YearMap!$I$2:$I$6, MATCH(C24, YearMap!$A$2:$A$6, 0)) -> 5266.7831 | Z24: =W24 - ((Y24 + IF(Parameters_Public!$C$20=1, Parameters_Public!$C$19, 0))*AC24) -> 3524817.4 | AA24: =IF($AC24>0, $Z24/$AC24, 0) -> 6373.9917 | AB24: =MAX(0, (MAX(0, $D24-BaselineCalc!$B$7) + MAX(0, $E24-BaselineCalc!$B$8))) -> 0 | AC24: =IF(LEFT($B24,2)="A_", $O24, IF(LEFT($B24,2)="B_", $M24+$O24, IF(LEFT($B24,2)="C_", $L24+$O24, $F24))) -> 553 | AD24: =((Y24 + IF(Parameters_Public!$C$20=1, INDEX(YearMap!$O$2:$O$6, MATCH(C24, YearMap!$A$2:$A$6, 0)), 0))*AC24) + AC24*INDEX(YearMap!$P$2:$P$6, MATCH(C24, YearMap!$A$2:$A$6, 0)) -> 6370588 | AE24: =W24 - (1-Parameters_Public!$C42)*$G24*$AB24*$J24*(1-$K24) -> 6853176.8 | AF24: =AD24-AE24 -> -482588.87 | AG24: =B24&"|"&C24 -> D_CUSTOM2|FY2028
A25: =AG25 -> D_CUSTOM2|FY2029 | B25: =Scenarios!A6 -> D_CUSTOM2 | C25: FY2029 | D25: =IF(Scenarios!D6=1,0, L25) -> 257 | E25: =IF(Scenarios!E6=1,0, M25) -> 296 | F25: =D25+E25 -> 553 | G25: =YearMap!B5 -> 6907.7273 | H25: =YearMap!C5 -> 1512280.6 | I25: =YearMap!D5 -> 1741770.6 | J25: =1-BaselineCalc!$B$5 -> 0.993 | K25: =Scenarios!G6 -> 0 | L25: =IF(Scenarios!$Q6=1,BaselineCalc!$B$7*(1+Parameters_Public!$C44)^(IF($C25="FY2026",0,IF($C25="FY2027",1,IF($C25="FY2028",2,IF($C25="FY2029",3,IF($C25="FY2030",4,0))))))+ROUND(Scenarios!L6*Scenarios!$F6,0),BaselineCalc!$B$7+ROUND(Scenarios!L6*Scenarios!$F6,0)) -> 257 | M25: =IF(Scenarios!$R6=1,BaselineCalc!$B$8*(1+Parameters_Public!$C45)^(IF($C25="FY2026",0,IF($C25="FY2027",1,IF($C25="FY2028",2,IF($C25="FY2029",3,IF($C25="FY2030",4,0))))))+Scenarios!L6-ROUND(Scenarios!L6*Scenarios!$F6,0),BaselineCalc!$B$8+Scenarios!L6-ROUND(Scenarios!L6*Scenarios!$F6,0)) -> 296 | N25: =(L25-D25) + (M25-E25) -> 0 | O25: =(Parameters_Public!$C$22*(L25-D25)+Parameters_Public!$C$23*(M25-E25)) -> 0 | P25: =YearMap!E5 -> 500 | Q25: =IF(Scenarios!N6="lease", YearMap!F5, YearMap!G5) -> 0.3 | R25: =IF(Scenarios!D6=1, Q25*H25, H25) -> 1512280.6 | S25: =IF(Scenarios!E6=1, Q25*I25, I25) -> 1741770.6 | T25: =IF(C25="FY2026", (Scenarios!D6+Scenarios!E6)*BaselineCalc!$B$22, 0) -> 0 | U25: =(R25+S25+G25*F25)*J25*(1-K25) -> 7024506.3 | V25: =O25*(G25+P25) -> 0 | W25: =U25+V25+IF(Parameters_Public!$C$26=1, T25, 0) -> 7024506.3 | X25: =IF(F25+O25>0, W25/(F25+O25),"") -> 12702.543 | Y25: =INDEX(YearMap!$I$2:$I$6, MATCH(C25, YearMap!$A$2:$A$6, 0)) -> 5398.4527 | Z25: =W25 - ((Y25 + IF(Parameters_Public!$C$20=1, Parameters_Public!$C$19, 0))*AC25) -> 3623333.6 | AA25: =IF($AC25>0, $Z25/$AC25, 0) -> 6552.1403 | AB25: =MAX(0, (MAX(0, $D25-BaselineCalc!$B$7) + MAX(0, $E25-BaselineCalc!$B$8))) -> 0 | AC25: =IF(LEFT($B25,2)="A_", $O25, IF(LEFT($B25,2)="B_", $M25+$O25, IF(LEFT($B25,2)="C_", $L25+$O25, $F25))) -> 553 | AD25: =((Y25 + IF(Parameters_Public!$C$20=1, INDEX(YearMap!$O$2:$O$6, MATCH(C25, YearMap!$A$2:$A$6, 0)), 0))*AC25) + AC25*INDEX(YearMap!$P$2:$P$6, MATCH(C25, YearMap!$A$2:$A$6, 0)) -> 6529852.7 | AE25: =W25 - (1-Parameters_Public!$C42)*$G25*$AB25*$J25*(1-$K25) -> 7024506.3 | AF25: =AD25-AE25 -> -494653.59 | AG25: =B25&"|"&C25 -> D_CUSTOM2|FY2029
A26: =AG26 -> D_CUSTOM2|FY2030 | B26: =Scenarios!A6 -> D_CUSTOM2 | C26: FY2030 | D26: =IF(Scenarios!D6=1,0, L26) -> 257 | E26: =IF(Scenarios!E6=1,0, M26) -> 296 | F26: =D26+E26 -> 553 | G26: =YearMap!B6 -> 7080.4205 | H26: =YearMap!C6 -> 1550087.6 | I26: =YearMap!D6 -> 1785314.9 | J26: =1-BaselineCalc!$B$5 -> 0.993 | K26: =Scenarios!G6 -> 0 | L26: =IF(Scenarios!$Q6=1,BaselineCalc!$B$7*(1+Parameters_Public!$C44)^(IF($C26="FY2026",0,IF($C26="FY2027",1,IF($C26="FY2028",2,IF($C26="FY2029",3,IF($C26="FY2030",4,0))))))+ROUND(Scenarios!M6*Scenarios!$F6,0),BaselineCalc!$B$7+ROUND(Scenarios!M6*Scenarios!$F6,0)) -> 257 | M26: =IF(Scenarios!$R6=1,BaselineCalc!$B$8*(1+Parameters_Public!$C45)^(IF($C26="FY2026",0,IF($C26="FY2027",1,IF($C26="FY2028",2,IF($C26="FY2029",3,IF($C26="FY2030",4,0))))))+Scenarios!M6-ROUND(Scenarios!M6*Scenarios!$F6,0),BaselineCalc!$B$8+Scenarios!M6-ROUND(Scenarios!M6*Scenarios!$F6,0)) -> 296 | N26: =(L26-D26) + (M26-E26) -> 0 | O26: =(Parameters_Public!$C$22*(L26-D26)+Parameters_Public!$C$23*(M26-E26)) -> 0 | P26: =YearMap!E6 -> 300 | Q26: =IF(Scenarios!N6="lease", YearMap!F6, YearMap!G6) -> 0.3 | R26: =IF(Scenarios!D6=1, Q26*H26, H26) -> 1550087.6 | S26: =IF(Scenarios!E6=1, Q26*I26, I26) -> 1785314.9 | T26: =IF(C26="FY2026", (Scenarios!D6+Scenarios!E6)*BaselineCalc!$B$22, 0) -> 0 | U26: =(R26+S26+G26*F26)*J26*(1-K26) -> 7200118.9 | V26: =O26*(G26+P26) -> 0 | W26: =U26+V26+IF(Parameters_Public!$C$26=1, T26, 0) -> 7200118.9 | X26: =IF(F26+O26>0, W26/(F26+O26),"") -> 13020.107 | Y26: =INDEX(YearMap!$I$2:$I$6, MATCH(C26, YearMap!$A$2:$A$6, 0)) -> 5533.414 | Z26: =W26 - ((Y26 + IF(Parameters_Public!$C$20=1, Parameters_Public!$C$19, 0))*AC26) -> 3724312.6 | AA26: =IF($AC26>0, $Z26/$AC26, 0) -> 6734.7425 | AB26: =MAX(0, (MAX(0, $D26-BaselineCalc!$B$7) + MAX(0, $E26-BaselineCalc!$B$8))) -> 0 | AC26: =IF(LEFT($B26,2)="A_", $O26, IF(LEFT($B26,2)="B_", $M26+$O26, IF(LEFT($B26,2)="C_", $L26+$O26, $F26))) -> 553 | AD26: =((Y26 + IF(Parameters_Public!$C$20=1, INDEX(YearMap!$O$2:$O$6, MATCH(C26, YearMap!$A$2:$A$6, 0)), 0))*AC26) + AC26*INDEX(YearMap!$P$2:$P$6, MATCH(C26, YearMap!$A$2:$A$6, 0)) -> 6693099 | AE26: =W26 - (1-Parameters_Public!$C42)*$G26*$AB26*$J26*(1-$K26) -> 7200118.9 | AF26: =AD26-AE26 -> -507019.93 | AG26: =B26&"|"&C26 -> D_CUSTOM2|FY2030
A27: =AG27 -> G_EchoGHubRamp_PimaTargets|FY2026 | B27: =Scenarios!A7 -> G_EchoGHubRamp_PimaTargets | C27: FY2026 | D27: =IF(Scenarios!D7=1,0, L27) -> 292 | E27: =IF(Scenarios!E7=1,0, M27) -> 311 | F27: =D27+E27 -> 603 | G27: =YearMap!B2 -> 6414.5115 | H27: =YearMap!C2 -> 1404302.9 | I27: =YearMap!D2 -> 1617407.2 | J27: =1-BaselineCalc!$B$5 -> 0.993 | K27: =Scenarios!G7 -> 0 | L27: =IF(Scenarios!$Q7=1,BaselineCalc!$B$7*(1+Parameters_Public!$C44)^(IF($C27="FY2026",0,IF($C27="FY2027",1,IF($C27="FY2028",2,IF($C27="FY2029",3,IF($C27="FY2030",4,0))))))+ROUND(Scenarios!I7*Scenarios!$F7,0),BaselineCalc!$B$7+ROUND(Scenarios!I7*Scenarios!$F7,0)) -> 292 | M27: =IF(Scenarios!$R7=1,BaselineCalc!$B$8*(1+Parameters_Public!$C45)^(IF($C27="FY2026",0,IF($C27="FY2027",1,IF($C27="FY2028",2,IF($C27="FY2029",3,IF($C27="FY2030",4,0))))))+Scenarios!I7-ROUND(Scenarios!I7*Scenarios!$F7,0),BaselineCalc!$B$8+Scenarios!I7-ROUND(Scenarios!I7*Scenarios!$F7,0)) -> 311 | N27: =(L27-D27) + (M27-E27) -> 0 | O27: =(Parameters_Public!$C$22*(L27-D27)+Parameters_Public!$C$23*(M27-E27)) -> 0 | P27: =YearMap!E2 -> 1000 | Q27: =IF(Scenarios!N7="lease", YearMap!F2, YearMap!G2) -> 0.5 | R27: =IF(Scenarios!D7=1, Q27*H27, H27) -> 1404302.9 | S27: =IF(Scenarios!E7=1, Q27*I27, I27) -> 1617407.2 | T27: =IF(C27="FY2026", (Scenarios!D7+Scenarios!E7)*BaselineCalc!$B$22, 0) -> 0 | U27: =(R27+S27+G27*F27)*J27*(1-K27) -> 6841432.9 | V27: =O27*(G27+P27) -> 0 | W27: =U27+V27+IF(Parameters_Public!$C$26=1, T27, 0) -> 6841432.9 | X27: =IF(F27+O27>0, W27/(F27+O27),"") -> 11345.66 | Y27: =INDEX(YearMap!$I$2:$I$6, MATCH(C27, YearMap!$A$2:$A$6, 0)) -> 5013 | Z27: =W27 - ((Y27 + IF(Parameters_Public!$C$20=1, Parameters_Public!$C$19, 0))*AC27) -> 3365168 | AA27: =IF($AC27>0, $Z27/$AC27, 0) -> 5580.7098 | AB27: =MAX(0, (MAX(0, $D27-BaselineCalc!$B$7) + MAX(0, $E27-BaselineCalc!$B$8))) -> 50 | AC27: =IF(LEFT($B27,2)="A_", $O27, IF(LEFT($B27,2)="B_", $M27+$O27, IF(LEFT($B27,2)="C_", $L27+$O27, $F27))) -> 603 | AD27: =((Y27 + IF(Parameters_Public!$C$20=1, INDEX(YearMap!$O$2:$O$6, MATCH(C27, YearMap!$A$2:$A$6, 0)), 0))*AC27) + AC27*INDEX(YearMap!$P$2:$P$6, MATCH(C27, YearMap!$A$2:$A$6, 0)) -> 6611864.8 | AE27: =W27 - (1-Parameters_Public!$C42)*$G27*$AB27*$J27*(1-$K27) -> 6522952.4 | AF27: =AD27-AE27 -> 88912.469 | AG27: =B27&"|"&C27 -> G_EchoGHubRamp_PimaTargets|FY2026
A28: =AG28 -> G_EchoGHubRamp_PimaTargets|FY2027 | B28: =Scenarios!A7 -> G_EchoGHubRamp_PimaTargets | C28: FY2027 | D28: =IF(Scenarios!D7=1,0, L28) -> 327 | E28: =IF(Scenarios!E7=1,0, M28) -> 326 | F28: =D28+E28 -> 653 | G28: =YearMap!B3 -> 6574.8743 | H28: =YearMap!C3 -> 1439410.4 | I28: =YearMap!D3 -> 1657842.4 | J28: =1-BaselineCalc!$B$5 -> 0.993 | K28: =Scenarios!G7 -> 0 | L28: =IF(Scenarios!$Q7=1,BaselineCalc!$B$7*(1+Parameters_Public!$C44)^(IF($C28="FY2026",0,IF($C28="FY2027",1,IF($C28="FY2028",2,IF($C28="FY2029",3,IF($C28="FY2030",4,0))))))+ROUND(Scenarios!J7*Scenarios!$F7,0),BaselineCalc!$B$7+ROUND(Scenarios!J7*Scenarios!$F7,0)) -> 327 | M28: =IF(Scenarios!$R7=1,BaselineCalc!$B$8*(1+Parameters_Public!$C45)^(IF($C28="FY2026",0,IF($C28="FY2027",1,IF($C28="FY2028",2,IF($C28="FY2029",3,IF($C28="FY2030",4,0))))))+Scenarios!J7-ROUND(Scenarios!J7*Scenarios!$F7,0),BaselineCalc!$B$8+Scenarios!J7-ROUND(Scenarios!J7*Scenarios!$F7,0)) -> 326 | N28: =(L28-D28) + (M28-E28) -> 0 | O28: =(Parameters_Public!$C$22*(L28-D28)+Parameters_Public!$C$23*(M28-E28)) -> 0 | P28: =YearMap!E3 -> 800 | Q28: =IF(Scenarios!N7="lease", YearMap!F3, YearMap!G3) -> 0.4 | R28: =IF(Scenarios!D7=1, Q28*H28, H28) -> 1439410.4 | S28: =IF(Scenarios!E7=1, Q28*I28, I28) -> 1657842.4 | T28: =IF(C28="FY2026", (Scenarios!D7+Scenarios!E7)*BaselineCalc!$B$22, 0) -> 0 | U28: =(R28+S28+G28*F28)*J28*(1-K28) -> 7338911.2 | V28: =O28*(G28+P28) -> 0 | W28: =U28+V28+IF(Parameters_Public!$C$26=1, T28, 0) -> 7338911.2 | X28: =IF(F28+O28>0, W28/(F28+O28),"") -> 11238.761 | Y28: =INDEX(YearMap!$I$2:$I$6, MATCH(C28, YearMap!$A$2:$A$6, 0)) -> 5138.325 | Z28: =W28 - ((Y28 + IF(Parameters_Public!$C$20=1, Parameters_Public!$C$19, 0))*AC28) -> 3492561.6 | AA28: =IF($AC28>0, $Z28/$AC28, 0) -> 5348.4864 | AB28: =MAX(0, (MAX(0, $D28-BaselineCalc!$B$7) + MAX(0, $E28-BaselineCalc!$B$8))) -> 100 | AC28: =IF(LEFT($B28,2)="A_", $O28, IF(LEFT($B28,2)="B_", $M28+$O28, IF(LEFT($B28,2)="C_", $L28+$O28, $F28))) -> 653 | AD28: =((Y28 + IF(Parameters_Public!$C$20=1, INDEX(YearMap!$O$2:$O$6, MATCH(C28, YearMap!$A$2:$A$6, 0)), 0))*AC28) + AC28*INDEX(YearMap!$P$2:$P$6, MATCH(C28, YearMap!$A$2:$A$6, 0)) -> 7339115.2 | AE28: =W28 - (1-Parameters_Public!$C42)*$G28*$AB28*$J28*(1-$K28) -> 6686026.2 | AF28: =AD28-AE28 -> 653088.97 | AG28: =B28&"|"&C28 -> G_EchoGHubRamp_PimaTargets|FY2027
A29: =AG29 -> G_EchoGHubRamp_PimaTargets|FY2028 | B29: =Scenarios!A7 -> G_EchoGHubRamp_PimaTargets | C29: FY2028 | D29: =IF(Scenarios!D7=1,0, L29) -> 362 | E29: =IF(Scenarios!E7=1,0, M29) -> 341 | F29: =D29+E29 -> 703 | G29: =YearMap!B4 -> 6739.2461 | H29: =YearMap!C4 -> 1475395.7 | I29: =YearMap!D4 -> 1699288.4 | J29: =1-BaselineCalc!$B$5 -> 0.993 | K29: =Scenarios!G7 -> 0 | L29: =IF(Scenarios!$Q7=1,BaselineCalc!$B$7*(1+Parameters_Public!$C44)^(IF($C29="FY2026",0,IF($C29="FY2027",1,IF($C29="FY2028",2,IF($C29="FY2029",3,IF($C29="FY2030",4,0))))))+ROUND(Scenarios!K7*Scenarios!$F7,0),BaselineCalc!$B$7+ROUND(Scenarios!K7*Scenarios!$F7,0)) -> 362 | M29: =IF(Scenarios!$R7=1,BaselineCalc!$B$8*(1+Parameters_Public!$C45)^(IF($C29="FY2026",0,IF($C29="FY2027",1,IF($C29="FY2028",2,IF($C29="FY2029",3,IF($C29="FY2030",4,0))))))+Scenarios!K7-ROUND(Scenarios!K7*Scenarios!$F7,0),BaselineCalc!$B$8+Scenarios!K7-ROUND(Scenarios!K7*Scenarios!$F7,0)) -> 341 | N29: =(L29-D29) + (M29-E29) -> 0 | O29: =(Parameters_Public!$C$22*(L29-D29)+Parameters_Public!$C$23*(M29-E29)) -> 0 | P29: =YearMap!E4 -> 600 | Q29: =IF(Scenarios!N7="lease", YearMap!F4, YearMap!G4) -> 0.35 | R29: =IF(Scenarios!D7=1, Q29*H29, H29) -> 1475395.7 | S29: =IF(Scenarios!E7=1, Q29*I29, I29) -> 1699288.4 | T29: =IF(C29="FY2026", (Scenarios!D7+Scenarios!E7)*BaselineCalc!$B$22, 0) -> 0 | U29: =(R29+S29+G29*F29)*J29*(1-K29) -> 7856987.6 | V29: =O29*(G29+P29) -> 0 | W29: =U29+V29+IF(Parameters_Public!$C$26=1, T29, 0) -> 7856987.6 | X29: =IF(F29+O29>0, W29/(F29+O29),"") -> 11176.369 | Y29: =INDEX(YearMap!$I$2:$I$6, MATCH(C29, YearMap!$A$2:$A$6, 0)) -> 5266.7831 | Z29: =W29 - ((Y29 + IF(Parameters_Public!$C$20=1, Parameters_Public!$C$19, 0))*AC29) -> 3625818.2 | AA29: =IF($AC29>0, $Z29/$AC29, 0) -> 5157.6361 | AB29: =MAX(0, (MAX(0, $D29-BaselineCalc!$B$7) + MAX(0, $E29-BaselineCalc!$B$8))) -> 150 | AC29: =IF(LEFT($B29,2)="A_", $O29, IF(LEFT($B29,2)="B_", $M29+$O29, IF(LEFT($B29,2)="C_", $L29+$O29, $F29))) -> 703 | AD29: =((Y29 + IF(Parameters_Public!$C$20=1, INDEX(YearMap!$O$2:$O$6, MATCH(C29, YearMap!$A$2:$A$6, 0)), 0))*AC29) + AC29*INDEX(YearMap!$P$2:$P$6, MATCH(C29, YearMap!$A$2:$A$6, 0)) -> 8098595.6 | AE29: =W29 - (1-Parameters_Public!$C42)*$G29*$AB29*$J29*(1-$K29) -> 6853176.8 | AF29: =AD29-AE29 -> 1245418.7 | AG29: =B29&"|"&C29 -> G_EchoGHubRamp_PimaTargets|FY2028
A30: =AG30 -> G_EchoGHubRamp_PimaTargets|FY2029 | B30: =Scenarios!A7 -> G_EchoGHubRamp_PimaTargets | C30: FY2029 | D30: =IF(Scenarios!D7=1,0, L30) -> 362 | E30: =IF(Scenarios!E7=1,0, M30) -> 341 | F30: =D30+E30 -> 703 | G30: =YearMap!B5 -> 6907.7273 | H30: =YearMap!C5 -> 1512280.6 | I30: =YearMap!D5 -> 1741770.6 | J30: =1-BaselineCalc!$B$5 -> 0.993 | K30: =Scenarios!G7 -> 0 | L30: =IF(Scenarios!$Q7=1,BaselineCalc!$B$7*(1+Parameters_Public!$C44)^(IF($C30="FY2026",0,IF($C30="FY2027",1,IF($C30="FY2028",2,IF($C30="FY2029",3,IF($C30="FY2030",4,0))))))+ROUND(Scenarios!L7*Scenarios!$F7,0),BaselineCalc!$B$7+ROUND(Scenarios!L7*Scenarios!$F7,0)) -> 362 | M30: =IF(Scenarios!$R7=1,BaselineCalc!$B$8*(1+Parameters_Public!$C45)^(IF($C30="FY2026",0,IF($C30="FY2027",1,IF($C30="FY2028",2,IF($C30="FY2029",3,IF($C30="FY2030",4,0))))))+Scenarios!L7-ROUND(Scenarios!L7*Scenarios!$F7,0),BaselineCalc!$B$8+Scenarios!L7-ROUND(Scenarios!L7*Scenarios!$F7,0)) -> 341 | N30: =(L30-D30) + (M30-E30) -> 0 | O30: =(Parameters_Public!$C$22*(L30-D30)+Parameters_Public!$C$23*(M30-E30)) -> 0 | P30: =YearMap!E5 -> 500 | Q30: =IF(Scenarios!N7="lease", YearMap!F5, YearMap!G5) -> 0.3 | R30: =IF(Scenarios!D7=1, Q30*H30, H30) -> 1512280.6 | S30: =IF(Scenarios!E7=1, Q30*I30, I30) -> 1741770.6 | T30: =IF(C30="FY2026", (Scenarios!D7+Scenarios!E7)*BaselineCalc!$B$22, 0) -> 0 | U30: =(R30+S30+G30*F30)*J30*(1-K30) -> 8053412.2 | V30: =O30*(G30+P30) -> 0 | W30: =U30+V30+IF(Parameters_Public!$C$26=1, T30, 0) -> 8053412.2 | X30: =IF(F30+O30>0, W30/(F30+O30),"") -> 11455.778 | Y30: =INDEX(YearMap!$I$2:$I$6, MATCH(C30, YearMap!$A$2:$A$6, 0)) -> 5398.4527 | Z30: =W30 - ((Y30 + IF(Parameters_Public!$C$20=1, Parameters_Public!$C$19, 0))*AC30) -> 3729679.1 | AA30: =IF($AC30>0, $Z30/$AC30, 0) -> 5305.3757 | AB30: =MAX(0, (MAX(0, $D30-BaselineCalc!$B$7) + MAX(0, $E30-BaselineCalc!$B$8))) -> 150 | AC30: =IF(LEFT($B30,2)="A_", $O30, IF(LEFT($B30,2)="B_", $M30+$O30, IF(LEFT($B30,2)="C_", $L30+$O30, $F30))) -> 703 | AD30: =((Y30 + IF(Parameters_Public!$C$20=1, INDEX(YearMap!$O$2:$O$6, MATCH(C30, YearMap!$A$2:$A$6, 0)), 0))*AC30) + AC30*INDEX(YearMap!$P$2:$P$6, MATCH(C30, YearMap!$A$2:$A$6, 0)) -> 8301060.5 | AE30: =W30 - (1-Parameters_Public!$C42)*$G30*$AB30*$J30*(1-$K30) -> 7024506.3 | AF30: =AD30-AE30 -> 1276554.2 | AG30: =B30&"|"&C30 -> G_EchoGHubRamp_PimaTargets|FY2029
A31: =AG31 -> G_EchoGHubRamp_PimaTargets|FY2030 | B31: =Scenarios!A7 -> G_EchoGHubRamp_PimaTargets | C31: FY2030 | D31: =IF(Scenarios!D7=1,0, L31) -> 362 | E31: =IF(Scenarios!E7=1,0, M31) -> 341 | F31: =D31+E31 -> 703 | G31: =YearMap!B6 -> 7080.4205 | H31: =YearMap!C6 -> 1550087.6 | I31: =YearMap!D6 -> 1785314.9 | J31: =1-BaselineCalc!$B$5 -> 0.993 | K31: =Scenarios!G7 -> 0 | L31: =IF(Scenarios!$Q7=1,BaselineCalc!$B$7*(1+Parameters_Public!$C44)^(IF($C31="FY2026",0,IF($C31="FY2027",1,IF($C31="FY2028",2,IF($C31="FY2029",3,IF($C31="FY2030",4,0))))))+ROUND(Scenarios!M7*Scenarios!$F7,0),BaselineCalc!$B$7+ROUND(Scenarios!M7*Scenarios!$F7,0)) -> 362 | M31: =IF(Scenarios!$R7=1,BaselineCalc!$B$8*(1+Parameters_Public!$C45)^(IF($C31="FY2026",0,IF($C31="FY2027",1,IF($C31="FY2028",2,IF($C31="FY2029",3,IF($C31="FY2030",4,0))))))+Scenarios!M7-ROUND(Scenarios!M7*Scenarios!$F7,0),BaselineCalc!$B$8+Scenarios!M7-ROUND(Scenarios!M7*Scenarios!$F7,0)) -> 341 | N31: =(L31-D31) + (M31-E31) -> 0 | O31: =(Parameters_Public!$C$22*(L31-D31)+Parameters_Public!$C$23*(M31-E31)) -> 0 | P31: =YearMap!E6 -> 300 | Q31: =IF(Scenarios!N7="lease", YearMap!F6, YearMap!G6) -> 0.3 | R31: =IF(Scenarios!D7=1, Q31*H31, H31) -> 1550087.6 | S31: =IF(Scenarios!E7=1, Q31*I31, I31) -> 1785314.9 | T31: =IF(C31="FY2026", (Scenarios!D7+Scenarios!E7)*BaselineCalc!$B$22, 0) -> 0 | U31: =(R31+S31+G31*F31)*J31*(1-K31) -> 8254747.6 | V31: =O31*(G31+P31) -> 0 | W31: =U31+V31+IF(Parameters_Public!$C$26=1, T31, 0) -> 8254747.6 | X31: =IF(F31+O31>0, W31/(F31+O31),"") -> 11742.173 | Y31: =INDEX(YearMap!$I$2:$I$6, MATCH(C31, YearMap!$A$2:$A$6, 0)) -> 5533.414 | Z31: =W31 - ((Y31 + IF(Parameters_Public!$C$20=1, Parameters_Public!$C$19, 0))*AC31) -> 3836136.6 | AA31: =IF($AC31>0, $Z31/$AC31, 0) -> 5456.8089 | AB31: =MAX(0, (MAX(0, $D31-BaselineCalc!$B$7) + MAX(0, $E31-BaselineCalc!$B$8))) -> 150 | AC31: =IF(LEFT($B31,2)="A_", $O31, IF(LEFT($B31,2)="B_", $M31+$O31, IF(LEFT($B31,2)="C_", $L31+$O31, $F31))) -> 703 | AD31: =((Y31 + IF(Parameters_Public!$C$20=1, INDEX(YearMap!$O$2:$O$6, MATCH(C31, YearMap!$A$2:$A$6, 0)), 0))*AC31) + AC31*INDEX(YearMap!$P$2:$P$6, MATCH(C31, YearMap!$A$2:$A$6, 0)) -> 8508587 | AE31: =W31 - (1-Parameters_Public!$C42)*$G31*$AB31*$J31*(1-$K31) -> 7200118.9 | AF31: =AD31-AE31 -> 1308468 | AG31: =B31&"|"&C31 -> G_EchoGHubRamp_PimaTargets|FY2030
A32: =AG32 -> A_Repurpose_Both_lease|FY2026 | B32: =Scenarios!A8 -> A_Repurpose_Both_lease | C32: FY2026 | D32: =IF(Scenarios!D8=1,0, L32) -> 0 | E32: =IF(Scenarios!E8=1,0, M32) -> 0 | F32: =D32+E32 -> 0 | G32: =YearMap!B2 -> 6414.5115 | H32: =YearMap!C2 -> 1404302.9 | I32: =YearMap!D2 -> 1617407.2 | J32: =1-BaselineCalc!$B$5 -> 0.993 | K32: =Scenarios!G8 -> 0 | L32: =IF(Scenarios!$Q8=1,BaselineCalc!$B$7*(1+Parameters_Public!$C44)^(IF($C32="FY2026",0,IF($C32="FY2027",1,IF($C32="FY2028",2,IF($C32="FY2029",3,IF($C32="FY2030",4,0))))))+ROUND(Scenarios!I8*Scenarios!$F8,0),BaselineCalc!$B$7+ROUND(Scenarios!I8*Scenarios!$F8,0)) -> 257 | M32: =IF(Scenarios!$R8=1,BaselineCalc!$B$8*(1+Parameters_Public!$C45)^(IF($C32="FY2026",0,IF($C32="FY2027",1,IF($C32="FY2028",2,IF($C32="FY2029",3,IF($C32="FY2030",4,0))))))+Scenarios!I8-ROUND(Scenarios!I8*Scenarios!$F8,0),BaselineCalc!$B$8+Scenarios!I8-ROUND(Scenarios!I8*Scenarios!$F8,0)) -> 296 | N32: =(L32-D32) + (M32-E32) -> 553 | O32: =(Parameters_Public!$C$22*(L32-D32)+Parameters_Public!$C$23*(M32-E32)) -> 184.025 | P32: =YearMap!E2 -> 1000 | Q32: =IF(Scenarios!N8="lease", YearMap!F2, YearMap!G2) -> 0.4 | R32: =IF(Scenarios!D8=1, Q32*H32, H32) -> 561721.15 | S32: =IF(Scenarios!E8=1, Q32*I32, I32) -> 646962.88 | T32: =IF(C32="FY2026", (Scenarios!D8+Scenarios!E8)*BaselineCalc!$B$22, 0) -> 2400000 | U32: =(R32+S32+G32*F32)*J32*(1-K32) -> 1200223.2 | V32: =O32*(G32+P32) -> 1364455.5 | W32: =U32+V32+IF(Parameters_Public!$C$26=1, T32, 0) -> 2564678.7 | X32: =IF(F32+O32>0, W32/(F32+O32),"") -> 13936.578 | Y32: =INDEX(YearMap!$I$2:$I$6, MATCH(C32, YearMap!$A$2:$A$6, 0)) -> 5013 | Z32: =W32 - ((Y32 + IF(Parameters_Public!$C$20=1, Parameters_Public!$C$19, 0))*AC32) -> 1503783.8 | AA32: =IF($AC32>0, $Z32/$AC32, 0) -> 8171.6277 | AB32: =MAX(0, (MAX(0, $D32-BaselineCalc!$B$7) + MAX(0, $E32-BaselineCalc!$B$8))) -> 0 | AC32: =IF(LEFT($B32,2)="A_", $O32, IF(LEFT($B32,2)="B_", $M32+$O32, IF(LEFT($B32,2)="C_", $L32+$O32, $F32))) -> 184.025 | AD32: =((Y32 + IF(Parameters_Public!$C$20=1, INDEX(YearMap!$O$2:$O$6, MATCH(C32, YearMap!$A$2:$A$6, 0)), 0))*AC32) + AC32*INDEX(YearMap!$P$2:$P$6, MATCH(C32, YearMap!$A$2:$A$6, 0)) -> 2017824.9 | AE32: =W32 - (1-Parameters_Public!$C42)*$G32*$AB32*$J32*(1-$K32) -> 2564678.7 | AF32: =AD32-AE32 -> -546853.79 | AG32: =B32&"|"&C32 -> A_Repurpose_Both_lease|FY2026
A33: =AG33 -> A_Repurpose_Both_lease|FY2027 | B33: =Scenarios!A8 -> A_Repurpose_Both_lease | C33: FY2027 | D33: =IF(Scenarios!D8=1,0, L33) -> 0 | E33: =IF(Scenarios!E8=1,0, M33) -> 0 | F33: =D33+E33 -> 0 | G33: =YearMap!B3 -> 6574.8743 | H33: =YearMap!C3 -> 1439410.4 | I33: =YearMap!D3 -> 1657842.4 | J33: =1-BaselineCalc!$B$5 -> 0.993 | K33: =Scenarios!G8 -> 0 | L33: =IF(Scenarios!$Q8=1,BaselineCalc!$B$7*(1+Parameters_Public!$C44)^(IF($C33="FY2026",0,IF($C33="FY2027",1,IF($C33="FY2028",2,IF($C33="FY2029",3,IF($C33="FY2030",4,0))))))+ROUND(Scenarios!J8*Scenarios!$F8,0),BaselineCalc!$B$7+ROUND(Scenarios!J8*Scenarios!$F8,0)) -> 257 | M33: =IF(Scenarios!$R8=1,BaselineCalc!$B$8*(1+Parameters_Public!$C45)^(IF($C33="FY2026",0,IF($C33="FY2027",1,IF($C33="FY2028",2,IF($C33="FY2029",3,IF($C33="FY2030",4,0))))))+Scenarios!J8-ROUND(Scenarios!J8*Scenarios!$F8,0),BaselineCalc!$B$8+Scenarios!J8-ROUND(Scenarios!J8*Scenarios!$F8,0)) -> 296 | N33: =(L33-D33) + (M33-E33) -> 553 | O33: =(Parameters_Public!$C$22*(L33-D33)+Parameters_Public!$C$23*(M33-E33)) -> 184.025 | P33: =YearMap!E3 -> 800 | Q33: =IF(Scenarios!N8="lease", YearMap!F3, YearMap!G3) -> 0.3 | R33: =IF(Scenarios!D8=1, Q33*H33, H33) -> 431823.13 | S33: =IF(Scenarios!E8=1, Q33*I33, I33) -> 497352.71 | T33: =IF(C33="FY2026", (Scenarios!D8+Scenarios!E8)*BaselineCalc!$B$22, 0) -> 0 | U33: =(R33+S33+G33*F33)*J33*(1-K33) -> 922671.61 | V33: =O33*(G33+P33) -> 1357161.2 | W33: =U33+V33+IF(Parameters_Public!$C$26=1, T33, 0) -> 2279832.9 | X33: =IF(F33+O33>0, W33/(F33+O33),"") -> 12388.713 | Y33: =INDEX(YearMap!$I$2:$I$6, MATCH(C33, YearMap!$A$2:$A$6, 0)) -> 5138.325 | Z33: =W33 - ((Y33 + IF(Parameters_Public!$C$20=1, Parameters_Public!$C$19, 0))*AC33) -> 1195875 | AA33: =IF($AC33>0, $Z33/$AC33, 0) -> 6498.4377 | AB33: =MAX(0, (MAX(0, $D33-BaselineCalc!$B$7) + MAX(0, $E33-BaselineCalc!$B$8))) -> 0 | AC33: =IF(LEFT($B33,2)="A_", $O33, IF(LEFT($B33,2)="B_", $M33+$O33, IF(LEFT($B33,2)="C_", $L33+$O33, $F33))) -> 184.025 | AD33: =((Y33 + IF(Parameters_Public!$C$20=1, INDEX(YearMap!$O$2:$O$6, MATCH(C33, YearMap!$A$2:$A$6, 0)), 0))*AC33) + AC33*INDEX(YearMap!$P$2:$P$6, MATCH(C33, YearMap!$A$2:$A$6, 0)) -> 2068270.5 | AE33: =W33 - (1-Parameters_Public!$C42)*$G33*$AB33*$J33*(1-$K33) -> 2279832.9 | AF33: =AD33-AE33 -> -211562.31 | AG33: =B33&"|"&C33 -> A_Repurpose_Both_lease|FY2027
A34: =AG34 -> A_Repurpose_Both_lease|FY2028 | B34: =Scenarios!A8 -> A_Repurpose_Both_lease | C34: FY2028 | D34: =IF(Scenarios!D8=1,0, L34) -> 0 | E34: =IF(Scenarios!E8=1,0, M34) -> 0 | F34: =D34+E34 -> 0 | G34: =YearMap!B4 -> 6739.2461 | H34: =YearMap!C4 -> 1475395.7 | I34: =YearMap!D4 -> 1699288.4 | J34: =1-BaselineCalc!$B$5 -> 0.993 | K34: =Scenarios!G8 -> 0 | L34: =IF(Scenarios!$Q8=1,BaselineCalc!$B$7*(1+Parameters_Public!$C44)^(IF($C34="FY2026",0,IF($C34="FY2027",1,IF($C34="FY2028",2,IF($C34="FY2029",3,IF($C34="FY2030",4,0))))))+ROUND(Scenarios!K8*Scenarios!$F8,0),BaselineCalc!$B$7+ROUND(Scenarios!K8*Scenarios!$F8,0)) -> 257 | M34: =IF(Scenarios!$R8=1,BaselineCalc!$B$8*(1+Parameters_Public!$C45)^(IF($C34="FY2026",0,IF($C34="FY2027",1,IF($C34="FY2028",2,IF($C34="FY2029",3,IF($C34="FY2030",4,0))))))+Scenarios!K8-ROUND(Scenarios!K8*Scenarios!$F8,0),BaselineCalc!$B$8+Scenarios!K8-ROUND(Scenarios!K8*Scenarios!$F8,0)) -> 296 | N34: =(L34-D34) + (M34-E34) -> 553 | O34: =(Parameters_Public!$C$22*(L34-D34)+Parameters_Public!$C$23*(M34-E34)) -> 184.025 | P34: =YearMap!E4 -> 600 | Q34: =IF(Scenarios!N8="lease", YearMap!F4, YearMap!G4) -> 0.2 | R34: =IF(Scenarios!D8=1, Q34*H34, H34) -> 295079.14 | S34: =IF(Scenarios!E8=1, Q34*I34, I34) -> 339857.69 | T34: =IF(C34="FY2026", (Scenarios!D8+Scenarios!E8)*BaselineCalc!$B$22, 0) -> 0 | U34: =(R34+S34+G34*F34)*J34*(1-K34) -> 630492.27 | V34: =O34*(G34+P34) -> 1350604.8 | W34: =U34+V34+IF(Parameters_Public!$C$26=1, T34, 0) -> 1981097 | X34: =IF(F34+O34>0, W34/(F34+O34),"") -> 10765.369 | Y34: =INDEX(YearMap!$I$2:$I$6, MATCH(C34, YearMap!$A$2:$A$6, 0)) -> 5266.7831 | Z34: =W34 - ((Y34 + IF(Parameters_Public!$C$20=1, Parameters_Public!$C$19, 0))*AC34) -> 873499.68 | AA34: =IF($AC34>0, $Z34/$AC34, 0) -> 4746.6359 | AB34: =MAX(0, (MAX(0, $D34-BaselineCalc!$B$7) + MAX(0, $E34-BaselineCalc!$B$8))) -> 0 | AC34: =IF(LEFT($B34,2)="A_", $O34, IF(LEFT($B34,2)="B_", $M34+$O34, IF(LEFT($B34,2)="C_", $L34+$O34, $F34))) -> 184.025 | AD34: =((Y34 + IF(Parameters_Public!$C$20=1, INDEX(YearMap!$O$2:$O$6, MATCH(C34, YearMap!$A$2:$A$6, 0)), 0))*AC34) + AC34*INDEX(YearMap!$P$2:$P$6, MATCH(C34, YearMap!$A$2:$A$6, 0)) -> 2119977.3 | AE34: =W34 - (1-Parameters_Public!$C42)*$G34*$AB34*$J34*(1-$K34) -> 1981097 | AF34: =AD34-AE34 -> 138880.27 | AG34: =B34&"|"&C34 -> A_Repurpose_Both_lease|FY2028
A35: =AG35 -> A_Repurpose_Both_lease|FY2029 | B35: =Scenarios!A8 -> A_Repurpose_Both_lease | C35: FY2029 | D35: =IF(Scenarios!D8=1,0, L35) -> 0 | E35: =IF(Scenarios!E8=1,0, M35) -> 0 | F35: =D35+E35 -> 0 | G35: =YearMap!B5 -> 6907.7273 | H35: =YearMap!C5 -> 1512280.6 | I35: =YearMap!D5 -> 1741770.6 | J35: =1-BaselineCalc!$B$5 -> 0.993 | K35: =Scenarios!G8 -> 0 | L35: =IF(Scenarios!$Q8=1,BaselineCalc!$B$7*(1+Parameters_Public!$C44)^(IF($C35="FY2026",0,IF($C35="FY2027",1,IF($C35="FY2028",2,IF($C35="FY2029",3,IF($C35="FY2030",4,0))))))+ROUND(Scenarios!L8*Scenarios!$F8,0),BaselineCalc!$B$7+ROUND(Scenarios!L8*Scenarios!$F8,0)) -> 257 | M35: =IF(Scenarios!$R8=1,BaselineCalc!$B$8*(1+Parameters_Public!$C45)^(IF($C35="FY2026",0,IF($C35="FY2027",1,IF($C35="FY2028",2,IF($C35="FY2029",3,IF($C35="FY2030",4,0))))))+Scenarios!L8-ROUND(Scenarios!L8*Scenarios!$F8,0),BaselineCalc!$B$8+Scenarios!L8-ROUND(Scenarios!L8*Scenarios!$F8,0)) -> 296 | N35: =(L35-D35) + (M35-E35) -> 553 | O35: =(Parameters_Public!$C$22*(L35-D35)+Parameters_Public!$C$23*(M35-E35)) -> 184.025 | P35: =YearMap!E5 -> 500 | Q35: =IF(Scenarios!N8="lease", YearMap!F5, YearMap!G5) -> 0.1 | R35: =IF(Scenarios!D8=1, Q35*H35, H35) -> 151228.06 | S35: =IF(Scenarios!E8=1, Q35*I35, I35) -> 174177.06 | T35: =IF(C35="FY2026", (Scenarios!D8+Scenarios!E8)*BaselineCalc!$B$22, 0) -> 0 | U35: =(R35+S35+G35*F35)*J35*(1-K35) -> 323127.29 | V35: =O35*(G35+P35) -> 1363207 | W35: =U35+V35+IF(Parameters_Public!$C$26=1, T35, 0) -> 1686334.3 | X35: =IF(F35+O35>0, W35/(F35+O35),"") -> 9163.6153 | Y35: =INDEX(YearMap!$I$2:$I$6, MATCH(C35, YearMap!$A$2:$A$6, 0)) -> 5398.4527 | Z35: =W35 - ((Y35 + IF(Parameters_Public!$C$20=1, Parameters_Public!$C$19, 0))*AC35) -> 554506.45 | AA35: =IF($AC35>0, $Z35/$AC35, 0) -> 3013.2126 | AB35: =MAX(0, (MAX(0, $D35-BaselineCalc!$B$7) + MAX(0, $E35-BaselineCalc!$B$8))) -> 0 | AC35: =IF(LEFT($B35,2)="A_", $O35, IF(LEFT($B35,2)="B_", $M35+$O35, IF(LEFT($B35,2)="C_", $L35+$O35, $F35))) -> 184.025 | AD35: =((Y35 + IF(Parameters_Public!$C$20=1, INDEX(YearMap!$O$2:$O$6, MATCH(C35, YearMap!$A$2:$A$6, 0)), 0))*AC35) + AC35*INDEX(YearMap!$P$2:$P$6, MATCH(C35, YearMap!$A$2:$A$6, 0)) -> 2172976.7 | AE35: =W35 - (1-Parameters_Public!$C42)*$G35*$AB35*$J35*(1-$K35) -> 1686334.3 | AF35: =AD35-AE35 -> 486642.44 | AG35: =B35&"|"&C35 -> A_Repurpose_Both_lease|FY2029
A36: =AG36 -> A_Repurpose_Both_lease|FY2030 | B36: =Scenarios!A8 -> A_Repurpose_Both_lease | C36: FY2030 | D36: =IF(Scenarios!D8=1,0, L36) -> 0 | E36: =IF(Scenarios!E8=1,0, M36) -> 0 | F36: =D36+E36 -> 0 | G36: =YearMap!B6 -> 7080.4205 | H36: =YearMap!C6 -> 1550087.6 | I36: =YearMap!D6 -> 1785314.9 | J36: =1-BaselineCalc!$B$5 -> 0.993 | K36: =Scenarios!G8 -> 0 | L36: =IF(Scenarios!$Q8=1,BaselineCalc!$B$7*(1+Parameters_Public!$C44)^(IF($C36="FY2026",0,IF($C36="FY2027",1,IF($C36="FY2028",2,IF($C36="FY2029",3,IF($C36="FY2030",4,0))))))+ROUND(Scenarios!M8*Scenarios!$F8,0),BaselineCalc!$B$7+ROUND(Scenarios!M8*Scenarios!$F8,0)) -> 257 | M36: =IF(Scenarios!$R8=1,BaselineCalc!$B$8*(1+Parameters_Public!$C45)^(IF($C36="FY2026",0,IF($C36="FY2027",1,IF($C36="FY2028",2,IF($C36="FY2029",3,IF($C36="FY2030",4,0))))))+Scenarios!M8-ROUND(Scenarios!M8*Scenarios!$F8,0),BaselineCalc!$B$8+Scenarios!M8-ROUND(Scenarios!M8*Scenarios!$F8,0)) -> 296 | N36: =(L36-D36) + (M36-E36) -> 553 | O36: =(Parameters_Public!$C$22*(L36-D36)+Parameters_Public!$C$23*(M36-E36)) -> 184.025 | P36: =YearMap!E6 -> 300 | Q36: =IF(Scenarios!N8="lease", YearMap!F6, YearMap!G6) -> 0.1 | R36: =IF(Scenarios!D8=1, Q36*H36, H36) -> 155008.76 | S36: =IF(Scenarios!E8=1, Q36*I36, I36) -> 178531.49 | T36: =IF(C36="FY2026", (Scenarios!D8+Scenarios!E8)*BaselineCalc!$B$22, 0) -> 0 | U36: =(R36+S36+G36*F36)*J36*(1-K36) -> 331205.47 | V36: =O36*(G36+P36) -> 1358181.9 | W36: =U36+V36+IF(Parameters_Public!$C$26=1, T36, 0) -> 1689387.3 | X36: =IF(F36+O36>0, W36/(F36+O36),"") -> 9180.2057 | Y36: =INDEX(YearMap!$I$2:$I$6, MATCH(C36, YearMap!$A$2:$A$6, 0)) -> 5533.414 | Z36: =W36 - ((Y36 + IF(Parameters_Public!$C$20=1, Parameters_Public!$C$19, 0))*AC36) -> 532723.24 | AA36: =IF($AC36>0, $Z36/$AC36, 0) -> 2894.8417 | AB36: =MAX(0, (MAX(0, $D36-BaselineCalc!$B$7) + MAX(0, $E36-BaselineCalc!$B$8))) -> 0 | AC36: =IF(LEFT($B36,2)="A_", $O36, IF(LEFT($B36,2)="B_", $M36+$O36, IF(LEFT($B36,2)="C_", $L36+$O36, $F36))) -> 184.025 | AD36: =((Y36 + IF(Parameters_Public!$C$20=1, INDEX(YearMap!$O$2:$O$6, MATCH(C36, YearMap!$A$2:$A$6, 0)), 0))*AC36) + AC36*INDEX(YearMap!$P$2:$P$6, MATCH(C36, YearMap!$A$2:$A$6, 0)) -> 2227301.2 | AE36: =W36 - (1-Parameters_Public!$C42)*$G36*$AB36*$J36*(1-$K36) -> 1689387.3 | AF36: =AD36-AE36 -> 537913.81 | AG36: =B36&"|"&C36 -> A_Repurpose_Both_lease|FY2030
A37: =AG37 -> A_Repurpose_Both_ops|FY2026 | B37: =Scenarios!A9 -> A_Repurpose_Both_ops | C37: FY2026 | D37: =IF(Scenarios!D9=1,0, L37) -> 0 | E37: =IF(Scenarios!E9=1,0, M37) -> 0 | F37: =D37+E37 -> 0 | G37: =YearMap!B2 -> 6414.5115 | H37: =YearMap!C2 -> 1404302.9 | I37: =YearMap!D2 -> 1617407.2 | J37: =1-BaselineCalc!$B$5 -> 0.993 | K37: =Scenarios!G9 -> 0 | L37: =IF(Scenarios!$Q9=1,BaselineCalc!$B$7*(1+Parameters_Public!$C44)^(IF($C37="FY2026",0,IF($C37="FY2027",1,IF($C37="FY2028",2,IF($C37="FY2029",3,IF($C37="FY2030",4,0))))))+ROUND(Scenarios!I9*Scenarios!$F9,0),BaselineCalc!$B$7+ROUND(Scenarios!I9*Scenarios!$F9,0)) -> 257 | M37: =IF(Scenarios!$R9=1,BaselineCalc!$B$8*(1+Parameters_Public!$C45)^(IF($C37="FY2026",0,IF($C37="FY2027",1,IF($C37="FY2028",2,IF($C37="FY2029",3,IF($C37="FY2030",4,0))))))+Scenarios!I9-ROUND(Scenarios!I9*Scenarios!$F9,0),BaselineCalc!$B$8+Scenarios!I9-ROUND(Scenarios!I9*Scenarios!$F9,0)) -> 296 | N37: =(L37-D37) + (M37-E37) -> 553 | O37: =(Parameters_Public!$C$22*(L37-D37)+Parameters_Public!$C$23*(M37-E37)) -> 184.025 | P37: =YearMap!E2 -> 1000 | Q37: =IF(Scenarios!N9="lease", YearMap!F2, YearMap!G2) -> 0.5 | R37: =IF(Scenarios!D9=1, Q37*H37, H37) -> 702151.43 | S37: =IF(Scenarios!E9=1, Q37*I37, I37) -> 808703.6 | T37: =IF(C37="FY2026", (Scenarios!D9+Scenarios!E9)*BaselineCalc!$B$22, 0) -> 2400000 | U37: =(R37+S37+G37*F37)*J37*(1-K37) -> 1500279 | V37: =O37*(G37+P37) -> 1364455.5 | W37: =U37+V37+IF(Parameters_Public!$C$26=1, T37, 0) -> 2864734.5 | X37: =IF(F37+O37>0, W37/(F37+O37),"") -> 15567.094 | Y37: =INDEX(YearMap!$I$2:$I$6, MATCH(C37, YearMap!$A$2:$A$6, 0)) -> 5013 | Z37: =W37 - ((Y37 + IF(Parameters_Public!$C$20=1, Parameters_Public!$C$19, 0))*AC37) -> 1803839.6 | AA37: =IF($AC37>0, $Z37/$AC37, 0) -> 9802.1443 | AB37: =MAX(0, (MAX(0, $D37-BaselineCalc!$B$7) + MAX(0, $E37-BaselineCalc!$B$8))) -> 0 | AC37: =IF(LEFT($B37,2)="A_", $O37, IF(LEFT($B37,2)="B_", $M37+$O37, IF(LEFT($B37,2)="C_", $L37+$O37, $F37))) -> 184.025 | AD37: =((Y37 + IF(Parameters_Public!$C$20=1, INDEX(YearMap!$O$2:$O$6, MATCH(C37, YearMap!$A$2:$A$6, 0)), 0))*AC37) + AC37*INDEX(YearMap!$P$2:$P$6, MATCH(C37, YearMap!$A$2:$A$6, 0)) -> 2017824.9 | AE37: =W37 - (1-Parameters_Public!$C42)*$G37*$AB37*$J37*(1-$K37) -> 2864734.5 | AF37: =AD37-AE37 -> -846909.6 | AG37: =B37&"|"&C37 -> A_Repurpose_Both_ops|FY2026
A38: =AG38 -> A_Repurpose_Both_ops|FY2027 | B38: =Scenarios!A9 -> A_Repurpose_Both_ops | C38: FY2027 | D38: =IF(Scenarios!D9=1,0, L38) -> 0 | E38: =IF(Scenarios!E9=1,0, M38) -> 0 | F38: =D38+E38 -> 0 | G38: =YearMap!B3 -> 6574.8743 | H38: =YearMap!C3 -> 1439410.4 | I38: =YearMap!D3 -> 1657842.4 | J38: =1-BaselineCalc!$B$5 -> 0.993 | K38: =Scenarios!G9 -> 0 | L38: =IF(Scenarios!$Q9=1,BaselineCalc!$B$7*(1+Parameters_Public!$C44)^(IF($C38="FY2026",0,IF($C38="FY2027",1,IF($C38="FY2028",2,IF($C38="FY2029",3,IF($C38="FY2030",4,0))))))+ROUND(Scenarios!J9*Scenarios!$F9,0),BaselineCalc!$B$7+ROUND(Scenarios!J9*Scenarios!$F9,0)) -> 257 | M38: =IF(Scenarios!$R9=1,BaselineCalc!$B$8*(1+Parameters_Public!$C45)^(IF($C38="FY2026",0,IF($C38="FY2027",1,IF($C38="FY2028",2,IF($C38="FY2029",3,IF($C38="FY2030",4,0))))))+Scenarios!J9-ROUND(Scenarios!J9*Scenarios!$F9,0),BaselineCalc!$B$8+Scenarios!J9-ROUND(Scenarios!J9*Scenarios!$F9,0)) -> 296 | N38: =(L38-D38) + (M38-E38) -> 553 | O38: =(Parameters_Public!$C$22*(L38-D38)+Parameters_Public!$C$23*(M38-E38)) -> 184.025 | P38: =YearMap!E3 -> 800 | Q38: =IF(Scenarios!N9="lease", YearMap!F3, YearMap!G3) -> 0.4 | R38: =IF(Scenarios!D9=1, Q38*H38, H38) -> 575764.18 | S38: =IF(Scenarios!E9=1, Q38*I38, I38) -> 663136.95 | T38: =IF(C38="FY2026", (Scenarios!D9+Scenarios!E9)*BaselineCalc!$B$22, 0) -> 0 | U38: =(R38+S38+G38*F38)*J38*(1-K38) -> 1230228.8 | V38: =O38*(G38+P38) -> 1357161.2 | W38: =U38+V38+IF(Parameters_Public!$C$26=1, T38, 0) -> 2587390.1 | X38: =IF(F38+O38>0, W38/(F38+O38),"") -> 14059.992 | Y38: =INDEX(YearMap!$I$2:$I$6, MATCH(C38, YearMap!$A$2:$A$6, 0)) -> 5138.325 | Z38: =W38 - ((Y38 + IF(Parameters_Public!$C$20=1, Parameters_Public!$C$19, 0))*AC38) -> 1503432.2 | AA38: =IF($AC38>0, $Z38/$AC38, 0) -> 8169.7172 | AB38: =MAX(0, (MAX(0, $D38-BaselineCalc!$B$7) + MAX(0, $E38-BaselineCalc!$B$8))) -> 0 | AC38: =IF(LEFT($B38,2)="A_", $O38, IF(LEFT($B38,2)="B_", $M38+$O38, IF(LEFT($B38,2)="C_", $L38+$O38, $F38))) -> 184.025 | AD38: =((Y38 + IF(Parameters_Public!$C$20=1, INDEX(YearMap!$O$2:$O$6, MATCH(C38, YearMap!$A$2:$A$6, 0)), 0))*AC38) + AC38*INDEX(YearMap!$P$2:$P$6, MATCH(C38, YearMap!$A$2:$A$6, 0)) -> 2068270.5 | AE38: =W38 - (1-Parameters_Public!$C42)*$G38*$AB38*$J38*(1-$K38) -> 2587390.1 | AF38: =AD38-AE38 -> -519119.51 | AG38: =B38&"|"&C38 -> A_Repurpose_Both_ops|FY2027
A39: =AG39 -> A_Repurpose_Both_ops|FY2028 | B39: =Scenarios!A9 -> A_Repurpose_Both_ops | C39: FY2028 | D39: =IF(Scenarios!D9=1,0, L39) -> 0 | E39: =IF(Scenarios!E9=1,0, M39) -> 0 | F39: =D39+E39 -> 0 | G39: =YearMap!B4 -> 6739.2461 | H39: =YearMap!C4 -> 1475395.7 | I39: =YearMap!D4 -> 1699288.4 | J39: =1-BaselineCalc!$B$5 -> 0.993 | K39: =Scenarios!G9 -> 0 | L39: =IF(Scenarios!$Q9=1,BaselineCalc!$B$7*(1+Parameters_Public!$C44)^(IF($C39="FY2026",0,IF($C39="FY2027",1,IF($C39="FY2028",2,IF($C39="FY2029",3,IF($C39="FY2030",4,0))))))+ROUND(Scenarios!K9*Scenarios!$F9,0),BaselineCalc!$B$7+ROUND(Scenarios!K9*Scenarios!$F9,0)) -> 257 | M39: =IF(Scenarios!$R9=1,BaselineCalc!$B$8*(1+Parameters_Public!$C45)^(IF($C39="FY2026",0,IF($C39="FY2027",1,IF($C39="FY2028",2,IF($C39="FY2029",3,IF($C39="FY2030",4,0))))))+Scenarios!K9-ROUND(Scenarios!K9*Scenarios!$F9,0),BaselineCalc!$B$8+Scenarios!K9-ROUND(Scenarios!K9*Scenarios!$F9,0)) -> 296 | N39: =(L39-D39) + (M39-E39) -> 553 | O39: =(Parameters_Public!$C$22*(L39-D39)+Parameters_Public!$C$23*(M39-E39)) -> 184.025 | P39: =YearMap!E4 -> 600 | Q39: =IF(Scenarios!N9="lease", YearMap!F4, YearMap!G4) -> 0.35 | R39: =IF(Scenarios!D9=1, Q39*H39, H39) -> 516388.5 | S39: =IF(Scenarios!E9=1, Q39*I39, I39) -> 594750.95 | T39: =IF(C39="FY2026", (Scenarios!D9+Scenarios!E9)*BaselineCalc!$B$22, 0) -> 0 | U39: =(R39+S39+G39*F39)*J39*(1-K39) -> 1103361.5 | V39: =O39*(G39+P39) -> 1350604.8 | W39: =U39+V39+IF(Parameters_Public!$C$26=1, T39, 0) -> 2453966.2 | X39: =IF(F39+O39>0, W39/(F39+O39),"") -> 13334.961 | Y39: =INDEX(YearMap!$I$2:$I$6, MATCH(C39, YearMap!$A$2:$A$6, 0)) -> 5266.7831 | Z39: =W39 - ((Y39 + IF(Parameters_Public!$C$20=1, Parameters_Public!$C$19, 0))*AC39) -> 1346368.9 | AA39: =IF($AC39>0, $Z39/$AC39, 0) -> 7316.2281 | AB39: =MAX(0, (MAX(0, $D39-BaselineCalc!$B$7) + MAX(0, $E39-BaselineCalc!$B$8))) -> 0 | AC39: =IF(LEFT($B39,2)="A_", $O39, IF(LEFT($B39,2)="B_", $M39+$O39, IF(LEFT($B39,2)="C_", $L39+$O39, $F39))) -> 184.025 | AD39: =((Y39 + IF(Parameters_Public!$C$20=1, INDEX(YearMap!$O$2:$O$6, MATCH(C39, YearMap!$A$2:$A$6, 0)), 0))*AC39) + AC39*INDEX(YearMap!$P$2:$P$6, MATCH(C39, YearMap!$A$2:$A$6, 0)) -> 2119977.3 | AE39: =W39 - (1-Parameters_Public!$C42)*$G39*$AB39*$J39*(1-$K39) -> 2453966.2 | AF39: =AD39-AE39 -> -333988.93 | AG39: =B39&"|"&C39 -> A_Repurpose_Both_ops|FY2028
A40: =AG40 -> A_Repurpose_Both_ops|FY2029 | B40: =Scenarios!A9 -> A_Repurpose_Both_ops | C40: FY2029 | D40: =IF(Scenarios!D9=1,0, L40) -> 0 | E40: =IF(Scenarios!E9=1,0, M40) -> 0 | F40: =D40+E40 -> 0 | G40: =YearMap!B5 -> 6907.7273 | H40: =YearMap!C5 -> 1512280.6 | I40: =YearMap!D5 -> 1741770.6 | J40: =1-BaselineCalc!$B$5 -> 0.993 | K40: =Scenarios!G9 -> 0 | L40: =IF(Scenarios!$Q9=1,BaselineCalc!$B$7*(1+Parameters_Public!$C44)^(IF($C40="FY2026",0,IF($C40="FY2027",1,IF($C40="FY2028",2,IF($C40="FY2029",3,IF($C40="FY2030",4,0))))))+ROUND(Scenarios!L9*Scenarios!$F9,0),BaselineCalc!$B$7+ROUND(Scenarios!L9*Scenarios!$F9,0)) -> 257 | M40: =IF(Scenarios!$R9=1,BaselineCalc!$B$8*(1+Parameters_Public!$C45)^(IF($C40="FY2026",0,IF($C40="FY2027",1,IF($C40="FY2028",2,IF($C40="FY2029",3,IF($C40="FY2030",4,0))))))+Scenarios!L9-ROUND(Scenarios!L9*Scenarios!$F9,0),BaselineCalc!$B$8+Scenarios!L9-ROUND(Scenarios!L9*Scenarios!$F9,0)) -> 296 | N40: =(L40-D40) + (M40-E40) -> 553 | O40: =(Parameters_Public!$C$22*(L40-D40)+Parameters_Public!$C$23*(M40-E40)) -> 184.025 | P40: =YearMap!E5 -> 500 | Q40: =IF(Scenarios!N9="lease", YearMap!F5, YearMap!G5) -> 0.3 | R40: =IF(Scenarios!D9=1, Q40*H40, H40) -> 453684.18 | S40: =IF(Scenarios!E9=1, Q40*I40, I40) -> 522531.19 | T40: =IF(C40="FY2026", (Scenarios!D9+Scenarios!E9)*BaselineCalc!$B$22, 0) -> 0 | U40: =(R40+S40+G40*F40)*J40*(1-K40) -> 969381.86 | V40: =O40*(G40+P40) -> 1363207 | W40: =U40+V40+IF(Parameters_Public!$C$26=1, T40, 0) -> 2332588.9 | X40: =IF(F40+O40>0, W40/(F40+O40),"") -> 12675.391 | Y40: =INDEX(YearMap!$I$2:$I$6, MATCH(C40, YearMap!$A$2:$A$6, 0)) -> 5398.4527 | Z40: =W40 - ((Y40 + IF(Parameters_Public!$C$20=1, Parameters_Public!$C$19, 0))*AC40) -> 1200761 | AA40: =IF($AC40>0, $Z40/$AC40, 0) -> 6524.9886 | AB40: =MAX(0, (MAX(0, $D40-BaselineCalc!$B$7) + MAX(0, $E40-BaselineCalc!$B$8))) -> 0 | AC40: =IF(LEFT($B40,2)="A_", $O40, IF(LEFT($B40,2)="B_", $M40+$O40, IF(LEFT($B40,2)="C_", $L40+$O40, $F40))) -> 184.025 | AD40: =((Y40 + IF(Parameters_Public!$C$20=1, INDEX(YearMap!$O$2:$O$6, MATCH(C40, YearMap!$A$2:$A$6, 0)), 0))*AC40) + AC40*INDEX(YearMap!$P$2:$P$6, MATCH(C40, YearMap!$A$2:$A$6, 0)) -> 2172976.7 | AE40: =W40 - (1-Parameters_Public!$C42)*$G40*$AB40*$J40*(1-$K40) -> 2332588.9 | AF40: =AD40-AE40 -> -159612.14 | AG40: =B40&"|"&C40 -> A_Repurpose_Both_ops|FY2029
A41: =AG41 -> A_Repurpose_Both_ops|FY2030 | B41: =Scenarios!A9 -> A_Repurpose_Both_ops | C41: FY2030 | D41: =IF(Scenarios!D9=1,0, L41) -> 0 | E41: =IF(Scenarios!E9=1,0, M41) -> 0 | F41: =D41+E41 -> 0 | G41: =YearMap!B6 -> 7080.4205 | H41: =YearMap!C6 -> 1550087.6 | I41: =YearMap!D6 -> 1785314.9 | J41: =1-BaselineCalc!$B$5 -> 0.993 | K41: =Scenarios!G9 -> 0 | L41: =IF(Scenarios!$Q9=1,BaselineCalc!$B$7*(1+Parameters_Public!$C44)^(IF($C41="FY2026",0,IF($C41="FY2027",1,IF($C41="FY2028",2,IF($C41="FY2029",3,IF($C41="FY2030",4,0))))))+ROUND(Scenarios!M9*Scenarios!$F9,0),BaselineCalc!$B$7+ROUND(Scenarios!M9*Scenarios!$F9,0)) -> 257 | M41: =IF(Scenarios!$R9=1,BaselineCalc!$B$8*(1+Parameters_Public!$C45)^(IF($C41="FY2026",0,IF($C41="FY2027",1,IF($C41="FY2028",2,IF($C41="FY2029",3,IF($C41="FY2030",4,0))))))+Scenarios!M9-ROUND(Scenarios!M9*Scenarios!$F9,0),BaselineCalc!$B$8+Scenarios!M9-ROUND(Scenarios!M9*Scenarios!$F9,0)) -> 296 | N41: =(L41-D41) + (M41-E41) -> 553 | O41: =(Parameters_Public!$C$22*(L41-D41)+Parameters_Public!$C$23*(M41-E41)) -> 184.025 | P41: =YearMap!E6 -> 300 | Q41: =IF(Scenarios!N9="lease", YearMap!F6, YearMap!G6) -> 0.3 | R41: =IF(Scenarios!D9=1, Q41*H41, H41) -> 465026.28 | S41: =IF(Scenarios!E9=1, Q41*I41, I41) -> 535594.47 | T41: =IF(C41="FY2026", (Scenarios!D9+Scenarios!E9)*BaselineCalc!$B$22, 0) -> 0 | U41: =(R41+S41+G41*F41)*J41*(1-K41) -> 993616.41 | V41: =O41*(G41+P41) -> 1358181.9 | W41: =U41+V41+IF(Parameters_Public!$C$26=1, T41, 0) -> 2351798.3 | X41: =IF(F41+O41>0, W41/(F41+O41),"") -> 12779.776 | Y41: =INDEX(YearMap!$I$2:$I$6, MATCH(C41, YearMap!$A$2:$A$6, 0)) -> 5533.414 | Z41: =W41 - ((Y41 + IF(Parameters_Public!$C$20=1, Parameters_Public!$C$19, 0))*AC41) -> 1195134.2 | AA41: =IF($AC41>0, $Z41/$AC41, 0) -> 6494.412 | AB41: =MAX(0, (MAX(0, $D41-BaselineCalc!$B$7) + MAX(0, $E41-BaselineCalc!$B$8))) -> 0 | AC41: =IF(LEFT($B41,2)="A_", $O41, IF(LEFT($B41,2)="B_", $M41+$O41, IF(LEFT($B41,2)="C_", $L41+$O41, $F41))) -> 184.025 | AD41: =((Y41 + IF(Parameters_Public!$C$20=1, INDEX(YearMap!$O$2:$O$6, MATCH(C41, YearMap!$A$2:$A$6, 0)), 0))*AC41) + AC41*INDEX(YearMap!$P$2:$P$6, MATCH(C41, YearMap!$A$2:$A$6, 0)) -> 2227301.2 | AE41: =W41 - (1-Parameters_Public!$C42)*$G41*$AB41*$J41*(1-$K41) -> 2351798.3 | AF41: =AD41-AE41 -> -124497.13 | AG41: =B41&"|"&C41 -> A_Repurpose_Both_ops|FY2030
A42: =AG42 -> B_Repurpose_Echo_lease_PimaTargets|FY2026 | B42: =Scenarios!A10 -> B_Repurpose_Echo_lease_PimaTargets | C42: FY2026 | D42: =IF(Scenarios!D10=1,0, L42) -> 0 | E42: =IF(Scenarios!E10=1,0, M42) -> 296 | F42: =D42+E42 -> 296 | G42: =YearMap!B2 -> 6414.5115 | H42: =YearMap!C2 -> 1404302.9 | I42: =YearMap!D2 -> 1617407.2 | J42: =1-BaselineCalc!$B$5 -> 0.993 | K42: =Scenarios!G10 -> 0 | L42: =IF(Scenarios!$Q10=1,BaselineCalc!$B$7*(1+Parameters_Public!$C44)^(IF($C42="FY2026",0,IF($C42="FY2027",1,IF($C42="FY2028",2,IF($C42="FY2029",3,IF($C42="FY2030",4,0))))))+ROUND(Scenarios!I10*Scenarios!$F10,0),BaselineCalc!$B$7+ROUND(Scenarios!I10*Scenarios!$F10,0)) -> 257 | M42: =IF(Scenarios!$R10=1,BaselineCalc!$B$8*(1+Parameters_Public!$C45)^(IF($C42="FY2026",0,IF($C42="FY2027",1,IF($C42="FY2028",2,IF($C42="FY2029",3,IF($C42="FY2030",4,0))))))+Scenarios!I10-ROUND(Scenarios!I10*Scenarios!$F10,0),BaselineCalc!$B$8+Scenarios!I10-ROUND(Scenarios!I10*Scenarios!$F10,0)) -> 296 | N42: =(L42-D42) + (M42-E42) -> 257 | O42: =(Parameters_Public!$C$22*(L42-D42)+Parameters_Public!$C$23*(M42-E42)) -> 6.425 | P42: =YearMap!E2 -> 1000 | Q42: =IF(Scenarios!N10="lease", YearMap!F2, YearMap!G2) -> 0.4 | R42: =IF(Scenarios!D10=1, Q42*H42, H42) -> 561721.15 | S42: =IF(Scenarios!E10=1, Q42*I42, I42) -> 1617407.2 | T42: =IF(C42="FY2026", (Scenarios!D10+Scenarios!E10)*BaselineCalc!$B$22, 0) -> 1200000 | U42: =(R42+S42+G42*F42)*J42*(1-K42) -> 4049279 | V42: =O42*(G42+P42) -> 47638.236 | W42: =U42+V42+IF(Parameters_Public!$C$26=1, T42, 0) -> 4096917.2 | X42: =IF(F42+O42>0, W42/(F42+O42),"") -> 13546.887 | Y42: =INDEX(YearMap!$I$2:$I$6, MATCH(C42, YearMap!$A$2:$A$6, 0)) -> 5013 | Z42: =W42 - ((Y42 + IF(Parameters_Public!$C$20=1, Parameters_Public!$C$19, 0))*AC42) -> 2353452.2 | AA42: =IF($AC42>0, $Z42/$AC42, 0) -> 7781.9367 | AB42: =MAX(0, (MAX(0, $D42-BaselineCalc!$B$7) + MAX(0, $E42-BaselineCalc!$B$8))) -> 0 | AC42: =IF(LEFT($B42,2)="A_", $O42, IF(LEFT($B42,2)="B_", $M42+$O42, IF(LEFT($B42,2)="C_", $L42+$O42, $F42))) -> 302.425 | AD42: =((Y42 + IF(Parameters_Public!$C$20=1, INDEX(YearMap!$O$2:$O$6, MATCH(C42, YearMap!$A$2:$A$6, 0)), 0))*AC42) + AC42*INDEX(YearMap!$P$2:$P$6, MATCH(C42, YearMap!$A$2:$A$6, 0)) -> 3316075 | AE42: =W42 - (1-Parameters_Public!$C42)*$G42*$AB42*$J42*(1-$K42) -> 4096917.2 | AF42: =AD42-AE42 -> -780842.21 | AG42: =B42&"|"&C42 -> B_Repurpose_Echo_lease_PimaTargets|FY2026
A43: =AG43 -> B_Repurpose_Echo_lease_PimaTargets|FY2027 | B43: =Scenarios!A10 -> B_Repurpose_Echo_lease_PimaTargets | C43: FY2027 | D43: =IF(Scenarios!D10=1,0, L43) -> 0 | E43: =IF(Scenarios!E10=1,0, M43) -> 296 | F43: =D43+E43 -> 296 | G43: =YearMap!B3 -> 6574.8743 | H43: =YearMap!C3 -> 1439410.4 | I43: =YearMap!D3 -> 1657842.4 | J43: =1-BaselineCalc!$B$5 -> 0.993 | K43: =Scenarios!G10 -> 0 | L43: =IF(Scenarios!$Q10=1,BaselineCalc!$B$7*(1+Parameters_Public!$C44)^(IF($C43="FY2026",0,IF($C43="FY2027",1,IF($C43="FY2028",2,IF($C43="FY2029",3,IF($C43="FY2030",4,0))))))+ROUND(Scenarios!J10*Scenarios!$F10,0),BaselineCalc!$B$7+ROUND(Scenarios!J10*Scenarios!$F10,0)) -> 257 | M43: =IF(Scenarios!$R10=1,BaselineCalc!$B$8*(1+Parameters_Public!$C45)^(IF($C43="FY2026",0,IF($C43="FY2027",1,IF($C43="FY2028",2,IF($C43="FY2029",3,IF($C43="FY2030",4,0))))))+Scenarios!J10-ROUND(Scenarios!J10*Scenarios!$F10,0),BaselineCalc!$B$8+Scenarios!J10-ROUND(Scenarios!J10*Scenarios!$F10,0)) -> 296 | N43: =(L43-D43) + (M43-E43) -> 257 | O43: =(Parameters_Public!$C$22*(L43-D43)+Parameters_Public!$C$23*(M43-E43)) -> 6.425 | P43: =YearMap!E3 -> 800 | Q43: =IF(Scenarios!N10="lease", YearMap!F3, YearMap!G3) -> 0.3 | R43: =IF(Scenarios!D10=1, Q43*H43, H43) -> 431823.13 | S43: =IF(Scenarios!E10=1, Q43*I43, I43) -> 1657842.4 | T43: =IF(C43="FY2026", (Scenarios!D10+Scenarios!E10)*BaselineCalc!$B$22, 0) -> 0 | U43: =(R43+S43+G43*F43)*J43*(1-K43) -> 4007577.5 | V43: =O43*(G43+P43) -> 47383.567 | W43: =U43+V43+IF(Parameters_Public!$C$26=1, T43, 0) -> 4054961.1 | X43: =IF(F43+O43>0, W43/(F43+O43),"") -> 13408.154 | Y43: =INDEX(YearMap!$I$2:$I$6, MATCH(C43, YearMap!$A$2:$A$6, 0)) -> 5138.325 | Z43: =W43 - ((Y43 + IF(Parameters_Public!$C$20=1, Parameters_Public!$C$19, 0))*AC43) -> 2273594.6 | AA43: =IF($AC43>0, $Z43/$AC43, 0) -> 7517.8793 | AB43: =MAX(0, (MAX(0, $D43-BaselineCalc!$B$7) + MAX(0, $E43-BaselineCalc!$B$8))) -> 0 | AC43: =IF(LEFT($B43,2)="A_", $O43, IF(LEFT($B43,2)="B_", $M43+$O43, IF(LEFT($B43,2)="C_", $L43+$O43, $F43))) -> 302.425 | AD43: =((Y43 + IF(Parameters_Public!$C$20=1, INDEX(YearMap!$O$2:$O$6, MATCH(C43, YearMap!$A$2:$A$6, 0)), 0))*AC43) + AC43*INDEX(YearMap!$P$2:$P$6, MATCH(C43, YearMap!$A$2:$A$6, 0)) -> 3398976.9 | AE43: =W43 - (1-Parameters_Public!$C42)*$G43*$AB43*$J43*(1-$K43) -> 4054961.1 | AF43: =AD43-AE43 -> -655984.19 | AG43: =B43&"|"&C43 -> B_Repurpose_Echo_lease_PimaTargets|FY2027
A44: =AG44 -> B_Repurpose_Echo_lease_PimaTargets|FY2028 | B44: =Scenarios!A10 -> B_Repurpose_Echo_lease_PimaTargets | C44: FY2028 | D44: =IF(Scenarios!D10=1,0, L44) -> 0 | E44: =IF(Scenarios!E10=1,0, M44) -> 296 | F44: =D44+E44 -> 296 | G44: =YearMap!B4 -> 6739.2461 | H44: =YearMap!C4 -> 1475395.7 | I44: =YearMap!D4 -> 1699288.4 | J44: =1-BaselineCalc!$B$5 -> 0.993 | K44: =Scenarios!G10 -> 0 | L44: =IF(Scenarios!$Q10=1,BaselineCalc!$B$7*(1+Parameters_Public!$C44)^(IF($C44="FY2026",0,IF($C44="FY2027",1,IF($C44="FY2028",2,IF($C44="FY2029",3,IF($C44="FY2030",4,0))))))+ROUND(Scenarios!K10*Scenarios!$F10,0),BaselineCalc!$B$7+ROUND(Scenarios!K10*Scenarios!$F10,0)) -> 257 | M44: =IF(Scenarios!$R10=1,BaselineCalc!$B$8*(1+Parameters_Public!$C45)^(IF($C44="FY2026",0,IF($C44="FY2027",1,IF($C44="FY2028",2,IF($C44="FY2029",3,IF($C44="FY2030",4,0))))))+Scenarios!K10-ROUND(Scenarios!K10*Scenarios!$F10,0),BaselineCalc!$B$8+Scenarios!K10-ROUND(Scenarios!K10*Scenarios!$F10,0)) -> 296 | N44: =(L44-D44) + (M44-E44) -> 257 | O44: =(Parameters_Public!$C$22*(L44-D44)+Parameters_Public!$C$23*(M44-E44)) -> 6.425 | P44: =YearMap!E4 -> 600 | Q44: =IF(Scenarios!N10="lease", YearMap!F4, YearMap!G4) -> 0.2 | R44: =IF(Scenarios!D10=1, Q44*H44, H44) -> 295079.14 | S44: =IF(Scenarios!E10=1, Q44*I44, I44) -> 1699288.4 | T44: =IF(C44="FY2026", (Scenarios!D10+Scenarios!E10)*BaselineCalc!$B$22, 0) -> 0 | U44: =(R44+S44+G44*F44)*J44*(1-K44) -> 3961260.1 | V44: =O44*(G44+P44) -> 47154.656 | W44: =U44+V44+IF(Parameters_Public!$C$26=1, T44, 0) -> 4008414.8 | X44: =IF(F44+O44>0, W44/(F44+O44),"") -> 13254.244 | Y44: =INDEX(YearMap!$I$2:$I$6, MATCH(C44, YearMap!$A$2:$A$6, 0)) -> 5266.7831 | Z44: =W44 - ((Y44 + IF(Parameters_Public!$C$20=1, Parameters_Public!$C$19, 0))*AC44) -> 2188199.4 | AA44: =IF($AC44>0, $Z44/$AC44, 0) -> 7235.5111 | AB44: =MAX(0, (MAX(0, $D44-BaselineCalc!$B$7) + MAX(0, $E44-BaselineCalc!$B$8))) -> 0 | AC44: =IF(LEFT($B44,2)="A_", $O44, IF(LEFT($B44,2)="B_", $M44+$O44, IF(LEFT($B44,2)="C_", $L44+$O44, $F44))) -> 302.425 | AD44: =((Y44 + IF(Parameters_Public!$C$20=1, INDEX(YearMap!$O$2:$O$6, MATCH(C44, YearMap!$A$2:$A$6, 0)), 0))*AC44) + AC44*INDEX(YearMap!$P$2:$P$6, MATCH(C44, YearMap!$A$2:$A$6, 0)) -> 3483951.3 | AE44: =W44 - (1-Parameters_Public!$C42)*$G44*$AB44*$J44*(1-$K44) -> 4008414.8 | AF44: =AD44-AE44 -> -524463.5 | AG44: =B44&"|"&C44 -> B_Repurpose_Echo_lease_PimaTargets|FY2028
A45: =AG45 -> B_Repurpose_Echo_lease_PimaTargets|FY2029 | B45: =Scenarios!A10 -> B_Repurpose_Echo_lease_PimaTargets | C45: FY2029 | D45: =IF(Scenarios!D10=1,0, L45) -> 0 | E45: =IF(Scenarios!E10=1,0, M45) -> 296 | F45: =D45+E45 -> 296 | G45: =YearMap!B5 -> 6907.7273 | H45: =YearMap!C5 -> 1512280.6 | I45: =YearMap!D5 -> 1741770.6 | J45: =1-BaselineCalc!$B$5 -> 0.993 | K45: =Scenarios!G10 -> 0 | L45: =IF(Scenarios!$Q10=1,BaselineCalc!$B$7*(1+Parameters_Public!$C44)^(IF($C45="FY2026",0,IF($C45="FY2027",1,IF($C45="FY2028",2,IF($C45="FY2029",3,IF($C45="FY2030",4,0))))))+ROUND(Scenarios!L10*Scenarios!$F10,0),BaselineCalc!$B$7+ROUND(Scenarios!L10*Scenarios!$F10,0)) -> 257 | M45: =IF(Scenarios!$R10=1,BaselineCalc!$B$8*(1+Parameters_Public!$C45)^(IF($C45="FY2026",0,IF($C45="FY2027",1,IF($C45="FY2028",2,IF($C45="FY2029",3,IF($C45="FY2030",4,0))))))+Scenarios!L10-ROUND(Scenarios!L10*Scenarios!$F10,0),BaselineCalc!$B$8+Scenarios!L10-ROUND(Scenarios!L10*Scenarios!$F10,0)) -> 296 | N45: =(L45-D45) + (M45-E45) -> 257 | O45: =(Parameters_Public!$C$22*(L45-D45)+Parameters_Public!$C$23*(M45-E45)) -> 6.425 | P45: =YearMap!E5 -> 500 | Q45: =IF(Scenarios!N10="lease", YearMap!F5, YearMap!G5) -> 0.1 | R45: =IF(Scenarios!D10=1, Q45*H45, H45) -> 151228.06 | S45: =IF(Scenarios!E10=1, Q45*I45, I45) -> 1741770.6 | T45: =IF(C45="FY2026", (Scenarios!D10+Scenarios!E10)*BaselineCalc!$B$22, 0) -> 0 | U45: =(R45+S45+G45*F45)*J45*(1-K45) -> 3910122.2 | V45: =O45*(G45+P45) -> 47594.648 | W45: =U45+V45+IF(Parameters_Public!$C$26=1, T45, 0) -> 3957716.8 | X45: =IF(F45+O45>0, W45/(F45+O45),"") -> 13086.606 | Y45: =INDEX(YearMap!$I$2:$I$6, MATCH(C45, YearMap!$A$2:$A$6, 0)) -> 5398.4527 | Z45: =W45 - ((Y45 + IF(Parameters_Public!$C$20=1, Parameters_Public!$C$19, 0))*AC45) -> 2097681.3 | AA45: =IF($AC45>0, $Z45/$AC45, 0) -> 6936.2033 | AB45: =MAX(0, (MAX(0, $D45-BaselineCalc!$B$7) + MAX(0, $E45-BaselineCalc!$B$8))) -> 0 | AC45: =IF(LEFT($B45,2)="A_", $O45, IF(LEFT($B45,2)="B_", $M45+$O45, IF(LEFT($B45,2)="C_", $L45+$O45, $F45))) -> 302.425 | AD45: =((Y45 + IF(Parameters_Public!$C$20=1, INDEX(YearMap!$O$2:$O$6, MATCH(C45, YearMap!$A$2:$A$6, 0)), 0))*AC45) + AC45*INDEX(YearMap!$P$2:$P$6, MATCH(C45, YearMap!$A$2:$A$6, 0)) -> 3571050.1 | AE45: =W45 - (1-Parameters_Public!$C42)*$G45*$AB45*$J45*(1-$K45) -> 3957716.8 | AF45: =AD45-AE45 -> -386666.75 | AG45: =B45&"|"&C45 -> B_Repurpose_Echo_lease_PimaTargets|FY2029
A46: =AG46 -> B_Repurpose_Echo_lease_PimaTargets|FY2030 | B46: =Scenarios!A10 -> B_Repurpose_Echo_lease_PimaTargets | C46: FY2030 | D46: =IF(Scenarios!D10=1,0, L46) -> 0 | E46: =IF(Scenarios!E10=1,0, M46) -> 296 | F46: =D46+E46 -> 296 | G46: =YearMap!B6 -> 7080.4205 | H46: =YearMap!C6 -> 1550087.6 | I46: =YearMap!D6 -> 1785314.9 | J46: =1-BaselineCalc!$B$5 -> 0.993 | K46: =Scenarios!G10 -> 0 | L46: =IF(Scenarios!$Q10=1,BaselineCalc!$B$7*(1+Parameters_Public!$C44)^(IF($C46="FY2026",0,IF($C46="FY2027",1,IF($C46="FY2028",2,IF($C46="FY2029",3,IF($C46="FY2030",4,0))))))+ROUND(Scenarios!M10*Scenarios!$F10,0),BaselineCalc!$B$7+ROUND(Scenarios!M10*Scenarios!$F10,0)) -> 257 | M46: =IF(Scenarios!$R10=1,BaselineCalc!$B$8*(1+Parameters_Public!$C45)^(IF($C46="FY2026",0,IF($C46="FY2027",1,IF($C46="FY2028",2,IF($C46="FY2029",3,IF($C46="FY2030",4,0))))))+Scenarios!M10-ROUND(Scenarios!M10*Scenarios!$F10,0),BaselineCalc!$B$8+Scenarios!M10-ROUND(Scenarios!M10*Scenarios!$F10,0)) -> 296 | N46: =(L46-D46) + (M46-E46) -> 257 | O46: =(Parameters_Public!$C$22*(L46-D46)+Parameters_Public!$C$23*(M46-E46)) -> 6.425 | P46: =YearMap!E6 -> 300 | Q46: =IF(Scenarios!N10="lease", YearMap!F6, YearMap!G6) -> 0.1 | R46: =IF(Scenarios!D10=1, Q46*H46, H46) -> 155008.76 | S46: =IF(Scenarios!E10=1, Q46*I46, I46) -> 1785314.9 | T46: =IF(C46="FY2026", (Scenarios!D10+Scenarios!E10)*BaselineCalc!$B$22, 0) -> 0 | U46: =(R46+S46+G46*F46)*J46*(1-K46) -> 4007875.2 | V46: =O46*(G46+P46) -> 47419.202 | W46: =U46+V46+IF(Parameters_Public!$C$26=1, T46, 0) -> 4055294.4 | X46: =IF(F46+O46>0, W46/(F46+O46),"") -> 13409.257 | Y46: =INDEX(YearMap!$I$2:$I$6, MATCH(C46, YearMap!$A$2:$A$6, 0)) -> 5533.414 | Z46: =W46 - ((Y46 + IF(Parameters_Public!$C$20=1, Parameters_Public!$C$19, 0))*AC46) -> 2154443.2 | AA46: =IF($AC46>0, $Z46/$AC46, 0) -> 7123.8926 | AB46: =MAX(0, (MAX(0, $D46-BaselineCalc!$B$7) + MAX(0, $E46-BaselineCalc!$B$8))) -> 0 | AC46: =IF(LEFT($B46,2)="A_", $O46, IF(LEFT($B46,2)="B_", $M46+$O46, IF(LEFT($B46,2)="C_", $L46+$O46, $F46))) -> 302.425 | AD46: =((Y46 + IF(Parameters_Public!$C$20=1, INDEX(YearMap!$O$2:$O$6, MATCH(C46, YearMap!$A$2:$A$6, 0)), 0))*AC46) + AC46*INDEX(YearMap!$P$2:$P$6, MATCH(C46, YearMap!$A$2:$A$6, 0)) -> 3660326.3 | AE46: =W46 - (1-Parameters_Public!$C42)*$G46*$AB46*$J46*(1-$K46) -> 4055294.4 | AF46: =AD46-AE46 -> -394968.1 | AG46: =B46&"|"&C46 -> B_Repurpose_Echo_lease_PimaTargets|FY2030
A47: =AG47 -> B_Repurpose_Echo_ops_PimaTargets|FY2026 | B47: =Scenarios!A11 -> B_Repurpose_Echo_ops_PimaTargets | C47: FY2026 | D47: =IF(Scenarios!D11=1,0, L47) -> 0 | E47: =IF(Scenarios!E11=1,0, M47) -> 312.66667 | F47: =D47+E47 -> 312.66667 | G47: =YearMap!B2 -> 6414.5115 | H47: =YearMap!C2 -> 1404302.9 | I47: =YearMap!D2 -> 1617407.2 | J47: =1-BaselineCalc!$B$5 -> 0.993 | K47: =Scenarios!G11 -> 0 | L47: =IF(Scenarios!$Q11=1,BaselineCalc!$B$7*(1+Parameters_Public!$C44)^(IF($C47="FY2026",0,IF($C47="FY2027",1,IF($C47="FY2028",2,IF($C47="FY2029",3,IF($C47="FY2030",4,0))))))+ROUND(Scenarios!I11*Scenarios!$F11,0),BaselineCalc!$B$7+ROUND(Scenarios!I11*Scenarios!$F11,0)) -> 257 | M47: =IF(Scenarios!$R11=1,BaselineCalc!$B$8*(1+Parameters_Public!$C45)^(IF($C47="FY2026",0,IF($C47="FY2027",1,IF($C47="FY2028",2,IF($C47="FY2029",3,IF($C47="FY2030",4,0))))))+Scenarios!I11-ROUND(Scenarios!I11*Scenarios!$F11,0),BaselineCalc!$B$8+Scenarios!I11-ROUND(Scenarios!I11*Scenarios!$F11,0)) -> 312.66667 | N47: =(L47-D47) + (M47-E47) -> 257 | O47: =(Parameters_Public!$C$22*(L47-D47)+Parameters_Public!$C$23*(M47-E47)) -> 6.425 | P47: =YearMap!E2 -> 1000 | Q47: =IF(Scenarios!N11="lease", YearMap!F2, YearMap!G2) -> 0.5 | R47: =IF(Scenarios!D11=1, Q47*H47, H47) -> 702151.43 | S47: =IF(Scenarios!E11=1, Q47*I47, I47) -> 1617407.2 | T47: =IF(C47="FY2026", (Scenarios!D11+Scenarios!E11)*BaselineCalc!$B$22, 0) -> 1200000 | U47: =(R47+S47+G47*F47)*J47*(1-K47) -> 4294886.4 | V47: =O47*(G47+P47) -> 47638.236 | W47: =U47+V47+IF(Parameters_Public!$C$26=1, T47, 0) -> 4342524.7 | X47: =IF(F47+O47>0, W47/(F47+O47),"") -> 13609.019 | Y47: =INDEX(YearMap!$I$2:$I$6, MATCH(C47, YearMap!$A$2:$A$6, 0)) -> 5013 | Z47: =W47 - ((Y47 + IF(Parameters_Public!$C$20=1, Parameters_Public!$C$19, 0))*AC47) -> 2502977.2 | AA47: =IF($AC47>0, $Z47/$AC47, 0) -> 7844.0693 | AB47: =MAX(0, (MAX(0, $D47-BaselineCalc!$B$7) + MAX(0, $E47-BaselineCalc!$B$8))) -> 16.666667 | AC47: =IF(LEFT($B47,2)="A_", $O47, IF(LEFT($B47,2)="B_", $M47+$O47, IF(LEFT($B47,2)="C_", $L47+$O47, $F47))) -> 319.09167 | AD47: =((Y47 + IF(Parameters_Public!$C$20=1, INDEX(YearMap!$O$2:$O$6, MATCH(C47, YearMap!$A$2:$A$6, 0)), 0))*AC47) + AC47*INDEX(YearMap!$P$2:$P$6, MATCH(C47, YearMap!$A$2:$A$6, 0)) -> 3498824.2 | AE47: =W47 - (1-Parameters_Public!$C42)*$G47*$AB47*$J47*(1-$K47) -> 4236364.5 | AF47: =AD47-AE47 -> -737540.32 | AG47: =B47&"|"&C47 -> B_Repurpose_Echo_ops_PimaTargets|FY2026
A48: =AG48 -> B_Repurpose_Echo_ops_PimaTargets|FY2027 | B48: =Scenarios!A11 -> B_Repurpose_Echo_ops_PimaTargets | C48: FY2027 | D48: =IF(Scenarios!D11=1,0, L48) -> 0 | E48: =IF(Scenarios!E11=1,0, M48) -> 329.33333 | F48: =D48+E48 -> 329.33333 | G48: =YearMap!B3 -> 6574.8743 | H48: =YearMap!C3 -> 1439410.4 | I48: =YearMap!D3 -> 1657842.4 | J48: =1-BaselineCalc!$B$5 -> 0.993 | K48: =Scenarios!G11 -> 0 | L48: =IF(Scenarios!$Q11=1,BaselineCalc!$B$7*(1+Parameters_Public!$C44)^(IF($C48="FY2026",0,IF($C48="FY2027",1,IF($C48="FY2028",2,IF($C48="FY2029",3,IF($C48="FY2030",4,0))))))+ROUND(Scenarios!J11*Scenarios!$F11,0),BaselineCalc!$B$7+ROUND(Scenarios!J11*Scenarios!$F11,0)) -> 257 | M48: =IF(Scenarios!$R11=1,BaselineCalc!$B$8*(1+Parameters_Public!$C45)^(IF($C48="FY2026",0,IF($C48="FY2027",1,IF($C48="FY2028",2,IF($C48="FY2029",3,IF($C48="FY2030",4,0))))))+Scenarios!J11-ROUND(Scenarios!J11*Scenarios!$F11,0),BaselineCalc!$B$8+Scenarios!J11-ROUND(Scenarios!J11*Scenarios!$F11,0)) -> 329.33333 | N48: =(L48-D48) + (M48-E48) -> 257 | O48: =(Parameters_Public!$C$22*(L48-D48)+Parameters_Public!$C$23*(M48-E48)) -> 6.425 | P48: =YearMap!E3 -> 800 | Q48: =IF(Scenarios!N11="lease", YearMap!F3, YearMap!G3) -> 0.4 | R48: =IF(Scenarios!D11=1, Q48*H48, H48) -> 575764.18 | S48: =IF(Scenarios!E11=1, Q48*I48, I48) -> 1657842.4 | T48: =IF(C48="FY2026", (Scenarios!D11+Scenarios!E11)*BaselineCalc!$B$22, 0) -> 0 | U48: =(R48+S48+G48*F48)*J48*(1-K48) -> 4368139.3 | V48: =O48*(G48+P48) -> 47383.567 | W48: =U48+V48+IF(Parameters_Public!$C$26=1, T48, 0) -> 4415522.9 | X48: =IF(F48+O48>0, W48/(F48+O48),"") -> 13150.896 | Y48: =INDEX(YearMap!$I$2:$I$6, MATCH(C48, YearMap!$A$2:$A$6, 0)) -> 5138.325 | Z48: =W48 - ((Y48 + IF(Parameters_Public!$C$20=1, Parameters_Public!$C$19, 0))*AC48) -> 2437813.9 | AA48: =IF($AC48>0, $Z48/$AC48, 0) -> 7260.6208 | AB48: =MAX(0, (MAX(0, $D48-BaselineCalc!$B$7) + MAX(0, $E48-BaselineCalc!$B$8))) -> 33.333333 | AC48: =IF(LEFT($B48,2)="A_", $O48, IF(LEFT($B48,2)="B_", $M48+$O48, IF(LEFT($B48,2)="C_", $L48+$O48, $F48))) -> 335.75833 | AD48: =((Y48 + IF(Parameters_Public!$C$20=1, INDEX(YearMap!$O$2:$O$6, MATCH(C48, YearMap!$A$2:$A$6, 0)), 0))*AC48) + AC48*INDEX(YearMap!$P$2:$P$6, MATCH(C48, YearMap!$A$2:$A$6, 0)) -> 3773612.7 | AE48: =W48 - (1-Parameters_Public!$C42)*$G48*$AB48*$J48*(1-$K48) -> 4197894.5 | AF48: =AD48-AE48 -> -424281.85 | AG48: =B48&"|"&C48 -> B_Repurpose_Echo_ops_PimaTargets|FY2027
A49: =AG49 -> B_Repurpose_Echo_ops_PimaTargets|FY2028 | B49: =Scenarios!A11 -> B_Repurpose_Echo_ops_PimaTargets | C49: FY2028 | D49: =IF(Scenarios!D11=1,0, L49) -> 0 | E49: =IF(Scenarios!E11=1,0, M49) -> 346 | F49: =D49+E49 -> 346 | G49: =YearMap!B4 -> 6739.2461 | H49: =YearMap!C4 -> 1475395.7 | I49: =YearMap!D4 -> 1699288.4 | J49: =1-BaselineCalc!$B$5 -> 0.993 | K49: =Scenarios!G11 -> 0 | L49: =IF(Scenarios!$Q11=1,BaselineCalc!$B$7*(1+Parameters_Public!$C44)^(IF($C49="FY2026",0,IF($C49="FY2027",1,IF($C49="FY2028",2,IF($C49="FY2029",3,IF($C49="FY2030",4,0))))))+ROUND(Scenarios!K11*Scenarios!$F11,0),BaselineCalc!$B$7+ROUND(Scenarios!K11*Scenarios!$F11,0)) -> 257 | M49: =IF(Scenarios!$R11=1,BaselineCalc!$B$8*(1+Parameters_Public!$C45)^(IF($C49="FY2026",0,IF($C49="FY2027",1,IF($C49="FY2028",2,IF($C49="FY2029",3,IF($C49="FY2030",4,0))))))+Scenarios!K11-ROUND(Scenarios!K11*Scenarios!$F11,0),BaselineCalc!$B$8+Scenarios!K11-ROUND(Scenarios!K11*Scenarios!$F11,0)) -> 346 | N49: =(L49-D49) + (M49-E49) -> 257 | O49: =(Parameters_Public!$C$22*(L49-D49)+Parameters_Public!$C$23*(M49-E49)) -> 6.425 | P49: =YearMap!E4 -> 600 | Q49: =IF(Scenarios!N11="lease", YearMap!F4, YearMap!G4) -> 0.35 | R49: =IF(Scenarios!D11=1, Q49*H49, H49) -> 516388.5 | S49: =IF(Scenarios!E11=1, Q49*I49, I49) -> 1699288.4 | T49: =IF(C49="FY2026", (Scenarios!D11+Scenarios!E11)*BaselineCalc!$B$22, 0) -> 0 | U49: =(R49+S49+G49*F49)*J49*(1-K49) -> 4515623.9 | V49: =O49*(G49+P49) -> 47154.656 | W49: =U49+V49+IF(Parameters_Public!$C$26=1, T49, 0) -> 4562778.6 | X49: =IF(F49+O49>0, W49/(F49+O49),"") -> 12946.807 | Y49: =INDEX(YearMap!$I$2:$I$6, MATCH(C49, YearMap!$A$2:$A$6, 0)) -> 5266.7831 | Z49: =W49 - ((Y49 + IF(Parameters_Public!$C$20=1, Parameters_Public!$C$19, 0))*AC49) -> 2441626.5 | AA49: =IF($AC49>0, $Z49/$AC49, 0) -> 6928.0742 | AB49: =MAX(0, (MAX(0, $D49-BaselineCalc!$B$7) + MAX(0, $E49-BaselineCalc!$B$8))) -> 50 | AC49: =IF(LEFT($B49,2)="A_", $O49, IF(LEFT($B49,2)="B_", $M49+$O49, IF(LEFT($B49,2)="C_", $L49+$O49, $F49))) -> 352.425 | AD49: =((Y49 + IF(Parameters_Public!$C$20=1, INDEX(YearMap!$O$2:$O$6, MATCH(C49, YearMap!$A$2:$A$6, 0)), 0))*AC49) + AC49*INDEX(YearMap!$P$2:$P$6, MATCH(C49, YearMap!$A$2:$A$6, 0)) -> 4059953.8 | AE49: =W49 - (1-Parameters_Public!$C42)*$G49*$AB49*$J49*(1-$K49) -> 4228175 | AF49: =AD49-AE49 -> -168221.16 | AG49: =B49&"|"&C49 -> B_Repurpose_Echo_ops_PimaTargets|FY2028
A50: =AG50 -> B_Repurpose_Echo_ops_PimaTargets|FY2029 | B50: =Scenarios!A11 -> B_Repurpose_Echo_ops_PimaTargets | C50: FY2029 | D50: =IF(Scenarios!D11=1,0, L50) -> 0 | E50: =IF(Scenarios!E11=1,0, M50) -> 346 | F50: =D50+E50 -> 346 | G50: =YearMap!B5 -> 6907.7273 | H50: =YearMap!C5 -> 1512280.6 | I50: =YearMap!D5 -> 1741770.6 | J50: =1-BaselineCalc!$B$5 -> 0.993 | K50: =Scenarios!G11 -> 0 | L50: =IF(Scenarios!$Q11=1,BaselineCalc!$B$7*(1+Parameters_Public!$C44)^(IF($C50="FY2026",0,IF($C50="FY2027",1,IF($C50="FY2028",2,IF($C50="FY2029",3,IF($C50="FY2030",4,0))))))+ROUND(Scenarios!L11*Scenarios!$F11,0),BaselineCalc!$B$7+ROUND(Scenarios!L11*Scenarios!$F11,0)) -> 257 | M50: =IF(Scenarios!$R11=1,BaselineCalc!$B$8*(1+Parameters_Public!$C45)^(IF($C50="FY2026",0,IF($C50="FY2027",1,IF($C50="FY2028",2,IF($C50="FY2029",3,IF($C50="FY2030",4,0))))))+Scenarios!L11-ROUND(Scenarios!L11*Scenarios!$F11,0),BaselineCalc!$B$8+Scenarios!L11-ROUND(Scenarios!L11*Scenarios!$F11,0)) -> 346 | N50: =(L50-D50) + (M50-E50) -> 257 | O50: =(Parameters_Public!$C$22*(L50-D50)+Parameters_Public!$C$23*(M50-E50)) -> 6.425 | P50: =YearMap!E5 -> 500 | Q50: =IF(Scenarios!N11="lease", YearMap!F5, YearMap!G5) -> 0.3 | R50: =IF(Scenarios!D11=1, Q50*H50, H50) -> 453684.18 | S50: =IF(Scenarios!E11=1, Q50*I50, I50) -> 1741770.6 | T50: =IF(C50="FY2026", (Scenarios!D11+Scenarios!E11)*BaselineCalc!$B$22, 0) -> 0 | U50: =(R50+S50+G50*F50)*J50*(1-K50) -> 4553429.8 | V50: =O50*(G50+P50) -> 47594.648 | W50: =U50+V50+IF(Parameters_Public!$C$26=1, T50, 0) -> 4601024.4 | X50: =IF(F50+O50>0, W50/(F50+O50),"") -> 13055.329 | Y50: =INDEX(YearMap!$I$2:$I$6, MATCH(C50, YearMap!$A$2:$A$6, 0)) -> 5398.4527 | Z50: =W50 - ((Y50 + IF(Parameters_Public!$C$20=1, Parameters_Public!$C$19, 0))*AC50) -> 2433468.7 | AA50: =IF($AC50>0, $Z50/$AC50, 0) -> 6904.9266 | AB50: =MAX(0, (MAX(0, $D50-BaselineCalc!$B$7) + MAX(0, $E50-BaselineCalc!$B$8))) -> 50 | AC50: =IF(LEFT($B50,2)="A_", $O50, IF(LEFT($B50,2)="B_", $M50+$O50, IF(LEFT($B50,2)="C_", $L50+$O50, $F50))) -> 352.425 | AD50: =((Y50 + IF(Parameters_Public!$C$20=1, INDEX(YearMap!$O$2:$O$6, MATCH(C50, YearMap!$A$2:$A$6, 0)), 0))*AC50) + AC50*INDEX(YearMap!$P$2:$P$6, MATCH(C50, YearMap!$A$2:$A$6, 0)) -> 4161452.7 | AE50: =W50 - (1-Parameters_Public!$C42)*$G50*$AB50*$J50*(1-$K50) -> 4258055.8 | AF50: =AD50-AE50 -> -96603.082 | AG50: =B50&"|"&C50 -> B_Repurpose_Echo_ops_PimaTargets|FY2029
A51: =AG51 -> B_Repurpose_Echo_ops_PimaTargets|FY2030 | B51: =Scenarios!A11 -> B_Repurpose_Echo_ops_PimaTargets | C51: FY2030 | D51: =IF(Scenarios!D11=1,0, L51) -> 0 | E51: =IF(Scenarios!E11=1,0, M51) -> 346 | F51: =D51+E51 -> 346 | G51: =YearMap!B6 -> 7080.4205 | H51: =YearMap!C6 -> 1550087.6 | I51: =YearMap!D6 -> 1785314.9 | J51: =1-BaselineCalc!$B$5 -> 0.993 | K51: =Scenarios!G11 -> 0 | L51: =IF(Scenarios!$Q11=1,BaselineCalc!$B$7*(1+Parameters_Public!$C44)^(IF($C51="FY2026",0,IF($C51="FY2027",1,IF($C51="FY2028",2,IF($C51="FY2029",3,IF($C51="FY2030",4,0))))))+ROUND(Scenarios!M11*Scenarios!$F11,0),BaselineCalc!$B$7+ROUND(Scenarios!M11*Scenarios!$F11,0)) -> 257 | M51: =IF(Scenarios!$R11=1,BaselineCalc!$B$8*(1+Parameters_Public!$C45)^(IF($C51="FY2026",0,IF($C51="FY2027",1,IF($C51="FY2028",2,IF($C51="FY2029",3,IF($C51="FY2030",4,0))))))+Scenarios!M11-ROUND(Scenarios!M11*Scenarios!$F11,0),BaselineCalc!$B$8+Scenarios!M11-ROUND(Scenarios!M11*Scenarios!$F11,0)) -> 346 | N51: =(L51-D51) + (M51-E51) -> 257 | O51: =(Parameters_Public!$C$22*(L51-D51)+Parameters_Public!$C$23*(M51-E51)) -> 6.425 | P51: =YearMap!E6 -> 300 | Q51: =IF(Scenarios!N11="lease", YearMap!F6, YearMap!G6) -> 0.3 | R51: =IF(Scenarios!D11=1, Q51*H51, H51) -> 465026.28 | S51: =IF(Scenarios!E11=1, Q51*I51, I51) -> 1785314.9 | T51: =IF(C51="FY2026", (Scenarios!D11+Scenarios!E11)*BaselineCalc!$B$22, 0) -> 0 | U51: =(R51+S51+G51*F51)*J51*(1-K51) -> 4667265.5 | V51: =O51*(G51+P51) -> 47419.202 | W51: =U51+V51+IF(Parameters_Public!$C$26=1, T51, 0) -> 4714684.7 | X51: =IF(F51+O51>0, W51/(F51+O51),"") -> 13377.838 | Y51: =INDEX(YearMap!$I$2:$I$6, MATCH(C51, YearMap!$A$2:$A$6, 0)) -> 5533.414 | Z51: =W51 - ((Y51 + IF(Parameters_Public!$C$20=1, Parameters_Public!$C$19, 0))*AC51) -> 2499565.3 | AA51: =IF($AC51>0, $Z51/$AC51, 0) -> 7092.4744 | AB51: =MAX(0, (MAX(0, $D51-BaselineCalc!$B$7) + MAX(0, $E51-BaselineCalc!$B$8))) -> 50 | AC51: =IF(LEFT($B51,2)="A_", $O51, IF(LEFT($B51,2)="B_", $M51+$O51, IF(LEFT($B51,2)="C_", $L51+$O51, $F51))) -> 352.425 | AD51: =((Y51 + IF(Parameters_Public!$C$20=1, INDEX(YearMap!$O$2:$O$6, MATCH(C51, YearMap!$A$2:$A$6, 0)), 0))*AC51) + AC51*INDEX(YearMap!$P$2:$P$6, MATCH(C51, YearMap!$A$2:$A$6, 0)) -> 4265489 | AE51: =W51 - (1-Parameters_Public!$C42)*$G51*$AB51*$J51*(1-$K51) -> 4363141.8 | AF51: =AD51-AE51 -> -97652.846 | AG51: =B51&"|"&C51 -> B_Repurpose_Echo_ops_PimaTargets|FY2030
A52: =AG52 -> C_Repurpose_Pima_lease_EchoGHub_EchoTargets|FY2026 | B52: =Scenarios!A12 -> C_Repurpose_Pima_lease_EchoGHub_EchoTargets | C52: FY2026 | D52: =IF(Scenarios!D12=1,0, L52) -> 257 | E52: =IF(Scenarios!E12=1,0, M52) -> 0 | F52: =D52+E52 -> 257 | G52: =YearMap!B2 -> 6414.5115 | H52: =YearMap!C2 -> 1404302.9 | I52: =YearMap!D2 -> 1617407.2 | J52: =1-BaselineCalc!$B$5 -> 0.993 | K52: =Scenarios!G12 -> 0 | L52: =IF(Scenarios!$Q12=1,BaselineCalc!$B$7*(1+Parameters_Public!$C44)^(IF($C52="FY2026",0,IF($C52="FY2027",1,IF($C52="FY2028",2,IF($C52="FY2029",3,IF($C52="FY2030",4,0))))))+ROUND(Scenarios!I12*Scenarios!$F12,0),BaselineCalc!$B$7+ROUND(Scenarios!I12*Scenarios!$F12,0)) -> 257 | M52: =IF(Scenarios!$R12=1,BaselineCalc!$B$8*(1+Parameters_Public!$C45)^(IF($C52="FY2026",0,IF($C52="FY2027",1,IF($C52="FY2028",2,IF($C52="FY2029",3,IF($C52="FY2030",4,0))))))+Scenarios!I12-ROUND(Scenarios!I12*Scenarios!$F12,0),BaselineCalc!$B$8+Scenarios!I12-ROUND(Scenarios!I12*Scenarios!$F12,0)) -> 296 | N52: =(L52-D52) + (M52-E52) -> 296 | O52: =(Parameters_Public!$C$22*(L52-D52)+Parameters_Public!$C$23*(M52-E52)) -> 177.6 | P52: =YearMap!E2 -> 1000 | Q52: =IF(Scenarios!N12="lease", YearMap!F2, YearMap!G2) -> 0.4 | R52: =IF(Scenarios!D12=1, Q52*H52, H52) -> 1404302.9 | S52: =IF(Scenarios!E12=1, Q52*I52, I52) -> 646962.88 | T52: =IF(C52="FY2026", (Scenarios!D12+Scenarios!E12)*BaselineCalc!$B$22, 0) -> 1200000 | U52: =(R52+S52+G52*F52)*J52*(1-K52) -> 3673896.6 | V52: =O52*(G52+P52) -> 1316817.2 | W52: =U52+V52+IF(Parameters_Public!$C$26=1, T52, 0) -> 4990713.9 | X52: =IF(F52+O52>0, W52/(F52+O52),"") -> 11483.465 | Y52: =INDEX(YearMap!$I$2:$I$6, MATCH(C52, YearMap!$A$2:$A$6, 0)) -> 5013 | Z52: =W52 - ((Y52 + IF(Parameters_Public!$C$20=1, Parameters_Public!$C$19, 0))*AC52) -> 2485266.6 | AA52: =IF($AC52>0, $Z52/$AC52, 0) -> 5718.515 | AB52: =MAX(0, (MAX(0, $D52-BaselineCalc!$B$7) + MAX(0, $E52-BaselineCalc!$B$8))) -> 0 | AC52: =IF(LEFT($B52,2)="A_", $O52, IF(LEFT($B52,2)="B_", $M52+$O52, IF(LEFT($B52,2)="C_", $L52+$O52, $F52))) -> 434.6 | AD52: =((Y52 + IF(Parameters_Public!$C$20=1, INDEX(YearMap!$O$2:$O$6, MATCH(C52, YearMap!$A$2:$A$6, 0)), 0))*AC52) + AC52*INDEX(YearMap!$P$2:$P$6, MATCH(C52, YearMap!$A$2:$A$6, 0)) -> 4765367.3 | AE52: =W52 - (1-Parameters_Public!$C42)*$G52*$AB52*$J52*(1-$K52) -> 4990713.9 | AF52: =AD52-AE52 -> -225346.61 | AG52: =B52&"|"&C52 -> C_Repurpose_Pima_lease_EchoGHub_EchoTargets|FY2026
A53: =AG53 -> C_Repurpose_Pima_lease_EchoGHub_EchoTargets|FY2027 | B53: =Scenarios!A12 -> C_Repurpose_Pima_lease_EchoGHub_EchoTargets | C53: FY2027 | D53: =IF(Scenarios!D12=1,0, L53) -> 257 | E53: =IF(Scenarios!E12=1,0, M53) -> 0 | F53: =D53+E53 -> 257 | G53: =YearMap!B3 -> 6574.8743 | H53: =YearMap!C3 -> 1439410.4 | I53: =YearMap!D3 -> 1657842.4 | J53: =1-BaselineCalc!$B$5 -> 0.993 | K53: =Scenarios!G12 -> 0 | L53: =IF(Scenarios!$Q12=1,BaselineCalc!$B$7*(1+Parameters_Public!$C44)^(IF($C53="FY2026",0,IF($C53="FY2027",1,IF($C53="FY2028",2,IF($C53="FY2029",3,IF($C53="FY2030",4,0))))))+ROUND(Scenarios!J12*Scenarios!$F12,0),BaselineCalc!$B$7+ROUND(Scenarios!J12*Scenarios!$F12,0)) -> 257 | M53: =IF(Scenarios!$R12=1,BaselineCalc!$B$8*(1+Parameters_Public!$C45)^(IF($C53="FY2026",0,IF($C53="FY2027",1,IF($C53="FY2028",2,IF($C53="FY2029",3,IF($C53="FY2030",4,0))))))+Scenarios!J12-ROUND(Scenarios!J12*Scenarios!$F12,0),BaselineCalc!$B$8+Scenarios!J12-ROUND(Scenarios!J12*Scenarios!$F12,0)) -> 296 | N53: =(L53-D53) + (M53-E53) -> 296 | O53: =(Parameters_Public!$C$22*(L53-D53)+Parameters_Public!$C$23*(M53-E53)) -> 177.6 | P53: =YearMap!E3 -> 800 | Q53: =IF(Scenarios!N12="lease", YearMap!F3, YearMap!G3) -> 0.3 | R53: =IF(Scenarios!D12=1, Q53*H53, H53) -> 1439410.4 | S53: =IF(Scenarios!E12=1, Q53*I53, I53) -> 497352.71 | T53: =IF(C53="FY2026", (Scenarios!D12+Scenarios!E12)*BaselineCalc!$B$22, 0) -> 0 | U53: =(R53+S53+G53*F53)*J53*(1-K53) -> 3601120.3 | V53: =O53*(G53+P53) -> 1309777.7 | W53: =U53+V53+IF(Parameters_Public!$C$26=1, T53, 0) -> 4910898 | X53: =IF(F53+O53>0, W53/(F53+O53),"") -> 11299.811 | Y53: =INDEX(YearMap!$I$2:$I$6, MATCH(C53, YearMap!$A$2:$A$6, 0)) -> 5138.325 | Z53: =W53 - ((Y53 + IF(Parameters_Public!$C$20=1, Parameters_Public!$C$19, 0))*AC53) -> 2350984.5 | AA53: =IF($AC53>0, $Z53/$AC53, 0) -> 5409.5363 | AB53: =MAX(0, (MAX(0, $D53-BaselineCalc!$B$7) + MAX(0, $E53-BaselineCalc!$B$8))) -> 0 | AC53: =IF(LEFT($B53,2)="A_", $O53, IF(LEFT($B53,2)="B_", $M53+$O53, IF(LEFT($B53,2)="C_", $L53+$O53, $F53))) -> 434.6 | AD53: =((Y53 + IF(Parameters_Public!$C$20=1, INDEX(YearMap!$O$2:$O$6, MATCH(C53, YearMap!$A$2:$A$6, 0)), 0))*AC53) + AC53*INDEX(YearMap!$P$2:$P$6, MATCH(C53, YearMap!$A$2:$A$6, 0)) -> 4884501.5 | AE53: =W53 - (1-Parameters_Public!$C42)*$G53*$AB53*$J53*(1-$K53) -> 4910898 | AF53: =AD53-AE53 -> -26396.527 | AG53: =B53&"|"&C53 -> C_Repurpose_Pima_lease_EchoGHub_EchoTargets|FY2027
A54: =AG54 -> C_Repurpose_Pima_lease_EchoGHub_EchoTargets|FY2028 | B54: =Scenarios!A12 -> C_Repurpose_Pima_lease_EchoGHub_EchoTargets | C54: FY2028 | D54: =IF(Scenarios!D12=1,0, L54) -> 257 | E54: =IF(Scenarios!E12=1,0, M54) -> 0 | F54: =D54+E54 -> 257 | G54: =YearMap!B4 -> 6739.2461 | H54: =YearMap!C4 -> 1475395.7 | I54: =YearMap!D4 -> 1699288.4 | J54: =1-BaselineCalc!$B$5 -> 0.993 | K54: =Scenarios!G12 -> 0 | L54: =IF(Scenarios!$Q12=1,BaselineCalc!$B$7*(1+Parameters_Public!$C44)^(IF($C54="FY2026",0,IF($C54="FY2027",1,IF($C54="FY2028",2,IF($C54="FY2029",3,IF($C54="FY2030",4,0))))))+ROUND(Scenarios!K12*Scenarios!$F12,0),BaselineCalc!$B$7+ROUND(Scenarios!K12*Scenarios!$F12,0)) -> 257 | M54: =IF(Scenarios!$R12=1,BaselineCalc!$B$8*(1+Parameters_Public!$C45)^(IF($C54="FY2026",0,IF($C54="FY2027",1,IF($C54="FY2028",2,IF($C54="FY2029",3,IF($C54="FY2030",4,0))))))+Scenarios!K12-ROUND(Scenarios!K12*Scenarios!$F12,0),BaselineCalc!$B$8+Scenarios!K12-ROUND(Scenarios!K12*Scenarios!$F12,0)) -> 296 | N54: =(L54-D54) + (M54-E54) -> 296 | O54: =(Parameters_Public!$C$22*(L54-D54)+Parameters_Public!$C$23*(M54-E54)) -> 177.6 | P54: =YearMap!E4 -> 600 | Q54: =IF(Scenarios!N12="lease", YearMap!F4, YearMap!G4) -> 0.2 | R54: =IF(Scenarios!D12=1, Q54*H54, H54) -> 1475395.7 | S54: =IF(Scenarios!E12=1, Q54*I54, I54) -> 339857.69 | T54: =IF(C54="FY2026", (Scenarios!D12+Scenarios!E12)*BaselineCalc!$B$22, 0) -> 0 | U54: =(R54+S54+G54*F54)*J54*(1-K54) -> 3522409 | V54: =O54*(G54+P54) -> 1303450.1 | W54: =U54+V54+IF(Parameters_Public!$C$26=1, T54, 0) -> 4825859.1 | X54: =IF(F54+O54>0, W54/(F54+O54),"") -> 11104.14 | Y54: =INDEX(YearMap!$I$2:$I$6, MATCH(C54, YearMap!$A$2:$A$6, 0)) -> 5266.7831 | Z54: =W54 - ((Y54 + IF(Parameters_Public!$C$20=1, Parameters_Public!$C$19, 0))*AC54) -> 2210117.7 | AA54: =IF($AC54>0, $Z54/$AC54, 0) -> 5085.4065 | AB54: =MAX(0, (MAX(0, $D54-BaselineCalc!$B$7) + MAX(0, $E54-BaselineCalc!$B$8))) -> 0 | AC54: =IF(LEFT($B54,2)="A_", $O54, IF(LEFT($B54,2)="B_", $M54+$O54, IF(LEFT($B54,2)="C_", $L54+$O54, $F54))) -> 434.6 | AD54: =((Y54 + IF(Parameters_Public!$C$20=1, INDEX(YearMap!$O$2:$O$6, MATCH(C54, YearMap!$A$2:$A$6, 0)), 0))*AC54) + AC54*INDEX(YearMap!$P$2:$P$6, MATCH(C54, YearMap!$A$2:$A$6, 0)) -> 5006614 | AE54: =W54 - (1-Parameters_Public!$C42)*$G54*$AB54*$J54*(1-$K54) -> 4825859.1 | AF54: =AD54-AE54 -> 180754.9 | AG54: =B54&"|"&C54 -> C_Repurpose_Pima_lease_EchoGHub_EchoTargets|FY2028
A55: =AG55 -> C_Repurpose_Pima_lease_EchoGHub_EchoTargets|FY2029 | B55: =Scenarios!A12 -> C_Repurpose_Pima_lease_EchoGHub_EchoTargets | C55: FY2029 | D55: =IF(Scenarios!D12=1,0, L55) -> 257 | E55: =IF(Scenarios!E12=1,0, M55) -> 0 | F55: =D55+E55 -> 257 | G55: =YearMap!B5 -> 6907.7273 | H55: =YearMap!C5 -> 1512280.6 | I55: =YearMap!D5 -> 1741770.6 | J55: =1-BaselineCalc!$B$5 -> 0.993 | K55: =Scenarios!G12 -> 0 | L55: =IF(Scenarios!$Q12=1,BaselineCalc!$B$7*(1+Parameters_Public!$C44)^(IF($C55="FY2026",0,IF($C55="FY2027",1,IF($C55="FY2028",2,IF($C55="FY2029",3,IF($C55="FY2030",4,0))))))+ROUND(Scenarios!L12*Scenarios!$F12,0),BaselineCalc!$B$7+ROUND(Scenarios!L12*Scenarios!$F12,0)) -> 257 | M55: =IF(Scenarios!$R12=1,BaselineCalc!$B$8*(1+Parameters_Public!$C45)^(IF($C55="FY2026",0,IF($C55="FY2027",1,IF($C55="FY2028",2,IF($C55="FY2029",3,IF($C55="FY2030",4,0))))))+Scenarios!L12-ROUND(Scenarios!L12*Scenarios!$F12,0),BaselineCalc!$B$8+Scenarios!L12-ROUND(Scenarios!L12*Scenarios!$F12,0)) -> 296 | N55: =(L55-D55) + (M55-E55) -> 296 | O55: =(Parameters_Public!$C$22*(L55-D55)+Parameters_Public!$C$23*(M55-E55)) -> 177.6 | P55: =YearMap!E5 -> 500 | Q55: =IF(Scenarios!N12="lease", YearMap!F5, YearMap!G5) -> 0.1 | R55: =IF(Scenarios!D12=1, Q55*H55, H55) -> 1512280.6 | S55: =IF(Scenarios!E12=1, Q55*I55, I55) -> 174177.06 | T55: =IF(C55="FY2026", (Scenarios!D12+Scenarios!E12)*BaselineCalc!$B$22, 0) -> 0 | U55: =(R55+S55+G55*F55)*J55*(1-K55) -> 3437511.4 | V55: =O55*(G55+P55) -> 1315612.4 | W55: =U55+V55+IF(Parameters_Public!$C$26=1, T55, 0) -> 4753123.7 | X55: =IF(F55+O55>0, W55/(F55+O55),"") -> 10936.778 | Y55: =INDEX(YearMap!$I$2:$I$6, MATCH(C55, YearMap!$A$2:$A$6, 0)) -> 5398.4527 | Z55: =W55 - ((Y55 + IF(Parameters_Public!$C$20=1, Parameters_Public!$C$19, 0))*AC55) -> 2080158.7 | AA55: =IF($AC55>0, $Z55/$AC55, 0) -> 4786.3753 | AB55: =MAX(0, (MAX(0, $D55-BaselineCalc!$B$7) + MAX(0, $E55-BaselineCalc!$B$8))) -> 0 | AC55: =IF(LEFT($B55,2)="A_", $O55, IF(LEFT($B55,2)="B_", $M55+$O55, IF(LEFT($B55,2)="C_", $L55+$O55, $F55))) -> 434.6 | AD55: =((Y55 + IF(Parameters_Public!$C$20=1, INDEX(YearMap!$O$2:$O$6, MATCH(C55, YearMap!$A$2:$A$6, 0)), 0))*AC55) + AC55*INDEX(YearMap!$P$2:$P$6, MATCH(C55, YearMap!$A$2:$A$6, 0)) -> 5131779.3 | AE55: =W55 - (1-Parameters_Public!$C42)*$G55*$AB55*$J55*(1-$K55) -> 4753123.7 | AF55: =AD55-AE55 -> 378655.6 | AG55: =B55&"|"&C55 -> C_Repurpose_Pima_lease_EchoGHub_EchoTargets|FY2029
A56: =AG56 -> C_Repurpose_Pima_lease_EchoGHub_EchoTargets|FY2030 | B56: =Scenarios!A12 -> C_Repurpose_Pima_lease_EchoGHub_EchoTargets | C56: FY2030 | D56: =IF(Scenarios!D12=1,0, L56) -> 257 | E56: =IF(Scenarios!E12=1,0, M56) -> 0 | F56: =D56+E56 -> 257 | G56: =YearMap!B6 -> 7080.4205 | H56: =YearMap!C6 -> 1550087.6 | I56: =YearMap!D6 -> 1785314.9 | J56: =1-BaselineCalc!$B$5 -> 0.993 | K56: =Scenarios!G12 -> 0 | L56: =IF(Scenarios!$Q12=1,BaselineCalc!$B$7*(1+Parameters_Public!$C44)^(IF($C56="FY2026",0,IF($C56="FY2027",1,IF($C56="FY2028",2,IF($C56="FY2029",3,IF($C56="FY2030",4,0))))))+ROUND(Scenarios!M12*Scenarios!$F12,0),BaselineCalc!$B$7+ROUND(Scenarios!M12*Scenarios!$F12,0)) -> 257 | M56: =IF(Scenarios!$R12=1,BaselineCalc!$B$8*(1+Parameters_Public!$C45)^(IF($C56="FY2026",0,IF($C56="FY2027",1,IF($C56="FY2028",2,IF($C56="FY2029",3,IF($C56="FY2030",4,0))))))+Scenarios!M12-ROUND(Scenarios!M12*Scenarios!$F12,0),BaselineCalc!$B$8+Scenarios!M12-ROUND(Scenarios!M12*Scenarios!$F12,0)) -> 296 | N56: =(L56-D56) + (M56-E56) -> 296 | O56: =(Parameters_Public!$C$22*(L56-D56)+Parameters_Public!$C$23*(M56-E56)) -> 177.6 | P56: =YearMap!E6 -> 300 | Q56: =IF(Scenarios!N12="lease", YearMap!F6, YearMap!G6) -> 0.1 | R56: =IF(Scenarios!D12=1, Q56*H56, H56) -> 1550087.6 | S56: =IF(Scenarios!E12=1, Q56*I56, I56) -> 178531.49 | T56: =IF(C56="FY2026", (Scenarios!D12+Scenarios!E12)*BaselineCalc!$B$22, 0) -> 0 | U56: =(R56+S56+G56*F56)*J56*(1-K56) -> 3523449.2 | V56: =O56*(G56+P56) -> 1310762.7 | W56: =U56+V56+IF(Parameters_Public!$C$26=1, T56, 0) -> 4834211.8 | X56: =IF(F56+O56>0, W56/(F56+O56),"") -> 11123.359 | Y56: =INDEX(YearMap!$I$2:$I$6, MATCH(C56, YearMap!$A$2:$A$6, 0)) -> 5533.414 | Z56: =W56 - ((Y56 + IF(Parameters_Public!$C$20=1, Parameters_Public!$C$19, 0))*AC56) -> 2102592.6 | AA56: =IF($AC56>0, $Z56/$AC56, 0) -> 4837.995 | AB56: =MAX(0, (MAX(0, $D56-BaselineCalc!$B$7) + MAX(0, $E56-BaselineCalc!$B$8))) -> 0 | AC56: =IF(LEFT($B56,2)="A_", $O56, IF(LEFT($B56,2)="B_", $M56+$O56, IF(LEFT($B56,2)="C_", $L56+$O56, $F56))) -> 434.6 | AD56: =((Y56 + IF(Parameters_Public!$C$20=1, INDEX(YearMap!$O$2:$O$6, MATCH(C56, YearMap!$A$2:$A$6, 0)), 0))*AC56) + AC56*INDEX(YearMap!$P$2:$P$6, MATCH(C56, YearMap!$A$2:$A$6, 0)) -> 5260073.8 | AE56: =W56 - (1-Parameters_Public!$C42)*$G56*$AB56*$J56*(1-$K56) -> 4834211.8 | AF56: =AD56-AE56 -> 425861.99 | AG56: =B56&"|"&C56 -> C_Repurpose_Pima_lease_EchoGHub_EchoTargets|FY2030
A57: =AG57 -> C_Repurpose_Pima_ops_EchoGHub_EchoTargets|FY2026 | B57: =Scenarios!A13 -> C_Repurpose_Pima_ops_EchoGHub_EchoTargets | C57: FY2026 | D57: =IF(Scenarios!D13=1,0, L57) -> 290 | E57: =IF(Scenarios!E13=1,0, M57) -> 0 | F57: =D57+E57 -> 290 | G57: =YearMap!B2 -> 6414.5115 | H57: =YearMap!C2 -> 1404302.9 | I57: =YearMap!D2 -> 1617407.2 | J57: =1-BaselineCalc!$B$5 -> 0.993 | K57: =Scenarios!G13 -> 0 | L57: =IF(Scenarios!$Q13=1,BaselineCalc!$B$7*(1+Parameters_Public!$C44)^(IF($C57="FY2026",0,IF($C57="FY2027",1,IF($C57="FY2028",2,IF($C57="FY2029",3,IF($C57="FY2030",4,0))))))+ROUND(Scenarios!I13*Scenarios!$F13,0),BaselineCalc!$B$7+ROUND(Scenarios!I13*Scenarios!$F13,0)) -> 290 | M57: =IF(Scenarios!$R13=1,BaselineCalc!$B$8*(1+Parameters_Public!$C45)^(IF($C57="FY2026",0,IF($C57="FY2027",1,IF($C57="FY2028",2,IF($C57="FY2029",3,IF($C57="FY2030",4,0))))))+Scenarios!I13-ROUND(Scenarios!I13*Scenarios!$F13,0),BaselineCalc!$B$8+Scenarios!I13-ROUND(Scenarios!I13*Scenarios!$F13,0)) -> 296.33333 | N57: =(L57-D57) + (M57-E57) -> 296.33333 | O57: =(Parameters_Public!$C$22*(L57-D57)+Parameters_Public!$C$23*(M57-E57)) -> 177.8 | P57: =YearMap!E2 -> 1000 | Q57: =IF(Scenarios!N13="lease", YearMap!F2, YearMap!G2) -> 0.5 | R57: =IF(Scenarios!D13=1, Q57*H57, H57) -> 1404302.9 | S57: =IF(Scenarios!E13=1, Q57*I57, I57) -> 808703.6 | T57: =IF(C57="FY2026", (Scenarios!D13+Scenarios!E13)*BaselineCalc!$B$22, 0) -> 1200000 | U57: =(R57+S57+G57*F57)*J57*(1-K57) -> 4044702.3 | V57: =O57*(G57+P57) -> 1318300.1 | W57: =U57+V57+IF(Parameters_Public!$C$26=1, T57, 0) -> 5363002.4 | X57: =IF(F57+O57>0, W57/(F57+O57),"") -> 11464.306 | Y57: =INDEX(YearMap!$I$2:$I$6, MATCH(C57, YearMap!$A$2:$A$6, 0)) -> 5013 | Z57: =W57 - ((Y57 + IF(Parameters_Public!$C$20=1, Parameters_Public!$C$19, 0))*AC57) -> 2666158.8 | AA57: =IF($AC57>0, $Z57/$AC57, 0) -> 5699.3562 | AB57: =MAX(0, (MAX(0, $D57-BaselineCalc!$B$7) + MAX(0, $E57-BaselineCalc!$B$8))) -> 33 | AC57: =IF(LEFT($B57,2)="A_", $O57, IF(LEFT($B57,2)="B_", $M57+$O57, IF(LEFT($B57,2)="C_", $L57+$O57, $F57))) -> 467.8 | AD57: =((Y57 + IF(Parameters_Public!$C$20=1, INDEX(YearMap!$O$2:$O$6, MATCH(C57, YearMap!$A$2:$A$6, 0)), 0))*AC57) + AC57*INDEX(YearMap!$P$2:$P$6, MATCH(C57, YearMap!$A$2:$A$6, 0)) -> 5129403.6 | AE57: =W57 - (1-Parameters_Public!$C42)*$G57*$AB57*$J57*(1-$K57) -> 5152805.3 | AF57: =AD57-AE57 -> -23401.706 | AG57: =B57&"|"&C57 -> C_Repurpose_Pima_ops_EchoGHub_EchoTargets|FY2026
A58: =AG58 -> C_Repurpose_Pima_ops_EchoGHub_EchoTargets|FY2027 | B58: =Scenarios!A13 -> C_Repurpose_Pima_ops_EchoGHub_EchoTargets | C58: FY2027 | D58: =IF(Scenarios!D13=1,0, L58) -> 324 | E58: =IF(Scenarios!E13=1,0, M58) -> 0 | F58: =D58+E58 -> 324 | G58: =YearMap!B3 -> 6574.8743 | H58: =YearMap!C3 -> 1439410.4 | I58: =YearMap!D3 -> 1657842.4 | J58: =1-BaselineCalc!$B$5 -> 0.993 | K58: =Scenarios!G13 -> 0 | L58: =IF(Scenarios!$Q13=1,BaselineCalc!$B$7*(1+Parameters_Public!$C44)^(IF($C58="FY2026",0,IF($C58="FY2027",1,IF($C58="FY2028",2,IF($C58="FY2029",3,IF($C58="FY2030",4,0))))))+ROUND(Scenarios!J13*Scenarios!$F13,0),BaselineCalc!$B$7+ROUND(Scenarios!J13*Scenarios!$F13,0)) -> 324 | M58: =IF(Scenarios!$R13=1,BaselineCalc!$B$8*(1+Parameters_Public!$C45)^(IF($C58="FY2026",0,IF($C58="FY2027",1,IF($C58="FY2028",2,IF($C58="FY2029",3,IF($C58="FY2030",4,0))))))+Scenarios!J13-ROUND(Scenarios!J13*Scenarios!$F13,0),BaselineCalc!$B$8+Scenarios!J13-ROUND(Scenarios!J13*Scenarios!$F13,0)) -> 295.66667 | N58: =(L58-D58) + (M58-E58) -> 295.66667 | O58: =(Parameters_Public!$C$22*(L58-D58)+Parameters_Public!$C$23*(M58-E58)) -> 177.4 | P58: =YearMap!E3 -> 800 | Q58: =IF(Scenarios!N13="lease", YearMap!F3, YearMap!G3) -> 0.4 | R58: =IF(Scenarios!D13=1, Q58*H58, H58) -> 1439410.4 | S58: =IF(Scenarios!E13=1, Q58*I58, I58) -> 663136.95 | T58: =IF(C58="FY2026", (Scenarios!D13+Scenarios!E13)*BaselineCalc!$B$22, 0) -> 0 | U58: =(R58+S58+G58*F58)*J58*(1-K58) -> 4203177 | V58: =O58*(G58+P58) -> 1308302.7 | W58: =U58+V58+IF(Parameters_Public!$C$26=1, T58, 0) -> 5511479.7 | X58: =IF(F58+O58>0, W58/(F58+O58),"") -> 10992.181 | Y58: =INDEX(YearMap!$I$2:$I$6, MATCH(C58, YearMap!$A$2:$A$6, 0)) -> 5138.325 | Z58: =W58 - ((Y58 + IF(Parameters_Public!$C$20=1, Parameters_Public!$C$19, 0))*AC58) -> 2558095.8 | AA58: =IF($AC58>0, $Z58/$AC58, 0) -> 5101.9063 | AB58: =MAX(0, (MAX(0, $D58-BaselineCalc!$B$7) + MAX(0, $E58-BaselineCalc!$B$8))) -> 67 | AC58: =IF(LEFT($B58,2)="A_", $O58, IF(LEFT($B58,2)="B_", $M58+$O58, IF(LEFT($B58,2)="C_", $L58+$O58, $F58))) -> 501.4 | AD58: =((Y58 + IF(Parameters_Public!$C$20=1, INDEX(YearMap!$O$2:$O$6, MATCH(C58, YearMap!$A$2:$A$6, 0)), 0))*AC58) + AC58*INDEX(YearMap!$P$2:$P$6, MATCH(C58, YearMap!$A$2:$A$6, 0)) -> 5635271.6 | AE58: =W58 - (1-Parameters_Public!$C42)*$G58*$AB58*$J58*(1-$K58) -> 5074046.8 | AF58: =AD58-AE58 -> 561224.83 | AG58: =B58&"|"&C58 -> C_Repurpose_Pima_ops_EchoGHub_EchoTargets|FY2027
A59: =AG59 -> C_Repurpose_Pima_ops_EchoGHub_EchoTargets|FY2028 | B59: =Scenarios!A13 -> C_Repurpose_Pima_ops_EchoGHub_EchoTargets | C59: FY2028 | D59: =IF(Scenarios!D13=1,0, L59) -> 357 | E59: =IF(Scenarios!E13=1,0, M59) -> 0 | F59: =D59+E59 -> 357 | G59: =YearMap!B4 -> 6739.2461 | H59: =YearMap!C4 -> 1475395.7 | I59: =YearMap!D4 -> 1699288.4 | J59: =1-BaselineCalc!$B$5 -> 0.993 | K59: =Scenarios!G13 -> 0 | L59: =IF(Scenarios!$Q13=1,BaselineCalc!$B$7*(1+Parameters_Public!$C44)^(IF($C59="FY2026",0,IF($C59="FY2027",1,IF($C59="FY2028",2,IF($C59="FY2029",3,IF($C59="FY2030",4,0))))))+ROUND(Scenarios!K13*Scenarios!$F13,0),BaselineCalc!$B$7+ROUND(Scenarios!K13*Scenarios!$F13,0)) -> 357 | M59: =IF(Scenarios!$R13=1,BaselineCalc!$B$8*(1+Parameters_Public!$C45)^(IF($C59="FY2026",0,IF($C59="FY2027",1,IF($C59="FY2028",2,IF($C59="FY2029",3,IF($C59="FY2030",4,0))))))+Scenarios!K13-ROUND(Scenarios!K13*Scenarios!$F13,0),BaselineCalc!$B$8+Scenarios!K13-ROUND(Scenarios!K13*Scenarios!$F13,0)) -> 296 | N59: =(L59-D59) + (M59-E59) -> 296 | O59: =(Parameters_Public!$C$22*(L59-D59)+Parameters_Public!$C$23*(M59-E59)) -> 177.6 | P59: =YearMap!E4 -> 600 | Q59: =IF(Scenarios!N13="lease", YearMap!F4, YearMap!G4) -> 0.35 | R59: =IF(Scenarios!D13=1, Q59*H59, H59) -> 1475395.7 | S59: =IF(Scenarios!E13=1, Q59*I59, I59) -> 594750.95 | T59: =IF(C59="FY2026", (Scenarios!D13+Scenarios!E13)*BaselineCalc!$B$22, 0) -> 0 | U59: =(R59+S59+G59*F59)*J59*(1-K59) -> 4444725.1 | V59: =O59*(G59+P59) -> 1303450.1 | W59: =U59+V59+IF(Parameters_Public!$C$26=1, T59, 0) -> 5748175.2 | X59: =IF(F59+O59>0, W59/(F59+O59),"") -> 10752.292 | Y59: =INDEX(YearMap!$I$2:$I$6, MATCH(C59, YearMap!$A$2:$A$6, 0)) -> 5266.7831 | Z59: =W59 - ((Y59 + IF(Parameters_Public!$C$20=1, Parameters_Public!$C$19, 0))*AC59) -> 2530560.5 | AA59: =IF($AC59>0, $Z59/$AC59, 0) -> 4733.5588 | AB59: =MAX(0, (MAX(0, $D59-BaselineCalc!$B$7) + MAX(0, $E59-BaselineCalc!$B$8))) -> 100 | AC59: =IF(LEFT($B59,2)="A_", $O59, IF(LEFT($B59,2)="B_", $M59+$O59, IF(LEFT($B59,2)="C_", $L59+$O59, $F59))) -> 534.6 | AD59: =((Y59 + IF(Parameters_Public!$C$20=1, INDEX(YearMap!$O$2:$O$6, MATCH(C59, YearMap!$A$2:$A$6, 0)), 0))*AC59) + AC59*INDEX(YearMap!$P$2:$P$6, MATCH(C59, YearMap!$A$2:$A$6, 0)) -> 6158619 | AE59: =W59 - (1-Parameters_Public!$C42)*$G59*$AB59*$J59*(1-$K59) -> 5078968.1 | AF59: =AD59-AE59 -> 1079650.9 | AG59: =B59&"|"&C59 -> C_Repurpose_Pima_ops_EchoGHub_EchoTargets|FY2028
A60: =AG60 -> C_Repurpose_Pima_ops_EchoGHub_EchoTargets|FY2029 | B60: =Scenarios!A13 -> C_Repurpose_Pima_ops_EchoGHub_EchoTargets | C60: FY2029 | D60: =IF(Scenarios!D13=1,0, L60) -> 357 | E60: =IF(Scenarios!E13=1,0, M60) -> 0 | F60: =D60+E60 -> 357 | G60: =YearMap!B5 -> 6907.7273 | H60: =YearMap!C5 -> 1512280.6 | I60: =YearMap!D5 -> 1741770.6 | J60: =1-BaselineCalc!$B$5 -> 0.993 | K60: =Scenarios!G13 -> 0 | L60: =IF(Scenarios!$Q13=1,BaselineCalc!$B$7*(1+Parameters_Public!$C44)^(IF($C60="FY2026",0,IF($C60="FY2027",1,IF($C60="FY2028",2,IF($C60="FY2029",3,IF($C60="FY2030",4,0))))))+ROUND(Scenarios!L13*Scenarios!$F13,0),BaselineCalc!$B$7+ROUND(Scenarios!L13*Scenarios!$F13,0)) -> 357 | M60: =IF(Scenarios!$R13=1,BaselineCalc!$B$8*(1+Parameters_Public!$C45)^(IF($C60="FY2026",0,IF($C60="FY2027",1,IF($C60="FY2028",2,IF($C60="FY2029",3,IF($C60="FY2030",4,0))))))+Scenarios!L13-ROUND(Scenarios!L13*Scenarios!$F13,0),BaselineCalc!$B$8+Scenarios!L13-ROUND(Scenarios!L13*Scenarios!$F13,0)) -> 296 | N60: =(L60-D60) + (M60-E60) -> 296 | O60: =(Parameters_Public!$C$22*(L60-D60)+Parameters_Public!$C$23*(M60-E60)) -> 177.6 | P60: =YearMap!E5 -> 500 | Q60: =IF(Scenarios!N13="lease", YearMap!F5, YearMap!G5) -> 0.3 | R60: =IF(Scenarios!D13=1, Q60*H60, H60) -> 1512280.6 | S60: =IF(Scenarios!E13=1, Q60*I60, I60) -> 522531.19 | T60: =IF(C60="FY2026", (Scenarios!D13+Scenarios!E13)*BaselineCalc!$B$22, 0) -> 0 | U60: =(R60+S60+G60*F60)*J60*(1-K60) -> 4469364.3 | V60: =O60*(G60+P60) -> 1315612.4 | W60: =U60+V60+IF(Parameters_Public!$C$26=1, T60, 0) -> 5784976.7 | X60: =IF(F60+O60>0, W60/(F60+O60),"") -> 10821.131 | Y60: =INDEX(YearMap!$I$2:$I$6, MATCH(C60, YearMap!$A$2:$A$6, 0)) -> 5398.4527 | Z60: =W60 - ((Y60 + IF(Parameters_Public!$C$20=1, Parameters_Public!$C$19, 0))*AC60) -> 2496971.4 | AA60: =IF($AC60>0, $Z60/$AC60, 0) -> 4670.7284 | AB60: =MAX(0, (MAX(0, $D60-BaselineCalc!$B$7) + MAX(0, $E60-BaselineCalc!$B$8))) -> 100 | AC60: =IF(LEFT($B60,2)="A_", $O60, IF(LEFT($B60,2)="B_", $M60+$O60, IF(LEFT($B60,2)="C_", $L60+$O60, $F60))) -> 534.6 | AD60: =((Y60 + IF(Parameters_Public!$C$20=1, INDEX(YearMap!$O$2:$O$6, MATCH(C60, YearMap!$A$2:$A$6, 0)), 0))*AC60) + AC60*INDEX(YearMap!$P$2:$P$6, MATCH(C60, YearMap!$A$2:$A$6, 0)) -> 6312584.5 | AE60: =W60 - (1-Parameters_Public!$C42)*$G60*$AB60*$J60*(1-$K60) -> 5099039.4 | AF60: =AD60-AE60 -> 1213545.1 | AG60: =B60&"|"&C60 -> C_Repurpose_Pima_ops_EchoGHub_EchoTargets|FY2029
A61: =AG61 -> C_Repurpose_Pima_ops_EchoGHub_EchoTargets|FY2030 | B61: =Scenarios!A13 -> C_Repurpose_Pima_ops_EchoGHub_EchoTargets | C61: FY2030 | D61: =IF(Scenarios!D13=1,0, L61) -> 357 | E61: =IF(Scenarios!E13=1,0, M61) -> 0 | F61: =D61+E61 -> 357 | G61: =YearMap!B6 -> 7080.4205 | H61: =YearMap!C6 -> 1550087.6 | I61: =YearMap!D6 -> 1785314.9 | J61: =1-BaselineCalc!$B$5 -> 0.993 | K61: =Scenarios!G13 -> 0 | L61: =IF(Scenarios!$Q13=1,BaselineCalc!$B$7*(1+Parameters_Public!$C44)^(IF($C61="FY2026",0,IF($C61="FY2027",1,IF($C61="FY2028",2,IF($C61="FY2029",3,IF($C61="FY2030",4,0))))))+ROUND(Scenarios!M13*Scenarios!$F13,0),BaselineCalc!$B$7+ROUND(Scenarios!M13*Scenarios!$F13,0)) -> 357 | M61: =IF(Scenarios!$R13=1,BaselineCalc!$B$8*(1+Parameters_Public!$C45)^(IF($C61="FY2026",0,IF($C61="FY2027",1,IF($C61="FY2028",2,IF($C61="FY2029",3,IF($C61="FY2030",4,0))))))+Scenarios!M13-ROUND(Scenarios!M13*Scenarios!$F13,0),BaselineCalc!$B$8+Scenarios!M13-ROUND(Scenarios!M13*Scenarios!$F13,0)) -> 296 | N61: =(L61-D61) + (M61-E61) -> 296 | O61: =(Parameters_Public!$C$22*(L61-D61)+Parameters_Public!$C$23*(M61-E61)) -> 177.6 | P61: =YearMap!E6 -> 300 | Q61: =IF(Scenarios!N13="lease", YearMap!F6, YearMap!G6) -> 0.3 | R61: =IF(Scenarios!D13=1, Q61*H61, H61) -> 1550087.6 | S61: =IF(Scenarios!E13=1, Q61*I61, I61) -> 535594.47 | T61: =IF(C61="FY2026", (Scenarios!D13+Scenarios!E13)*BaselineCalc!$B$22, 0) -> 0 | U61: =(R61+S61+G61*F61)*J61*(1-K61) -> 4581098.4 | V61: =O61*(G61+P61) -> 1310762.7 | W61: =U61+V61+IF(Parameters_Public!$C$26=1, T61, 0) -> 5891861.1 | X61: =IF(F61+O61>0, W61/(F61+O61),"") -> 11021.065 | Y61: =INDEX(YearMap!$I$2:$I$6, MATCH(C61, YearMap!$A$2:$A$6, 0)) -> 5533.414 | Z61: =W61 - ((Y61 + IF(Parameters_Public!$C$20=1, Parameters_Public!$C$19, 0))*AC61) -> 2531705.5 | AA61: =IF($AC61>0, $Z61/$AC61, 0) -> 4735.7006 | AB61: =MAX(0, (MAX(0, $D61-BaselineCalc!$B$7) + MAX(0, $E61-BaselineCalc!$B$8))) -> 100 | AC61: =IF(LEFT($B61,2)="A_", $O61, IF(LEFT($B61,2)="B_", $M61+$O61, IF(LEFT($B61,2)="C_", $L61+$O61, $F61))) -> 534.6 | AD61: =((Y61 + IF(Parameters_Public!$C$20=1, INDEX(YearMap!$O$2:$O$6, MATCH(C61, YearMap!$A$2:$A$6, 0)), 0))*AC61) + AC61*INDEX(YearMap!$P$2:$P$6, MATCH(C61, YearMap!$A$2:$A$6, 0)) -> 6470399.1 | AE61: =W61 - (1-Parameters_Public!$C42)*$G61*$AB61*$J61*(1-$K61) -> 5188775.4 | AF61: =AD61-AE61 -> 1281623.8 | AG61: =B61&"|"&C61 -> C_Repurpose_Pima_ops_EchoGHub_EchoTargets|FY2030
