Workbook

Sheet Dashboard
A1: SUSD Keep-Open vs Repurpose — Interactive Dashboard (v4.4)
A3: Pick scenarios & assumptions
D4: Metric | E4: A (baseline) | F4: X (compare)
A5: Baseline A (auto): | B5: A_Repurpose_Both_ops | D5: FY2030 Net ($) | E5: =INDEX(Summary_Costs!$C$2:$C$13, MATCH($B$5, Summary_Costs!$A$2:$A$13, 0)) | F5: =INDEX(Summary_Costs!$C$2:$C$13, MATCH($B$6, Summary_Costs!$A$2:$A$13, 0))
A6: Compare to (X): | B6: G_DHub_EchoRamp | C6: D_Grow_Both_150 | D6: 5‑yr Avg Net ($) | E6: =INDEX(Summary_Costs!$E$2:$E$13, MATCH($B$5, Summary_Costs!$A$2:$A$13, 0)) | F6: =INDEX(Summary_Costs!$E$2:$E$13, MATCH($B$6, Summary_Costs!$A$2:$A$13, 0))
A7: Compare to (Y) [optional]: | B7: G_DHub_EchoRamp | D7: # students displaced | E7: =INDEX(Summary_Costs!$F$2:$F$13, MATCH($B$5, Summary_Costs!$A$2:$A$13, 0)) | F7: =INDEX(Summary_Costs!$F$2:$F$13, MATCH($B$6, Summary_Costs!$A$2:$A$13, 0))
D8: FY2030 # served (open & retained) | E8: =INDEX(Summary_Costs!$G$2:$G$13, MATCH($B$5, Summary_Costs!$A$2:$A$13, 0)) | F8: =INDEX(Summary_Costs!$G$2:$G$13, MATCH($B$6, Summary_Costs!$A$2:$A$13, 0))
D10: Δ vs A by FY2030 ($) | F10: =F5-E5
D11: Δ vs A (5‑yr Avg) ($) | F11: =F6-E6
A15: Year | B15: A Net ($) | C15: X Net ($)
A16: FY2026 | B16: =SUMIFS(MultiYear_ProForma!$AA:$AA, MultiYear_ProForma!$B:$B, $B$5, MultiYear_ProForma!$C:$C, "FY2026") | C16: =SUMIFS(MultiYear_ProForma!$AA:$AA, MultiYear_ProForma!$B:$B, $B$6, MultiYear_ProForma!$C:$C, "FY2026")
A17: FY2027 | B17: =SUMIFS(MultiYear_ProForma!$AA:$AA, MultiYear_ProForma!$B:$B, $B$5, MultiYear_ProForma!$C:$C, "FY2027") | C17: =SUMIFS(MultiYear_ProForma!$AA:$AA, MultiYear_ProForma!$B:$B, $B$6, MultiYear_ProForma!$C:$C, "FY2027")
A18: FY2028 | B18: =SUMIFS(MultiYear_ProForma!$AA:$AA, MultiYear_ProForma!$B:$B, $B$5, MultiYear_ProForma!$C:$C, "FY2028") | C18: =SUMIFS(MultiYear_ProForma!$AA:$AA, MultiYear_ProForma!$B:$B, $B$6, MultiYear_ProForma!$C:$C, "FY2028")
A19: FY2029 | B19: =SUMIFS(MultiYear_ProForma!$AA:$AA, MultiYear_ProForma!$B:$B, $B$5, MultiYear_ProForma!$C:$C, "FY2029") | C19: =SUMIFS(MultiYear_ProForma!$AA:$AA, MultiYear_ProForma!$B:$B, $B$6, MultiYear_ProForma!$C:$C, "FY2029")
A20: FY2030 | B20: =SUMIFS(MultiYear_ProForma!$AA:$AA, MultiYear_ProForma!$B:$B, $B$5, MultiYear_ProForma!$C:$C, "FY2030") | C20: =SUMIFS(MultiYear_ProForma!$AA:$AA, MultiYear_ProForma!$B:$B, $B$6, MultiYear_ProForma!$C:$C, "FY2030")
A25: Notes
A26: • 'Net ($)' = Comparable M&O costs minus base state aid on students served (open & retained). This is a two‑site view (Echo+Pima), not the entire district budget. • Positive Δ vs A means the comparator is more expensive than 'A_Repurpose_Both_ops' under the Parameters tab assumptions.

Sheet Cards
A1: Mini-Cards: A (Repurpose-Both) vs X and Y
A3: Comparator X | B3: =Dashboard!$B$6 | D3: Comparator Y | E3: =Dashboard!$B$7
A4: r* needed (year/mode/h) | B4: =Dashboard!$I$23 | D4: r* needed (year/mode/h) | E4: =Dashboard!$I$24
A5: Δ FY2030 $/student | B5: =Dashboard!$I$26 | D5: Δ FY2030 $/student | E5: =Dashboard!$I$27
A6: Δ 5-yr Avg $/student | B6: =Dashboard!$I$28 | D6: Δ 5-yr Avg $/student | E6: =Dashboard!$I$29
A7: # displaced (A) | B7: =INDEX(Summary_Costs!$F:$F, MATCH(Dashboard!$B$5, Summary_Costs!$A:$A,0)) | D7: # displaced (A) | E7: =INDEX(Summary_Costs!$F:$F, MATCH(Dashboard!$B$5, Summary_Costs!$A:$A,0))
A8: # displaced (X) | B8: =INDEX(Summary_Costs!$F:$F, MATCH(Dashboard!$B$6, Summary_Costs!$A:$A,0)) | D8: # displaced (Y) | E8: =INDEX(Summary_Costs!$F:$F, MATCH(Dashboard!$B$7, Summary_Costs!$A:$A,0))
A9: Distinctiveness / Reversibility | B9: =Dashboard!$E$26 & " / " & Dashboard!$F$26 | D9: Distinctiveness / Reversibility | E9: =Dashboard!$E$33 & " / " & Dashboard!$F$33

Sheet BaselineCalc
A1: Parameter | B1: Value | C1: Notes
A2: MO inflation | B2: 0.025 | C2: Annual inflation factor.
A3: Base MO per ADM (FY25) | B3: 9936 | C3: Working base for FY25.
A4: Fixed share of MO | B4: 0.3 | C4: Share treated as semi‑fixed (plant/insurance).
A5: Ops savings (keep‑open) | B5: 0.007 | C5: Light discipline if sites remain open (not used here).
A6: Extra savings (Co‑location) | B6: 0.015 | C6: Incremental savings for co‑location (not used here).
A7: Echo base ADM | B7: 257
A8: Pima base ADM | B8: 296
A9: Total base ADM | B9: =B7+B8 | C9: Echo base ADM + Pima base ADM
A12: Helper / Derivation | B12: FY26 | C12: FY27 | D12: FY28 | E12: FY29 | F12: FY30 | G12: Notes
A13: Base total MO (FY25) | B13: =B9*B3 | C13: =C14/$B$4 | D13: =D14/$B$4 | E13: =E14/$B$4 | F13: =F14/$B$4 | G13: Total ADM × Base MO/ADM | K13: B13 = B9*B3 (Base total MO, FY25)
A14: Fixed MO (FY25) | B14: =B13*B4 | C14: =B17 | D14: =C17 | E14: =D17 | F14: =E17 | G14: Fixed = Base total × Fixed share | K14: B14 = B13*B4 (Fixed MO, FY25)
A15: Var per student (FY25) | B15: =(B13-B14)/B9 | C15: =B18 | D15: =C18 | E15: =D18 | F15: =E18 | G15: Variable = (Base total − Fixed)/Total ADM | K15: B15 = (B13–B14)/B9 (Variable $/student, FY25)
A17: Fixed total ($) | B17: =$B$14*(1+$B$2)^1 | C17: =$B$14*(1+$B$2)^2 | D17: =$B$14*(1+$B$2)^3 | E17: =$B$14*(1+$B$2)^4 | F17: =$B$14*(1+$B$2)^5
A18: Var unit ($/student) | B18: =$B$15*(1+$B$2)^1 | C18: =$B$15*(1+$B$2)^2 | D18: =$B$15*(1+$B$2)^3 | E18: =$B$15*(1+$B$2)^4 | F18: =$B$15*(1+$B$2)^5
A19: Echo fixed ($) | B19: =B17*($B$7/$B$9) | C19: =C17*($B$7/$B$9) | D19: =D17*($B$7/$B$9) | E19: =E17*($B$7/$B$9) | F19: =F17*($B$7/$B$9)
A20: Pima fixed ($) | B20: =B17*($B$8/$B$9) | C20: =C17*($B$8/$B$9) | D20: =D17*($B$8/$B$9) | E20: =E17*($B$8/$B$9) | F20: =F17*($B$8/$B$9)
A21: Repurpose TI per closed site (FY26) | B21: 1200000
A22: Retention r (central) | B22: 0.75
A24: Notes
A25: All formulas are same‑sheet and reference the Parameter cells above.
A26: Base State Aid per ADM (FY26) | B26: 5113 | C26: Editable; ADE base aid.
A27: Aid inflation (annual) | B27: 0.02 | C27: Editable; assumed growth in base aid.

Sheet YearMap
A1: Year | B1: VarUnit$ | C1: EchoFixed$ | D1: PimaFixed$ | E1: h | F1: f_lease | G1: f_ops | H1: YearIdx | I1: Aid$
A2: FY2026 | B2: =BaselineCalc!B18 | C2: =BaselineCalc!B19 | D2: =BaselineCalc!B20 | E2: 1000 | F2: 0.4 | G2: 0.4 | H2: 1 | I2: =BaselineCalc!$B$26*(1+BaselineCalc!$B$27)^(H2-1)
A3: FY2027 | B3: =BaselineCalc!C18 | C3: =BaselineCalc!C19 | D3: =BaselineCalc!C20 | E3: 800 | F3: 0.3 | G3: 0.35 | H3: 2 | I3: =BaselineCalc!$B$26*(1+BaselineCalc!$B$27)^(H3-1)
A4: FY2028 | B4: =BaselineCalc!D18 | C4: =BaselineCalc!D19 | D4: =BaselineCalc!D20 | E4: 600 | F4: 0.2 | G4: 0.3 | H4: 3 | I4: =BaselineCalc!$B$26*(1+BaselineCalc!$B$27)^(H4-1)
A5: FY2029 | B5: =BaselineCalc!E18 | C5: =BaselineCalc!E19 | D5: =BaselineCalc!E20 | E5: 400 | F5: 0.1 | G5: 0.25 | H5: 4 | I5: =BaselineCalc!$B$26*(1+BaselineCalc!$B$27)^(H5-1)
A6: FY2030 | B6: =BaselineCalc!F18 | C6: =BaselineCalc!F19 | D6: =BaselineCalc!F20 | E6: 300 | F6: 0 | G6: 0.2 | H6: 5 | I6: =BaselineCalc!$B$26*(1+BaselineCalc!$B$27)^(H6-1)

Sheet MultiYear_ProForma
A1: =Y1 | B1: ScenarioKey | C1: Year | D1: Echo_ADM | E1: Pima_ADM | F1: Total_ADM | G1: VarUnit$ | H1: EchoFixed$ | I1: PimaFixed$ | J1: OpsFactor | K1: ExtraSave | L1: EchoPotential_ADM | M1: PimaPotential_ADM | N1: Displaced_ADM | O1: Retained_ADM | P1: h | Q1: CarryFrac | R1: EchoFixedEff$ | S1: PimaFixedEff$ | T1: TI_adds$ | U1: SiteCost$ | V1: RetainedSvc$ | W1: Comparable_MO$ | X1: Comparable_per_Student$ | Y1: Key | Z1: Aid_per_ADM | AA1: Net_MO_after_aid$ | AB1: Net_per_served$ | AC1: Overlay_ADM | AD1: Served_ADM | AE1: Revenue$ | AF1: Adj_MO$
A2: =Y2 | B2: =Scenarios!A2 | C2: FY2026 | D2: =IF(Scenarios!D2=1,0, L2) | E2: =IF(Scenarios!E2=1,0, M2) | F2: =D2+E2 | G2: =YearMap!B2 | H2: =YearMap!C2 | I2: =YearMap!D2 | J2: =1-BaselineCalc!$B$5 | K2: =Scenarios!G2 | L2: =BaselineCalc!$B$7 + ROUND(Scenarios!I2*Scenarios!F2,0) | M2: =BaselineCalc!$B$8 + Scenarios!I2 - ROUND(Scenarios!I2*Scenarios!F2,0) | N2: =(L2-D2) + (M2-E2) | O2: =BaselineCalc!$B$22 * N2 | P2: =YearMap!E2 | Q2: =IF(Scenarios!N2="lease", YearMap!F2, YearMap!G2) | R2: =IF(Scenarios!D2=1, Q2*H2, H2) | S2: =IF(Scenarios!E2=1, Q2*I2, I2) | T2: =IF(C2="FY2026", (Scenarios!D2+Scenarios!E2)*BaselineCalc!$B$21, 0) | U2: =(R2+S2+G2*F2)*J2*(1-K2) | V2: =O2*(G2+P2) | W2: =U2+V2+T2 | X2: =IF(F2+O2>0, W2/(F2+O2),"") | Y2: =B2&"|"&C2 | Z2: =INDEX(YearMap!$I$2:$I$6, MATCH(C2, YearMap!$A$2:$A$6, 0)) | AA2: 0 | AB2: 0 | AC2: 0 | AD2: 0 | AE2: 0 | AF2: 0
A3: =Y3 | B3: =Scenarios!A2 | C3: FY2027 | D3: =IF(Scenarios!D2=1,0, L3) | E3: =IF(Scenarios!E2=1,0, M3) | F3: =D3+E3 | G3: =YearMap!B3 | H3: =YearMap!C3 | I3: =YearMap!D3 | J3: =1-BaselineCalc!$B$5 | K3: =Scenarios!G2 | L3: =BaselineCalc!$B$7 + ROUND(Scenarios!J2*Scenarios!F2,0) | M3: =BaselineCalc!$B$8 + Scenarios!J2 - ROUND(Scenarios!J2*Scenarios!F2,0) | N3: =(L3-D3) + (M3-E3) | O3: =BaselineCalc!$B$22 * N3 | P3: =YearMap!E3 | Q3: =IF(Scenarios!N2="lease", YearMap!F3, YearMap!G3) | R3: =IF(Scenarios!D2=1, Q3*H3, H3) | S3: =IF(Scenarios!E2=1, Q3*I3, I3) | T3: =IF(C3="FY2026", (Scenarios!D2+Scenarios!E2)*BaselineCalc!$B$21, 0) | U3: =(R3+S3+G3*F3)*J3*(1-K3) | V3: =O3*(G3+P3) | W3: =U3+V3+T3 | X3: =IF(F3+O3>0, W3/(F3+O3),"") | Y3: =B3&"|"&C3 | Z3: =INDEX(YearMap!$I$2:$I$6, MATCH(C3, YearMap!$A$2:$A$6, 0)) | AA3: 0 | AB3: 0 | AC3: 0 | AD3: 0 | AE3: 0 | AF3: 0
A4: =Y4 | B4: =Scenarios!A2 | C4: FY2028 | D4: =IF(Scenarios!D2=1,0, L4) | E4: =IF(Scenarios!E2=1,0, M4) | F4: =D4+E4 | G4: =YearMap!B4 | H4: =YearMap!C4 | I4: =YearMap!D4 | J4: =1-BaselineCalc!$B$5 | K4: =Scenarios!G2 | L4: =BaselineCalc!$B$7 + ROUND(Scenarios!K2*Scenarios!F2,0) | M4: =BaselineCalc!$B$8 + Scenarios!K2 - ROUND(Scenarios!K2*Scenarios!F2,0) | N4: =(L4-D4) + (M4-E4) | O4: =BaselineCalc!$B$22 * N4 | P4: =YearMap!E4 | Q4: =IF(Scenarios!N2="lease", YearMap!F4, YearMap!G4) | R4: =IF(Scenarios!D2=1, Q4*H4, H4) | S4: =IF(Scenarios!E2=1, Q4*I4, I4) | T4: =IF(C4="FY2026", (Scenarios!D2+Scenarios!E2)*BaselineCalc!$B$21, 0) | U4: =(R4+S4+G4*F4)*J4*(1-K4) | V4: =O4*(G4+P4) | W4: =U4+V4+T4 | X4: =IF(F4+O4>0, W4/(F4+O4),"") | Y4: =B4&"|"&C4 | Z4: =INDEX(YearMap!$I$2:$I$6, MATCH(C4, YearMap!$A$2:$A$6, 0)) | AA4: 0 | AB4: 0 | AC4: 0 | AD4: 0 | AE4: 0 | AF4: 0
A5: =Y5 | B5: =Scenarios!A2 | C5: FY2029 | D5: =IF(Scenarios!D2=1,0, L5) | E5: =IF(Scenarios!E2=1,0, M5) | F5: =D5+E5 | G5: =YearMap!B5 | H5: =YearMap!C5 | I5: =YearMap!D5 | J5: =1-BaselineCalc!$B$5 | K5: =Scenarios!G2 | L5: =BaselineCalc!$B$7 + ROUND(Scenarios!L2*Scenarios!F2,0) | M5: =BaselineCalc!$B$8 + Scenarios!L2 - ROUND(Scenarios!L2*Scenarios!F2,0) | N5: =(L5-D5) + (M5-E5) | O5: =BaselineCalc!$B$22 * N5 | P5: =YearMap!E5 | Q5: =IF(Scenarios!N2="lease", YearMap!F5, YearMap!G5) | R5: =IF(Scenarios!D2=1, Q5*H5, H5) | S5: =IF(Scenarios!E2=1, Q5*I5, I5) | T5: =IF(C5="FY2026", (Scenarios!D2+Scenarios!E2)*BaselineCalc!$B$21, 0) | U5: =(R5+S5+G5*F5)*J5*(1-K5) | V5: =O5*(G5+P5) | W5: =U5+V5+T5 | X5: =IF(F5+O5>0, W5/(F5+O5),"") | Y5: =B5&"|"&C5 | Z5: =INDEX(YearMap!$I$2:$I$6, MATCH(C5, YearMap!$A$2:$A$6, 0)) | AA5: 0 | AB5: 0 | AC5: 0 | AD5: 0 | AE5: 0 | AF5: 0
A6: =Y6 | B6: =Scenarios!A2 | C6: FY2030 | D6: =IF(Scenarios!D2=1,0, L6) | E6: =IF(Scenarios!E2=1,0, M6) | F6: =D6+E6 | G6: =YearMap!B6 | H6: =YearMap!C6 | I6: =YearMap!D6 | J6: =1-BaselineCalc!$B$5 | K6: =Scenarios!G2 | L6: =BaselineCalc!$B$7 + ROUND(Scenarios!M2*Scenarios!F2,0) | M6: =BaselineCalc!$B$8 + Scenarios!M2 - ROUND(Scenarios!M2*Scenarios!F2,0) | N6: =(L6-D6) + (M6-E6) | O6: =BaselineCalc!$B$22 * N6 | P6: =YearMap!E6 | Q6: =IF(Scenarios!N2="lease", YearMap!F6, YearMap!G6) | R6: =IF(Scenarios!D2=1, Q6*H6, H6) | S6: =IF(Scenarios!E2=1, Q6*I6, I6) | T6: =IF(C6="FY2026", (Scenarios!D2+Scenarios!E2)*BaselineCalc!$B$21, 0) | U6: =(R6+S6+G6*F6)*J6*(1-K6) | V6: =O6*(G6+P6) | W6: =U6+V6+T6 | X6: =IF(F6+O6>0, W6/(F6+O6),"") | Y6: =B6&"|"&C6 | Z6: =INDEX(YearMap!$I$2:$I$6, MATCH(C6, YearMap!$A$2:$A$6, 0)) | AA6: 0 | AB6: 0 | AC6: 0 | AD6: 0 | AE6: 0 | AF6: 0
A7: =Y7 | B7: =Scenarios!A3 | C7: FY2026 | D7: =IF(Scenarios!D3=1,0, L7) | E7: =IF(Scenarios!E3=1,0, M7) | F7: =D7+E7 | G7: =YearMap!B2 | H7: =YearMap!C2 | I7: =YearMap!D2 | J7: =1-BaselineCalc!$B$5 | K7: =Scenarios!G3 | L7: =BaselineCalc!$B$7 + ROUND(Scenarios!I3*Scenarios!F3,0) | M7: =BaselineCalc!$B$8 + Scenarios!I3 - ROUND(Scenarios!J3*Scenarios!F3,0) | N7: =(L7-D7) + (M7-E7) | O7: =BaselineCalc!$B$22 * N7 | P7: =YearMap!E2 | Q7: =IF(Scenarios!N3="lease", YearMap!F2, YearMap!G2) | R7: =IF(Scenarios!D3=1, Q7*H7, H7) | S7: =IF(Scenarios!E3=1, Q7*I7, I7) | T7: =IF(C7="FY2026", (Scenarios!D3+Scenarios!E3)*BaselineCalc!$B$21, 0) | U7: =(R7+S7+G7*F7)*J7*(1-K7) | V7: =O7*(G7+P7) | W7: =U7+V7+T7 | X7: =IF(F7+O7>0, W7/(F7+O7),"") | Y7: =B7&"|"&C7 | Z7: =INDEX(YearMap!$I$2:$I$6, MATCH(C7, YearMap!$A$2:$A$6, 0)) | AA7: 0 | AB7: 0 | AC7: 0 | AD7: 0 | AE7: 0 | AF7: 0
A8: =Y8 | B8: =Scenarios!A3 | C8: FY2027 | D8: =IF(Scenarios!D3=1,0, L8) | E8: =IF(Scenarios!E3=1,0, M8) | F8: =D8+E8 | G8: =YearMap!B3 | H8: =YearMap!C3 | I8: =YearMap!D3 | J8: =1-BaselineCalc!$B$5 | K8: =Scenarios!G3 | L8: =BaselineCalc!$B$7 + ROUND(Scenarios!J3*Scenarios!F3,0) | M8: =BaselineCalc!$B$8 + Scenarios!J3 - ROUND(Scenarios!J3*Scenarios!F3,0) | N8: =(L8-D8) + (M8-E8) | O8: =BaselineCalc!$B$22 * N8 | P8: =YearMap!E3 | Q8: =IF(Scenarios!N3="lease", YearMap!F3, YearMap!G3) | R8: =IF(Scenarios!D3=1, Q8*H8, H8) | S8: =IF(Scenarios!E3=1, Q8*I8, I8) | T8: =IF(C8="FY2026", (Scenarios!D3+Scenarios!E3)*BaselineCalc!$B$21, 0) | U8: =(R8+S8+G8*F8)*J8*(1-K8) | V8: =O8*(G8+P8) | W8: =U8+V8+T8 | X8: =IF(F8+O8>0, W8/(F8+O8),"") | Y8: =B8&"|"&C8 | Z8: =INDEX(YearMap!$I$2:$I$6, MATCH(C8, YearMap!$A$2:$A$6, 0)) | AA8: 0 | AB8: 0 | AC8: 0 | AD8: 0 | AE8: 0 | AF8: 0
A9: =Y9 | B9: =Scenarios!A3 | C9: FY2028 | D9: =IF(Scenarios!D3=1,0, L9) | E9: =IF(Scenarios!E3=1,0, M9) | F9: =D9+E9 | G9: =YearMap!B4 | H9: =YearMap!C4 | I9: =YearMap!D4 | J9: =1-BaselineCalc!$B$5 | K9: =Scenarios!G3 | L9: =BaselineCalc!$B$7 + ROUND(Scenarios!K3*Scenarios!F3,0) | M9: =BaselineCalc!$B$8 + Scenarios!K3 - ROUND(Scenarios!K3*Scenarios!F3,0) | N9: =(L9-D9) + (M9-E9) | O9: =BaselineCalc!$B$22 * N9 | P9: =YearMap!E4 | Q9: =IF(Scenarios!N3="lease", YearMap!F4, YearMap!G4) | R9: =IF(Scenarios!D3=1, Q9*H9, H9) | S9: =IF(Scenarios!E3=1, Q9*I9, I9) | T9: =IF(C9="FY2026", (Scenarios!D3+Scenarios!E3)*BaselineCalc!$B$21, 0) | U9: =(R9+S9+G9*F9)*J9*(1-K9) | V9: =O9*(G9+P9) | W9: =U9+V9+T9 | X9: =IF(F9+O9>0, W9/(F9+O9),"") | Y9: =B9&"|"&C9 | Z9: =INDEX(YearMap!$I$2:$I$6, MATCH(C9, YearMap!$A$2:$A$6, 0)) | AA9: 0 | AB9: 0 | AC9: 0 | AD9: 0 | AE9: 0 | AF9: 0
A10: =Y10 | B10: =Scenarios!A3 | C10: FY2029 | D10: =IF(Scenarios!D3=1,0, L10) | E10: =IF(Scenarios!E3=1,0, M10) | F10: =D10+E10 | G10: =YearMap!B5 | H10: =YearMap!C5 | I10: =YearMap!D5 | J10: =1-BaselineCalc!$B$5 | K10: =Scenarios!G3 | L10: =BaselineCalc!$B$7 + ROUND(Scenarios!L3*Scenarios!F3,0) | M10: =BaselineCalc!$B$8 + Scenarios!L3 - ROUND(Scenarios!L3*Scenarios!F3,0) | N10: =(L10-D10) + (M10-E10) | O10: =BaselineCalc!$B$22 * N10 | P10: =YearMap!E5 | Q10: =IF(Scenarios!N3="lease", YearMap!F5, YearMap!G5) | R10: =IF(Scenarios!D3=1, Q10*H10, H10) | S10: =IF(Scenarios!E3=1, Q10*I10, I10) | T10: =IF(C10="FY2026", (Scenarios!D3+Scenarios!E3)*BaselineCalc!$B$21, 0) | U10: =(R10+S10+G10*F10)*J10*(1-K10) | V10: =O10*(G10+P10) | W10: =U10+V10+T10 | X10: =IF(F10+O10>0, W10/(F10+O10),"") | Y10: =B10&"|"&C10 | Z10: =INDEX(YearMap!$I$2:$I$6, MATCH(C10, YearMap!$A$2:$A$6, 0)) | AA10: 0 | AB10: 0 | AC10: 0 | AD10: 0 | AE10: 0 | AF10: 0
A11: =Y11 | B11: =Scenarios!A3 | C11: FY2030 | D11: =IF(Scenarios!D3=1,0, L11) | E11: =IF(Scenarios!E3=1,0, M11) | F11: =D11+E11 | G11: =YearMap!B6 | H11: =YearMap!C6 | I11: =YearMap!D6 | J11: =1-BaselineCalc!$B$5 | K11: =Scenarios!G3 | L11: =BaselineCalc!$B$7 + ROUND(Scenarios!M3*Scenarios!F3,0) | M11: =BaselineCalc!$B$8 + Scenarios!M3 - ROUND(Scenarios!M3*Scenarios!F3,0) | N11: =(L11-D11) + (M11-E11) | O11: =BaselineCalc!$B$22 * N11 | P11: =YearMap!E6 | Q11: =IF(Scenarios!N3="lease", YearMap!F6, YearMap!G6) | R11: =IF(Scenarios!D3=1, Q11*H11, H11) | S11: =IF(Scenarios!E3=1, Q11*I11, I11) | T11: =IF(C11="FY2026", (Scenarios!D3+Scenarios!E3)*BaselineCalc!$B$21, 0) | U11: =(R11+S11+G11*F11)*J11*(1-K11) | V11: =O11*(G11+P11) | W11: =U11+V11+T11 | X11: =IF(F11+O11>0, W11/(F11+O11),"") | Y11: =B11&"|"&C11 | Z11: =INDEX(YearMap!$I$2:$I$6, MATCH(C11, YearMap!$A$2:$A$6, 0)) | AA11: 0 | AB11: 0 | AC11: 0 | AD11: 0 | AE11: 0 | AF11: 0
A12: =Y12 | B12: =Scenarios!A4 | C12: FY2026 | D12: =IF(Scenarios!D4=1,0, L12) | E12: =IF(Scenarios!E4=1,0, M12) | F12: =D12+E12 | G12: =YearMap!B2 | H12: =YearMap!C2 | I12: =YearMap!D2 | J12: =1-BaselineCalc!$B$5 | K12: =Scenarios!G4 | L12: =BaselineCalc!$B$7 + ROUND(Scenarios!I4*Scenarios!F4,0) | M12: =BaselineCalc!$B$8 + Scenarios!I4 - ROUND(Scenarios!I4*Scenarios!F4,0) | N12: =(L12-D12) + (M12-E12) | O12: =BaselineCalc!$B$22 * N12 | P12: =YearMap!E2 | Q12: =IF(Scenarios!N4="lease", YearMap!F2, YearMap!G2) | R12: =IF(Scenarios!D4=1, Q12*H12, H12) | S12: =IF(Scenarios!E4=1, Q12*I12, I12) | T12: =IF(C12="FY2026", (Scenarios!D4+Scenarios!E4)*BaselineCalc!$B$21, 0) | U12: =(R12+S12+G12*F12)*J12*(1-K12) | V12: =O12*(G12+P12) | W12: =U12+V12+T12 | X12: =IF(F12+O12>0, W12/(F12+O12),"") | Y12: =B12&"|"&C12 | Z12: =INDEX(YearMap!$I$2:$I$6, MATCH(C12, YearMap!$A$2:$A$6, 0)) | AA12: 0 | AB12: 0 | AC12: 0 | AD12: 0 | AE12: 0 | AF12: 0
A13: =Y13 | B13: =Scenarios!A4 | C13: FY2027 | D13: =IF(Scenarios!D4=1,0, L13) | E13: =IF(Scenarios!E4=1,0, M13) | F13: =D13+E13 | G13: =YearMap!B3 | H13: =YearMap!C3 | I13: =YearMap!D3 | J13: =1-BaselineCalc!$B$5 | K13: =Scenarios!G4 | L13: =BaselineCalc!$B$7 + ROUND(Scenarios!J4*Scenarios!F4,0) | M13: =BaselineCalc!$B$8 + Scenarios!J4 - ROUND(Scenarios!J4*Scenarios!F4,0) | N13: =(L13-D13) + (M13-E13) | O13: =BaselineCalc!$B$22 * N13 | P13: =YearMap!E3 | Q13: =IF(Scenarios!N4="lease", YearMap!F3, YearMap!G3) | R13: =IF(Scenarios!D4=1, Q13*H13, H13) | S13: =IF(Scenarios!E4=1, Q13*I13, I13) | T13: =IF(C13="FY2026", (Scenarios!D4+Scenarios!E4)*BaselineCalc!$B$21, 0) | U13: =(R13+S13+G13*F13)*J13*(1-K13) | V13: =O13*(G13+P13) | W13: =U13+V13+T13 | X13: =IF(F13+O13>0, W13/(F13+O13),"") | Y13: =B13&"|"&C13 | Z13: =INDEX(YearMap!$I$2:$I$6, MATCH(C13, YearMap!$A$2:$A$6, 0)) | AA13: 0 | AB13: 0 | AC13: 0 | AD13: 0 | AE13: 0 | AF13: 0
A14: =Y14 | B14: =Scenarios!A4 | C14: FY2028 | D14: =IF(Scenarios!D4=1,0, L14) | E14: =IF(Scenarios!E4=1,0, M14) | F14: =D14+E14 | G14: =YearMap!B4 | H14: =YearMap!C4 | I14: =YearMap!D4 | J14: =1-BaselineCalc!$B$5 | K14: =Scenarios!G4 | L14: =BaselineCalc!$B$7 + ROUND(Scenarios!K4*Scenarios!F4,0) | M14: =BaselineCalc!$B$8 + Scenarios!K4 - ROUND(Scenarios!K4*Scenarios!F4,0) | N14: =(L14-D14) + (M14-E14) | O14: =BaselineCalc!$B$22 * N14 | P14: =YearMap!E4 | Q14: =IF(Scenarios!N4="lease", YearMap!F4, YearMap!G4) | R14: =IF(Scenarios!D4=1, Q14*H14, H14) | S14: =IF(Scenarios!E4=1, Q14*I14, I14) | T14: =IF(C14="FY2026", (Scenarios!D4+Scenarios!E4)*BaselineCalc!$B$21, 0) | U14: =(R14+S14+G14*F14)*J14*(1-K14) | V14: =O14*(G14+P14) | W14: =U14+V14+T14 | X14: =IF(F14+O14>0, W14/(F14+O14),"") | Y14: =B14&"|"&C14 | Z14: =INDEX(YearMap!$I$2:$I$6, MATCH(C14, YearMap!$A$2:$A$6, 0)) | AA14: 0 | AB14: 0 | AC14: 0 | AD14: 0 | AE14: 0 | AF14: 0
A15: =Y15 | B15: =Scenarios!A4 | C15: FY2029 | D15: =IF(Scenarios!D4=1,0, L15) | E15: =IF(Scenarios!E4=1,0, M15) | F15: =D15+E15 | G15: =YearMap!B5 | H15: =YearMap!C5 | I15: =YearMap!D5 | J15: =1-BaselineCalc!$B$5 | K15: =Scenarios!G4 | L15: =BaselineCalc!$B$7 + ROUND(Scenarios!L4*Scenarios!F4,0) | M15: =BaselineCalc!$B$8 + Scenarios!L4 - ROUND(Scenarios!L4*Scenarios!F4,0) | N15: =(L15-D15) + (M15-E15) | O15: =BaselineCalc!$B$22 * N15 | P15: =YearMap!E5 | Q15: =IF(Scenarios!N4="lease", YearMap!F5, YearMap!G5) | R15: =IF(Scenarios!D4=1, Q15*H15, H15) | S15: =IF(Scenarios!E4=1, Q15*I15, I15) | T15: =IF(C15="FY2026", (Scenarios!D4+Scenarios!E4)*BaselineCalc!$B$21, 0) | U15: =(R15+S15+G15*F15)*J15*(1-K15) | V15: =O15*(G15+P15) | W15: =U15+V15+T15 | X15: =IF(F15+O15>0, W15/(F15+O15),"") | Y15: =B15&"|"&C15 | Z15: =INDEX(YearMap!$I$2:$I$6, MATCH(C15, YearMap!$A$2:$A$6, 0)) | AA15: 0 | AB15: 0 | AC15: 0 | AD15: 0 | AE15: 0 | AF15: 0
A16: =Y16 | B16: =Scenarios!A4 | C16: FY2030 | D16: =IF(Scenarios!D4=1,0, L16) | E16: =IF(Scenarios!E4=1,0, M16) | F16: =D16+E16 | G16: =YearMap!B6 | H16: =YearMap!C6 | I16: =YearMap!D6 | J16: =1-BaselineCalc!$B$5 | K16: =Scenarios!G4 | L16: =BaselineCalc!$B$7 + ROUND(Scenarios!M4*Scenarios!F4,0) | M16: =BaselineCalc!$B$8 + Scenarios!M4 - ROUND(Scenarios!M4*Scenarios!F4,0) | N16: =(L16-D16) + (M16-E16) | O16: =BaselineCalc!$B$22 * N16 | P16: =YearMap!E6 | Q16: =IF(Scenarios!N4="lease", YearMap!F6, YearMap!G6) | R16: =IF(Scenarios!D4=1, Q16*H16, H16) | S16: =IF(Scenarios!E4=1, Q16*I16, I16) | T16: =IF(C16="FY2026", (Scenarios!D4+Scenarios!E4)*BaselineCalc!$B$21, 0) | U16: =(R16+S16+G16*F16)*J16*(1-K16) | V16: =O16*(G16+P16) | W16: =U16+V16+T16 | X16: =IF(F16+O16>0, W16/(F16+O16),"") | Y16: =B16&"|"&C16 | Z16: =INDEX(YearMap!$I$2:$I$6, MATCH(C16, YearMap!$A$2:$A$6, 0)) | AA16: 0 | AB16: 0 | AC16: 0 | AD16: 0 | AE16: 0 | AF16: 0
A17: =Y17 | B17: =Scenarios!A5 | C17: FY2026 | D17: =IF(Scenarios!D5=1,0, L17) | E17: =IF(Scenarios!E5=1,0, M17) | F17: =D17+E17 | G17: =YearMap!B2 | H17: =YearMap!C2 | I17: =YearMap!D2 | J17: =1-BaselineCalc!$B$5 | K17: =Scenarios!G5 | L17: =BaselineCalc!$B$7 + ROUND(Scenarios!I5*Scenarios!F5,0) | M17: =BaselineCalc!$B$8 + Scenarios!I5 - ROUND(Scenarios!I5*Scenarios!F5,0) | N17: =(L17-D17) + (M17-E17) | O17: =BaselineCalc!$B$22 * N17 | P17: =YearMap!E2 | Q17: =IF(Scenarios!N5="lease", YearMap!F2, YearMap!G2) | R17: =IF(Scenarios!D5=1, Q17*H17, H17) | S17: =IF(Scenarios!E5=1, Q17*I17, I17) | T17: =IF(C17="FY2026", (Scenarios!D5+Scenarios!E5)*BaselineCalc!$B$21, 0) | U17: =(R17+S17+G17*F17)*J17*(1-K17) | V17: =O17*(G17+P17) | W17: =U17+V17+T17 | X17: =IF(F17+O17>0, W17/(F17+O17),"") | Y17: =B17&"|"&C17 | Z17: =INDEX(YearMap!$I$2:$I$6, MATCH(C17, YearMap!$A$2:$A$6, 0)) | AA17: 0 | AB17: 0 | AC17: 0 | AD17: 0 | AE17: 0 | AF17: 0
A18: =Y18 | B18: =Scenarios!A5 | C18: FY2027 | D18: =IF(Scenarios!D5=1,0, L18) | E18: =IF(Scenarios!E5=1,0, M18) | F18: =D18+E18 | G18: =YearMap!B3 | H18: =YearMap!C3 | I18: =YearMap!D3 | J18: =1-BaselineCalc!$B$5 | K18: =Scenarios!G5 | L18: =BaselineCalc!$B$7 + ROUND(Scenarios!J5*Scenarios!F5,0) | M18: =BaselineCalc!$B$8 + Scenarios!J5 - ROUND(Scenarios!J5*Scenarios!F5,0) | N18: =(L18-D18) + (M18-E18) | O18: =BaselineCalc!$B$22 * N18 | P18: =YearMap!E3 | Q18: =IF(Scenarios!N5="lease", YearMap!F3, YearMap!G3) | R18: =IF(Scenarios!D5=1, Q18*H18, H18) | S18: =IF(Scenarios!E5=1, Q18*I18, I18) | T18: =IF(C18="FY2026", (Scenarios!D5+Scenarios!E5)*BaselineCalc!$B$21, 0) | U18: =(R18+S18+G18*F18)*J18*(1-K18) | V18: =O18*(G18+P18) | W18: =U18+V18+T18 | X18: =IF(F18+O18>0, W18/(F18+O18),"") | Y18: =B18&"|"&C18 | Z18: =INDEX(YearMap!$I$2:$I$6, MATCH(C18, YearMap!$A$2:$A$6, 0)) | AA18: 0 | AB18: 0 | AC18: 0 | AD18: 0 | AE18: 0 | AF18: 0
A19: =Y19 | B19: =Scenarios!A5 | C19: FY2028 | D19: =IF(Scenarios!D5=1,0, L19) | E19: =IF(Scenarios!E5=1,0, M19) | F19: =D19+E19 | G19: =YearMap!B4 | H19: =YearMap!C4 | I19: =YearMap!D4 | J19: =1-BaselineCalc!$B$5 | K19: =Scenarios!G5 | L19: =BaselineCalc!$B$7 + ROUND(Scenarios!K5*Scenarios!F5,0) | M19: =BaselineCalc!$B$8 + Scenarios!K5 - ROUND(Scenarios!K5*Scenarios!F5,0) | N19: =(L19-D19) + (M19-E19) | O19: =BaselineCalc!$B$22 * N19 | P19: =YearMap!E4 | Q19: =IF(Scenarios!N5="lease", YearMap!F4, YearMap!G4) | R19: =IF(Scenarios!D5=1, Q19*H19, H19) | S19: =IF(Scenarios!E5=1, Q19*I19, I19) | T19: =IF(C19="FY2026", (Scenarios!D5+Scenarios!E5)*BaselineCalc!$B$21, 0) | U19: =(R19+S19+G19*F19)*J19*(1-K19) | V19: =O19*(G19+P19) | W19: =U19+V19+T19 | X19: =IF(F19+O19>0, W19/(F19+O19),"") | Y19: =B19&"|"&C19 | Z19: =INDEX(YearMap!$I$2:$I$6, MATCH(C19, YearMap!$A$2:$A$6, 0)) | AA19: 0 | AB19: 0 | AC19: 0 | AD19: 0 | AE19: 0 | AF19: 0
A20: =Y20 | B20: =Scenarios!A5 | C20: FY2029 | D20: =IF(Scenarios!D5=1,0, L20) | E20: =IF(Scenarios!E5=1,0, M20) | F20: =D20+E20 | G20: =YearMap!B5 | H20: =YearMap!C5 | I20: =YearMap!D5 | J20: =1-BaselineCalc!$B$5 | K20: =Scenarios!G5 | L20: =BaselineCalc!$B$7 + ROUND(Scenarios!L5*Scenarios!F5,0) | M20: =BaselineCalc!$B$8 + Scenarios!L5 - ROUND(Scenarios!L5*Scenarios!F5,0) | N20: =(L20-D20) + (M20-E20) | O20: =BaselineCalc!$B$22 * N20 | P20: =YearMap!E5 | Q20: =IF(Scenarios!N5="lease", YearMap!F5, YearMap!G5) | R20: =IF(Scenarios!D5=1, Q20*H20, H20) | S20: =IF(Scenarios!E5=1, Q20*I20, I20) | T20: =IF(C20="FY2026", (Scenarios!D5+Scenarios!E5)*BaselineCalc!$B$21, 0) | U20: =(R20+S20+G20*F20)*J20*(1-K20) | V20: =O20*(G20+P20) | W20: =U20+V20+T20 | X20: =IF(F20+O20>0, W20/(F20+O20),"") | Y20: =B20&"|"&C20 | Z20: =INDEX(YearMap!$I$2:$I$6, MATCH(C20, YearMap!$A$2:$A$6, 0)) | AA20: 0 | AB20: 0 | AC20: 0 | AD20: 0 | AE20: 0 | AF20: 0
A21: =Y21 | B21: =Scenarios!A5 | C21: FY2030 | D21: =IF(Scenarios!D5=1,0, L21) | E21: =IF(Scenarios!E5=1,0, M21) | F21: =D21+E21 | G21: =YearMap!B6 | H21: =YearMap!C6 | I21: =YearMap!D6 | J21: =1-BaselineCalc!$B$5 | K21: =Scenarios!G5 | L21: =BaselineCalc!$B$7 + ROUND(Scenarios!M5*Scenarios!F5,0) | M21: =BaselineCalc!$B$8 + Scenarios!M5 - ROUND(Scenarios!M5*Scenarios!F5,0) | N21: =(L21-D21) + (M21-E21) | O21: =BaselineCalc!$B$22 * N21 | P21: =YearMap!E6 | Q21: =IF(Scenarios!N5="lease", YearMap!F6, YearMap!G6) | R21: =IF(Scenarios!D5=1, Q21*H21, H21) | S21: =IF(Scenarios!E5=1, Q21*I21, I21) | T21: =IF(C21="FY2026", (Scenarios!D5+Scenarios!E5)*BaselineCalc!$B$21, 0) | U21: =(R21+S21+G21*F21)*J21*(1-K21) | V21: =O21*(G21+P21) | W21: =U21+V21+T21 | X21: =IF(F21+O21>0, W21/(F21+O21),"") | Y21: =B21&"|"&C21 | Z21: =INDEX(YearMap!$I$2:$I$6, MATCH(C21, YearMap!$A$2:$A$6, 0)) | AA21: 0 | AB21: 0 | AC21: 0 | AD21: 0 | AE21: 0 | AF21: 0
A22: =Y22 | B22: =Scenarios!A6 | C22: FY2026 | D22: =IF(Scenarios!D6=1,0, L22) | E22: =IF(Scenarios!E6=1,0, M22) | F22: =D22+E22 | G22: =YearMap!B2 | H22: =YearMap!C2 | I22: =YearMap!D2 | J22: =1-BaselineCalc!$B$5 | K22: =Scenarios!G6 | L22: =BaselineCalc!$B$7 + ROUND(Scenarios!I6*Scenarios!F6,0) | M22: =BaselineCalc!$B$8 + Scenarios!I6 - ROUND(Scenarios!I6*Scenarios!F6,0) | N22: =(L22-D22) + (M22-E22) | O22: =BaselineCalc!$B$22 * N22 | P22: =YearMap!E2 | Q22: =IF(Scenarios!N6="lease", YearMap!F2, YearMap!G2) | R22: =IF(Scenarios!D6=1, Q22*H22, H22) | S22: =IF(Scenarios!E6=1, Q22*I22, I22) | T22: =IF(C22="FY2026", (Scenarios!D6+Scenarios!E6)*BaselineCalc!$B$21, 0) | U22: =(R22+S22+G22*F22)*J22*(1-K22) | V22: =O22*(G22+P22) | W22: =U22+V22+T22 | X22: =IF(F22+O22>0, W22/(F22+O22),"") | Y22: =B22&"|"&C22 | Z22: =INDEX(YearMap!$I$2:$I$6, MATCH(C22, YearMap!$A$2:$A$6, 0)) | AA22: 0 | AB22: 0 | AC22: 0 | AD22: 0 | AE22: 0 | AF22: 0
A23: =Y23 | B23: =Scenarios!A6 | C23: FY2027 | D23: =IF(Scenarios!D6=1,0, L23) | E23: =IF(Scenarios!E6=1,0, M23) | F23: =D23+E23 | G23: =YearMap!B3 | H23: =YearMap!C3 | I23: =YearMap!D3 | J23: =1-BaselineCalc!$B$5 | K23: =Scenarios!G6 | L23: =BaselineCalc!$B$7 + ROUND(Scenarios!J6*Scenarios!F6,0) | M23: =BaselineCalc!$B$8 + Scenarios!J6 - ROUND(Scenarios!J6*Scenarios!F6,0) | N23: =(L23-D23) + (M23-E23) | O23: =BaselineCalc!$B$22 * N23 | P23: =YearMap!E3 | Q23: =IF(Scenarios!N6="lease", YearMap!F3, YearMap!G3) | R23: =IF(Scenarios!D6=1, Q23*H23, H23) | S23: =IF(Scenarios!E6=1, Q23*I23, I23) | T23: =IF(C23="FY2026", (Scenarios!D6+Scenarios!E6)*BaselineCalc!$B$21, 0) | U23: =(R23+S23+G23*F23)*J23*(1-K23) | V23: =O23*(G23+P23) | W23: =U23+V23+T23 | X23: =IF(F23+O23>0, W23/(F23+O23),"") | Y23: =B23&"|"&C23 | Z23: =INDEX(YearMap!$I$2:$I$6, MATCH(C23, YearMap!$A$2:$A$6, 0)) | AA23: 0 | AB23: 0 | AC23: 0 | AD23: 0 | AE23: 0 | AF23: 0
A24: =Y24 | B24: =Scenarios!A6 | C24: FY2028 | D24: =IF(Scenarios!D6=1,0, L24) | E24: =IF(Scenarios!E6=1,0, M24) | F24: =D24+E24 | G24: =YearMap!B4 | H24: =YearMap!C4 | I24: =YearMap!D4 | J24: =1-BaselineCalc!$B$5 | K24: =Scenarios!G6 | L24: =BaselineCalc!$B$7 + ROUND(Scenarios!K6*Scenarios!F6,0) | M24: =BaselineCalc!$B$8 + Scenarios!K6 - ROUND(Scenarios!K6*Scenarios!F6,0) | N24: =(L24-D24) + (M24-E24) | O24: =BaselineCalc!$B$22 * N24 | P24: =YearMap!E4 | Q24: =IF(Scenarios!N6="lease", YearMap!F4, YearMap!G4) | R24: =IF(Scenarios!D6=1, Q24*H24, H24) | S24: =IF(Scenarios!E6=1, Q24*I24, I24) | T24: =IF(C24="FY2026", (Scenarios!D6+Scenarios!E6)*BaselineCalc!$B$21, 0) | U24: =(R24+S24+G24*F24)*J24*(1-K24) | V24: =O24*(G24+P24) | W24: =U24+V24+T24 | X24: =IF(F24+O24>0, W24/(F24+O24),"") | Y24: =B24&"|"&C24 | Z24: =INDEX(YearMap!$I$2:$I$6, MATCH(C24, YearMap!$A$2:$A$6, 0)) | AA24: 0 | AB24: 0 | AC24: 0 | AD24: 0 | AE24: 0 | AF24: 0
A25: =Y25 | B25: =Scenarios!A6 | C25: FY2029 | D25: =IF(Scenarios!D6=1,0, L25) | E25: =IF(Scenarios!E6=1,0, M25) | F25: =D25+E25 | G25: =YearMap!B5 | H25: =YearMap!C5 | I25: =YearMap!D5 | J25: =1-BaselineCalc!$B$5 | K25: =Scenarios!G6 | L25: =BaselineCalc!$B$7 + ROUND(Scenarios!L6*Scenarios!F6,0) | M25: =BaselineCalc!$B$8 + Scenarios!L6 - ROUND(Scenarios!L6*Scenarios!F6,0) | N25: =(L25-D25) + (M25-E25) | O25: =BaselineCalc!$B$22 * N25 | P25: =YearMap!E5 | Q25: =IF(Scenarios!N6="lease", YearMap!F5, YearMap!G5) | R25: =IF(Scenarios!D6=1, Q25*H25, H25) | S25: =IF(Scenarios!E6=1, Q25*I25, I25) | T25: =IF(C25="FY2026", (Scenarios!D6+Scenarios!E6)*BaselineCalc!$B$21, 0) | U25: =(R25+S25+G25*F25)*J25*(1-K25) | V25: =O25*(G25+P25) | W25: =U25+V25+T25 | X25: =IF(F25+O25>0, W25/(F25+O25),"") | Y25: =B25&"|"&C25 | Z25: =INDEX(YearMap!$I$2:$I$6, MATCH(C25, YearMap!$A$2:$A$6, 0)) | AA25: 0 | AB25: 0 | AC25: 0 | AD25: 0 | AE25: 0 | AF25: 0
A26: =Y26 | B26: =Scenarios!A6 | C26: FY2030 | D26: =IF(Scenarios!D6=1,0, L26) | E26: =IF(Scenarios!E6=1,0, M26) | F26: =D26+E26 | G26: =YearMap!B6 | H26: =YearMap!C6 | I26: =YearMap!D6 | J26: =1-BaselineCalc!$B$5 | K26: =Scenarios!G6 | L26: =BaselineCalc!$B$7 + ROUND(Scenarios!M6*Scenarios!F6,0) | M26: =BaselineCalc!$B$8 + Scenarios!M6 - ROUND(Scenarios!M6*Scenarios!F6,0) | N26: =(L26-D26) + (M26-E26) | O26: =BaselineCalc!$B$22 * N26 | P26: =YearMap!E6 | Q26: =IF(Scenarios!N6="lease", YearMap!F6, YearMap!G6) | R26: =IF(Scenarios!D6=1, Q26*H26, H26) | S26: =IF(Scenarios!E6=1, Q26*I26, I26) | T26: =IF(C26="FY2026", (Scenarios!D6+Scenarios!E6)*BaselineCalc!$B$21, 0) | U26: =(R26+S26+G26*F26)*J26*(1-K26) | V26: =O26*(G26+P26) | W26: =U26+V26+T26 | X26: =IF(F26+O26>0, W26/(F26+O26),"") | Y26: =B26&"|"&C26 | Z26: =INDEX(YearMap!$I$2:$I$6, MATCH(C26, YearMap!$A$2:$A$6, 0)) | AA26: 0 | AB26: 0 | AC26: 0 | AD26: 0 | AE26: 0 | AF26: 0
A27: =Y27 | B27: =Scenarios!A7 | C27: FY2026 | D27: =IF(Scenarios!D7=1,0, L27) | E27: =IF(Scenarios!E7=1,0, M27) | F27: =D27+E27 | G27: =YearMap!B2 | H27: =YearMap!C2 | I27: =YearMap!D2 | J27: =1-BaselineCalc!$B$5 | K27: =Scenarios!G7 | L27: =BaselineCalc!$B$7 + ROUND(Scenarios!I7*Scenarios!F7,0) | M27: =BaselineCalc!$B$8 + Scenarios!I7 - ROUND(Scenarios!I7*Scenarios!F7,0) | N27: =(L27-D27) + (M27-E27) | O27: =BaselineCalc!$B$22 * N27 | P27: =YearMap!E2 | Q27: =IF(Scenarios!N7="lease", YearMap!F2, YearMap!G2) | R27: =IF(Scenarios!D7=1, Q27*H27, H27) | S27: =IF(Scenarios!E7=1, Q27*I27, I27) | T27: =IF(C27="FY2026", (Scenarios!D7+Scenarios!E7)*BaselineCalc!$B$21, 0) | U27: =(R27+S27+G27*F27)*J27*(1-K27) | V27: =O27*(G27+P27) | W27: =U27+V27+T27 | X27: =IF(F27+O27>0, W27/(F27+O27),"") | Y27: =B27&"|"&C27 | Z27: =INDEX(YearMap!$I$2:$I$6, MATCH(C27, YearMap!$A$2:$A$6, 0)) | AA27: 0 | AB27: 0 | AC27: 0 | AD27: 0 | AE27: 0 | AF27: 0
A28: =Y28 | B28: =Scenarios!A7 | C28: FY2027 | D28: =IF(Scenarios!D7=1,0, L28) | E28: =IF(Scenarios!E7=1,0, M28) | F28: =D28+E28 | G28: =YearMap!B3 | H28: =YearMap!C3 | I28: =YearMap!D3 | J28: =1-BaselineCalc!$B$5 | K28: =Scenarios!G7 | L28: =BaselineCalc!$B$7 + ROUND(Scenarios!J7*Scenarios!F7,0) | M28: =BaselineCalc!$B$8 + Scenarios!J7 - ROUND(Scenarios!J7*Scenarios!F7,0) | N28: =(L28-D28) + (M28-E28) | O28: =BaselineCalc!$B$22 * N28 | P28: =YearMap!E3 | Q28: =IF(Scenarios!N7="lease", YearMap!F3, YearMap!G3) | R28: =IF(Scenarios!D7=1, Q28*H28, H28) | S28: =IF(Scenarios!E7=1, Q28*I28, I28) | T28: =IF(C28="FY2026", (Scenarios!D7+Scenarios!E7)*BaselineCalc!$B$21, 0) | U28: =(R28+S28+G28*F28)*J28*(1-K28) | V28: =O28*(G28+P28) | W28: =U28+V28+T28 | X28: =IF(F28+O28>0, W28/(F28+O28),"") | Y28: =B28&"|"&C28 | Z28: =INDEX(YearMap!$I$2:$I$6, MATCH(C28, YearMap!$A$2:$A$6, 0)) | AA28: 0 | AB28: 0 | AC28: 0 | AD28: 0 | AE28: 0 | AF28: 0
A29: =Y29 | B29: =Scenarios!A7 | C29: FY2028 | D29: =IF(Scenarios!D7=1,0, L29) | E29: =IF(Scenarios!E7=1,0, M29) | F29: =D29+E29 | G29: =YearMap!B4 | H29: =YearMap!C4 | I29: =YearMap!D4 | J29: =1-BaselineCalc!$B$5 | K29: =Scenarios!G7 | L29: =BaselineCalc!$B$7 + ROUND(Scenarios!K7*Scenarios!F7,0) | M29: =BaselineCalc!$B$8 + Scenarios!K7 - ROUND(Scenarios!K7*Scenarios!F7,0) | N29: =(L29-D29) + (M29-E29) | O29: =BaselineCalc!$B$22 * N29 | P29: =YearMap!E4 | Q29: =IF(Scenarios!N7="lease", YearMap!F4, YearMap!G4) | R29: =IF(Scenarios!D7=1, Q29*H29, H29) | S29: =IF(Scenarios!E7=1, Q29*I29, I29) | T29: =IF(C29="FY2026", (Scenarios!D7+Scenarios!E7)*BaselineCalc!$B$21, 0) | U29: =(R29+S29+G29*F29)*J29*(1-K29) | V29: =O29*(G29+P29) | W29: =U29+V29+T29 | X29: =IF(F29+O29>0, W29/(F29+O29),"") | Y29: =B29&"|"&C29 | Z29: =INDEX(YearMap!$I$2:$I$6, MATCH(C29, YearMap!$A$2:$A$6, 0)) | AA29: 0 | AB29: 0 | AC29: 0 | AD29: 0 | AE29: 0 | AF29: 0
A30: =Y30 | B30: =Scenarios!A7 | C30: FY2029 | D30: =IF(Scenarios!D7=1,0, L30) | E30: =IF(Scenarios!E7=1,0, M30) | F30: =D30+E30 | G30: =YearMap!B5 | H30: =YearMap!C5 | I30: =YearMap!D5 | J30: =1-BaselineCalc!$B$5 | K30: =Scenarios!G7 | L30: =BaselineCalc!$B$7 + ROUND(Scenarios!L7*Scenarios!F7,0) | M30: =BaselineCalc!$B$8 + Scenarios!L7 - ROUND(Scenarios!L7*Scenarios!F7,0) | N30: =(L30-D30) + (M30-E30) | O30: =BaselineCalc!$B$22 * N30 | P30: =YearMap!E5 | Q30: =IF(Scenarios!N7="lease", YearMap!F5, YearMap!G5) | R30: =IF(Scenarios!D7=1, Q30*H30, H30) | S30: =IF(Scenarios!E7=1, Q30*I30, I30) | T30: =IF(C30="FY2026", (Scenarios!D7+Scenarios!E7)*BaselineCalc!$B$21, 0) | U30: =(R30+S30+G30*F30)*J30*(1-K30) | V30: =O30*(G30+P30) | W30: =U30+V30+T30 | X30: =IF(F30+O30>0, W30/(F30+O30),"") | Y30: =B30&"|"&C30 | Z30: =INDEX(YearMap!$I$2:$I$6, MATCH(C30, YearMap!$A$2:$A$6, 0)) | AA30: 0 | AB30: 0 | AC30: 0 | AD30: 0 | AE30: 0 | AF30: 0
A31: =Y31 | B31: =Scenarios!A7 | C31: FY2030 | D31: =IF(Scenarios!D7=1,0, L31) | E31: =IF(Scenarios!E7=1,0, M31) | F31: =D31+E31 | G31: =YearMap!B6 | H31: =YearMap!C6 | I31: =YearMap!D6 | J31: =1-BaselineCalc!$B$5 | K31: =Scenarios!G7 | L31: =BaselineCalc!$B$7 + ROUND(Scenarios!M7*Scenarios!F7,0) | M31: =BaselineCalc!$B$8 + Scenarios!M7 - ROUND(Scenarios!M7*Scenarios!F7,0) | N31: =(L31-D31) + (M31-E31) | O31: =BaselineCalc!$B$22 * N31 | P31: =YearMap!E6 | Q31: =IF(Scenarios!N7="lease", YearMap!F6, YearMap!G6) | R31: =IF(Scenarios!D7=1, Q31*H31, H31) | S31: =IF(Scenarios!E7=1, Q31*I31, I31) | T31: =IF(C31="FY2026", (Scenarios!D7+Scenarios!E7)*BaselineCalc!$B$21, 0) | U31: =(R31+S31+G31*F31)*J31*(1-K31) | V31: =O31*(G31+P31) | W31: =U31+V31+T31 | X31: =IF(F31+O31>0, W31/(F31+O31),"") | Y31: =B31&"|"&C31 | Z31: =INDEX(YearMap!$I$2:$I$6, MATCH(C31, YearMap!$A$2:$A$6, 0)) | AA31: 0 | AB31: 0 | AC31: 0 | AD31: 0 | AE31: 0 | AF31: 0
A32: =Y32 | B32: =Scenarios!A8 | C32: FY2026 | D32: =IF(Scenarios!D8=1,0, L32) | E32: =IF(Scenarios!E8=1,0, M32) | F32: =D32+E32 | G32: =YearMap!B2 | H32: =YearMap!C2 | I32: =YearMap!D2 | J32: =1-BaselineCalc!$B$5 | K32: =Scenarios!G8 | L32: =BaselineCalc!$B$7 + ROUND(Scenarios!I8*Scenarios!F8,0) | M32: =BaselineCalc!$B$8 + Scenarios!I8 - ROUND(Scenarios!I8*Scenarios!F8,0) | N32: =(L32-D32) + (M32-E32) | O32: =BaselineCalc!$B$22 * N32 | P32: =YearMap!E2 | Q32: =IF(Scenarios!N8="lease", YearMap!F2, YearMap!G2) | R32: =IF(Scenarios!D8=1, Q32*H32, H32) | S32: =IF(Scenarios!E8=1, Q32*I32, I32) | T32: =IF(C32="FY2026", (Scenarios!D8+Scenarios!E8)*BaselineCalc!$B$21, 0) | U32: =(R32+S32+G32*F32)*J32*(1-K32) | V32: =O32*(G32+P32) | W32: =U32+V32+T32 | X32: =IF(F32+O32>0, W32/(F32+O32),"") | Y32: =B32&"|"&C32 | Z32: =INDEX(YearMap!$I$2:$I$6, MATCH(C32, YearMap!$A$2:$A$6, 0)) | AA32: 0 | AB32: 0 | AC32: 0 | AD32: 0 | AE32: 0 | AF32: 0
A33: =Y33 | B33: =Scenarios!A8 | C33: FY2027 | D33: =IF(Scenarios!D8=1,0, L33) | E33: =IF(Scenarios!E8=1,0, M33) | F33: =D33+E33 | G33: =YearMap!B3 | H33: =YearMap!C3 | I33: =YearMap!D3 | J33: =1-BaselineCalc!$B$5 | K33: =Scenarios!G8 | L33: =BaselineCalc!$B$7 + ROUND(Scenarios!J8*Scenarios!F8,0) | M33: =BaselineCalc!$B$8 + Scenarios!J8 - ROUND(Scenarios!J8*Scenarios!F8,0) | N33: =(L33-D33) + (M33-E33) | O33: =BaselineCalc!$B$22 * N33 | P33: =YearMap!E3 | Q33: =IF(Scenarios!N8="lease", YearMap!F3, YearMap!G3) | R33: =IF(Scenarios!D8=1, Q33*H33, H33) | S33: =IF(Scenarios!E8=1, Q33*I33, I33) | T33: =IF(C33="FY2026", (Scenarios!D8+Scenarios!E8)*BaselineCalc!$B$21, 0) | U33: =(R33+S33+G33*F33)*J33*(1-K33) | V33: =O33*(G33+P33) | W33: =U33+V33+T33 | X33: =IF(F33+O33>0, W33/(F33+O33),"") | Y33: =B33&"|"&C33 | Z33: =INDEX(YearMap!$I$2:$I$6, MATCH(C33, YearMap!$A$2:$A$6, 0)) | AA33: 0 | AB33: 0 | AC33: 0 | AD33: 0 | AE33: 0 | AF33: 0
A34: =Y34 | B34: =Scenarios!A8 | C34: FY2028 | D34: =IF(Scenarios!D8=1,0, L34) | E34: =IF(Scenarios!E8=1,0, M34) | F34: =D34+E34 | G34: =YearMap!B4 | H34: =YearMap!C4 | I34: =YearMap!D4 | J34: =1-BaselineCalc!$B$5 | K34: =Scenarios!G8 | L34: =BaselineCalc!$B$7 + ROUND(Scenarios!K8*Scenarios!F8,0) | M34: =BaselineCalc!$B$8 + Scenarios!K8 - ROUND(Scenarios!K8*Scenarios!F8,0) | N34: =(L34-D34) + (M34-E34) | O34: =BaselineCalc!$B$22 * N34 | P34: =YearMap!E4 | Q34: =IF(Scenarios!N8="lease", YearMap!F4, YearMap!G4) | R34: =IF(Scenarios!D8=1, Q34*H34, H34) | S34: =IF(Scenarios!E8=1, Q34*I34, I34) | T34: =IF(C34="FY2026", (Scenarios!D8+Scenarios!E8)*BaselineCalc!$B$21, 0) | U34: =(R34+S34+G34*F34)*J34*(1-K34) | V34: =O34*(G34+P34) | W34: =U34+V34+T34 | X34: =IF(F34+O34>0, W34/(F34+O34),"") | Y34: =B34&"|"&C34 | Z34: =INDEX(YearMap!$I$2:$I$6, MATCH(C34, YearMap!$A$2:$A$6, 0)) | AA34: 0 | AB34: 0 | AC34: 0 | AD34: 0 | AE34: 0 | AF34: 0
A35: =Y35 | B35: =Scenarios!A8 | C35: FY2029 | D35: =IF(Scenarios!D8=1,0, L35) | E35: =IF(Scenarios!E8=1,0, M35) | F35: =D35+E35 | G35: =YearMap!B5 | H35: =YearMap!C5 | I35: =YearMap!D5 | J35: =1-BaselineCalc!$B$5 | K35: =Scenarios!G8 | L35: =BaselineCalc!$B$7 + ROUND(Scenarios!L8*Scenarios!F8,0) | M35: =BaselineCalc!$B$8 + Scenarios!L8 - ROUND(Scenarios!L8*Scenarios!F8,0) | N35: =(L35-D35) + (M35-E35) | O35: =BaselineCalc!$B$22 * N35 | P35: =YearMap!E5 | Q35: =IF(Scenarios!N8="lease", YearMap!F5, YearMap!G5) | R35: =IF(Scenarios!D8=1, Q35*H35, H35) | S35: =IF(Scenarios!E8=1, Q35*I35, I35) | T35: =IF(C35="FY2026", (Scenarios!D8+Scenarios!E8)*BaselineCalc!$B$21, 0) | U35: =(R35+S35+G35*F35)*J35*(1-K35) | V35: =O35*(G35+P35) | W35: =U35+V35+T35 | X35: =IF(F35+O35>0, W35/(F35+O35),"") | Y35: =B35&"|"&C35 | Z35: =INDEX(YearMap!$I$2:$I$6, MATCH(C35, YearMap!$A$2:$A$6, 0)) | AA35: 0 | AB35: 0 | AC35: 0 | AD35: 0 | AE35: 0 | AF35: 0
A36: =Y36 | B36: =Scenarios!A8 | C36: FY2030 | D36: =IF(Scenarios!D8=1,0, L36) | E36: =IF(Scenarios!E8=1,0, M36) | F36: =D36+E36 | G36: =YearMap!B6 | H36: =YearMap!C6 | I36: =YearMap!D6 | J36: =1-BaselineCalc!$B$5 | K36: =Scenarios!G8 | L36: =BaselineCalc!$B$7 + ROUND(Scenarios!M8*Scenarios!F8,0) | M36: =BaselineCalc!$B$8 + Scenarios!M8 - ROUND(Scenarios!M8*Scenarios!F8,0) | N36: =(L36-D36) + (M36-E36) | O36: =BaselineCalc!$B$22 * N36 | P36: =YearMap!E6 | Q36: =IF(Scenarios!N8="lease", YearMap!F6, YearMap!G6) | R36: =IF(Scenarios!D8=1, Q36*H36, H36) | S36: =IF(Scenarios!E8=1, Q36*I36, I36) | T36: =IF(C36="FY2026", (Scenarios!D8+Scenarios!E8)*BaselineCalc!$B$21, 0) | U36: =(R36+S36+G36*F36)*J36*(1-K36) | V36: =O36*(G36+P36) | W36: =U36+V36+T36 | X36: =IF(F36+O36>0, W36/(F36+O36),"") | Y36: =B36&"|"&C36 | Z36: =INDEX(YearMap!$I$2:$I$6, MATCH(C36, YearMap!$A$2:$A$6, 0)) | AA36: 0 | AB36: 0 | AC36: 0 | AD36: 0 | AE36: 0 | AF36: 0
A37: =Y37 | B37: =Scenarios!A9 | C37: FY2026 | D37: =IF(Scenarios!D9=1,0, L37) | E37: =IF(Scenarios!E9=1,0, M37) | F37: =D37+E37 | G37: =YearMap!B2 | H37: =YearMap!C2 | I37: =YearMap!D2 | J37: =1-BaselineCalc!$B$5 | K37: =Scenarios!G9 | L37: =BaselineCalc!$B$7 + ROUND(Scenarios!I9*Scenarios!F9,0) | M37: =BaselineCalc!$B$8 + Scenarios!I9 - ROUND(Scenarios!I9*Scenarios!F9,0) | N37: =(L37-D37) + (M37-E37) | O37: =BaselineCalc!$B$22 * N37 | P37: =YearMap!E2 | Q37: =IF(Scenarios!N9="lease", YearMap!F2, YearMap!G2) | R37: =IF(Scenarios!D9=1, Q37*H37, H37) | S37: =IF(Scenarios!E9=1, Q37*I37, I37) | T37: =IF(C37="FY2026", (Scenarios!D9+Scenarios!E9)*BaselineCalc!$B$21, 0) | U37: =(R37+S37+G37*F37)*J37*(1-K37) | V37: =O37*(G37+P37) | W37: =U37+V37+T37 | X37: =IF(F37+O37>0, W37/(F37+O37),"") | Y37: =B37&"|"&C37 | Z37: =INDEX(YearMap!$I$2:$I$6, MATCH(C37, YearMap!$A$2:$A$6, 0)) | AA37: 0 | AB37: 0 | AC37: 0 | AD37: 0 | AE37: 0 | AF37: 0
A38: =Y38 | B38: =Scenarios!A9 | C38: FY2027 | D38: =IF(Scenarios!D9=1,0, L38) | E38: =IF(Scenarios!E9=1,0, M38) | F38: =D38+E38 | G38: =YearMap!B3 | H38: =YearMap!C3 | I38: =YearMap!D3 | J38: =1-BaselineCalc!$B$5 | K38: =Scenarios!G9 | L38: =BaselineCalc!$B$7 + ROUND(Scenarios!J9*Scenarios!F9,0) | M38: =BaselineCalc!$B$8 + Scenarios!J9 - ROUND(Scenarios!J9*Scenarios!F9,0) | N38: =(L38-D38) + (M38-E38) | O38: =BaselineCalc!$B$22 * N38 | P38: =YearMap!E3 | Q38: =IF(Scenarios!N9="lease", YearMap!F3, YearMap!G3) | R38: =IF(Scenarios!D9=1, Q38*H38, H38) | S38: =IF(Scenarios!E9=1, Q38*I38, I38) | T38: =IF(C38="FY2026", (Scenarios!D9+Scenarios!E9)*BaselineCalc!$B$21, 0) | U38: =(R38+S38+G38*F38)*J38*(1-K38) | V38: =O38*(G38+P38) | W38: =U38+V38+T38 | X38: =IF(F38+O38>0, W38/(F38+O38),"") | Y38: =B38&"|"&C38 | Z38: =INDEX(YearMap!$I$2:$I$6, MATCH(C38, YearMap!$A$2:$A$6, 0)) | AA38: 0 | AB38: 0 | AC38: 0 | AD38: 0 | AE38: 0 | AF38: 0
A39: =Y39 | B39: =Scenarios!A9 | C39: FY2028 | D39: =IF(Scenarios!D9=1,0, L39) | E39: =IF(Scenarios!E9=1,0, M39) | F39: =D39+E39 | G39: =YearMap!B4 | H39: =YearMap!C4 | I39: =YearMap!D4 | J39: =1-BaselineCalc!$B$5 | K39: =Scenarios!G9 | L39: =BaselineCalc!$B$7 + ROUND(Scenarios!K9*Scenarios!F9,0) | M39: =BaselineCalc!$B$8 + Scenarios!K9 - ROUND(Scenarios!K9*Scenarios!F9,0) | N39: =(L39-D39) + (M39-E39) | O39: =BaselineCalc!$B$22 * N39 | P39: =YearMap!E4 | Q39: =IF(Scenarios!N9="lease", YearMap!F4, YearMap!G4) | R39: =IF(Scenarios!D9=1, Q39*H39, H39) | S39: =IF(Scenarios!E9=1, Q39*I39, I39) | T39: =IF(C39="FY2026", (Scenarios!D9+Scenarios!E9)*BaselineCalc!$B$21, 0) | U39: =(R39+S39+G39*F39)*J39*(1-K39) | V39: =O39*(G39+P39) | W39: =U39+V39+T39 | X39: =IF(F39+O39>0, W39/(F39+O39),"") | Y39: =B39&"|"&C39 | Z39: =INDEX(YearMap!$I$2:$I$6, MATCH(C39, YearMap!$A$2:$A$6, 0)) | AA39: 0 | AB39: 0 | AC39: 0 | AD39: 0 | AE39: 0 | AF39: 0
A40: =Y40 | B40: =Scenarios!A9 | C40: FY2029 | D40: =IF(Scenarios!D9=1,0, L40) | E40: =IF(Scenarios!E9=1,0, M40) | F40: =D40+E40 | G40: =YearMap!B5 | H40: =YearMap!C5 | I40: =YearMap!D5 | J40: =1-BaselineCalc!$B$5 | K40: =Scenarios!G9 | L40: =BaselineCalc!$B$7 + ROUND(Scenarios!L9*Scenarios!F9,0) | M40: =BaselineCalc!$B$8 + Scenarios!L9 - ROUND(Scenarios!L9*Scenarios!F9,0) | N40: =(L40-D40) + (M40-E40) | O40: =BaselineCalc!$B$22 * N40 | P40: =YearMap!E5 | Q40: =IF(Scenarios!N9="lease", YearMap!F5, YearMap!G5) | R40: =IF(Scenarios!D9=1, Q40*H40, H40) | S40: =IF(Scenarios!E9=1, Q40*I40, I40) | T40: =IF(C40="FY2026", (Scenarios!D9+Scenarios!E9)*BaselineCalc!$B$21, 0) | U40: =(R40+S40+G40*F40)*J40*(1-K40) | V40: =O40*(G40+P40) | W40: =U40+V40+T40 | X40: =IF(F40+O40>0, W40/(F40+O40),"") | Y40: =B40&"|"&C40 | Z40: =INDEX(YearMap!$I$2:$I$6, MATCH(C40, YearMap!$A$2:$A$6, 0)) | AA40: 0 | AB40: 0 | AC40: 0 | AD40: 0 | AE40: 0 | AF40: 0
A41: =Y41 | B41: =Scenarios!A9 | C41: FY2030 | D41: =IF(Scenarios!D9=1,0, L41) | E41: =IF(Scenarios!E9=1,0, M41) | F41: =D41+E41 | G41: =YearMap!B6 | H41: =YearMap!C6 | I41: =YearMap!D6 | J41: =1-BaselineCalc!$B$5 | K41: =Scenarios!G9 | L41: =BaselineCalc!$B$7 + ROUND(Scenarios!M9*Scenarios!F9,0) | M41: =BaselineCalc!$B$8 + Scenarios!M9 - ROUND(Scenarios!M9*Scenarios!F9,0) | N41: =(L41-D41) + (M41-E41) | O41: =BaselineCalc!$B$22 * N41 | P41: =YearMap!E6 | Q41: =IF(Scenarios!N9="lease", YearMap!F6, YearMap!G6) | R41: =IF(Scenarios!D9=1, Q41*H41, H41) | S41: =IF(Scenarios!E9=1, Q41*I41, I41) | T41: =IF(C41="FY2026", (Scenarios!D9+Scenarios!E9)*BaselineCalc!$B$21, 0) | U41: =(R41+S41+G41*F41)*J41*(1-K41) | V41: =O41*(G41+P41) | W41: =U41+V41+T41 | X41: =IF(F41+O41>0, W41/(F41+O41),"") | Y41: =B41&"|"&C41 | Z41: =INDEX(YearMap!$I$2:$I$6, MATCH(C41, YearMap!$A$2:$A$6, 0)) | AA41: 0 | AB41: 0 | AC41: 0 | AD41: 0 | AE41: 0 | AF41: 0
A42: =Y42 | B42: =Scenarios!A10 | C42: FY2026 | D42: =IF(Scenarios!D10=1,0, L42) | E42: =IF(Scenarios!E10=1,0, M42) | F42: =D42+E42 | G42: =YearMap!B2 | H42: =YearMap!C2 | I42: =YearMap!D2 | J42: =1-BaselineCalc!$B$5 | K42: =Scenarios!G10 | L42: =BaselineCalc!$B$7 + ROUND(Scenarios!I10*Scenarios!F10,0) | M42: =BaselineCalc!$B$8 + Scenarios!I10 - ROUND(Scenarios!I10*Scenarios!F10,0) | N42: =(L42-D42) + (M42-E42) | O42: =BaselineCalc!$B$22 * N42 | P42: =YearMap!E2 | Q42: =IF(Scenarios!N10="lease", YearMap!F2, YearMap!G2) | R42: =IF(Scenarios!D10=1, Q42*H42, H42) | S42: =IF(Scenarios!E10=1, Q42*I42, I42) | T42: =IF(C42="FY2026", (Scenarios!D10+Scenarios!E10)*BaselineCalc!$B$21, 0) | U42: =(R42+S42+G42*F42)*J42*(1-K42) | V42: =O42*(G42+P42) | W42: =U42+V42+T42 | X42: =IF(F42+O42>0, W42/(F42+O42),"") | Y42: =B42&"|"&C42 | Z42: =INDEX(YearMap!$I$2:$I$6, MATCH(C42, YearMap!$A$2:$A$6, 0)) | AA42: 0 | AB42: 0 | AC42: 0 | AD42: 0 | AE42: 0 | AF42: 0
A43: =Y43 | B43: =Scenarios!A10 | C43: FY2027 | D43: =IF(Scenarios!D10=1,0, L43) | E43: =IF(Scenarios!E10=1,0, M43) | F43: =D43+E43 | G43: =YearMap!B3 | H43: =YearMap!C3 | I43: =YearMap!D3 | J43: =1-BaselineCalc!$B$5 | K43: =Scenarios!G10 | L43: =BaselineCalc!$B$7 + ROUND(Scenarios!J10*Scenarios!F10,0) | M43: =BaselineCalc!$B$8 + Scenarios!J10 - ROUND(Scenarios!J10*Scenarios!F10,0) | N43: =(L43-D43) + (M43-E43) | O43: =BaselineCalc!$B$22 * N43 | P43: =YearMap!E3 | Q43: =IF(Scenarios!N10="lease", YearMap!F3, YearMap!G3) | R43: =IF(Scenarios!D10=1, Q43*H43, H43) | S43: =IF(Scenarios!E10=1, Q43*I43, I43) | T43: =IF(C43="FY2026", (Scenarios!D10+Scenarios!E10)*BaselineCalc!$B$21, 0) | U43: =(R43+S43+G43*F43)*J43*(1-K43) | V43: =O43*(G43+P43) | W43: =U43+V43+T43 | X43: =IF(F43+O43>0, W43/(F43+O43),"") | Y43: =B43&"|"&C43 | Z43: =INDEX(YearMap!$I$2:$I$6, MATCH(C43, YearMap!$A$2:$A$6, 0)) | AA43: 0 | AB43: 0 | AC43: 0 | AD43: 0 | AE43: 0 | AF43: 0
A44: =Y44 | B44: =Scenarios!A10 | C44: FY2028 | D44: =IF(Scenarios!D10=1,0, L44) | E44: =IF(Scenarios!E10=1,0, M44) | F44: =D44+E44 | G44: =YearMap!B4 | H44: =YearMap!C4 | I44: =YearMap!D4 | J44: =1-BaselineCalc!$B$5 | K44: =Scenarios!G10 | L44: =BaselineCalc!$B$7 + ROUND(Scenarios!K10*Scenarios!F10,0) | M44: =BaselineCalc!$B$8 + Scenarios!K10 - ROUND(Scenarios!K10*Scenarios!F10,0) | N44: =(L44-D44) + (M44-E44) | O44: =BaselineCalc!$B$22 * N44 | P44: =YearMap!E4 | Q44: =IF(Scenarios!N10="lease", YearMap!F4, YearMap!G4) | R44: =IF(Scenarios!D10=1, Q44*H44, H44) | S44: =IF(Scenarios!E10=1, Q44*I44, I44) | T44: =IF(C44="FY2026", (Scenarios!D10+Scenarios!E10)*BaselineCalc!$B$21, 0) | U44: =(R44+S44+G44*F44)*J44*(1-K44) | V44: =O44*(G44+P44) | W44: =U44+V44+T44 | X44: =IF(F44+O44>0, W44/(F44+O44),"") | Y44: =B44&"|"&C44 | Z44: =INDEX(YearMap!$I$2:$I$6, MATCH(C44, YearMap!$A$2:$A$6, 0)) | AA44: 0 | AB44: 0 | AC44: 0 | AD44: 0 | AE44: 0 | AF44: 0
A45: =Y45 | B45: =Scenarios!A10 | C45: FY2029 | D45: =IF(Scenarios!D10=1,0, L45) | E45: =IF(Scenarios!E10=1,0, M45) | F45: =D45+E45 | G45: =YearMap!B5 | H45: =YearMap!C5 | I45: =YearMap!D5 | J45: =1-BaselineCalc!$B$5 | K45: =Scenarios!G10 | L45: =BaselineCalc!$B$7 + ROUND(Scenarios!L10*Scenarios!F10,0) | M45: =BaselineCalc!$B$8 + Scenarios!L10 - ROUND(Scenarios!L10*Scenarios!F10,0) | N45: =(L45-D45) + (M45-E45) | O45: =BaselineCalc!$B$22 * N45 | P45: =YearMap!E5 | Q45: =IF(Scenarios!N10="lease", YearMap!F5, YearMap!G5) | R45: =IF(Scenarios!D10=1, Q45*H45, H45) | S45: =IF(Scenarios!E10=1, Q45*I45, I45) | T45: =IF(C45="FY2026", (Scenarios!D10+Scenarios!E10)*BaselineCalc!$B$21, 0) | U45: =(R45+S45+G45*F45)*J45*(1-K45) | V45: =O45*(G45+P45) | W45: =U45+V45+T45 | X45: =IF(F45+O45>0, W45/(F45+O45),"") | Y45: =B45&"|"&C45 | Z45: =INDEX(YearMap!$I$2:$I$6, MATCH(C45, YearMap!$A$2:$A$6, 0)) | AA45: 0 | AB45: 0 | AC45: 0 | AD45: 0 | AE45: 0 | AF45: 0
A46: =Y46 | B46: =Scenarios!A10 | C46: FY2030 | D46: =IF(Scenarios!D10=1,0, L46) | E46: =IF(Scenarios!E10=1,0, M46) | F46: =D46+E46 | G46: =YearMap!B6 | H46: =YearMap!C6 | I46: =YearMap!D6 | J46: =1-BaselineCalc!$B$5 | K46: =Scenarios!G10 | L46: =BaselineCalc!$B$7 + ROUND(Scenarios!M10*Scenarios!F10,0) | M46: =BaselineCalc!$B$8 + Scenarios!M10 - ROUND(Scenarios!M10*Scenarios!F10,0) | N46: =(L46-D46) + (M46-E46) | O46: =BaselineCalc!$B$22 * N46 | P46: =YearMap!E6 | Q46: =IF(Scenarios!N10="lease", YearMap!F6, YearMap!G6) | R46: =IF(Scenarios!D10=1, Q46*H46, H46) | S46: =IF(Scenarios!E10=1, Q46*I46, I46) | T46: =IF(C46="FY2026", (Scenarios!D10+Scenarios!E10)*BaselineCalc!$B$21, 0) | U46: =(R46+S46+G46*F46)*J46*(1-K46) | V46: =O46*(G46+P46) | W46: =U46+V46+T46 | X46: =IF(F46+O46>0, W46/(F46+O46),"") | Y46: =B46&"|"&C46 | Z46: =INDEX(YearMap!$I$2:$I$6, MATCH(C46, YearMap!$A$2:$A$6, 0)) | AA46: 0 | AB46: 0 | AC46: 0 | AD46: 0 | AE46: 0 | AF46: 0
A47: =Y47 | B47: =Scenarios!A11 | C47: FY2026 | D47: =IF(Scenarios!D11=1,0, L47) | E47: =IF(Scenarios!E11=1,0, M47) | F47: =D47+E47 | G47: =YearMap!B2 | H47: =YearMap!C2 | I47: =YearMap!D2 | J47: =1-BaselineCalc!$B$5 | K47: =Scenarios!G11 | L47: =BaselineCalc!$B$7 + ROUND(Scenarios!I11*Scenarios!F11,0) | M47: =BaselineCalc!$B$8 + Scenarios!I11 - ROUND(Scenarios!I11*Scenarios!F11,0) | N47: =(L47-D47) + (M47-E47) | O47: =BaselineCalc!$B$22 * N47 | P47: =YearMap!E2 | Q47: =IF(Scenarios!N11="lease", YearMap!F2, YearMap!G2) | R47: =IF(Scenarios!D11=1, Q47*H47, H47) | S47: =IF(Scenarios!E11=1, Q47*I47, I47) | T47: =IF(C47="FY2026", (Scenarios!D11+Scenarios!E11)*BaselineCalc!$B$21, 0) | U47: =(R47+S47+G47*F47)*J47*(1-K47) | V47: =O47*(G47+P47) | W47: =U47+V47+T47 | X47: =IF(F47+O47>0, W47/(F47+O47),"") | Y47: =B47&"|"&C47 | Z47: =INDEX(YearMap!$I$2:$I$6, MATCH(C47, YearMap!$A$2:$A$6, 0)) | AA47: 0 | AB47: 0 | AC47: 0 | AD47: 0 | AE47: 0 | AF47: 0
A48: =Y48 | B48: =Scenarios!A11 | C48: FY2027 | D48: =IF(Scenarios!D11=1,0, L48) | E48: =IF(Scenarios!E11=1,0, M48) | F48: =D48+E48 | G48: =YearMap!B3 | H48: =YearMap!C3 | I48: =YearMap!D3 | J48: =1-BaselineCalc!$B$5 | K48: =Scenarios!G11 | L48: =BaselineCalc!$B$7 + ROUND(Scenarios!J11*Scenarios!F11,0) | M48: =BaselineCalc!$B$8 + Scenarios!J11 - ROUND(Scenarios!J11*Scenarios!F11,0) | N48: =(L48-D48) + (M48-E48) | O48: =BaselineCalc!$B$22 * N48 | P48: =YearMap!E3 | Q48: =IF(Scenarios!N11="lease", YearMap!F3, YearMap!G3) | R48: =IF(Scenarios!D11=1, Q48*H48, H48) | S48: =IF(Scenarios!E11=1, Q48*I48, I48) | T48: =IF(C48="FY2026", (Scenarios!D11+Scenarios!E11)*BaselineCalc!$B$21, 0) | U48: =(R48+S48+G48*F48)*J48*(1-K48) | V48: =O48*(G48+P48) | W48: =U48+V48+T48 | X48: =IF(F48+O48>0, W48/(F48+O48),"") | Y48: =B48&"|"&C48 | Z48: =INDEX(YearMap!$I$2:$I$6, MATCH(C48, YearMap!$A$2:$A$6, 0)) | AA48: 0 | AB48: 0 | AC48: 0 | AD48: 0 | AE48: 0 | AF48: 0
A49: =Y49 | B49: =Scenarios!A11 | C49: FY2028 | D49: =IF(Scenarios!D11=1,0, L49) | E49: =IF(Scenarios!E11=1,0, M49) | F49: =D49+E49 | G49: =YearMap!B4 | H49: =YearMap!C4 | I49: =YearMap!D4 | J49: =1-BaselineCalc!$B$5 | K49: =Scenarios!G11 | L49: =BaselineCalc!$B$7 + ROUND(Scenarios!K11*Scenarios!F11,0) | M49: =BaselineCalc!$B$8 + Scenarios!K11 - ROUND(Scenarios!K11*Scenarios!F11,0) | N49: =(L49-D49) + (M49-E49) | O49: =BaselineCalc!$B$22 * N49 | P49: =YearMap!E4 | Q49: =IF(Scenarios!N11="lease", YearMap!F4, YearMap!G4) | R49: =IF(Scenarios!D11=1, Q49*H49, H49) | S49: =IF(Scenarios!E11=1, Q49*I49, I49) | T49: =IF(C49="FY2026", (Scenarios!D11+Scenarios!E11)*BaselineCalc!$B$21, 0) | U49: =(R49+S49+G49*F49)*J49*(1-K49) | V49: =O49*(G49+P49) | W49: =U49+V49+T49 | X49: =IF(F49+O49>0, W49/(F49+O49),"") | Y49: =B49&"|"&C49 | Z49: =INDEX(YearMap!$I$2:$I$6, MATCH(C49, YearMap!$A$2:$A$6, 0)) | AA49: 0 | AB49: 0 | AC49: 0 | AD49: 0 | AE49: 0 | AF49: 0
A50: =Y50 | B50: =Scenarios!A11 | C50: FY2029 | D50: =IF(Scenarios!D11=1,0, L50) | E50: =IF(Scenarios!E11=1,0, M50) | F50: =D50+E50 | G50: =YearMap!B5 | H50: =YearMap!C5 | I50: =YearMap!D5 | J50: =1-BaselineCalc!$B$5 | K50: =Scenarios!G11 | L50: =BaselineCalc!$B$7 + ROUND(Scenarios!L11*Scenarios!F11,0) | M50: =BaselineCalc!$B$8 + Scenarios!L11 - ROUND(Scenarios!L11*Scenarios!F11,0) | N50: =(L50-D50) + (M50-E50) | O50: =BaselineCalc!$B$22 * N50 | P50: =YearMap!E5 | Q50: =IF(Scenarios!N11="lease", YearMap!F5, YearMap!G5) | R50: =IF(Scenarios!D11=1, Q50*H50, H50) | S50: =IF(Scenarios!E11=1, Q50*I50, I50) | T50: =IF(C50="FY2026", (Scenarios!D11+Scenarios!E11)*BaselineCalc!$B$21, 0) | U50: =(R50+S50+G50*F50)*J50*(1-K50) | V50: =O50*(G50+P50) | W50: =U50+V50+T50 | X50: =IF(F50+O50>0, W50/(F50+O50),"") | Y50: =B50&"|"&C50 | Z50: =INDEX(YearMap!$I$2:$I$6, MATCH(C50, YearMap!$A$2:$A$6, 0)) | AA50: 0 | AB50: 0 | AC50: 0 | AD50: 0 | AE50: 0 | AF50: 0
A51: =Y51 | B51: =Scenarios!A11 | C51: FY2030 | D51: =IF(Scenarios!D11=1,0, L51) | E51: =IF(Scenarios!E11=1,0, M51) | F51: =D51+E51 | G51: =YearMap!B6 | H51: =YearMap!C6 | I51: =YearMap!D6 | J51: =1-BaselineCalc!$B$5 | K51: =Scenarios!G11 | L51: =BaselineCalc!$B$7 + ROUND(Scenarios!M11*Scenarios!F11,0) | M51: =BaselineCalc!$B$8 + Scenarios!M11 - ROUND(Scenarios!M11*Scenarios!F11,0) | N51: =(L51-D51) + (M51-E51) | O51: =BaselineCalc!$B$22 * N51 | P51: =YearMap!E6 | Q51: =IF(Scenarios!N11="lease", YearMap!F6, YearMap!G6) | R51: =IF(Scenarios!D11=1, Q51*H51, H51) | S51: =IF(Scenarios!E11=1, Q51*I51, I51) | T51: =IF(C51="FY2026", (Scenarios!D11+Scenarios!E11)*BaselineCalc!$B$21, 0) | U51: =(R51+S51+G51*F51)*J51*(1-K51) | V51: =O51*(G51+P51) | W51: =U51+V51+T51 | X51: =IF(F51+O51>0, W51/(F51+O51),"") | Y51: =B51&"|"&C51 | Z51: =INDEX(YearMap!$I$2:$I$6, MATCH(C51, YearMap!$A$2:$A$6, 0)) | AA51: 0 | AB51: 0 | AC51: 0 | AD51: 0 | AE51: 0 | AF51: 0
A52: =Y52 | B52: =Scenarios!A12 | C52: FY2026 | D52: =IF(Scenarios!D12=1,0, L52) | E52: =IF(Scenarios!E12=1,0, M52) | F52: =D52+E52 | G52: =YearMap!B2 | H52: =YearMap!C2 | I52: =YearMap!D2 | J52: =1-BaselineCalc!$B$5 | K52: =Scenarios!G12 | L52: =BaselineCalc!$B$7 + ROUND(Scenarios!I12*Scenarios!F12,0) | M52: =BaselineCalc!$B$8 + Scenarios!I12 - ROUND(Scenarios!I12*Scenarios!F12,0) | N52: =(L52-D52) + (M52-E52) | O52: =BaselineCalc!$B$22 * N52 | P52: =YearMap!E2 | Q52: =IF(Scenarios!N12="lease", YearMap!F2, YearMap!G2) | R52: =IF(Scenarios!D12=1, Q52*H52, H52) | S52: =IF(Scenarios!E12=1, Q52*I52, I52) | T52: =IF(C52="FY2026", (Scenarios!D12+Scenarios!E12)*BaselineCalc!$B$21, 0) | U52: =(R52+S52+G52*F52)*J52*(1-K52) | V52: =O52*(G52+P52) | W52: =U52+V52+T52 | X52: =IF(F52+O52>0, W52/(F52+O52),"") | Y52: =B52&"|"&C52 | Z52: =INDEX(YearMap!$I$2:$I$6, MATCH(C52, YearMap!$A$2:$A$6, 0)) | AA52: 0 | AB52: 0 | AC52: 0 | AD52: 0 | AE52: 0 | AF52: 0
A53: =Y53 | B53: =Scenarios!A12 | C53: FY2027 | D53: =IF(Scenarios!D12=1,0, L53) | E53: =IF(Scenarios!E12=1,0, M53) | F53: =D53+E53 | G53: =YearMap!B3 | H53: =YearMap!C3 | I53: =YearMap!D3 | J53: =1-BaselineCalc!$B$5 | K53: =Scenarios!G12 | L53: =BaselineCalc!$B$7 + ROUND(Scenarios!J12*Scenarios!F12,0) | M53: =BaselineCalc!$B$8 + Scenarios!J12 - ROUND(Scenarios!J12*Scenarios!F12,0) | N53: =(L53-D53) + (M53-E53) | O53: =BaselineCalc!$B$22 * N53 | P53: =YearMap!E3 | Q53: =IF(Scenarios!N12="lease", YearMap!F3, YearMap!G3) | R53: =IF(Scenarios!D12=1, Q53*H53, H53) | S53: =IF(Scenarios!E12=1, Q53*I53, I53) | T53: =IF(C53="FY2026", (Scenarios!D12+Scenarios!E12)*BaselineCalc!$B$21, 0) | U53: =(R53+S53+G53*F53)*J53*(1-K53) | V53: =O53*(G53+P53) | W53: =U53+V53+T53 | X53: =IF(F53+O53>0, W53/(F53+O53),"") | Y53: =B53&"|"&C53 | Z53: =INDEX(YearMap!$I$2:$I$6, MATCH(C53, YearMap!$A$2:$A$6, 0)) | AA53: 0 | AB53: 0 | AC53: 0 | AD53: 0 | AE53: 0 | AF53: 0
A54: =Y54 | B54: =Scenarios!A12 | C54: FY2028 | D54: =IF(Scenarios!D12=1,0, L54) | E54: =IF(Scenarios!E12=1,0, M54) | F54: =D54+E54 | G54: =YearMap!B4 | H54: =YearMap!C4 | I54: =YearMap!D4 | J54: =1-BaselineCalc!$B$5 | K54: =Scenarios!G12 | L54: =BaselineCalc!$B$7 + ROUND(Scenarios!K12*Scenarios!F12,0) | M54: =BaselineCalc!$B$8 + Scenarios!K12 - ROUND(Scenarios!K12*Scenarios!F12,0) | N54: =(L54-D54) + (M54-E54) | O54: =BaselineCalc!$B$22 * N54 | P54: =YearMap!E4 | Q54: =IF(Scenarios!N12="lease", YearMap!F4, YearMap!G4) | R54: =IF(Scenarios!D12=1, Q54*H54, H54) | S54: =IF(Scenarios!E12=1, Q54*I54, I54) | T54: =IF(C54="FY2026", (Scenarios!D12+Scenarios!E12)*BaselineCalc!$B$21, 0) | U54: =(R54+S54+G54*F54)*J54*(1-K54) | V54: =O54*(G54+P54) | W54: =U54+V54+T54 | X54: =IF(F54+O54>0, W54/(F54+O54),"") | Y54: =B54&"|"&C54 | Z54: =INDEX(YearMap!$I$2:$I$6, MATCH(C54, YearMap!$A$2:$A$6, 0)) | AA54: 0 | AB54: 0 | AC54: 0 | AD54: 0 | AE54: 0 | AF54: 0
A55: =Y55 | B55: =Scenarios!A12 | C55: FY2029 | D55: =IF(Scenarios!D12=1,0, L55) | E55: =IF(Scenarios!E12=1,0, M55) | F55: =D55+E55 | G55: =YearMap!B5 | H55: =YearMap!C5 | I55: =YearMap!D5 | J55: =1-BaselineCalc!$B$5 | K55: =Scenarios!G12 | L55: =BaselineCalc!$B$7 + ROUND(Scenarios!L12*Scenarios!F12,0) | M55: =BaselineCalc!$B$8 + Scenarios!L12 - ROUND(Scenarios!L12*Scenarios!F12,0) | N55: =(L55-D55) + (M55-E55) | O55: =BaselineCalc!$B$22 * N55 | P55: =YearMap!E5 | Q55: =IF(Scenarios!N12="lease", YearMap!F5, YearMap!G5) | R55: =IF(Scenarios!D12=1, Q55*H55, H55) | S55: =IF(Scenarios!E12=1, Q55*I55, I55) | T55: =IF(C55="FY2026", (Scenarios!D12+Scenarios!E12)*BaselineCalc!$B$21, 0) | U55: =(R55+S55+G55*F55)*J55*(1-K55) | V55: =O55*(G55+P55) | W55: =U55+V55+T55 | X55: =IF(F55+O55>0, W55/(F55+O55),"") | Y55: =B55&"|"&C55 | Z55: =INDEX(YearMap!$I$2:$I$6, MATCH(C55, YearMap!$A$2:$A$6, 0)) | AA55: 0 | AB55: 0 | AC55: 0 | AD55: 0 | AE55: 0 | AF55: 0
A56: =Y56 | B56: =Scenarios!A12 | C56: FY2030 | D56: =IF(Scenarios!D12=1,0, L56) | E56: =IF(Scenarios!E12=1,0, M56) | F56: =D56+E56 | G56: =YearMap!B6 | H56: =YearMap!C6 | I56: =YearMap!D6 | J56: =1-BaselineCalc!$B$5 | K56: =Scenarios!G12 | L56: =BaselineCalc!$B$7 + ROUND(Scenarios!M12*Scenarios!F12,0) | M56: =BaselineCalc!$B$8 + Scenarios!M12 - ROUND(Scenarios!M12*Scenarios!F12,0) | N56: =(L56-D56) + (M56-E56) | O56: =BaselineCalc!$B$22 * N56 | P56: =YearMap!E6 | Q56: =IF(Scenarios!N12="lease", YearMap!F6, YearMap!G6) | R56: =IF(Scenarios!D12=1, Q56*H56, H56) | S56: =IF(Scenarios!E12=1, Q56*I56, I56) | T56: =IF(C56="FY2026", (Scenarios!D12+Scenarios!E12)*BaselineCalc!$B$21, 0) | U56: =(R56+S56+G56*F56)*J56*(1-K56) | V56: =O56*(G56+P56) | W56: =U56+V56+T56 | X56: =IF(F56+O56>0, W56/(F56+O56),"") | Y56: =B56&"|"&C56 | Z56: =INDEX(YearMap!$I$2:$I$6, MATCH(C56, YearMap!$A$2:$A$6, 0)) | AA56: 0 | AB56: 0 | AC56: 0 | AD56: 0 | AE56: 0 | AF56: 0
A57: =Y57 | B57: =Scenarios!A13 | C57: FY2026 | D57: =IF(Scenarios!D13=1,0, L57) | E57: =IF(Scenarios!E13=1,0, M57) | F57: =D57+E57 | G57: =YearMap!B2 | H57: =YearMap!C2 | I57: =YearMap!D2 | J57: =1-BaselineCalc!$B$5 | K57: =Scenarios!G13 | L57: =BaselineCalc!$B$7 + ROUND(Scenarios!I13*Scenarios!F13,0) | M57: =BaselineCalc!$B$8 + Scenarios!I13 - ROUND(Scenarios!I13*Scenarios!F13,0) | N57: =(L57-D57) + (M57-E57) | O57: =BaselineCalc!$B$22 * N57 | P57: =YearMap!E2 | Q57: =IF(Scenarios!N13="lease", YearMap!F2, YearMap!G2) | R57: =IF(Scenarios!D13=1, Q57*H57, H57) | S57: =IF(Scenarios!E13=1, Q57*I57, I57) | T57: =IF(C57="FY2026", (Scenarios!D13+Scenarios!E13)*BaselineCalc!$B$21, 0) | U57: =(R57+S57+G57*F57)*J57*(1-K57) | V57: =O57*(G57+P57) | W57: =U57+V57+T57 | X57: =IF(F57+O57>0, W57/(F57+O57),"") | Y57: =B57&"|"&C57 | Z57: =INDEX(YearMap!$I$2:$I$6, MATCH(C57, YearMap!$A$2:$A$6, 0)) | AA57: 0 | AB57: 0 | AC57: 0 | AD57: 0 | AE57: 0 | AF57: 0
A58: =Y58 | B58: =Scenarios!A13 | C58: FY2027 | D58: =IF(Scenarios!D13=1,0, L58) | E58: =IF(Scenarios!E13=1,0, M58) | F58: =D58+E58 | G58: =YearMap!B3 | H58: =YearMap!C3 | I58: =YearMap!D3 | J58: =1-BaselineCalc!$B$5 | K58: =Scenarios!G13 | L58: =BaselineCalc!$B$7 + ROUND(Scenarios!J13*Scenarios!F13,0) | M58: =BaselineCalc!$B$8 + Scenarios!J13 - ROUND(Scenarios!J13*Scenarios!F13,0) | N58: =(L58-D58) + (M58-E58) | O58: =BaselineCalc!$B$22 * N58 | P58: =YearMap!E3 | Q58: =IF(Scenarios!N13="lease", YearMap!F3, YearMap!G3) | R58: =IF(Scenarios!D13=1, Q58*H58, H58) | S58: =IF(Scenarios!E13=1, Q58*I58, I58) | T58: =IF(C58="FY2026", (Scenarios!D13+Scenarios!E13)*BaselineCalc!$B$21, 0) | U58: =(R58+S58+G58*F58)*J58*(1-K58) | V58: =O58*(G58+P58) | W58: =U58+V58+T58 | X58: =IF(F58+O58>0, W58/(F58+O58),"") | Y58: =B58&"|"&C58 | Z58: =INDEX(YearMap!$I$2:$I$6, MATCH(C58, YearMap!$A$2:$A$6, 0)) | AA58: 0 | AB58: 0 | AC58: 0 | AD58: 0 | AE58: 0 | AF58: 0
A59: =Y59 | B59: =Scenarios!A13 | C59: FY2028 | D59: =IF(Scenarios!D13=1,0, L59) | E59: =IF(Scenarios!E13=1,0, M59) | F59: =D59+E59 | G59: =YearMap!B4 | H59: =YearMap!C4 | I59: =YearMap!D4 | J59: =1-BaselineCalc!$B$5 | K59: =Scenarios!G13 | L59: =BaselineCalc!$B$7 + ROUND(Scenarios!K13*Scenarios!F13,0) | M59: =BaselineCalc!$B$8 + Scenarios!K13 - ROUND(Scenarios!K13*Scenarios!F13,0) | N59: =(L59-D59) + (M59-E59) | O59: =BaselineCalc!$B$22 * N59 | P59: =YearMap!E4 | Q59: =IF(Scenarios!N13="lease", YearMap!F4, YearMap!G4) | R59: =IF(Scenarios!D13=1, Q59*H59, H59) | S59: =IF(Scenarios!E13=1, Q59*I59, I59) | T59: =IF(C59="FY2026", (Scenarios!D13+Scenarios!E13)*BaselineCalc!$B$21, 0) | U59: =(R59+S59+G59*F59)*J59*(1-K59) | V59: =O59*(G59+P59) | W59: =U59+V59+T59 | X59: =IF(F59+O59>0, W59/(F59+O59),"") | Y59: =B59&"|"&C59 | Z59: =INDEX(YearMap!$I$2:$I$6, MATCH(C59, YearMap!$A$2:$A$6, 0)) | AA59: 0 | AB59: 0 | AC59: 0 | AD59: 0 | AE59: 0 | AF59: 0
A60: =Y60 | B60: =Scenarios!A13 | C60: FY2029 | D60: =IF(Scenarios!D13=1,0, L60) | E60: =IF(Scenarios!E13=1,0, M60) | F60: =D60+E60 | G60: =YearMap!B5 | H60: =YearMap!C5 | I60: =YearMap!D5 | J60: =1-BaselineCalc!$B$5 | K60: =Scenarios!G13 | L60: =BaselineCalc!$B$7 + ROUND(Scenarios!L13*Scenarios!F13,0) | M60: =BaselineCalc!$B$8 + Scenarios!L13 - ROUND(Scenarios!L13*Scenarios!F13,0) | N60: =(L60-D60) + (M60-E60) | O60: =BaselineCalc!$B$22 * N60 | P60: =YearMap!E5 | Q60: =IF(Scenarios!N13="lease", YearMap!F5, YearMap!G5) | R60: =IF(Scenarios!D13=1, Q60*H60, H60) | S60: =IF(Scenarios!E13=1, Q60*I60, I60) | T60: =IF(C60="FY2026", (Scenarios!D13+Scenarios!E13)*BaselineCalc!$B$21, 0) | U60: =(R60+S60+G60*F60)*J60*(1-K60) | V60: =O60*(G60+P60) | W60: =U60+V60+T60 | X60: =IF(F60+O60>0, W60/(F60+O60),"") | Y60: =B60&"|"&C60 | Z60: =INDEX(YearMap!$I$2:$I$6, MATCH(C60, YearMap!$A$2:$A$6, 0)) | AA60: 0 | AB60: 0 | AC60: 0 | AD60: 0 | AE60: 0 | AF60: 0
A61: =Y61 | B61: =Scenarios!A13 | C61: FY2030 | D61: =IF(Scenarios!D13=1,0, L61) | E61: =IF(Scenarios!E13=1,0, M61) | F61: =D61+E61 | G61: =YearMap!B6 | H61: =YearMap!C6 | I61: =YearMap!D6 | J61: =1-BaselineCalc!$B$5 | K61: =Scenarios!G13 | L61: =BaselineCalc!$B$7 + ROUND(Scenarios!M13*Scenarios!F13,0) | M61: =BaselineCalc!$B$8 + Scenarios!M13 - ROUND(Scenarios!M13*Scenarios!F13,0) | N61: =(L61-D61) + (M61-E61) | O61: =BaselineCalc!$B$22 * N61 | P61: =YearMap!E6 | Q61: =IF(Scenarios!N13="lease", YearMap!F6, YearMap!G6) | R61: =IF(Scenarios!D13=1, Q61*H61, H61) | S61: =IF(Scenarios!E13=1, Q61*I61, I61) | T61: =IF(C61="FY2026", (Scenarios!D13+Scenarios!E13)*BaselineCalc!$B$21, 0) | U61: =(R61+S61+G61*F61)*J61*(1-K61) | V61: =O61*(G61+P61) | W61: =U61+V61+T61 | X61: =IF(F61+O61>0, W61/(F61+O61),"") | Y61: =B61&"|"&C61 | Z61: =INDEX(YearMap!$I$2:$I$6, MATCH(C61, YearMap!$A$2:$A$6, 0)) | AA61: 0 | AB61: 0 | AC61: 0 | AD61: 0 | AE61: 0 | AF61: 0

Sheet Scenarios
A1: ScenarioKey | B1: Label | C1: Overlay | D1: CloseEcho | E1: ClosePima | F1: EchoShareDist | G1: ExtraSave | H1: Notes | I1: Overlay_FY26 | J1: Overlay_FY27 | K1: Overlay_FY28 | L1: Overlay_FY29 | M1: Overlay_FY30 | N1: Carry
A2: D_Grow_Both_0 | B2: D. Grow Both (Overlay 0) | C2: 0 | D2: 0 | E2: 0 | F2: 0.5 | G2: 0 | H2: Baseline + outreach; no closures | I2: =$C2 | J2: =$C2 | K2: =$C2 | L2: =$C2 | M2: =$C2
A3: E_StatusQuo_Targets_0 | B3: E. Status‑Quo + Targets (0) | C3: 0 | D3: 0 | E3: 0 | F3: 0.5 | G3: 0 | H3: Baseline + targets; no closures | I3: =$C3 | J3: =$C3 | K3: =$C3 | L3: =$C3 | M3: =$C3
A4: F_CoLocation_Echo_0 | B4: F. Co‑Location @ Echo (0) | C4: 0 | D4: 0 | E4: 0 | F4: 0.7 | G4: 0.015 | H4: Shared‑use efficiencies later (no closure) | I4: =$C4 | J4: =$C4 | K4: =$C4 | L4: =$C4 | M4: =$C4
A5: D_Grow_Both_100 | B5: D. Grow Both (Overlay 100) | C5: 100 | D5: 0 | E5: 0 | F5: 0.5 | G5: 0 | H5: Baseline +100 overlay | I5: =$C5 | J5: =$C5 | K5: =$C5 | L5: =$C5 | M5: =$C5
A6: D_Grow_Both_150 | B6: D. Grow Both (Overlay 150) | C6: 150 | D6: 0 | E6: 0 | F6: 0.5 | G6: 0 | H6: Baseline +150 overlay | I6: =$C6 | J6: =$C6 | K6: =$C6 | L6: =$C6 | M6: =$C6
A7: G_DHub_EchoRamp | B7: G. D‑Hub @ Echo (Ramp 50→100→150) | C7: 150 | D7: 0 | E7: 0 | F7: 0.7 | G7: 0 | H7: Time‑phased ramp (+50,+100,+150 years 1–3) | I7: =C7/3 | J7: =I7+C7/3 | K7: =J7+C7/3 | L7: =C7 | M7: =C7
A8: A_Repurpose_Both_lease | B8: A. Repurpose BOTH (lease) | C8: 0 | D8: 1 | E8: 1 | F8: 0.5 | G8: 0 | H8: Repurpose both; lease/sale glide | I8: =$C8 | J8: =$C8 | K8: =$C8 | L8: =$C8 | M8: =$C8 | N8: lease
A9: A_Repurpose_Both_ops | B9: A. Repurpose BOTH (ops) | C9: 0 | D9: 1 | E9: 1 | F9: 0.5 | G9: 0 | H9: Repurpose both; operations carry | I9: =$C9 | J9: =$C9 | K9: =$C9 | L9: =$C9 | M9: =$C9 | N9: ops
A10: B_Repurpose_Echo_lease | B10: B. Repurpose ECHO (lease) | C10: 0 | D10: 1 | E10: 0 | F10: 0.5 | G10: 0 | H10: Repurpose Echo only; lease glide | I10: =$C10 | J10: =$C10 | K10: =$C10 | L10: =$C10 | M10: =$C10 | N10: lease
A11: B_Repurpose_Echo_ops | B11: B. Repurpose ECHO (ops) | C11: 0 | D11: 1 | E11: 0 | F11: 0.5 | G11: 0 | H11: Repurpose Echo only; ops carry | I11: =$C11 | J11: =$C11 | K11: =$C11 | L11: =$C11 | M11: =$C11 | N11: ops
A12: C_Repurpose_Pima_lease | B12: C. Repurpose PIMA (lease) | C12: 0 | D12: 0 | E12: 1 | F12: 0.5 | G12: 0 | H12: Repurpose Pima only; lease glide | I12: =$C12 | J12: =$C12 | K12: =$C12 | L12: =$C12 | M12: =$C12 | N12: lease
A13: C_Repurpose_Pima_ops | B13: C. Repurpose PIMA (ops) | C13: 0 | D13: 0 | E13: 1 | F13: 0.5 | G13: 0 | H13: Repurpose Pima only; ops carry | I13: =$C13 | J13: =$C13 | K13: =$C13 | L13: =$C13 | M13: =$C13 | N13: ops
A15: ScenarioKey | B15: Year | C15: Echo_ADM | D15: Pima_ADM | E15: Total_ADM | F15: VarUnit$ | G15: EchoFixed$ | H15: PimaFixed$ | I15: Key
A16: =A2 | B16: FY2026 | C16: =IF(D2=1,0, BaselineCalc!$B$7 + ROUND(I2*F2,0)) | D16: =IF(E2=1,0, BaselineCalc!$B$8 + I2 - ROUND(I2*F2,0)) | E16: =C16+D16 | F16: =YearMap!B2 | G16: =YearMap!C2 | H16: =YearMap!D2 | I16: =A16&"|"&B16
A17: =A2 | B17: FY2027 | C17: =IF(D2=1,0, BaselineCalc!$B$7 + ROUND(J2*F2,0)) | D17: =IF(E2=1,0, BaselineCalc!$B$8 + J2 - ROUND(J2*F2,0)) | E17: =C17+D17 | F17: =YearMap!B3 | G17: =YearMap!C3 | H17: =YearMap!D3 | I17: =A17&"|"&B17
A18: =A2 | B18: FY2028 | C18: =IF(D2=1,0, BaselineCalc!$B$7 + ROUND(K2*F2,0)) | D18: =IF(E2=1,0, BaselineCalc!$B$8 + K2 - ROUND(K2*F2,0)) | E18: =C18+D18 | F18: =YearMap!B4 | G18: =YearMap!C4 | H18: =YearMap!D4 | I18: =A18&"|"&B18
A19: =A2 | B19: FY2029 | C19: =IF(D2=1,0, BaselineCalc!$B$7 + ROUND(L2*F2,0)) | D19: =IF(E2=1,0, BaselineCalc!$B$8 + L2 - ROUND(L2*F2,0)) | E19: =C19+D19 | F19: =YearMap!B5 | G19: =YearMap!C5 | H19: =YearMap!D5 | I19: =A19&"|"&B19
A20: =A2 | B20: FY2030 | C20: =IF(D2=1,0, BaselineCalc!$B$7 + ROUND(M2*F2,0)) | D20: =IF(E2=1,0, BaselineCalc!$B$8 + M2 - ROUND(M2*F2,0)) | E20: =C20+D20 | F20: =YearMap!B6 | G20: =YearMap!C6 | H20: =YearMap!D6 | I20: =A20&"|"&B20
A21: =A3 | B21: FY2026 | C21: =IF(D3=1,0, BaselineCalc!$B$7 + ROUND(I3*F3,0)) | D21: =IF(E3=1,0, BaselineCalc!$B$8 + I3 - ROUND(I3*F3,0)) | E21: =C21+D21 | F21: =YearMap!B2 | G21: =YearMap!C2 | H21: =YearMap!D2 | I21: =A21&"|"&B21
A22: =A3 | B22: FY2027 | C22: =IF(D3=1,0, BaselineCalc!$B$7 + ROUND(J3*F3,0)) | D22: =IF(E3=1,0, BaselineCalc!$B$8 + J3 - ROUND(J3*F3,0)) | E22: =C22+D22 | F22: =YearMap!B3 | G22: =YearMap!C3 | H22: =YearMap!D3 | I22: =A22&"|"&B22
A23: =A3 | B23: FY2028 | C23: =IF(D3=1,0, BaselineCalc!$B$7 + ROUND(K3*F3,0)) | D23: =IF(E3=1,0, BaselineCalc!$B$8 + K3 - ROUND(K3*F3,0)) | E23: =C23+D23 | F23: =YearMap!B4 | G23: =YearMap!C4 | H23: =YearMap!D4 | I23: =A23&"|"&B23
A24: =A3 | B24: FY2029 | C24: =IF(D3=1,0, BaselineCalc!$B$7 + ROUND(L3*F3,0)) | D24: =IF(E3=1,0, BaselineCalc!$B$8 + L3 - ROUND(L3*F3,0)) | E24: =C24+D24 | F24: =YearMap!B5 | G24: =YearMap!C5 | H24: =YearMap!D5 | I24: =A24&"|"&B24
A25: =A3 | B25: FY2030 | C25: =IF(D3=1,0, BaselineCalc!$B$7 + ROUND(M3*F3,0)) | D25: =IF(E3=1,0, BaselineCalc!$B$8 + M3 - ROUND(M3*F3,0)) | E25: =C25+D25 | F25: =YearMap!B6 | G25: =YearMap!C6 | H25: =YearMap!D6 | I25: =A25&"|"&B25
A26: =A4 | B26: FY2026 | C26: =IF(D4=1,0, BaselineCalc!$B$7 + ROUND(I4*F4,0)) | D26: =IF(E4=1,0, BaselineCalc!$B$8 + I4 - ROUND(I4*F4,0)) | E26: =C26+D26 | F26: =YearMap!B2 | G26: =YearMap!C2 | H26: =YearMap!D2 | I26: =A26&"|"&B26
A27: =A4 | B27: FY2027 | C27: =IF(D4=1,0, BaselineCalc!$B$7 + ROUND(J4*F4,0)) | D27: =IF(E4=1,0, BaselineCalc!$B$8 + J4 - ROUND(J4*F4,0)) | E27: =C27+D27 | F27: =YearMap!B3 | G27: =YearMap!C3 | H27: =YearMap!D3 | I27: =A27&"|"&B27
A28: =A4 | B28: FY2028 | C28: =IF(D4=1,0, BaselineCalc!$B$7 + ROUND(K4*F4,0)) | D28: =IF(E4=1,0, BaselineCalc!$B$8 + K4 - ROUND(K4*F4,0)) | E28: =C28+D28 | F28: =YearMap!B4 | G28: =YearMap!C4 | H28: =YearMap!D4 | I28: =A28&"|"&B28
A29: =A4 | B29: FY2029 | C29: =IF(D4=1,0, BaselineCalc!$B$7 + ROUND(L4*F4,0)) | D29: =IF(E4=1,0, BaselineCalc!$B$8 + L4 - ROUND(L4*F4,0)) | E29: =C29+D29 | F29: =YearMap!B5 | G29: =YearMap!C5 | H29: =YearMap!D5 | I29: =A29&"|"&B29
A30: =A4 | B30: FY2030 | C30: =IF(D4=1,0, BaselineCalc!$B$7 + ROUND(M4*F4,0)) | D30: =IF(E4=1,0, BaselineCalc!$B$8 + M4 - ROUND(M4*F4,0)) | E30: =C30+D30 | F30: =YearMap!B6 | G30: =YearMap!C6 | H30: =YearMap!D6 | I30: =A30&"|"&B30
A31: =A5 | B31: FY2026 | C31: =IF(D5=1,0, BaselineCalc!$B$7 + ROUND(I5*F5,0)) | D31: =IF(E5=1,0, BaselineCalc!$B$8 + I5 - ROUND(I5*F5,0)) | E31: =C31+D31 | F31: =YearMap!B2 | G31: =YearMap!C2 | H31: =YearMap!D2 | I31: =A31&"|"&B31
A32: =A5 | B32: FY2027 | C32: =IF(D5=1,0, BaselineCalc!$B$7 + ROUND(J5*F5,0)) | D32: =IF(E5=1,0, BaselineCalc!$B$8 + J5 - ROUND(J5*F5,0)) | E32: =C32+D32 | F32: =YearMap!B3 | G32: =YearMap!C3 | H32: =YearMap!D3 | I32: =A32&"|"&B32
A33: =A5 | B33: FY2028 | C33: =IF(D5=1,0, BaselineCalc!$B$7 + ROUND(K5*F5,0)) | D33: =IF(E5=1,0, BaselineCalc!$B$8 + K5 - ROUND(K5*F5,0)) | E33: =C33+D33 | F33: =YearMap!B4 | G33: =YearMap!C4 | H33: =YearMap!D4 | I33: =A33&"|"&B33
A34: =A5 | B34: FY2029 | C34: =IF(D5=1,0, BaselineCalc!$B$7 + ROUND(L5*F5,0)) | D34: =IF(E5=1,0, BaselineCalc!$B$8 + L5 - ROUND(L5*F5,0)) | E34: =C34+D34 | F34: =YearMap!B5 | G34: =YearMap!C5 | H34: =YearMap!D5 | I34: =A34&"|"&B34
A35: =A5 | B35: FY2030 | C35: =IF(D5=1,0, BaselineCalc!$B$7 + ROUND(M5*F5,0)) | D35: =IF(E5=1,0, BaselineCalc!$B$8 + M5 - ROUND(M5*F5,0)) | E35: =C35+D35 | F35: =YearMap!B6 | G35: =YearMap!C6 | H35: =YearMap!D6 | I35: =A35&"|"&B35
A36: =A6 | B36: FY2026 | C36: =IF(D6=1,0, BaselineCalc!$B$7 + ROUND(I6*F6,0)) | D36: =IF(E6=1,0, BaselineCalc!$B$8 + I6 - ROUND(I6*F6,0)) | E36: =C36+D36 | F36: =YearMap!B2 | G36: =YearMap!C2 | H36: =YearMap!D2 | I36: =A36&"|"&B36
A37: =A6 | B37: FY2027 | C37: =IF(D6=1,0, BaselineCalc!$B$7 + ROUND(J6*F6,0)) | D37: =IF(E6=1,0, BaselineCalc!$B$8 + J6 - ROUND(J6*F6,0)) | E37: =C37+D37 | F37: =YearMap!B3 | G37: =YearMap!C3 | H37: =YearMap!D3 | I37: =A37&"|"&B37
A38: =A6 | B38: FY2028 | C38: =IF(D6=1,0, BaselineCalc!$B$7 + ROUND(K6*F6,0)) | D38: =IF(E6=1,0, BaselineCalc!$B$8 + K6 - ROUND(K6*F6,0)) | E38: =C38+D38 | F38: =YearMap!B4 | G38: =YearMap!C4 | H38: =YearMap!D4 | I38: =A38&"|"&B38
A39: =A6 | B39: FY2029 | C39: =IF(D6=1,0, BaselineCalc!$B$7 + ROUND(L6*F6,0)) | D39: =IF(E6=1,0, BaselineCalc!$B$8 + L6 - ROUND(L6*F6,0)) | E39: =C39+D39 | F39: =YearMap!B5 | G39: =YearMap!C5 | H39: =YearMap!D5 | I39: =A39&"|"&B39
A40: =A6 | B40: FY2030 | C40: =IF(D6=1,0, BaselineCalc!$B$7 + ROUND(M6*F6,0)) | D40: =IF(E6=1,0, BaselineCalc!$B$8 + M6 - ROUND(M6*F6,0)) | E40: =C40+D40 | F40: =YearMap!B6 | G40: =YearMap!C6 | H40: =YearMap!D6 | I40: =A40&"|"&B40
A41: =A7 | B41: FY2026 | C41: =IF(D7=1,0, BaselineCalc!$B$7 + ROUND(I7*F7,0)) | D41: =IF(E7=1,0, BaselineCalc!$B$8 + I7 - ROUND(I7*F7,0)) | E41: =C41+D41 | F41: =YearMap!B2 | G41: =YearMap!C2 | H41: =YearMap!D2 | I41: =A41&"|"&B41
A42: =A7 | B42: FY2027 | C42: =IF(D7=1,0, BaselineCalc!$B$7 + ROUND(J7*F7,0)) | D42: =IF(E7=1,0, BaselineCalc!$B$8 + J7 - ROUND(J7*F7,0)) | E42: =C42+D42 | F42: =YearMap!B3 | G42: =YearMap!C3 | H42: =YearMap!D3 | I42: =A42&"|"&B42
A43: =A7 | B43: FY2028 | C43: =IF(D7=1,0, BaselineCalc!$B$7 + ROUND(K7*F7,0)) | D43: =IF(E7=1,0, BaselineCalc!$B$8 + K7 - ROUND(K7*F7,0)) | E43: =C43+D43 | F43: =YearMap!B4 | G43: =YearMap!C4 | H43: =YearMap!D4 | I43: =A43&"|"&B43
A44: =A7 | B44: FY2029 | C44: =IF(D7=1,0, BaselineCalc!$B$7 + ROUND(L7*F7,0)) | D44: =IF(E7=1,0, BaselineCalc!$B$8 + L7 - ROUND(L7*F7,0)) | E44: =C44+D44 | F44: =YearMap!B5 | G44: =YearMap!C5 | H44: =YearMap!D5 | I44: =A44&"|"&B44
A45: =A7 | B45: FY2030 | C45: =IF(D7=1,0, BaselineCalc!$B$7 + ROUND(M7*F7,0)) | D45: =IF(E7=1,0, BaselineCalc!$B$8 + M7 - ROUND(M7*F7,0)) | E45: =C45+D45 | F45: =YearMap!B6 | G45: =YearMap!C6 | H45: =YearMap!D6 | I45: =A45&"|"&B45
A46: =A8 | B46: FY2026 | C46: =IF(D8=1,0, BaselineCalc!$B$7 + ROUND(I8*F8,0)) | D46: =IF(E8=1,0, BaselineCalc!$B$8 + I8 - ROUND(I8*F8,0)) | E46: =C46+D46 | F46: =YearMap!B2 | G46: =YearMap!C2 | H46: =YearMap!D2 | I46: =A46&"|"&B46
A47: =A8 | B47: FY2027 | C47: =IF(D8=1,0, BaselineCalc!$B$7 + ROUND(J8*F8,0)) | D47: =IF(E8=1,0, BaselineCalc!$B$8 + J8 - ROUND(J8*F8,0)) | E47: =C47+D47 | F47: =YearMap!B3 | G47: =YearMap!C3 | H47: =YearMap!D3 | I47: =A47&"|"&B47
A48: =A8 | B48: FY2028 | C48: =IF(D8=1,0, BaselineCalc!$B$7 + ROUND(K8*F8,0)) | D48: =IF(E8=1,0, BaselineCalc!$B$8 + K8 - ROUND(K8*F8,0)) | E48: =C48+D48 | F48: =YearMap!B4 | G48: =YearMap!C4 | H48: =YearMap!D4 | I48: =A48&"|"&B48
A49: =A8 | B49: FY2029 | C49: =IF(D8=1,0, BaselineCalc!$B$7 + ROUND(L8*F8,0)) | D49: =IF(E8=1,0, BaselineCalc!$B$8 + L8 - ROUND(L8*F8,0)) | E49: =C49+D49 | F49: =YearMap!B5 | G49: =YearMap!C5 | H49: =YearMap!D5 | I49: =A49&"|"&B49
A50: =A8 | B50: FY2030 | C50: =IF(D8=1,0, BaselineCalc!$B$7 + ROUND(M8*F8,0)) | D50: =IF(E8=1,0, BaselineCalc!$B$8 + M8 - ROUND(M8*F8,0)) | E50: =C50+D50 | F50: =YearMap!B6 | G50: =YearMap!C6 | H50: =YearMap!D6 | I50: =A50&"|"&B50
A51: =A9 | B51: FY2026 | C51: =IF(D9=1,0, BaselineCalc!$B$7 + ROUND(I9*F9,0)) | D51: =IF(E9=1,0, BaselineCalc!$B$8 + I9 - ROUND(I9*F9,0)) | E51: =C51+D51 | F51: =YearMap!B2 | G51: =YearMap!C2 | H51: =YearMap!D2 | I51: =A51&"|"&B51
A52: =A9 | B52: FY2027 | C52: =IF(D9=1,0, BaselineCalc!$B$7 + ROUND(J9*F9,0)) | D52: =IF(E9=1,0, BaselineCalc!$B$8 + J9 - ROUND(J9*F9,0)) | E52: =C52+D52 | F52: =YearMap!B3 | G52: =YearMap!C3 | H52: =YearMap!D3 | I52: =A52&"|"&B52
A53: =A9 | B53: FY2028 | C53: =IF(D9=1,0, BaselineCalc!$B$7 + ROUND(K9*F9,0)) | D53: =IF(E9=1,0, BaselineCalc!$B$8 + K9 - ROUND(K9*F9,0)) | E53: =C53+D53 | F53: =YearMap!B4 | G53: =YearMap!C4 | H53: =YearMap!D4 | I53: =A53&"|"&B53
A54: =A9 | B54: FY2029 | C54: =IF(D9=1,0, BaselineCalc!$B$7 + ROUND(L9*F9,0)) | D54: =IF(E9=1,0, BaselineCalc!$B$8 + L9 - ROUND(L9*F9,0)) | E54: =C54+D54 | F54: =YearMap!B5 | G54: =YearMap!C5 | H54: =YearMap!D5 | I54: =A54&"|"&B54
A55: =A9 | B55: FY2030 | C55: =IF(D9=1,0, BaselineCalc!$B$7 + ROUND(M9*F9,0)) | D55: =IF(E9=1,0, BaselineCalc!$B$8 + M9 - ROUND(M9*F9,0)) | E55: =C55+D55 | F55: =YearMap!B6 | G55: =YearMap!C6 | H55: =YearMap!D6 | I55: =A55&"|"&B55
A56: =A10 | B56: FY2026 | C56: =IF(D10=1,0, BaselineCalc!$B$7 + ROUND(I10*F10,0)) | D56: =IF(E10=1,0, BaselineCalc!$B$8 + I10 - ROUND(I10*F10,0)) | E56: =C56+D56 | F56: =YearMap!B2 | G56: =YearMap!C2 | H56: =YearMap!D2 | I56: =A56&"|"&B56
A57: =A10 | B57: FY2027 | C57: =IF(D10=1,0, BaselineCalc!$B$7 + ROUND(J10*F10,0)) | D57: =IF(E10=1,0, BaselineCalc!$B$8 + J10 - ROUND(J10*F10,0)) | E57: =C57+D57 | F57: =YearMap!B3 | G57: =YearMap!C3 | H57: =YearMap!D3 | I57: =A57&"|"&B57
A58: =A10 | B58: FY2028 | C58: =IF(D10=1,0, BaselineCalc!$B$7 + ROUND(K10*F10,0)) | D58: =IF(E10=1,0, BaselineCalc!$B$8 + K10 - ROUND(K10*F10,0)) | E58: =C58+D58 | F58: =YearMap!B4 | G58: =YearMap!C4 | H58: =YearMap!D4 | I58: =A58&"|"&B58
A59: =A10 | B59: FY2029 | C59: =IF(D10=1,0, BaselineCalc!$B$7 + ROUND(L10*F10,0)) | D59: =IF(E10=1,0, BaselineCalc!$B$8 + L10 - ROUND(L10*F10,0)) | E59: =C59+D59 | F59: =YearMap!B5 | G59: =YearMap!C5 | H59: =YearMap!D5 | I59: =A59&"|"&B59
A60: =A10 | B60: FY2030 | C60: =IF(D10=1,0, BaselineCalc!$B$7 + ROUND(M10*F10,0)) | D60: =IF(E10=1,0, BaselineCalc!$B$8 + M10 - ROUND(M10*F10,0)) | E60: =C60+D60 | F60: =YearMap!B6 | G60: =YearMap!C6 | H60: =YearMap!D6 | I60: =A60&"|"&B60
A61: =A11 | B61: FY2026 | C61: =IF(D11=1,0, BaselineCalc!$B$7 + ROUND(I11*F11,0)) | D61: =IF(E11=1,0, BaselineCalc!$B$8 + I11 - ROUND(I11*F11,0)) | E61: =C61+D61 | F61: =YearMap!B2 | G61: =YearMap!C2 | H61: =YearMap!D2 | I61: =A61&"|"&B61
A62: =A11 | B62: FY2027 | C62: =IF(D11=1,0, BaselineCalc!$B$7 + ROUND(J11*F11,0)) | D62: =IF(E11=1,0, BaselineCalc!$B$8 + J11 - ROUND(J11*F11,0)) | E62: =C62+D62 | F62: =YearMap!B3 | G62: =YearMap!C3 | H62: =YearMap!D3 | I62: =A62&"|"&B62
A63: =A11 | B63: FY2028 | C63: =IF(D11=1,0, BaselineCalc!$B$7 + ROUND(K11*F11,0)) | D63: =IF(E11=1,0, BaselineCalc!$B$8 + K11 - ROUND(K11*F11,0)) | E63: =C63+D63 | F63: =YearMap!B4 | G63: =YearMap!C4 | H63: =YearMap!D4 | I63: =A63&"|"&B63
A64: =A11 | B64: FY2029 | C64: =IF(D11=1,0, BaselineCalc!$B$7 + ROUND(L11*F11,0)) | D64: =IF(E11=1,0, BaselineCalc!$B$8 + L11 - ROUND(L11*F11,0)) | E64: =C64+D64 | F64: =YearMap!B5 | G64: =YearMap!C5 | H64: =YearMap!D5 | I64: =A64&"|"&B64
A65: =A11 | B65: FY2030 | C65: =IF(D11=1,0, BaselineCalc!$B$7 + ROUND(M11*F11,0)) | D65: =IF(E11=1,0, BaselineCalc!$B$8 + M11 - ROUND(M11*F11,0)) | E65: =C65+D65 | F65: =YearMap!B6 | G65: =YearMap!C6 | H65: =YearMap!D6 | I65: =A65&"|"&B65
A66: =A12 | B66: FY2026 | C66: =IF(D12=1,0, BaselineCalc!$B$7 + ROUND(I12*F12,0)) | D66: =IF(E12=1,0, BaselineCalc!$B$8 + I12 - ROUND(I12*F12,0)) | E66: =C66+D66 | F66: =YearMap!B2 | G66: =YearMap!C2 | H66: =YearMap!D2 | I66: =A66&"|"&B66
A67: =A12 | B67: FY2027 | C67: =IF(D12=1,0, BaselineCalc!$B$7 + ROUND(J12*F12,0)) | D67: =IF(E12=1,0, BaselineCalc!$B$8 + J12 - ROUND(J12*F12,0)) | E67: =C67+D67 | F67: =YearMap!B3 | G67: =YearMap!C3 | H67: =YearMap!D3 | I67: =A67&"|"&B67
A68: =A12 | B68: FY2028 | C68: =IF(D12=1,0, BaselineCalc!$B$7 + ROUND(K12*F12,0)) | D68: =IF(E12=1,0, BaselineCalc!$B$8 + K12 - ROUND(K12*F12,0)) | E68: =C68+D68 | F68: =YearMap!B4 | G68: =YearMap!C4 | H68: =YearMap!D4 | I68: =A68&"|"&B68
A69: =A12 | B69: FY2029 | C69: =IF(D12=1,0, BaselineCalc!$B$7 + ROUND(L12*F12,0)) | D69: =IF(E12=1,0, BaselineCalc!$B$8 + L12 - ROUND(L12*F12,0)) | E69: =C69+D69 | F69: =YearMap!B5 | G69: =YearMap!C5 | H69: =YearMap!D5 | I69: =A69&"|"&B69
A70: =A12 | B70: FY2030 | C70: =IF(D12=1,0, BaselineCalc!$B$7 + ROUND(M12*F12,0)) | D70: =IF(E12=1,0, BaselineCalc!$B$8 + M12 - ROUND(M12*F12,0)) | E70: =C70+D70 | F70: =YearMap!B6 | G70: =YearMap!C6 | H70: =YearMap!D6 | I70: =A70&"|"&B70
A71: =A13 | B71: FY2026 | C71: =IF(D13=1,0, BaselineCalc!$B$7 + ROUND(I13*F13,0)) | D71: =IF(E13=1,0, BaselineCalc!$B$8 + I13 - ROUND(I13*F13,0)) | E71: =C71+D71 | F71: =YearMap!B2 | G71: =YearMap!C2 | H71: =YearMap!D2 | I71: =A71&"|"&B71
A72: =A13 | B72: FY2027 | C72: =IF(D13=1,0, BaselineCalc!$B$7 + ROUND(J13*F13,0)) | D72: =IF(E13=1,0, BaselineCalc!$B$8 + J13 - ROUND(J13*F13,0)) | E72: =C72+D72 | F72: =YearMap!B3 | G72: =YearMap!C3 | H72: =YearMap!D3 | I72: =A72&"|"&B72
A73: =A13 | B73: FY2028 | C73: =IF(D13=1,0, BaselineCalc!$B$7 + ROUND(K13*F13,0)) | D73: =IF(E13=1,0, BaselineCalc!$B$8 + K13 - ROUND(K13*F13,0)) | E73: =C73+D73 | F73: =YearMap!B4 | G73: =YearMap!C4 | H73: =YearMap!D4 | I73: =A73&"|"&B73
A74: =A13 | B74: FY2029 | C74: =IF(D13=1,0, BaselineCalc!$B$7 + ROUND(L13*F13,0)) | D74: =IF(E13=1,0, BaselineCalc!$B$8 + L13 - ROUND(L13*F13,0)) | E74: =C74+D74 | F74: =YearMap!B5 | G74: =YearMap!C5 | H74: =YearMap!D5 | I74: =A74&"|"&B74
A75: =A13 | B75: FY2030 | C75: =IF(D13=1,0, BaselineCalc!$B$7 + ROUND(M13*F13,0)) | D75: =IF(E13=1,0, BaselineCalc!$B$8 + M13 - ROUND(M13*F13,0)) | E75: =C75+D75 | F75: =YearMap!B6 | G75: =YearMap!C6 | H75: =YearMap!D6 | I75: =A75&"|"&B75

Sheet Summary_Costs
A1: ScenarioKey | B1: FY2028 Comparable $/Student | C1: FY2030 Comparable $/Student | D1: 3‑yr Avg Comparable $/Student (FY26–FY28) | E1: 5‑yr Avg Comparable $/Student (FY26–FY30) | F1: # students displaced | G1: FY2030 # students served (open & retained) | H1: FY2028 Net ($) | J1: FY2030 Net ($) | M1: 5-yr Net Avg ($) | N1: 5-yr Avg Net ($) | O1: Δ FY2030 vs A ($) | P1: Δ 5-yr Avg vs A ($)
A2: =Scenarios!A2 | B2: =INDEX(MultiYear_ProForma!$X$2:$X$61, MATCH(Scenarios!A2&"|FY2028", MultiYear_ProForma!$Y$2:$Y$61, 0)) | C2: =INDEX(MultiYear_ProForma!$X$2:$X$61, MATCH(Scenarios!A2&"|FY2030", MultiYear_ProForma!$Y$2:$Y$61, 0)) | D2: =AVERAGE(INDEX(MultiYear_ProForma!$X$2:$X$61, MATCH(Scenarios!A2&"|FY2026", MultiYear_ProForma!$Y$2:$Y$61, 0)),INDEX(MultiYear_ProForma!$X$2:$X$61, MATCH(Scenarios!A2&"|FY2027", MultiYear_ProForma!$Y$2:$Y$61, 0)),INDEX(MultiYear_ProForma!$X$2:$X$61, MATCH(Scenarios!A2&"|FY2028", MultiYear_ProForma!$Y$2:$Y$61, 0))) | E2: =AVERAGE(INDEX(MultiYear_ProForma!$X$2:$X$61, MATCH(Scenarios!A2&"|FY2026", MultiYear_ProForma!$Y$2:$Y$61, 0)),INDEX(MultiYear_ProForma!$X$2:$X$61, MATCH(Scenarios!A2&"|FY2027", MultiYear_ProForma!$Y$2:$Y$61, 0)),INDEX(MultiYear_ProForma!$X$2:$X$61, MATCH(Scenarios!A2&"|FY2028", MultiYear_ProForma!$Y$2:$Y$61, 0)),INDEX(MultiYear_ProForma!$X$2:$X$61, MATCH(Scenarios!A2&"|FY2029", MultiYear_ProForma!$Y$2:$Y$61, 0)),INDEX(MultiYear_ProForma!$X$2:$X$61, MATCH(Scenarios!A2&"|FY2030", MultiYear_ProForma!$Y$2:$Y$61, 0))) | F2: =IFERROR(VLOOKUP($A2&"|FY2026", MultiYear_ProForma!$A:$Y, 14, FALSE), "") | G2: =IFERROR(VLOOKUP($A2&"|FY2030", MultiYear_ProForma!$A:$Y, 6, FALSE) + VLOOKUP($A2&"|FY2030", MultiYear_ProForma!$A:$Y, 15, FALSE), "") | H2: 0 | J2: 0 | K2: =INDEX(MultiYear_ProForma!$AA:$AA,MATCH($A2&"|"&"FY2028",MultiYear_ProForma!$B:$B&"|"&MultiYear_ProForma!$C:$C,0)) | L2: =INDEX(MultiYear_ProForma!$AA:$AA,MATCH($A2&"|"&"FY2030",MultiYear_ProForma!$B:$B&"|"&MultiYear_ProForma!$C:$C,0)) | M2: =(SUMIFS(MultiYear_ProForma!$AA:$AA, MultiYear_ProForma!$B:$B, $A2, MultiYear_ProForma!$C:$C, "FY2026")+SUMIFS(MultiYear_ProForma!$AA:$AA, MultiYear_ProForma!$B:$B, $A2, MultiYear_ProForma!$C:$C, "FY2027")+SUMIFS(MultiYear_ProForma!$AA:$AA, MultiYear_ProForma!$B:$B, $A2, MultiYear_ProForma!$C:$C, "FY2028")+SUMIFS(MultiYear_ProForma!$AA:$AA, MultiYear_ProForma!$B:$B, $A2, MultiYear_ProForma!$C:$C, "FY2029")+SUMIFS(MultiYear_ProForma!$AA:$AA, MultiYear_ProForma!$B:$B, $A2, MultiYear_ProForma!$C:$C, "FY2030"))/5 | N2: 0
A3: =Scenarios!A3 | B3: =INDEX(MultiYear_ProForma!$X$2:$X$61, MATCH(Scenarios!A3&"|FY2028", MultiYear_ProForma!$Y$2:$Y$61, 0)) | C3: =INDEX(MultiYear_ProForma!$X$2:$X$61, MATCH(Scenarios!A3&"|FY2030", MultiYear_ProForma!$Y$2:$Y$61, 0)) | D3: =AVERAGE(INDEX(MultiYear_ProForma!$X$2:$X$61, MATCH(Scenarios!A3&"|FY2026", MultiYear_ProForma!$Y$2:$Y$61, 0)),INDEX(MultiYear_ProForma!$X$2:$X$61, MATCH(Scenarios!A3&"|FY2027", MultiYear_ProForma!$Y$2:$Y$61, 0)),INDEX(MultiYear_ProForma!$X$2:$X$61, MATCH(Scenarios!A3&"|FY2028", MultiYear_ProForma!$Y$2:$Y$61, 0))) | E3: =AVERAGE(INDEX(MultiYear_ProForma!$X$2:$X$61, MATCH(Scenarios!A3&"|FY2026", MultiYear_ProForma!$Y$2:$Y$61, 0)),INDEX(MultiYear_ProForma!$X$2:$X$61, MATCH(Scenarios!A3&"|FY2027", MultiYear_ProForma!$Y$2:$Y$61, 0)),INDEX(MultiYear_ProForma!$X$2:$X$61, MATCH(Scenarios!A3&"|FY2028", MultiYear_ProForma!$Y$2:$Y$61, 0)),INDEX(MultiYear_ProForma!$X$2:$X$61, MATCH(Scenarios!A3&"|FY2029", MultiYear_ProForma!$Y$2:$Y$61, 0)),INDEX(MultiYear_ProForma!$X$2:$X$61, MATCH(Scenarios!A3&"|FY2030", MultiYear_ProForma!$Y$2:$Y$61, 0))) | F3: =IFERROR(VLOOKUP($A3&"|FY2026", MultiYear_ProForma!$A:$Y, 14, FALSE), "") | G3: =IFERROR(VLOOKUP($A3&"|FY2030", MultiYear_ProForma!$A:$Y, 6, FALSE) + VLOOKUP($A3&"|FY2030", MultiYear_ProForma!$A:$Y, 15, FALSE), "") | H3: 0 | J3: 0 | K3: =INDEX(MultiYear_ProForma!$AA:$AA,MATCH($A3&"|"&"FY2028",MultiYear_ProForma!$B:$B&"|"&MultiYear_ProForma!$C:$C,0)) | L3: =INDEX(MultiYear_ProForma!$AA:$AA,MATCH($A3&"|"&"FY2030",MultiYear_ProForma!$B:$B&"|"&MultiYear_ProForma!$C:$C,0)) | M3: =(SUMIFS(MultiYear_ProForma!$AA:$AA, MultiYear_ProForma!$B:$B, $A3, MultiYear_ProForma!$C:$C, "FY2026")+SUMIFS(MultiYear_ProForma!$AA:$AA, MultiYear_ProForma!$B:$B, $A3, MultiYear_ProForma!$C:$C, "FY2027")+SUMIFS(MultiYear_ProForma!$AA:$AA, MultiYear_ProForma!$B:$B, $A3, MultiYear_ProForma!$C:$C, "FY2028")+SUMIFS(MultiYear_ProForma!$AA:$AA, MultiYear_ProForma!$B:$B, $A3, MultiYear_ProForma!$C:$C, "FY2029")+SUMIFS(MultiYear_ProForma!$AA:$AA, MultiYear_ProForma!$B:$B, $A3, MultiYear_ProForma!$C:$C, "FY2030"))/5 | N3: 0
A4: =Scenarios!A4 | B4: =INDEX(MultiYear_ProForma!$X$2:$X$61, MATCH(Scenarios!A4&"|FY2028", MultiYear_ProForma!$Y$2:$Y$61, 0)) | C4: =INDEX(MultiYear_ProForma!$X$2:$X$61, MATCH(Scenarios!A4&"|FY2030", MultiYear_ProForma!$Y$2:$Y$61, 0)) | D4: =AVERAGE(INDEX(MultiYear_ProForma!$X$2:$X$61, MATCH(Scenarios!A4&"|FY2026", MultiYear_ProForma!$Y$2:$Y$61, 0)),INDEX(MultiYear_ProForma!$X$2:$X$61, MATCH(Scenarios!A4&"|FY2027", MultiYear_ProForma!$Y$2:$Y$61, 0)),INDEX(MultiYear_ProForma!$X$2:$X$61, MATCH(Scenarios!A4&"|FY2028", MultiYear_ProForma!$Y$2:$Y$61, 0))) | E4: =AVERAGE(INDEX(MultiYear_ProForma!$X$2:$X$61, MATCH(Scenarios!A4&"|FY2026", MultiYear_ProForma!$Y$2:$Y$61, 0)),INDEX(MultiYear_ProForma!$X$2:$X$61, MATCH(Scenarios!A4&"|FY2027", MultiYear_ProForma!$Y$2:$Y$61, 0)),INDEX(MultiYear_ProForma!$X$2:$X$61, MATCH(Scenarios!A4&"|FY2028", MultiYear_ProForma!$Y$2:$Y$61, 0)),INDEX(MultiYear_ProForma!$X$2:$X$61, MATCH(Scenarios!A4&"|FY2029", MultiYear_ProForma!$Y$2:$Y$61, 0)),INDEX(MultiYear_ProForma!$X$2:$X$61, MATCH(Scenarios!A4&"|FY2030", MultiYear_ProForma!$Y$2:$Y$61, 0))) | F4: =IFERROR(VLOOKUP($A4&"|FY2026", MultiYear_ProForma!$A:$Y, 14, FALSE), "") | G4: =IFERROR(VLOOKUP($A4&"|FY2030", MultiYear_ProForma!$A:$Y, 6, FALSE) + VLOOKUP($A4&"|FY2030", MultiYear_ProForma!$A:$Y, 15, FALSE), "") | H4: 0 | J4: 0 | K4: =INDEX(MultiYear_ProForma!$AA:$AA,MATCH($A4&"|"&"FY2028",MultiYear_ProForma!$B:$B&"|"&MultiYear_ProForma!$C:$C,0)) | L4: =INDEX(MultiYear_ProForma!$AA:$AA,MATCH($A4&"|"&"FY2030",MultiYear_ProForma!$B:$B&"|"&MultiYear_ProForma!$C:$C,0)) | M4: =(SUMIFS(MultiYear_ProForma!$AA:$AA, MultiYear_ProForma!$B:$B, $A4, MultiYear_ProForma!$C:$C, "FY2026")+SUMIFS(MultiYear_ProForma!$AA:$AA, MultiYear_ProForma!$B:$B, $A4, MultiYear_ProForma!$C:$C, "FY2027")+SUMIFS(MultiYear_ProForma!$AA:$AA, MultiYear_ProForma!$B:$B, $A4, MultiYear_ProForma!$C:$C, "FY2028")+SUMIFS(MultiYear_ProForma!$AA:$AA, MultiYear_ProForma!$B:$B, $A4, MultiYear_ProForma!$C:$C, "FY2029")+SUMIFS(MultiYear_ProForma!$AA:$AA, MultiYear_ProForma!$B:$B, $A4, MultiYear_ProForma!$C:$C, "FY2030"))/5 | N4: 0
A5: =Scenarios!A5 | B5: =INDEX(MultiYear_ProForma!$X$2:$X$61, MATCH(Scenarios!A5&"|FY2028", MultiYear_ProForma!$Y$2:$Y$61, 0)) | C5: =INDEX(MultiYear_ProForma!$X$2:$X$61, MATCH(Scenarios!A5&"|FY2030", MultiYear_ProForma!$Y$2:$Y$61, 0)) | D5: =AVERAGE(INDEX(MultiYear_ProForma!$X$2:$X$61, MATCH(Scenarios!A5&"|FY2026", MultiYear_ProForma!$Y$2:$Y$61, 0)),INDEX(MultiYear_ProForma!$X$2:$X$61, MATCH(Scenarios!A5&"|FY2027", MultiYear_ProForma!$Y$2:$Y$61, 0)),INDEX(MultiYear_ProForma!$X$2:$X$61, MATCH(Scenarios!A5&"|FY2028", MultiYear_ProForma!$Y$2:$Y$61, 0))) | E5: =AVERAGE(INDEX(MultiYear_ProForma!$X$2:$X$61, MATCH(Scenarios!A5&"|FY2026", MultiYear_ProForma!$Y$2:$Y$61, 0)),INDEX(MultiYear_ProForma!$X$2:$X$61, MATCH(Scenarios!A5&"|FY2027", MultiYear_ProForma!$Y$2:$Y$61, 0)),INDEX(MultiYear_ProForma!$X$2:$X$61, MATCH(Scenarios!A5&"|FY2028", MultiYear_ProForma!$Y$2:$Y$61, 0)),INDEX(MultiYear_ProForma!$X$2:$X$61, MATCH(Scenarios!A5&"|FY2029", MultiYear_ProForma!$Y$2:$Y$61, 0)),INDEX(MultiYear_ProForma!$X$2:$X$61, MATCH(Scenarios!A5&"|FY2030", MultiYear_ProForma!$Y$2:$Y$61, 0))) | F5: =IFERROR(VLOOKUP($A5&"|FY2026", MultiYear_ProForma!$A:$Y, 14, FALSE), "") | G5: =IFERROR(VLOOKUP($A5&"|FY2030", MultiYear_ProForma!$A:$Y, 6, FALSE) + VLOOKUP($A5&"|FY2030", MultiYear_ProForma!$A:$Y, 15, FALSE), "") | H5: 0 | J5: 0 | K5: =INDEX(MultiYear_ProForma!$AA:$AA,MATCH($A5&"|"&"FY2028",MultiYear_ProForma!$B:$B&"|"&MultiYear_ProForma!$C:$C,0)) | L5: =INDEX(MultiYear_ProForma!$AA:$AA,MATCH($A5&"|"&"FY2030",MultiYear_ProForma!$B:$B&"|"&MultiYear_ProForma!$C:$C,0)) | M5: =(SUMIFS(MultiYear_ProForma!$AA:$AA, MultiYear_ProForma!$B:$B, $A5, MultiYear_ProForma!$C:$C, "FY2026")+SUMIFS(MultiYear_ProForma!$AA:$AA, MultiYear_ProForma!$B:$B, $A5, MultiYear_ProForma!$C:$C, "FY2027")+SUMIFS(MultiYear_ProForma!$AA:$AA, MultiYear_ProForma!$B:$B, $A5, MultiYear_ProForma!$C:$C, "FY2028")+SUMIFS(MultiYear_ProForma!$AA:$AA, MultiYear_ProForma!$B:$B, $A5, MultiYear_ProForma!$C:$C, "FY2029")+SUMIFS(MultiYear_ProForma!$AA:$AA, MultiYear_ProForma!$B:$B, $A5, MultiYear_ProForma!$C:$C, "FY2030"))/5 | N5: 0
A6: =Scenarios!A6 | B6: =INDEX(MultiYear_ProForma!$X$2:$X$61, MATCH(Scenarios!A6&"|FY2028", MultiYear_ProForma!$Y$2:$Y$61, 0)) | C6: =INDEX(MultiYear_ProForma!$X$2:$X$61, MATCH(Scenarios!A6&"|FY2030", MultiYear_ProForma!$Y$2:$Y$61, 0)) | D6: =AVERAGE(INDEX(MultiYear_ProForma!$X$2:$X$61, MATCH(Scenarios!A6&"|FY2026", MultiYear_ProForma!$Y$2:$Y$61, 0)),INDEX(MultiYear_ProForma!$X$2:$X$61, MATCH(Scenarios!A6&"|FY2027", MultiYear_ProForma!$Y$2:$Y$61, 0)),INDEX(MultiYear_ProForma!$X$2:$X$61, MATCH(Scenarios!A6&"|FY2028", MultiYear_ProForma!$Y$2:$Y$61, 0))) | E6: =AVERAGE(INDEX(MultiYear_ProForma!$X$2:$X$61, MATCH(Scenarios!A6&"|FY2026", MultiYear_ProForma!$Y$2:$Y$61, 0)),INDEX(MultiYear_ProForma!$X$2:$X$61, MATCH(Scenarios!A6&"|FY2027", MultiYear_ProForma!$Y$2:$Y$61, 0)),INDEX(MultiYear_ProForma!$X$2:$X$61, MATCH(Scenarios!A6&"|FY2028", MultiYear_ProForma!$Y$2:$Y$61, 0)),INDEX(MultiYear_ProForma!$X$2:$X$61, MATCH(Scenarios!A6&"|FY2029", MultiYear_ProForma!$Y$2:$Y$61, 0)),INDEX(MultiYear_ProForma!$X$2:$X$61, MATCH(Scenarios!A6&"|FY2030", MultiYear_ProForma!$Y$2:$Y$61, 0))) | F6: =IFERROR(VLOOKUP($A6&"|FY2026", MultiYear_ProForma!$A:$Y, 14, FALSE), "") | G6: =IFERROR(VLOOKUP($A6&"|FY2030", MultiYear_ProForma!$A:$Y, 6, FALSE) + VLOOKUP($A6&"|FY2030", MultiYear_ProForma!$A:$Y, 15, FALSE), "") | H6: 0 | J6: 0 | K6: =INDEX(MultiYear_ProForma!$AA:$AA,MATCH($A6&"|"&"FY2028",MultiYear_ProForma!$B:$B&"|"&MultiYear_ProForma!$C:$C,0)) | L6: =INDEX(MultiYear_ProForma!$AA:$AA,MATCH($A6&"|"&"FY2030",MultiYear_ProForma!$B:$B&"|"&MultiYear_ProForma!$C:$C,0)) | M6: =(SUMIFS(MultiYear_ProForma!$AA:$AA, MultiYear_ProForma!$B:$B, $A6, MultiYear_ProForma!$C:$C, "FY2026")+SUMIFS(MultiYear_ProForma!$AA:$AA, MultiYear_ProForma!$B:$B, $A6, MultiYear_ProForma!$C:$C, "FY2027")+SUMIFS(MultiYear_ProForma!$AA:$AA, MultiYear_ProForma!$B:$B, $A6, MultiYear_ProForma!$C:$C, "FY2028")+SUMIFS(MultiYear_ProForma!$AA:$AA, MultiYear_ProForma!$B:$B, $A6, MultiYear_ProForma!$C:$C, "FY2029")+SUMIFS(MultiYear_ProForma!$AA:$AA, MultiYear_ProForma!$B:$B, $A6, MultiYear_ProForma!$C:$C, "FY2030"))/5 | N6: 0
A7: =Scenarios!A7 | B7: =INDEX(MultiYear_ProForma!$X$2:$X$61, MATCH(Scenarios!A7&"|FY2028", MultiYear_ProForma!$Y$2:$Y$61, 0)) | C7: =INDEX(MultiYear_ProForma!$X$2:$X$61, MATCH(Scenarios!A7&"|FY2030", MultiYear_ProForma!$Y$2:$Y$61, 0)) | D7: =AVERAGE(INDEX(MultiYear_ProForma!$X$2:$X$61, MATCH(Scenarios!A7&"|FY2026", MultiYear_ProForma!$Y$2:$Y$61, 0)),INDEX(MultiYear_ProForma!$X$2:$X$61, MATCH(Scenarios!A7&"|FY2027", MultiYear_ProForma!$Y$2:$Y$61, 0)),INDEX(MultiYear_ProForma!$X$2:$X$61, MATCH(Scenarios!A7&"|FY2028", MultiYear_ProForma!$Y$2:$Y$61, 0))) | E7: =AVERAGE(INDEX(MultiYear_ProForma!$X$2:$X$61, MATCH(Scenarios!A7&"|FY2026", MultiYear_ProForma!$Y$2:$Y$61, 0)),INDEX(MultiYear_ProForma!$X$2:$X$61, MATCH(Scenarios!A7&"|FY2027", MultiYear_ProForma!$Y$2:$Y$61, 0)),INDEX(MultiYear_ProForma!$X$2:$X$61, MATCH(Scenarios!A7&"|FY2028", MultiYear_ProForma!$Y$2:$Y$61, 0)),INDEX(MultiYear_ProForma!$X$2:$X$61, MATCH(Scenarios!A7&"|FY2029", MultiYear_ProForma!$Y$2:$Y$61, 0)),INDEX(MultiYear_ProForma!$X$2:$X$61, MATCH(Scenarios!A7&"|FY2030", MultiYear_ProForma!$Y$2:$Y$61, 0))) | F7: =IFERROR(VLOOKUP($A7&"|FY2026", MultiYear_ProForma!$A:$Y, 14, FALSE), "") | G7: =IFERROR(VLOOKUP($A7&"|FY2030", MultiYear_ProForma!$A:$Y, 6, FALSE) + VLOOKUP($A7&"|FY2030", MultiYear_ProForma!$A:$Y, 15, FALSE), "") | H7: 0 | J7: 0 | K7: =INDEX(MultiYear_ProForma!$AA:$AA,MATCH($A7&"|"&"FY2028",MultiYear_ProForma!$B:$B&"|"&MultiYear_ProForma!$C:$C,0)) | L7: =INDEX(MultiYear_ProForma!$AA:$AA,MATCH($A7&"|"&"FY2030",MultiYear_ProForma!$B:$B&"|"&MultiYear_ProForma!$C:$C,0)) | M7: =(SUMIFS(MultiYear_ProForma!$AA:$AA, MultiYear_ProForma!$B:$B, $A7, MultiYear_ProForma!$C:$C, "FY2026")+SUMIFS(MultiYear_ProForma!$AA:$AA, MultiYear_ProForma!$B:$B, $A7, MultiYear_ProForma!$C:$C, "FY2027")+SUMIFS(MultiYear_ProForma!$AA:$AA, MultiYear_ProForma!$B:$B, $A7, MultiYear_ProForma!$C:$C, "FY2028")+SUMIFS(MultiYear_ProForma!$AA:$AA, MultiYear_ProForma!$B:$B, $A7, MultiYear_ProForma!$C:$C, "FY2029")+SUMIFS(MultiYear_ProForma!$AA:$AA, MultiYear_ProForma!$B:$B, $A7, MultiYear_ProForma!$C:$C, "FY2030"))/5 | N7: 0
A8: =Scenarios!A8 | B8: =INDEX(MultiYear_ProForma!$X$2:$X$61, MATCH(Scenarios!A8&"|FY2028", MultiYear_ProForma!$Y$2:$Y$61, 0)) | C8: =INDEX(MultiYear_ProForma!$X$2:$X$61, MATCH(Scenarios!A8&"|FY2030", MultiYear_ProForma!$Y$2:$Y$61, 0)) | D8: =AVERAGE(INDEX(MultiYear_ProForma!$X$2:$X$61, MATCH(Scenarios!A8&"|FY2026", MultiYear_ProForma!$Y$2:$Y$61, 0)),INDEX(MultiYear_ProForma!$X$2:$X$61, MATCH(Scenarios!A8&"|FY2027", MultiYear_ProForma!$Y$2:$Y$61, 0)),INDEX(MultiYear_ProForma!$X$2:$X$61, MATCH(Scenarios!A8&"|FY2028", MultiYear_ProForma!$Y$2:$Y$61, 0))) | E8: =AVERAGE(INDEX(MultiYear_ProForma!$X$2:$X$61, MATCH(Scenarios!A8&"|FY2026", MultiYear_ProForma!$Y$2:$Y$61, 0)),INDEX(MultiYear_ProForma!$X$2:$X$61, MATCH(Scenarios!A8&"|FY2027", MultiYear_ProForma!$Y$2:$Y$61, 0)),INDEX(MultiYear_ProForma!$X$2:$X$61, MATCH(Scenarios!A8&"|FY2028", MultiYear_ProForma!$Y$2:$Y$61, 0)),INDEX(MultiYear_ProForma!$X$2:$X$61, MATCH(Scenarios!A8&"|FY2029", MultiYear_ProForma!$Y$2:$Y$61, 0)),INDEX(MultiYear_ProForma!$X$2:$X$61, MATCH(Scenarios!A8&"|FY2030", MultiYear_ProForma!$Y$2:$Y$61, 0))) | F8: =IFERROR(VLOOKUP($A8&"|FY2026", MultiYear_ProForma!$A:$Y, 14, FALSE), "") | G8: =IFERROR(VLOOKUP($A8&"|FY2030", MultiYear_ProForma!$A:$Y, 6, FALSE) + VLOOKUP($A8&"|FY2030", MultiYear_ProForma!$A:$Y, 15, FALSE), "") | H8: 0 | J8: 0 | K8: =INDEX(MultiYear_ProForma!$AA:$AA,MATCH($A8&"|"&"FY2028",MultiYear_ProForma!$B:$B&"|"&MultiYear_ProForma!$C:$C,0)) | L8: =INDEX(MultiYear_ProForma!$AA:$AA,MATCH($A8&"|"&"FY2030",MultiYear_ProForma!$B:$B&"|"&MultiYear_ProForma!$C:$C,0)) | M8: =(SUMIFS(MultiYear_ProForma!$AA:$AA, MultiYear_ProForma!$B:$B, $A8, MultiYear_ProForma!$C:$C, "FY2026")+SUMIFS(MultiYear_ProForma!$AA:$AA, MultiYear_ProForma!$B:$B, $A8, MultiYear_ProForma!$C:$C, "FY2027")+SUMIFS(MultiYear_ProForma!$AA:$AA, MultiYear_ProForma!$B:$B, $A8, MultiYear_ProForma!$C:$C, "FY2028")+SUMIFS(MultiYear_ProForma!$AA:$AA, MultiYear_ProForma!$B:$B, $A8, MultiYear_ProForma!$C:$C, "FY2029")+SUMIFS(MultiYear_ProForma!$AA:$AA, MultiYear_ProForma!$B:$B, $A8, MultiYear_ProForma!$C:$C, "FY2030"))/5 | N8: 0
A9: =Scenarios!A9 | B9: =INDEX(MultiYear_ProForma!$X$2:$X$61, MATCH(Scenarios!A9&"|FY2028", MultiYear_ProForma!$Y$2:$Y$61, 0)) | C9: =INDEX(MultiYear_ProForma!$X$2:$X$61, MATCH(Scenarios!A9&"|FY2030", MultiYear_ProForma!$Y$2:$Y$61, 0)) | D9: =AVERAGE(INDEX(MultiYear_ProForma!$X$2:$X$61, MATCH(Scenarios!A9&"|FY2026", MultiYear_ProForma!$Y$2:$Y$61, 0)),INDEX(MultiYear_ProForma!$X$2:$X$61, MATCH(Scenarios!A9&"|FY2027", MultiYear_ProForma!$Y$2:$Y$61, 0)),INDEX(MultiYear_ProForma!$X$2:$X$61, MATCH(Scenarios!A9&"|FY2028", MultiYear_ProForma!$Y$2:$Y$61, 0))) | E9: =AVERAGE(INDEX(MultiYear_ProForma!$X$2:$X$61, MATCH(Scenarios!A9&"|FY2026", MultiYear_ProForma!$Y$2:$Y$61, 0)),INDEX(MultiYear_ProForma!$X$2:$X$61, MATCH(Scenarios!A9&"|FY2027", MultiYear_ProForma!$Y$2:$Y$61, 0)),INDEX(MultiYear_ProForma!$X$2:$X$61, MATCH(Scenarios!A9&"|FY2028", MultiYear_ProForma!$Y$2:$Y$61, 0)),INDEX(MultiYear_ProForma!$X$2:$X$61, MATCH(Scenarios!A9&"|FY2029", MultiYear_ProForma!$Y$2:$Y$61, 0)),INDEX(MultiYear_ProForma!$X$2:$X$61, MATCH(Scenarios!A9&"|FY2030", MultiYear_ProForma!$Y$2:$Y$61, 0))) | F9: =IFERROR(VLOOKUP($A9&"|FY2026", MultiYear_ProForma!$A:$Y, 14, FALSE), "") | G9: =IFERROR(VLOOKUP($A9&"|FY2030", MultiYear_ProForma!$A:$Y, 6, FALSE) + VLOOKUP($A9&"|FY2030", MultiYear_ProForma!$A:$Y, 15, FALSE), "") | H9: 0 | J9: 0 | K9: =INDEX(MultiYear_ProForma!$AA:$AA,MATCH($A9&"|"&"FY2028",MultiYear_ProForma!$B:$B&"|"&MultiYear_ProForma!$C:$C,0)) | L9: =INDEX(MultiYear_ProForma!$AA:$AA,MATCH($A9&"|"&"FY2030",MultiYear_ProForma!$B:$B&"|"&MultiYear_ProForma!$C:$C,0)) | M9: =(SUMIFS(MultiYear_ProForma!$AA:$AA, MultiYear_ProForma!$B:$B, $A9, MultiYear_ProForma!$C:$C, "FY2026")+SUMIFS(MultiYear_ProForma!$AA:$AA, MultiYear_ProForma!$B:$B, $A9, MultiYear_ProForma!$C:$C, "FY2027")+SUMIFS(MultiYear_ProForma!$AA:$AA, MultiYear_ProForma!$B:$B, $A9, MultiYear_ProForma!$C:$C, "FY2028")+SUMIFS(MultiYear_ProForma!$AA:$AA, MultiYear_ProForma!$B:$B, $A9, MultiYear_ProForma!$C:$C, "FY2029")+SUMIFS(MultiYear_ProForma!$AA:$AA, MultiYear_ProForma!$B:$B, $A9, MultiYear_ProForma!$C:$C, "FY2030"))/5 | N9: 0
A10: =Scenarios!A10 | B10: =INDEX(MultiYear_ProForma!$X$2:$X$61, MATCH(Scenarios!A10&"|FY2028", MultiYear_ProForma!$Y$2:$Y$61, 0)) | C10: =INDEX(MultiYear_ProForma!$X$2:$X$61, MATCH(Scenarios!A10&"|FY2030", MultiYear_ProForma!$Y$2:$Y$61, 0)) | D10: =AVERAGE(INDEX(MultiYear_ProForma!$X$2:$X$61, MATCH(Scenarios!A10&"|FY2026", MultiYear_ProForma!$Y$2:$Y$61, 0)),INDEX(MultiYear_ProForma!$X$2:$X$61, MATCH(Scenarios!A10&"|FY2027", MultiYear_ProForma!$Y$2:$Y$61, 0)),INDEX(MultiYear_ProForma!$X$2:$X$61, MATCH(Scenarios!A10&"|FY2028", MultiYear_ProForma!$Y$2:$Y$61, 0))) | E10: =AVERAGE(INDEX(MultiYear_ProForma!$X$2:$X$61, MATCH(Scenarios!A10&"|FY2026", MultiYear_ProForma!$Y$2:$Y$61, 0)),INDEX(MultiYear_ProForma!$X$2:$X$61, MATCH(Scenarios!A10&"|FY2027", MultiYear_ProForma!$Y$2:$Y$61, 0)),INDEX(MultiYear_ProForma!$X$2:$X$61, MATCH(Scenarios!A10&"|FY2028", MultiYear_ProForma!$Y$2:$Y$61, 0)),INDEX(MultiYear_ProForma!$X$2:$X$61, MATCH(Scenarios!A10&"|FY2029", MultiYear_ProForma!$Y$2:$Y$61, 0)),INDEX(MultiYear_ProForma!$X$2:$X$61, MATCH(Scenarios!A10&"|FY2030", MultiYear_ProForma!$Y$2:$Y$61, 0))) | F10: =IFERROR(VLOOKUP($A10&"|FY2026", MultiYear_ProForma!$A:$Y, 14, FALSE), "") | G10: =IFERROR(VLOOKUP($A10&"|FY2030", MultiYear_ProForma!$A:$Y, 6, FALSE) + VLOOKUP($A10&"|FY2030", MultiYear_ProForma!$A:$Y, 15, FALSE), "") | H10: 0 | J10: 0 | K10: =INDEX(MultiYear_ProForma!$AA:$AA,MATCH($A10&"|"&"FY2028",MultiYear_ProForma!$B:$B&"|"&MultiYear_ProForma!$C:$C,0)) | L10: =INDEX(MultiYear_ProForma!$AA:$AA,MATCH($A10&"|"&"FY2030",MultiYear_ProForma!$B:$B&"|"&MultiYear_ProForma!$C:$C,0)) | M10: =(SUMIFS(MultiYear_ProForma!$AA:$AA, MultiYear_ProForma!$B:$B, $A10, MultiYear_ProForma!$C:$C, "FY2026")+SUMIFS(MultiYear_ProForma!$AA:$AA, MultiYear_ProForma!$B:$B, $A10, MultiYear_ProForma!$C:$C, "FY2027")+SUMIFS(MultiYear_ProForma!$AA:$AA, MultiYear_ProForma!$B:$B, $A10, MultiYear_ProForma!$C:$C, "FY2028")+SUMIFS(MultiYear_ProForma!$AA:$AA, MultiYear_ProForma!$B:$B, $A10, MultiYear_ProForma!$C:$C, "FY2029")+SUMIFS(MultiYear_ProForma!$AA:$AA, MultiYear_ProForma!$B:$B, $A10, MultiYear_ProForma!$C:$C, "FY2030"))/5 | N10: 0
A11: =Scenarios!A11 | B11: =INDEX(MultiYear_ProForma!$X$2:$X$61, MATCH(Scenarios!A11&"|FY2028", MultiYear_ProForma!$Y$2:$Y$61, 0)) | C11: =INDEX(MultiYear_ProForma!$X$2:$X$61, MATCH(Scenarios!A11&"|FY2030", MultiYear_ProForma!$Y$2:$Y$61, 0)) | D11: =AVERAGE(INDEX(MultiYear_ProForma!$X$2:$X$61, MATCH(Scenarios!A11&"|FY2026", MultiYear_ProForma!$Y$2:$Y$61, 0)),INDEX(MultiYear_ProForma!$X$2:$X$61, MATCH(Scenarios!A11&"|FY2027", MultiYear_ProForma!$Y$2:$Y$61, 0)),INDEX(MultiYear_ProForma!$X$2:$X$61, MATCH(Scenarios!A11&"|FY2028", MultiYear_ProForma!$Y$2:$Y$61, 0))) | E11: =AVERAGE(INDEX(MultiYear_ProForma!$X$2:$X$61, MATCH(Scenarios!A11&"|FY2026", MultiYear_ProForma!$Y$2:$Y$61, 0)),INDEX(MultiYear_ProForma!$X$2:$X$61, MATCH(Scenarios!A11&"|FY2027", MultiYear_ProForma!$Y$2:$Y$61, 0)),INDEX(MultiYear_ProForma!$X$2:$X$61, MATCH(Scenarios!A11&"|FY2028", MultiYear_ProForma!$Y$2:$Y$61, 0)),INDEX(MultiYear_ProForma!$X$2:$X$61, MATCH(Scenarios!A11&"|FY2029", MultiYear_ProForma!$Y$2:$Y$61, 0)),INDEX(MultiYear_ProForma!$X$2:$X$61, MATCH(Scenarios!A11&"|FY2030", MultiYear_ProForma!$Y$2:$Y$61, 0))) | F11: =IFERROR(VLOOKUP($A11&"|FY2026", MultiYear_ProForma!$A:$Y, 14, FALSE), "") | G11: =IFERROR(VLOOKUP($A11&"|FY2030", MultiYear_ProForma!$A:$Y, 6, FALSE) + VLOOKUP($A11&"|FY2030", MultiYear_ProForma!$A:$Y, 15, FALSE), "") | H11: 0 | J11: 0 | K11: =INDEX(MultiYear_ProForma!$AA:$AA,MATCH($A11&"|"&"FY2028",MultiYear_ProForma!$B:$B&"|"&MultiYear_ProForma!$C:$C,0)) | L11: =INDEX(MultiYear_ProForma!$AA:$AA,MATCH($A11&"|"&"FY2030",MultiYear_ProForma!$B:$B&"|"&MultiYear_ProForma!$C:$C,0)) | M11: =(SUMIFS(MultiYear_ProForma!$AA:$AA, MultiYear_ProForma!$B:$B, $A11, MultiYear_ProForma!$C:$C, "FY2026")+SUMIFS(MultiYear_ProForma!$AA:$AA, MultiYear_ProForma!$B:$B, $A11, MultiYear_ProForma!$C:$C, "FY2027")+SUMIFS(MultiYear_ProForma!$AA:$AA, MultiYear_ProForma!$B:$B, $A11, MultiYear_ProForma!$C:$C, "FY2028")+SUMIFS(MultiYear_ProForma!$AA:$AA, MultiYear_ProForma!$B:$B, $A11, MultiYear_ProForma!$C:$C, "FY2029")+SUMIFS(MultiYear_ProForma!$AA:$AA, MultiYear_ProForma!$B:$B, $A11, MultiYear_ProForma!$C:$C, "FY2030"))/5 | N11: 0
A12: =Scenarios!A12 | B12: =INDEX(MultiYear_ProForma!$X$2:$X$61, MATCH(Scenarios!A12&"|FY2028", MultiYear_ProForma!$Y$2:$Y$61, 0)) | C12: =INDEX(MultiYear_ProForma!$X$2:$X$61, MATCH(Scenarios!A12&"|FY2030", MultiYear_ProForma!$Y$2:$Y$61, 0)) | D12: =AVERAGE(INDEX(MultiYear_ProForma!$X$2:$X$61, MATCH(Scenarios!A12&"|FY2026", MultiYear_ProForma!$Y$2:$Y$61, 0)),INDEX(MultiYear_ProForma!$X$2:$X$61, MATCH(Scenarios!A12&"|FY2027", MultiYear_ProForma!$Y$2:$Y$61, 0)),INDEX(MultiYear_ProForma!$X$2:$X$61, MATCH(Scenarios!A12&"|FY2028", MultiYear_ProForma!$Y$2:$Y$61, 0))) | E12: =AVERAGE(INDEX(MultiYear_ProForma!$X$2:$X$61, MATCH(Scenarios!A12&"|FY2026", MultiYear_ProForma!$Y$2:$Y$61, 0)),INDEX(MultiYear_ProForma!$X$2:$X$61, MATCH(Scenarios!A12&"|FY2027", MultiYear_ProForma!$Y$2:$Y$61, 0)),INDEX(MultiYear_ProForma!$X$2:$X$61, MATCH(Scenarios!A12&"|FY2028", MultiYear_ProForma!$Y$2:$Y$61, 0)),INDEX(MultiYear_ProForma!$X$2:$X$61, MATCH(Scenarios!A12&"|FY2029", MultiYear_ProForma!$Y$2:$Y$61, 0)),INDEX(MultiYear_ProForma!$X$2:$X$61, MATCH(Scenarios!A12&"|FY2030", MultiYear_ProForma!$Y$2:$Y$61, 0))) | F12: =IFERROR(VLOOKUP($A12&"|FY2026", MultiYear_ProForma!$A:$Y, 14, FALSE), "") | G12: =IFERROR(VLOOKUP($A12&"|FY2030", MultiYear_ProForma!$A:$Y, 6, FALSE) + VLOOKUP($A12&"|FY2030", MultiYear_ProForma!$A:$Y, 15, FALSE), "") | H12: 0 | J12: 0 | K12: =INDEX(MultiYear_ProForma!$AA:$AA,MATCH($A12&"|"&"FY2028",MultiYear_ProForma!$B:$B&"|"&MultiYear_ProForma!$C:$C,0)) | L12: =INDEX(MultiYear_ProForma!$AA:$AA,MATCH($A12&"|"&"FY2030",MultiYear_ProForma!$B:$B&"|"&MultiYear_ProForma!$C:$C,0)) | M12: =(SUMIFS(MultiYear_ProForma!$AA:$AA, MultiYear_ProForma!$B:$B, $A12, MultiYear_ProForma!$C:$C, "FY2026")+SUMIFS(MultiYear_ProForma!$AA:$AA, MultiYear_ProForma!$B:$B, $A12, MultiYear_ProForma!$C:$C, "FY2027")+SUMIFS(MultiYear_ProForma!$AA:$AA, MultiYear_ProForma!$B:$B, $A12, MultiYear_ProForma!$C:$C, "FY2028")+SUMIFS(MultiYear_ProForma!$AA:$AA, MultiYear_ProForma!$B:$B, $A12, MultiYear_ProForma!$C:$C, "FY2029")+SUMIFS(MultiYear_ProForma!$AA:$AA, MultiYear_ProForma!$B:$B, $A12, MultiYear_ProForma!$C:$C, "FY2030"))/5 | N12: 0
A13: =Scenarios!A13 | B13: =INDEX(MultiYear_ProForma!$X$2:$X$61, MATCH(Scenarios!A13&"|FY2028", MultiYear_ProForma!$Y$2:$Y$61, 0)) | C13: =INDEX(MultiYear_ProForma!$X$2:$X$61, MATCH(Scenarios!A13&"|FY2030", MultiYear_ProForma!$Y$2:$Y$61, 0)) | D13: =AVERAGE(INDEX(MultiYear_ProForma!$X$2:$X$61, MATCH(Scenarios!A13&"|FY2026", MultiYear_ProForma!$Y$2:$Y$61, 0)),INDEX(MultiYear_ProForma!$X$2:$X$61, MATCH(Scenarios!A13&"|FY2027", MultiYear_ProForma!$Y$2:$Y$61, 0)),INDEX(MultiYear_ProForma!$X$2:$X$61, MATCH(Scenarios!A13&"|FY2028", MultiYear_ProForma!$Y$2:$Y$61, 0))) | E13: =AVERAGE(INDEX(MultiYear_ProForma!$X$2:$X$61, MATCH(Scenarios!A13&"|FY2026", MultiYear_ProForma!$Y$2:$Y$61, 0)),INDEX(MultiYear_ProForma!$X$2:$X$61, MATCH(Scenarios!A13&"|FY2027", MultiYear_ProForma!$Y$2:$Y$61, 0)),INDEX(MultiYear_ProForma!$X$2:$X$61, MATCH(Scenarios!A13&"|FY2028", MultiYear_ProForma!$Y$2:$Y$61, 0)),INDEX(MultiYear_ProForma!$X$2:$X$61, MATCH(Scenarios!A13&"|FY2029", MultiYear_ProForma!$Y$2:$Y$61, 0)),INDEX(MultiYear_ProForma!$X$2:$X$61, MATCH(Scenarios!A13&"|FY2030", MultiYear_ProForma!$Y$2:$Y$61, 0))) | F13: =IFERROR(VLOOKUP($A13&"|FY2026", MultiYear_ProForma!$A:$Y, 14, FALSE), "") | G13: =IFERROR(VLOOKUP($A13&"|FY2030", MultiYear_ProForma!$A:$Y, 6, FALSE) + VLOOKUP($A13&"|FY2030", MultiYear_ProForma!$A:$Y, 15, FALSE), "") | H13: 0 | J13: 0 | K13: =INDEX(MultiYear_ProForma!$AA:$AA,MATCH($A13&"|"&"FY2028",MultiYear_ProForma!$B:$B&"|"&MultiYear_ProForma!$C:$C,0)) | L13: =INDEX(MultiYear_ProForma!$AA:$AA,MATCH($A13&"|"&"FY2030",MultiYear_ProForma!$B:$B&"|"&MultiYear_ProForma!$C:$C,0)) | M13: =(SUMIFS(MultiYear_ProForma!$AA:$AA, MultiYear_ProForma!$B:$B, $A13, MultiYear_ProForma!$C:$C, "FY2026")+SUMIFS(MultiYear_ProForma!$AA:$AA, MultiYear_ProForma!$B:$B, $A13, MultiYear_ProForma!$C:$C, "FY2027")+SUMIFS(MultiYear_ProForma!$AA:$AA, MultiYear_ProForma!$B:$B, $A13, MultiYear_ProForma!$C:$C, "FY2028")+SUMIFS(MultiYear_ProForma!$AA:$AA, MultiYear_ProForma!$B:$B, $A13, MultiYear_ProForma!$C:$C, "FY2029")+SUMIFS(MultiYear_ProForma!$AA:$AA, MultiYear_ProForma!$B:$B, $A13, MultiYear_ProForma!$C:$C, "FY2030"))/5 | N13: 0

Sheet BreakEven
A1: Break-even retention r* for A_Repurpose_Both vs selected keep-open scenario
A3: Keep-open scenario (pick from Summary_Costs!A) | B3: D_Grow_Both_0
A5: OpsFactor | B5: =1-BaselineCalc!$B$5
A6: M (displaced if close both) | B6: =BaselineCalc!$B$7 + BaselineCalc!$B$8
A8: FY2028 helpers
A9: Var | B9: =YearMap!B4
A10: EchoFixed | B10: =YearMap!C4
A11: PimaFixed | B11: =YearMap!D4
A12: f_ops | B12: =YearMap!G4
A13: f_lease | B13: =YearMap!F4
A14: Ct(FY2028) | B14: =INDEX(Summary_Costs!$B:$B, MATCH($B$3, Summary_Costs!$A:$A, 0))
B16: h → | C16: 200 | D16: 300 | E16: 400 | F16: 600 | G16: 800 | H16: 1000 | I16: 1200 | J16: 1500
A17: FY2028 f_ops | C17: =IF(($B$14-( $B$9+C16))<=0,NA(),($B$5*$B$12*($B$10+$B$11))/($B$6*($B$14-( $B$9+C16)))) | D17: =IF(($B$14-( $B$9+D16))<=0,NA(),($B$5*$B$12*($B$10+$B$11))/($B$6*($B$14-( $B$9+D16)))) | E17: =IF(($B$14-( $B$9+E16))<=0,NA(),($B$5*$B$12*($B$10+$B$11))/($B$6*($B$14-( $B$9+E16)))) | F17: =IF(($B$14-( $B$9+F16))<=0,NA(),($B$5*$B$12*($B$10+$B$11))/($B$6*($B$14-( $B$9+F16)))) | G17: =IF(($B$14-( $B$9+G16))<=0,NA(),($B$5*$B$12*($B$10+$B$11))/($B$6*($B$14-( $B$9+G16)))) | H17: =IF(($B$14-( $B$9+H16))<=0,NA(),($B$5*$B$12*($B$10+$B$11))/($B$6*($B$14-( $B$9+H16)))) | I17: =IF(($B$14-( $B$9+I16))<=0,NA(),($B$5*$B$12*($B$10+$B$11))/($B$6*($B$14-( $B$9+I16)))) | J17: =IF(($B$14-( $B$9+J16))<=0,NA(),($B$5*$B$12*($B$10+$B$11))/($B$6*($B$14-( $B$9+J16))))
A18: FY2028 f_lease | C18: =IF(($B$14-( $B$9+C16))<=0,NA(),($B$5*$B$13*($B$10+$B$11))/($B$6*($B$14-( $B$9+C16)))) | D18: =IF(($B$14-( $B$9+D16))<=0,NA(),($B$5*$B$13*($B$10+$B$11))/($B$6*($B$14-( $B$9+D16)))) | E18: =IF(($B$14-( $B$9+E16))<=0,NA(),($B$5*$B$13*($B$10+$B$11))/($B$6*($B$14-( $B$9+E16)))) | F18: =IF(($B$14-( $B$9+F16))<=0,NA(),($B$5*$B$13*($B$10+$B$11))/($B$6*($B$14-( $B$9+F16)))) | G18: =IF(($B$14-( $B$9+G16))<=0,NA(),($B$5*$B$13*($B$10+$B$11))/($B$6*($B$14-( $B$9+G16)))) | H18: =IF(($B$14-( $B$9+H16))<=0,NA(),($B$5*$B$13*($B$10+$B$11))/($B$6*($B$14-( $B$9+H16)))) | I18: =IF(($B$14-( $B$9+I16))<=0,NA(),($B$5*$B$13*($B$10+$B$11))/($B$6*($B$14-( $B$9+I16)))) | J18: =IF(($B$14-( $B$9+J16))<=0,NA(),($B$5*$B$13*($B$10+$B$11))/($B$6*($B$14-( $B$9+J16))))
A22: FY2030 helpers
A23: Var | B23: =YearMap!B6
A24: EchoFixed | B24: =YearMap!C6
A25: PimaFixed | B25: =YearMap!D6
A26: f_ops | B26: =YearMap!G6
A27: f_lease | B27: =YearMap!F6
A28: Ct(FY2030) | B28: =INDEX(Summary_Costs!$C:$C, MATCH($B$3, Summary_Costs!$A:$A, 0))
B30: h → | C30: 200 | D30: 300 | E30: 400 | F30: 600 | G30: 800 | H30: 1000 | I30: 1200 | J30: 1500
A31: FY2030 f_ops | C31: =IF(($B$28-( $B$23+C30))<=0,NA(),($B$5*$B$26*($B$24+$B$25))/($B$6*($B$28-( $B$23+C30)))) | D31: =IF(($B$28-( $B$23+D30))<=0,NA(),($B$5*$B$26*($B$24+$B$25))/($B$6*($B$28-( $B$23+D30)))) | E31: =IF(($B$28-( $B$23+E30))<=0,NA(),($B$5*$B$26*($B$24+$B$25))/($B$6*($B$28-( $B$23+E30)))) | F31: =IF(($B$28-( $B$23+F30))<=0,NA(),($B$5*$B$26*($B$24+$B$25))/($B$6*($B$28-( $B$23+F30)))) | G31: =IF(($B$28-( $B$23+G30))<=0,NA(),($B$5*$B$26*($B$24+$B$25))/($B$6*($B$28-( $B$23+G30)))) | H31: =IF(($B$28-( $B$23+H30))<=0,NA(),($B$5*$B$26*($B$24+$B$25))/($B$6*($B$28-( $B$23+H30)))) | I31: =IF(($B$28-( $B$23+I30))<=0,NA(),($B$5*$B$26*($B$24+$B$25))/($B$6*($B$28-( $B$23+I30)))) | J31: =IF(($B$28-( $B$23+J30))<=0,NA(),($B$5*$B$26*($B$24+$B$25))/($B$6*($B$28-( $B$23+J30))))
A32: FY2030 f_lease | C32: =IF(($B$28-( $B$23+C30))<=0,NA(),($B$5*$B$27*($B$24+$B$25))/($B$6*($B$28-( $B$23+C30)))) | D32: =IF(($B$28-( $B$23+D30))<=0,NA(),($B$5*$B$27*($B$24+$B$25))/($B$6*($B$28-( $B$23+D30)))) | E32: =IF(($B$28-( $B$23+E30))<=0,NA(),($B$5*$B$27*($B$24+$B$25))/($B$6*($B$28-( $B$23+E30)))) | F32: =IF(($B$28-( $B$23+F30))<=0,NA(),($B$5*$B$27*($B$24+$B$25))/($B$6*($B$28-( $B$23+F30)))) | G32: =IF(($B$28-( $B$23+G30))<=0,NA(),($B$5*$B$27*($B$24+$B$25))/($B$6*($B$28-( $B$23+G30)))) | H32: =IF(($B$28-( $B$23+H30))<=0,NA(),($B$5*$B$27*($B$24+$B$25))/($B$6*($B$28-( $B$23+H30)))) | I32: =IF(($B$28-( $B$23+I30))<=0,NA(),($B$5*$B$27*($B$24+$B$25))/($B$6*($B$28-( $B$23+I30)))) | J32: =IF(($B$28-( $B$23+J30))<=0,NA(),($B$5*$B$27*($B$24+$B$25))/($B$6*($B$28-( $B$23+J30))))

Sheet Notes
A1: FAQs
B2: Why “Fixed share of M&O = 0.30”?
B3: District M&O typically has a sizable semi‑fixed component (plant ops/custodial/insurance/admin overhead). Without site‑level detail yet, 30% is a conservative placeholder in the middle of the 25–40% range many K‑12 systems sit in. We will replace it with SUSD plant ops + insurance shares when available.
B5: Why “Ops savings (keep‑open) = 0.007 (0.7%)”?
B6: This represents “light discipline” (utilities/purchasing tweaks, route smoothing) that does not depend on closing a site. I set it very low on purpose so it doesn’t drive results. We’ll calibrate with SUSD data (e.g., last year’s utility audits) if provided.
B8: Why “Extra savings (co‑location) = 0.015 (1.5%)”?
B9: This reflects incremental savings from consolidating some services on one campus (custodial/grounds/partial routing). Again kept small and conservative; we’ll swap in real custodial (sq‑ft), grounds and route deltas when we get them.
B11: Why “Repurpose TI per closed site (FY26) = $1.2M”? What is “one‑time carry/TI”?
B12: “TI” = tenant improvements / transition investments needed to convert a K‑8 to a different use (early learning, admin consolidation) and carry costs in year one (e.g., abatement, doors/security, low‑voltage re‑work, furniture, swing space). A light‑touch repurpose can easily run $10–$20/sq‑ft; Echo’s plant is ~77k sq ft, so $1.2M is a reasonable placeholder (we are not assuming a gut remodel). We’ll replace this with SUSD’s scope/estimate if they have one.
A17: Definitions
B18: MO inflation
B19: Base MO per ADM (FY25)
B20: Fixed share of MO
B21: Ops savings (keep‑open)
B22: Extra savings (Co‑location)
B23: Echo base ADM
B24: Pima base ADM
B25: Total base ADM

Sheet Attributes
A1: ScenarioKey | B1: Distinctiveness | C1: Reversibility
A2: A_Repurpose_Both_ops | B2: - | C2: Low
A3: A_Repurpose_Both_lease | B3: - | C3: Low
A4: F_CoLocation_Echo_0 | B4: + | C4: High
A5: D_Grow_Both_0 | B5: + | C5: Med
A6: D_Grow_Both_100 | B6: + | C6: Med
A7: D_Grow_Both_150 | B7: + | C7: Med
A8: E_StatusQuo_Targets_0 | B8: o | C8: High
A9: G_DHub_EchoRamp | B9: + | C9: Med-High

Sheet BreakEven_X
A1: Break-even retention r* for A_Repurpose_Both vs selected keep-open scenario
A3: Keep-open scenario (pick from Summary_Costs!A) | B3: =Dashboard!$B$6
A5: OpsFactor | B5: =1-BaselineCalc!$B$5
A6: M (displaced if close both) | B6: =BaselineCalc!$B$7 + BaselineCalc!$B$8
A8: FY2028 helpers
A9: Var | B9: =YearMap!B4
A10: EchoFixed | B10: =YearMap!C4
A11: PimaFixed | B11: =YearMap!D4
A12: f_ops | B12: =YearMap!G4
A13: f_lease | B13: =YearMap!F4
A14: Ct(FY2028) | B14: =INDEX(Summary_Costs!$B:$B, MATCH($B$3, Summary_Costs!$A:$A, 0))
B16: h → | C16: 200 | D16: 300 | E16: 400 | F16: 600 | G16: 800 | H16: 1000 | I16: 1200 | J16: 1500
A17: FY2028 f_ops | C17: =IF(($B$14-( $B$9+C16))<=0,NA(),($B$5*$B$12*($B$10+$B$11))/($B$6*($B$14-( $B$9+C16)))) | D17: =IF(($B$14-( $B$9+D16))<=0,NA(),($B$5*$B$12*($B$10+$B$11))/($B$6*($B$14-( $B$9+D16)))) | E17: =IF(($B$14-( $B$9+E16))<=0,NA(),($B$5*$B$12*($B$10+$B$11))/($B$6*($B$14-( $B$9+E16)))) | F17: =IF(($B$14-( $B$9+F16))<=0,NA(),($B$5*$B$12*($B$10+$B$11))/($B$6*($B$14-( $B$9+F16)))) | G17: =IF(($B$14-( $B$9+G16))<=0,NA(),($B$5*$B$12*($B$10+$B$11))/($B$6*($B$14-( $B$9+G16)))) | H17: =IF(($B$14-( $B$9+H16))<=0,NA(),($B$5*$B$12*($B$10+$B$11))/($B$6*($B$14-( $B$9+H16)))) | I17: =IF(($B$14-( $B$9+I16))<=0,NA(),($B$5*$B$12*($B$10+$B$11))/($B$6*($B$14-( $B$9+I16)))) | J17: =IF(($B$14-( $B$9+J16))<=0,NA(),($B$5*$B$12*($B$10+$B$11))/($B$6*($B$14-( $B$9+J16))))
A18: FY2028 f_lease | C18: =IF(($B$14-( $B$9+C16))<=0,NA(),($B$5*$B$13*($B$10+$B$11))/($B$6*($B$14-( $B$9+C16)))) | D18: =IF(($B$14-( $B$9+D16))<=0,NA(),($B$5*$B$13*($B$10+$B$11))/($B$6*($B$14-( $B$9+D16)))) | E18: =IF(($B$14-( $B$9+E16))<=0,NA(),($B$5*$B$13*($B$10+$B$11))/($B$6*($B$14-( $B$9+E16)))) | F18: =IF(($B$14-( $B$9+F16))<=0,NA(),($B$5*$B$13*($B$10+$B$11))/($B$6*($B$14-( $B$9+F16)))) | G18: =IF(($B$14-( $B$9+G16))<=0,NA(),($B$5*$B$13*($B$10+$B$11))/($B$6*($B$14-( $B$9+G16)))) | H18: =IF(($B$14-( $B$9+H16))<=0,NA(),($B$5*$B$13*($B$10+$B$11))/($B$6*($B$14-( $B$9+H16)))) | I18: =IF(($B$14-( $B$9+I16))<=0,NA(),($B$5*$B$13*($B$10+$B$11))/($B$6*($B$14-( $B$9+I16)))) | J18: =IF(($B$14-( $B$9+J16))<=0,NA(),($B$5*$B$13*($B$10+$B$11))/($B$6*($B$14-( $B$9+J16))))
A22: FY2030 helpers
A23: Var | B23: =YearMap!B6
A24: EchoFixed | B24: =YearMap!C6
A25: PimaFixed | B25: =YearMap!D6
A26: f_ops | B26: =YearMap!G6
A27: f_lease | B27: =YearMap!F6
A28: Ct(FY2030) | B28: =INDEX(Summary_Costs!$C:$C, MATCH($B$3, Summary_Costs!$A:$A, 0))
B30: h → | C30: 200 | D30: 300 | E30: 400 | F30: 600 | G30: 800 | H30: 1000 | I30: 1200 | J30: 1500
A31: FY2030 f_ops | C31: =IF(($B$28-( $B$23+C30))<=0,NA(),($B$5*$B$26*($B$24+$B$25))/($B$6*($B$28-( $B$23+C30)))) | D31: =IF(($B$28-( $B$23+D30))<=0,NA(),($B$5*$B$26*($B$24+$B$25))/($B$6*($B$28-( $B$23+D30)))) | E31: =IF(($B$28-( $B$23+E30))<=0,NA(),($B$5*$B$26*($B$24+$B$25))/($B$6*($B$28-( $B$23+E30)))) | F31: =IF(($B$28-( $B$23+F30))<=0,NA(),($B$5*$B$26*($B$24+$B$25))/($B$6*($B$28-( $B$23+F30)))) | G31: =IF(($B$28-( $B$23+G30))<=0,NA(),($B$5*$B$26*($B$24+$B$25))/($B$6*($B$28-( $B$23+G30)))) | H31: =IF(($B$28-( $B$23+H30))<=0,NA(),($B$5*$B$26*($B$24+$B$25))/($B$6*($B$28-( $B$23+H30)))) | I31: =IF(($B$28-( $B$23+I30))<=0,NA(),($B$5*$B$26*($B$24+$B$25))/($B$6*($B$28-( $B$23+I30)))) | J31: =IF(($B$28-( $B$23+J30))<=0,NA(),($B$5*$B$26*($B$24+$B$25))/($B$6*($B$28-( $B$23+J30))))
A32: FY2030 f_lease | C32: =IF(($B$28-( $B$23+C30))<=0,NA(),($B$5*$B$27*($B$24+$B$25))/($B$6*($B$28-( $B$23+C30)))) | D32: =IF(($B$28-( $B$23+D30))<=0,NA(),($B$5*$B$27*($B$24+$B$25))/($B$6*($B$28-( $B$23+D30)))) | E32: =IF(($B$28-( $B$23+E30))<=0,NA(),($B$5*$B$27*($B$24+$B$25))/($B$6*($B$28-( $B$23+E30)))) | F32: =IF(($B$28-( $B$23+F30))<=0,NA(),($B$5*$B$27*($B$24+$B$25))/($B$6*($B$28-( $B$23+F30)))) | G32: =IF(($B$28-( $B$23+G30))<=0,NA(),($B$5*$B$27*($B$24+$B$25))/($B$6*($B$28-( $B$23+G30)))) | H32: =IF(($B$28-( $B$23+H30))<=0,NA(),($B$5*$B$27*($B$24+$B$25))/($B$6*($B$28-( $B$23+H30)))) | I32: =IF(($B$28-( $B$23+I30))<=0,NA(),($B$5*$B$27*($B$24+$B$25))/($B$6*($B$28-( $B$23+I30)))) | J32: =IF(($B$28-( $B$23+J30))<=0,NA(),($B$5*$B$27*($B$24+$B$25))/($B$6*($B$28-( $B$23+J30))))

Sheet BreakEven_Y
A1: Break-even retention r* for A_Repurpose_Both vs selected keep-open scenario
A3: Keep-open scenario (pick from Summary_Costs!A) | B3: =Dashboard!$B$7
A5: OpsFactor | B5: =1-BaselineCalc!$B$5
A6: M (displaced if close both) | B6: =BaselineCalc!$B$7 + BaselineCalc!$B$8
A8: FY2028 helpers
A9: Var | B9: =YearMap!B4
A10: EchoFixed | B10: =YearMap!C4
A11: PimaFixed | B11: =YearMap!D4
A12: f_ops | B12: =YearMap!G4
A13: f_lease | B13: =YearMap!F4
A14: Ct(FY2028) | B14: =INDEX(Summary_Costs!$B:$B, MATCH($B$3, Summary_Costs!$A:$A, 0))
B16: h → | C16: 200 | D16: 300 | E16: 400 | F16: 600 | G16: 800 | H16: 1000 | I16: 1200 | J16: 1500
A17: FY2028 f_ops | C17: =IF(($B$14-( $B$9+C16))<=0,NA(),($B$5*$B$12*($B$10+$B$11))/($B$6*($B$14-( $B$9+C16)))) | D17: =IF(($B$14-( $B$9+D16))<=0,NA(),($B$5*$B$12*($B$10+$B$11))/($B$6*($B$14-( $B$9+D16)))) | E17: =IF(($B$14-( $B$9+E16))<=0,NA(),($B$5*$B$12*($B$10+$B$11))/($B$6*($B$14-( $B$9+E16)))) | F17: =IF(($B$14-( $B$9+F16))<=0,NA(),($B$5*$B$12*($B$10+$B$11))/($B$6*($B$14-( $B$9+F16)))) | G17: =IF(($B$14-( $B$9+G16))<=0,NA(),($B$5*$B$12*($B$10+$B$11))/($B$6*($B$14-( $B$9+G16)))) | H17: =IF(($B$14-( $B$9+H16))<=0,NA(),($B$5*$B$12*($B$10+$B$11))/($B$6*($B$14-( $B$9+H16)))) | I17: =IF(($B$14-( $B$9+I16))<=0,NA(),($B$5*$B$12*($B$10+$B$11))/($B$6*($B$14-( $B$9+I16)))) | J17: =IF(($B$14-( $B$9+J16))<=0,NA(),($B$5*$B$12*($B$10+$B$11))/($B$6*($B$14-( $B$9+J16))))
A18: FY2028 f_lease | C18: =IF(($B$14-( $B$9+C16))<=0,NA(),($B$5*$B$13*($B$10+$B$11))/($B$6*($B$14-( $B$9+C16)))) | D18: =IF(($B$14-( $B$9+D16))<=0,NA(),($B$5*$B$13*($B$10+$B$11))/($B$6*($B$14-( $B$9+D16)))) | E18: =IF(($B$14-( $B$9+E16))<=0,NA(),($B$5*$B$13*($B$10+$B$11))/($B$6*($B$14-( $B$9+E16)))) | F18: =IF(($B$14-( $B$9+F16))<=0,NA(),($B$5*$B$13*($B$10+$B$11))/($B$6*($B$14-( $B$9+F16)))) | G18: =IF(($B$14-( $B$9+G16))<=0,NA(),($B$5*$B$13*($B$10+$B$11))/($B$6*($B$14-( $B$9+G16)))) | H18: =IF(($B$14-( $B$9+H16))<=0,NA(),($B$5*$B$13*($B$10+$B$11))/($B$6*($B$14-( $B$9+H16)))) | I18: =IF(($B$14-( $B$9+I16))<=0,NA(),($B$5*$B$13*($B$10+$B$11))/($B$6*($B$14-( $B$9+I16)))) | J18: =IF(($B$14-( $B$9+J16))<=0,NA(),($B$5*$B$13*($B$10+$B$11))/($B$6*($B$14-( $B$9+J16))))
A22: FY2030 helpers
A23: Var | B23: =YearMap!B6
A24: EchoFixed | B24: =YearMap!C6
A25: PimaFixed | B25: =YearMap!D6
A26: f_ops | B26: =YearMap!G6
A27: f_lease | B27: =YearMap!F6
A28: Ct(FY2030) | B28: =INDEX(Summary_Costs!$C:$C, MATCH($B$3, Summary_Costs!$A:$A, 0))
B30: h → | C30: 200 | D30: 300 | E30: 400 | F30: 600 | G30: 800 | H30: 1000 | I30: 1200 | J30: 1500
A31: FY2030 f_ops | C31: =IF(($B$28-( $B$23+C30))<=0,NA(),($B$5*$B$26*($B$24+$B$25))/($B$6*($B$28-( $B$23+C30)))) | D31: =IF(($B$28-( $B$23+D30))<=0,NA(),($B$5*$B$26*($B$24+$B$25))/($B$6*($B$28-( $B$23+D30)))) | E31: =IF(($B$28-( $B$23+E30))<=0,NA(),($B$5*$B$26*($B$24+$B$25))/($B$6*($B$28-( $B$23+E30)))) | F31: =IF(($B$28-( $B$23+F30))<=0,NA(),($B$5*$B$26*($B$24+$B$25))/($B$6*($B$28-( $B$23+F30)))) | G31: =IF(($B$28-( $B$23+G30))<=0,NA(),($B$5*$B$26*($B$24+$B$25))/($B$6*($B$28-( $B$23+G30)))) | H31: =IF(($B$28-( $B$23+H30))<=0,NA(),($B$5*$B$26*($B$24+$B$25))/($B$6*($B$28-( $B$23+H30)))) | I31: =IF(($B$28-( $B$23+I30))<=0,NA(),($B$5*$B$26*($B$24+$B$25))/($B$6*($B$28-( $B$23+I30)))) | J31: =IF(($B$28-( $B$23+J30))<=0,NA(),($B$5*$B$26*($B$24+$B$25))/($B$6*($B$28-( $B$23+J30))))
A32: FY2030 f_lease | C32: =IF(($B$28-( $B$23+C30))<=0,NA(),($B$5*$B$27*($B$24+$B$25))/($B$6*($B$28-( $B$23+C30)))) | D32: =IF(($B$28-( $B$23+D30))<=0,NA(),($B$5*$B$27*($B$24+$B$25))/($B$6*($B$28-( $B$23+D30)))) | E32: =IF(($B$28-( $B$23+E30))<=0,NA(),($B$5*$B$27*($B$24+$B$25))/($B$6*($B$28-( $B$23+E30)))) | F32: =IF(($B$28-( $B$23+F30))<=0,NA(),($B$5*$B$27*($B$24+$B$25))/($B$6*($B$28-( $B$23+F30)))) | G32: =IF(($B$28-( $B$23+G30))<=0,NA(),($B$5*$B$27*($B$24+$B$25))/($B$6*($B$28-( $B$23+G30)))) | H32: =IF(($B$28-( $B$23+H30))<=0,NA(),($B$5*$B$27*($B$24+$B$25))/($B$6*($B$28-( $B$23+H30)))) | I32: =IF(($B$28-( $B$23+I30))<=0,NA(),($B$5*$B$27*($B$24+$B$25))/($B$6*($B$28-( $B$23+I30)))) | J32: =IF(($B$28-( $B$23+J30))<=0,NA(),($B$5*$B$27*($B$24+$B$25))/($B$6*($B$28-( $B$23+J30))))

Sheet Parameters
A1: Parameter | B1: Value
A2: MarginalFactor_for_Overlay | B2: 0.5
