Workbook

Sheet BaselineCalc
A1: Parameter | B1: Value | C1: Notes
A2: MO inflation | B2: 0.025 | C2: Annual inflation factor.
A3: Base MO per ADM (FY25) | B3: 9936 | C3: Working base for FY25.
A4: Fixed share of MO | B4: 0.3 | C4: Share treated as semi‑fixed (plant/insurance).
A5: Ops savings (keep‑open) | B5: 0.007 | C5: Light discipline if sites remain open (not used here).
A6: Extra savings (Co‑location) | B6: 0.015 | C6: Incremental savings for co‑location (not used here).
A7: Echo base ADM | B7: 257
A8: Pima base ADM | B8: 296
A9: Total base ADM | B9: =B7+B8 | C9: Echo base ADM + Pima base ADM
A12: Helper / Derivation | B12: FY26 | C12: FY27 | D12: FY28 | E12: FY29 | F12: FY30 | G12: Notes
A13: Base total MO (FY25) | B13: =B9*B3 | C13: =C14/$B$4 | D13: =D14/$B$4 | E13: =E14/$B$4 | F13: =F14/$B$4 | G13: Total ADM × Base MO/ADM | K13: B13 = B9*B3 (Base total MO, FY25)
A14: Fixed MO (FY25) | B14: =B13*B4 | C14: =B17 | D14: =C17 | E14: =D17 | F14: =E17 | G14: Fixed = Base total × Fixed share | K14: B14 = B13*B4 (Fixed MO, FY25)
A15: Var per student (FY25) | B15: =(B13-B14)/B9 | C15: =B18 | D15: =C18 | E15: =D18 | F15: =E18 | G15: Variable = (Base total − Fixed)/Total ADM | K15: B15 = (B13–B14)/B9 (Variable $/student, FY25)
A17: Fixed total ($) | B17: =$B$14*(1+$B$2)^1 | C17: =$B$14*(1+$B$2)^2 | D17: =$B$14*(1+$B$2)^3 | E17: =$B$14*(1+$B$2)^4 | F17: =$B$14*(1+$B$2)^5
A18: Var unit ($/student) | B18: =$B$15*(1+$B$2)^1 | C18: =$B$15*(1+$B$2)^2 | D18: =$B$15*(1+$B$2)^3 | E18: =$B$15*(1+$B$2)^4 | F18: =$B$15*(1+$B$2)^5
A19: Echo fixed ($) | B19: =B17*($B$7/$B$9) | C19: =C17*($B$7/$B$9) | D19: =D17*($B$7/$B$9) | E19: =E17*($B$7/$B$9) | F19: =F17*($B$7/$B$9)
A20: Pima fixed ($) | B20: =B17*($B$8/$B$9) | C20: =C17*($B$8/$B$9) | D20: =D17*($B$8/$B$9) | E20: =E17*($B$8/$B$9) | F20: =F17*($B$8/$B$9)
A22: Notes
A23: All formulas are same‑sheet and reference the Parameter cells above.

Sheet YearMap
A1: Year | B1: VarUnit$ | C1: EchoFixed$ | D1: PimaFixed$ | E1: h | F1: f_lease | G1: f_ops
A2: FY2026 | B2: =BaselineCalc!B18 | C2: =BaselineCalc!B19 | D2: =BaselineCalc!B20 | E2: 1000 | F2: 0.4 | G2: 0.4
A3: FY2027 | B3: =BaselineCalc!C18 | C3: =BaselineCalc!C19 | D3: =BaselineCalc!C20 | E3: 800 | F3: 0.3 | G3: 0.35
A4: FY2028 | B4: =BaselineCalc!D18 | C4: =BaselineCalc!D19 | D4: =BaselineCalc!D20 | E4: 600 | F4: 0.2 | G4: 0.3
A5: FY2029 | B5: =BaselineCalc!E18 | C5: =BaselineCalc!E19 | D5: =BaselineCalc!E20 | E5: 400 | F5: 0.1 | G5: 0.25
A6: FY2030 | B6: =BaselineCalc!F18 | C6: =BaselineCalc!F19 | D6: =BaselineCalc!F20 | E6: 300 | F6: 0 | G6: 0.2

Sheet Scenarios
A1: ScenarioKey | B1: Label | C1: Overlay | D1: CloseEcho | E1: ClosePima | F1: EchoShareDist | G1: ExtraSave | H1: Notes
A2: D_Grow_Both_0 | B2: D. Grow Both (Overlay 0) | C2: 0 | D2: 0 | E2: 0 | F2: 0.5 | G2: 0 | H2: Baseline + outreach; no closures
A3: E_StatusQuo_Targets_0 | B3: E. Status‑Quo + Targets (0) | C3: 0 | D3: 0 | E3: 0 | F3: 0.5 | G3: 0 | H3: Baseline + targets; no closures
A4: F_CoLocation_Echo_0 | B4: F. Co‑Location @ Echo (0) | C4: 0 | D4: 0 | E4: 0 | F4: 0.7 | G4: 0.015 | H4: Shared‑use efficiencies later (no closure)
A6: ScenarioKey | B6: Year | C6: Echo_ADM | D6: Pima_ADM | E6: Total_ADM | F6: VarUnit$ | G6: EchoFixed$ | H6: PimaFixed$ | I6: Key
A7: =A2 | B7: FY2026 | C7: =IF(D2=1,0, BaselineCalc!$B$7 + ROUND(C2*F2,0)) | D7: =IF(E2=1,0, BaselineCalc!$B$8 + C2 - ROUND(C2*F2,0)) | E7: =C7+D7 | F7: =VLOOKUP(B7,YearMap!$A$2:$B$6,2,FALSE) | G7: =VLOOKUP(B7,YearMap!$A$2:$C$6,3,FALSE) | H7: =VLOOKUP(B7,YearMap!$A$2:$D$6,4,FALSE) | I7: =A7&"|"&B7
A8: =A2 | B8: FY2027 | C8: =IF(D2=1,0, BaselineCalc!$B$7 + ROUND(C2*F2,0)) | D8: =IF(E2=1,0, BaselineCalc!$B$8 + C2 - ROUND(C2*F2,0)) | E8: =C8+D8 | F8: =VLOOKUP(B8,YearMap!$A$2:$B$6,2,FALSE) | G8: =VLOOKUP(B8,YearMap!$A$2:$C$6,3,FALSE) | H8: =VLOOKUP(B8,YearMap!$A$2:$D$6,4,FALSE) | I8: =A8&"|"&B8
A9: =A2 | B9: FY2028 | C9: =IF(D2=1,0, BaselineCalc!$B$7 + ROUND(C2*F2,0)) | D9: =IF(E2=1,0, BaselineCalc!$B$8 + C2 - ROUND(C2*F2,0)) | E9: =C9+D9 | F9: =VLOOKUP(B9,YearMap!$A$2:$B$6,2,FALSE) | G9: =VLOOKUP(B9,YearMap!$A$2:$C$6,3,FALSE) | H9: =VLOOKUP(B9,YearMap!$A$2:$D$6,4,FALSE) | I9: =A9&"|"&B9
A10: =A2 | B10: FY2029 | C10: =IF(D2=1,0, BaselineCalc!$B$7 + ROUND(C2*F2,0)) | D10: =IF(E2=1,0, BaselineCalc!$B$8 + C2 - ROUND(C2*F2,0)) | E10: =C10+D10 | F10: =VLOOKUP(B10,YearMap!$A$2:$B$6,2,FALSE) | G10: =VLOOKUP(B10,YearMap!$A$2:$C$6,3,FALSE) | H10: =VLOOKUP(B10,YearMap!$A$2:$D$6,4,FALSE) | I10: =A10&"|"&B10
A11: =A2 | B11: FY2030 | C11: =IF(D2=1,0, BaselineCalc!$B$7 + ROUND(C2*F2,0)) | D11: =IF(E2=1,0, BaselineCalc!$B$8 + C2 - ROUND(C2*F2,0)) | E11: =C11+D11 | F11: =VLOOKUP(B11,YearMap!$A$2:$B$6,2,FALSE) | G11: =VLOOKUP(B11,YearMap!$A$2:$C$6,3,FALSE) | H11: =VLOOKUP(B11,YearMap!$A$2:$D$6,4,FALSE) | I11: =A11&"|"&B11
A12: =A3 | B12: FY2026 | C12: =IF(D3=1,0, BaselineCalc!$B$7 + ROUND(C3*F3,0)) | D12: =IF(E3=1,0, BaselineCalc!$B$8 + C3 - ROUND(C3*F3,0)) | E12: =C12+D12 | F12: =VLOOKUP(B12,YearMap!$A$2:$B$6,2,FALSE) | G12: =VLOOKUP(B12,YearMap!$A$2:$C$6,3,FALSE) | H12: =VLOOKUP(B12,YearMap!$A$2:$D$6,4,FALSE) | I12: =A12&"|"&B12
A13: =A3 | B13: FY2027 | C13: =IF(D3=1,0, BaselineCalc!$B$7 + ROUND(C3*F3,0)) | D13: =IF(E3=1,0, BaselineCalc!$B$8 + C3 - ROUND(C3*F3,0)) | E13: =C13+D13 | F13: =VLOOKUP(B13,YearMap!$A$2:$B$6,2,FALSE) | G13: =VLOOKUP(B13,YearMap!$A$2:$C$6,3,FALSE) | H13: =VLOOKUP(B13,YearMap!$A$2:$D$6,4,FALSE) | I13: =A13&"|"&B13
A14: =A3 | B14: FY2028 | C14: =IF(D3=1,0, BaselineCalc!$B$7 + ROUND(C3*F3,0)) | D14: =IF(E3=1,0, BaselineCalc!$B$8 + C3 - ROUND(C3*F3,0)) | E14: =C14+D14 | F14: =VLOOKUP(B14,YearMap!$A$2:$B$6,2,FALSE) | G14: =VLOOKUP(B14,YearMap!$A$2:$C$6,3,FALSE) | H14: =VLOOKUP(B14,YearMap!$A$2:$D$6,4,FALSE) | I14: =A14&"|"&B14
A15: =A3 | B15: FY2029 | C15: =IF(D3=1,0, BaselineCalc!$B$7 + ROUND(C3*F3,0)) | D15: =IF(E3=1,0, BaselineCalc!$B$8 + C3 - ROUND(C3*F3,0)) | E15: =C15+D15 | F15: =VLOOKUP(B15,YearMap!$A$2:$B$6,2,FALSE) | G15: =VLOOKUP(B15,YearMap!$A$2:$C$6,3,FALSE) | H15: =VLOOKUP(B15,YearMap!$A$2:$D$6,4,FALSE) | I15: =A15&"|"&B15
A16: =A3 | B16: FY2030 | C16: =IF(D3=1,0, BaselineCalc!$B$7 + ROUND(C3*F3,0)) | D16: =IF(E3=1,0, BaselineCalc!$B$8 + C3 - ROUND(C3*F3,0)) | E16: =C16+D16 | F16: =VLOOKUP(B16,YearMap!$A$2:$B$6,2,FALSE) | G16: =VLOOKUP(B16,YearMap!$A$2:$C$6,3,FALSE) | H16: =VLOOKUP(B16,YearMap!$A$2:$D$6,4,FALSE) | I16: =A16&"|"&B16
A17: =A4 | B17: FY2026 | C17: =IF(D4=1,0, BaselineCalc!$B$7 + ROUND(C4*F4,0)) | D17: =IF(E4=1,0, BaselineCalc!$B$8 + C4 - ROUND(C4*F4,0)) | E17: =C17+D17 | F17: =VLOOKUP(B17,YearMap!$A$2:$B$6,2,FALSE) | G17: =VLOOKUP(B17,YearMap!$A$2:$C$6,3,FALSE) | H17: =VLOOKUP(B17,YearMap!$A$2:$D$6,4,FALSE) | I17: =A17&"|"&B17
A18: =A4 | B18: FY2027 | C18: =IF(D4=1,0, BaselineCalc!$B$7 + ROUND(C4*F4,0)) | D18: =IF(E4=1,0, BaselineCalc!$B$8 + C4 - ROUND(C4*F4,0)) | E18: =C18+D18 | F18: =VLOOKUP(B18,YearMap!$A$2:$B$6,2,FALSE) | G18: =VLOOKUP(B18,YearMap!$A$2:$C$6,3,FALSE) | H18: =VLOOKUP(B18,YearMap!$A$2:$D$6,4,FALSE) | I18: =A18&"|"&B18
A19: =A4 | B19: FY2028 | C19: =IF(D4=1,0, BaselineCalc!$B$7 + ROUND(C4*F4,0)) | D19: =IF(E4=1,0, BaselineCalc!$B$8 + C4 - ROUND(C4*F4,0)) | E19: =C19+D19 | F19: =VLOOKUP(B19,YearMap!$A$2:$B$6,2,FALSE) | G19: =VLOOKUP(B19,YearMap!$A$2:$C$6,3,FALSE) | H19: =VLOOKUP(B19,YearMap!$A$2:$D$6,4,FALSE) | I19: =A19&"|"&B19
A20: =A4 | B20: FY2029 | C20: =IF(D4=1,0, BaselineCalc!$B$7 + ROUND(C4*F4,0)) | D20: =IF(E4=1,0, BaselineCalc!$B$8 + C4 - ROUND(C4*F4,0)) | E20: =C20+D20 | F20: =VLOOKUP(B20,YearMap!$A$2:$B$6,2,FALSE) | G20: =VLOOKUP(B20,YearMap!$A$2:$C$6,3,FALSE) | H20: =VLOOKUP(B20,YearMap!$A$2:$D$6,4,FALSE) | I20: =A20&"|"&B20
A21: =A4 | B21: FY2030 | C21: =IF(D4=1,0, BaselineCalc!$B$7 + ROUND(C4*F4,0)) | D21: =IF(E4=1,0, BaselineCalc!$B$8 + C4 - ROUND(C4*F4,0)) | E21: =C21+D21 | F21: =VLOOKUP(B21,YearMap!$A$2:$B$6,2,FALSE) | G21: =VLOOKUP(B21,YearMap!$A$2:$C$6,3,FALSE) | H21: =VLOOKUP(B21,YearMap!$A$2:$D$6,4,FALSE) | I21: =A21&"|"&B21
A22: D_Grow_Both_100 | B22: D. Grow Both (Overlay 100) | C22: 100 | D22: 0 | E22: 0 | F22: 0.5 | G22: 0 | H22: Baseline +100 overlay
A23: D_Grow_Both_150 | B23: D. Grow Both (Overlay 150) | C23: 150 | D23: 0 | E23: 0 | F23: 0.5 | G23: 0 | H23: Baseline +150 overlay
A24: G_DHub_EchoRamp | B24: G. D‑Hub @ Echo (Ramp 50→100→150) | C24: 150 | D24: 0 | E24: 0 | F24: 0.7 | G24: 0 | H24: Time‑phased ramp: +50, +100, +150

Sheet Notes
A1: FAQs
B2: Why “Fixed share of M&O = 0.30”?
B3: District M&O typically has a sizable semi‑fixed component (plant ops/custodial/insurance/admin overhead). Without site‑level detail yet, 30% is a conservative placeholder in the middle of the 25–40% range many K‑12 systems sit in. We will replace it with SUSD plant ops + insurance shares when available.
B5: Why “Ops savings (keep‑open) = 0.007 (0.7%)”?
B6: This represents “light discipline” (utilities/purchasing tweaks, route smoothing) that does not depend on closing a site. I set it very low on purpose so it doesn’t drive results. We’ll calibrate with SUSD data (e.g., last year’s utility audits) if provided.
B8: Why “Extra savings (co‑location) = 0.015 (1.5%)”?
B9: This reflects incremental savings from consolidating some services on one campus (custodial/grounds/partial routing). Again kept small and conservative; we’ll swap in real custodial (sq‑ft), grounds and route deltas when we get them.
B11: Why “Repurpose TI per closed site (FY26) = $1.2M”? What is “one‑time carry/TI”?
B12: “TI” = tenant improvements / transition investments needed to convert a K‑8 to a different use (early learning, admin consolidation) and carry costs in year one (e.g., abatement, doors/security, low‑voltage re‑work, furniture, swing space). A light‑touch repurpose can easily run $10–$20/sq‑ft; Echo’s plant is ~77k sq ft, so $1.2M is a reasonable placeholder (we are not assuming a gut remodel). We’ll replace this with SUSD’s scope/estimate if they have one.
A17: Definitions
B18: MO inflation
B19: Base MO per ADM (FY25)
B20: Fixed share of MO
B21: Ops savings (keep‑open)
B22: Extra savings (Co‑location)
B23: Echo base ADM
B24: Pima base ADM
B25: Total base ADM

Sheet MultiYear_ProForma
A1: ScenarioKey | B1: Year | C1: Echo_ADM | D1: Pima_ADM | E1: Total_ADM | F1: VarUnit$ | G1: EchoFixed$ | H1: PimaFixed$ | I1: OpsFactor | J1: ExtraSave | K1: Total_MO$ | L1: MO_per_ADM$ | M1: Key
A2: =Scenarios!A2 | B2: FY2026 | C2: =IF(Scenarios!D2=1,0, BaselineCalc!$B$7 + ROUND((=IF(ISNUMBER(SEARCH("Ramp",A2)), CHOOSE(MATCH(B2,{"FY2026","FY2027","FY2028","FY2029","FY2030"},0),50,100,150,150,150), Scenarios!C2))*Scenarios!F2,0)) | D2: =IF(Scenarios!E2=1,0, BaselineCalc!$B$8 + (=IF(ISNUMBER(SEARCH("Ramp",A2)), CHOOSE(MATCH(B2,{"FY2026","FY2027","FY2028","FY2029","FY2030"},0),50,100,150,150,150), Scenarios!C2)) - ROUND((=IF(ISNUMBER(SEARCH("Ramp",A2)), CHOOSE(MATCH(B2,{"FY2026","FY2027","FY2028","FY2029","FY2030"},0),50,100,150,150,150), Scenarios!C2))*Scenarios!F2,0)) | E2: =C2+D2 | F2: =VLOOKUP(B2,YearMap!$A$2:$B$6,2,FALSE) | G2: =VLOOKUP(B2,YearMap!$A$2:$C$6,3,FALSE) | H2: =VLOOKUP(B2,YearMap!$A$2:$D$6,4,FALSE) | I2: =1-BaselineCalc!$B$5 | J2: =Scenarios!G2 | K2: =(G2+H2+F2*E2)*I2*(1-J2) | L2: =IF(E2>0, K2/E2, NA()) | M2: =A2&"|"&B2
A3: =Scenarios!A2 | B3: FY2027 | C3: =IF(Scenarios!D2=1,0, BaselineCalc!$B$7 + ROUND((=IF(ISNUMBER(SEARCH("Ramp",A3)), CHOOSE(MATCH(B3,{"FY2026","FY2027","FY2028","FY2029","FY2030"},0),50,100,150,150,150), Scenarios!C2))*Scenarios!F2,0)) | D3: =IF(Scenarios!E2=1,0, BaselineCalc!$B$8 + (=IF(ISNUMBER(SEARCH("Ramp",A3)), CHOOSE(MATCH(B3,{"FY2026","FY2027","FY2028","FY2029","FY2030"},0),50,100,150,150,150), Scenarios!C2)) - ROUND((=IF(ISNUMBER(SEARCH("Ramp",A3)), CHOOSE(MATCH(B3,{"FY2026","FY2027","FY2028","FY2029","FY2030"},0),50,100,150,150,150), Scenarios!C2))*Scenarios!F2,0)) | E3: =C3+D3 | F3: =VLOOKUP(B3,YearMap!$A$2:$B$6,2,FALSE) | G3: =VLOOKUP(B3,YearMap!$A$2:$C$6,3,FALSE) | H3: =VLOOKUP(B3,YearMap!$A$2:$D$6,4,FALSE) | I3: =1-BaselineCalc!$B$5 | J3: =Scenarios!G2 | K3: =(G3+H3+F3*E3)*I3*(1-J3) | L3: =IF(E3>0, K3/E3, NA()) | M3: =A3&"|"&B3
A4: =Scenarios!A2 | B4: FY2028 | C4: =IF(Scenarios!D2=1,0, BaselineCalc!$B$7 + ROUND((=IF(ISNUMBER(SEARCH("Ramp",A4)), CHOOSE(MATCH(B4,{"FY2026","FY2027","FY2028","FY2029","FY2030"},0),50,100,150,150,150), Scenarios!C2))*Scenarios!F2,0)) | D4: =IF(Scenarios!E2=1,0, BaselineCalc!$B$8 + (=IF(ISNUMBER(SEARCH("Ramp",A4)), CHOOSE(MATCH(B4,{"FY2026","FY2027","FY2028","FY2029","FY2030"},0),50,100,150,150,150), Scenarios!C2)) - ROUND((=IF(ISNUMBER(SEARCH("Ramp",A4)), CHOOSE(MATCH(B4,{"FY2026","FY2027","FY2028","FY2029","FY2030"},0),50,100,150,150,150), Scenarios!C2))*Scenarios!F2,0)) | E4: =C4+D4 | F4: =VLOOKUP(B4,YearMap!$A$2:$B$6,2,FALSE) | G4: =VLOOKUP(B4,YearMap!$A$2:$C$6,3,FALSE) | H4: =VLOOKUP(B4,YearMap!$A$2:$D$6,4,FALSE) | I4: =1-BaselineCalc!$B$5 | J4: =Scenarios!G2 | K4: =(G4+H4+F4*E4)*I4*(1-J4) | L4: =IF(E4>0, K4/E4, NA()) | M4: =A4&"|"&B4
A5: =Scenarios!A2 | B5: FY2029 | C5: =IF(Scenarios!D2=1,0, BaselineCalc!$B$7 + ROUND((=IF(ISNUMBER(SEARCH("Ramp",A5)), CHOOSE(MATCH(B5,{"FY2026","FY2027","FY2028","FY2029","FY2030"},0),50,100,150,150,150), Scenarios!C2))*Scenarios!F2,0)) | D5: =IF(Scenarios!E2=1,0, BaselineCalc!$B$8 + (=IF(ISNUMBER(SEARCH("Ramp",A5)), CHOOSE(MATCH(B5,{"FY2026","FY2027","FY2028","FY2029","FY2030"},0),50,100,150,150,150), Scenarios!C2)) - ROUND((=IF(ISNUMBER(SEARCH("Ramp",A5)), CHOOSE(MATCH(B5,{"FY2026","FY2027","FY2028","FY2029","FY2030"},0),50,100,150,150,150), Scenarios!C2))*Scenarios!F2,0)) | E5: =C5+D5 | F5: =VLOOKUP(B5,YearMap!$A$2:$B$6,2,FALSE) | G5: =VLOOKUP(B5,YearMap!$A$2:$C$6,3,FALSE) | H5: =VLOOKUP(B5,YearMap!$A$2:$D$6,4,FALSE) | I5: =1-BaselineCalc!$B$5 | J5: =Scenarios!G2 | K5: =(G5+H5+F5*E5)*I5*(1-J5) | L5: =IF(E5>0, K5/E5, NA()) | M5: =A5&"|"&B5
A6: =Scenarios!A2 | B6: FY2030 | C6: =IF(Scenarios!D2=1,0, BaselineCalc!$B$7 + ROUND((=IF(ISNUMBER(SEARCH("Ramp",A6)), CHOOSE(MATCH(B6,{"FY2026","FY2027","FY2028","FY2029","FY2030"},0),50,100,150,150,150), Scenarios!C2))*Scenarios!F2,0)) | D6: =IF(Scenarios!E2=1,0, BaselineCalc!$B$8 + (=IF(ISNUMBER(SEARCH("Ramp",A6)), CHOOSE(MATCH(B6,{"FY2026","FY2027","FY2028","FY2029","FY2030"},0),50,100,150,150,150), Scenarios!C2)) - ROUND((=IF(ISNUMBER(SEARCH("Ramp",A6)), CHOOSE(MATCH(B6,{"FY2026","FY2027","FY2028","FY2029","FY2030"},0),50,100,150,150,150), Scenarios!C2))*Scenarios!F2,0)) | E6: =C6+D6 | F6: =VLOOKUP(B6,YearMap!$A$2:$B$6,2,FALSE) | G6: =VLOOKUP(B6,YearMap!$A$2:$C$6,3,FALSE) | H6: =VLOOKUP(B6,YearMap!$A$2:$D$6,4,FALSE) | I6: =1-BaselineCalc!$B$5 | J6: =Scenarios!G2 | K6: =(G6+H6+F6*E6)*I6*(1-J6) | L6: =IF(E6>0, K6/E6, NA()) | M6: =A6&"|"&B6
A7: =Scenarios!A3 | B7: FY2026 | C7: =IF(Scenarios!D3=1,0, BaselineCalc!$B$7 + ROUND((=IF(ISNUMBER(SEARCH("Ramp",A7)), CHOOSE(MATCH(B7,{"FY2026","FY2027","FY2028","FY2029","FY2030"},0),50,100,150,150,150), Scenarios!C3))*Scenarios!F3,0)) | D7: =IF(Scenarios!E3=1,0, BaselineCalc!$B$8 + (=IF(ISNUMBER(SEARCH("Ramp",A7)), CHOOSE(MATCH(B7,{"FY2026","FY2027","FY2028","FY2029","FY2030"},0),50,100,150,150,150), Scenarios!C3)) - ROUND((=IF(ISNUMBER(SEARCH("Ramp",A7)), CHOOSE(MATCH(B7,{"FY2026","FY2027","FY2028","FY2029","FY2030"},0),50,100,150,150,150), Scenarios!C3))*Scenarios!F3,0)) | E7: =C7+D7 | F7: =VLOOKUP(B7,YearMap!$A$2:$B$6,2,FALSE) | G7: =VLOOKUP(B7,YearMap!$A$2:$C$6,3,FALSE) | H7: =VLOOKUP(B7,YearMap!$A$2:$D$6,4,FALSE) | I7: =1-BaselineCalc!$B$5 | J7: =Scenarios!G3 | K7: =(G7+H7+F7*E7)*I7*(1-J7) | L7: =IF(E7>0, K7/E7, NA()) | M7: =A7&"|"&B7
A8: =Scenarios!A3 | B8: FY2027 | C8: =IF(Scenarios!D3=1,0, BaselineCalc!$B$7 + ROUND((=IF(ISNUMBER(SEARCH("Ramp",A8)), CHOOSE(MATCH(B8,{"FY2026","FY2027","FY2028","FY2029","FY2030"},0),50,100,150,150,150), Scenarios!C3))*Scenarios!F3,0)) | D8: =IF(Scenarios!E3=1,0, BaselineCalc!$B$8 + (=IF(ISNUMBER(SEARCH("Ramp",A8)), CHOOSE(MATCH(B8,{"FY2026","FY2027","FY2028","FY2029","FY2030"},0),50,100,150,150,150), Scenarios!C3)) - ROUND((=IF(ISNUMBER(SEARCH("Ramp",A8)), CHOOSE(MATCH(B8,{"FY2026","FY2027","FY2028","FY2029","FY2030"},0),50,100,150,150,150), Scenarios!C3))*Scenarios!F3,0)) | E8: =C8+D8 | F8: =VLOOKUP(B8,YearMap!$A$2:$B$6,2,FALSE) | G8: =VLOOKUP(B8,YearMap!$A$2:$C$6,3,FALSE) | H8: =VLOOKUP(B8,YearMap!$A$2:$D$6,4,FALSE) | I8: =1-BaselineCalc!$B$5 | J8: =Scenarios!G3 | K8: =(G8+H8+F8*E8)*I8*(1-J8) | L8: =IF(E8>0, K8/E8, NA()) | M8: =A8&"|"&B8
A9: =Scenarios!A3 | B9: FY2028 | C9: =IF(Scenarios!D3=1,0, BaselineCalc!$B$7 + ROUND((=IF(ISNUMBER(SEARCH("Ramp",A9)), CHOOSE(MATCH(B9,{"FY2026","FY2027","FY2028","FY2029","FY2030"},0),50,100,150,150,150), Scenarios!C3))*Scenarios!F3,0)) | D9: =IF(Scenarios!E3=1,0, BaselineCalc!$B$8 + (=IF(ISNUMBER(SEARCH("Ramp",A9)), CHOOSE(MATCH(B9,{"FY2026","FY2027","FY2028","FY2029","FY2030"},0),50,100,150,150,150), Scenarios!C3)) - ROUND((=IF(ISNUMBER(SEARCH("Ramp",A9)), CHOOSE(MATCH(B9,{"FY2026","FY2027","FY2028","FY2029","FY2030"},0),50,100,150,150,150), Scenarios!C3))*Scenarios!F3,0)) | E9: =C9+D9 | F9: =VLOOKUP(B9,YearMap!$A$2:$B$6,2,FALSE) | G9: =VLOOKUP(B9,YearMap!$A$2:$C$6,3,FALSE) | H9: =VLOOKUP(B9,YearMap!$A$2:$D$6,4,FALSE) | I9: =1-BaselineCalc!$B$5 | J9: =Scenarios!G3 | K9: =(G9+H9+F9*E9)*I9*(1-J9) | L9: =IF(E9>0, K9/E9, NA()) | M9: =A9&"|"&B9
A10: =Scenarios!A3 | B10: FY2029 | C10: =IF(Scenarios!D3=1,0, BaselineCalc!$B$7 + ROUND((=IF(ISNUMBER(SEARCH("Ramp",A10)), CHOOSE(MATCH(B10,{"FY2026","FY2027","FY2028","FY2029","FY2030"},0),50,100,150,150,150), Scenarios!C3))*Scenarios!F3,0)) | D10: =IF(Scenarios!E3=1,0, BaselineCalc!$B$8 + (=IF(ISNUMBER(SEARCH("Ramp",A10)), CHOOSE(MATCH(B10,{"FY2026","FY2027","FY2028","FY2029","FY2030"},0),50,100,150,150,150), Scenarios!C3)) - ROUND((=IF(ISNUMBER(SEARCH("Ramp",A10)), CHOOSE(MATCH(B10,{"FY2026","FY2027","FY2028","FY2029","FY2030"},0),50,100,150,150,150), Scenarios!C3))*Scenarios!F3,0)) | E10: =C10+D10 | F10: =VLOOKUP(B10,YearMap!$A$2:$B$6,2,FALSE) | G10: =VLOOKUP(B10,YearMap!$A$2:$C$6,3,FALSE) | H10: =VLOOKUP(B10,YearMap!$A$2:$D$6,4,FALSE) | I10: =1-BaselineCalc!$B$5 | J10: =Scenarios!G3 | K10: =(G10+H10+F10*E10)*I10*(1-J10) | L10: =IF(E10>0, K10/E10, NA()) | M10: =A10&"|"&B10
A11: =Scenarios!A3 | B11: FY2030 | C11: =IF(Scenarios!D3=1,0, BaselineCalc!$B$7 + ROUND((=IF(ISNUMBER(SEARCH("Ramp",A11)), CHOOSE(MATCH(B11,{"FY2026","FY2027","FY2028","FY2029","FY2030"},0),50,100,150,150,150), Scenarios!C3))*Scenarios!F3,0)) | D11: =IF(Scenarios!E3=1,0, BaselineCalc!$B$8 + (=IF(ISNUMBER(SEARCH("Ramp",A11)), CHOOSE(MATCH(B11,{"FY2026","FY2027","FY2028","FY2029","FY2030"},0),50,100,150,150,150), Scenarios!C3)) - ROUND((=IF(ISNUMBER(SEARCH("Ramp",A11)), CHOOSE(MATCH(B11,{"FY2026","FY2027","FY2028","FY2029","FY2030"},0),50,100,150,150,150), Scenarios!C3))*Scenarios!F3,0)) | E11: =C11+D11 | F11: =VLOOKUP(B11,YearMap!$A$2:$B$6,2,FALSE) | G11: =VLOOKUP(B11,YearMap!$A$2:$C$6,3,FALSE) | H11: =VLOOKUP(B11,YearMap!$A$2:$D$6,4,FALSE) | I11: =1-BaselineCalc!$B$5 | J11: =Scenarios!G3 | K11: =(G11+H11+F11*E11)*I11*(1-J11) | L11: =IF(E11>0, K11/E11, NA()) | M11: =A11&"|"&B11
A12: =Scenarios!A4 | B12: FY2026 | C12: =IF(Scenarios!D4=1,0, BaselineCalc!$B$7 + ROUND((=IF(ISNUMBER(SEARCH("Ramp",A12)), CHOOSE(MATCH(B12,{"FY2026","FY2027","FY2028","FY2029","FY2030"},0),50,100,150,150,150), Scenarios!C4))*Scenarios!F4,0)) | D12: =IF(Scenarios!E4=1,0, BaselineCalc!$B$8 + (=IF(ISNUMBER(SEARCH("Ramp",A12)), CHOOSE(MATCH(B12,{"FY2026","FY2027","FY2028","FY2029","FY2030"},0),50,100,150,150,150), Scenarios!C4)) - ROUND((=IF(ISNUMBER(SEARCH("Ramp",A12)), CHOOSE(MATCH(B12,{"FY2026","FY2027","FY2028","FY2029","FY2030"},0),50,100,150,150,150), Scenarios!C4))*Scenarios!F4,0)) | E12: =C12+D12 | F12: =VLOOKUP(B12,YearMap!$A$2:$B$6,2,FALSE) | G12: =VLOOKUP(B12,YearMap!$A$2:$C$6,3,FALSE) | H12: =VLOOKUP(B12,YearMap!$A$2:$D$6,4,FALSE) | I12: =1-BaselineCalc!$B$5 | J12: =Scenarios!G4 | K12: =(G12+H12+F12*E12)*I12*(1-J12) | L12: =IF(E12>0, K12/E12, NA()) | M12: =A12&"|"&B12
A13: =Scenarios!A4 | B13: FY2027 | C13: =IF(Scenarios!D4=1,0, BaselineCalc!$B$7 + ROUND((=IF(ISNUMBER(SEARCH("Ramp",A13)), CHOOSE(MATCH(B13,{"FY2026","FY2027","FY2028","FY2029","FY2030"},0),50,100,150,150,150), Scenarios!C4))*Scenarios!F4,0)) | D13: =IF(Scenarios!E4=1,0, BaselineCalc!$B$8 + (=IF(ISNUMBER(SEARCH("Ramp",A13)), CHOOSE(MATCH(B13,{"FY2026","FY2027","FY2028","FY2029","FY2030"},0),50,100,150,150,150), Scenarios!C4)) - ROUND((=IF(ISNUMBER(SEARCH("Ramp",A13)), CHOOSE(MATCH(B13,{"FY2026","FY2027","FY2028","FY2029","FY2030"},0),50,100,150,150,150), Scenarios!C4))*Scenarios!F4,0)) | E13: =C13+D13 | F13: =VLOOKUP(B13,YearMap!$A$2:$B$6,2,FALSE) | G13: =VLOOKUP(B13,YearMap!$A$2:$C$6,3,FALSE) | H13: =VLOOKUP(B13,YearMap!$A$2:$D$6,4,FALSE) | I13: =1-BaselineCalc!$B$5 | J13: =Scenarios!G4 | K13: =(G13+H13+F13*E13)*I13*(1-J13) | L13: =IF(E13>0, K13/E13, NA()) | M13: =A13&"|"&B13
A14: =Scenarios!A4 | B14: FY2028 | C14: =IF(Scenarios!D4=1,0, BaselineCalc!$B$7 + ROUND((=IF(ISNUMBER(SEARCH("Ramp",A14)), CHOOSE(MATCH(B14,{"FY2026","FY2027","FY2028","FY2029","FY2030"},0),50,100,150,150,150), Scenarios!C4))*Scenarios!F4,0)) | D14: =IF(Scenarios!E4=1,0, BaselineCalc!$B$8 + (=IF(ISNUMBER(SEARCH("Ramp",A14)), CHOOSE(MATCH(B14,{"FY2026","FY2027","FY2028","FY2029","FY2030"},0),50,100,150,150,150), Scenarios!C4)) - ROUND((=IF(ISNUMBER(SEARCH("Ramp",A14)), CHOOSE(MATCH(B14,{"FY2026","FY2027","FY2028","FY2029","FY2030"},0),50,100,150,150,150), Scenarios!C4))*Scenarios!F4,0)) | E14: =C14+D14 | F14: =VLOOKUP(B14,YearMap!$A$2:$B$6,2,FALSE) | G14: =VLOOKUP(B14,YearMap!$A$2:$C$6,3,FALSE) | H14: =VLOOKUP(B14,YearMap!$A$2:$D$6,4,FALSE) | I14: =1-BaselineCalc!$B$5 | J14: =Scenarios!G4 | K14: =(G14+H14+F14*E14)*I14*(1-J14) | L14: =IF(E14>0, K14/E14, NA()) | M14: =A14&"|"&B14
A15: =Scenarios!A4 | B15: FY2029 | C15: =IF(Scenarios!D4=1,0, BaselineCalc!$B$7 + ROUND((=IF(ISNUMBER(SEARCH("Ramp",A15)), CHOOSE(MATCH(B15,{"FY2026","FY2027","FY2028","FY2029","FY2030"},0),50,100,150,150,150), Scenarios!C4))*Scenarios!F4,0)) | D15: =IF(Scenarios!E4=1,0, BaselineCalc!$B$8 + (=IF(ISNUMBER(SEARCH("Ramp",A15)), CHOOSE(MATCH(B15,{"FY2026","FY2027","FY2028","FY2029","FY2030"},0),50,100,150,150,150), Scenarios!C4)) - ROUND((=IF(ISNUMBER(SEARCH("Ramp",A15)), CHOOSE(MATCH(B15,{"FY2026","FY2027","FY2028","FY2029","FY2030"},0),50,100,150,150,150), Scenarios!C4))*Scenarios!F4,0)) | E15: =C15+D15 | F15: =VLOOKUP(B15,YearMap!$A$2:$B$6,2,FALSE) | G15: =VLOOKUP(B15,YearMap!$A$2:$C$6,3,FALSE) | H15: =VLOOKUP(B15,YearMap!$A$2:$D$6,4,FALSE) | I15: =1-BaselineCalc!$B$5 | J15: =Scenarios!G4 | K15: =(G15+H15+F15*E15)*I15*(1-J15) | L15: =IF(E15>0, K15/E15, NA()) | M15: =A15&"|"&B15
A16: =Scenarios!A4 | B16: FY2030 | C16: =IF(Scenarios!D4=1,0, BaselineCalc!$B$7 + ROUND((=IF(ISNUMBER(SEARCH("Ramp",A16)), CHOOSE(MATCH(B16,{"FY2026","FY2027","FY2028","FY2029","FY2030"},0),50,100,150,150,150), Scenarios!C4))*Scenarios!F4,0)) | D16: =IF(Scenarios!E4=1,0, BaselineCalc!$B$8 + (=IF(ISNUMBER(SEARCH("Ramp",A16)), CHOOSE(MATCH(B16,{"FY2026","FY2027","FY2028","FY2029","FY2030"},0),50,100,150,150,150), Scenarios!C4)) - ROUND((=IF(ISNUMBER(SEARCH("Ramp",A16)), CHOOSE(MATCH(B16,{"FY2026","FY2027","FY2028","FY2029","FY2030"},0),50,100,150,150,150), Scenarios!C4))*Scenarios!F4,0)) | E16: =C16+D16 | F16: =VLOOKUP(B16,YearMap!$A$2:$B$6,2,FALSE) | G16: =VLOOKUP(B16,YearMap!$A$2:$C$6,3,FALSE) | H16: =VLOOKUP(B16,YearMap!$A$2:$D$6,4,FALSE) | I16: =1-BaselineCalc!$B$5 | J16: =Scenarios!G4 | K16: =(G16+H16+F16*E16)*I16*(1-J16) | L16: =IF(E16>0, K16/E16, NA()) | M16: =A16&"|"&B16
A17: =Scenarios!A6 | B17: FY2026 | C17: =IF(Scenarios!D6=1,0, BaselineCalc!$B$7 + ROUND((=IF(ISNUMBER(SEARCH("Ramp",A17)), CHOOSE(MATCH(B17,{"FY2026","FY2027","FY2028","FY2029","FY2030"},0),50,100,150,150,150), Scenarios!C6))*Scenarios!F6,0)) | D17: =IF(Scenarios!E6=1,0, BaselineCalc!$B$8 + (=IF(ISNUMBER(SEARCH("Ramp",A17)), CHOOSE(MATCH(B17,{"FY2026","FY2027","FY2028","FY2029","FY2030"},0),50,100,150,150,150), Scenarios!C6)) - ROUND((=IF(ISNUMBER(SEARCH("Ramp",A17)), CHOOSE(MATCH(B17,{"FY2026","FY2027","FY2028","FY2029","FY2030"},0),50,100,150,150,150), Scenarios!C6))*Scenarios!F6,0)) | E17: =C17+D17 | F17: =VLOOKUP(B17,YearMap!$A$2:$B$6,2,FALSE) | G17: =VLOOKUP(B17,YearMap!$A$2:$C$6,3,FALSE) | H17: =VLOOKUP(B17,YearMap!$A$2:$D$6,4,FALSE) | I17: =1-BaselineCalc!$B$5 | J17: =Scenarios!G6 | K17: =(G17+H17+F17*E17)*I17*(1-J17) | L17: =IF(E17>0, K17/E17, NA()) | M17: =A17&"|"&B17
A18: =Scenarios!A6 | B18: FY2027 | C18: =IF(Scenarios!D6=1,0, BaselineCalc!$B$7 + ROUND((=IF(ISNUMBER(SEARCH("Ramp",A18)), CHOOSE(MATCH(B18,{"FY2026","FY2027","FY2028","FY2029","FY2030"},0),50,100,150,150,150), Scenarios!C6))*Scenarios!F6,0)) | D18: =IF(Scenarios!E6=1,0, BaselineCalc!$B$8 + (=IF(ISNUMBER(SEARCH("Ramp",A18)), CHOOSE(MATCH(B18,{"FY2026","FY2027","FY2028","FY2029","FY2030"},0),50,100,150,150,150), Scenarios!C6)) - ROUND((=IF(ISNUMBER(SEARCH("Ramp",A18)), CHOOSE(MATCH(B18,{"FY2026","FY2027","FY2028","FY2029","FY2030"},0),50,100,150,150,150), Scenarios!C6))*Scenarios!F6,0)) | E18: =C18+D18 | F18: =VLOOKUP(B18,YearMap!$A$2:$B$6,2,FALSE) | G18: =VLOOKUP(B18,YearMap!$A$2:$C$6,3,FALSE) | H18: =VLOOKUP(B18,YearMap!$A$2:$D$6,4,FALSE) | I18: =1-BaselineCalc!$B$5 | J18: =Scenarios!G6 | K18: =(G18+H18+F18*E18)*I18*(1-J18) | L18: =IF(E18>0, K18/E18, NA()) | M18: =A18&"|"&B18
A19: =Scenarios!A6 | B19: FY2028 | C19: =IF(Scenarios!D6=1,0, BaselineCalc!$B$7 + ROUND((=IF(ISNUMBER(SEARCH("Ramp",A19)), CHOOSE(MATCH(B19,{"FY2026","FY2027","FY2028","FY2029","FY2030"},0),50,100,150,150,150), Scenarios!C6))*Scenarios!F6,0)) | D19: =IF(Scenarios!E6=1,0, BaselineCalc!$B$8 + (=IF(ISNUMBER(SEARCH("Ramp",A19)), CHOOSE(MATCH(B19,{"FY2026","FY2027","FY2028","FY2029","FY2030"},0),50,100,150,150,150), Scenarios!C6)) - ROUND((=IF(ISNUMBER(SEARCH("Ramp",A19)), CHOOSE(MATCH(B19,{"FY2026","FY2027","FY2028","FY2029","FY2030"},0),50,100,150,150,150), Scenarios!C6))*Scenarios!F6,0)) | E19: =C19+D19 | F19: =VLOOKUP(B19,YearMap!$A$2:$B$6,2,FALSE) | G19: =VLOOKUP(B19,YearMap!$A$2:$C$6,3,FALSE) | H19: =VLOOKUP(B19,YearMap!$A$2:$D$6,4,FALSE) | I19: =1-BaselineCalc!$B$5 | J19: =Scenarios!G6 | K19: =(G19+H19+F19*E19)*I19*(1-J19) | L19: =IF(E19>0, K19/E19, NA()) | M19: =A19&"|"&B19
A20: =Scenarios!A6 | B20: FY2029 | C20: =IF(Scenarios!D6=1,0, BaselineCalc!$B$7 + ROUND((=IF(ISNUMBER(SEARCH("Ramp",A20)), CHOOSE(MATCH(B20,{"FY2026","FY2027","FY2028","FY2029","FY2030"},0),50,100,150,150,150), Scenarios!C6))*Scenarios!F6,0)) | D20: =IF(Scenarios!E6=1,0, BaselineCalc!$B$8 + (=IF(ISNUMBER(SEARCH("Ramp",A20)), CHOOSE(MATCH(B20,{"FY2026","FY2027","FY2028","FY2029","FY2030"},0),50,100,150,150,150), Scenarios!C6)) - ROUND((=IF(ISNUMBER(SEARCH("Ramp",A20)), CHOOSE(MATCH(B20,{"FY2026","FY2027","FY2028","FY2029","FY2030"},0),50,100,150,150,150), Scenarios!C6))*Scenarios!F6,0)) | E20: =C20+D20 | F20: =VLOOKUP(B20,YearMap!$A$2:$B$6,2,FALSE) | G20: =VLOOKUP(B20,YearMap!$A$2:$C$6,3,FALSE) | H20: =VLOOKUP(B20,YearMap!$A$2:$D$6,4,FALSE) | I20: =1-BaselineCalc!$B$5 | J20: =Scenarios!G6 | K20: =(G20+H20+F20*E20)*I20*(1-J20) | L20: =IF(E20>0, K20/E20, NA()) | M20: =A20&"|"&B20
A21: =Scenarios!A6 | B21: FY2030 | C21: =IF(Scenarios!D6=1,0, BaselineCalc!$B$7 + ROUND((=IF(ISNUMBER(SEARCH("Ramp",A21)), CHOOSE(MATCH(B21,{"FY2026","FY2027","FY2028","FY2029","FY2030"},0),50,100,150,150,150), Scenarios!C6))*Scenarios!F6,0)) | D21: =IF(Scenarios!E6=1,0, BaselineCalc!$B$8 + (=IF(ISNUMBER(SEARCH("Ramp",A21)), CHOOSE(MATCH(B21,{"FY2026","FY2027","FY2028","FY2029","FY2030"},0),50,100,150,150,150), Scenarios!C6)) - ROUND((=IF(ISNUMBER(SEARCH("Ramp",A21)), CHOOSE(MATCH(B21,{"FY2026","FY2027","FY2028","FY2029","FY2030"},0),50,100,150,150,150), Scenarios!C6))*Scenarios!F6,0)) | E21: =C21+D21 | F21: =VLOOKUP(B21,YearMap!$A$2:$B$6,2,FALSE) | G21: =VLOOKUP(B21,YearMap!$A$2:$C$6,3,FALSE) | H21: =VLOOKUP(B21,YearMap!$A$2:$D$6,4,FALSE) | I21: =1-BaselineCalc!$B$5 | J21: =Scenarios!G6 | K21: =(G21+H21+F21*E21)*I21*(1-J21) | L21: =IF(E21>0, K21/E21, NA()) | M21: =A21&"|"&B21
A22: =Scenarios!A7 | B22: FY2026 | C22: =IF(Scenarios!D7=1,0, BaselineCalc!$B$7 + ROUND((=IF(ISNUMBER(SEARCH("Ramp",A22)), CHOOSE(MATCH(B22,{"FY2026","FY2027","FY2028","FY2029","FY2030"},0),50,100,150,150,150), Scenarios!C7))*Scenarios!F7,0)) | D22: =IF(Scenarios!E7=1,0, BaselineCalc!$B$8 + (=IF(ISNUMBER(SEARCH("Ramp",A22)), CHOOSE(MATCH(B22,{"FY2026","FY2027","FY2028","FY2029","FY2030"},0),50,100,150,150,150), Scenarios!C7)) - ROUND((=IF(ISNUMBER(SEARCH("Ramp",A22)), CHOOSE(MATCH(B22,{"FY2026","FY2027","FY2028","FY2029","FY2030"},0),50,100,150,150,150), Scenarios!C7))*Scenarios!F7,0)) | E22: =C22+D22 | F22: =VLOOKUP(B22,YearMap!$A$2:$B$6,2,FALSE) | G22: =VLOOKUP(B22,YearMap!$A$2:$C$6,3,FALSE) | H22: =VLOOKUP(B22,YearMap!$A$2:$D$6,4,FALSE) | I22: =1-BaselineCalc!$B$5 | J22: =Scenarios!G7 | K22: =(G22+H22+F22*E22)*I22*(1-J22) | L22: =IF(E22>0, K22/E22, NA()) | M22: =A22&"|"&B22
A23: =Scenarios!A7 | B23: FY2027 | C23: =IF(Scenarios!D7=1,0, BaselineCalc!$B$7 + ROUND((=IF(ISNUMBER(SEARCH("Ramp",A23)), CHOOSE(MATCH(B23,{"FY2026","FY2027","FY2028","FY2029","FY2030"},0),50,100,150,150,150), Scenarios!C7))*Scenarios!F7,0)) | D23: =IF(Scenarios!E7=1,0, BaselineCalc!$B$8 + (=IF(ISNUMBER(SEARCH("Ramp",A23)), CHOOSE(MATCH(B23,{"FY2026","FY2027","FY2028","FY2029","FY2030"},0),50,100,150,150,150), Scenarios!C7)) - ROUND((=IF(ISNUMBER(SEARCH("Ramp",A23)), CHOOSE(MATCH(B23,{"FY2026","FY2027","FY2028","FY2029","FY2030"},0),50,100,150,150,150), Scenarios!C7))*Scenarios!F7,0)) | E23: =C23+D23 | F23: =VLOOKUP(B23,YearMap!$A$2:$B$6,2,FALSE) | G23: =VLOOKUP(B23,YearMap!$A$2:$C$6,3,FALSE) | H23: =VLOOKUP(B23,YearMap!$A$2:$D$6,4,FALSE) | I23: =1-BaselineCalc!$B$5 | J23: =Scenarios!G7 | K23: =(G23+H23+F23*E23)*I23*(1-J23) | L23: =IF(E23>0, K23/E23, NA()) | M23: =A23&"|"&B23
A24: =Scenarios!A7 | B24: FY2028 | C24: =IF(Scenarios!D7=1,0, BaselineCalc!$B$7 + ROUND((=IF(ISNUMBER(SEARCH("Ramp",A24)), CHOOSE(MATCH(B24,{"FY2026","FY2027","FY2028","FY2029","FY2030"},0),50,100,150,150,150), Scenarios!C7))*Scenarios!F7,0)) | D24: =IF(Scenarios!E7=1,0, BaselineCalc!$B$8 + (=IF(ISNUMBER(SEARCH("Ramp",A24)), CHOOSE(MATCH(B24,{"FY2026","FY2027","FY2028","FY2029","FY2030"},0),50,100,150,150,150), Scenarios!C7)) - ROUND((=IF(ISNUMBER(SEARCH("Ramp",A24)), CHOOSE(MATCH(B24,{"FY2026","FY2027","FY2028","FY2029","FY2030"},0),50,100,150,150,150), Scenarios!C7))*Scenarios!F7,0)) | E24: =C24+D24 | F24: =VLOOKUP(B24,YearMap!$A$2:$B$6,2,FALSE) | G24: =VLOOKUP(B24,YearMap!$A$2:$C$6,3,FALSE) | H24: =VLOOKUP(B24,YearMap!$A$2:$D$6,4,FALSE) | I24: =1-BaselineCalc!$B$5 | J24: =Scenarios!G7 | K24: =(G24+H24+F24*E24)*I24*(1-J24) | L24: =IF(E24>0, K24/E24, NA()) | M24: =A24&"|"&B24
A25: =Scenarios!A7 | B25: FY2029 | C25: =IF(Scenarios!D7=1,0, BaselineCalc!$B$7 + ROUND((=IF(ISNUMBER(SEARCH("Ramp",A25)), CHOOSE(MATCH(B25,{"FY2026","FY2027","FY2028","FY2029","FY2030"},0),50,100,150,150,150), Scenarios!C7))*Scenarios!F7,0)) | D25: =IF(Scenarios!E7=1,0, BaselineCalc!$B$8 + (=IF(ISNUMBER(SEARCH("Ramp",A25)), CHOOSE(MATCH(B25,{"FY2026","FY2027","FY2028","FY2029","FY2030"},0),50,100,150,150,150), Scenarios!C7)) - ROUND((=IF(ISNUMBER(SEARCH("Ramp",A25)), CHOOSE(MATCH(B25,{"FY2026","FY2027","FY2028","FY2029","FY2030"},0),50,100,150,150,150), Scenarios!C7))*Scenarios!F7,0)) | E25: =C25+D25 | F25: =VLOOKUP(B25,YearMap!$A$2:$B$6,2,FALSE) | G25: =VLOOKUP(B25,YearMap!$A$2:$C$6,3,FALSE) | H25: =VLOOKUP(B25,YearMap!$A$2:$D$6,4,FALSE) | I25: =1-BaselineCalc!$B$5 | J25: =Scenarios!G7 | K25: =(G25+H25+F25*E25)*I25*(1-J25) | L25: =IF(E25>0, K25/E25, NA()) | M25: =A25&"|"&B25
A26: =Scenarios!A7 | B26: FY2030 | C26: =IF(Scenarios!D7=1,0, BaselineCalc!$B$7 + ROUND((=IF(ISNUMBER(SEARCH("Ramp",A26)), CHOOSE(MATCH(B26,{"FY2026","FY2027","FY2028","FY2029","FY2030"},0),50,100,150,150,150), Scenarios!C7))*Scenarios!F7,0)) | D26: =IF(Scenarios!E7=1,0, BaselineCalc!$B$8 + (=IF(ISNUMBER(SEARCH("Ramp",A26)), CHOOSE(MATCH(B26,{"FY2026","FY2027","FY2028","FY2029","FY2030"},0),50,100,150,150,150), Scenarios!C7)) - ROUND((=IF(ISNUMBER(SEARCH("Ramp",A26)), CHOOSE(MATCH(B26,{"FY2026","FY2027","FY2028","FY2029","FY2030"},0),50,100,150,150,150), Scenarios!C7))*Scenarios!F7,0)) | E26: =C26+D26 | F26: =VLOOKUP(B26,YearMap!$A$2:$B$6,2,FALSE) | G26: =VLOOKUP(B26,YearMap!$A$2:$C$6,3,FALSE) | H26: =VLOOKUP(B26,YearMap!$A$2:$D$6,4,FALSE) | I26: =1-BaselineCalc!$B$5 | J26: =Scenarios!G7 | K26: =(G26+H26+F26*E26)*I26*(1-J26) | L26: =IF(E26>0, K26/E26, NA()) | M26: =A26&"|"&B26
A27: =Scenarios!A8 | B27: FY2026 | C27: =IF(Scenarios!D8=1,0, BaselineCalc!$B$7 + ROUND((=IF(ISNUMBER(SEARCH("Ramp",A27)), CHOOSE(MATCH(B27,{"FY2026","FY2027","FY2028","FY2029","FY2030"},0),50,100,150,150,150), Scenarios!C8))*Scenarios!F8,0)) | D27: =IF(Scenarios!E8=1,0, BaselineCalc!$B$8 + (=IF(ISNUMBER(SEARCH("Ramp",A27)), CHOOSE(MATCH(B27,{"FY2026","FY2027","FY2028","FY2029","FY2030"},0),50,100,150,150,150), Scenarios!C8)) - ROUND((=IF(ISNUMBER(SEARCH("Ramp",A27)), CHOOSE(MATCH(B27,{"FY2026","FY2027","FY2028","FY2029","FY2030"},0),50,100,150,150,150), Scenarios!C8))*Scenarios!F8,0)) | E27: =C27+D27 | F27: =VLOOKUP(B27,YearMap!$A$2:$B$6,2,FALSE) | G27: =VLOOKUP(B27,YearMap!$A$2:$C$6,3,FALSE) | H27: =VLOOKUP(B27,YearMap!$A$2:$D$6,4,FALSE) | I27: =1-BaselineCalc!$B$5 | J27: =Scenarios!G8 | K27: =(G27+H27+F27*E27)*I27*(1-J27) | L27: =IF(E27>0, K27/E27, NA()) | M27: =A27&"|"&B27
A28: =Scenarios!A8 | B28: FY2027 | C28: =IF(Scenarios!D8=1,0, BaselineCalc!$B$7 + ROUND((=IF(ISNUMBER(SEARCH("Ramp",A28)), CHOOSE(MATCH(B28,{"FY2026","FY2027","FY2028","FY2029","FY2030"},0),50,100,150,150,150), Scenarios!C8))*Scenarios!F8,0)) | D28: =IF(Scenarios!E8=1,0, BaselineCalc!$B$8 + (=IF(ISNUMBER(SEARCH("Ramp",A28)), CHOOSE(MATCH(B28,{"FY2026","FY2027","FY2028","FY2029","FY2030"},0),50,100,150,150,150), Scenarios!C8)) - ROUND((=IF(ISNUMBER(SEARCH("Ramp",A28)), CHOOSE(MATCH(B28,{"FY2026","FY2027","FY2028","FY2029","FY2030"},0),50,100,150,150,150), Scenarios!C8))*Scenarios!F8,0)) | E28: =C28+D28 | F28: =VLOOKUP(B28,YearMap!$A$2:$B$6,2,FALSE) | G28: =VLOOKUP(B28,YearMap!$A$2:$C$6,3,FALSE) | H28: =VLOOKUP(B28,YearMap!$A$2:$D$6,4,FALSE) | I28: =1-BaselineCalc!$B$5 | J28: =Scenarios!G8 | K28: =(G28+H28+F28*E28)*I28*(1-J28) | L28: =IF(E28>0, K28/E28, NA()) | M28: =A28&"|"&B28
A29: =Scenarios!A8 | B29: FY2028 | C29: =IF(Scenarios!D8=1,0, BaselineCalc!$B$7 + ROUND((=IF(ISNUMBER(SEARCH("Ramp",A29)), CHOOSE(MATCH(B29,{"FY2026","FY2027","FY2028","FY2029","FY2030"},0),50,100,150,150,150), Scenarios!C8))*Scenarios!F8,0)) | D29: =IF(Scenarios!E8=1,0, BaselineCalc!$B$8 + (=IF(ISNUMBER(SEARCH("Ramp",A29)), CHOOSE(MATCH(B29,{"FY2026","FY2027","FY2028","FY2029","FY2030"},0),50,100,150,150,150), Scenarios!C8)) - ROUND((=IF(ISNUMBER(SEARCH("Ramp",A29)), CHOOSE(MATCH(B29,{"FY2026","FY2027","FY2028","FY2029","FY2030"},0),50,100,150,150,150), Scenarios!C8))*Scenarios!F8,0)) | E29: =C29+D29 | F29: =VLOOKUP(B29,YearMap!$A$2:$B$6,2,FALSE) | G29: =VLOOKUP(B29,YearMap!$A$2:$C$6,3,FALSE) | H29: =VLOOKUP(B29,YearMap!$A$2:$D$6,4,FALSE) | I29: =1-BaselineCalc!$B$5 | J29: =Scenarios!G8 | K29: =(G29+H29+F29*E29)*I29*(1-J29) | L29: =IF(E29>0, K29/E29, NA()) | M29: =A29&"|"&B29
A30: =Scenarios!A8 | B30: FY2029 | C30: =IF(Scenarios!D8=1,0, BaselineCalc!$B$7 + ROUND((=IF(ISNUMBER(SEARCH("Ramp",A30)), CHOOSE(MATCH(B30,{"FY2026","FY2027","FY2028","FY2029","FY2030"},0),50,100,150,150,150), Scenarios!C8))*Scenarios!F8,0)) | D30: =IF(Scenarios!E8=1,0, BaselineCalc!$B$8 + (=IF(ISNUMBER(SEARCH("Ramp",A30)), CHOOSE(MATCH(B30,{"FY2026","FY2027","FY2028","FY2029","FY2030"},0),50,100,150,150,150), Scenarios!C8)) - ROUND((=IF(ISNUMBER(SEARCH("Ramp",A30)), CHOOSE(MATCH(B30,{"FY2026","FY2027","FY2028","FY2029","FY2030"},0),50,100,150,150,150), Scenarios!C8))*Scenarios!F8,0)) | E30: =C30+D30 | F30: =VLOOKUP(B30,YearMap!$A$2:$B$6,2,FALSE) | G30: =VLOOKUP(B30,YearMap!$A$2:$C$6,3,FALSE) | H30: =VLOOKUP(B30,YearMap!$A$2:$D$6,4,FALSE) | I30: =1-BaselineCalc!$B$5 | J30: =Scenarios!G8 | K30: =(G30+H30+F30*E30)*I30*(1-J30) | L30: =IF(E30>0, K30/E30, NA()) | M30: =A30&"|"&B30
A31: =Scenarios!A8 | B31: FY2030 | C31: =IF(Scenarios!D8=1,0, BaselineCalc!$B$7 + ROUND((=IF(ISNUMBER(SEARCH("Ramp",A31)), CHOOSE(MATCH(B31,{"FY2026","FY2027","FY2028","FY2029","FY2030"},0),50,100,150,150,150), Scenarios!C8))*Scenarios!F8,0)) | D31: =IF(Scenarios!E8=1,0, BaselineCalc!$B$8 + (=IF(ISNUMBER(SEARCH("Ramp",A31)), CHOOSE(MATCH(B31,{"FY2026","FY2027","FY2028","FY2029","FY2030"},0),50,100,150,150,150), Scenarios!C8)) - ROUND((=IF(ISNUMBER(SEARCH("Ramp",A31)), CHOOSE(MATCH(B31,{"FY2026","FY2027","FY2028","FY2029","FY2030"},0),50,100,150,150,150), Scenarios!C8))*Scenarios!F8,0)) | E31: =C31+D31 | F31: =VLOOKUP(B31,YearMap!$A$2:$B$6,2,FALSE) | G31: =VLOOKUP(B31,YearMap!$A$2:$C$6,3,FALSE) | H31: =VLOOKUP(B31,YearMap!$A$2:$D$6,4,FALSE) | I31: =1-BaselineCalc!$B$5 | J31: =Scenarios!G8 | K31: =(G31+H31+F31*E31)*I31*(1-J31) | L31: =IF(E31>0, K31/E31, NA()) | M31: =A31&"|"&B31
A32: =Scenarios!A9 | B32: FY2026 | C32: =IF(Scenarios!D9=1,0, BaselineCalc!$B$7 + ROUND((=IF(ISNUMBER(SEARCH("Ramp",A32)), CHOOSE(MATCH(B32,{"FY2026","FY2027","FY2028","FY2029","FY2030"},0),50,100,150,150,150), Scenarios!C9))*Scenarios!F9,0)) | D32: =IF(Scenarios!E9=1,0, BaselineCalc!$B$8 + (=IF(ISNUMBER(SEARCH("Ramp",A32)), CHOOSE(MATCH(B32,{"FY2026","FY2027","FY2028","FY2029","FY2030"},0),50,100,150,150,150), Scenarios!C9)) - ROUND((=IF(ISNUMBER(SEARCH("Ramp",A32)), CHOOSE(MATCH(B32,{"FY2026","FY2027","FY2028","FY2029","FY2030"},0),50,100,150,150,150), Scenarios!C9))*Scenarios!F9,0)) | E32: =C32+D32 | F32: =VLOOKUP(B32,YearMap!$A$2:$B$6,2,FALSE) | G32: =VLOOKUP(B32,YearMap!$A$2:$C$6,3,FALSE) | H32: =VLOOKUP(B32,YearMap!$A$2:$D$6,4,FALSE) | I32: =1-BaselineCalc!$B$5 | J32: =Scenarios!G9 | K32: =(G32+H32+F32*E32)*I32*(1-J32) | L32: =IF(E32>0, K32/E32, NA()) | M32: =A32&"|"&B32
A33: =Scenarios!A9 | B33: FY2027 | C33: =IF(Scenarios!D9=1,0, BaselineCalc!$B$7 + ROUND((=IF(ISNUMBER(SEARCH("Ramp",A33)), CHOOSE(MATCH(B33,{"FY2026","FY2027","FY2028","FY2029","FY2030"},0),50,100,150,150,150), Scenarios!C9))*Scenarios!F9,0)) | D33: =IF(Scenarios!E9=1,0, BaselineCalc!$B$8 + (=IF(ISNUMBER(SEARCH("Ramp",A33)), CHOOSE(MATCH(B33,{"FY2026","FY2027","FY2028","FY2029","FY2030"},0),50,100,150,150,150), Scenarios!C9)) - ROUND((=IF(ISNUMBER(SEARCH("Ramp",A33)), CHOOSE(MATCH(B33,{"FY2026","FY2027","FY2028","FY2029","FY2030"},0),50,100,150,150,150), Scenarios!C9))*Scenarios!F9,0)) | E33: =C33+D33 | F33: =VLOOKUP(B33,YearMap!$A$2:$B$6,2,FALSE) | G33: =VLOOKUP(B33,YearMap!$A$2:$C$6,3,FALSE) | H33: =VLOOKUP(B33,YearMap!$A$2:$D$6,4,FALSE) | I33: =1-BaselineCalc!$B$5 | J33: =Scenarios!G9 | K33: =(G33+H33+F33*E33)*I33*(1-J33) | L33: =IF(E33>0, K33/E33, NA()) | M33: =A33&"|"&B33
A34: =Scenarios!A9 | B34: FY2028 | C34: =IF(Scenarios!D9=1,0, BaselineCalc!$B$7 + ROUND((=IF(ISNUMBER(SEARCH("Ramp",A34)), CHOOSE(MATCH(B34,{"FY2026","FY2027","FY2028","FY2029","FY2030"},0),50,100,150,150,150), Scenarios!C9))*Scenarios!F9,0)) | D34: =IF(Scenarios!E9=1,0, BaselineCalc!$B$8 + (=IF(ISNUMBER(SEARCH("Ramp",A34)), CHOOSE(MATCH(B34,{"FY2026","FY2027","FY2028","FY2029","FY2030"},0),50,100,150,150,150), Scenarios!C9)) - ROUND((=IF(ISNUMBER(SEARCH("Ramp",A34)), CHOOSE(MATCH(B34,{"FY2026","FY2027","FY2028","FY2029","FY2030"},0),50,100,150,150,150), Scenarios!C9))*Scenarios!F9,0)) | E34: =C34+D34 | F34: =VLOOKUP(B34,YearMap!$A$2:$B$6,2,FALSE) | G34: =VLOOKUP(B34,YearMap!$A$2:$C$6,3,FALSE) | H34: =VLOOKUP(B34,YearMap!$A$2:$D$6,4,FALSE) | I34: =1-BaselineCalc!$B$5 | J34: =Scenarios!G9 | K34: =(G34+H34+F34*E34)*I34*(1-J34) | L34: =IF(E34>0, K34/E34, NA()) | M34: =A34&"|"&B34
A35: =Scenarios!A9 | B35: FY2029 | C35: =IF(Scenarios!D9=1,0, BaselineCalc!$B$7 + ROUND((=IF(ISNUMBER(SEARCH("Ramp",A35)), CHOOSE(MATCH(B35,{"FY2026","FY2027","FY2028","FY2029","FY2030"},0),50,100,150,150,150), Scenarios!C9))*Scenarios!F9,0)) | D35: =IF(Scenarios!E9=1,0, BaselineCalc!$B$8 + (=IF(ISNUMBER(SEARCH("Ramp",A35)), CHOOSE(MATCH(B35,{"FY2026","FY2027","FY2028","FY2029","FY2030"},0),50,100,150,150,150), Scenarios!C9)) - ROUND((=IF(ISNUMBER(SEARCH("Ramp",A35)), CHOOSE(MATCH(B35,{"FY2026","FY2027","FY2028","FY2029","FY2030"},0),50,100,150,150,150), Scenarios!C9))*Scenarios!F9,0)) | E35: =C35+D35 | F35: =VLOOKUP(B35,YearMap!$A$2:$B$6,2,FALSE) | G35: =VLOOKUP(B35,YearMap!$A$2:$C$6,3,FALSE) | H35: =VLOOKUP(B35,YearMap!$A$2:$D$6,4,FALSE) | I35: =1-BaselineCalc!$B$5 | J35: =Scenarios!G9 | K35: =(G35+H35+F35*E35)*I35*(1-J35) | L35: =IF(E35>0, K35/E35, NA()) | M35: =A35&"|"&B35
A36: =Scenarios!A9 | B36: FY2030 | C36: =IF(Scenarios!D9=1,0, BaselineCalc!$B$7 + ROUND((=IF(ISNUMBER(SEARCH("Ramp",A36)), CHOOSE(MATCH(B36,{"FY2026","FY2027","FY2028","FY2029","FY2030"},0),50,100,150,150,150), Scenarios!C9))*Scenarios!F9,0)) | D36: =IF(Scenarios!E9=1,0, BaselineCalc!$B$8 + (=IF(ISNUMBER(SEARCH("Ramp",A36)), CHOOSE(MATCH(B36,{"FY2026","FY2027","FY2028","FY2029","FY2030"},0),50,100,150,150,150), Scenarios!C9)) - ROUND((=IF(ISNUMBER(SEARCH("Ramp",A36)), CHOOSE(MATCH(B36,{"FY2026","FY2027","FY2028","FY2029","FY2030"},0),50,100,150,150,150), Scenarios!C9))*Scenarios!F9,0)) | E36: =C36+D36 | F36: =VLOOKUP(B36,YearMap!$A$2:$B$6,2,FALSE) | G36: =VLOOKUP(B36,YearMap!$A$2:$C$6,3,FALSE) | H36: =VLOOKUP(B36,YearMap!$A$2:$D$6,4,FALSE) | I36: =1-BaselineCalc!$B$5 | J36: =Scenarios!G9 | K36: =(G36+H36+F36*E36)*I36*(1-J36) | L36: =IF(E36>0, K36/E36, NA()) | M36: =A36&"|"&B36
A37: =Scenarios!A10 | B37: FY2026 | C37: =IF(Scenarios!D10=1,0, BaselineCalc!$B$7 + ROUND((=IF(ISNUMBER(SEARCH("Ramp",A37)), CHOOSE(MATCH(B37,{"FY2026","FY2027","FY2028","FY2029","FY2030"},0),50,100,150,150,150), Scenarios!C10))*Scenarios!F10,0)) | D37: =IF(Scenarios!E10=1,0, BaselineCalc!$B$8 + (=IF(ISNUMBER(SEARCH("Ramp",A37)), CHOOSE(MATCH(B37,{"FY2026","FY2027","FY2028","FY2029","FY2030"},0),50,100,150,150,150), Scenarios!C10)) - ROUND((=IF(ISNUMBER(SEARCH("Ramp",A37)), CHOOSE(MATCH(B37,{"FY2026","FY2027","FY2028","FY2029","FY2030"},0),50,100,150,150,150), Scenarios!C10))*Scenarios!F10,0)) | E37: =C37+D37 | F37: =VLOOKUP(B37,YearMap!$A$2:$B$6,2,FALSE) | G37: =VLOOKUP(B37,YearMap!$A$2:$C$6,3,FALSE) | H37: =VLOOKUP(B37,YearMap!$A$2:$D$6,4,FALSE) | I37: =1-BaselineCalc!$B$5 | J37: =Scenarios!G10 | K37: =(G37+H37+F37*E37)*I37*(1-J37) | L37: =IF(E37>0, K37/E37, NA()) | M37: =A37&"|"&B37
A38: =Scenarios!A10 | B38: FY2027 | C38: =IF(Scenarios!D10=1,0, BaselineCalc!$B$7 + ROUND((=IF(ISNUMBER(SEARCH("Ramp",A38)), CHOOSE(MATCH(B38,{"FY2026","FY2027","FY2028","FY2029","FY2030"},0),50,100,150,150,150), Scenarios!C10))*Scenarios!F10,0)) | D38: =IF(Scenarios!E10=1,0, BaselineCalc!$B$8 + (=IF(ISNUMBER(SEARCH("Ramp",A38)), CHOOSE(MATCH(B38,{"FY2026","FY2027","FY2028","FY2029","FY2030"},0),50,100,150,150,150), Scenarios!C10)) - ROUND((=IF(ISNUMBER(SEARCH("Ramp",A38)), CHOOSE(MATCH(B38,{"FY2026","FY2027","FY2028","FY2029","FY2030"},0),50,100,150,150,150), Scenarios!C10))*Scenarios!F10,0)) | E38: =C38+D38 | F38: =VLOOKUP(B38,YearMap!$A$2:$B$6,2,FALSE) | G38: =VLOOKUP(B38,YearMap!$A$2:$C$6,3,FALSE) | H38: =VLOOKUP(B38,YearMap!$A$2:$D$6,4,FALSE) | I38: =1-BaselineCalc!$B$5 | J38: =Scenarios!G10 | K38: =(G38+H38+F38*E38)*I38*(1-J38) | L38: =IF(E38>0, K38/E38, NA()) | M38: =A38&"|"&B38
A39: =Scenarios!A10 | B39: FY2028 | C39: =IF(Scenarios!D10=1,0, BaselineCalc!$B$7 + ROUND((=IF(ISNUMBER(SEARCH("Ramp",A39)), CHOOSE(MATCH(B39,{"FY2026","FY2027","FY2028","FY2029","FY2030"},0),50,100,150,150,150), Scenarios!C10))*Scenarios!F10,0)) | D39: =IF(Scenarios!E10=1,0, BaselineCalc!$B$8 + (=IF(ISNUMBER(SEARCH("Ramp",A39)), CHOOSE(MATCH(B39,{"FY2026","FY2027","FY2028","FY2029","FY2030"},0),50,100,150,150,150), Scenarios!C10)) - ROUND((=IF(ISNUMBER(SEARCH("Ramp",A39)), CHOOSE(MATCH(B39,{"FY2026","FY2027","FY2028","FY2029","FY2030"},0),50,100,150,150,150), Scenarios!C10))*Scenarios!F10,0)) | E39: =C39+D39 | F39: =VLOOKUP(B39,YearMap!$A$2:$B$6,2,FALSE) | G39: =VLOOKUP(B39,YearMap!$A$2:$C$6,3,FALSE) | H39: =VLOOKUP(B39,YearMap!$A$2:$D$6,4,FALSE) | I39: =1-BaselineCalc!$B$5 | J39: =Scenarios!G10 | K39: =(G39+H39+F39*E39)*I39*(1-J39) | L39: =IF(E39>0, K39/E39, NA()) | M39: =A39&"|"&B39
A40: =Scenarios!A10 | B40: FY2029 | C40: =IF(Scenarios!D10=1,0, BaselineCalc!$B$7 + ROUND((=IF(ISNUMBER(SEARCH("Ramp",A40)), CHOOSE(MATCH(B40,{"FY2026","FY2027","FY2028","FY2029","FY2030"},0),50,100,150,150,150), Scenarios!C10))*Scenarios!F10,0)) | D40: =IF(Scenarios!E10=1,0, BaselineCalc!$B$8 + (=IF(ISNUMBER(SEARCH("Ramp",A40)), CHOOSE(MATCH(B40,{"FY2026","FY2027","FY2028","FY2029","FY2030"},0),50,100,150,150,150), Scenarios!C10)) - ROUND((=IF(ISNUMBER(SEARCH("Ramp",A40)), CHOOSE(MATCH(B40,{"FY2026","FY2027","FY2028","FY2029","FY2030"},0),50,100,150,150,150), Scenarios!C10))*Scenarios!F10,0)) | E40: =C40+D40 | F40: =VLOOKUP(B40,YearMap!$A$2:$B$6,2,FALSE) | G40: =VLOOKUP(B40,YearMap!$A$2:$C$6,3,FALSE) | H40: =VLOOKUP(B40,YearMap!$A$2:$D$6,4,FALSE) | I40: =1-BaselineCalc!$B$5 | J40: =Scenarios!G10 | K40: =(G40+H40+F40*E40)*I40*(1-J40) | L40: =IF(E40>0, K40/E40, NA()) | M40: =A40&"|"&B40
A41: =Scenarios!A10 | B41: FY2030 | C41: =IF(Scenarios!D10=1,0, BaselineCalc!$B$7 + ROUND((=IF(ISNUMBER(SEARCH("Ramp",A41)), CHOOSE(MATCH(B41,{"FY2026","FY2027","FY2028","FY2029","FY2030"},0),50,100,150,150,150), Scenarios!C10))*Scenarios!F10,0)) | D41: =IF(Scenarios!E10=1,0, BaselineCalc!$B$8 + (=IF(ISNUMBER(SEARCH("Ramp",A41)), CHOOSE(MATCH(B41,{"FY2026","FY2027","FY2028","FY2029","FY2030"},0),50,100,150,150,150), Scenarios!C10)) - ROUND((=IF(ISNUMBER(SEARCH("Ramp",A41)), CHOOSE(MATCH(B41,{"FY2026","FY2027","FY2028","FY2029","FY2030"},0),50,100,150,150,150), Scenarios!C10))*Scenarios!F10,0)) | E41: =C41+D41 | F41: =VLOOKUP(B41,YearMap!$A$2:$B$6,2,FALSE) | G41: =VLOOKUP(B41,YearMap!$A$2:$C$6,3,FALSE) | H41: =VLOOKUP(B41,YearMap!$A$2:$D$6,4,FALSE) | I41: =1-BaselineCalc!$B$5 | J41: =Scenarios!G10 | K41: =(G41+H41+F41*E41)*I41*(1-J41) | L41: =IF(E41>0, K41/E41, NA()) | M41: =A41&"|"&B41
A42: =Scenarios!A11 | B42: FY2026 | C42: =IF(Scenarios!D11=1,0, BaselineCalc!$B$7 + ROUND((=IF(ISNUMBER(SEARCH("Ramp",A42)), CHOOSE(MATCH(B42,{"FY2026","FY2027","FY2028","FY2029","FY2030"},0),50,100,150,150,150), Scenarios!C11))*Scenarios!F11,0)) | D42: =IF(Scenarios!E11=1,0, BaselineCalc!$B$8 + (=IF(ISNUMBER(SEARCH("Ramp",A42)), CHOOSE(MATCH(B42,{"FY2026","FY2027","FY2028","FY2029","FY2030"},0),50,100,150,150,150), Scenarios!C11)) - ROUND((=IF(ISNUMBER(SEARCH("Ramp",A42)), CHOOSE(MATCH(B42,{"FY2026","FY2027","FY2028","FY2029","FY2030"},0),50,100,150,150,150), Scenarios!C11))*Scenarios!F11,0)) | E42: =C42+D42 | F42: =VLOOKUP(B42,YearMap!$A$2:$B$6,2,FALSE) | G42: =VLOOKUP(B42,YearMap!$A$2:$C$6,3,FALSE) | H42: =VLOOKUP(B42,YearMap!$A$2:$D$6,4,FALSE) | I42: =1-BaselineCalc!$B$5 | J42: =Scenarios!G11 | K42: =(G42+H42+F42*E42)*I42*(1-J42) | L42: =IF(E42>0, K42/E42, NA()) | M42: =A42&"|"&B42
A43: =Scenarios!A11 | B43: FY2027 | C43: =IF(Scenarios!D11=1,0, BaselineCalc!$B$7 + ROUND((=IF(ISNUMBER(SEARCH("Ramp",A43)), CHOOSE(MATCH(B43,{"FY2026","FY2027","FY2028","FY2029","FY2030"},0),50,100,150,150,150), Scenarios!C11))*Scenarios!F11,0)) | D43: =IF(Scenarios!E11=1,0, BaselineCalc!$B$8 + (=IF(ISNUMBER(SEARCH("Ramp",A43)), CHOOSE(MATCH(B43,{"FY2026","FY2027","FY2028","FY2029","FY2030"},0),50,100,150,150,150), Scenarios!C11)) - ROUND((=IF(ISNUMBER(SEARCH("Ramp",A43)), CHOOSE(MATCH(B43,{"FY2026","FY2027","FY2028","FY2029","FY2030"},0),50,100,150,150,150), Scenarios!C11))*Scenarios!F11,0)) | E43: =C43+D43 | F43: =VLOOKUP(B43,YearMap!$A$2:$B$6,2,FALSE) | G43: =VLOOKUP(B43,YearMap!$A$2:$C$6,3,FALSE) | H43: =VLOOKUP(B43,YearMap!$A$2:$D$6,4,FALSE) | I43: =1-BaselineCalc!$B$5 | J43: =Scenarios!G11 | K43: =(G43+H43+F43*E43)*I43*(1-J43) | L43: =IF(E43>0, K43/E43, NA()) | M43: =A43&"|"&B43
A44: =Scenarios!A11 | B44: FY2028 | C44: =IF(Scenarios!D11=1,0, BaselineCalc!$B$7 + ROUND((=IF(ISNUMBER(SEARCH("Ramp",A44)), CHOOSE(MATCH(B44,{"FY2026","FY2027","FY2028","FY2029","FY2030"},0),50,100,150,150,150), Scenarios!C11))*Scenarios!F11,0)) | D44: =IF(Scenarios!E11=1,0, BaselineCalc!$B$8 + (=IF(ISNUMBER(SEARCH("Ramp",A44)), CHOOSE(MATCH(B44,{"FY2026","FY2027","FY2028","FY2029","FY2030"},0),50,100,150,150,150), Scenarios!C11)) - ROUND((=IF(ISNUMBER(SEARCH("Ramp",A44)), CHOOSE(MATCH(B44,{"FY2026","FY2027","FY2028","FY2029","FY2030"},0),50,100,150,150,150), Scenarios!C11))*Scenarios!F11,0)) | E44: =C44+D44 | F44: =VLOOKUP(B44,YearMap!$A$2:$B$6,2,FALSE) | G44: =VLOOKUP(B44,YearMap!$A$2:$C$6,3,FALSE) | H44: =VLOOKUP(B44,YearMap!$A$2:$D$6,4,FALSE) | I44: =1-BaselineCalc!$B$5 | J44: =Scenarios!G11 | K44: =(G44+H44+F44*E44)*I44*(1-J44) | L44: =IF(E44>0, K44/E44, NA()) | M44: =A44&"|"&B44
A45: =Scenarios!A11 | B45: FY2029 | C45: =IF(Scenarios!D11=1,0, BaselineCalc!$B$7 + ROUND((=IF(ISNUMBER(SEARCH("Ramp",A45)), CHOOSE(MATCH(B45,{"FY2026","FY2027","FY2028","FY2029","FY2030"},0),50,100,150,150,150), Scenarios!C11))*Scenarios!F11,0)) | D45: =IF(Scenarios!E11=1,0, BaselineCalc!$B$8 + (=IF(ISNUMBER(SEARCH("Ramp",A45)), CHOOSE(MATCH(B45,{"FY2026","FY2027","FY2028","FY2029","FY2030"},0),50,100,150,150,150), Scenarios!C11)) - ROUND((=IF(ISNUMBER(SEARCH("Ramp",A45)), CHOOSE(MATCH(B45,{"FY2026","FY2027","FY2028","FY2029","FY2030"},0),50,100,150,150,150), Scenarios!C11))*Scenarios!F11,0)) | E45: =C45+D45 | F45: =VLOOKUP(B45,YearMap!$A$2:$B$6,2,FALSE) | G45: =VLOOKUP(B45,YearMap!$A$2:$C$6,3,FALSE) | H45: =VLOOKUP(B45,YearMap!$A$2:$D$6,4,FALSE) | I45: =1-BaselineCalc!$B$5 | J45: =Scenarios!G11 | K45: =(G45+H45+F45*E45)*I45*(1-J45) | L45: =IF(E45>0, K45/E45, NA()) | M45: =A45&"|"&B45
A46: =Scenarios!A11 | B46: FY2030 | C46: =IF(Scenarios!D11=1,0, BaselineCalc!$B$7 + ROUND((=IF(ISNUMBER(SEARCH("Ramp",A46)), CHOOSE(MATCH(B46,{"FY2026","FY2027","FY2028","FY2029","FY2030"},0),50,100,150,150,150), Scenarios!C11))*Scenarios!F11,0)) | D46: =IF(Scenarios!E11=1,0, BaselineCalc!$B$8 + (=IF(ISNUMBER(SEARCH("Ramp",A46)), CHOOSE(MATCH(B46,{"FY2026","FY2027","FY2028","FY2029","FY2030"},0),50,100,150,150,150), Scenarios!C11)) - ROUND((=IF(ISNUMBER(SEARCH("Ramp",A46)), CHOOSE(MATCH(B46,{"FY2026","FY2027","FY2028","FY2029","FY2030"},0),50,100,150,150,150), Scenarios!C11))*Scenarios!F11,0)) | E46: =C46+D46 | F46: =VLOOKUP(B46,YearMap!$A$2:$B$6,2,FALSE) | G46: =VLOOKUP(B46,YearMap!$A$2:$C$6,3,FALSE) | H46: =VLOOKUP(B46,YearMap!$A$2:$D$6,4,FALSE) | I46: =1-BaselineCalc!$B$5 | J46: =Scenarios!G11 | K46: =(G46+H46+F46*E46)*I46*(1-J46) | L46: =IF(E46>0, K46/E46, NA()) | M46: =A46&"|"&B46
A47: =Scenarios!A12 | B47: FY2026 | C47: =IF(Scenarios!D12=1,0, BaselineCalc!$B$7 + ROUND((=IF(ISNUMBER(SEARCH("Ramp",A47)), CHOOSE(MATCH(B47,{"FY2026","FY2027","FY2028","FY2029","FY2030"},0),50,100,150,150,150), Scenarios!C12))*Scenarios!F12,0)) | D47: =IF(Scenarios!E12=1,0, BaselineCalc!$B$8 + (=IF(ISNUMBER(SEARCH("Ramp",A47)), CHOOSE(MATCH(B47,{"FY2026","FY2027","FY2028","FY2029","FY2030"},0),50,100,150,150,150), Scenarios!C12)) - ROUND((=IF(ISNUMBER(SEARCH("Ramp",A47)), CHOOSE(MATCH(B47,{"FY2026","FY2027","FY2028","FY2029","FY2030"},0),50,100,150,150,150), Scenarios!C12))*Scenarios!F12,0)) | E47: =C47+D47 | F47: =VLOOKUP(B47,YearMap!$A$2:$B$6,2,FALSE) | G47: =VLOOKUP(B47,YearMap!$A$2:$C$6,3,FALSE) | H47: =VLOOKUP(B47,YearMap!$A$2:$D$6,4,FALSE) | I47: =1-BaselineCalc!$B$5 | J47: =Scenarios!G12 | K47: =(G47+H47+F47*E47)*I47*(1-J47) | L47: =IF(E47>0, K47/E47, NA()) | M47: =A47&"|"&B47
A48: =Scenarios!A12 | B48: FY2027 | C48: =IF(Scenarios!D12=1,0, BaselineCalc!$B$7 + ROUND((=IF(ISNUMBER(SEARCH("Ramp",A48)), CHOOSE(MATCH(B48,{"FY2026","FY2027","FY2028","FY2029","FY2030"},0),50,100,150,150,150), Scenarios!C12))*Scenarios!F12,0)) | D48: =IF(Scenarios!E12=1,0, BaselineCalc!$B$8 + (=IF(ISNUMBER(SEARCH("Ramp",A48)), CHOOSE(MATCH(B48,{"FY2026","FY2027","FY2028","FY2029","FY2030"},0),50,100,150,150,150), Scenarios!C12)) - ROUND((=IF(ISNUMBER(SEARCH("Ramp",A48)), CHOOSE(MATCH(B48,{"FY2026","FY2027","FY2028","FY2029","FY2030"},0),50,100,150,150,150), Scenarios!C12))*Scenarios!F12,0)) | E48: =C48+D48 | F48: =VLOOKUP(B48,YearMap!$A$2:$B$6,2,FALSE) | G48: =VLOOKUP(B48,YearMap!$A$2:$C$6,3,FALSE) | H48: =VLOOKUP(B48,YearMap!$A$2:$D$6,4,FALSE) | I48: =1-BaselineCalc!$B$5 | J48: =Scenarios!G12 | K48: =(G48+H48+F48*E48)*I48*(1-J48) | L48: =IF(E48>0, K48/E48, NA()) | M48: =A48&"|"&B48
A49: =Scenarios!A12 | B49: FY2028 | C49: =IF(Scenarios!D12=1,0, BaselineCalc!$B$7 + ROUND((=IF(ISNUMBER(SEARCH("Ramp",A49)), CHOOSE(MATCH(B49,{"FY2026","FY2027","FY2028","FY2029","FY2030"},0),50,100,150,150,150), Scenarios!C12))*Scenarios!F12,0)) | D49: =IF(Scenarios!E12=1,0, BaselineCalc!$B$8 + (=IF(ISNUMBER(SEARCH("Ramp",A49)), CHOOSE(MATCH(B49,{"FY2026","FY2027","FY2028","FY2029","FY2030"},0),50,100,150,150,150), Scenarios!C12)) - ROUND((=IF(ISNUMBER(SEARCH("Ramp",A49)), CHOOSE(MATCH(B49,{"FY2026","FY2027","FY2028","FY2029","FY2030"},0),50,100,150,150,150), Scenarios!C12))*Scenarios!F12,0)) | E49: =C49+D49 | F49: =VLOOKUP(B49,YearMap!$A$2:$B$6,2,FALSE) | G49: =VLOOKUP(B49,YearMap!$A$2:$C$6,3,FALSE) | H49: =VLOOKUP(B49,YearMap!$A$2:$D$6,4,FALSE) | I49: =1-BaselineCalc!$B$5 | J49: =Scenarios!G12 | K49: =(G49+H49+F49*E49)*I49*(1-J49) | L49: =IF(E49>0, K49/E49, NA()) | M49: =A49&"|"&B49
A50: =Scenarios!A12 | B50: FY2029 | C50: =IF(Scenarios!D12=1,0, BaselineCalc!$B$7 + ROUND((=IF(ISNUMBER(SEARCH("Ramp",A50)), CHOOSE(MATCH(B50,{"FY2026","FY2027","FY2028","FY2029","FY2030"},0),50,100,150,150,150), Scenarios!C12))*Scenarios!F12,0)) | D50: =IF(Scenarios!E12=1,0, BaselineCalc!$B$8 + (=IF(ISNUMBER(SEARCH("Ramp",A50)), CHOOSE(MATCH(B50,{"FY2026","FY2027","FY2028","FY2029","FY2030"},0),50,100,150,150,150), Scenarios!C12)) - ROUND((=IF(ISNUMBER(SEARCH("Ramp",A50)), CHOOSE(MATCH(B50,{"FY2026","FY2027","FY2028","FY2029","FY2030"},0),50,100,150,150,150), Scenarios!C12))*Scenarios!F12,0)) | E50: =C50+D50 | F50: =VLOOKUP(B50,YearMap!$A$2:$B$6,2,FALSE) | G50: =VLOOKUP(B50,YearMap!$A$2:$C$6,3,FALSE) | H50: =VLOOKUP(B50,YearMap!$A$2:$D$6,4,FALSE) | I50: =1-BaselineCalc!$B$5 | J50: =Scenarios!G12 | K50: =(G50+H50+F50*E50)*I50*(1-J50) | L50: =IF(E50>0, K50/E50, NA()) | M50: =A50&"|"&B50
A51: =Scenarios!A12 | B51: FY2030 | C51: =IF(Scenarios!D12=1,0, BaselineCalc!$B$7 + ROUND((=IF(ISNUMBER(SEARCH("Ramp",A51)), CHOOSE(MATCH(B51,{"FY2026","FY2027","FY2028","FY2029","FY2030"},0),50,100,150,150,150), Scenarios!C12))*Scenarios!F12,0)) | D51: =IF(Scenarios!E12=1,0, BaselineCalc!$B$8 + (=IF(ISNUMBER(SEARCH("Ramp",A51)), CHOOSE(MATCH(B51,{"FY2026","FY2027","FY2028","FY2029","FY2030"},0),50,100,150,150,150), Scenarios!C12)) - ROUND((=IF(ISNUMBER(SEARCH("Ramp",A51)), CHOOSE(MATCH(B51,{"FY2026","FY2027","FY2028","FY2029","FY2030"},0),50,100,150,150,150), Scenarios!C12))*Scenarios!F12,0)) | E51: =C51+D51 | F51: =VLOOKUP(B51,YearMap!$A$2:$B$6,2,FALSE) | G51: =VLOOKUP(B51,YearMap!$A$2:$C$6,3,FALSE) | H51: =VLOOKUP(B51,YearMap!$A$2:$D$6,4,FALSE) | I51: =1-BaselineCalc!$B$5 | J51: =Scenarios!G12 | K51: =(G51+H51+F51*E51)*I51*(1-J51) | L51: =IF(E51>0, K51/E51, NA()) | M51: =A51&"|"&B51
A52: =Scenarios!A13 | B52: FY2026 | C52: =IF(Scenarios!D13=1,0, BaselineCalc!$B$7 + ROUND((=IF(ISNUMBER(SEARCH("Ramp",A52)), CHOOSE(MATCH(B52,{"FY2026","FY2027","FY2028","FY2029","FY2030"},0),50,100,150,150,150), Scenarios!C13))*Scenarios!F13,0)) | D52: =IF(Scenarios!E13=1,0, BaselineCalc!$B$8 + (=IF(ISNUMBER(SEARCH("Ramp",A52)), CHOOSE(MATCH(B52,{"FY2026","FY2027","FY2028","FY2029","FY2030"},0),50,100,150,150,150), Scenarios!C13)) - ROUND((=IF(ISNUMBER(SEARCH("Ramp",A52)), CHOOSE(MATCH(B52,{"FY2026","FY2027","FY2028","FY2029","FY2030"},0),50,100,150,150,150), Scenarios!C13))*Scenarios!F13,0)) | E52: =C52+D52 | F52: =VLOOKUP(B52,YearMap!$A$2:$B$6,2,FALSE) | G52: =VLOOKUP(B52,YearMap!$A$2:$C$6,3,FALSE) | H52: =VLOOKUP(B52,YearMap!$A$2:$D$6,4,FALSE) | I52: =1-BaselineCalc!$B$5 | J52: =Scenarios!G13 | K52: =(G52+H52+F52*E52)*I52*(1-J52) | L52: =IF(E52>0, K52/E52, NA()) | M52: =A52&"|"&B52
A53: =Scenarios!A13 | B53: FY2027 | C53: =IF(Scenarios!D13=1,0, BaselineCalc!$B$7 + ROUND((=IF(ISNUMBER(SEARCH("Ramp",A53)), CHOOSE(MATCH(B53,{"FY2026","FY2027","FY2028","FY2029","FY2030"},0),50,100,150,150,150), Scenarios!C13))*Scenarios!F13,0)) | D53: =IF(Scenarios!E13=1,0, BaselineCalc!$B$8 + (=IF(ISNUMBER(SEARCH("Ramp",A53)), CHOOSE(MATCH(B53,{"FY2026","FY2027","FY2028","FY2029","FY2030"},0),50,100,150,150,150), Scenarios!C13)) - ROUND((=IF(ISNUMBER(SEARCH("Ramp",A53)), CHOOSE(MATCH(B53,{"FY2026","FY2027","FY2028","FY2029","FY2030"},0),50,100,150,150,150), Scenarios!C13))*Scenarios!F13,0)) | E53: =C53+D53 | F53: =VLOOKUP(B53,YearMap!$A$2:$B$6,2,FALSE) | G53: =VLOOKUP(B53,YearMap!$A$2:$C$6,3,FALSE) | H53: =VLOOKUP(B53,YearMap!$A$2:$D$6,4,FALSE) | I53: =1-BaselineCalc!$B$5 | J53: =Scenarios!G13 | K53: =(G53+H53+F53*E53)*I53*(1-J53) | L53: =IF(E53>0, K53/E53, NA()) | M53: =A53&"|"&B53
A54: =Scenarios!A13 | B54: FY2028 | C54: =IF(Scenarios!D13=1,0, BaselineCalc!$B$7 + ROUND((=IF(ISNUMBER(SEARCH("Ramp",A54)), CHOOSE(MATCH(B54,{"FY2026","FY2027","FY2028","FY2029","FY2030"},0),50,100,150,150,150), Scenarios!C13))*Scenarios!F13,0)) | D54: =IF(Scenarios!E13=1,0, BaselineCalc!$B$8 + (=IF(ISNUMBER(SEARCH("Ramp",A54)), CHOOSE(MATCH(B54,{"FY2026","FY2027","FY2028","FY2029","FY2030"},0),50,100,150,150,150), Scenarios!C13)) - ROUND((=IF(ISNUMBER(SEARCH("Ramp",A54)), CHOOSE(MATCH(B54,{"FY2026","FY2027","FY2028","FY2029","FY2030"},0),50,100,150,150,150), Scenarios!C13))*Scenarios!F13,0)) | E54: =C54+D54 | F54: =VLOOKUP(B54,YearMap!$A$2:$B$6,2,FALSE) | G54: =VLOOKUP(B54,YearMap!$A$2:$C$6,3,FALSE) | H54: =VLOOKUP(B54,YearMap!$A$2:$D$6,4,FALSE) | I54: =1-BaselineCalc!$B$5 | J54: =Scenarios!G13 | K54: =(G54+H54+F54*E54)*I54*(1-J54) | L54: =IF(E54>0, K54/E54, NA()) | M54: =A54&"|"&B54
A55: =Scenarios!A13 | B55: FY2029 | C55: =IF(Scenarios!D13=1,0, BaselineCalc!$B$7 + ROUND((=IF(ISNUMBER(SEARCH("Ramp",A55)), CHOOSE(MATCH(B55,{"FY2026","FY2027","FY2028","FY2029","FY2030"},0),50,100,150,150,150), Scenarios!C13))*Scenarios!F13,0)) | D55: =IF(Scenarios!E13=1,0, BaselineCalc!$B$8 + (=IF(ISNUMBER(SEARCH("Ramp",A55)), CHOOSE(MATCH(B55,{"FY2026","FY2027","FY2028","FY2029","FY2030"},0),50,100,150,150,150), Scenarios!C13)) - ROUND((=IF(ISNUMBER(SEARCH("Ramp",A55)), CHOOSE(MATCH(B55,{"FY2026","FY2027","FY2028","FY2029","FY2030"},0),50,100,150,150,150), Scenarios!C13))*Scenarios!F13,0)) | E55: =C55+D55 | F55: =VLOOKUP(B55,YearMap!$A$2:$B$6,2,FALSE) | G55: =VLOOKUP(B55,YearMap!$A$2:$C$6,3,FALSE) | H55: =VLOOKUP(B55,YearMap!$A$2:$D$6,4,FALSE) | I55: =1-BaselineCalc!$B$5 | J55: =Scenarios!G13 | K55: =(G55+H55+F55*E55)*I55*(1-J55) | L55: =IF(E55>0, K55/E55, NA()) | M55: =A55&"|"&B55
A56: =Scenarios!A13 | B56: FY2030 | C56: =IF(Scenarios!D13=1,0, BaselineCalc!$B$7 + ROUND((=IF(ISNUMBER(SEARCH("Ramp",A56)), CHOOSE(MATCH(B56,{"FY2026","FY2027","FY2028","FY2029","FY2030"},0),50,100,150,150,150), Scenarios!C13))*Scenarios!F13,0)) | D56: =IF(Scenarios!E13=1,0, BaselineCalc!$B$8 + (=IF(ISNUMBER(SEARCH("Ramp",A56)), CHOOSE(MATCH(B56,{"FY2026","FY2027","FY2028","FY2029","FY2030"},0),50,100,150,150,150), Scenarios!C13)) - ROUND((=IF(ISNUMBER(SEARCH("Ramp",A56)), CHOOSE(MATCH(B56,{"FY2026","FY2027","FY2028","FY2029","FY2030"},0),50,100,150,150,150), Scenarios!C13))*Scenarios!F13,0)) | E56: =C56+D56 | F56: =VLOOKUP(B56,YearMap!$A$2:$B$6,2,FALSE) | G56: =VLOOKUP(B56,YearMap!$A$2:$C$6,3,FALSE) | H56: =VLOOKUP(B56,YearMap!$A$2:$D$6,4,FALSE) | I56: =1-BaselineCalc!$B$5 | J56: =Scenarios!G13 | K56: =(G56+H56+F56*E56)*I56*(1-J56) | L56: =IF(E56>0, K56/E56, NA()) | M56: =A56&"|"&B56
A57: =Scenarios!A14 | B57: FY2026 | C57: =IF(Scenarios!D14=1,0, BaselineCalc!$B$7 + ROUND((=IF(ISNUMBER(SEARCH("Ramp",A57)), CHOOSE(MATCH(B57,{"FY2026","FY2027","FY2028","FY2029","FY2030"},0),50,100,150,150,150), Scenarios!C14))*Scenarios!F14,0)) | D57: =IF(Scenarios!E14=1,0, BaselineCalc!$B$8 + (=IF(ISNUMBER(SEARCH("Ramp",A57)), CHOOSE(MATCH(B57,{"FY2026","FY2027","FY2028","FY2029","FY2030"},0),50,100,150,150,150), Scenarios!C14)) - ROUND((=IF(ISNUMBER(SEARCH("Ramp",A57)), CHOOSE(MATCH(B57,{"FY2026","FY2027","FY2028","FY2029","FY2030"},0),50,100,150,150,150), Scenarios!C14))*Scenarios!F14,0)) | E57: =C57+D57 | F57: =VLOOKUP(B57,YearMap!$A$2:$B$6,2,FALSE) | G57: =VLOOKUP(B57,YearMap!$A$2:$C$6,3,FALSE) | H57: =VLOOKUP(B57,YearMap!$A$2:$D$6,4,FALSE) | I57: =1-BaselineCalc!$B$5 | J57: =Scenarios!G14 | K57: =(G57+H57+F57*E57)*I57*(1-J57) | L57: =IF(E57>0, K57/E57, NA()) | M57: =A57&"|"&B57
A58: =Scenarios!A14 | B58: FY2027 | C58: =IF(Scenarios!D14=1,0, BaselineCalc!$B$7 + ROUND((=IF(ISNUMBER(SEARCH("Ramp",A58)), CHOOSE(MATCH(B58,{"FY2026","FY2027","FY2028","FY2029","FY2030"},0),50,100,150,150,150), Scenarios!C14))*Scenarios!F14,0)) | D58: =IF(Scenarios!E14=1,0, BaselineCalc!$B$8 + (=IF(ISNUMBER(SEARCH("Ramp",A58)), CHOOSE(MATCH(B58,{"FY2026","FY2027","FY2028","FY2029","FY2030"},0),50,100,150,150,150), Scenarios!C14)) - ROUND((=IF(ISNUMBER(SEARCH("Ramp",A58)), CHOOSE(MATCH(B58,{"FY2026","FY2027","FY2028","FY2029","FY2030"},0),50,100,150,150,150), Scenarios!C14))*Scenarios!F14,0)) | E58: =C58+D58 | F58: =VLOOKUP(B58,YearMap!$A$2:$B$6,2,FALSE) | G58: =VLOOKUP(B58,YearMap!$A$2:$C$6,3,FALSE) | H58: =VLOOKUP(B58,YearMap!$A$2:$D$6,4,FALSE) | I58: =1-BaselineCalc!$B$5 | J58: =Scenarios!G14 | K58: =(G58+H58+F58*E58)*I58*(1-J58) | L58: =IF(E58>0, K58/E58, NA()) | M58: =A58&"|"&B58
A59: =Scenarios!A14 | B59: FY2028 | C59: =IF(Scenarios!D14=1,0, BaselineCalc!$B$7 + ROUND((=IF(ISNUMBER(SEARCH("Ramp",A59)), CHOOSE(MATCH(B59,{"FY2026","FY2027","FY2028","FY2029","FY2030"},0),50,100,150,150,150), Scenarios!C14))*Scenarios!F14,0)) | D59: =IF(Scenarios!E14=1,0, BaselineCalc!$B$8 + (=IF(ISNUMBER(SEARCH("Ramp",A59)), CHOOSE(MATCH(B59,{"FY2026","FY2027","FY2028","FY2029","FY2030"},0),50,100,150,150,150), Scenarios!C14)) - ROUND((=IF(ISNUMBER(SEARCH("Ramp",A59)), CHOOSE(MATCH(B59,{"FY2026","FY2027","FY2028","FY2029","FY2030"},0),50,100,150,150,150), Scenarios!C14))*Scenarios!F14,0)) | E59: =C59+D59 | F59: =VLOOKUP(B59,YearMap!$A$2:$B$6,2,FALSE) | G59: =VLOOKUP(B59,YearMap!$A$2:$C$6,3,FALSE) | H59: =VLOOKUP(B59,YearMap!$A$2:$D$6,4,FALSE) | I59: =1-BaselineCalc!$B$5 | J59: =Scenarios!G14 | K59: =(G59+H59+F59*E59)*I59*(1-J59) | L59: =IF(E59>0, K59/E59, NA()) | M59: =A59&"|"&B59
A60: =Scenarios!A14 | B60: FY2029 | C60: =IF(Scenarios!D14=1,0, BaselineCalc!$B$7 + ROUND((=IF(ISNUMBER(SEARCH("Ramp",A60)), CHOOSE(MATCH(B60,{"FY2026","FY2027","FY2028","FY2029","FY2030"},0),50,100,150,150,150), Scenarios!C14))*Scenarios!F14,0)) | D60: =IF(Scenarios!E14=1,0, BaselineCalc!$B$8 + (=IF(ISNUMBER(SEARCH("Ramp",A60)), CHOOSE(MATCH(B60,{"FY2026","FY2027","FY2028","FY2029","FY2030"},0),50,100,150,150,150), Scenarios!C14)) - ROUND((=IF(ISNUMBER(SEARCH("Ramp",A60)), CHOOSE(MATCH(B60,{"FY2026","FY2027","FY2028","FY2029","FY2030"},0),50,100,150,150,150), Scenarios!C14))*Scenarios!F14,0)) | E60: =C60+D60 | F60: =VLOOKUP(B60,YearMap!$A$2:$B$6,2,FALSE) | G60: =VLOOKUP(B60,YearMap!$A$2:$C$6,3,FALSE) | H60: =VLOOKUP(B60,YearMap!$A$2:$D$6,4,FALSE) | I60: =1-BaselineCalc!$B$5 | J60: =Scenarios!G14 | K60: =(G60+H60+F60*E60)*I60*(1-J60) | L60: =IF(E60>0, K60/E60, NA()) | M60: =A60&"|"&B60
A61: =Scenarios!A14 | B61: FY2030 | C61: =IF(Scenarios!D14=1,0, BaselineCalc!$B$7 + ROUND((=IF(ISNUMBER(SEARCH("Ramp",A61)), CHOOSE(MATCH(B61,{"FY2026","FY2027","FY2028","FY2029","FY2030"},0),50,100,150,150,150), Scenarios!C14))*Scenarios!F14,0)) | D61: =IF(Scenarios!E14=1,0, BaselineCalc!$B$8 + (=IF(ISNUMBER(SEARCH("Ramp",A61)), CHOOSE(MATCH(B61,{"FY2026","FY2027","FY2028","FY2029","FY2030"},0),50,100,150,150,150), Scenarios!C14)) - ROUND((=IF(ISNUMBER(SEARCH("Ramp",A61)), CHOOSE(MATCH(B61,{"FY2026","FY2027","FY2028","FY2029","FY2030"},0),50,100,150,150,150), Scenarios!C14))*Scenarios!F14,0)) | E61: =C61+D61 | F61: =VLOOKUP(B61,YearMap!$A$2:$B$6,2,FALSE) | G61: =VLOOKUP(B61,YearMap!$A$2:$C$6,3,FALSE) | H61: =VLOOKUP(B61,YearMap!$A$2:$D$6,4,FALSE) | I61: =1-BaselineCalc!$B$5 | J61: =Scenarios!G14 | K61: =(G61+H61+F61*E61)*I61*(1-J61) | L61: =IF(E61>0, K61/E61, NA()) | M61: =A61&"|"&B61
A62: =Scenarios!A15 | B62: FY2026 | C62: =IF(Scenarios!D15=1,0, BaselineCalc!$B$7 + ROUND((=IF(ISNUMBER(SEARCH("Ramp",A62)), CHOOSE(MATCH(B62,{"FY2026","FY2027","FY2028","FY2029","FY2030"},0),50,100,150,150,150), Scenarios!C15))*Scenarios!F15,0)) | D62: =IF(Scenarios!E15=1,0, BaselineCalc!$B$8 + (=IF(ISNUMBER(SEARCH("Ramp",A62)), CHOOSE(MATCH(B62,{"FY2026","FY2027","FY2028","FY2029","FY2030"},0),50,100,150,150,150), Scenarios!C15)) - ROUND((=IF(ISNUMBER(SEARCH("Ramp",A62)), CHOOSE(MATCH(B62,{"FY2026","FY2027","FY2028","FY2029","FY2030"},0),50,100,150,150,150), Scenarios!C15))*Scenarios!F15,0)) | E62: =C62+D62 | F62: =VLOOKUP(B62,YearMap!$A$2:$B$6,2,FALSE) | G62: =VLOOKUP(B62,YearMap!$A$2:$C$6,3,FALSE) | H62: =VLOOKUP(B62,YearMap!$A$2:$D$6,4,FALSE) | I62: =1-BaselineCalc!$B$5 | J62: =Scenarios!G15 | K62: =(G62+H62+F62*E62)*I62*(1-J62) | L62: =IF(E62>0, K62/E62, NA()) | M62: =A62&"|"&B62
A63: =Scenarios!A15 | B63: FY2027 | C63: =IF(Scenarios!D15=1,0, BaselineCalc!$B$7 + ROUND((=IF(ISNUMBER(SEARCH("Ramp",A63)), CHOOSE(MATCH(B63,{"FY2026","FY2027","FY2028","FY2029","FY2030"},0),50,100,150,150,150), Scenarios!C15))*Scenarios!F15,0)) | D63: =IF(Scenarios!E15=1,0, BaselineCalc!$B$8 + (=IF(ISNUMBER(SEARCH("Ramp",A63)), CHOOSE(MATCH(B63,{"FY2026","FY2027","FY2028","FY2029","FY2030"},0),50,100,150,150,150), Scenarios!C15)) - ROUND((=IF(ISNUMBER(SEARCH("Ramp",A63)), CHOOSE(MATCH(B63,{"FY2026","FY2027","FY2028","FY2029","FY2030"},0),50,100,150,150,150), Scenarios!C15))*Scenarios!F15,0)) | E63: =C63+D63 | F63: =VLOOKUP(B63,YearMap!$A$2:$B$6,2,FALSE) | G63: =VLOOKUP(B63,YearMap!$A$2:$C$6,3,FALSE) | H63: =VLOOKUP(B63,YearMap!$A$2:$D$6,4,FALSE) | I63: =1-BaselineCalc!$B$5 | J63: =Scenarios!G15 | K63: =(G63+H63+F63*E63)*I63*(1-J63) | L63: =IF(E63>0, K63/E63, NA()) | M63: =A63&"|"&B63
A64: =Scenarios!A15 | B64: FY2028 | C64: =IF(Scenarios!D15=1,0, BaselineCalc!$B$7 + ROUND((=IF(ISNUMBER(SEARCH("Ramp",A64)), CHOOSE(MATCH(B64,{"FY2026","FY2027","FY2028","FY2029","FY2030"},0),50,100,150,150,150), Scenarios!C15))*Scenarios!F15,0)) | D64: =IF(Scenarios!E15=1,0, BaselineCalc!$B$8 + (=IF(ISNUMBER(SEARCH("Ramp",A64)), CHOOSE(MATCH(B64,{"FY2026","FY2027","FY2028","FY2029","FY2030"},0),50,100,150,150,150), Scenarios!C15)) - ROUND((=IF(ISNUMBER(SEARCH("Ramp",A64)), CHOOSE(MATCH(B64,{"FY2026","FY2027","FY2028","FY2029","FY2030"},0),50,100,150,150,150), Scenarios!C15))*Scenarios!F15,0)) | E64: =C64+D64 | F64: =VLOOKUP(B64,YearMap!$A$2:$B$6,2,FALSE) | G64: =VLOOKUP(B64,YearMap!$A$2:$C$6,3,FALSE) | H64: =VLOOKUP(B64,YearMap!$A$2:$D$6,4,FALSE) | I64: =1-BaselineCalc!$B$5 | J64: =Scenarios!G15 | K64: =(G64+H64+F64*E64)*I64*(1-J64) | L64: =IF(E64>0, K64/E64, NA()) | M64: =A64&"|"&B64
A65: =Scenarios!A15 | B65: FY2029 | C65: =IF(Scenarios!D15=1,0, BaselineCalc!$B$7 + ROUND((=IF(ISNUMBER(SEARCH("Ramp",A65)), CHOOSE(MATCH(B65,{"FY2026","FY2027","FY2028","FY2029","FY2030"},0),50,100,150,150,150), Scenarios!C15))*Scenarios!F15,0)) | D65: =IF(Scenarios!E15=1,0, BaselineCalc!$B$8 + (=IF(ISNUMBER(SEARCH("Ramp",A65)), CHOOSE(MATCH(B65,{"FY2026","FY2027","FY2028","FY2029","FY2030"},0),50,100,150,150,150), Scenarios!C15)) - ROUND((=IF(ISNUMBER(SEARCH("Ramp",A65)), CHOOSE(MATCH(B65,{"FY2026","FY2027","FY2028","FY2029","FY2030"},0),50,100,150,150,150), Scenarios!C15))*Scenarios!F15,0)) | E65: =C65+D65 | F65: =VLOOKUP(B65,YearMap!$A$2:$B$6,2,FALSE) | G65: =VLOOKUP(B65,YearMap!$A$2:$C$6,3,FALSE) | H65: =VLOOKUP(B65,YearMap!$A$2:$D$6,4,FALSE) | I65: =1-BaselineCalc!$B$5 | J65: =Scenarios!G15 | K65: =(G65+H65+F65*E65)*I65*(1-J65) | L65: =IF(E65>0, K65/E65, NA()) | M65: =A65&"|"&B65
A66: =Scenarios!A15 | B66: FY2030 | C66: =IF(Scenarios!D15=1,0, BaselineCalc!$B$7 + ROUND((=IF(ISNUMBER(SEARCH("Ramp",A66)), CHOOSE(MATCH(B66,{"FY2026","FY2027","FY2028","FY2029","FY2030"},0),50,100,150,150,150), Scenarios!C15))*Scenarios!F15,0)) | D66: =IF(Scenarios!E15=1,0, BaselineCalc!$B$8 + (=IF(ISNUMBER(SEARCH("Ramp",A66)), CHOOSE(MATCH(B66,{"FY2026","FY2027","FY2028","FY2029","FY2030"},0),50,100,150,150,150), Scenarios!C15)) - ROUND((=IF(ISNUMBER(SEARCH("Ramp",A66)), CHOOSE(MATCH(B66,{"FY2026","FY2027","FY2028","FY2029","FY2030"},0),50,100,150,150,150), Scenarios!C15))*Scenarios!F15,0)) | E66: =C66+D66 | F66: =VLOOKUP(B66,YearMap!$A$2:$B$6,2,FALSE) | G66: =VLOOKUP(B66,YearMap!$A$2:$C$6,3,FALSE) | H66: =VLOOKUP(B66,YearMap!$A$2:$D$6,4,FALSE) | I66: =1-BaselineCalc!$B$5 | J66: =Scenarios!G15 | K66: =(G66+H66+F66*E66)*I66*(1-J66) | L66: =IF(E66>0, K66/E66, NA()) | M66: =A66&"|"&B66
A67: =Scenarios!A16 | B67: FY2026 | C67: =IF(Scenarios!D16=1,0, BaselineCalc!$B$7 + ROUND((=IF(ISNUMBER(SEARCH("Ramp",A67)), CHOOSE(MATCH(B67,{"FY2026","FY2027","FY2028","FY2029","FY2030"},0),50,100,150,150,150), Scenarios!C16))*Scenarios!F16,0)) | D67: =IF(Scenarios!E16=1,0, BaselineCalc!$B$8 + (=IF(ISNUMBER(SEARCH("Ramp",A67)), CHOOSE(MATCH(B67,{"FY2026","FY2027","FY2028","FY2029","FY2030"},0),50,100,150,150,150), Scenarios!C16)) - ROUND((=IF(ISNUMBER(SEARCH("Ramp",A67)), CHOOSE(MATCH(B67,{"FY2026","FY2027","FY2028","FY2029","FY2030"},0),50,100,150,150,150), Scenarios!C16))*Scenarios!F16,0)) | E67: =C67+D67 | F67: =VLOOKUP(B67,YearMap!$A$2:$B$6,2,FALSE) | G67: =VLOOKUP(B67,YearMap!$A$2:$C$6,3,FALSE) | H67: =VLOOKUP(B67,YearMap!$A$2:$D$6,4,FALSE) | I67: =1-BaselineCalc!$B$5 | J67: =Scenarios!G16 | K67: =(G67+H67+F67*E67)*I67*(1-J67) | L67: =IF(E67>0, K67/E67, NA()) | M67: =A67&"|"&B67
A68: =Scenarios!A16 | B68: FY2027 | C68: =IF(Scenarios!D16=1,0, BaselineCalc!$B$7 + ROUND((=IF(ISNUMBER(SEARCH("Ramp",A68)), CHOOSE(MATCH(B68,{"FY2026","FY2027","FY2028","FY2029","FY2030"},0),50,100,150,150,150), Scenarios!C16))*Scenarios!F16,0)) | D68: =IF(Scenarios!E16=1,0, BaselineCalc!$B$8 + (=IF(ISNUMBER(SEARCH("Ramp",A68)), CHOOSE(MATCH(B68,{"FY2026","FY2027","FY2028","FY2029","FY2030"},0),50,100,150,150,150), Scenarios!C16)) - ROUND((=IF(ISNUMBER(SEARCH("Ramp",A68)), CHOOSE(MATCH(B68,{"FY2026","FY2027","FY2028","FY2029","FY2030"},0),50,100,150,150,150), Scenarios!C16))*Scenarios!F16,0)) | E68: =C68+D68 | F68: =VLOOKUP(B68,YearMap!$A$2:$B$6,2,FALSE) | G68: =VLOOKUP(B68,YearMap!$A$2:$C$6,3,FALSE) | H68: =VLOOKUP(B68,YearMap!$A$2:$D$6,4,FALSE) | I68: =1-BaselineCalc!$B$5 | J68: =Scenarios!G16 | K68: =(G68+H68+F68*E68)*I68*(1-J68) | L68: =IF(E68>0, K68/E68, NA()) | M68: =A68&"|"&B68
A69: =Scenarios!A16 | B69: FY2028 | C69: =IF(Scenarios!D16=1,0, BaselineCalc!$B$7 + ROUND((=IF(ISNUMBER(SEARCH("Ramp",A69)), CHOOSE(MATCH(B69,{"FY2026","FY2027","FY2028","FY2029","FY2030"},0),50,100,150,150,150), Scenarios!C16))*Scenarios!F16,0)) | D69: =IF(Scenarios!E16=1,0, BaselineCalc!$B$8 + (=IF(ISNUMBER(SEARCH("Ramp",A69)), CHOOSE(MATCH(B69,{"FY2026","FY2027","FY2028","FY2029","FY2030"},0),50,100,150,150,150), Scenarios!C16)) - ROUND((=IF(ISNUMBER(SEARCH("Ramp",A69)), CHOOSE(MATCH(B69,{"FY2026","FY2027","FY2028","FY2029","FY2030"},0),50,100,150,150,150), Scenarios!C16))*Scenarios!F16,0)) | E69: =C69+D69 | F69: =VLOOKUP(B69,YearMap!$A$2:$B$6,2,FALSE) | G69: =VLOOKUP(B69,YearMap!$A$2:$C$6,3,FALSE) | H69: =VLOOKUP(B69,YearMap!$A$2:$D$6,4,FALSE) | I69: =1-BaselineCalc!$B$5 | J69: =Scenarios!G16 | K69: =(G69+H69+F69*E69)*I69*(1-J69) | L69: =IF(E69>0, K69/E69, NA()) | M69: =A69&"|"&B69
A70: =Scenarios!A16 | B70: FY2029 | C70: =IF(Scenarios!D16=1,0, BaselineCalc!$B$7 + ROUND((=IF(ISNUMBER(SEARCH("Ramp",A70)), CHOOSE(MATCH(B70,{"FY2026","FY2027","FY2028","FY2029","FY2030"},0),50,100,150,150,150), Scenarios!C16))*Scenarios!F16,0)) | D70: =IF(Scenarios!E16=1,0, BaselineCalc!$B$8 + (=IF(ISNUMBER(SEARCH("Ramp",A70)), CHOOSE(MATCH(B70,{"FY2026","FY2027","FY2028","FY2029","FY2030"},0),50,100,150,150,150), Scenarios!C16)) - ROUND((=IF(ISNUMBER(SEARCH("Ramp",A70)), CHOOSE(MATCH(B70,{"FY2026","FY2027","FY2028","FY2029","FY2030"},0),50,100,150,150,150), Scenarios!C16))*Scenarios!F16,0)) | E70: =C70+D70 | F70: =VLOOKUP(B70,YearMap!$A$2:$B$6,2,FALSE) | G70: =VLOOKUP(B70,YearMap!$A$2:$C$6,3,FALSE) | H70: =VLOOKUP(B70,YearMap!$A$2:$D$6,4,FALSE) | I70: =1-BaselineCalc!$B$5 | J70: =Scenarios!G16 | K70: =(G70+H70+F70*E70)*I70*(1-J70) | L70: =IF(E70>0, K70/E70, NA()) | M70: =A70&"|"&B70
A71: =Scenarios!A16 | B71: FY2030 | C71: =IF(Scenarios!D16=1,0, BaselineCalc!$B$7 + ROUND((=IF(ISNUMBER(SEARCH("Ramp",A71)), CHOOSE(MATCH(B71,{"FY2026","FY2027","FY2028","FY2029","FY2030"},0),50,100,150,150,150), Scenarios!C16))*Scenarios!F16,0)) | D71: =IF(Scenarios!E16=1,0, BaselineCalc!$B$8 + (=IF(ISNUMBER(SEARCH("Ramp",A71)), CHOOSE(MATCH(B71,{"FY2026","FY2027","FY2028","FY2029","FY2030"},0),50,100,150,150,150), Scenarios!C16)) - ROUND((=IF(ISNUMBER(SEARCH("Ramp",A71)), CHOOSE(MATCH(B71,{"FY2026","FY2027","FY2028","FY2029","FY2030"},0),50,100,150,150,150), Scenarios!C16))*Scenarios!F16,0)) | E71: =C71+D71 | F71: =VLOOKUP(B71,YearMap!$A$2:$B$6,2,FALSE) | G71: =VLOOKUP(B71,YearMap!$A$2:$C$6,3,FALSE) | H71: =VLOOKUP(B71,YearMap!$A$2:$D$6,4,FALSE) | I71: =1-BaselineCalc!$B$5 | J71: =Scenarios!G16 | K71: =(G71+H71+F71*E71)*I71*(1-J71) | L71: =IF(E71>0, K71/E71, NA()) | M71: =A71&"|"&B71
A72: =Scenarios!A17 | B72: FY2026 | C72: =IF(Scenarios!D17=1,0, BaselineCalc!$B$7 + ROUND((=IF(ISNUMBER(SEARCH("Ramp",A72)), CHOOSE(MATCH(B72,{"FY2026","FY2027","FY2028","FY2029","FY2030"},0),50,100,150,150,150), Scenarios!C17))*Scenarios!F17,0)) | D72: =IF(Scenarios!E17=1,0, BaselineCalc!$B$8 + (=IF(ISNUMBER(SEARCH("Ramp",A72)), CHOOSE(MATCH(B72,{"FY2026","FY2027","FY2028","FY2029","FY2030"},0),50,100,150,150,150), Scenarios!C17)) - ROUND((=IF(ISNUMBER(SEARCH("Ramp",A72)), CHOOSE(MATCH(B72,{"FY2026","FY2027","FY2028","FY2029","FY2030"},0),50,100,150,150,150), Scenarios!C17))*Scenarios!F17,0)) | E72: =C72+D72 | F72: =VLOOKUP(B72,YearMap!$A$2:$B$6,2,FALSE) | G72: =VLOOKUP(B72,YearMap!$A$2:$C$6,3,FALSE) | H72: =VLOOKUP(B72,YearMap!$A$2:$D$6,4,FALSE) | I72: =1-BaselineCalc!$B$5 | J72: =Scenarios!G17 | K72: =(G72+H72+F72*E72)*I72*(1-J72) | L72: =IF(E72>0, K72/E72, NA()) | M72: =A72&"|"&B72
A73: =Scenarios!A17 | B73: FY2027 | C73: =IF(Scenarios!D17=1,0, BaselineCalc!$B$7 + ROUND((=IF(ISNUMBER(SEARCH("Ramp",A73)), CHOOSE(MATCH(B73,{"FY2026","FY2027","FY2028","FY2029","FY2030"},0),50,100,150,150,150), Scenarios!C17))*Scenarios!F17,0)) | D73: =IF(Scenarios!E17=1,0, BaselineCalc!$B$8 + (=IF(ISNUMBER(SEARCH("Ramp",A73)), CHOOSE(MATCH(B73,{"FY2026","FY2027","FY2028","FY2029","FY2030"},0),50,100,150,150,150), Scenarios!C17)) - ROUND((=IF(ISNUMBER(SEARCH("Ramp",A73)), CHOOSE(MATCH(B73,{"FY2026","FY2027","FY2028","FY2029","FY2030"},0),50,100,150,150,150), Scenarios!C17))*Scenarios!F17,0)) | E73: =C73+D73 | F73: =VLOOKUP(B73,YearMap!$A$2:$B$6,2,FALSE) | G73: =VLOOKUP(B73,YearMap!$A$2:$C$6,3,FALSE) | H73: =VLOOKUP(B73,YearMap!$A$2:$D$6,4,FALSE) | I73: =1-BaselineCalc!$B$5 | J73: =Scenarios!G17 | K73: =(G73+H73+F73*E73)*I73*(1-J73) | L73: =IF(E73>0, K73/E73, NA()) | M73: =A73&"|"&B73
A74: =Scenarios!A17 | B74: FY2028 | C74: =IF(Scenarios!D17=1,0, BaselineCalc!$B$7 + ROUND((=IF(ISNUMBER(SEARCH("Ramp",A74)), CHOOSE(MATCH(B74,{"FY2026","FY2027","FY2028","FY2029","FY2030"},0),50,100,150,150,150), Scenarios!C17))*Scenarios!F17,0)) | D74: =IF(Scenarios!E17=1,0, BaselineCalc!$B$8 + (=IF(ISNUMBER(SEARCH("Ramp",A74)), CHOOSE(MATCH(B74,{"FY2026","FY2027","FY2028","FY2029","FY2030"},0),50,100,150,150,150), Scenarios!C17)) - ROUND((=IF(ISNUMBER(SEARCH("Ramp",A74)), CHOOSE(MATCH(B74,{"FY2026","FY2027","FY2028","FY2029","FY2030"},0),50,100,150,150,150), Scenarios!C17))*Scenarios!F17,0)) | E74: =C74+D74 | F74: =VLOOKUP(B74,YearMap!$A$2:$B$6,2,FALSE) | G74: =VLOOKUP(B74,YearMap!$A$2:$C$6,3,FALSE) | H74: =VLOOKUP(B74,YearMap!$A$2:$D$6,4,FALSE) | I74: =1-BaselineCalc!$B$5 | J74: =Scenarios!G17 | K74: =(G74+H74+F74*E74)*I74*(1-J74) | L74: =IF(E74>0, K74/E74, NA()) | M74: =A74&"|"&B74
A75: =Scenarios!A17 | B75: FY2029 | C75: =IF(Scenarios!D17=1,0, BaselineCalc!$B$7 + ROUND((=IF(ISNUMBER(SEARCH("Ramp",A75)), CHOOSE(MATCH(B75,{"FY2026","FY2027","FY2028","FY2029","FY2030"},0),50,100,150,150,150), Scenarios!C17))*Scenarios!F17,0)) | D75: =IF(Scenarios!E17=1,0, BaselineCalc!$B$8 + (=IF(ISNUMBER(SEARCH("Ramp",A75)), CHOOSE(MATCH(B75,{"FY2026","FY2027","FY2028","FY2029","FY2030"},0),50,100,150,150,150), Scenarios!C17)) - ROUND((=IF(ISNUMBER(SEARCH("Ramp",A75)), CHOOSE(MATCH(B75,{"FY2026","FY2027","FY2028","FY2029","FY2030"},0),50,100,150,150,150), Scenarios!C17))*Scenarios!F17,0)) | E75: =C75+D75 | F75: =VLOOKUP(B75,YearMap!$A$2:$B$6,2,FALSE) | G75: =VLOOKUP(B75,YearMap!$A$2:$C$6,3,FALSE) | H75: =VLOOKUP(B75,YearMap!$A$2:$D$6,4,FALSE) | I75: =1-BaselineCalc!$B$5 | J75: =Scenarios!G17 | K75: =(G75+H75+F75*E75)*I75*(1-J75) | L75: =IF(E75>0, K75/E75, NA()) | M75: =A75&"|"&B75
A76: =Scenarios!A17 | B76: FY2030 | C76: =IF(Scenarios!D17=1,0, BaselineCalc!$B$7 + ROUND((=IF(ISNUMBER(SEARCH("Ramp",A76)), CHOOSE(MATCH(B76,{"FY2026","FY2027","FY2028","FY2029","FY2030"},0),50,100,150,150,150), Scenarios!C17))*Scenarios!F17,0)) | D76: =IF(Scenarios!E17=1,0, BaselineCalc!$B$8 + (=IF(ISNUMBER(SEARCH("Ramp",A76)), CHOOSE(MATCH(B76,{"FY2026","FY2027","FY2028","FY2029","FY2030"},0),50,100,150,150,150), Scenarios!C17)) - ROUND((=IF(ISNUMBER(SEARCH("Ramp",A76)), CHOOSE(MATCH(B76,{"FY2026","FY2027","FY2028","FY2029","FY2030"},0),50,100,150,150,150), Scenarios!C17))*Scenarios!F17,0)) | E76: =C76+D76 | F76: =VLOOKUP(B76,YearMap!$A$2:$B$6,2,FALSE) | G76: =VLOOKUP(B76,YearMap!$A$2:$C$6,3,FALSE) | H76: =VLOOKUP(B76,YearMap!$A$2:$D$6,4,FALSE) | I76: =1-BaselineCalc!$B$5 | J76: =Scenarios!G17 | K76: =(G76+H76+F76*E76)*I76*(1-J76) | L76: =IF(E76>0, K76/E76, NA()) | M76: =A76&"|"&B76
A77: =Scenarios!A18 | B77: FY2026 | C77: =IF(Scenarios!D18=1,0, BaselineCalc!$B$7 + ROUND((=IF(ISNUMBER(SEARCH("Ramp",A77)), CHOOSE(MATCH(B77,{"FY2026","FY2027","FY2028","FY2029","FY2030"},0),50,100,150,150,150), Scenarios!C18))*Scenarios!F18,0)) | D77: =IF(Scenarios!E18=1,0, BaselineCalc!$B$8 + (=IF(ISNUMBER(SEARCH("Ramp",A77)), CHOOSE(MATCH(B77,{"FY2026","FY2027","FY2028","FY2029","FY2030"},0),50,100,150,150,150), Scenarios!C18)) - ROUND((=IF(ISNUMBER(SEARCH("Ramp",A77)), CHOOSE(MATCH(B77,{"FY2026","FY2027","FY2028","FY2029","FY2030"},0),50,100,150,150,150), Scenarios!C18))*Scenarios!F18,0)) | E77: =C77+D77 | F77: =VLOOKUP(B77,YearMap!$A$2:$B$6,2,FALSE) | G77: =VLOOKUP(B77,YearMap!$A$2:$C$6,3,FALSE) | H77: =VLOOKUP(B77,YearMap!$A$2:$D$6,4,FALSE) | I77: =1-BaselineCalc!$B$5 | J77: =Scenarios!G18 | K77: =(G77+H77+F77*E77)*I77*(1-J77) | L77: =IF(E77>0, K77/E77, NA()) | M77: =A77&"|"&B77
A78: =Scenarios!A18 | B78: FY2027 | C78: =IF(Scenarios!D18=1,0, BaselineCalc!$B$7 + ROUND((=IF(ISNUMBER(SEARCH("Ramp",A78)), CHOOSE(MATCH(B78,{"FY2026","FY2027","FY2028","FY2029","FY2030"},0),50,100,150,150,150), Scenarios!C18))*Scenarios!F18,0)) | D78: =IF(Scenarios!E18=1,0, BaselineCalc!$B$8 + (=IF(ISNUMBER(SEARCH("Ramp",A78)), CHOOSE(MATCH(B78,{"FY2026","FY2027","FY2028","FY2029","FY2030"},0),50,100,150,150,150), Scenarios!C18)) - ROUND((=IF(ISNUMBER(SEARCH("Ramp",A78)), CHOOSE(MATCH(B78,{"FY2026","FY2027","FY2028","FY2029","FY2030"},0),50,100,150,150,150), Scenarios!C18))*Scenarios!F18,0)) | E78: =C78+D78 | F78: =VLOOKUP(B78,YearMap!$A$2:$B$6,2,FALSE) | G78: =VLOOKUP(B78,YearMap!$A$2:$C$6,3,FALSE) | H78: =VLOOKUP(B78,YearMap!$A$2:$D$6,4,FALSE) | I78: =1-BaselineCalc!$B$5 | J78: =Scenarios!G18 | K78: =(G78+H78+F78*E78)*I78*(1-J78) | L78: =IF(E78>0, K78/E78, NA()) | M78: =A78&"|"&B78
A79: =Scenarios!A18 | B79: FY2028 | C79: =IF(Scenarios!D18=1,0, BaselineCalc!$B$7 + ROUND((=IF(ISNUMBER(SEARCH("Ramp",A79)), CHOOSE(MATCH(B79,{"FY2026","FY2027","FY2028","FY2029","FY2030"},0),50,100,150,150,150), Scenarios!C18))*Scenarios!F18,0)) | D79: =IF(Scenarios!E18=1,0, BaselineCalc!$B$8 + (=IF(ISNUMBER(SEARCH("Ramp",A79)), CHOOSE(MATCH(B79,{"FY2026","FY2027","FY2028","FY2029","FY2030"},0),50,100,150,150,150), Scenarios!C18)) - ROUND((=IF(ISNUMBER(SEARCH("Ramp",A79)), CHOOSE(MATCH(B79,{"FY2026","FY2027","FY2028","FY2029","FY2030"},0),50,100,150,150,150), Scenarios!C18))*Scenarios!F18,0)) | E79: =C79+D79 | F79: =VLOOKUP(B79,YearMap!$A$2:$B$6,2,FALSE) | G79: =VLOOKUP(B79,YearMap!$A$2:$C$6,3,FALSE) | H79: =VLOOKUP(B79,YearMap!$A$2:$D$6,4,FALSE) | I79: =1-BaselineCalc!$B$5 | J79: =Scenarios!G18 | K79: =(G79+H79+F79*E79)*I79*(1-J79) | L79: =IF(E79>0, K79/E79, NA()) | M79: =A79&"|"&B79
A80: =Scenarios!A18 | B80: FY2029 | C80: =IF(Scenarios!D18=1,0, BaselineCalc!$B$7 + ROUND((=IF(ISNUMBER(SEARCH("Ramp",A80)), CHOOSE(MATCH(B80,{"FY2026","FY2027","FY2028","FY2029","FY2030"},0),50,100,150,150,150), Scenarios!C18))*Scenarios!F18,0)) | D80: =IF(Scenarios!E18=1,0, BaselineCalc!$B$8 + (=IF(ISNUMBER(SEARCH("Ramp",A80)), CHOOSE(MATCH(B80,{"FY2026","FY2027","FY2028","FY2029","FY2030"},0),50,100,150,150,150), Scenarios!C18)) - ROUND((=IF(ISNUMBER(SEARCH("Ramp",A80)), CHOOSE(MATCH(B80,{"FY2026","FY2027","FY2028","FY2029","FY2030"},0),50,100,150,150,150), Scenarios!C18))*Scenarios!F18,0)) | E80: =C80+D80 | F80: =VLOOKUP(B80,YearMap!$A$2:$B$6,2,FALSE) | G80: =VLOOKUP(B80,YearMap!$A$2:$C$6,3,FALSE) | H80: =VLOOKUP(B80,YearMap!$A$2:$D$6,4,FALSE) | I80: =1-BaselineCalc!$B$5 | J80: =Scenarios!G18 | K80: =(G80+H80+F80*E80)*I80*(1-J80) | L80: =IF(E80>0, K80/E80, NA()) | M80: =A80&"|"&B80
A81: =Scenarios!A18 | B81: FY2030 | C81: =IF(Scenarios!D18=1,0, BaselineCalc!$B$7 + ROUND((=IF(ISNUMBER(SEARCH("Ramp",A81)), CHOOSE(MATCH(B81,{"FY2026","FY2027","FY2028","FY2029","FY2030"},0),50,100,150,150,150), Scenarios!C18))*Scenarios!F18,0)) | D81: =IF(Scenarios!E18=1,0, BaselineCalc!$B$8 + (=IF(ISNUMBER(SEARCH("Ramp",A81)), CHOOSE(MATCH(B81,{"FY2026","FY2027","FY2028","FY2029","FY2030"},0),50,100,150,150,150), Scenarios!C18)) - ROUND((=IF(ISNUMBER(SEARCH("Ramp",A81)), CHOOSE(MATCH(B81,{"FY2026","FY2027","FY2028","FY2029","FY2030"},0),50,100,150,150,150), Scenarios!C18))*Scenarios!F18,0)) | E81: =C81+D81 | F81: =VLOOKUP(B81,YearMap!$A$2:$B$6,2,FALSE) | G81: =VLOOKUP(B81,YearMap!$A$2:$C$6,3,FALSE) | H81: =VLOOKUP(B81,YearMap!$A$2:$D$6,4,FALSE) | I81: =1-BaselineCalc!$B$5 | J81: =Scenarios!G18 | K81: =(G81+H81+F81*E81)*I81*(1-J81) | L81: =IF(E81>0, K81/E81, NA()) | M81: =A81&"|"&B81
A82: =Scenarios!A19 | B82: FY2026 | C82: =IF(Scenarios!D19=1,0, BaselineCalc!$B$7 + ROUND((=IF(ISNUMBER(SEARCH("Ramp",A82)), CHOOSE(MATCH(B82,{"FY2026","FY2027","FY2028","FY2029","FY2030"},0),50,100,150,150,150), Scenarios!C19))*Scenarios!F19,0)) | D82: =IF(Scenarios!E19=1,0, BaselineCalc!$B$8 + (=IF(ISNUMBER(SEARCH("Ramp",A82)), CHOOSE(MATCH(B82,{"FY2026","FY2027","FY2028","FY2029","FY2030"},0),50,100,150,150,150), Scenarios!C19)) - ROUND((=IF(ISNUMBER(SEARCH("Ramp",A82)), CHOOSE(MATCH(B82,{"FY2026","FY2027","FY2028","FY2029","FY2030"},0),50,100,150,150,150), Scenarios!C19))*Scenarios!F19,0)) | E82: =C82+D82 | F82: =VLOOKUP(B82,YearMap!$A$2:$B$6,2,FALSE) | G82: =VLOOKUP(B82,YearMap!$A$2:$C$6,3,FALSE) | H82: =VLOOKUP(B82,YearMap!$A$2:$D$6,4,FALSE) | I82: =1-BaselineCalc!$B$5 | J82: =Scenarios!G19 | K82: =(G82+H82+F82*E82)*I82*(1-J82) | L82: =IF(E82>0, K82/E82, NA()) | M82: =A82&"|"&B82
A83: =Scenarios!A19 | B83: FY2027 | C83: =IF(Scenarios!D19=1,0, BaselineCalc!$B$7 + ROUND((=IF(ISNUMBER(SEARCH("Ramp",A83)), CHOOSE(MATCH(B83,{"FY2026","FY2027","FY2028","FY2029","FY2030"},0),50,100,150,150,150), Scenarios!C19))*Scenarios!F19,0)) | D83: =IF(Scenarios!E19=1,0, BaselineCalc!$B$8 + (=IF(ISNUMBER(SEARCH("Ramp",A83)), CHOOSE(MATCH(B83,{"FY2026","FY2027","FY2028","FY2029","FY2030"},0),50,100,150,150,150), Scenarios!C19)) - ROUND((=IF(ISNUMBER(SEARCH("Ramp",A83)), CHOOSE(MATCH(B83,{"FY2026","FY2027","FY2028","FY2029","FY2030"},0),50,100,150,150,150), Scenarios!C19))*Scenarios!F19,0)) | E83: =C83+D83 | F83: =VLOOKUP(B83,YearMap!$A$2:$B$6,2,FALSE) | G83: =VLOOKUP(B83,YearMap!$A$2:$C$6,3,FALSE) | H83: =VLOOKUP(B83,YearMap!$A$2:$D$6,4,FALSE) | I83: =1-BaselineCalc!$B$5 | J83: =Scenarios!G19 | K83: =(G83+H83+F83*E83)*I83*(1-J83) | L83: =IF(E83>0, K83/E83, NA()) | M83: =A83&"|"&B83
A84: =Scenarios!A19 | B84: FY2028 | C84: =IF(Scenarios!D19=1,0, BaselineCalc!$B$7 + ROUND((=IF(ISNUMBER(SEARCH("Ramp",A84)), CHOOSE(MATCH(B84,{"FY2026","FY2027","FY2028","FY2029","FY2030"},0),50,100,150,150,150), Scenarios!C19))*Scenarios!F19,0)) | D84: =IF(Scenarios!E19=1,0, BaselineCalc!$B$8 + (=IF(ISNUMBER(SEARCH("Ramp",A84)), CHOOSE(MATCH(B84,{"FY2026","FY2027","FY2028","FY2029","FY2030"},0),50,100,150,150,150), Scenarios!C19)) - ROUND((=IF(ISNUMBER(SEARCH("Ramp",A84)), CHOOSE(MATCH(B84,{"FY2026","FY2027","FY2028","FY2029","FY2030"},0),50,100,150,150,150), Scenarios!C19))*Scenarios!F19,0)) | E84: =C84+D84 | F84: =VLOOKUP(B84,YearMap!$A$2:$B$6,2,FALSE) | G84: =VLOOKUP(B84,YearMap!$A$2:$C$6,3,FALSE) | H84: =VLOOKUP(B84,YearMap!$A$2:$D$6,4,FALSE) | I84: =1-BaselineCalc!$B$5 | J84: =Scenarios!G19 | K84: =(G84+H84+F84*E84)*I84*(1-J84) | L84: =IF(E84>0, K84/E84, NA()) | M84: =A84&"|"&B84
A85: =Scenarios!A19 | B85: FY2029 | C85: =IF(Scenarios!D19=1,0, BaselineCalc!$B$7 + ROUND((=IF(ISNUMBER(SEARCH("Ramp",A85)), CHOOSE(MATCH(B85,{"FY2026","FY2027","FY2028","FY2029","FY2030"},0),50,100,150,150,150), Scenarios!C19))*Scenarios!F19,0)) | D85: =IF(Scenarios!E19=1,0, BaselineCalc!$B$8 + (=IF(ISNUMBER(SEARCH("Ramp",A85)), CHOOSE(MATCH(B85,{"FY2026","FY2027","FY2028","FY2029","FY2030"},0),50,100,150,150,150), Scenarios!C19)) - ROUND((=IF(ISNUMBER(SEARCH("Ramp",A85)), CHOOSE(MATCH(B85,{"FY2026","FY2027","FY2028","FY2029","FY2030"},0),50,100,150,150,150), Scenarios!C19))*Scenarios!F19,0)) | E85: =C85+D85 | F85: =VLOOKUP(B85,YearMap!$A$2:$B$6,2,FALSE) | G85: =VLOOKUP(B85,YearMap!$A$2:$C$6,3,FALSE) | H85: =VLOOKUP(B85,YearMap!$A$2:$D$6,4,FALSE) | I85: =1-BaselineCalc!$B$5 | J85: =Scenarios!G19 | K85: =(G85+H85+F85*E85)*I85*(1-J85) | L85: =IF(E85>0, K85/E85, NA()) | M85: =A85&"|"&B85
A86: =Scenarios!A19 | B86: FY2030 | C86: =IF(Scenarios!D19=1,0, BaselineCalc!$B$7 + ROUND((=IF(ISNUMBER(SEARCH("Ramp",A86)), CHOOSE(MATCH(B86,{"FY2026","FY2027","FY2028","FY2029","FY2030"},0),50,100,150,150,150), Scenarios!C19))*Scenarios!F19,0)) | D86: =IF(Scenarios!E19=1,0, BaselineCalc!$B$8 + (=IF(ISNUMBER(SEARCH("Ramp",A86)), CHOOSE(MATCH(B86,{"FY2026","FY2027","FY2028","FY2029","FY2030"},0),50,100,150,150,150), Scenarios!C19)) - ROUND((=IF(ISNUMBER(SEARCH("Ramp",A86)), CHOOSE(MATCH(B86,{"FY2026","FY2027","FY2028","FY2029","FY2030"},0),50,100,150,150,150), Scenarios!C19))*Scenarios!F19,0)) | E86: =C86+D86 | F86: =VLOOKUP(B86,YearMap!$A$2:$B$6,2,FALSE) | G86: =VLOOKUP(B86,YearMap!$A$2:$C$6,3,FALSE) | H86: =VLOOKUP(B86,YearMap!$A$2:$D$6,4,FALSE) | I86: =1-BaselineCalc!$B$5 | J86: =Scenarios!G19 | K86: =(G86+H86+F86*E86)*I86*(1-J86) | L86: =IF(E86>0, K86/E86, NA()) | M86: =A86&"|"&B86
A87: =Scenarios!A20 | B87: FY2026 | C87: =IF(Scenarios!D20=1,0, BaselineCalc!$B$7 + ROUND((=IF(ISNUMBER(SEARCH("Ramp",A87)), CHOOSE(MATCH(B87,{"FY2026","FY2027","FY2028","FY2029","FY2030"},0),50,100,150,150,150), Scenarios!C20))*Scenarios!F20,0)) | D87: =IF(Scenarios!E20=1,0, BaselineCalc!$B$8 + (=IF(ISNUMBER(SEARCH("Ramp",A87)), CHOOSE(MATCH(B87,{"FY2026","FY2027","FY2028","FY2029","FY2030"},0),50,100,150,150,150), Scenarios!C20)) - ROUND((=IF(ISNUMBER(SEARCH("Ramp",A87)), CHOOSE(MATCH(B87,{"FY2026","FY2027","FY2028","FY2029","FY2030"},0),50,100,150,150,150), Scenarios!C20))*Scenarios!F20,0)) | E87: =C87+D87 | F87: =VLOOKUP(B87,YearMap!$A$2:$B$6,2,FALSE) | G87: =VLOOKUP(B87,YearMap!$A$2:$C$6,3,FALSE) | H87: =VLOOKUP(B87,YearMap!$A$2:$D$6,4,FALSE) | I87: =1-BaselineCalc!$B$5 | J87: =Scenarios!G20 | K87: =(G87+H87+F87*E87)*I87*(1-J87) | L87: =IF(E87>0, K87/E87, NA()) | M87: =A87&"|"&B87
A88: =Scenarios!A20 | B88: FY2027 | C88: =IF(Scenarios!D20=1,0, BaselineCalc!$B$7 + ROUND((=IF(ISNUMBER(SEARCH("Ramp",A88)), CHOOSE(MATCH(B88,{"FY2026","FY2027","FY2028","FY2029","FY2030"},0),50,100,150,150,150), Scenarios!C20))*Scenarios!F20,0)) | D88: =IF(Scenarios!E20=1,0, BaselineCalc!$B$8 + (=IF(ISNUMBER(SEARCH("Ramp",A88)), CHOOSE(MATCH(B88,{"FY2026","FY2027","FY2028","FY2029","FY2030"},0),50,100,150,150,150), Scenarios!C20)) - ROUND((=IF(ISNUMBER(SEARCH("Ramp",A88)), CHOOSE(MATCH(B88,{"FY2026","FY2027","FY2028","FY2029","FY2030"},0),50,100,150,150,150), Scenarios!C20))*Scenarios!F20,0)) | E88: =C88+D88 | F88: =VLOOKUP(B88,YearMap!$A$2:$B$6,2,FALSE) | G88: =VLOOKUP(B88,YearMap!$A$2:$C$6,3,FALSE) | H88: =VLOOKUP(B88,YearMap!$A$2:$D$6,4,FALSE) | I88: =1-BaselineCalc!$B$5 | J88: =Scenarios!G20 | K88: =(G88+H88+F88*E88)*I88*(1-J88) | L88: =IF(E88>0, K88/E88, NA()) | M88: =A88&"|"&B88
A89: =Scenarios!A20 | B89: FY2028 | C89: =IF(Scenarios!D20=1,0, BaselineCalc!$B$7 + ROUND((=IF(ISNUMBER(SEARCH("Ramp",A89)), CHOOSE(MATCH(B89,{"FY2026","FY2027","FY2028","FY2029","FY2030"},0),50,100,150,150,150), Scenarios!C20))*Scenarios!F20,0)) | D89: =IF(Scenarios!E20=1,0, BaselineCalc!$B$8 + (=IF(ISNUMBER(SEARCH("Ramp",A89)), CHOOSE(MATCH(B89,{"FY2026","FY2027","FY2028","FY2029","FY2030"},0),50,100,150,150,150), Scenarios!C20)) - ROUND((=IF(ISNUMBER(SEARCH("Ramp",A89)), CHOOSE(MATCH(B89,{"FY2026","FY2027","FY2028","FY2029","FY2030"},0),50,100,150,150,150), Scenarios!C20))*Scenarios!F20,0)) | E89: =C89+D89 | F89: =VLOOKUP(B89,YearMap!$A$2:$B$6,2,FALSE) | G89: =VLOOKUP(B89,YearMap!$A$2:$C$6,3,FALSE) | H89: =VLOOKUP(B89,YearMap!$A$2:$D$6,4,FALSE) | I89: =1-BaselineCalc!$B$5 | J89: =Scenarios!G20 | K89: =(G89+H89+F89*E89)*I89*(1-J89) | L89: =IF(E89>0, K89/E89, NA()) | M89: =A89&"|"&B89
A90: =Scenarios!A20 | B90: FY2029 | C90: =IF(Scenarios!D20=1,0, BaselineCalc!$B$7 + ROUND((=IF(ISNUMBER(SEARCH("Ramp",A90)), CHOOSE(MATCH(B90,{"FY2026","FY2027","FY2028","FY2029","FY2030"},0),50,100,150,150,150), Scenarios!C20))*Scenarios!F20,0)) | D90: =IF(Scenarios!E20=1,0, BaselineCalc!$B$8 + (=IF(ISNUMBER(SEARCH("Ramp",A90)), CHOOSE(MATCH(B90,{"FY2026","FY2027","FY2028","FY2029","FY2030"},0),50,100,150,150,150), Scenarios!C20)) - ROUND((=IF(ISNUMBER(SEARCH("Ramp",A90)), CHOOSE(MATCH(B90,{"FY2026","FY2027","FY2028","FY2029","FY2030"},0),50,100,150,150,150), Scenarios!C20))*Scenarios!F20,0)) | E90: =C90+D90 | F90: =VLOOKUP(B90,YearMap!$A$2:$B$6,2,FALSE) | G90: =VLOOKUP(B90,YearMap!$A$2:$C$6,3,FALSE) | H90: =VLOOKUP(B90,YearMap!$A$2:$D$6,4,FALSE) | I90: =1-BaselineCalc!$B$5 | J90: =Scenarios!G20 | K90: =(G90+H90+F90*E90)*I90*(1-J90) | L90: =IF(E90>0, K90/E90, NA()) | M90: =A90&"|"&B90
A91: =Scenarios!A20 | B91: FY2030 | C91: =IF(Scenarios!D20=1,0, BaselineCalc!$B$7 + ROUND((=IF(ISNUMBER(SEARCH("Ramp",A91)), CHOOSE(MATCH(B91,{"FY2026","FY2027","FY2028","FY2029","FY2030"},0),50,100,150,150,150), Scenarios!C20))*Scenarios!F20,0)) | D91: =IF(Scenarios!E20=1,0, BaselineCalc!$B$8 + (=IF(ISNUMBER(SEARCH("Ramp",A91)), CHOOSE(MATCH(B91,{"FY2026","FY2027","FY2028","FY2029","FY2030"},0),50,100,150,150,150), Scenarios!C20)) - ROUND((=IF(ISNUMBER(SEARCH("Ramp",A91)), CHOOSE(MATCH(B91,{"FY2026","FY2027","FY2028","FY2029","FY2030"},0),50,100,150,150,150), Scenarios!C20))*Scenarios!F20,0)) | E91: =C91+D91 | F91: =VLOOKUP(B91,YearMap!$A$2:$B$6,2,FALSE) | G91: =VLOOKUP(B91,YearMap!$A$2:$C$6,3,FALSE) | H91: =VLOOKUP(B91,YearMap!$A$2:$D$6,4,FALSE) | I91: =1-BaselineCalc!$B$5 | J91: =Scenarios!G20 | K91: =(G91+H91+F91*E91)*I91*(1-J91) | L91: =IF(E91>0, K91/E91, NA()) | M91: =A91&"|"&B91
A92: =Scenarios!A21 | B92: FY2026 | C92: =IF(Scenarios!D21=1,0, BaselineCalc!$B$7 + ROUND((=IF(ISNUMBER(SEARCH("Ramp",A92)), CHOOSE(MATCH(B92,{"FY2026","FY2027","FY2028","FY2029","FY2030"},0),50,100,150,150,150), Scenarios!C21))*Scenarios!F21,0)) | D92: =IF(Scenarios!E21=1,0, BaselineCalc!$B$8 + (=IF(ISNUMBER(SEARCH("Ramp",A92)), CHOOSE(MATCH(B92,{"FY2026","FY2027","FY2028","FY2029","FY2030"},0),50,100,150,150,150), Scenarios!C21)) - ROUND((=IF(ISNUMBER(SEARCH("Ramp",A92)), CHOOSE(MATCH(B92,{"FY2026","FY2027","FY2028","FY2029","FY2030"},0),50,100,150,150,150), Scenarios!C21))*Scenarios!F21,0)) | E92: =C92+D92 | F92: =VLOOKUP(B92,YearMap!$A$2:$B$6,2,FALSE) | G92: =VLOOKUP(B92,YearMap!$A$2:$C$6,3,FALSE) | H92: =VLOOKUP(B92,YearMap!$A$2:$D$6,4,FALSE) | I92: =1-BaselineCalc!$B$5 | J92: =Scenarios!G21 | K92: =(G92+H92+F92*E92)*I92*(1-J92) | L92: =IF(E92>0, K92/E92, NA()) | M92: =A92&"|"&B92
A93: =Scenarios!A21 | B93: FY2027 | C93: =IF(Scenarios!D21=1,0, BaselineCalc!$B$7 + ROUND((=IF(ISNUMBER(SEARCH("Ramp",A93)), CHOOSE(MATCH(B93,{"FY2026","FY2027","FY2028","FY2029","FY2030"},0),50,100,150,150,150), Scenarios!C21))*Scenarios!F21,0)) | D93: =IF(Scenarios!E21=1,0, BaselineCalc!$B$8 + (=IF(ISNUMBER(SEARCH("Ramp",A93)), CHOOSE(MATCH(B93,{"FY2026","FY2027","FY2028","FY2029","FY2030"},0),50,100,150,150,150), Scenarios!C21)) - ROUND((=IF(ISNUMBER(SEARCH("Ramp",A93)), CHOOSE(MATCH(B93,{"FY2026","FY2027","FY2028","FY2029","FY2030"},0),50,100,150,150,150), Scenarios!C21))*Scenarios!F21,0)) | E93: =C93+D93 | F93: =VLOOKUP(B93,YearMap!$A$2:$B$6,2,FALSE) | G93: =VLOOKUP(B93,YearMap!$A$2:$C$6,3,FALSE) | H93: =VLOOKUP(B93,YearMap!$A$2:$D$6,4,FALSE) | I93: =1-BaselineCalc!$B$5 | J93: =Scenarios!G21 | K93: =(G93+H93+F93*E93)*I93*(1-J93) | L93: =IF(E93>0, K93/E93, NA()) | M93: =A93&"|"&B93
A94: =Scenarios!A21 | B94: FY2028 | C94: =IF(Scenarios!D21=1,0, BaselineCalc!$B$7 + ROUND((=IF(ISNUMBER(SEARCH("Ramp",A94)), CHOOSE(MATCH(B94,{"FY2026","FY2027","FY2028","FY2029","FY2030"},0),50,100,150,150,150), Scenarios!C21))*Scenarios!F21,0)) | D94: =IF(Scenarios!E21=1,0, BaselineCalc!$B$8 + (=IF(ISNUMBER(SEARCH("Ramp",A94)), CHOOSE(MATCH(B94,{"FY2026","FY2027","FY2028","FY2029","FY2030"},0),50,100,150,150,150), Scenarios!C21)) - ROUND((=IF(ISNUMBER(SEARCH("Ramp",A94)), CHOOSE(MATCH(B94,{"FY2026","FY2027","FY2028","FY2029","FY2030"},0),50,100,150,150,150), Scenarios!C21))*Scenarios!F21,0)) | E94: =C94+D94 | F94: =VLOOKUP(B94,YearMap!$A$2:$B$6,2,FALSE) | G94: =VLOOKUP(B94,YearMap!$A$2:$C$6,3,FALSE) | H94: =VLOOKUP(B94,YearMap!$A$2:$D$6,4,FALSE) | I94: =1-BaselineCalc!$B$5 | J94: =Scenarios!G21 | K94: =(G94+H94+F94*E94)*I94*(1-J94) | L94: =IF(E94>0, K94/E94, NA()) | M94: =A94&"|"&B94
A95: =Scenarios!A21 | B95: FY2029 | C95: =IF(Scenarios!D21=1,0, BaselineCalc!$B$7 + ROUND((=IF(ISNUMBER(SEARCH("Ramp",A95)), CHOOSE(MATCH(B95,{"FY2026","FY2027","FY2028","FY2029","FY2030"},0),50,100,150,150,150), Scenarios!C21))*Scenarios!F21,0)) | D95: =IF(Scenarios!E21=1,0, BaselineCalc!$B$8 + (=IF(ISNUMBER(SEARCH("Ramp",A95)), CHOOSE(MATCH(B95,{"FY2026","FY2027","FY2028","FY2029","FY2030"},0),50,100,150,150,150), Scenarios!C21)) - ROUND((=IF(ISNUMBER(SEARCH("Ramp",A95)), CHOOSE(MATCH(B95,{"FY2026","FY2027","FY2028","FY2029","FY2030"},0),50,100,150,150,150), Scenarios!C21))*Scenarios!F21,0)) | E95: =C95+D95 | F95: =VLOOKUP(B95,YearMap!$A$2:$B$6,2,FALSE) | G95: =VLOOKUP(B95,YearMap!$A$2:$C$6,3,FALSE) | H95: =VLOOKUP(B95,YearMap!$A$2:$D$6,4,FALSE) | I95: =1-BaselineCalc!$B$5 | J95: =Scenarios!G21 | K95: =(G95+H95+F95*E95)*I95*(1-J95) | L95: =IF(E95>0, K95/E95, NA()) | M95: =A95&"|"&B95
A96: =Scenarios!A21 | B96: FY2030 | C96: =IF(Scenarios!D21=1,0, BaselineCalc!$B$7 + ROUND((=IF(ISNUMBER(SEARCH("Ramp",A96)), CHOOSE(MATCH(B96,{"FY2026","FY2027","FY2028","FY2029","FY2030"},0),50,100,150,150,150), Scenarios!C21))*Scenarios!F21,0)) | D96: =IF(Scenarios!E21=1,0, BaselineCalc!$B$8 + (=IF(ISNUMBER(SEARCH("Ramp",A96)), CHOOSE(MATCH(B96,{"FY2026","FY2027","FY2028","FY2029","FY2030"},0),50,100,150,150,150), Scenarios!C21)) - ROUND((=IF(ISNUMBER(SEARCH("Ramp",A96)), CHOOSE(MATCH(B96,{"FY2026","FY2027","FY2028","FY2029","FY2030"},0),50,100,150,150,150), Scenarios!C21))*Scenarios!F21,0)) | E96: =C96+D96 | F96: =VLOOKUP(B96,YearMap!$A$2:$B$6,2,FALSE) | G96: =VLOOKUP(B96,YearMap!$A$2:$C$6,3,FALSE) | H96: =VLOOKUP(B96,YearMap!$A$2:$D$6,4,FALSE) | I96: =1-BaselineCalc!$B$5 | J96: =Scenarios!G21 | K96: =(G96+H96+F96*E96)*I96*(1-J96) | L96: =IF(E96>0, K96/E96, NA()) | M96: =A96&"|"&B96
A97: =Scenarios!A22 | B97: FY2026 | C97: =IF(Scenarios!D22=1,0, BaselineCalc!$B$7 + ROUND((=IF(ISNUMBER(SEARCH("Ramp",A97)), CHOOSE(MATCH(B97,{"FY2026","FY2027","FY2028","FY2029","FY2030"},0),50,100,150,150,150), Scenarios!C22))*Scenarios!F22,0)) | D97: =IF(Scenarios!E22=1,0, BaselineCalc!$B$8 + (=IF(ISNUMBER(SEARCH("Ramp",A97)), CHOOSE(MATCH(B97,{"FY2026","FY2027","FY2028","FY2029","FY2030"},0),50,100,150,150,150), Scenarios!C22)) - ROUND((=IF(ISNUMBER(SEARCH("Ramp",A97)), CHOOSE(MATCH(B97,{"FY2026","FY2027","FY2028","FY2029","FY2030"},0),50,100,150,150,150), Scenarios!C22))*Scenarios!F22,0)) | E97: =C97+D97 | F97: =VLOOKUP(B97,YearMap!$A$2:$B$6,2,FALSE) | G97: =VLOOKUP(B97,YearMap!$A$2:$C$6,3,FALSE) | H97: =VLOOKUP(B97,YearMap!$A$2:$D$6,4,FALSE) | I97: =1-BaselineCalc!$B$5 | J97: =Scenarios!G22 | K97: =(G97+H97+F97*E97)*I97*(1-J97) | L97: =IF(E97>0, K97/E97, NA()) | M97: =A97&"|"&B97
A98: =Scenarios!A22 | B98: FY2027 | C98: =IF(Scenarios!D22=1,0, BaselineCalc!$B$7 + ROUND((=IF(ISNUMBER(SEARCH("Ramp",A98)), CHOOSE(MATCH(B98,{"FY2026","FY2027","FY2028","FY2029","FY2030"},0),50,100,150,150,150), Scenarios!C22))*Scenarios!F22,0)) | D98: =IF(Scenarios!E22=1,0, BaselineCalc!$B$8 + (=IF(ISNUMBER(SEARCH("Ramp",A98)), CHOOSE(MATCH(B98,{"FY2026","FY2027","FY2028","FY2029","FY2030"},0),50,100,150,150,150), Scenarios!C22)) - ROUND((=IF(ISNUMBER(SEARCH("Ramp",A98)), CHOOSE(MATCH(B98,{"FY2026","FY2027","FY2028","FY2029","FY2030"},0),50,100,150,150,150), Scenarios!C22))*Scenarios!F22,0)) | E98: =C98+D98 | F98: =VLOOKUP(B98,YearMap!$A$2:$B$6,2,FALSE) | G98: =VLOOKUP(B98,YearMap!$A$2:$C$6,3,FALSE) | H98: =VLOOKUP(B98,YearMap!$A$2:$D$6,4,FALSE) | I98: =1-BaselineCalc!$B$5 | J98: =Scenarios!G22 | K98: =(G98+H98+F98*E98)*I98*(1-J98) | L98: =IF(E98>0, K98/E98, NA()) | M98: =A98&"|"&B98
A99: =Scenarios!A22 | B99: FY2028 | C99: =IF(Scenarios!D22=1,0, BaselineCalc!$B$7 + ROUND((=IF(ISNUMBER(SEARCH("Ramp",A99)), CHOOSE(MATCH(B99,{"FY2026","FY2027","FY2028","FY2029","FY2030"},0),50,100,150,150,150), Scenarios!C22))*Scenarios!F22,0)) | D99: =IF(Scenarios!E22=1,0, BaselineCalc!$B$8 + (=IF(ISNUMBER(SEARCH("Ramp",A99)), CHOOSE(MATCH(B99,{"FY2026","FY2027","FY2028","FY2029","FY2030"},0),50,100,150,150,150), Scenarios!C22)) - ROUND((=IF(ISNUMBER(SEARCH("Ramp",A99)), CHOOSE(MATCH(B99,{"FY2026","FY2027","FY2028","FY2029","FY2030"},0),50,100,150,150,150), Scenarios!C22))*Scenarios!F22,0)) | E99: =C99+D99 | F99: =VLOOKUP(B99,YearMap!$A$2:$B$6,2,FALSE) | G99: =VLOOKUP(B99,YearMap!$A$2:$C$6,3,FALSE) | H99: =VLOOKUP(B99,YearMap!$A$2:$D$6,4,FALSE) | I99: =1-BaselineCalc!$B$5 | J99: =Scenarios!G22 | K99: =(G99+H99+F99*E99)*I99*(1-J99) | L99: =IF(E99>0, K99/E99, NA()) | M99: =A99&"|"&B99
A100: =Scenarios!A22 | B100: FY2029 | C100: =IF(Scenarios!D22=1,0, BaselineCalc!$B$7 + ROUND((=IF(ISNUMBER(SEARCH("Ramp",A100)), CHOOSE(MATCH(B100,{"FY2026","FY2027","FY2028","FY2029","FY2030"},0),50,100,150,150,150), Scenarios!C22))*Scenarios!F22,0)) | D100: =IF(Scenarios!E22=1,0, BaselineCalc!$B$8 + (=IF(ISNUMBER(SEARCH("Ramp",A100)), CHOOSE(MATCH(B100,{"FY2026","FY2027","FY2028","FY2029","FY2030"},0),50,100,150,150,150), Scenarios!C22)) - ROUND((=IF(ISNUMBER(SEARCH("Ramp",A100)), CHOOSE(MATCH(B100,{"FY2026","FY2027","FY2028","FY2029","FY2030"},0),50,100,150,150,150), Scenarios!C22))*Scenarios!F22,0)) | E100: =C100+D100 | F100: =VLOOKUP(B100,YearMap!$A$2:$B$6,2,FALSE) | G100: =VLOOKUP(B100,YearMap!$A$2:$C$6,3,FALSE) | H100: =VLOOKUP(B100,YearMap!$A$2:$D$6,4,FALSE) | I100: =1-BaselineCalc!$B$5 | J100: =Scenarios!G22 | K100: =(G100+H100+F100*E100)*I100*(1-J100) | L100: =IF(E100>0, K100/E100, NA()) | M100: =A100&"|"&B100
...

Sheet Summary_Costs
A1: ScenarioKey | B1: FY2028 MO/ADM | C1: FY2030 MO/ADM | D1: 3-yr Avg MO/ADM (FY26–FY28) | E1: 5-yr Avg MO/ADM (FY26–FY30)
A2: =Scenarios!A2 | B2: =INDEX(MultiYear_ProForma!$L$2:$L$111, MATCH( Scenarios!A2&"|FY2028", MultiYear_ProForma!$M$2:$M$111, 0)) | C2: =INDEX(MultiYear_ProForma!$L$2:$L$111, MATCH( Scenarios!A2&"|FY2030", MultiYear_ProForma!$M$2:$M$111, 0)) | D2: =AVERAGE(INDEX(MultiYear_ProForma!$L$2:$L$111, MATCH(Scenarios!A2&"|FY2026", MultiYear_ProForma!$M$2:$M$111, 0)),INDEX(MultiYear_ProForma!$L$2:$L$111, MATCH(Scenarios!A2&"|FY2027", MultiYear_ProForma!$M$2:$M$111, 0)),INDEX(MultiYear_ProForma!$L$2:$L$111, MATCH(Scenarios!A2&"|FY2028", MultiYear_ProForma!$M$2:$M$111, 0))) | E2: =AVERAGE(INDEX(MultiYear_ProForma!$L$2:$L$111, MATCH(Scenarios!A2&"|FY2026", MultiYear_ProForma!$M$2:$M$111, 0)),INDEX(MultiYear_ProForma!$L$2:$L$111, MATCH(Scenarios!A2&"|FY2027", MultiYear_ProForma!$M$2:$M$111, 0)),INDEX(MultiYear_ProForma!$L$2:$L$111, MATCH(Scenarios!A2&"|FY2028", MultiYear_ProForma!$M$2:$M$111, 0)),INDEX(MultiYear_ProForma!$L$2:$L$111, MATCH(Scenarios!A2&"|FY2029", MultiYear_ProForma!$M$2:$M$111, 0)),INDEX(MultiYear_ProForma!$L$2:$L$111, MATCH(Scenarios!A2&"|FY2030", MultiYear_ProForma!$M$2:$M$111, 0)))
A3: =Scenarios!A3 | B3: =INDEX(MultiYear_ProForma!$L$2:$L$111, MATCH( Scenarios!A3&"|FY2028", MultiYear_ProForma!$M$2:$M$111, 0)) | C3: =INDEX(MultiYear_ProForma!$L$2:$L$111, MATCH( Scenarios!A3&"|FY2030", MultiYear_ProForma!$M$2:$M$111, 0)) | D3: =AVERAGE(INDEX(MultiYear_ProForma!$L$2:$L$111, MATCH(Scenarios!A3&"|FY2026", MultiYear_ProForma!$M$2:$M$111, 0)),INDEX(MultiYear_ProForma!$L$2:$L$111, MATCH(Scenarios!A3&"|FY2027", MultiYear_ProForma!$M$2:$M$111, 0)),INDEX(MultiYear_ProForma!$L$2:$L$111, MATCH(Scenarios!A3&"|FY2028", MultiYear_ProForma!$M$2:$M$111, 0))) | E3: =AVERAGE(INDEX(MultiYear_ProForma!$L$2:$L$111, MATCH(Scenarios!A3&"|FY2026", MultiYear_ProForma!$M$2:$M$111, 0)),INDEX(MultiYear_ProForma!$L$2:$L$111, MATCH(Scenarios!A3&"|FY2027", MultiYear_ProForma!$M$2:$M$111, 0)),INDEX(MultiYear_ProForma!$L$2:$L$111, MATCH(Scenarios!A3&"|FY2028", MultiYear_ProForma!$M$2:$M$111, 0)),INDEX(MultiYear_ProForma!$L$2:$L$111, MATCH(Scenarios!A3&"|FY2029", MultiYear_ProForma!$M$2:$M$111, 0)),INDEX(MultiYear_ProForma!$L$2:$L$111, MATCH(Scenarios!A3&"|FY2030", MultiYear_ProForma!$M$2:$M$111, 0)))
A4: =Scenarios!A4 | B4: =INDEX(MultiYear_ProForma!$L$2:$L$111, MATCH( Scenarios!A4&"|FY2028", MultiYear_ProForma!$M$2:$M$111, 0)) | C4: =INDEX(MultiYear_ProForma!$L$2:$L$111, MATCH( Scenarios!A4&"|FY2030", MultiYear_ProForma!$M$2:$M$111, 0)) | D4: =AVERAGE(INDEX(MultiYear_ProForma!$L$2:$L$111, MATCH(Scenarios!A4&"|FY2026", MultiYear_ProForma!$M$2:$M$111, 0)),INDEX(MultiYear_ProForma!$L$2:$L$111, MATCH(Scenarios!A4&"|FY2027", MultiYear_ProForma!$M$2:$M$111, 0)),INDEX(MultiYear_ProForma!$L$2:$L$111, MATCH(Scenarios!A4&"|FY2028", MultiYear_ProForma!$M$2:$M$111, 0))) | E4: =AVERAGE(INDEX(MultiYear_ProForma!$L$2:$L$111, MATCH(Scenarios!A4&"|FY2026", MultiYear_ProForma!$M$2:$M$111, 0)),INDEX(MultiYear_ProForma!$L$2:$L$111, MATCH(Scenarios!A4&"|FY2027", MultiYear_ProForma!$M$2:$M$111, 0)),INDEX(MultiYear_ProForma!$L$2:$L$111, MATCH(Scenarios!A4&"|FY2028", MultiYear_ProForma!$M$2:$M$111, 0)),INDEX(MultiYear_ProForma!$L$2:$L$111, MATCH(Scenarios!A4&"|FY2029", MultiYear_ProForma!$M$2:$M$111, 0)),INDEX(MultiYear_ProForma!$L$2:$L$111, MATCH(Scenarios!A4&"|FY2030", MultiYear_ProForma!$M$2:$M$111, 0)))
A5: =Scenarios!A6 | B5: =INDEX(MultiYear_ProForma!$L$2:$L$111, MATCH( Scenarios!A6&"|FY2028", MultiYear_ProForma!$M$2:$M$111, 0)) | C5: =INDEX(MultiYear_ProForma!$L$2:$L$111, MATCH( Scenarios!A6&"|FY2030", MultiYear_ProForma!$M$2:$M$111, 0)) | D5: =AVERAGE(INDEX(MultiYear_ProForma!$L$2:$L$111, MATCH(Scenarios!A6&"|FY2026", MultiYear_ProForma!$M$2:$M$111, 0)),INDEX(MultiYear_ProForma!$L$2:$L$111, MATCH(Scenarios!A6&"|FY2027", MultiYear_ProForma!$M$2:$M$111, 0)),INDEX(MultiYear_ProForma!$L$2:$L$111, MATCH(Scenarios!A6&"|FY2028", MultiYear_ProForma!$M$2:$M$111, 0))) | E5: =AVERAGE(INDEX(MultiYear_ProForma!$L$2:$L$111, MATCH(Scenarios!A6&"|FY2026", MultiYear_ProForma!$M$2:$M$111, 0)),INDEX(MultiYear_ProForma!$L$2:$L$111, MATCH(Scenarios!A6&"|FY2027", MultiYear_ProForma!$M$2:$M$111, 0)),INDEX(MultiYear_ProForma!$L$2:$L$111, MATCH(Scenarios!A6&"|FY2028", MultiYear_ProForma!$M$2:$M$111, 0)),INDEX(MultiYear_ProForma!$L$2:$L$111, MATCH(Scenarios!A6&"|FY2029", MultiYear_ProForma!$M$2:$M$111, 0)),INDEX(MultiYear_ProForma!$L$2:$L$111, MATCH(Scenarios!A6&"|FY2030", MultiYear_ProForma!$M$2:$M$111, 0)))
A6: =Scenarios!A7 | B6: =INDEX(MultiYear_ProForma!$L$2:$L$111, MATCH( Scenarios!A7&"|FY2028", MultiYear_ProForma!$M$2:$M$111, 0)) | C6: =INDEX(MultiYear_ProForma!$L$2:$L$111, MATCH( Scenarios!A7&"|FY2030", MultiYear_ProForma!$M$2:$M$111, 0)) | D6: =AVERAGE(INDEX(MultiYear_ProForma!$L$2:$L$111, MATCH(Scenarios!A7&"|FY2026", MultiYear_ProForma!$M$2:$M$111, 0)),INDEX(MultiYear_ProForma!$L$2:$L$111, MATCH(Scenarios!A7&"|FY2027", MultiYear_ProForma!$M$2:$M$111, 0)),INDEX(MultiYear_ProForma!$L$2:$L$111, MATCH(Scenarios!A7&"|FY2028", MultiYear_ProForma!$M$2:$M$111, 0))) | E6: =AVERAGE(INDEX(MultiYear_ProForma!$L$2:$L$111, MATCH(Scenarios!A7&"|FY2026", MultiYear_ProForma!$M$2:$M$111, 0)),INDEX(MultiYear_ProForma!$L$2:$L$111, MATCH(Scenarios!A7&"|FY2027", MultiYear_ProForma!$M$2:$M$111, 0)),INDEX(MultiYear_ProForma!$L$2:$L$111, MATCH(Scenarios!A7&"|FY2028", MultiYear_ProForma!$M$2:$M$111, 0)),INDEX(MultiYear_ProForma!$L$2:$L$111, MATCH(Scenarios!A7&"|FY2029", MultiYear_ProForma!$M$2:$M$111, 0)),INDEX(MultiYear_ProForma!$L$2:$L$111, MATCH(Scenarios!A7&"|FY2030", MultiYear_ProForma!$M$2:$M$111, 0)))
A7: =Scenarios!A8 | B7: =INDEX(MultiYear_ProForma!$L$2:$L$111, MATCH( Scenarios!A8&"|FY2028", MultiYear_ProForma!$M$2:$M$111, 0)) | C7: =INDEX(MultiYear_ProForma!$L$2:$L$111, MATCH( Scenarios!A8&"|FY2030", MultiYear_ProForma!$M$2:$M$111, 0)) | D7: =AVERAGE(INDEX(MultiYear_ProForma!$L$2:$L$111, MATCH(Scenarios!A8&"|FY2026", MultiYear_ProForma!$M$2:$M$111, 0)),INDEX(MultiYear_ProForma!$L$2:$L$111, MATCH(Scenarios!A8&"|FY2027", MultiYear_ProForma!$M$2:$M$111, 0)),INDEX(MultiYear_ProForma!$L$2:$L$111, MATCH(Scenarios!A8&"|FY2028", MultiYear_ProForma!$M$2:$M$111, 0))) | E7: =AVERAGE(INDEX(MultiYear_ProForma!$L$2:$L$111, MATCH(Scenarios!A8&"|FY2026", MultiYear_ProForma!$M$2:$M$111, 0)),INDEX(MultiYear_ProForma!$L$2:$L$111, MATCH(Scenarios!A8&"|FY2027", MultiYear_ProForma!$M$2:$M$111, 0)),INDEX(MultiYear_ProForma!$L$2:$L$111, MATCH(Scenarios!A8&"|FY2028", MultiYear_ProForma!$M$2:$M$111, 0)),INDEX(MultiYear_ProForma!$L$2:$L$111, MATCH(Scenarios!A8&"|FY2029", MultiYear_ProForma!$M$2:$M$111, 0)),INDEX(MultiYear_ProForma!$L$2:$L$111, MATCH(Scenarios!A8&"|FY2030", MultiYear_ProForma!$M$2:$M$111, 0)))
A8: =Scenarios!A9 | B8: =INDEX(MultiYear_ProForma!$L$2:$L$111, MATCH( Scenarios!A9&"|FY2028", MultiYear_ProForma!$M$2:$M$111, 0)) | C8: =INDEX(MultiYear_ProForma!$L$2:$L$111, MATCH( Scenarios!A9&"|FY2030", MultiYear_ProForma!$M$2:$M$111, 0)) | D8: =AVERAGE(INDEX(MultiYear_ProForma!$L$2:$L$111, MATCH(Scenarios!A9&"|FY2026", MultiYear_ProForma!$M$2:$M$111, 0)),INDEX(MultiYear_ProForma!$L$2:$L$111, MATCH(Scenarios!A9&"|FY2027", MultiYear_ProForma!$M$2:$M$111, 0)),INDEX(MultiYear_ProForma!$L$2:$L$111, MATCH(Scenarios!A9&"|FY2028", MultiYear_ProForma!$M$2:$M$111, 0))) | E8: =AVERAGE(INDEX(MultiYear_ProForma!$L$2:$L$111, MATCH(Scenarios!A9&"|FY2026", MultiYear_ProForma!$M$2:$M$111, 0)),INDEX(MultiYear_ProForma!$L$2:$L$111, MATCH(Scenarios!A9&"|FY2027", MultiYear_ProForma!$M$2:$M$111, 0)),INDEX(MultiYear_ProForma!$L$2:$L$111, MATCH(Scenarios!A9&"|FY2028", MultiYear_ProForma!$M$2:$M$111, 0)),INDEX(MultiYear_ProForma!$L$2:$L$111, MATCH(Scenarios!A9&"|FY2029", MultiYear_ProForma!$M$2:$M$111, 0)),INDEX(MultiYear_ProForma!$L$2:$L$111, MATCH(Scenarios!A9&"|FY2030", MultiYear_ProForma!$M$2:$M$111, 0)))
A9: =Scenarios!A10 | B9: =INDEX(MultiYear_ProForma!$L$2:$L$111, MATCH( Scenarios!A10&"|FY2028", MultiYear_ProForma!$M$2:$M$111, 0)) | C9: =INDEX(MultiYear_ProForma!$L$2:$L$111, MATCH( Scenarios!A10&"|FY2030", MultiYear_ProForma!$M$2:$M$111, 0)) | D9: =AVERAGE(INDEX(MultiYear_ProForma!$L$2:$L$111, MATCH(Scenarios!A10&"|FY2026", MultiYear_ProForma!$M$2:$M$111, 0)),INDEX(MultiYear_ProForma!$L$2:$L$111, MATCH(Scenarios!A10&"|FY2027", MultiYear_ProForma!$M$2:$M$111, 0)),INDEX(MultiYear_ProForma!$L$2:$L$111, MATCH(Scenarios!A10&"|FY2028", MultiYear_ProForma!$M$2:$M$111, 0))) | E9: =AVERAGE(INDEX(MultiYear_ProForma!$L$2:$L$111, MATCH(Scenarios!A10&"|FY2026", MultiYear_ProForma!$M$2:$M$111, 0)),INDEX(MultiYear_ProForma!$L$2:$L$111, MATCH(Scenarios!A10&"|FY2027", MultiYear_ProForma!$M$2:$M$111, 0)),INDEX(MultiYear_ProForma!$L$2:$L$111, MATCH(Scenarios!A10&"|FY2028", MultiYear_ProForma!$M$2:$M$111, 0)),INDEX(MultiYear_ProForma!$L$2:$L$111, MATCH(Scenarios!A10&"|FY2029", MultiYear_ProForma!$M$2:$M$111, 0)),INDEX(MultiYear_ProForma!$L$2:$L$111, MATCH(Scenarios!A10&"|FY2030", MultiYear_ProForma!$M$2:$M$111, 0)))
A10: =Scenarios!A11 | B10: =INDEX(MultiYear_ProForma!$L$2:$L$111, MATCH( Scenarios!A11&"|FY2028", MultiYear_ProForma!$M$2:$M$111, 0)) | C10: =INDEX(MultiYear_ProForma!$L$2:$L$111, MATCH( Scenarios!A11&"|FY2030", MultiYear_ProForma!$M$2:$M$111, 0)) | D10: =AVERAGE(INDEX(MultiYear_ProForma!$L$2:$L$111, MATCH(Scenarios!A11&"|FY2026", MultiYear_ProForma!$M$2:$M$111, 0)),INDEX(MultiYear_ProForma!$L$2:$L$111, MATCH(Scenarios!A11&"|FY2027", MultiYear_ProForma!$M$2:$M$111, 0)),INDEX(MultiYear_ProForma!$L$2:$L$111, MATCH(Scenarios!A11&"|FY2028", MultiYear_ProForma!$M$2:$M$111, 0))) | E10: =AVERAGE(INDEX(MultiYear_ProForma!$L$2:$L$111, MATCH(Scenarios!A11&"|FY2026", MultiYear_ProForma!$M$2:$M$111, 0)),INDEX(MultiYear_ProForma!$L$2:$L$111, MATCH(Scenarios!A11&"|FY2027", MultiYear_ProForma!$M$2:$M$111, 0)),INDEX(MultiYear_ProForma!$L$2:$L$111, MATCH(Scenarios!A11&"|FY2028", MultiYear_ProForma!$M$2:$M$111, 0)),INDEX(MultiYear_ProForma!$L$2:$L$111, MATCH(Scenarios!A11&"|FY2029", MultiYear_ProForma!$M$2:$M$111, 0)),INDEX(MultiYear_ProForma!$L$2:$L$111, MATCH(Scenarios!A11&"|FY2030", MultiYear_ProForma!$M$2:$M$111, 0)))
A11: =Scenarios!A12 | B11: =INDEX(MultiYear_ProForma!$L$2:$L$111, MATCH( Scenarios!A12&"|FY2028", MultiYear_ProForma!$M$2:$M$111, 0)) | C11: =INDEX(MultiYear_ProForma!$L$2:$L$111, MATCH( Scenarios!A12&"|FY2030", MultiYear_ProForma!$M$2:$M$111, 0)) | D11: =AVERAGE(INDEX(MultiYear_ProForma!$L$2:$L$111, MATCH(Scenarios!A12&"|FY2026", MultiYear_ProForma!$M$2:$M$111, 0)),INDEX(MultiYear_ProForma!$L$2:$L$111, MATCH(Scenarios!A12&"|FY2027", MultiYear_ProForma!$M$2:$M$111, 0)),INDEX(MultiYear_ProForma!$L$2:$L$111, MATCH(Scenarios!A12&"|FY2028", MultiYear_ProForma!$M$2:$M$111, 0))) | E11: =AVERAGE(INDEX(MultiYear_ProForma!$L$2:$L$111, MATCH(Scenarios!A12&"|FY2026", MultiYear_ProForma!$M$2:$M$111, 0)),INDEX(MultiYear_ProForma!$L$2:$L$111, MATCH(Scenarios!A12&"|FY2027", MultiYear_ProForma!$M$2:$M$111, 0)),INDEX(MultiYear_ProForma!$L$2:$L$111, MATCH(Scenarios!A12&"|FY2028", MultiYear_ProForma!$M$2:$M$111, 0)),INDEX(MultiYear_ProForma!$L$2:$L$111, MATCH(Scenarios!A12&"|FY2029", MultiYear_ProForma!$M$2:$M$111, 0)),INDEX(MultiYear_ProForma!$L$2:$L$111, MATCH(Scenarios!A12&"|FY2030", MultiYear_ProForma!$M$2:$M$111, 0)))
A12: =Scenarios!A13 | B12: =INDEX(MultiYear_ProForma!$L$2:$L$111, MATCH( Scenarios!A13&"|FY2028", MultiYear_ProForma!$M$2:$M$111, 0)) | C12: =INDEX(MultiYear_ProForma!$L$2:$L$111, MATCH( Scenarios!A13&"|FY2030", MultiYear_ProForma!$M$2:$M$111, 0)) | D12: =AVERAGE(INDEX(MultiYear_ProForma!$L$2:$L$111, MATCH(Scenarios!A13&"|FY2026", MultiYear_ProForma!$M$2:$M$111, 0)),INDEX(MultiYear_ProForma!$L$2:$L$111, MATCH(Scenarios!A13&"|FY2027", MultiYear_ProForma!$M$2:$M$111, 0)),INDEX(MultiYear_ProForma!$L$2:$L$111, MATCH(Scenarios!A13&"|FY2028", MultiYear_ProForma!$M$2:$M$111, 0))) | E12: =AVERAGE(INDEX(MultiYear_ProForma!$L$2:$L$111, MATCH(Scenarios!A13&"|FY2026", MultiYear_ProForma!$M$2:$M$111, 0)),INDEX(MultiYear_ProForma!$L$2:$L$111, MATCH(Scenarios!A13&"|FY2027", MultiYear_ProForma!$M$2:$M$111, 0)),INDEX(MultiYear_ProForma!$L$2:$L$111, MATCH(Scenarios!A13&"|FY2028", MultiYear_ProForma!$M$2:$M$111, 0)),INDEX(MultiYear_ProForma!$L$2:$L$111, MATCH(Scenarios!A13&"|FY2029", MultiYear_ProForma!$M$2:$M$111, 0)),INDEX(MultiYear_ProForma!$L$2:$L$111, MATCH(Scenarios!A13&"|FY2030", MultiYear_ProForma!$M$2:$M$111, 0)))
A13: =Scenarios!A14 | B13: =INDEX(MultiYear_ProForma!$L$2:$L$111, MATCH( Scenarios!A14&"|FY2028", MultiYear_ProForma!$M$2:$M$111, 0)) | C13: =INDEX(MultiYear_ProForma!$L$2:$L$111, MATCH( Scenarios!A14&"|FY2030", MultiYear_ProForma!$M$2:$M$111, 0)) | D13: =AVERAGE(INDEX(MultiYear_ProForma!$L$2:$L$111, MATCH(Scenarios!A14&"|FY2026", MultiYear_ProForma!$M$2:$M$111, 0)),INDEX(MultiYear_ProForma!$L$2:$L$111, MATCH(Scenarios!A14&"|FY2027", MultiYear_ProForma!$M$2:$M$111, 0)),INDEX(MultiYear_ProForma!$L$2:$L$111, MATCH(Scenarios!A14&"|FY2028", MultiYear_ProForma!$M$2:$M$111, 0))) | E13: =AVERAGE(INDEX(MultiYear_ProForma!$L$2:$L$111, MATCH(Scenarios!A14&"|FY2026", MultiYear_ProForma!$M$2:$M$111, 0)),INDEX(MultiYear_ProForma!$L$2:$L$111, MATCH(Scenarios!A14&"|FY2027", MultiYear_ProForma!$M$2:$M$111, 0)),INDEX(MultiYear_ProForma!$L$2:$L$111, MATCH(Scenarios!A14&"|FY2028", MultiYear_ProForma!$M$2:$M$111, 0)),INDEX(MultiYear_ProForma!$L$2:$L$111, MATCH(Scenarios!A14&"|FY2029", MultiYear_ProForma!$M$2:$M$111, 0)),INDEX(MultiYear_ProForma!$L$2:$L$111, MATCH(Scenarios!A14&"|FY2030", MultiYear_ProForma!$M$2:$M$111, 0)))
A14: =Scenarios!A15 | B14: =INDEX(MultiYear_ProForma!$L$2:$L$111, MATCH( Scenarios!A15&"|FY2028", MultiYear_ProForma!$M$2:$M$111, 0)) | C14: =INDEX(MultiYear_ProForma!$L$2:$L$111, MATCH( Scenarios!A15&"|FY2030", MultiYear_ProForma!$M$2:$M$111, 0)) | D14: =AVERAGE(INDEX(MultiYear_ProForma!$L$2:$L$111, MATCH(Scenarios!A15&"|FY2026", MultiYear_ProForma!$M$2:$M$111, 0)),INDEX(MultiYear_ProForma!$L$2:$L$111, MATCH(Scenarios!A15&"|FY2027", MultiYear_ProForma!$M$2:$M$111, 0)),INDEX(MultiYear_ProForma!$L$2:$L$111, MATCH(Scenarios!A15&"|FY2028", MultiYear_ProForma!$M$2:$M$111, 0))) | E14: =AVERAGE(INDEX(MultiYear_ProForma!$L$2:$L$111, MATCH(Scenarios!A15&"|FY2026", MultiYear_ProForma!$M$2:$M$111, 0)),INDEX(MultiYear_ProForma!$L$2:$L$111, MATCH(Scenarios!A15&"|FY2027", MultiYear_ProForma!$M$2:$M$111, 0)),INDEX(MultiYear_ProForma!$L$2:$L$111, MATCH(Scenarios!A15&"|FY2028", MultiYear_ProForma!$M$2:$M$111, 0)),INDEX(MultiYear_ProForma!$L$2:$L$111, MATCH(Scenarios!A15&"|FY2029", MultiYear_ProForma!$M$2:$M$111, 0)),INDEX(MultiYear_ProForma!$L$2:$L$111, MATCH(Scenarios!A15&"|FY2030", MultiYear_ProForma!$M$2:$M$111, 0)))
A15: =Scenarios!A16 | B15: =INDEX(MultiYear_ProForma!$L$2:$L$111, MATCH( Scenarios!A16&"|FY2028", MultiYear_ProForma!$M$2:$M$111, 0)) | C15: =INDEX(MultiYear_ProForma!$L$2:$L$111, MATCH( Scenarios!A16&"|FY2030", MultiYear_ProForma!$M$2:$M$111, 0)) | D15: =AVERAGE(INDEX(MultiYear_ProForma!$L$2:$L$111, MATCH(Scenarios!A16&"|FY2026", MultiYear_ProForma!$M$2:$M$111, 0)),INDEX(MultiYear_ProForma!$L$2:$L$111, MATCH(Scenarios!A16&"|FY2027", MultiYear_ProForma!$M$2:$M$111, 0)),INDEX(MultiYear_ProForma!$L$2:$L$111, MATCH(Scenarios!A16&"|FY2028", MultiYear_ProForma!$M$2:$M$111, 0))) | E15: =AVERAGE(INDEX(MultiYear_ProForma!$L$2:$L$111, MATCH(Scenarios!A16&"|FY2026", MultiYear_ProForma!$M$2:$M$111, 0)),INDEX(MultiYear_ProForma!$L$2:$L$111, MATCH(Scenarios!A16&"|FY2027", MultiYear_ProForma!$M$2:$M$111, 0)),INDEX(MultiYear_ProForma!$L$2:$L$111, MATCH(Scenarios!A16&"|FY2028", MultiYear_ProForma!$M$2:$M$111, 0)),INDEX(MultiYear_ProForma!$L$2:$L$111, MATCH(Scenarios!A16&"|FY2029", MultiYear_ProForma!$M$2:$M$111, 0)),INDEX(MultiYear_ProForma!$L$2:$L$111, MATCH(Scenarios!A16&"|FY2030", MultiYear_ProForma!$M$2:$M$111, 0)))
A16: =Scenarios!A17 | B16: =INDEX(MultiYear_ProForma!$L$2:$L$111, MATCH( Scenarios!A17&"|FY2028", MultiYear_ProForma!$M$2:$M$111, 0)) | C16: =INDEX(MultiYear_ProForma!$L$2:$L$111, MATCH( Scenarios!A17&"|FY2030", MultiYear_ProForma!$M$2:$M$111, 0)) | D16: =AVERAGE(INDEX(MultiYear_ProForma!$L$2:$L$111, MATCH(Scenarios!A17&"|FY2026", MultiYear_ProForma!$M$2:$M$111, 0)),INDEX(MultiYear_ProForma!$L$2:$L$111, MATCH(Scenarios!A17&"|FY2027", MultiYear_ProForma!$M$2:$M$111, 0)),INDEX(MultiYear_ProForma!$L$2:$L$111, MATCH(Scenarios!A17&"|FY2028", MultiYear_ProForma!$M$2:$M$111, 0))) | E16: =AVERAGE(INDEX(MultiYear_ProForma!$L$2:$L$111, MATCH(Scenarios!A17&"|FY2026", MultiYear_ProForma!$M$2:$M$111, 0)),INDEX(MultiYear_ProForma!$L$2:$L$111, MATCH(Scenarios!A17&"|FY2027", MultiYear_ProForma!$M$2:$M$111, 0)),INDEX(MultiYear_ProForma!$L$2:$L$111, MATCH(Scenarios!A17&"|FY2028", MultiYear_ProForma!$M$2:$M$111, 0)),INDEX(MultiYear_ProForma!$L$2:$L$111, MATCH(Scenarios!A17&"|FY2029", MultiYear_ProForma!$M$2:$M$111, 0)),INDEX(MultiYear_ProForma!$L$2:$L$111, MATCH(Scenarios!A17&"|FY2030", MultiYear_ProForma!$M$2:$M$111, 0)))
... A23: =Scenarios!A24 | B23: =INDEX(MultiYear_ProForma!$L$2:$L$111, MATCH( Scenarios!A24&"|FY2028", MultiYear_ProForma!$M$2:$M$111, 0)) | C23: =INDEX(MultiYear_ProForma!$L$2:$L$111, MATCH( Scenarios!A24&"|FY2030", MultiYear_ProForma!$M$2:$M$111, 0)) | D23: =AVERAGE(INDEX(MultiYear_ProForma!$L$2:$L$111, MATCH(Scenarios!A24&"|FY2026", MultiYear_ProForma!$M$2:$M$111, 0)),INDEX(MultiYear_ProForma!$L$2:$L$111, MATCH(Scenarios!A24&"|FY2027", MultiYear_ProForma!$M$2:$M$111, 0)),INDEX(MultiYear_ProForma!$L$2:$L$111, MATCH(Scenarios!A24&"|FY2028", MultiYear_ProForma!$M$2:$M$111, 0))) | E23: =AVERAGE(INDEX(MultiYear_ProForma!$L$2:$L$111, MATCH(Scenarios!A24&"|FY2026", MultiYear_ProForma!$M$2:$M$111, 0)),INDEX(MultiYear_ProForma!$L$2:$L$111, MATCH(Scenarios!A24&"|FY2027", MultiYear_ProForma!$M$2:$M$111, 0)),INDEX(MultiYear_ProForma!$L$2:$L$111, MATCH(Scenarios!A24&"|FY2028", MultiYear_ProForma!$M$2:$M$111, 0)),INDEX(MultiYear_ProForma!$L$2:$L$111, MATCH(Scenarios!A24&"|FY2029", MultiYear_ProForma!$M$2:$M$111, 0)),INDEX(MultiYear_ProForma!$L$2:$L$111, MATCH(Scenarios!A24&"|FY2030", MultiYear_ProForma!$M$2:$M$111, 0)))
