Workbook
Name ADM_Day_Select: Parameters_Public!C8
Name Aid_growth: BaselineCalc!B28
Name Base_Aid_per_ADM: Parameters_Public!C18
Name BaseAid_per_ADM: Parameters_Public!C18
Name Capex_ArtsHub: Parameters_Public!C28
Name Capex_in_MO_Toggle: Parameters_Public!C30
Name Capex_InnovHub: Parameters_Public!C29
Name Echo_ADM0: Parameters_Public!C10
Name Echo_ADM0_selected: Parameters_Public!C10
Name Echo_retention_r: Parameters_Public!C23
Name EchoFixed_FY25_Total: Site_Fixed!C8
Name f_lease_profile: Control_Center!$D$23:$H$23
Name f_ops_profile: Control_Center!$D$22:$H$22
Name Growth_overhead_alpha: Parameters_Public!C47
Name h_taper_profile: Control_Center!$C$22:$G$26
Name Incremental_uplift_alpha: Parameters_Public!C49
Name M_O_per_ADM_Audited: Parameters_Public!C14
Name MarginalFactor_for_Overlay: Parameters_Public!C43
Name MO_inflation: Control_Center!C6
Name Override_per_ADM_proxy: Parameters_Public!C19
Name Override_percent: Parameters_Public!C17
Name Override_toggle: Parameters_Public!C20
Name Pima_ADM0: Parameters_Public!C11
Name Pima_ADM0_selected: Parameters_Public!C11
Name Pima_retention_r: Parameters_Public!C24
Name PimaFixed_FY25_Total: Site_Fixed!C15
Name Portable_seat_cost: Parameters_Public!C34
Name TI_in_MO_Toggle: Parameters_Public!C26
Name TI_per_Site: Parameters_Public!C27
Name Uplift_base_per_ADM: Parameters_Public!C21

Sheet Workbook_Purpose_Overview

Sheet How_To_Use_The_Workbook
B1: How to use the workbook
B2: Start on Scenario_Comparison: choose two scenarios to compare; review the operational, capital, and student-related results.
B3: Test assumptions (override switch, retention r, trend flags) only if you would like to check sensitivity.
B4: Check capacity gates (receiving bands).
B5: Open Budget_Neutral_Calculator if you’re considering a non‑repurpose plan: it shows N⁰—how many students are needed to be Net ≥ 0.
B6: Look at Summary_Figures to scan all scenarios with the same signals.
B7: Use Inputs_Definitions_Sources for terms, references, and what’s still awaiting audited paste.
B8: Check What_Is_$900K_Savings if you are curious xxxxxx

Sheet Dashboard
B1: Go-forward scenario summary view* | C1: *SUSD-sourced data used wherever possible. Sources and assumptions are noted in Inputs_Definitions_Sources
B2: Choose view >> | C2: 2030
J3: SUMMARY (Selected View) | N3: INTUITION (quick read)
B4: ="FY"&IF(C2=2026, "26", IF(C2=2030, "30", "Average 2026-2030"))&" simulated P&L and capital spend by scenario" | C4: A2 | D4: B2 | E4: C2 | F4: D1 | G4: E1 | J4: Operating Net | K4: =C33 | L4: =D33 | N4: B2<C2 in FY26: Echo r lower → fewer served; h applies.
C5: Scenario A (Repurpose Both Lease) | D5: Scenario B (Repurpose Echo Lease; Grow Pima) | E5: Scenario C (Repurpose Pima Lease; Grow Echo) | F5: Scenario D (Grow Both) | G5: Scenario E (Continued Decline) | H5: Source / Confidence Level | I5: Model sensitivity | J5: Revenue | K5: =C14 | L5: =D14 | N5: Grow Both FY26 negative: Yr‑1 deficit + small overlay; improves by FY30.
B6: Baseline ADM Echo | C6: =IF($C$2=2026,C$67,IF($C$2=2030,C$103,C$67)) | D6: =IF($C$2=2026,D$67,IF($C$2=2030,D$103,D$67)) | E6: =IF($C$2=2026,E$67,IF($C$2=2030,E$103,E$67)) | F6: =IF($C$2=2026,F$67,IF($C$2=2030,F$103,F$67)) | G6: =IF($C$2=2026,G$67,IF($C$2=2030,G$103,G$67)) | H6: *** | J6: Variable M&O + h | K6: =C28 | L6: =D28
B7: Baseline ADM Pima | C7: =IF($C$2=2026,C$68,IF($C$2=2030,C$104,C$68)) | D7: =IF($C$2=2026,D$68,IF($C$2=2030,D$104,D$68)) | E7: =IF($C$2=2026,E$68,IF($C$2=2030,E$104,E$68)) | F7: =IF($C$2=2026,F$68,IF($C$2=2030,F$104,F$68)) | G7: =IF($C$2=2026,G$68,IF($C$2=2030,G$104,G$68)) | J7: Fixed M&O (net) | K7: =C31 | L7: =D31
B8: ADM change FY26 | C8: =IF($C$2=2026,C$69,IF($C$2=2030,C$105,C$69)) | D8: =IF($C$2=2026,D$69,IF($C$2=2030,D$105,D$69)) | E8: =IF($C$2=2026,E$69,IF($C$2=2030,E$105,E$69)) | F8: =IF($C$2=2026,F$69,IF($C$2=2030,F$105,F$69)) | G8: =IF($C$2=2026,G$69,IF($C$2=2030,G$105,G$69)) | J8: One-time Capital (FY26) | K8: =C36 | L8: =D36
B9: Echo retention ratio | C9: =IF($C$2=2026,C$70,IF($C$2=2030,C$106,C$70)) | D9: =IF($C$2=2026,D$70,IF($C$2=2030,D$106,D$70)) | E9: =IF($C$2=2026,E$70,IF($C$2=2030,E$106,E$70)) | F9: =IF($C$2=2026,F$70,IF($C$2=2030,F$106,F$70)) | G9: =IF($C$2=2026,G$70,IF($C$2=2030,G$106,G$70)) | H9: *
B10: Pima retention ratio | C10: =IF($C$2=2026,C$71,IF($C$2=2030,C$107,C$71)) | D10: =IF($C$2=2026,D$71,IF($C$2=2030,D$107,D$71)) | E10: =IF($C$2=2026,E$71,IF($C$2=2030,E$107,E$71)) | F10: =IF($C$2=2026,F$71,IF($C$2=2030,F$107,F$71)) | G10: =IF($C$2=2026,G$71,IF($C$2=2030,G$107,G$71)) | H10: **
B11: Number of students transitioning | C11: =IF($C$2=2026,C$72,IF($C$2=2030,C$108,C$72)) | D11: =IF($C$2=2026,D$72,IF($C$2=2030,D$108,D$72)) | E11: =IF($C$2=2026,E$72,IF($C$2=2030,E$108,E$72)) | F11: =IF($C$2=2026,F$72,IF($C$2=2030,F$108,F$72)) | G11: =IF($C$2=2026,G$72,IF($C$2=2030,G$108,G$72))
B12: Students served FY26 | C12: =IF($C$2=2026,C$73,IF($C$2=2030,C$109,C$73)) | D12: =IF($C$2=2026,D$73,IF($C$2=2030,D$109,D$73)) | E12: =IF($C$2=2026,E$73,IF($C$2=2030,E$109,E$73)) | F12: =IF($C$2=2026,F$73,IF($C$2=2030,F$109,F$73)) | G12: =IF($C$2=2026,G$73,IF($C$2=2030,G$109,G$73)) | J12: Sensitivity (Δ Net FY2030)
B13: Revenue per served student ($/ADM) | C13: =IF($C$2=2026,C$74,IF($C$2=2030,C$110,"")) | D13: =IF($C$2=2026,D$74,IF($C$2=2030,D$110,"")) | E13: =IF($C$2=2026,E$74,IF($C$2=2030,E$110,"")) | F13: =IF($C$2=2026,F$74,IF($C$2=2030,F$110,"")) | G13: =IF($C$2=2026,G$74,IF($C$2=2030,G$110,"")) | J13: Site‑Fixed ±$100k/site
B14: Total 'revenue' | C14: =IF($C$2=2026,C$75,IF($C$2=2030,C$111,C$75)) | D14: =IF($C$2=2026,D$75,IF($C$2=2030,D$111,D$75)) | E14: =IF($C$2=2026,E$75,IF($C$2=2030,E$111,E$75)) | F14: =IF($C$2=2026,F$75,IF($C$2=2030,F$111,F$75)) | G14: =IF($C$2=2026,G$75,IF($C$2=2030,G$111,G$75)) | J14: f_ops / f_lease ±0.05
B15: Districtwide gross Maint & Operations cost per non-new ADM | C15: =IF($C$2=2026,C$76,IF($C$2=2030,C$112,C$76)) | D15: =IF($C$2=2026,D$76,IF($C$2=2030,D$112,D$76)) | E15: =IF($C$2=2026,E$76,IF($C$2=2030,E$112,E$76)) | F15: =IF($C$2=2026,F$76,IF($C$2=2030,F$112,F$76)) | G15: =IF($C$2=2026,G$76,IF($C$2=2030,G$112,G$76)) | J15: Retention r ±10 pp
B16: Variable M&O per non-new student ($/ADM) | C16: =IF($C$2=2026,C$77,IF($C$2=2030,C$113,"")) | D16: =IF($C$2=2026,D$77,IF($C$2=2030,D$113,"")) | E16: =IF($C$2=2026,E$77,IF($C$2=2030,E$113,"")) | F16: =IF($C$2=2026,F$77,IF($C$2=2030,F$113,"")) | G16: =IF($C$2=2026,G$77,IF($C$2=2030,G$113,"")) | J16: MFO {0.5, 0.6, 0.8}
B17: Non-new students | C17: =IF($C$2=2026,C$78,IF($C$2=2030,C$114,C$78)) | D17: =IF($C$2=2026,D$78,IF($C$2=2030,D$114,D$78)) | E17: =IF($C$2=2026,E$78,IF($C$2=2030,E$114,E$78)) | F17: =IF($C$2=2026,F$78,IF($C$2=2030,F$114,F$78)) | G17: =IF($C$2=2026,G$78,IF($C$2=2030,G$114,G$78)) | J17: Uplift ±10%
B18: Total variable gross cost of non-new students | C18: =IF($C$2=2026,C$79,IF($C$2=2030,C$115,C$79)) | D18: =IF($C$2=2026,D$79,IF($C$2=2030,D$115,D$79)) | E18: =IF($C$2=2026,E$79,IF($C$2=2030,E$115,E$79)) | F18: =IF($C$2=2026,F$79,IF($C$2=2030,F$115,F$79)) | G18: =IF($C$2=2026,G$79,IF($C$2=2030,G$115,G$79)) | J18: After discounting estimated fixed, adjusting for inflation
B19: New students | C19: =IF($C$2=2026,C$80,IF($C$2=2030,C$116,C$80)) | D19: =IF($C$2=2026,D$80,IF($C$2=2030,D$116,D$80)) | E19: =IF($C$2=2026,E$80,IF($C$2=2030,E$116,E$80)) | F19: =IF($C$2=2026,F$80,IF($C$2=2030,F$116,F$80)) | G19: =IF($C$2=2026,G$80,IF($C$2=2030,G$116,G$80))
B20: Marginal variable cost to add new students | C20: =IF($C$2=2026,C$81,IF($C$2=2030,C$117,C$81)) | D20: =IF($C$2=2026,D$81,IF($C$2=2030,D$117,D$81)) | E20: =IF($C$2=2026,E$81,IF($C$2=2030,E$117,E$81)) | F20: =IF($C$2=2026,F$81,IF($C$2=2030,F$117,F$81)) | G20: =IF($C$2=2026,G$81,IF($C$2=2030,G$117,G$81)) | H20: ** | J20: Estimated proportion of full cost
B21: Variable gross M&O / new student | C21: =IF($C$2=2026,C$82,IF($C$2=2030,C$118,C$82)) | D21: =IF($C$2=2026,D$82,IF($C$2=2030,D$118,D$82)) | E21: =IF($C$2=2026,E$82,IF($C$2=2030,E$118,E$82)) | F21: =IF($C$2=2026,F$82,IF($C$2=2030,F$118,F$82)) | G21: =IF($C$2=2026,G$82,IF($C$2=2030,G$118,G$82)) | J21: M&O = Maintenance & Operations cost
B22: Incremental overhead per new student | C22: =IF($C$2=2026,C$83,IF($C$2=2030,C$119,C$83)) | D22: =IF($C$2=2026,D$83,IF($C$2=2030,D$119,D$83)) | E22: =IF($C$2=2026,E$83,IF($C$2=2030,E$119,E$83)) | F22: =IF($C$2=2026,F$83,IF($C$2=2030,F$119,F$83)) | G22: =IF($C$2=2026,G$83,IF($C$2=2030,G$119,G$83)) | J22: Estimted in model as proportion of repurpose transition cost
B23: Per new student cost (m + routing) | C23: =IF($C$2=2026,C$84,IF($C$2=2030,C$120,"")) | D23: =IF($C$2=2026,D$84,IF($C$2=2030,D$120,"")) | E23: =IF($C$2=2026,E$84,IF($C$2=2030,E$120,"")) | F23: =IF($C$2=2026,F$84,IF($C$2=2030,F$120,"")) | G23: =IF($C$2=2026,G$84,IF($C$2=2030,G$120,""))
B24: Total variable gross cost of new students | C24: =IF($C$2=2026,C$85,IF($C$2=2030,C$121,C$85)) | D24: =IF($C$2=2026,D$85,IF($C$2=2030,D$121,D$85)) | E24: =IF($C$2=2026,E$85,IF($C$2=2030,E$121,E$85)) | F24: =IF($C$2=2026,F$85,IF($C$2=2030,F$121,F$85)) | G24: =IF($C$2=2026,G$85,IF($C$2=2030,G$121,G$85))
B25: Total variable gross M&O cost | C25: =IF($C$2=2026,C$86,IF($C$2=2030,C$122,C$86)) | D25: =IF($C$2=2026,D$86,IF($C$2=2030,D$122,D$86)) | E25: =IF($C$2=2026,E$86,IF($C$2=2030,E$122,E$86)) | F25: =IF($C$2=2026,F$86,IF($C$2=2030,F$122,F$86)) | G25: =IF($C$2=2026,G$86,IF($C$2=2030,G$122,G$86))
B26: Transition cost (routing, transportation, etc.) FY26 | C26: =IF($C$2=2026,C$87,IF($C$2=2030,C$123,C$87)) | D26: =IF($C$2=2026,D$87,IF($C$2=2030,D$123,D$87)) | E26: =IF($C$2=2026,E$87,IF($C$2=2030,E$123,E$87)) | F26: =IF($C$2=2026,F$87,IF($C$2=2030,F$123,F$87)) | G26: =IF($C$2=2026,G$87,IF($C$2=2030,G$123,G$87)) | H26: ** | J26: Assuming adjustments in routing or other transportation investment needed for students displaced from repurpose; tapers over time
B27: Routing/Admin cost FYxx (h) | C27: =IF($C$2=2026,C$88,IF($C$2=2030,C$124,"")) | D27: =IF($C$2=2026,D$88,IF($C$2=2030,D$124,"")) | E27: =IF($C$2=2026,E$88,IF($C$2=2030,E$124,"")) | F27: =IF($C$2=2026,F$88,IF($C$2=2030,F$124,"")) | G27: =IF($C$2=2026,G$88,IF($C$2=2030,G$124,""))
B28: Total gross M&O + transition cost | C28: =IF($C$2=2026,C$89,IF($C$2=2030,C$125,C$89)) | D28: =IF($C$2=2026,D$89,IF($C$2=2030,D$125,D$89)) | E28: =IF($C$2=2026,E$89,IF($C$2=2030,E$125,E$89)) | F28: =IF($C$2=2026,F$89,IF($C$2=2030,F$125,F$89)) | G28: =IF($C$2=2026,G$89,IF($C$2=2030,G$125,G$89))
B29: Base open site fixed total | C29: =IF($C$2=2026,C$90,IF($C$2=2030,C$126,C$90)) | D29: =IF($C$2=2026,D$90,IF($C$2=2030,D$126,D$90)) | E29: =IF($C$2=2026,E$90,IF($C$2=2030,E$126,E$90)) | F29: =IF($C$2=2026,F$90,IF($C$2=2030,F$126,F$90)) | G29: =IF($C$2=2026,G$90,IF($C$2=2030,G$126,G$90)) | H29: *
B30: Estimated repurpose site fixed cost carry ratio | C30: =IF($C$2=2026,C$91,IF($C$2=2030,C$127,C$91)) | D30: =IF($C$2=2026,D$91,IF($C$2=2030,D$127,D$91)) | E30: =IF($C$2=2026,E$91,IF($C$2=2030,E$127,E$91)) | F30: =IF($C$2=2026,F$91,IF($C$2=2030,F$127,F$91)) | G30: =IF($C$2=2026,G$91,IF($C$2=2030,G$127,G$91)) | H30: **
B31: Fixed M&O (net) | C31: =IF($C$2=2026,C$92,IF($C$2=2030,C$128,"")) | D31: =IF($C$2=2026,D$92,IF($C$2=2030,D$128,"")) | E31: =IF($C$2=2026,E$92,IF($C$2=2030,E$128,"")) | F31: =IF($C$2=2026,F$92,IF($C$2=2030,F$128,"")) | G31: =IF($C$2=2026,G$92,IF($C$2=2030,G$128,""))
B32: Net total cost | C32: =IF($C$2=2026,C$93,IF($C$2=2030,C$129,C$93)) | D32: =IF($C$2=2026,D$93,IF($C$2=2030,D$129,D$93)) | E32: =IF($C$2=2026,E$93,IF($C$2=2030,E$129,E$93)) | F32: =IF($C$2=2026,F$93,IF($C$2=2030,F$129,F$93)) | G32: =IF($C$2=2026,G$93,IF($C$2=2030,G$129,G$93))
B33: Net operating $ FY26 | C33: =IF($C$2=2026,C$94,IF($C$2=2030,C$130,C$94)) | D33: =IF($C$2=2026,D$94,IF($C$2=2030,D$130,D$94)) | E33: =IF($C$2=2026,E$94,IF($C$2=2030,E$130,E$94)) | F33: =IF($C$2=2026,F$94,IF($C$2=2030,F$130,F$94)) | G33: =IF($C$2=2026,G$94,IF($C$2=2030,G$130,G$94))
B36: FY26 Capital investment | C36: =Capital_Summary!$B$77 | D36: =Capital_Summary!$B$79 | E36: =Capital_Summary!B81 | F36: =Capital_Summary!B74 | G36: =Capital_Summary!B83
B41: (Check-MultiYear_Proforma) Net operating $ / year | C41: =IF($C$2=2026,MultiYear_ProForma!$AF$32,IF($C$2=2030,MultiYear_ProForma!$AF$36,"")) | D41: =IF($C$2=2026,MultiYear_ProForma!$AF$42,IF($C$2=2030,MultiYear_ProForma!$AF$46,"")) | E41: =IF($C$2=2026,MultiYear_ProForma!$AF$52,IF($C$2=2030,MultiYear_ProForma!$AF$56,"")) | F41: =IF($C$2=2026,MultiYear_ProForma!$AF$17,IF($C$2=2030,MultiYear_ProForma!$AF$21,"")) | G41: =IF($C$2=2026,MultiYear_ProForma!$AF$62,IF($C$2=2030,MultiYear_ProForma!$AF$66,""))
B42: Difference in MYP net vs. Dashboard net | C42: =C41-C33 | D42: =D41-D33 | E42: =E41-E33 | F42: =F41-F33 | G42: =G41-G33
B43: % difference in MYP net vs. Dashboard net | C43: =C42/C41 | D43: =D42/D41 | E43: =E42/E41 | F43: =F42/F41 | G43: =G42/G41
B65: FY2026 | C65: A2 | D65: B2 | E65: C2 | F65: D1 | G65: E1
C66: Scenario A (Repurpose Both Lease) | D66: Scenario B (Repurpose Echo Lease; Grow Pima) | E66: Scenario C (Repurpose Pima Lease; Grow Echo) | F66: Scenario D (Grow Both) | G66: Scenario E (Continued Decline) | H66: Source / Confidence Level | I66: Model sensitivity | J66: Note
B67: Baseline ADM Echo | C67: =Parameters_Public!$C$10 | D67: =Parameters_Public!$C$10 | E67: =Parameters_Public!$C$10 | F67: =Parameters_Public!$C$10 | G67: =Parameters_Public!$C$10 | H67: ***
B68: Baseline ADM Pima | C68: =Parameters_Public!$C$11 | D68: =Parameters_Public!$C$11 | E68: =Parameters_Public!$C$11 | F68: =Parameters_Public!$C$11 | G68: =Parameters_Public!$C$11
B69: ADM change FY26 | C69: 0 | D69: =MultiYear_ProForma!$AB$42 | E69: =MultiYear_ProForma!$AB$52 | F69: =MultiYear_ProForma!$AB$17 | G69: 0
B70: Echo retention ratio | C70: =Parameters_Public!$C$23 | D70: =Parameters_Public!$C$23 | E70: ="N/A" | F70: ="N/A" | G70: ="N/A" | H70: *
B71: Pima retention ratio | C71: =Parameters_Public!$C$24 | D71: ="N/A" | E71: =Parameters_Public!$C$24 | F71: ="N/A" | G71: ="N/A" | H71: **
B72: Number of students transitioning | C72: =MultiYear_ProForma!$O$32 | D72: =MultiYear_ProForma!$O$42 | E72: =MultiYear_ProForma!$O$52 | F72: =MultiYear_ProForma!$O$17 | G72: =MultiYear_ProForma!$O$62
B73: Students served FY26 | C73: =C72+C69 | D73: =D68+D72+D69 | E73: =E72+E67+E69 | F73: =F69+F68+F67 | G73: =G68+G67+G69
B74: Per‑served revenue ($/ADM) | C74: =MultiYear_ProForma!$AD$32/Dashboard!C73 | D74: =MultiYear_ProForma!$AD$42/Dashboard!D73 | E74: =MultiYear_ProForma!$AD$52/Dashboard!E73 | F74: =MultiYear_ProForma!$AD$17/Dashboard!F73 | G74: =MultiYear_ProForma!$AD$62/Dashboard!G73 | J74: Base+override; to be conservative, small adjustment down for new students
B75: Total 'revenue' | C75: =C74*C73 | D75: =D74*D73 | E75: =E74*E73 | F75: =F74*F73 | G75: =G74*G73
B76: Districtwide gross Maint & Operations cost per non-new ADM | C76: =Parameters_Public!$C$14 | D76: =Parameters_Public!$C$14 | E76: =Parameters_Public!$C$14 | F76: =Parameters_Public!$C$14 | G76: =Parameters_Public!$C$14 | J76: Maintenance & Operations referred to as "M&O"
B77: Variable cost / non-new ADM | C77: =BaselineCalc!$B$18*(IF(ROUNDUP(IF(C70="N/A", 0, C70)+IF(C71="N/A", 0, C71), 0)=2, 1,IF(ROUNDUP(IF(C70="N/A", 0, C70)+IF(C71="N/A", 0, C71), 0)=1,(1-BaselineCalc!$B$5/2),(1-BaselineCalc!$B$5)))) | D77: =BaselineCalc!$B$18*(IF(ROUNDUP(IF(D70="N/A", 0, D70)+IF(D71="N/A", 0, D71), 0)=2, 1,IF(ROUNDUP(IF(D70="N/A", 0, D70)+IF(D71="N/A", 0, D71), 0)=1,(1-BaselineCalc!$B$5*(D68/(D68+D72))),(1-BaselineCalc!$B$5)))) | E77: =BaselineCalc!$B$18*(IF(ROUNDUP(IF(E70="N/A", 0, E70)+IF(E71="N/A", 0, E71), 0)=2, 1,IF(ROUNDUP(IF(E70="N/A", 0, E70)+IF(E71="N/A", 0, E71), 0)=1,(1-BaselineCalc!$B$5*(E67/(E67+E72))),(1-BaselineCalc!$B$5)))) | F77: =BaselineCalc!$B$18*(IF(ROUNDUP(IF(F70="N/A", 0, F70)+IF(F71="N/A", 0, F71), 0)=2, 1,IF(ROUNDUP(IF(F70="N/A", 0, F70)+IF(F71="N/A", 0, F71), 0)=1,(1-BaselineCalc!$B$5/2),(1-BaselineCalc!$B$5)))) | G77: =BaselineCalc!$B$18*(IF(ROUNDUP(IF(G70="N/A", 0, G70)+IF(G71="N/A", 0, G71), 0)=2, 1,IF(ROUNDUP(IF(G70="N/A", 0, G70)+IF(G71="N/A", 0, G71), 0)=1,(1-BaselineCalc!$B$5/2),(1-BaselineCalc!$B$5))))
B78: Non-new students | C78: =MAX(C73 - C69, 0) | D78: =MAX(D73 - D69, 0) | E78: =MAX(E73 - E69, 0) | F78: =MAX(F73 - F69, 0) | G78: =MAX(G73 - G69, 0)
B79: Total variable gross cost of non-new students | C79: =C78*C77 | D79: =D78*D77 | E79: =E78*E77 | F79: =F78*F77 | G79: =G78*G77 | J79: After discounting estimated fixed, adjusting for inflation
B80: New students | C80: =C69 | D80: =D69 | E80: =E69 | F80: =F69 | G80: =G69
B81: Marginal variable cost to add new students | C81: =Parameters_Public!$C$43 | D81: =Parameters_Public!$C$43 | E81: =Parameters_Public!$C$43 | F81: =Parameters_Public!$C$43 | G81: =Parameters_Public!$C$43 | H81: ** | J81: Estimated proportion of full cost
B82: Variable gross M&O / new student | C82: =IFERROR((C77*C81), "N/A") | D82: =IFERROR((D77*D81), "N/A") | E82: =IFERROR((E77*E81), "N/A") | F82: =IFERROR((F77*F81), "N/A") | G82: =IFERROR((G77*G81), "N/A") | J82: M&O = Maintenance & Operations cost
B83: Incremental overhead per new student | C83: ="$"&YearMap!$E$2*Parameters_Public!$C$47&"/student" | D83: ="$"&YearMap!$E$2*Parameters_Public!$C$47&"/student" | E83: ="$"&YearMap!$E$2*Parameters_Public!$C$47&"/student" | F83: ="$"&YearMap!$E$2*Parameters_Public!$C$47&"/student" | G83: ="$"&YearMap!$E$2*Parameters_Public!$C$47&"/student" | J83: Estimted in model as proportion of repurpose transition cost
B84: Variable gross M&O + growth overhead / new student | C84: =BaselineCalc!$B$18*(1-BaselineCalc!$B$5)*Parameters_Public!$C$43+YearMap!$Q$2 | D84: =BaselineCalc!$B$18*(1-BaselineCalc!$B$5)*Parameters_Public!$C$43+YearMap!$Q$2 | E84: =BaselineCalc!$B$18*(1-BaselineCalc!$B$5)*Parameters_Public!$C$43+YearMap!$Q$2 | F84: =BaselineCalc!$B$18*(1-BaselineCalc!$B$5)*Parameters_Public!$C$43+YearMap!$Q$2 | G84: =BaselineCalc!$B$18*(1-BaselineCalc!$B$5)*Parameters_Public!$C$43+YearMap!$Q$2
B85: Total variable gross cost of new students | C85: =IF(C84*C69=0, "N/A", C84*C69) | D85: =IF(D84*D69=0, "N/A", D84*D69) | E85: =IF(E84*E69=0, "N/A", E84*E69) | F85: =IF(F84*F69=0, "N/A", F84*F69) | G85: =IF(G84*G69=0, "N/A", G84*G69)
B86: Total variable gross M&O cost | C86: =C79+IF(ISNUMBER(C85),C85,0) | D86: =D79+IF(ISNUMBER(D85),D85,0) | E86: =E79+IF(ISNUMBER(E85),E85,0) | F86: =F79+IF(ISNUMBER(F85),F85,0) | G86: =G79+IF(ISNUMBER(G85),G85,0)
B87: Transition cost (routing, transportation, etc.) FY26 | C87: ="$"&YearMap!$E$2&"/student" | D87: ="$"&YearMap!$E$2&"/student" | E87: ="$"&YearMap!$E$2&"/student" | F87: ="N/A" | G87: ="N/A" | H87: ** | J87: Assuming adjustments in routing or other transportation investment needed for students displaced from repurpose; tapers over time
B88: Total transition cost FY26 | C88: =YearMap!$E$2*IF(ISNUMBER(C72), C72, 0) | D88: =YearMap!$E$2*IF(ISNUMBER(D72), D72, 0) | E88: =YearMap!$E$2*IF(ISNUMBER(E72), E72, 0) | F88: =YearMap!$E$2*IF(ISNUMBER(F72), F72, 0) | G88: =YearMap!$E$2*IF(ISNUMBER(G72), G72, 0)
B89: Total gross M&O + transition cost | C89: =C86+IF(ISNUMBER(C88),C88,0) | D89: =D86+IF(ISNUMBER(D88),D88,0) | E89: =E86+IF(ISNUMBER(E88),E88,0) | F89: =F86+IF(ISNUMBER(F88),F88,0) | G89: =G86+IF(ISNUMBER(G88),G88,0)
B90: Base open site fixed total | C90: =BaselineCalc!$B$19+BaselineCalc!$B$20 | D90: =BaselineCalc!$B$20 | E90: =BaselineCalc!$B$19 | F90: =BaselineCalc!$B$19+BaselineCalc!$B$20 | G90: =BaselineCalc!$B$19+BaselineCalc!$B$20 | H90: *
B91: Estimated repurpose site fixed cost carry ratio | C91: =YearMap!$F$2 | D91: =YearMap!$F$2 | E91: =YearMap!$F$2 | F91: ="N/A" | G91: ="N/A" | H91: **
B92: Net fixed cost total | C92: =MultiYear_ProForma!$U$32 | D92: =MultiYear_ProForma!$U$42 | E92: =MultiYear_ProForma!$U$52 | F92: =MultiYear_ProForma!$U$17 | G92: =MultiYear_ProForma!$U$62
B93: Net total cost | C93: =C86+IF(ISNUMBER(C88),C88,0)+C92 | D93: =D86+IF(ISNUMBER(D88),D88,0)+D92 | E93: =E86+IF(ISNUMBER(E88),E88,0)+E92 | F93: =F86+IF(ISNUMBER(F88),F88,0)+F92 | G93: =G86+IF(ISNUMBER(G88),G88,0)+G92
B94: Net operating $ FY26 | C94: =C75-C93 | D94: =D75-D93 | E94: =E75-E93 | F94: =F75-F93 | G94: =G75-G93
B97: Capital investment $ FY26 | C97: =Capital_Summary!$B$77 | D97: =Capital_Summary!$B$79 | E97: =Capital_Summary!B142 | F97: =Capital_Summary!B135 | G97: =Capital_Summary!B144
B101: FY2030 | C101: A2 | D101: B2 | E101: C2 | F101: D1 | G101: E1
C102: Scenario A (Repurpose Both Lease) | D102: Scenario B (Repurpose Echo Lease; Grow Pima) | E102: Scenario C (Repurpose Pima Lease; Grow Echo) | F102: Scenario D (Grow Both) | G102: Scenario E (Continued Decline) | H102: Source / Confidence Level | I102: Model sensitivity | J102: Note
B103: Baseline ADM Echo | C103: =Parameters_Public!$C$10 | D103: =Parameters_Public!$C$10 | E103: =Parameters_Public!$C$10 | F103: =Parameters_Public!$C$10 | G103: =Parameters_Public!$C$10 | H103: ***
B104: Baseline ADM Pima | C104: =Parameters_Public!$C$11 | D104: =Parameters_Public!$C$11 | E104: =Parameters_Public!$C$11 | F104: =Parameters_Public!$C$11 | G104: =Parameters_Public!$C$11
B105: ADM change FY30 | C105: =MultiYear_ProForma!$AB$36 | D105: =MultiYear_ProForma!$AB$46 | E105: =MultiYear_ProForma!$AB$56 | F105: =MultiYear_ProForma!$AB$21 | G105: =MultiYear_ProForma!$AB$66
B106: Echo retention ratio | C106: =Parameters_Public!$C$23 | D106: =Parameters_Public!$C$23 | E106: ="N/A" | F106: ="N/A" | G106: ="N/A" | H106: *
B107: Pima retention ratio | C107: =Parameters_Public!$C$24 | D107: ="N/A" | E107: =Parameters_Public!$C$24 | F107: ="N/A" | G107: ="N/A" | H107: **
B108: Number of students transitioning | C108: =MultiYear_ProForma!$O$36 | D108: =MultiYear_ProForma!$O$46 | E108: =MultiYear_ProForma!$O$56 | F108: =MultiYear_ProForma!$O$21 | G108: =MultiYear_ProForma!$O$66
B109: Students served FY30 | C109: =C108+C105 | D109: =D104+D108+D105 | E109: =E108+E103+E105 | F109: =F105+F104+F103 | G109: =G104+G103+G105
B110: Per‑served revenue ($/ADM) | C110: =MultiYear_ProForma!$AD$36/Dashboard!C109 | D110: =MultiYear_ProForma!$AD$46/Dashboard!D109 | E110: =MultiYear_ProForma!$AD$56/Dashboard!E109 | F110: =MultiYear_ProForma!$AD$21/Dashboard!F109 | G110: =MultiYear_ProForma!$AD$66/Dashboard!G109 | J110: Base+override; to be conservative, small adjustment down for new students
B111: Total 'revenue' | C111: =C110*C109 | D111: =D110*D109 | E111: =E110*E109 | F111: =F110*F109 | G111: =G110*G109
B112: Districtwide gross Maint & Operations cost per non-new ADM | C112: =Parameters_Public!$C$14 | D112: =Parameters_Public!$C$14 | E112: =Parameters_Public!$C$14 | F112: =Parameters_Public!$C$14 | G112: =Parameters_Public!$C$14 | J112: Maintenance & Operations referred to as "M&O"
B113: Variable cost / non-new ADM | C113: =IF(C114=0,0,(C108/C114)*MultiYear_ProForma!$G$36+((C114-C108)/C114)*(MultiYear_ProForma!$G$36*(1-BaselineCalc!$B$5))) | D113: =IF(D114=0,0,(D108/D114)*MultiYear_ProForma!$G$46+((D114-D108)/D114)*(MultiYear_ProForma!$G$46*(1-BaselineCalc!$B$5))) | E113: =IF(E114=0,0,(E108/E114)*MultiYear_ProForma!$G$56+((E114-E108)/E114)*(MultiYear_ProForma!$G$56*(1-BaselineCalc!$B$5))) | F113: =IF(F114=0,0,(F108/F114)*MultiYear_ProForma!$G$21+((F114-F108)/F114)*(MultiYear_ProForma!$G$21*(1-BaselineCalc!$B$5))) | G113: =IF(G114=0,0,(G108/G114)*MultiYear_ProForma!$G$66+((G114-G108)/G114)*(MultiYear_ProForma!$G$66*(1-BaselineCalc!$B$5)))
B114: Non-new students | C114: =MAX(C109 - C105, 0) | D114: =MAX(D109 - D105, 0) | E114: =MAX(E109 - E105, 0) | F114: =MAX(F109 - F105, 0) | G114: =MAX(G109 - G105, 0)
B115: Total variable gross cost of non-new students | C115: =C114*C113 | D115: =D114*D113 | E115: =E114*E113 | F115: =F114*F113 | G115: =G114*G113 | J115: After discounting estimated fixed, adjusting for inflation
B116: New students | C116: =C105 | D116: =D105 | E116: =E105 | F116: =F105 | G116: =G105
B117: Marginal variable cost to add new students | C117: =Parameters_Public!$C$43 | D117: =Parameters_Public!$C$43 | E117: =Parameters_Public!$C$43 | F117: =Parameters_Public!$C$43 | G117: =Parameters_Public!$C$43 | H117: ** | J117: Estimated proportion of full cost
B118: Variable gross M&O / new student | C118: =IFERROR((C113*C117), "N/A") | D118: =IFERROR((D113*D117), "N/A") | E118: =IFERROR((E113*E117), "N/A") | F118: =IFERROR((F113*F117), "N/A") | G118: =IFERROR((G113*G117), "N/A") | J118: M&O = Maintenance & Operations cost
B119: Incremental overhead per new student | C119: ="$"&YearMap!$E$2*Parameters_Public!$C$47&"/student" | D119: ="$"&YearMap!$E$2*Parameters_Public!$C$47&"/student" | E119: ="$"&YearMap!$E$2*Parameters_Public!$C$47&"/student" | F119: ="$"&YearMap!$E$2*Parameters_Public!$C$47&"/student" | G119: ="$"&YearMap!$E$2*Parameters_Public!$C$47&"/student" | J119: Estimted in model as proportion of repurpose transition cost
B120: Variable gross M&O + growth overhead / new student | C120: =MultiYear_ProForma!$G$36*(1-BaselineCalc!$B$5)*Parameters_Public!$C$43+YearMap!$Q$6 | D120: =MultiYear_ProForma!$G$46*(1-BaselineCalc!$B$5)*Parameters_Public!$C$43+YearMap!$Q$6 | E120: =MultiYear_ProForma!$G$56*(1-BaselineCalc!$B$5)*Parameters_Public!$C$43+YearMap!$Q$6 | F120: =MultiYear_ProForma!$G$21*(1-BaselineCalc!$B$5)*Parameters_Public!$C$43+YearMap!$Q$6 | G120: =MultiYear_ProForma!$G$66*(1-BaselineCalc!$B$5)*Parameters_Public!$C$43+YearMap!$Q$6
B121: Total variable gross cost of new students | C121: =IF(C120*C116=0,"N/A",C120*C116) | D121: =IF(D120*D116=0,"N/A",D120*D116) | E121: =IF(E120*E116=0,"N/A",E120*E116) | F121: =IF(F120*F116=0,"N/A",F120*F116) | G121: =IF(G120*G116=0,"N/A",G120*G116)
B122: Total variable gross M&O cost | C122: =C115+IF(ISNUMBER(C121),C121,0) | D122: =D115+IF(ISNUMBER(D121),D121,0) | E122: =E115+IF(ISNUMBER(E121),E121,0) | F122: =F115+IF(ISNUMBER(F121),F121,0) | G122: =G115+IF(ISNUMBER(G121),G121,0)
B123: Transition cost (routing, transportation, etc.) FY30 | C123: ="$"&YearMap!$E$2&"/student" | D123: ="$"&YearMap!$E$2&"/student" | E123: ="$"&YearMap!$E$2&"/student" | F123: ="N/A" | G123: ="N/A" | H123: ** | J123: Assuming adjustments in routing or other transportation investment needed for students displaced from repurpose; tapers over time
B124: Total transition cost FY30 | C124: =YearMap!$E$6*IF(ISNUMBER(C108), C108, 0) | D124: =YearMap!$E$6*IF(ISNUMBER(D108), D108, 0) | E124: =YearMap!$E$6*IF(ISNUMBER(E108), E108, 0) | F124: =YearMap!$E$6*IF(ISNUMBER(F108), F108, 0) | G124: =YearMap!$E$6*IF(ISNUMBER(G108), G108, 0)
B125: Total gross M&O + transition cost | C125: =C122+IF(ISNUMBER(C124),C124,0) | D125: =D122+IF(ISNUMBER(D124),D124,0) | E125: =E122+IF(ISNUMBER(E124),E124,0) | F125: =F122+IF(ISNUMBER(F124),F124,0) | G125: =G122+IF(ISNUMBER(G124),G124,0)
B126: Base open site fixed total | C126: =BaselineCalc!$B$19+BaselineCalc!$B$20 | D126: =BaselineCalc!$B$20 | E126: =BaselineCalc!$B$19 | F126: =BaselineCalc!$B$19+BaselineCalc!$B$20 | G126: =BaselineCalc!$B$19+BaselineCalc!$B$20 | H126: *
B127: Estimated repurpose site fixed cost carry ratio | C127: =YearMap!$F$2 | D127: =YearMap!$F$2 | E127: =YearMap!$F$2 | F127: ="N/A" | G127: ="N/A" | H127: **
B128: Net fixed cost total | C128: =MultiYear_ProForma!$U$36 | D128: =MultiYear_ProForma!$U$46 | E128: =MultiYear_ProForma!$U$56 | F128: =MultiYear_ProForma!$U$21 | G128: =MultiYear_ProForma!$U$66
B129: Net total cost | C129: =C122+IF(ISNUMBER(C124),C124,0)+C128 | D129: =D122+IF(ISNUMBER(D124),D124,0)+D128 | E129: =E122+IF(ISNUMBER(E124),E124,0)+E128 | F129: =F122+IF(ISNUMBER(F124),F124,0)+F128 | G129: =G122+IF(ISNUMBER(G124),G124,0)+G128
B130: Net operating $ FY30 | C130: =C111-C129 | D130: =D111-D129 | E130: =E111-E129 | F130: =F111-F129 | G130: =G111-G129
B133: Capital investment $ FY30 | C133: =Capital_Summary!$B$77 | D133: =Capital_Summary!$B$79 | E133: =Capital_Summary!B178 | F133: =Capital_Summary!B171 | G133: =Capital_Summary!B180

Sheet Working_test
B1: FY26 simulated P&L by scenario
C2: Scenario A2 (Repurpose Both Lease) | D2: Scenario D1 (Grow Both) | E2: Scenario E1 (Continued Decline) | F2: Scenario B2 (Repurpose Echo Lease; Grow Pima) | G2: Scenario C2 (Repurpose Pima Lease; Grow Echo) | H2: Source / Confidence Level
B3: Baseline ADM Echo | C3: =Parameters_Public!$C$10 | D3: =Parameters_Public!$C$10 | E3: =Parameters_Public!$C$10 | F3: =Parameters_Public!$C$10 | G3: =Parameters_Public!$C$10 | H3: ***
B4: Baseline ADM Pima | C4: =Parameters_Public!$C$11 | D4: =Parameters_Public!$C$11 | E4: =Parameters_Public!$C$11 | F4: =Parameters_Public!$C$11 | G4: =Parameters_Public!$C$11
B5: ADM change FY26 | C5: 0 | D5: =MultiYear_ProForma!$AB$17 | E5: 0 | F5: =MultiYear_ProForma!$AB$42 | G5: =MultiYear_ProForma!$AB$52
B6: r_e (Echo retention ratio) | C6: =Parameters_Public!$C$23 | D6: ="N/A" | E6: ="N/A" | F6: =Parameters_Public!$C$23 | G6: ="N/A" | H6: *
B7: r_p (Pima retention ratio) | C7: =Parameters_Public!$C$24 | D7: ="N/A" | E7: ="N/A" | F7: N/A | G7: =Parameters_Public!$C$24 | H7: **
B8: Number of students transitioning | C8: =Parameters_Public!$C$10*Parameters_Public!$C$23+Parameters_Public!$C$11*Parameters_Public!$C$24 | D8: ="N/A" | E8: ="N/A" | F8: =Parameters_Public!$C$10*Parameters_Public!$C$23 | G8: =Parameters_Public!$C$11*Parameters_Public!$C$24
B9: Students served FY26 | C9: =C8+C5 | D9: =D5+D4+D3 | E9: =E4+E3+E5 | F9: =F4+F8+F5 | G9: =G8+G3+G5
B10: Funding/student (base+override; to be conservative, small adjustment down for new students) | C10: =MultiYear_ProForma!$AD$32/Working_test!C9 | D10: =MultiYear_ProForma!$AD$17/Working_test!D9 | E10: =MultiYear_ProForma!$AD$62/Working_test!E9 | F10: =MultiYear_ProForma!$AD$42/Working_test!F9 | G10: =MultiYear_ProForma!$AD$52/Working_test!G9
B11: Implied total 'revenue' | C11: =C10*C9 | D11: =D10*D9 | E11: =E10*E9 | F11: =F10*F9 | G11: =G10*G9
B12: Districtwide gross Maintenance & Operations cost per non-new ADM | C12: =Parameters_Public!$C$14 | D12: =Parameters_Public!$C$14 | E12: =Parameters_Public!$C$14 | F12: =Parameters_Public!$C$14 | G12: =Parameters_Public!$C$14
B13: Variable cost / non-new ADM after discounting estimated fixed, adjusting for inflation | C13: =BaselineCalc!$B$18 | D13: =BaselineCalc!$B$18 | E13: =BaselineCalc!$B$18 | F13: =BaselineCalc!$B$18 | G13: =BaselineCalc!$B$18
B14: Non-new students | C14: =C8 | D14: =D3+D4 | E14: =E9 | F14: =F3+F4 | G14: =G3+G4
B15: Implied total variable gross cost of non-new students | C15: =C14*C13 | D15: =D14*D13 | E15: =E14*E13 | F15: =F14*F13 | G15: =G14*G13
B16: New students | C16: =C5 | D16: =D5 | E16: =E5 | F16: =F5 | G16: =G5
B17: Marginal variable cost to add new students (as proportion of full cost) | C17: =Parameters_Public!$C$43 | D17: =Parameters_Public!$C$43 | E17: =Parameters_Public!$C$43 | F17: =Parameters_Public!$C$43 | G17: =Parameters_Public!$C$43 | H17: **
B18: Implied variable gross M&O / new student | C18: =IFERROR((C13*C17), "N/A") | D18: =IFERROR((D13*D17), "N/A") | E18: =IFERROR((E13*E17), "N/A") | F18: =IFERROR((F13*F17), "N/A") | G18: =IFERROR((G13*G17), "N/A")
B19: Implied total variable gross cost of new students | C19: =IF(C18*C5=0, "N/A", C18*C5) | D19: =IF(D18*D5=0, "N/A", D18*D5) | E19: =IF(E18*E5=0, "N/A", E18*E5) | F19: =IF(F18*F5=0, "N/A", F18*F5) | G19: =IF(G18*G5=0, "N/A", G18*G5)
B20: Total variable gross M&O | C20: =IF(C19="N/A", 0, C19)+C15 | D20: =IF(D19="N/A", 0, D19)+D15 | E20: =IF(E19="N/A", 0, E19)+E15 | F20: =IF(F19="N/A", 0, F19)+F15 | G20: =IF(G19="N/A", 0, G19)+G15
B21: h (Transition cost (routing, transportation, etc.) FY26) | C21: ="$"&YearMap!$E$2&"/student" | D21: ="N/A" | E21: ="N/A" | F21: ="$"&YearMap!$E$2&"/student" | G21: ="$"&YearMap!$E$2&"/student" | H21: **
B22: Implied total transition cost FY26 | C22: =YearMap!$E$2*C8 | D22: ="N/A" | E22: ="N/A" | F22: =YearMap!$E$2*F8 | G22: =YearMap!$E$2*G8
B23: Total gross M&O + transition cost | C23: =C20+IF(C22="N/A", 0, C22) | D23: =D20+IF(D22="N/A", 0, D22) | E23: =E20+IF(E22="N/A", 0, E22) | F23: =F20+IF(F22="N/A", 0, F22) | G23: =G20+IF(G22="N/A", 0, G22)
B24: Base open site fixed total | C24: =Site_Fixed!$D$10+Site_Fixed!$D$17 | D24: =Site_Fixed!$D$10+Site_Fixed!$D$17 | E24: =Site_Fixed!$D$10+Site_Fixed!$D$17 | F24: =Site_Fixed!$D$10 | G24: =Site_Fixed!$D$17 | H24: *
B25: Estimated repurpose site fixed carry ratio | C25: =YearMap!$F$2 | D25: ="N/A" | E25: ="N/A" | F25: =YearMap!$F$2 | G25: =YearMap!$F$2 | H25: **
B26: Net fixed total | C26: =IFERROR(C24*(C25), C24) | D26: =IFERROR(D24*(D25), D24) | E26: =IFERROR(E24*(E25), E24) | F26: =F24+IFERROR(G24*(F25), G24) | G26: =F24+IFERROR(F24*(G25), F24)
B27: Net total cost | C27: =C26+C23 | D27: =D26+D23 | E27: =E26+E23 | F27: =F26+F23 | G27: =G26+G23
B28: Net operating $ / year FY26 | C28: =C11-C27 | D28: =D11-D27 | E28: =E11-E27 | F28: =F11-F27 | G28: =G11-G27
B31: Net cost | C31: =C23-C26
B33: Net operating $ / year FY26 | C33: =MultiYear_ProForma!$AF$32 | D33: =MultiYear_ProForma!$AF$17 | E33: =MultiYear_ProForma!$AF$62 | F33: =MultiYear_ProForma!$AF$42 | G33: =MultiYear_ProForma!$AF$52
B35: Implied fixed cost savings / student | C35: =IFERROR(C26/C9, 0) | D35: =IFERROR(D26/D9, 0) | E35: =IFERROR(E26/E9, 0) | F35: =IFERROR(F26/F9, 0) | G35: =IFERROR(G26/G9, 0)
B36: Net cost / student | C36: =C18-C35
B37: Total net cost
B39: FY26 Capital Cost | H39: **
B40: Execution Feasibility | C40: HIGH RISK (Logistics / Community) | D40: HIGH RISK (Marketing / Enrollment) | E40: LOW RISK (Passive) | F40: MEDIUM RISK | G40: MEDIUM RISK | H40: **
B41: Distinctiveness / reputation impact | C41: Very negative | D41: Very positive | E41: Positive | F41: Neutral to positive | G41: Neutral to positive
B42: District financial 'health' impact | C42: Positive | D42: Positive | E42: Negative | F42: Neutral to positive | G42: Neutral to positive
B44: h (Transition cost (routing, transportation, etc.) FY30) | C44: ="$"&YearMap!$E$6&"/student" | D44: ="N/A" | E44: ="N/A" | F44: ="$"&YearMap!$E$6&"/student" | G44: ="$"&YearMap!$E$6&"/student"
B45: Implied total transition cost FY30 | C45: =YearMap!$E$6*C8 | D45: ="N/A" | E45: ="N/A" | F45: =YearMap!$E$6*F8 | G45: =YearMap!$E$6*G8
B47: f_lease (Proportion of fixed cost carried FY30) | C47: =YearMap!$F$6 | D47: ="N/A" | E47: ="N/A" | F47: =YearMap!$F$6 | G47: =YearMap!$F$6 | H47: **
B48: Implied actual fixed cost savings FY30 | C48: =C24*(1-C47) | D48: ="N/A" | E48: ="N/A" | F48: =F24*(1-F47) | G48: =G24*(1-G47)
B50: Change in ADM over 5 years | C50: ="N/A" | D50: ="&Scenarios!M6&""students" | E50: -43 students | H50: **
B52: Net operating $ / year FY30 | C52: =Summary_Figures!$F$11
B53: Average net operating $ / year FY26-FY30 | C53: =Summary_Figures!$G$11 | H53: **
B57: how solid is the repurpose savings estimate?
A58: Average net operating $ / year FY26-FY30 if site fixed savings are… | B58: 10% less than assumed
B59: 20% less than assumed
B60: 10% more than assumed
B61: 20% more than assumed
A62: Average net operating $ / year FY26-FY30 if f_lease savings glidepath is… | B62: slightly more conservative (xx)
B63: moderately more conservative (yy)
B64: slightly less conservative (zz)
B65: moderately less conservative (aa)
B66: retention
B69: what does it take to achieve budget-neutral on the keep-open scenarios?
C70: Scenario A2 (Repurpose Lease) | D70: Scenario D1 (Grow Both) | E70: Scenario E1 (Decline) | F70: Scenario E2 (Repurpose Echo lease; Grow Pima) | G70: Scenario D2 (Repurpose Pima; Grow Echo) | H70: Source / Confidence Level
B71: change in number of students to yield budget-neutral
B72: average retention rate required to yield budget-neutral
A73: Average net operating $ / year FY26-FY30 if site fixed savings are… | B73: 10% less than assumed
B74: 20% less than assumed
B75: 10% more than assumed
B76: 20% more than assumed
A77: Average net operating $ / year FY26-FY30 if f_lease savings glidepath is… | B77: slightly more conservative (xx)
B78: moderately more conservative (yy)
B79: slightly less conservative (zz)
B80: moderately less conservative (aa)
B83: what if the input assumptions were adjusted as follows (CHOOSE):

Sheet Scenario_Comparison
B1: Echo & Pima — Go-forward scenario comparison view
B3: Scenarios (CHOOSE) | C3: Description | I3: Assumed enrollment change (over 3 yrs)
B4: A2_Repurpose_Both_lease | C4: =VLOOKUP($B4,Scenarios!$A$2:$C$15, 2, 0) | J4: =IF(ROUND(SUMIFS(MultiYear_ProForma!$AC:$AC,MultiYear_ProForma!$B:$B,$B4,MultiYear_ProForma!$C:$C,"FY2030")-BaselineCalc!$B$9, 0)>0, "+"&ROUND(SUMIFS(MultiYear_ProForma!$AC:$AC,MultiYear_ProForma!$B:$B,$B4,MultiYear_ProForma!$C:$C,"FY2030")-BaselineCalc!$B$9, 0), ROUND(SUMIFS(MultiYear_ProForma!$AC:$AC,MultiYear_ProForma!$B:$B,$B4,MultiYear_ProForma!$C:$C,"FY2030")-BaselineCalc!$B$9, 0))
B5: E1_StatusQuo_Decline | C5: =VLOOKUP($B5,Scenarios!$A$2:$C$15, 2, 0) | J5: =IF(ROUND(SUMIFS(MultiYear_ProForma!$AC:$AC,MultiYear_ProForma!$B:$B,$B5,MultiYear_ProForma!$C:$C,"FY2030")-BaselineCalc!$B$9, 0)>0, "+"&ROUND(SUMIFS(MultiYear_ProForma!$AC:$AC,MultiYear_ProForma!$B:$B,$B5,MultiYear_ProForma!$C:$C,"FY2030")-BaselineCalc!$B$9, 0), ROUND(SUMIFS(MultiYear_ProForma!$AC:$AC,MultiYear_ProForma!$B:$B,$B5,MultiYear_ProForma!$C:$C,"FY2030")-BaselineCalc!$B$9, 0))
B24: Notes: Assumptions reflect: r (retention assumptions), override, marginal factor (e.g. assumed reduced variable cost to add new students), trend flags; h (receiving schools transportation route adjustment premium) tapers yearly. Receiving site should not exceed spare seats + portables
B26: Year | C26: Operating Net$ (Base) | D26: Operating Net$ (Comparator)
B27: FY2026 | C27: =SUMIFS(MultiYear_ProForma!$AF$2:$AF$66, MultiYear_ProForma!$B$2:$B$66, $B$4, MultiYear_ProForma!$C$2:$C$66, "FY2026") | D27: =SUMIFS(MultiYear_ProForma!$AF$2:$AF$66, MultiYear_ProForma!$B$2:$B$66, $B$5, MultiYear_ProForma!$C$2:$C$66, "FY2026")
B28: FY2027 | C28: =SUMIFS(MultiYear_ProForma!$AF$2:$AF$66, MultiYear_ProForma!$B$2:$B$66, $B$4, MultiYear_ProForma!$C$2:$C$66, "FY2027") | D28: =SUMIFS(MultiYear_ProForma!$AF$2:$AF$66, MultiYear_ProForma!$B$2:$B$66, $B$5, MultiYear_ProForma!$C$2:$C$66, "FY2027")
B29: FY2028 | C29: =SUMIFS(MultiYear_ProForma!$AF$2:$AF$66, MultiYear_ProForma!$B$2:$B$66, $B$4, MultiYear_ProForma!$C$2:$C$66, "FY2028") | D29: =SUMIFS(MultiYear_ProForma!$AF$2:$AF$66, MultiYear_ProForma!$B$2:$B$66, $B$5, MultiYear_ProForma!$C$2:$C$66, "FY2028")
B30: FY2029 | C30: =SUMIFS(MultiYear_ProForma!$AF$2:$AF$66, MultiYear_ProForma!$B$2:$B$66, $B$4, MultiYear_ProForma!$C$2:$C$66, "FY2029") | D30: =SUMIFS(MultiYear_ProForma!$AF$2:$AF$66, MultiYear_ProForma!$B$2:$B$66, $B$5, MultiYear_ProForma!$C$2:$C$66, "FY2029")
B31: FY2030 | C31: =SUMIFS(MultiYear_ProForma!$AF$2:$AF$66, MultiYear_ProForma!$B$2:$B$66, $B$4, MultiYear_ProForma!$C$2:$C$66, "FY2030") | D31: =SUMIFS(MultiYear_ProForma!$AF$2:$AF$66, MultiYear_ProForma!$B$2:$B$66, $B$5, MultiYear_ProForma!$C$2:$C$66, "FY2030")
B33: Assumptions (from Parameters_Public / Control_Center)
B34: Retention r (Echo central) | C34: =Parameters_Public!C23
B35: Retention r (Pima central) | C35: =Parameters_Public!C24
B36: MarginalFactor_for_Overlay | C36: =Parameters_Public!C43
B37: Override % | C37: =Parameters_Public!C17
B38: Override toggle (0/1) | C38: =Parameters_Public!C20
B39: Keep-open ops savings (fraction of MO) | C39: =Control_Center!C10
B40: Extra savings for co-location (fraction of MO) | C40: =Control_Center!C11
B41: • Routing/admin overhead h tapers by year (see YearMap). Try ±20% sensitivity when routing assumptions are uncertain.
D43: Interpretation
B44: One-time Capital FY 2026 (Base) | C44: =SUMIFS(Capital_Summary!$H$4:$H$83, Capital_Summary!$A$4:$A$83, B4, Capital_Summary!$B$4:$B$83, "FY2026") | D44: =""&$B$5&" will be $"&TEXT(ROUND(ABS(C45-C44),0), "#,##0")&" "&IF(C45>C44,"MORE COSTLY","LESS COSTLY")&" than "&$B$4&" in terms of capital investment required "
B45: One-time Capital FY 2026 (Comparator) | C45: =SUMIFS(Capital_Summary!$H$4:$H$83, Capital_Summary!$A$4:$A$83, B5, Capital_Summary!$B$4:$B$83, "FY2026")
B47: Avg Net (FY26–30) (Base)—rounded | C47: =ROUND((SUMIFS(MultiYear_ProForma!$AF$2:$AF$66,MultiYear_ProForma!$B$2:$B$66,$B$4,MultiYear_ProForma!$C$2:$C$66,"FY2026")+SUMIFS(MultiYear_ProForma!$AF$2:$AF$66,MultiYear_ProForma!$B$2:$B$66,$B$4,MultiYear_ProForma!$C$2:$C$66,"FY2027")+SUMIFS(MultiYear_ProForma!$AF$2:$AF$66,MultiYear_ProForma!$B$2:$B$66,$B$4,MultiYear_ProForma!$C$2:$C$66,"FY2028")+SUMIFS(MultiYear_ProForma!$AF$2:$AF$66,MultiYear_ProForma!$B$2:$B$66,$B$4,MultiYear_ProForma!$C$2:$C$66,"FY2029")+SUMIFS(MultiYear_ProForma!$AF$2:$AF$66,MultiYear_ProForma!$B$2:$B$66,$B$4,MultiYear_ProForma!$C$2:$C$66,"FY2030"))/5,-4) | D47: ="On average from 2026 through 2030, "&$B$5&" will be $"&TEXT(ABS(ROUND(C49,0)), "#,##0")&" "&IF(C49<0,"MORE COSTLY","LESS COSTLY")&" to operate annually than "&$B$4&""
B48: Avg Net (FY26–30) (Comparator)—rounded | C48: =ROUND((SUMIFS(MultiYear_ProForma!$AF$2:$AF$66, MultiYear_ProForma!$B$2:$B$66, $B$5, MultiYear_ProForma!$C$2:$C$66, "FY2026")+SUMIFS(MultiYear_ProForma!$AF$2:$AF$66, MultiYear_ProForma!$B$2:$B$66, $C$5, MultiYear_ProForma!$C$2:$C$66, "FY2027")+SUMIFS(MultiYear_ProForma!$AF$2:$AF$66, MultiYear_ProForma!$B$2:$B$66, $B$5, MultiYear_ProForma!$C$2:$C$66, "FY2028")+SUMIFS(MultiYear_ProForma!$AF$2:$AF$66, MultiYear_ProForma!$B$2:$B$66, $B$5, MultiYear_ProForma!$C$2:$C$66, "FY2029")+SUMIFS(MultiYear_ProForma!$AF$2:$AF$66, MultiYear_ProForma!$B$2:$B$66, $B$5, MultiYear_ProForma!$C$2:$C$66, "FY2030"))/5, -4)
B49: Δ vs Base (Avg FY26–30)—rounded | C49: =ROUND(C48-C47, -4)
B52: FY2030 Net (Base)—rounded | C52: =ROUND(SUMIFS(MultiYear_ProForma!$AF$2:$AF$66, MultiYear_ProForma!$B$2:$B$66, $B$4, MultiYear_ProForma!$C$2:$C$66, "FY2030"), -4) | D52: ="By 2030, "&$B$5&" will be $"&TEXT(ABS(ROUND(C54,0)), "#,##0")&" "&IF(C54<0,"MORE COSTLY","LESS COSTLY")&" to operate annually than "&$B$4&""
B53: FY2030 Net (Comparator)—rounded | C53: =ROUND(SUMIFS(MultiYear_ProForma!$AF$2:$AF$66, MultiYear_ProForma!$B$2:$B$66, $B$5, MultiYear_ProForma!$C$2:$C$66, "FY2030"), -4)
B54: Δ vs Base (FY2030)—rounded | C54: =ROUND(C53-C52, -4)
B56: Students displaced (FY26) (Base) | C56: =SUMIFS(MultiYear_ProForma!$N$2:$N$66, MultiYear_ProForma!$B$2:$B$66, $B$4, MultiYear_ProForma!$C$2:$C$66, "FY2026") | D56: =""&$B$5&" will displace "&ROUND(ABS(C57-C56),0)&" "&IF(C57>C56,"MORE STUDENTS","FEWER STUDENTS")&" than "&$B$4&""
B57: Students displaced (FY26) (Comparator) | C57: =SUMIFS(MultiYear_ProForma!$N$2:$N$66, MultiYear_ProForma!$B$2:$B$66, $B$5, MultiYear_ProForma!$C$2:$C$66, "FY2026")
B59: Students served (FY2030) (Base) | C59: =SUMIFS(MultiYear_ProForma!$AC$2:$AC$66, MultiYear_ProForma!$B$2:$B$66, $B$4, MultiYear_ProForma!$C$2:$C$66, "FY2030") | D59: =""&$B$5&" will serve "&ROUND(ABS(C60-C59),0)&" "&IF(C60>C59,"MORE STUDENTS","FEWER STUDENTS")&" than "&$B$4&""
B60: Students served (FY2030) (Comparator) | C60: =SUMIFS(MultiYear_ProForma!$AC$2:$AC$66, MultiYear_ProForma!$B$2:$B$66, $B$5, MultiYear_ProForma!$C$2:$C$66, "FY2030")

Sheet Budget_Neutral_Calculator
B1: Budget‑Neutral Calculator (Operating $)
B3: Scenario (Choose one): | C3: E1_StatusQuo_Decline
B5: Metric | C5: FY2026 | D5: FY2030
B6: mᵗ: Incremental margin per added ADM | C6: =INDEX(YearMap!$I$2:$I$6, MATCH("FY2026",YearMap!$A$2:$A$6,0))+IF(Override_toggle=1, INDEX(YearMap!$O$2:$O$6, MATCH("FY2026",YearMap!$A$2:$A$6,0)),0)+INDEX(YearMap!$P$2:$P$6, MATCH("FY2026",YearMap!$A$2:$A$6,0))-INDEX(YearMap!$B$2:$B$6, MATCH("FY2026",YearMap!$A$2:$A$6,0))-INDEX(YearMap!$Q$2:$Q$6, MATCH("FY2026",YearMap!$A$2:$A$6,0)) | D6: =INDEX(YearMap!$I$2:$I$6, MATCH("FY2030",YearMap!$A$2:$A$6,0))+IF(Override_toggle=1, INDEX(YearMap!$O$2:$O$6, MATCH("FY2030",YearMap!$A$2:$A$6,0)),0)+INDEX(YearMap!$P$2:$P$6, MATCH("FY2030",YearMap!$A$2:$A$6,0))-INDEX(YearMap!$B$2:$B$6, MATCH("FY2030",YearMap!$A$2:$A$6,0))-INDEX(YearMap!$Q$2:$Q$6, MATCH("FY2030",YearMap!$A$2:$A$6,0))
B7: Net (operating) | C7: =SUMIFS(MultiYear_ProForma!$AF$2:$AF$66,MultiYear_ProForma!$B$2:$B$66,$C$3,MultiYear_ProForma!$C$2:$C$66,"FY2026") | D7: =SUMIFS(MultiYear_ProForma!$AF$2:$AF$66,MultiYear_ProForma!$B$2:$B$66,$C$3,MultiYear_ProForma!$C$2:$C$66,"FY2030")
B8: N⁰: Additional students needed for Net ≥ 0 | C8: =IFERROR(MAX(0,-$C$7/$C$6),"") | D8: =IFERROR(MAX(0,-$D$7/$D$6),"")
B10: Interpretation
B11: =IF(D8=0, "The "&C3&" is budget neutral or better given current assumptions in the model; additional enrollment is not necessary.", "Given current assumptions in the model, to be budget neutral by FY2030, the "&C3&" scenario requires enrollment of "&ROUND(D8, 0)&" additional students.")
B13: Notes:
B14: This tool tests budget neutrality for any scenario: N⁰ = max(0, −Netₜ / mᵗ).
B15: mᵗ uses YearMap (Aid + Override_if_on + Uplift − VarUnit$ − Growth_overhead). Net excludes capital.

Sheet Summary_Figures
B1: Choose base scenario (for comparison): | C1: E1_StatusQuo_Decline | P1: Chart titles
A2: Net = (M&O operating) − (Aid + Override + Uplift). Capital is excluded. Uplift is indexed to Aid growth. | P2: ="(Comparison) Change in ops net $ by scenario compared to "&C1&" (Positive = savings)"
A3: Students: Displaced = FY2026; Served = FY2030 (open + retained). | P3: ="(Nominal) One-time capital (FY26) & Average 5-yr net ops $ by scenario"
A4: Scenario key | B4: Scenario | C4: One-time Capital (FY26) | D4: Net FY26 Operational $ | E4: Net FY28 Operational $ | F4: Net FY30 Operational $ | G4: AVG 5-yr net operational $ | H4: 5-yr Operating Net $ (sum FY26-30) | I4: Displaced students | J4: Served students FY30 | K4: Net Op $ / Served (FY2030) | L4: Δ vs Base (FY2030 Net) | M4: Δ vs Base (5-yr Avg Net)
A5: =LEFT(B5, 2) | B5: =Scenarios!A3 | C5: =SUMIFS(Capital_Summary!$H$4:$H$83, Capital_Summary!$A$4:$A$83, B5, Capital_Summary!$B$4:$B$83, "FY2026")*-1 | D5: =SUMIFS(MultiYear_ProForma!$AF$2:$AF$66, MultiYear_ProForma!$B$2:$B$66, B5, MultiYear_ProForma!$C$2:$C$66, "FY2026") | E5: =SUMIFS(MultiYear_ProForma!$AF$2:$AF$66, MultiYear_ProForma!$B$2:$B$66, B5, MultiYear_ProForma!$C$2:$C$66, "FY2028") | F5: =SUMIFS(MultiYear_ProForma!$AF$2:$AF$66, MultiYear_ProForma!$B$2:$B$66, B5, MultiYear_ProForma!$C$2:$C$66, "FY2030") | G5: =(SUMIFS(MultiYear_ProForma!$AF$2:$AF$66, MultiYear_ProForma!$B$2:$B$66, B5, MultiYear_ProForma!$C$2:$C$66, "FY2026")+SUMIFS(MultiYear_ProForma!$AF$2:$AF$66, MultiYear_ProForma!$B$2:$B$66, B5, MultiYear_ProForma!$C$2:$C$66, "FY2027")+SUMIFS(MultiYear_ProForma!$AF$2:$AF$66, MultiYear_ProForma!$B$2:$B$66, B5, MultiYear_ProForma!$C$2:$C$66, "FY2028")+SUMIFS(MultiYear_ProForma!$AF$2:$AF$66, MultiYear_ProForma!$B$2:$B$66, B5, MultiYear_ProForma!$C$2:$C$66, "FY2029")+SUMIFS(MultiYear_ProForma!$AF$2:$AF$66, MultiYear_ProForma!$B$2:$B$66, B5, MultiYear_ProForma!$C$2:$C$66, "FY2030"))/5 | H5: =(SUMIFS(MultiYear_ProForma!$AF$2:$AF$66, MultiYear_ProForma!$B$2:$B$66, B5, MultiYear_ProForma!$C$2:$C$66, "FY2026")+SUMIFS(MultiYear_ProForma!$AF$2:$AF$66, MultiYear_ProForma!$B$2:$B$66, B5, MultiYear_ProForma!$C$2:$C$66, "FY2027")+SUMIFS(MultiYear_ProForma!$AF$2:$AF$66, MultiYear_ProForma!$B$2:$B$66, B5, MultiYear_ProForma!$C$2:$C$66, "FY2028")+SUMIFS(MultiYear_ProForma!$AF$2:$AF$66, MultiYear_ProForma!$B$2:$B$66, B5, MultiYear_ProForma!$C$2:$C$66, "FY2029")+SUMIFS(MultiYear_ProForma!$AF$2:$AF$66, MultiYear_ProForma!$B$2:$B$66, B5, MultiYear_ProForma!$C$2:$C$66, "FY2030")) | I5: =SUMIFS(MultiYear_ProForma!$N$2:$N$66, MultiYear_ProForma!$B$2:$B$66, B5, MultiYear_ProForma!$C$2:$C$66, "FY2026") | J5: =SUMIFS(MultiYear_ProForma!$AC$2:$AC$66, MultiYear_ProForma!$B$2:$B$66, B5, MultiYear_ProForma!$C$2:$C$66, "FY2030") | K5: =F5/J5 | L5: =F5-(VLOOKUP($C$1,$B$5:$G$17,5, 0)) | M5: =G5-(VLOOKUP($C$1,$B$5:$J$17,6, 0))
A6: =LEFT(B6, 2) | B6: =Scenarios!A4 | C6: =SUMIFS(Capital_Summary!$H$4:$H$83, Capital_Summary!$A$4:$A$83, B6, Capital_Summary!$B$4:$B$83, "FY2026")*-1 | D6: =SUMIFS(MultiYear_ProForma!$AF$2:$AF$66, MultiYear_ProForma!$B$2:$B$66, B6, MultiYear_ProForma!$C$2:$C$66, "FY2026") | E6: =SUMIFS(MultiYear_ProForma!$AF$2:$AF$66, MultiYear_ProForma!$B$2:$B$66, B6, MultiYear_ProForma!$C$2:$C$66, "FY2028") | F6: =SUMIFS(MultiYear_ProForma!$AF$2:$AF$66, MultiYear_ProForma!$B$2:$B$66, B6, MultiYear_ProForma!$C$2:$C$66, "FY2030") | G6: =(SUMIFS(MultiYear_ProForma!$AF$2:$AF$66, MultiYear_ProForma!$B$2:$B$66, B6, MultiYear_ProForma!$C$2:$C$66, "FY2026")+SUMIFS(MultiYear_ProForma!$AF$2:$AF$66, MultiYear_ProForma!$B$2:$B$66, B6, MultiYear_ProForma!$C$2:$C$66, "FY2027")+SUMIFS(MultiYear_ProForma!$AF$2:$AF$66, MultiYear_ProForma!$B$2:$B$66, B6, MultiYear_ProForma!$C$2:$C$66, "FY2028")+SUMIFS(MultiYear_ProForma!$AF$2:$AF$66, MultiYear_ProForma!$B$2:$B$66, B6, MultiYear_ProForma!$C$2:$C$66, "FY2029")+SUMIFS(MultiYear_ProForma!$AF$2:$AF$66, MultiYear_ProForma!$B$2:$B$66, B6, MultiYear_ProForma!$C$2:$C$66, "FY2030"))/5 | H6: =(SUMIFS(MultiYear_ProForma!$AF$2:$AF$66, MultiYear_ProForma!$B$2:$B$66, B6, MultiYear_ProForma!$C$2:$C$66, "FY2026")+SUMIFS(MultiYear_ProForma!$AF$2:$AF$66, MultiYear_ProForma!$B$2:$B$66, B6, MultiYear_ProForma!$C$2:$C$66, "FY2027")+SUMIFS(MultiYear_ProForma!$AF$2:$AF$66, MultiYear_ProForma!$B$2:$B$66, B6, MultiYear_ProForma!$C$2:$C$66, "FY2028")+SUMIFS(MultiYear_ProForma!$AF$2:$AF$66, MultiYear_ProForma!$B$2:$B$66, B6, MultiYear_ProForma!$C$2:$C$66, "FY2029")+SUMIFS(MultiYear_ProForma!$AF$2:$AF$66, MultiYear_ProForma!$B$2:$B$66, B6, MultiYear_ProForma!$C$2:$C$66, "FY2030")) | I6: =SUMIFS(MultiYear_ProForma!$N$2:$N$66, MultiYear_ProForma!$B$2:$B$66, B6, MultiYear_ProForma!$C$2:$C$66, "FY2026") | J6: =SUMIFS(MultiYear_ProForma!$AC$2:$AC$66, MultiYear_ProForma!$B$2:$B$66, B6, MultiYear_ProForma!$C$2:$C$66, "FY2030") | K6: =F6/J6 | L6: =F6-(VLOOKUP($C$1,$B$5:$G$17,5, 0)) | M6: =G6-(VLOOKUP($C$1,$B$5:$J$17,6, 0))
A7: =LEFT(B7, 2) | B7: =Scenarios!A5 | C7: =SUMIFS(Capital_Summary!$H$4:$H$83, Capital_Summary!$A$4:$A$83, B7, Capital_Summary!$B$4:$B$83, "FY2026")*-1 | D7: =SUMIFS(MultiYear_ProForma!$AF$2:$AF$66, MultiYear_ProForma!$B$2:$B$66, B7, MultiYear_ProForma!$C$2:$C$66, "FY2026") | E7: =SUMIFS(MultiYear_ProForma!$AF$2:$AF$66, MultiYear_ProForma!$B$2:$B$66, B7, MultiYear_ProForma!$C$2:$C$66, "FY2028") | F7: =SUMIFS(MultiYear_ProForma!$AF$2:$AF$66, MultiYear_ProForma!$B$2:$B$66, B7, MultiYear_ProForma!$C$2:$C$66, "FY2030") | G7: =(SUMIFS(MultiYear_ProForma!$AF$2:$AF$66, MultiYear_ProForma!$B$2:$B$66, B7, MultiYear_ProForma!$C$2:$C$66, "FY2026")+SUMIFS(MultiYear_ProForma!$AF$2:$AF$66, MultiYear_ProForma!$B$2:$B$66, B7, MultiYear_ProForma!$C$2:$C$66, "FY2027")+SUMIFS(MultiYear_ProForma!$AF$2:$AF$66, MultiYear_ProForma!$B$2:$B$66, B7, MultiYear_ProForma!$C$2:$C$66, "FY2028")+SUMIFS(MultiYear_ProForma!$AF$2:$AF$66, MultiYear_ProForma!$B$2:$B$66, B7, MultiYear_ProForma!$C$2:$C$66, "FY2029")+SUMIFS(MultiYear_ProForma!$AF$2:$AF$66, MultiYear_ProForma!$B$2:$B$66, B7, MultiYear_ProForma!$C$2:$C$66, "FY2030"))/5 | H7: =(SUMIFS(MultiYear_ProForma!$AF$2:$AF$66, MultiYear_ProForma!$B$2:$B$66, B7, MultiYear_ProForma!$C$2:$C$66, "FY2026")+SUMIFS(MultiYear_ProForma!$AF$2:$AF$66, MultiYear_ProForma!$B$2:$B$66, B7, MultiYear_ProForma!$C$2:$C$66, "FY2027")+SUMIFS(MultiYear_ProForma!$AF$2:$AF$66, MultiYear_ProForma!$B$2:$B$66, B7, MultiYear_ProForma!$C$2:$C$66, "FY2028")+SUMIFS(MultiYear_ProForma!$AF$2:$AF$66, MultiYear_ProForma!$B$2:$B$66, B7, MultiYear_ProForma!$C$2:$C$66, "FY2029")+SUMIFS(MultiYear_ProForma!$AF$2:$AF$66, MultiYear_ProForma!$B$2:$B$66, B7, MultiYear_ProForma!$C$2:$C$66, "FY2030")) | I7: =SUMIFS(MultiYear_ProForma!$N$2:$N$66, MultiYear_ProForma!$B$2:$B$66, B7, MultiYear_ProForma!$C$2:$C$66, "FY2026") | J7: =SUMIFS(MultiYear_ProForma!$AC$2:$AC$66, MultiYear_ProForma!$B$2:$B$66, B7, MultiYear_ProForma!$C$2:$C$66, "FY2030") | K7: =F7/J7 | L7: =F7-(VLOOKUP($C$1,$B$5:$G$17,5, 0)) | M7: =G7-(VLOOKUP($C$1,$B$5:$J$17,6, 0))
A8: =LEFT(B8, 2) | B8: =Scenarios!A6 | C8: =SUMIFS(Capital_Summary!$H$4:$H$83, Capital_Summary!$A$4:$A$83, B8, Capital_Summary!$B$4:$B$83, "FY2026")*-1 | D8: =SUMIFS(MultiYear_ProForma!$AF$2:$AF$66, MultiYear_ProForma!$B$2:$B$66, B8, MultiYear_ProForma!$C$2:$C$66, "FY2026") | E8: =SUMIFS(MultiYear_ProForma!$AF$2:$AF$66, MultiYear_ProForma!$B$2:$B$66, B8, MultiYear_ProForma!$C$2:$C$66, "FY2028") | F8: =SUMIFS(MultiYear_ProForma!$AF$2:$AF$66, MultiYear_ProForma!$B$2:$B$66, B8, MultiYear_ProForma!$C$2:$C$66, "FY2030") | G8: =(SUMIFS(MultiYear_ProForma!$AF$2:$AF$66, MultiYear_ProForma!$B$2:$B$66, B8, MultiYear_ProForma!$C$2:$C$66, "FY2026")+SUMIFS(MultiYear_ProForma!$AF$2:$AF$66, MultiYear_ProForma!$B$2:$B$66, B8, MultiYear_ProForma!$C$2:$C$66, "FY2027")+SUMIFS(MultiYear_ProForma!$AF$2:$AF$66, MultiYear_ProForma!$B$2:$B$66, B8, MultiYear_ProForma!$C$2:$C$66, "FY2028")+SUMIFS(MultiYear_ProForma!$AF$2:$AF$66, MultiYear_ProForma!$B$2:$B$66, B8, MultiYear_ProForma!$C$2:$C$66, "FY2029")+SUMIFS(MultiYear_ProForma!$AF$2:$AF$66, MultiYear_ProForma!$B$2:$B$66, B8, MultiYear_ProForma!$C$2:$C$66, "FY2030"))/5 | H8: =(SUMIFS(MultiYear_ProForma!$AF$2:$AF$66, MultiYear_ProForma!$B$2:$B$66, B8, MultiYear_ProForma!$C$2:$C$66, "FY2026")+SUMIFS(MultiYear_ProForma!$AF$2:$AF$66, MultiYear_ProForma!$B$2:$B$66, B8, MultiYear_ProForma!$C$2:$C$66, "FY2027")+SUMIFS(MultiYear_ProForma!$AF$2:$AF$66, MultiYear_ProForma!$B$2:$B$66, B8, MultiYear_ProForma!$C$2:$C$66, "FY2028")+SUMIFS(MultiYear_ProForma!$AF$2:$AF$66, MultiYear_ProForma!$B$2:$B$66, B8, MultiYear_ProForma!$C$2:$C$66, "FY2029")+SUMIFS(MultiYear_ProForma!$AF$2:$AF$66, MultiYear_ProForma!$B$2:$B$66, B8, MultiYear_ProForma!$C$2:$C$66, "FY2030")) | I8: =SUMIFS(MultiYear_ProForma!$N$2:$N$66, MultiYear_ProForma!$B$2:$B$66, B8, MultiYear_ProForma!$C$2:$C$66, "FY2026") | J8: =SUMIFS(MultiYear_ProForma!$AC$2:$AC$66, MultiYear_ProForma!$B$2:$B$66, B8, MultiYear_ProForma!$C$2:$C$66, "FY2030") | K8: =F8/J8 | L8: =F8-(VLOOKUP($C$1,$B$5:$G$17,5, 0)) | M8: =G8-(VLOOKUP($C$1,$B$5:$J$17,6, 0))
A9: =LEFT(B9, 2) | B9: =Scenarios!A7 | C9: =SUMIFS(Capital_Summary!$H$4:$H$83, Capital_Summary!$A$4:$A$83, B9, Capital_Summary!$B$4:$B$83, "FY2026")*-1 | D9: =SUMIFS(MultiYear_ProForma!$AF$2:$AF$66, MultiYear_ProForma!$B$2:$B$66, B9, MultiYear_ProForma!$C$2:$C$66, "FY2026") | E9: =SUMIFS(MultiYear_ProForma!$AF$2:$AF$66, MultiYear_ProForma!$B$2:$B$66, B9, MultiYear_ProForma!$C$2:$C$66, "FY2028") | F9: =SUMIFS(MultiYear_ProForma!$AF$2:$AF$66, MultiYear_ProForma!$B$2:$B$66, B9, MultiYear_ProForma!$C$2:$C$66, "FY2030") | G9: =(SUMIFS(MultiYear_ProForma!$AF$2:$AF$66, MultiYear_ProForma!$B$2:$B$66, B9, MultiYear_ProForma!$C$2:$C$66, "FY2026")+SUMIFS(MultiYear_ProForma!$AF$2:$AF$66, MultiYear_ProForma!$B$2:$B$66, B9, MultiYear_ProForma!$C$2:$C$66, "FY2027")+SUMIFS(MultiYear_ProForma!$AF$2:$AF$66, MultiYear_ProForma!$B$2:$B$66, B9, MultiYear_ProForma!$C$2:$C$66, "FY2028")+SUMIFS(MultiYear_ProForma!$AF$2:$AF$66, MultiYear_ProForma!$B$2:$B$66, B9, MultiYear_ProForma!$C$2:$C$66, "FY2029")+SUMIFS(MultiYear_ProForma!$AF$2:$AF$66, MultiYear_ProForma!$B$2:$B$66, B9, MultiYear_ProForma!$C$2:$C$66, "FY2030"))/5 | H9: =(SUMIFS(MultiYear_ProForma!$AF$2:$AF$66, MultiYear_ProForma!$B$2:$B$66, B9, MultiYear_ProForma!$C$2:$C$66, "FY2026")+SUMIFS(MultiYear_ProForma!$AF$2:$AF$66, MultiYear_ProForma!$B$2:$B$66, B9, MultiYear_ProForma!$C$2:$C$66, "FY2027")+SUMIFS(MultiYear_ProForma!$AF$2:$AF$66, MultiYear_ProForma!$B$2:$B$66, B9, MultiYear_ProForma!$C$2:$C$66, "FY2028")+SUMIFS(MultiYear_ProForma!$AF$2:$AF$66, MultiYear_ProForma!$B$2:$B$66, B9, MultiYear_ProForma!$C$2:$C$66, "FY2029")+SUMIFS(MultiYear_ProForma!$AF$2:$AF$66, MultiYear_ProForma!$B$2:$B$66, B9, MultiYear_ProForma!$C$2:$C$66, "FY2030")) | I9: =SUMIFS(MultiYear_ProForma!$N$2:$N$66, MultiYear_ProForma!$B$2:$B$66, B9, MultiYear_ProForma!$C$2:$C$66, "FY2026") | J9: =SUMIFS(MultiYear_ProForma!$AC$2:$AC$66, MultiYear_ProForma!$B$2:$B$66, B9, MultiYear_ProForma!$C$2:$C$66, "FY2030") | K9: =F9/J9 | L9: =F9-(VLOOKUP($C$1,$B$5:$G$17,5, 0)) | M9: =G9-(VLOOKUP($C$1,$B$5:$J$17,6, 0))
A10: =LEFT(B10, 2) | B10: =Scenarios!A8 | C10: =SUMIFS(Capital_Summary!$H$4:$H$83, Capital_Summary!$A$4:$A$83, B10, Capital_Summary!$B$4:$B$83, "FY2026")*-1 | D10: =SUMIFS(MultiYear_ProForma!$AF$2:$AF$66, MultiYear_ProForma!$B$2:$B$66, B10, MultiYear_ProForma!$C$2:$C$66, "FY2026") | E10: =SUMIFS(MultiYear_ProForma!$AF$2:$AF$66, MultiYear_ProForma!$B$2:$B$66, B10, MultiYear_ProForma!$C$2:$C$66, "FY2028") | F10: =SUMIFS(MultiYear_ProForma!$AF$2:$AF$66, MultiYear_ProForma!$B$2:$B$66, B10, MultiYear_ProForma!$C$2:$C$66, "FY2030") | G10: =(SUMIFS(MultiYear_ProForma!$AF$2:$AF$66, MultiYear_ProForma!$B$2:$B$66, B10, MultiYear_ProForma!$C$2:$C$66, "FY2026")+SUMIFS(MultiYear_ProForma!$AF$2:$AF$66, MultiYear_ProForma!$B$2:$B$66, B10, MultiYear_ProForma!$C$2:$C$66, "FY2027")+SUMIFS(MultiYear_ProForma!$AF$2:$AF$66, MultiYear_ProForma!$B$2:$B$66, B10, MultiYear_ProForma!$C$2:$C$66, "FY2028")+SUMIFS(MultiYear_ProForma!$AF$2:$AF$66, MultiYear_ProForma!$B$2:$B$66, B10, MultiYear_ProForma!$C$2:$C$66, "FY2029")+SUMIFS(MultiYear_ProForma!$AF$2:$AF$66, MultiYear_ProForma!$B$2:$B$66, B10, MultiYear_ProForma!$C$2:$C$66, "FY2030"))/5 | H10: =(SUMIFS(MultiYear_ProForma!$AF$2:$AF$66, MultiYear_ProForma!$B$2:$B$66, B10, MultiYear_ProForma!$C$2:$C$66, "FY2026")+SUMIFS(MultiYear_ProForma!$AF$2:$AF$66, MultiYear_ProForma!$B$2:$B$66, B10, MultiYear_ProForma!$C$2:$C$66, "FY2027")+SUMIFS(MultiYear_ProForma!$AF$2:$AF$66, MultiYear_ProForma!$B$2:$B$66, B10, MultiYear_ProForma!$C$2:$C$66, "FY2028")+SUMIFS(MultiYear_ProForma!$AF$2:$AF$66, MultiYear_ProForma!$B$2:$B$66, B10, MultiYear_ProForma!$C$2:$C$66, "FY2029")+SUMIFS(MultiYear_ProForma!$AF$2:$AF$66, MultiYear_ProForma!$B$2:$B$66, B10, MultiYear_ProForma!$C$2:$C$66, "FY2030")) | I10: =SUMIFS(MultiYear_ProForma!$N$2:$N$66, MultiYear_ProForma!$B$2:$B$66, B10, MultiYear_ProForma!$C$2:$C$66, "FY2026") | J10: =SUMIFS(MultiYear_ProForma!$AC$2:$AC$66, MultiYear_ProForma!$B$2:$B$66, B10, MultiYear_ProForma!$C$2:$C$66, "FY2030") | K10: =F10/J10 | L10: =F10-(VLOOKUP($C$1,$B$5:$G$17,5, 0)) | M10: =G10-(VLOOKUP($C$1,$B$5:$J$17,6, 0))
A11: =LEFT(B11, 2) | B11: =Scenarios!A9 | C11: =SUMIFS(Capital_Summary!$H$4:$H$83, Capital_Summary!$A$4:$A$83, B11, Capital_Summary!$B$4:$B$83, "FY2026")*-1 | D11: =SUMIFS(MultiYear_ProForma!$AF$2:$AF$66, MultiYear_ProForma!$B$2:$B$66, B11, MultiYear_ProForma!$C$2:$C$66, "FY2026") | E11: =SUMIFS(MultiYear_ProForma!$AF$2:$AF$66, MultiYear_ProForma!$B$2:$B$66, B11, MultiYear_ProForma!$C$2:$C$66, "FY2028") | F11: =SUMIFS(MultiYear_ProForma!$AF$2:$AF$66, MultiYear_ProForma!$B$2:$B$66, B11, MultiYear_ProForma!$C$2:$C$66, "FY2030") | G11: =(SUMIFS(MultiYear_ProForma!$AF$2:$AF$66, MultiYear_ProForma!$B$2:$B$66, B11, MultiYear_ProForma!$C$2:$C$66, "FY2026")+SUMIFS(MultiYear_ProForma!$AF$2:$AF$66, MultiYear_ProForma!$B$2:$B$66, B11, MultiYear_ProForma!$C$2:$C$66, "FY2027")+SUMIFS(MultiYear_ProForma!$AF$2:$AF$66, MultiYear_ProForma!$B$2:$B$66, B11, MultiYear_ProForma!$C$2:$C$66, "FY2028")+SUMIFS(MultiYear_ProForma!$AF$2:$AF$66, MultiYear_ProForma!$B$2:$B$66, B11, MultiYear_ProForma!$C$2:$C$66, "FY2029")+SUMIFS(MultiYear_ProForma!$AF$2:$AF$66, MultiYear_ProForma!$B$2:$B$66, B11, MultiYear_ProForma!$C$2:$C$66, "FY2030"))/5 | H11: =(SUMIFS(MultiYear_ProForma!$AF$2:$AF$66, MultiYear_ProForma!$B$2:$B$66, B11, MultiYear_ProForma!$C$2:$C$66, "FY2026")+SUMIFS(MultiYear_ProForma!$AF$2:$AF$66, MultiYear_ProForma!$B$2:$B$66, B11, MultiYear_ProForma!$C$2:$C$66, "FY2027")+SUMIFS(MultiYear_ProForma!$AF$2:$AF$66, MultiYear_ProForma!$B$2:$B$66, B11, MultiYear_ProForma!$C$2:$C$66, "FY2028")+SUMIFS(MultiYear_ProForma!$AF$2:$AF$66, MultiYear_ProForma!$B$2:$B$66, B11, MultiYear_ProForma!$C$2:$C$66, "FY2029")+SUMIFS(MultiYear_ProForma!$AF$2:$AF$66, MultiYear_ProForma!$B$2:$B$66, B11, MultiYear_ProForma!$C$2:$C$66, "FY2030")) | I11: =SUMIFS(MultiYear_ProForma!$N$2:$N$66, MultiYear_ProForma!$B$2:$B$66, B11, MultiYear_ProForma!$C$2:$C$66, "FY2026") | J11: =SUMIFS(MultiYear_ProForma!$AC$2:$AC$66, MultiYear_ProForma!$B$2:$B$66, B11, MultiYear_ProForma!$C$2:$C$66, "FY2030") | K11: =F11/J11 | L11: =F11-(VLOOKUP($C$1,$B$5:$G$17,5, 0)) | M11: =G11-(VLOOKUP($C$1,$B$5:$J$17,6, 0))
A12: =LEFT(B12, 2) | B12: =Scenarios!A10 | C12: =SUMIFS(Capital_Summary!$H$4:$H$83, Capital_Summary!$A$4:$A$83, B12, Capital_Summary!$B$4:$B$83, "FY2026")*-1 | D12: =SUMIFS(MultiYear_ProForma!$AF$2:$AF$66, MultiYear_ProForma!$B$2:$B$66, B12, MultiYear_ProForma!$C$2:$C$66, "FY2026") | E12: =SUMIFS(MultiYear_ProForma!$AF$2:$AF$66, MultiYear_ProForma!$B$2:$B$66, B12, MultiYear_ProForma!$C$2:$C$66, "FY2028") | F12: =SUMIFS(MultiYear_ProForma!$AF$2:$AF$66, MultiYear_ProForma!$B$2:$B$66, B12, MultiYear_ProForma!$C$2:$C$66, "FY2030") | G12: =(SUMIFS(MultiYear_ProForma!$AF$2:$AF$66, MultiYear_ProForma!$B$2:$B$66, B12, MultiYear_ProForma!$C$2:$C$66, "FY2026")+SUMIFS(MultiYear_ProForma!$AF$2:$AF$66, MultiYear_ProForma!$B$2:$B$66, B12, MultiYear_ProForma!$C$2:$C$66, "FY2027")+SUMIFS(MultiYear_ProForma!$AF$2:$AF$66, MultiYear_ProForma!$B$2:$B$66, B12, MultiYear_ProForma!$C$2:$C$66, "FY2028")+SUMIFS(MultiYear_ProForma!$AF$2:$AF$66, MultiYear_ProForma!$B$2:$B$66, B12, MultiYear_ProForma!$C$2:$C$66, "FY2029")+SUMIFS(MultiYear_ProForma!$AF$2:$AF$66, MultiYear_ProForma!$B$2:$B$66, B12, MultiYear_ProForma!$C$2:$C$66, "FY2030"))/5 | H12: =(SUMIFS(MultiYear_ProForma!$AF$2:$AF$66, MultiYear_ProForma!$B$2:$B$66, B12, MultiYear_ProForma!$C$2:$C$66, "FY2026")+SUMIFS(MultiYear_ProForma!$AF$2:$AF$66, MultiYear_ProForma!$B$2:$B$66, B12, MultiYear_ProForma!$C$2:$C$66, "FY2027")+SUMIFS(MultiYear_ProForma!$AF$2:$AF$66, MultiYear_ProForma!$B$2:$B$66, B12, MultiYear_ProForma!$C$2:$C$66, "FY2028")+SUMIFS(MultiYear_ProForma!$AF$2:$AF$66, MultiYear_ProForma!$B$2:$B$66, B12, MultiYear_ProForma!$C$2:$C$66, "FY2029")+SUMIFS(MultiYear_ProForma!$AF$2:$AF$66, MultiYear_ProForma!$B$2:$B$66, B12, MultiYear_ProForma!$C$2:$C$66, "FY2030")) | I12: =SUMIFS(MultiYear_ProForma!$N$2:$N$66, MultiYear_ProForma!$B$2:$B$66, B12, MultiYear_ProForma!$C$2:$C$66, "FY2026") | J12: =SUMIFS(MultiYear_ProForma!$AC$2:$AC$66, MultiYear_ProForma!$B$2:$B$66, B12, MultiYear_ProForma!$C$2:$C$66, "FY2030") | K12: =F12/J12 | L12: =F12-(VLOOKUP($C$1,$B$5:$G$17,5, 0)) | M12: =G12-(VLOOKUP($C$1,$B$5:$J$17,6, 0))
A13: =LEFT(B13, 2) | B13: =Scenarios!A11 | C13: =SUMIFS(Capital_Summary!$H$4:$H$83, Capital_Summary!$A$4:$A$83, B13, Capital_Summary!$B$4:$B$83, "FY2026")*-1 | D13: =SUMIFS(MultiYear_ProForma!$AF$2:$AF$66, MultiYear_ProForma!$B$2:$B$66, B13, MultiYear_ProForma!$C$2:$C$66, "FY2026") | E13: =SUMIFS(MultiYear_ProForma!$AF$2:$AF$66, MultiYear_ProForma!$B$2:$B$66, B13, MultiYear_ProForma!$C$2:$C$66, "FY2028") | F13: =SUMIFS(MultiYear_ProForma!$AF$2:$AF$66, MultiYear_ProForma!$B$2:$B$66, B13, MultiYear_ProForma!$C$2:$C$66, "FY2030") | G13: =(SUMIFS(MultiYear_ProForma!$AF$2:$AF$66, MultiYear_ProForma!$B$2:$B$66, B13, MultiYear_ProForma!$C$2:$C$66, "FY2026")+SUMIFS(MultiYear_ProForma!$AF$2:$AF$66, MultiYear_ProForma!$B$2:$B$66, B13, MultiYear_ProForma!$C$2:$C$66, "FY2027")+SUMIFS(MultiYear_ProForma!$AF$2:$AF$66, MultiYear_ProForma!$B$2:$B$66, B13, MultiYear_ProForma!$C$2:$C$66, "FY2028")+SUMIFS(MultiYear_ProForma!$AF$2:$AF$66, MultiYear_ProForma!$B$2:$B$66, B13, MultiYear_ProForma!$C$2:$C$66, "FY2029")+SUMIFS(MultiYear_ProForma!$AF$2:$AF$66, MultiYear_ProForma!$B$2:$B$66, B13, MultiYear_ProForma!$C$2:$C$66, "FY2030"))/5 | H13: =(SUMIFS(MultiYear_ProForma!$AF$2:$AF$66, MultiYear_ProForma!$B$2:$B$66, B13, MultiYear_ProForma!$C$2:$C$66, "FY2026")+SUMIFS(MultiYear_ProForma!$AF$2:$AF$66, MultiYear_ProForma!$B$2:$B$66, B13, MultiYear_ProForma!$C$2:$C$66, "FY2027")+SUMIFS(MultiYear_ProForma!$AF$2:$AF$66, MultiYear_ProForma!$B$2:$B$66, B13, MultiYear_ProForma!$C$2:$C$66, "FY2028")+SUMIFS(MultiYear_ProForma!$AF$2:$AF$66, MultiYear_ProForma!$B$2:$B$66, B13, MultiYear_ProForma!$C$2:$C$66, "FY2029")+SUMIFS(MultiYear_ProForma!$AF$2:$AF$66, MultiYear_ProForma!$B$2:$B$66, B13, MultiYear_ProForma!$C$2:$C$66, "FY2030")) | I13: =SUMIFS(MultiYear_ProForma!$N$2:$N$66, MultiYear_ProForma!$B$2:$B$66, B13, MultiYear_ProForma!$C$2:$C$66, "FY2026") | J13: =SUMIFS(MultiYear_ProForma!$AC$2:$AC$66, MultiYear_ProForma!$B$2:$B$66, B13, MultiYear_ProForma!$C$2:$C$66, "FY2030") | K13: =F13/J13 | L13: =F13-(VLOOKUP($C$1,$B$5:$G$17,5, 0)) | M13: =G13-(VLOOKUP($C$1,$B$5:$J$17,6, 0))
A14: =LEFT(B14, 2) | B14: =Scenarios!A12 | C14: =SUMIFS(Capital_Summary!$H$4:$H$83, Capital_Summary!$A$4:$A$83, B14, Capital_Summary!$B$4:$B$83, "FY2026")*-1 | D14: =SUMIFS(MultiYear_ProForma!$AF$2:$AF$66, MultiYear_ProForma!$B$2:$B$66, B14, MultiYear_ProForma!$C$2:$C$66, "FY2026") | E14: =SUMIFS(MultiYear_ProForma!$AF$2:$AF$66, MultiYear_ProForma!$B$2:$B$66, B14, MultiYear_ProForma!$C$2:$C$66, "FY2028") | F14: =SUMIFS(MultiYear_ProForma!$AF$2:$AF$66, MultiYear_ProForma!$B$2:$B$66, B14, MultiYear_ProForma!$C$2:$C$66, "FY2030") | G14: =(SUMIFS(MultiYear_ProForma!$AF$2:$AF$66, MultiYear_ProForma!$B$2:$B$66, B14, MultiYear_ProForma!$C$2:$C$66, "FY2026")+SUMIFS(MultiYear_ProForma!$AF$2:$AF$66, MultiYear_ProForma!$B$2:$B$66, B14, MultiYear_ProForma!$C$2:$C$66, "FY2027")+SUMIFS(MultiYear_ProForma!$AF$2:$AF$66, MultiYear_ProForma!$B$2:$B$66, B14, MultiYear_ProForma!$C$2:$C$66, "FY2028")+SUMIFS(MultiYear_ProForma!$AF$2:$AF$66, MultiYear_ProForma!$B$2:$B$66, B14, MultiYear_ProForma!$C$2:$C$66, "FY2029")+SUMIFS(MultiYear_ProForma!$AF$2:$AF$66, MultiYear_ProForma!$B$2:$B$66, B14, MultiYear_ProForma!$C$2:$C$66, "FY2030"))/5 | H14: =(SUMIFS(MultiYear_ProForma!$AF$2:$AF$66, MultiYear_ProForma!$B$2:$B$66, B14, MultiYear_ProForma!$C$2:$C$66, "FY2026")+SUMIFS(MultiYear_ProForma!$AF$2:$AF$66, MultiYear_ProForma!$B$2:$B$66, B14, MultiYear_ProForma!$C$2:$C$66, "FY2027")+SUMIFS(MultiYear_ProForma!$AF$2:$AF$66, MultiYear_ProForma!$B$2:$B$66, B14, MultiYear_ProForma!$C$2:$C$66, "FY2028")+SUMIFS(MultiYear_ProForma!$AF$2:$AF$66, MultiYear_ProForma!$B$2:$B$66, B14, MultiYear_ProForma!$C$2:$C$66, "FY2029")+SUMIFS(MultiYear_ProForma!$AF$2:$AF$66, MultiYear_ProForma!$B$2:$B$66, B14, MultiYear_ProForma!$C$2:$C$66, "FY2030")) | I14: =SUMIFS(MultiYear_ProForma!$N$2:$N$66, MultiYear_ProForma!$B$2:$B$66, B14, MultiYear_ProForma!$C$2:$C$66, "FY2026") | J14: =SUMIFS(MultiYear_ProForma!$AC$2:$AC$66, MultiYear_ProForma!$B$2:$B$66, B14, MultiYear_ProForma!$C$2:$C$66, "FY2030") | K14: =F14/J14 | L14: =F14-(VLOOKUP($C$1,$B$5:$G$17,5, 0)) | M14: =G14-(VLOOKUP($C$1,$B$5:$J$17,6, 0))
A15: =LEFT(B15, 2) | B15: =Scenarios!A13 | C15: =SUMIFS(Capital_Summary!$H$4:$H$83, Capital_Summary!$A$4:$A$83, B15, Capital_Summary!$B$4:$B$83, "FY2026")*-1 | D15: =SUMIFS(MultiYear_ProForma!$AF$2:$AF$66, MultiYear_ProForma!$B$2:$B$66, B15, MultiYear_ProForma!$C$2:$C$66, "FY2026") | E15: =SUMIFS(MultiYear_ProForma!$AF$2:$AF$66, MultiYear_ProForma!$B$2:$B$66, B15, MultiYear_ProForma!$C$2:$C$66, "FY2028") | F15: =SUMIFS(MultiYear_ProForma!$AF$2:$AF$66, MultiYear_ProForma!$B$2:$B$66, B15, MultiYear_ProForma!$C$2:$C$66, "FY2030") | G15: =(SUMIFS(MultiYear_ProForma!$AF$2:$AF$66, MultiYear_ProForma!$B$2:$B$66, B15, MultiYear_ProForma!$C$2:$C$66, "FY2026")+SUMIFS(MultiYear_ProForma!$AF$2:$AF$66, MultiYear_ProForma!$B$2:$B$66, B15, MultiYear_ProForma!$C$2:$C$66, "FY2027")+SUMIFS(MultiYear_ProForma!$AF$2:$AF$66, MultiYear_ProForma!$B$2:$B$66, B15, MultiYear_ProForma!$C$2:$C$66, "FY2028")+SUMIFS(MultiYear_ProForma!$AF$2:$AF$66, MultiYear_ProForma!$B$2:$B$66, B15, MultiYear_ProForma!$C$2:$C$66, "FY2029")+SUMIFS(MultiYear_ProForma!$AF$2:$AF$66, MultiYear_ProForma!$B$2:$B$66, B15, MultiYear_ProForma!$C$2:$C$66, "FY2030"))/5 | H15: =(SUMIFS(MultiYear_ProForma!$AF$2:$AF$66, MultiYear_ProForma!$B$2:$B$66, B15, MultiYear_ProForma!$C$2:$C$66, "FY2026")+SUMIFS(MultiYear_ProForma!$AF$2:$AF$66, MultiYear_ProForma!$B$2:$B$66, B15, MultiYear_ProForma!$C$2:$C$66, "FY2027")+SUMIFS(MultiYear_ProForma!$AF$2:$AF$66, MultiYear_ProForma!$B$2:$B$66, B15, MultiYear_ProForma!$C$2:$C$66, "FY2028")+SUMIFS(MultiYear_ProForma!$AF$2:$AF$66, MultiYear_ProForma!$B$2:$B$66, B15, MultiYear_ProForma!$C$2:$C$66, "FY2029")+SUMIFS(MultiYear_ProForma!$AF$2:$AF$66, MultiYear_ProForma!$B$2:$B$66, B15, MultiYear_ProForma!$C$2:$C$66, "FY2030")) | I15: =SUMIFS(MultiYear_ProForma!$N$2:$N$66, MultiYear_ProForma!$B$2:$B$66, B15, MultiYear_ProForma!$C$2:$C$66, "FY2026") | J15: =SUMIFS(MultiYear_ProForma!$AC$2:$AC$66, MultiYear_ProForma!$B$2:$B$66, B15, MultiYear_ProForma!$C$2:$C$66, "FY2030") | K15: =F15/J15 | L15: =F15-(VLOOKUP($C$1,$B$5:$G$17,5, 0)) | M15: =G15-(VLOOKUP($C$1,$B$5:$J$17,6, 0))
A16: =LEFT(B16, 2) | B16: =Scenarios!A14 | C16: =SUMIFS(Capital_Summary!$H$4:$H$83, Capital_Summary!$A$4:$A$83, B16, Capital_Summary!$B$4:$B$83, "FY2026")*-1 | D16: =SUMIFS(MultiYear_ProForma!$AF$2:$AF$66, MultiYear_ProForma!$B$2:$B$66, B16, MultiYear_ProForma!$C$2:$C$66, "FY2026") | E16: =SUMIFS(MultiYear_ProForma!$AF$2:$AF$66, MultiYear_ProForma!$B$2:$B$66, B16, MultiYear_ProForma!$C$2:$C$66, "FY2028") | F16: =SUMIFS(MultiYear_ProForma!$AF$2:$AF$66, MultiYear_ProForma!$B$2:$B$66, B16, MultiYear_ProForma!$C$2:$C$66, "FY2030") | G16: =(SUMIFS(MultiYear_ProForma!$AF$2:$AF$66, MultiYear_ProForma!$B$2:$B$66, B16, MultiYear_ProForma!$C$2:$C$66, "FY2026")+SUMIFS(MultiYear_ProForma!$AF$2:$AF$66, MultiYear_ProForma!$B$2:$B$66, B16, MultiYear_ProForma!$C$2:$C$66, "FY2027")+SUMIFS(MultiYear_ProForma!$AF$2:$AF$66, MultiYear_ProForma!$B$2:$B$66, B16, MultiYear_ProForma!$C$2:$C$66, "FY2028")+SUMIFS(MultiYear_ProForma!$AF$2:$AF$66, MultiYear_ProForma!$B$2:$B$66, B16, MultiYear_ProForma!$C$2:$C$66, "FY2029")+SUMIFS(MultiYear_ProForma!$AF$2:$AF$66, MultiYear_ProForma!$B$2:$B$66, B16, MultiYear_ProForma!$C$2:$C$66, "FY2030"))/5 | H16: =(SUMIFS(MultiYear_ProForma!$AF$2:$AF$66, MultiYear_ProForma!$B$2:$B$66, B16, MultiYear_ProForma!$C$2:$C$66, "FY2026")+SUMIFS(MultiYear_ProForma!$AF$2:$AF$66, MultiYear_ProForma!$B$2:$B$66, B16, MultiYear_ProForma!$C$2:$C$66, "FY2027")+SUMIFS(MultiYear_ProForma!$AF$2:$AF$66, MultiYear_ProForma!$B$2:$B$66, B16, MultiYear_ProForma!$C$2:$C$66, "FY2028")+SUMIFS(MultiYear_ProForma!$AF$2:$AF$66, MultiYear_ProForma!$B$2:$B$66, B16, MultiYear_ProForma!$C$2:$C$66, "FY2029")+SUMIFS(MultiYear_ProForma!$AF$2:$AF$66, MultiYear_ProForma!$B$2:$B$66, B16, MultiYear_ProForma!$C$2:$C$66, "FY2030")) | I16: =SUMIFS(MultiYear_ProForma!$N$2:$N$66, MultiYear_ProForma!$B$2:$B$66, B16, MultiYear_ProForma!$C$2:$C$66, "FY2026") | J16: =SUMIFS(MultiYear_ProForma!$AC$2:$AC$66, MultiYear_ProForma!$B$2:$B$66, B16, MultiYear_ProForma!$C$2:$C$66, "FY2030") | K16: =F16/J16 | L16: =F16-(VLOOKUP($C$1,$B$5:$G$17,5, 0)) | M16: =G16-(VLOOKUP($C$1,$B$5:$J$17,6, 0))
A17: =LEFT(B17, 2) | B17: =Scenarios!A15 | C17: =SUMIFS(Capital_Summary!$H$4:$H$83, Capital_Summary!$A$4:$A$83, B17, Capital_Summary!$B$4:$B$83, "FY2026")*-1 | D17: =SUMIFS(MultiYear_ProForma!$AF$2:$AF$66, MultiYear_ProForma!$B$2:$B$66, B17, MultiYear_ProForma!$C$2:$C$66, "FY2026") | E17: =SUMIFS(MultiYear_ProForma!$AF$2:$AF$66, MultiYear_ProForma!$B$2:$B$66, B17, MultiYear_ProForma!$C$2:$C$66, "FY2028") | F17: =SUMIFS(MultiYear_ProForma!$AF$2:$AF$66, MultiYear_ProForma!$B$2:$B$66, B17, MultiYear_ProForma!$C$2:$C$66, "FY2030") | G17: =(SUMIFS(MultiYear_ProForma!$AF$2:$AF$66, MultiYear_ProForma!$B$2:$B$66, B17, MultiYear_ProForma!$C$2:$C$66, "FY2026")+SUMIFS(MultiYear_ProForma!$AF$2:$AF$66, MultiYear_ProForma!$B$2:$B$66, B17, MultiYear_ProForma!$C$2:$C$66, "FY2027")+SUMIFS(MultiYear_ProForma!$AF$2:$AF$66, MultiYear_ProForma!$B$2:$B$66, B17, MultiYear_ProForma!$C$2:$C$66, "FY2028")+SUMIFS(MultiYear_ProForma!$AF$2:$AF$66, MultiYear_ProForma!$B$2:$B$66, B17, MultiYear_ProForma!$C$2:$C$66, "FY2029")+SUMIFS(MultiYear_ProForma!$AF$2:$AF$66, MultiYear_ProForma!$B$2:$B$66, B17, MultiYear_ProForma!$C$2:$C$66, "FY2030"))/5 | H17: =(SUMIFS(MultiYear_ProForma!$AF$2:$AF$66, MultiYear_ProForma!$B$2:$B$66, B17, MultiYear_ProForma!$C$2:$C$66, "FY2026")+SUMIFS(MultiYear_ProForma!$AF$2:$AF$66, MultiYear_ProForma!$B$2:$B$66, B17, MultiYear_ProForma!$C$2:$C$66, "FY2027")+SUMIFS(MultiYear_ProForma!$AF$2:$AF$66, MultiYear_ProForma!$B$2:$B$66, B17, MultiYear_ProForma!$C$2:$C$66, "FY2028")+SUMIFS(MultiYear_ProForma!$AF$2:$AF$66, MultiYear_ProForma!$B$2:$B$66, B17, MultiYear_ProForma!$C$2:$C$66, "FY2029")+SUMIFS(MultiYear_ProForma!$AF$2:$AF$66, MultiYear_ProForma!$B$2:$B$66, B17, MultiYear_ProForma!$C$2:$C$66, "FY2030")) | I17: =SUMIFS(MultiYear_ProForma!$N$2:$N$66, MultiYear_ProForma!$B$2:$B$66, B17, MultiYear_ProForma!$C$2:$C$66, "FY2026") | J17: =SUMIFS(MultiYear_ProForma!$AC$2:$AC$66, MultiYear_ProForma!$B$2:$B$66, B17, MultiYear_ProForma!$C$2:$C$66, "FY2030") | K17: =F17/J17 | L17: =F17-(VLOOKUP($C$1,$B$5:$G$17,5, 0)) | M17: =G17-(VLOOKUP($C$1,$B$5:$J$17,6, 0))
B19: Note: Displaced = FY26; Served = FY30. Net = M&O − (Aid + Override + Uplift); showing one-time capital (fy26) as negative number for visualization purposes

Sheet What_Is_The_$900K-$1M_Savings

Sheet Parameters_Public
A1: Public Inputs — Audited Baselines and Overrides (Phase A) | C1: Yellow fields are editable
A3: ADM (official) | C3: Values | E3: Notes | I3: Notes2
B4: Echo 40th | C4: 257 | E4: Estimate used at this point; need to replace. Find official 40th day ADM for Echo (enter audited)
B5: Echo 100th | C5: 257 | E5: Estimate used at this point; need to replace. Find official 100th day ADM for Echo (enter audited)
B6: Pima 40th | C6: 296 | E6: Estimate used at this point; need to replace. Find official 40th day ADM for Pima (enter audited)
B7: Pima 100th | C7: 296 | E7: Estimate used at this point; need to replace. Find official 100th day ADM for Pima (enter audited)
B8: Use Day (40 or 100) | C8: 40 | E8: Choose which count the model uses (40 or 100).
B10: Echo_ADM0 (selected) | C10: =IF(C8=40,C4,C5) | E10: Model‑read Echo_ADM0 selected based on 40/100 day switch.
B11: Pima_ADM0 (selected) | C11: =IF(C8=40,C6,C7) | E11: Model‑read Pima_ADM0 selected based on 40/100 day switch.
A13: M&O/ADM (district), audited (ACFR)
B14: M_O_per_ADM_Audited | C14: 11589 | E14: Estimate used at this point. Enter the audited districtwide Maintenance & Operations cost per ADM from the latest ACFR/Adopted Budget. Used as the FY25 base.
A16: Override — property‑tax override
B17: Override percent | C17: 0.15 | E17: Districtwide override percent (e.g., 15%).
B18: Base aid per ADM (proxy for RCL per pupil) | C18: 5013 | E18: Proxy base for calculating per‑ADM override; replace with RCL per pupil if available.
B19: Override per ADM (proxy) | C19: =C17*C18 | E19: Computed per‑ADM amount used wherever the model needs a per‑student override term.
B20: Override toggle (1=on, 0=off) | C20: 1 | E20: Global on/off switch for including override in revenue calculations.
B21: Other General Fund revenue per served ADM (optional uplift) | C21: 5200 | E21: Everything not in “Base Aid + Override”: add‑on weights (e.g., SPED Group A/B), Transportation Support Level (TSL), and District Additional Assistance (DAA) — all components of the Equalization Base. (The Legislature’s primer shows Equalization Base = BSL + TSL + DAA, BLA = $5,013.33 in FY25. General Fund (Fund 001) revenues, FY2024 (actual): $192.213M (property taxes + state aid & grants). resources.finalsite.net Using SUSD’s FY2024 ACFR (audited): General Fund revenues (FY2024) = $215.4M (MD&A notes), General Fund expenditures = $233.7M. Scottsdale Unified School District Average Daily Membership (FY2024) = 19,748 (Operating Statistics table). Scottsdale Unified School District → GF revenue per ADM ≈ $215.4M / 19,748 ≈ $10,900/ADM. | I21: Using SUSD’s FY2024 ACFR (audited): General Fund revenues (FY2024) = $215.4M (MD&A notes), General Fund expenditures = $233.7M. Scottsdale Unified School District Average Daily Membership (FY2024) = 19,748 (Operating Statistics table). Scottsdale Unified School District → GF revenue per ADM ≈ $215.4M / 19,748 ≈ $10,900/ADM. State base amounts (policy context): FY2024 Base Level Amount (BLA) = $4,914.71. Arizona Department of Education FY2025 BLA = $5,013.33 (Senate research issue brief; also reiterates Equalization Base = BSL + TSL + DAA). Arizona Legislature Your model treats revenue as Aid (BLA‑based) + Override (+ optional uplift). To reconcile absolute Nets with audited magnitudes, we add an uplift that approximates everything in GF that isn’t “base + override,” e.g., TSL, DAA, formula add‑ons/weights, Prop 123 allocations, etc. (that’s what the Equalization Base framework is capturing when you aggregate components). Arizona Legislature Two reasonable calibration anchors: FY2024 basis: Uplift ≈ GF revenue per ADM − (BLA + Override) ≈ 10,900 − (4,914.71 + 0.15 × 4,914.71) ≈ 10,900 − (4,914.71 + 737) ≈ $5,250/ADM (rounded). Scottsdale Unified School District +2 Scottsdale Unified School District +2 FY2025 basis: Uplift ≈ 10,900 − (5,013.33 + 0.15 × 5,013.33) ≈ 10,900 − (5,013.33 + 752) ≈ $5,135/ADM (rounded). Scottsdale Unified School District +2 Scottsdale Unified School District +2 Uplift $5,100–$5,300/ADM is defensible on FY24 data and the state’s formula structure.
B22: Aid per ADM annual growth | C22: 0.025 | E22: Assuming aid grows around the same rate as cost inflation.
B23: Retention r — Echo (central) | C23: 0.6 | E23: Share of displaced Echo students re-enrolling in SUSD (0–1). As a choice school with 50% or more of families living outside the district, we can assume this will be lower than Pima.
B24: Retention r — Pima (central) | C24: 0.85 | E24: Share of displaced Pima students re-enrolling in SUSD (0–1). Not a significant amount of research on retention from closed schools; Chicago public retained 90%+ of students who were majority in boundaries when closing schools.
A26: Capital Treatment & Growth Capex (DRAFT placeholders)
B28: Include TI in Operating M&O? (0/1) | C28: 0 | E28: 0 = treat TI as capital (exclude from operating nets); 1 = include TI in Comparable_MO$
B29: TI per closed site (one-time) | C29: =BaselineCalc!$B$22 | E29: “TI” = tenant improvements / transition investments needed to convert a K‑8 to a different use (early learning, admin consolidation) and carry costs in year one (e.g., abatement, doors/security, low‑voltage re‑work, furniture, swing space); DRAFT Ops TI: Mirrors BaselineCalc TI unit; replace with capital plan when available
B30: Growth Capex — Arts Hub (one-time) | C30: 800000 | E30: DRAFT placeholder; enter benchmarked capital required to enable Arts hub
B31: Growth Capex — Innovation Hub (one-time) | C31: 1200000 | E31: DRAFT placeholder; enter benchmarked capital required for Innovation hub
B32: Include Growth Capex in Operating? (0/1) | C32: 0 | E32: 0 = treat growth capex as capital (recommended); 1 = include in Comparable_MO$ (what‑if only)
B33: TI per closed site (lease case) | C33: 800000 | E33: DRAFT: lease TI placeholder; separate from ops TI (C27)
B34: Portable seat cost (capital $ per seat) | C34: 12000 | E34: DRAFT: per-seat portables or TI to add seats at receivers
B35: Spare K–5 seats across receivers (FY26) | C35: 300 | E35: User input: available elementary seats to absorb retained K–5
B36: Spare 6–8 seats across receivers (FY26) | C36: 100 | E36: User input: available middle seats to absorb retained 6–8
B38: Echo K–5 share of ADM | C38: 0.7 | E38: DRAFT: distribution of Echo ADM by grade band
B39: Echo 6–8 share of ADM | C39: 0.3
B40: Pima K–5 share of ADM | C40: 1
B41: Pima 6–8 share of ADM | C41: 0
B43: MarginalFactor_for_Overlay (central source) | C43: 0.6 | E43: Assuming marginal cost (as a function of standard variable cost per student) of new students from growth (assuming there is available capacity in Echo and Pima; ideally, this would be a step function)
B44: Echo ADM trend default | C44: -0.02 | E44: Default enrollment trend from forecasts; placeholder value for now -- need to verify this
B45: Pima ADM trend default | C45: -0.02 | E45: Default enrollment trend from forecasts; placeholder value for now -- need to verify this
B47: Growth overhead per added ADM (α × h) | C47: 0.2 | E47: Assuming some incremental transportation overhead for growth-related new students; we model it as a percentage of closed school transition-related incremental transportation overhead
B49: Incremental uplift alpha (overlay share of base uplift) | C49: 0.85 | E49: Applied only to Overlay_ADM; keeps marginal revenue conservative because some ‘other GF’ (weights/TSL/DAA) don’t scale 1:1. Typical range 0.70–0.90 (default 0.85).

Sheet Inputs_Definitions_Sources
A1: Audited & Policy Anchors (paste into Parameters when available)
A2: Anchor | B2: Value / Status | C2: Source (short) | D2: Used for | E2: Owner | F2: Paste location | G2: Source URL
A3: BLA (Base Level Amount) FY2025 | B3: 5,013.33 | C3: AZ Senate Issue Brief / ADE update | D3: YearMap → Aid$ | E3: Finance | F3: Parameters_Public!C18 or BaselineCalc | G3: https://www.azleg.gov/Briefs/Senate/ARIZONA%27S%20SCHOOL%20FINANCE%20SYSTEM%202024.PDF
A4: M&O Override % | B4: 15% (RCL) | C4: SUSD M&O Override page | D4: Override per ADM; Revenue$ | E4: Finance | F4: Parameters_Public!C17 | G4: https://www.susd.org/Page/658
A5: Override toggle | B5: 0/1 (board policy) | C5: Model control | D5: Revenue$ switch | E5: Model | F5: Parameters_Public!C20
A6: District M&O per ADM (audited) | B6: FY2024 value (e.g., 14,049) | C6: SUSD ACFR FY2024, Operating Statistics | D6: Sanity checks / narratives | E6: Finance | F6: Parameters_Public!C14
A7: Transportation Support Level (TSL) | B7: Per route‑mile schedule | C7: AZ Senate Issue Brief / ADE | D7: Revenue context | E7: Finance | F7: Definitions_Sources | G7: https://www.azed.gov/finance/fy2025-school-finance-fiscal-operations-updates
A8: Transport cost per eligible rider | B8: ≈ 3,183 (FY2024 anchor) | C8: City of Scottsdale Auditor report | D8: h₀ (retention overhead) anchor | E8: Ops | F8: Control_Center | G8: https://www.scottsdaleaz.gov/docs/default-source/scottsdaleaz/auditor/2025-reports/susd-transportation---audit-2508.pdf?sfvrsn=144e4f2d_1
A9: Echo/Pima 40th & 100th (FY2025) | B9: To paste (AzEDS export SDADMS72/75) | C9: ADE School Finance / District export | D9: Base ADM by site | E9: Data | F9: Parameters_Public | G9: https://www.ade.az.gov/schoolfinance/Reports
A10: Site‑fixed ledgers (Fund 001, by site) | B10: To paste (Echo & Pima) | C10: SUSD Finance site/cost‑center ledgers | D10: Replace fallback fixed | E10: Finance | F10: Site_Fixed | G10: https://www.azauditor.gov/arizona-school-district-spending-fiscal-year-2024-analysis-and-data-file
A12: Core Definitions & Derivations
A13: Term | B13: Definition / Formula | C13: Appears on | D13: Depends on | E13: Notes | F13: Named range (if any)
A14: Operating Net ($) | B14: M&O − (Aid + Override + Uplift); capital excluded. | C14: Summary_Figures; Scenario_Comparison; Board_OnePager | D14: YearMap revenues, MultiYear_ProForma costs | E14: Fund 001 lens only.
A15: Δ vs Base (FY2030) | B15: Comparator FY2030 Net − Base FY2030 Net. | C15: Summary_Figures; Scenario_Comparison | D15: Net$
A16: Δ vs Base (Avg FY26–30) | B16: Comparator 5‑yr Avg Net − Base 5‑yr Avg Net. | C16: Summary_Figures; Scenario_Comparison | D16: Net$ FY26..30
A17: Displaced (FY26) | B17: Displaced students in first action year. | C17: Summary_Figures; Scenario_Comparison | D17: Scenario mechanics
A18: Served (FY2030) | B18: Open + retained ADM in FY2030. | C18: Summary_Figures; Scenario_Comparison | D18: Served_ADM (MPF col AC)
A19: Comparable net per served | B19: FY2030 Net ÷ FY2030 Served_ADM. | C19: Optional on Summary_Figures | D19: Net$, Served_ADM | E19: Normalization when served counts differ.
A20: mᵗ (incremental margin per ADM) | B20: Aid + Override_if_on + Uplift − VarUnit$ − g | C20: Budget_Neutral_Calculator | D20: YearMap; Override_toggle | E20: Year‑specific.
A21: N⁰ (budget‑neutral students) | B21: max(0, −Netₜ / mᵗ) | C21: Budget_Neutral_Calculator | D21: mᵗ; Netₜ | E21: Shown for FY26 & FY30.
A22: Uplift (base) | B22: Other GF per served ADM; indexed with Aid growth. | C22: YearMap (Uplift_per_ADM) | D22: Aid_growth; Uplift_base_per_ADM | F22: Uplift_base_per_ADM
A23: Uplift (incremental) | B23: α × Uplift(base) applied to Overlay_ADM only. | C23: YearMap; Revenue$ | D23: Incremental_uplift_alpha | E23: Keeps marginal revenue conservative. | F23: Incremental_uplift_alpha
A24: Retention overhead (h) | B24: Routing/admin overhead per retained student; tapers annually. | C24: YearMap (h) | D24: h_taper_profile | E24: First‑year set from transport cost anchor. | F24: h_taper_profile
A25: Growth overhead (g) | B25: α × h applied to Overlay_ADM. | C25: YearMap (Growth_overhead_per_ADM) | D25: Growth_overhead_alpha; h_taper_profile | E25: Smaller than h; symmetry with repurpose. | F25: Growth_overhead_alpha
A26: Fixed savings realization | B26: Savings = (1−f)×SiteFixed$; f_ops, f_lease ramp FY26→FY30. | C26: MPF (EchoFixedEff$, PimaFixedEff$) | D26: f_ops_profile; f_lease_profile; Site_Fixed | E26: Replace fallback with audited site‑fixed. | F26: f_ops_profile; f_lease_profile
A27: Trend gates | B27: Apply_Echo_Trend / Apply_Pima_Trend toggle Potential_ADM by site. | C27: Scenarios; MPF | D27: Scenarios columns R/S; Parameters_Public trends | E27: On by scenario.
A28: ADM (Average Daily Membership) | B28: Unweighted attendance measure used for funding: membership days through the first 100 instructional days (or 200 for year-round) divided by days in period; see A.R.S. 15-901(1). | C28: Parameters; Baselines; Narrative | D28: ADE statute/SDADMS calculations | E28: Pre-K typically excluded from ADM for formula funding.
A29: Variable unit cost (VarUnit$)
A30: Marginal-cost factor for overlay seats | B30: Factor (<1) scaling VarUnit$ on overlay ADM to reflect partial sectioning in slack capacity years. | C30: MultiYear_Pro_Forma | D30: Parameters_Public MarginalFactor_for_Overlay | E30: Default 0.50; tune with scheduling/sectioning review.
A31: Retention rate r | B31: Share of displaced students who stay in SUSD and are re-routed to receiving sites; they remain in Served_ADM and incur h. | C31: Scenarios; MultiYear_Pro_Forma | D31: Parameters_Public r values | E31: Higher r keeps revenue but increases overhead h.
A32: Co-location extra savings | B32: Additional operating savings (beyond standard f_ops) modeled when consolidating two programs on one site. | C32: Scenarios; MultiYear_Pro_Forma | D32: Control_Center setting; scenario flags | E32: Small effect; fine-tune with facilities/ops.
A33: Keep-open ops savings | B33: Minor efficiency factor applied to scenarios that keep a site open (e.g., utilities, scheduling refinements). | C33: Scenarios; MultiYear_Pro_Forma | D33: Control_Center setting | E33: Small symmetric adjustment for fairness.
A35: Repurpose-related pathway parameters
A36: Gate / Mechanism | B36: How enforced in model | C36: What to watch | D36: Where implemented | E36: Notes | F36: Owner
A37: Receiving capacity gate | B37: Band‑level spare seats + portables; flag if exceeded. | C37: No site over capacity. | D37: Receiving_Capacity; Scenario_Comparison | F37: Planning
A38: Quality gate (optional)
A39: Retention gate | B39: Retention r applied to displaced cohorts. | C39: Measure r achieved. | D39: Parameters_Public; MPF | E39: Supports r* framing if needed. | F39: Enrollment
A40: Budget neutrality | B40: N⁰ calculator for FY26/FY30. | C40: N⁰ = 0 means Net≥0. | D40: Budget_Neutral_Calculator | E40: Scenario‑specific. | F40: Finance
A41: Fixed savings realization | B41: f_ops/f_lease ramp applied to site‑fixed. | C41: Use audited site‑fixed; avoid over‑crediting. | D41: YearMap; MPF | F41: Finance/Ops
A43: Audit paste checklist (to finalize model)
A44: Data item | B44: Status | C44: Source | D44: Paste location | E44: Note
A45: Echo—site‑fixed (Fund 001 by function) | B45: Pending | C45: SUSD Finance site ledger | D45: Site_Fixed | E45: Using estimated figures in site_fixed tab for now
A46: Pima—site‑fixed (Fund 001 by function) | B46: Pending | C46: SUSD Finance site ledger | D46: Site_Fixed | E46: Using estimated figures in site_fixed tab for now
A47: Echo/Pima 40th/100th (FY2025) | B47: Pending | C47: AzEDS SDADMS72/75 export | D47: Parameters_Public
A48: Transport cost unit anchors | B48: Drafted | C48: City of Scottsdale audit | D48: Control_Center (h₀; α)
A50: Other items / additional descriptions
A51: Item | B51: What | C51: Detail
A52: ADM | B52: ADM stands for Average Daily Membership. It is the primary metric used by the state of Arizona to determine funding for a school district. What it is: ADM is essentially the official student count. It is not based on how many students are present on any single day (that would be average daily attendance), but rather on how many students are officially enrolled in the district. | C52: How it's calculated: The state uses enrollment data from specific points in the school year to generate an average. This average, the ADM, becomes the official "student count" for that fiscal year. Why it matters: Nearly all state funding is allocated on a per-student basis using ADM. This number is multiplied by various weights (e.g., for high school students, special education, etc.) to create a "weighted student count," which is the foundational number for calculating the district's total state aid. An audit of SUSD's ADM, for example, is a check to ensure the district reported its enrollment correctly and received the proper amount of funding.
A53: M&O | B53: M&O stands for Maintenance and Operations. This is the largest and most important part of a school district's budget. What it is: The M&O budget is the "bucket" of money that pays for all the day-to-day, non-capital expenses of running the school district. It is the district's operating budget. | C53: What it pays for: Salaries and benefits for all employees (teachers, principals, support staff, administrators) Classroom supplies (textbooks, software, paper, etc.) Utilities (electricity, water, gas) Transportation (bus fuel and maintenance) Student services and athletics
A54: Base state aid per pupil (FY2025) | B54: Revenue per ADM in “Aid per ADM” line; grown by CPI in out‑years (model uses a placeholder near $5.1k) | C54: Arizona FY2025 budget bill (HB 2906) sets the base level per pupil at $5,013 for FY2025. ADE School Finance memo for FY2025 base level (final), plus any FY2026 update; SUSD’s per‑pupil revenue schedule (by weight) if would like to add K‑8 weights locally. Arizona Senate Issue Brief – K‑12 School Finance (official, widely used reference). Shows the Base Level Amount (FY 2024‑25 = $5,013.33), the factor that (with district weights) drives state aid. ADE lists the same figure in its finance materials.
A55: Echo Canyon base ADM (≈257) | B55: Baseline students “served” in keep‑open scenarios | C55: ADE School Report Cards / Arizona Education Profiles (school pages) + SUSD 40th‑day board reports for Echo Canyon’s latest K‑8 enrollment ADE school page data used. SUSD October (40th‑day) ADM sheet listing Echo Canyon K‑8 ADM (most recent year) and the same for the prior 3 years.
A56: Pima base ADM (≈296) | B56: Baseline students “served” in keep‑open scenarios | C56: ADE School Report Cards page for Pima Traditional (enrollment tile). The “Enrollment” 🛈 on that page for the specific year has enrollment data.
A57: District M&O (Fund 001) context | B57: Grounds the “M&O per ADM” baseline used in comparable $/student | C57: From ACFR or adopted budget: Fund 001 totals and function detail by object/function; district ADM used in budget; site‑level M&O if available. | D57: Scottsdale USD ACFR FY2024 (annual comprehensive financial report) — Fund statements and notes establish M&O (Fund 001) totals and function splits (instruction, plant ops, admin, etc.). We used it to sanity‑check the order of magnitude for per‑pupil operating cost. (Scottsdale Unified School District)
A58: “Fixed‑like” share of M&O (used conservative placeholder) | B58: Splits total M&O into “semi‑fixed” (plant ops, insurance, admin, central) vs “variable” (classroom sections, supplies, a slice of transport) to compute EchoFixed$ and PimaFixed$ | C58: SUSD site‑level: plant ops/maintenance, insurance, utilities, admin FTE & benefits at Echo/Pima. Can use that to replace the proxy with real fixed amounts. The file allocates the fixed share across the two schools pro‑rata (by base ADM) as a temporary step. Can replace with the actual plant ops/insurance/utilities/admin for each site from Fund 001 to remove that simplification. | D58: Arizona Auditor General – Arizona School District Spending – FY2024 portal (official statewide analysis). The Overview and category definitions show the functional buckets (instruction, administration, plant operations & maintenance, student support, etc.) districts report and that we treat as the “more fixed‑like” categories. (sdspending.azauditor.gov)
A59: Overlay | B59: Using this term in the spreadsheet to mean addition of new students (growth) | C59: Not an official district term; just using in this spreadsheet
A60: Variable unit cost (VarUnit$) | B60: $ per student applied to “served ADM,” plus marginal‑cost factor on overlay seats | C60: Assumption derived from Fund 001 minus fixed share, divided by total ADM; then Marginal factor (see below) reduces cost for overlay seats. Can tighten with SUSD staffing ratios & actual sectioning at K–8; confirm what portion of M&O truly scales with added sections (teachers, aides, supplies, a slice of transport).
A61: Marginal‑cost factor for overlay seats | B61: Applies only to overlay growth students in keep‑open scenarios; models that not every dollar is average cost | C61: Can tighten with SUSD’s teacher‑section & aide staffing rules, average class sizes, and any marginal staffing adders at K–8 (arts, specialists). | D61: Assumption w/ rationale: Roughly half of per‑pupil cost is staffing/supplies/transport that scale with sections; the remainder is semi‑fixed plant/admin. This aligns with Auditor General function splits and is intentionally conservative. We’ll replace with SUSD’s staffing & plant data if provided. (Sun Devil Central)
A62: Receiving overhead “h” (FY26 $1,000 → FY30 $300) | B62: Per retained student transition/route/admin cost added when a site is repurposed; tapers as routes stabilize | C62: Assumption with AZ context: AZ districts’ transport spend per rider is often $2k–$3k (statewide average $2,862 cited in a district budget narrative), so $1,000 tapering to $300 is a conservative placeholder for incremental cost, not full bus cost. Can tighten with SUSD transportation cost per route-hour, average riders per route, and the specific route changes proposed in the repurpose option.
A63: Retention rate “r” (central 0.75; sensitivities 0.65–0.85) | B63: Share of displaced Echo+Pima students who remain in SUSD (the rest leave choose other options) | C63: SUSD post‑closure enrollment tracking (where displaced students re‑enroll), by receiving school; use that to set “r” from observed data. | D63: Assumption, benchmarked to closure research: large‑district closure work (e.g., Chicago) shows most students remain in‑district the next year (CPS analyses place that figure well above half); retention varies with hand‑off quality and distance. We model 65–85% to bracket. (UChicago Consortium on School Research) Large‑district evidence: UChicago Consortium’s analyses of the 2013 CPS closures found most displaced students remained in district the next year; outcomes varied with the quality and distance of receiving schools. That supports using a central r ~ 0.75 with a band. UChicago Consortium on School Research What we could not find in AZ: districts rarely publish explicit post‑closure retention; we can proxy from post‑closure enrollment by receiving schools if SUSD shares it. Echo nuance: Because Echo is open‑enrollment and draws many out‑of‑district students, those families may be less likely to follow to a different SUSD school after a closure (they already cross a boundary by choice). That argues for running a lower Echo‑weighted r scenario (e.g., 0.55–0.65) in addition to the district‑wide 0.65–0.85 band.
A64: Carry fractions f_ops / f_lease (e.g., 0.40 → 0 by FY30) | B64: Share of each site’s fixed costs that persist after repurpose under ops mothball vs lease/sale | C64: Assumption pending facilities plan. The glide‑path (e.g., 40%→30%→20%→10%→0%) reflects how fast plant/insurance/utilities can be retired or passed to a tenant.
A65: TI / one‑time repurpose costs (e.g., $2.4M) | B65: “TI_adds$” in the pro‑forma for the first 1–2 years. Why “Repurpose TI per closed site (FY26) = $1.2M”? What is “one‑time carry/TI”? “TI” = tenant improvements / transition investments needed to convert a K‑8 to a different use (early learning, admin consolidation) and carry costs in year one (e.g., abatement, doors/security, low‑voltage re‑work, furniture, swing space). A light‑touch repurpose can easily run $10–$20/sq‑ft; Echo’s plant is ~77k sq ft, so $1.2M is a reasonable placeholder (we are not assuming a huge remodel). Can replace this with SUSD’s scope/estimate if they have one. | C65: Tighten with SUSD engineering estimate for tenant improvements or district reconfiguration (scope, cost, which fund, and amortization).
A66: Extra cost savings for co-location scenario | B66: Why “Extra savings (co‑location) = 0.015 (1.5%)”? This reflects incremental savings from consolidating some services on one campus (custodial/grounds/partial routing). Again kept small and conservative; can use real custodial (sq‑ft), grounds and route deltas if available. | C66: https://legiscan.com/AZ/text/HB2969/2025?utm_source=chatgpt.com
A67: Ops savings (for keep-open scenarios) | B67: Ops savings (keep‑open) = 0.007 (0.7%)”? This represents “light discipline” (utilities/purchasing tweaks, route smoothing) that does not depend on closing a site. Set low on purpose so it doesn’t drive results. Can calibrate with SUSD data (e.g., last year’s utility audits) if provided.
A68: K–8 capacity / square footage | B68: Context for “utilization” and whether overlay targets are feasible | C68: To be anchored to SFB (AZ School Facilities Board) capacity files and SUSD construction docs. SUSD/SFB: design capacity and current utilization for Echo & Pima (post‑rebuild specs for Pima).
A69: Pre‑K contribution | B69: Excluded from ADM and revenue in the model (unless tuition/lease modeled) | C69: If SUSD intends district‑operated tuition Pre‑K on site, can request pro forma for net contribution (tuition – staffing – TI). | D69: Supported by statute & ADE finance practice—general Pre‑K does not generate state ADM (exception: SPED preschool). (Arizona Department of Education)
A70: ADM definition (what “counts”) | B70: Explains why Pre‑K is excluded and why K can count at 0.5; supports “served” math | C70: SUSD’s 40th‑day and 100th‑day ADM certification for Echo and Pima (K–8 breakouts). | D70: A.R.S. §15‑901 and legislative fact sheet: Kindergarten generates 0.5 ADM unless full‑time; ADM is a statutory count, and preschool is generally not included in ADM (except some SPED programs). (LegiScan)
A71: MarginalFactor_for_Overlay | B71: Fraction of average per‑ADM MO$ that applies to added students when you grow keep‑open schools. | C71: Default 0.50 (i.e., ~half of average cost is truly variable: teachers/sections, supplies, some transport; the rest is plant/admin which doesn’t scale 1:1). | D71: Grounded in function splits from AAG/USFR: plant/admin/central ≈ 30–40% semi‑fixed, instruction/ops ≈ 60–70% variable; we start at 0.50 to be conservative. (Auditor General) | E71: If we get class‑size/FTE trigger rules, we can upgrade this to step‑functions (sections) by grade.
A72: Site_fixed tab | B72: Utilities are included in plant ops sub-cateogry for now, as an educated estimate was made from district budget information that does not de-couple utilities from plant ops. | C72: To be replaced with audited data when available.

Sheet Scenarios
C1: Yellow fields are editable
A2: ScenarioKey | B2: Label | C2: Enrollment add over 3 years | D2: CloseEcho (0 = no; 1 = yes) | E2: ClosePima (0 = no; 1 = yes) | F2: EchoShareDist (share of enrollment adds) | G2: ExtraSave (cost efficiency assumption) | H2: Notes | I2: Overlay_FY26 | J2: Overlay_FY27 | K2: Overlay_FY28 | L2: Overlay_FY29 | M2: Overlay_FY30 | N2: Carry | O2: Growth_Echo | P2: Growth_Pima | Q2: Apply_Echo_Trend | R2: Apply_Pima_Trend
A3: F1_CUSTOM1 | B3: CUSTOM_KeepOpen_v1 | C3: 0 | D3: 0 | E3: 0 | F3: 0.5 | G3: 0 | H3: Baseline + outreach; no closures | I3: =C3/3 | J3: =I3+C3/3 | K3: =J3+C3/3 | L3: =C3 | M3: =C3 | O3: None | P3: None | Q3: 0 | R3: 0
A4: D4_StatusQuo_Targets | B4: Echo & Pima open; uplift warm handoff effort (intra-SUSD); initiate cross-district marketing | C4: 75 | D4: 0 | E4: 0 | F4: 0.5 | G4: 0 | H4: Baseline + targets; no closures | I4: =C4/3 | J4: =I4+C4/3 | K4: =J4+C4/3 | L4: =C4 | M4: =C4 | O4: None | P4: None | Q4: 0 | R4: 0
A5: D3_CoLocation_Echo_Targets | B5: Echo & Pima open; co-locate e.g. district teacher learning center at Echo; uplift warm handoff effort (intra-SUSD); initiate cross-district marketing | C5: 50 | D5: 0 | E5: 0 | F5: 0.5 | G5: 0.05 | H5: Shared‑use efficiencies (no closure) | I5: =C5/3 | J5: =I5+C5/3 | K5: =J5+C5/3 | L5: =C5 | M5: =C5 | O5: None | P5: None | Q5: 0 | R5: 0
A6: D1_Grow_Both_Targets | B6: Echo & Pima open; growth initiatives Echo (e.g. innovation) & Pima (e.g. arts); uplift warm handoff effort (intra-SUSD); initiate cross-district marketing | C6: 150 | D6: 0 | E6: 0 | F6: 0.5 | G6: 0 | H6: Baseline + growth initiatives | I6: =C6/3 | J6: =I6+C6/3 | K6: =J6+C6/3 | L6: =C6 | M6: =C6 | O6: Innov | P6: Arts | Q6: 0 | R6: 0
A7: E2_StatusQuo_Steady | B7: Echo & Pima open; no operational or strategic growth actions; no change in enrollment | C7: 0 | D7: 0 | E7: 0 | F7: 0.5 | G7: 0 | H7: Baseline steady enrollment | I7: =C7/3 | J7: =I7+C7/3 | K7: =J7+C7/3 | L7: =C7 | M7: =C7 | O7: None | P7: None | Q7: 0 | R7: 0
A8: D2_EchoGHubRamp_PimaTargets | B8: Echo & Pima open; growth initiative Echo (e.g. arts); no growth initiative Pima; uplift warm handoff effort (intra-SUSD); initiate cross-district marketing | C8: 125 | D8: 0 | E8: 0 | F8: 0.7 | G8: 0 | H8: Time‑phased ramp over years 1-3 | I8: =C8/3 | J8: =I8+C8/3 | K8: =J8+C8/3 | L8: =C8 | M8: =C8 | O8: Arts | P8: None | Q8: 0 | R8: 0
A9: A2_Repurpose_Both_lease | B9: Repurpose both Echo & Pima; lease both properties; fixed cost reduction rate, retention %, and transition cost assumptions are key drivers | C9: 0 | D9: 1 | E9: 1 | F9: 0.5 | G9: 0 | H9: Repurpose both; lease/sale glide | I9: =C9/3 | J9: =I9+C9/3 | K9: =J9+C9/3 | L9: =C9 | M9: =C9 | N9: lease | O9: None | P9: None | Q9: 0 | R9: 0
A10: A1_Repurpose_Both_ops | B10: Repurpose both Echo & Pima; operationally convert both properties (e.g. early learning center); fixed cost reduction rate, retention %, and transition cost assumptions are key drivers | C10: 0 | D10: 1 | E10: 1 | F10: 0.5 | G10: 0 | H10: Repurpose both; operations carry | I10: =C10/3 | J10: =I10+C10/3 | K10: =J10+C10/3 | L10: =C10 | M10: =C10 | N10: ops | O10: None | P10: None | Q10: 0 | R10: 0
A11: B2_Repurpose_Echo_lease_PimaTargets | B11: Repurpose ECHO (lease) + Growth Hub @ Pima + Pima Op Growth Targets | C11: 50 | D11: 1 | E11: 0 | F11: 0 | G11: 0 | H11: Repurpose Echo only; lease glide | I11: =C11/3 | J11: =I11+C11/3 | K11: =J11+C11/3 | L11: =C11 | M11: =C11 | N11: lease | O11: None | P11: Arts | Q11: 0 | R11: 0
A12: B1_Repurpose_Echo_ops_PimaTargets | B12: Repurpose ECHO (ops) + Growth Hub @ Pima + Pima Op Growth Targets | C12: 50 | D12: 1 | E12: 0 | F12: 0 | G12: 0 | H12: Repurpose Echo only; ops carry | I12: =C12/3 | J12: =I12+C12/3 | K12: =J12+C12/3 | L12: =C12 | M12: =C12 | N12: ops | O12: None | P12: Arts | Q12: 0 | R12: 0
A13: C2_Repurpose_Pima_lease_EchoGHub_EchoTargets | B13: Repurpose PIMA (lease) + Growth Hub @ Echo + Echo Op Growth Targets | C13: 50 | D13: 0 | E13: 1 | F13: 1 | G13: 0 | H13: Repurpose Pima only; lease glide | I13: =C13/3 | J13: =I13+C13/3 | K13: =J13+C13/3 | L13: =C13 | M13: =C13 | N13: lease | O13: Arts | P13: None | Q13: 0 | R13: 0
A14: C1_Repurpose_Pima_ops_EchoGHub_EchoTargets | B14: Repurpose PIMA (ops) + Growth Hub @ Echo + Echo Op Growth Targets | C14: 50 | D14: 0 | E14: 1 | F14: 1 | G14: 0 | H14: Repurpose Pima only; ops carry | I14: =C14/3 | J14: =I14+C14/3 | K14: =J14+C14/3 | L14: =C14 | M14: =C14 | N14: ops | O14: Arts | P14: None | Q14: 0 | R14: 0
A15: E1_StatusQuo_Decline | B15: Echo & Pima open; no operational or strategic growth actions; enrollment decline trend continues | C15: 0 | D15: 0 | E15: 0 | F15: 0 | G15: 0 | H15: Keep open but decline per district forecast | I15: =C15/3 | J15: =I15+C15/3 | K15: =J15+C15/3 | L15: =C15 | M15: =C15 | O15: None | P15: None | Q15: 1 | R15: 1
A27: ScenarioKey | B27: Year | C27: Echo_ADM | D27: Pima_ADM | E27: Total_ADM | F27: VarUnit$ | G27: EchoFixed$ | H27: PimaFixed$ | I27: Key | O27: None | P27: None
A28: =A3 | B28: FY2026 | C28: =IF(D3=1,0, BaselineCalc!$B$7 + ROUND(I3*F3,0)) | D28: =IF(E3=1,0, BaselineCalc!$B$8 + I3 - ROUND(I3*F3,0)) | E28: =C28+D28 | F28: =YearMap!B2 | G28: =YearMap!C2 | H28: =YearMap!D2 | I28: =A28&"|"&B28 | O28: None | P28: None
A29: =A3 | B29: FY2027 | C29: =IF(D3=1,0, BaselineCalc!$B$7 + ROUND(J3*F3,0)) | D29: =IF(E3=1,0, BaselineCalc!$B$8 + J3 - ROUND(J3*F3,0)) | E29: =C29+D29 | F29: =YearMap!B3 | G29: =YearMap!C3 | H29: =YearMap!D3 | I29: =A29&"|"&B29 | O29: None | P29: None
A30: =A3 | B30: FY2028 | C30: =IF(D3=1,0, BaselineCalc!$B$7 + ROUND(K3*F3,0)) | D30: =IF(E3=1,0, BaselineCalc!$B$8 + K3 - ROUND(K3*F3,0)) | E30: =C30+D30 | F30: =YearMap!B4 | G30: =YearMap!C4 | H30: =YearMap!D4 | I30: =A30&"|"&B30 | O30: None | P30: None
A31: =A3 | B31: FY2029 | C31: =IF(D3=1,0, BaselineCalc!$B$7 + ROUND(L3*F3,0)) | D31: =IF(E3=1,0, BaselineCalc!$B$8 + L3 - ROUND(L3*F3,0)) | E31: =C31+D31 | F31: =YearMap!B5 | G31: =YearMap!C5 | H31: =YearMap!D5 | I31: =A31&"|"&B31 | O31: None | P31: None
A32: =A3 | B32: FY2030 | C32: =IF(D3=1,0, BaselineCalc!$B$7 + ROUND(M3*F3,0)) | D32: =IF(E3=1,0, BaselineCalc!$B$8 + M3 - ROUND(M3*F3,0)) | E32: =C32+D32 | F32: =YearMap!B6 | G32: =YearMap!C6 | H32: =YearMap!D6 | I32: =A32&"|"&B32 | O32: None | P32: None
A33: =A4 | B33: FY2026 | C33: =IF(D4=1,0, BaselineCalc!$B$7 + ROUND(I4*F4,0)) | D33: =IF(E4=1,0, BaselineCalc!$B$8 + I4 - ROUND(I4*F4,0)) | E33: =C33+D33 | F33: =YearMap!B2 | G33: =YearMap!C2 | H33: =YearMap!D2 | I33: =A33&"|"&B33 | O33: None | P33: None
A34: =A4 | B34: FY2027 | C34: =IF(D4=1,0, BaselineCalc!$B$7 + ROUND(J4*F4,0)) | D34: =IF(E4=1,0, BaselineCalc!$B$8 + J4 - ROUND(J4*F4,0)) | E34: =C34+D34 | F34: =YearMap!B3 | G34: =YearMap!C3 | H34: =YearMap!D3 | I34: =A34&"|"&B34 | O34: None | P34: None
A35: =A4 | B35: FY2028 | C35: =IF(D4=1,0, BaselineCalc!$B$7 + ROUND(K4*F4,0)) | D35: =IF(E4=1,0, BaselineCalc!$B$8 + K4 - ROUND(K4*F4,0)) | E35: =C35+D35 | F35: =YearMap!B4 | G35: =YearMap!C4 | H35: =YearMap!D4 | I35: =A35&"|"&B35 | O35: None | P35: None
A36: =A4 | B36: FY2029 | C36: =IF(D4=1,0, BaselineCalc!$B$7 + ROUND(L4*F4,0)) | D36: =IF(E4=1,0, BaselineCalc!$B$8 + L4 - ROUND(L4*F4,0)) | E36: =C36+D36 | F36: =YearMap!B5 | G36: =YearMap!C5 | H36: =YearMap!D5 | I36: =A36&"|"&B36 | O36: None | P36: None
A37: =A4 | B37: FY2030 | C37: =IF(D4=1,0, BaselineCalc!$B$7 + ROUND(M4*F4,0)) | D37: =IF(E4=1,0, BaselineCalc!$B$8 + M4 - ROUND(M4*F4,0)) | E37: =C37+D37 | F37: =YearMap!B6 | G37: =YearMap!C6 | H37: =YearMap!D6 | I37: =A37&"|"&B37 | O37: None | P37: None
A38: =A5 | B38: FY2026 | C38: =IF(D5=1,0, BaselineCalc!$B$7 + ROUND(I5*F5,0)) | D38: =IF(E5=1,0, BaselineCalc!$B$8 + I5 - ROUND(I5*F5,0)) | E38: =C38+D38 | F38: =YearMap!B2 | G38: =YearMap!C2 | H38: =YearMap!D2 | I38: =A38&"|"&B38 | O38: None | P38: None
A39: =A5 | B39: FY2027 | C39: =IF(D5=1,0, BaselineCalc!$B$7 + ROUND(J5*F5,0)) | D39: =IF(E5=1,0, BaselineCalc!$B$8 + J5 - ROUND(J5*F5,0)) | E39: =C39+D39 | F39: =YearMap!B3 | G39: =YearMap!C3 | H39: =YearMap!D3 | I39: =A39&"|"&B39 | O39: None | P39: None
A40: =A5 | B40: FY2028 | C40: =IF(D5=1,0, BaselineCalc!$B$7 + ROUND(K5*F5,0)) | D40: =IF(E5=1,0, BaselineCalc!$B$8 + K5 - ROUND(K5*F5,0)) | E40: =C40+D40 | F40: =YearMap!B4 | G40: =YearMap!C4 | H40: =YearMap!D4 | I40: =A40&"|"&B40 | O40: None | P40: None
A41: =A5 | B41: FY2029 | C41: =IF(D5=1,0, BaselineCalc!$B$7 + ROUND(L5*F5,0)) | D41: =IF(E5=1,0, BaselineCalc!$B$8 + L5 - ROUND(L5*F5,0)) | E41: =C41+D41 | F41: =YearMap!B5 | G41: =YearMap!C5 | H41: =YearMap!D5 | I41: =A41&"|"&B41 | O41: None | P41: None
A42: =A5 | B42: FY2030 | C42: =IF(D5=1,0, BaselineCalc!$B$7 + ROUND(M5*F5,0)) | D42: =IF(E5=1,0, BaselineCalc!$B$8 + M5 - ROUND(M5*F5,0)) | E42: =C42+D42 | F42: =YearMap!B6 | G42: =YearMap!C6 | H42: =YearMap!D6 | I42: =A42&"|"&B42 | O42: None | P42: None
A43: =A6 | B43: FY2026 | C43: =IF(D6=1,0, BaselineCalc!$B$7 + ROUND(I6*F6,0)) | D43: =IF(E6=1,0, BaselineCalc!$B$8 + I6 - ROUND(I6*F6,0)) | E43: =C43+D43 | F43: =YearMap!B2 | G43: =YearMap!C2 | H43: =YearMap!D2 | I43: =A43&"|"&B43 | O43: None | P43: None
A44: =A6 | B44: FY2027 | C44: =IF(D6=1,0, BaselineCalc!$B$7 + ROUND(J6*F6,0)) | D44: =IF(E6=1,0, BaselineCalc!$B$8 + J6 - ROUND(J6*F6,0)) | E44: =C44+D44 | F44: =YearMap!B3 | G44: =YearMap!C3 | H44: =YearMap!D3 | I44: =A44&"|"&B44 | O44: None | P44: None
A45: =A6 | B45: FY2028 | C45: =IF(D6=1,0, BaselineCalc!$B$7 + ROUND(K6*F6,0)) | D45: =IF(E6=1,0, BaselineCalc!$B$8 + K6 - ROUND(K6*F6,0)) | E45: =C45+D45 | F45: =YearMap!B4 | G45: =YearMap!C4 | H45: =YearMap!D4 | I45: =A45&"|"&B45 | O45: None | P45: None
A46: =A6 | B46: FY2029 | C46: =IF(D6=1,0, BaselineCalc!$B$7 + ROUND(L6*F6,0)) | D46: =IF(E6=1,0, BaselineCalc!$B$8 + L6 - ROUND(L6*F6,0)) | E46: =C46+D46 | F46: =YearMap!B5 | G46: =YearMap!C5 | H46: =YearMap!D5 | I46: =A46&"|"&B46 | O46: None | P46: None
A47: =A6 | B47: FY2030 | C47: =IF(D6=1,0, BaselineCalc!$B$7 + ROUND(M6*F6,0)) | D47: =IF(E6=1,0, BaselineCalc!$B$8 + M6 - ROUND(M6*F6,0)) | E47: =C47+D47 | F47: =YearMap!B6 | G47: =YearMap!C6 | H47: =YearMap!D6 | I47: =A47&"|"&B47 | O47: None | P47: None
A48: =A7 | B48: FY2026 | C48: =IF(D7=1,0, BaselineCalc!$B$7 + ROUND(I7*F7,0)) | D48: =IF(E7=1,0, BaselineCalc!$B$8 + I7 - ROUND(I7*F7,0)) | E48: =C48+D48 | F48: =YearMap!B2 | G48: =YearMap!C2 | H48: =YearMap!D2 | I48: =A48&"|"&B48 | O48: None | P48: None
A49: =A7 | B49: FY2027 | C49: =IF(D7=1,0, BaselineCalc!$B$7 + ROUND(J7*F7,0)) | D49: =IF(E7=1,0, BaselineCalc!$B$8 + J7 - ROUND(J7*F7,0)) | E49: =C49+D49 | F49: =YearMap!B3 | G49: =YearMap!C3 | H49: =YearMap!D3 | I49: =A49&"|"&B49 | O49: None | P49: None
A50: =A7 | B50: FY2028 | C50: =IF(D7=1,0, BaselineCalc!$B$7 + ROUND(K7*F7,0)) | D50: =IF(E7=1,0, BaselineCalc!$B$8 + K7 - ROUND(K7*F7,0)) | E50: =C50+D50 | F50: =YearMap!B4 | G50: =YearMap!C4 | H50: =YearMap!D4 | I50: =A50&"|"&B50 | O50: None | P50: None
A51: =A7 | B51: FY2029 | C51: =IF(D7=1,0, BaselineCalc!$B$7 + ROUND(L7*F7,0)) | D51: =IF(E7=1,0, BaselineCalc!$B$8 + L7 - ROUND(L7*F7,0)) | E51: =C51+D51 | F51: =YearMap!B5 | G51: =YearMap!C5 | H51: =YearMap!D5 | I51: =A51&"|"&B51 | O51: None | P51: None
A52: =A7 | B52: FY2030 | C52: =IF(D7=1,0, BaselineCalc!$B$7 + ROUND(M7*F7,0)) | D52: =IF(E7=1,0, BaselineCalc!$B$8 + M7 - ROUND(M7*F7,0)) | E52: =C52+D52 | F52: =YearMap!B6 | G52: =YearMap!C6 | H52: =YearMap!D6 | I52: =A52&"|"&B52 | O52: None | P52: None
A53: =A8 | B53: FY2026 | C53: =IF(D8=1,0, BaselineCalc!$B$7 + ROUND(I8*F8,0)) | D53: =IF(E8=1,0, BaselineCalc!$B$8 + I8 - ROUND(I8*F8,0)) | E53: =C53+D53 | F53: =YearMap!B2 | G53: =YearMap!C2 | H53: =YearMap!D2 | I53: =A53&"|"&B53 | O53: None | P53: None
A54: =A8 | B54: FY2027 | C54: =IF(D8=1,0, BaselineCalc!$B$7 + ROUND(J8*F8,0)) | D54: =IF(E8=1,0, BaselineCalc!$B$8 + J8 - ROUND(J8*F8,0)) | E54: =C54+D54 | F54: =YearMap!B3 | G54: =YearMap!C3 | H54: =YearMap!D3 | I54: =A54&"|"&B54 | O54: None | P54: None
A55: =A8 | B55: FY2028 | C55: =IF(D8=1,0, BaselineCalc!$B$7 + ROUND(K8*F8,0)) | D55: =IF(E8=1,0, BaselineCalc!$B$8 + K8 - ROUND(K8*F8,0)) | E55: =C55+D55 | F55: =YearMap!B4 | G55: =YearMap!C4 | H55: =YearMap!D4 | I55: =A55&"|"&B55 | O55: None | P55: None
A56: =A8 | B56: FY2029 | C56: =IF(D8=1,0, BaselineCalc!$B$7 + ROUND(L8*F8,0)) | D56: =IF(E8=1,0, BaselineCalc!$B$8 + L8 - ROUND(L8*F8,0)) | E56: =C56+D56 | F56: =YearMap!B5 | G56: =YearMap!C5 | H56: =YearMap!D5 | I56: =A56&"|"&B56 | O56: None | P56: None
A57: =A8 | B57: FY2030 | C57: =IF(D8=1,0, BaselineCalc!$B$7 + ROUND(M8*F8,0)) | D57: =IF(E8=1,0, BaselineCalc!$B$8 + M8 - ROUND(M8*F8,0)) | E57: =C57+D57 | F57: =YearMap!B6 | G57: =YearMap!C6 | H57: =YearMap!D6 | I57: =A57&"|"&B57 | O57: None | P57: None
A58: =A9 | B58: FY2026 | C58: =IF(D9=1,0, BaselineCalc!$B$7 + ROUND(I9*F9,0)) | D58: =IF(E9=1,0, BaselineCalc!$B$8 + I9 - ROUND(I9*F9,0)) | E58: =C58+D58 | F58: =YearMap!B2 | G58: =YearMap!C2 | H58: =YearMap!D2 | I58: =A58&"|"&B58 | O58: None | P58: None
A59: =A9 | B59: FY2027 | C59: =IF(D9=1,0, BaselineCalc!$B$7 + ROUND(J9*F9,0)) | D59: =IF(E9=1,0, BaselineCalc!$B$8 + J9 - ROUND(J9*F9,0)) | E59: =C59+D59 | F59: =YearMap!B3 | G59: =YearMap!C3 | H59: =YearMap!D3 | I59: =A59&"|"&B59 | O59: None | P59: None
A60: =A9 | B60: FY2028 | C60: =IF(D9=1,0, BaselineCalc!$B$7 + ROUND(K9*F9,0)) | D60: =IF(E9=1,0, BaselineCalc!$B$8 + K9 - ROUND(K9*F9,0)) | E60: =C60+D60 | F60: =YearMap!B4 | G60: =YearMap!C4 | H60: =YearMap!D4 | I60: =A60&"|"&B60 | O60: None | P60: None
A61: =A9 | B61: FY2029 | C61: =IF(D9=1,0, BaselineCalc!$B$7 + ROUND(L9*F9,0)) | D61: =IF(E9=1,0, BaselineCalc!$B$8 + L9 - ROUND(L9*F9,0)) | E61: =C61+D61 | F61: =YearMap!B5 | G61: =YearMap!C5 | H61: =YearMap!D5 | I61: =A61&"|"&B61 | O61: None | P61: None
A62: =A9 | B62: FY2030 | C62: =IF(D9=1,0, BaselineCalc!$B$7 + ROUND(M9*F9,0)) | D62: =IF(E9=1,0, BaselineCalc!$B$8 + M9 - ROUND(M9*F9,0)) | E62: =C62+D62 | F62: =YearMap!B6 | G62: =YearMap!C6 | H62: =YearMap!D6 | I62: =A62&"|"&B62 | O62: None | P62: None
A63: =A10 | B63: FY2026 | C63: =IF(D10=1,0, BaselineCalc!$B$7 + ROUND(I10*F10,0)) | D63: =IF(E10=1,0, BaselineCalc!$B$8 + I10 - ROUND(I10*F10,0)) | E63: =C63+D63 | F63: =YearMap!B2 | G63: =YearMap!C2 | H63: =YearMap!D2 | I63: =A63&"|"&B63 | O63: None | P63: None
A64: =A10 | B64: FY2027 | C64: =IF(D10=1,0, BaselineCalc!$B$7 + ROUND(J10*F10,0)) | D64: =IF(E10=1,0, BaselineCalc!$B$8 + J10 - ROUND(J10*F10,0)) | E64: =C64+D64 | F64: =YearMap!B3 | G64: =YearMap!C3 | H64: =YearMap!D3 | I64: =A64&"|"&B64 | O64: None | P64: None
A65: =A10 | B65: FY2028 | C65: =IF(D10=1,0, BaselineCalc!$B$7 + ROUND(K10*F10,0)) | D65: =IF(E10=1,0, BaselineCalc!$B$8 + K10 - ROUND(K10*F10,0)) | E65: =C65+D65 | F65: =YearMap!B4 | G65: =YearMap!C4 | H65: =YearMap!D4 | I65: =A65&"|"&B65 | O65: None | P65: None
A66: =A10 | B66: FY2029 | C66: =IF(D10=1,0, BaselineCalc!$B$7 + ROUND(L10*F10,0)) | D66: =IF(E10=1,0, BaselineCalc!$B$8 + L10 - ROUND(L10*F10,0)) | E66: =C66+D66 | F66: =YearMap!B5 | G66: =YearMap!C5 | H66: =YearMap!D5 | I66: =A66&"|"&B66 | O66: None | P66: None
A67: =A10 | B67: FY2030 | C67: =IF(D10=1,0, BaselineCalc!$B$7 + ROUND(M10*F10,0)) | D67: =IF(E10=1,0, BaselineCalc!$B$8 + M10 - ROUND(M10*F10,0)) | E67: =C67+D67 | F67: =YearMap!B6 | G67: =YearMap!C6 | H67: =YearMap!D6 | I67: =A67&"|"&B67 | O67: None | P67: None
A68: =A11 | B68: FY2026 | C68: =IF(D11=1,0, BaselineCalc!$B$7 + ROUND(I11*F11,0)) | D68: =IF(E11=1,0, BaselineCalc!$B$8 + I11 - ROUND(I11*F11,0)) | E68: =C68+D68 | F68: =YearMap!B2 | G68: =YearMap!C2 | H68: =YearMap!D2 | I68: =A68&"|"&B68 | O68: None | P68: None
A69: =A11 | B69: FY2027 | C69: =IF(D11=1,0, BaselineCalc!$B$7 + ROUND(J11*F11,0)) | D69: =IF(E11=1,0, BaselineCalc!$B$8 + J11 - ROUND(J11*F11,0)) | E69: =C69+D69 | F69: =YearMap!B3 | G69: =YearMap!C3 | H69: =YearMap!D3 | I69: =A69&"|"&B69 | O69: None | P69: None
A70: =A11 | B70: FY2028 | C70: =IF(D11=1,0, BaselineCalc!$B$7 + ROUND(K11*F11,0)) | D70: =IF(E11=1,0, BaselineCalc!$B$8 + K11 - ROUND(K11*F11,0)) | E70: =C70+D70 | F70: =YearMap!B4 | G70: =YearMap!C4 | H70: =YearMap!D4 | I70: =A70&"|"&B70 | O70: None | P70: None
A71: =A11 | B71: FY2029 | C71: =IF(D11=1,0, BaselineCalc!$B$7 + ROUND(L11*F11,0)) | D71: =IF(E11=1,0, BaselineCalc!$B$8 + L11 - ROUND(L11*F11,0)) | E71: =C71+D71 | F71: =YearMap!B5 | G71: =YearMap!C5 | H71: =YearMap!D5 | I71: =A71&"|"&B71 | O71: None | P71: None
A72: =A11 | B72: FY2030 | C72: =IF(D11=1,0, BaselineCalc!$B$7 + ROUND(M11*F11,0)) | D72: =IF(E11=1,0, BaselineCalc!$B$8 + M11 - ROUND(M11*F11,0)) | E72: =C72+D72 | F72: =YearMap!B6 | G72: =YearMap!C6 | H72: =YearMap!D6 | I72: =A72&"|"&B72 | O72: None | P72: None
A73: =A12 | B73: FY2026 | C73: =IF(D12=1,0, BaselineCalc!$B$7 + ROUND(I12*F12,0)) | D73: =IF(E12=1,0, BaselineCalc!$B$8 + I12 - ROUND(I12*F12,0)) | E73: =C73+D73 | F73: =YearMap!B2 | G73: =YearMap!C2 | H73: =YearMap!D2 | I73: =A73&"|"&B73 | O73: None | P73: None
A74: =A12 | B74: FY2027 | C74: =IF(D12=1,0, BaselineCalc!$B$7 + ROUND(J12*F12,0)) | D74: =IF(E12=1,0, BaselineCalc!$B$8 + J12 - ROUND(J12*F12,0)) | E74: =C74+D74 | F74: =YearMap!B3 | G74: =YearMap!C3 | H74: =YearMap!D3 | I74: =A74&"|"&B74 | O74: None | P74: None
A75: =A12 | B75: FY2028 | C75: =IF(D12=1,0, BaselineCalc!$B$7 + ROUND(K12*F12,0)) | D75: =IF(E12=1,0, BaselineCalc!$B$8 + K12 - ROUND(K12*F12,0)) | E75: =C75+D75 | F75: =YearMap!B4 | G75: =YearMap!C4 | H75: =YearMap!D4 | I75: =A75&"|"&B75 | O75: None | P75: None
A76: =A12 | B76: FY2029 | C76: =IF(D12=1,0, BaselineCalc!$B$7 + ROUND(L12*F12,0)) | D76: =IF(E12=1,0, BaselineCalc!$B$8 + L12 - ROUND(L12*F12,0)) | E76: =C76+D76 | F76: =YearMap!B5 | G76: =YearMap!C5 | H76: =YearMap!D5 | I76: =A76&"|"&B76 | O76: None | P76: None
A77: =A12 | B77: FY2030 | C77: =IF(D12=1,0, BaselineCalc!$B$7 + ROUND(M12*F12,0)) | D77: =IF(E12=1,0, BaselineCalc!$B$8 + M12 - ROUND(M12*F12,0)) | E77: =C77+D77 | F77: =YearMap!B6 | G77: =YearMap!C6 | H77: =YearMap!D6 | I77: =A77&"|"&B77 | O77: None | P77: None
A78: =A13 | B78: FY2026 | C78: =IF(D13=1,0, BaselineCalc!$B$7 + ROUND(I13*F13,0)) | D78: =IF(E13=1,0, BaselineCalc!$B$8 + I13 - ROUND(I13*F13,0)) | E78: =C78+D78 | F78: =YearMap!B2 | G78: =YearMap!C2 | H78: =YearMap!D2 | I78: =A78&"|"&B78 | O78: None | P78: None
A79: =A13 | B79: FY2027 | C79: =IF(D13=1,0, BaselineCalc!$B$7 + ROUND(J13*F13,0)) | D79: =IF(E13=1,0, BaselineCalc!$B$8 + J13 - ROUND(J13*F13,0)) | E79: =C79+D79 | F79: =YearMap!B3 | G79: =YearMap!C3 | H79: =YearMap!D3 | I79: =A79&"|"&B79 | O79: None | P79: None
A80: =A13 | B80: FY2028 | C80: =IF(D13=1,0, BaselineCalc!$B$7 + ROUND(K13*F13,0)) | D80: =IF(E13=1,0, BaselineCalc!$B$8 + K13 - ROUND(K13*F13,0)) | E80: =C80+D80 | F80: =YearMap!B4 | G80: =YearMap!C4 | H80: =YearMap!D4 | I80: =A80&"|"&B80 | O80: None | P80: None
A81: =A13 | B81: FY2029 | C81: =IF(D13=1,0, BaselineCalc!$B$7 + ROUND(L13*F13,0)) | D81: =IF(E13=1,0, BaselineCalc!$B$8 + L13 - ROUND(L13*F13,0)) | E81: =C81+D81 | F81: =YearMap!B5 | G81: =YearMap!C5 | H81: =YearMap!D5 | I81: =A81&"|"&B81 | O81: None | P81: None
A82: =A13 | B82: FY2030 | C82: =IF(D13=1,0, BaselineCalc!$B$7 + ROUND(M13*F13,0)) | D82: =IF(E13=1,0, BaselineCalc!$B$8 + M13 - ROUND(M13*F13,0)) | E82: =C82+D82 | F82: =YearMap!B6 | G82: =YearMap!C6 | H82: =YearMap!D6 | I82: =A82&"|"&B82 | O82: None | P82: None
A83: =A14 | B83: FY2026 | C83: =IF(D14=1,0, BaselineCalc!$B$7 + ROUND(I14*F14,0)) | D83: =IF(E14=1,0, BaselineCalc!$B$8 + I14 - ROUND(I14*F14,0)) | E83: =C83+D83 | F83: =YearMap!B2 | G83: =YearMap!C2 | H83: =YearMap!D2 | I83: =A83&"|"&B83 | O83: None | P83: None
A84: =A14 | B84: FY2027 | C84: =IF(D14=1,0, BaselineCalc!$B$7 + ROUND(J14*F14,0)) | D84: =IF(E14=1,0, BaselineCalc!$B$8 + J14 - ROUND(J14*F14,0)) | E84: =C84+D84 | F84: =YearMap!B3 | G84: =YearMap!C3 | H84: =YearMap!D3 | I84: =A84&"|"&B84 | O84: None | P84: None
A85: =A14 | B85: FY2028 | C85: =IF(D14=1,0, BaselineCalc!$B$7 + ROUND(K14*F14,0)) | D85: =IF(E14=1,0, BaselineCalc!$B$8 + K14 - ROUND(K14*F14,0)) | E85: =C85+D85 | F85: =YearMap!B4 | G85: =YearMap!C4 | H85: =YearMap!D4 | I85: =A85&"|"&B85 | O85: None | P85: None
A86: =A14 | B86: FY2029 | C86: =IF(D14=1,0, BaselineCalc!$B$7 + ROUND(L14*F14,0)) | D86: =IF(E14=1,0, BaselineCalc!$B$8 + L14 - ROUND(L14*F14,0)) | E86: =C86+D86 | F86: =YearMap!B5 | G86: =YearMap!C5 | H86: =YearMap!D5 | I86: =A86&"|"&B86 | O86: None | P86: None
A87: =A14 | B87: FY2030 | C87: =IF(D14=1,0, BaselineCalc!$B$7 + ROUND(M14*F14,0)) | D87: =IF(E14=1,0, BaselineCalc!$B$8 + M14 - ROUND(M14*F14,0)) | E87: =C87+D87 | F87: =YearMap!B6 | G87: =YearMap!C6 | H87: =YearMap!D6 | I87: =A87&"|"&B87 | O87: None | P87: None

Sheet MultiYear_ProForma
A1: =AG1 | B1: ScenarioKey | C1: Year | D1: Echo_ADM | E1: Pima_ADM | F1: Total_ADM | G1: VarUnit$ | H1: EchoFixed$ | I1: PimaFixed$ | J1: OpsFactor | K1: ExtraSave | L1: EchoPotential_ADM | M1: PimaPotential_ADM | N1: Displaced_ADM | O1: Retained_ADM | P1: h | Q1: CarryFrac | R1: EchoFixedEff$ | S1: PimaFixedEff$ | T1: TI_adds$ | U1: SiteCost$ | V1: RetainedSvc$ | W1: Comparable_MO$ | X1: Comparable_per_Student$ | Y1: Aid_per_ADM | Z1: Net_MO_after_aid$ | AA1: Net_per_served$ | AB1: Overlay_ADM | AC1: Served_ADM | AD1: Revenue$ | AE1: Adj_MO$ | AF1: Net$ | AG1: Key
A2: =AG2 | B2: =Scenarios!A3 | C2: FY2026 | D2: =IF(Scenarios!D3=1,0, L2) | E2: =IF(Scenarios!E3=1,0, M2) | F2: =D2+E2 | G2: =YearMap!B2 | H2: =YearMap!C2 | I2: =YearMap!D2 | J2: =1-BaselineCalc!$B$5 | K2: =Scenarios!G3 | L2: =IF(Scenarios!$Q3=1,BaselineCalc!$B$7*(1+Parameters_Public!$C44)^(IF($C2="FY2026",0,IF($C2="FY2027",1,IF($C2="FY2028",2,IF($C2="FY2029",3,IF($C2="FY2030",4,0))))))+ROUND(Scenarios!I3*Scenarios!$F3,0),BaselineCalc!$B$7+ROUND(Scenarios!I3*Scenarios!$F3,0)) | M2: =IF(Scenarios!$R3=1,BaselineCalc!$B$8*(1+Parameters_Public!$C45)^(IF($C2="FY2026",0,IF($C2="FY2027",1,IF($C2="FY2028",2,IF($C2="FY2029",3,IF($C2="FY2030",4,0))))))+Scenarios!I3-ROUND(Scenarios!I3*Scenarios!$F3,0),BaselineCalc!$B$8+Scenarios!I3-ROUND(Scenarios!I3*Scenarios!$F3,0)) | N2: =(L2-D2) + (M2-E2) | O2: =(Parameters_Public!$C$23*(L2-D2)+Parameters_Public!$C$24*(M2-E2)) | P2: =YearMap!E2 | Q2: =IF(Scenarios!N3="lease", YearMap!F2, YearMap!G2) | R2: =IF(Scenarios!D3=1, Q2*H2, H2) | S2: =IF(Scenarios!E3=1, Q2*I2, I2) | T2: =IF(C2="FY2026", (Scenarios!D3+Scenarios!E3)*BaselineCalc!$B$22, 0) | U2: =(R2+S2+G2*F2)*J2*(1-K2) | V2: =O2*(G2+P2) | W2: =U2+V2+IF(Parameters_Public!$C$28=1, T2, 0) | X2: =IF(F2+O2>0, W2/(F2+O2),"") | Y2: =INDEX(YearMap!$I$2:$I$6, MATCH(C2, YearMap!$A$2:$A$6, 0)) | Z2: =W2 - ((Y2 + IF(Parameters_Public!$C$20=1, Parameters_Public!$C$19, 0))*AC2) | AA2: =IF($AC2>0, $Z2/$AC2, 0) | AB2: =MAX(0, (MAX(0, $D2-BaselineCalc!$B$7) + MAX(0, $E2-BaselineCalc!$B$8))) | AC2: =L2+M2-N2+O2 | AD2: =( (Y2 + IF(Parameters_Public!$C20=1, INDEX(YearMap!$O$2:$O$6, MATCH(C2, YearMap!$A$2:$A$6, 0)), 0)) * AC2 ) + AC2*INDEX(YearMap!$P$2:$P$6, MATCH(C2, YearMap!$A$2:$A$6, 0)) + AB2*( INDEX(YearMap!$R$2:$R$6, MATCH(C2, YearMap!$A$2:$A$6, 0)) - INDEX(YearMap!$P$2:$P$6, MATCH(C2, YearMap!$A$2:$A$6, 0)) ) | AE2: =(W2 - (1-Parameters_Public!$C$43)*$G2*$AB2*$J2*(1-$K2)) + AB2*INDEX(YearMap!$Q$2:$Q$6, MATCH(C2, YearMap!$A$2:$A$6, 0)) | AF2: =AD2-AE2 | AG2: =B2&"|"&C2
A3: =AG3 | B3: =Scenarios!A3 | C3: FY2027 | D3: =IF(Scenarios!D3=1,0, L3) | E3: =IF(Scenarios!E3=1,0, M3) | F3: =D3+E3 | G3: =YearMap!B3 | H3: =YearMap!C3 | I3: =YearMap!D3 | J3: =1-BaselineCalc!$B$5 | K3: =Scenarios!G3 | L3: =IF(Scenarios!$Q3=1,BaselineCalc!$B$7*(1+Parameters_Public!$C44)^(IF($C3="FY2026",0,IF($C3="FY2027",1,IF($C3="FY2028",2,IF($C3="FY2029",3,IF($C3="FY2030",4,0))))))+ROUND(Scenarios!J3*Scenarios!$F3,0),BaselineCalc!$B$7+ROUND(Scenarios!J3*Scenarios!$F3,0)) | M3: =IF(Scenarios!$R3=1,BaselineCalc!$B$8*(1+Parameters_Public!$C45)^(IF($C3="FY2026",0,IF($C3="FY2027",1,IF($C3="FY2028",2,IF($C3="FY2029",3,IF($C3="FY2030",4,0))))))+Scenarios!J3-ROUND(Scenarios!J3*Scenarios!$F3,0),BaselineCalc!$B$8+Scenarios!J3-ROUND(Scenarios!J3*Scenarios!$F3,0)) | N3: =(L3-D3) + (M3-E3) | O3: =(Parameters_Public!$C$23*(L3-D3)+Parameters_Public!$C$24*(M3-E3)) | P3: =YearMap!E3 | Q3: =IF(Scenarios!N3="lease", YearMap!F3, YearMap!G3) | R3: =IF(Scenarios!D3=1, Q3*H3, H3) | S3: =IF(Scenarios!E3=1, Q3*I3, I3) | T3: =IF(C3="FY2026", (Scenarios!D3+Scenarios!E3)*BaselineCalc!$B$22, 0) | U3: =(R3+S3+G3*F3)*J3*(1-K3) | V3: =O3*(G3+P3) | W3: =U3+V3+IF(Parameters_Public!$C$28=1, T3, 0) | X3: =IF(F3+O3>0, W3/(F3+O3),"") | Y3: =INDEX(YearMap!$I$2:$I$6, MATCH(C3, YearMap!$A$2:$A$6, 0)) | Z3: =W3 - ((Y3 + IF(Parameters_Public!$C$20=1, Parameters_Public!$C$19, 0))*AC3) | AA3: =IF($AC3>0, $Z3/$AC3, 0) | AB3: =MAX(0, (MAX(0, $D3-BaselineCalc!$B$7) + MAX(0, $E3-BaselineCalc!$B$8))) | AC3: =L3+M3-N3+O3 | AD3: =( (Y3 + IF(Parameters_Public!$C20=1, INDEX(YearMap!$O$2:$O$6, MATCH(C3, YearMap!$A$2:$A$6, 0)), 0)) * AC3 ) + AC3*INDEX(YearMap!$P$2:$P$6, MATCH(C3, YearMap!$A$2:$A$6, 0)) + AB3*( INDEX(YearMap!$R$2:$R$6, MATCH(C3, YearMap!$A$2:$A$6, 0)) - INDEX(YearMap!$P$2:$P$6, MATCH(C3, YearMap!$A$2:$A$6, 0)) ) | AE3: =(W3 - (1-Parameters_Public!$C$43)*$G3*$AB3*$J3*(1-$K3)) + AB3*INDEX(YearMap!$Q$2:$Q$6, MATCH(C3, YearMap!$A$2:$A$6, 0)) | AF3: =AD3-AE3 | AG3: =B3&"|"&C3
A4: =AG4 | B4: =Scenarios!A3 | C4: FY2028 | D4: =IF(Scenarios!D3=1,0, L4) | E4: =IF(Scenarios!E3=1,0, M4) | F4: =D4+E4 | G4: =YearMap!B4 | H4: =YearMap!C4 | I4: =YearMap!D4 | J4: =1-BaselineCalc!$B$5 | K4: =Scenarios!G3 | L4: =IF(Scenarios!$Q3=1,BaselineCalc!$B$7*(1+Parameters_Public!$C44)^(IF($C4="FY2026",0,IF($C4="FY2027",1,IF($C4="FY2028",2,IF($C4="FY2029",3,IF($C4="FY2030",4,0))))))+ROUND(Scenarios!K3*Scenarios!$F3,0),BaselineCalc!$B$7+ROUND(Scenarios!K3*Scenarios!$F3,0)) | M4: =IF(Scenarios!$R3=1,BaselineCalc!$B$8*(1+Parameters_Public!$C45)^(IF($C4="FY2026",0,IF($C4="FY2027",1,IF($C4="FY2028",2,IF($C4="FY2029",3,IF($C4="FY2030",4,0))))))+Scenarios!K3-ROUND(Scenarios!K3*Scenarios!$F3,0),BaselineCalc!$B$8+Scenarios!K3-ROUND(Scenarios!K3*Scenarios!$F3,0)) | N4: =(L4-D4) + (M4-E4) | O4: =(Parameters_Public!$C$23*(L4-D4)+Parameters_Public!$C$24*(M4-E4)) | P4: =YearMap!E4 | Q4: =IF(Scenarios!N3="lease", YearMap!F4, YearMap!G4) | R4: =IF(Scenarios!D3=1, Q4*H4, H4) | S4: =IF(Scenarios!E3=1, Q4*I4, I4) | T4: =IF(C4="FY2026", (Scenarios!D3+Scenarios!E3)*BaselineCalc!$B$22, 0) | U4: =(R4+S4+G4*F4)*J4*(1-K4) | V4: =O4*(G4+P4) | W4: =U4+V4+IF(Parameters_Public!$C$28=1, T4, 0) | X4: =IF(F4+O4>0, W4/(F4+O4),"") | Y4: =INDEX(YearMap!$I$2:$I$6, MATCH(C4, YearMap!$A$2:$A$6, 0)) | Z4: =W4 - ((Y4 + IF(Parameters_Public!$C$20=1, Parameters_Public!$C$19, 0))*AC4) | AA4: =IF($AC4>0, $Z4/$AC4, 0) | AB4: =MAX(0, (MAX(0, $D4-BaselineCalc!$B$7) + MAX(0, $E4-BaselineCalc!$B$8))) | AC4: =L4+M4-N4+O4 | AD4: =( (Y4 + IF(Parameters_Public!$C20=1, INDEX(YearMap!$O$2:$O$6, MATCH(C4, YearMap!$A$2:$A$6, 0)), 0)) * AC4 ) + AC4*INDEX(YearMap!$P$2:$P$6, MATCH(C4, YearMap!$A$2:$A$6, 0)) + AB4*( INDEX(YearMap!$R$2:$R$6, MATCH(C4, YearMap!$A$2:$A$6, 0)) - INDEX(YearMap!$P$2:$P$6, MATCH(C4, YearMap!$A$2:$A$6, 0)) ) | AE4: =(W4 - (1-Parameters_Public!$C$43)*$G4*$AB4*$J4*(1-$K4)) + AB4*INDEX(YearMap!$Q$2:$Q$6, MATCH(C4, YearMap!$A$2:$A$6, 0)) | AF4: =AD4-AE4 | AG4: =B4&"|"&C4
A5: =AG5 | B5: =Scenarios!A3 | C5: FY2029 | D5: =IF(Scenarios!D3=1,0, L5) | E5: =IF(Scenarios!E3=1,0, M5) | F5: =D5+E5 | G5: =YearMap!B5 | H5: =YearMap!C5 | I5: =YearMap!D5 | J5: =1-BaselineCalc!$B$5 | K5: =Scenarios!G3 | L5: =IF(Scenarios!$Q3=1,BaselineCalc!$B$7*(1+Parameters_Public!$C44)^(IF($C5="FY2026",0,IF($C5="FY2027",1,IF($C5="FY2028",2,IF($C5="FY2029",3,IF($C5="FY2030",4,0))))))+ROUND(Scenarios!L3*Scenarios!$F3,0),BaselineCalc!$B$7+ROUND(Scenarios!L3*Scenarios!$F3,0)) | M5: =IF(Scenarios!$R3=1,BaselineCalc!$B$8*(1+Parameters_Public!$C45)^(IF($C5="FY2026",0,IF($C5="FY2027",1,IF($C5="FY2028",2,IF($C5="FY2029",3,IF($C5="FY2030",4,0))))))+Scenarios!L3-ROUND(Scenarios!L3*Scenarios!$F3,0),BaselineCalc!$B$8+Scenarios!L3-ROUND(Scenarios!L3*Scenarios!$F3,0)) | N5: =(L5-D5) + (M5-E5) | O5: =(Parameters_Public!$C$23*(L5-D5)+Parameters_Public!$C$24*(M5-E5)) | P5: =YearMap!E5 | Q5: =IF(Scenarios!N3="lease", YearMap!F5, YearMap!G5) | R5: =IF(Scenarios!D3=1, Q5*H5, H5) | S5: =IF(Scenarios!E3=1, Q5*I5, I5) | T5: =IF(C5="FY2026", (Scenarios!D3+Scenarios!E3)*BaselineCalc!$B$22, 0) | U5: =(R5+S5+G5*F5)*J5*(1-K5) | V5: =O5*(G5+P5) | W5: =U5+V5+IF(Parameters_Public!$C$28=1, T5, 0) | X5: =IF(F5+O5>0, W5/(F5+O5),"") | Y5: =INDEX(YearMap!$I$2:$I$6, MATCH(C5, YearMap!$A$2:$A$6, 0)) | Z5: =W5 - ((Y5 + IF(Parameters_Public!$C$20=1, Parameters_Public!$C$19, 0))*AC5) | AA5: =IF($AC5>0, $Z5/$AC5, 0) | AB5: =MAX(0, (MAX(0, $D5-BaselineCalc!$B$7) + MAX(0, $E5-BaselineCalc!$B$8))) | AC5: =L5+M5-N5+O5 | AD5: =( (Y5 + IF(Parameters_Public!$C20=1, INDEX(YearMap!$O$2:$O$6, MATCH(C5, YearMap!$A$2:$A$6, 0)), 0)) * AC5 ) + AC5*INDEX(YearMap!$P$2:$P$6, MATCH(C5, YearMap!$A$2:$A$6, 0)) + AB5*( INDEX(YearMap!$R$2:$R$6, MATCH(C5, YearMap!$A$2:$A$6, 0)) - INDEX(YearMap!$P$2:$P$6, MATCH(C5, YearMap!$A$2:$A$6, 0)) ) | AE5: =(W5 - (1-Parameters_Public!$C$43)*$G5*$AB5*$J5*(1-$K5)) + AB5*INDEX(YearMap!$Q$2:$Q$6, MATCH(C5, YearMap!$A$2:$A$6, 0)) | AF5: =AD5-AE5 | AG5: =B5&"|"&C5
A6: =AG6 | B6: =Scenarios!A3 | C6: FY2030 | D6: =IF(Scenarios!D3=1,0, L6) | E6: =IF(Scenarios!E3=1,0, M6) | F6: =D6+E6 | G6: =YearMap!B6 | H6: =YearMap!C6 | I6: =YearMap!D6 | J6: =1-BaselineCalc!$B$5 | K6: =Scenarios!G3 | L6: =IF(Scenarios!$Q3=1,BaselineCalc!$B$7*(1+Parameters_Public!$C44)^(IF($C6="FY2026",0,IF($C6="FY2027",1,IF($C6="FY2028",2,IF($C6="FY2029",3,IF($C6="FY2030",4,0))))))+ROUND(Scenarios!M3*Scenarios!$F3,0),BaselineCalc!$B$7+ROUND(Scenarios!M3*Scenarios!$F3,0)) | M6: =IF(Scenarios!$R3=1,BaselineCalc!$B$8*(1+Parameters_Public!$C45)^(IF($C6="FY2026",0,IF($C6="FY2027",1,IF($C6="FY2028",2,IF($C6="FY2029",3,IF($C6="FY2030",4,0))))))+Scenarios!M3-ROUND(Scenarios!M3*Scenarios!$F3,0),BaselineCalc!$B$8+Scenarios!M3-ROUND(Scenarios!M3*Scenarios!$F3,0)) | N6: =(L6-D6) + (M6-E6) | O6: =(Parameters_Public!$C$23*(L6-D6)+Parameters_Public!$C$24*(M6-E6)) | P6: =YearMap!E6 | Q6: =IF(Scenarios!N3="lease", YearMap!F6, YearMap!G6) | R6: =IF(Scenarios!D3=1, Q6*H6, H6) | S6: =IF(Scenarios!E3=1, Q6*I6, I6) | T6: =IF(C6="FY2026", (Scenarios!D3+Scenarios!E3)*BaselineCalc!$B$22, 0) | U6: =(R6+S6+G6*F6)*J6*(1-K6) | V6: =O6*(G6+P6) | W6: =U6+V6+IF(Parameters_Public!$C$28=1, T6, 0) | X6: =IF(F6+O6>0, W6/(F6+O6),"") | Y6: =INDEX(YearMap!$I$2:$I$6, MATCH(C6, YearMap!$A$2:$A$6, 0)) | Z6: =W6 - ((Y6 + IF(Parameters_Public!$C$20=1, Parameters_Public!$C$19, 0))*AC6) | AA6: =IF($AC6>0, $Z6/$AC6, 0) | AB6: =MAX(0, (MAX(0, $D6-BaselineCalc!$B$7) + MAX(0, $E6-BaselineCalc!$B$8))) | AC6: =L6+M6-N6+O6 | AD6: =( (Y6 + IF(Parameters_Public!$C20=1, INDEX(YearMap!$O$2:$O$6, MATCH(C6, YearMap!$A$2:$A$6, 0)), 0)) * AC6 ) + AC6*INDEX(YearMap!$P$2:$P$6, MATCH(C6, YearMap!$A$2:$A$6, 0)) + AB6*( INDEX(YearMap!$R$2:$R$6, MATCH(C6, YearMap!$A$2:$A$6, 0)) - INDEX(YearMap!$P$2:$P$6, MATCH(C6, YearMap!$A$2:$A$6, 0)) ) | AE6: =(W6 - (1-Parameters_Public!$C$43)*$G6*$AB6*$J6*(1-$K6)) + AB6*INDEX(YearMap!$Q$2:$Q$6, MATCH(C6, YearMap!$A$2:$A$6, 0)) | AF6: =AD6-AE6 | AG6: =B6&"|"&C6
A7: =AG7 | B7: =Scenarios!A4 | C7: FY2026 | D7: =IF(Scenarios!D4=1,0, L7) | E7: =IF(Scenarios!E4=1,0, M7) | F7: =D7+E7 | G7: =YearMap!B2 | H7: =YearMap!C2 | I7: =YearMap!D2 | J7: =1-BaselineCalc!$B$5 | K7: =Scenarios!G4 | L7: =IF(Scenarios!$Q4=1,BaselineCalc!$B$7*(1+Parameters_Public!$C44)^(IF($C7="FY2026",0,IF($C7="FY2027",1,IF($C7="FY2028",2,IF($C7="FY2029",3,IF($C7="FY2030",4,0))))))+ROUND(Scenarios!I4*Scenarios!$F4,0),BaselineCalc!$B$7+ROUND(Scenarios!I4*Scenarios!$F4,0)) | M7: =IF(Scenarios!$R4=1,BaselineCalc!$B$8*(1+Parameters_Public!$C45)^(IF($C7="FY2026",0,IF($C7="FY2027",1,IF($C7="FY2028",2,IF($C7="FY2029",3,IF($C7="FY2030",4,0))))))+Scenarios!I4-ROUND(Scenarios!I4*Scenarios!$F4,0),BaselineCalc!$B$8+Scenarios!I4-ROUND(Scenarios!I4*Scenarios!$F4,0)) | N7: =(L7-D7) + (M7-E7) | O7: =(Parameters_Public!$C$23*(L7-D7)+Parameters_Public!$C$24*(M7-E7)) | P7: =YearMap!E2 | Q7: =IF(Scenarios!N4="lease", YearMap!F2, YearMap!G2) | R7: =IF(Scenarios!D4=1, Q7*H7, H7) | S7: =IF(Scenarios!E4=1, Q7*I7, I7) | T7: =IF(C7="FY2026", (Scenarios!D4+Scenarios!E4)*BaselineCalc!$B$22, 0) | U7: =(R7+S7+G7*F7)*J7*(1-K7) | V7: =O7*(G7+P7) | W7: =U7+V7+IF(Parameters_Public!$C$28=1, T7, 0) | X7: =IF(F7+O7>0, W7/(F7+O7),"") | Y7: =INDEX(YearMap!$I$2:$I$6, MATCH(C7, YearMap!$A$2:$A$6, 0)) | Z7: =W7 - ((Y7 + IF(Parameters_Public!$C$20=1, Parameters_Public!$C$19, 0))*AC7) | AA7: =IF($AC7>0, $Z7/$AC7, 0) | AB7: =MAX(0, (MAX(0, $D7-BaselineCalc!$B$7) + MAX(0, $E7-BaselineCalc!$B$8))) | AC7: =L7+M7-N7+O7 | AD7: =( (Y7 + IF(Parameters_Public!$C20=1, INDEX(YearMap!$O$2:$O$6, MATCH(C7, YearMap!$A$2:$A$6, 0)), 0)) * AC7 ) + AC7*INDEX(YearMap!$P$2:$P$6, MATCH(C7, YearMap!$A$2:$A$6, 0)) + AB7*( INDEX(YearMap!$R$2:$R$6, MATCH(C7, YearMap!$A$2:$A$6, 0)) - INDEX(YearMap!$P$2:$P$6, MATCH(C7, YearMap!$A$2:$A$6, 0)) ) | AE7: =(W7 - (1-Parameters_Public!$C$43)*$G7*$AB7*$J7*(1-$K7)) + AB7*INDEX(YearMap!$Q$2:$Q$6, MATCH(C7, YearMap!$A$2:$A$6, 0)) | AF7: =AD7-AE7 | AG7: =B7&"|"&C7
A8: =AG8 | B8: =Scenarios!A4 | C8: FY2027 | D8: =IF(Scenarios!D4=1,0, L8) | E8: =IF(Scenarios!E4=1,0, M8) | F8: =D8+E8 | G8: =YearMap!B3 | H8: =YearMap!C3 | I8: =YearMap!D3 | J8: =1-BaselineCalc!$B$5 | K8: =Scenarios!G4 | L8: =IF(Scenarios!$Q4=1,BaselineCalc!$B$7*(1+Parameters_Public!$C44)^(IF($C8="FY2026",0,IF($C8="FY2027",1,IF($C8="FY2028",2,IF($C8="FY2029",3,IF($C8="FY2030",4,0))))))+ROUND(Scenarios!J4*Scenarios!$F4,0),BaselineCalc!$B$7+ROUND(Scenarios!J4*Scenarios!$F4,0)) | M8: =IF(Scenarios!$R4=1,BaselineCalc!$B$8*(1+Parameters_Public!$C45)^(IF($C8="FY2026",0,IF($C8="FY2027",1,IF($C8="FY2028",2,IF($C8="FY2029",3,IF($C8="FY2030",4,0))))))+Scenarios!J4-ROUND(Scenarios!J4*Scenarios!$F4,0),BaselineCalc!$B$8+Scenarios!J4-ROUND(Scenarios!J4*Scenarios!$F4,0)) | N8: =(L8-D8) + (M8-E8) | O8: =(Parameters_Public!$C$23*(L8-D8)+Parameters_Public!$C$24*(M8-E8)) | P8: =YearMap!E3 | Q8: =IF(Scenarios!N4="lease", YearMap!F3, YearMap!G3) | R8: =IF(Scenarios!D4=1, Q8*H8, H8) | S8: =IF(Scenarios!E4=1, Q8*I8, I8) | T8: =IF(C8="FY2026", (Scenarios!D4+Scenarios!E4)*BaselineCalc!$B$22, 0) | U8: =(R8+S8+G8*F8)*J8*(1-K8) | V8: =O8*(G8+P8) | W8: =U8+V8+IF(Parameters_Public!$C$28=1, T8, 0) | X8: =IF(F8+O8>0, W8/(F8+O8),"") | Y8: =INDEX(YearMap!$I$2:$I$6, MATCH(C8, YearMap!$A$2:$A$6, 0)) | Z8: =W8 - ((Y8 + IF(Parameters_Public!$C$20=1, Parameters_Public!$C$19, 0))*AC8) | AA8: =IF($AC8>0, $Z8/$AC8, 0) | AB8: =MAX(0, (MAX(0, $D8-BaselineCalc!$B$7) + MAX(0, $E8-BaselineCalc!$B$8))) | AC8: =L8+M8-N8+O8 | AD8: =( (Y8 + IF(Parameters_Public!$C20=1, INDEX(YearMap!$O$2:$O$6, MATCH(C8, YearMap!$A$2:$A$6, 0)), 0)) * AC8 ) + AC8*INDEX(YearMap!$P$2:$P$6, MATCH(C8, YearMap!$A$2:$A$6, 0)) + AB8*( INDEX(YearMap!$R$2:$R$6, MATCH(C8, YearMap!$A$2:$A$6, 0)) - INDEX(YearMap!$P$2:$P$6, MATCH(C8, YearMap!$A$2:$A$6, 0)) ) | AE8: =(W8 - (1-Parameters_Public!$C$43)*$G8*$AB8*$J8*(1-$K8)) + AB8*INDEX(YearMap!$Q$2:$Q$6, MATCH(C8, YearMap!$A$2:$A$6, 0)) | AF8: =AD8-AE8 | AG8: =B8&"|"&C8
A9: =AG9 | B9: =Scenarios!A4 | C9: FY2028 | D9: =IF(Scenarios!D4=1,0, L9) | E9: =IF(Scenarios!E4=1,0, M9) | F9: =D9+E9 | G9: =YearMap!B4 | H9: =YearMap!C4 | I9: =YearMap!D4 | J9: =1-BaselineCalc!$B$5 | K9: =Scenarios!G4 | L9: =IF(Scenarios!$Q4=1,BaselineCalc!$B$7*(1+Parameters_Public!$C44)^(IF($C9="FY2026",0,IF($C9="FY2027",1,IF($C9="FY2028",2,IF($C9="FY2029",3,IF($C9="FY2030",4,0))))))+ROUND(Scenarios!K4*Scenarios!$F4,0),BaselineCalc!$B$7+ROUND(Scenarios!K4*Scenarios!$F4,0)) | M9: =IF(Scenarios!$R4=1,BaselineCalc!$B$8*(1+Parameters_Public!$C45)^(IF($C9="FY2026",0,IF($C9="FY2027",1,IF($C9="FY2028",2,IF($C9="FY2029",3,IF($C9="FY2030",4,0))))))+Scenarios!K4-ROUND(Scenarios!K4*Scenarios!$F4,0),BaselineCalc!$B$8+Scenarios!K4-ROUND(Scenarios!K4*Scenarios!$F4,0)) | N9: =(L9-D9) + (M9-E9) | O9: =(Parameters_Public!$C$23*(L9-D9)+Parameters_Public!$C$24*(M9-E9)) | P9: =YearMap!E4 | Q9: =IF(Scenarios!N4="lease", YearMap!F4, YearMap!G4) | R9: =IF(Scenarios!D4=1, Q9*H9, H9) | S9: =IF(Scenarios!E4=1, Q9*I9, I9) | T9: =IF(C9="FY2026", (Scenarios!D4+Scenarios!E4)*BaselineCalc!$B$22, 0) | U9: =(R9+S9+G9*F9)*J9*(1-K9) | V9: =O9*(G9+P9) | W9: =U9+V9+IF(Parameters_Public!$C$28=1, T9, 0) | X9: =IF(F9+O9>0, W9/(F9+O9),"") | Y9: =INDEX(YearMap!$I$2:$I$6, MATCH(C9, YearMap!$A$2:$A$6, 0)) | Z9: =W9 - ((Y9 + IF(Parameters_Public!$C$20=1, Parameters_Public!$C$19, 0))*AC9) | AA9: =IF($AC9>0, $Z9/$AC9, 0) | AB9: =MAX(0, (MAX(0, $D9-BaselineCalc!$B$7) + MAX(0, $E9-BaselineCalc!$B$8))) | AC9: =L9+M9-N9+O9 | AD9: =( (Y9 + IF(Parameters_Public!$C20=1, INDEX(YearMap!$O$2:$O$6, MATCH(C9, YearMap!$A$2:$A$6, 0)), 0)) * AC9 ) + AC9*INDEX(YearMap!$P$2:$P$6, MATCH(C9, YearMap!$A$2:$A$6, 0)) + AB9*( INDEX(YearMap!$R$2:$R$6, MATCH(C9, YearMap!$A$2:$A$6, 0)) - INDEX(YearMap!$P$2:$P$6, MATCH(C9, YearMap!$A$2:$A$6, 0)) ) | AE9: =(W9 - (1-Parameters_Public!$C$43)*$G9*$AB9*$J9*(1-$K9)) + AB9*INDEX(YearMap!$Q$2:$Q$6, MATCH(C9, YearMap!$A$2:$A$6, 0)) | AF9: =AD9-AE9 | AG9: =B9&"|"&C9
A10: =AG10 | B10: =Scenarios!A4 | C10: FY2029 | D10: =IF(Scenarios!D4=1,0, L10) | E10: =IF(Scenarios!E4=1,0, M10) | F10: =D10+E10 | G10: =YearMap!B5 | H10: =YearMap!C5 | I10: =YearMap!D5 | J10: =1-BaselineCalc!$B$5 | K10: =Scenarios!G4 | L10: =IF(Scenarios!$Q4=1,BaselineCalc!$B$7*(1+Parameters_Public!$C44)^(IF($C10="FY2026",0,IF($C10="FY2027",1,IF($C10="FY2028",2,IF($C10="FY2029",3,IF($C10="FY2030",4,0))))))+ROUND(Scenarios!L4*Scenarios!$F4,0),BaselineCalc!$B$7+ROUND(Scenarios!L4*Scenarios!$F4,0)) | M10: =IF(Scenarios!$R4=1,BaselineCalc!$B$8*(1+Parameters_Public!$C45)^(IF($C10="FY2026",0,IF($C10="FY2027",1,IF($C10="FY2028",2,IF($C10="FY2029",3,IF($C10="FY2030",4,0))))))+Scenarios!L4-ROUND(Scenarios!L4*Scenarios!$F4,0),BaselineCalc!$B$8+Scenarios!L4-ROUND(Scenarios!L4*Scenarios!$F4,0)) | N10: =(L10-D10) + (M10-E10) | O10: =(Parameters_Public!$C$23*(L10-D10)+Parameters_Public!$C$24*(M10-E10)) | P10: =YearMap!E5 | Q10: =IF(Scenarios!N4="lease", YearMap!F5, YearMap!G5) | R10: =IF(Scenarios!D4=1, Q10*H10, H10) | S10: =IF(Scenarios!E4=1, Q10*I10, I10) | T10: =IF(C10="FY2026", (Scenarios!D4+Scenarios!E4)*BaselineCalc!$B$22, 0) | U10: =(R10+S10+G10*F10)*J10*(1-K10) | V10: =O10*(G10+P10) | W10: =U10+V10+IF(Parameters_Public!$C$28=1, T10, 0) | X10: =IF(F10+O10>0, W10/(F10+O10),"") | Y10: =INDEX(YearMap!$I$2:$I$6, MATCH(C10, YearMap!$A$2:$A$6, 0)) | Z10: =W10 - ((Y10 + IF(Parameters_Public!$C$20=1, Parameters_Public!$C$19, 0))*AC10) | AA10: =IF($AC10>0, $Z10/$AC10, 0) | AB10: =MAX(0, (MAX(0, $D10-BaselineCalc!$B$7) + MAX(0, $E10-BaselineCalc!$B$8))) | AC10: =L10+M10-N10+O10 | AD10: =( (Y10 + IF(Parameters_Public!$C20=1, INDEX(YearMap!$O$2:$O$6, MATCH(C10, YearMap!$A$2:$A$6, 0)), 0)) * AC10 ) + AC10*INDEX(YearMap!$P$2:$P$6, MATCH(C10, YearMap!$A$2:$A$6, 0)) + AB10*( INDEX(YearMap!$R$2:$R$6, MATCH(C10, YearMap!$A$2:$A$6, 0)) - INDEX(YearMap!$P$2:$P$6, MATCH(C10, YearMap!$A$2:$A$6, 0)) ) | AE10: =(W10 - (1-Parameters_Public!$C$43)*$G10*$AB10*$J10*(1-$K10)) + AB10*INDEX(YearMap!$Q$2:$Q$6, MATCH(C10, YearMap!$A$2:$A$6, 0)) | AF10: =AD10-AE10 | AG10: =B10&"|"&C10
A11: =AG11 | B11: =Scenarios!A4 | C11: FY2030 | D11: =IF(Scenarios!D4=1,0, L11) | E11: =IF(Scenarios!E4=1,0, M11) | F11: =D11+E11 | G11: =YearMap!B6 | H11: =YearMap!C6 | I11: =YearMap!D6 | J11: =1-BaselineCalc!$B$5 | K11: =Scenarios!G4 | L11: =IF(Scenarios!$Q4=1,BaselineCalc!$B$7*(1+Parameters_Public!$C44)^(IF($C11="FY2026",0,IF($C11="FY2027",1,IF($C11="FY2028",2,IF($C11="FY2029",3,IF($C11="FY2030",4,0))))))+ROUND(Scenarios!M4*Scenarios!$F4,0),BaselineCalc!$B$7+ROUND(Scenarios!M4*Scenarios!$F4,0)) | M11: =IF(Scenarios!$R4=1,BaselineCalc!$B$8*(1+Parameters_Public!$C45)^(IF($C11="FY2026",0,IF($C11="FY2027",1,IF($C11="FY2028",2,IF($C11="FY2029",3,IF($C11="FY2030",4,0))))))+Scenarios!M4-ROUND(Scenarios!M4*Scenarios!$F4,0),BaselineCalc!$B$8+Scenarios!M4-ROUND(Scenarios!M4*Scenarios!$F4,0)) | N11: =(L11-D11) + (M11-E11) | O11: =(Parameters_Public!$C$23*(L11-D11)+Parameters_Public!$C$24*(M11-E11)) | P11: =YearMap!E6 | Q11: =IF(Scenarios!N4="lease", YearMap!F6, YearMap!G6) | R11: =IF(Scenarios!D4=1, Q11*H11, H11) | S11: =IF(Scenarios!E4=1, Q11*I11, I11) | T11: =IF(C11="FY2026", (Scenarios!D4+Scenarios!E4)*BaselineCalc!$B$22, 0) | U11: =(R11+S11+G11*F11)*J11*(1-K11) | V11: =O11*(G11+P11) | W11: =U11+V11+IF(Parameters_Public!$C$28=1, T11, 0) | X11: =IF(F11+O11>0, W11/(F11+O11),"") | Y11: =INDEX(YearMap!$I$2:$I$6, MATCH(C11, YearMap!$A$2:$A$6, 0)) | Z11: =W11 - ((Y11 + IF(Parameters_Public!$C$20=1, Parameters_Public!$C$19, 0))*AC11) | AA11: =IF($AC11>0, $Z11/$AC11, 0) | AB11: =MAX(0, (MAX(0, $D11-BaselineCalc!$B$7) + MAX(0, $E11-BaselineCalc!$B$8))) | AC11: =L11+M11-N11+O11 | AD11: =( (Y11 + IF(Parameters_Public!$C20=1, INDEX(YearMap!$O$2:$O$6, MATCH(C11, YearMap!$A$2:$A$6, 0)), 0)) * AC11 ) + AC11*INDEX(YearMap!$P$2:$P$6, MATCH(C11, YearMap!$A$2:$A$6, 0)) + AB11*( INDEX(YearMap!$R$2:$R$6, MATCH(C11, YearMap!$A$2:$A$6, 0)) - INDEX(YearMap!$P$2:$P$6, MATCH(C11, YearMap!$A$2:$A$6, 0)) ) | AE11: =(W11 - (1-Parameters_Public!$C$43)*$G11*$AB11*$J11*(1-$K11)) + AB11*INDEX(YearMap!$Q$2:$Q$6, MATCH(C11, YearMap!$A$2:$A$6, 0)) | AF11: =AD11-AE11 | AG11: =B11&"|"&C11
A12: =AG12 | B12: =Scenarios!A5 | C12: FY2026 | D12: =IF(Scenarios!D5=1,0, L12) | E12: =IF(Scenarios!E5=1,0, M12) | F12: =D12+E12 | G12: =YearMap!B2 | H12: =YearMap!C2 | I12: =YearMap!D2 | J12: =1-BaselineCalc!$B$5 | K12: =Scenarios!G5 | L12: =IF(Scenarios!$Q5=1,BaselineCalc!$B$7*(1+Parameters_Public!$C44)^(IF($C12="FY2026",0,IF($C12="FY2027",1,IF($C12="FY2028",2,IF($C12="FY2029",3,IF($C12="FY2030",4,0))))))+ROUND(Scenarios!I5*Scenarios!$F5,0),BaselineCalc!$B$7+ROUND(Scenarios!I5*Scenarios!$F5,0)) | M12: =IF(Scenarios!$R5=1,BaselineCalc!$B$8*(1+Parameters_Public!$C45)^(IF($C12="FY2026",0,IF($C12="FY2027",1,IF($C12="FY2028",2,IF($C12="FY2029",3,IF($C12="FY2030",4,0))))))+Scenarios!I5-ROUND(Scenarios!I5*Scenarios!$F5,0),BaselineCalc!$B$8+Scenarios!I5-ROUND(Scenarios!I5*Scenarios!$F5,0)) | N12: =(L12-D12) + (M12-E12) | O12: =(Parameters_Public!$C$23*(L12-D12)+Parameters_Public!$C$24*(M12-E12)) | P12: =YearMap!E2 | Q12: =IF(Scenarios!N5="lease", YearMap!F2, YearMap!G2) | R12: =IF(Scenarios!D5=1, Q12*H12, H12) | S12: =IF(Scenarios!E5=1, Q12*I12, I12) | T12: =IF(C12="FY2026", (Scenarios!D5+Scenarios!E5)*BaselineCalc!$B$22, 0) | U12: =(R12+S12+G12*F12)*J12*(1-K12) | V12: =O12*(G12+P12) | W12: =U12+V12+IF(Parameters_Public!$C$28=1, T12, 0) | X12: =IF(F12+O12>0, W12/(F12+O12),"") | Y12: =INDEX(YearMap!$I$2:$I$6, MATCH(C12, YearMap!$A$2:$A$6, 0)) | Z12: =W12 - ((Y12 + IF(Parameters_Public!$C$20=1, Parameters_Public!$C$19, 0))*AC12) | AA12: =IF($AC12>0, $Z12/$AC12, 0) | AB12: =MAX(0, (MAX(0, $D12-BaselineCalc!$B$7) + MAX(0, $E12-BaselineCalc!$B$8))) | AC12: =L12+M12-N12+O12 | AD12: =( (Y12 + IF(Parameters_Public!$C20=1, INDEX(YearMap!$O$2:$O$6, MATCH(C12, YearMap!$A$2:$A$6, 0)), 0)) * AC12 ) + AC12*INDEX(YearMap!$P$2:$P$6, MATCH(C12, YearMap!$A$2:$A$6, 0)) + AB12*( INDEX(YearMap!$R$2:$R$6, MATCH(C12, YearMap!$A$2:$A$6, 0)) - INDEX(YearMap!$P$2:$P$6, MATCH(C12, YearMap!$A$2:$A$6, 0)) ) | AE12: =(W12 - (1-Parameters_Public!$C$43)*$G12*$AB12*$J12*(1-$K12)) + AB12*INDEX(YearMap!$Q$2:$Q$6, MATCH(C12, YearMap!$A$2:$A$6, 0)) | AF12: =AD12-AE12 | AG12: =B12&"|"&C12
A13: =AG13 | B13: =Scenarios!A5 | C13: FY2027 | D13: =IF(Scenarios!D5=1,0, L13) | E13: =IF(Scenarios!E5=1,0, M13) | F13: =D13+E13 | G13: =YearMap!B3 | H13: =YearMap!C3 | I13: =YearMap!D3 | J13: =1-BaselineCalc!$B$5 | K13: =Scenarios!G5 | L13: =IF(Scenarios!$Q5=1,BaselineCalc!$B$7*(1+Parameters_Public!$C44)^(IF($C13="FY2026",0,IF($C13="FY2027",1,IF($C13="FY2028",2,IF($C13="FY2029",3,IF($C13="FY2030",4,0))))))+ROUND(Scenarios!J5*Scenarios!$F5,0),BaselineCalc!$B$7+ROUND(Scenarios!J5*Scenarios!$F5,0)) | M13: =IF(Scenarios!$R5=1,BaselineCalc!$B$8*(1+Parameters_Public!$C45)^(IF($C13="FY2026",0,IF($C13="FY2027",1,IF($C13="FY2028",2,IF($C13="FY2029",3,IF($C13="FY2030",4,0))))))+Scenarios!J5-ROUND(Scenarios!J5*Scenarios!$F5,0),BaselineCalc!$B$8+Scenarios!J5-ROUND(Scenarios!J5*Scenarios!$F5,0)) | N13: =(L13-D13) + (M13-E13) | O13: =(Parameters_Public!$C$23*(L13-D13)+Parameters_Public!$C$24*(M13-E13)) | P13: =YearMap!E3 | Q13: =IF(Scenarios!N5="lease", YearMap!F3, YearMap!G3) | R13: =IF(Scenarios!D5=1, Q13*H13, H13) | S13: =IF(Scenarios!E5=1, Q13*I13, I13) | T13: =IF(C13="FY2026", (Scenarios!D5+Scenarios!E5)*BaselineCalc!$B$22, 0) | U13: =(R13+S13+G13*F13)*J13*(1-K13) | V13: =O13*(G13+P13) | W13: =U13+V13+IF(Parameters_Public!$C$28=1, T13, 0) | X13: =IF(F13+O13>0, W13/(F13+O13),"") | Y13: =INDEX(YearMap!$I$2:$I$6, MATCH(C13, YearMap!$A$2:$A$6, 0)) | Z13: =W13 - ((Y13 + IF(Parameters_Public!$C$20=1, Parameters_Public!$C$19, 0))*AC13) | AA13: =IF($AC13>0, $Z13/$AC13, 0) | AB13: =MAX(0, (MAX(0, $D13-BaselineCalc!$B$7) + MAX(0, $E13-BaselineCalc!$B$8))) | AC13: =L13+M13-N13+O13 | AD13: =( (Y13 + IF(Parameters_Public!$C20=1, INDEX(YearMap!$O$2:$O$6, MATCH(C13, YearMap!$A$2:$A$6, 0)), 0)) * AC13 ) + AC13*INDEX(YearMap!$P$2:$P$6, MATCH(C13, YearMap!$A$2:$A$6, 0)) + AB13*( INDEX(YearMap!$R$2:$R$6, MATCH(C13, YearMap!$A$2:$A$6, 0)) - INDEX(YearMap!$P$2:$P$6, MATCH(C13, YearMap!$A$2:$A$6, 0)) ) | AE13: =(W13 - (1-Parameters_Public!$C$43)*$G13*$AB13*$J13*(1-$K13)) + AB13*INDEX(YearMap!$Q$2:$Q$6, MATCH(C13, YearMap!$A$2:$A$6, 0)) | AF13: =AD13-AE13 | AG13: =B13&"|"&C13
A14: =AG14 | B14: =Scenarios!A5 | C14: FY2028 | D14: =IF(Scenarios!D5=1,0, L14) | E14: =IF(Scenarios!E5=1,0, M14) | F14: =D14+E14 | G14: =YearMap!B4 | H14: =YearMap!C4 | I14: =YearMap!D4 | J14: =1-BaselineCalc!$B$5 | K14: =Scenarios!G5 | L14: =IF(Scenarios!$Q5=1,BaselineCalc!$B$7*(1+Parameters_Public!$C44)^(IF($C14="FY2026",0,IF($C14="FY2027",1,IF($C14="FY2028",2,IF($C14="FY2029",3,IF($C14="FY2030",4,0))))))+ROUND(Scenarios!K5*Scenarios!$F5,0),BaselineCalc!$B$7+ROUND(Scenarios!K5*Scenarios!$F5,0)) | M14: =IF(Scenarios!$R5=1,BaselineCalc!$B$8*(1+Parameters_Public!$C45)^(IF($C14="FY2026",0,IF($C14="FY2027",1,IF($C14="FY2028",2,IF($C14="FY2029",3,IF($C14="FY2030",4,0))))))+Scenarios!K5-ROUND(Scenarios!K5*Scenarios!$F5,0),BaselineCalc!$B$8+Scenarios!K5-ROUND(Scenarios!K5*Scenarios!$F5,0)) | N14: =(L14-D14) + (M14-E14) | O14: =(Parameters_Public!$C$23*(L14-D14)+Parameters_Public!$C$24*(M14-E14)) | P14: =YearMap!E4 | Q14: =IF(Scenarios!N5="lease", YearMap!F4, YearMap!G4) | R14: =IF(Scenarios!D5=1, Q14*H14, H14) | S14: =IF(Scenarios!E5=1, Q14*I14, I14) | T14: =IF(C14="FY2026", (Scenarios!D5+Scenarios!E5)*BaselineCalc!$B$22, 0) | U14: =(R14+S14+G14*F14)*J14*(1-K14) | V14: =O14*(G14+P14) | W14: =U14+V14+IF(Parameters_Public!$C$28=1, T14, 0) | X14: =IF(F14+O14>0, W14/(F14+O14),"") | Y14: =INDEX(YearMap!$I$2:$I$6, MATCH(C14, YearMap!$A$2:$A$6, 0)) | Z14: =W14 - ((Y14 + IF(Parameters_Public!$C$20=1, Parameters_Public!$C$19, 0))*AC14) | AA14: =IF($AC14>0, $Z14/$AC14, 0) | AB14: =MAX(0, (MAX(0, $D14-BaselineCalc!$B$7) + MAX(0, $E14-BaselineCalc!$B$8))) | AC14: =L14+M14-N14+O14 | AD14: =( (Y14 + IF(Parameters_Public!$C20=1, INDEX(YearMap!$O$2:$O$6, MATCH(C14, YearMap!$A$2:$A$6, 0)), 0)) * AC14 ) + AC14*INDEX(YearMap!$P$2:$P$6, MATCH(C14, YearMap!$A$2:$A$6, 0)) + AB14*( INDEX(YearMap!$R$2:$R$6, MATCH(C14, YearMap!$A$2:$A$6, 0)) - INDEX(YearMap!$P$2:$P$6, MATCH(C14, YearMap!$A$2:$A$6, 0)) ) | AE14: =(W14 - (1-Parameters_Public!$C$43)*$G14*$AB14*$J14*(1-$K14)) + AB14*INDEX(YearMap!$Q$2:$Q$6, MATCH(C14, YearMap!$A$2:$A$6, 0)) | AF14: =AD14-AE14 | AG14: =B14&"|"&C14
A15: =AG15 | B15: =Scenarios!A5 | C15: FY2029 | D15: =IF(Scenarios!D5=1,0, L15) | E15: =IF(Scenarios!E5=1,0, M15) | F15: =D15+E15 | G15: =YearMap!B5 | H15: =YearMap!C5 | I15: =YearMap!D5 | J15: =1-BaselineCalc!$B$5 | K15: =Scenarios!G5 | L15: =IF(Scenarios!$Q5=1,BaselineCalc!$B$7*(1+Parameters_Public!$C44)^(IF($C15="FY2026",0,IF($C15="FY2027",1,IF($C15="FY2028",2,IF($C15="FY2029",3,IF($C15="FY2030",4,0))))))+ROUND(Scenarios!L5*Scenarios!$F5,0),BaselineCalc!$B$7+ROUND(Scenarios!L5*Scenarios!$F5,0)) | M15: =IF(Scenarios!$R5=1,BaselineCalc!$B$8*(1+Parameters_Public!$C45)^(IF($C15="FY2026",0,IF($C15="FY2027",1,IF($C15="FY2028",2,IF($C15="FY2029",3,IF($C15="FY2030",4,0))))))+Scenarios!L5-ROUND(Scenarios!L5*Scenarios!$F5,0),BaselineCalc!$B$8+Scenarios!L5-ROUND(Scenarios!L5*Scenarios!$F5,0)) | N15: =(L15-D15) + (M15-E15) | O15: =(Parameters_Public!$C$23*(L15-D15)+Parameters_Public!$C$24*(M15-E15)) | P15: =YearMap!E5 | Q15: =IF(Scenarios!N5="lease", YearMap!F5, YearMap!G5) | R15: =IF(Scenarios!D5=1, Q15*H15, H15) | S15: =IF(Scenarios!E5=1, Q15*I15, I15) | T15: =IF(C15="FY2026", (Scenarios!D5+Scenarios!E5)*BaselineCalc!$B$22, 0) | U15: =(R15+S15+G15*F15)*J15*(1-K15) | V15: =O15*(G15+P15) | W15: =U15+V15+IF(Parameters_Public!$C$28=1, T15, 0) | X15: =IF(F15+O15>0, W15/(F15+O15),"") | Y15: =INDEX(YearMap!$I$2:$I$6, MATCH(C15, YearMap!$A$2:$A$6, 0)) | Z15: =W15 - ((Y15 + IF(Parameters_Public!$C$20=1, Parameters_Public!$C$19, 0))*AC15) | AA15: =IF($AC15>0, $Z15/$AC15, 0) | AB15: =MAX(0, (MAX(0, $D15-BaselineCalc!$B$7) + MAX(0, $E15-BaselineCalc!$B$8))) | AC15: =L15+M15-N15+O15 | AD15: =( (Y15 + IF(Parameters_Public!$C20=1, INDEX(YearMap!$O$2:$O$6, MATCH(C15, YearMap!$A$2:$A$6, 0)), 0)) * AC15 ) + AC15*INDEX(YearMap!$P$2:$P$6, MATCH(C15, YearMap!$A$2:$A$6, 0)) + AB15*( INDEX(YearMap!$R$2:$R$6, MATCH(C15, YearMap!$A$2:$A$6, 0)) - INDEX(YearMap!$P$2:$P$6, MATCH(C15, YearMap!$A$2:$A$6, 0)) ) | AE15: =(W15 - (1-Parameters_Public!$C$43)*$G15*$AB15*$J15*(1-$K15)) + AB15*INDEX(YearMap!$Q$2:$Q$6, MATCH(C15, YearMap!$A$2:$A$6, 0)) | AF15: =AD15-AE15 | AG15: =B15&"|"&C15
A16: =AG16 | B16: =Scenarios!A5 | C16: FY2030 | D16: =IF(Scenarios!D5=1,0, L16) | E16: =IF(Scenarios!E5=1,0, M16) | F16: =D16+E16 | G16: =YearMap!B6 | H16: =YearMap!C6 | I16: =YearMap!D6 | J16: =1-BaselineCalc!$B$5 | K16: =Scenarios!G5 | L16: =IF(Scenarios!$Q5=1,BaselineCalc!$B$7*(1+Parameters_Public!$C44)^(IF($C16="FY2026",0,IF($C16="FY2027",1,IF($C16="FY2028",2,IF($C16="FY2029",3,IF($C16="FY2030",4,0))))))+ROUND(Scenarios!M5*Scenarios!$F5,0),BaselineCalc!$B$7+ROUND(Scenarios!M5*Scenarios!$F5,0)) | M16: =IF(Scenarios!$R5=1,BaselineCalc!$B$8*(1+Parameters_Public!$C45)^(IF($C16="FY2026",0,IF($C16="FY2027",1,IF($C16="FY2028",2,IF($C16="FY2029",3,IF($C16="FY2030",4,0))))))+Scenarios!M5-ROUND(Scenarios!M5*Scenarios!$F5,0),BaselineCalc!$B$8+Scenarios!M5-ROUND(Scenarios!M5*Scenarios!$F5,0)) | N16: =(L16-D16) + (M16-E16) | O16: =(Parameters_Public!$C$23*(L16-D16)+Parameters_Public!$C$24*(M16-E16)) | P16: =YearMap!E6 | Q16: =IF(Scenarios!N5="lease", YearMap!F6, YearMap!G6) | R16: =IF(Scenarios!D5=1, Q16*H16, H16) | S16: =IF(Scenarios!E5=1, Q16*I16, I16) | T16: =IF(C16="FY2026", (Scenarios!D5+Scenarios!E5)*BaselineCalc!$B$22, 0) | U16: =(R16+S16+G16*F16)*J16*(1-K16) | V16: =O16*(G16+P16) | W16: =U16+V16+IF(Parameters_Public!$C$28=1, T16, 0) | X16: =IF(F16+O16>0, W16/(F16+O16),"") | Y16: =INDEX(YearMap!$I$2:$I$6, MATCH(C16, YearMap!$A$2:$A$6, 0)) | Z16: =W16 - ((Y16 + IF(Parameters_Public!$C$20=1, Parameters_Public!$C$19, 0))*AC16) | AA16: =IF($AC16>0, $Z16/$AC16, 0) | AB16: =MAX(0, (MAX(0, $D16-BaselineCalc!$B$7) + MAX(0, $E16-BaselineCalc!$B$8))) | AC16: =L16+M16-N16+O16 | AD16: =( (Y16 + IF(Parameters_Public!$C20=1, INDEX(YearMap!$O$2:$O$6, MATCH(C16, YearMap!$A$2:$A$6, 0)), 0)) * AC16 ) + AC16*INDEX(YearMap!$P$2:$P$6, MATCH(C16, YearMap!$A$2:$A$6, 0)) + AB16*( INDEX(YearMap!$R$2:$R$6, MATCH(C16, YearMap!$A$2:$A$6, 0)) - INDEX(YearMap!$P$2:$P$6, MATCH(C16, YearMap!$A$2:$A$6, 0)) ) | AE16: =(W16 - (1-Parameters_Public!$C$43)*$G16*$AB16*$J16*(1-$K16)) + AB16*INDEX(YearMap!$Q$2:$Q$6, MATCH(C16, YearMap!$A$2:$A$6, 0)) | AF16: =AD16-AE16 | AG16: =B16&"|"&C16
A17: =AG17 | B17: =Scenarios!A6 | C17: FY2026 | D17: =IF(Scenarios!D6=1,0, L17) | E17: =IF(Scenarios!E6=1,0, M17) | F17: =D17+E17 | G17: =YearMap!B2 | H17: =YearMap!C2 | I17: =YearMap!D2 | J17: =1-BaselineCalc!$B$5 | K17: =Scenarios!G6 | L17: =IF(Scenarios!$Q6=1,BaselineCalc!$B$7*(1+Parameters_Public!$C44)^(IF($C17="FY2026",0,IF($C17="FY2027",1,IF($C17="FY2028",2,IF($C17="FY2029",3,IF($C17="FY2030",4,0))))))+ROUND(Scenarios!I6*Scenarios!$F6,0),BaselineCalc!$B$7+ROUND(Scenarios!I6*Scenarios!$F6,0)) | M17: =IF(Scenarios!$R6=1,BaselineCalc!$B$8*(1+Parameters_Public!$C45)^(IF($C17="FY2026",0,IF($C17="FY2027",1,IF($C17="FY2028",2,IF($C17="FY2029",3,IF($C17="FY2030",4,0))))))+Scenarios!I6-ROUND(Scenarios!I6*Scenarios!$F6,0),BaselineCalc!$B$8+Scenarios!I6-ROUND(Scenarios!I6*Scenarios!$F6,0)) | N17: =(L17-D17) + (M17-E17) | O17: =(Parameters_Public!$C$23*(L17-D17)+Parameters_Public!$C$24*(M17-E17)) | P17: =YearMap!E2 | Q17: =IF(Scenarios!N6="lease", YearMap!F2, YearMap!G2) | R17: =IF(Scenarios!D6=1, Q17*H17, H17) | S17: =IF(Scenarios!E6=1, Q17*I17, I17) | T17: =IF(C17="FY2026", (Scenarios!D6+Scenarios!E6)*BaselineCalc!$B$22, 0) | U17: =(R17+S17+G17*F17)*J17*(1-K17) | V17: =O17*(G17+P17) | W17: =U17+V17+IF(Parameters_Public!$C$28=1, T17, 0) | X17: =IF(F17+O17>0, W17/(F17+O17),"") | Y17: =INDEX(YearMap!$I$2:$I$6, MATCH(C17, YearMap!$A$2:$A$6, 0)) | Z17: =W17 - ((Y17 + IF(Parameters_Public!$C$20=1, Parameters_Public!$C$19, 0))*AC17) | AA17: =IF($AC17>0, $Z17/$AC17, 0) | AB17: =MAX(0, (MAX(0, $D17-BaselineCalc!$B$7) + MAX(0, $E17-BaselineCalc!$B$8))) | AC17: =L17+M17-N17+O17 | AD17: =( (Y17 + IF(Parameters_Public!$C20=1, INDEX(YearMap!$O$2:$O$6, MATCH(C17, YearMap!$A$2:$A$6, 0)), 0)) * AC17 ) + AC17*INDEX(YearMap!$P$2:$P$6, MATCH(C17, YearMap!$A$2:$A$6, 0)) + AB17*( INDEX(YearMap!$R$2:$R$6, MATCH(C17, YearMap!$A$2:$A$6, 0)) - INDEX(YearMap!$P$2:$P$6, MATCH(C17, YearMap!$A$2:$A$6, 0)) ) | AE17: =(W17 - (1-Parameters_Public!$C$43)*$G17*$AB17*$J17*(1-$K17)) + AB17*INDEX(YearMap!$Q$2:$Q$6, MATCH(C17, YearMap!$A$2:$A$6, 0)) | AF17: =AD17-AE17 | AG17: =B17&"|"&C17
A18: =AG18 | B18: =Scenarios!A6 | C18: FY2027 | D18: =IF(Scenarios!D6=1,0, L18) | E18: =IF(Scenarios!E6=1,0, M18) | F18: =D18+E18 | G18: =YearMap!B3 | H18: =YearMap!C3 | I18: =YearMap!D3 | J18: =1-BaselineCalc!$B$5 | K18: =Scenarios!G6 | L18: =IF(Scenarios!$Q6=1,BaselineCalc!$B$7*(1+Parameters_Public!$C44)^(IF($C18="FY2026",0,IF($C18="FY2027",1,IF($C18="FY2028",2,IF($C18="FY2029",3,IF($C18="FY2030",4,0))))))+ROUND(Scenarios!J6*Scenarios!$F6,0),BaselineCalc!$B$7+ROUND(Scenarios!J6*Scenarios!$F6,0)) | M18: =IF(Scenarios!$R6=1,BaselineCalc!$B$8*(1+Parameters_Public!$C45)^(IF($C18="FY2026",0,IF($C18="FY2027",1,IF($C18="FY2028",2,IF($C18="FY2029",3,IF($C18="FY2030",4,0))))))+Scenarios!J6-ROUND(Scenarios!J6*Scenarios!$F6,0),BaselineCalc!$B$8+Scenarios!J6-ROUND(Scenarios!J6*Scenarios!$F6,0)) | N18: =(L18-D18) + (M18-E18) | O18: =(Parameters_Public!$C$23*(L18-D18)+Parameters_Public!$C$24*(M18-E18)) | P18: =YearMap!E3 | Q18: =IF(Scenarios!N6="lease", YearMap!F3, YearMap!G3) | R18: =IF(Scenarios!D6=1, Q18*H18, H18) | S18: =IF(Scenarios!E6=1, Q18*I18, I18) | T18: =IF(C18="FY2026", (Scenarios!D6+Scenarios!E6)*BaselineCalc!$B$22, 0) | U18: =(R18+S18+G18*F18)*J18*(1-K18) | V18: =O18*(G18+P18) | W18: =U18+V18+IF(Parameters_Public!$C$28=1, T18, 0) | X18: =IF(F18+O18>0, W18/(F18+O18),"") | Y18: =INDEX(YearMap!$I$2:$I$6, MATCH(C18, YearMap!$A$2:$A$6, 0)) | Z18: =W18 - ((Y18 + IF(Parameters_Public!$C$20=1, Parameters_Public!$C$19, 0))*AC18) | AA18: =IF($AC18>0, $Z18/$AC18, 0) | AB18: =MAX(0, (MAX(0, $D18-BaselineCalc!$B$7) + MAX(0, $E18-BaselineCalc!$B$8))) | AC18: =L18+M18-N18+O18 | AD18: =( (Y18 + IF(Parameters_Public!$C20=1, INDEX(YearMap!$O$2:$O$6, MATCH(C18, YearMap!$A$2:$A$6, 0)), 0)) * AC18 ) + AC18*INDEX(YearMap!$P$2:$P$6, MATCH(C18, YearMap!$A$2:$A$6, 0)) + AB18*( INDEX(YearMap!$R$2:$R$6, MATCH(C18, YearMap!$A$2:$A$6, 0)) - INDEX(YearMap!$P$2:$P$6, MATCH(C18, YearMap!$A$2:$A$6, 0)) ) | AE18: =(W18 - (1-Parameters_Public!$C$43)*$G18*$AB18*$J18*(1-$K18)) + AB18*INDEX(YearMap!$Q$2:$Q$6, MATCH(C18, YearMap!$A$2:$A$6, 0)) | AF18: =AD18-AE18 | AG18: =B18&"|"&C18
A19: =AG19 | B19: =Scenarios!A6 | C19: FY2028 | D19: =IF(Scenarios!D6=1,0, L19) | E19: =IF(Scenarios!E6=1,0, M19) | F19: =D19+E19 | G19: =YearMap!B4 | H19: =YearMap!C4 | I19: =YearMap!D4 | J19: =1-BaselineCalc!$B$5 | K19: =Scenarios!G6 | L19: =IF(Scenarios!$Q6=1,BaselineCalc!$B$7*(1+Parameters_Public!$C44)^(IF($C19="FY2026",0,IF($C19="FY2027",1,IF($C19="FY2028",2,IF($C19="FY2029",3,IF($C19="FY2030",4,0))))))+ROUND(Scenarios!K6*Scenarios!$F6,0),BaselineCalc!$B$7+ROUND(Scenarios!K6*Scenarios!$F6,0)) | M19: =IF(Scenarios!$R6=1,BaselineCalc!$B$8*(1+Parameters_Public!$C45)^(IF($C19="FY2026",0,IF($C19="FY2027",1,IF($C19="FY2028",2,IF($C19="FY2029",3,IF($C19="FY2030",4,0))))))+Scenarios!K6-ROUND(Scenarios!K6*Scenarios!$F6,0),BaselineCalc!$B$8+Scenarios!K6-ROUND(Scenarios!K6*Scenarios!$F6,0)) | N19: =(L19-D19) + (M19-E19) | O19: =(Parameters_Public!$C$23*(L19-D19)+Parameters_Public!$C$24*(M19-E19)) | P19: =YearMap!E4 | Q19: =IF(Scenarios!N6="lease", YearMap!F4, YearMap!G4) | R19: =IF(Scenarios!D6=1, Q19*H19, H19) | S19: =IF(Scenarios!E6=1, Q19*I19, I19) | T19: =IF(C19="FY2026", (Scenarios!D6+Scenarios!E6)*BaselineCalc!$B$22, 0) | U19: =(R19+S19+G19*F19)*J19*(1-K19) | V19: =O19*(G19+P19) | W19: =U19+V19+IF(Parameters_Public!$C$28=1, T19, 0) | X19: =IF(F19+O19>0, W19/(F19+O19),"") | Y19: =INDEX(YearMap!$I$2:$I$6, MATCH(C19, YearMap!$A$2:$A$6, 0)) | Z19: =W19 - ((Y19 + IF(Parameters_Public!$C$20=1, Parameters_Public!$C$19, 0))*AC19) | AA19: =IF($AC19>0, $Z19/$AC19, 0) | AB19: =MAX(0, (MAX(0, $D19-BaselineCalc!$B$7) + MAX(0, $E19-BaselineCalc!$B$8))) | AC19: =L19+M19-N19+O19 | AD19: =( (Y19 + IF(Parameters_Public!$C20=1, INDEX(YearMap!$O$2:$O$6, MATCH(C19, YearMap!$A$2:$A$6, 0)), 0)) * AC19 ) + AC19*INDEX(YearMap!$P$2:$P$6, MATCH(C19, YearMap!$A$2:$A$6, 0)) + AB19*( INDEX(YearMap!$R$2:$R$6, MATCH(C19, YearMap!$A$2:$A$6, 0)) - INDEX(YearMap!$P$2:$P$6, MATCH(C19, YearMap!$A$2:$A$6, 0)) ) | AE19: =(W19 - (1-Parameters_Public!$C$43)*$G19*$AB19*$J19*(1-$K19)) + AB19*INDEX(YearMap!$Q$2:$Q$6, MATCH(C19, YearMap!$A$2:$A$6, 0)) | AF19: =AD19-AE19 | AG19: =B19&"|"&C19
A20: =AG20 | B20: =Scenarios!A6 | C20: FY2029 | D20: =IF(Scenarios!D6=1,0, L20) | E20: =IF(Scenarios!E6=1,0, M20) | F20: =D20+E20 | G20: =YearMap!B5 | H20: =YearMap!C5 | I20: =YearMap!D5 | J20: =1-BaselineCalc!$B$5 | K20: =Scenarios!G6 | L20: =IF(Scenarios!$Q6=1,BaselineCalc!$B$7*(1+Parameters_Public!$C44)^(IF($C20="FY2026",0,IF($C20="FY2027",1,IF($C20="FY2028",2,IF($C20="FY2029",3,IF($C20="FY2030",4,0))))))+ROUND(Scenarios!L6*Scenarios!$F6,0),BaselineCalc!$B$7+ROUND(Scenarios!L6*Scenarios!$F6,0)) | M20: =IF(Scenarios!$R6=1,BaselineCalc!$B$8*(1+Parameters_Public!$C45)^(IF($C20="FY2026",0,IF($C20="FY2027",1,IF($C20="FY2028",2,IF($C20="FY2029",3,IF($C20="FY2030",4,0))))))+Scenarios!L6-ROUND(Scenarios!L6*Scenarios!$F6,0),BaselineCalc!$B$8+Scenarios!L6-ROUND(Scenarios!L6*Scenarios!$F6,0)) | N20: =(L20-D20) + (M20-E20) | O20: =(Parameters_Public!$C$23*(L20-D20)+Parameters_Public!$C$24*(M20-E20)) | P20: =YearMap!E5 | Q20: =IF(Scenarios!N6="lease", YearMap!F5, YearMap!G5) | R20: =IF(Scenarios!D6=1, Q20*H20, H20) | S20: =IF(Scenarios!E6=1, Q20*I20, I20) | T20: =IF(C20="FY2026", (Scenarios!D6+Scenarios!E6)*BaselineCalc!$B$22, 0) | U20: =(R20+S20+G20*F20)*J20*(1-K20) | V20: =O20*(G20+P20) | W20: =U20+V20+IF(Parameters_Public!$C$28=1, T20, 0) | X20: =IF(F20+O20>0, W20/(F20+O20),"") | Y20: =INDEX(YearMap!$I$2:$I$6, MATCH(C20, YearMap!$A$2:$A$6, 0)) | Z20: =W20 - ((Y20 + IF(Parameters_Public!$C$20=1, Parameters_Public!$C$19, 0))*AC20) | AA20: =IF($AC20>0, $Z20/$AC20, 0) | AB20: =MAX(0, (MAX(0, $D20-BaselineCalc!$B$7) + MAX(0, $E20-BaselineCalc!$B$8))) | AC20: =L20+M20-N20+O20 | AD20: =( (Y20 + IF(Parameters_Public!$C20=1, INDEX(YearMap!$O$2:$O$6, MATCH(C20, YearMap!$A$2:$A$6, 0)), 0)) * AC20 ) + AC20*INDEX(YearMap!$P$2:$P$6, MATCH(C20, YearMap!$A$2:$A$6, 0)) + AB20*( INDEX(YearMap!$R$2:$R$6, MATCH(C20, YearMap!$A$2:$A$6, 0)) - INDEX(YearMap!$P$2:$P$6, MATCH(C20, YearMap!$A$2:$A$6, 0)) ) | AE20: =(W20 - (1-Parameters_Public!$C$43)*$G20*$AB20*$J20*(1-$K20)) + AB20*INDEX(YearMap!$Q$2:$Q$6, MATCH(C20, YearMap!$A$2:$A$6, 0)) | AF20: =AD20-AE20 | AG20: =B20&"|"&C20
A21: =AG21 | B21: =Scenarios!A6 | C21: FY2030 | D21: =IF(Scenarios!D6=1,0, L21) | E21: =IF(Scenarios!E6=1,0, M21) | F21: =D21+E21 | G21: =YearMap!B6 | H21: =YearMap!C6 | I21: =YearMap!D6 | J21: =1-BaselineCalc!$B$5 | K21: =Scenarios!G6 | L21: =IF(Scenarios!$Q6=1,BaselineCalc!$B$7*(1+Parameters_Public!$C44)^(IF($C21="FY2026",0,IF($C21="FY2027",1,IF($C21="FY2028",2,IF($C21="FY2029",3,IF($C21="FY2030",4,0))))))+ROUND(Scenarios!M6*Scenarios!$F6,0),BaselineCalc!$B$7+ROUND(Scenarios!M6*Scenarios!$F6,0)) | M21: =IF(Scenarios!$R6=1,BaselineCalc!$B$8*(1+Parameters_Public!$C45)^(IF($C21="FY2026",0,IF($C21="FY2027",1,IF($C21="FY2028",2,IF($C21="FY2029",3,IF($C21="FY2030",4,0))))))+Scenarios!M6-ROUND(Scenarios!M6*Scenarios!$F6,0),BaselineCalc!$B$8+Scenarios!M6-ROUND(Scenarios!M6*Scenarios!$F6,0)) | N21: =(L21-D21) + (M21-E21) | O21: =(Parameters_Public!$C$23*(L21-D21)+Parameters_Public!$C$24*(M21-E21)) | P21: =YearMap!E6 | Q21: =IF(Scenarios!N6="lease", YearMap!F6, YearMap!G6) | R21: =IF(Scenarios!D6=1, Q21*H21, H21) | S21: =IF(Scenarios!E6=1, Q21*I21, I21) | T21: =IF(C21="FY2026", (Scenarios!D6+Scenarios!E6)*BaselineCalc!$B$22, 0) | U21: =(R21+S21+G21*F21)*J21*(1-K21) | V21: =O21*(G21+P21) | W21: =U21+V21+IF(Parameters_Public!$C$28=1, T21, 0) | X21: =IF(F21+O21>0, W21/(F21+O21),"") | Y21: =INDEX(YearMap!$I$2:$I$6, MATCH(C21, YearMap!$A$2:$A$6, 0)) | Z21: =W21 - ((Y21 + IF(Parameters_Public!$C$20=1, Parameters_Public!$C$19, 0))*AC21) | AA21: =IF($AC21>0, $Z21/$AC21, 0) | AB21: =MAX(0, (MAX(0, $D21-BaselineCalc!$B$7) + MAX(0, $E21-BaselineCalc!$B$8))) | AC21: =L21+M21-N21+O21 | AD21: =( (Y21 + IF(Parameters_Public!$C20=1, INDEX(YearMap!$O$2:$O$6, MATCH(C21, YearMap!$A$2:$A$6, 0)), 0)) * AC21 ) + AC21*INDEX(YearMap!$P$2:$P$6, MATCH(C21, YearMap!$A$2:$A$6, 0)) + AB21*( INDEX(YearMap!$R$2:$R$6, MATCH(C21, YearMap!$A$2:$A$6, 0)) - INDEX(YearMap!$P$2:$P$6, MATCH(C21, YearMap!$A$2:$A$6, 0)) ) | AE21: =(W21 - (1-Parameters_Public!$C$43)*$G21*$AB21*$J21*(1-$K21)) + AB21*INDEX(YearMap!$Q$2:$Q$6, MATCH(C21, YearMap!$A$2:$A$6, 0)) | AF21: =AD21-AE21 | AG21: =B21&"|"&C21
A22: =AG22 | B22: =Scenarios!A7 | C22: FY2026 | D22: =IF(Scenarios!D7=1,0, L22) | E22: =IF(Scenarios!E7=1,0, M22) | F22: =D22+E22 | G22: =YearMap!B2 | H22: =YearMap!C2 | I22: =YearMap!D2 | J22: =1-BaselineCalc!$B$5 | K22: =Scenarios!G7 | L22: =IF(Scenarios!$Q7=1,BaselineCalc!$B$7*(1+Parameters_Public!$C44)^(IF($C22="FY2026",0,IF($C22="FY2027",1,IF($C22="FY2028",2,IF($C22="FY2029",3,IF($C22="FY2030",4,0))))))+ROUND(Scenarios!I7*Scenarios!$F7,0),BaselineCalc!$B$7+ROUND(Scenarios!I7*Scenarios!$F7,0)) | M22: =IF(Scenarios!$R7=1,BaselineCalc!$B$8*(1+Parameters_Public!$C45)^(IF($C22="FY2026",0,IF($C22="FY2027",1,IF($C22="FY2028",2,IF($C22="FY2029",3,IF($C22="FY2030",4,0))))))+Scenarios!I7-ROUND(Scenarios!I7*Scenarios!$F7,0),BaselineCalc!$B$8+Scenarios!I7-ROUND(Scenarios!I7*Scenarios!$F7,0)) | N22: =(L22-D22) + (M22-E22) | O22: =(Parameters_Public!$C$23*(L22-D22)+Parameters_Public!$C$24*(M22-E22)) | P22: =YearMap!E2 | Q22: =IF(Scenarios!N7="lease", YearMap!F2, YearMap!G2) | R22: =IF(Scenarios!D7=1, Q22*H22, H22) | S22: =IF(Scenarios!E7=1, Q22*I22, I22) | T22: =IF(C22="FY2026", (Scenarios!D7+Scenarios!E7)*BaselineCalc!$B$22, 0) | U22: =(R22+S22+G22*F22)*J22*(1-K22) | V22: =O22*(G22+P22) | W22: =U22+V22+IF(Parameters_Public!$C$28=1, T22, 0) | X22: =IF(F22+O22>0, W22/(F22+O22),"") | Y22: =INDEX(YearMap!$I$2:$I$6, MATCH(C22, YearMap!$A$2:$A$6, 0)) | Z22: =W22 - ((Y22 + IF(Parameters_Public!$C$20=1, Parameters_Public!$C$19, 0))*AC22) | AA22: =IF($AC22>0, $Z22/$AC22, 0) | AB22: =MAX(0, (MAX(0, $D22-BaselineCalc!$B$7) + MAX(0, $E22-BaselineCalc!$B$8))) | AC22: =L22+M22-N22+O22 | AD22: =( (Y22 + IF(Parameters_Public!$C20=1, INDEX(YearMap!$O$2:$O$6, MATCH(C22, YearMap!$A$2:$A$6, 0)), 0)) * AC22 ) + AC22*INDEX(YearMap!$P$2:$P$6, MATCH(C22, YearMap!$A$2:$A$6, 0)) + AB22*( INDEX(YearMap!$R$2:$R$6, MATCH(C22, YearMap!$A$2:$A$6, 0)) - INDEX(YearMap!$P$2:$P$6, MATCH(C22, YearMap!$A$2:$A$6, 0)) ) | AE22: =(W22 - (1-Parameters_Public!$C$43)*$G22*$AB22*$J22*(1-$K22)) + AB22*INDEX(YearMap!$Q$2:$Q$6, MATCH(C22, YearMap!$A$2:$A$6, 0)) | AF22: =AD22-AE22 | AG22: =B22&"|"&C22
A23: =AG23 | B23: =Scenarios!A7 | C23: FY2027 | D23: =IF(Scenarios!D7=1,0, L23) | E23: =IF(Scenarios!E7=1,0, M23) | F23: =D23+E23 | G23: =YearMap!B3 | H23: =YearMap!C3 | I23: =YearMap!D3 | J23: =1-BaselineCalc!$B$5 | K23: =Scenarios!G7 | L23: =IF(Scenarios!$Q7=1,BaselineCalc!$B$7*(1+Parameters_Public!$C44)^(IF($C23="FY2026",0,IF($C23="FY2027",1,IF($C23="FY2028",2,IF($C23="FY2029",3,IF($C23="FY2030",4,0))))))+ROUND(Scenarios!J7*Scenarios!$F7,0),BaselineCalc!$B$7+ROUND(Scenarios!J7*Scenarios!$F7,0)) | M23: =IF(Scenarios!$R7=1,BaselineCalc!$B$8*(1+Parameters_Public!$C45)^(IF($C23="FY2026",0,IF($C23="FY2027",1,IF($C23="FY2028",2,IF($C23="FY2029",3,IF($C23="FY2030",4,0))))))+Scenarios!J7-ROUND(Scenarios!J7*Scenarios!$F7,0),BaselineCalc!$B$8+Scenarios!J7-ROUND(Scenarios!J7*Scenarios!$F7,0)) | N23: =(L23-D23) + (M23-E23) | O23: =(Parameters_Public!$C$23*(L23-D23)+Parameters_Public!$C$24*(M23-E23)) | P23: =YearMap!E3 | Q23: =IF(Scenarios!N7="lease", YearMap!F3, YearMap!G3) | R23: =IF(Scenarios!D7=1, Q23*H23, H23) | S23: =IF(Scenarios!E7=1, Q23*I23, I23) | T23: =IF(C23="FY2026", (Scenarios!D7+Scenarios!E7)*BaselineCalc!$B$22, 0) | U23: =(R23+S23+G23*F23)*J23*(1-K23) | V23: =O23*(G23+P23) | W23: =U23+V23+IF(Parameters_Public!$C$28=1, T23, 0) | X23: =IF(F23+O23>0, W23/(F23+O23),"") | Y23: =INDEX(YearMap!$I$2:$I$6, MATCH(C23, YearMap!$A$2:$A$6, 0)) | Z23: =W23 - ((Y23 + IF(Parameters_Public!$C$20=1, Parameters_Public!$C$19, 0))*AC23) | AA23: =IF($AC23>0, $Z23/$AC23, 0) | AB23: =MAX(0, (MAX(0, $D23-BaselineCalc!$B$7) + MAX(0, $E23-BaselineCalc!$B$8))) | AC23: =L23+M23-N23+O23 | AD23: =( (Y23 + IF(Parameters_Public!$C20=1, INDEX(YearMap!$O$2:$O$6, MATCH(C23, YearMap!$A$2:$A$6, 0)), 0)) * AC23 ) + AC23*INDEX(YearMap!$P$2:$P$6, MATCH(C23, YearMap!$A$2:$A$6, 0)) + AB23*( INDEX(YearMap!$R$2:$R$6, MATCH(C23, YearMap!$A$2:$A$6, 0)) - INDEX(YearMap!$P$2:$P$6, MATCH(C23, YearMap!$A$2:$A$6, 0)) ) | AE23: =(W23 - (1-Parameters_Public!$C$43)*$G23*$AB23*$J23*(1-$K23)) + AB23*INDEX(YearMap!$Q$2:$Q$6, MATCH(C23, YearMap!$A$2:$A$6, 0)) | AF23: =AD23-AE23 | AG23: =B23&"|"&C23
A24: =AG24 | B24: =Scenarios!A7 | C24: FY2028 | D24: =IF(Scenarios!D7=1,0, L24) | E24: =IF(Scenarios!E7=1,0, M24) | F24: =D24+E24 | G24: =YearMap!B4 | H24: =YearMap!C4 | I24: =YearMap!D4 | J24: =1-BaselineCalc!$B$5 | K24: =Scenarios!G7 | L24: =IF(Scenarios!$Q7=1,BaselineCalc!$B$7*(1+Parameters_Public!$C44)^(IF($C24="FY2026",0,IF($C24="FY2027",1,IF($C24="FY2028",2,IF($C24="FY2029",3,IF($C24="FY2030",4,0))))))+ROUND(Scenarios!K7*Scenarios!$F7,0),BaselineCalc!$B$7+ROUND(Scenarios!K7*Scenarios!$F7,0)) | M24: =IF(Scenarios!$R7=1,BaselineCalc!$B$8*(1+Parameters_Public!$C45)^(IF($C24="FY2026",0,IF($C24="FY2027",1,IF($C24="FY2028",2,IF($C24="FY2029",3,IF($C24="FY2030",4,0))))))+Scenarios!K7-ROUND(Scenarios!K7*Scenarios!$F7,0),BaselineCalc!$B$8+Scenarios!K7-ROUND(Scenarios!K7*Scenarios!$F7,0)) | N24: =(L24-D24) + (M24-E24) | O24: =(Parameters_Public!$C$23*(L24-D24)+Parameters_Public!$C$24*(M24-E24)) | P24: =YearMap!E4 | Q24: =IF(Scenarios!N7="lease", YearMap!F4, YearMap!G4) | R24: =IF(Scenarios!D7=1, Q24*H24, H24) | S24: =IF(Scenarios!E7=1, Q24*I24, I24) | T24: =IF(C24="FY2026", (Scenarios!D7+Scenarios!E7)*BaselineCalc!$B$22, 0) | U24: =(R24+S24+G24*F24)*J24*(1-K24) | V24: =O24*(G24+P24) | W24: =U24+V24+IF(Parameters_Public!$C$28=1, T24, 0) | X24: =IF(F24+O24>0, W24/(F24+O24),"") | Y24: =INDEX(YearMap!$I$2:$I$6, MATCH(C24, YearMap!$A$2:$A$6, 0)) | Z24: =W24 - ((Y24 + IF(Parameters_Public!$C$20=1, Parameters_Public!$C$19, 0))*AC24) | AA24: =IF($AC24>0, $Z24/$AC24, 0) | AB24: =MAX(0, (MAX(0, $D24-BaselineCalc!$B$7) + MAX(0, $E24-BaselineCalc!$B$8))) | AC24: =L24+M24-N24+O24 | AD24: =( (Y24 + IF(Parameters_Public!$C20=1, INDEX(YearMap!$O$2:$O$6, MATCH(C24, YearMap!$A$2:$A$6, 0)), 0)) * AC24 ) + AC24*INDEX(YearMap!$P$2:$P$6, MATCH(C24, YearMap!$A$2:$A$6, 0)) + AB24*( INDEX(YearMap!$R$2:$R$6, MATCH(C24, YearMap!$A$2:$A$6, 0)) - INDEX(YearMap!$P$2:$P$6, MATCH(C24, YearMap!$A$2:$A$6, 0)) ) | AE24: =(W24 - (1-Parameters_Public!$C$43)*$G24*$AB24*$J24*(1-$K24)) + AB24*INDEX(YearMap!$Q$2:$Q$6, MATCH(C24, YearMap!$A$2:$A$6, 0)) | AF24: =AD24-AE24 | AG24: =B24&"|"&C24
A25: =AG25 | B25: =Scenarios!A7 | C25: FY2029 | D25: =IF(Scenarios!D7=1,0, L25) | E25: =IF(Scenarios!E7=1,0, M25) | F25: =D25+E25 | G25: =YearMap!B5 | H25: =YearMap!C5 | I25: =YearMap!D5 | J25: =1-BaselineCalc!$B$5 | K25: =Scenarios!G7 | L25: =IF(Scenarios!$Q7=1,BaselineCalc!$B$7*(1+Parameters_Public!$C44)^(IF($C25="FY2026",0,IF($C25="FY2027",1,IF($C25="FY2028",2,IF($C25="FY2029",3,IF($C25="FY2030",4,0))))))+ROUND(Scenarios!L7*Scenarios!$F7,0),BaselineCalc!$B$7+ROUND(Scenarios!L7*Scenarios!$F7,0)) | M25: =IF(Scenarios!$R7=1,BaselineCalc!$B$8*(1+Parameters_Public!$C45)^(IF($C25="FY2026",0,IF($C25="FY2027",1,IF($C25="FY2028",2,IF($C25="FY2029",3,IF($C25="FY2030",4,0))))))+Scenarios!L7-ROUND(Scenarios!L7*Scenarios!$F7,0),BaselineCalc!$B$8+Scenarios!L7-ROUND(Scenarios!L7*Scenarios!$F7,0)) | N25: =(L25-D25) + (M25-E25) | O25: =(Parameters_Public!$C$23*(L25-D25)+Parameters_Public!$C$24*(M25-E25)) | P25: =YearMap!E5 | Q25: =IF(Scenarios!N7="lease", YearMap!F5, YearMap!G5) | R25: =IF(Scenarios!D7=1, Q25*H25, H25) | S25: =IF(Scenarios!E7=1, Q25*I25, I25) | T25: =IF(C25="FY2026", (Scenarios!D7+Scenarios!E7)*BaselineCalc!$B$22, 0) | U25: =(R25+S25+G25*F25)*J25*(1-K25) | V25: =O25*(G25+P25) | W25: =U25+V25+IF(Parameters_Public!$C$28=1, T25, 0) | X25: =IF(F25+O25>0, W25/(F25+O25),"") | Y25: =INDEX(YearMap!$I$2:$I$6, MATCH(C25, YearMap!$A$2:$A$6, 0)) | Z25: =W25 - ((Y25 + IF(Parameters_Public!$C$20=1, Parameters_Public!$C$19, 0))*AC25) | AA25: =IF($AC25>0, $Z25/$AC25, 0) | AB25: =MAX(0, (MAX(0, $D25-BaselineCalc!$B$7) + MAX(0, $E25-BaselineCalc!$B$8))) | AC25: =L25+M25-N25+O25 | AD25: =( (Y25 + IF(Parameters_Public!$C20=1, INDEX(YearMap!$O$2:$O$6, MATCH(C25, YearMap!$A$2:$A$6, 0)), 0)) * AC25 ) + AC25*INDEX(YearMap!$P$2:$P$6, MATCH(C25, YearMap!$A$2:$A$6, 0)) + AB25*( INDEX(YearMap!$R$2:$R$6, MATCH(C25, YearMap!$A$2:$A$6, 0)) - INDEX(YearMap!$P$2:$P$6, MATCH(C25, YearMap!$A$2:$A$6, 0)) ) | AE25: =(W25 - (1-Parameters_Public!$C$43)*$G25*$AB25*$J25*(1-$K25)) + AB25*INDEX(YearMap!$Q$2:$Q$6, MATCH(C25, YearMap!$A$2:$A$6, 0)) | AF25: =AD25-AE25 | AG25: =B25&"|"&C25
A26: =AG26 | B26: =Scenarios!A7 | C26: FY2030 | D26: =IF(Scenarios!D7=1,0, L26) | E26: =IF(Scenarios!E7=1,0, M26) | F26: =D26+E26 | G26: =YearMap!B6 | H26: =YearMap!C6 | I26: =YearMap!D6 | J26: =1-BaselineCalc!$B$5 | K26: =Scenarios!G7 | L26: =IF(Scenarios!$Q7=1,BaselineCalc!$B$7*(1+Parameters_Public!$C44)^(IF($C26="FY2026",0,IF($C26="FY2027",1,IF($C26="FY2028",2,IF($C26="FY2029",3,IF($C26="FY2030",4,0))))))+ROUND(Scenarios!M7*Scenarios!$F7,0),BaselineCalc!$B$7+ROUND(Scenarios!M7*Scenarios!$F7,0)) | M26: =IF(Scenarios!$R7=1,BaselineCalc!$B$8*(1+Parameters_Public!$C45)^(IF($C26="FY2026",0,IF($C26="FY2027",1,IF($C26="FY2028",2,IF($C26="FY2029",3,IF($C26="FY2030",4,0))))))+Scenarios!M7-ROUND(Scenarios!M7*Scenarios!$F7,0),BaselineCalc!$B$8+Scenarios!M7-ROUND(Scenarios!M7*Scenarios!$F7,0)) | N26: =(L26-D26) + (M26-E26) | O26: =(Parameters_Public!$C$23*(L26-D26)+Parameters_Public!$C$24*(M26-E26)) | P26: =YearMap!E6 | Q26: =IF(Scenarios!N7="lease", YearMap!F6, YearMap!G6) | R26: =IF(Scenarios!D7=1, Q26*H26, H26) | S26: =IF(Scenarios!E7=1, Q26*I26, I26) | T26: =IF(C26="FY2026", (Scenarios!D7+Scenarios!E7)*BaselineCalc!$B$22, 0) | U26: =(R26+S26+G26*F26)*J26*(1-K26) | V26: =O26*(G26+P26) | W26: =U26+V26+IF(Parameters_Public!$C$28=1, T26, 0) | X26: =IF(F26+O26>0, W26/(F26+O26),"") | Y26: =INDEX(YearMap!$I$2:$I$6, MATCH(C26, YearMap!$A$2:$A$6, 0)) | Z26: =W26 - ((Y26 + IF(Parameters_Public!$C$20=1, Parameters_Public!$C$19, 0))*AC26) | AA26: =IF($AC26>0, $Z26/$AC26, 0) | AB26: =MAX(0, (MAX(0, $D26-BaselineCalc!$B$7) + MAX(0, $E26-BaselineCalc!$B$8))) | AC26: =L26+M26-N26+O26 | AD26: =( (Y26 + IF(Parameters_Public!$C20=1, INDEX(YearMap!$O$2:$O$6, MATCH(C26, YearMap!$A$2:$A$6, 0)), 0)) * AC26 ) + AC26*INDEX(YearMap!$P$2:$P$6, MATCH(C26, YearMap!$A$2:$A$6, 0)) + AB26*( INDEX(YearMap!$R$2:$R$6, MATCH(C26, YearMap!$A$2:$A$6, 0)) - INDEX(YearMap!$P$2:$P$6, MATCH(C26, YearMap!$A$2:$A$6, 0)) ) | AE26: =(W26 - (1-Parameters_Public!$C$43)*$G26*$AB26*$J26*(1-$K26)) + AB26*INDEX(YearMap!$Q$2:$Q$6, MATCH(C26, YearMap!$A$2:$A$6, 0)) | AF26: =AD26-AE26 | AG26: =B26&"|"&C26
A27: =AG27 | B27: =Scenarios!A8 | C27: FY2026 | D27: =IF(Scenarios!D8=1,0, L27) | E27: =IF(Scenarios!E8=1,0, M27) | F27: =D27+E27 | G27: =YearMap!B2 | H27: =YearMap!C2 | I27: =YearMap!D2 | J27: =1-BaselineCalc!$B$5 | K27: =Scenarios!G8 | L27: =IF(Scenarios!$Q8=1,BaselineCalc!$B$7*(1+Parameters_Public!$C44)^(IF($C27="FY2026",0,IF($C27="FY2027",1,IF($C27="FY2028",2,IF($C27="FY2029",3,IF($C27="FY2030",4,0))))))+ROUND(Scenarios!I8*Scenarios!$F8,0),BaselineCalc!$B$7+ROUND(Scenarios!I8*Scenarios!$F8,0)) | M27: =IF(Scenarios!$R8=1,BaselineCalc!$B$8*(1+Parameters_Public!$C45)^(IF($C27="FY2026",0,IF($C27="FY2027",1,IF($C27="FY2028",2,IF($C27="FY2029",3,IF($C27="FY2030",4,0))))))+Scenarios!I8-ROUND(Scenarios!I8*Scenarios!$F8,0),BaselineCalc!$B$8+Scenarios!I8-ROUND(Scenarios!I8*Scenarios!$F8,0)) | N27: =(L27-D27) + (M27-E27) | O27: =(Parameters_Public!$C$23*(L27-D27)+Parameters_Public!$C$24*(M27-E27)) | P27: =YearMap!E2 | Q27: =IF(Scenarios!N8="lease", YearMap!F2, YearMap!G2) | R27: =IF(Scenarios!D8=1, Q27*H27, H27) | S27: =IF(Scenarios!E8=1, Q27*I27, I27) | T27: =IF(C27="FY2026", (Scenarios!D8+Scenarios!E8)*BaselineCalc!$B$22, 0) | U27: =(R27+S27+G27*F27)*J27*(1-K27) | V27: =O27*(G27+P27) | W27: =U27+V27+IF(Parameters_Public!$C$28=1, T27, 0) | X27: =IF(F27+O27>0, W27/(F27+O27),"") | Y27: =INDEX(YearMap!$I$2:$I$6, MATCH(C27, YearMap!$A$2:$A$6, 0)) | Z27: =W27 - ((Y27 + IF(Parameters_Public!$C$20=1, Parameters_Public!$C$19, 0))*AC27) | AA27: =IF($AC27>0, $Z27/$AC27, 0) | AB27: =MAX(0, (MAX(0, $D27-BaselineCalc!$B$7) + MAX(0, $E27-BaselineCalc!$B$8))) | AC27: =L27+M27-N27+O27 | AD27: =( (Y27 + IF(Parameters_Public!$C20=1, INDEX(YearMap!$O$2:$O$6, MATCH(C27, YearMap!$A$2:$A$6, 0)), 0)) * AC27 ) + AC27*INDEX(YearMap!$P$2:$P$6, MATCH(C27, YearMap!$A$2:$A$6, 0)) + AB27*( INDEX(YearMap!$R$2:$R$6, MATCH(C27, YearMap!$A$2:$A$6, 0)) - INDEX(YearMap!$P$2:$P$6, MATCH(C27, YearMap!$A$2:$A$6, 0)) ) | AE27: =(W27 - (1-Parameters_Public!$C$43)*$G27*$AB27*$J27*(1-$K27)) + AB27*INDEX(YearMap!$Q$2:$Q$6, MATCH(C27, YearMap!$A$2:$A$6, 0)) | AF27: =AD27-AE27 | AG27: =B27&"|"&C27
A28: =AG28 | B28: =Scenarios!A8 | C28: FY2027 | D28: =IF(Scenarios!D8=1,0, L28) | E28: =IF(Scenarios!E8=1,0, M28) | F28: =D28+E28 | G28: =YearMap!B3 | H28: =YearMap!C3 | I28: =YearMap!D3 | J28: =1-BaselineCalc!$B$5 | K28: =Scenarios!G8 | L28: =IF(Scenarios!$Q8=1,BaselineCalc!$B$7*(1+Parameters_Public!$C44)^(IF($C28="FY2026",0,IF($C28="FY2027",1,IF($C28="FY2028",2,IF($C28="FY2029",3,IF($C28="FY2030",4,0))))))+ROUND(Scenarios!J8*Scenarios!$F8,0),BaselineCalc!$B$7+ROUND(Scenarios!J8*Scenarios!$F8,0)) | M28: =IF(Scenarios!$R8=1,BaselineCalc!$B$8*(1+Parameters_Public!$C45)^(IF($C28="FY2026",0,IF($C28="FY2027",1,IF($C28="FY2028",2,IF($C28="FY2029",3,IF($C28="FY2030",4,0))))))+Scenarios!J8-ROUND(Scenarios!J8*Scenarios!$F8,0),BaselineCalc!$B$8+Scenarios!J8-ROUND(Scenarios!J8*Scenarios!$F8,0)) | N28: =(L28-D28) + (M28-E28) | O28: =(Parameters_Public!$C$23*(L28-D28)+Parameters_Public!$C$24*(M28-E28)) | P28: =YearMap!E3 | Q28: =IF(Scenarios!N8="lease", YearMap!F3, YearMap!G3) | R28: =IF(Scenarios!D8=1, Q28*H28, H28) | S28: =IF(Scenarios!E8=1, Q28*I28, I28) | T28: =IF(C28="FY2026", (Scenarios!D8+Scenarios!E8)*BaselineCalc!$B$22, 0) | U28: =(R28+S28+G28*F28)*J28*(1-K28) | V28: =O28*(G28+P28) | W28: =U28+V28+IF(Parameters_Public!$C$28=1, T28, 0) | X28: =IF(F28+O28>0, W28/(F28+O28),"") | Y28: =INDEX(YearMap!$I$2:$I$6, MATCH(C28, YearMap!$A$2:$A$6, 0)) | Z28: =W28 - ((Y28 + IF(Parameters_Public!$C$20=1, Parameters_Public!$C$19, 0))*AC28) | AA28: =IF($AC28>0, $Z28/$AC28, 0) | AB28: =MAX(0, (MAX(0, $D28-BaselineCalc!$B$7) + MAX(0, $E28-BaselineCalc!$B$8))) | AC28: =L28+M28-N28+O28 | AD28: =( (Y28 + IF(Parameters_Public!$C20=1, INDEX(YearMap!$O$2:$O$6, MATCH(C28, YearMap!$A$2:$A$6, 0)), 0)) * AC28 ) + AC28*INDEX(YearMap!$P$2:$P$6, MATCH(C28, YearMap!$A$2:$A$6, 0)) + AB28*( INDEX(YearMap!$R$2:$R$6, MATCH(C28, YearMap!$A$2:$A$6, 0)) - INDEX(YearMap!$P$2:$P$6, MATCH(C28, YearMap!$A$2:$A$6, 0)) ) | AE28: =(W28 - (1-Parameters_Public!$C$43)*$G28*$AB28*$J28*(1-$K28)) + AB28*INDEX(YearMap!$Q$2:$Q$6, MATCH(C28, YearMap!$A$2:$A$6, 0)) | AF28: =AD28-AE28 | AG28: =B28&"|"&C28
A29: =AG29 | B29: =Scenarios!A8 | C29: FY2028 | D29: =IF(Scenarios!D8=1,0, L29) | E29: =IF(Scenarios!E8=1,0, M29) | F29: =D29+E29 | G29: =YearMap!B4 | H29: =YearMap!C4 | I29: =YearMap!D4 | J29: =1-BaselineCalc!$B$5 | K29: =Scenarios!G8 | L29: =IF(Scenarios!$Q8=1,BaselineCalc!$B$7*(1+Parameters_Public!$C44)^(IF($C29="FY2026",0,IF($C29="FY2027",1,IF($C29="FY2028",2,IF($C29="FY2029",3,IF($C29="FY2030",4,0))))))+ROUND(Scenarios!K8*Scenarios!$F8,0),BaselineCalc!$B$7+ROUND(Scenarios!K8*Scenarios!$F8,0)) | M29: =IF(Scenarios!$R8=1,BaselineCalc!$B$8*(1+Parameters_Public!$C45)^(IF($C29="FY2026",0,IF($C29="FY2027",1,IF($C29="FY2028",2,IF($C29="FY2029",3,IF($C29="FY2030",4,0))))))+Scenarios!K8-ROUND(Scenarios!K8*Scenarios!$F8,0),BaselineCalc!$B$8+Scenarios!K8-ROUND(Scenarios!K8*Scenarios!$F8,0)) | N29: =(L29-D29) + (M29-E29) | O29: =(Parameters_Public!$C$23*(L29-D29)+Parameters_Public!$C$24*(M29-E29)) | P29: =YearMap!E4 | Q29: =IF(Scenarios!N8="lease", YearMap!F4, YearMap!G4) | R29: =IF(Scenarios!D8=1, Q29*H29, H29) | S29: =IF(Scenarios!E8=1, Q29*I29, I29) | T29: =IF(C29="FY2026", (Scenarios!D8+Scenarios!E8)*BaselineCalc!$B$22, 0) | U29: =(R29+S29+G29*F29)*J29*(1-K29) | V29: =O29*(G29+P29) | W29: =U29+V29+IF(Parameters_Public!$C$28=1, T29, 0) | X29: =IF(F29+O29>0, W29/(F29+O29),"") | Y29: =INDEX(YearMap!$I$2:$I$6, MATCH(C29, YearMap!$A$2:$A$6, 0)) | Z29: =W29 - ((Y29 + IF(Parameters_Public!$C$20=1, Parameters_Public!$C$19, 0))*AC29) | AA29: =IF($AC29>0, $Z29/$AC29, 0) | AB29: =MAX(0, (MAX(0, $D29-BaselineCalc!$B$7) + MAX(0, $E29-BaselineCalc!$B$8))) | AC29: =L29+M29-N29+O29 | AD29: =( (Y29 + IF(Parameters_Public!$C20=1, INDEX(YearMap!$O$2:$O$6, MATCH(C29, YearMap!$A$2:$A$6, 0)), 0)) * AC29 ) + AC29*INDEX(YearMap!$P$2:$P$6, MATCH(C29, YearMap!$A$2:$A$6, 0)) + AB29*( INDEX(YearMap!$R$2:$R$6, MATCH(C29, YearMap!$A$2:$A$6, 0)) - INDEX(YearMap!$P$2:$P$6, MATCH(C29, YearMap!$A$2:$A$6, 0)) ) | AE29: =(W29 - (1-Parameters_Public!$C$43)*$G29*$AB29*$J29*(1-$K29)) + AB29*INDEX(YearMap!$Q$2:$Q$6, MATCH(C29, YearMap!$A$2:$A$6, 0)) | AF29: =AD29-AE29 | AG29: =B29&"|"&C29
A30: =AG30 | B30: =Scenarios!A8 | C30: FY2029 | D30: =IF(Scenarios!D8=1,0, L30) | E30: =IF(Scenarios!E8=1,0, M30) | F30: =D30+E30 | G30: =YearMap!B5 | H30: =YearMap!C5 | I30: =YearMap!D5 | J30: =1-BaselineCalc!$B$5 | K30: =Scenarios!G8 | L30: =IF(Scenarios!$Q8=1,BaselineCalc!$B$7*(1+Parameters_Public!$C44)^(IF($C30="FY2026",0,IF($C30="FY2027",1,IF($C30="FY2028",2,IF($C30="FY2029",3,IF($C30="FY2030",4,0))))))+ROUND(Scenarios!L8*Scenarios!$F8,0),BaselineCalc!$B$7+ROUND(Scenarios!L8*Scenarios!$F8,0)) | M30: =IF(Scenarios!$R8=1,BaselineCalc!$B$8*(1+Parameters_Public!$C45)^(IF($C30="FY2026",0,IF($C30="FY2027",1,IF($C30="FY2028",2,IF($C30="FY2029",3,IF($C30="FY2030",4,0))))))+Scenarios!L8-ROUND(Scenarios!L8*Scenarios!$F8,0),BaselineCalc!$B$8+Scenarios!L8-ROUND(Scenarios!L8*Scenarios!$F8,0)) | N30: =(L30-D30) + (M30-E30) | O30: =(Parameters_Public!$C$23*(L30-D30)+Parameters_Public!$C$24*(M30-E30)) | P30: =YearMap!E5 | Q30: =IF(Scenarios!N8="lease", YearMap!F5, YearMap!G5) | R30: =IF(Scenarios!D8=1, Q30*H30, H30) | S30: =IF(Scenarios!E8=1, Q30*I30, I30) | T30: =IF(C30="FY2026", (Scenarios!D8+Scenarios!E8)*BaselineCalc!$B$22, 0) | U30: =(R30+S30+G30*F30)*J30*(1-K30) | V30: =O30*(G30+P30) | W30: =U30+V30+IF(Parameters_Public!$C$28=1, T30, 0) | X30: =IF(F30+O30>0, W30/(F30+O30),"") | Y30: =INDEX(YearMap!$I$2:$I$6, MATCH(C30, YearMap!$A$2:$A$6, 0)) | Z30: =W30 - ((Y30 + IF(Parameters_Public!$C$20=1, Parameters_Public!$C$19, 0))*AC30) | AA30: =IF($AC30>0, $Z30/$AC30, 0) | AB30: =MAX(0, (MAX(0, $D30-BaselineCalc!$B$7) + MAX(0, $E30-BaselineCalc!$B$8))) | AC30: =L30+M30-N30+O30 | AD30: =( (Y30 + IF(Parameters_Public!$C20=1, INDEX(YearMap!$O$2:$O$6, MATCH(C30, YearMap!$A$2:$A$6, 0)), 0)) * AC30 ) + AC30*INDEX(YearMap!$P$2:$P$6, MATCH(C30, YearMap!$A$2:$A$6, 0)) + AB30*( INDEX(YearMap!$R$2:$R$6, MATCH(C30, YearMap!$A$2:$A$6, 0)) - INDEX(YearMap!$P$2:$P$6, MATCH(C30, YearMap!$A$2:$A$6, 0)) ) | AE30: =(W30 - (1-Parameters_Public!$C$43)*$G30*$AB30*$J30*(1-$K30)) + AB30*INDEX(YearMap!$Q$2:$Q$6, MATCH(C30, YearMap!$A$2:$A$6, 0)) | AF30: =AD30-AE30 | AG30: =B30&"|"&C30
A31: =AG31 | B31: =Scenarios!A8 | C31: FY2030 | D31: =IF(Scenarios!D8=1,0, L31) | E31: =IF(Scenarios!E8=1,0, M31) | F31: =D31+E31 | G31: =YearMap!B6 | H31: =YearMap!C6 | I31: =YearMap!D6 | J31: =1-BaselineCalc!$B$5 | K31: =Scenarios!G8 | L31: =IF(Scenarios!$Q8=1,BaselineCalc!$B$7*(1+Parameters_Public!$C44)^(IF($C31="FY2026",0,IF($C31="FY2027",1,IF($C31="FY2028",2,IF($C31="FY2029",3,IF($C31="FY2030",4,0))))))+ROUND(Scenarios!M8*Scenarios!$F8,0),BaselineCalc!$B$7+ROUND(Scenarios!M8*Scenarios!$F8,0)) | M31: =IF(Scenarios!$R8=1,BaselineCalc!$B$8*(1+Parameters_Public!$C45)^(IF($C31="FY2026",0,IF($C31="FY2027",1,IF($C31="FY2028",2,IF($C31="FY2029",3,IF($C31="FY2030",4,0))))))+Scenarios!M8-ROUND(Scenarios!M8*Scenarios!$F8,0),BaselineCalc!$B$8+Scenarios!M8-ROUND(Scenarios!M8*Scenarios!$F8,0)) | N31: =(L31-D31) + (M31-E31) | O31: =(Parameters_Public!$C$23*(L31-D31)+Parameters_Public!$C$24*(M31-E31)) | P31: =YearMap!E6 | Q31: =IF(Scenarios!N8="lease", YearMap!F6, YearMap!G6) | R31: =IF(Scenarios!D8=1, Q31*H31, H31) | S31: =IF(Scenarios!E8=1, Q31*I31, I31) | T31: =IF(C31="FY2026", (Scenarios!D8+Scenarios!E8)*BaselineCalc!$B$22, 0) | U31: =(R31+S31+G31*F31)*J31*(1-K31) | V31: =O31*(G31+P31) | W31: =U31+V31+IF(Parameters_Public!$C$28=1, T31, 0) | X31: =IF(F31+O31>0, W31/(F31+O31),"") | Y31: =INDEX(YearMap!$I$2:$I$6, MATCH(C31, YearMap!$A$2:$A$6, 0)) | Z31: =W31 - ((Y31 + IF(Parameters_Public!$C$20=1, Parameters_Public!$C$19, 0))*AC31) | AA31: =IF($AC31>0, $Z31/$AC31, 0) | AB31: =MAX(0, (MAX(0, $D31-BaselineCalc!$B$7) + MAX(0, $E31-BaselineCalc!$B$8))) | AC31: =L31+M31-N31+O31 | AD31: =( (Y31 + IF(Parameters_Public!$C20=1, INDEX(YearMap!$O$2:$O$6, MATCH(C31, YearMap!$A$2:$A$6, 0)), 0)) * AC31 ) + AC31*INDEX(YearMap!$P$2:$P$6, MATCH(C31, YearMap!$A$2:$A$6, 0)) + AB31*( INDEX(YearMap!$R$2:$R$6, MATCH(C31, YearMap!$A$2:$A$6, 0)) - INDEX(YearMap!$P$2:$P$6, MATCH(C31, YearMap!$A$2:$A$6, 0)) ) | AE31: =(W31 - (1-Parameters_Public!$C$43)*$G31*$AB31*$J31*(1-$K31)) + AB31*INDEX(YearMap!$Q$2:$Q$6, MATCH(C31, YearMap!$A$2:$A$6, 0)) | AF31: =AD31-AE31 | AG31: =B31&"|"&C31
A32: =AG32 | B32: =Scenarios!A9 | C32: FY2026 | D32: =IF(Scenarios!D9=1,0, L32) | E32: =IF(Scenarios!E9=1,0, M32) | F32: =D32+E32 | G32: =YearMap!B2 | H32: =YearMap!C2 | I32: =YearMap!D2 | J32: =1-BaselineCalc!$B$5 | K32: =Scenarios!G9 | L32: =IF(Scenarios!$Q9=1,BaselineCalc!$B$7*(1+Parameters_Public!$C44)^(IF($C32="FY2026",0,IF($C32="FY2027",1,IF($C32="FY2028",2,IF($C32="FY2029",3,IF($C32="FY2030",4,0))))))+ROUND(Scenarios!I9*Scenarios!$F9,0),BaselineCalc!$B$7+ROUND(Scenarios!I9*Scenarios!$F9,0)) | M32: =IF(Scenarios!$R9=1,BaselineCalc!$B$8*(1+Parameters_Public!$C45)^(IF($C32="FY2026",0,IF($C32="FY2027",1,IF($C32="FY2028",2,IF($C32="FY2029",3,IF($C32="FY2030",4,0))))))+Scenarios!I9-ROUND(Scenarios!I9*Scenarios!$F9,0),BaselineCalc!$B$8+Scenarios!I9-ROUND(Scenarios!I9*Scenarios!$F9,0)) | N32: =(L32-D32) + (M32-E32) | O32: =(Parameters_Public!$C$23*(L32-D32)+Parameters_Public!$C$24*(M32-E32)) | P32: =YearMap!E2 | Q32: =IF(Scenarios!N9="lease", YearMap!F2, YearMap!G2) | R32: =IF(Scenarios!D9=1, Q32*H32, H32) | S32: =IF(Scenarios!E9=1, Q32*I32, I32) | T32: =IF(C32="FY2026", (Scenarios!D9+Scenarios!E9)*BaselineCalc!$B$22, 0) | U32: =(R32+S32+G32*F32)*J32*(1-K32) | V32: =O32*(G32+P32) | W32: =U32+V32+IF(Parameters_Public!$C$28=1, T32, 0) | X32: =IF(F32+O32>0, W32/(F32+O32),"") | Y32: =INDEX(YearMap!$I$2:$I$6, MATCH(C32, YearMap!$A$2:$A$6, 0)) | Z32: =W32 - ((Y32 + IF(Parameters_Public!$C$20=1, Parameters_Public!$C$19, 0))*AC32) | AA32: =IF($AC32>0, $Z32/$AC32, 0) | AB32: =MAX(0, (MAX(0, $D32-BaselineCalc!$B$7) + MAX(0, $E32-BaselineCalc!$B$8))) | AC32: =L32+M32-N32+O32 | AD32: =( (Y32 + IF(Parameters_Public!$C20=1, INDEX(YearMap!$O$2:$O$6, MATCH(C32, YearMap!$A$2:$A$6, 0)), 0)) * AC32 ) + AC32*INDEX(YearMap!$P$2:$P$6, MATCH(C32, YearMap!$A$2:$A$6, 0)) + AB32*( INDEX(YearMap!$R$2:$R$6, MATCH(C32, YearMap!$A$2:$A$6, 0)) - INDEX(YearMap!$P$2:$P$6, MATCH(C32, YearMap!$A$2:$A$6, 0)) ) | AE32: =(W32 - (1-Parameters_Public!$C$43)*$G32*$AB32*$J32*(1-$K32)) + AB32*INDEX(YearMap!$Q$2:$Q$6, MATCH(C32, YearMap!$A$2:$A$6, 0)) | AF32: =AD32-AE32 | AG32: =B32&"|"&C32
A33: =AG33 | B33: =Scenarios!A9 | C33: FY2027 | D33: =IF(Scenarios!D9=1,0, L33) | E33: =IF(Scenarios!E9=1,0, M33) | F33: =D33+E33 | G33: =YearMap!B3 | H33: =YearMap!C3 | I33: =YearMap!D3 | J33: =1-BaselineCalc!$B$5 | K33: =Scenarios!G9 | L33: =IF(Scenarios!$Q9=1,BaselineCalc!$B$7*(1+Parameters_Public!$C44)^(IF($C33="FY2026",0,IF($C33="FY2027",1,IF($C33="FY2028",2,IF($C33="FY2029",3,IF($C33="FY2030",4,0))))))+ROUND(Scenarios!J9*Scenarios!$F9,0),BaselineCalc!$B$7+ROUND(Scenarios!J9*Scenarios!$F9,0)) | M33: =IF(Scenarios!$R9=1,BaselineCalc!$B$8*(1+Parameters_Public!$C45)^(IF($C33="FY2026",0,IF($C33="FY2027",1,IF($C33="FY2028",2,IF($C33="FY2029",3,IF($C33="FY2030",4,0))))))+Scenarios!J9-ROUND(Scenarios!J9*Scenarios!$F9,0),BaselineCalc!$B$8+Scenarios!J9-ROUND(Scenarios!J9*Scenarios!$F9,0)) | N33: =(L33-D33) + (M33-E33) | O33: =(Parameters_Public!$C$23*(L33-D33)+Parameters_Public!$C$24*(M33-E33)) | P33: =YearMap!E3 | Q33: =IF(Scenarios!N9="lease", YearMap!F3, YearMap!G3) | R33: =IF(Scenarios!D9=1, Q33*H33, H33) | S33: =IF(Scenarios!E9=1, Q33*I33, I33) | T33: =IF(C33="FY2026", (Scenarios!D9+Scenarios!E9)*BaselineCalc!$B$22, 0) | U33: =(R33+S33+G33*F33)*J33*(1-K33) | V33: =O33*(G33+P33) | W33: =U33+V33+IF(Parameters_Public!$C$28=1, T33, 0) | X33: =IF(F33+O33>0, W33/(F33+O33),"") | Y33: =INDEX(YearMap!$I$2:$I$6, MATCH(C33, YearMap!$A$2:$A$6, 0)) | Z33: =W33 - ((Y33 + IF(Parameters_Public!$C$20=1, Parameters_Public!$C$19, 0))*AC33) | AA33: =IF($AC33>0, $Z33/$AC33, 0) | AB33: =MAX(0, (MAX(0, $D33-BaselineCalc!$B$7) + MAX(0, $E33-BaselineCalc!$B$8))) | AC33: =L33+M33-N33+O33 | AD33: =( (Y33 + IF(Parameters_Public!$C20=1, INDEX(YearMap!$O$2:$O$6, MATCH(C33, YearMap!$A$2:$A$6, 0)), 0)) * AC33 ) + AC33*INDEX(YearMap!$P$2:$P$6, MATCH(C33, YearMap!$A$2:$A$6, 0)) + AB33*( INDEX(YearMap!$R$2:$R$6, MATCH(C33, YearMap!$A$2:$A$6, 0)) - INDEX(YearMap!$P$2:$P$6, MATCH(C33, YearMap!$A$2:$A$6, 0)) ) | AE33: =(W33 - (1-Parameters_Public!$C$43)*$G33*$AB33*$J33*(1-$K33)) + AB33*INDEX(YearMap!$Q$2:$Q$6, MATCH(C33, YearMap!$A$2:$A$6, 0)) | AF33: =AD33-AE33 | AG33: =B33&"|"&C33
A34: =AG34 | B34: =Scenarios!A9 | C34: FY2028 | D34: =IF(Scenarios!D9=1,0, L34) | E34: =IF(Scenarios!E9=1,0, M34) | F34: =D34+E34 | G34: =YearMap!B4 | H34: =YearMap!C4 | I34: =YearMap!D4 | J34: =1-BaselineCalc!$B$5 | K34: =Scenarios!G9 | L34: =IF(Scenarios!$Q9=1,BaselineCalc!$B$7*(1+Parameters_Public!$C44)^(IF($C34="FY2026",0,IF($C34="FY2027",1,IF($C34="FY2028",2,IF($C34="FY2029",3,IF($C34="FY2030",4,0))))))+ROUND(Scenarios!K9*Scenarios!$F9,0),BaselineCalc!$B$7+ROUND(Scenarios!K9*Scenarios!$F9,0)) | M34: =IF(Scenarios!$R9=1,BaselineCalc!$B$8*(1+Parameters_Public!$C45)^(IF($C34="FY2026",0,IF($C34="FY2027",1,IF($C34="FY2028",2,IF($C34="FY2029",3,IF($C34="FY2030",4,0))))))+Scenarios!K9-ROUND(Scenarios!K9*Scenarios!$F9,0),BaselineCalc!$B$8+Scenarios!K9-ROUND(Scenarios!K9*Scenarios!$F9,0)) | N34: =(L34-D34) + (M34-E34) | O34: =(Parameters_Public!$C$23*(L34-D34)+Parameters_Public!$C$24*(M34-E34)) | P34: =YearMap!E4 | Q34: =IF(Scenarios!N9="lease", YearMap!F4, YearMap!G4) | R34: =IF(Scenarios!D9=1, Q34*H34, H34) | S34: =IF(Scenarios!E9=1, Q34*I34, I34) | T34: =IF(C34="FY2026", (Scenarios!D9+Scenarios!E9)*BaselineCalc!$B$22, 0) | U34: =(R34+S34+G34*F34)*J34*(1-K34) | V34: =O34*(G34+P34) | W34: =U34+V34+IF(Parameters_Public!$C$28=1, T34, 0) | X34: =IF(F34+O34>0, W34/(F34+O34),"") | Y34: =INDEX(YearMap!$I$2:$I$6, MATCH(C34, YearMap!$A$2:$A$6, 0)) | Z34: =W34 - ((Y34 + IF(Parameters_Public!$C$20=1, Parameters_Public!$C$19, 0))*AC34) | AA34: =IF($AC34>0, $Z34/$AC34, 0) | AB34: =MAX(0, (MAX(0, $D34-BaselineCalc!$B$7) + MAX(0, $E34-BaselineCalc!$B$8))) | AC34: =L34+M34-N34+O34 | AD34: =( (Y34 + IF(Parameters_Public!$C20=1, INDEX(YearMap!$O$2:$O$6, MATCH(C34, YearMap!$A$2:$A$6, 0)), 0)) * AC34 ) + AC34*INDEX(YearMap!$P$2:$P$6, MATCH(C34, YearMap!$A$2:$A$6, 0)) + AB34*( INDEX(YearMap!$R$2:$R$6, MATCH(C34, YearMap!$A$2:$A$6, 0)) - INDEX(YearMap!$P$2:$P$6, MATCH(C34, YearMap!$A$2:$A$6, 0)) ) | AE34: =(W34 - (1-Parameters_Public!$C$43)*$G34*$AB34*$J34*(1-$K34)) + AB34*INDEX(YearMap!$Q$2:$Q$6, MATCH(C34, YearMap!$A$2:$A$6, 0)) | AF34: =AD34-AE34 | AG34: =B34&"|"&C34
A35: =AG35 | B35: =Scenarios!A9 | C35: FY2029 | D35: =IF(Scenarios!D9=1,0, L35) | E35: =IF(Scenarios!E9=1,0, M35) | F35: =D35+E35 | G35: =YearMap!B5 | H35: =YearMap!C5 | I35: =YearMap!D5 | J35: =1-BaselineCalc!$B$5 | K35: =Scenarios!G9 | L35: =IF(Scenarios!$Q9=1,BaselineCalc!$B$7*(1+Parameters_Public!$C44)^(IF($C35="FY2026",0,IF($C35="FY2027",1,IF($C35="FY2028",2,IF($C35="FY2029",3,IF($C35="FY2030",4,0))))))+ROUND(Scenarios!L9*Scenarios!$F9,0),BaselineCalc!$B$7+ROUND(Scenarios!L9*Scenarios!$F9,0)) | M35: =IF(Scenarios!$R9=1,BaselineCalc!$B$8*(1+Parameters_Public!$C45)^(IF($C35="FY2026",0,IF($C35="FY2027",1,IF($C35="FY2028",2,IF($C35="FY2029",3,IF($C35="FY2030",4,0))))))+Scenarios!L9-ROUND(Scenarios!L9*Scenarios!$F9,0),BaselineCalc!$B$8+Scenarios!L9-ROUND(Scenarios!L9*Scenarios!$F9,0)) | N35: =(L35-D35) + (M35-E35) | O35: =(Parameters_Public!$C$23*(L35-D35)+Parameters_Public!$C$24*(M35-E35)) | P35: =YearMap!E5 | Q35: =IF(Scenarios!N9="lease", YearMap!F5, YearMap!G5) | R35: =IF(Scenarios!D9=1, Q35*H35, H35) | S35: =IF(Scenarios!E9=1, Q35*I35, I35) | T35: =IF(C35="FY2026", (Scenarios!D9+Scenarios!E9)*BaselineCalc!$B$22, 0) | U35: =(R35+S35+G35*F35)*J35*(1-K35) | V35: =O35*(G35+P35) | W35: =U35+V35+IF(Parameters_Public!$C$28=1, T35, 0) | X35: =IF(F35+O35>0, W35/(F35+O35),"") | Y35: =INDEX(YearMap!$I$2:$I$6, MATCH(C35, YearMap!$A$2:$A$6, 0)) | Z35: =W35 - ((Y35 + IF(Parameters_Public!$C$20=1, Parameters_Public!$C$19, 0))*AC35) | AA35: =IF($AC35>0, $Z35/$AC35, 0) | AB35: =MAX(0, (MAX(0, $D35-BaselineCalc!$B$7) + MAX(0, $E35-BaselineCalc!$B$8))) | AC35: =L35+M35-N35+O35 | AD35: =( (Y35 + IF(Parameters_Public!$C20=1, INDEX(YearMap!$O$2:$O$6, MATCH(C35, YearMap!$A$2:$A$6, 0)), 0)) * AC35 ) + AC35*INDEX(YearMap!$P$2:$P$6, MATCH(C35, YearMap!$A$2:$A$6, 0)) + AB35*( INDEX(YearMap!$R$2:$R$6, MATCH(C35, YearMap!$A$2:$A$6, 0)) - INDEX(YearMap!$P$2:$P$6, MATCH(C35, YearMap!$A$2:$A$6, 0)) ) | AE35: =(W35 - (1-Parameters_Public!$C$43)*$G35*$AB35*$J35*(1-$K35)) + AB35*INDEX(YearMap!$Q$2:$Q$6, MATCH(C35, YearMap!$A$2:$A$6, 0)) | AF35: =AD35-AE35 | AG35: =B35&"|"&C35
A36: =AG36 | B36: =Scenarios!A9 | C36: FY2030 | D36: =IF(Scenarios!D9=1,0, L36) | E36: =IF(Scenarios!E9=1,0, M36) | F36: =D36+E36 | G36: =YearMap!B6 | H36: =YearMap!C6 | I36: =YearMap!D6 | J36: =1-BaselineCalc!$B$5 | K36: =Scenarios!G9 | L36: =IF(Scenarios!$Q9=1,BaselineCalc!$B$7*(1+Parameters_Public!$C44)^(IF($C36="FY2026",0,IF($C36="FY2027",1,IF($C36="FY2028",2,IF($C36="FY2029",3,IF($C36="FY2030",4,0))))))+ROUND(Scenarios!M9*Scenarios!$F9,0),BaselineCalc!$B$7+ROUND(Scenarios!M9*Scenarios!$F9,0)) | M36: =IF(Scenarios!$R9=1,BaselineCalc!$B$8*(1+Parameters_Public!$C45)^(IF($C36="FY2026",0,IF($C36="FY2027",1,IF($C36="FY2028",2,IF($C36="FY2029",3,IF($C36="FY2030",4,0))))))+Scenarios!M9-ROUND(Scenarios!M9*Scenarios!$F9,0),BaselineCalc!$B$8+Scenarios!M9-ROUND(Scenarios!M9*Scenarios!$F9,0)) | N36: =(L36-D36) + (M36-E36) | O36: =(Parameters_Public!$C$23*(L36-D36)+Parameters_Public!$C$24*(M36-E36)) | P36: =YearMap!E6 | Q36: =IF(Scenarios!N9="lease", YearMap!F6, YearMap!G6) | R36: =IF(Scenarios!D9=1, Q36*H36, H36) | S36: =IF(Scenarios!E9=1, Q36*I36, I36) | T36: =IF(C36="FY2026", (Scenarios!D9+Scenarios!E9)*BaselineCalc!$B$22, 0) | U36: =(R36+S36+G36*F36)*J36*(1-K36) | V36: =O36*(G36+P36) | W36: =U36+V36+IF(Parameters_Public!$C$28=1, T36, 0) | X36: =IF(F36+O36>0, W36/(F36+O36),"") | Y36: =INDEX(YearMap!$I$2:$I$6, MATCH(C36, YearMap!$A$2:$A$6, 0)) | Z36: =W36 - ((Y36 + IF(Parameters_Public!$C$20=1, Parameters_Public!$C$19, 0))*AC36) | AA36: =IF($AC36>0, $Z36/$AC36, 0) | AB36: =MAX(0, (MAX(0, $D36-BaselineCalc!$B$7) + MAX(0, $E36-BaselineCalc!$B$8))) | AC36: =L36+M36-N36+O36 | AD36: =( (Y36 + IF(Parameters_Public!$C20=1, INDEX(YearMap!$O$2:$O$6, MATCH(C36, YearMap!$A$2:$A$6, 0)), 0)) * AC36 ) + AC36*INDEX(YearMap!$P$2:$P$6, MATCH(C36, YearMap!$A$2:$A$6, 0)) + AB36*( INDEX(YearMap!$R$2:$R$6, MATCH(C36, YearMap!$A$2:$A$6, 0)) - INDEX(YearMap!$P$2:$P$6, MATCH(C36, YearMap!$A$2:$A$6, 0)) ) | AE36: =(W36 - (1-Parameters_Public!$C$43)*$G36*$AB36*$J36*(1-$K36)) + AB36*INDEX(YearMap!$Q$2:$Q$6, MATCH(C36, YearMap!$A$2:$A$6, 0)) | AF36: =AD36-AE36 | AG36: =B36&"|"&C36
A37: =AG37 | B37: =Scenarios!A10 | C37: FY2026 | D37: =IF(Scenarios!D10=1,0, L37) | E37: =IF(Scenarios!E10=1,0, M37) | F37: =D37+E37 | G37: =YearMap!B2 | H37: =YearMap!C2 | I37: =YearMap!D2 | J37: =1-BaselineCalc!$B$5 | K37: =Scenarios!G10 | L37: =IF(Scenarios!$Q10=1,BaselineCalc!$B$7*(1+Parameters_Public!$C44)^(IF($C37="FY2026",0,IF($C37="FY2027",1,IF($C37="FY2028",2,IF($C37="FY2029",3,IF($C37="FY2030",4,0))))))+ROUND(Scenarios!I10*Scenarios!$F10,0),BaselineCalc!$B$7+ROUND(Scenarios!I10*Scenarios!$F10,0)) | M37: =IF(Scenarios!$R10=1,BaselineCalc!$B$8*(1+Parameters_Public!$C45)^(IF($C37="FY2026",0,IF($C37="FY2027",1,IF($C37="FY2028",2,IF($C37="FY2029",3,IF($C37="FY2030",4,0))))))+Scenarios!I10-ROUND(Scenarios!I10*Scenarios!$F10,0),BaselineCalc!$B$8+Scenarios!I10-ROUND(Scenarios!I10*Scenarios!$F10,0)) | N37: =(L37-D37) + (M37-E37) | O37: =(Parameters_Public!$C$23*(L37-D37)+Parameters_Public!$C$24*(M37-E37)) | P37: =YearMap!E2 | Q37: =IF(Scenarios!N10="lease", YearMap!F2, YearMap!G2) | R37: =IF(Scenarios!D10=1, Q37*H37, H37) | S37: =IF(Scenarios!E10=1, Q37*I37, I37) | T37: =IF(C37="FY2026", (Scenarios!D10+Scenarios!E10)*BaselineCalc!$B$22, 0) | U37: =(R37+S37+G37*F37)*J37*(1-K37) | V37: =O37*(G37+P37) | W37: =U37+V37+IF(Parameters_Public!$C$28=1, T37, 0) | X37: =IF(F37+O37>0, W37/(F37+O37),"") | Y37: =INDEX(YearMap!$I$2:$I$6, MATCH(C37, YearMap!$A$2:$A$6, 0)) | Z37: =W37 - ((Y37 + IF(Parameters_Public!$C$20=1, Parameters_Public!$C$19, 0))*AC37) | AA37: =IF($AC37>0, $Z37/$AC37, 0) | AB37: =MAX(0, (MAX(0, $D37-BaselineCalc!$B$7) + MAX(0, $E37-BaselineCalc!$B$8))) | AC37: =L37+M37-N37+O37 | AD37: =( (Y37 + IF(Parameters_Public!$C20=1, INDEX(YearMap!$O$2:$O$6, MATCH(C37, YearMap!$A$2:$A$6, 0)), 0)) * AC37 ) + AC37*INDEX(YearMap!$P$2:$P$6, MATCH(C37, YearMap!$A$2:$A$6, 0)) + AB37*( INDEX(YearMap!$R$2:$R$6, MATCH(C37, YearMap!$A$2:$A$6, 0)) - INDEX(YearMap!$P$2:$P$6, MATCH(C37, YearMap!$A$2:$A$6, 0)) ) | AE37: =(W37 - (1-Parameters_Public!$C$43)*$G37*$AB37*$J37*(1-$K37)) + AB37*INDEX(YearMap!$Q$2:$Q$6, MATCH(C37, YearMap!$A$2:$A$6, 0)) | AF37: =AD37-AE37 | AG37: =B37&"|"&C37
A38: =AG38 | B38: =Scenarios!A10 | C38: FY2027 | D38: =IF(Scenarios!D10=1,0, L38) | E38: =IF(Scenarios!E10=1,0, M38) | F38: =D38+E38 | G38: =YearMap!B3 | H38: =YearMap!C3 | I38: =YearMap!D3 | J38: =1-BaselineCalc!$B$5 | K38: =Scenarios!G10 | L38: =IF(Scenarios!$Q10=1,BaselineCalc!$B$7*(1+Parameters_Public!$C44)^(IF($C38="FY2026",0,IF($C38="FY2027",1,IF($C38="FY2028",2,IF($C38="FY2029",3,IF($C38="FY2030",4,0))))))+ROUND(Scenarios!J10*Scenarios!$F10,0),BaselineCalc!$B$7+ROUND(Scenarios!J10*Scenarios!$F10,0)) | M38: =IF(Scenarios!$R10=1,BaselineCalc!$B$8*(1+Parameters_Public!$C45)^(IF($C38="FY2026",0,IF($C38="FY2027",1,IF($C38="FY2028",2,IF($C38="FY2029",3,IF($C38="FY2030",4,0))))))+Scenarios!J10-ROUND(Scenarios!J10*Scenarios!$F10,0),BaselineCalc!$B$8+Scenarios!J10-ROUND(Scenarios!J10*Scenarios!$F10,0)) | N38: =(L38-D38) + (M38-E38) | O38: =(Parameters_Public!$C$23*(L38-D38)+Parameters_Public!$C$24*(M38-E38)) | P38: =YearMap!E3 | Q38: =IF(Scenarios!N10="lease", YearMap!F3, YearMap!G3) | R38: =IF(Scenarios!D10=1, Q38*H38, H38) | S38: =IF(Scenarios!E10=1, Q38*I38, I38) | T38: =IF(C38="FY2026", (Scenarios!D10+Scenarios!E10)*BaselineCalc!$B$22, 0) | U38: =(R38+S38+G38*F38)*J38*(1-K38) | V38: =O38*(G38+P38) | W38: =U38+V38+IF(Parameters_Public!$C$28=1, T38, 0) | X38: =IF(F38+O38>0, W38/(F38+O38),"") | Y38: =INDEX(YearMap!$I$2:$I$6, MATCH(C38, YearMap!$A$2:$A$6, 0)) | Z38: =W38 - ((Y38 + IF(Parameters_Public!$C$20=1, Parameters_Public!$C$19, 0))*AC38) | AA38: =IF($AC38>0, $Z38/$AC38, 0) | AB38: =MAX(0, (MAX(0, $D38-BaselineCalc!$B$7) + MAX(0, $E38-BaselineCalc!$B$8))) | AC38: =L38+M38-N38+O38 | AD38: =( (Y38 + IF(Parameters_Public!$C20=1, INDEX(YearMap!$O$2:$O$6, MATCH(C38, YearMap!$A$2:$A$6, 0)), 0)) * AC38 ) + AC38*INDEX(YearMap!$P$2:$P$6, MATCH(C38, YearMap!$A$2:$A$6, 0)) + AB38*( INDEX(YearMap!$R$2:$R$6, MATCH(C38, YearMap!$A$2:$A$6, 0)) - INDEX(YearMap!$P$2:$P$6, MATCH(C38, YearMap!$A$2:$A$6, 0)) ) | AE38: =(W38 - (1-Parameters_Public!$C$43)*$G38*$AB38*$J38*(1-$K38)) + AB38*INDEX(YearMap!$Q$2:$Q$6, MATCH(C38, YearMap!$A$2:$A$6, 0)) | AF38: =AD38-AE38 | AG38: =B38&"|"&C38
A39: =AG39 | B39: =Scenarios!A10 | C39: FY2028 | D39: =IF(Scenarios!D10=1,0, L39) | E39: =IF(Scenarios!E10=1,0, M39) | F39: =D39+E39 | G39: =YearMap!B4 | H39: =YearMap!C4 | I39: =YearMap!D4 | J39: =1-BaselineCalc!$B$5 | K39: =Scenarios!G10 | L39: =IF(Scenarios!$Q10=1,BaselineCalc!$B$7*(1+Parameters_Public!$C44)^(IF($C39="FY2026",0,IF($C39="FY2027",1,IF($C39="FY2028",2,IF($C39="FY2029",3,IF($C39="FY2030",4,0))))))+ROUND(Scenarios!K10*Scenarios!$F10,0),BaselineCalc!$B$7+ROUND(Scenarios!K10*Scenarios!$F10,0)) | M39: =IF(Scenarios!$R10=1,BaselineCalc!$B$8*(1+Parameters_Public!$C45)^(IF($C39="FY2026",0,IF($C39="FY2027",1,IF($C39="FY2028",2,IF($C39="FY2029",3,IF($C39="FY2030",4,0))))))+Scenarios!K10-ROUND(Scenarios!K10*Scenarios!$F10,0),BaselineCalc!$B$8+Scenarios!K10-ROUND(Scenarios!K10*Scenarios!$F10,0)) | N39: =(L39-D39) + (M39-E39) | O39: =(Parameters_Public!$C$23*(L39-D39)+Parameters_Public!$C$24*(M39-E39)) | P39: =YearMap!E4 | Q39: =IF(Scenarios!N10="lease", YearMap!F4, YearMap!G4) | R39: =IF(Scenarios!D10=1, Q39*H39, H39) | S39: =IF(Scenarios!E10=1, Q39*I39, I39) | T39: =IF(C39="FY2026", (Scenarios!D10+Scenarios!E10)*BaselineCalc!$B$22, 0) | U39: =(R39+S39+G39*F39)*J39*(1-K39) | V39: =O39*(G39+P39) | W39: =U39+V39+IF(Parameters_Public!$C$28=1, T39, 0) | X39: =IF(F39+O39>0, W39/(F39+O39),"") | Y39: =INDEX(YearMap!$I$2:$I$6, MATCH(C39, YearMap!$A$2:$A$6, 0)) | Z39: =W39 - ((Y39 + IF(Parameters_Public!$C$20=1, Parameters_Public!$C$19, 0))*AC39) | AA39: =IF($AC39>0, $Z39/$AC39, 0) | AB39: =MAX(0, (MAX(0, $D39-BaselineCalc!$B$7) + MAX(0, $E39-BaselineCalc!$B$8))) | AC39: =L39+M39-N39+O39 | AD39: =( (Y39 + IF(Parameters_Public!$C20=1, INDEX(YearMap!$O$2:$O$6, MATCH(C39, YearMap!$A$2:$A$6, 0)), 0)) * AC39 ) + AC39*INDEX(YearMap!$P$2:$P$6, MATCH(C39, YearMap!$A$2:$A$6, 0)) + AB39*( INDEX(YearMap!$R$2:$R$6, MATCH(C39, YearMap!$A$2:$A$6, 0)) - INDEX(YearMap!$P$2:$P$6, MATCH(C39, YearMap!$A$2:$A$6, 0)) ) | AE39: =(W39 - (1-Parameters_Public!$C$43)*$G39*$AB39*$J39*(1-$K39)) + AB39*INDEX(YearMap!$Q$2:$Q$6, MATCH(C39, YearMap!$A$2:$A$6, 0)) | AF39: =AD39-AE39 | AG39: =B39&"|"&C39
