Workbook

Sheet Summary

Sheet Control_Center
A1: Control center - yellow shaded fields are editable inputs
A3: Foundational inputs
B5: Parameter | C5: Value | H5: Notes
B6: MO inflation | C6: 0.025 | H6: Annual inflation factor.
B7: Base MO per ADM (FY25) | C7: 9936 | H7: "MO" = xx. Working base for FY25. Calculated from reported budget data and enrollment estimates - as relates to Echo Canyon and Pima only.
B8: Fixed share of MO | C8: 0.46 | H8: Share of MO treated as semi‑fixed (plant/insurance).
B9: Base State Aid per ADM (FY26) | C9: 5013 | H9: Editable; ADE base aid.
B10: Ops savings (keep‑open) | C10: 0.007 | H10: Light discipline if sites remain open (not used here).
B11: Extra savings (Co‑location) | C11: 0.015 | H11: Incremental savings for co‑location (not used here).
B12: Echo base ADM | C12: 257 | H12: "ADM" = average daily membership; roughly equivalent to enrollment. Approximate current Echo enrollment
B13: Pima base ADM | C13: 296 | H13: Approximate current Pima enrollment
B14: Total base ADM | C14: =C12+C13 -> 553 | H14: Echo base ADM + Pima base ADM
B15: Repurpose TI per closed site (FY26) | C15: 1200000 | H15: Research suggests a xx
B16: Retention r (in case of repurpose) | C16: 0.75 | H16: Research suggests a range in the 0.5-0.8 range. Since Echo is a choice school with high % of families from out of district, reality might be lower?
B17: MarginalFactor_for_Overlay | C17: 0.4 | H17: Assuming there is a reduced marginal cost of adding new (growth) students, especially when the schools (Echo and Pima) have capacity. In reality this is probably a complicated step function, but we can approximate.
A19: Repurpose trajectory assumptions
B21: Year | C21: h | D21: f_lease | E21: f_ops
B22: FY2026 | C22: 1000 | D22: 0.4 | E22: 0.5 | H22: (For 'h') Research suggests an incremental transition cost (largely related to bus transportation) that can start higher than $1000. Assumption is this is managed down over time
B23: FY2027 | C23: 800 | D23: 0.3 | E23: 0.4 | H23: (For 'f_lease') Assuming repurpose = lease… depending on lease timing and type / arrangement (e.g. triple net?), district will carry some percentage of fixed and semi-fixed costs for a certain period of time
B24: FY2028 | C24: 600 | D24: 0.2 | E24: 0.35 | H24: (For 'f_ops') Assuming repurpose = some operational repurpose (not lease or sale)… depending on timing and type of repurpose, district will still carry some percentage of fixed and semi-fixed costs
B25: FY2029 | C25: 500 | D25: 0.1 | E25: 0.3
B26: FY2030 | C26: 300 | D26: 0.1 | E26: 0.3
A28: Scenario assumptions
A30: (Reference) | B30: Scenario title | C30: TargetGrowth (#) | D30: CloseEcho (0 or 1) | E30: ClosePima (0 or 1) | F30: EchoShareGrowth (ratio) | G30: ExtraOpSavings (ratio)
A31: D. Grow Both (Overlay 0) | B31: CUSTOM_KeepOpen_v1 | C31: 0 | D31: 0 | E31: 0 | F31: 0.5 | G31: 0
A32: E. Status‑Quo + Targets (0) | B32: Status‑Quo + Op Growth Targets | C32: 150 | D32: 0 | E32: 0 | F32: 0.5 | G32: 0 | H32: Echo and Pima remain open; uplift warm handoff effort (intra-SUSD) and implement cross-district marketing initiative (e.g. capture ~10% of Kyrene's displaced families?)
A33: F. Co‑Location @ Echo (0) | B33: Co‑Location @ Echo + Op Growth Targets | C33: 150 | D33: 0 | E33: 0 | F33: 0.5 | G33: 0.05
A34: D. Grow Both (Overlay 100) | B34: Grow Both + Op Growth Targets | C34: 250 | D34: 0 | E34: 0 | F34: 0.5 | G34: 0
A35: D. Grow Both (Overlay 150) | B35: CUSTOM_KeepOpen_v2 | C35: 0 | D35: 0 | E35: 0 | F35: 0.5 | G35: 0
A36: G. D‑Hub @ Echo (Ramp 50→100→150) | B36: Growth Hub @ Echo + Status-Quo Pima + Op Growth Targets | C36: 150 | D36: 0 | E36: 0 | F36: 0.7 | G36: 0
A37: A. Repurpose BOTH (lease) | B37: Repurpose BOTH (lease) | C37: 0 | D37: 1 | E37: 1 | F37: 0.5 | G37: 0
A38: A. Repurpose BOTH (ops) | B38: Repurpose BOTH (ops) | C38: 0 | D38: 1 | E38: 1 | F38: 0.5 | G38: 0
A39: B. Repurpose ECHO (lease) | B39: Repurpose ECHO (lease) + Status-Quo Pima + Pima Op Growth Targets | C39: 0 | D39: 1 | E39: 0 | F39: 0 | G39: 0
A40: B. Repurpose ECHO (ops) | B40: Repurpose ECHO (ops) + Status-Quo Pima + Pima Op Growth Targets | C40: 150 | D40: 1 | E40: 0 | F40: 0 | G40: 0
A41: C. Repurpose PIMA (lease) | B41: Repurpose PIMA (lease) + Growth Hub @ Echo + Echo Op Growth Targets | C41: 0 | D41: 0 | E41: 1 | F41: 1 | G41: 0
A42: C. Repurpose PIMA (ops) | B42: Repurpose PIMA (ops) + Growth Hub @ Echo + Echo Op Growth Targets | C42: 200 | D42: 0 | E42: 1 | F42: 1 | G42: 0
A44: Qualitative assessment
B46: Scenario title | C46: Distinctiveness | D46: Reversibility | H46: Example qualitative metrics to consider. Possibly interesting as part of overall story.
B47: CUSTOM1 | C47: + | D47: Med
B48: Status‑Quo + Op Growth Targets | C48: o | D48: High
B49: Co‑Location @ Echo + Op Growth Targets | C49: ++ | D49: Med
B50: Grow Both + Op Growth Targets | C50: ++ | D50: Med
B51: CUSTOM2 | C51: + | D51: Med
B52: Growth Hub @ Echo + Status-Quo Pima + Op Growth Targets | C52: ++ | D52: Med
B53: Repurpose BOTH (lease) | C53: -- | D53: Low
B54: Repurpose BOTH (ops) | C54: - | D54: Low-Med
B55: Repurpose ECHO (lease) + Status-Quo Pima + Pima Op Growth Targets | C55: - | D55: Low-Med
B56: Repurpose ECHO (ops) + Status-Quo Pima + Pima Op Growth Targets | C56: o | D56: Low-Med
B57: Repurpose PIMA (lease) + Growth Hub @ Echo + Echo Op Growth Targets | C57: - | D57: Low-Med
B58: Repurpose PIMA (ops) + Growth Hub @ Echo + Echo Op Growth Targets | C58: o | D58: Low-Med

Sheet Dashboard
G1: Operational | I1: Qualitative | K1: Net figures ('revenue' - 'cost') | O1: Scenario net figures vs. Repurpose both (ops)
B2: ScenarioKey | C2: FY2028 Comparable $/Student | D2: FY2030 Comparable $/Student | E2: 3‑yr Avg Comparable $/Student (FY26–FY28) | F2: 5‑yr Avg Comparable $/Student (FY26–FY30) | G2: # Students displaced | H2: FY2030 # students served (open & retained) | I2: =Control_Center!C46 -> Distinctiveness | J2: =Control_Center!D46 -> Reversibility | K2: FY2028 Net ($) | L2: FY2030 Net ($) | M2: 5-yr Net Avg ($) | N2: (Ref) Control center labels | O2: Δ FY2030 Net ($) vs Repurpose BOTH (ops) | P2: Δ 5-yr Avg Net ($) vs Repurpose BOTH (ops)
B3: =Scenarios!A8 -> A_Repurpose_Both_lease | C3: =INDEX(MultiYear_ProForma!$X$2:$X$61, MATCH(Scenarios!A8&"|FY2028", MultiYear_ProForma!$AG$2:$AG$61, 0)) -> 7681.3358 | D3: =INDEX(MultiYear_ProForma!$X$2:$X$61, MATCH(Scenarios!A8&"|FY2030", MultiYear_ProForma!$AG$2:$AG$61, 0)) -> 7055.1657 | E3: =AVERAGE(INDEX(MultiYear_ProForma!$X$2:$X$61, MATCH(Scenarios!A8&"|FY2026", MultiYear_ProForma!$AG$2:$AG$61, 0)),INDEX(MultiYear_ProForma!$X$2:$X$61, MATCH(Scenarios!A8&"|FY2027", MultiYear_ProForma!$AG$2:$AG$61, 0)),INDEX(MultiYear_ProForma!$X$2:$X$61, MATCH(Scenarios!A8&"|FY2028", MultiYear_ProForma!$AG$2:$AG$61, 0))) -> 10264.337 | F3: =AVERAGE(INDEX(MultiYear_ProForma!$X$2:$X$61, MATCH(Scenarios!A8&"|FY2026", MultiYear_ProForma!$AG$2:$AG$61, 0)),INDEX(MultiYear_ProForma!$X$2:$X$61, MATCH(Scenarios!A8&"|FY2027", MultiYear_ProForma!$AG$2:$AG$61, 0)),INDEX(MultiYear_ProForma!$X$2:$X$61, MATCH(Scenarios!A8&"|FY2028", MultiYear_ProForma!$AG$2:$AG$61, 0)),INDEX(MultiYear_ProForma!$X$2:$X$61, MATCH(Scenarios!A8&"|FY2029", MultiYear_ProForma!$AG$2:$AG$61, 0)),INDEX(MultiYear_ProForma!$X$2:$X$61, MATCH(Scenarios!A8&"|FY2030", MultiYear_ProForma!$AG$2:$AG$61, 0))) -> 8987.7164 | G3: =IFERROR(VLOOKUP($B3&"|FY2026", MultiYear_ProForma!$A:$AG, 14, FALSE), "") -> 553 | H3: =IFERROR(VLOOKUP($B3&"|FY2030", MultiYear_ProForma!$A:$AG, 6, FALSE) + VLOOKUP($B3&"|FY2030", MultiYear_ProForma!$A:$AG, 15, FALSE), "") -> 414.75 | I3: =Control_Center!C48 -> o | J3: =Control_Center!D48 -> High | K3: =SUMIFS(MultiYear_ProForma!$AF:$AF, MultiYear_ProForma!$B:$B, $B3, MultiYear_ProForma!$C:$C, "FY2028") -> -1022695 | L3: =SUMIFS(MultiYear_ProForma!$AF:$AF, MultiYear_ProForma!$B:$B, $B3, MultiYear_ProForma!$C:$C, "FY2030") -> -675600.07 | M3: =(SUMIFS(MultiYear_ProForma!$AF:$AF, MultiYear_ProForma!$B:$B, $B3, MultiYear_ProForma!$C:$C, "FY2026")+SUMIFS(MultiYear_ProForma!$AF:$AF, MultiYear_ProForma!$B:$B, $B3, MultiYear_ProForma!$C:$C, "FY2027")+SUMIFS(MultiYear_ProForma!$AF:$AF, MultiYear_ProForma!$B:$B, $B3, MultiYear_ProForma!$C:$C, "FY2028")+SUMIFS(MultiYear_ProForma!$AF:$AF, MultiYear_ProForma!$B:$B, $B3, MultiYear_ProForma!$C:$C, "FY2029")+SUMIFS(MultiYear_ProForma!$AF:$AF, MultiYear_ProForma!$B:$B, $B3, MultiYear_ProForma!$C:$C, "FY2030"))/5 -> -1563668 | N3: =Control_Center!B37 -> Repurpose BOTH (lease) | O3: =L3 - INDEX(L:L, MATCH("A_Repurpose_Both_ops", $B:$B, 0)) -> 567927.79 | P3: =M3 - INDEX(M:M, MATCH("A_Repurpose_Both_ops", $B:$B, 0)) -> 409674.21
B4: =Scenarios!A13 -> C_Repurpose_Pima_ops_EchoGHub_EchoTargets | C4: =INDEX(MultiYear_ProForma!$X$2:$X$61, MATCH(Scenarios!A13&"|FY2028", MultiYear_ProForma!$AG$2:$AG$61, 0)) -> 8542.5912 | D4: =INDEX(MultiYear_ProForma!$X$2:$X$61, MATCH(Scenarios!A13&"|FY2030", MultiYear_ProForma!$AG$2:$AG$61, 0)) -> 8755.1176 | E4: =AVERAGE(INDEX(MultiYear_ProForma!$X$2:$X$61, MATCH(Scenarios!A13&"|FY2026", MultiYear_ProForma!$AG$2:$AG$61, 0)),INDEX(MultiYear_ProForma!$X$2:$X$61, MATCH(Scenarios!A13&"|FY2027", MultiYear_ProForma!$AG$2:$AG$61, 0)),INDEX(MultiYear_ProForma!$X$2:$X$61, MATCH(Scenarios!A13&"|FY2028", MultiYear_ProForma!$AG$2:$AG$61, 0))) -> 9131.2109 | F4: =AVERAGE(INDEX(MultiYear_ProForma!$X$2:$X$61, MATCH(Scenarios!A13&"|FY2026", MultiYear_ProForma!$AG$2:$AG$61, 0)),INDEX(MultiYear_ProForma!$X$2:$X$61, MATCH(Scenarios!A13&"|FY2027", MultiYear_ProForma!$AG$2:$AG$61, 0)),INDEX(MultiYear_ProForma!$X$2:$X$61, MATCH(Scenarios!A13&"|FY2028", MultiYear_ProForma!$AG$2:$AG$61, 0)),INDEX(MultiYear_ProForma!$X$2:$X$61, MATCH(Scenarios!A13&"|FY2029", MultiYear_ProForma!$AG$2:$AG$61, 0)),INDEX(MultiYear_ProForma!$X$2:$X$61, MATCH(Scenarios!A13&"|FY2030", MultiYear_ProForma!$AG$2:$AG$61, 0))) -> 8951.6222 | G4: =IFERROR(VLOOKUP($B4&"|FY2026", MultiYear_ProForma!$A:$AG, 14, FALSE), "") -> 296 | H4: =IFERROR(VLOOKUP($B4&"|FY2030", MultiYear_ProForma!$A:$AG, 6, FALSE) + VLOOKUP($B4&"|FY2030", MultiYear_ProForma!$A:$AG, 15, FALSE), "") -> 679 | I4: =Control_Center!C47 -> + | J4: =Control_Center!D47 -> Med | K4: =SUMIFS(MultiYear_ProForma!$AF:$AF, MultiYear_ProForma!$B:$B, $B4, MultiYear_ProForma!$C:$C, "FY2028") -> -1570572.3 | L4: =SUMIFS(MultiYear_ProForma!$AF:$AF, MultiYear_ProForma!$B:$B, $B4, MultiYear_ProForma!$C:$C, "FY2030") -> -1536951.9 | M4: =(SUMIFS(MultiYear_ProForma!$AF:$AF, MultiYear_ProForma!$B:$B, $B4, MultiYear_ProForma!$C:$C, "FY2026")+SUMIFS(MultiYear_ProForma!$AF:$AF, MultiYear_ProForma!$B:$B, $B4, MultiYear_ProForma!$C:$C, "FY2027")+SUMIFS(MultiYear_ProForma!$AF:$AF, MultiYear_ProForma!$B:$B, $B4, MultiYear_ProForma!$C:$C, "FY2028")+SUMIFS(MultiYear_ProForma!$AF:$AF, MultiYear_ProForma!$B:$B, $B4, MultiYear_ProForma!$C:$C, "FY2029")+SUMIFS(MultiYear_ProForma!$AF:$AF, MultiYear_ProForma!$B:$B, $B4, MultiYear_ProForma!$C:$C, "FY2030"))/5 -> -1846495.6 | N4: =Control_Center!B42 -> Repurpose PIMA (ops) + Growth Hub @ Echo + Echo Op Growth Targets | O4: =L4 - INDEX(L:L, MATCH("A_Repurpose_Both_ops", $B:$B, 0)) -> -293424.08 | P4: =M4 - INDEX(M:M, MATCH("A_Repurpose_Both_ops", $B:$B, 0)) -> 126846.56
B5: =Scenarios!A4 -> F_CoLocation_Echo_Targets | C5: =INDEX(MultiYear_ProForma!$X$2:$X$61, MATCH(Scenarios!A4&"|FY2028", MultiYear_ProForma!$AG$2:$AG$61, 0)) -> 9103.1137 | D5: =INDEX(MultiYear_ProForma!$X$2:$X$61, MATCH(Scenarios!A4&"|FY2030", MultiYear_ProForma!$AG$2:$AG$61, 0)) -> 9563.9588 | E5: =AVERAGE(INDEX(MultiYear_ProForma!$X$2:$X$61, MATCH(Scenarios!A4&"|FY2026", MultiYear_ProForma!$AG$2:$AG$61, 0)),INDEX(MultiYear_ProForma!$X$2:$X$61, MATCH(Scenarios!A4&"|FY2027", MultiYear_ProForma!$AG$2:$AG$61, 0)),INDEX(MultiYear_ProForma!$X$2:$X$61, MATCH(Scenarios!A4&"|FY2028", MultiYear_ProForma!$AG$2:$AG$61, 0))) -> 8882.8916 | F5: =AVERAGE(INDEX(MultiYear_ProForma!$X$2:$X$61, MATCH(Scenarios!A4&"|FY2026", MultiYear_ProForma!$AG$2:$AG$61, 0)),INDEX(MultiYear_ProForma!$X$2:$X$61, MATCH(Scenarios!A4&"|FY2027", MultiYear_ProForma!$AG$2:$AG$61, 0)),INDEX(MultiYear_ProForma!$X$2:$X$61, MATCH(Scenarios!A4&"|FY2028", MultiYear_ProForma!$AG$2:$AG$61, 0)),INDEX(MultiYear_ProForma!$X$2:$X$61, MATCH(Scenarios!A4&"|FY2029", MultiYear_ProForma!$AG$2:$AG$61, 0)),INDEX(MultiYear_ProForma!$X$2:$X$61, MATCH(Scenarios!A4&"|FY2030", MultiYear_ProForma!$AG$2:$AG$61, 0))) -> 9108.665 | G5: =IFERROR(VLOOKUP($B5&"|FY2026", MultiYear_ProForma!$A:$AG, 14, FALSE), "") -> 0 | H5: =IFERROR(VLOOKUP($B5&"|FY2030", MultiYear_ProForma!$A:$AG, 6, FALSE) + VLOOKUP($B5&"|FY2030", MultiYear_ProForma!$A:$AG, 15, FALSE), "") -> 703 | I5: =Control_Center!C50 -> ++ | J5: =Control_Center!D50 -> Med | K5: =SUMIFS(MultiYear_ProForma!$AF:$AF, MultiYear_ProForma!$B:$B, $B5, MultiYear_ProForma!$C:$C, "FY2028") -> -2242414.5 | L5: =SUMIFS(MultiYear_ProForma!$AF:$AF, MultiYear_ProForma!$B:$B, $B5, MultiYear_ProForma!$C:$C, "FY2030") -> -2393426.8 | M5: =(SUMIFS(MultiYear_ProForma!$AF:$AF, MultiYear_ProForma!$B:$B, $B5, MultiYear_ProForma!$C:$C, "FY2026")+SUMIFS(MultiYear_ProForma!$AF:$AF, MultiYear_ProForma!$B:$B, $B5, MultiYear_ProForma!$C:$C, "FY2027")+SUMIFS(MultiYear_ProForma!$AF:$AF, MultiYear_ProForma!$B:$B, $B5, MultiYear_ProForma!$C:$C, "FY2028")+SUMIFS(MultiYear_ProForma!$AF:$AF, MultiYear_ProForma!$B:$B, $B5, MultiYear_ProForma!$C:$C, "FY2029")+SUMIFS(MultiYear_ProForma!$AF:$AF, MultiYear_ProForma!$B:$B, $B5, MultiYear_ProForma!$C:$C, "FY2030"))/5 -> -2244580 | N5: =Control_Center!B33 -> Co‑Location @ Echo + Op Growth Targets | O5: =L5 - INDEX(L:L, MATCH("A_Repurpose_Both_ops", $B:$B, 0)) -> -1149899 | P5: =M5 - INDEX(M:M, MATCH("A_Repurpose_Both_ops", $B:$B, 0)) -> -271237.83
B6: =Scenarios!A9 -> A_Repurpose_Both_ops | C6: =INDEX(MultiYear_ProForma!$X$2:$X$61, MATCH(Scenarios!A9&"|FY2028", MultiYear_ProForma!$AG$2:$AG$61, 0)) -> 8658.8437 | D6: =INDEX(MultiYear_ProForma!$X$2:$X$61, MATCH(Scenarios!A9&"|FY2030", MultiYear_ProForma!$AG$2:$AG$61, 0)) -> 8424.4913 | E6: =AVERAGE(INDEX(MultiYear_ProForma!$X$2:$X$61, MATCH(Scenarios!A9&"|FY2026", MultiYear_ProForma!$AG$2:$AG$61, 0)),INDEX(MultiYear_ProForma!$X$2:$X$61, MATCH(Scenarios!A9&"|FY2027", MultiYear_ProForma!$AG$2:$AG$61, 0)),INDEX(MultiYear_ProForma!$X$2:$X$61, MATCH(Scenarios!A9&"|FY2028", MultiYear_ProForma!$AG$2:$AG$61, 0))) -> 11008.856 | F6: =AVERAGE(INDEX(MultiYear_ProForma!$X$2:$X$61, MATCH(Scenarios!A9&"|FY2026", MultiYear_ProForma!$AG$2:$AG$61, 0)),INDEX(MultiYear_ProForma!$X$2:$X$61, MATCH(Scenarios!A9&"|FY2027", MultiYear_ProForma!$AG$2:$AG$61, 0)),INDEX(MultiYear_ProForma!$X$2:$X$61, MATCH(Scenarios!A9&"|FY2028", MultiYear_ProForma!$AG$2:$AG$61, 0)),INDEX(MultiYear_ProForma!$X$2:$X$61, MATCH(Scenarios!A9&"|FY2029", MultiYear_ProForma!$AG$2:$AG$61, 0)),INDEX(MultiYear_ProForma!$X$2:$X$61, MATCH(Scenarios!A9&"|FY2030", MultiYear_ProForma!$AG$2:$AG$61, 0))) -> 9975.4782 | G6: =IFERROR(VLOOKUP($B6&"|FY2026", MultiYear_ProForma!$A:$AG, 14, FALSE), "") -> 553 | H6: =IFERROR(VLOOKUP($B6&"|FY2030", MultiYear_ProForma!$A:$AG, 6, FALSE) + VLOOKUP($B6&"|FY2030", MultiYear_ProForma!$A:$AG, 15, FALSE), "") -> 414.75 | I6: =Control_Center!C52 -> ++ | J6: =Control_Center!D52 -> Med | K6: =SUMIFS(MultiYear_ProForma!$AF:$AF, MultiYear_ProForma!$B:$B, $B6, MultiYear_ProForma!$C:$C, "FY2028") -> -1428116.3 | L6: =SUMIFS(MultiYear_ProForma!$AF:$AF, MultiYear_ProForma!$B:$B, $B6, MultiYear_ProForma!$C:$C, "FY2030") -> -1243527.9 | M6: =(SUMIFS(MultiYear_ProForma!$AF:$AF, MultiYear_ProForma!$B:$B, $B6, MultiYear_ProForma!$C:$C, "FY2026")+SUMIFS(MultiYear_ProForma!$AF:$AF, MultiYear_ProForma!$B:$B, $B6, MultiYear_ProForma!$C:$C, "FY2027")+SUMIFS(MultiYear_ProForma!$AF:$AF, MultiYear_ProForma!$B:$B, $B6, MultiYear_ProForma!$C:$C, "FY2028")+SUMIFS(MultiYear_ProForma!$AF:$AF, MultiYear_ProForma!$B:$B, $B6, MultiYear_ProForma!$C:$C, "FY2029")+SUMIFS(MultiYear_ProForma!$AF:$AF, MultiYear_ProForma!$B:$B, $B6, MultiYear_ProForma!$C:$C, "FY2030"))/5 -> -1973342.2 | N6: =Control_Center!B38 -> Repurpose BOTH (ops) | O6: =L6 - INDEX(L:L, MATCH("A_Repurpose_Both_ops", $B:$B, 0)) -> 0 | P6: =M6 - INDEX(M:M, MATCH("A_Repurpose_Both_ops", $B:$B, 0)) -> 0
B7: =Scenarios!A11 -> B_Repurpose_Echo_ops_PimaTargets | C7: =INDEX(MultiYear_ProForma!$X$2:$X$61, MATCH(Scenarios!A11&"|FY2028", MultiYear_ProForma!$AG$2:$AG$61, 0)) -> 8883.9911 | D7: =INDEX(MultiYear_ProForma!$X$2:$X$61, MATCH(Scenarios!A11&"|FY2030", MultiYear_ProForma!$AG$2:$AG$61, 0)) -> 9130.7464 | E7: =AVERAGE(INDEX(MultiYear_ProForma!$X$2:$X$61, MATCH(Scenarios!A11&"|FY2026", MultiYear_ProForma!$AG$2:$AG$61, 0)),INDEX(MultiYear_ProForma!$X$2:$X$61, MATCH(Scenarios!A11&"|FY2027", MultiYear_ProForma!$AG$2:$AG$61, 0)),INDEX(MultiYear_ProForma!$X$2:$X$61, MATCH(Scenarios!A11&"|FY2028", MultiYear_ProForma!$AG$2:$AG$61, 0))) -> 9485.5878 | F7: =AVERAGE(INDEX(MultiYear_ProForma!$X$2:$X$61, MATCH(Scenarios!A11&"|FY2026", MultiYear_ProForma!$AG$2:$AG$61, 0)),INDEX(MultiYear_ProForma!$X$2:$X$61, MATCH(Scenarios!A11&"|FY2027", MultiYear_ProForma!$AG$2:$AG$61, 0)),INDEX(MultiYear_ProForma!$X$2:$X$61, MATCH(Scenarios!A11&"|FY2028", MultiYear_ProForma!$AG$2:$AG$61, 0)),INDEX(MultiYear_ProForma!$X$2:$X$61, MATCH(Scenarios!A11&"|FY2029", MultiYear_ProForma!$AG$2:$AG$61, 0)),INDEX(MultiYear_ProForma!$X$2:$X$61, MATCH(Scenarios!A11&"|FY2030", MultiYear_ProForma!$AG$2:$AG$61, 0))) -> 9311.6231 | G7: =IFERROR(VLOOKUP($B7&"|FY2026", MultiYear_ProForma!$A:$AG, 14, FALSE), "") -> 257 | H7: =IFERROR(VLOOKUP($B7&"|FY2030", MultiYear_ProForma!$A:$AG, 6, FALSE) + VLOOKUP($B7&"|FY2030", MultiYear_ProForma!$A:$AG, 15, FALSE), "") -> 638.75 | I7: =Control_Center!C49 -> ++ | J7: =Control_Center!D49 -> Med | K7: =SUMIFS(MultiYear_ProForma!$AF:$AF, MultiYear_ProForma!$B:$B, $B7, MultiYear_ProForma!$C:$C, "FY2028") -> -1826853.4 | L7: =SUMIFS(MultiYear_ProForma!$AF:$AF, MultiYear_ProForma!$B:$B, $B7, MultiYear_ProForma!$C:$C, "FY2030") -> -1823737.5 | M7: =(SUMIFS(MultiYear_ProForma!$AF:$AF, MultiYear_ProForma!$B:$B, $B7, MultiYear_ProForma!$C:$C, "FY2026")+SUMIFS(MultiYear_ProForma!$AF:$AF, MultiYear_ProForma!$B:$B, $B7, MultiYear_ProForma!$C:$C, "FY2027")+SUMIFS(MultiYear_ProForma!$AF:$AF, MultiYear_ProForma!$B:$B, $B7, MultiYear_ProForma!$C:$C, "FY2028")+SUMIFS(MultiYear_ProForma!$AF:$AF, MultiYear_ProForma!$B:$B, $B7, MultiYear_ProForma!$C:$C, "FY2029")+SUMIFS(MultiYear_ProForma!$AF:$AF, MultiYear_ProForma!$B:$B, $B7, MultiYear_ProForma!$C:$C, "FY2030"))/5 -> -2098381.9 | N7: =Control_Center!B40 -> Repurpose ECHO (ops) + Status-Quo Pima + Pima Op Growth Targets | O7: =L7 - INDEX(L:L, MATCH("A_Repurpose_Both_ops", $B:$B, 0)) -> -580209.61 | P7: =M7 - INDEX(M:M, MATCH("A_Repurpose_Both_ops", $B:$B, 0)) -> -125039.76
B8: =Scenarios!A5 -> D_Grow_Both_Targets | C8: =INDEX(MultiYear_ProForma!$X$2:$X$61, MATCH(Scenarios!A5&"|FY2028", MultiYear_ProForma!$AG$2:$AG$61, 0)) -> 9103.4355 | D8: =INDEX(MultiYear_ProForma!$X$2:$X$61, MATCH(Scenarios!A5&"|FY2030", MultiYear_ProForma!$AG$2:$AG$61, 0)) -> 9564.2969 | E8: =AVERAGE(INDEX(MultiYear_ProForma!$X$2:$X$61, MATCH(Scenarios!A5&"|FY2026", MultiYear_ProForma!$AG$2:$AG$61, 0)),INDEX(MultiYear_ProForma!$X$2:$X$61, MATCH(Scenarios!A5&"|FY2027", MultiYear_ProForma!$AG$2:$AG$61, 0)),INDEX(MultiYear_ProForma!$X$2:$X$61, MATCH(Scenarios!A5&"|FY2028", MultiYear_ProForma!$AG$2:$AG$61, 0))) -> 8883.2057 | F8: =AVERAGE(INDEX(MultiYear_ProForma!$X$2:$X$61, MATCH(Scenarios!A5&"|FY2026", MultiYear_ProForma!$AG$2:$AG$61, 0)),INDEX(MultiYear_ProForma!$X$2:$X$61, MATCH(Scenarios!A5&"|FY2027", MultiYear_ProForma!$AG$2:$AG$61, 0)),INDEX(MultiYear_ProForma!$X$2:$X$61, MATCH(Scenarios!A5&"|FY2028", MultiYear_ProForma!$AG$2:$AG$61, 0)),INDEX(MultiYear_ProForma!$X$2:$X$61, MATCH(Scenarios!A5&"|FY2029", MultiYear_ProForma!$AG$2:$AG$61, 0)),INDEX(MultiYear_ProForma!$X$2:$X$61, MATCH(Scenarios!A5&"|FY2030", MultiYear_ProForma!$AG$2:$AG$61, 0))) -> 9108.9871 | G8: =IFERROR(VLOOKUP($B8&"|FY2026", MultiYear_ProForma!$A:$AG, 14, FALSE), "") -> 0 | H8: =IFERROR(VLOOKUP($B8&"|FY2030", MultiYear_ProForma!$A:$AG, 6, FALSE) + VLOOKUP($B8&"|FY2030", MultiYear_ProForma!$A:$AG, 15, FALSE), "") -> 803 | I8: =Control_Center!C56 -> o | J8: =Control_Center!D56 -> Low-Med | K8: =SUMIFS(MultiYear_ProForma!$AF:$AF, MultiYear_ProForma!$B:$B, $B8, MultiYear_ProForma!$C:$C, "FY2028") -> -2261360.1 | L8: =SUMIFS(MultiYear_ProForma!$AF:$AF, MultiYear_ProForma!$B:$B, $B8, MultiYear_ProForma!$C:$C, "FY2030") -> -2418664.4 | M8: =(SUMIFS(MultiYear_ProForma!$AF:$AF, MultiYear_ProForma!$B:$B, $B8, MultiYear_ProForma!$C:$C, "FY2026")+SUMIFS(MultiYear_ProForma!$AF:$AF, MultiYear_ProForma!$B:$B, $B8, MultiYear_ProForma!$C:$C, "FY2027")+SUMIFS(MultiYear_ProForma!$AF:$AF, MultiYear_ProForma!$B:$B, $B8, MultiYear_ProForma!$C:$C, "FY2028")+SUMIFS(MultiYear_ProForma!$AF:$AF, MultiYear_ProForma!$B:$B, $B8, MultiYear_ProForma!$C:$C, "FY2029")+SUMIFS(MultiYear_ProForma!$AF:$AF, MultiYear_ProForma!$B:$B, $B8, MultiYear_ProForma!$C:$C, "FY2030"))/5 -> -2263650.6 | N8: =Control_Center!B34 -> Grow Both + Op Growth Targets | O8: =L8 - INDEX(L:L, MATCH("A_Repurpose_Both_ops", $B:$B, 0)) -> -1175136.6 | P8: =M8 - INDEX(M:M, MATCH("A_Repurpose_Both_ops", $B:$B, 0)) -> -290308.47
B9: =Scenarios!A12 -> C_Repurpose_Pima_lease_EchoGHub_EchoTargets | C9: =INDEX(MultiYear_ProForma!$X$2:$X$61, MATCH(Scenarios!A12&"|FY2028", MultiYear_ProForma!$AG$2:$AG$61, 0)) -> 9260.7589 | D9: =INDEX(MultiYear_ProForma!$X$2:$X$61, MATCH(Scenarios!A12&"|FY2030", MultiYear_ProForma!$AG$2:$AG$61, 0)) -> 9259.1497 | E9: =AVERAGE(INDEX(MultiYear_ProForma!$X$2:$X$61, MATCH(Scenarios!A12&"|FY2026", MultiYear_ProForma!$AG$2:$AG$61, 0)),INDEX(MultiYear_ProForma!$X$2:$X$61, MATCH(Scenarios!A12&"|FY2027", MultiYear_ProForma!$AG$2:$AG$61, 0)),INDEX(MultiYear_ProForma!$X$2:$X$61, MATCH(Scenarios!A12&"|FY2028", MultiYear_ProForma!$AG$2:$AG$61, 0))) -> 10261.086 | F9: =AVERAGE(INDEX(MultiYear_ProForma!$X$2:$X$61, MATCH(Scenarios!A12&"|FY2026", MultiYear_ProForma!$AG$2:$AG$61, 0)),INDEX(MultiYear_ProForma!$X$2:$X$61, MATCH(Scenarios!A12&"|FY2027", MultiYear_ProForma!$AG$2:$AG$61, 0)),INDEX(MultiYear_ProForma!$X$2:$X$61, MATCH(Scenarios!A12&"|FY2028", MultiYear_ProForma!$AG$2:$AG$61, 0)),INDEX(MultiYear_ProForma!$X$2:$X$61, MATCH(Scenarios!A12&"|FY2029", MultiYear_ProForma!$AG$2:$AG$61, 0)),INDEX(MultiYear_ProForma!$X$2:$X$61, MATCH(Scenarios!A12&"|FY2030", MultiYear_ProForma!$AG$2:$AG$61, 0))) -> 9834.3619 | G9: =IFERROR(VLOOKUP($B9&"|FY2026", MultiYear_ProForma!$A:$AG, 14, FALSE), "") -> 296 | H9: =IFERROR(VLOOKUP($B9&"|FY2030", MultiYear_ProForma!$A:$AG, 6, FALSE) + VLOOKUP($B9&"|FY2030", MultiYear_ProForma!$A:$AG, 15, FALSE), "") -> 479 | I9: =Control_Center!C53 -> -- | J9: =Control_Center!D53 -> Low | K9: =SUMIFS(MultiYear_ProForma!$AF:$AF, MultiYear_ProForma!$B:$B, $B9, MultiYear_ProForma!$C:$C, "FY2028") -> -1937666.9 | L9: =SUMIFS(MultiYear_ProForma!$AF:$AF, MultiYear_ProForma!$B:$B, $B9, MultiYear_ProForma!$C:$C, "FY2030") -> -1835967.4 | M9: =(SUMIFS(MultiYear_ProForma!$AF:$AF, MultiYear_ProForma!$B:$B, $B9, MultiYear_ProForma!$C:$C, "FY2026")+SUMIFS(MultiYear_ProForma!$AF:$AF, MultiYear_ProForma!$B:$B, $B9, MultiYear_ProForma!$C:$C, "FY2027")+SUMIFS(MultiYear_ProForma!$AF:$AF, MultiYear_ProForma!$B:$B, $B9, MultiYear_ProForma!$C:$C, "FY2028")+SUMIFS(MultiYear_ProForma!$AF:$AF, MultiYear_ProForma!$B:$B, $B9, MultiYear_ProForma!$C:$C, "FY2029")+SUMIFS(MultiYear_ProForma!$AF:$AF, MultiYear_ProForma!$B:$B, $B9, MultiYear_ProForma!$C:$C, "FY2030"))/5 -> -2211443 | N9: =Control_Center!B41 -> Repurpose PIMA (lease) + Growth Hub @ Echo + Echo Op Growth Targets | O9: =L9 - INDEX(L:L, MATCH("A_Repurpose_Both_ops", $B:$B, 0)) -> -592439.53 | P9: =M9 - INDEX(M:M, MATCH("A_Repurpose_Both_ops", $B:$B, 0)) -> -238100.85
B10: =Scenarios!A10 -> B_Repurpose_Echo_lease_PimaTargets | C10: =INDEX(MultiYear_ProForma!$X$2:$X$61, MATCH(Scenarios!A10&"|FY2028", MultiYear_ProForma!$AG$2:$AG$61, 0)) -> 9464.1488 | D10: =INDEX(MultiYear_ProForma!$X$2:$X$61, MATCH(Scenarios!A10&"|FY2030", MultiYear_ProForma!$AG$2:$AG$61, 0)) -> 9542.9675 | E10: =AVERAGE(INDEX(MultiYear_ProForma!$X$2:$X$61, MATCH(Scenarios!A10&"|FY2026", MultiYear_ProForma!$AG$2:$AG$61, 0)),INDEX(MultiYear_ProForma!$X$2:$X$61, MATCH(Scenarios!A10&"|FY2027", MultiYear_ProForma!$AG$2:$AG$61, 0)),INDEX(MultiYear_ProForma!$X$2:$X$61, MATCH(Scenarios!A10&"|FY2028", MultiYear_ProForma!$AG$2:$AG$61, 0))) -> 10384.863 | F10: =AVERAGE(INDEX(MultiYear_ProForma!$X$2:$X$61, MATCH(Scenarios!A10&"|FY2026", MultiYear_ProForma!$AG$2:$AG$61, 0)),INDEX(MultiYear_ProForma!$X$2:$X$61, MATCH(Scenarios!A10&"|FY2027", MultiYear_ProForma!$AG$2:$AG$61, 0)),INDEX(MultiYear_ProForma!$X$2:$X$61, MATCH(Scenarios!A10&"|FY2028", MultiYear_ProForma!$AG$2:$AG$61, 0)),INDEX(MultiYear_ProForma!$X$2:$X$61, MATCH(Scenarios!A10&"|FY2029", MultiYear_ProForma!$AG$2:$AG$61, 0)),INDEX(MultiYear_ProForma!$X$2:$X$61, MATCH(Scenarios!A10&"|FY2030", MultiYear_ProForma!$AG$2:$AG$61, 0))) -> 10017.906 | G10: =IFERROR(VLOOKUP($B10&"|FY2026", MultiYear_ProForma!$A:$AG, 14, FALSE), "") -> 257 | H10: =IFERROR(VLOOKUP($B10&"|FY2030", MultiYear_ProForma!$A:$AG, 6, FALSE) + VLOOKUP($B10&"|FY2030", MultiYear_ProForma!$A:$AG, 15, FALSE), "") -> 488.75 | I10: =Control_Center!C54 -> - | J10: =Control_Center!D54 -> Low-Med | K10: =SUMIFS(MultiYear_ProForma!$AF:$AF, MultiYear_ProForma!$B:$B, $B10, MultiYear_ProForma!$C:$C, "FY2028") -> -2076514.8 | L10: =SUMIFS(MultiYear_ProForma!$AF:$AF, MultiYear_ProForma!$B:$B, $B10, MultiYear_ProForma!$C:$C, "FY2030") -> -2012054.3 | M10: =(SUMIFS(MultiYear_ProForma!$AF:$AF, MultiYear_ProForma!$B:$B, $B10, MultiYear_ProForma!$C:$C, "FY2026")+SUMIFS(MultiYear_ProForma!$AF:$AF, MultiYear_ProForma!$B:$B, $B10, MultiYear_ProForma!$C:$C, "FY2027")+SUMIFS(MultiYear_ProForma!$AF:$AF, MultiYear_ProForma!$B:$B, $B10, MultiYear_ProForma!$C:$C, "FY2028")+SUMIFS(MultiYear_ProForma!$AF:$AF, MultiYear_ProForma!$B:$B, $B10, MultiYear_ProForma!$C:$C, "FY2029")+SUMIFS(MultiYear_ProForma!$AF:$AF, MultiYear_ProForma!$B:$B, $B10, MultiYear_ProForma!$C:$C, "FY2030"))/5 -> -2346163.7 | N10: =Control_Center!B39 -> Repurpose ECHO (lease) + Status-Quo Pima + Pima Op Growth Targets | O10: =L10 - INDEX(L:L, MATCH("A_Repurpose_Both_ops", $B:$B, 0)) -> -768526.4 | P10: =M10 - INDEX(M:M, MATCH("A_Repurpose_Both_ops", $B:$B, 0)) -> -372821.58
B11: =Scenarios!A3 -> E_StatusQuo_Targets | C11: =INDEX(MultiYear_ProForma!$X$2:$X$61, MATCH(Scenarios!A3&"|FY2028", MultiYear_ProForma!$AG$2:$AG$61, 0)) -> 9582.2249 | D11: =INDEX(MultiYear_ProForma!$X$2:$X$61, MATCH(Scenarios!A3&"|FY2030", MultiYear_ProForma!$AG$2:$AG$61, 0)) -> 10067.325 | E11: =AVERAGE(INDEX(MultiYear_ProForma!$X$2:$X$61, MATCH(Scenarios!A3&"|FY2026", MultiYear_ProForma!$AG$2:$AG$61, 0)),INDEX(MultiYear_ProForma!$X$2:$X$61, MATCH(Scenarios!A3&"|FY2027", MultiYear_ProForma!$AG$2:$AG$61, 0)),INDEX(MultiYear_ProForma!$X$2:$X$61, MATCH(Scenarios!A3&"|FY2028", MultiYear_ProForma!$AG$2:$AG$61, 0))) -> 9350.4122 | F11: =AVERAGE(INDEX(MultiYear_ProForma!$X$2:$X$61, MATCH(Scenarios!A3&"|FY2026", MultiYear_ProForma!$AG$2:$AG$61, 0)),INDEX(MultiYear_ProForma!$X$2:$X$61, MATCH(Scenarios!A3&"|FY2027", MultiYear_ProForma!$AG$2:$AG$61, 0)),INDEX(MultiYear_ProForma!$X$2:$X$61, MATCH(Scenarios!A3&"|FY2028", MultiYear_ProForma!$AG$2:$AG$61, 0)),INDEX(MultiYear_ProForma!$X$2:$X$61, MATCH(Scenarios!A3&"|FY2029", MultiYear_ProForma!$AG$2:$AG$61, 0)),INDEX(MultiYear_ProForma!$X$2:$X$61, MATCH(Scenarios!A3&"|FY2030", MultiYear_ProForma!$AG$2:$AG$61, 0))) -> 9588.0684 | G11: =IFERROR(VLOOKUP($B11&"|FY2026", MultiYear_ProForma!$A:$AG, 14, FALSE), "") -> 0 | H11: =IFERROR(VLOOKUP($B11&"|FY2030", MultiYear_ProForma!$A:$AG, 6, FALSE) + VLOOKUP($B11&"|FY2030", MultiYear_ProForma!$A:$AG, 15, FALSE), "") -> 703 | I11: =Control_Center!C58 -> o | J11: =Control_Center!D58 -> Low-Med | K11: =SUMIFS(MultiYear_ProForma!$AF:$AF, MultiYear_ProForma!$B:$B, $B11, MultiYear_ProForma!$C:$C, "FY2028") -> -2553410.8 | L11: =SUMIFS(MultiYear_ProForma!$AF:$AF, MultiYear_ProForma!$B:$B, $B11, MultiYear_ProForma!$C:$C, "FY2030") -> -2720167.3 | M11: =(SUMIFS(MultiYear_ProForma!$AF:$AF, MultiYear_ProForma!$B:$B, $B11, MultiYear_ProForma!$C:$C, "FY2026")+SUMIFS(MultiYear_ProForma!$AF:$AF, MultiYear_ProForma!$B:$B, $B11, MultiYear_ProForma!$C:$C, "FY2027")+SUMIFS(MultiYear_ProForma!$AF:$AF, MultiYear_ProForma!$B:$B, $B11, MultiYear_ProForma!$C:$C, "FY2028")+SUMIFS(MultiYear_ProForma!$AF:$AF, MultiYear_ProForma!$B:$B, $B11, MultiYear_ProForma!$C:$C, "FY2029")+SUMIFS(MultiYear_ProForma!$AF:$AF, MultiYear_ProForma!$B:$B, $B11, MultiYear_ProForma!$C:$C, "FY2030"))/5 -> -2555765.9 | N11: =Control_Center!B32 -> Status‑Quo + Op Growth Targets | O11: =L11 - INDEX(L:L, MATCH("A_Repurpose_Both_ops", $B:$B, 0)) -> -1476639.4 | P11: =M11 - INDEX(M:M, MATCH("A_Repurpose_Both_ops", $B:$B, 0)) -> -582423.73
B12: =Scenarios!A7 -> G_EchoGHubRamp_PimaTargets | C12: =INDEX(MultiYear_ProForma!$X$2:$X$61, MATCH(Scenarios!A7&"|FY2028", MultiYear_ProForma!$AG$2:$AG$61, 0)) -> 9582.2249 | D12: =INDEX(MultiYear_ProForma!$X$2:$X$61, MATCH(Scenarios!A7&"|FY2030", MultiYear_ProForma!$AG$2:$AG$61, 0)) -> 10067.325 | E12: =AVERAGE(INDEX(MultiYear_ProForma!$X$2:$X$61, MATCH(Scenarios!A7&"|FY2026", MultiYear_ProForma!$AG$2:$AG$61, 0)),INDEX(MultiYear_ProForma!$X$2:$X$61, MATCH(Scenarios!A7&"|FY2027", MultiYear_ProForma!$AG$2:$AG$61, 0)),INDEX(MultiYear_ProForma!$X$2:$X$61, MATCH(Scenarios!A7&"|FY2028", MultiYear_ProForma!$AG$2:$AG$61, 0))) -> 9648.4371 | F12: =AVERAGE(INDEX(MultiYear_ProForma!$X$2:$X$61, MATCH(Scenarios!A7&"|FY2026", MultiYear_ProForma!$AG$2:$AG$61, 0)),INDEX(MultiYear_ProForma!$X$2:$X$61, MATCH(Scenarios!A7&"|FY2027", MultiYear_ProForma!$AG$2:$AG$61, 0)),INDEX(MultiYear_ProForma!$X$2:$X$61, MATCH(Scenarios!A7&"|FY2028", MultiYear_ProForma!$AG$2:$AG$61, 0)),INDEX(MultiYear_ProForma!$X$2:$X$61, MATCH(Scenarios!A7&"|FY2029", MultiYear_ProForma!$AG$2:$AG$61, 0)),INDEX(MultiYear_ProForma!$X$2:$X$61, MATCH(Scenarios!A7&"|FY2030", MultiYear_ProForma!$AG$2:$AG$61, 0))) -> 9766.8834 | G12: =IFERROR(VLOOKUP($B12&"|FY2026", MultiYear_ProForma!$A:$AG, 14, FALSE), "") -> 0 | H12: =IFERROR(VLOOKUP($B12&"|FY2030", MultiYear_ProForma!$A:$AG, 6, FALSE) + VLOOKUP($B12&"|FY2030", MultiYear_ProForma!$A:$AG, 15, FALSE), "") -> 703 | I12: =Control_Center!C55 -> - | J12: =Control_Center!D55 -> Low-Med | K12: =SUMIFS(MultiYear_ProForma!$AF:$AF, MultiYear_ProForma!$B:$B, $B12, MultiYear_ProForma!$C:$C, "FY2028") -> -2553410.8 | L12: =SUMIFS(MultiYear_ProForma!$AF:$AF, MultiYear_ProForma!$B:$B, $B12, MultiYear_ProForma!$C:$C, "FY2030") -> -2720167.3 | M12: =(SUMIFS(MultiYear_ProForma!$AF:$AF, MultiYear_ProForma!$B:$B, $B12, MultiYear_ProForma!$C:$C, "FY2026")+SUMIFS(MultiYear_ProForma!$AF:$AF, MultiYear_ProForma!$B:$B, $B12, MultiYear_ProForma!$C:$C, "FY2027")+SUMIFS(MultiYear_ProForma!$AF:$AF, MultiYear_ProForma!$B:$B, $B12, MultiYear_ProForma!$C:$C, "FY2028")+SUMIFS(MultiYear_ProForma!$AF:$AF, MultiYear_ProForma!$B:$B, $B12, MultiYear_ProForma!$C:$C, "FY2029")+SUMIFS(MultiYear_ProForma!$AF:$AF, MultiYear_ProForma!$B:$B, $B12, MultiYear_ProForma!$C:$C, "FY2030"))/5 -> -2641079.4 | N12: =Control_Center!B36 -> Growth Hub @ Echo + Status-Quo Pima + Op Growth Targets | O12: =L12 - INDEX(L:L, MATCH("A_Repurpose_Both_ops", $B:$B, 0)) -> -1476639.4 | P12: =M12 - INDEX(M:M, MATCH("A_Repurpose_Both_ops", $B:$B, 0)) -> -667737.28
B13: =Scenarios!A6 -> D_CUSTOM2 | C13: =INDEX(MultiYear_ProForma!$X$2:$X$61, MATCH(Scenarios!A6&"|FY2028", MultiYear_ProForma!$AG$2:$AG$61, 0)) -> 10625.085 | D13: =INDEX(MultiYear_ProForma!$X$2:$X$61, MATCH(Scenarios!A6&"|FY2030", MultiYear_ProForma!$AG$2:$AG$61, 0)) -> 11162.98 | E13: =AVERAGE(INDEX(MultiYear_ProForma!$X$2:$X$61, MATCH(Scenarios!A6&"|FY2026", MultiYear_ProForma!$AG$2:$AG$61, 0)),INDEX(MultiYear_ProForma!$X$2:$X$61, MATCH(Scenarios!A6&"|FY2027", MultiYear_ProForma!$AG$2:$AG$61, 0)),INDEX(MultiYear_ProForma!$X$2:$X$61, MATCH(Scenarios!A6&"|FY2028", MultiYear_ProForma!$AG$2:$AG$61, 0))) -> 10368.044 | F13: =AVERAGE(INDEX(MultiYear_ProForma!$X$2:$X$61, MATCH(Scenarios!A6&"|FY2026", MultiYear_ProForma!$AG$2:$AG$61, 0)),INDEX(MultiYear_ProForma!$X$2:$X$61, MATCH(Scenarios!A6&"|FY2027", MultiYear_ProForma!$AG$2:$AG$61, 0)),INDEX(MultiYear_ProForma!$X$2:$X$61, MATCH(Scenarios!A6&"|FY2028", MultiYear_ProForma!$AG$2:$AG$61, 0)),INDEX(MultiYear_ProForma!$X$2:$X$61, MATCH(Scenarios!A6&"|FY2029", MultiYear_ProForma!$AG$2:$AG$61, 0)),INDEX(MultiYear_ProForma!$X$2:$X$61, MATCH(Scenarios!A6&"|FY2030", MultiYear_ProForma!$AG$2:$AG$61, 0))) -> 10631.565 | G13: =IFERROR(VLOOKUP($B13&"|FY2026", MultiYear_ProForma!$A:$AG, 14, FALSE), "") -> 0 | H13: =IFERROR(VLOOKUP($B13&"|FY2030", MultiYear_ProForma!$A:$AG, 6, FALSE) + VLOOKUP($B13&"|FY2030", MultiYear_ProForma!$A:$AG, 15, FALSE), "") -> 553 | I13: =Control_Center!C51 -> + | J13: =Control_Center!D51 -> Med | K13: =SUMIFS(MultiYear_ProForma!$AF:$AF, MultiYear_ProForma!$B:$B, $B13, MultiYear_ProForma!$C:$C, "FY2028") -> -2991486.8 | L13: =SUMIFS(MultiYear_ProForma!$AF:$AF, MultiYear_ProForma!$B:$B, $B13, MultiYear_ProForma!$C:$C, "FY2030") -> -3172421.6 | M13: =(SUMIFS(MultiYear_ProForma!$AF:$AF, MultiYear_ProForma!$B:$B, $B13, MultiYear_ProForma!$C:$C, "FY2026")+SUMIFS(MultiYear_ProForma!$AF:$AF, MultiYear_ProForma!$B:$B, $B13, MultiYear_ProForma!$C:$C, "FY2027")+SUMIFS(MultiYear_ProForma!$AF:$AF, MultiYear_ProForma!$B:$B, $B13, MultiYear_ProForma!$C:$C, "FY2028")+SUMIFS(MultiYear_ProForma!$AF:$AF, MultiYear_ProForma!$B:$B, $B13, MultiYear_ProForma!$C:$C, "FY2029")+SUMIFS(MultiYear_ProForma!$AF:$AF, MultiYear_ProForma!$B:$B, $B13, MultiYear_ProForma!$C:$C, "FY2030"))/5 -> -2993938.8 | N13: =Control_Center!B35 -> CUSTOM_KeepOpen_v2 | O13: =L13 - INDEX(L:L, MATCH("A_Repurpose_Both_ops", $B:$B, 0)) -> -1928893.7 | P13: =M13 - INDEX(M:M, MATCH("A_Repurpose_Both_ops", $B:$B, 0)) -> -1020596.6
B14: =Scenarios!A2 -> D_CUSTOM1 | C14: =INDEX(MultiYear_ProForma!$X$2:$X$61, MATCH(Scenarios!A2&"|FY2028", MultiYear_ProForma!$AG$2:$AG$61, 0)) -> 10625.085 | D14: =INDEX(MultiYear_ProForma!$X$2:$X$61, MATCH(Scenarios!A2&"|FY2030", MultiYear_ProForma!$AG$2:$AG$61, 0)) -> 11162.98 | E14: =AVERAGE(INDEX(MultiYear_ProForma!$X$2:$X$61, MATCH(Scenarios!A2&"|FY2026", MultiYear_ProForma!$AG$2:$AG$61, 0)),INDEX(MultiYear_ProForma!$X$2:$X$61, MATCH(Scenarios!A2&"|FY2027", MultiYear_ProForma!$AG$2:$AG$61, 0)),INDEX(MultiYear_ProForma!$X$2:$X$61, MATCH(Scenarios!A2&"|FY2028", MultiYear_ProForma!$AG$2:$AG$61, 0))) -> 10368.044 | F14: =AVERAGE(INDEX(MultiYear_ProForma!$X$2:$X$61, MATCH(Scenarios!A2&"|FY2026", MultiYear_ProForma!$AG$2:$AG$61, 0)),INDEX(MultiYear_ProForma!$X$2:$X$61, MATCH(Scenarios!A2&"|FY2027", MultiYear_ProForma!$AG$2:$AG$61, 0)),INDEX(MultiYear_ProForma!$X$2:$X$61, MATCH(Scenarios!A2&"|FY2028", MultiYear_ProForma!$AG$2:$AG$61, 0)),INDEX(MultiYear_ProForma!$X$2:$X$61, MATCH(Scenarios!A2&"|FY2029", MultiYear_ProForma!$AG$2:$AG$61, 0)),INDEX(MultiYear_ProForma!$X$2:$X$61, MATCH(Scenarios!A2&"|FY2030", MultiYear_ProForma!$AG$2:$AG$61, 0))) -> 10631.565 | G14: =IFERROR(VLOOKUP($B14&"|FY2026", MultiYear_ProForma!$A:$AG, 14, FALSE), "") -> 0 | H14: =IFERROR(VLOOKUP($B14&"|FY2030", MultiYear_ProForma!$A:$AG, 6, FALSE) + VLOOKUP($B14&"|FY2030", MultiYear_ProForma!$A:$AG, 15, FALSE), "") -> 553 | I14: =Control_Center!C57 -> - | J14: =Control_Center!D57 -> Low-Med | K14: =SUMIFS(MultiYear_ProForma!$AF:$AF, MultiYear_ProForma!$B:$B, $B14, MultiYear_ProForma!$C:$C, "FY2028") -> -2991486.8 | L14: =SUMIFS(MultiYear_ProForma!$AF:$AF, MultiYear_ProForma!$B:$B, $B14, MultiYear_ProForma!$C:$C, "FY2030") -> -3172421.6 | M14: =(SUMIFS(MultiYear_ProForma!$AF:$AF, MultiYear_ProForma!$B:$B, $B14, MultiYear_ProForma!$C:$C, "FY2026")+SUMIFS(MultiYear_ProForma!$AF:$AF, MultiYear_ProForma!$B:$B, $B14, MultiYear_ProForma!$C:$C, "FY2027")+SUMIFS(MultiYear_ProForma!$AF:$AF, MultiYear_ProForma!$B:$B, $B14, MultiYear_ProForma!$C:$C, "FY2028")+SUMIFS(MultiYear_ProForma!$AF:$AF, MultiYear_ProForma!$B:$B, $B14, MultiYear_ProForma!$C:$C, "FY2029")+SUMIFS(MultiYear_ProForma!$AF:$AF, MultiYear_ProForma!$B:$B, $B14, MultiYear_ProForma!$C:$C, "FY2030"))/5 -> -2993938.8 | N14: =Control_Center!B31 -> CUSTOM_KeepOpen_v1 | O14: =L14 - INDEX(L:L, MATCH("A_Repurpose_Both_ops", $B:$B, 0)) -> -1928893.7 | P14: =M14 - INDEX(M:M, MATCH("A_Repurpose_Both_ops", $B:$B, 0)) -> -1020596.6

Sheet Definitions_Sources
B2: Parameter / input | C2: Description / how we used it | D2: Public source & how derived | E2: What to request to confirm / refine
B3: ADM | C3: ADM stands for Average Daily Membership. It is the primary metric used by the state of Arizona to determine funding for a school district. What it is: ADM is essentially the official student count. It is not based on how many students are present on any single day (that would be average daily attendance), but rather on how many students are officially enrolled in the district. | D3: How it's calculated: The state uses enrollment data from specific points in the school year to generate an average. This average, the ADM, becomes the official "student count" for that fiscal year. Why it matters: Nearly all state funding is allocated on a per-student basis using ADM. This number is multiplied by various weights (e.g., for high school students, special education, etc.) to create a "weighted student count," which is the foundational number for calculating the district's total state aid. An audit of SUSD's ADM, for example, is a check to ensure the district reported its enrollment correctly and received the proper amount of funding.
B4: M&O | C4: M&O stands for Maintenance and Operations. This is the largest and most important part of a school district's budget. What it is: The M&O budget is the "bucket" of money that pays for all the day-to-day, non-capital expenses of running the school district. It is the district's operating budget. | D4: What it pays for: Salaries and benefits for all employees (teachers, principals, support staff, administrators) Classroom supplies (textbooks, software, paper, etc.) Utilities (electricity, water, gas) Transportation (bus fuel and maintenance) Student services and athletics
B5: Base state aid per pupil (FY2025) | C5: Revenue per ADM in “Aid per ADM” line; grown by CPI in out‑years (model uses a placeholder near $5.1k) | D5: Arizona FY2025 budget bill (HB 2906) sets the base level per pupil at $5,013 for FY2025. Arizona Senate Issue Brief – K‑12 School Finance (official, widely used reference). Shows the Base Level Amount (FY 2024‑25 = $5,013.33), the factor that (with district weights) drives state aid. ADE lists the same figure in its finance materials. | E5: ADE School Finance memo for FY2025 base level (final), plus any FY2026 update; SUSD’s per‑pupil revenue schedule (by weight) if you want to add K‑8 weights locally.
B6: Echo Canyon base ADM (≈257) | C6: Baseline students “served” in keep‑open scenarios | D6: ADE School Report Cards / Arizona Education Profiles (school pages) + SUSD 40th‑day board reports for Echo Canyon’s latest K‑8 enrollment ADE school page data used. | E6: SUSD October (40th‑day) ADM sheet listing Echo Canyon K‑8 ADM (most recent year) and the same for the prior 3 years.
B7: Pima base ADM (≈296) | C7: Baseline students “served” in keep‑open scenarios | D7: ADE School Report Cards page for Pima Traditional (enrollment tile). The “Enrollment” 🛈 on that page for the specific year has enrollment data. | E7: Same 40th‑day ADM sheet as above, for Pima K‑8.
B8: District M&O (Fund 001) context | C8: Grounds the “M&O per ADM” baseline used in comparable $/student | D8: Scottsdale USD ACFR FY2024 (annual comprehensive financial report) — Fund statements and notes establish M&O (Fund 001) totals and function splits (instruction, plant ops, admin, etc.). We used it to sanity‑check the order of magnitude for per‑pupil operating cost. (Scottsdale Unified School District) | E8: From ACFR or adopted budget: Fund 001 totals and function detail by object/function; district ADM used in budget; site‑level M&O if available.
B9: “Fixed‑like” share of M&O ≈ 30–40% (used 30% as a conservative placeholder) | C9: Splits total M&O into “semi‑fixed” (plant ops, insurance, admin, central) vs “variable” (classroom sections, supplies, a slice of transport) to compute EchoFixed$ and PimaFixed$ | D9: Arizona Auditor General – Arizona School District Spending – FY2024 portal (official statewide analysis). The Overview and category definitions show the functional buckets (instruction, administration, plant operations & maintenance, student support, etc.) districts report and that we treat as the “more fixed‑like” categories. (sdspending.azauditor.gov) | E9: SUSD site‑level: plant ops/maintenance, insurance, utilities, admin FTE & benefits at Echo/Pima. Use that to replace the 30% proxy with real fixed amounts. The file allocates the fixed share across the two schools pro‑rata (by base ADM) as a temporary step. Replace with the actual plant ops/insurance/utilities/admin for each site from Fund 001 to remove that simplification.
B10: M&O Inflation
B11: AID inflation
B12: Overlay | C12: Using this term in the spreadsheet to mean growth of new students | D12: Not an official district term; just using in this spreadsheet
B13: Variable unit cost (VarUnit$) | C13: $ per student applied to “served ADM,” plus marginal‑cost factor on overlay seats | D13: Assumption derived from Fund 001 minus fixed share, divided by total ADM; then Marginal factor (see below) reduces cost for overlay seats. | E13: SUSD staffing ratios & actual sectioning at K–8; confirm what portion of M&O truly scales with added sections (teachers, aides, supplies, a slice of transport).
B14: Marginal‑cost factor for overlay seats (0.50) | C14: Applies only to overlay growth students in keep‑open scenarios; models that not every dollar is average cost | D14: Assumption w/ rationale: Roughly half of per‑pupil cost is staffing/supplies/transport that scale with sections; the remainder is semi‑fixed plant/admin. This aligns with Auditor General function splits and is intentionally conservative. We’ll replace with SUSD’s staffing & plant data if provided. (Sun Devil Central) | E14: SUSD’s teacher‑section & aide staffing rules, average class sizes, and any marginal staffing adders at K–8 (arts, specialists).
B15: Receiving overhead “h” (FY26 $1,000 → FY30 $300) | C15: Per retained student transition/route/admin cost added when a site is repurposed; tapers as routes stabilize | D15: Assumption with AZ context: AZ districts’ transport spend per rider is often $2k–$3k (statewide average $2,862 cited in a district budget narrative), so $1,000 tapering to $300 is a conservative placeholder for incremental cost, not full bus cost. | E15: SUSD transportation cost per route-hour, average riders per route, and the specific route changes proposed in the repurpose option. | F15: Transportation / receiving overhead order‑of‑magnitude | G15: Our h parameter adds incremental per‑retained‑student cost (routing/transition/admin) only when a repurpose occurs, tapering as routes stabilize | H15: AAG district audits show cost per rider varies (several audited districts fall near $900–$1,100 per rider; others higher depending on geography), demonstrating the right order of magnitude for incremental routing burden. Examples: Safford USD 2022 $893 per rider; Snowflake USD 2023 $1,008 per rider. | I15: Keeping h = $1,000 → $300 (FY26→FY30) is defensible as incremental overhead, not full bus cost. Leave Parameters!h_FY values editable; note they should be zero in keep‑open scenarios (no forced transfers).
B16: Retention rate “r” (central 0.75; sensitivities 0.65–0.85) | C16: Share of displaced Echo+Pima students who remain in SUSD (the rest leave to charters/other districts) | D16: Assumption, benchmarked to closure research: large‑district closure work (e.g., Chicago) shows most students remain in‑district the next year (CPS analyses place that figure well above half); retention varies with hand‑off quality and distance. We model 65–85% to bracket. (UChicago Consortium on School Research) Large‑district evidence: UChicago Consortium’s analyses of the 2013 CPS closures found most displaced students remained in district the next year; outcomes varied with the quality and distance of receiving schools. That supports using a central r ~ 0.75 with a band. UChicago Consortium on School Research What we could not find in AZ: districts rarely publish explicit post‑closure retention; you can proxy from post‑closure enrollment by receiving schools if SUSD shares it. Echo nuance: Because Echo is open‑enrollment and draws many out‑of‑district students, those families may be less likely to follow to a different SUSD school after a closure (they already cross a boundary by choice). That argues for running a lower Echo‑weighted r scenario (e.g., 0.55–0.65) in addition to the district‑wide 0.65–0.85 band. Make that explicit in the dashboard and in the sensitivity mini‑cards. | E16: SUSD post‑closure enrollment tracking (where displaced students re‑enroll), by receiving school; use that to set “r” from observed data.
B17: Carry fractions f_ops / f_lease (e.g., 0.40 → 0 by FY30) | C17: Share of each site’s fixed costs that persist after repurpose under ops mothball vs lease/sale | D17: Assumption pending facilities plan. The glide‑path (e.g., 40%→30%→20%→10%→0%) reflects how fast plant/insurance/utilities can be retired or passed to a tenant. | E17: SUSD facilities memo: timeline to partial/full mothball, target lease/sale timing, and which cost lines truly zero out under each scenario.
B18: TI / one‑time repurpose costs (e.g., $2.4M) | C18: “TI_adds$” in the pro‑forma for the first 1–2 years. Why “Repurpose TI per closed site (FY26) = $1.2M”? What is “one‑time carry/TI”? “TI” = tenant improvements / transition investments needed to convert a K‑8 to a different use (early learning, admin consolidation) and carry costs in year one (e.g., abatement, doors/security, low‑voltage re‑work, furniture, swing space). A light‑touch repurpose can easily run $10–$20/sq‑ft; Echo’s plant is ~77k sq ft, so $1.2M is a reasonable placeholder (we are not assuming a gut remodel). We’ll replace this with SUSD’s scope/estimate if they have one. | D18: Assumption (placeholder). | E18: SUSD engineering estimate for tenant improvements or district reconfiguration (scope, cost, which fund, and amortization).
B19: Extra cost savings for co-location scenario | C19: Why “Extra savings (co‑location) = 0.015 (1.5%)”? This reflects incremental savings from consolidating some services on one campus (custodial/grounds/partial routing). Again kept small and conservative; we’ll swap in real custodial (sq‑ft), grounds and route deltas when we get them.
B20: Ops savings (for keep-open scenarios) | C20: Ops savings (keep‑open) = 0.007 (0.7%)”? This represents “light discipline” (utilities/purchasing tweaks, route smoothing) that does not depend on closing a site. I set it very low on purpose so it doesn’t drive results. We’ll calibrate with SUSD data (e.g., last year’s utility audits) if provided.
B22: Scenario overlays (+0 / +100 / +150 / +200) | C22: Size of growth push in keep‑open options (D, F, G) | D22: Assumption based on capacity headroom + practical recruitment targets. | E22: SUSD SFB capacity for Echo/Pima and neighboring receiving schools; actual classroom/wing availability by grade band.
B23: K–8 capacity / square footage | C23: Context for “utilization” and whether overlay targets are feasible | D23: Not yet populated; to be anchored to SFB (AZ School Facilities Board) capacity files and SUSD construction docs. | E23: SUSD/SFB: design capacity and current utilization for Echo & Pima (post‑rebuild specs for Pima).
B24: Pre‑K contribution | C24: Excluded from ADM and revenue in the model (unless tuition/lease modeled) | D24: Supported by statute & ADE finance practice—general Pre‑K does not generate state ADM (exception: SPED preschool). (Arizona Department of Education) | E24: If SUSD intends district‑operated tuition Pre‑K on site, request pro forma for net contribution (tuition – staffing – TI).
B25: ADM definition (what “counts”) | C25: Explains why Pre‑K is excluded and why K can count at 0.5; supports “served” math | D25: A.R.S. §15‑901 and legislative fact sheet: Kindergarten generates 0.5 ADM unless full‑time; ADM is a statutory count, and preschool is generally not included in ADM (except some SPED programs). (LegiScan) | E25: SUSD’s 40th‑day and 100th‑day ADM certification for Echo and Pima (K–8 breakouts).
B28: Model input / claim | C28: How we’re using it in the model | D28: Public source to cite (what to grab) | E28: How to apply in the file
B32: Parameter / Input | C32: Description | D32: Where it lives | E32: Notes on logic / calculation | F32: Source to use for final vetting
B33: Base MO per ADM (FY25) | C33: Working average M&O per student at FY25 | D33: BaselineCalc | E33: Drives Base total MO = Total ADM × Base MO/ADM | F33: Replace with SUSD ACFR/Adopted Budget (FY24–FY25) for precision
B34: Fixed share of MO | C34: Semi‑fixed share (plant ops, admin, insurance, custodial) | D34: BaselineCalc | E34: Fixed MO = Base total MO × Fixed share | F34: Validate vs ACFR function split (% Plant/Admin/Insurance) | G34: Notes on Pima & Echo fixed $ placeholders: The file allocates the fixed share across the two schools pro‑rata (by base ADM) as a temporary step. Replace with the actual plant ops/insurance/utilities/admin for each site from Fund 001 to remove that simplification.
B35: Var per student (FY25) | C35: Derived variable cost per student | D35: BaselineCalc | E35: (Base total – Fixed) ÷ total ADM | F35: Derived
B36: MO inflation | C36: Annual inflation on M&O lines | D36: BaselineCalc | E36: Inflates VarUnit$ across YearMap | F36: Use district inflation guidance
B37: Echo/Pima base ADM | C37: Starting enrollment | D37: BaselineCalc | E37: Builds Total base ADM = Echo + Pima | F37: District official
B38: YearMap VarUnit$ (FY26–FY30) | C38: Inflated variable per‑student cost | D38: YearMap | E38: Starts from BaselineCalc Var$ then inflation | F38: Derived
B39: Aid$ per ADM (FY26–FY30) | C39: State equalization aid per student | D39: YearMap | E39: Used to net out revenue: Net_MO_after_aid$ / Served_ADM | F39: Replace with ADE equalization worksheets for those years
B40: h (FY26–FY30) | C40: Receiving overhead per retained student | D40: YearMap | E40: Added for transition: routes, scheduling, admin | F40: Calibrate with transpo/admin data
B41: f_ops (FY26–FY30) | C41: Fixed‑carry fraction under mothball path | D41: YearMap | E41: Carry$ = f_ops × site fixed costs | F41: Needs calibration vs plant ops/insurance
B42: f_lease (FY26–FY30) | C42: Fixed‑carry fraction under lease/sale | D42: YearMap | E42: Carry$ = f_lease × site fixed costs (→0 by FY30) | F42: Requires credible lease/sale timeline
B43: MarginalFactor_for_Overlay | C43: Share of VarUnit$ applied to overlay seats | D43: Other_Parameters (v6 = 0.30) | E43: Keeps growth seats from carrying full average M&O | F43: Documented below (why 0.30)
B44: Scenario controls | C44: Overlay amounts by year; closures; co‑location flag; hub ramp | D44: Scenarios | E44: Dashboard pulls one comparator vs baseline | F44: Scenario definitions are transparent on the Scenarios tab

Sheet Q&A

Sheet MultiYear_ProForma
A1: =AG1 -> Key | B1: ScenarioKey | C1: Year | D1: Echo_ADM | E1: Pima_ADM | F1: Total_ADM | G1: VarUnit$ | H1: EchoFixed$ | I1: PimaFixed$ | J1: OpsFactor | K1: ExtraSave | L1: EchoPotential_ADM | M1: PimaPotential_ADM | N1: Displaced_ADM | O1: Retained_ADM | P1: h | Q1: CarryFrac | R1: EchoFixedEff$ | S1: PimaFixedEff$ | T1: TI_adds$ | U1: SiteCost$ | V1: RetainedSvc$ | W1: Comparable_MO$ | X1: Comparable_per_Student$ | Y1: Aid_per_ADM | Z1: Net_MO_after_aid$ | AA1: Net_per_served$ | AB1: Overlay_ADM | AC1: Served_ADM | AD1: Revenue$ | AE1: Adj_MO$ | AF1: Net$ | AG1: Key
A2: =AG2 -> D_CUSTOM1|FY2026 | B2: =Scenarios!A2 -> D_CUSTOM1 | C2: FY2026 | D2: =IF(Scenarios!D2=1,0, L2) -> 257 | E2: =IF(Scenarios!E2=1,0, M2) -> 296 | F2: =D2+E2 -> 553 | G2: =YearMap!B2 -> 5499.576 | H2: =YearMap!C2 -> 1203999.8 | I2: =YearMap!D2 -> 1386707.9 | J2: =1-BaselineCalc!$B$5 -> 0.993 | K2: =Scenarios!G2 -> 0 | L2: =BaselineCalc!$B$7 + ROUND(Scenarios!I2*Scenarios!F2,0) -> 257 | M2: =BaselineCalc!$B$8 + Scenarios!I2 - ROUND(Scenarios!I2*Scenarios!F2,0) -> 296 | N2: =(L2-D2) + (M2-E2) -> 0 | O2: =BaselineCalc!$B$23 * N2 -> 0 | P2: =YearMap!E2 -> 1000 | Q2: =IF(Scenarios!N2="lease", YearMap!F2, YearMap!G2) -> 0.5 | R2: =IF(Scenarios!D2=1, Q2*H2, H2) -> 1203999.8 | S2: =IF(Scenarios!E2=1, Q2*I2, I2) -> 1386707.9 | T2: =IF(C2="FY2026", (Scenarios!D2+Scenarios!E2)*BaselineCalc!$B$22, 0) -> 0 | U2: =(R2+S2+G2*F2)*J2*(1-K2) -> 5592549.4 | V2: =O2*(G2+P2) -> 0 | W2: =U2+V2+T2 -> 5592549.4 | X2: =IF(F2+O2>0, W2/(F2+O2),"") -> 10113.109 | Y2: =INDEX(YearMap!$I$2:$I$6, MATCH(C2, YearMap!$A$2:$A$6, 0)) -> 5013 | Z2: =$W2-$Y2*$AC2 -> 2820360.4 | AA2: =IF($AC2>0, $Z2/$AC2, 0) -> 5100.1092 | AB2: =MAX(0, (MAX(0, $D2-BaselineCalc!$B$7) + MAX(0, $E2-BaselineCalc!$B$8))) -> 0 | AC2: =IF(LEFT($B2,2)="A_", $O2, IF(LEFT($B2,2)="B_", $M2+$O2, IF(LEFT($B2,2)="C_", $L2+$O2, $F2))) -> 553 | AD2: =$Y2*$AC2 -> 2772189 | AE2: =W2 - (1-Other_Parameters!$B$2)*$G2*$AB2*$J2*(1-$K2) -> 5592549.4 | AF2: =AD2-AE2 -> -2820360.4 | AG2: =B2&"|"&C2 -> D_CUSTOM1|FY2026
A3: =AG3 -> D_CUSTOM1|FY2027 | B3: =Scenarios!A2 -> D_CUSTOM1 | C3: FY2027 | D3: =IF(Scenarios!D2=1,0, L3) -> 257 | E3: =IF(Scenarios!E2=1,0, M3) -> 296 | F3: =D3+E3 -> 553 | G3: =YearMap!B3 -> 5637.0654 | H3: =YearMap!C3 -> 1234099.8 | I3: =YearMap!D3 -> 1421375.6 | J3: =1-BaselineCalc!$B$5 -> 0.993 | K3: =Scenarios!G2 -> 0 | L3: =BaselineCalc!$B$7 + ROUND(Scenarios!J2*Scenarios!F2,0) -> 257 | M3: =BaselineCalc!$B$8 + Scenarios!J2 - ROUND(Scenarios!J2*Scenarios!F2,0) -> 296 | N3: =(L3-D3) + (M3-E3) -> 0 | O3: =BaselineCalc!$B$23 * N3 -> 0 | P3: =YearMap!E3 -> 800 | Q3: =IF(Scenarios!N2="lease", YearMap!F3, YearMap!G3) -> 0.4 | R3: =IF(Scenarios!D2=1, Q3*H3, H3) -> 1234099.8 | S3: =IF(Scenarios!E2=1, Q3*I3, I3) -> 1421375.6 | T3: =IF(C3="FY2026", (Scenarios!D2+Scenarios!E2)*BaselineCalc!$B$22, 0) -> 0 | U3: =(R3+S3+G3*F3)*J3*(1-K3) -> 5732363.1 | V3: =O3*(G3+P3) -> 0 | W3: =U3+V3+T3 -> 5732363.1 | X3: =IF(F3+O3>0, W3/(F3+O3),"") -> 10365.937 | Y3: =INDEX(YearMap!$I$2:$I$6, MATCH(C3, YearMap!$A$2:$A$6, 0)) -> 5113.26 | Z3: =$W3-$Y3*$AC3 -> 2904730.3 | AA3: =IF($AC3>0, $Z3/$AC3, 0) -> 5252.6769 | AB3: =MAX(0, (MAX(0, $D3-BaselineCalc!$B$7) + MAX(0, $E3-BaselineCalc!$B$8))) -> 0 | AC3: =IF(LEFT($B3,2)="A_", $O3, IF(LEFT($B3,2)="B_", $M3+$O3, IF(LEFT($B3,2)="C_", $L3+$O3, $F3))) -> 553 | AD3: =$Y3*$AC3 -> 2827632.8 | AE3: =W3 - (1-Other_Parameters!$B$2)*$G3*$AB3*$J3*(1-$K3) -> 5732363.1 | AF3: =AD3-AE3 -> -2904730.3 | AG3: =B3&"|"&C3 -> D_CUSTOM1|FY2027
A4: =AG4 -> D_CUSTOM1|FY2028 | B4: =Scenarios!A2 -> D_CUSTOM1 | C4: FY2028 | D4: =IF(Scenarios!D2=1,0, L4) -> 257 | E4: =IF(Scenarios!E2=1,0, M4) -> 296 | F4: =D4+E4 -> 553 | G4: =YearMap!B4 -> 5777.992 | H4: =YearMap!C4 -> 1264952.3 | I4: =YearMap!D4 -> 1456910 | J4: =1-BaselineCalc!$B$5 -> 0.993 | K4: =Scenarios!G2 -> 0 | L4: =BaselineCalc!$B$7 + ROUND(Scenarios!K2*Scenarios!F2,0) -> 257 | M4: =BaselineCalc!$B$8 + Scenarios!K2 - ROUND(Scenarios!K2*Scenarios!F2,0) -> 296 | N4: =(L4-D4) + (M4-E4) -> 0 | O4: =BaselineCalc!$B$23 * N4 -> 0 | P4: =YearMap!E4 -> 600 | Q4: =IF(Scenarios!N2="lease", YearMap!F4, YearMap!G4) -> 0.35 | R4: =IF(Scenarios!D2=1, Q4*H4, H4) -> 1264952.3 | S4: =IF(Scenarios!E2=1, Q4*I4, I4) -> 1456910 | T4: =IF(C4="FY2026", (Scenarios!D2+Scenarios!E2)*BaselineCalc!$B$22, 0) -> 0 | U4: =(R4+S4+G4*F4)*J4*(1-K4) -> 5875672.2 | V4: =O4*(G4+P4) -> 0 | W4: =U4+V4+T4 -> 5875672.2 | X4: =IF(F4+O4>0, W4/(F4+O4),"") -> 10625.085 | Y4: =INDEX(YearMap!$I$2:$I$6, MATCH(C4, YearMap!$A$2:$A$6, 0)) -> 5215.5252 | Z4: =$W4-$Y4*$AC4 -> 2991486.8 | AA4: =IF($AC4>0, $Z4/$AC4, 0) -> 5409.5602 | AB4: =MAX(0, (MAX(0, $D4-BaselineCalc!$B$7) + MAX(0, $E4-BaselineCalc!$B$8))) -> 0 | AC4: =IF(LEFT($B4,2)="A_", $O4, IF(LEFT($B4,2)="B_", $M4+$O4, IF(LEFT($B4,2)="C_", $L4+$O4, $F4))) -> 553 | AD4: =$Y4*$AC4 -> 2884185.4 | AE4: =W4 - (1-Other_Parameters!$B$2)*$G4*$AB4*$J4*(1-$K4) -> 5875672.2 | AF4: =AD4-AE4 -> -2991486.8 | AG4: =B4&"|"&C4 -> D_CUSTOM1|FY2028
A5: =AG5 -> D_CUSTOM1|FY2029 | B5: =Scenarios!A2 -> D_CUSTOM1 | C5: FY2029 | D5: =IF(Scenarios!D2=1,0, L5) -> 257 | E5: =IF(Scenarios!E2=1,0, M5) -> 296 | F5: =D5+E5 -> 553 | G5: =YearMap!B5 -> 5922.4418 | H5: =YearMap!C5 -> 1296576.1 | I5: =YearMap!D5 -> 1493332.7 | J5: =1-BaselineCalc!$B$5 -> 0.993 | K5: =Scenarios!G2 -> 0 | L5: =BaselineCalc!$B$7 + ROUND(Scenarios!L2*Scenarios!F2,0) -> 257 | M5: =BaselineCalc!$B$8 + Scenarios!L2 - ROUND(Scenarios!L2*Scenarios!F2,0) -> 296 | N5: =(L5-D5) + (M5-E5) -> 0 | O5: =BaselineCalc!$B$23 * N5 -> 0 | P5: =YearMap!E5 -> 500 | Q5: =IF(Scenarios!N2="lease", YearMap!F5, YearMap!G5) -> 0.3 | R5: =IF(Scenarios!D2=1, Q5*H5, H5) -> 1296576.1 | S5: =IF(Scenarios!E2=1, Q5*I5, I5) -> 1493332.7 | T5: =IF(C5="FY2026", (Scenarios!D2+Scenarios!E2)*BaselineCalc!$B$22, 0) -> 0 | U5: =(R5+S5+G5*F5)*J5*(1-K5) -> 6022564 | V5: =O5*(G5+P5) -> 0 | W5: =U5+V5+T5 -> 6022564 | X5: =IF(F5+O5>0, W5/(F5+O5),"") -> 10890.712 | Y5: =INDEX(YearMap!$I$2:$I$6, MATCH(C5, YearMap!$A$2:$A$6, 0)) -> 5319.8357 | Z5: =$W5-$Y5*$AC5 -> 3080694.9 | AA5: =IF($AC5>0, $Z5/$AC5, 0) -> 5570.8768 | AB5: =MAX(0, (MAX(0, $D5-BaselineCalc!$B$7) + MAX(0, $E5-BaselineCalc!$B$8))) -> 0 | AC5: =IF(LEFT($B5,2)="A_", $O5, IF(LEFT($B5,2)="B_", $M5+$O5, IF(LEFT($B5,2)="C_", $L5+$O5, $F5))) -> 553 | AD5: =$Y5*$AC5 -> 2941869.1 | AE5: =W5 - (1-Other_Parameters!$B$2)*$G5*$AB5*$J5*(1-$K5) -> 6022564 | AF5: =AD5-AE5 -> -3080694.9 | AG5: =B5&"|"&C5 -> D_CUSTOM1|FY2029
A6: =AG6 -> D_CUSTOM1|FY2030 | B6: =Scenarios!A2 -> D_CUSTOM1 | C6: FY2030 | D6: =IF(Scenarios!D2=1,0, L6) -> 257 | E6: =IF(Scenarios!E2=1,0, M6) -> 296 | F6: =D6+E6 -> 553 | G6: =YearMap!B6 -> 6070.5029 | H6: =YearMap!C6 -> 1328990.5 | I6: =YearMap!D6 -> 1530666.1 | J6: =1-BaselineCalc!$B$5 -> 0.993 | K6: =Scenarios!G2 -> 0 | L6: =BaselineCalc!$B$7 + ROUND(Scenarios!M2*Scenarios!F2,0) -> 257 | M6: =BaselineCalc!$B$8 + Scenarios!M2 - ROUND(Scenarios!M2*Scenarios!F2,0) -> 296 | N6: =(L6-D6) + (M6-E6) -> 0 | O6: =BaselineCalc!$B$23 * N6 -> 0 | P6: =YearMap!E6 -> 300 | Q6: =IF(Scenarios!N2="lease", YearMap!F6, YearMap!G6) -> 0.3 | R6: =IF(Scenarios!D2=1, Q6*H6, H6) -> 1328990.5 | S6: =IF(Scenarios!E2=1, Q6*I6, I6) -> 1530666.1 | T6: =IF(C6="FY2026", (Scenarios!D2+Scenarios!E2)*BaselineCalc!$B$22, 0) -> 0 | U6: =(R6+S6+G6*F6)*J6*(1-K6) -> 6173128.1 | V6: =O6*(G6+P6) -> 0 | W6: =U6+V6+T6 -> 6173128.1 | X6: =IF(F6+O6>0, W6/(F6+O6),"") -> 11162.98 | Y6: =INDEX(YearMap!$I$2:$I$6, MATCH(C6, YearMap!$A$2:$A$6, 0)) -> 5426.2324 | Z6: =$W6-$Y6*$AC6 -> 3172421.6 | AA6: =IF($AC6>0, $Z6/$AC6, 0) -> 5736.7479 | AB6: =MAX(0, (MAX(0, $D6-BaselineCalc!$B$7) + MAX(0, $E6-BaselineCalc!$B$8))) -> 0 | AC6: =IF(LEFT($B6,2)="A_", $O6, IF(LEFT($B6,2)="B_", $M6+$O6, IF(LEFT($B6,2)="C_", $L6+$O6, $F6))) -> 553 | AD6: =$Y6*$AC6 -> 3000706.5 | AE6: =W6 - (1-Other_Parameters!$B$2)*$G6*$AB6*$J6*(1-$K6) -> 6173128.1 | AF6: =AD6-AE6 -> -3172421.6 | AG6: =B6&"|"&C6 -> D_CUSTOM1|FY2030
A7: =AG7 -> E_StatusQuo_Targets|FY2026 | B7: =Scenarios!A3 -> E_StatusQuo_Targets | C7: FY2026 | D7: =IF(Scenarios!D3=1,0, L7) -> 332 | E7: =IF(Scenarios!E3=1,0, M7) -> 371 | F7: =D7+E7 -> 703 | G7: =YearMap!B2 -> 5499.576 | H7: =YearMap!C2 -> 1203999.8 | I7: =YearMap!D2 -> 1386707.9 | J7: =1-BaselineCalc!$B$5 -> 0.993 | K7: =Scenarios!G3 -> 0 | L7: =BaselineCalc!$B$7 + ROUND(Scenarios!I3*Scenarios!F3,0) -> 332 | M7: =BaselineCalc!$B$8 + Scenarios!I3 - ROUND(Scenarios!J3*Scenarios!F3,0) -> 371 | N7: =(L7-D7) + (M7-E7) -> 0 | O7: =BaselineCalc!$B$23 * N7 -> 0 | P7: =YearMap!E2 -> 1000 | Q7: =IF(Scenarios!N3="lease", YearMap!F2, YearMap!G2) -> 0.5 | R7: =IF(Scenarios!D3=1, Q7*H7, H7) -> 1203999.8 | S7: =IF(Scenarios!E3=1, Q7*I7, I7) -> 1386707.9 | T7: =IF(C7="FY2026", (Scenarios!D3+Scenarios!E3)*BaselineCalc!$B$22, 0) -> 0 | U7: =(R7+S7+G7*F7)*J7*(1-K7) -> 6411711.2 | V7: =O7*(G7+P7) -> 0 | W7: =U7+V7+T7 -> 6411711.2 | X7: =IF(F7+O7>0, W7/(F7+O7),"") -> 9120.4996 | Y7: =INDEX(YearMap!$I$2:$I$6, MATCH(C7, YearMap!$A$2:$A$6, 0)) -> 5013 | Z7: =$W7-$Y7*$AC7 -> 2887572.2 | AA7: =IF($AC7>0, $Z7/$AC7, 0) -> 4107.4996 | AB7: =MAX(0, (MAX(0, $D7-BaselineCalc!$B$7) + MAX(0, $E7-BaselineCalc!$B$8))) -> 150 | AC7: =IF(LEFT($B7,2)="A_", $O7, IF(LEFT($B7,2)="B_", $M7+$O7, IF(LEFT($B7,2)="C_", $L7+$O7, $F7))) -> 703 | AD7: =$Y7*$AC7 -> 3524139 | AE7: =W7 - (1-Other_Parameters!$B$2)*$G7*$AB7*$J7*(1-$K7) -> 5920214.1 | AF7: =AD7-AE7 -> -2396075.1 | AG7: =B7&"|"&C7 -> E_StatusQuo_Targets|FY2026
A8: =AG8 -> E_StatusQuo_Targets|FY2027 | B8: =Scenarios!A3 -> E_StatusQuo_Targets | C8: FY2027 | D8: =IF(Scenarios!D3=1,0, L8) -> 332 | E8: =IF(Scenarios!E3=1,0, M8) -> 371 | F8: =D8+E8 -> 703 | G8: =YearMap!B3 -> 5637.0654 | H8: =YearMap!C3 -> 1234099.8 | I8: =YearMap!D3 -> 1421375.6 | J8: =1-BaselineCalc!$B$5 -> 0.993 | K8: =Scenarios!G3 -> 0 | L8: =BaselineCalc!$B$7 + ROUND(Scenarios!J3*Scenarios!F3,0) -> 332 | M8: =BaselineCalc!$B$8 + Scenarios!J3 - ROUND(Scenarios!J3*Scenarios!F3,0) -> 371 | N8: =(L8-D8) + (M8-E8) -> 0 | O8: =BaselineCalc!$B$23 * N8 -> 0 | P8: =YearMap!E3 -> 800 | Q8: =IF(Scenarios!N3="lease", YearMap!F3, YearMap!G3) -> 0.4 | R8: =IF(Scenarios!D3=1, Q8*H8, H8) -> 1234099.8 | S8: =IF(Scenarios!E3=1, Q8*I8, I8) -> 1421375.6 | T8: =IF(C8="FY2026", (Scenarios!D3+Scenarios!E3)*BaselineCalc!$B$22, 0) -> 0 | U8: =(R8+S8+G8*F8)*J8*(1-K8) -> 6572004 | V8: =O8*(G8+P8) -> 0 | W8: =U8+V8+T8 -> 6572004 | X8: =IF(F8+O8>0, W8/(F8+O8),"") -> 9348.5121 | Y8: =INDEX(YearMap!$I$2:$I$6, MATCH(C8, YearMap!$A$2:$A$6, 0)) -> 5113.26 | Z8: =$W8-$Y8*$AC8 -> 2977382.2 | AA8: =IF($AC8>0, $Z8/$AC8, 0) -> 4235.2521 | AB8: =MAX(0, (MAX(0, $D8-BaselineCalc!$B$7) + MAX(0, $E8-BaselineCalc!$B$8))) -> 150 | AC8: =IF(LEFT($B8,2)="A_", $O8, IF(LEFT($B8,2)="B_", $M8+$O8, IF(LEFT($B8,2)="C_", $L8+$O8, $F8))) -> 703 | AD8: =$Y8*$AC8 -> 3594621.8 | AE8: =W8 - (1-Other_Parameters!$B$2)*$G8*$AB8*$J8*(1-$K8) -> 6068219.5 | AF8: =AD8-AE8 -> -2473597.7 | AG8: =B8&"|"&C8 -> E_StatusQuo_Targets|FY2027
A9: =AG9 -> E_StatusQuo_Targets|FY2028 | B9: =Scenarios!A3 -> E_StatusQuo_Targets | C9: FY2028 | D9: =IF(Scenarios!D3=1,0, L9) -> 332 | E9: =IF(Scenarios!E3=1,0, M9) -> 371 | F9: =D9+E9 -> 703 | G9: =YearMap!B4 -> 5777.992 | H9: =YearMap!C4 -> 1264952.3 | I9: =YearMap!D4 -> 1456910 | J9: =1-BaselineCalc!$B$5 -> 0.993 | K9: =Scenarios!G3 -> 0 | L9: =BaselineCalc!$B$7 + ROUND(Scenarios!K3*Scenarios!F3,0) -> 332 | M9: =BaselineCalc!$B$8 + Scenarios!K3 - ROUND(Scenarios!K3*Scenarios!F3,0) -> 371 | N9: =(L9-D9) + (M9-E9) -> 0 | O9: =BaselineCalc!$B$23 * N9 -> 0 | P9: =YearMap!E4 -> 600 | Q9: =IF(Scenarios!N3="lease", YearMap!F4, YearMap!G4) -> 0.35 | R9: =IF(Scenarios!D3=1, Q9*H9, H9) -> 1264952.3 | S9: =IF(Scenarios!E3=1, Q9*I9, I9) -> 1456910 | T9: =IF(C9="FY2026", (Scenarios!D3+Scenarios!E3)*BaselineCalc!$B$22, 0) -> 0 | U9: =(R9+S9+G9*F9)*J9*(1-K9) -> 6736304.1 | V9: =O9*(G9+P9) -> 0 | W9: =U9+V9+T9 -> 6736304.1 | X9: =IF(F9+O9>0, W9/(F9+O9),"") -> 9582.2249 | Y9: =INDEX(YearMap!$I$2:$I$6, MATCH(C9, YearMap!$A$2:$A$6, 0)) -> 5215.5252 | Z9: =$W9-$Y9*$AC9 -> 3069789.9 | AA9: =IF($AC9>0, $Z9/$AC9, 0) -> 4366.6997 | AB9: =MAX(0, (MAX(0, $D9-BaselineCalc!$B$7) + MAX(0, $E9-BaselineCalc!$B$8))) -> 150 | AC9: =IF(LEFT($B9,2)="A_", $O9, IF(LEFT($B9,2)="B_", $M9+$O9, IF(LEFT($B9,2)="C_", $L9+$O9, $F9))) -> 703 | AD9: =$Y9*$AC9 -> 3666514.2 | AE9: =W9 - (1-Other_Parameters!$B$2)*$G9*$AB9*$J9*(1-$K9) -> 6219925 | AF9: =AD9-AE9 -> -2553410.8 | AG9: =B9&"|"&C9 -> E_StatusQuo_Targets|FY2028
A10: =AG10 -> E_StatusQuo_Targets|FY2029 | B10: =Scenarios!A3 -> E_StatusQuo_Targets | C10: FY2029 | D10: =IF(Scenarios!D3=1,0, L10) -> 332 | E10: =IF(Scenarios!E3=1,0, M10) -> 371 | F10: =D10+E10 -> 703 | G10: =YearMap!B5 -> 5922.4418 | H10: =YearMap!C5 -> 1296576.1 | I10: =YearMap!D5 -> 1493332.7 | J10: =1-BaselineCalc!$B$5 -> 0.993 | K10: =Scenarios!G3 -> 0 | L10: =BaselineCalc!$B$7 + ROUND(Scenarios!L3*Scenarios!F3,0) -> 332 | M10: =BaselineCalc!$B$8 + Scenarios!L3 - ROUND(Scenarios!L3*Scenarios!F3,0) -> 371 | N10: =(L10-D10) + (M10-E10) -> 0 | O10: =BaselineCalc!$B$23 * N10 -> 0 | P10: =YearMap!E5 -> 500 | Q10: =IF(Scenarios!N3="lease", YearMap!F5, YearMap!G5) -> 0.3 | R10: =IF(Scenarios!D3=1, Q10*H10, H10) -> 1296576.1 | S10: =IF(Scenarios!E3=1, Q10*I10, I10) -> 1493332.7 | T10: =IF(C10="FY2026", (Scenarios!D3+Scenarios!E3)*BaselineCalc!$B$22, 0) -> 0 | U10: =(R10+S10+G10*F10)*J10*(1-K10) -> 6904711.7 | V10: =O10*(G10+P10) -> 0 | W10: =U10+V10+T10 -> 6904711.7 | X10: =IF(F10+O10>0, W10/(F10+O10),"") -> 9821.7805 | Y10: =INDEX(YearMap!$I$2:$I$6, MATCH(C10, YearMap!$A$2:$A$6, 0)) -> 5319.8357 | Z10: =$W10-$Y10*$AC10 -> 3164867.2 | AA10: =IF($AC10>0, $Z10/$AC10, 0) -> 4501.9448 | AB10: =MAX(0, (MAX(0, $D10-BaselineCalc!$B$7) + MAX(0, $E10-BaselineCalc!$B$8))) -> 150 | AC10: =IF(LEFT($B10,2)="A_", $O10, IF(LEFT($B10,2)="B_", $M10+$O10, IF(LEFT($B10,2)="C_", $L10+$O10, $F10))) -> 703 | AD10: =$Y10*$AC10 -> 3739844.5 | AE10: =W10 - (1-Other_Parameters!$B$2)*$G10*$AB10*$J10*(1-$K10) -> 6375423.1 | AF10: =AD10-AE10 -> -2635578.6 | AG10: =B10&"|"&C10 -> E_StatusQuo_Targets|FY2029
A11: =AG11 -> E_StatusQuo_Targets|FY2030 | B11: =Scenarios!A3 -> E_StatusQuo_Targets | C11: FY2030 | D11: =IF(Scenarios!D3=1,0, L11) -> 332 | E11: =IF(Scenarios!E3=1,0, M11) -> 371 | F11: =D11+E11 -> 703 | G11: =YearMap!B6 -> 6070.5029 | H11: =YearMap!C6 -> 1328990.5 | I11: =YearMap!D6 -> 1530666.1 | J11: =1-BaselineCalc!$B$5 -> 0.993 | K11: =Scenarios!G3 -> 0 | L11: =BaselineCalc!$B$7 + ROUND(Scenarios!M3*Scenarios!F3,0) -> 332 | M11: =BaselineCalc!$B$8 + Scenarios!M3 - ROUND(Scenarios!M3*Scenarios!F3,0) -> 371 | N11: =(L11-D11) + (M11-E11) -> 0 | O11: =BaselineCalc!$B$23 * N11 -> 0 | P11: =YearMap!E6 -> 300 | Q11: =IF(Scenarios!N3="lease", YearMap!F6, YearMap!G6) -> 0.3 | R11: =IF(Scenarios!D3=1, Q11*H11, H11) -> 1328990.5 | S11: =IF(Scenarios!E3=1, Q11*I11, I11) -> 1530666.1 | T11: =IF(C11="FY2026", (Scenarios!D3+Scenarios!E3)*BaselineCalc!$B$22, 0) -> 0 | U11: =(R11+S11+G11*F11)*J11*(1-K11) -> 7077329.5 | V11: =O11*(G11+P11) -> 0 | W11: =U11+V11+T11 -> 7077329.5 | X11: =IF(F11+O11>0, W11/(F11+O11),"") -> 10067.325 | Y11: =INDEX(YearMap!$I$2:$I$6, MATCH(C11, YearMap!$A$2:$A$6, 0)) -> 5426.2324 | Z11: =$W11-$Y11*$AC11 -> 3262688.1 | AA11: =IF($AC11>0, $Z11/$AC11, 0) -> 4641.0926 | AB11: =MAX(0, (MAX(0, $D11-BaselineCalc!$B$7) + MAX(0, $E11-BaselineCalc!$B$8))) -> 150 | AC11: =IF(LEFT($B11,2)="A_", $O11, IF(LEFT($B11,2)="B_", $M11+$O11, IF(LEFT($B11,2)="C_", $L11+$O11, $F11))) -> 703 | AD11: =$Y11*$AC11 -> 3814641.4 | AE11: =W11 - (1-Other_Parameters!$B$2)*$G11*$AB11*$J11*(1-$K11) -> 6534808.7 | AF11: =AD11-AE11 -> -2720167.3 | AG11: =B11&"|"&C11 -> E_StatusQuo_Targets|FY2030
A12: =AG12 -> F_CoLocation_Echo_Targets|FY2026 | B12: =Scenarios!A4 -> F_CoLocation_Echo_Targets | C12: FY2026 | D12: =IF(Scenarios!D4=1,0, L12) -> 332 | E12: =IF(Scenarios!E4=1,0, M12) -> 371 | F12: =D12+E12 -> 703 | G12: =YearMap!B2 -> 5499.576 | H12: =YearMap!C2 -> 1203999.8 | I12: =YearMap!D2 -> 1386707.9 | J12: =1-BaselineCalc!$B$5 -> 0.993 | K12: =Scenarios!G4 -> 0.05 | L12: =BaselineCalc!$B$7 + ROUND(Scenarios!I4*Scenarios!F4,0) -> 332 | M12: =BaselineCalc!$B$8 + Scenarios!I4 - ROUND(Scenarios!I4*Scenarios!F4,0) -> 371 | N12: =(L12-D12) + (M12-E12) -> 0 | O12: =BaselineCalc!$B$23 * N12 -> 0 | P12: =YearMap!E2 -> 1000 | Q12: =IF(Scenarios!N4="lease", YearMap!F2, YearMap!G2) -> 0.5 | R12: =IF(Scenarios!D4=1, Q12*H12, H12) -> 1203999.8 | S12: =IF(Scenarios!E4=1, Q12*I12, I12) -> 1386707.9 | T12: =IF(C12="FY2026", (Scenarios!D4+Scenarios!E4)*BaselineCalc!$B$22, 0) -> 0 | U12: =(R12+S12+G12*F12)*J12*(1-K12) -> 6091125.7 | V12: =O12*(G12+P12) -> 0 | W12: =U12+V12+T12 -> 6091125.7 | X12: =IF(F12+O12>0, W12/(F12+O12),"") -> 8664.4746 | Y12: =INDEX(YearMap!$I$2:$I$6, MATCH(C12, YearMap!$A$2:$A$6, 0)) -> 5013 | Z12: =$W12-$Y12*$AC12 -> 2566986.7 | AA12: =IF($AC12>0, $Z12/$AC12, 0) -> 3651.4746 | AB12: =MAX(0, (MAX(0, $D12-BaselineCalc!$B$7) + MAX(0, $E12-BaselineCalc!$B$8))) -> 150 | AC12: =IF(LEFT($B12,2)="A_", $O12, IF(LEFT($B12,2)="B_", $M12+$O12, IF(LEFT($B12,2)="C_", $L12+$O12, $F12))) -> 703 | AD12: =$Y12*$AC12 -> 3524139 | AE12: =W12 - (1-Other_Parameters!$B$2)*$G12*$AB12*$J12*(1-$K12) -> 5624203.4 | AF12: =AD12-AE12 -> -2100064.4 | AG12: =B12&"|"&C12 -> F_CoLocation_Echo_Targets|FY2026
A13: =AG13 -> F_CoLocation_Echo_Targets|FY2027 | B13: =Scenarios!A4 -> F_CoLocation_Echo_Targets | C13: FY2027 | D13: =IF(Scenarios!D4=1,0, L13) -> 332 | E13: =IF(Scenarios!E4=1,0, M13) -> 371 | F13: =D13+E13 -> 703 | G13: =YearMap!B3 -> 5637.0654 | H13: =YearMap!C3 -> 1234099.8 | I13: =YearMap!D3 -> 1421375.6 | J13: =1-BaselineCalc!$B$5 -> 0.993 | K13: =Scenarios!G4 -> 0.05 | L13: =BaselineCalc!$B$7 + ROUND(Scenarios!J4*Scenarios!F4,0) -> 332 | M13: =BaselineCalc!$B$8 + Scenarios!J4 - ROUND(Scenarios!J4*Scenarios!F4,0) -> 371 | N13: =(L13-D13) + (M13-E13) -> 0 | O13: =BaselineCalc!$B$23 * N13 -> 0 | P13: =YearMap!E3 -> 800 | Q13: =IF(Scenarios!N4="lease", YearMap!F3, YearMap!G3) -> 0.4 | R13: =IF(Scenarios!D4=1, Q13*H13, H13) -> 1234099.8 | S13: =IF(Scenarios!E4=1, Q13*I13, I13) -> 1421375.6 | T13: =IF(C13="FY2026", (Scenarios!D4+Scenarios!E4)*BaselineCalc!$B$22, 0) -> 0 | U13: =(R13+S13+G13*F13)*J13*(1-K13) -> 6243403.8 | V13: =O13*(G13+P13) -> 0 | W13: =U13+V13+T13 -> 6243403.8 | X13: =IF(F13+O13>0, W13/(F13+O13),"") -> 8881.0865 | Y13: =INDEX(YearMap!$I$2:$I$6, MATCH(C13, YearMap!$A$2:$A$6, 0)) -> 5113.26 | Z13: =$W13-$Y13*$AC13 -> 2648782 | AA13: =IF($AC13>0, $Z13/$AC13, 0) -> 3767.8265 | AB13: =MAX(0, (MAX(0, $D13-BaselineCalc!$B$7) + MAX(0, $E13-BaselineCalc!$B$8))) -> 150 | AC13: =IF(LEFT($B13,2)="A_", $O13, IF(LEFT($B13,2)="B_", $M13+$O13, IF(LEFT($B13,2)="C_", $L13+$O13, $F13))) -> 703 | AD13: =$Y13*$AC13 -> 3594621.8 | AE13: =W13 - (1-Other_Parameters!$B$2)*$G13*$AB13*$J13*(1-$K13) -> 5764808.5 | AF13: =AD13-AE13 -> -2170186.7 | AG13: =B13&"|"&C13 -> F_CoLocation_Echo_Targets|FY2027
A14: =AG14 -> F_CoLocation_Echo_Targets|FY2028 | B14: =Scenarios!A4 -> F_CoLocation_Echo_Targets | C14: FY2028 | D14: =IF(Scenarios!D4=1,0, L14) -> 332 | E14: =IF(Scenarios!E4=1,0, M14) -> 371 | F14: =D14+E14 -> 703 | G14: =YearMap!B4 -> 5777.992 | H14: =YearMap!C4 -> 1264952.3 | I14: =YearMap!D4 -> 1456910 | J14: =1-BaselineCalc!$B$5 -> 0.993 | K14: =Scenarios!G4 -> 0.05 | L14: =BaselineCalc!$B$7 + ROUND(Scenarios!K4*Scenarios!F4,0) -> 332 | M14: =BaselineCalc!$B$8 + Scenarios!K4 - ROUND(Scenarios!K4*Scenarios!F4,0) -> 371 | N14: =(L14-D14) + (M14-E14) -> 0 | O14: =BaselineCalc!$B$23 * N14 -> 0 | P14: =YearMap!E4 -> 600 | Q14: =IF(Scenarios!N4="lease", YearMap!F4, YearMap!G4) -> 0.35 | R14: =IF(Scenarios!D4=1, Q14*H14, H14) -> 1264952.3 | S14: =IF(Scenarios!E4=1, Q14*I14, I14) -> 1456910 | T14: =IF(C14="FY2026", (Scenarios!D4+Scenarios!E4)*BaselineCalc!$B$22, 0) -> 0 | U14: =(R14+S14+G14*F14)*J14*(1-K14) -> 6399488.9 | V14: =O14*(G14+P14) -> 0 | W14: =U14+V14+T14 -> 6399488.9 | X14: =IF(F14+O14>0, W14/(F14+O14),"") -> 9103.1137 | Y14: =INDEX(YearMap!$I$2:$I$6, MATCH(C14, YearMap!$A$2:$A$6, 0)) -> 5215.5252 | Z14: =$W14-$Y14*$AC14 -> 2732974.7 | AA14: =IF($AC14>0, $Z14/$AC14, 0) -> 3887.5885 | AB14: =MAX(0, (MAX(0, $D14-BaselineCalc!$B$7) + MAX(0, $E14-BaselineCalc!$B$8))) -> 150 | AC14: =IF(LEFT($B14,2)="A_", $O14, IF(LEFT($B14,2)="B_", $M14+$O14, IF(LEFT($B14,2)="C_", $L14+$O14, $F14))) -> 703 | AD14: =$Y14*$AC14 -> 3666514.2 | AE14: =W14 - (1-Other_Parameters!$B$2)*$G14*$AB14*$J14*(1-$K14) -> 5908928.7 | AF14: =AD14-AE14 -> -2242414.5 | AG14: =B14&"|"&C14 -> F_CoLocation_Echo_Targets|FY2028
A15: =AG15 -> F_CoLocation_Echo_Targets|FY2029 | B15: =Scenarios!A4 -> F_CoLocation_Echo_Targets | C15: FY2029 | D15: =IF(Scenarios!D4=1,0, L15) -> 332 | E15: =IF(Scenarios!E4=1,0, M15) -> 371 | F15: =D15+E15 -> 703 | G15: =YearMap!B5 -> 5922.4418 | H15: =YearMap!C5 -> 1296576.1 | I15: =YearMap!D5 -> 1493332.7 | J15: =1-BaselineCalc!$B$5 -> 0.993 | K15: =Scenarios!G4 -> 0.05 | L15: =BaselineCalc!$B$7 + ROUND(Scenarios!L4*Scenarios!F4,0) -> 332 | M15: =BaselineCalc!$B$8 + Scenarios!L4 - ROUND(Scenarios!L4*Scenarios!F4,0) -> 371 | N15: =(L15-D15) + (M15-E15) -> 0 | O15: =BaselineCalc!$B$23 * N15 -> 0 | P15: =YearMap!E5 -> 500 | Q15: =IF(Scenarios!N4="lease", YearMap!F5, YearMap!G5) -> 0.3 | R15: =IF(Scenarios!D4=1, Q15*H15, H15) -> 1296576.1 | S15: =IF(Scenarios!E4=1, Q15*I15, I15) -> 1493332.7 | T15: =IF(C15="FY2026", (Scenarios!D4+Scenarios!E4)*BaselineCalc!$B$22, 0) -> 0 | U15: =(R15+S15+G15*F15)*J15*(1-K15) -> 6559476.1 | V15: =O15*(G15+P15) -> 0 | W15: =U15+V15+T15 -> 6559476.1 | X15: =IF(F15+O15>0, W15/(F15+O15),"") -> 9330.6915 | Y15: =INDEX(YearMap!$I$2:$I$6, MATCH(C15, YearMap!$A$2:$A$6, 0)) -> 5319.8357 | Z15: =$W15-$Y15*$AC15 -> 2819631.6 | AA15: =IF($AC15>0, $Z15/$AC15, 0) -> 4010.8558 | AB15: =MAX(0, (MAX(0, $D15-BaselineCalc!$B$7) + MAX(0, $E15-BaselineCalc!$B$8))) -> 150 | AC15: =IF(LEFT($B15,2)="A_", $O15, IF(LEFT($B15,2)="B_", $M15+$O15, IF(LEFT($B15,2)="C_", $L15+$O15, $F15))) -> 703 | AD15: =$Y15*$AC15 -> 3739844.5 | AE15: =W15 - (1-Other_Parameters!$B$2)*$G15*$AB15*$J15*(1-$K15) -> 6056651.9 | AF15: =AD15-AE15 -> -2316807.4 | AG15: =B15&"|"&C15 -> F_CoLocation_Echo_Targets|FY2029
A16: =AG16 -> F_CoLocation_Echo_Targets|FY2030 | B16: =Scenarios!A4 -> F_CoLocation_Echo_Targets | C16: FY2030 | D16: =IF(Scenarios!D4=1,0, L16) -> 332 | E16: =IF(Scenarios!E4=1,0, M16) -> 371 | F16: =D16+E16 -> 703 | G16: =YearMap!B6 -> 6070.5029 | H16: =YearMap!C6 -> 1328990.5 | I16: =YearMap!D6 -> 1530666.1 | J16: =1-BaselineCalc!$B$5 -> 0.993 | K16: =Scenarios!G4 -> 0.05 | L16: =BaselineCalc!$B$7 + ROUND(Scenarios!M4*Scenarios!F4,0) -> 332 | M16: =BaselineCalc!$B$8 + Scenarios!M4 - ROUND(Scenarios!M4*Scenarios!F4,0) -> 371 | N16: =(L16-D16) + (M16-E16) -> 0 | O16: =BaselineCalc!$B$23 * N16 -> 0 | P16: =YearMap!E6 -> 300 | Q16: =IF(Scenarios!N4="lease", YearMap!F6, YearMap!G6) -> 0.3 | R16: =IF(Scenarios!D4=1, Q16*H16, H16) -> 1328990.5 | S16: =IF(Scenarios!E4=1, Q16*I16, I16) -> 1530666.1 | T16: =IF(C16="FY2026", (Scenarios!D4+Scenarios!E4)*BaselineCalc!$B$22, 0) -> 0 | U16: =(R16+S16+G16*F16)*J16*(1-K16) -> 6723463 | V16: =O16*(G16+P16) -> 0 | W16: =U16+V16+T16 -> 6723463 | X16: =IF(F16+O16>0, W16/(F16+O16),"") -> 9563.9588 | Y16: =INDEX(YearMap!$I$2:$I$6, MATCH(C16, YearMap!$A$2:$A$6, 0)) -> 5426.2324 | Z16: =$W16-$Y16*$AC16 -> 2908821.6 | AA16: =IF($AC16>0, $Z16/$AC16, 0) -> 4137.7264 | AB16: =MAX(0, (MAX(0, $D16-BaselineCalc!$B$7) + MAX(0, $E16-BaselineCalc!$B$8))) -> 150 | AC16: =IF(LEFT($B16,2)="A_", $O16, IF(LEFT($B16,2)="B_", $M16+$O16, IF(LEFT($B16,2)="C_", $L16+$O16, $F16))) -> 703 | AD16: =$Y16*$AC16 -> 3814641.4 | AE16: =W16 - (1-Other_Parameters!$B$2)*$G16*$AB16*$J16*(1-$K16) -> 6208068.2 | AF16: =AD16-AE16 -> -2393426.8 | AG16: =B16&"|"&C16 -> F_CoLocation_Echo_Targets|FY2030
A17: =AG17 -> D_Grow_Both_Targets|FY2026 | B17: =Scenarios!A5 -> D_Grow_Both_Targets | C17: FY2026 | D17: =IF(Scenarios!D5=1,0, L17) -> 382 | E17: =IF(Scenarios!E5=1,0, M17) -> 421 | F17: =D17+E17 -> 803 | G17: =YearMap!B2 -> 5499.576 | H17: =YearMap!C2 -> 1203999.8 | I17: =YearMap!D2 -> 1386707.9 | J17: =1-BaselineCalc!$B$5 -> 0.993 | K17: =Scenarios!G5 -> 0 | L17: =BaselineCalc!$B$7 + ROUND(Scenarios!I5*Scenarios!F5,0) -> 382 | M17: =BaselineCalc!$B$8 + Scenarios!I5 - ROUND(Scenarios!I5*Scenarios!F5,0) -> 421 | N17: =(L17-D17) + (M17-E17) -> 0 | O17: =BaselineCalc!$B$23 * N17 -> 0 | P17: =YearMap!E2 -> 1000 | Q17: =IF(Scenarios!N5="lease", YearMap!F2, YearMap!G2) -> 0.5 | R17: =IF(Scenarios!D5=1, Q17*H17, H17) -> 1203999.8 | S17: =IF(Scenarios!E5=1, Q17*I17, I17) -> 1386707.9 | T17: =IF(C17="FY2026", (Scenarios!D5+Scenarios!E5)*BaselineCalc!$B$22, 0) -> 0 | U17: =(R17+S17+G17*F17)*J17*(1-K17) -> 6957819.1 | V17: =O17*(G17+P17) -> 0 | W17: =U17+V17+T17 -> 6957819.1 | X17: =IF(F17+O17>0, W17/(F17+O17),"") -> 8664.781 | Y17: =INDEX(YearMap!$I$2:$I$6, MATCH(C17, YearMap!$A$2:$A$6, 0)) -> 5013 | Z17: =$W17-$Y17*$AC17 -> 2932380.1 | AA17: =IF($AC17>0, $Z17/$AC17, 0) -> 3651.781 | AB17: =MAX(0, (MAX(0, $D17-BaselineCalc!$B$7) + MAX(0, $E17-BaselineCalc!$B$8))) -> 250 | AC17: =IF(LEFT($B17,2)="A_", $O17, IF(LEFT($B17,2)="B_", $M17+$O17, IF(LEFT($B17,2)="C_", $L17+$O17, $F17))) -> 803 | AD17: =$Y17*$AC17 -> 4025439 | AE17: =W17 - (1-Other_Parameters!$B$2)*$G17*$AB17*$J17*(1-$K17) -> 6138657.3 | AF17: =AD17-AE17 -> -2113218.3 | AG17: =B17&"|"&C17 -> D_Grow_Both_Targets|FY2026
A18: =AG18 -> D_Grow_Both_Targets|FY2027 | B18: =Scenarios!A5 -> D_Grow_Both_Targets | C18: FY2027 | D18: =IF(Scenarios!D5=1,0, L18) -> 382 | E18: =IF(Scenarios!E5=1,0, M18) -> 421 | F18: =D18+E18 -> 803 | G18: =YearMap!B3 -> 5637.0654 | H18: =YearMap!C3 -> 1234099.8 | I18: =YearMap!D3 -> 1421375.6 | J18: =1-BaselineCalc!$B$5 -> 0.993 | K18: =Scenarios!G5 -> 0 | L18: =BaselineCalc!$B$7 + ROUND(Scenarios!J5*Scenarios!F5,0) -> 382 | M18: =BaselineCalc!$B$8 + Scenarios!J5 - ROUND(Scenarios!J5*Scenarios!F5,0) -> 421 | N18: =(L18-D18) + (M18-E18) -> 0 | O18: =BaselineCalc!$B$23 * N18 -> 0 | P18: =YearMap!E3 -> 800 | Q18: =IF(Scenarios!N5="lease", YearMap!F3, YearMap!G3) -> 0.4 | R18: =IF(Scenarios!D5=1, Q18*H18, H18) -> 1234099.8 | S18: =IF(Scenarios!E5=1, Q18*I18, I18) -> 1421375.6 | T18: =IF(C18="FY2026", (Scenarios!D5+Scenarios!E5)*BaselineCalc!$B$22, 0) -> 0 | U18: =(R18+S18+G18*F18)*J18*(1-K18) -> 7131764.6 | V18: =O18*(G18+P18) -> 0 | W18: =U18+V18+T18 -> 7131764.6 | X18: =IF(F18+O18>0, W18/(F18+O18),"") -> 8881.4005 | Y18: =INDEX(YearMap!$I$2:$I$6, MATCH(C18, YearMap!$A$2:$A$6, 0)) -> 5113.26 | Z18: =$W18-$Y18*$AC18 -> 3025816.8 | AA18: =IF($AC18>0, $Z18/$AC18, 0) -> 3768.1405 | AB18: =MAX(0, (MAX(0, $D18-BaselineCalc!$B$7) + MAX(0, $E18-BaselineCalc!$B$8))) -> 250 | AC18: =IF(LEFT($B18,2)="A_", $O18, IF(LEFT($B18,2)="B_", $M18+$O18, IF(LEFT($B18,2)="C_", $L18+$O18, $F18))) -> 803 | AD18: =$Y18*$AC18 -> 4105947.8 | AE18: =W18 - (1-Other_Parameters!$B$2)*$G18*$AB18*$J18*(1-$K18) -> 6292123.7 | AF18: =AD18-AE18 -> -2186175.9 | AG18: =B18&"|"&C18 -> D_Grow_Both_Targets|FY2027
A19: =AG19 -> D_Grow_Both_Targets|FY2028 | B19: =Scenarios!A5 -> D_Grow_Both_Targets | C19: FY2028 | D19: =IF(Scenarios!D5=1,0, L19) -> 382 | E19: =IF(Scenarios!E5=1,0, M19) -> 421 | F19: =D19+E19 -> 803 | G19: =YearMap!B4 -> 5777.992 | H19: =YearMap!C4 -> 1264952.3 | I19: =YearMap!D4 -> 1456910 | J19: =1-BaselineCalc!$B$5 -> 0.993 | K19: =Scenarios!G5 -> 0 | L19: =BaselineCalc!$B$7 + ROUND(Scenarios!K5*Scenarios!F5,0) -> 382 | M19: =BaselineCalc!$B$8 + Scenarios!K5 - ROUND(Scenarios!K5*Scenarios!F5,0) -> 421 | N19: =(L19-D19) + (M19-E19) -> 0 | O19: =BaselineCalc!$B$23 * N19 -> 0 | P19: =YearMap!E4 -> 600 | Q19: =IF(Scenarios!N5="lease", YearMap!F4, YearMap!G4) -> 0.35 | R19: =IF(Scenarios!D5=1, Q19*H19, H19) -> 1264952.3 | S19: =IF(Scenarios!E5=1, Q19*I19, I19) -> 1456910 | T19: =IF(C19="FY2026", (Scenarios!D5+Scenarios!E5)*BaselineCalc!$B$22, 0) -> 0 | U19: =(R19+S19+G19*F19)*J19*(1-K19) -> 7310058.7 | V19: =O19*(G19+P19) -> 0 | W19: =U19+V19+T19 -> 7310058.7 | X19: =IF(F19+O19>0, W19/(F19+O19),"") -> 9103.4355 | Y19: =INDEX(YearMap!$I$2:$I$6, MATCH(C19, YearMap!$A$2:$A$6, 0)) -> 5215.5252 | Z19: =$W19-$Y19*$AC19 -> 3121992 | AA19: =IF($AC19>0, $Z19/$AC19, 0) -> 3887.9103 | AB19: =MAX(0, (MAX(0, $D19-BaselineCalc!$B$7) + MAX(0, $E19-BaselineCalc!$B$8))) -> 250 | AC19: =IF(LEFT($B19,2)="A_", $O19, IF(LEFT($B19,2)="B_", $M19+$O19, IF(LEFT($B19,2)="C_", $L19+$O19, $F19))) -> 803 | AD19: =$Y19*$AC19 -> 4188066.7 | AE19: =W19 - (1-Other_Parameters!$B$2)*$G19*$AB19*$J19*(1-$K19) -> 6449426.8 | AF19: =AD19-AE19 -> -2261360.1 | AG19: =B19&"|"&C19 -> D_Grow_Both_Targets|FY2028
A20: =AG20 -> D_Grow_Both_Targets|FY2029 | B20: =Scenarios!A5 -> D_Grow_Both_Targets | C20: FY2029 | D20: =IF(Scenarios!D5=1,0, L20) -> 382 | E20: =IF(Scenarios!E5=1,0, M20) -> 421 | F20: =D20+E20 -> 803 | G20: =YearMap!B5 -> 5922.4418 | H20: =YearMap!C5 -> 1296576.1 | I20: =YearMap!D5 -> 1493332.7 | J20: =1-BaselineCalc!$B$5 -> 0.993 | K20: =Scenarios!G5 -> 0 | L20: =BaselineCalc!$B$7 + ROUND(Scenarios!L5*Scenarios!F5,0) -> 382 | M20: =BaselineCalc!$B$8 + Scenarios!L5 - ROUND(Scenarios!L5*Scenarios!F5,0) -> 421 | N20: =(L20-D20) + (M20-E20) -> 0 | O20: =BaselineCalc!$B$23 * N20 -> 0 | P20: =YearMap!E5 -> 500 | Q20: =IF(Scenarios!N5="lease", YearMap!F5, YearMap!G5) -> 0.3 | R20: =IF(Scenarios!D5=1, Q20*H20, H20) -> 1296576.1 | S20: =IF(Scenarios!E5=1, Q20*I20, I20) -> 1493332.7 | T20: =IF(C20="FY2026", (Scenarios!D5+Scenarios!E5)*BaselineCalc!$B$22, 0) -> 0 | U20: =(R20+S20+G20*F20)*J20*(1-K20) -> 7492810.2 | V20: =O20*(G20+P20) -> 0 | W20: =U20+V20+T20 -> 7492810.2 | X20: =IF(F20+O20>0, W20/(F20+O20),"") -> 9331.0214 | Y20: =INDEX(YearMap!$I$2:$I$6, MATCH(C20, YearMap!$A$2:$A$6, 0)) -> 5319.8357 | Z20: =$W20-$Y20*$AC20 -> 3220982.1 | AA20: =IF($AC20>0, $Z20/$AC20, 0) -> 4011.1857 | AB20: =MAX(0, (MAX(0, $D20-BaselineCalc!$B$7) + MAX(0, $E20-BaselineCalc!$B$8))) -> 250 | AC20: =IF(LEFT($B20,2)="A_", $O20, IF(LEFT($B20,2)="B_", $M20+$O20, IF(LEFT($B20,2)="C_", $L20+$O20, $F20))) -> 803 | AD20: =$Y20*$AC20 -> 4271828.1 | AE20: =W20 - (1-Other_Parameters!$B$2)*$G20*$AB20*$J20*(1-$K20) -> 6610662.5 | AF20: =AD20-AE20 -> -2338834.4 | AG20: =B20&"|"&C20 -> D_Grow_Both_Targets|FY2029
A21: =AG21 -> D_Grow_Both_Targets|FY2030 | B21: =Scenarios!A5 -> D_Grow_Both_Targets | C21: FY2030 | D21: =IF(Scenarios!D5=1,0, L21) -> 382 | E21: =IF(Scenarios!E5=1,0, M21) -> 421 | F21: =D21+E21 -> 803 | G21: =YearMap!B6 -> 6070.5029 | H21: =YearMap!C6 -> 1328990.5 | I21: =YearMap!D6 -> 1530666.1 | J21: =1-BaselineCalc!$B$5 -> 0.993 | K21: =Scenarios!G5 -> 0 | L21: =BaselineCalc!$B$7 + ROUND(Scenarios!M5*Scenarios!F5,0) -> 382 | M21: =BaselineCalc!$B$8 + Scenarios!M5 - ROUND(Scenarios!M5*Scenarios!F5,0) -> 421 | N21: =(L21-D21) + (M21-E21) -> 0 | O21: =BaselineCalc!$B$23 * N21 -> 0 | P21: =YearMap!E6 -> 300 | Q21: =IF(Scenarios!N5="lease", YearMap!F6, YearMap!G6) -> 0.3 | R21: =IF(Scenarios!D5=1, Q21*H21, H21) -> 1328990.5 | S21: =IF(Scenarios!E5=1, Q21*I21, I21) -> 1530666.1 | T21: =IF(C21="FY2026", (Scenarios!D5+Scenarios!E5)*BaselineCalc!$B$22, 0) -> 0 | U21: =(R21+S21+G21*F21)*J21*(1-K21) -> 7680130.4 | V21: =O21*(G21+P21) -> 0 | W21: =U21+V21+T21 -> 7680130.4 | X21: =IF(F21+O21>0, W21/(F21+O21),"") -> 9564.2969 | Y21: =INDEX(YearMap!$I$2:$I$6, MATCH(C21, YearMap!$A$2:$A$6, 0)) -> 5426.2324 | Z21: =$W21-$Y21*$AC21 -> 3322865.8 | AA21: =IF($AC21>0, $Z21/$AC21, 0) -> 4138.0645 | AB21: =MAX(0, (MAX(0, $D21-BaselineCalc!$B$7) + MAX(0, $E21-BaselineCalc!$B$8))) -> 250 | AC21: =IF(LEFT($B21,2)="A_", $O21, IF(LEFT($B21,2)="B_", $M21+$O21, IF(LEFT($B21,2)="C_", $L21+$O21, $F21))) -> 803 | AD21: =$Y21*$AC21 -> 4357264.6 | AE21: =W21 - (1-Other_Parameters!$B$2)*$G21*$AB21*$J21*(1-$K21) -> 6775929 | AF21: =AD21-AE21 -> -2418664.4 | AG21: =B21&"|"&C21 -> D_Grow_Both_Targets|FY2030
A22: =AG22 -> D_CUSTOM2|FY2026 | B22: =Scenarios!A6 -> D_CUSTOM2 | C22: FY2026 | D22: =IF(Scenarios!D6=1,0, L22) -> 257 | E22: =IF(Scenarios!E6=1,0, M22) -> 296 | F22: =D22+E22 -> 553 | G22: =YearMap!B2 -> 5499.576 | H22: =YearMap!C2 -> 1203999.8 | I22: =YearMap!D2 -> 1386707.9 | J22: =1-BaselineCalc!$B$5 -> 0.993 | K22: =Scenarios!G6 -> 0 | L22: =BaselineCalc!$B$7 + ROUND(Scenarios!I6*Scenarios!F6,0) -> 257 | M22: =BaselineCalc!$B$8 + Scenarios!I6 - ROUND(Scenarios!I6*Scenarios!F6,0) -> 296 | N22: =(L22-D22) + (M22-E22) -> 0 | O22: =BaselineCalc!$B$23 * N22 -> 0 | P22: =YearMap!E2 -> 1000 | Q22: =IF(Scenarios!N6="lease", YearMap!F2, YearMap!G2) -> 0.5 | R22: =IF(Scenarios!D6=1, Q22*H22, H22) -> 1203999.8 | S22: =IF(Scenarios!E6=1, Q22*I22, I22) -> 1386707.9 | T22: =IF(C22="FY2026", (Scenarios!D6+Scenarios!E6)*BaselineCalc!$B$22, 0) -> 0 | U22: =(R22+S22+G22*F22)*J22*(1-K22) -> 5592549.4 | V22: =O22*(G22+P22) -> 0 | W22: =U22+V22+T22 -> 5592549.4 | X22: =IF(F22+O22>0, W22/(F22+O22),"") -> 10113.109 | Y22: =INDEX(YearMap!$I$2:$I$6, MATCH(C22, YearMap!$A$2:$A$6, 0)) -> 5013 | Z22: =$W22-$Y22*$AC22 -> 2820360.4 | AA22: =IF($AC22>0, $Z22/$AC22, 0) -> 5100.1092 | AB22: =MAX(0, (MAX(0, $D22-BaselineCalc!$B$7) + MAX(0, $E22-BaselineCalc!$B$8))) -> 0 | AC22: =IF(LEFT($B22,2)="A_", $O22, IF(LEFT($B22,2)="B_", $M22+$O22, IF(LEFT($B22,2)="C_", $L22+$O22, $F22))) -> 553 | AD22: =$Y22*$AC22 -> 2772189 | AE22: =W22 - (1-Other_Parameters!$B$2)*$G22*$AB22*$J22*(1-$K22) -> 5592549.4 | AF22: =AD22-AE22 -> -2820360.4 | AG22: =B22&"|"&C22 -> D_CUSTOM2|FY2026
A23: =AG23 -> D_CUSTOM2|FY2027 | B23: =Scenarios!A6 -> D_CUSTOM2 | C23: FY2027 | D23: =IF(Scenarios!D6=1,0, L23) -> 257 | E23: =IF(Scenarios!E6=1,0, M23) -> 296 | F23: =D23+E23 -> 553 | G23: =YearMap!B3 -> 5637.0654 | H23: =YearMap!C3 -> 1234099.8 | I23: =YearMap!D3 -> 1421375.6 | J23: =1-BaselineCalc!$B$5 -> 0.993 | K23: =Scenarios!G6 -> 0 | L23: =BaselineCalc!$B$7 + ROUND(Scenarios!J6*Scenarios!F6,0) -> 257 | M23: =BaselineCalc!$B$8 + Scenarios!J6 - ROUND(Scenarios!J6*Scenarios!F6,0) -> 296 | N23: =(L23-D23) + (M23-E23) -> 0 | O23: =BaselineCalc!$B$23 * N23 -> 0 | P23: =YearMap!E3 -> 800 | Q23: =IF(Scenarios!N6="lease", YearMap!F3, YearMap!G3) -> 0.4 | R23: =IF(Scenarios!D6=1, Q23*H23, H23) -> 1234099.8 | S23: =IF(Scenarios!E6=1, Q23*I23, I23) -> 1421375.6 | T23: =IF(C23="FY2026", (Scenarios!D6+Scenarios!E6)*BaselineCalc!$B$22, 0) -> 0 | U23: =(R23+S23+G23*F23)*J23*(1-K23) -> 5732363.1 | V23: =O23*(G23+P23) -> 0 | W23: =U23+V23+T23 -> 5732363.1 | X23: =IF(F23+O23>0, W23/(F23+O23),"") -> 10365.937 | Y23: =INDEX(YearMap!$I$2:$I$6, MATCH(C23, YearMap!$A$2:$A$6, 0)) -> 5113.26 | Z23: =$W23-$Y23*$AC23 -> 2904730.3 | AA23: =IF($AC23>0, $Z23/$AC23, 0) -> 5252.6769 | AB23: =MAX(0, (MAX(0, $D23-BaselineCalc!$B$7) + MAX(0, $E23-BaselineCalc!$B$8))) -> 0 | AC23: =IF(LEFT($B23,2)="A_", $O23, IF(LEFT($B23,2)="B_", $M23+$O23, IF(LEFT($B23,2)="C_", $L23+$O23, $F23))) -> 553 | AD23: =$Y23*$AC23 -> 2827632.8 | AE23: =W23 - (1-Other_Parameters!$B$2)*$G23*$AB23*$J23*(1-$K23) -> 5732363.1 | AF23: =AD23-AE23 -> -2904730.3 | AG23: =B23&"|"&C23 -> D_CUSTOM2|FY2027
A24: =AG24 -> D_CUSTOM2|FY2028 | B24: =Scenarios!A6 -> D_CUSTOM2 | C24: FY2028 | D24: =IF(Scenarios!D6=1,0, L24) -> 257 | E24: =IF(Scenarios!E6=1,0, M24) -> 296 | F24: =D24+E24 -> 553 | G24: =YearMap!B4 -> 5777.992 | H24: =YearMap!C4 -> 1264952.3 | I24: =YearMap!D4 -> 1456910 | J24: =1-BaselineCalc!$B$5 -> 0.993 | K24: =Scenarios!G6 -> 0 | L24: =BaselineCalc!$B$7 + ROUND(Scenarios!K6*Scenarios!F6,0) -> 257 | M24: =BaselineCalc!$B$8 + Scenarios!K6 - ROUND(Scenarios!K6*Scenarios!F6,0) -> 296 | N24: =(L24-D24) + (M24-E24) -> 0 | O24: =BaselineCalc!$B$23 * N24 -> 0 | P24: =YearMap!E4 -> 600 | Q24: =IF(Scenarios!N6="lease", YearMap!F4, YearMap!G4) -> 0.35 | R24: =IF(Scenarios!D6=1, Q24*H24, H24) -> 1264952.3 | S24: =IF(Scenarios!E6=1, Q24*I24, I24) -> 1456910 | T24: =IF(C24="FY2026", (Scenarios!D6+Scenarios!E6)*BaselineCalc!$B$22, 0) -> 0 | U24: =(R24+S24+G24*F24)*J24*(1-K24) -> 5875672.2 | V24: =O24*(G24+P24) -> 0 | W24: =U24+V24+T24 -> 5875672.2 | X24: =IF(F24+O24>0, W24/(F24+O24),"") -> 10625.085 | Y24: =INDEX(YearMap!$I$2:$I$6, MATCH(C24, YearMap!$A$2:$A$6, 0)) -> 5215.5252 | Z24: =$W24-$Y24*$AC24 -> 2991486.8 | AA24: =IF($AC24>0, $Z24/$AC24, 0) -> 5409.5602 | AB24: =MAX(0, (MAX(0, $D24-BaselineCalc!$B$7) + MAX(0, $E24-BaselineCalc!$B$8))) -> 0 | AC24: =IF(LEFT($B24,2)="A_", $O24, IF(LEFT($B24,2)="B_", $M24+$O24, IF(LEFT($B24,2)="C_", $L24+$O24, $F24))) -> 553 | AD24: =$Y24*$AC24 -> 2884185.4 | AE24: =W24 - (1-Other_Parameters!$B$2)*$G24*$AB24*$J24*(1-$K24) -> 5875672.2 | AF24: =AD24-AE24 -> -2991486.8 | AG24: =B24&"|"&C24 -> D_CUSTOM2|FY2028
A25: =AG25 -> D_CUSTOM2|FY2029 | B25: =Scenarios!A6 -> D_CUSTOM2 | C25: FY2029 | D25: =IF(Scenarios!D6=1,0, L25) -> 257 | E25: =IF(Scenarios!E6=1,0, M25) -> 296 | F25: =D25+E25 -> 553 | G25: =YearMap!B5 -> 5922.4418 | H25: =YearMap!C5 -> 1296576.1 | I25: =YearMap!D5 -> 1493332.7 | J25: =1-BaselineCalc!$B$5 -> 0.993 | K25: =Scenarios!G6 -> 0 | L25: =BaselineCalc!$B$7 + ROUND(Scenarios!L6*Scenarios!F6,0) -> 257 | M25: =BaselineCalc!$B$8 + Scenarios!L6 - ROUND(Scenarios!L6*Scenarios!F6,0) -> 296 | N25: =(L25-D25) + (M25-E25) -> 0 | O25: =BaselineCalc!$B$23 * N25 -> 0 | P25: =YearMap!E5 -> 500 | Q25: =IF(Scenarios!N6="lease", YearMap!F5, YearMap!G5) -> 0.3 | R25: =IF(Scenarios!D6=1, Q25*H25, H25) -> 1296576.1 | S25: =IF(Scenarios!E6=1, Q25*I25, I25) -> 1493332.7 | T25: =IF(C25="FY2026", (Scenarios!D6+Scenarios!E6)*BaselineCalc!$B$22, 0) -> 0 | U25: =(R25+S25+G25*F25)*J25*(1-K25) -> 6022564 | V25: =O25*(G25+P25) -> 0 | W25: =U25+V25+T25 -> 6022564 | X25: =IF(F25+O25>0, W25/(F25+O25),"") -> 10890.712 | Y25: =INDEX(YearMap!$I$2:$I$6, MATCH(C25, YearMap!$A$2:$A$6, 0)) -> 5319.8357 | Z25: =$W25-$Y25*$AC25 -> 3080694.9 | AA25: =IF($AC25>0, $Z25/$AC25, 0) -> 5570.8768 | AB25: =MAX(0, (MAX(0, $D25-BaselineCalc!$B$7) + MAX(0, $E25-BaselineCalc!$B$8))) -> 0 | AC25: =IF(LEFT($B25,2)="A_", $O25, IF(LEFT($B25,2)="B_", $M25+$O25, IF(LEFT($B25,2)="C_", $L25+$O25, $F25))) -> 553 | AD25: =$Y25*$AC25 -> 2941869.1 | AE25: =W25 - (1-Other_Parameters!$B$2)*$G25*$AB25*$J25*(1-$K25) -> 6022564 | AF25: =AD25-AE25 -> -3080694.9 | AG25: =B25&"|"&C25 -> D_CUSTOM2|FY2029
A26: =AG26 -> D_CUSTOM2|FY2030 | B26: =Scenarios!A6 -> D_CUSTOM2 | C26: FY2030 | D26: =IF(Scenarios!D6=1,0, L26) -> 257 | E26: =IF(Scenarios!E6=1,0, M26) -> 296 | F26: =D26+E26 -> 553 | G26: =YearMap!B6 -> 6070.5029 | H26: =YearMap!C6 -> 1328990.5 | I26: =YearMap!D6 -> 1530666.1 | J26: =1-BaselineCalc!$B$5 -> 0.993 | K26: =Scenarios!G6 -> 0 | L26: =BaselineCalc!$B$7 + ROUND(Scenarios!M6*Scenarios!F6,0) -> 257 | M26: =BaselineCalc!$B$8 + Scenarios!M6 - ROUND(Scenarios!M6*Scenarios!F6,0) -> 296 | N26: =(L26-D26) + (M26-E26) -> 0 | O26: =BaselineCalc!$B$23 * N26 -> 0 | P26: =YearMap!E6 -> 300 | Q26: =IF(Scenarios!N6="lease", YearMap!F6, YearMap!G6) -> 0.3 | R26: =IF(Scenarios!D6=1, Q26*H26, H26) -> 1328990.5 | S26: =IF(Scenarios!E6=1, Q26*I26, I26) -> 1530666.1 | T26: =IF(C26="FY2026", (Scenarios!D6+Scenarios!E6)*BaselineCalc!$B$22, 0) -> 0 | U26: =(R26+S26+G26*F26)*J26*(1-K26) -> 6173128.1 | V26: =O26*(G26+P26) -> 0 | W26: =U26+V26+T26 -> 6173128.1 | X26: =IF(F26+O26>0, W26/(F26+O26),"") -> 11162.98 | Y26: =INDEX(YearMap!$I$2:$I$6, MATCH(C26, YearMap!$A$2:$A$6, 0)) -> 5426.2324 | Z26: =$W26-$Y26*$AC26 -> 3172421.6 | AA26: =IF($AC26>0, $Z26/$AC26, 0) -> 5736.7479 | AB26: =MAX(0, (MAX(0, $D26-BaselineCalc!$B$7) + MAX(0, $E26-BaselineCalc!$B$8))) -> 0 | AC26: =IF(LEFT($B26,2)="A_", $O26, IF(LEFT($B26,2)="B_", $M26+$O26, IF(LEFT($B26,2)="C_", $L26+$O26, $F26))) -> 553 | AD26: =$Y26*$AC26 -> 3000706.5 | AE26: =W26 - (1-Other_Parameters!$B$2)*$G26*$AB26*$J26*(1-$K26) -> 6173128.1 | AF26: =AD26-AE26 -> -3172421.6 | AG26: =B26&"|"&C26 -> D_CUSTOM2|FY2030
A27: =AG27 -> G_EchoGHubRamp_PimaTargets|FY2026 | B27: =Scenarios!A7 -> G_EchoGHubRamp_PimaTargets | C27: FY2026 | D27: =IF(Scenarios!D7=1,0, L27) -> 292 | E27: =IF(Scenarios!E7=1,0, M27) -> 311 | F27: =D27+E27 -> 603 | G27: =YearMap!B2 -> 5499.576 | H27: =YearMap!C2 -> 1203999.8 | I27: =YearMap!D2 -> 1386707.9 | J27: =1-BaselineCalc!$B$5 -> 0.993 | K27: =Scenarios!G7 -> 0 | L27: =BaselineCalc!$B$7 + ROUND(Scenarios!I7*Scenarios!F7,0) -> 292 | M27: =BaselineCalc!$B$8 + Scenarios!I7 - ROUND(Scenarios!I7*Scenarios!F7,0) -> 311 | N27: =(L27-D27) + (M27-E27) -> 0 | O27: =BaselineCalc!$B$23 * N27 -> 0 | P27: =YearMap!E2 -> 1000 | Q27: =IF(Scenarios!N7="lease", YearMap!F2, YearMap!G2) -> 0.5 | R27: =IF(Scenarios!D7=1, Q27*H27, H27) -> 1203999.8 | S27: =IF(Scenarios!E7=1, Q27*I27, I27) -> 1386707.9 | T27: =IF(C27="FY2026", (Scenarios!D7+Scenarios!E7)*BaselineCalc!$B$22, 0) -> 0 | U27: =(R27+S27+G27*F27)*J27*(1-K27) -> 5865603.3 | V27: =O27*(G27+P27) -> 0 | W27: =U27+V27+T27 -> 5865603.3 | X27: =IF(F27+O27>0, W27/(F27+O27),"") -> 9727.3687 | Y27: =INDEX(YearMap!$I$2:$I$6, MATCH(C27, YearMap!$A$2:$A$6, 0)) -> 5013 | Z27: =$W27-$Y27*$AC27 -> 2842764.3 | AA27: =IF($AC27>0, $Z27/$AC27, 0) -> 4714.3687 | AB27: =MAX(0, (MAX(0, $D27-BaselineCalc!$B$7) + MAX(0, $E27-BaselineCalc!$B$8))) -> 50 | AC27: =IF(LEFT($B27,2)="A_", $O27, IF(LEFT($B27,2)="B_", $M27+$O27, IF(LEFT($B27,2)="C_", $L27+$O27, $F27))) -> 603 | AD27: =$Y27*$AC27 -> 3022839 | AE27: =W27 - (1-Other_Parameters!$B$2)*$G27*$AB27*$J27*(1-$K27) -> 5701771 | AF27: =AD27-AE27 -> -2678932 | AG27: =B27&"|"&C27 -> G_EchoGHubRamp_PimaTargets|FY2026
A28: =AG28 -> G_EchoGHubRamp_PimaTargets|FY2027 | B28: =Scenarios!A7 -> G_EchoGHubRamp_PimaTargets | C28: FY2027 | D28: =IF(Scenarios!D7=1,0, L28) -> 327 | E28: =IF(Scenarios!E7=1,0, M28) -> 326 | F28: =D28+E28 -> 653 | G28: =YearMap!B3 -> 5637.0654 | H28: =YearMap!C3 -> 1234099.8 | I28: =YearMap!D3 -> 1421375.6 | J28: =1-BaselineCalc!$B$5 -> 0.993 | K28: =Scenarios!G7 -> 0 | L28: =BaselineCalc!$B$7 + ROUND(Scenarios!J7*Scenarios!F7,0) -> 327 | M28: =BaselineCalc!$B$8 + Scenarios!J7 - ROUND(Scenarios!J7*Scenarios!F7,0) -> 326 | N28: =(L28-D28) + (M28-E28) -> 0 | O28: =BaselineCalc!$B$23 * N28 -> 0 | P28: =YearMap!E3 -> 800 | Q28: =IF(Scenarios!N7="lease", YearMap!F3, YearMap!G3) -> 0.4 | R28: =IF(Scenarios!D7=1, Q28*H28, H28) -> 1234099.8 | S28: =IF(Scenarios!E7=1, Q28*I28, I28) -> 1421375.6 | T28: =IF(C28="FY2026", (Scenarios!D7+Scenarios!E7)*BaselineCalc!$B$22, 0) -> 0 | U28: =(R28+S28+G28*F28)*J28*(1-K28) -> 6292123.7 | V28: =O28*(G28+P28) -> 0 | W28: =U28+V28+T28 -> 6292123.7 | X28: =IF(F28+O28>0, W28/(F28+O28),"") -> 9635.7178 | Y28: =INDEX(YearMap!$I$2:$I$6, MATCH(C28, YearMap!$A$2:$A$6, 0)) -> 5113.26 | Z28: =$W28-$Y28*$AC28 -> 2953164.9 | AA28: =IF($AC28>0, $Z28/$AC28, 0) -> 4522.4578 | AB28: =MAX(0, (MAX(0, $D28-BaselineCalc!$B$7) + MAX(0, $E28-BaselineCalc!$B$8))) -> 100 | AC28: =IF(LEFT($B28,2)="A_", $O28, IF(LEFT($B28,2)="B_", $M28+$O28, IF(LEFT($B28,2)="C_", $L28+$O28, $F28))) -> 653 | AD28: =$Y28*$AC28 -> 3338958.8 | AE28: =W28 - (1-Other_Parameters!$B$2)*$G28*$AB28*$J28*(1-$K28) -> 5956267.4 | AF28: =AD28-AE28 -> -2617308.6 | AG28: =B28&"|"&C28 -> G_EchoGHubRamp_PimaTargets|FY2027
A29: =AG29 -> G_EchoGHubRamp_PimaTargets|FY2028 | B29: =Scenarios!A7 -> G_EchoGHubRamp_PimaTargets | C29: FY2028 | D29: =IF(Scenarios!D7=1,0, L29) -> 362 | E29: =IF(Scenarios!E7=1,0, M29) -> 341 | F29: =D29+E29 -> 703 | G29: =YearMap!B4 -> 5777.992 | H29: =YearMap!C4 -> 1264952.3 | I29: =YearMap!D4 -> 1456910 | J29: =1-BaselineCalc!$B$5 -> 0.993 | K29: =Scenarios!G7 -> 0 | L29: =BaselineCalc!$B$7 + ROUND(Scenarios!K7*Scenarios!F7,0) -> 362 | M29: =BaselineCalc!$B$8 + Scenarios!K7 - ROUND(Scenarios!K7*Scenarios!F7,0) -> 341 | N29: =(L29-D29) + (M29-E29) -> 0 | O29: =BaselineCalc!$B$23 * N29 -> 0 | P29: =YearMap!E4 -> 600 | Q29: =IF(Scenarios!N7="lease", YearMap!F4, YearMap!G4) -> 0.35 | R29: =IF(Scenarios!D7=1, Q29*H29, H29) -> 1264952.3 | S29: =IF(Scenarios!E7=1, Q29*I29, I29) -> 1456910 | T29: =IF(C29="FY2026", (Scenarios!D7+Scenarios!E7)*BaselineCalc!$B$22, 0) -> 0 | U29: =(R29+S29+G29*F29)*J29*(1-K29) -> 6736304.1 | V29: =O29*(G29+P29) -> 0 | W29: =U29+V29+T29 -> 6736304.1 | X29: =IF(F29+O29>0, W29/(F29+O29),"") -> 9582.2249 | Y29: =INDEX(YearMap!$I$2:$I$6, MATCH(C29, YearMap!$A$2:$A$6, 0)) -> 5215.5252 | Z29: =$W29-$Y29*$AC29 -> 3069789.9 | AA29: =IF($AC29>0, $Z29/$AC29, 0) -> 4366.6997 | AB29: =MAX(0, (MAX(0, $D29-BaselineCalc!$B$7) + MAX(0, $E29-BaselineCalc!$B$8))) -> 150 | AC29: =IF(LEFT($B29,2)="A_", $O29, IF(LEFT($B29,2)="B_", $M29+$O29, IF(LEFT($B29,2)="C_", $L29+$O29, $F29))) -> 703 | AD29: =$Y29*$AC29 -> 3666514.2 | AE29: =W29 - (1-Other_Parameters!$B$2)*$G29*$AB29*$J29*(1-$K29) -> 6219925 | AF29: =AD29-AE29 -> -2553410.8 | AG29: =B29&"|"&C29 -> G_EchoGHubRamp_PimaTargets|FY2028
A30: =AG30 -> G_EchoGHubRamp_PimaTargets|FY2029 | B30: =Scenarios!A7 -> G_EchoGHubRamp_PimaTargets | C30: FY2029 | D30: =IF(Scenarios!D7=1,0, L30) -> 362 | E30: =IF(Scenarios!E7=1,0, M30) -> 341 | F30: =D30+E30 -> 703 | G30: =YearMap!B5 -> 5922.4418 | H30: =YearMap!C5 -> 1296576.1 | I30: =YearMap!D5 -> 1493332.7 | J30: =1-BaselineCalc!$B$5 -> 0.993 | K30: =Scenarios!G7 -> 0 | L30: =BaselineCalc!$B$7 + ROUND(Scenarios!L7*Scenarios!F7,0) -> 362 | M30: =BaselineCalc!$B$8 + Scenarios!L7 - ROUND(Scenarios!L7*Scenarios!F7,0) -> 341 | N30: =(L30-D30) + (M30-E30) -> 0 | O30: =BaselineCalc!$B$23 * N30 -> 0 | P30: =YearMap!E5 -> 500 | Q30: =IF(Scenarios!N7="lease", YearMap!F5, YearMap!G5) -> 0.3 | R30: =IF(Scenarios!D7=1, Q30*H30, H30) -> 1296576.1 | S30: =IF(Scenarios!E7=1, Q30*I30, I30) -> 1493332.7 | T30: =IF(C30="FY2026", (Scenarios!D7+Scenarios!E7)*BaselineCalc!$B$22, 0) -> 0 | U30: =(R30+S30+G30*F30)*J30*(1-K30) -> 6904711.7 | V30: =O30*(G30+P30) -> 0 | W30: =U30+V30+T30 -> 6904711.7 | X30: =IF(F30+O30>0, W30/(F30+O30),"") -> 9821.7805 | Y30: =INDEX(YearMap!$I$2:$I$6, MATCH(C30, YearMap!$A$2:$A$6, 0)) -> 5319.8357 | Z30: =$W30-$Y30*$AC30 -> 3164867.2 | AA30: =IF($AC30>0, $Z30/$AC30, 0) -> 4501.9448 | AB30: =MAX(0, (MAX(0, $D30-BaselineCalc!$B$7) + MAX(0, $E30-BaselineCalc!$B$8))) -> 150 | AC30: =IF(LEFT($B30,2)="A_", $O30, IF(LEFT($B30,2)="B_", $M30+$O30, IF(LEFT($B30,2)="C_", $L30+$O30, $F30))) -> 703 | AD30: =$Y30*$AC30 -> 3739844.5 | AE30: =W30 - (1-Other_Parameters!$B$2)*$G30*$AB30*$J30*(1-$K30) -> 6375423.1 | AF30: =AD30-AE30 -> -2635578.6 | AG30: =B30&"|"&C30 -> G_EchoGHubRamp_PimaTargets|FY2029
A31: =AG31 -> G_EchoGHubRamp_PimaTargets|FY2030 | B31: =Scenarios!A7 -> G_EchoGHubRamp_PimaTargets | C31: FY2030 | D31: =IF(Scenarios!D7=1,0, L31) -> 362 | E31: =IF(Scenarios!E7=1,0, M31) -> 341 | F31: =D31+E31 -> 703 | G31: =YearMap!B6 -> 6070.5029 | H31: =YearMap!C6 -> 1328990.5 | I31: =YearMap!D6 -> 1530666.1 | J31: =1-BaselineCalc!$B$5 -> 0.993 | K31: =Scenarios!G7 -> 0 | L31: =BaselineCalc!$B$7 + ROUND(Scenarios!M7*Scenarios!F7,0) -> 362 | M31: =BaselineCalc!$B$8 + Scenarios!M7 - ROUND(Scenarios!M7*Scenarios!F7,0) -> 341 | N31: =(L31-D31) + (M31-E31) -> 0 | O31: =BaselineCalc!$B$23 * N31 -> 0 | P31: =YearMap!E6 -> 300 | Q31: =IF(Scenarios!N7="lease", YearMap!F6, YearMap!G6) -> 0.3 | R31: =IF(Scenarios!D7=1, Q31*H31, H31) -> 1328990.5 | S31: =IF(Scenarios!E7=1, Q31*I31, I31) -> 1530666.1 | T31: =IF(C31="FY2026", (Scenarios!D7+Scenarios!E7)*BaselineCalc!$B$22, 0) -> 0 | U31: =(R31+S31+G31*F31)*J31*(1-K31) -> 7077329.5 | V31: =O31*(G31+P31) -> 0 | W31: =U31+V31+T31 -> 7077329.5 | X31: =IF(F31+O31>0, W31/(F31+O31),"") -> 10067.325 | Y31: =INDEX(YearMap!$I$2:$I$6, MATCH(C31, YearMap!$A$2:$A$6, 0)) -> 5426.2324 | Z31: =$W31-$Y31*$AC31 -> 3262688.1 | AA31: =IF($AC31>0, $Z31/$AC31, 0) -> 4641.0926 | AB31: =MAX(0, (MAX(0, $D31-BaselineCalc!$B$7) + MAX(0, $E31-BaselineCalc!$B$8))) -> 150 | AC31: =IF(LEFT($B31,2)="A_", $O31, IF(LEFT($B31,2)="B_", $M31+$O31, IF(LEFT($B31,2)="C_", $L31+$O31, $F31))) -> 703 | AD31: =$Y31*$AC31 -> 3814641.4 | AE31: =W31 - (1-Other_Parameters!$B$2)*$G31*$AB31*$J31*(1-$K31) -> 6534808.7 | AF31: =AD31-AE31 -> -2720167.3 | AG31: =B31&"|"&C31 -> G_EchoGHubRamp_PimaTargets|FY2030
A32: =AG32 -> A_Repurpose_Both_lease|FY2026 | B32: =Scenarios!A8 -> A_Repurpose_Both_lease | C32: FY2026 | D32: =IF(Scenarios!D8=1,0, L32) -> 0 | E32: =IF(Scenarios!E8=1,0, M32) -> 0 | F32: =D32+E32 -> 0 | G32: =YearMap!B2 -> 5499.576 | H32: =YearMap!C2 -> 1203999.8 | I32: =YearMap!D2 -> 1386707.9 | J32: =1-BaselineCalc!$B$5 -> 0.993 | K32: =Scenarios!G8 -> 0 | L32: =BaselineCalc!$B$7 + ROUND(Scenarios!I8*Scenarios!F8,0) -> 257 | M32: =BaselineCalc!$B$8 + Scenarios!I8 - ROUND(Scenarios!I8*Scenarios!F8,0) -> 296 | N32: =(L32-D32) + (M32-E32) -> 553 | O32: =BaselineCalc!$B$23 * N32 -> 414.75 | P32: =YearMap!E2 -> 1000 | Q32: =IF(Scenarios!N8="lease", YearMap!F2, YearMap!G2) -> 0.4 | R32: =IF(Scenarios!D8=1, Q32*H32, H32) -> 481599.91 | S32: =IF(Scenarios!E8=1, Q32*I32, I32) -> 554683.16 | T32: =IF(C32="FY2026", (Scenarios!D8+Scenarios!E8)*BaselineCalc!$B$22, 0) -> 2400000 | U32: =(R32+S32+G32*F32)*J32*(1-K32) -> 1029029.1 | V32: =O32*(G32+P32) -> 2695699.1 | W32: =U32+V32+T32 -> 6124728.2 | X32: =IF(F32+O32>0, W32/(F32+O32),"") -> 14767.277 | Y32: =INDEX(YearMap!$I$2:$I$6, MATCH(C32, YearMap!$A$2:$A$6, 0)) -> 5013 | Z32: =$W32-$Y32*$AC32 -> 4045586.5 | AA32: =IF($AC32>0, $Z32/$AC32, 0) -> 9754.2772 | AB32: =MAX(0, (MAX(0, $D32-BaselineCalc!$B$7) + MAX(0, $E32-BaselineCalc!$B$8))) -> 0 | AC32: =IF(LEFT($B32,2)="A_", $O32, IF(LEFT($B32,2)="B_", $M32+$O32, IF(LEFT($B32,2)="C_", $L32+$O32, $F32))) -> 414.75 | AD32: =$Y32*$AC32 -> 2079141.8 | AE32: =W32 - (1-Other_Parameters!$B$2)*$G32*$AB32*$J32*(1-$K32) -> 6124728.2 | AF32: =AD32-AE32 -> -4045586.5 | AG32: =B32&"|"&C32 -> A_Repurpose_Both_lease|FY2026
A33: =AG33 -> A_Repurpose_Both_lease|FY2027 | B33: =Scenarios!A8 -> A_Repurpose_Both_lease | C33: FY2027 | D33: =IF(Scenarios!D8=1,0, L33) -> 0 | E33: =IF(Scenarios!E8=1,0, M33) -> 0 | F33: =D33+E33 -> 0 | G33: =YearMap!B3 -> 5637.0654 | H33: =YearMap!C3 -> 1234099.8 | I33: =YearMap!D3 -> 1421375.6 | J33: =1-BaselineCalc!$B$5 -> 0.993 | K33: =Scenarios!G8 -> 0 | L33: =BaselineCalc!$B$7 + ROUND(Scenarios!J8*Scenarios!F8,0) -> 257 | M33: =BaselineCalc!$B$8 + Scenarios!J8 - ROUND(Scenarios!J8*Scenarios!F8,0) -> 296 | N33: =(L33-D33) + (M33-E33) -> 553 | O33: =BaselineCalc!$B$23 * N33 -> 414.75 | P33: =YearMap!E3 -> 800 | Q33: =IF(Scenarios!N8="lease", YearMap!F3, YearMap!G3) -> 0.3 | R33: =IF(Scenarios!D8=1, Q33*H33, H33) -> 370229.93 | S33: =IF(Scenarios!E8=1, Q33*I33, I33) -> 426412.68 | T33: =IF(C33="FY2026", (Scenarios!D8+Scenarios!E8)*BaselineCalc!$B$22, 0) -> 0 | U33: =(R33+S33+G33*F33)*J33*(1-K33) -> 791066.11 | V33: =O33*(G33+P33) -> 2669772.9 | W33: =U33+V33+T33 -> 3460839 | X33: =IF(F33+O33>0, W33/(F33+O33),"") -> 8344.3978 | Y33: =INDEX(YearMap!$I$2:$I$6, MATCH(C33, YearMap!$A$2:$A$6, 0)) -> 5113.26 | Z33: =$W33-$Y33*$AC33 -> 1340114.4 | AA33: =IF($AC33>0, $Z33/$AC33, 0) -> 3231.1378 | AB33: =MAX(0, (MAX(0, $D33-BaselineCalc!$B$7) + MAX(0, $E33-BaselineCalc!$B$8))) -> 0 | AC33: =IF(LEFT($B33,2)="A_", $O33, IF(LEFT($B33,2)="B_", $M33+$O33, IF(LEFT($B33,2)="C_", $L33+$O33, $F33))) -> 414.75 | AD33: =$Y33*$AC33 -> 2120724.6 | AE33: =W33 - (1-Other_Parameters!$B$2)*$G33*$AB33*$J33*(1-$K33) -> 3460839 | AF33: =AD33-AE33 -> -1340114.4 | AG33: =B33&"|"&C33 -> A_Repurpose_Both_lease|FY2027
A34: =AG34 -> A_Repurpose_Both_lease|FY2028 | B34: =Scenarios!A8 -> A_Repurpose_Both_lease | C34: FY2028 | D34: =IF(Scenarios!D8=1,0, L34) -> 0 | E34: =IF(Scenarios!E8=1,0, M34) -> 0 | F34: =D34+E34 -> 0 | G34: =YearMap!B4 -> 5777.992 | H34: =YearMap!C4 -> 1264952.3 | I34: =YearMap!D4 -> 1456910 | J34: =1-BaselineCalc!$B$5 -> 0.993 | K34: =Scenarios!G8 -> 0 | L34: =BaselineCalc!$B$7 + ROUND(Scenarios!K8*Scenarios!F8,0) -> 257 | M34: =BaselineCalc!$B$8 + Scenarios!K8 - ROUND(Scenarios!K8*Scenarios!F8,0) -> 296 | N34: =(L34-D34) + (M34-E34) -> 553 | O34: =BaselineCalc!$B$23 * N34 -> 414.75 | P34: =YearMap!E4 -> 600 | Q34: =IF(Scenarios!N8="lease", YearMap!F4, YearMap!G4) -> 0.2 | R34: =IF(Scenarios!D8=1, Q34*H34, H34) -> 252990.45 | S34: =IF(Scenarios!E8=1, Q34*I34, I34) -> 291382 | T34: =IF(C34="FY2026", (Scenarios!D8+Scenarios!E8)*BaselineCalc!$B$22, 0) -> 0 | U34: =(R34+S34+G34*F34)*J34*(1-K34) -> 540561.84 | V34: =O34*(G34+P34) -> 2645272.2 | W34: =U34+V34+T34 -> 3185834 | X34: =IF(F34+O34>0, W34/(F34+O34),"") -> 7681.3358 | Y34: =INDEX(YearMap!$I$2:$I$6, MATCH(C34, YearMap!$A$2:$A$6, 0)) -> 5215.5252 | Z34: =$W34-$Y34*$AC34 -> 1022695 | AA34: =IF($AC34>0, $Z34/$AC34, 0) -> 2465.8106 | AB34: =MAX(0, (MAX(0, $D34-BaselineCalc!$B$7) + MAX(0, $E34-BaselineCalc!$B$8))) -> 0 | AC34: =IF(LEFT($B34,2)="A_", $O34, IF(LEFT($B34,2)="B_", $M34+$O34, IF(LEFT($B34,2)="C_", $L34+$O34, $F34))) -> 414.75 | AD34: =$Y34*$AC34 -> 2163139.1 | AE34: =W34 - (1-Other_Parameters!$B$2)*$G34*$AB34*$J34*(1-$K34) -> 3185834 | AF34: =AD34-AE34 -> -1022695 | AG34: =B34&"|"&C34 -> A_Repurpose_Both_lease|FY2028
A35: =AG35 -> A_Repurpose_Both_lease|FY2029 | B35: =Scenarios!A8 -> A_Repurpose_Both_lease | C35: FY2029 | D35: =IF(Scenarios!D8=1,0, L35) -> 0 | E35: =IF(Scenarios!E8=1,0, M35) -> 0 | F35: =D35+E35 -> 0 | G35: =YearMap!B5 -> 5922.4418 | H35: =YearMap!C5 -> 1296576.1 | I35: =YearMap!D5 -> 1493332.7 | J35: =1-BaselineCalc!$B$5 -> 0.993 | K35: =Scenarios!G8 -> 0 | L35: =BaselineCalc!$B$7 + ROUND(Scenarios!L8*Scenarios!F8,0) -> 257 | M35: =BaselineCalc!$B$8 + Scenarios!L8 - ROUND(Scenarios!L8*Scenarios!F8,0) -> 296 | N35: =(L35-D35) + (M35-E35) -> 553 | O35: =BaselineCalc!$B$23 * N35 -> 414.75 | P35: =YearMap!E5 -> 500 | Q35: =IF(Scenarios!N8="lease", YearMap!F5, YearMap!G5) -> 0.1 | R35: =IF(Scenarios!D8=1, Q35*H35, H35) -> 129657.61 | S35: =IF(Scenarios!E8=1, Q35*I35, I35) -> 149333.27 | T35: =IF(C35="FY2026", (Scenarios!D8+Scenarios!E8)*BaselineCalc!$B$22, 0) -> 0 | U35: =(R35+S35+G35*F35)*J35*(1-K35) -> 277037.94 | V35: =O35*(G35+P35) -> 2663707.8 | W35: =U35+V35+T35 -> 2940745.7 | X35: =IF(F35+O35>0, W35/(F35+O35),"") -> 7090.4055 | Y35: =INDEX(YearMap!$I$2:$I$6, MATCH(C35, YearMap!$A$2:$A$6, 0)) -> 5319.8357 | Z35: =$W35-$Y35*$AC35 -> 734343.84 | AA35: =IF($AC35>0, $Z35/$AC35, 0) -> 1770.5698 | AB35: =MAX(0, (MAX(0, $D35-BaselineCalc!$B$7) + MAX(0, $E35-BaselineCalc!$B$8))) -> 0 | AC35: =IF(LEFT($B35,2)="A_", $O35, IF(LEFT($B35,2)="B_", $M35+$O35, IF(LEFT($B35,2)="C_", $L35+$O35, $F35))) -> 414.75 | AD35: =$Y35*$AC35 -> 2206401.9 | AE35: =W35 - (1-Other_Parameters!$B$2)*$G35*$AB35*$J35*(1-$K35) -> 2940745.7 | AF35: =AD35-AE35 -> -734343.84 | AG35: =B35&"|"&C35 -> A_Repurpose_Both_lease|FY2029
A36: =AG36 -> A_Repurpose_Both_lease|FY2030 | B36: =Scenarios!A8 -> A_Repurpose_Both_lease | C36: FY2030 | D36: =IF(Scenarios!D8=1,0, L36) -> 0 | E36: =IF(Scenarios!E8=1,0, M36) -> 0 | F36: =D36+E36 -> 0 | G36: =YearMap!B6 -> 6070.5029 | H36: =YearMap!C6 -> 1328990.5 | I36: =YearMap!D6 -> 1530666.1 | J36: =1-BaselineCalc!$B$5 -> 0.993 | K36: =Scenarios!G8 -> 0 | L36: =BaselineCalc!$B$7 + ROUND(Scenarios!M8*Scenarios!F8,0) -> 257 | M36: =BaselineCalc!$B$8 + Scenarios!M8 - ROUND(Scenarios!M8*Scenarios!F8,0) -> 296 | N36: =(L36-D36) + (M36-E36) -> 553 | O36: =BaselineCalc!$B$23 * N36 -> 414.75 | P36: =YearMap!E6 -> 300 | Q36: =IF(Scenarios!N8="lease", YearMap!F6, YearMap!G6) -> 0.1 | R36: =IF(Scenarios!D8=1, Q36*H36, H36) -> 132899.05 | S36: =IF(Scenarios!E8=1, Q36*I36, I36) -> 153066.61 | T36: =IF(C36="FY2026", (Scenarios!D8+Scenarios!E8)*BaselineCalc!$B$22, 0) -> 0 | U36: =(R36+S36+G36*F36)*J36*(1-K36) -> 283963.89 | V36: =O36*(G36+P36) -> 2642166.1 | W36: =U36+V36+T36 -> 2926130 | X36: =IF(F36+O36>0, W36/(F36+O36),"") -> 7055.1657 | Y36: =INDEX(YearMap!$I$2:$I$6, MATCH(C36, YearMap!$A$2:$A$6, 0)) -> 5426.2324 | Z36: =$W36-$Y36*$AC36 -> 675600.07 | AA36: =IF($AC36>0, $Z36/$AC36, 0) -> 1628.9333 | AB36: =MAX(0, (MAX(0, $D36-BaselineCalc!$B$7) + MAX(0, $E36-BaselineCalc!$B$8))) -> 0 | AC36: =IF(LEFT($B36,2)="A_", $O36, IF(LEFT($B36,2)="B_", $M36+$O36, IF(LEFT($B36,2)="C_", $L36+$O36, $F36))) -> 414.75 | AD36: =$Y36*$AC36 -> 2250529.9 | AE36: =W36 - (1-Other_Parameters!$B$2)*$G36*$AB36*$J36*(1-$K36) -> 2926130 | AF36: =AD36-AE36 -> -675600.07 | AG36: =B36&"|"&C36 -> A_Repurpose_Both_lease|FY2030
A37: =AG37 -> A_Repurpose_Both_ops|FY2026 | B37: =Scenarios!A9 -> A_Repurpose_Both_ops | C37: FY2026 | D37: =IF(Scenarios!D9=1,0, L37) -> 0 | E37: =IF(Scenarios!E9=1,0, M37) -> 0 | F37: =D37+E37 -> 0 | G37: =YearMap!B2 -> 5499.576 | H37: =YearMap!C2 -> 1203999.8 | I37: =YearMap!D2 -> 1386707.9 | J37: =1-BaselineCalc!$B$5 -> 0.993 | K37: =Scenarios!G9 -> 0 | L37: =BaselineCalc!$B$7 + ROUND(Scenarios!I9*Scenarios!F9,0) -> 257 | M37: =BaselineCalc!$B$8 + Scenarios!I9 - ROUND(Scenarios!I9*Scenarios!F9,0) -> 296 | N37: =(L37-D37) + (M37-E37) -> 553 | O37: =BaselineCalc!$B$23 * N37 -> 414.75 | P37: =YearMap!E2 -> 1000 | Q37: =IF(Scenarios!N9="lease", YearMap!F2, YearMap!G2) -> 0.5 | R37: =IF(Scenarios!D9=1, Q37*H37, H37) -> 601999.88 | S37: =IF(Scenarios!E9=1, Q37*I37, I37) -> 693353.95 | T37: =IF(C37="FY2026", (Scenarios!D9+Scenarios!E9)*BaselineCalc!$B$22, 0) -> 2400000 | U37: =(R37+S37+G37*F37)*J37*(1-K37) -> 1286286.4 | V37: =O37*(G37+P37) -> 2695699.1 | W37: =U37+V37+T37 -> 6381985.5 | X37: =IF(F37+O37>0, W37/(F37+O37),"") -> 15387.548 | Y37: =INDEX(YearMap!$I$2:$I$6, MATCH(C37, YearMap!$A$2:$A$6, 0)) -> 5013 | Z37: =$W37-$Y37*$AC37 -> 4302843.8 | AA37: =IF($AC37>0, $Z37/$AC37, 0) -> 10374.548 | AB37: =MAX(0, (MAX(0, $D37-BaselineCalc!$B$7) + MAX(0, $E37-BaselineCalc!$B$8))) -> 0 | AC37: =IF(LEFT($B37,2)="A_", $O37, IF(LEFT($B37,2)="B_", $M37+$O37, IF(LEFT($B37,2)="C_", $L37+$O37, $F37))) -> 414.75 | AD37: =$Y37*$AC37 -> 2079141.8 | AE37: =W37 - (1-Other_Parameters!$B$2)*$G37*$AB37*$J37*(1-$K37) -> 6381985.5 | AF37: =AD37-AE37 -> -4302843.8 | AG37: =B37&"|"&C37 -> A_Repurpose_Both_ops|FY2026
A38: =AG38 -> A_Repurpose_Both_ops|FY2027 | B38: =Scenarios!A9 -> A_Repurpose_Both_ops | C38: FY2027 | D38: =IF(Scenarios!D9=1,0, L38) -> 0 | E38: =IF(Scenarios!E9=1,0, M38) -> 0 | F38: =D38+E38 -> 0 | G38: =YearMap!B3 -> 5637.0654 | H38: =YearMap!C3 -> 1234099.8 | I38: =YearMap!D3 -> 1421375.6 | J38: =1-BaselineCalc!$B$5 -> 0.993 | K38: =Scenarios!G9 -> 0 | L38: =BaselineCalc!$B$7 + ROUND(Scenarios!J9*Scenarios!F9,0) -> 257 | M38: =BaselineCalc!$B$8 + Scenarios!J9 - ROUND(Scenarios!J9*Scenarios!F9,0) -> 296 | N38: =(L38-D38) + (M38-E38) -> 553 | O38: =BaselineCalc!$B$23 * N38 -> 414.75 | P38: =YearMap!E3 -> 800 | Q38: =IF(Scenarios!N9="lease", YearMap!F3, YearMap!G3) -> 0.4 | R38: =IF(Scenarios!D9=1, Q38*H38, H38) -> 493639.9 | S38: =IF(Scenarios!E9=1, Q38*I38, I38) -> 568550.24 | T38: =IF(C38="FY2026", (Scenarios!D9+Scenarios!E9)*BaselineCalc!$B$22, 0) -> 0 | U38: =(R38+S38+G38*F38)*J38*(1-K38) -> 1054754.8 | V38: =O38*(G38+P38) -> 2669772.9 | W38: =U38+V38+T38 -> 3724527.7 | X38: =IF(F38+O38>0, W38/(F38+O38),"") -> 8980.1753 | Y38: =INDEX(YearMap!$I$2:$I$6, MATCH(C38, YearMap!$A$2:$A$6, 0)) -> 5113.26 | Z38: =$W38-$Y38*$AC38 -> 1603803.1 | AA38: =IF($AC38>0, $Z38/$AC38, 0) -> 3866.9153 | AB38: =MAX(0, (MAX(0, $D38-BaselineCalc!$B$7) + MAX(0, $E38-BaselineCalc!$B$8))) -> 0 | AC38: =IF(LEFT($B38,2)="A_", $O38, IF(LEFT($B38,2)="B_", $M38+$O38, IF(LEFT($B38,2)="C_", $L38+$O38, $F38))) -> 414.75 | AD38: =$Y38*$AC38 -> 2120724.6 | AE38: =W38 - (1-Other_Parameters!$B$2)*$G38*$AB38*$J38*(1-$K38) -> 3724527.7 | AF38: =AD38-AE38 -> -1603803.1 | AG38: =B38&"|"&C38 -> A_Repurpose_Both_ops|FY2027
A39: =AG39 -> A_Repurpose_Both_ops|FY2028 | B39: =Scenarios!A9 -> A_Repurpose_Both_ops | C39: FY2028 | D39: =IF(Scenarios!D9=1,0, L39) -> 0 | E39: =IF(Scenarios!E9=1,0, M39) -> 0 | F39: =D39+E39 -> 0 | G39: =YearMap!B4 -> 5777.992 | H39: =YearMap!C4 -> 1264952.3 | I39: =YearMap!D4 -> 1456910 | J39: =1-BaselineCalc!$B$5 -> 0.993 | K39: =Scenarios!G9 -> 0 | L39: =BaselineCalc!$B$7 + ROUND(Scenarios!K9*Scenarios!F9,0) -> 257 | M39: =BaselineCalc!$B$8 + Scenarios!K9 - ROUND(Scenarios!K9*Scenarios!F9,0) -> 296 | N39: =(L39-D39) + (M39-E39) -> 553 | O39: =BaselineCalc!$B$23 * N39 -> 414.75 | P39: =YearMap!E4 -> 600 | Q39: =IF(Scenarios!N9="lease", YearMap!F4, YearMap!G4) -> 0.35 | R39: =IF(Scenarios!D9=1, Q39*H39, H39) -> 442733.29 | S39: =IF(Scenarios!E9=1, Q39*I39, I39) -> 509918.5 | T39: =IF(C39="FY2026", (Scenarios!D9+Scenarios!E9)*BaselineCalc!$B$22, 0) -> 0 | U39: =(R39+S39+G39*F39)*J39*(1-K39) -> 945983.22 | V39: =O39*(G39+P39) -> 2645272.2 | W39: =U39+V39+T39 -> 3591255.4 | X39: =IF(F39+O39>0, W39/(F39+O39),"") -> 8658.8437 | Y39: =INDEX(YearMap!$I$2:$I$6, MATCH(C39, YearMap!$A$2:$A$6, 0)) -> 5215.5252 | Z39: =$W39-$Y39*$AC39 -> 1428116.3 | AA39: =IF($AC39>0, $Z39/$AC39, 0) -> 3443.3185 | AB39: =MAX(0, (MAX(0, $D39-BaselineCalc!$B$7) + MAX(0, $E39-BaselineCalc!$B$8))) -> 0 | AC39: =IF(LEFT($B39,2)="A_", $O39, IF(LEFT($B39,2)="B_", $M39+$O39, IF(LEFT($B39,2)="C_", $L39+$O39, $F39))) -> 414.75 | AD39: =$Y39*$AC39 -> 2163139.1 | AE39: =W39 - (1-Other_Parameters!$B$2)*$G39*$AB39*$J39*(1-$K39) -> 3591255.4 | AF39: =AD39-AE39 -> -1428116.3 | AG39: =B39&"|"&C39 -> A_Repurpose_Both_ops|FY2028
A40: =AG40 -> A_Repurpose_Both_ops|FY2029 | B40: =Scenarios!A9 -> A_Repurpose_Both_ops | C40: FY2029 | D40: =IF(Scenarios!D9=1,0, L40) -> 0 | E40: =IF(Scenarios!E9=1,0, M40) -> 0 | F40: =D40+E40 -> 0 | G40: =YearMap!B5 -> 5922.4418 | H40: =YearMap!C5 -> 1296576.1 | I40: =YearMap!D5 -> 1493332.7 | J40: =1-BaselineCalc!$B$5 -> 0.993 | K40: =Scenarios!G9 -> 0 | L40: =BaselineCalc!$B$7 + ROUND(Scenarios!L9*Scenarios!F9,0) -> 257 | M40: =BaselineCalc!$B$8 + Scenarios!L9 - ROUND(Scenarios!L9*Scenarios!F9,0) -> 296 | N40: =(L40-D40) + (M40-E40) -> 553 | O40: =BaselineCalc!$B$23 * N40 -> 414.75 | P40: =YearMap!E5 -> 500 | Q40: =IF(Scenarios!N9="lease", YearMap!F5, YearMap!G5) -> 0.3 | R40: =IF(Scenarios!D9=1, Q40*H40, H40) -> 388972.82 | S40: =IF(Scenarios!E9=1, Q40*I40, I40) -> 447999.82 | T40: =IF(C40="FY2026", (Scenarios!D9+Scenarios!E9)*BaselineCalc!$B$22, 0) -> 0 | U40: =(R40+S40+G40*F40)*J40*(1-K40) -> 831113.83 | V40: =O40*(G40+P40) -> 2663707.8 | W40: =U40+V40+T40 -> 3494821.6 | X40: =IF(F40+O40>0, W40/(F40+O40),"") -> 8426.3329 | Y40: =INDEX(YearMap!$I$2:$I$6, MATCH(C40, YearMap!$A$2:$A$6, 0)) -> 5319.8357 | Z40: =$W40-$Y40*$AC40 -> 1288419.7 | AA40: =IF($AC40>0, $Z40/$AC40, 0) -> 3106.4972 | AB40: =MAX(0, (MAX(0, $D40-BaselineCalc!$B$7) + MAX(0, $E40-BaselineCalc!$B$8))) -> 0 | AC40: =IF(LEFT($B40,2)="A_", $O40, IF(LEFT($B40,2)="B_", $M40+$O40, IF(LEFT($B40,2)="C_", $L40+$O40, $F40))) -> 414.75 | AD40: =$Y40*$AC40 -> 2206401.9 | AE40: =W40 - (1-Other_Parameters!$B$2)*$G40*$AB40*$J40*(1-$K40) -> 3494821.6 | AF40: =AD40-AE40 -> -1288419.7 | AG40: =B40&"|"&C40 -> A_Repurpose_Both_ops|FY2029
A41: =AG41 -> A_Repurpose_Both_ops|FY2030 | B41: =Scenarios!A9 -> A_Repurpose_Both_ops | C41: FY2030 | D41: =IF(Scenarios!D9=1,0, L41) -> 0 | E41: =IF(Scenarios!E9=1,0, M41) -> 0 | F41: =D41+E41 -> 0 | G41: =YearMap!B6 -> 6070.5029 | H41: =YearMap!C6 -> 1328990.5 | I41: =YearMap!D6 -> 1530666.1 | J41: =1-BaselineCalc!$B$5 -> 0.993 | K41: =Scenarios!G9 -> 0 | L41: =BaselineCalc!$B$7 + ROUND(Scenarios!M9*Scenarios!F9,0) -> 257 | M41: =BaselineCalc!$B$8 + Scenarios!M9 - ROUND(Scenarios!M9*Scenarios!F9,0) -> 296 | N41: =(L41-D41) + (M41-E41) -> 553 | O41: =BaselineCalc!$B$23 * N41 -> 414.75 | P41: =YearMap!E6 -> 300 | Q41: =IF(Scenarios!N9="lease", YearMap!F6, YearMap!G6) -> 0.3 | R41: =IF(Scenarios!D9=1, Q41*H41, H41) -> 398697.14 | S41: =IF(Scenarios!E9=1, Q41*I41, I41) -> 459199.82 | T41: =IF(C41="FY2026", (Scenarios!D9+Scenarios!E9)*BaselineCalc!$B$22, 0) -> 0 | U41: =(R41+S41+G41*F41)*J41*(1-K41) -> 851891.68 | V41: =O41*(G41+P41) -> 2642166.1 | W41: =U41+V41+T41 -> 3494057.7 | X41: =IF(F41+O41>0, W41/(F41+O41),"") -> 8424.4913 | Y41: =INDEX(YearMap!$I$2:$I$6, MATCH(C41, YearMap!$A$2:$A$6, 0)) -> 5426.2324 | Z41: =$W41-$Y41*$AC41 -> 1243527.9 | AA41: =IF($AC41>0, $Z41/$AC41, 0) -> 2998.2588 | AB41: =MAX(0, (MAX(0, $D41-BaselineCalc!$B$7) + MAX(0, $E41-BaselineCalc!$B$8))) -> 0 | AC41: =IF(LEFT($B41,2)="A_", $O41, IF(LEFT($B41,2)="B_", $M41+$O41, IF(LEFT($B41,2)="C_", $L41+$O41, $F41))) -> 414.75 | AD41: =$Y41*$AC41 -> 2250529.9 | AE41: =W41 - (1-Other_Parameters!$B$2)*$G41*$AB41*$J41*(1-$K41) -> 3494057.7 | AF41: =AD41-AE41 -> -1243527.9 | AG41: =B41&"|"&C41 -> A_Repurpose_Both_ops|FY2030
A42: =AG42 -> B_Repurpose_Echo_lease_PimaTargets|FY2026 | B42: =Scenarios!A10 -> B_Repurpose_Echo_lease_PimaTargets | C42: FY2026 | D42: =IF(Scenarios!D10=1,0, L42) -> 0 | E42: =IF(Scenarios!E10=1,0, M42) -> 296 | F42: =D42+E42 -> 296 | G42: =YearMap!B2 -> 5499.576 | H42: =YearMap!C2 -> 1203999.8 | I42: =YearMap!D2 -> 1386707.9 | J42: =1-BaselineCalc!$B$5 -> 0.993 | K42: =Scenarios!G10 -> 0 | L42: =BaselineCalc!$B$7 + ROUND(Scenarios!I10*Scenarios!F10,0) -> 257 | M42: =BaselineCalc!$B$8 + Scenarios!I10 - ROUND(Scenarios!I10*Scenarios!F10,0) -> 296 | N42: =(L42-D42) + (M42-E42) -> 257 | O42: =BaselineCalc!$B$23 * N42 -> 192.75 | P42: =YearMap!E2 -> 1000 | Q42: =IF(Scenarios!N10="lease", YearMap!F2, YearMap!G2) -> 0.4 | R42: =IF(Scenarios!D10=1, Q42*H42, H42) -> 481599.91 | S42: =IF(Scenarios!E10=1, Q42*I42, I42) -> 1386707.9 | T42: =IF(C42="FY2026", (Scenarios!D10+Scenarios!E10)*BaselineCalc!$B$22, 0) -> 1200000 | U42: =(R42+S42+G42*F42)*J42*(1-K42) -> 3471709 | V42: =O42*(G42+P42) -> 1252793.3 | W42: =U42+V42+T42 -> 5924502.3 | X42: =IF(F42+O42>0, W42/(F42+O42),"") -> 12121.744 | Y42: =INDEX(YearMap!$I$2:$I$6, MATCH(C42, YearMap!$A$2:$A$6, 0)) -> 5013 | Z42: =$W42-$Y42*$AC42 -> 3474398.6 | AA42: =IF($AC42>0, $Z42/$AC42, 0) -> 7108.7438 | AB42: =MAX(0, (MAX(0, $D42-BaselineCalc!$B$7) + MAX(0, $E42-BaselineCalc!$B$8))) -> 0 | AC42: =IF(LEFT($B42,2)="A_", $O42, IF(LEFT($B42,2)="B_", $M42+$O42, IF(LEFT($B42,2)="C_", $L42+$O42, $F42))) -> 488.75 | AD42: =$Y42*$AC42 -> 2450103.8 | AE42: =W42 - (1-Other_Parameters!$B$2)*$G42*$AB42*$J42*(1-$K42) -> 5924502.3 | AF42: =AD42-AE42 -> -3474398.6 | AG42: =B42&"|"&C42 -> B_Repurpose_Echo_lease_PimaTargets|FY2026
A43: =AG43 -> B_Repurpose_Echo_lease_PimaTargets|FY2027 | B43: =Scenarios!A10 -> B_Repurpose_Echo_lease_PimaTargets | C43: FY2027 | D43: =IF(Scenarios!D10=1,0, L43) -> 0 | E43: =IF(Scenarios!E10=1,0, M43) -> 296 | F43: =D43+E43 -> 296 | G43: =YearMap!B3 -> 5637.0654 | H43: =YearMap!C3 -> 1234099.8 | I43: =YearMap!D3 -> 1421375.6 | J43: =1-BaselineCalc!$B$5 -> 0.993 | K43: =Scenarios!G10 -> 0 | L43: =BaselineCalc!$B$7 + ROUND(Scenarios!J10*Scenarios!F10,0) -> 257 | M43: =BaselineCalc!$B$8 + Scenarios!J10 - ROUND(Scenarios!J10*Scenarios!F10,0) -> 296 | N43: =(L43-D43) + (M43-E43) -> 257 | O43: =BaselineCalc!$B$23 * N43 -> 192.75 | P43: =YearMap!E3 -> 800 | Q43: =IF(Scenarios!N10="lease", YearMap!F3, YearMap!G3) -> 0.3 | R43: =IF(Scenarios!D10=1, Q43*H43, H43) -> 370229.93 | S43: =IF(Scenarios!E10=1, Q43*I43, I43) -> 1421375.6 | T43: =IF(C43="FY2026", (Scenarios!D10+Scenarios!E10)*BaselineCalc!$B$22, 0) -> 0 | U43: =(R43+S43+G43*F43)*J43*(1-K43) -> 3435955.7 | V43: =O43*(G43+P43) -> 1240744.4 | W43: =U43+V43+T43 -> 4676700 | X43: =IF(F43+O43>0, W43/(F43+O43),"") -> 9568.6957 | Y43: =INDEX(YearMap!$I$2:$I$6, MATCH(C43, YearMap!$A$2:$A$6, 0)) -> 5113.26 | Z43: =$W43-$Y43*$AC43 -> 2177594.2 | AA43: =IF($AC43>0, $Z43/$AC43, 0) -> 4455.4357 | AB43: =MAX(0, (MAX(0, $D43-BaselineCalc!$B$7) + MAX(0, $E43-BaselineCalc!$B$8))) -> 0 | AC43: =IF(LEFT($B43,2)="A_", $O43, IF(LEFT($B43,2)="B_", $M43+$O43, IF(LEFT($B43,2)="C_", $L43+$O43, $F43))) -> 488.75 | AD43: =$Y43*$AC43 -> 2499105.8 | AE43: =W43 - (1-Other_Parameters!$B$2)*$G43*$AB43*$J43*(1-$K43) -> 4676700 | AF43: =AD43-AE43 -> -2177594.2 | AG43: =B43&"|"&C43 -> B_Repurpose_Echo_lease_PimaTargets|FY2027
A44: =AG44 -> B_Repurpose_Echo_lease_PimaTargets|FY2028 | B44: =Scenarios!A10 -> B_Repurpose_Echo_lease_PimaTargets | C44: FY2028 | D44: =IF(Scenarios!D10=1,0, L44) -> 0 | E44: =IF(Scenarios!E10=1,0, M44) -> 296 | F44: =D44+E44 -> 296 | G44: =YearMap!B4 -> 5777.992 | H44: =YearMap!C4 -> 1264952.3 | I44: =YearMap!D4 -> 1456910 | J44: =1-BaselineCalc!$B$5 -> 0.993 | K44: =Scenarios!G10 -> 0 | L44: =BaselineCalc!$B$7 + ROUND(Scenarios!K10*Scenarios!F10,0) -> 257 | M44: =BaselineCalc!$B$8 + Scenarios!K10 - ROUND(Scenarios!K10*Scenarios!F10,0) -> 296 | N44: =(L44-D44) + (M44-E44) -> 257 | O44: =BaselineCalc!$B$23 * N44 -> 192.75 | P44: =YearMap!E4 -> 600 | Q44: =IF(Scenarios!N10="lease", YearMap!F4, YearMap!G4) -> 0.2 | R44: =IF(Scenarios!D10=1, Q44*H44, H44) -> 252990.45 | S44: =IF(Scenarios!E10=1, Q44*I44, I44) -> 1456910 | T44: =IF(C44="FY2026", (Scenarios!D10+Scenarios!E10)*BaselineCalc!$B$22, 0) -> 0 | U44: =(R44+S44+G44*F44)*J44*(1-K44) -> 3396244.8 | V44: =O44*(G44+P44) -> 1229358 | W44: =U44+V44+T44 -> 4625602.7 | X44: =IF(F44+O44>0, W44/(F44+O44),"") -> 9464.1488 | Y44: =INDEX(YearMap!$I$2:$I$6, MATCH(C44, YearMap!$A$2:$A$6, 0)) -> 5215.5252 | Z44: =$W44-$Y44*$AC44 -> 2076514.8 | AA44: =IF($AC44>0, $Z44/$AC44, 0) -> 4248.6236 | AB44: =MAX(0, (MAX(0, $D44-BaselineCalc!$B$7) + MAX(0, $E44-BaselineCalc!$B$8))) -> 0 | AC44: =IF(LEFT($B44,2)="A_", $O44, IF(LEFT($B44,2)="B_", $M44+$O44, IF(LEFT($B44,2)="C_", $L44+$O44, $F44))) -> 488.75 | AD44: =$Y44*$AC44 -> 2549087.9 | AE44: =W44 - (1-Other_Parameters!$B$2)*$G44*$AB44*$J44*(1-$K44) -> 4625602.7 | AF44: =AD44-AE44 -> -2076514.8 | AG44: =B44&"|"&C44 -> B_Repurpose_Echo_lease_PimaTargets|FY2028
A45: =AG45 -> B_Repurpose_Echo_lease_PimaTargets|FY2029 | B45: =Scenarios!A10 -> B_Repurpose_Echo_lease_PimaTargets | C45: FY2029 | D45: =IF(Scenarios!D10=1,0, L45) -> 0 | E45: =IF(Scenarios!E10=1,0, M45) -> 296 | F45: =D45+E45 -> 296 | G45: =YearMap!B5 -> 5922.4418 | H45: =YearMap!C5 -> 1296576.1 | I45: =YearMap!D5 -> 1493332.7 | J45: =1-BaselineCalc!$B$5 -> 0.993 | K45: =Scenarios!G10 -> 0 | L45: =BaselineCalc!$B$7 + ROUND(Scenarios!L10*Scenarios!F10,0) -> 257 | M45: =BaselineCalc!$B$8 + Scenarios!L10 - ROUND(Scenarios!L10*Scenarios!F10,0) -> 296 | N45: =(L45-D45) + (M45-E45) -> 257 | O45: =BaselineCalc!$B$23 * N45 -> 192.75 | P45: =YearMap!E5 -> 500 | Q45: =IF(Scenarios!N10="lease", YearMap!F5, YearMap!G5) -> 0.1 | R45: =IF(Scenarios!D10=1, Q45*H45, H45) -> 129657.61 | S45: =IF(Scenarios!E10=1, Q45*I45, I45) -> 1493332.7 | T45: =IF(C45="FY2026", (Scenarios!D10+Scenarios!E10)*BaselineCalc!$B$22, 0) -> 0 | U45: =(R45+S45+G45*F45)*J45*(1-K45) -> 3352400.9 | V45: =O45*(G45+P45) -> 1237925.7 | W45: =U45+V45+T45 -> 4590326.6 | X45: =IF(F45+O45>0, W45/(F45+O45),"") -> 9391.9725 | Y45: =INDEX(YearMap!$I$2:$I$6, MATCH(C45, YearMap!$A$2:$A$6, 0)) -> 5319.8357 | Z45: =$W45-$Y45*$AC45 -> 1990256.9 | AA45: =IF($AC45>0, $Z45/$AC45, 0) -> 4072.1368 | AB45: =MAX(0, (MAX(0, $D45-BaselineCalc!$B$7) + MAX(0, $E45-BaselineCalc!$B$8))) -> 0 | AC45: =IF(LEFT($B45,2)="A_", $O45, IF(LEFT($B45,2)="B_", $M45+$O45, IF(LEFT($B45,2)="C_", $L45+$O45, $F45))) -> 488.75 | AD45: =$Y45*$AC45 -> 2600069.7 | AE45: =W45 - (1-Other_Parameters!$B$2)*$G45*$AB45*$J45*(1-$K45) -> 4590326.6 | AF45: =AD45-AE45 -> -1990256.9 | AG45: =B45&"|"&C45 -> B_Repurpose_Echo_lease_PimaTargets|FY2029
A46: =AG46 -> B_Repurpose_Echo_lease_PimaTargets|FY2030 | B46: =Scenarios!A10 -> B_Repurpose_Echo_lease_PimaTargets | C46: FY2030 | D46: =IF(Scenarios!D10=1,0, L46) -> 0 | E46: =IF(Scenarios!E10=1,0, M46) -> 296 | F46: =D46+E46 -> 296 | G46: =YearMap!B6 -> 6070.5029 | H46: =YearMap!C6 -> 1328990.5 | I46: =YearMap!D6 -> 1530666.1 | J46: =1-BaselineCalc!$B$5 -> 0.993 | K46: =Scenarios!G10 -> 0 | L46: =BaselineCalc!$B$7 + ROUND(Scenarios!M10*Scenarios!F10,0) -> 257 | M46: =BaselineCalc!$B$8 + Scenarios!M10 - ROUND(Scenarios!M10*Scenarios!F10,0) -> 296 | N46: =(L46-D46) + (M46-E46) -> 257 | O46: =BaselineCalc!$B$23 * N46 -> 192.75 | P46: =YearMap!E6 -> 300 | Q46: =IF(Scenarios!N10="lease", YearMap!F6, YearMap!G6) -> 0.1 | R46: =IF(Scenarios!D10=1, Q46*H46, H46) -> 132899.05 | S46: =IF(Scenarios!E10=1, Q46*I46, I46) -> 1530666.1 | T46: =IF(C46="FY2026", (Scenarios!D10+Scenarios!E10)*BaselineCalc!$B$22, 0) -> 0 | U46: =(R46+S46+G46*F46)*J46*(1-K46) -> 3436210.9 | V46: =O46*(G46+P46) -> 1227914.4 | W46: =U46+V46+T46 -> 4664125.4 | X46: =IF(F46+O46>0, W46/(F46+O46),"") -> 9542.9675 | Y46: =INDEX(YearMap!$I$2:$I$6, MATCH(C46, YearMap!$A$2:$A$6, 0)) -> 5426.2324 | Z46: =$W46-$Y46*$AC46 -> 2012054.3 | AA46: =IF($AC46>0, $Z46/$AC46, 0) -> 4116.7351 | AB46: =MAX(0, (MAX(0, $D46-BaselineCalc!$B$7) + MAX(0, $E46-BaselineCalc!$B$8))) -> 0 | AC46: =IF(LEFT($B46,2)="A_", $O46, IF(LEFT($B46,2)="B_", $M46+$O46, IF(LEFT($B46,2)="C_", $L46+$O46, $F46))) -> 488.75 | AD46: =$Y46*$AC46 -> 2652071.1 | AE46: =W46 - (1-Other_Parameters!$B$2)*$G46*$AB46*$J46*(1-$K46) -> 4664125.4 | AF46: =AD46-AE46 -> -2012054.3 | AG46: =B46&"|"&C46 -> B_Repurpose_Echo_lease_PimaTargets|FY2030
A47: =AG47 -> B_Repurpose_Echo_ops_PimaTargets|FY2026 | B47: =Scenarios!A11 -> B_Repurpose_Echo_ops_PimaTargets | C47: FY2026 | D47: =IF(Scenarios!D11=1,0, L47) -> 0 | E47: =IF(Scenarios!E11=1,0, M47) -> 446 | F47: =D47+E47 -> 446 | G47: =YearMap!B2 -> 5499.576 | H47: =YearMap!C2 -> 1203999.8 | I47: =YearMap!D2 -> 1386707.9 | J47: =1-BaselineCalc!$B$5 -> 0.993 | K47: =Scenarios!G11 -> 0 | L47: =BaselineCalc!$B$7 + ROUND(Scenarios!I11*Scenarios!F11,0) -> 257 | M47: =BaselineCalc!$B$8 + Scenarios!I11 - ROUND(Scenarios!I11*Scenarios!F11,0) -> 446 | N47: =(L47-D47) + (M47-E47) -> 257 | O47: =BaselineCalc!$B$23 * N47 -> 192.75 | P47: =YearMap!E2 -> 1000 | Q47: =IF(Scenarios!N11="lease", YearMap!F2, YearMap!G2) -> 0.5 | R47: =IF(Scenarios!D11=1, Q47*H47, H47) -> 601999.88 | S47: =IF(Scenarios!E11=1, Q47*I47, I47) -> 1386707.9 | T47: =IF(C47="FY2026", (Scenarios!D11+Scenarios!E11)*BaselineCalc!$B$22, 0) -> 1200000 | U47: =(R47+S47+G47*F47)*J47*(1-K47) -> 4410428.1 | V47: =O47*(G47+P47) -> 1252793.3 | W47: =U47+V47+T47 -> 6863221.3 | X47: =IF(F47+O47>0, W47/(F47+O47),"") -> 10744.769 | Y47: =INDEX(YearMap!$I$2:$I$6, MATCH(C47, YearMap!$A$2:$A$6, 0)) -> 5013 | Z47: =$W47-$Y47*$AC47 -> 3661167.6 | AA47: =IF($AC47>0, $Z47/$AC47, 0) -> 5731.7692 | AB47: =MAX(0, (MAX(0, $D47-BaselineCalc!$B$7) + MAX(0, $E47-BaselineCalc!$B$8))) -> 150 | AC47: =IF(LEFT($B47,2)="A_", $O47, IF(LEFT($B47,2)="B_", $M47+$O47, IF(LEFT($B47,2)="C_", $L47+$O47, $F47))) -> 638.75 | AD47: =$Y47*$AC47 -> 3202053.8 | AE47: =W47 - (1-Other_Parameters!$B$2)*$G47*$AB47*$J47*(1-$K47) -> 6371724.2 | AF47: =AD47-AE47 -> -3169670.5 | AG47: =B47&"|"&C47 -> B_Repurpose_Echo_ops_PimaTargets|FY2026
A48: =AG48 -> B_Repurpose_Echo_ops_PimaTargets|FY2027 | B48: =Scenarios!A11 -> B_Repurpose_Echo_ops_PimaTargets | C48: FY2027 | D48: =IF(Scenarios!D11=1,0, L48) -> 0 | E48: =IF(Scenarios!E11=1,0, M48) -> 446 | F48: =D48+E48 -> 446 | G48: =YearMap!B3 -> 5637.0654 | H48: =YearMap!C3 -> 1234099.8 | I48: =YearMap!D3 -> 1421375.6 | J48: =1-BaselineCalc!$B$5 -> 0.993 | K48: =Scenarios!G11 -> 0 | L48: =BaselineCalc!$B$7 + ROUND(Scenarios!J11*Scenarios!F11,0) -> 257 | M48: =BaselineCalc!$B$8 + Scenarios!J11 - ROUND(Scenarios!J11*Scenarios!F11,0) -> 446 | N48: =(L48-D48) + (M48-E48) -> 257 | O48: =BaselineCalc!$B$23 * N48 -> 192.75 | P48: =YearMap!E3 -> 800 | Q48: =IF(Scenarios!N11="lease", YearMap!F3, YearMap!G3) -> 0.4 | R48: =IF(Scenarios!D11=1, Q48*H48, H48) -> 493639.9 | S48: =IF(Scenarios!E11=1, Q48*I48, I48) -> 1421375.6 | T48: =IF(C48="FY2026", (Scenarios!D11+Scenarios!E11)*BaselineCalc!$B$22, 0) -> 0 | U48: =(R48+S48+G48*F48)*J48*(1-K48) -> 4398142.6 | V48: =O48*(G48+P48) -> 1240744.4 | W48: =U48+V48+T48 -> 5638887 | X48: =IF(F48+O48>0, W48/(F48+O48),"") -> 8828.0031 | Y48: =INDEX(YearMap!$I$2:$I$6, MATCH(C48, YearMap!$A$2:$A$6, 0)) -> 5113.26 | Z48: =$W48-$Y48*$AC48 -> 2372792.2 | AA48: =IF($AC48>0, $Z48/$AC48, 0) -> 3714.7431 | AB48: =MAX(0, (MAX(0, $D48-BaselineCalc!$B$7) + MAX(0, $E48-BaselineCalc!$B$8))) -> 150 | AC48: =IF(LEFT($B48,2)="A_", $O48, IF(LEFT($B48,2)="B_", $M48+$O48, IF(LEFT($B48,2)="C_", $L48+$O48, $F48))) -> 638.75 | AD48: =$Y48*$AC48 -> 3266094.8 | AE48: =W48 - (1-Other_Parameters!$B$2)*$G48*$AB48*$J48*(1-$K48) -> 5135102.5 | AF48: =AD48-AE48 -> -1869007.6 | AG48: =B48&"|"&C48 -> B_Repurpose_Echo_ops_PimaTargets|FY2027
A49: =AG49 -> B_Repurpose_Echo_ops_PimaTargets|FY2028 | B49: =Scenarios!A11 -> B_Repurpose_Echo_ops_PimaTargets | C49: FY2028 | D49: =IF(Scenarios!D11=1,0, L49) -> 0 | E49: =IF(Scenarios!E11=1,0, M49) -> 446 | F49: =D49+E49 -> 446 | G49: =YearMap!B4 -> 5777.992 | H49: =YearMap!C4 -> 1264952.3 | I49: =YearMap!D4 -> 1456910 | J49: =1-BaselineCalc!$B$5 -> 0.993 | K49: =Scenarios!G11 -> 0 | L49: =BaselineCalc!$B$7 + ROUND(Scenarios!K11*Scenarios!F11,0) -> 257 | M49: =BaselineCalc!$B$8 + Scenarios!K11 - ROUND(Scenarios!K11*Scenarios!F11,0) -> 446 | N49: =(L49-D49) + (M49-E49) -> 257 | O49: =BaselineCalc!$B$23 * N49 -> 192.75 | P49: =YearMap!E4 -> 600 | Q49: =IF(Scenarios!N11="lease", YearMap!F4, YearMap!G4) -> 0.35 | R49: =IF(Scenarios!D11=1, Q49*H49, H49) -> 442733.29 | S49: =IF(Scenarios!E11=1, Q49*I49, I49) -> 1456910 | T49: =IF(C49="FY2026", (Scenarios!D11+Scenarios!E11)*BaselineCalc!$B$22, 0) -> 0 | U49: =(R49+S49+G49*F49)*J49*(1-K49) -> 4445291.3 | V49: =O49*(G49+P49) -> 1229358 | W49: =U49+V49+T49 -> 5674649.3 | X49: =IF(F49+O49>0, W49/(F49+O49),"") -> 8883.9911 | Y49: =INDEX(YearMap!$I$2:$I$6, MATCH(C49, YearMap!$A$2:$A$6, 0)) -> 5215.5252 | Z49: =$W49-$Y49*$AC49 -> 2343232.6 | AA49: =IF($AC49>0, $Z49/$AC49, 0) -> 3668.4659 | AB49: =MAX(0, (MAX(0, $D49-BaselineCalc!$B$7) + MAX(0, $E49-BaselineCalc!$B$8))) -> 150 | AC49: =IF(LEFT($B49,2)="A_", $O49, IF(LEFT($B49,2)="B_", $M49+$O49, IF(LEFT($B49,2)="C_", $L49+$O49, $F49))) -> 638.75 | AD49: =$Y49*$AC49 -> 3331416.7 | AE49: =W49 - (1-Other_Parameters!$B$2)*$G49*$AB49*$J49*(1-$K49) -> 5158270.2 | AF49: =AD49-AE49 -> -1826853.4 | AG49: =B49&"|"&C49 -> B_Repurpose_Echo_ops_PimaTargets|FY2028
A50: =AG50 -> B_Repurpose_Echo_ops_PimaTargets|FY2029 | B50: =Scenarios!A11 -> B_Repurpose_Echo_ops_PimaTargets | C50: FY2029 | D50: =IF(Scenarios!D11=1,0, L50) -> 0 | E50: =IF(Scenarios!E11=1,0, M50) -> 446 | F50: =D50+E50 -> 446 | G50: =YearMap!B5 -> 5922.4418 | H50: =YearMap!C5 -> 1296576.1 | I50: =YearMap!D5 -> 1493332.7 | J50: =1-BaselineCalc!$B$5 -> 0.993 | K50: =Scenarios!G11 -> 0 | L50: =BaselineCalc!$B$7 + ROUND(Scenarios!L11*Scenarios!F11,0) -> 257 | M50: =BaselineCalc!$B$8 + Scenarios!L11 - ROUND(Scenarios!L11*Scenarios!F11,0) -> 446 | N50: =(L50-D50) + (M50-E50) -> 257 | O50: =BaselineCalc!$B$23 * N50 -> 192.75 | P50: =YearMap!E5 -> 500 | Q50: =IF(Scenarios!N11="lease", YearMap!F5, YearMap!G5) -> 0.3 | R50: =IF(Scenarios!D11=1, Q50*H50, H50) -> 388972.82 | S50: =IF(Scenarios!E11=1, Q50*I50, I50) -> 1493332.7 | T50: =IF(C50="FY2026", (Scenarios!D11+Scenarios!E11)*BaselineCalc!$B$22, 0) -> 0 | U50: =(R50+S50+G50*F50)*J50*(1-K50) -> 4492048.6 | V50: =O50*(G50+P50) -> 1237925.7 | W50: =U50+V50+T50 -> 5729974.3 | X50: =IF(F50+O50>0, W50/(F50+O50),"") -> 8970.6055 | Y50: =INDEX(YearMap!$I$2:$I$6, MATCH(C50, YearMap!$A$2:$A$6, 0)) -> 5319.8357 | Z50: =$W50-$Y50*$AC50 -> 2331929.2 | AA50: =IF($AC50>0, $Z50/$AC50, 0) -> 3650.7698 | AB50: =MAX(0, (MAX(0, $D50-BaselineCalc!$B$7) + MAX(0, $E50-BaselineCalc!$B$8))) -> 150 | AC50: =IF(LEFT($B50,2)="A_", $O50, IF(LEFT($B50,2)="B_", $M50+$O50, IF(LEFT($B50,2)="C_", $L50+$O50, $F50))) -> 638.75 | AD50: =$Y50*$AC50 -> 3398045.1 | AE50: =W50 - (1-Other_Parameters!$B$2)*$G50*$AB50*$J50*(1-$K50) -> 5200685.7 | AF50: =AD50-AE50 -> -1802640.6 | AG50: =B50&"|"&C50 -> B_Repurpose_Echo_ops_PimaTargets|FY2029
A51: =AG51 -> B_Repurpose_Echo_ops_PimaTargets|FY2030 | B51: =Scenarios!A11 -> B_Repurpose_Echo_ops_PimaTargets | C51: FY2030 | D51: =IF(Scenarios!D11=1,0, L51) -> 0 | E51: =IF(Scenarios!E11=1,0, M51) -> 446 | F51: =D51+E51 -> 446 | G51: =YearMap!B6 -> 6070.5029 | H51: =YearMap!C6 -> 1328990.5 | I51: =YearMap!D6 -> 1530666.1 | J51: =1-BaselineCalc!$B$5 -> 0.993 | K51: =Scenarios!G11 -> 0 | L51: =BaselineCalc!$B$7 + ROUND(Scenarios!M11*Scenarios!F11,0) -> 257 | M51: =BaselineCalc!$B$8 + Scenarios!M11 - ROUND(Scenarios!M11*Scenarios!F11,0) -> 446 | N51: =(L51-D51) + (M51-E51) -> 257 | O51: =BaselineCalc!$B$23 * N51 -> 192.75 | P51: =YearMap!E6 -> 300 | Q51: =IF(Scenarios!N11="lease", YearMap!F6, YearMap!G6) -> 0.3 | R51: =IF(Scenarios!D11=1, Q51*H51, H51) -> 398697.14 | S51: =IF(Scenarios!E11=1, Q51*I51, I51) -> 1530666.1 | T51: =IF(C51="FY2026", (Scenarios!D11+Scenarios!E11)*BaselineCalc!$B$22, 0) -> 0 | U51: =(R51+S51+G51*F51)*J51*(1-K51) -> 4604349.8 | V51: =O51*(G51+P51) -> 1227914.4 | W51: =U51+V51+T51 -> 5832264.3 | X51: =IF(F51+O51>0, W51/(F51+O51),"") -> 9130.7464 | Y51: =INDEX(YearMap!$I$2:$I$6, MATCH(C51, YearMap!$A$2:$A$6, 0)) -> 5426.2324 | Z51: =$W51-$Y51*$AC51 -> 2366258.3 | AA51: =IF($AC51>0, $Z51/$AC51, 0) -> 3704.514 | AB51: =MAX(0, (MAX(0, $D51-BaselineCalc!$B$7) + MAX(0, $E51-BaselineCalc!$B$8))) -> 150 | AC51: =IF(LEFT($B51,2)="A_", $O51, IF(LEFT($B51,2)="B_", $M51+$O51, IF(LEFT($B51,2)="C_", $L51+$O51, $F51))) -> 638.75 | AD51: =$Y51*$AC51 -> 3466006 | AE51: =W51 - (1-Other_Parameters!$B$2)*$G51*$AB51*$J51*(1-$K51) -> 5289743.4 | AF51: =AD51-AE51 -> -1823737.5 | AG51: =B51&"|"&C51 -> B_Repurpose_Echo_ops_PimaTargets|FY2030
A52: =AG52 -> C_Repurpose_Pima_lease_EchoGHub_EchoTargets|FY2026 | B52: =Scenarios!A12 -> C_Repurpose_Pima_lease_EchoGHub_EchoTargets | C52: FY2026 | D52: =IF(Scenarios!D12=1,0, L52) -> 257 | E52: =IF(Scenarios!E12=1,0, M52) -> 0 | F52: =D52+E52 -> 257 | G52: =YearMap!B2 -> 5499.576 | H52: =YearMap!C2 -> 1203999.8 | I52: =YearMap!D2 -> 1386707.9 | J52: =1-BaselineCalc!$B$5 -> 0.993 | K52: =Scenarios!G12 -> 0 | L52: =BaselineCalc!$B$7 + ROUND(Scenarios!I12*Scenarios!F12,0) -> 257 | M52: =BaselineCalc!$B$8 + Scenarios!I12 - ROUND(Scenarios!I12*Scenarios!F12,0) -> 296 | N52: =(L52-D52) + (M52-E52) -> 296 | O52: =BaselineCalc!$B$23 * N52 -> 222 | P52: =YearMap!E2 -> 1000 | Q52: =IF(Scenarios!N12="lease", YearMap!F2, YearMap!G2) -> 0.4 | R52: =IF(Scenarios!D12=1, Q52*H52, H52) -> 1203999.8 | S52: =IF(Scenarios!E12=1, Q52*I52, I52) -> 554683.16 | T52: =IF(C52="FY2026", (Scenarios!D12+Scenarios!E12)*BaselineCalc!$B$22, 0) -> 1200000 | U52: =(R52+S52+G52*F52)*J52*(1-K52) -> 3149869.4 | V52: =O52*(G52+P52) -> 1442905.9 | W52: =U52+V52+T52 -> 5792775.3 | X52: =IF(F52+O52>0, W52/(F52+O52),"") -> 12093.477 | Y52: =INDEX(YearMap!$I$2:$I$6, MATCH(C52, YearMap!$A$2:$A$6, 0)) -> 5013 | Z52: =$W52-$Y52*$AC52 -> 3391548.3 | AA52: =IF($AC52>0, $Z52/$AC52, 0) -> 7080.4767 | AB52: =MAX(0, (MAX(0, $D52-BaselineCalc!$B$7) + MAX(0, $E52-BaselineCalc!$B$8))) -> 0 | AC52: =IF(LEFT($B52,2)="A_", $O52, IF(LEFT($B52,2)="B_", $M52+$O52, IF(LEFT($B52,2)="C_", $L52+$O52, $F52))) -> 479 | AD52: =$Y52*$AC52 -> 2401227 | AE52: =W52 - (1-Other_Parameters!$B$2)*$G52*$AB52*$J52*(1-$K52) -> 5792775.3 | AF52: =AD52-AE52 -> -3391548.3 | AG52: =B52&"|"&C52 -> C_Repurpose_Pima_lease_EchoGHub_EchoTargets|FY2026
A53: =AG53 -> C_Repurpose_Pima_lease_EchoGHub_EchoTargets|FY2027 | B53: =Scenarios!A12 -> C_Repurpose_Pima_lease_EchoGHub_EchoTargets | C53: FY2027 | D53: =IF(Scenarios!D12=1,0, L53) -> 257 | E53: =IF(Scenarios!E12=1,0, M53) -> 0 | F53: =D53+E53 -> 257 | G53: =YearMap!B3 -> 5637.0654 | H53: =YearMap!C3 -> 1234099.8 | I53: =YearMap!D3 -> 1421375.6 | J53: =1-BaselineCalc!$B$5 -> 0.993 | K53: =Scenarios!G12 -> 0 | L53: =BaselineCalc!$B$7 + ROUND(Scenarios!J12*Scenarios!F12,0) -> 257 | M53: =BaselineCalc!$B$8 + Scenarios!J12 - ROUND(Scenarios!J12*Scenarios!F12,0) -> 296 | N53: =(L53-D53) + (M53-E53) -> 296 | O53: =BaselineCalc!$B$23 * N53 -> 222 | P53: =YearMap!E3 -> 800 | Q53: =IF(Scenarios!N12="lease", YearMap!F3, YearMap!G3) -> 0.3 | R53: =IF(Scenarios!D12=1, Q53*H53, H53) -> 1234099.8 | S53: =IF(Scenarios!E12=1, Q53*I53, I53) -> 426412.68 | T53: =IF(C53="FY2026", (Scenarios!D12+Scenarios!E12)*BaselineCalc!$B$22, 0) -> 0 | U53: =(R53+S53+G53*F53)*J53*(1-K53) -> 3087473.6 | V53: =O53*(G53+P53) -> 1429028.5 | W53: =U53+V53+T53 -> 4516502.1 | X53: =IF(F53+O53>0, W53/(F53+O53),"") -> 9429.0232 | Y53: =INDEX(YearMap!$I$2:$I$6, MATCH(C53, YearMap!$A$2:$A$6, 0)) -> 5113.26 | Z53: =$W53-$Y53*$AC53 -> 2067250.6 | AA53: =IF($AC53>0, $Z53/$AC53, 0) -> 4315.7632 | AB53: =MAX(0, (MAX(0, $D53-BaselineCalc!$B$7) + MAX(0, $E53-BaselineCalc!$B$8))) -> 0 | AC53: =IF(LEFT($B53,2)="A_", $O53, IF(LEFT($B53,2)="B_", $M53+$O53, IF(LEFT($B53,2)="C_", $L53+$O53, $F53))) -> 479 | AD53: =$Y53*$AC53 -> 2449251.5 | AE53: =W53 - (1-Other_Parameters!$B$2)*$G53*$AB53*$J53*(1-$K53) -> 4516502.1 | AF53: =AD53-AE53 -> -2067250.6 | AG53: =B53&"|"&C53 -> C_Repurpose_Pima_lease_EchoGHub_EchoTargets|FY2027
A54: =AG54 -> C_Repurpose_Pima_lease_EchoGHub_EchoTargets|FY2028 | B54: =Scenarios!A12 -> C_Repurpose_Pima_lease_EchoGHub_EchoTargets | C54: FY2028 | D54: =IF(Scenarios!D12=1,0, L54) -> 257 | E54: =IF(Scenarios!E12=1,0, M54) -> 0 | F54: =D54+E54 -> 257 | G54: =YearMap!B4 -> 5777.992 | H54: =YearMap!C4 -> 1264952.3 | I54: =YearMap!D4 -> 1456910 | J54: =1-BaselineCalc!$B$5 -> 0.993 | K54: =Scenarios!G12 -> 0 | L54: =BaselineCalc!$B$7 + ROUND(Scenarios!K12*Scenarios!F12,0) -> 257 | M54: =BaselineCalc!$B$8 + Scenarios!K12 - ROUND(Scenarios!K12*Scenarios!F12,0) -> 296 | N54: =(L54-D54) + (M54-E54) -> 296 | O54: =BaselineCalc!$B$23 * N54 -> 222 | P54: =YearMap!E4 -> 600 | Q54: =IF(Scenarios!N12="lease", YearMap!F4, YearMap!G4) -> 0.2 | R54: =IF(Scenarios!D12=1, Q54*H54, H54) -> 1264952.3 | S54: =IF(Scenarios!E12=1, Q54*I54, I54) -> 291382 | T54: =IF(C54="FY2026", (Scenarios!D12+Scenarios!E12)*BaselineCalc!$B$22, 0) -> 0 | U54: =(R54+S54+G54*F54)*J54*(1-K54) -> 3019989.3 | V54: =O54*(G54+P54) -> 1415914.2 | W54: =U54+V54+T54 -> 4435903.5 | X54: =IF(F54+O54>0, W54/(F54+O54),"") -> 9260.7589 | Y54: =INDEX(YearMap!$I$2:$I$6, MATCH(C54, YearMap!$A$2:$A$6, 0)) -> 5215.5252 | Z54: =$W54-$Y54*$AC54 -> 1937666.9 | AA54: =IF($AC54>0, $Z54/$AC54, 0) -> 4045.2337 | AB54: =MAX(0, (MAX(0, $D54-BaselineCalc!$B$7) + MAX(0, $E54-BaselineCalc!$B$8))) -> 0 | AC54: =IF(LEFT($B54,2)="A_", $O54, IF(LEFT($B54,2)="B_", $M54+$O54, IF(LEFT($B54,2)="C_", $L54+$O54, $F54))) -> 479 | AD54: =$Y54*$AC54 -> 2498236.6 | AE54: =W54 - (1-Other_Parameters!$B$2)*$G54*$AB54*$J54*(1-$K54) -> 4435903.5 | AF54: =AD54-AE54 -> -1937666.9 | AG54: =B54&"|"&C54 -> C_Repurpose_Pima_lease_EchoGHub_EchoTargets|FY2028
A55: =AG55 -> C_Repurpose_Pima_lease_EchoGHub_EchoTargets|FY2029 | B55: =Scenarios!A12 -> C_Repurpose_Pima_lease_EchoGHub_EchoTargets | C55: FY2029 | D55: =IF(Scenarios!D12=1,0, L55) -> 257 | E55: =IF(Scenarios!E12=1,0, M55) -> 0 | F55: =D55+E55 -> 257 | G55: =YearMap!B5 -> 5922.4418 | H55: =YearMap!C5 -> 1296576.1 | I55: =YearMap!D5 -> 1493332.7 | J55: =1-BaselineCalc!$B$5 -> 0.993 | K55: =Scenarios!G12 -> 0 | L55: =BaselineCalc!$B$7 + ROUND(Scenarios!L12*Scenarios!F12,0) -> 257 | M55: =BaselineCalc!$B$8 + Scenarios!L12 - ROUND(Scenarios!L12*Scenarios!F12,0) -> 296 | N55: =(L55-D55) + (M55-E55) -> 296 | O55: =BaselineCalc!$B$23 * N55 -> 222 | P55: =YearMap!E5 -> 500 | Q55: =IF(Scenarios!N12="lease", YearMap!F5, YearMap!G5) -> 0.1 | R55: =IF(Scenarios!D12=1, Q55*H55, H55) -> 1296576.1 | S55: =IF(Scenarios!E12=1, Q55*I55, I55) -> 149333.27 | T55: =IF(C55="FY2026", (Scenarios!D12+Scenarios!E12)*BaselineCalc!$B$22, 0) -> 0 | U55: =(R55+S55+G55*F55)*J55*(1-K55) -> 2947201.1 | V55: =O55*(G55+P55) -> 1425782.1 | W55: =U55+V55+T55 -> 4372983.1 | X55: =IF(F55+O55>0, W55/(F55+O55),"") -> 9129.4011 | Y55: =INDEX(YearMap!$I$2:$I$6, MATCH(C55, YearMap!$A$2:$A$6, 0)) -> 5319.8357 | Z55: =$W55-$Y55*$AC55 -> 1824781.8 | AA55: =IF($AC55>0, $Z55/$AC55, 0) -> 3809.5654 | AB55: =MAX(0, (MAX(0, $D55-BaselineCalc!$B$7) + MAX(0, $E55-BaselineCalc!$B$8))) -> 0 | AC55: =IF(LEFT($B55,2)="A_", $O55, IF(LEFT($B55,2)="B_", $M55+$O55, IF(LEFT($B55,2)="C_", $L55+$O55, $F55))) -> 479 | AD55: =$Y55*$AC55 -> 2548201.3 | AE55: =W55 - (1-Other_Parameters!$B$2)*$G55*$AB55*$J55*(1-$K55) -> 4372983.1 | AF55: =AD55-AE55 -> -1824781.8 | AG55: =B55&"|"&C55 -> C_Repurpose_Pima_lease_EchoGHub_EchoTargets|FY2029
A56: =AG56 -> C_Repurpose_Pima_lease_EchoGHub_EchoTargets|FY2030 | B56: =Scenarios!A12 -> C_Repurpose_Pima_lease_EchoGHub_EchoTargets | C56: FY2030 | D56: =IF(Scenarios!D12=1,0, L56) -> 257 | E56: =IF(Scenarios!E12=1,0, M56) -> 0 | F56: =D56+E56 -> 257 | G56: =YearMap!B6 -> 6070.5029 | H56: =YearMap!C6 -> 1328990.5 | I56: =YearMap!D6 -> 1530666.1 | J56: =1-BaselineCalc!$B$5 -> 0.993 | K56: =Scenarios!G12 -> 0 | L56: =BaselineCalc!$B$7 + ROUND(Scenarios!M12*Scenarios!F12,0) -> 257 | M56: =BaselineCalc!$B$8 + Scenarios!M12 - ROUND(Scenarios!M12*Scenarios!F12,0) -> 296 | N56: =(L56-D56) + (M56-E56) -> 296 | O56: =BaselineCalc!$B$23 * N56 -> 222 | P56: =YearMap!E6 -> 300 | Q56: =IF(Scenarios!N12="lease", YearMap!F6, YearMap!G6) -> 0.1 | R56: =IF(Scenarios!D12=1, Q56*H56, H56) -> 1328990.5 | S56: =IF(Scenarios!E12=1, Q56*I56, I56) -> 153066.61 | T56: =IF(C56="FY2026", (Scenarios!D12+Scenarios!E12)*BaselineCalc!$B$22, 0) -> 0 | U56: =(R56+S56+G56*F56)*J56*(1-K56) -> 3020881.1 | V56: =O56*(G56+P56) -> 1414251.6 | W56: =U56+V56+T56 -> 4435132.7 | X56: =IF(F56+O56>0, W56/(F56+O56),"") -> 9259.1497 | Y56: =INDEX(YearMap!$I$2:$I$6, MATCH(C56, YearMap!$A$2:$A$6, 0)) -> 5426.2324 | Z56: =$W56-$Y56*$AC56 -> 1835967.4 | AA56: =IF($AC56>0, $Z56/$AC56, 0) -> 3832.9173 | AB56: =MAX(0, (MAX(0, $D56-BaselineCalc!$B$7) + MAX(0, $E56-BaselineCalc!$B$8))) -> 0 | AC56: =IF(LEFT($B56,2)="A_", $O56, IF(LEFT($B56,2)="B_", $M56+$O56, IF(LEFT($B56,2)="C_", $L56+$O56, $F56))) -> 479 | AD56: =$Y56*$AC56 -> 2599165.3 | AE56: =W56 - (1-Other_Parameters!$B$2)*$G56*$AB56*$J56*(1-$K56) -> 4435132.7 | AF56: =AD56-AE56 -> -1835967.4 | AG56: =B56&"|"&C56 -> C_Repurpose_Pima_lease_EchoGHub_EchoTargets|FY2030
A57: =AG57 -> C_Repurpose_Pima_ops_EchoGHub_EchoTargets|FY2026 | B57: =Scenarios!A13 -> C_Repurpose_Pima_ops_EchoGHub_EchoTargets | C57: FY2026 | D57: =IF(Scenarios!D13=1,0, L57) -> 457 | E57: =IF(Scenarios!E13=1,0, M57) -> 0 | F57: =D57+E57 -> 457 | G57: =YearMap!B2 -> 5499.576 | H57: =YearMap!C2 -> 1203999.8 | I57: =YearMap!D2 -> 1386707.9 | J57: =1-BaselineCalc!$B$5 -> 0.993 | K57: =Scenarios!G13 -> 0 | L57: =BaselineCalc!$B$7 + ROUND(Scenarios!I13*Scenarios!F13,0) -> 457 | M57: =BaselineCalc!$B$8 + Scenarios!I13 - ROUND(Scenarios!I13*Scenarios!F13,0) -> 296 | N57: =(L57-D57) + (M57-E57) -> 296 | O57: =BaselineCalc!$B$23 * N57 -> 222 | P57: =YearMap!E2 -> 1000 | Q57: =IF(Scenarios!N13="lease", YearMap!F2, YearMap!G2) -> 0.5 | R57: =IF(Scenarios!D13=1, Q57*H57, H57) -> 1203999.8 | S57: =IF(Scenarios!E13=1, Q57*I57, I57) -> 693353.95 | T57: =IF(C57="FY2026", (Scenarios!D13+Scenarios!E13)*BaselineCalc!$B$22, 0) -> 1200000 | U57: =(R57+S57+G57*F57)*J57*(1-K57) -> 4379785.3 | V57: =O57*(G57+P57) -> 1442905.9 | W57: =U57+V57+T57 -> 7022691.2 | X57: =IF(F57+O57>0, W57/(F57+O57),"") -> 10342.697 | Y57: =INDEX(YearMap!$I$2:$I$6, MATCH(C57, YearMap!$A$2:$A$6, 0)) -> 5013 | Z57: =$W57-$Y57*$AC57 -> 3618864.2 | AA57: =IF($AC57>0, $Z57/$AC57, 0) -> 5329.6969 | AB57: =MAX(0, (MAX(0, $D57-BaselineCalc!$B$7) + MAX(0, $E57-BaselineCalc!$B$8))) -> 200 | AC57: =IF(LEFT($B57,2)="A_", $O57, IF(LEFT($B57,2)="B_", $M57+$O57, IF(LEFT($B57,2)="C_", $L57+$O57, $F57))) -> 679 | AD57: =$Y57*$AC57 -> 3403827 | AE57: =W57 - (1-Other_Parameters!$B$2)*$G57*$AB57*$J57*(1-$K57) -> 6367361.7 | AF57: =AD57-AE57 -> -2963534.7 | AG57: =B57&"|"&C57 -> C_Repurpose_Pima_ops_EchoGHub_EchoTargets|FY2026
A58: =AG58 -> C_Repurpose_Pima_ops_EchoGHub_EchoTargets|FY2027 | B58: =Scenarios!A13 -> C_Repurpose_Pima_ops_EchoGHub_EchoTargets | C58: FY2027 | D58: =IF(Scenarios!D13=1,0, L58) -> 457 | E58: =IF(Scenarios!E13=1,0, M58) -> 0 | F58: =D58+E58 -> 457 | G58: =YearMap!B3 -> 5637.0654 | H58: =YearMap!C3 -> 1234099.8 | I58: =YearMap!D3 -> 1421375.6 | J58: =1-BaselineCalc!$B$5 -> 0.993 | K58: =Scenarios!G13 -> 0 | L58: =BaselineCalc!$B$7 + ROUND(Scenarios!J13*Scenarios!F13,0) -> 457 | M58: =BaselineCalc!$B$8 + Scenarios!J13 - ROUND(Scenarios!J13*Scenarios!F13,0) -> 296 | N58: =(L58-D58) + (M58-E58) -> 296 | O58: =BaselineCalc!$B$23 * N58 -> 222 | P58: =YearMap!E3 -> 800 | Q58: =IF(Scenarios!N13="lease", YearMap!F3, YearMap!G3) -> 0.4 | R58: =IF(Scenarios!D13=1, Q58*H58, H58) -> 1234099.8 | S58: =IF(Scenarios!E13=1, Q58*I58, I58) -> 568550.24 | T58: =IF(C58="FY2026", (Scenarios!D13+Scenarios!E13)*BaselineCalc!$B$22, 0) -> 0 | U58: =(R58+S58+G58*F58)*J58*(1-K58) -> 4348137.4 | V58: =O58*(G58+P58) -> 1429028.5 | W58: =U58+V58+T58 -> 5777165.9 | X58: =IF(F58+O58>0, W58/(F58+O58),"") -> 8508.3445 | Y58: =INDEX(YearMap!$I$2:$I$6, MATCH(C58, YearMap!$A$2:$A$6, 0)) -> 5113.26 | Z58: =$W58-$Y58*$AC58 -> 2305262.3 | AA58: =IF($AC58>0, $Z58/$AC58, 0) -> 3395.0845 | AB58: =MAX(0, (MAX(0, $D58-BaselineCalc!$B$7) + MAX(0, $E58-BaselineCalc!$B$8))) -> 200 | AC58: =IF(LEFT($B58,2)="A_", $O58, IF(LEFT($B58,2)="B_", $M58+$O58, IF(LEFT($B58,2)="C_", $L58+$O58, $F58))) -> 679 | AD58: =$Y58*$AC58 -> 3471903.5 | AE58: =W58 - (1-Other_Parameters!$B$2)*$G58*$AB58*$J58*(1-$K58) -> 5105453.2 | AF58: =AD58-AE58 -> -1633549.6 | AG58: =B58&"|"&C58 -> C_Repurpose_Pima_ops_EchoGHub_EchoTargets|FY2027
A59: =AG59 -> C_Repurpose_Pima_ops_EchoGHub_EchoTargets|FY2028 | B59: =Scenarios!A13 -> C_Repurpose_Pima_ops_EchoGHub_EchoTargets | C59: FY2028 | D59: =IF(Scenarios!D13=1,0, L59) -> 457 | E59: =IF(Scenarios!E13=1,0, M59) -> 0 | F59: =D59+E59 -> 457 | G59: =YearMap!B4 -> 5777.992 | H59: =YearMap!C4 -> 1264952.3 | I59: =YearMap!D4 -> 1456910 | J59: =1-BaselineCalc!$B$5 -> 0.993 | K59: =Scenarios!G13 -> 0 | L59: =BaselineCalc!$B$7 + ROUND(Scenarios!K13*Scenarios!F13,0) -> 457 | M59: =BaselineCalc!$B$8 + Scenarios!K13 - ROUND(Scenarios!K13*Scenarios!F13,0) -> 296 | N59: =(L59-D59) + (M59-E59) -> 296 | O59: =BaselineCalc!$B$23 * N59 -> 222 | P59: =YearMap!E4 -> 600 | Q59: =IF(Scenarios!N13="lease", YearMap!F4, YearMap!G4) -> 0.35 | R59: =IF(Scenarios!D13=1, Q59*H59, H59) -> 1264952.3 | S59: =IF(Scenarios!E13=1, Q59*I59, I59) -> 509918.5 | T59: =IF(C59="FY2026", (Scenarios!D13+Scenarios!E13)*BaselineCalc!$B$22, 0) -> 0 | U59: =(R59+S59+G59*F59)*J59*(1-K59) -> 4384505.2 | V59: =O59*(G59+P59) -> 1415914.2 | W59: =U59+V59+T59 -> 5800419.5 | X59: =IF(F59+O59>0, W59/(F59+O59),"") -> 8542.5912 | Y59: =INDEX(YearMap!$I$2:$I$6, MATCH(C59, YearMap!$A$2:$A$6, 0)) -> 5215.5252 | Z59: =$W59-$Y59*$AC59 -> 2259077.8 | AA59: =IF($AC59>0, $Z59/$AC59, 0) -> 3327.066 | AB59: =MAX(0, (MAX(0, $D59-BaselineCalc!$B$7) + MAX(0, $E59-BaselineCalc!$B$8))) -> 200 | AC59: =IF(LEFT($B59,2)="A_", $O59, IF(LEFT($B59,2)="B_", $M59+$O59, IF(LEFT($B59,2)="C_", $L59+$O59, $F59))) -> 679 | AD59: =$Y59*$AC59 -> 3541341.6 | AE59: =W59 - (1-Other_Parameters!$B$2)*$G59*$AB59*$J59*(1-$K59) -> 5111913.9 | AF59: =AD59-AE59 -> -1570572.3 | AG59: =B59&"|"&C59 -> C_Repurpose_Pima_ops_EchoGHub_EchoTargets|FY2028
A60: =AG60 -> C_Repurpose_Pima_ops_EchoGHub_EchoTargets|FY2029 | B60: =Scenarios!A13 -> C_Repurpose_Pima_ops_EchoGHub_EchoTargets | C60: FY2029 | D60: =IF(Scenarios!D13=1,0, L60) -> 457 | E60: =IF(Scenarios!E13=1,0, M60) -> 0 | F60: =D60+E60 -> 457 | G60: =YearMap!B5 -> 5922.4418 | H60: =YearMap!C5 -> 1296576.1 | I60: =YearMap!D5 -> 1493332.7 | J60: =1-BaselineCalc!$B$5 -> 0.993 | K60: =Scenarios!G13 -> 0 | L60: =BaselineCalc!$B$7 + ROUND(Scenarios!L13*Scenarios!F13,0) -> 457 | M60: =BaselineCalc!$B$8 + Scenarios!L13 - ROUND(Scenarios!L13*Scenarios!F13,0) -> 296 | N60: =(L60-D60) + (M60-E60) -> 296 | O60: =BaselineCalc!$B$23 * N60 -> 222 | P60: =YearMap!E5 -> 500 | Q60: =IF(Scenarios!N13="lease", YearMap!F5, YearMap!G5) -> 0.3 | R60: =IF(Scenarios!D13=1, Q60*H60, H60) -> 1296576.1 | S60: =IF(Scenarios!E13=1, Q60*I60, I60) -> 447999.82 | T60: =IF(C60="FY2026", (Scenarios!D13+Scenarios!E13)*BaselineCalc!$B$22, 0) -> 0 | U60: =(R60+S60+G60*F60)*J60*(1-K60) -> 4419973.9 | V60: =O60*(G60+P60) -> 1425782.1 | W60: =U60+V60+T60 -> 5845756 | X60: =IF(F60+O60>0, W60/(F60+O60),"") -> 8609.3608 | Y60: =INDEX(YearMap!$I$2:$I$6, MATCH(C60, YearMap!$A$2:$A$6, 0)) -> 5319.8357 | Z60: =$W60-$Y60*$AC60 -> 2233587.5 | AA60: =IF($AC60>0, $Z60/$AC60, 0) -> 3289.5251 | AB60: =MAX(0, (MAX(0, $D60-BaselineCalc!$B$7) + MAX(0, $E60-BaselineCalc!$B$8))) -> 200 | AC60: =IF(LEFT($B60,2)="A_", $O60, IF(LEFT($B60,2)="B_", $M60+$O60, IF(LEFT($B60,2)="C_", $L60+$O60, $F60))) -> 679 | AD60: =$Y60*$AC60 -> 3612168.4 | AE60: =W60 - (1-Other_Parameters!$B$2)*$G60*$AB60*$J60*(1-$K60) -> 5140037.8 | AF60: =AD60-AE60 -> -1527869.4 | AG60: =B60&"|"&C60 -> C_Repurpose_Pima_ops_EchoGHub_EchoTargets|FY2029
A61: =AG61 -> C_Repurpose_Pima_ops_EchoGHub_EchoTargets|FY2030 | B61: =Scenarios!A13 -> C_Repurpose_Pima_ops_EchoGHub_EchoTargets | C61: FY2030 | D61: =IF(Scenarios!D13=1,0, L61) -> 457 | E61: =IF(Scenarios!E13=1,0, M61) -> 0 | F61: =D61+E61 -> 457 | G61: =YearMap!B6 -> 6070.5029 | H61: =YearMap!C6 -> 1328990.5 | I61: =YearMap!D6 -> 1530666.1 | J61: =1-BaselineCalc!$B$5 -> 0.993 | K61: =Scenarios!G13 -> 0 | L61: =BaselineCalc!$B$7 + ROUND(Scenarios!M13*Scenarios!F13,0) -> 457 | M61: =BaselineCalc!$B$8 + Scenarios!M13 - ROUND(Scenarios!M13*Scenarios!F13,0) -> 296 | N61: =(L61-D61) + (M61-E61) -> 296 | O61: =BaselineCalc!$B$23 * N61 -> 222 | P61: =YearMap!E6 -> 300 | Q61: =IF(Scenarios!N13="lease", YearMap!F6, YearMap!G6) -> 0.3 | R61: =IF(Scenarios!D13=1, Q61*H61, H61) -> 1328990.5 | S61: =IF(Scenarios!E13=1, Q61*I61, I61) -> 459199.82 | T61: =IF(C61="FY2026", (Scenarios!D13+Scenarios!E13)*BaselineCalc!$B$22, 0) -> 0 | U61: =(R61+S61+G61*F61)*J61*(1-K61) -> 4530473.2 | V61: =O61*(G61+P61) -> 1414251.6 | W61: =U61+V61+T61 -> 5944724.9 | X61: =IF(F61+O61>0, W61/(F61+O61),"") -> 8755.1176 | Y61: =INDEX(YearMap!$I$2:$I$6, MATCH(C61, YearMap!$A$2:$A$6, 0)) -> 5426.2324 | Z61: =$W61-$Y61*$AC61 -> 2260313.1 | AA61: =IF($AC61>0, $Z61/$AC61, 0) -> 3328.8852 | AB61: =MAX(0, (MAX(0, $D61-BaselineCalc!$B$7) + MAX(0, $E61-BaselineCalc!$B$8))) -> 200 | AC61: =IF(LEFT($B61,2)="A_", $O61, IF(LEFT($B61,2)="B_", $M61+$O61, IF(LEFT($B61,2)="C_", $L61+$O61, $F61))) -> 679 | AD61: =$Y61*$AC61 -> 3684411.8 | AE61: =W61 - (1-Other_Parameters!$B$2)*$G61*$AB61*$J61*(1-$K61) -> 5221363.7 | AF61: =AD61-AE61 -> -1536951.9 | AG61: =B61&"|"&C61 -> C_Repurpose_Pima_ops_EchoGHub_EchoTargets|FY2030

Sheet BaselineCalc
A1: Parameter | B1: Value | C1: Notes
A2: MO inflation | B2: =Control_Center!C6 -> 0.025 | C2: Annual inflation factor.
A3: Base MO per ADM (FY25) | B3: =Control_Center!C7 -> 9936 | C3: Working base for FY25.
A4: Fixed share of MO | B4: =Control_Center!C8 -> 0.46 | C4: Share treated as semi‑fixed (plant/insurance).
A5: Ops savings (keep‑open) | B5: =Control_Center!C10 -> 0.007 | C5: Light discipline if sites remain open (not used here).
A6: Extra savings (Co‑location) | B6: =Control_Center!C11 -> 0.015 | C6: Incremental savings for co‑location (not used here).
A7: Echo base ADM | B7: =Control_Center!C12 -> 257
A8: Pima base ADM | B8: =Control_Center!C13 -> 296
A9: Total base ADM | B9: =B7+B8 -> 553 | C9: Echo base ADM + Pima base ADM
A12: Helper / Derivation | B12: FY26 | C12: FY27 | D12: FY28 | E12: FY29 | F12: FY30 | G12: Notes
A13: Base total MO (FY25) | B13: =B9*B3 -> 5494608 | C13: =C14/$B$4 -> 5631973.2 | D13: =D14/$B$4 -> 5772772.5 | E13: =E14/$B$4 -> 5917091.8 | F13: =F14/$B$4 -> 6065019.1 | G13: Total ADM × Base MO/ADM | K13: B13 = B9*B3 (Base total MO, FY25)
A14: Fixed MO (FY25) | B14: =B13*B4 -> 2527519.7 | C14: =B17 -> 2590707.7 | D14: =C17 -> 2655475.4 | E14: =D17 -> 2721862.2 | F14: =E17 -> 2789908.8 | G14: Fixed = Base total × Fixed share | K14: B14 = B13*B4 (Fixed MO, FY25)
A15: Var per student (FY25) | B15: =(B13-B14)/B9 -> 5365.44 | C15: =B18 -> 5499.576 | D15: =C18 -> 5637.0654 | E15: =D18 -> 5777.992 | F15: =E18 -> 5922.4418 | G15: Variable = (Base total − Fixed)/Total ADM | K15: B15 = (B13–B14)/B9 (Variable $/student, FY25)
A17: Fixed total ($) | B17: =$B$14*(1+$B$2)^1 -> 2590707.7 | C17: =$B$14*(1+$B$2)^2 -> 2655475.4 | D17: =$B$14*(1+$B$2)^3 -> 2721862.2 | E17: =$B$14*(1+$B$2)^4 -> 2789908.8 | F17: =$B$14*(1+$B$2)^5 -> 2859656.5
A18: Var unit ($/student) | B18: =$B$15*(1+$B$2)^1 -> 5499.576 | C18: =$B$15*(1+$B$2)^2 -> 5637.0654 | D18: =$B$15*(1+$B$2)^3 -> 5777.992 | E18: =$B$15*(1+$B$2)^4 -> 5922.4418 | F18: =$B$15*(1+$B$2)^5 -> 6070.5029
A19: Echo fixed ($) | B19: =B17*($B$7/$B$9) -> 1203999.8 | C19: =C17*($B$7/$B$9) -> 1234099.8 | D19: =D17*($B$7/$B$9) -> 1264952.3 | E19: =E17*($B$7/$B$9) -> 1296576.1 | F19: =F17*($B$7/$B$9) -> 1328990.5
A20: Pima fixed ($) | B20: =B17*($B$8/$B$9) -> 1386707.9 | C20: =C17*($B$8/$B$9) -> 1421375.6 | D20: =D17*($B$8/$B$9) -> 1456910 | E20: =E17*($B$8/$B$9) -> 1493332.7 | F20: =F17*($B$8/$B$9) -> 1530666.1
A22: Repurpose TI per closed site (FY26) | B22: =Control_Center!C15 -> 1200000
A23: Retention r (central) | B23: =Control_Center!C16 -> 0.75
A25: Notes
A26: All formulas are same‑sheet and reference the Parameter cells above.
A27: Base State Aid per ADM (FY26) | B27: =Control_Center!C9 -> 5013 | C27: Editable; ADE base aid.
A28: Aid inflation (annual) | B28: 0.02 | C28: Editable; assumed growth in base aid.

Sheet YearMap
A1: Year | B1: VarUnit$ | C1: EchoFixed$ | D1: PimaFixed$ | E1: h | F1: f_lease | G1: f_ops | H1: YearIdx | I1: Aid$ | L1: Orig h | M1: Orig f_lease | N1: Orig f_ops
A2: FY2026 | B2: =BaselineCalc!B18 -> 5499.576 | C2: =BaselineCalc!B19 -> 1203999.8 | D2: =BaselineCalc!B20 -> 1386707.9 | E2: =Control_Center!C22 -> 1000 | F2: =Control_Center!D22 -> 0.4 | G2: =Control_Center!E22 -> 0.5 | H2: 1 | I2: =BaselineCalc!$B$27*(1+BaselineCalc!$B$28)^(H2-1) -> 5013 | L2: 1000 | M2: 0.4 | N2: 0.4
A3: FY2027 | B3: =BaselineCalc!C18 -> 5637.0654 | C3: =BaselineCalc!C19 -> 1234099.8 | D3: =BaselineCalc!C20 -> 1421375.6 | E3: =Control_Center!C23 -> 800 | F3: =Control_Center!D23 -> 0.3 | G3: =Control_Center!E23 -> 0.4 | H3: 2 | I3: =BaselineCalc!$B$27*(1+BaselineCalc!$B$28)^(H3-1) -> 5113.26 | L3: 800 | M3: 0.3 | N3: 0.35
A4: FY2028 | B4: =BaselineCalc!D18 -> 5777.992 | C4: =BaselineCalc!D19 -> 1264952.3 | D4: =BaselineCalc!D20 -> 1456910 | E4: =Control_Center!C24 -> 600 | F4: =Control_Center!D24 -> 0.2 | G4: =Control_Center!E24 -> 0.35 | H4: 3 | I4: =BaselineCalc!$B$27*(1+BaselineCalc!$B$28)^(H4-1) -> 5215.5252 | L4: 600 | M4: 0.2 | N4: 0.3
A5: FY2029 | B5: =BaselineCalc!E18 -> 5922.4418 | C5: =BaselineCalc!E19 -> 1296576.1 | D5: =BaselineCalc!E20 -> 1493332.7 | E5: =Control_Center!C25 -> 500 | F5: =Control_Center!D25 -> 0.1 | G5: =Control_Center!E25 -> 0.3 | H5: 4 | I5: =BaselineCalc!$B$27*(1+BaselineCalc!$B$28)^(H5-1) -> 5319.8357 | L5: 400 | M5: 0.1 | N5: 0.25
A6: FY2030 | B6: =BaselineCalc!F18 -> 6070.5029 | C6: =BaselineCalc!F19 -> 1328990.5 | D6: =BaselineCalc!F20 -> 1530666.1 | E6: =Control_Center!C26 -> 300 | F6: =Control_Center!D26 -> 0.1 | G6: =Control_Center!E26 -> 0.3 | H6: 5 | I6: =BaselineCalc!$B$27*(1+BaselineCalc!$B$28)^(H6-1) -> 5426.2324 | L6: 300 | M6: 0 | N6: 0.2

Sheet Scenarios
A1: ScenarioKey | B1: Label | C1: Overlay | D1: CloseEcho | E1: ClosePima | F1: EchoShareDist | G1: ExtraSave | H1: Notes | I1: Overlay_FY26 | J1: Overlay_FY27 | K1: Overlay_FY28 | L1: Overlay_FY29 | M1: Overlay_FY30 | N1: Carry
A2: D_CUSTOM1 | B2: =Control_Center!B31 -> CUSTOM_KeepOpen_v1 | C2: =Control_Center!C31 -> 0 | D2: =Control_Center!D31 -> 0 | E2: =Control_Center!E31 -> 0 | F2: =Control_Center!F31 -> 0.5 | G2: =Control_Center!G31 -> 0 | H2: Baseline + outreach; no closures | I2: =$C2 -> 0 | J2: =$C2 -> 0 | K2: =$C2 -> 0 | L2: =$C2 -> 0 | M2: =$C2 -> 0
A3: E_StatusQuo_Targets | B3: =Control_Center!B32 -> Status‑Quo + Op Growth Targets | C3: =Control_Center!C32 -> 150 | D3: =Control_Center!D32 -> 0 | E3: =Control_Center!E32 -> 0 | F3: =Control_Center!F32 -> 0.5 | G3: =Control_Center!G32 -> 0 | H3: Baseline + targets; no closures | I3: =$C3 -> 150 | J3: =$C3 -> 150 | K3: =$C3 -> 150 | L3: =$C3 -> 150 | M3: =$C3 -> 150
A4: F_CoLocation_Echo_Targets | B4: =Control_Center!B33 -> Co‑Location @ Echo + Op Growth Targets | C4: =Control_Center!C33 -> 150 | D4: =Control_Center!D33 -> 0 | E4: =Control_Center!E33 -> 0 | F4: =Control_Center!F33 -> 0.5 | G4: =Control_Center!G33 -> 0.05 | H4: Shared‑use efficiencies later (no closure) | I4: =$C4 -> 150 | J4: =$C4 -> 150 | K4: =$C4 -> 150 | L4: =$C4 -> 150 | M4: =$C4 -> 150
A5: D_Grow_Both_Targets | B5: =Control_Center!B34 -> Grow Both + Op Growth Targets | C5: =Control_Center!C34 -> 250 | D5: =Control_Center!D34 -> 0 | E5: =Control_Center!E34 -> 0 | F5: =Control_Center!F34 -> 0.5 | G5: =Control_Center!G34 -> 0 | H5: Baseline +100 overlay | I5: =$C5 -> 250 | J5: =$C5 -> 250 | K5: =$C5 -> 250 | L5: =$C5 -> 250 | M5: =$C5 -> 250
A6: D_CUSTOM2 | B6: =Control_Center!B35 -> CUSTOM_KeepOpen_v2 | C6: =Control_Center!C35 -> 0 | D6: =Control_Center!D35 -> 0 | E6: =Control_Center!E35 -> 0 | F6: =Control_Center!F35 -> 0.5 | G6: =Control_Center!G35 -> 0 | H6: Baseline +150 overlay | I6: =$C6 -> 0 | J6: =$C6 -> 0 | K6: =$C6 -> 0 | L6: =$C6 -> 0 | M6: =$C6 -> 0
A7: G_EchoGHubRamp_PimaTargets | B7: =Control_Center!B36 -> Growth Hub @ Echo + Status-Quo Pima + Op Growth Targets | C7: =Control_Center!C36 -> 150 | D7: =Control_Center!D36 -> 0 | E7: =Control_Center!E36 -> 0 | F7: =Control_Center!F36 -> 0.7 | G7: =Control_Center!G36 -> 0 | H7: Time‑phased ramp (+50,+100,+150 years 1–3) | I7: =C7/3 -> 50 | J7: =I7+C7/3 -> 100 | K7: =J7+C7/3 -> 150 | L7: =C7 -> 150 | M7: =C7 -> 150
A8: A_Repurpose_Both_lease | B8: =Control_Center!B37 -> Repurpose BOTH (lease) | C8: =Control_Center!C37 -> 0 | D8: =Control_Center!D37 -> 1 | E8: =Control_Center!E37 -> 1 | F8: =Control_Center!F37 -> 0.5 | G8: =Control_Center!G37 -> 0 | H8: Repurpose both; lease/sale glide | I8: =$C8 -> 0 | J8: =$C8 -> 0 | K8: =$C8 -> 0 | L8: =$C8 -> 0 | M8: =$C8 -> 0 | N8: lease
A9: A_Repurpose_Both_ops | B9: =Control_Center!B38 -> Repurpose BOTH (ops) | C9: =Control_Center!C38 -> 0 | D9: =Control_Center!D38 -> 1 | E9: =Control_Center!E38 -> 1 | F9: =Control_Center!F38 -> 0.5 | G9: =Control_Center!G38 -> 0 | H9: Repurpose both; operations carry | I9: =$C9 -> 0 | J9: =$C9 -> 0 | K9: =$C9 -> 0 | L9: =$C9 -> 0 | M9: =$C9 -> 0 | N9: ops
A10: B_Repurpose_Echo_lease_PimaTargets | B10: =Control_Center!B39 -> Repurpose ECHO (lease) + Status-Quo Pima + Pima Op Growth Targets | C10: =Control_Center!C39 -> 0 | D10: =Control_Center!D39 -> 1 | E10: =Control_Center!E39 -> 0 | F10: =Control_Center!F39 -> 0 | G10: =Control_Center!G39 -> 0 | H10: Repurpose Echo only; lease glide | I10: =$C10 -> 0 | J10: =$C10 -> 0 | K10: =$C10 -> 0 | L10: =$C10 -> 0 | M10: =$C10 -> 0 | N10: lease
A11: B_Repurpose_Echo_ops_PimaTargets | B11: =Control_Center!B40 -> Repurpose ECHO (ops) + Status-Quo Pima + Pima Op Growth Targets | C11: =Control_Center!C40 -> 150 | D11: =Control_Center!D40 -> 1 | E11: =Control_Center!E40 -> 0 | F11: =Control_Center!F40 -> 0 | G11: =Control_Center!G40 -> 0 | H11: Repurpose Echo only; ops carry | I11: =$C11 -> 150 | J11: =$C11 -> 150 | K11: =$C11 -> 150 | L11: =$C11 -> 150 | M11: =$C11 -> 150 | N11: ops
A12: C_Repurpose_Pima_lease_EchoGHub_EchoTargets | B12: =Control_Center!B41 -> Repurpose PIMA (lease) + Growth Hub @ Echo + Echo Op Growth Targets | C12: =Control_Center!C41 -> 0 | D12: =Control_Center!D41 -> 0 | E12: =Control_Center!E41 -> 1 | F12: =Control_Center!F41 -> 1 | G12: =Control_Center!G41 -> 0 | H12: Repurpose Pima only; lease glide | I12: =$C12 -> 0 | J12: =$C12 -> 0 | K12: =$C12 -> 0 | L12: =$C12 -> 0 | M12: =$C12 -> 0 | N12: lease
A13: C_Repurpose_Pima_ops_EchoGHub_EchoTargets | B13: =Control_Center!B42 -> Repurpose PIMA (ops) + Growth Hub @ Echo + Echo Op Growth Targets | C13: =Control_Center!C42 -> 200 | D13: =Control_Center!D42 -> 0 | E13: =Control_Center!E42 -> 1 | F13: =Control_Center!F42 -> 1 | G13: =Control_Center!G42 -> 0 | H13: Repurpose Pima only; ops carry | I13: =$C13 -> 200 | J13: =$C13 -> 200 | K13: =$C13 -> 200 | L13: =$C13 -> 200 | M13: =$C13 -> 200 | N13: ops
A15: ScenarioKey | B15: Year | C15: Echo_ADM | D15: Pima_ADM | E15: Total_ADM | F15: VarUnit$ | G15: EchoFixed$ | H15: PimaFixed$ | I15: Key
A16: =A2 -> D_CUSTOM1 | B16: FY2026 | C16: =IF(D2=1,0, BaselineCalc!$B$7 + ROUND(I2*F2,0)) -> 257 | D16: =IF(E2=1,0, BaselineCalc!$B$8 + I2 - ROUND(I2*F2,0)) -> 296 | E16: =C16+D16 -> 553 | F16: =YearMap!B2 -> 5499.576 | G16: =YearMap!C2 -> 1203999.8 | H16: =YearMap!D2 -> 1386707.9 | I16: =A16&"|"&B16 -> D_CUSTOM1|FY2026
A17: =A2 -> D_CUSTOM1 | B17: FY2027 | C17: =IF(D2=1,0, BaselineCalc!$B$7 + ROUND(J2*F2,0)) -> 257 | D17: =IF(E2=1,0, BaselineCalc!$B$8 + J2 - ROUND(J2*F2,0)) -> 296 | E17: =C17+D17 -> 553 | F17: =YearMap!B3 -> 5637.0654 | G17: =YearMap!C3 -> 1234099.8 | H17: =YearMap!D3 -> 1421375.6 | I17: =A17&"|"&B17 -> D_CUSTOM1|FY2027
A18: =A2 -> D_CUSTOM1 | B18: FY2028 | C18: =IF(D2=1,0, BaselineCalc!$B$7 + ROUND(K2*F2,0)) -> 257 | D18: =IF(E2=1,0, BaselineCalc!$B$8 + K2 - ROUND(K2*F2,0)) -> 296 | E18: =C18+D18 -> 553 | F18: =YearMap!B4 -> 5777.992 | G18: =YearMap!C4 -> 1264952.3 | H18: =YearMap!D4 -> 1456910 | I18: =A18&"|"&B18 -> D_CUSTOM1|FY2028
A19: =A2 -> D_CUSTOM1 | B19: FY2029 | C19: =IF(D2=1,0, BaselineCalc!$B$7 + ROUND(L2*F2,0)) -> 257 | D19: =IF(E2=1,0, BaselineCalc!$B$8 + L2 - ROUND(L2*F2,0)) -> 296 | E19: =C19+D19 -> 553 | F19: =YearMap!B5 -> 5922.4418 | G19: =YearMap!C5 -> 1296576.1 | H19: =YearMap!D5 -> 1493332.7 | I19: =A19&"|"&B19 -> D_CUSTOM1|FY2029
A20: =A2 -> D_CUSTOM1 | B20: FY2030 | C20: =IF(D2=1,0, BaselineCalc!$B$7 + ROUND(M2*F2,0)) -> 257 | D20: =IF(E2=1,0, BaselineCalc!$B$8 + M2 - ROUND(M2*F2,0)) -> 296 | E20: =C20+D20 -> 553 | F20: =YearMap!B6 -> 6070.5029 | G20: =YearMap!C6 -> 1328990.5 | H20: =YearMap!D6 -> 1530666.1 | I20: =A20&"|"&B20 -> D_CUSTOM1|FY2030
A21: =A3 -> E_StatusQuo_Targets | B21: FY2026 | C21: =IF(D3=1,0, BaselineCalc!$B$7 + ROUND(I3*F3,0)) -> 332 | D21: =IF(E3=1,0, BaselineCalc!$B$8 + I3 - ROUND(I3*F3,0)) -> 371 | E21: =C21+D21 -> 703 | F21: =YearMap!B2 -> 5499.576 | G21: =YearMap!C2 -> 1203999.8 | H21: =YearMap!D2 -> 1386707.9 | I21: =A21&"|"&B21 -> E_StatusQuo_Targets|FY2026
A22: =A3 -> E_StatusQuo_Targets | B22: FY2027 | C22: =IF(D3=1,0, BaselineCalc!$B$7 + ROUND(J3*F3,0)) -> 332 | D22: =IF(E3=1,0, BaselineCalc!$B$8 + J3 - ROUND(J3*F3,0)) -> 371 | E22: =C22+D22 -> 703 | F22: =YearMap!B3 -> 5637.0654 | G22: =YearMap!C3 -> 1234099.8 | H22: =YearMap!D3 -> 1421375.6 | I22: =A22&"|"&B22 -> E_StatusQuo_Targets|FY2027
A23: =A3 -> E_StatusQuo_Targets | B23: FY2028 | C23: =IF(D3=1,0, BaselineCalc!$B$7 + ROUND(K3*F3,0)) -> 332 | D23: =IF(E3=1,0, BaselineCalc!$B$8 + K3 - ROUND(K3*F3,0)) -> 371 | E23: =C23+D23 -> 703 | F23: =YearMap!B4 -> 5777.992 | G23: =YearMap!C4 -> 1264952.3 | H23: =YearMap!D4 -> 1456910 | I23: =A23&"|"&B23 -> E_StatusQuo_Targets|FY2028
A24: =A3 -> E_StatusQuo_Targets | B24: FY2029 | C24: =IF(D3=1,0, BaselineCalc!$B$7 + ROUND(L3*F3,0)) -> 332 | D24: =IF(E3=1,0, BaselineCalc!$B$8 + L3 - ROUND(L3*F3,0)) -> 371 | E24: =C24+D24 -> 703 | F24: =YearMap!B5 -> 5922.4418 | G24: =YearMap!C5 -> 1296576.1 | H24: =YearMap!D5 -> 1493332.7 | I24: =A24&"|"&B24 -> E_StatusQuo_Targets|FY2029
A25: =A3 -> E_StatusQuo_Targets | B25: FY2030 | C25: =IF(D3=1,0, BaselineCalc!$B$7 + ROUND(M3*F3,0)) -> 332 | D25: =IF(E3=1,0, BaselineCalc!$B$8 + M3 - ROUND(M3*F3,0)) -> 371 | E25: =C25+D25 -> 703 | F25: =YearMap!B6 -> 6070.5029 | G25: =YearMap!C6 -> 1328990.5 | H25: =YearMap!D6 -> 1530666.1 | I25: =A25&"|"&B25 -> E_StatusQuo_Targets|FY2030
A26: =A4 -> F_CoLocation_Echo_Targets | B26: FY2026 | C26: =IF(D4=1,0, BaselineCalc!$B$7 + ROUND(I4*F4,0)) -> 332 | D26: =IF(E4=1,0, BaselineCalc!$B$8 + I4 - ROUND(I4*F4,0)) -> 371 | E26: =C26+D26 -> 703 | F26: =YearMap!B2 -> 5499.576 | G26: =YearMap!C2 -> 1203999.8 | H26: =YearMap!D2 -> 1386707.9 | I26: =A26&"|"&B26 -> F_CoLocation_Echo_Targets|FY2026
A27: =A4 -> F_CoLocation_Echo_Targets | B27: FY2027 | C27: =IF(D4=1,0, BaselineCalc!$B$7 + ROUND(J4*F4,0)) -> 332 | D27: =IF(E4=1,0, BaselineCalc!$B$8 + J4 - ROUND(J4*F4,0)) -> 371 | E27: =C27+D27 -> 703 | F27: =YearMap!B3 -> 5637.0654 | G27: =YearMap!C3 -> 1234099.8 | H27: =YearMap!D3 -> 1421375.6 | I27: =A27&"|"&B27 -> F_CoLocation_Echo_Targets|FY2027
A28: =A4 -> F_CoLocation_Echo_Targets | B28: FY2028 | C28: =IF(D4=1,0, BaselineCalc!$B$7 + ROUND(K4*F4,0)) -> 332 | D28: =IF(E4=1,0, BaselineCalc!$B$8 + K4 - ROUND(K4*F4,0)) -> 371 | E28: =C28+D28 -> 703 | F28: =YearMap!B4 -> 5777.992 | G28: =YearMap!C4 -> 1264952.3 | H28: =YearMap!D4 -> 1456910 | I28: =A28&"|"&B28 -> F_CoLocation_Echo_Targets|FY2028
A29: =A4 -> F_CoLocation_Echo_Targets | B29: FY2029 | C29: =IF(D4=1,0, BaselineCalc!$B$7 + ROUND(L4*F4,0)) -> 332 | D29: =IF(E4=1,0, BaselineCalc!$B$8 + L4 - ROUND(L4*F4,0)) -> 371 | E29: =C29+D29 -> 703 | F29: =YearMap!B5 -> 5922.4418 | G29: =YearMap!C5 -> 1296576.1 | H29: =YearMap!D5 -> 1493332.7 | I29: =A29&"|"&B29 -> F_CoLocation_Echo_Targets|FY2029
A30: =A4 -> F_CoLocation_Echo_Targets | B30: FY2030 | C30: =IF(D4=1,0, BaselineCalc!$B$7 + ROUND(M4*F4,0)) -> 332 | D30: =IF(E4=1,0, BaselineCalc!$B$8 + M4 - ROUND(M4*F4,0)) -> 371 | E30: =C30+D30 -> 703 | F30: =YearMap!B6 -> 6070.5029 | G30: =YearMap!C6 -> 1328990.5 | H30: =YearMap!D6 -> 1530666.1 | I30: =A30&"|"&B30 -> F_CoLocation_Echo_Targets|FY2030
A31: =A5 -> D_Grow_Both_Targets | B31: FY2026 | C31: =IF(D5=1,0, BaselineCalc!$B$7 + ROUND(I5*F5,0)) -> 382 | D31: =IF(E5=1,0, BaselineCalc!$B$8 + I5 - ROUND(I5*F5,0)) -> 421 | E31: =C31+D31 -> 803 | F31: =YearMap!B2 -> 5499.576 | G31: =YearMap!C2 -> 1203999.8 | H31: =YearMap!D2 -> 1386707.9 | I31: =A31&"|"&B31 -> D_Grow_Both_Targets|FY2026
A32: =A5 -> D_Grow_Both_Targets | B32: FY2027 | C32: =IF(D5=1,0, BaselineCalc!$B$7 + ROUND(J5*F5,0)) -> 382 | D32: =IF(E5=1,0, BaselineCalc!$B$8 + J5 - ROUND(J5*F5,0)) -> 421 | E32: =C32+D32 -> 803 | F32: =YearMap!B3 -> 5637.0654 | G32: =YearMap!C3 -> 1234099.8 | H32: =YearMap!D3 -> 1421375.6 | I32: =A32&"|"&B32 -> D_Grow_Both_Targets|FY2027
A33: =A5 -> D_Grow_Both_Targets | B33: FY2028 | C33: =IF(D5=1,0, BaselineCalc!$B$7 + ROUND(K5*F5,0)) -> 382 | D33: =IF(E5=1,0, BaselineCalc!$B$8 + K5 - ROUND(K5*F5,0)) -> 421 | E33: =C33+D33 -> 803 | F33: =YearMap!B4 -> 5777.992 | G33: =YearMap!C4 -> 1264952.3 | H33: =YearMap!D4 -> 1456910 | I33: =A33&"|"&B33 -> D_Grow_Both_Targets|FY2028
A34: =A5 -> D_Grow_Both_Targets | B34: FY2029 | C34: =IF(D5=1,0, BaselineCalc!$B$7 + ROUND(L5*F5,0)) -> 382 | D34: =IF(E5=1,0, BaselineCalc!$B$8 + L5 - ROUND(L5*F5,0)) -> 421 | E34: =C34+D34 -> 803 | F34: =YearMap!B5 -> 5922.4418 | G34: =YearMap!C5 -> 1296576.1 | H34: =YearMap!D5 -> 1493332.7 | I34: =A34&"|"&B34 -> D_Grow_Both_Targets|FY2029
A35: =A5 -> D_Grow_Both_Targets | B35: FY2030 | C35: =IF(D5=1,0, BaselineCalc!$B$7 + ROUND(M5*F5,0)) -> 382 | D35: =IF(E5=1,0, BaselineCalc!$B$8 + M5 - ROUND(M5*F5,0)) -> 421 | E35: =C35+D35 -> 803 | F35: =YearMap!B6 -> 6070.5029 | G35: =YearMap!C6 -> 1328990.5 | H35: =YearMap!D6 -> 1530666.1 | I35: =A35&"|"&B35 -> D_Grow_Both_Targets|FY2030
A36: =A6 -> D_CUSTOM2 | B36: FY2026 | C36: =IF(D6=1,0, BaselineCalc!$B$7 + ROUND(I6*F6,0)) -> 257 | D36: =IF(E6=1,0, BaselineCalc!$B$8 + I6 - ROUND(I6*F6,0)) -> 296 | E36: =C36+D36 -> 553 | F36: =YearMap!B2 -> 5499.576 | G36: =YearMap!C2 -> 1203999.8 | H36: =YearMap!D2 -> 1386707.9 | I36: =A36&"|"&B36 -> D_CUSTOM2|FY2026
A37: =A6 -> D_CUSTOM2 | B37: FY2027 | C37: =IF(D6=1,0, BaselineCalc!$B$7 + ROUND(J6*F6,0)) -> 257 | D37: =IF(E6=1,0, BaselineCalc!$B$8 + J6 - ROUND(J6*F6,0)) -> 296 | E37: =C37+D37 -> 553 | F37: =YearMap!B3 -> 5637.0654 | G37: =YearMap!C3 -> 1234099.8 | H37: =YearMap!D3 -> 1421375.6 | I37: =A37&"|"&B37 -> D_CUSTOM2|FY2027
A38: =A6 -> D_CUSTOM2 | B38: FY2028 | C38: =IF(D6=1,0, BaselineCalc!$B$7 + ROUND(K6*F6,0)) -> 257 | D38: =IF(E6=1,0, BaselineCalc!$B$8 + K6 - ROUND(K6*F6,0)) -> 296 | E38: =C38+D38 -> 553 | F38: =YearMap!B4 -> 5777.992 | G38: =YearMap!C4 -> 1264952.3 | H38: =YearMap!D4 -> 1456910 | I38: =A38&"|"&B38 -> D_CUSTOM2|FY2028
A39: =A6 -> D_CUSTOM2 | B39: FY2029 | C39: =IF(D6=1,0, BaselineCalc!$B$7 + ROUND(L6*F6,0)) -> 257 | D39: =IF(E6=1,0, BaselineCalc!$B$8 + L6 - ROUND(L6*F6,0)) -> 296 | E39: =C39+D39 -> 553 | F39: =YearMap!B5 -> 5922.4418 | G39: =YearMap!C5 -> 1296576.1 | H39: =YearMap!D5 -> 1493332.7 | I39: =A39&"|"&B39 -> D_CUSTOM2|FY2029
A40: =A6 -> D_CUSTOM2 | B40: FY2030 | C40: =IF(D6=1,0, BaselineCalc!$B$7 + ROUND(M6*F6,0)) -> 257 | D40: =IF(E6=1,0, BaselineCalc!$B$8 + M6 - ROUND(M6*F6,0)) -> 296 | E40: =C40+D40 -> 553 | F40: =YearMap!B6 -> 6070.5029 | G40: =YearMap!C6 -> 1328990.5 | H40: =YearMap!D6 -> 1530666.1 | I40: =A40&"|"&B40 -> D_CUSTOM2|FY2030
A41: =A7 -> G_EchoGHubRamp_PimaTargets | B41: FY2026 | C41: =IF(D7=1,0, BaselineCalc!$B$7 + ROUND(I7*F7,0)) -> 292 | D41: =IF(E7=1,0, BaselineCalc!$B$8 + I7 - ROUND(I7*F7,0)) -> 311 | E41: =C41+D41 -> 603 | F41: =YearMap!B2 -> 5499.576 | G41: =YearMap!C2 -> 1203999.8 | H41: =YearMap!D2 -> 1386707.9 | I41: =A41&"|"&B41 -> G_EchoGHubRamp_PimaTargets|FY2026
A42: =A7 -> G_EchoGHubRamp_PimaTargets | B42: FY2027 | C42: =IF(D7=1,0, BaselineCalc!$B$7 + ROUND(J7*F7,0)) -> 327 | D42: =IF(E7=1,0, BaselineCalc!$B$8 + J7 - ROUND(J7*F7,0)) -> 326 | E42: =C42+D42 -> 653 | F42: =YearMap!B3 -> 5637.0654 | G42: =YearMap!C3 -> 1234099.8 | H42: =YearMap!D3 -> 1421375.6 | I42: =A42&"|"&B42 -> G_EchoGHubRamp_PimaTargets|FY2027
A43: =A7 -> G_EchoGHubRamp_PimaTargets | B43: FY2028 | C43: =IF(D7=1,0, BaselineCalc!$B$7 + ROUND(K7*F7,0)) -> 362 | D43: =IF(E7=1,0, BaselineCalc!$B$8 + K7 - ROUND(K7*F7,0)) -> 341 | E43: =C43+D43 -> 703 | F43: =YearMap!B4 -> 5777.992 | G43: =YearMap!C4 -> 1264952.3 | H43: =YearMap!D4 -> 1456910 | I43: =A43&"|"&B43 -> G_EchoGHubRamp_PimaTargets|FY2028
A44: =A7 -> G_EchoGHubRamp_PimaTargets | B44: FY2029 | C44: =IF(D7=1,0, BaselineCalc!$B$7 + ROUND(L7*F7,0)) -> 362 | D44: =IF(E7=1,0, BaselineCalc!$B$8 + L7 - ROUND(L7*F7,0)) -> 341 | E44: =C44+D44 -> 703 | F44: =YearMap!B5 -> 5922.4418 | G44: =YearMap!C5 -> 1296576.1 | H44: =YearMap!D5 -> 1493332.7 | I44: =A44&"|"&B44 -> G_EchoGHubRamp_PimaTargets|FY2029
A45: =A7 -> G_EchoGHubRamp_PimaTargets | B45: FY2030 | C45: =IF(D7=1,0, BaselineCalc!$B$7 + ROUND(M7*F7,0)) -> 362 | D45: =IF(E7=1,0, BaselineCalc!$B$8 + M7 - ROUND(M7*F7,0)) -> 341 | E45: =C45+D45 -> 703 | F45: =YearMap!B6 -> 6070.5029 | G45: =YearMap!C6 -> 1328990.5 | H45: =YearMap!D6 -> 1530666.1 | I45: =A45&"|"&B45 -> G_EchoGHubRamp_PimaTargets|FY2030
A46: =A8 -> A_Repurpose_Both_lease | B46: FY2026 | C46: =IF(D8=1,0, BaselineCalc!$B$7 + ROUND(I8*F8,0)) -> 0 | D46: =IF(E8=1,0, BaselineCalc!$B$8 + I8 - ROUND(I8*F8,0)) -> 0 | E46: =C46+D46 -> 0 | F46: =YearMap!B2 -> 5499.576 | G46: =YearMap!C2 -> 1203999.8 | H46: =YearMap!D2 -> 1386707.9 | I46: =A46&"|"&B46 -> A_Repurpose_Both_lease|FY2026
A47: =A8 -> A_Repurpose_Both_lease | B47: FY2027 | C47: =IF(D8=1,0, BaselineCalc!$B$7 + ROUND(J8*F8,0)) -> 0 | D47: =IF(E8=1,0, BaselineCalc!$B$8 + J8 - ROUND(J8*F8,0)) -> 0 | E47: =C47+D47 -> 0 | F47: =YearMap!B3 -> 5637.0654 | G47: =YearMap!C3 -> 1234099.8 | H47: =YearMap!D3 -> 1421375.6 | I47: =A47&"|"&B47 -> A_Repurpose_Both_lease|FY2027
A48: =A8 -> A_Repurpose_Both_lease | B48: FY2028 | C48: =IF(D8=1,0, BaselineCalc!$B$7 + ROUND(K8*F8,0)) -> 0 | D48: =IF(E8=1,0, BaselineCalc!$B$8 + K8 - ROUND(K8*F8,0)) -> 0 | E48: =C48+D48 -> 0 | F48: =YearMap!B4 -> 5777.992 | G48: =YearMap!C4 -> 1264952.3 | H48: =YearMap!D4 -> 1456910 | I48: =A48&"|"&B48 -> A_Repurpose_Both_lease|FY2028
A49: =A8 -> A_Repurpose_Both_lease | B49: FY2029 | C49: =IF(D8=1,0, BaselineCalc!$B$7 + ROUND(L8*F8,0)) -> 0 | D49: =IF(E8=1,0, BaselineCalc!$B$8 + L8 - ROUND(L8*F8,0)) -> 0 | E49: =C49+D49 -> 0 | F49: =YearMap!B5 -> 5922.4418 | G49: =YearMap!C5 -> 1296576.1 | H49: =YearMap!D5 -> 1493332.7 | I49: =A49&"|"&B49 -> A_Repurpose_Both_lease|FY2029
A50: =A8 -> A_Repurpose_Both_lease | B50: FY2030 | C50: =IF(D8=1,0, BaselineCalc!$B$7 + ROUND(M8*F8,0)) -> 0 | D50: =IF(E8=1,0, BaselineCalc!$B$8 + M8 - ROUND(M8*F8,0)) -> 0 | E50: =C50+D50 -> 0 | F50: =YearMap!B6 -> 6070.5029 | G50: =YearMap!C6 -> 1328990.5 | H50: =YearMap!D6 -> 1530666.1 | I50: =A50&"|"&B50 -> A_Repurpose_Both_lease|FY2030
A51: =A9 -> A_Repurpose_Both_ops | B51: FY2026 | C51: =IF(D9=1,0, BaselineCalc!$B$7 + ROUND(I9*F9,0)) -> 0 | D51: =IF(E9=1,0, BaselineCalc!$B$8 + I9 - ROUND(I9*F9,0)) -> 0 | E51: =C51+D51 -> 0 | F51: =YearMap!B2 -> 5499.576 | G51: =YearMap!C2 -> 1203999.8 | H51: =YearMap!D2 -> 1386707.9 | I51: =A51&"|"&B51 -> A_Repurpose_Both_ops|FY2026
A52: =A9 -> A_Repurpose_Both_ops | B52: FY2027 | C52: =IF(D9=1,0, BaselineCalc!$B$7 + ROUND(J9*F9,0)) -> 0 | D52: =IF(E9=1,0, BaselineCalc!$B$8 + J9 - ROUND(J9*F9,0)) -> 0 | E52: =C52+D52 -> 0 | F52: =YearMap!B3 -> 5637.0654 | G52: =YearMap!C3 -> 1234099.8 | H52: =YearMap!D3 -> 1421375.6 | I52: =A52&"|"&B52 -> A_Repurpose_Both_ops|FY2027
A53: =A9 -> A_Repurpose_Both_ops | B53: FY2028 | C53: =IF(D9=1,0, BaselineCalc!$B$7 + ROUND(K9*F9,0)) -> 0 | D53: =IF(E9=1,0, BaselineCalc!$B$8 + K9 - ROUND(K9*F9,0)) -> 0 | E53: =C53+D53 -> 0 | F53: =YearMap!B4 -> 5777.992 | G53: =YearMap!C4 -> 1264952.3 | H53: =YearMap!D4 -> 1456910 | I53: =A53&"|"&B53 -> A_Repurpose_Both_ops|FY2028
A54: =A9 -> A_Repurpose_Both_ops | B54: FY2029 | C54: =IF(D9=1,0, BaselineCalc!$B$7 + ROUND(L9*F9,0)) -> 0 | D54: =IF(E9=1,0, BaselineCalc!$B$8 + L9 - ROUND(L9*F9,0)) -> 0 | E54: =C54+D54 -> 0 | F54: =YearMap!B5 -> 5922.4418 | G54: =YearMap!C5 -> 1296576.1 | H54: =YearMap!D5 -> 1493332.7 | I54: =A54&"|"&B54 -> A_Repurpose_Both_ops|FY2029
A55: =A9 -> A_Repurpose_Both_ops | B55: FY2030 | C55: =IF(D9=1,0, BaselineCalc!$B$7 + ROUND(M9*F9,0)) -> 0 | D55: =IF(E9=1,0, BaselineCalc!$B$8 + M9 - ROUND(M9*F9,0)) -> 0 | E55: =C55+D55 -> 0 | F55: =YearMap!B6 -> 6070.5029 | G55: =YearMap!C6 -> 1328990.5 | H55: =YearMap!D6 -> 1530666.1 | I55: =A55&"|"&B55 -> A_Repurpose_Both_ops|FY2030
A56: =A10 -> B_Repurpose_Echo_lease_PimaTargets | B56: FY2026 | C56: =IF(D10=1,0, BaselineCalc!$B$7 + ROUND(I10*F10,0)) -> 0 | D56: =IF(E10=1,0, BaselineCalc!$B$8 + I10 - ROUND(I10*F10,0)) -> 296 | E56: =C56+D56 -> 296 | F56: =YearMap!B2 -> 5499.576 | G56: =YearMap!C2 -> 1203999.8 | H56: =YearMap!D2 -> 1386707.9 | I56: =A56&"|"&B56 -> B_Repurpose_Echo_lease_PimaTargets|FY2026
A57: =A10 -> B_Repurpose_Echo_lease_PimaTargets | B57: FY2027 | C57: =IF(D10=1,0, BaselineCalc!$B$7 + ROUND(J10*F10,0)) -> 0 | D57: =IF(E10=1,0, BaselineCalc!$B$8 + J10 - ROUND(J10*F10,0)) -> 296 | E57: =C57+D57 -> 296 | F57: =YearMap!B3 -> 5637.0654 | G57: =YearMap!C3 -> 1234099.8 | H57: =YearMap!D3 -> 1421375.6 | I57: =A57&"|"&B57 -> B_Repurpose_Echo_lease_PimaTargets|FY2027
A58: =A10 -> B_Repurpose_Echo_lease_PimaTargets | B58: FY2028 | C58: =IF(D10=1,0, BaselineCalc!$B$7 + ROUND(K10*F10,0)) -> 0 | D58: =IF(E10=1,0, BaselineCalc!$B$8 + K10 - ROUND(K10*F10,0)) -> 296 | E58: =C58+D58 -> 296 | F58: =YearMap!B4 -> 5777.992 | G58: =YearMap!C4 -> 1264952.3 | H58: =YearMap!D4 -> 1456910 | I58: =A58&"|"&B58 -> B_Repurpose_Echo_lease_PimaTargets|FY2028
A59: =A10 -> B_Repurpose_Echo_lease_PimaTargets | B59: FY2029 | C59: =IF(D10=1,0, BaselineCalc!$B$7 + ROUND(L10*F10,0)) -> 0 | D59: =IF(E10=1,0, BaselineCalc!$B$8 + L10 - ROUND(L10*F10,0)) -> 296 | E59: =C59+D59 -> 296 | F59: =YearMap!B5 -> 5922.4418 | G59: =YearMap!C5 -> 1296576.1 | H59: =YearMap!D5 -> 1493332.7 | I59: =A59&"|"&B59 -> B_Repurpose_Echo_lease_PimaTargets|FY2029
A60: =A10 -> B_Repurpose_Echo_lease_PimaTargets | B60: FY2030 | C60: =IF(D10=1,0, BaselineCalc!$B$7 + ROUND(M10*F10,0)) -> 0 | D60: =IF(E10=1,0, BaselineCalc!$B$8 + M10 - ROUND(M10*F10,0)) -> 296 | E60: =C60+D60 -> 296 | F60: =YearMap!B6 -> 6070.5029 | G60: =YearMap!C6 -> 1328990.5 | H60: =YearMap!D6 -> 1530666.1 | I60: =A60&"|"&B60 -> B_Repurpose_Echo_lease_PimaTargets|FY2030
A61: =A11 -> B_Repurpose_Echo_ops_PimaTargets | B61: FY2026 | C61: =IF(D11=1,0, BaselineCalc!$B$7 + ROUND(I11*F11,0)) -> 0 | D61: =IF(E11=1,0, BaselineCalc!$B$8 + I11 - ROUND(I11*F11,0)) -> 446 | E61: =C61+D61 -> 446 | F61: =YearMap!B2 -> 5499.576 | G61: =YearMap!C2 -> 1203999.8 | H61: =YearMap!D2 -> 1386707.9 | I61: =A61&"|"&B61 -> B_Repurpose_Echo_ops_PimaTargets|FY2026
A62: =A11 -> B_Repurpose_Echo_ops_PimaTargets | B62: FY2027 | C62: =IF(D11=1,0, BaselineCalc!$B$7 + ROUND(J11*F11,0)) -> 0 | D62: =IF(E11=1,0, BaselineCalc!$B$8 + J11 - ROUND(J11*F11,0)) -> 446 | E62: =C62+D62 -> 446 | F62: =YearMap!B3 -> 5637.0654 | G62: =YearMap!C3 -> 1234099.8 | H62: =YearMap!D3 -> 1421375.6 | I62: =A62&"|"&B62 -> B_Repurpose_Echo_ops_PimaTargets|FY2027
A63: =A11 -> B_Repurpose_Echo_ops_PimaTargets | B63: FY2028 | C63: =IF(D11=1,0, BaselineCalc!$B$7 + ROUND(K11*F11,0)) -> 0 | D63: =IF(E11=1,0, BaselineCalc!$B$8 + K11 - ROUND(K11*F11,0)) -> 446 | E63: =C63+D63 -> 446 | F63: =YearMap!B4 -> 5777.992 | G63: =YearMap!C4 -> 1264952.3 | H63: =YearMap!D4 -> 1456910 | I63: =A63&"|"&B63 -> B_Repurpose_Echo_ops_PimaTargets|FY2028
A64: =A11 -> B_Repurpose_Echo_ops_PimaTargets | B64: FY2029 | C64: =IF(D11=1,0, BaselineCalc!$B$7 + ROUND(L11*F11,0)) -> 0 | D64: =IF(E11=1,0, BaselineCalc!$B$8 + L11 - ROUND(L11*F11,0)) -> 446 | E64: =C64+D64 -> 446 | F64: =YearMap!B5 -> 5922.4418 | G64: =YearMap!C5 -> 1296576.1 | H64: =YearMap!D5 -> 1493332.7 | I64: =A64&"|"&B64 -> B_Repurpose_Echo_ops_PimaTargets|FY2029
A65: =A11 -> B_Repurpose_Echo_ops_PimaTargets | B65: FY2030 | C65: =IF(D11=1,0, BaselineCalc!$B$7 + ROUND(M11*F11,0)) -> 0 | D65: =IF(E11=1,0, BaselineCalc!$B$8 + M11 - ROUND(M11*F11,0)) -> 446 | E65: =C65+D65 -> 446 | F65: =YearMap!B6 -> 6070.5029 | G65: =YearMap!C6 -> 1328990.5 | H65: =YearMap!D6 -> 1530666.1 | I65: =A65&"|"&B65 -> B_Repurpose_Echo_ops_PimaTargets|FY2030
A66: =A12 -> C_Repurpose_Pima_lease_EchoGHub_EchoTargets | B66: FY2026 | C66: =IF(D12=1,0, BaselineCalc!$B$7 + ROUND(I12*F12,0)) -> 257 | D66: =IF(E12=1,0, BaselineCalc!$B$8 + I12 - ROUND(I12*F12,0)) -> 0 | E66: =C66+D66 -> 257 | F66: =YearMap!B2 -> 5499.576 | G66: =YearMap!C2 -> 1203999.8 | H66: =YearMap!D2 -> 1386707.9 | I66: =A66&"|"&B66 -> C_Repurpose_Pima_lease_EchoGHub_EchoTargets|FY2026
A67: =A12 -> C_Repurpose_Pima_lease_EchoGHub_EchoTargets | B67: FY2027 | C67: =IF(D12=1,0, BaselineCalc!$B$7 + ROUND(J12*F12,0)) -> 257 | D67: =IF(E12=1,0, BaselineCalc!$B$8 + J12 - ROUND(J12*F12,0)) -> 0 | E67: =C67+D67 -> 257 | F67: =YearMap!B3 -> 5637.0654 | G67: =YearMap!C3 -> 1234099.8 | H67: =YearMap!D3 -> 1421375.6 | I67: =A67&"|"&B67 -> C_Repurpose_Pima_lease_EchoGHub_EchoTargets|FY2027
A68: =A12 -> C_Repurpose_Pima_lease_EchoGHub_EchoTargets | B68: FY2028 | C68: =IF(D12=1,0, BaselineCalc!$B$7 + ROUND(K12*F12,0)) -> 257 | D68: =IF(E12=1,0, BaselineCalc!$B$8 + K12 - ROUND(K12*F12,0)) -> 0 | E68: =C68+D68 -> 257 | F68: =YearMap!B4 -> 5777.992 | G68: =YearMap!C4 -> 1264952.3 | H68: =YearMap!D4 -> 1456910 | I68: =A68&"|"&B68 -> C_Repurpose_Pima_lease_EchoGHub_EchoTargets|FY2028
A69: =A12 -> C_Repurpose_Pima_lease_EchoGHub_EchoTargets | B69: FY2029 | C69: =IF(D12=1,0, BaselineCalc!$B$7 + ROUND(L12*F12,0)) -> 257 | D69: =IF(E12=1,0, BaselineCalc!$B$8 + L12 - ROUND(L12*F12,0)) -> 0 | E69: =C69+D69 -> 257 | F69: =YearMap!B5 -> 5922.4418 | G69: =YearMap!C5 -> 1296576.1 | H69: =YearMap!D5 -> 1493332.7 | I69: =A69&"|"&B69 -> C_Repurpose_Pima_lease_EchoGHub_EchoTargets|FY2029
A70: =A12 -> C_Repurpose_Pima_lease_EchoGHub_EchoTargets | B70: FY2030 | C70: =IF(D12=1,0, BaselineCalc!$B$7 + ROUND(M12*F12,0)) -> 257 | D70: =IF(E12=1,0, BaselineCalc!$B$8 + M12 - ROUND(M12*F12,0)) -> 0 | E70: =C70+D70 -> 257 | F70: =YearMap!B6 -> 6070.5029 | G70: =YearMap!C6 -> 1328990.5 | H70: =YearMap!D6 -> 1530666.1 | I70: =A70&"|"&B70 -> C_Repurpose_Pima_lease_EchoGHub_EchoTargets|FY2030
A71: =A13 -> C_Repurpose_Pima_ops_EchoGHub_EchoTargets | B71: FY2026 | C71: =IF(D13=1,0, BaselineCalc!$B$7 + ROUND(I13*F13,0)) -> 457 | D71: =IF(E13=1,0, BaselineCalc!$B$8 + I13 - ROUND(I13*F13,0)) -> 0 | E71: =C71+D71 -> 457 | F71: =YearMap!B2 -> 5499.576 | G71: =YearMap!C2 -> 1203999.8 | H71: =YearMap!D2 -> 1386707.9 | I71: =A71&"|"&B71 -> C_Repurpose_Pima_ops_EchoGHub_EchoTargets|FY2026
A72: =A13 -> C_Repurpose_Pima_ops_EchoGHub_EchoTargets | B72: FY2027 | C72: =IF(D13=1,0, BaselineCalc!$B$7 + ROUND(J13*F13,0)) -> 457 | D72: =IF(E13=1,0, BaselineCalc!$B$8 + J13 - ROUND(J13*F13,0)) -> 0 | E72: =C72+D72 -> 457 | F72: =YearMap!B3 -> 5637.0654 | G72: =YearMap!C3 -> 1234099.8 | H72: =YearMap!D3 -> 1421375.6 | I72: =A72&"|"&B72 -> C_Repurpose_Pima_ops_EchoGHub_EchoTargets|FY2027
A73: =A13 -> C_Repurpose_Pima_ops_EchoGHub_EchoTargets | B73: FY2028 | C73: =IF(D13=1,0, BaselineCalc!$B$7 + ROUND(K13*F13,0)) -> 457 | D73: =IF(E13=1,0, BaselineCalc!$B$8 + K13 - ROUND(K13*F13,0)) -> 0 | E73: =C73+D73 -> 457 | F73: =YearMap!B4 -> 5777.992 | G73: =YearMap!C4 -> 1264952.3 | H73: =YearMap!D4 -> 1456910 | I73: =A73&"|"&B73 -> C_Repurpose_Pima_ops_EchoGHub_EchoTargets|FY2028
A74: =A13 -> C_Repurpose_Pima_ops_EchoGHub_EchoTargets | B74: FY2029 | C74: =IF(D13=1,0, BaselineCalc!$B$7 + ROUND(L13*F13,0)) -> 457 | D74: =IF(E13=1,0, BaselineCalc!$B$8 + L13 - ROUND(L13*F13,0)) -> 0 | E74: =C74+D74 -> 457 | F74: =YearMap!B5 -> 5922.4418 | G74: =YearMap!C5 -> 1296576.1 | H74: =YearMap!D5 -> 1493332.7 | I74: =A74&"|"&B74 -> C_Repurpose_Pima_ops_EchoGHub_EchoTargets|FY2029
A75: =A13 -> C_Repurpose_Pima_ops_EchoGHub_EchoTargets | B75: FY2030 | C75: =IF(D13=1,0, BaselineCalc!$B$7 + ROUND(M13*F13,0)) -> 457 | D75: =IF(E13=1,0, BaselineCalc!$B$8 + M13 - ROUND(M13*F13,0)) -> 0 | E75: =C75+D75 -> 457 | F75: =YearMap!B6 -> 6070.5029 | G75: =YearMap!C6 -> 1328990.5 | H75: =YearMap!D6 -> 1530666.1 | I75: =A75&"|"&B75 -> C_Repurpose_Pima_ops_EchoGHub_EchoTargets|FY2030

Sheet Other_Parameters
A1: Parameter | B1: Value | D1: Orig
A2: MarginalFactor_for_Overlay | B2: =Control_Center!C17 -> 0.4 | D2: 0.4
