Workbook

Sheet Dashboard
A1: SUSD Keep-Open vs Repurpose — Interactive Dashboard (v4.4)
A3: Pick scenarios & assumptions
D4: Metric | E4: A (baseline) | F4: X (compare)
A5: Baseline A (auto): | B5: A_Repurpose_Both_ops | D5: FY2030 Net ($) | E5: =INDEX(Summary_Costs!$C$2:$C$13, MATCH($B$5, Summary_Costs!$A$2:$A$13, 0)) -> 9062.2088 | F5: =INDEX(Summary_Costs!$C$2:$C$13, MATCH($B$6, Summary_Costs!$A$2:$A$13, 0)) -> 10448.423
A6: Compare to (X): | B6: G_DHub_EchoRamp | C6: D_Grow_Both_150 | D6: 5‑yr Avg Net ($) | E6: =INDEX(Summary_Costs!$E$2:$E$13, MATCH($B$5, Summary_Costs!$A$2:$A$13, 0)) -> 10537.171 | F6: =INDEX(Summary_Costs!$E$2:$E$13, MATCH($B$6, Summary_Costs!$A$2:$A$13, 0)) -> 10067.642
A7: Compare to (Y) [optional]: | B7: G_DHub_EchoRamp | D7: # students displaced | E7: =INDEX(Summary_Costs!$F$2:$F$13, MATCH($B$5, Summary_Costs!$A$2:$A$13, 0)) -> 553 | F7: =INDEX(Summary_Costs!$F$2:$F$13, MATCH($B$6, Summary_Costs!$A$2:$A$13, 0)) -> 0
D8: FY2030 # served (open & retained) | E8: =INDEX(Summary_Costs!$G$2:$G$13, MATCH($B$5, Summary_Costs!$A$2:$A$13, 0)) -> 414.75 | F8: =INDEX(Summary_Costs!$G$2:$G$13, MATCH($B$6, Summary_Costs!$A$2:$A$13, 0)) -> 703
D10: Δ vs A by FY2030 ($) | F10: =F5-E5 -> 1386.2137
D11: Δ vs A (5‑yr Avg) ($) | F11: =F6-E6 -> -469.52853
A15: Year | B15: A Net ($) | C15: X Net ($)
A16: FY2026 | B16: =SUMIFS(MultiYear_ProForma!$AA:$AA, MultiYear_ProForma!$B:$B, $B$5, MultiYear_ProForma!$C:$C, "FY2026") -> 4322025.1 | C16: =SUMIFS(MultiYear_ProForma!$AA:$AA, MultiYear_ProForma!$B:$B, $B$6, MultiYear_ProForma!$C:$C, "FY2026") -> 2863369.2
A17: FY2027 | B17: =SUMIFS(MultiYear_ProForma!$AA:$AA, MultiYear_ProForma!$B:$B, $B$5, MultiYear_ProForma!$C:$C, "FY2027") -> 1801374.6 | C17: =SUMIFS(MultiYear_ProForma!$AA:$AA, MultiYear_ProForma!$B:$B, $B$6, MultiYear_ProForma!$C:$C, "FY2027") -> 3052413.9
A18: FY2028 | B18: =SUMIFS(MultiYear_ProForma!$AA:$AA, MultiYear_ProForma!$B:$B, $B$5, MultiYear_ProForma!$C:$C, "FY2028") -> 1677844 | C18: =SUMIFS(MultiYear_ProForma!$AA:$AA, MultiYear_ProForma!$B:$B, $B$6, MultiYear_ProForma!$C:$C, "FY2028") -> 3251651.8
A19: FY2029 | B19: =SUMIFS(MultiYear_ProForma!$AA:$AA, MultiYear_ProForma!$B:$B, $B$5, MultiYear_ProForma!$C:$C, "FY2029") -> 1551311.9 | C19: =SUMIFS(MultiYear_ProForma!$AA:$AA, MultiYear_ProForma!$B:$B, $B$6, MultiYear_ProForma!$C:$C, "FY2029") -> 3351641.4
A20: FY2030 | B20: =SUMIFS(MultiYear_ProForma!$AA:$AA, MultiYear_ProForma!$B:$B, $B$5, MultiYear_ProForma!$C:$C, "FY2030") -> 1463127.3 | C20: =SUMIFS(MultiYear_ProForma!$AA:$AA, MultiYear_ProForma!$B:$B, $B$6, MultiYear_ProForma!$C:$C, "FY2030") -> 3454504.7
A25: Notes
A26: • 'Net ($)' = Comparable M&O costs minus base state aid on students served (open & retained). This is a two‑site view (Echo+Pima), not the entire district budget. • Positive Δ vs A means the comparator is more expensive than 'A_Repurpose_Both_ops' under the Parameters tab assumptions.

Sheet Cards
A1: Mini-Cards: A (Repurpose-Both) vs X and Y
A3: Comparator X | B3: =Dashboard!$B$6 -> G_DHub_EchoRamp | D3: Comparator Y | E3: =Dashboard!$B$7 -> G_DHub_EchoRamp
A4: r* needed (year/mode/h) | B4: =Dashboard!$I$23 -> 0 | D4: r* needed (year/mode/h) | E4: =Dashboard!$I$24 -> 0
A5: Δ FY2030 $/student | B5: =Dashboard!$I$26 -> 0 | D5: Δ FY2030 $/student | E5: =Dashboard!$I$27 -> 0
A6: Δ 5-yr Avg $/student | B6: =Dashboard!$I$28 -> 0 | D6: Δ 5-yr Avg $/student | E6: =Dashboard!$I$29 -> 0
A7: # displaced (A) | B7: =INDEX(Summary_Costs!$F:$F, MATCH(Dashboard!$B$5, Summary_Costs!$A:$A,0)) -> 553 | D7: # displaced (A) | E7: =INDEX(Summary_Costs!$F:$F, MATCH(Dashboard!$B$5, Summary_Costs!$A:$A,0)) -> 553
A8: # displaced (X) | B8: =INDEX(Summary_Costs!$F:$F, MATCH(Dashboard!$B$6, Summary_Costs!$A:$A,0)) -> 0 | D8: # displaced (Y) | E8: =INDEX(Summary_Costs!$F:$F, MATCH(Dashboard!$B$7, Summary_Costs!$A:$A,0)) -> 0
A9: Distinctiveness / Reversibility | B9: =Dashboard!$E$26 & " / " & Dashboard!$F$26 -> / | D9: Distinctiveness / Reversibility | E9: =Dashboard!$E$33 & " / " & Dashboard!$F$33 -> /

Sheet BaselineCalc
A1: Parameter | B1: Value | C1: Notes
A2: MO inflation | B2: 0.025 | C2: Annual inflation factor.
A3: Base MO per ADM (FY25) | B3: 9936 | C3: Working base for FY25.
A4: Fixed share of MO | B4: 0.3 | C4: Share treated as semi‑fixed (plant/insurance).
A5: Ops savings (keep‑open) | B5: 0.007 | C5: Light discipline if sites remain open (not used here).
A6: Extra savings (Co‑location) | B6: 0.015 | C6: Incremental savings for co‑location (not used here).
A7: Echo base ADM | B7: 257
A8: Pima base ADM | B8: 296
A9: Total base ADM | B9: =B7+B8 -> 553 | C9: Echo base ADM + Pima base ADM
A12: Helper / Derivation | B12: FY26 | C12: FY27 | D12: FY28 | E12: FY29 | F12: FY30 | G12: Notes
A13: Base total MO (FY25) | B13: =B9*B3 -> 5494608 | C13: =C14/$B$4 -> 5631973.2 | D13: =D14/$B$4 -> 5772772.5 | E13: =E14/$B$4 -> 5917091.8 | F13: =F14/$B$4 -> 6065019.1 | G13: Total ADM × Base MO/ADM | K13: B13 = B9*B3 (Base total MO, FY25)
A14: Fixed MO (FY25) | B14: =B13*B4 -> 1648382.4 | C14: =B17 -> 1689592 | D14: =C17 -> 1731831.8 | E14: =D17 -> 1775127.6 | F14: =E17 -> 1819505.7 | G14: Fixed = Base total × Fixed share | K14: B14 = B13*B4 (Fixed MO, FY25)
A15: Var per student (FY25) | B15: =(B13-B14)/B9 -> 6955.2 | C15: =B18 -> 7129.08 | D15: =C18 -> 7307.307 | E15: =D18 -> 7489.9897 | F15: =E18 -> 7677.2394 | G15: Variable = (Base total − Fixed)/Total ADM | K15: B15 = (B13–B14)/B9 (Variable $/student, FY25)
A17: Fixed total ($) | B17: =$B$14*(1+$B$2)^1 -> 1689592 | C17: =$B$14*(1+$B$2)^2 -> 1731831.8 | D17: =$B$14*(1+$B$2)^3 -> 1775127.6 | E17: =$B$14*(1+$B$2)^4 -> 1819505.7 | F17: =$B$14*(1+$B$2)^5 -> 1864993.4
A18: Var unit ($/student) | B18: =$B$15*(1+$B$2)^1 -> 7129.08 | C18: =$B$15*(1+$B$2)^2 -> 7307.307 | D18: =$B$15*(1+$B$2)^3 -> 7489.9897 | E18: =$B$15*(1+$B$2)^4 -> 7677.2394 | F18: =$B$15*(1+$B$2)^5 -> 7869.1704
A19: Echo fixed ($) | B19: =B17*($B$7/$B$9) -> 785217.24 | C19: =C17*($B$7/$B$9) -> 804847.67 | D19: =D17*($B$7/$B$9) -> 824968.86 | E19: =E17*($B$7/$B$9) -> 845593.08 | F19: =F17*($B$7/$B$9) -> 866732.91
A20: Pima fixed ($) | B20: =B17*($B$8/$B$9) -> 904374.72 | C20: =C17*($B$8/$B$9) -> 926984.09 | D20: =D17*($B$8/$B$9) -> 950158.69 | E20: =E17*($B$8/$B$9) -> 973912.66 | F20: =F17*($B$8/$B$9) -> 998260.47
A21: Repurpose TI per closed site (FY26) | B21: 1200000
A22: Retention r (central) | B22: 0.75
A24: Notes
A25: All formulas are same‑sheet and reference the Parameter cells above.
A26: Base State Aid per ADM (FY26) | B26: 5113 | C26: Editable; ADE base aid.
A27: Aid inflation (annual) | B27: 0.02 | C27: Editable; assumed growth in base aid.

Sheet YearMap
A1: Year | B1: VarUnit$ | C1: EchoFixed$ | D1: PimaFixed$ | E1: h | F1: f_lease | G1: f_ops | H1: YearIdx | I1: Aid$
A2: FY2026 | B2: =BaselineCalc!B18 -> 7129.08 | C2: =BaselineCalc!B19 -> 785217.24 | D2: =BaselineCalc!B20 -> 904374.72 | E2: 1000 | F2: 0.4 | G2: 0.4 | H2: 1 | I2: =BaselineCalc!$B$26*(1+BaselineCalc!$B$27)^(H2-1) -> 5113
A3: FY2027 | B3: =BaselineCalc!C18 -> 7307.307 | C3: =BaselineCalc!C19 -> 804847.67 | D3: =BaselineCalc!C20 -> 926984.09 | E3: 800 | F3: 0.3 | G3: 0.35 | H3: 2 | I3: =BaselineCalc!$B$26*(1+BaselineCalc!$B$27)^(H3-1) -> 5215.26
A4: FY2028 | B4: =BaselineCalc!D18 -> 7489.9897 | C4: =BaselineCalc!D19 -> 824968.86 | D4: =BaselineCalc!D20 -> 950158.69 | E4: 600 | F4: 0.2 | G4: 0.3 | H4: 3 | I4: =BaselineCalc!$B$26*(1+BaselineCalc!$B$27)^(H4-1) -> 5319.5652
A5: FY2029 | B5: =BaselineCalc!E18 -> 7677.2394 | C5: =BaselineCalc!E19 -> 845593.08 | D5: =BaselineCalc!E20 -> 973912.66 | E5: 400 | F5: 0.1 | G5: 0.25 | H5: 4 | I5: =BaselineCalc!$B$26*(1+BaselineCalc!$B$27)^(H5-1) -> 5425.9565
A6: FY2030 | B6: =BaselineCalc!F18 -> 7869.1704 | C6: =BaselineCalc!F19 -> 866732.91 | D6: =BaselineCalc!F20 -> 998260.47 | E6: 300 | F6: 0 | G6: 0.2 | H6: 5 | I6: =BaselineCalc!$B$26*(1+BaselineCalc!$B$27)^(H6-1) -> 5534.4756

Sheet MultiYear_ProForma
A1: =Y1 -> Key | B1: ScenarioKey | C1: Year | D1: Echo_ADM | E1: Pima_ADM | F1: Total_ADM | G1: VarUnit$ | H1: EchoFixed$ | I1: PimaFixed$ | J1: OpsFactor | K1: ExtraSave | L1: EchoPotential_ADM | M1: PimaPotential_ADM | N1: Displaced_ADM | O1: Retained_ADM | P1: h | Q1: CarryFrac | R1: EchoFixedEff$ | S1: PimaFixedEff$ | T1: TI_adds$ | U1: SiteCost$ | V1: RetainedSvc$ | W1: Comparable_MO$ | X1: Comparable_per_Student$ | Y1: Key | Z1: Aid_per_ADM | AA1: Net_MO_after_aid$ | AB1: Net_per_served$
A2: =Y2 -> D_Grow_Both_0|FY2026 | B2: =Scenarios!A2 -> D_Grow_Both_0 | C2: FY2026 | D2: =IF(Scenarios!D2=1,0, L2) -> 257 | E2: =IF(Scenarios!E2=1,0, M2) -> 296 | F2: =D2+E2 -> 553 | G2: =YearMap!B2 -> 7129.08 | H2: =YearMap!C2 -> 785217.24 | I2: =YearMap!D2 -> 904374.72 | J2: =1-BaselineCalc!$B$5 -> 0.993 | K2: =Scenarios!G2 -> 0 | L2: =BaselineCalc!$B$7 + ROUND(Scenarios!I2*Scenarios!F2,0) -> 257 | M2: =BaselineCalc!$B$8 + Scenarios!I2 - ROUND(Scenarios!I2*Scenarios!F2,0) -> 296 | N2: =(L2-D2) + (M2-E2) -> 0 | O2: =BaselineCalc!$B$22 * N2 -> 0 | P2: =YearMap!E2 -> 1000 | Q2: =IF(Scenarios!N2="lease", YearMap!F2, YearMap!G2) -> 0.4 | R2: =IF(Scenarios!D2=1, Q2*H2, H2) -> 785217.24 | S2: =IF(Scenarios!E2=1, Q2*I2, I2) -> 904374.72 | T2: =IF(C2="FY2026", (Scenarios!D2+Scenarios!E2)*BaselineCalc!$B$21, 0) -> 0 | U2: =(R2+S2+G2*F2)*J2*(1-K2) -> 5592549.4 | V2: =O2*(G2+P2) -> 0 | W2: =U2+V2+T2 -> 5592549.4 | X2: =IF(F2+O2>0, W2/(F2+O2),"") -> 10113.109 | Y2: =B2&"|"&C2 -> D_Grow_Both_0|FY2026 | Z2: =INDEX(YearMap!$I$2:$I$6, MATCH(C2, YearMap!$A$2:$A$6, 0)) -> 5113 | AA2: =$W2 - $Z2 * (IF(LEFT($B2,2)="A_", $O2, IF(LEFT($B2,2)="B_", $M2+$O2, IF(LEFT($B2,2)="C_", $L2+$O2, $F2)))) -> 2765060.4 | AB2: =IF((IF(LEFT($B2,2)="A_", $O2, IF(LEFT($B2,2)="B_", $M2+$O2, IF(LEFT($B2,2)="C_", $L2+$O2, $F2))))>0, $AA2 / (IF(LEFT($B2,2)="A_", $O2, IF(LEFT($B2,2)="B_", $M2+$O2, IF(LEFT($B2,2)="C_", $L2+$O2, $F2)))), "") -> 5000.1092
A3: =Y3 -> D_Grow_Both_0|FY2027 | B3: =Scenarios!A2 -> D_Grow_Both_0 | C3: FY2027 | D3: =IF(Scenarios!D2=1,0, L3) -> 257 | E3: =IF(Scenarios!E2=1,0, M3) -> 296 | F3: =D3+E3 -> 553 | G3: =YearMap!B3 -> 7307.307 | H3: =YearMap!C3 -> 804847.67 | I3: =YearMap!D3 -> 926984.09 | J3: =1-BaselineCalc!$B$5 -> 0.993 | K3: =Scenarios!G2 -> 0 | L3: =BaselineCalc!$B$7 + ROUND(Scenarios!J2*Scenarios!F2,0) -> 257 | M3: =BaselineCalc!$B$8 + Scenarios!J2 - ROUND(Scenarios!J2*Scenarios!F2,0) -> 296 | N3: =(L3-D3) + (M3-E3) -> 0 | O3: =BaselineCalc!$B$22 * N3 -> 0 | P3: =YearMap!E3 -> 800 | Q3: =IF(Scenarios!N2="lease", YearMap!F3, YearMap!G3) -> 0.35 | R3: =IF(Scenarios!D2=1, Q3*H3, H3) -> 804847.67 | S3: =IF(Scenarios!E2=1, Q3*I3, I3) -> 926984.09 | T3: =IF(C3="FY2026", (Scenarios!D2+Scenarios!E2)*BaselineCalc!$B$21, 0) -> 0 | U3: =(R3+S3+G3*F3)*J3*(1-K3) -> 5732363.1 | V3: =O3*(G3+P3) -> 0 | W3: =U3+V3+T3 -> 5732363.1 | X3: =IF(F3+O3>0, W3/(F3+O3),"") -> 10365.937 | Y3: =B3&"|"&C3 -> D_Grow_Both_0|FY2027 | Z3: =INDEX(YearMap!$I$2:$I$6, MATCH(C3, YearMap!$A$2:$A$6, 0)) -> 5215.26 | AA3: =$W3 - $Z3 * (IF(LEFT($B3,2)="A_", $O3, IF(LEFT($B3,2)="B_", $M3+$O3, IF(LEFT($B3,2)="C_", $L3+$O3, $F3)))) -> 2848324.3 | AB3: =IF((IF(LEFT($B3,2)="A_", $O3, IF(LEFT($B3,2)="B_", $M3+$O3, IF(LEFT($B3,2)="C_", $L3+$O3, $F3))))>0, $AA3 / (IF(LEFT($B3,2)="A_", $O3, IF(LEFT($B3,2)="B_", $M3+$O3, IF(LEFT($B3,2)="C_", $L3+$O3, $F3)))), "") -> 5150.6769
A4: =Y4 -> D_Grow_Both_0|FY2028 | B4: =Scenarios!A2 -> D_Grow_Both_0 | C4: FY2028 | D4: =IF(Scenarios!D2=1,0, L4) -> 257 | E4: =IF(Scenarios!E2=1,0, M4) -> 296 | F4: =D4+E4 -> 553 | G4: =YearMap!B4 -> 7489.9897 | H4: =YearMap!C4 -> 824968.86 | I4: =YearMap!D4 -> 950158.69 | J4: =1-BaselineCalc!$B$5 -> 0.993 | K4: =Scenarios!G2 -> 0 | L4: =BaselineCalc!$B$7 + ROUND(Scenarios!K2*Scenarios!F2,0) -> 257 | M4: =BaselineCalc!$B$8 + Scenarios!K2 - ROUND(Scenarios!K2*Scenarios!F2,0) -> 296 | N4: =(L4-D4) + (M4-E4) -> 0 | O4: =BaselineCalc!$B$22 * N4 -> 0 | P4: =YearMap!E4 -> 600 | Q4: =IF(Scenarios!N2="lease", YearMap!F4, YearMap!G4) -> 0.3 | R4: =IF(Scenarios!D2=1, Q4*H4, H4) -> 824968.86 | S4: =IF(Scenarios!E2=1, Q4*I4, I4) -> 950158.69 | T4: =IF(C4="FY2026", (Scenarios!D2+Scenarios!E2)*BaselineCalc!$B$21, 0) -> 0 | U4: =(R4+S4+G4*F4)*J4*(1-K4) -> 5875672.2 | V4: =O4*(G4+P4) -> 0 | W4: =U4+V4+T4 -> 5875672.2 | X4: =IF(F4+O4>0, W4/(F4+O4),"") -> 10625.085 | Y4: =B4&"|"&C4 -> D_Grow_Both_0|FY2028 | Z4: =INDEX(YearMap!$I$2:$I$6, MATCH(C4, YearMap!$A$2:$A$6, 0)) -> 5319.5652 | AA4: =$W4 - $Z4 * (IF(LEFT($B4,2)="A_", $O4, IF(LEFT($B4,2)="B_", $M4+$O4, IF(LEFT($B4,2)="C_", $L4+$O4, $F4)))) -> 2933952.6 | AB4: =IF((IF(LEFT($B4,2)="A_", $O4, IF(LEFT($B4,2)="B_", $M4+$O4, IF(LEFT($B4,2)="C_", $L4+$O4, $F4))))>0, $AA4 / (IF(LEFT($B4,2)="A_", $O4, IF(LEFT($B4,2)="B_", $M4+$O4, IF(LEFT($B4,2)="C_", $L4+$O4, $F4)))), "") -> 5305.5202
A5: =Y5 -> D_Grow_Both_0|FY2029 | B5: =Scenarios!A2 -> D_Grow_Both_0 | C5: FY2029 | D5: =IF(Scenarios!D2=1,0, L5) -> 257 | E5: =IF(Scenarios!E2=1,0, M5) -> 296 | F5: =D5+E5 -> 553 | G5: =YearMap!B5 -> 7677.2394 | H5: =YearMap!C5 -> 845593.08 | I5: =YearMap!D5 -> 973912.66 | J5: =1-BaselineCalc!$B$5 -> 0.993 | K5: =Scenarios!G2 -> 0 | L5: =BaselineCalc!$B$7 + ROUND(Scenarios!L2*Scenarios!F2,0) -> 257 | M5: =BaselineCalc!$B$8 + Scenarios!L2 - ROUND(Scenarios!L2*Scenarios!F2,0) -> 296 | N5: =(L5-D5) + (M5-E5) -> 0 | O5: =BaselineCalc!$B$22 * N5 -> 0 | P5: =YearMap!E5 -> 400 | Q5: =IF(Scenarios!N2="lease", YearMap!F5, YearMap!G5) -> 0.25 | R5: =IF(Scenarios!D2=1, Q5*H5, H5) -> 845593.08 | S5: =IF(Scenarios!E2=1, Q5*I5, I5) -> 973912.66 | T5: =IF(C5="FY2026", (Scenarios!D2+Scenarios!E2)*BaselineCalc!$B$21, 0) -> 0 | U5: =(R5+S5+G5*F5)*J5*(1-K5) -> 6022564 | V5: =O5*(G5+P5) -> 0 | W5: =U5+V5+T5 -> 6022564 | X5: =IF(F5+O5>0, W5/(F5+O5),"") -> 10890.712 | Y5: =B5&"|"&C5 -> D_Grow_Both_0|FY2029 | Z5: =INDEX(YearMap!$I$2:$I$6, MATCH(C5, YearMap!$A$2:$A$6, 0)) -> 5425.9565 | AA5: =$W5 - $Z5 * (IF(LEFT($B5,2)="A_", $O5, IF(LEFT($B5,2)="B_", $M5+$O5, IF(LEFT($B5,2)="C_", $L5+$O5, $F5)))) -> 3022010.1 | AB5: =IF((IF(LEFT($B5,2)="A_", $O5, IF(LEFT($B5,2)="B_", $M5+$O5, IF(LEFT($B5,2)="C_", $L5+$O5, $F5))))>0, $AA5 / (IF(LEFT($B5,2)="A_", $O5, IF(LEFT($B5,2)="B_", $M5+$O5, IF(LEFT($B5,2)="C_", $L5+$O5, $F5)))), "") -> 5464.756
A6: =Y6 -> D_Grow_Both_0|FY2030 | B6: =Scenarios!A2 -> D_Grow_Both_0 | C6: FY2030 | D6: =IF(Scenarios!D2=1,0, L6) -> 257 | E6: =IF(Scenarios!E2=1,0, M6) -> 296 | F6: =D6+E6 -> 553 | G6: =YearMap!B6 -> 7869.1704 | H6: =YearMap!C6 -> 866732.91 | I6: =YearMap!D6 -> 998260.47 | J6: =1-BaselineCalc!$B$5 -> 0.993 | K6: =Scenarios!G2 -> 0 | L6: =BaselineCalc!$B$7 + ROUND(Scenarios!M2*Scenarios!F2,0) -> 257 | M6: =BaselineCalc!$B$8 + Scenarios!M2 - ROUND(Scenarios!M2*Scenarios!F2,0) -> 296 | N6: =(L6-D6) + (M6-E6) -> 0 | O6: =BaselineCalc!$B$22 * N6 -> 0 | P6: =YearMap!E6 -> 300 | Q6: =IF(Scenarios!N2="lease", YearMap!F6, YearMap!G6) -> 0.2 | R6: =IF(Scenarios!D2=1, Q6*H6, H6) -> 866732.91 | S6: =IF(Scenarios!E2=1, Q6*I6, I6) -> 998260.47 | T6: =IF(C6="FY2026", (Scenarios!D2+Scenarios!E2)*BaselineCalc!$B$21, 0) -> 0 | U6: =(R6+S6+G6*F6)*J6*(1-K6) -> 6173128.1 | V6: =O6*(G6+P6) -> 0 | W6: =U6+V6+T6 -> 6173128.1 | X6: =IF(F6+O6>0, W6/(F6+O6),"") -> 11162.98 | Y6: =B6&"|"&C6 -> D_Grow_Both_0|FY2030 | Z6: =INDEX(YearMap!$I$2:$I$6, MATCH(C6, YearMap!$A$2:$A$6, 0)) -> 5534.4756 | AA6: =$W6 - $Z6 * (IF(LEFT($B6,2)="A_", $O6, IF(LEFT($B6,2)="B_", $M6+$O6, IF(LEFT($B6,2)="C_", $L6+$O6, $F6)))) -> 3112563.1 | AB6: =IF((IF(LEFT($B6,2)="A_", $O6, IF(LEFT($B6,2)="B_", $M6+$O6, IF(LEFT($B6,2)="C_", $L6+$O6, $F6))))>0, $AA6 / (IF(LEFT($B6,2)="A_", $O6, IF(LEFT($B6,2)="B_", $M6+$O6, IF(LEFT($B6,2)="C_", $L6+$O6, $F6)))), "") -> 5628.5047
A7: =Y7 -> E_StatusQuo_Targets_0|FY2026 | B7: =Scenarios!A3 -> E_StatusQuo_Targets_0 | C7: FY2026 | D7: =IF(Scenarios!D3=1,0, L7) -> 257 | E7: =IF(Scenarios!E3=1,0, M7) -> 296 | F7: =D7+E7 -> 553 | G7: =YearMap!B2 -> 7129.08 | H7: =YearMap!C2 -> 785217.24 | I7: =YearMap!D2 -> 904374.72 | J7: =1-BaselineCalc!$B$5 -> 0.993 | K7: =Scenarios!G3 -> 0 | L7: =BaselineCalc!$B$7 + ROUND(Scenarios!I3*Scenarios!F3,0) -> 257 | M7: =BaselineCalc!$B$8 + Scenarios!I3 - ROUND(Scenarios!J3*Scenarios!F3,0) -> 296 | N7: =(L7-D7) + (M7-E7) -> 0 | O7: =BaselineCalc!$B$22 * N7 -> 0 | P7: =YearMap!E2 -> 1000 | Q7: =IF(Scenarios!N3="lease", YearMap!F2, YearMap!G2) -> 0.4 | R7: =IF(Scenarios!D3=1, Q7*H7, H7) -> 785217.24 | S7: =IF(Scenarios!E3=1, Q7*I7, I7) -> 904374.72 | T7: =IF(C7="FY2026", (Scenarios!D3+Scenarios!E3)*BaselineCalc!$B$21, 0) -> 0 | U7: =(R7+S7+G7*F7)*J7*(1-K7) -> 5592549.4 | V7: =O7*(G7+P7) -> 0 | W7: =U7+V7+T7 -> 5592549.4 | X7: =IF(F7+O7>0, W7/(F7+O7),"") -> 10113.109 | Y7: =B7&"|"&C7 -> E_StatusQuo_Targets_0|FY2026 | Z7: =INDEX(YearMap!$I$2:$I$6, MATCH(C7, YearMap!$A$2:$A$6, 0)) -> 5113 | AA7: =$W7 - $Z7 * (IF(LEFT($B7,2)="A_", $O7, IF(LEFT($B7,2)="B_", $M7+$O7, IF(LEFT($B7,2)="C_", $L7+$O7, $F7)))) -> 2765060.4 | AB7: =IF((IF(LEFT($B7,2)="A_", $O7, IF(LEFT($B7,2)="B_", $M7+$O7, IF(LEFT($B7,2)="C_", $L7+$O7, $F7))))>0, $AA7 / (IF(LEFT($B7,2)="A_", $O7, IF(LEFT($B7,2)="B_", $M7+$O7, IF(LEFT($B7,2)="C_", $L7+$O7, $F7)))), "") -> 5000.1092
A8: =Y8 -> E_StatusQuo_Targets_0|FY2027 | B8: =Scenarios!A3 -> E_StatusQuo_Targets_0 | C8: FY2027 | D8: =IF(Scenarios!D3=1,0, L8) -> 257 | E8: =IF(Scenarios!E3=1,0, M8) -> 296 | F8: =D8+E8 -> 553 | G8: =YearMap!B3 -> 7307.307 | H8: =YearMap!C3 -> 804847.67 | I8: =YearMap!D3 -> 926984.09 | J8: =1-BaselineCalc!$B$5 -> 0.993 | K8: =Scenarios!G3 -> 0 | L8: =BaselineCalc!$B$7 + ROUND(Scenarios!J3*Scenarios!F3,0) -> 257 | M8: =BaselineCalc!$B$8 + Scenarios!J3 - ROUND(Scenarios!J3*Scenarios!F3,0) -> 296 | N8: =(L8-D8) + (M8-E8) -> 0 | O8: =BaselineCalc!$B$22 * N8 -> 0 | P8: =YearMap!E3 -> 800 | Q8: =IF(Scenarios!N3="lease", YearMap!F3, YearMap!G3) -> 0.35 | R8: =IF(Scenarios!D3=1, Q8*H8, H8) -> 804847.67 | S8: =IF(Scenarios!E3=1, Q8*I8, I8) -> 926984.09 | T8: =IF(C8="FY2026", (Scenarios!D3+Scenarios!E3)*BaselineCalc!$B$21, 0) -> 0 | U8: =(R8+S8+G8*F8)*J8*(1-K8) -> 5732363.1 | V8: =O8*(G8+P8) -> 0 | W8: =U8+V8+T8 -> 5732363.1 | X8: =IF(F8+O8>0, W8/(F8+O8),"") -> 10365.937 | Y8: =B8&"|"&C8 -> E_StatusQuo_Targets_0|FY2027 | Z8: =INDEX(YearMap!$I$2:$I$6, MATCH(C8, YearMap!$A$2:$A$6, 0)) -> 5215.26 | AA8: =$W8 - $Z8 * (IF(LEFT($B8,2)="A_", $O8, IF(LEFT($B8,2)="B_", $M8+$O8, IF(LEFT($B8,2)="C_", $L8+$O8, $F8)))) -> 2848324.3 | AB8: =IF((IF(LEFT($B8,2)="A_", $O8, IF(LEFT($B8,2)="B_", $M8+$O8, IF(LEFT($B8,2)="C_", $L8+$O8, $F8))))>0, $AA8 / (IF(LEFT($B8,2)="A_", $O8, IF(LEFT($B8,2)="B_", $M8+$O8, IF(LEFT($B8,2)="C_", $L8+$O8, $F8)))), "") -> 5150.6769
A9: =Y9 -> E_StatusQuo_Targets_0|FY2028 | B9: =Scenarios!A3 -> E_StatusQuo_Targets_0 | C9: FY2028 | D9: =IF(Scenarios!D3=1,0, L9) -> 257 | E9: =IF(Scenarios!E3=1,0, M9) -> 296 | F9: =D9+E9 -> 553 | G9: =YearMap!B4 -> 7489.9897 | H9: =YearMap!C4 -> 824968.86 | I9: =YearMap!D4 -> 950158.69 | J9: =1-BaselineCalc!$B$5 -> 0.993 | K9: =Scenarios!G3 -> 0 | L9: =BaselineCalc!$B$7 + ROUND(Scenarios!K3*Scenarios!F3,0) -> 257 | M9: =BaselineCalc!$B$8 + Scenarios!K3 - ROUND(Scenarios!K3*Scenarios!F3,0) -> 296 | N9: =(L9-D9) + (M9-E9) -> 0 | O9: =BaselineCalc!$B$22 * N9 -> 0 | P9: =YearMap!E4 -> 600 | Q9: =IF(Scenarios!N3="lease", YearMap!F4, YearMap!G4) -> 0.3 | R9: =IF(Scenarios!D3=1, Q9*H9, H9) -> 824968.86 | S9: =IF(Scenarios!E3=1, Q9*I9, I9) -> 950158.69 | T9: =IF(C9="FY2026", (Scenarios!D3+Scenarios!E3)*BaselineCalc!$B$21, 0) -> 0 | U9: =(R9+S9+G9*F9)*J9*(1-K9) -> 5875672.2 | V9: =O9*(G9+P9) -> 0 | W9: =U9+V9+T9 -> 5875672.2 | X9: =IF(F9+O9>0, W9/(F9+O9),"") -> 10625.085 | Y9: =B9&"|"&C9 -> E_StatusQuo_Targets_0|FY2028 | Z9: =INDEX(YearMap!$I$2:$I$6, MATCH(C9, YearMap!$A$2:$A$6, 0)) -> 5319.5652 | AA9: =$W9 - $Z9 * (IF(LEFT($B9,2)="A_", $O9, IF(LEFT($B9,2)="B_", $M9+$O9, IF(LEFT($B9,2)="C_", $L9+$O9, $F9)))) -> 2933952.6 | AB9: =IF((IF(LEFT($B9,2)="A_", $O9, IF(LEFT($B9,2)="B_", $M9+$O9, IF(LEFT($B9,2)="C_", $L9+$O9, $F9))))>0, $AA9 / (IF(LEFT($B9,2)="A_", $O9, IF(LEFT($B9,2)="B_", $M9+$O9, IF(LEFT($B9,2)="C_", $L9+$O9, $F9)))), "") -> 5305.5202
A10: =Y10 -> E_StatusQuo_Targets_0|FY2029 | B10: =Scenarios!A3 -> E_StatusQuo_Targets_0 | C10: FY2029 | D10: =IF(Scenarios!D3=1,0, L10) -> 257 | E10: =IF(Scenarios!E3=1,0, M10) -> 296 | F10: =D10+E10 -> 553 | G10: =YearMap!B5 -> 7677.2394 | H10: =YearMap!C5 -> 845593.08 | I10: =YearMap!D5 -> 973912.66 | J10: =1-BaselineCalc!$B$5 -> 0.993 | K10: =Scenarios!G3 -> 0 | L10: =BaselineCalc!$B$7 + ROUND(Scenarios!L3*Scenarios!F3,0) -> 257 | M10: =BaselineCalc!$B$8 + Scenarios!L3 - ROUND(Scenarios!L3*Scenarios!F3,0) -> 296 | N10: =(L10-D10) + (M10-E10) -> 0 | O10: =BaselineCalc!$B$22 * N10 -> 0 | P10: =YearMap!E5 -> 400 | Q10: =IF(Scenarios!N3="lease", YearMap!F5, YearMap!G5) -> 0.25 | R10: =IF(Scenarios!D3=1, Q10*H10, H10) -> 845593.08 | S10: =IF(Scenarios!E3=1, Q10*I10, I10) -> 973912.66 | T10: =IF(C10="FY2026", (Scenarios!D3+Scenarios!E3)*BaselineCalc!$B$21, 0) -> 0 | U10: =(R10+S10+G10*F10)*J10*(1-K10) -> 6022564 | V10: =O10*(G10+P10) -> 0 | W10: =U10+V10+T10 -> 6022564 | X10: =IF(F10+O10>0, W10/(F10+O10),"") -> 10890.712 | Y10: =B10&"|"&C10 -> E_StatusQuo_Targets_0|FY2029 | Z10: =INDEX(YearMap!$I$2:$I$6, MATCH(C10, YearMap!$A$2:$A$6, 0)) -> 5425.9565 | AA10: =$W10 - $Z10 * (IF(LEFT($B10,2)="A_", $O10, IF(LEFT($B10,2)="B_", $M10+$O10, IF(LEFT($B10,2)="C_", $L10+$O10, $F10)))) -> 3022010.1 | AB10: =IF((IF(LEFT($B10,2)="A_", $O10, IF(LEFT($B10,2)="B_", $M10+$O10, IF(LEFT($B10,2)="C_", $L10+$O10, $F10))))>0, $AA10 / (IF(LEFT($B10,2)="A_", $O10, IF(LEFT($B10,2)="B_", $M10+$O10, IF(LEFT($B10,2)="C_", $L10+$O10, $F10)))), "") -> 5464.756
A11: =Y11 -> E_StatusQuo_Targets_0|FY2030 | B11: =Scenarios!A3 -> E_StatusQuo_Targets_0 | C11: FY2030 | D11: =IF(Scenarios!D3=1,0, L11) -> 257 | E11: =IF(Scenarios!E3=1,0, M11) -> 296 | F11: =D11+E11 -> 553 | G11: =YearMap!B6 -> 7869.1704 | H11: =YearMap!C6 -> 866732.91 | I11: =YearMap!D6 -> 998260.47 | J11: =1-BaselineCalc!$B$5 -> 0.993 | K11: =Scenarios!G3 -> 0 | L11: =BaselineCalc!$B$7 + ROUND(Scenarios!M3*Scenarios!F3,0) -> 257 | M11: =BaselineCalc!$B$8 + Scenarios!M3 - ROUND(Scenarios!M3*Scenarios!F3,0) -> 296 | N11: =(L11-D11) + (M11-E11) -> 0 | O11: =BaselineCalc!$B$22 * N11 -> 0 | P11: =YearMap!E6 -> 300 | Q11: =IF(Scenarios!N3="lease", YearMap!F6, YearMap!G6) -> 0.2 | R11: =IF(Scenarios!D3=1, Q11*H11, H11) -> 866732.91 | S11: =IF(Scenarios!E3=1, Q11*I11, I11) -> 998260.47 | T11: =IF(C11="FY2026", (Scenarios!D3+Scenarios!E3)*BaselineCalc!$B$21, 0) -> 0 | U11: =(R11+S11+G11*F11)*J11*(1-K11) -> 6173128.1 | V11: =O11*(G11+P11) -> 0 | W11: =U11+V11+T11 -> 6173128.1 | X11: =IF(F11+O11>0, W11/(F11+O11),"") -> 11162.98 | Y11: =B11&"|"&C11 -> E_StatusQuo_Targets_0|FY2030 | Z11: =INDEX(YearMap!$I$2:$I$6, MATCH(C11, YearMap!$A$2:$A$6, 0)) -> 5534.4756 | AA11: =$W11 - $Z11 * (IF(LEFT($B11,2)="A_", $O11, IF(LEFT($B11,2)="B_", $M11+$O11, IF(LEFT($B11,2)="C_", $L11+$O11, $F11)))) -> 3112563.1 | AB11: =IF((IF(LEFT($B11,2)="A_", $O11, IF(LEFT($B11,2)="B_", $M11+$O11, IF(LEFT($B11,2)="C_", $L11+$O11, $F11))))>0, $AA11 / (IF(LEFT($B11,2)="A_", $O11, IF(LEFT($B11,2)="B_", $M11+$O11, IF(LEFT($B11,2)="C_", $L11+$O11, $F11)))), "") -> 5628.5047
A12: =Y12 -> F_CoLocation_Echo_0|FY2026 | B12: =Scenarios!A4 -> F_CoLocation_Echo_0 | C12: FY2026 | D12: =IF(Scenarios!D4=1,0, L12) -> 257 | E12: =IF(Scenarios!E4=1,0, M12) -> 296 | F12: =D12+E12 -> 553 | G12: =YearMap!B2 -> 7129.08 | H12: =YearMap!C2 -> 785217.24 | I12: =YearMap!D2 -> 904374.72 | J12: =1-BaselineCalc!$B$5 -> 0.993 | K12: =Scenarios!G4 -> 0.015 | L12: =BaselineCalc!$B$7 + ROUND(Scenarios!I4*Scenarios!F4,0) -> 257 | M12: =BaselineCalc!$B$8 + Scenarios!I4 - ROUND(Scenarios!I4*Scenarios!F4,0) -> 296 | N12: =(L12-D12) + (M12-E12) -> 0 | O12: =BaselineCalc!$B$22 * N12 -> 0 | P12: =YearMap!E2 -> 1000 | Q12: =IF(Scenarios!N4="lease", YearMap!F2, YearMap!G2) -> 0.4 | R12: =IF(Scenarios!D4=1, Q12*H12, H12) -> 785217.24 | S12: =IF(Scenarios!E4=1, Q12*I12, I12) -> 904374.72 | T12: =IF(C12="FY2026", (Scenarios!D4+Scenarios!E4)*BaselineCalc!$B$21, 0) -> 0 | U12: =(R12+S12+G12*F12)*J12*(1-K12) -> 5508661.1 | V12: =O12*(G12+P12) -> 0 | W12: =U12+V12+T12 -> 5508661.1 | X12: =IF(F12+O12>0, W12/(F12+O12),"") -> 9961.4126 | Y12: =B12&"|"&C12 -> F_CoLocation_Echo_0|FY2026 | Z12: =INDEX(YearMap!$I$2:$I$6, MATCH(C12, YearMap!$A$2:$A$6, 0)) -> 5113 | AA12: =$W12 - $Z12 * (IF(LEFT($B12,2)="A_", $O12, IF(LEFT($B12,2)="B_", $M12+$O12, IF(LEFT($B12,2)="C_", $L12+$O12, $F12)))) -> 2681172.1 | AB12: =IF((IF(LEFT($B12,2)="A_", $O12, IF(LEFT($B12,2)="B_", $M12+$O12, IF(LEFT($B12,2)="C_", $L12+$O12, $F12))))>0, $AA12 / (IF(LEFT($B12,2)="A_", $O12, IF(LEFT($B12,2)="B_", $M12+$O12, IF(LEFT($B12,2)="C_", $L12+$O12, $F12)))), "") -> 4848.4126
A13: =Y13 -> F_CoLocation_Echo_0|FY2027 | B13: =Scenarios!A4 -> F_CoLocation_Echo_0 | C13: FY2027 | D13: =IF(Scenarios!D4=1,0, L13) -> 257 | E13: =IF(Scenarios!E4=1,0, M13) -> 296 | F13: =D13+E13 -> 553 | G13: =YearMap!B3 -> 7307.307 | H13: =YearMap!C3 -> 804847.67 | I13: =YearMap!D3 -> 926984.09 | J13: =1-BaselineCalc!$B$5 -> 0.993 | K13: =Scenarios!G4 -> 0.015 | L13: =BaselineCalc!$B$7 + ROUND(Scenarios!J4*Scenarios!F4,0) -> 257 | M13: =BaselineCalc!$B$8 + Scenarios!J4 - ROUND(Scenarios!J4*Scenarios!F4,0) -> 296 | N13: =(L13-D13) + (M13-E13) -> 0 | O13: =BaselineCalc!$B$22 * N13 -> 0 | P13: =YearMap!E3 -> 800 | Q13: =IF(Scenarios!N4="lease", YearMap!F3, YearMap!G3) -> 0.35 | R13: =IF(Scenarios!D4=1, Q13*H13, H13) -> 804847.67 | S13: =IF(Scenarios!E4=1, Q13*I13, I13) -> 926984.09 | T13: =IF(C13="FY2026", (Scenarios!D4+Scenarios!E4)*BaselineCalc!$B$21, 0) -> 0 | U13: =(R13+S13+G13*F13)*J13*(1-K13) -> 5646377.7 | V13: =O13*(G13+P13) -> 0 | W13: =U13+V13+T13 -> 5646377.7 | X13: =IF(F13+O13>0, W13/(F13+O13),"") -> 10210.448 | Y13: =B13&"|"&C13 -> F_CoLocation_Echo_0|FY2027 | Z13: =INDEX(YearMap!$I$2:$I$6, MATCH(C13, YearMap!$A$2:$A$6, 0)) -> 5215.26 | AA13: =$W13 - $Z13 * (IF(LEFT($B13,2)="A_", $O13, IF(LEFT($B13,2)="B_", $M13+$O13, IF(LEFT($B13,2)="C_", $L13+$O13, $F13)))) -> 2762338.9 | AB13: =IF((IF(LEFT($B13,2)="A_", $O13, IF(LEFT($B13,2)="B_", $M13+$O13, IF(LEFT($B13,2)="C_", $L13+$O13, $F13))))>0, $AA13 / (IF(LEFT($B13,2)="A_", $O13, IF(LEFT($B13,2)="B_", $M13+$O13, IF(LEFT($B13,2)="C_", $L13+$O13, $F13)))), "") -> 4995.1879
A14: =Y14 -> F_CoLocation_Echo_0|FY2028 | B14: =Scenarios!A4 -> F_CoLocation_Echo_0 | C14: FY2028 | D14: =IF(Scenarios!D4=1,0, L14) -> 257 | E14: =IF(Scenarios!E4=1,0, M14) -> 296 | F14: =D14+E14 -> 553 | G14: =YearMap!B4 -> 7489.9897 | H14: =YearMap!C4 -> 824968.86 | I14: =YearMap!D4 -> 950158.69 | J14: =1-BaselineCalc!$B$5 -> 0.993 | K14: =Scenarios!G4 -> 0.015 | L14: =BaselineCalc!$B$7 + ROUND(Scenarios!K4*Scenarios!F4,0) -> 257 | M14: =BaselineCalc!$B$8 + Scenarios!K4 - ROUND(Scenarios!K4*Scenarios!F4,0) -> 296 | N14: =(L14-D14) + (M14-E14) -> 0 | O14: =BaselineCalc!$B$22 * N14 -> 0 | P14: =YearMap!E4 -> 600 | Q14: =IF(Scenarios!N4="lease", YearMap!F4, YearMap!G4) -> 0.3 | R14: =IF(Scenarios!D4=1, Q14*H14, H14) -> 824968.86 | S14: =IF(Scenarios!E4=1, Q14*I14, I14) -> 950158.69 | T14: =IF(C14="FY2026", (Scenarios!D4+Scenarios!E4)*BaselineCalc!$B$21, 0) -> 0 | U14: =(R14+S14+G14*F14)*J14*(1-K14) -> 5787537.1 | V14: =O14*(G14+P14) -> 0 | W14: =U14+V14+T14 -> 5787537.1 | X14: =IF(F14+O14>0, W14/(F14+O14),"") -> 10465.709 | Y14: =B14&"|"&C14 -> F_CoLocation_Echo_0|FY2028 | Z14: =INDEX(YearMap!$I$2:$I$6, MATCH(C14, YearMap!$A$2:$A$6, 0)) -> 5319.5652 | AA14: =$W14 - $Z14 * (IF(LEFT($B14,2)="A_", $O14, IF(LEFT($B14,2)="B_", $M14+$O14, IF(LEFT($B14,2)="C_", $L14+$O14, $F14)))) -> 2845817.6 | AB14: =IF((IF(LEFT($B14,2)="A_", $O14, IF(LEFT($B14,2)="B_", $M14+$O14, IF(LEFT($B14,2)="C_", $L14+$O14, $F14))))>0, $AA14 / (IF(LEFT($B14,2)="A_", $O14, IF(LEFT($B14,2)="B_", $M14+$O14, IF(LEFT($B14,2)="C_", $L14+$O14, $F14)))), "") -> 5146.1439
A15: =Y15 -> F_CoLocation_Echo_0|FY2029 | B15: =Scenarios!A4 -> F_CoLocation_Echo_0 | C15: FY2029 | D15: =IF(Scenarios!D4=1,0, L15) -> 257 | E15: =IF(Scenarios!E4=1,0, M15) -> 296 | F15: =D15+E15 -> 553 | G15: =YearMap!B5 -> 7677.2394 | H15: =YearMap!C5 -> 845593.08 | I15: =YearMap!D5 -> 973912.66 | J15: =1-BaselineCalc!$B$5 -> 0.993 | K15: =Scenarios!G4 -> 0.015 | L15: =BaselineCalc!$B$7 + ROUND(Scenarios!L4*Scenarios!F4,0) -> 257 | M15: =BaselineCalc!$B$8 + Scenarios!L4 - ROUND(Scenarios!L4*Scenarios!F4,0) -> 296 | N15: =(L15-D15) + (M15-E15) -> 0 | O15: =BaselineCalc!$B$22 * N15 -> 0 | P15: =YearMap!E5 -> 400 | Q15: =IF(Scenarios!N4="lease", YearMap!F5, YearMap!G5) -> 0.25 | R15: =IF(Scenarios!D4=1, Q15*H15, H15) -> 845593.08 | S15: =IF(Scenarios!E4=1, Q15*I15, I15) -> 973912.66 | T15: =IF(C15="FY2026", (Scenarios!D4+Scenarios!E4)*BaselineCalc!$B$21, 0) -> 0 | U15: =(R15+S15+G15*F15)*J15*(1-K15) -> 5932225.5 | V15: =O15*(G15+P15) -> 0 | W15: =U15+V15+T15 -> 5932225.5 | X15: =IF(F15+O15>0, W15/(F15+O15),"") -> 10727.352 | Y15: =B15&"|"&C15 -> F_CoLocation_Echo_0|FY2029 | Z15: =INDEX(YearMap!$I$2:$I$6, MATCH(C15, YearMap!$A$2:$A$6, 0)) -> 5425.9565 | AA15: =$W15 - $Z15 * (IF(LEFT($B15,2)="A_", $O15, IF(LEFT($B15,2)="B_", $M15+$O15, IF(LEFT($B15,2)="C_", $L15+$O15, $F15)))) -> 2931671.6 | AB15: =IF((IF(LEFT($B15,2)="A_", $O15, IF(LEFT($B15,2)="B_", $M15+$O15, IF(LEFT($B15,2)="C_", $L15+$O15, $F15))))>0, $AA15 / (IF(LEFT($B15,2)="A_", $O15, IF(LEFT($B15,2)="B_", $M15+$O15, IF(LEFT($B15,2)="C_", $L15+$O15, $F15)))), "") -> 5301.3953
A16: =Y16 -> F_CoLocation_Echo_0|FY2030 | B16: =Scenarios!A4 -> F_CoLocation_Echo_0 | C16: FY2030 | D16: =IF(Scenarios!D4=1,0, L16) -> 257 | E16: =IF(Scenarios!E4=1,0, M16) -> 296 | F16: =D16+E16 -> 553 | G16: =YearMap!B6 -> 7869.1704 | H16: =YearMap!C6 -> 866732.91 | I16: =YearMap!D6 -> 998260.47 | J16: =1-BaselineCalc!$B$5 -> 0.993 | K16: =Scenarios!G4 -> 0.015 | L16: =BaselineCalc!$B$7 + ROUND(Scenarios!M4*Scenarios!F4,0) -> 257 | M16: =BaselineCalc!$B$8 + Scenarios!M4 - ROUND(Scenarios!M4*Scenarios!F4,0) -> 296 | N16: =(L16-D16) + (M16-E16) -> 0 | O16: =BaselineCalc!$B$22 * N16 -> 0 | P16: =YearMap!E6 -> 300 | Q16: =IF(Scenarios!N4="lease", YearMap!F6, YearMap!G6) -> 0.2 | R16: =IF(Scenarios!D4=1, Q16*H16, H16) -> 866732.91 | S16: =IF(Scenarios!E4=1, Q16*I16, I16) -> 998260.47 | T16: =IF(C16="FY2026", (Scenarios!D4+Scenarios!E4)*BaselineCalc!$B$21, 0) -> 0 | U16: =(R16+S16+G16*F16)*J16*(1-K16) -> 6080531.2 | V16: =O16*(G16+P16) -> 0 | W16: =U16+V16+T16 -> 6080531.2 | X16: =IF(F16+O16>0, W16/(F16+O16),"") -> 10995.536 | Y16: =B16&"|"&C16 -> F_CoLocation_Echo_0|FY2030 | Z16: =INDEX(YearMap!$I$2:$I$6, MATCH(C16, YearMap!$A$2:$A$6, 0)) -> 5534.4756 | AA16: =$W16 - $Z16 * (IF(LEFT($B16,2)="A_", $O16, IF(LEFT($B16,2)="B_", $M16+$O16, IF(LEFT($B16,2)="C_", $L16+$O16, $F16)))) -> 3019966.2 | AB16: =IF((IF(LEFT($B16,2)="A_", $O16, IF(LEFT($B16,2)="B_", $M16+$O16, IF(LEFT($B16,2)="C_", $L16+$O16, $F16))))>0, $AA16 / (IF(LEFT($B16,2)="A_", $O16, IF(LEFT($B16,2)="B_", $M16+$O16, IF(LEFT($B16,2)="C_", $L16+$O16, $F16)))), "") -> 5461.06
A17: =Y17 -> D_Grow_Both_100|FY2026 | B17: =Scenarios!A5 -> D_Grow_Both_100 | C17: FY2026 | D17: =IF(Scenarios!D5=1,0, L17) -> 307 | E17: =IF(Scenarios!E5=1,0, M17) -> 346 | F17: =D17+E17 -> 653 | G17: =YearMap!B2 -> 7129.08 | H17: =YearMap!C2 -> 785217.24 | I17: =YearMap!D2 -> 904374.72 | J17: =1-BaselineCalc!$B$5 -> 0.993 | K17: =Scenarios!G5 -> 0 | L17: =BaselineCalc!$B$7 + ROUND(Scenarios!I5*Scenarios!F5,0) -> 307 | M17: =BaselineCalc!$B$8 + Scenarios!I5 - ROUND(Scenarios!I5*Scenarios!F5,0) -> 346 | N17: =(L17-D17) + (M17-E17) -> 0 | O17: =BaselineCalc!$B$22 * N17 -> 0 | P17: =YearMap!E2 -> 1000 | Q17: =IF(Scenarios!N5="lease", YearMap!F2, YearMap!G2) -> 0.4 | R17: =IF(Scenarios!D5=1, Q17*H17, H17) -> 785217.24 | S17: =IF(Scenarios!E5=1, Q17*I17, I17) -> 904374.72 | T17: =IF(C17="FY2026", (Scenarios!D5+Scenarios!E5)*BaselineCalc!$B$21, 0) -> 0 | U17: =(R17+S17+G17*F17)*J17*(1-K17) -> 6300467 | V17: =O17*(G17+P17) -> 0 | W17: =U17+V17+T17 -> 6300467 | X17: =IF(F17+O17>0, W17/(F17+O17),"") -> 9648.4947 | Y17: =B17&"|"&C17 -> D_Grow_Both_100|FY2026 | Z17: =INDEX(YearMap!$I$2:$I$6, MATCH(C17, YearMap!$A$2:$A$6, 0)) -> 5113 | AA17: =$W17 - $Z17 * (IF(LEFT($B17,2)="A_", $O17, IF(LEFT($B17,2)="B_", $M17+$O17, IF(LEFT($B17,2)="C_", $L17+$O17, $F17)))) -> 2961678 | AB17: =IF((IF(LEFT($B17,2)="A_", $O17, IF(LEFT($B17,2)="B_", $M17+$O17, IF(LEFT($B17,2)="C_", $L17+$O17, $F17))))>0, $AA17 / (IF(LEFT($B17,2)="A_", $O17, IF(LEFT($B17,2)="B_", $M17+$O17, IF(LEFT($B17,2)="C_", $L17+$O17, $F17)))), "") -> 4535.4947
A18: =Y18 -> D_Grow_Both_100|FY2027 | B18: =Scenarios!A5 -> D_Grow_Both_100 | C18: FY2027 | D18: =IF(Scenarios!D5=1,0, L18) -> 307 | E18: =IF(Scenarios!E5=1,0, M18) -> 346 | F18: =D18+E18 -> 653 | G18: =YearMap!B3 -> 7307.307 | H18: =YearMap!C3 -> 804847.67 | I18: =YearMap!D3 -> 926984.09 | J18: =1-BaselineCalc!$B$5 -> 0.993 | K18: =Scenarios!G5 -> 0 | L18: =BaselineCalc!$B$7 + ROUND(Scenarios!J5*Scenarios!F5,0) -> 307 | M18: =BaselineCalc!$B$8 + Scenarios!J5 - ROUND(Scenarios!J5*Scenarios!F5,0) -> 346 | N18: =(L18-D18) + (M18-E18) -> 0 | O18: =BaselineCalc!$B$22 * N18 -> 0 | P18: =YearMap!E3 -> 800 | Q18: =IF(Scenarios!N5="lease", YearMap!F3, YearMap!G3) -> 0.35 | R18: =IF(Scenarios!D5=1, Q18*H18, H18) -> 804847.67 | S18: =IF(Scenarios!E5=1, Q18*I18, I18) -> 926984.09 | T18: =IF(C18="FY2026", (Scenarios!D5+Scenarios!E5)*BaselineCalc!$B$21, 0) -> 0 | U18: =(R18+S18+G18*F18)*J18*(1-K18) -> 6457978.7 | V18: =O18*(G18+P18) -> 0 | W18: =U18+V18+T18 -> 6457978.7 | X18: =IF(F18+O18>0, W18/(F18+O18),"") -> 9889.7071 | Y18: =B18&"|"&C18 -> D_Grow_Both_100|FY2027 | Z18: =INDEX(YearMap!$I$2:$I$6, MATCH(C18, YearMap!$A$2:$A$6, 0)) -> 5215.26 | AA18: =$W18 - $Z18 * (IF(LEFT($B18,2)="A_", $O18, IF(LEFT($B18,2)="B_", $M18+$O18, IF(LEFT($B18,2)="C_", $L18+$O18, $F18)))) -> 3052413.9 | AB18: =IF((IF(LEFT($B18,2)="A_", $O18, IF(LEFT($B18,2)="B_", $M18+$O18, IF(LEFT($B18,2)="C_", $L18+$O18, $F18))))>0, $AA18 / (IF(LEFT($B18,2)="A_", $O18, IF(LEFT($B18,2)="B_", $M18+$O18, IF(LEFT($B18,2)="C_", $L18+$O18, $F18)))), "") -> 4674.4471
A19: =Y19 -> D_Grow_Both_100|FY2028 | B19: =Scenarios!A5 -> D_Grow_Both_100 | C19: FY2028 | D19: =IF(Scenarios!D5=1,0, L19) -> 307 | E19: =IF(Scenarios!E5=1,0, M19) -> 346 | F19: =D19+E19 -> 653 | G19: =YearMap!B4 -> 7489.9897 | H19: =YearMap!C4 -> 824968.86 | I19: =YearMap!D4 -> 950158.69 | J19: =1-BaselineCalc!$B$5 -> 0.993 | K19: =Scenarios!G5 -> 0 | L19: =BaselineCalc!$B$7 + ROUND(Scenarios!K5*Scenarios!F5,0) -> 307 | M19: =BaselineCalc!$B$8 + Scenarios!K5 - ROUND(Scenarios!K5*Scenarios!F5,0) -> 346 | N19: =(L19-D19) + (M19-E19) -> 0 | O19: =BaselineCalc!$B$22 * N19 -> 0 | P19: =YearMap!E4 -> 600 | Q19: =IF(Scenarios!N5="lease", YearMap!F4, YearMap!G4) -> 0.3 | R19: =IF(Scenarios!D5=1, Q19*H19, H19) -> 824968.86 | S19: =IF(Scenarios!E5=1, Q19*I19, I19) -> 950158.69 | T19: =IF(C19="FY2026", (Scenarios!D5+Scenarios!E5)*BaselineCalc!$B$21, 0) -> 0 | U19: =(R19+S19+G19*F19)*J19*(1-K19) -> 6619428.2 | V19: =O19*(G19+P19) -> 0 | W19: =U19+V19+T19 -> 6619428.2 | X19: =IF(F19+O19>0, W19/(F19+O19),"") -> 10136.95 | Y19: =B19&"|"&C19 -> D_Grow_Both_100|FY2028 | Z19: =INDEX(YearMap!$I$2:$I$6, MATCH(C19, YearMap!$A$2:$A$6, 0)) -> 5319.5652 | AA19: =$W19 - $Z19 * (IF(LEFT($B19,2)="A_", $O19, IF(LEFT($B19,2)="B_", $M19+$O19, IF(LEFT($B19,2)="C_", $L19+$O19, $F19)))) -> 3145752.1 | AB19: =IF((IF(LEFT($B19,2)="A_", $O19, IF(LEFT($B19,2)="B_", $M19+$O19, IF(LEFT($B19,2)="C_", $L19+$O19, $F19))))>0, $AA19 / (IF(LEFT($B19,2)="A_", $O19, IF(LEFT($B19,2)="B_", $M19+$O19, IF(LEFT($B19,2)="C_", $L19+$O19, $F19)))), "") -> 4817.3845
A20: =Y20 -> D_Grow_Both_100|FY2029 | B20: =Scenarios!A5 -> D_Grow_Both_100 | C20: FY2029 | D20: =IF(Scenarios!D5=1,0, L20) -> 307 | E20: =IF(Scenarios!E5=1,0, M20) -> 346 | F20: =D20+E20 -> 653 | G20: =YearMap!B5 -> 7677.2394 | H20: =YearMap!C5 -> 845593.08 | I20: =YearMap!D5 -> 973912.66 | J20: =1-BaselineCalc!$B$5 -> 0.993 | K20: =Scenarios!G5 -> 0 | L20: =BaselineCalc!$B$7 + ROUND(Scenarios!L5*Scenarios!F5,0) -> 307 | M20: =BaselineCalc!$B$8 + Scenarios!L5 - ROUND(Scenarios!L5*Scenarios!F5,0) -> 346 | N20: =(L20-D20) + (M20-E20) -> 0 | O20: =BaselineCalc!$B$22 * N20 -> 0 | P20: =YearMap!E5 -> 400 | Q20: =IF(Scenarios!N5="lease", YearMap!F5, YearMap!G5) -> 0.25 | R20: =IF(Scenarios!D5=1, Q20*H20, H20) -> 845593.08 | S20: =IF(Scenarios!E5=1, Q20*I20, I20) -> 973912.66 | T20: =IF(C20="FY2026", (Scenarios!D5+Scenarios!E5)*BaselineCalc!$B$21, 0) -> 0 | U20: =(R20+S20+G20*F20)*J20*(1-K20) -> 6784913.9 | V20: =O20*(G20+P20) -> 0 | W20: =U20+V20+T20 -> 6784913.9 | X20: =IF(F20+O20>0, W20/(F20+O20),"") -> 10390.373 | Y20: =B20&"|"&C20 -> D_Grow_Both_100|FY2029 | Z20: =INDEX(YearMap!$I$2:$I$6, MATCH(C20, YearMap!$A$2:$A$6, 0)) -> 5425.9565 | AA20: =$W20 - $Z20 * (IF(LEFT($B20,2)="A_", $O20, IF(LEFT($B20,2)="B_", $M20+$O20, IF(LEFT($B20,2)="C_", $L20+$O20, $F20)))) -> 3241764.3 | AB20: =IF((IF(LEFT($B20,2)="A_", $O20, IF(LEFT($B20,2)="B_", $M20+$O20, IF(LEFT($B20,2)="C_", $L20+$O20, $F20))))>0, $AA20 / (IF(LEFT($B20,2)="A_", $O20, IF(LEFT($B20,2)="B_", $M20+$O20, IF(LEFT($B20,2)="C_", $L20+$O20, $F20)))), "") -> 4964.417
A21: =Y21 -> D_Grow_Both_100|FY2030 | B21: =Scenarios!A5 -> D_Grow_Both_100 | C21: FY2030 | D21: =IF(Scenarios!D5=1,0, L21) -> 307 | E21: =IF(Scenarios!E5=1,0, M21) -> 346 | F21: =D21+E21 -> 653 | G21: =YearMap!B6 -> 7869.1704 | H21: =YearMap!C6 -> 866732.91 | I21: =YearMap!D6 -> 998260.47 | J21: =1-BaselineCalc!$B$5 -> 0.993 | K21: =Scenarios!G5 -> 0 | L21: =BaselineCalc!$B$7 + ROUND(Scenarios!M5*Scenarios!F5,0) -> 307 | M21: =BaselineCalc!$B$8 + Scenarios!M5 - ROUND(Scenarios!M5*Scenarios!F5,0) -> 346 | N21: =(L21-D21) + (M21-E21) -> 0 | O21: =BaselineCalc!$B$22 * N21 -> 0 | P21: =YearMap!E6 -> 300 | Q21: =IF(Scenarios!N5="lease", YearMap!F6, YearMap!G6) -> 0.2 | R21: =IF(Scenarios!D5=1, Q21*H21, H21) -> 866732.91 | S21: =IF(Scenarios!E5=1, Q21*I21, I21) -> 998260.47 | T21: =IF(C21="FY2026", (Scenarios!D5+Scenarios!E5)*BaselineCalc!$B$21, 0) -> 0 | U21: =(R21+S21+G21*F21)*J21*(1-K21) -> 6954536.7 | V21: =O21*(G21+P21) -> 0 | W21: =U21+V21+T21 -> 6954536.7 | X21: =IF(F21+O21>0, W21/(F21+O21),"") -> 10650.133 | Y21: =B21&"|"&C21 -> D_Grow_Both_100|FY2030 | Z21: =INDEX(YearMap!$I$2:$I$6, MATCH(C21, YearMap!$A$2:$A$6, 0)) -> 5534.4756 | AA21: =$W21 - $Z21 * (IF(LEFT($B21,2)="A_", $O21, IF(LEFT($B21,2)="B_", $M21+$O21, IF(LEFT($B21,2)="C_", $L21+$O21, $F21)))) -> 3340524.1 | AB21: =IF((IF(LEFT($B21,2)="A_", $O21, IF(LEFT($B21,2)="B_", $M21+$O21, IF(LEFT($B21,2)="C_", $L21+$O21, $F21))))>0, $AA21 / (IF(LEFT($B21,2)="A_", $O21, IF(LEFT($B21,2)="B_", $M21+$O21, IF(LEFT($B21,2)="C_", $L21+$O21, $F21)))), "") -> 5115.6572
A22: =Y22 -> D_Grow_Both_150|FY2026 | B22: =Scenarios!A6 -> D_Grow_Both_150 | C22: FY2026 | D22: =IF(Scenarios!D6=1,0, L22) -> 332 | E22: =IF(Scenarios!E6=1,0, M22) -> 371 | F22: =D22+E22 -> 703 | G22: =YearMap!B2 -> 7129.08 | H22: =YearMap!C2 -> 785217.24 | I22: =YearMap!D2 -> 904374.72 | J22: =1-BaselineCalc!$B$5 -> 0.993 | K22: =Scenarios!G6 -> 0 | L22: =BaselineCalc!$B$7 + ROUND(Scenarios!I6*Scenarios!F6,0) -> 332 | M22: =BaselineCalc!$B$8 + Scenarios!I6 - ROUND(Scenarios!I6*Scenarios!F6,0) -> 371 | N22: =(L22-D22) + (M22-E22) -> 0 | O22: =BaselineCalc!$B$22 * N22 -> 0 | P22: =YearMap!E2 -> 1000 | Q22: =IF(Scenarios!N6="lease", YearMap!F2, YearMap!G2) -> 0.4 | R22: =IF(Scenarios!D6=1, Q22*H22, H22) -> 785217.24 | S22: =IF(Scenarios!E6=1, Q22*I22, I22) -> 904374.72 | T22: =IF(C22="FY2026", (Scenarios!D6+Scenarios!E6)*BaselineCalc!$B$21, 0) -> 0 | U22: =(R22+S22+G22*F22)*J22*(1-K22) -> 6654425.9 | V22: =O22*(G22+P22) -> 0 | W22: =U22+V22+T22 -> 6654425.9 | X22: =IF(F22+O22>0, W22/(F22+O22),"") -> 9465.7551 | Y22: =B22&"|"&C22 -> D_Grow_Both_150|FY2026 | Z22: =INDEX(YearMap!$I$2:$I$6, MATCH(C22, YearMap!$A$2:$A$6, 0)) -> 5113 | AA22: =$W22 - $Z22 * (IF(LEFT($B22,2)="A_", $O22, IF(LEFT($B22,2)="B_", $M22+$O22, IF(LEFT($B22,2)="C_", $L22+$O22, $F22)))) -> 3059986.9 | AB22: =IF((IF(LEFT($B22,2)="A_", $O22, IF(LEFT($B22,2)="B_", $M22+$O22, IF(LEFT($B22,2)="C_", $L22+$O22, $F22))))>0, $AA22 / (IF(LEFT($B22,2)="A_", $O22, IF(LEFT($B22,2)="B_", $M22+$O22, IF(LEFT($B22,2)="C_", $L22+$O22, $F22)))), "") -> 4352.7551
A23: =Y23 -> D_Grow_Both_150|FY2027 | B23: =Scenarios!A6 -> D_Grow_Both_150 | C23: FY2027 | D23: =IF(Scenarios!D6=1,0, L23) -> 332 | E23: =IF(Scenarios!E6=1,0, M23) -> 371 | F23: =D23+E23 -> 703 | G23: =YearMap!B3 -> 7307.307 | H23: =YearMap!C3 -> 804847.67 | I23: =YearMap!D3 -> 926984.09 | J23: =1-BaselineCalc!$B$5 -> 0.993 | K23: =Scenarios!G6 -> 0 | L23: =BaselineCalc!$B$7 + ROUND(Scenarios!J6*Scenarios!F6,0) -> 332 | M23: =BaselineCalc!$B$8 + Scenarios!J6 - ROUND(Scenarios!J6*Scenarios!F6,0) -> 371 | N23: =(L23-D23) + (M23-E23) -> 0 | O23: =BaselineCalc!$B$22 * N23 -> 0 | P23: =YearMap!E3 -> 800 | Q23: =IF(Scenarios!N6="lease", YearMap!F3, YearMap!G3) -> 0.35 | R23: =IF(Scenarios!D6=1, Q23*H23, H23) -> 804847.67 | S23: =IF(Scenarios!E6=1, Q23*I23, I23) -> 926984.09 | T23: =IF(C23="FY2026", (Scenarios!D6+Scenarios!E6)*BaselineCalc!$B$21, 0) -> 0 | U23: =(R23+S23+G23*F23)*J23*(1-K23) -> 6820786.5 | V23: =O23*(G23+P23) -> 0 | W23: =U23+V23+T23 -> 6820786.5 | X23: =IF(F23+O23>0, W23/(F23+O23),"") -> 9702.399 | Y23: =B23&"|"&C23 -> D_Grow_Both_150|FY2027 | Z23: =INDEX(YearMap!$I$2:$I$6, MATCH(C23, YearMap!$A$2:$A$6, 0)) -> 5215.26 | AA23: =$W23 - $Z23 * (IF(LEFT($B23,2)="A_", $O23, IF(LEFT($B23,2)="B_", $M23+$O23, IF(LEFT($B23,2)="C_", $L23+$O23, $F23)))) -> 3154458.7 | AB23: =IF((IF(LEFT($B23,2)="A_", $O23, IF(LEFT($B23,2)="B_", $M23+$O23, IF(LEFT($B23,2)="C_", $L23+$O23, $F23))))>0, $AA23 / (IF(LEFT($B23,2)="A_", $O23, IF(LEFT($B23,2)="B_", $M23+$O23, IF(LEFT($B23,2)="C_", $L23+$O23, $F23)))), "") -> 4487.139
A24: =Y24 -> D_Grow_Both_150|FY2028 | B24: =Scenarios!A6 -> D_Grow_Both_150 | C24: FY2028 | D24: =IF(Scenarios!D6=1,0, L24) -> 332 | E24: =IF(Scenarios!E6=1,0, M24) -> 371 | F24: =D24+E24 -> 703 | G24: =YearMap!B4 -> 7489.9897 | H24: =YearMap!C4 -> 824968.86 | I24: =YearMap!D4 -> 950158.69 | J24: =1-BaselineCalc!$B$5 -> 0.993 | K24: =Scenarios!G6 -> 0 | L24: =BaselineCalc!$B$7 + ROUND(Scenarios!K6*Scenarios!F6,0) -> 332 | M24: =BaselineCalc!$B$8 + Scenarios!K6 - ROUND(Scenarios!K6*Scenarios!F6,0) -> 371 | N24: =(L24-D24) + (M24-E24) -> 0 | O24: =BaselineCalc!$B$22 * N24 -> 0 | P24: =YearMap!E4 -> 600 | Q24: =IF(Scenarios!N6="lease", YearMap!F4, YearMap!G4) -> 0.3 | R24: =IF(Scenarios!D6=1, Q24*H24, H24) -> 824968.86 | S24: =IF(Scenarios!E6=1, Q24*I24, I24) -> 950158.69 | T24: =IF(C24="FY2026", (Scenarios!D6+Scenarios!E6)*BaselineCalc!$B$21, 0) -> 0 | U24: =(R24+S24+G24*F24)*J24*(1-K24) -> 6991306.2 | V24: =O24*(G24+P24) -> 0 | W24: =U24+V24+T24 -> 6991306.2 | X24: =IF(F24+O24>0, W24/(F24+O24),"") -> 9944.959 | Y24: =B24&"|"&C24 -> D_Grow_Both_150|FY2028 | Z24: =INDEX(YearMap!$I$2:$I$6, MATCH(C24, YearMap!$A$2:$A$6, 0)) -> 5319.5652 | AA24: =$W24 - $Z24 * (IF(LEFT($B24,2)="A_", $O24, IF(LEFT($B24,2)="B_", $M24+$O24, IF(LEFT($B24,2)="C_", $L24+$O24, $F24)))) -> 3251651.8 | AB24: =IF((IF(LEFT($B24,2)="A_", $O24, IF(LEFT($B24,2)="B_", $M24+$O24, IF(LEFT($B24,2)="C_", $L24+$O24, $F24))))>0, $AA24 / (IF(LEFT($B24,2)="A_", $O24, IF(LEFT($B24,2)="B_", $M24+$O24, IF(LEFT($B24,2)="C_", $L24+$O24, $F24)))), "") -> 4625.3938
A25: =Y25 -> D_Grow_Both_150|FY2029 | B25: =Scenarios!A6 -> D_Grow_Both_150 | C25: FY2029 | D25: =IF(Scenarios!D6=1,0, L25) -> 332 | E25: =IF(Scenarios!E6=1,0, M25) -> 371 | F25: =D25+E25 -> 703 | G25: =YearMap!B5 -> 7677.2394 | H25: =YearMap!C5 -> 845593.08 | I25: =YearMap!D5 -> 973912.66 | J25: =1-BaselineCalc!$B$5 -> 0.993 | K25: =Scenarios!G6 -> 0 | L25: =BaselineCalc!$B$7 + ROUND(Scenarios!L6*Scenarios!F6,0) -> 332 | M25: =BaselineCalc!$B$8 + Scenarios!L6 - ROUND(Scenarios!L6*Scenarios!F6,0) -> 371 | N25: =(L25-D25) + (M25-E25) -> 0 | O25: =BaselineCalc!$B$22 * N25 -> 0 | P25: =YearMap!E5 -> 400 | Q25: =IF(Scenarios!N6="lease", YearMap!F5, YearMap!G5) -> 0.25 | R25: =IF(Scenarios!D6=1, Q25*H25, H25) -> 845593.08 | S25: =IF(Scenarios!E6=1, Q25*I25, I25) -> 973912.66 | T25: =IF(C25="FY2026", (Scenarios!D6+Scenarios!E6)*BaselineCalc!$B$21, 0) -> 0 | U25: =(R25+S25+G25*F25)*J25*(1-K25) -> 7166088.8 | V25: =O25*(G25+P25) -> 0 | W25: =U25+V25+T25 -> 7166088.8 | X25: =IF(F25+O25>0, W25/(F25+O25),"") -> 10193.583 | Y25: =B25&"|"&C25 -> D_Grow_Both_150|FY2029 | Z25: =INDEX(YearMap!$I$2:$I$6, MATCH(C25, YearMap!$A$2:$A$6, 0)) -> 5425.9565 | AA25: =$W25 - $Z25 * (IF(LEFT($B25,2)="A_", $O25, IF(LEFT($B25,2)="B_", $M25+$O25, IF(LEFT($B25,2)="C_", $L25+$O25, $F25)))) -> 3351641.4 | AB25: =IF((IF(LEFT($B25,2)="A_", $O25, IF(LEFT($B25,2)="B_", $M25+$O25, IF(LEFT($B25,2)="C_", $L25+$O25, $F25))))>0, $AA25 / (IF(LEFT($B25,2)="A_", $O25, IF(LEFT($B25,2)="B_", $M25+$O25, IF(LEFT($B25,2)="C_", $L25+$O25, $F25)))), "") -> 4767.6264
A26: =Y26 -> D_Grow_Both_150|FY2030 | B26: =Scenarios!A6 -> D_Grow_Both_150 | C26: FY2030 | D26: =IF(Scenarios!D6=1,0, L26) -> 332 | E26: =IF(Scenarios!E6=1,0, M26) -> 371 | F26: =D26+E26 -> 703 | G26: =YearMap!B6 -> 7869.1704 | H26: =YearMap!C6 -> 866732.91 | I26: =YearMap!D6 -> 998260.47 | J26: =1-BaselineCalc!$B$5 -> 0.993 | K26: =Scenarios!G6 -> 0 | L26: =BaselineCalc!$B$7 + ROUND(Scenarios!M6*Scenarios!F6,0) -> 332 | M26: =BaselineCalc!$B$8 + Scenarios!M6 - ROUND(Scenarios!M6*Scenarios!F6,0) -> 371 | N26: =(L26-D26) + (M26-E26) -> 0 | O26: =BaselineCalc!$B$22 * N26 -> 0 | P26: =YearMap!E6 -> 300 | Q26: =IF(Scenarios!N6="lease", YearMap!F6, YearMap!G6) -> 0.2 | R26: =IF(Scenarios!D6=1, Q26*H26, H26) -> 866732.91 | S26: =IF(Scenarios!E6=1, Q26*I26, I26) -> 998260.47 | T26: =IF(C26="FY2026", (Scenarios!D6+Scenarios!E6)*BaselineCalc!$B$21, 0) -> 0 | U26: =(R26+S26+G26*F26)*J26*(1-K26) -> 7345241 | V26: =O26*(G26+P26) -> 0 | W26: =U26+V26+T26 -> 7345241 | X26: =IF(F26+O26>0, W26/(F26+O26),"") -> 10448.423 | Y26: =B26&"|"&C26 -> D_Grow_Both_150|FY2030 | Z26: =INDEX(YearMap!$I$2:$I$6, MATCH(C26, YearMap!$A$2:$A$6, 0)) -> 5534.4756 | AA26: =$W26 - $Z26 * (IF(LEFT($B26,2)="A_", $O26, IF(LEFT($B26,2)="B_", $M26+$O26, IF(LEFT($B26,2)="C_", $L26+$O26, $F26)))) -> 3454504.7 | AB26: =IF((IF(LEFT($B26,2)="A_", $O26, IF(LEFT($B26,2)="B_", $M26+$O26, IF(LEFT($B26,2)="C_", $L26+$O26, $F26))))>0, $AA26 / (IF(LEFT($B26,2)="A_", $O26, IF(LEFT($B26,2)="B_", $M26+$O26, IF(LEFT($B26,2)="C_", $L26+$O26, $F26)))), "") -> 4913.9469
A27: =Y27 -> G_DHub_EchoRamp|FY2026 | B27: =Scenarios!A7 -> G_DHub_EchoRamp | C27: FY2026 | D27: =IF(Scenarios!D7=1,0, L27) -> 292 | E27: =IF(Scenarios!E7=1,0, M27) -> 311 | F27: =D27+E27 -> 603 | G27: =YearMap!B2 -> 7129.08 | H27: =YearMap!C2 -> 785217.24 | I27: =YearMap!D2 -> 904374.72 | J27: =1-BaselineCalc!$B$5 -> 0.993 | K27: =Scenarios!G7 -> 0 | L27: =BaselineCalc!$B$7 + ROUND(Scenarios!I7*Scenarios!F7,0) -> 292 | M27: =BaselineCalc!$B$8 + Scenarios!I7 - ROUND(Scenarios!I7*Scenarios!F7,0) -> 311 | N27: =(L27-D27) + (M27-E27) -> 0 | O27: =BaselineCalc!$B$22 * N27 -> 0 | P27: =YearMap!E2 -> 1000 | Q27: =IF(Scenarios!N7="lease", YearMap!F2, YearMap!G2) -> 0.4 | R27: =IF(Scenarios!D7=1, Q27*H27, H27) -> 785217.24 | S27: =IF(Scenarios!E7=1, Q27*I27, I27) -> 904374.72 | T27: =IF(C27="FY2026", (Scenarios!D7+Scenarios!E7)*BaselineCalc!$B$21, 0) -> 0 | U27: =(R27+S27+G27*F27)*J27*(1-K27) -> 5946508.2 | V27: =O27*(G27+P27) -> 0 | W27: =U27+V27+T27 -> 5946508.2 | X27: =IF(F27+O27>0, W27/(F27+O27),"") -> 9861.5393 | Y27: =B27&"|"&C27 -> G_DHub_EchoRamp|FY2026 | Z27: =INDEX(YearMap!$I$2:$I$6, MATCH(C27, YearMap!$A$2:$A$6, 0)) -> 5113 | AA27: =$W27 - $Z27 * (IF(LEFT($B27,2)="A_", $O27, IF(LEFT($B27,2)="B_", $M27+$O27, IF(LEFT($B27,2)="C_", $L27+$O27, $F27)))) -> 2863369.2 | AB27: =IF((IF(LEFT($B27,2)="A_", $O27, IF(LEFT($B27,2)="B_", $M27+$O27, IF(LEFT($B27,2)="C_", $L27+$O27, $F27))))>0, $AA27 / (IF(LEFT($B27,2)="A_", $O27, IF(LEFT($B27,2)="B_", $M27+$O27, IF(LEFT($B27,2)="C_", $L27+$O27, $F27)))), "") -> 4748.5393
A28: =Y28 -> G_DHub_EchoRamp|FY2027 | B28: =Scenarios!A7 -> G_DHub_EchoRamp | C28: FY2027 | D28: =IF(Scenarios!D7=1,0, L28) -> 327 | E28: =IF(Scenarios!E7=1,0, M28) -> 326 | F28: =D28+E28 -> 653 | G28: =YearMap!B3 -> 7307.307 | H28: =YearMap!C3 -> 804847.67 | I28: =YearMap!D3 -> 926984.09 | J28: =1-BaselineCalc!$B$5 -> 0.993 | K28: =Scenarios!G7 -> 0 | L28: =BaselineCalc!$B$7 + ROUND(Scenarios!J7*Scenarios!F7,0) -> 327 | M28: =BaselineCalc!$B$8 + Scenarios!J7 - ROUND(Scenarios!J7*Scenarios!F7,0) -> 326 | N28: =(L28-D28) + (M28-E28) -> 0 | O28: =BaselineCalc!$B$22 * N28 -> 0 | P28: =YearMap!E3 -> 800 | Q28: =IF(Scenarios!N7="lease", YearMap!F3, YearMap!G3) -> 0.35 | R28: =IF(Scenarios!D7=1, Q28*H28, H28) -> 804847.67 | S28: =IF(Scenarios!E7=1, Q28*I28, I28) -> 926984.09 | T28: =IF(C28="FY2026", (Scenarios!D7+Scenarios!E7)*BaselineCalc!$B$21, 0) -> 0 | U28: =(R28+S28+G28*F28)*J28*(1-K28) -> 6457978.7 | V28: =O28*(G28+P28) -> 0 | W28: =U28+V28+T28 -> 6457978.7 | X28: =IF(F28+O28>0, W28/(F28+O28),"") -> 9889.7071 | Y28: =B28&"|"&C28 -> G_DHub_EchoRamp|FY2027 | Z28: =INDEX(YearMap!$I$2:$I$6, MATCH(C28, YearMap!$A$2:$A$6, 0)) -> 5215.26 | AA28: =$W28 - $Z28 * (IF(LEFT($B28,2)="A_", $O28, IF(LEFT($B28,2)="B_", $M28+$O28, IF(LEFT($B28,2)="C_", $L28+$O28, $F28)))) -> 3052413.9 | AB28: =IF((IF(LEFT($B28,2)="A_", $O28, IF(LEFT($B28,2)="B_", $M28+$O28, IF(LEFT($B28,2)="C_", $L28+$O28, $F28))))>0, $AA28 / (IF(LEFT($B28,2)="A_", $O28, IF(LEFT($B28,2)="B_", $M28+$O28, IF(LEFT($B28,2)="C_", $L28+$O28, $F28)))), "") -> 4674.4471
A29: =Y29 -> G_DHub_EchoRamp|FY2028 | B29: =Scenarios!A7 -> G_DHub_EchoRamp | C29: FY2028 | D29: =IF(Scenarios!D7=1,0, L29) -> 362 | E29: =IF(Scenarios!E7=1,0, M29) -> 341 | F29: =D29+E29 -> 703 | G29: =YearMap!B4 -> 7489.9897 | H29: =YearMap!C4 -> 824968.86 | I29: =YearMap!D4 -> 950158.69 | J29: =1-BaselineCalc!$B$5 -> 0.993 | K29: =Scenarios!G7 -> 0 | L29: =BaselineCalc!$B$7 + ROUND(Scenarios!K7*Scenarios!F7,0) -> 362 | M29: =BaselineCalc!$B$8 + Scenarios!K7 - ROUND(Scenarios!K7*Scenarios!F7,0) -> 341 | N29: =(L29-D29) + (M29-E29) -> 0 | O29: =BaselineCalc!$B$22 * N29 -> 0 | P29: =YearMap!E4 -> 600 | Q29: =IF(Scenarios!N7="lease", YearMap!F4, YearMap!G4) -> 0.3 | R29: =IF(Scenarios!D7=1, Q29*H29, H29) -> 824968.86 | S29: =IF(Scenarios!E7=1, Q29*I29, I29) -> 950158.69 | T29: =IF(C29="FY2026", (Scenarios!D7+Scenarios!E7)*BaselineCalc!$B$21, 0) -> 0 | U29: =(R29+S29+G29*F29)*J29*(1-K29) -> 6991306.2 | V29: =O29*(G29+P29) -> 0 | W29: =U29+V29+T29 -> 6991306.2 | X29: =IF(F29+O29>0, W29/(F29+O29),"") -> 9944.959 | Y29: =B29&"|"&C29 -> G_DHub_EchoRamp|FY2028 | Z29: =INDEX(YearMap!$I$2:$I$6, MATCH(C29, YearMap!$A$2:$A$6, 0)) -> 5319.5652 | AA29: =$W29 - $Z29 * (IF(LEFT($B29,2)="A_", $O29, IF(LEFT($B29,2)="B_", $M29+$O29, IF(LEFT($B29,2)="C_", $L29+$O29, $F29)))) -> 3251651.8 | AB29: =IF((IF(LEFT($B29,2)="A_", $O29, IF(LEFT($B29,2)="B_", $M29+$O29, IF(LEFT($B29,2)="C_", $L29+$O29, $F29))))>0, $AA29 / (IF(LEFT($B29,2)="A_", $O29, IF(LEFT($B29,2)="B_", $M29+$O29, IF(LEFT($B29,2)="C_", $L29+$O29, $F29)))), "") -> 4625.3938
A30: =Y30 -> G_DHub_EchoRamp|FY2029 | B30: =Scenarios!A7 -> G_DHub_EchoRamp | C30: FY2029 | D30: =IF(Scenarios!D7=1,0, L30) -> 362 | E30: =IF(Scenarios!E7=1,0, M30) -> 341 | F30: =D30+E30 -> 703 | G30: =YearMap!B5 -> 7677.2394 | H30: =YearMap!C5 -> 845593.08 | I30: =YearMap!D5 -> 973912.66 | J30: =1-BaselineCalc!$B$5 -> 0.993 | K30: =Scenarios!G7 -> 0 | L30: =BaselineCalc!$B$7 + ROUND(Scenarios!L7*Scenarios!F7,0) -> 362 | M30: =BaselineCalc!$B$8 + Scenarios!L7 - ROUND(Scenarios!L7*Scenarios!F7,0) -> 341 | N30: =(L30-D30) + (M30-E30) -> 0 | O30: =BaselineCalc!$B$22 * N30 -> 0 | P30: =YearMap!E5 -> 400 | Q30: =IF(Scenarios!N7="lease", YearMap!F5, YearMap!G5) -> 0.25 | R30: =IF(Scenarios!D7=1, Q30*H30, H30) -> 845593.08 | S30: =IF(Scenarios!E7=1, Q30*I30, I30) -> 973912.66 | T30: =IF(C30="FY2026", (Scenarios!D7+Scenarios!E7)*BaselineCalc!$B$21, 0) -> 0 | U30: =(R30+S30+G30*F30)*J30*(1-K30) -> 7166088.8 | V30: =O30*(G30+P30) -> 0 | W30: =U30+V30+T30 -> 7166088.8 | X30: =IF(F30+O30>0, W30/(F30+O30),"") -> 10193.583 | Y30: =B30&"|"&C30 -> G_DHub_EchoRamp|FY2029 | Z30: =INDEX(YearMap!$I$2:$I$6, MATCH(C30, YearMap!$A$2:$A$6, 0)) -> 5425.9565 | AA30: =$W30 - $Z30 * (IF(LEFT($B30,2)="A_", $O30, IF(LEFT($B30,2)="B_", $M30+$O30, IF(LEFT($B30,2)="C_", $L30+$O30, $F30)))) -> 3351641.4 | AB30: =IF((IF(LEFT($B30,2)="A_", $O30, IF(LEFT($B30,2)="B_", $M30+$O30, IF(LEFT($B30,2)="C_", $L30+$O30, $F30))))>0, $AA30 / (IF(LEFT($B30,2)="A_", $O30, IF(LEFT($B30,2)="B_", $M30+$O30, IF(LEFT($B30,2)="C_", $L30+$O30, $F30)))), "") -> 4767.6264
A31: =Y31 -> G_DHub_EchoRamp|FY2030 | B31: =Scenarios!A7 -> G_DHub_EchoRamp | C31: FY2030 | D31: =IF(Scenarios!D7=1,0, L31) -> 362 | E31: =IF(Scenarios!E7=1,0, M31) -> 341 | F31: =D31+E31 -> 703 | G31: =YearMap!B6 -> 7869.1704 | H31: =YearMap!C6 -> 866732.91 | I31: =YearMap!D6 -> 998260.47 | J31: =1-BaselineCalc!$B$5 -> 0.993 | K31: =Scenarios!G7 -> 0 | L31: =BaselineCalc!$B$7 + ROUND(Scenarios!M7*Scenarios!F7,0) -> 362 | M31: =BaselineCalc!$B$8 + Scenarios!M7 - ROUND(Scenarios!M7*Scenarios!F7,0) -> 341 | N31: =(L31-D31) + (M31-E31) -> 0 | O31: =BaselineCalc!$B$22 * N31 -> 0 | P31: =YearMap!E6 -> 300 | Q31: =IF(Scenarios!N7="lease", YearMap!F6, YearMap!G6) -> 0.2 | R31: =IF(Scenarios!D7=1, Q31*H31, H31) -> 866732.91 | S31: =IF(Scenarios!E7=1, Q31*I31, I31) -> 998260.47 | T31: =IF(C31="FY2026", (Scenarios!D7+Scenarios!E7)*BaselineCalc!$B$21, 0) -> 0 | U31: =(R31+S31+G31*F31)*J31*(1-K31) -> 7345241 | V31: =O31*(G31+P31) -> 0 | W31: =U31+V31+T31 -> 7345241 | X31: =IF(F31+O31>0, W31/(F31+O31),"") -> 10448.423 | Y31: =B31&"|"&C31 -> G_DHub_EchoRamp|FY2030 | Z31: =INDEX(YearMap!$I$2:$I$6, MATCH(C31, YearMap!$A$2:$A$6, 0)) -> 5534.4756 | AA31: =$W31 - $Z31 * (IF(LEFT($B31,2)="A_", $O31, IF(LEFT($B31,2)="B_", $M31+$O31, IF(LEFT($B31,2)="C_", $L31+$O31, $F31)))) -> 3454504.7 | AB31: =IF((IF(LEFT($B31,2)="A_", $O31, IF(LEFT($B31,2)="B_", $M31+$O31, IF(LEFT($B31,2)="C_", $L31+$O31, $F31))))>0, $AA31 / (IF(LEFT($B31,2)="A_", $O31, IF(LEFT($B31,2)="B_", $M31+$O31, IF(LEFT($B31,2)="C_", $L31+$O31, $F31)))), "") -> 4913.9469
A32: =Y32 -> A_Repurpose_Both_lease|FY2026 | B32: =Scenarios!A8 -> A_Repurpose_Both_lease | C32: FY2026 | D32: =IF(Scenarios!D8=1,0, L32) -> 0 | E32: =IF(Scenarios!E8=1,0, M32) -> 0 | F32: =D32+E32 -> 0 | G32: =YearMap!B2 -> 7129.08 | H32: =YearMap!C2 -> 785217.24 | I32: =YearMap!D2 -> 904374.72 | J32: =1-BaselineCalc!$B$5 -> 0.993 | K32: =Scenarios!G8 -> 0 | L32: =BaselineCalc!$B$7 + ROUND(Scenarios!I8*Scenarios!F8,0) -> 257 | M32: =BaselineCalc!$B$8 + Scenarios!I8 - ROUND(Scenarios!I8*Scenarios!F8,0) -> 296 | N32: =(L32-D32) + (M32-E32) -> 553 | O32: =BaselineCalc!$B$22 * N32 -> 414.75 | P32: =YearMap!E2 -> 1000 | Q32: =IF(Scenarios!N8="lease", YearMap!F2, YearMap!G2) -> 0.4 | R32: =IF(Scenarios!D8=1, Q32*H32, H32) -> 314086.9 | S32: =IF(Scenarios!E8=1, Q32*I32, I32) -> 361749.89 | T32: =IF(C32="FY2026", (Scenarios!D8+Scenarios!E8)*BaselineCalc!$B$21, 0) -> 2400000 | U32: =(R32+S32+G32*F32)*J32*(1-K32) -> 671105.93 | V32: =O32*(G32+P32) -> 3371535.9 | W32: =U32+V32+T32 -> 6442641.9 | X32: =IF(F32+O32>0, W32/(F32+O32),"") -> 15533.796 | Y32: =B32&"|"&C32 -> A_Repurpose_Both_lease|FY2026 | Z32: =INDEX(YearMap!$I$2:$I$6, MATCH(C32, YearMap!$A$2:$A$6, 0)) -> 5113 | AA32: =$W32 - $Z32 * (IF(LEFT($B32,2)="A_", $O32, IF(LEFT($B32,2)="B_", $M32+$O32, IF(LEFT($B32,2)="C_", $L32+$O32, $F32)))) -> 4322025.1 | AB32: =IF((IF(LEFT($B32,2)="A_", $O32, IF(LEFT($B32,2)="B_", $M32+$O32, IF(LEFT($B32,2)="C_", $L32+$O32, $F32))))>0, $AA32 / (IF(LEFT($B32,2)="A_", $O32, IF(LEFT($B32,2)="B_", $M32+$O32, IF(LEFT($B32,2)="C_", $L32+$O32, $F32)))), "") -> 10420.796
A33: =Y33 -> A_Repurpose_Both_lease|FY2027 | B33: =Scenarios!A8 -> A_Repurpose_Both_lease | C33: FY2027 | D33: =IF(Scenarios!D8=1,0, L33) -> 0 | E33: =IF(Scenarios!E8=1,0, M33) -> 0 | F33: =D33+E33 -> 0 | G33: =YearMap!B3 -> 7307.307 | H33: =YearMap!C3 -> 804847.67 | I33: =YearMap!D3 -> 926984.09 | J33: =1-BaselineCalc!$B$5 -> 0.993 | K33: =Scenarios!G8 -> 0 | L33: =BaselineCalc!$B$7 + ROUND(Scenarios!J8*Scenarios!F8,0) -> 257 | M33: =BaselineCalc!$B$8 + Scenarios!J8 - ROUND(Scenarios!J8*Scenarios!F8,0) -> 296 | N33: =(L33-D33) + (M33-E33) -> 553 | O33: =BaselineCalc!$B$22 * N33 -> 414.75 | P33: =YearMap!E3 -> 800 | Q33: =IF(Scenarios!N8="lease", YearMap!F3, YearMap!G3) -> 0.3 | R33: =IF(Scenarios!D8=1, Q33*H33, H33) -> 241454.3 | S33: =IF(Scenarios!E8=1, Q33*I33, I33) -> 278095.23 | T33: =IF(C33="FY2026", (Scenarios!D8+Scenarios!E8)*BaselineCalc!$B$21, 0) -> 0 | U33: =(R33+S33+G33*F33)*J33*(1-K33) -> 515912.68 | V33: =O33*(G33+P33) -> 3362505.6 | W33: =U33+V33+T33 -> 3878418.3 | X33: =IF(F33+O33>0, W33/(F33+O33),"") -> 9351.2194 | Y33: =B33&"|"&C33 -> A_Repurpose_Both_lease|FY2027 | Z33: =INDEX(YearMap!$I$2:$I$6, MATCH(C33, YearMap!$A$2:$A$6, 0)) -> 5215.26 | AA33: =$W33 - $Z33 * (IF(LEFT($B33,2)="A_", $O33, IF(LEFT($B33,2)="B_", $M33+$O33, IF(LEFT($B33,2)="C_", $L33+$O33, $F33)))) -> 1715389.2 | AB33: =IF((IF(LEFT($B33,2)="A_", $O33, IF(LEFT($B33,2)="B_", $M33+$O33, IF(LEFT($B33,2)="C_", $L33+$O33, $F33))))>0, $AA33 / (IF(LEFT($B33,2)="A_", $O33, IF(LEFT($B33,2)="B_", $M33+$O33, IF(LEFT($B33,2)="C_", $L33+$O33, $F33)))), "") -> 4135.9594
A34: =Y34 -> A_Repurpose_Both_lease|FY2028 | B34: =Scenarios!A8 -> A_Repurpose_Both_lease | C34: FY2028 | D34: =IF(Scenarios!D8=1,0, L34) -> 0 | E34: =IF(Scenarios!E8=1,0, M34) -> 0 | F34: =D34+E34 -> 0 | G34: =YearMap!B4 -> 7489.9897 | H34: =YearMap!C4 -> 824968.86 | I34: =YearMap!D4 -> 950158.69 | J34: =1-BaselineCalc!$B$5 -> 0.993 | K34: =Scenarios!G8 -> 0 | L34: =BaselineCalc!$B$7 + ROUND(Scenarios!K8*Scenarios!F8,0) -> 257 | M34: =BaselineCalc!$B$8 + Scenarios!K8 - ROUND(Scenarios!K8*Scenarios!F8,0) -> 296 | N34: =(L34-D34) + (M34-E34) -> 553 | O34: =BaselineCalc!$B$22 * N34 -> 414.75 | P34: =YearMap!E4 -> 600 | Q34: =IF(Scenarios!N8="lease", YearMap!F4, YearMap!G4) -> 0.2 | R34: =IF(Scenarios!D8=1, Q34*H34, H34) -> 164993.77 | S34: =IF(Scenarios!E8=1, Q34*I34, I34) -> 190031.74 | T34: =IF(C34="FY2026", (Scenarios!D8+Scenarios!E8)*BaselineCalc!$B$21, 0) -> 0 | U34: =(R34+S34+G34*F34)*J34*(1-K34) -> 352540.33 | V34: =O34*(G34+P34) -> 3355323.2 | W34: =U34+V34+T34 -> 3707863.5 | X34: =IF(F34+O34>0, W34/(F34+O34),"") -> 8939.9965 | Y34: =B34&"|"&C34 -> A_Repurpose_Both_lease|FY2028 | Z34: =INDEX(YearMap!$I$2:$I$6, MATCH(C34, YearMap!$A$2:$A$6, 0)) -> 5319.5652 | AA34: =$W34 - $Z34 * (IF(LEFT($B34,2)="A_", $O34, IF(LEFT($B34,2)="B_", $M34+$O34, IF(LEFT($B34,2)="C_", $L34+$O34, $F34)))) -> 1501573.9 | AB34: =IF((IF(LEFT($B34,2)="A_", $O34, IF(LEFT($B34,2)="B_", $M34+$O34, IF(LEFT($B34,2)="C_", $L34+$O34, $F34))))>0, $AA34 / (IF(LEFT($B34,2)="A_", $O34, IF(LEFT($B34,2)="B_", $M34+$O34, IF(LEFT($B34,2)="C_", $L34+$O34, $F34)))), "") -> 3620.4313
A35: =Y35 -> A_Repurpose_Both_lease|FY2029 | B35: =Scenarios!A8 -> A_Repurpose_Both_lease | C35: FY2029 | D35: =IF(Scenarios!D8=1,0, L35) -> 0 | E35: =IF(Scenarios!E8=1,0, M35) -> 0 | F35: =D35+E35 -> 0 | G35: =YearMap!B5 -> 7677.2394 | H35: =YearMap!C5 -> 845593.08 | I35: =YearMap!D5 -> 973912.66 | J35: =1-BaselineCalc!$B$5 -> 0.993 | K35: =Scenarios!G8 -> 0 | L35: =BaselineCalc!$B$7 + ROUND(Scenarios!L8*Scenarios!F8,0) -> 257 | M35: =BaselineCalc!$B$8 + Scenarios!L8 - ROUND(Scenarios!L8*Scenarios!F8,0) -> 296 | N35: =(L35-D35) + (M35-E35) -> 553 | O35: =BaselineCalc!$B$22 * N35 -> 414.75 | P35: =YearMap!E5 -> 400 | Q35: =IF(Scenarios!N8="lease", YearMap!F5, YearMap!G5) -> 0.1 | R35: =IF(Scenarios!D8=1, Q35*H35, H35) -> 84559.308 | S35: =IF(Scenarios!E8=1, Q35*I35, I35) -> 97391.266 | T35: =IF(C35="FY2026", (Scenarios!D8+Scenarios!E8)*BaselineCalc!$B$21, 0) -> 0 | U35: =(R35+S35+G35*F35)*J35*(1-K35) -> 180676.92 | V35: =O35*(G35+P35) -> 3350035 | W35: =U35+V35+T35 -> 3530712 | X35: =IF(F35+O35>0, W35/(F35+O35),"") -> 8512.8679 | Y35: =B35&"|"&C35 -> A_Repurpose_Both_lease|FY2029 | Z35: =INDEX(YearMap!$I$2:$I$6, MATCH(C35, YearMap!$A$2:$A$6, 0)) -> 5425.9565 | AA35: =$W35 - $Z35 * (IF(LEFT($B35,2)="A_", $O35, IF(LEFT($B35,2)="B_", $M35+$O35, IF(LEFT($B35,2)="C_", $L35+$O35, $F35)))) -> 1280296.5 | AB35: =IF((IF(LEFT($B35,2)="A_", $O35, IF(LEFT($B35,2)="B_", $M35+$O35, IF(LEFT($B35,2)="C_", $L35+$O35, $F35))))>0, $AA35 / (IF(LEFT($B35,2)="A_", $O35, IF(LEFT($B35,2)="B_", $M35+$O35, IF(LEFT($B35,2)="C_", $L35+$O35, $F35)))), "") -> 3086.9114
A36: =Y36 -> A_Repurpose_Both_lease|FY2030 | B36: =Scenarios!A8 -> A_Repurpose_Both_lease | C36: FY2030 | D36: =IF(Scenarios!D8=1,0, L36) -> 0 | E36: =IF(Scenarios!E8=1,0, M36) -> 0 | F36: =D36+E36 -> 0 | G36: =YearMap!B6 -> 7869.1704 | H36: =YearMap!C6 -> 866732.91 | I36: =YearMap!D6 -> 998260.47 | J36: =1-BaselineCalc!$B$5 -> 0.993 | K36: =Scenarios!G8 -> 0 | L36: =BaselineCalc!$B$7 + ROUND(Scenarios!M8*Scenarios!F8,0) -> 257 | M36: =BaselineCalc!$B$8 + Scenarios!M8 - ROUND(Scenarios!M8*Scenarios!F8,0) -> 296 | N36: =(L36-D36) + (M36-E36) -> 553 | O36: =BaselineCalc!$B$22 * N36 -> 414.75 | P36: =YearMap!E6 -> 300 | Q36: =IF(Scenarios!N8="lease", YearMap!F6, YearMap!G6) -> 0 | R36: =IF(Scenarios!D8=1, Q36*H36, H36) -> 0 | S36: =IF(Scenarios!E8=1, Q36*I36, I36) -> 0 | T36: =IF(C36="FY2026", (Scenarios!D8+Scenarios!E8)*BaselineCalc!$B$21, 0) -> 0 | U36: =(R36+S36+G36*F36)*J36*(1-K36) -> 0 | V36: =O36*(G36+P36) -> 3388163.4 | W36: =U36+V36+T36 -> 3388163.4 | X36: =IF(F36+O36>0, W36/(F36+O36),"") -> 8169.1704 | Y36: =B36&"|"&C36 -> A_Repurpose_Both_lease|FY2030 | Z36: =INDEX(YearMap!$I$2:$I$6, MATCH(C36, YearMap!$A$2:$A$6, 0)) -> 5534.4756 | AA36: =$W36 - $Z36 * (IF(LEFT($B36,2)="A_", $O36, IF(LEFT($B36,2)="B_", $M36+$O36, IF(LEFT($B36,2)="C_", $L36+$O36, $F36)))) -> 1092739.7 | AB36: =IF((IF(LEFT($B36,2)="A_", $O36, IF(LEFT($B36,2)="B_", $M36+$O36, IF(LEFT($B36,2)="C_", $L36+$O36, $F36))))>0, $AA36 / (IF(LEFT($B36,2)="A_", $O36, IF(LEFT($B36,2)="B_", $M36+$O36, IF(LEFT($B36,2)="C_", $L36+$O36, $F36)))), "") -> 2634.6948
A37: =Y37 -> A_Repurpose_Both_ops|FY2026 | B37: =Scenarios!A9 -> A_Repurpose_Both_ops | C37: FY2026 | D37: =IF(Scenarios!D9=1,0, L37) -> 0 | E37: =IF(Scenarios!E9=1,0, M37) -> 0 | F37: =D37+E37 -> 0 | G37: =YearMap!B2 -> 7129.08 | H37: =YearMap!C2 -> 785217.24 | I37: =YearMap!D2 -> 904374.72 | J37: =1-BaselineCalc!$B$5 -> 0.993 | K37: =Scenarios!G9 -> 0 | L37: =BaselineCalc!$B$7 + ROUND(Scenarios!I9*Scenarios!F9,0) -> 257 | M37: =BaselineCalc!$B$8 + Scenarios!I9 - ROUND(Scenarios!I9*Scenarios!F9,0) -> 296 | N37: =(L37-D37) + (M37-E37) -> 553 | O37: =BaselineCalc!$B$22 * N37 -> 414.75 | P37: =YearMap!E2 -> 1000 | Q37: =IF(Scenarios!N9="lease", YearMap!F2, YearMap!G2) -> 0.4 | R37: =IF(Scenarios!D9=1, Q37*H37, H37) -> 314086.9 | S37: =IF(Scenarios!E9=1, Q37*I37, I37) -> 361749.89 | T37: =IF(C37="FY2026", (Scenarios!D9+Scenarios!E9)*BaselineCalc!$B$21, 0) -> 2400000 | U37: =(R37+S37+G37*F37)*J37*(1-K37) -> 671105.93 | V37: =O37*(G37+P37) -> 3371535.9 | W37: =U37+V37+T37 -> 6442641.9 | X37: =IF(F37+O37>0, W37/(F37+O37),"") -> 15533.796 | Y37: =B37&"|"&C37 -> A_Repurpose_Both_ops|FY2026 | Z37: =INDEX(YearMap!$I$2:$I$6, MATCH(C37, YearMap!$A$2:$A$6, 0)) -> 5113 | AA37: =$W37 - $Z37 * (IF(LEFT($B37,2)="A_", $O37, IF(LEFT($B37,2)="B_", $M37+$O37, IF(LEFT($B37,2)="C_", $L37+$O37, $F37)))) -> 4322025.1 | AB37: =IF((IF(LEFT($B37,2)="A_", $O37, IF(LEFT($B37,2)="B_", $M37+$O37, IF(LEFT($B37,2)="C_", $L37+$O37, $F37))))>0, $AA37 / (IF(LEFT($B37,2)="A_", $O37, IF(LEFT($B37,2)="B_", $M37+$O37, IF(LEFT($B37,2)="C_", $L37+$O37, $F37)))), "") -> 10420.796
A38: =Y38 -> A_Repurpose_Both_ops|FY2027 | B38: =Scenarios!A9 -> A_Repurpose_Both_ops | C38: FY2027 | D38: =IF(Scenarios!D9=1,0, L38) -> 0 | E38: =IF(Scenarios!E9=1,0, M38) -> 0 | F38: =D38+E38 -> 0 | G38: =YearMap!B3 -> 7307.307 | H38: =YearMap!C3 -> 804847.67 | I38: =YearMap!D3 -> 926984.09 | J38: =1-BaselineCalc!$B$5 -> 0.993 | K38: =Scenarios!G9 -> 0 | L38: =BaselineCalc!$B$7 + ROUND(Scenarios!J9*Scenarios!F9,0) -> 257 | M38: =BaselineCalc!$B$8 + Scenarios!J9 - ROUND(Scenarios!J9*Scenarios!F9,0) -> 296 | N38: =(L38-D38) + (M38-E38) -> 553 | O38: =BaselineCalc!$B$22 * N38 -> 414.75 | P38: =YearMap!E3 -> 800 | Q38: =IF(Scenarios!N9="lease", YearMap!F3, YearMap!G3) -> 0.35 | R38: =IF(Scenarios!D9=1, Q38*H38, H38) -> 281696.68 | S38: =IF(Scenarios!E9=1, Q38*I38, I38) -> 324444.43 | T38: =IF(C38="FY2026", (Scenarios!D9+Scenarios!E9)*BaselineCalc!$B$21, 0) -> 0 | U38: =(R38+S38+G38*F38)*J38*(1-K38) -> 601898.13 | V38: =O38*(G38+P38) -> 3362505.6 | W38: =U38+V38+T38 -> 3964403.7 | X38: =IF(F38+O38>0, W38/(F38+O38),"") -> 9558.5382 | Y38: =B38&"|"&C38 -> A_Repurpose_Both_ops|FY2027 | Z38: =INDEX(YearMap!$I$2:$I$6, MATCH(C38, YearMap!$A$2:$A$6, 0)) -> 5215.26 | AA38: =$W38 - $Z38 * (IF(LEFT($B38,2)="A_", $O38, IF(LEFT($B38,2)="B_", $M38+$O38, IF(LEFT($B38,2)="C_", $L38+$O38, $F38)))) -> 1801374.6 | AB38: =IF((IF(LEFT($B38,2)="A_", $O38, IF(LEFT($B38,2)="B_", $M38+$O38, IF(LEFT($B38,2)="C_", $L38+$O38, $F38))))>0, $AA38 / (IF(LEFT($B38,2)="A_", $O38, IF(LEFT($B38,2)="B_", $M38+$O38, IF(LEFT($B38,2)="C_", $L38+$O38, $F38)))), "") -> 4343.2782
A39: =Y39 -> A_Repurpose_Both_ops|FY2028 | B39: =Scenarios!A9 -> A_Repurpose_Both_ops | C39: FY2028 | D39: =IF(Scenarios!D9=1,0, L39) -> 0 | E39: =IF(Scenarios!E9=1,0, M39) -> 0 | F39: =D39+E39 -> 0 | G39: =YearMap!B4 -> 7489.9897 | H39: =YearMap!C4 -> 824968.86 | I39: =YearMap!D4 -> 950158.69 | J39: =1-BaselineCalc!$B$5 -> 0.993 | K39: =Scenarios!G9 -> 0 | L39: =BaselineCalc!$B$7 + ROUND(Scenarios!K9*Scenarios!F9,0) -> 257 | M39: =BaselineCalc!$B$8 + Scenarios!K9 - ROUND(Scenarios!K9*Scenarios!F9,0) -> 296 | N39: =(L39-D39) + (M39-E39) -> 553 | O39: =BaselineCalc!$B$22 * N39 -> 414.75 | P39: =YearMap!E4 -> 600 | Q39: =IF(Scenarios!N9="lease", YearMap!F4, YearMap!G4) -> 0.3 | R39: =IF(Scenarios!D9=1, Q39*H39, H39) -> 247490.66 | S39: =IF(Scenarios!E9=1, Q39*I39, I39) -> 285047.61 | T39: =IF(C39="FY2026", (Scenarios!D9+Scenarios!E9)*BaselineCalc!$B$21, 0) -> 0 | U39: =(R39+S39+G39*F39)*J39*(1-K39) -> 528810.5 | V39: =O39*(G39+P39) -> 3355323.2 | W39: =U39+V39+T39 -> 3884133.7 | X39: =IF(F39+O39>0, W39/(F39+O39),"") -> 9364.9999 | Y39: =B39&"|"&C39 -> A_Repurpose_Both_ops|FY2028 | Z39: =INDEX(YearMap!$I$2:$I$6, MATCH(C39, YearMap!$A$2:$A$6, 0)) -> 5319.5652 | AA39: =$W39 - $Z39 * (IF(LEFT($B39,2)="A_", $O39, IF(LEFT($B39,2)="B_", $M39+$O39, IF(LEFT($B39,2)="C_", $L39+$O39, $F39)))) -> 1677844 | AB39: =IF((IF(LEFT($B39,2)="A_", $O39, IF(LEFT($B39,2)="B_", $M39+$O39, IF(LEFT($B39,2)="C_", $L39+$O39, $F39))))>0, $AA39 / (IF(LEFT($B39,2)="A_", $O39, IF(LEFT($B39,2)="B_", $M39+$O39, IF(LEFT($B39,2)="C_", $L39+$O39, $F39)))), "") -> 4045.4347
A40: =Y40 -> A_Repurpose_Both_ops|FY2029 | B40: =Scenarios!A9 -> A_Repurpose_Both_ops | C40: FY2029 | D40: =IF(Scenarios!D9=1,0, L40) -> 0 | E40: =IF(Scenarios!E9=1,0, M40) -> 0 | F40: =D40+E40 -> 0 | G40: =YearMap!B5 -> 7677.2394 | H40: =YearMap!C5 -> 845593.08 | I40: =YearMap!D5 -> 973912.66 | J40: =1-BaselineCalc!$B$5 -> 0.993 | K40: =Scenarios!G9 -> 0 | L40: =BaselineCalc!$B$7 + ROUND(Scenarios!L9*Scenarios!F9,0) -> 257 | M40: =BaselineCalc!$B$8 + Scenarios!L9 - ROUND(Scenarios!L9*Scenarios!F9,0) -> 296 | N40: =(L40-D40) + (M40-E40) -> 553 | O40: =BaselineCalc!$B$22 * N40 -> 414.75 | P40: =YearMap!E5 -> 400 | Q40: =IF(Scenarios!N9="lease", YearMap!F5, YearMap!G5) -> 0.25 | R40: =IF(Scenarios!D9=1, Q40*H40, H40) -> 211398.27 | S40: =IF(Scenarios!E9=1, Q40*I40, I40) -> 243478.16 | T40: =IF(C40="FY2026", (Scenarios!D9+Scenarios!E9)*BaselineCalc!$B$21, 0) -> 0 | U40: =(R40+S40+G40*F40)*J40*(1-K40) -> 451692.3 | V40: =O40*(G40+P40) -> 3350035 | W40: =U40+V40+T40 -> 3801727.3 | X40: =IF(F40+O40>0, W40/(F40+O40),"") -> 9166.3107 | Y40: =B40&"|"&C40 -> A_Repurpose_Both_ops|FY2029 | Z40: =INDEX(YearMap!$I$2:$I$6, MATCH(C40, YearMap!$A$2:$A$6, 0)) -> 5425.9565 | AA40: =$W40 - $Z40 * (IF(LEFT($B40,2)="A_", $O40, IF(LEFT($B40,2)="B_", $M40+$O40, IF(LEFT($B40,2)="C_", $L40+$O40, $F40)))) -> 1551311.9 | AB40: =IF((IF(LEFT($B40,2)="A_", $O40, IF(LEFT($B40,2)="B_", $M40+$O40, IF(LEFT($B40,2)="C_", $L40+$O40, $F40))))>0, $AA40 / (IF(LEFT($B40,2)="A_", $O40, IF(LEFT($B40,2)="B_", $M40+$O40, IF(LEFT($B40,2)="C_", $L40+$O40, $F40)))), "") -> 3740.3542
A41: =Y41 -> A_Repurpose_Both_ops|FY2030 | B41: =Scenarios!A9 -> A_Repurpose_Both_ops | C41: FY2030 | D41: =IF(Scenarios!D9=1,0, L41) -> 0 | E41: =IF(Scenarios!E9=1,0, M41) -> 0 | F41: =D41+E41 -> 0 | G41: =YearMap!B6 -> 7869.1704 | H41: =YearMap!C6 -> 866732.91 | I41: =YearMap!D6 -> 998260.47 | J41: =1-BaselineCalc!$B$5 -> 0.993 | K41: =Scenarios!G9 -> 0 | L41: =BaselineCalc!$B$7 + ROUND(Scenarios!M9*Scenarios!F9,0) -> 257 | M41: =BaselineCalc!$B$8 + Scenarios!M9 - ROUND(Scenarios!M9*Scenarios!F9,0) -> 296 | N41: =(L41-D41) + (M41-E41) -> 553 | O41: =BaselineCalc!$B$22 * N41 -> 414.75 | P41: =YearMap!E6 -> 300 | Q41: =IF(Scenarios!N9="lease", YearMap!F6, YearMap!G6) -> 0.2 | R41: =IF(Scenarios!D9=1, Q41*H41, H41) -> 173346.58 | S41: =IF(Scenarios!E9=1, Q41*I41, I41) -> 199652.09 | T41: =IF(C41="FY2026", (Scenarios!D9+Scenarios!E9)*BaselineCalc!$B$21, 0) -> 0 | U41: =(R41+S41+G41*F41)*J41*(1-K41) -> 370387.69 | V41: =O41*(G41+P41) -> 3388163.4 | W41: =U41+V41+T41 -> 3758551.1 | X41: =IF(F41+O41>0, W41/(F41+O41),"") -> 9062.2088 | Y41: =B41&"|"&C41 -> A_Repurpose_Both_ops|FY2030 | Z41: =INDEX(YearMap!$I$2:$I$6, MATCH(C41, YearMap!$A$2:$A$6, 0)) -> 5534.4756 | AA41: =$W41 - $Z41 * (IF(LEFT($B41,2)="A_", $O41, IF(LEFT($B41,2)="B_", $M41+$O41, IF(LEFT($B41,2)="C_", $L41+$O41, $F41)))) -> 1463127.3 | AB41: =IF((IF(LEFT($B41,2)="A_", $O41, IF(LEFT($B41,2)="B_", $M41+$O41, IF(LEFT($B41,2)="C_", $L41+$O41, $F41))))>0, $AA41 / (IF(LEFT($B41,2)="A_", $O41, IF(LEFT($B41,2)="B_", $M41+$O41, IF(LEFT($B41,2)="C_", $L41+$O41, $F41)))), "") -> 3527.7332
A42: =Y42 -> B_Repurpose_Echo_lease|FY2026 | B42: =Scenarios!A10 -> B_Repurpose_Echo_lease | C42: FY2026 | D42: =IF(Scenarios!D10=1,0, L42) -> 0 | E42: =IF(Scenarios!E10=1,0, M42) -> 296 | F42: =D42+E42 -> 296 | G42: =YearMap!B2 -> 7129.08 | H42: =YearMap!C2 -> 785217.24 | I42: =YearMap!D2 -> 904374.72 | J42: =1-BaselineCalc!$B$5 -> 0.993 | K42: =Scenarios!G10 -> 0 | L42: =BaselineCalc!$B$7 + ROUND(Scenarios!I10*Scenarios!F10,0) -> 257 | M42: =BaselineCalc!$B$8 + Scenarios!I10 - ROUND(Scenarios!I10*Scenarios!F10,0) -> 296 | N42: =(L42-D42) + (M42-E42) -> 257 | O42: =BaselineCalc!$B$22 * N42 -> 192.75 | P42: =YearMap!E2 -> 1000 | Q42: =IF(Scenarios!N10="lease", YearMap!F2, YearMap!G2) -> 0.4 | R42: =IF(Scenarios!D10=1, Q42*H42, H42) -> 314086.9 | S42: =IF(Scenarios!E10=1, Q42*I42, I42) -> 904374.72 | T42: =IF(C42="FY2026", (Scenarios!D10+Scenarios!E10)*BaselineCalc!$B$21, 0) -> 1200000 | U42: =(R42+S42+G42*F42)*J42*(1-K42) -> 3305368.6 | V42: =O42*(G42+P42) -> 1566880.2 | W42: =U42+V42+T42 -> 6072248.8 | X42: =IF(F42+O42>0, W42/(F42+O42),"") -> 12424.038 | Y42: =B42&"|"&C42 -> B_Repurpose_Echo_lease|FY2026 | Z42: =INDEX(YearMap!$I$2:$I$6, MATCH(C42, YearMap!$A$2:$A$6, 0)) -> 5113 | AA42: =$W42 - $Z42 * (IF(LEFT($B42,2)="A_", $O42, IF(LEFT($B42,2)="B_", $M42+$O42, IF(LEFT($B42,2)="C_", $L42+$O42, $F42)))) -> 3573270 | AB42: =IF((IF(LEFT($B42,2)="A_", $O42, IF(LEFT($B42,2)="B_", $M42+$O42, IF(LEFT($B42,2)="C_", $L42+$O42, $F42))))>0, $AA42 / (IF(LEFT($B42,2)="A_", $O42, IF(LEFT($B42,2)="B_", $M42+$O42, IF(LEFT($B42,2)="C_", $L42+$O42, $F42)))), "") -> 7311.0384
A43: =Y43 -> B_Repurpose_Echo_lease|FY2027 | B43: =Scenarios!A10 -> B_Repurpose_Echo_lease | C43: FY2027 | D43: =IF(Scenarios!D10=1,0, L43) -> 0 | E43: =IF(Scenarios!E10=1,0, M43) -> 296 | F43: =D43+E43 -> 296 | G43: =YearMap!B3 -> 7307.307 | H43: =YearMap!C3 -> 804847.67 | I43: =YearMap!D3 -> 926984.09 | J43: =1-BaselineCalc!$B$5 -> 0.993 | K43: =Scenarios!G10 -> 0 | L43: =BaselineCalc!$B$7 + ROUND(Scenarios!J10*Scenarios!F10,0) -> 257 | M43: =BaselineCalc!$B$8 + Scenarios!J10 - ROUND(Scenarios!J10*Scenarios!F10,0) -> 296 | N43: =(L43-D43) + (M43-E43) -> 257 | O43: =BaselineCalc!$B$22 * N43 -> 192.75 | P43: =YearMap!E3 -> 800 | Q43: =IF(Scenarios!N10="lease", YearMap!F3, YearMap!G3) -> 0.3 | R43: =IF(Scenarios!D10=1, Q43*H43, H43) -> 241454.3 | S43: =IF(Scenarios!E10=1, Q43*I43, I43) -> 926984.09 | T43: =IF(C43="FY2026", (Scenarios!D10+Scenarios!E10)*BaselineCalc!$B$21, 0) -> 0 | U43: =(R43+S43+G43*F43)*J43*(1-K43) -> 3308081.5 | V43: =O43*(G43+P43) -> 1562683.4 | W43: =U43+V43+T43 -> 4870764.9 | X43: =IF(F43+O43>0, W43/(F43+O43),"") -> 9965.7593 | Y43: =B43&"|"&C43 -> B_Repurpose_Echo_lease|FY2027 | Z43: =INDEX(YearMap!$I$2:$I$6, MATCH(C43, YearMap!$A$2:$A$6, 0)) -> 5215.26 | AA43: =$W43 - $Z43 * (IF(LEFT($B43,2)="A_", $O43, IF(LEFT($B43,2)="B_", $M43+$O43, IF(LEFT($B43,2)="C_", $L43+$O43, $F43)))) -> 2321806.6 | AB43: =IF((IF(LEFT($B43,2)="A_", $O43, IF(LEFT($B43,2)="B_", $M43+$O43, IF(LEFT($B43,2)="C_", $L43+$O43, $F43))))>0, $AA43 / (IF(LEFT($B43,2)="A_", $O43, IF(LEFT($B43,2)="B_", $M43+$O43, IF(LEFT($B43,2)="C_", $L43+$O43, $F43)))), "") -> 4750.4993
A44: =Y44 -> B_Repurpose_Echo_lease|FY2028 | B44: =Scenarios!A10 -> B_Repurpose_Echo_lease | C44: FY2028 | D44: =IF(Scenarios!D10=1,0, L44) -> 0 | E44: =IF(Scenarios!E10=1,0, M44) -> 296 | F44: =D44+E44 -> 296 | G44: =YearMap!B4 -> 7489.9897 | H44: =YearMap!C4 -> 824968.86 | I44: =YearMap!D4 -> 950158.69 | J44: =1-BaselineCalc!$B$5 -> 0.993 | K44: =Scenarios!G10 -> 0 | L44: =BaselineCalc!$B$7 + ROUND(Scenarios!K10*Scenarios!F10,0) -> 257 | M44: =BaselineCalc!$B$8 + Scenarios!K10 - ROUND(Scenarios!K10*Scenarios!F10,0) -> 296 | N44: =(L44-D44) + (M44-E44) -> 257 | O44: =BaselineCalc!$B$22 * N44 -> 192.75 | P44: =YearMap!E4 -> 600 | Q44: =IF(Scenarios!N10="lease", YearMap!F4, YearMap!G4) -> 0.2 | R44: =IF(Scenarios!D10=1, Q44*H44, H44) -> 164993.77 | S44: =IF(Scenarios!E10=1, Q44*I44, I44) -> 950158.69 | T44: =IF(C44="FY2026", (Scenarios!D10+Scenarios!E10)*BaselineCalc!$B$21, 0) -> 0 | U44: =(R44+S44+G44*F44)*J44*(1-K44) -> 3308864.1 | V44: =O44*(G44+P44) -> 1559345.5 | W44: =U44+V44+T44 -> 4868209.6 | X44: =IF(F44+O44>0, W44/(F44+O44),"") -> 9960.5311 | Y44: =B44&"|"&C44 -> B_Repurpose_Echo_lease|FY2028 | Z44: =INDEX(YearMap!$I$2:$I$6, MATCH(C44, YearMap!$A$2:$A$6, 0)) -> 5319.5652 | AA44: =$W44 - $Z44 * (IF(LEFT($B44,2)="A_", $O44, IF(LEFT($B44,2)="B_", $M44+$O44, IF(LEFT($B44,2)="C_", $L44+$O44, $F44)))) -> 2268272.1 | AB44: =IF((IF(LEFT($B44,2)="A_", $O44, IF(LEFT($B44,2)="B_", $M44+$O44, IF(LEFT($B44,2)="C_", $L44+$O44, $F44))))>0, $AA44 / (IF(LEFT($B44,2)="A_", $O44, IF(LEFT($B44,2)="B_", $M44+$O44, IF(LEFT($B44,2)="C_", $L44+$O44, $F44)))), "") -> 4640.9659
A45: =Y45 -> B_Repurpose_Echo_lease|FY2029 | B45: =Scenarios!A10 -> B_Repurpose_Echo_lease | C45: FY2029 | D45: =IF(Scenarios!D10=1,0, L45) -> 0 | E45: =IF(Scenarios!E10=1,0, M45) -> 296 | F45: =D45+E45 -> 296 | G45: =YearMap!B5 -> 7677.2394 | H45: =YearMap!C5 -> 845593.08 | I45: =YearMap!D5 -> 973912.66 | J45: =1-BaselineCalc!$B$5 -> 0.993 | K45: =Scenarios!G10 -> 0 | L45: =BaselineCalc!$B$7 + ROUND(Scenarios!L10*Scenarios!F10,0) -> 257 | M45: =BaselineCalc!$B$8 + Scenarios!L10 - ROUND(Scenarios!L10*Scenarios!F10,0) -> 296 | N45: =(L45-D45) + (M45-E45) -> 257 | O45: =BaselineCalc!$B$22 * N45 -> 192.75 | P45: =YearMap!E5 -> 400 | Q45: =IF(Scenarios!N10="lease", YearMap!F5, YearMap!G5) -> 0.1 | R45: =IF(Scenarios!D10=1, Q45*H45, H45) -> 84559.308 | S45: =IF(Scenarios!E10=1, Q45*I45, I45) -> 973912.66 | T45: =IF(C45="FY2026", (Scenarios!D10+Scenarios!E10)*BaselineCalc!$B$21, 0) -> 0 | U45: =(R45+S45+G45*F45)*J45*(1-K45) -> 3307618.3 | V45: =O45*(G45+P45) -> 1556887.9 | W45: =U45+V45+T45 -> 4864506.2 | X45: =IF(F45+O45>0, W45/(F45+O45),"") -> 9952.9538 | Y45: =B45&"|"&C45 -> B_Repurpose_Echo_lease|FY2029 | Z45: =INDEX(YearMap!$I$2:$I$6, MATCH(C45, YearMap!$A$2:$A$6, 0)) -> 5425.9565 | AA45: =$W45 - $Z45 * (IF(LEFT($B45,2)="A_", $O45, IF(LEFT($B45,2)="B_", $M45+$O45, IF(LEFT($B45,2)="C_", $L45+$O45, $F45)))) -> 2212569.9 | AB45: =IF((IF(LEFT($B45,2)="A_", $O45, IF(LEFT($B45,2)="B_", $M45+$O45, IF(LEFT($B45,2)="C_", $L45+$O45, $F45))))>0, $AA45 / (IF(LEFT($B45,2)="A_", $O45, IF(LEFT($B45,2)="B_", $M45+$O45, IF(LEFT($B45,2)="C_", $L45+$O45, $F45)))), "") -> 4526.9973
A46: =Y46 -> B_Repurpose_Echo_lease|FY2030 | B46: =Scenarios!A10 -> B_Repurpose_Echo_lease | C46: FY2030 | D46: =IF(Scenarios!D10=1,0, L46) -> 0 | E46: =IF(Scenarios!E10=1,0, M46) -> 296 | F46: =D46+E46 -> 296 | G46: =YearMap!B6 -> 7869.1704 | H46: =YearMap!C6 -> 866732.91 | I46: =YearMap!D6 -> 998260.47 | J46: =1-BaselineCalc!$B$5 -> 0.993 | K46: =Scenarios!G10 -> 0 | L46: =BaselineCalc!$B$7 + ROUND(Scenarios!M10*Scenarios!F10,0) -> 257 | M46: =BaselineCalc!$B$8 + Scenarios!M10 - ROUND(Scenarios!M10*Scenarios!F10,0) -> 296 | N46: =(L46-D46) + (M46-E46) -> 257 | O46: =BaselineCalc!$B$22 * N46 -> 192.75 | P46: =YearMap!E6 -> 300 | Q46: =IF(Scenarios!N10="lease", YearMap!F6, YearMap!G6) -> 0 | R46: =IF(Scenarios!D10=1, Q46*H46, H46) -> 0 | S46: =IF(Scenarios!E10=1, Q46*I46, I46) -> 998260.47 | T46: =IF(C46="FY2026", (Scenarios!D10+Scenarios!E10)*BaselineCalc!$B$21, 0) -> 0 | U46: =(R46+S46+G46*F46)*J46*(1-K46) -> 3304242.2 | V46: =O46*(G46+P46) -> 1574607.6 | W46: =U46+V46+T46 -> 4878849.8 | X46: =IF(F46+O46>0, W46/(F46+O46),"") -> 9982.3013 | Y46: =B46&"|"&C46 -> B_Repurpose_Echo_lease|FY2030 | Z46: =INDEX(YearMap!$I$2:$I$6, MATCH(C46, YearMap!$A$2:$A$6, 0)) -> 5534.4756 | AA46: =$W46 - $Z46 * (IF(LEFT($B46,2)="A_", $O46, IF(LEFT($B46,2)="B_", $M46+$O46, IF(LEFT($B46,2)="C_", $L46+$O46, $F46)))) -> 2173874.8 | AB46: =IF((IF(LEFT($B46,2)="A_", $O46, IF(LEFT($B46,2)="B_", $M46+$O46, IF(LEFT($B46,2)="C_", $L46+$O46, $F46))))>0, $AA46 / (IF(LEFT($B46,2)="A_", $O46, IF(LEFT($B46,2)="B_", $M46+$O46, IF(LEFT($B46,2)="C_", $L46+$O46, $F46)))), "") -> 4447.8257
A47: =Y47 -> B_Repurpose_Echo_ops|FY2026 | B47: =Scenarios!A11 -> B_Repurpose_Echo_ops | C47: FY2026 | D47: =IF(Scenarios!D11=1,0, L47) -> 0 | E47: =IF(Scenarios!E11=1,0, M47) -> 296 | F47: =D47+E47 -> 296 | G47: =YearMap!B2 -> 7129.08 | H47: =YearMap!C2 -> 785217.24 | I47: =YearMap!D2 -> 904374.72 | J47: =1-BaselineCalc!$B$5 -> 0.993 | K47: =Scenarios!G11 -> 0 | L47: =BaselineCalc!$B$7 + ROUND(Scenarios!I11*Scenarios!F11,0) -> 257 | M47: =BaselineCalc!$B$8 + Scenarios!I11 - ROUND(Scenarios!I11*Scenarios!F11,0) -> 296 | N47: =(L47-D47) + (M47-E47) -> 257 | O47: =BaselineCalc!$B$22 * N47 -> 192.75 | P47: =YearMap!E2 -> 1000 | Q47: =IF(Scenarios!N11="lease", YearMap!F2, YearMap!G2) -> 0.4 | R47: =IF(Scenarios!D11=1, Q47*H47, H47) -> 314086.9 | S47: =IF(Scenarios!E11=1, Q47*I47, I47) -> 904374.72 | T47: =IF(C47="FY2026", (Scenarios!D11+Scenarios!E11)*BaselineCalc!$B$21, 0) -> 1200000 | U47: =(R47+S47+G47*F47)*J47*(1-K47) -> 3305368.6 | V47: =O47*(G47+P47) -> 1566880.2 | W47: =U47+V47+T47 -> 6072248.8 | X47: =IF(F47+O47>0, W47/(F47+O47),"") -> 12424.038 | Y47: =B47&"|"&C47 -> B_Repurpose_Echo_ops|FY2026 | Z47: =INDEX(YearMap!$I$2:$I$6, MATCH(C47, YearMap!$A$2:$A$6, 0)) -> 5113 | AA47: =$W47 - $Z47 * (IF(LEFT($B47,2)="A_", $O47, IF(LEFT($B47,2)="B_", $M47+$O47, IF(LEFT($B47,2)="C_", $L47+$O47, $F47)))) -> 3573270 | AB47: =IF((IF(LEFT($B47,2)="A_", $O47, IF(LEFT($B47,2)="B_", $M47+$O47, IF(LEFT($B47,2)="C_", $L47+$O47, $F47))))>0, $AA47 / (IF(LEFT($B47,2)="A_", $O47, IF(LEFT($B47,2)="B_", $M47+$O47, IF(LEFT($B47,2)="C_", $L47+$O47, $F47)))), "") -> 7311.0384
A48: =Y48 -> B_Repurpose_Echo_ops|FY2027 | B48: =Scenarios!A11 -> B_Repurpose_Echo_ops | C48: FY2027 | D48: =IF(Scenarios!D11=1,0, L48) -> 0 | E48: =IF(Scenarios!E11=1,0, M48) -> 296 | F48: =D48+E48 -> 296 | G48: =YearMap!B3 -> 7307.307 | H48: =YearMap!C3 -> 804847.67 | I48: =YearMap!D3 -> 926984.09 | J48: =1-BaselineCalc!$B$5 -> 0.993 | K48: =Scenarios!G11 -> 0 | L48: =BaselineCalc!$B$7 + ROUND(Scenarios!J11*Scenarios!F11,0) -> 257 | M48: =BaselineCalc!$B$8 + Scenarios!J11 - ROUND(Scenarios!J11*Scenarios!F11,0) -> 296 | N48: =(L48-D48) + (M48-E48) -> 257 | O48: =BaselineCalc!$B$22 * N48 -> 192.75 | P48: =YearMap!E3 -> 800 | Q48: =IF(Scenarios!N11="lease", YearMap!F3, YearMap!G3) -> 0.35 | R48: =IF(Scenarios!D11=1, Q48*H48, H48) -> 281696.68 | S48: =IF(Scenarios!E11=1, Q48*I48, I48) -> 926984.09 | T48: =IF(C48="FY2026", (Scenarios!D11+Scenarios!E11)*BaselineCalc!$B$21, 0) -> 0 | U48: =(R48+S48+G48*F48)*J48*(1-K48) -> 3348042.1 | V48: =O48*(G48+P48) -> 1562683.4 | W48: =U48+V48+T48 -> 4910725.6 | X48: =IF(F48+O48>0, W48/(F48+O48),"") -> 10047.52 | Y48: =B48&"|"&C48 -> B_Repurpose_Echo_ops|FY2027 | Z48: =INDEX(YearMap!$I$2:$I$6, MATCH(C48, YearMap!$A$2:$A$6, 0)) -> 5215.26 | AA48: =$W48 - $Z48 * (IF(LEFT($B48,2)="A_", $O48, IF(LEFT($B48,2)="B_", $M48+$O48, IF(LEFT($B48,2)="C_", $L48+$O48, $F48)))) -> 2361767.2 | AB48: =IF((IF(LEFT($B48,2)="A_", $O48, IF(LEFT($B48,2)="B_", $M48+$O48, IF(LEFT($B48,2)="C_", $L48+$O48, $F48))))>0, $AA48 / (IF(LEFT($B48,2)="A_", $O48, IF(LEFT($B48,2)="B_", $M48+$O48, IF(LEFT($B48,2)="C_", $L48+$O48, $F48)))), "") -> 4832.2603
A49: =Y49 -> B_Repurpose_Echo_ops|FY2028 | B49: =Scenarios!A11 -> B_Repurpose_Echo_ops | C49: FY2028 | D49: =IF(Scenarios!D11=1,0, L49) -> 0 | E49: =IF(Scenarios!E11=1,0, M49) -> 296 | F49: =D49+E49 -> 296 | G49: =YearMap!B4 -> 7489.9897 | H49: =YearMap!C4 -> 824968.86 | I49: =YearMap!D4 -> 950158.69 | J49: =1-BaselineCalc!$B$5 -> 0.993 | K49: =Scenarios!G11 -> 0 | L49: =BaselineCalc!$B$7 + ROUND(Scenarios!K11*Scenarios!F11,0) -> 257 | M49: =BaselineCalc!$B$8 + Scenarios!K11 - ROUND(Scenarios!K11*Scenarios!F11,0) -> 296 | N49: =(L49-D49) + (M49-E49) -> 257 | O49: =BaselineCalc!$B$22 * N49 -> 192.75 | P49: =YearMap!E4 -> 600 | Q49: =IF(Scenarios!N11="lease", YearMap!F4, YearMap!G4) -> 0.3 | R49: =IF(Scenarios!D11=1, Q49*H49, H49) -> 247490.66 | S49: =IF(Scenarios!E11=1, Q49*I49, I49) -> 950158.69 | T49: =IF(C49="FY2026", (Scenarios!D11+Scenarios!E11)*BaselineCalc!$B$21, 0) -> 0 | U49: =(R49+S49+G49*F49)*J49*(1-K49) -> 3390783.5 | V49: =O49*(G49+P49) -> 1559345.5 | W49: =U49+V49+T49 -> 4950129 | X49: =IF(F49+O49>0, W49/(F49+O49),"") -> 10128.141 | Y49: =B49&"|"&C49 -> B_Repurpose_Echo_ops|FY2028 | Z49: =INDEX(YearMap!$I$2:$I$6, MATCH(C49, YearMap!$A$2:$A$6, 0)) -> 5319.5652 | AA49: =$W49 - $Z49 * (IF(LEFT($B49,2)="A_", $O49, IF(LEFT($B49,2)="B_", $M49+$O49, IF(LEFT($B49,2)="C_", $L49+$O49, $F49)))) -> 2350191.5 | AB49: =IF((IF(LEFT($B49,2)="A_", $O49, IF(LEFT($B49,2)="B_", $M49+$O49, IF(LEFT($B49,2)="C_", $L49+$O49, $F49))))>0, $AA49 / (IF(LEFT($B49,2)="A_", $O49, IF(LEFT($B49,2)="B_", $M49+$O49, IF(LEFT($B49,2)="C_", $L49+$O49, $F49)))), "") -> 4808.576
A50: =Y50 -> B_Repurpose_Echo_ops|FY2029 | B50: =Scenarios!A11 -> B_Repurpose_Echo_ops | C50: FY2029 | D50: =IF(Scenarios!D11=1,0, L50) -> 0 | E50: =IF(Scenarios!E11=1,0, M50) -> 296 | F50: =D50+E50 -> 296 | G50: =YearMap!B5 -> 7677.2394 | H50: =YearMap!C5 -> 845593.08 | I50: =YearMap!D5 -> 973912.66 | J50: =1-BaselineCalc!$B$5 -> 0.993 | K50: =Scenarios!G11 -> 0 | L50: =BaselineCalc!$B$7 + ROUND(Scenarios!L11*Scenarios!F11,0) -> 257 | M50: =BaselineCalc!$B$8 + Scenarios!L11 - ROUND(Scenarios!L11*Scenarios!F11,0) -> 296 | N50: =(L50-D50) + (M50-E50) -> 257 | O50: =BaselineCalc!$B$22 * N50 -> 192.75 | P50: =YearMap!E5 -> 400 | Q50: =IF(Scenarios!N11="lease", YearMap!F5, YearMap!G5) -> 0.25 | R50: =IF(Scenarios!D11=1, Q50*H50, H50) -> 211398.27 | S50: =IF(Scenarios!E11=1, Q50*I50, I50) -> 973912.66 | T50: =IF(C50="FY2026", (Scenarios!D11+Scenarios!E11)*BaselineCalc!$B$21, 0) -> 0 | U50: =(R50+S50+G50*F50)*J50*(1-K50) -> 3433569.4 | V50: =O50*(G50+P50) -> 1556887.9 | W50: =U50+V50+T50 -> 4990457.3 | X50: =IF(F50+O50>0, W50/(F50+O50),"") -> 10210.654 | Y50: =B50&"|"&C50 -> B_Repurpose_Echo_ops|FY2029 | Z50: =INDEX(YearMap!$I$2:$I$6, MATCH(C50, YearMap!$A$2:$A$6, 0)) -> 5425.9565 | AA50: =$W50 - $Z50 * (IF(LEFT($B50,2)="A_", $O50, IF(LEFT($B50,2)="B_", $M50+$O50, IF(LEFT($B50,2)="C_", $L50+$O50, $F50)))) -> 2338521 | AB50: =IF((IF(LEFT($B50,2)="A_", $O50, IF(LEFT($B50,2)="B_", $M50+$O50, IF(LEFT($B50,2)="C_", $L50+$O50, $F50))))>0, $AA50 / (IF(LEFT($B50,2)="A_", $O50, IF(LEFT($B50,2)="B_", $M50+$O50, IF(LEFT($B50,2)="C_", $L50+$O50, $F50)))), "") -> 4784.6978
A51: =Y51 -> B_Repurpose_Echo_ops|FY2030 | B51: =Scenarios!A11 -> B_Repurpose_Echo_ops | C51: FY2030 | D51: =IF(Scenarios!D11=1,0, L51) -> 0 | E51: =IF(Scenarios!E11=1,0, M51) -> 296 | F51: =D51+E51 -> 296 | G51: =YearMap!B6 -> 7869.1704 | H51: =YearMap!C6 -> 866732.91 | I51: =YearMap!D6 -> 998260.47 | J51: =1-BaselineCalc!$B$5 -> 0.993 | K51: =Scenarios!G11 -> 0 | L51: =BaselineCalc!$B$7 + ROUND(Scenarios!M11*Scenarios!F11,0) -> 257 | M51: =BaselineCalc!$B$8 + Scenarios!M11 - ROUND(Scenarios!M11*Scenarios!F11,0) -> 296 | N51: =(L51-D51) + (M51-E51) -> 257 | O51: =BaselineCalc!$B$22 * N51 -> 192.75 | P51: =YearMap!E6 -> 300 | Q51: =IF(Scenarios!N11="lease", YearMap!F6, YearMap!G6) -> 0.2 | R51: =IF(Scenarios!D11=1, Q51*H51, H51) -> 173346.58 | S51: =IF(Scenarios!E11=1, Q51*I51, I51) -> 998260.47 | T51: =IF(C51="FY2026", (Scenarios!D11+Scenarios!E11)*BaselineCalc!$B$21, 0) -> 0 | U51: =(R51+S51+G51*F51)*J51*(1-K51) -> 3476375.3 | V51: =O51*(G51+P51) -> 1574607.6 | W51: =U51+V51+T51 -> 5050982.9 | X51: =IF(F51+O51>0, W51/(F51+O51),"") -> 10334.492 | Y51: =B51&"|"&C51 -> B_Repurpose_Echo_ops|FY2030 | Z51: =INDEX(YearMap!$I$2:$I$6, MATCH(C51, YearMap!$A$2:$A$6, 0)) -> 5534.4756 | AA51: =$W51 - $Z51 * (IF(LEFT($B51,2)="A_", $O51, IF(LEFT($B51,2)="B_", $M51+$O51, IF(LEFT($B51,2)="C_", $L51+$O51, $F51)))) -> 2346008 | AB51: =IF((IF(LEFT($B51,2)="A_", $O51, IF(LEFT($B51,2)="B_", $M51+$O51, IF(LEFT($B51,2)="C_", $L51+$O51, $F51))))>0, $AA51 / (IF(LEFT($B51,2)="A_", $O51, IF(LEFT($B51,2)="B_", $M51+$O51, IF(LEFT($B51,2)="C_", $L51+$O51, $F51)))), "") -> 4800.0163
A52: =Y52 -> C_Repurpose_Pima_lease|FY2026 | B52: =Scenarios!A12 -> C_Repurpose_Pima_lease | C52: FY2026 | D52: =IF(Scenarios!D12=1,0, L52) -> 257 | E52: =IF(Scenarios!E12=1,0, M52) -> 0 | F52: =D52+E52 -> 257 | G52: =YearMap!B2 -> 7129.08 | H52: =YearMap!C2 -> 785217.24 | I52: =YearMap!D2 -> 904374.72 | J52: =1-BaselineCalc!$B$5 -> 0.993 | K52: =Scenarios!G12 -> 0 | L52: =BaselineCalc!$B$7 + ROUND(Scenarios!I12*Scenarios!F12,0) -> 257 | M52: =BaselineCalc!$B$8 + Scenarios!I12 - ROUND(Scenarios!I12*Scenarios!F12,0) -> 296 | N52: =(L52-D52) + (M52-E52) -> 296 | O52: =BaselineCalc!$B$22 * N52 -> 222 | P52: =YearMap!E2 -> 1000 | Q52: =IF(Scenarios!N12="lease", YearMap!F2, YearMap!G2) -> 0.4 | R52: =IF(Scenarios!D12=1, Q52*H52, H52) -> 785217.24 | S52: =IF(Scenarios!E12=1, Q52*I52, I52) -> 361749.89 | T52: =IF(C52="FY2026", (Scenarios!D12+Scenarios!E12)*BaselineCalc!$B$21, 0) -> 1200000 | U52: =(R52+S52+G52*F52)*J52*(1-K52) -> 2958286.7 | V52: =O52*(G52+P52) -> 1804655.8 | W52: =U52+V52+T52 -> 5962942.5 | X52: =IF(F52+O52>0, W52/(F52+O52),"") -> 12448.732 | Y52: =B52&"|"&C52 -> C_Repurpose_Pima_lease|FY2026 | Z52: =INDEX(YearMap!$I$2:$I$6, MATCH(C52, YearMap!$A$2:$A$6, 0)) -> 5113 | AA52: =$W52 - $Z52 * (IF(LEFT($B52,2)="A_", $O52, IF(LEFT($B52,2)="B_", $M52+$O52, IF(LEFT($B52,2)="C_", $L52+$O52, $F52)))) -> 3513815.5 | AB52: =IF((IF(LEFT($B52,2)="A_", $O52, IF(LEFT($B52,2)="B_", $M52+$O52, IF(LEFT($B52,2)="C_", $L52+$O52, $F52))))>0, $AA52 / (IF(LEFT($B52,2)="A_", $O52, IF(LEFT($B52,2)="B_", $M52+$O52, IF(LEFT($B52,2)="C_", $L52+$O52, $F52)))), "") -> 7335.7317
A53: =Y53 -> C_Repurpose_Pima_lease|FY2027 | B53: =Scenarios!A12 -> C_Repurpose_Pima_lease | C53: FY2027 | D53: =IF(Scenarios!D12=1,0, L53) -> 257 | E53: =IF(Scenarios!E12=1,0, M53) -> 0 | F53: =D53+E53 -> 257 | G53: =YearMap!B3 -> 7307.307 | H53: =YearMap!C3 -> 804847.67 | I53: =YearMap!D3 -> 926984.09 | J53: =1-BaselineCalc!$B$5 -> 0.993 | K53: =Scenarios!G12 -> 0 | L53: =BaselineCalc!$B$7 + ROUND(Scenarios!J12*Scenarios!F12,0) -> 257 | M53: =BaselineCalc!$B$8 + Scenarios!J12 - ROUND(Scenarios!J12*Scenarios!F12,0) -> 296 | N53: =(L53-D53) + (M53-E53) -> 296 | O53: =BaselineCalc!$B$22 * N53 -> 222 | P53: =YearMap!E3 -> 800 | Q53: =IF(Scenarios!N12="lease", YearMap!F3, YearMap!G3) -> 0.3 | R53: =IF(Scenarios!D12=1, Q53*H53, H53) -> 804847.67 | S53: =IF(Scenarios!E12=1, Q53*I53, I53) -> 278095.23 | T53: =IF(C53="FY2026", (Scenarios!D12+Scenarios!E12)*BaselineCalc!$B$21, 0) -> 0 | U53: =(R53+S53+G53*F53)*J53*(1-K53) -> 2940194.4 | V53: =O53*(G53+P53) -> 1799822.2 | W53: =U53+V53+T53 -> 4740016.5 | X53: =IF(F53+O53>0, W53/(F53+O53),"") -> 9895.6503 | Y53: =B53&"|"&C53 -> C_Repurpose_Pima_lease|FY2027 | Z53: =INDEX(YearMap!$I$2:$I$6, MATCH(C53, YearMap!$A$2:$A$6, 0)) -> 5215.26 | AA53: =$W53 - $Z53 * (IF(LEFT($B53,2)="A_", $O53, IF(LEFT($B53,2)="B_", $M53+$O53, IF(LEFT($B53,2)="C_", $L53+$O53, $F53)))) -> 2241907 | AB53: =IF((IF(LEFT($B53,2)="A_", $O53, IF(LEFT($B53,2)="B_", $M53+$O53, IF(LEFT($B53,2)="C_", $L53+$O53, $F53))))>0, $AA53 / (IF(LEFT($B53,2)="A_", $O53, IF(LEFT($B53,2)="B_", $M53+$O53, IF(LEFT($B53,2)="C_", $L53+$O53, $F53)))), "") -> 4680.3903
A54: =Y54 -> C_Repurpose_Pima_lease|FY2028 | B54: =Scenarios!A12 -> C_Repurpose_Pima_lease | C54: FY2028 | D54: =IF(Scenarios!D12=1,0, L54) -> 257 | E54: =IF(Scenarios!E12=1,0, M54) -> 0 | F54: =D54+E54 -> 257 | G54: =YearMap!B4 -> 7489.9897 | H54: =YearMap!C4 -> 824968.86 | I54: =YearMap!D4 -> 950158.69 | J54: =1-BaselineCalc!$B$5 -> 0.993 | K54: =Scenarios!G12 -> 0 | L54: =BaselineCalc!$B$7 + ROUND(Scenarios!K12*Scenarios!F12,0) -> 257 | M54: =BaselineCalc!$B$8 + Scenarios!K12 - ROUND(Scenarios!K12*Scenarios!F12,0) -> 296 | N54: =(L54-D54) + (M54-E54) -> 296 | O54: =BaselineCalc!$B$22 * N54 -> 222 | P54: =YearMap!E4 -> 600 | Q54: =IF(Scenarios!N12="lease", YearMap!F4, YearMap!G4) -> 0.2 | R54: =IF(Scenarios!D12=1, Q54*H54, H54) -> 824968.86 | S54: =IF(Scenarios!E12=1, Q54*I54, I54) -> 190031.74 | T54: =IF(C54="FY2026", (Scenarios!D12+Scenarios!E12)*BaselineCalc!$B$21, 0) -> 0 | U54: =(R54+S54+G54*F54)*J54*(1-K54) -> 2919348.5 | V54: =O54*(G54+P54) -> 1795977.7 | W54: =U54+V54+T54 -> 4715326.2 | X54: =IF(F54+O54>0, W54/(F54+O54),"") -> 9844.1047 | Y54: =B54&"|"&C54 -> C_Repurpose_Pima_lease|FY2028 | Z54: =INDEX(YearMap!$I$2:$I$6, MATCH(C54, YearMap!$A$2:$A$6, 0)) -> 5319.5652 | AA54: =$W54 - $Z54 * (IF(LEFT($B54,2)="A_", $O54, IF(LEFT($B54,2)="B_", $M54+$O54, IF(LEFT($B54,2)="C_", $L54+$O54, $F54)))) -> 2167254.4 | AB54: =IF((IF(LEFT($B54,2)="A_", $O54, IF(LEFT($B54,2)="B_", $M54+$O54, IF(LEFT($B54,2)="C_", $L54+$O54, $F54))))>0, $AA54 / (IF(LEFT($B54,2)="A_", $O54, IF(LEFT($B54,2)="B_", $M54+$O54, IF(LEFT($B54,2)="C_", $L54+$O54, $F54)))), "") -> 4524.5395
A55: =Y55 -> C_Repurpose_Pima_lease|FY2029 | B55: =Scenarios!A12 -> C_Repurpose_Pima_lease | C55: FY2029 | D55: =IF(Scenarios!D12=1,0, L55) -> 257 | E55: =IF(Scenarios!E12=1,0, M55) -> 0 | F55: =D55+E55 -> 257 | G55: =YearMap!B5 -> 7677.2394 | H55: =YearMap!C5 -> 845593.08 | I55: =YearMap!D5 -> 973912.66 | J55: =1-BaselineCalc!$B$5 -> 0.993 | K55: =Scenarios!G12 -> 0 | L55: =BaselineCalc!$B$7 + ROUND(Scenarios!L12*Scenarios!F12,0) -> 257 | M55: =BaselineCalc!$B$8 + Scenarios!L12 - ROUND(Scenarios!L12*Scenarios!F12,0) -> 296 | N55: =(L55-D55) + (M55-E55) -> 296 | O55: =BaselineCalc!$B$22 * N55 -> 222 | P55: =YearMap!E5 -> 400 | Q55: =IF(Scenarios!N12="lease", YearMap!F5, YearMap!G5) -> 0.1 | R55: =IF(Scenarios!D12=1, Q55*H55, H55) -> 845593.08 | S55: =IF(Scenarios!E12=1, Q55*I55, I55) -> 97391.266 | T55: =IF(C55="FY2026", (Scenarios!D12+Scenarios!E12)*BaselineCalc!$B$21, 0) -> 0 | U55: =(R55+S55+G55*F55)*J55*(1-K55) -> 2895622.6 | V55: =O55*(G55+P55) -> 1793147.2 | W55: =U55+V55+T55 -> 4688769.8 | X55: =IF(F55+O55>0, W55/(F55+O55),"") -> 9788.6634 | Y55: =B55&"|"&C55 -> C_Repurpose_Pima_lease|FY2029 | Z55: =INDEX(YearMap!$I$2:$I$6, MATCH(C55, YearMap!$A$2:$A$6, 0)) -> 5425.9565 | AA55: =$W55 - $Z55 * (IF(LEFT($B55,2)="A_", $O55, IF(LEFT($B55,2)="B_", $M55+$O55, IF(LEFT($B55,2)="C_", $L55+$O55, $F55)))) -> 2089736.6 | AB55: =IF((IF(LEFT($B55,2)="A_", $O55, IF(LEFT($B55,2)="B_", $M55+$O55, IF(LEFT($B55,2)="C_", $L55+$O55, $F55))))>0, $AA55 / (IF(LEFT($B55,2)="A_", $O55, IF(LEFT($B55,2)="B_", $M55+$O55, IF(LEFT($B55,2)="C_", $L55+$O55, $F55)))), "") -> 4362.7069
A56: =Y56 -> C_Repurpose_Pima_lease|FY2030 | B56: =Scenarios!A12 -> C_Repurpose_Pima_lease | C56: FY2030 | D56: =IF(Scenarios!D12=1,0, L56) -> 257 | E56: =IF(Scenarios!E12=1,0, M56) -> 0 | F56: =D56+E56 -> 257 | G56: =YearMap!B6 -> 7869.1704 | H56: =YearMap!C6 -> 866732.91 | I56: =YearMap!D6 -> 998260.47 | J56: =1-BaselineCalc!$B$5 -> 0.993 | K56: =Scenarios!G12 -> 0 | L56: =BaselineCalc!$B$7 + ROUND(Scenarios!M12*Scenarios!F12,0) -> 257 | M56: =BaselineCalc!$B$8 + Scenarios!M12 - ROUND(Scenarios!M12*Scenarios!F12,0) -> 296 | N56: =(L56-D56) + (M56-E56) -> 296 | O56: =BaselineCalc!$B$22 * N56 -> 222 | P56: =YearMap!E6 -> 300 | Q56: =IF(Scenarios!N12="lease", YearMap!F6, YearMap!G6) -> 0 | R56: =IF(Scenarios!D12=1, Q56*H56, H56) -> 866732.91 | S56: =IF(Scenarios!E12=1, Q56*I56, I56) -> 0 | T56: =IF(C56="FY2026", (Scenarios!D12+Scenarios!E12)*BaselineCalc!$B$21, 0) -> 0 | U56: =(R56+S56+G56*F56)*J56*(1-K56) -> 2868885.9 | V56: =O56*(G56+P56) -> 1813555.8 | W56: =U56+V56+T56 -> 4682441.8 | X56: =IF(F56+O56>0, W56/(F56+O56),"") -> 9775.4525 | Y56: =B56&"|"&C56 -> C_Repurpose_Pima_lease|FY2030 | Z56: =INDEX(YearMap!$I$2:$I$6, MATCH(C56, YearMap!$A$2:$A$6, 0)) -> 5534.4756 | AA56: =$W56 - $Z56 * (IF(LEFT($B56,2)="A_", $O56, IF(LEFT($B56,2)="B_", $M56+$O56, IF(LEFT($B56,2)="C_", $L56+$O56, $F56)))) -> 2031427.9 | AB56: =IF((IF(LEFT($B56,2)="A_", $O56, IF(LEFT($B56,2)="B_", $M56+$O56, IF(LEFT($B56,2)="C_", $L56+$O56, $F56))))>0, $AA56 / (IF(LEFT($B56,2)="A_", $O56, IF(LEFT($B56,2)="B_", $M56+$O56, IF(LEFT($B56,2)="C_", $L56+$O56, $F56)))), "") -> 4240.9769
A57: =Y57 -> C_Repurpose_Pima_ops|FY2026 | B57: =Scenarios!A13 -> C_Repurpose_Pima_ops | C57: FY2026 | D57: =IF(Scenarios!D13=1,0, L57) -> 257 | E57: =IF(Scenarios!E13=1,0, M57) -> 0 | F57: =D57+E57 -> 257 | G57: =YearMap!B2 -> 7129.08 | H57: =YearMap!C2 -> 785217.24 | I57: =YearMap!D2 -> 904374.72 | J57: =1-BaselineCalc!$B$5 -> 0.993 | K57: =Scenarios!G13 -> 0 | L57: =BaselineCalc!$B$7 + ROUND(Scenarios!I13*Scenarios!F13,0) -> 257 | M57: =BaselineCalc!$B$8 + Scenarios!I13 - ROUND(Scenarios!I13*Scenarios!F13,0) -> 296 | N57: =(L57-D57) + (M57-E57) -> 296 | O57: =BaselineCalc!$B$22 * N57 -> 222 | P57: =YearMap!E2 -> 1000 | Q57: =IF(Scenarios!N13="lease", YearMap!F2, YearMap!G2) -> 0.4 | R57: =IF(Scenarios!D13=1, Q57*H57, H57) -> 785217.24 | S57: =IF(Scenarios!E13=1, Q57*I57, I57) -> 361749.89 | T57: =IF(C57="FY2026", (Scenarios!D13+Scenarios!E13)*BaselineCalc!$B$21, 0) -> 1200000 | U57: =(R57+S57+G57*F57)*J57*(1-K57) -> 2958286.7 | V57: =O57*(G57+P57) -> 1804655.8 | W57: =U57+V57+T57 -> 5962942.5 | X57: =IF(F57+O57>0, W57/(F57+O57),"") -> 12448.732 | Y57: =B57&"|"&C57 -> C_Repurpose_Pima_ops|FY2026 | Z57: =INDEX(YearMap!$I$2:$I$6, MATCH(C57, YearMap!$A$2:$A$6, 0)) -> 5113 | AA57: =$W57 - $Z57 * (IF(LEFT($B57,2)="A_", $O57, IF(LEFT($B57,2)="B_", $M57+$O57, IF(LEFT($B57,2)="C_", $L57+$O57, $F57)))) -> 3513815.5 | AB57: =IF((IF(LEFT($B57,2)="A_", $O57, IF(LEFT($B57,2)="B_", $M57+$O57, IF(LEFT($B57,2)="C_", $L57+$O57, $F57))))>0, $AA57 / (IF(LEFT($B57,2)="A_", $O57, IF(LEFT($B57,2)="B_", $M57+$O57, IF(LEFT($B57,2)="C_", $L57+$O57, $F57)))), "") -> 7335.7317
A58: =Y58 -> C_Repurpose_Pima_ops|FY2027 | B58: =Scenarios!A13 -> C_Repurpose_Pima_ops | C58: FY2027 | D58: =IF(Scenarios!D13=1,0, L58) -> 257 | E58: =IF(Scenarios!E13=1,0, M58) -> 0 | F58: =D58+E58 -> 257 | G58: =YearMap!B3 -> 7307.307 | H58: =YearMap!C3 -> 804847.67 | I58: =YearMap!D3 -> 926984.09 | J58: =1-BaselineCalc!$B$5 -> 0.993 | K58: =Scenarios!G13 -> 0 | L58: =BaselineCalc!$B$7 + ROUND(Scenarios!J13*Scenarios!F13,0) -> 257 | M58: =BaselineCalc!$B$8 + Scenarios!J13 - ROUND(Scenarios!J13*Scenarios!F13,0) -> 296 | N58: =(L58-D58) + (M58-E58) -> 296 | O58: =BaselineCalc!$B$22 * N58 -> 222 | P58: =YearMap!E3 -> 800 | Q58: =IF(Scenarios!N13="lease", YearMap!F3, YearMap!G3) -> 0.35 | R58: =IF(Scenarios!D13=1, Q58*H58, H58) -> 804847.67 | S58: =IF(Scenarios!E13=1, Q58*I58, I58) -> 324444.43 | T58: =IF(C58="FY2026", (Scenarios!D13+Scenarios!E13)*BaselineCalc!$B$21, 0) -> 0 | U58: =(R58+S58+G58*F58)*J58*(1-K58) -> 2986219.1 | V58: =O58*(G58+P58) -> 1799822.2 | W58: =U58+V58+T58 -> 4786041.3 | X58: =IF(F58+O58>0, W58/(F58+O58),"") -> 9991.7354 | Y58: =B58&"|"&C58 -> C_Repurpose_Pima_ops|FY2027 | Z58: =INDEX(YearMap!$I$2:$I$6, MATCH(C58, YearMap!$A$2:$A$6, 0)) -> 5215.26 | AA58: =$W58 - $Z58 * (IF(LEFT($B58,2)="A_", $O58, IF(LEFT($B58,2)="B_", $M58+$O58, IF(LEFT($B58,2)="C_", $L58+$O58, $F58)))) -> 2287931.7 | AB58: =IF((IF(LEFT($B58,2)="A_", $O58, IF(LEFT($B58,2)="B_", $M58+$O58, IF(LEFT($B58,2)="C_", $L58+$O58, $F58))))>0, $AA58 / (IF(LEFT($B58,2)="A_", $O58, IF(LEFT($B58,2)="B_", $M58+$O58, IF(LEFT($B58,2)="C_", $L58+$O58, $F58)))), "") -> 4776.4754
A59: =Y59 -> C_Repurpose_Pima_ops|FY2028 | B59: =Scenarios!A13 -> C_Repurpose_Pima_ops | C59: FY2028 | D59: =IF(Scenarios!D13=1,0, L59) -> 257 | E59: =IF(Scenarios!E13=1,0, M59) -> 0 | F59: =D59+E59 -> 257 | G59: =YearMap!B4 -> 7489.9897 | H59: =YearMap!C4 -> 824968.86 | I59: =YearMap!D4 -> 950158.69 | J59: =1-BaselineCalc!$B$5 -> 0.993 | K59: =Scenarios!G13 -> 0 | L59: =BaselineCalc!$B$7 + ROUND(Scenarios!K13*Scenarios!F13,0) -> 257 | M59: =BaselineCalc!$B$8 + Scenarios!K13 - ROUND(Scenarios!K13*Scenarios!F13,0) -> 296 | N59: =(L59-D59) + (M59-E59) -> 296 | O59: =BaselineCalc!$B$22 * N59 -> 222 | P59: =YearMap!E4 -> 600 | Q59: =IF(Scenarios!N13="lease", YearMap!F4, YearMap!G4) -> 0.3 | R59: =IF(Scenarios!D13=1, Q59*H59, H59) -> 824968.86 | S59: =IF(Scenarios!E13=1, Q59*I59, I59) -> 285047.61 | T59: =IF(C59="FY2026", (Scenarios!D13+Scenarios!E13)*BaselineCalc!$B$21, 0) -> 0 | U59: =(R59+S59+G59*F59)*J59*(1-K59) -> 3013699.2 | V59: =O59*(G59+P59) -> 1795977.7 | W59: =U59+V59+T59 -> 4809676.9 | X59: =IF(F59+O59>0, W59/(F59+O59),"") -> 10041.079 | Y59: =B59&"|"&C59 -> C_Repurpose_Pima_ops|FY2028 | Z59: =INDEX(YearMap!$I$2:$I$6, MATCH(C59, YearMap!$A$2:$A$6, 0)) -> 5319.5652 | AA59: =$W59 - $Z59 * (IF(LEFT($B59,2)="A_", $O59, IF(LEFT($B59,2)="B_", $M59+$O59, IF(LEFT($B59,2)="C_", $L59+$O59, $F59)))) -> 2261605.2 | AB59: =IF((IF(LEFT($B59,2)="A_", $O59, IF(LEFT($B59,2)="B_", $M59+$O59, IF(LEFT($B59,2)="C_", $L59+$O59, $F59))))>0, $AA59 / (IF(LEFT($B59,2)="A_", $O59, IF(LEFT($B59,2)="B_", $M59+$O59, IF(LEFT($B59,2)="C_", $L59+$O59, $F59)))), "") -> 4721.514
A60: =Y60 -> C_Repurpose_Pima_ops|FY2029 | B60: =Scenarios!A13 -> C_Repurpose_Pima_ops | C60: FY2029 | D60: =IF(Scenarios!D13=1,0, L60) -> 257 | E60: =IF(Scenarios!E13=1,0, M60) -> 0 | F60: =D60+E60 -> 257 | G60: =YearMap!B5 -> 7677.2394 | H60: =YearMap!C5 -> 845593.08 | I60: =YearMap!D5 -> 973912.66 | J60: =1-BaselineCalc!$B$5 -> 0.993 | K60: =Scenarios!G13 -> 0 | L60: =BaselineCalc!$B$7 + ROUND(Scenarios!L13*Scenarios!F13,0) -> 257 | M60: =BaselineCalc!$B$8 + Scenarios!L13 - ROUND(Scenarios!L13*Scenarios!F13,0) -> 296 | N60: =(L60-D60) + (M60-E60) -> 296 | O60: =BaselineCalc!$B$22 * N60 -> 222 | P60: =YearMap!E5 -> 400 | Q60: =IF(Scenarios!N13="lease", YearMap!F5, YearMap!G5) -> 0.25 | R60: =IF(Scenarios!D13=1, Q60*H60, H60) -> 845593.08 | S60: =IF(Scenarios!E13=1, Q60*I60, I60) -> 243478.16 | T60: =IF(C60="FY2026", (Scenarios!D13+Scenarios!E13)*BaselineCalc!$B$21, 0) -> 0 | U60: =(R60+S60+G60*F60)*J60*(1-K60) -> 3040686.9 | V60: =O60*(G60+P60) -> 1793147.2 | W60: =U60+V60+T60 -> 4833834.1 | X60: =IF(F60+O60>0, W60/(F60+O60),"") -> 10091.512 | Y60: =B60&"|"&C60 -> C_Repurpose_Pima_ops|FY2029 | Z60: =INDEX(YearMap!$I$2:$I$6, MATCH(C60, YearMap!$A$2:$A$6, 0)) -> 5425.9565 | AA60: =$W60 - $Z60 * (IF(LEFT($B60,2)="A_", $O60, IF(LEFT($B60,2)="B_", $M60+$O60, IF(LEFT($B60,2)="C_", $L60+$O60, $F60)))) -> 2234800.9 | AB60: =IF((IF(LEFT($B60,2)="A_", $O60, IF(LEFT($B60,2)="B_", $M60+$O60, IF(LEFT($B60,2)="C_", $L60+$O60, $F60))))>0, $AA60 / (IF(LEFT($B60,2)="A_", $O60, IF(LEFT($B60,2)="B_", $M60+$O60, IF(LEFT($B60,2)="C_", $L60+$O60, $F60)))), "") -> 4665.5551
A61: =Y61 -> C_Repurpose_Pima_ops|FY2030 | B61: =Scenarios!A13 -> C_Repurpose_Pima_ops | C61: FY2030 | D61: =IF(Scenarios!D13=1,0, L61) -> 257 | E61: =IF(Scenarios!E13=1,0, M61) -> 0 | F61: =D61+E61 -> 257 | G61: =YearMap!B6 -> 7869.1704 | H61: =YearMap!C6 -> 866732.91 | I61: =YearMap!D6 -> 998260.47 | J61: =1-BaselineCalc!$B$5 -> 0.993 | K61: =Scenarios!G13 -> 0 | L61: =BaselineCalc!$B$7 + ROUND(Scenarios!M13*Scenarios!F13,0) -> 257 | M61: =BaselineCalc!$B$8 + Scenarios!M13 - ROUND(Scenarios!M13*Scenarios!F13,0) -> 296 | N61: =(L61-D61) + (M61-E61) -> 296 | O61: =BaselineCalc!$B$22 * N61 -> 222 | P61: =YearMap!E6 -> 300 | Q61: =IF(Scenarios!N13="lease", YearMap!F6, YearMap!G6) -> 0.2 | R61: =IF(Scenarios!D13=1, Q61*H61, H61) -> 866732.91 | S61: =IF(Scenarios!E13=1, Q61*I61, I61) -> 199652.09 | T61: =IF(C61="FY2026", (Scenarios!D13+Scenarios!E13)*BaselineCalc!$B$21, 0) -> 0 | U61: =(R61+S61+G61*F61)*J61*(1-K61) -> 3067140.5 | V61: =O61*(G61+P61) -> 1813555.8 | W61: =U61+V61+T61 -> 4880696.3 | X61: =IF(F61+O61>0, W61/(F61+O61),"") -> 10189.345 | Y61: =B61&"|"&C61 -> C_Repurpose_Pima_ops|FY2030 | Z61: =INDEX(YearMap!$I$2:$I$6, MATCH(C61, YearMap!$A$2:$A$6, 0)) -> 5534.4756 | AA61: =$W61 - $Z61 * (IF(LEFT($B61,2)="A_", $O61, IF(LEFT($B61,2)="B_", $M61+$O61, IF(LEFT($B61,2)="C_", $L61+$O61, $F61)))) -> 2229682.5 | AB61: =IF((IF(LEFT($B61,2)="A_", $O61, IF(LEFT($B61,2)="B_", $M61+$O61, IF(LEFT($B61,2)="C_", $L61+$O61, $F61))))>0, $AA61 / (IF(LEFT($B61,2)="A_", $O61, IF(LEFT($B61,2)="B_", $M61+$O61, IF(LEFT($B61,2)="C_", $L61+$O61, $F61)))), "") -> 4654.8695

Sheet Scenarios
A1: ScenarioKey | B1: Label | C1: Overlay | D1: CloseEcho | E1: ClosePima | F1: EchoShareDist | G1: ExtraSave | H1: Notes | I1: Overlay_FY26 | J1: Overlay_FY27 | K1: Overlay_FY28 | L1: Overlay_FY29 | M1: Overlay_FY30 | N1: Carry
A2: D_Grow_Both_0 | B2: D. Grow Both (Overlay 0) | C2: 0 | D2: 0 | E2: 0 | F2: 0.5 | G2: 0 | H2: Baseline + outreach; no closures | I2: =$C2 -> 0 | J2: =$C2 -> 0 | K2: =$C2 -> 0 | L2: =$C2 -> 0 | M2: =$C2 -> 0
A3: E_StatusQuo_Targets_0 | B3: E. Status‑Quo + Targets (0) | C3: 0 | D3: 0 | E3: 0 | F3: 0.5 | G3: 0 | H3: Baseline + targets; no closures | I3: =$C3 -> 0 | J3: =$C3 -> 0 | K3: =$C3 -> 0 | L3: =$C3 -> 0 | M3: =$C3 -> 0
A4: F_CoLocation_Echo_0 | B4: F. Co‑Location @ Echo (0) | C4: 0 | D4: 0 | E4: 0 | F4: 0.7 | G4: 0.015 | H4: Shared‑use efficiencies later (no closure) | I4: =$C4 -> 0 | J4: =$C4 -> 0 | K4: =$C4 -> 0 | L4: =$C4 -> 0 | M4: =$C4 -> 0
A5: D_Grow_Both_100 | B5: D. Grow Both (Overlay 100) | C5: 100 | D5: 0 | E5: 0 | F5: 0.5 | G5: 0 | H5: Baseline +100 overlay | I5: =$C5 -> 100 | J5: =$C5 -> 100 | K5: =$C5 -> 100 | L5: =$C5 -> 100 | M5: =$C5 -> 100
A6: D_Grow_Both_150 | B6: D. Grow Both (Overlay 150) | C6: 150 | D6: 0 | E6: 0 | F6: 0.5 | G6: 0 | H6: Baseline +150 overlay | I6: =$C6 -> 150 | J6: =$C6 -> 150 | K6: =$C6 -> 150 | L6: =$C6 -> 150 | M6: =$C6 -> 150
A7: G_DHub_EchoRamp | B7: G. D‑Hub @ Echo (Ramp 50→100→150) | C7: 150 | D7: 0 | E7: 0 | F7: 0.7 | G7: 0 | H7: Time‑phased ramp (+50,+100,+150 years 1–3) | I7: =C7/3 -> 50 | J7: =I7+C7/3 -> 100 | K7: =J7+C7/3 -> 150 | L7: =C7 -> 150 | M7: =C7 -> 150
A8: A_Repurpose_Both_lease | B8: A. Repurpose BOTH (lease) | C8: 0 | D8: 1 | E8: 1 | F8: 0.5 | G8: 0 | H8: Repurpose both; lease/sale glide | I8: =$C8 -> 0 | J8: =$C8 -> 0 | K8: =$C8 -> 0 | L8: =$C8 -> 0 | M8: =$C8 -> 0 | N8: lease
A9: A_Repurpose_Both_ops | B9: A. Repurpose BOTH (ops) | C9: 0 | D9: 1 | E9: 1 | F9: 0.5 | G9: 0 | H9: Repurpose both; operations carry | I9: =$C9 -> 0 | J9: =$C9 -> 0 | K9: =$C9 -> 0 | L9: =$C9 -> 0 | M9: =$C9 -> 0 | N9: ops
A10: B_Repurpose_Echo_lease | B10: B. Repurpose ECHO (lease) | C10: 0 | D10: 1 | E10: 0 | F10: 0.5 | G10: 0 | H10: Repurpose Echo only; lease glide | I10: =$C10 -> 0 | J10: =$C10 -> 0 | K10: =$C10 -> 0 | L10: =$C10 -> 0 | M10: =$C10 -> 0 | N10: lease
A11: B_Repurpose_Echo_ops | B11: B. Repurpose ECHO (ops) | C11: 0 | D11: 1 | E11: 0 | F11: 0.5 | G11: 0 | H11: Repurpose Echo only; ops carry | I11: =$C11 -> 0 | J11: =$C11 -> 0 | K11: =$C11 -> 0 | L11: =$C11 -> 0 | M11: =$C11 -> 0 | N11: ops
A12: C_Repurpose_Pima_lease | B12: C. Repurpose PIMA (lease) | C12: 0 | D12: 0 | E12: 1 | F12: 0.5 | G12: 0 | H12: Repurpose Pima only; lease glide | I12: =$C12 -> 0 | J12: =$C12 -> 0 | K12: =$C12 -> 0 | L12: =$C12 -> 0 | M12: =$C12 -> 0 | N12: lease
A13: C_Repurpose_Pima_ops | B13: C. Repurpose PIMA (ops) | C13: 0 | D13: 0 | E13: 1 | F13: 0.5 | G13: 0 | H13: Repurpose Pima only; ops carry | I13: =$C13 -> 0 | J13: =$C13 -> 0 | K13: =$C13 -> 0 | L13: =$C13 -> 0 | M13: =$C13 -> 0 | N13: ops
A15: ScenarioKey | B15: Year | C15: Echo_ADM | D15: Pima_ADM | E15: Total_ADM | F15: VarUnit$ | G15: EchoFixed$ | H15: PimaFixed$ | I15: Key
A16: =A2 -> D_Grow_Both_0 | B16: FY2026 | C16: =IF(D2=1,0, BaselineCalc!$B$7 + ROUND(I2*F2,0)) -> 257 | D16: =IF(E2=1,0, BaselineCalc!$B$8 + I2 - ROUND(I2*F2,0)) -> 296 | E16: =C16+D16 -> 553 | F16: =YearMap!B2 -> 7129.08 | G16: =YearMap!C2 -> 785217.24 | H16: =YearMap!D2 -> 904374.72 | I16: =A16&"|"&B16 -> D_Grow_Both_0|FY2026
A17: =A2 -> D_Grow_Both_0 | B17: FY2027 | C17: =IF(D2=1,0, BaselineCalc!$B$7 + ROUND(J2*F2,0)) -> 257 | D17: =IF(E2=1,0, BaselineCalc!$B$8 + J2 - ROUND(J2*F2,0)) -> 296 | E17: =C17+D17 -> 553 | F17: =YearMap!B3 -> 7307.307 | G17: =YearMap!C3 -> 804847.67 | H17: =YearMap!D3 -> 926984.09 | I17: =A17&"|"&B17 -> D_Grow_Both_0|FY2027
A18: =A2 -> D_Grow_Both_0 | B18: FY2028 | C18: =IF(D2=1,0, BaselineCalc!$B$7 + ROUND(K2*F2,0)) -> 257 | D18: =IF(E2=1,0, BaselineCalc!$B$8 + K2 - ROUND(K2*F2,0)) -> 296 | E18: =C18+D18 -> 553 | F18: =YearMap!B4 -> 7489.9897 | G18: =YearMap!C4 -> 824968.86 | H18: =YearMap!D4 -> 950158.69 | I18: =A18&"|"&B18 -> D_Grow_Both_0|FY2028
A19: =A2 -> D_Grow_Both_0 | B19: FY2029 | C19: =IF(D2=1,0, BaselineCalc!$B$7 + ROUND(L2*F2,0)) -> 257 | D19: =IF(E2=1,0, BaselineCalc!$B$8 + L2 - ROUND(L2*F2,0)) -> 296 | E19: =C19+D19 -> 553 | F19: =YearMap!B5 -> 7677.2394 | G19: =YearMap!C5 -> 845593.08 | H19: =YearMap!D5 -> 973912.66 | I19: =A19&"|"&B19 -> D_Grow_Both_0|FY2029
A20: =A2 -> D_Grow_Both_0 | B20: FY2030 | C20: =IF(D2=1,0, BaselineCalc!$B$7 + ROUND(M2*F2,0)) -> 257 | D20: =IF(E2=1,0, BaselineCalc!$B$8 + M2 - ROUND(M2*F2,0)) -> 296 | E20: =C20+D20 -> 553 | F20: =YearMap!B6 -> 7869.1704 | G20: =YearMap!C6 -> 866732.91 | H20: =YearMap!D6 -> 998260.47 | I20: =A20&"|"&B20 -> D_Grow_Both_0|FY2030
A21: =A3 -> E_StatusQuo_Targets_0 | B21: FY2026 | C21: =IF(D3=1,0, BaselineCalc!$B$7 + ROUND(I3*F3,0)) -> 257 | D21: =IF(E3=1,0, BaselineCalc!$B$8 + I3 - ROUND(I3*F3,0)) -> 296 | E21: =C21+D21 -> 553 | F21: =YearMap!B2 -> 7129.08 | G21: =YearMap!C2 -> 785217.24 | H21: =YearMap!D2 -> 904374.72 | I21: =A21&"|"&B21 -> E_StatusQuo_Targets_0|FY2026
A22: =A3 -> E_StatusQuo_Targets_0 | B22: FY2027 | C22: =IF(D3=1,0, BaselineCalc!$B$7 + ROUND(J3*F3,0)) -> 257 | D22: =IF(E3=1,0, BaselineCalc!$B$8 + J3 - ROUND(J3*F3,0)) -> 296 | E22: =C22+D22 -> 553 | F22: =YearMap!B3 -> 7307.307 | G22: =YearMap!C3 -> 804847.67 | H22: =YearMap!D3 -> 926984.09 | I22: =A22&"|"&B22 -> E_StatusQuo_Targets_0|FY2027
A23: =A3 -> E_StatusQuo_Targets_0 | B23: FY2028 | C23: =IF(D3=1,0, BaselineCalc!$B$7 + ROUND(K3*F3,0)) -> 257 | D23: =IF(E3=1,0, BaselineCalc!$B$8 + K3 - ROUND(K3*F3,0)) -> 296 | E23: =C23+D23 -> 553 | F23: =YearMap!B4 -> 7489.9897 | G23: =YearMap!C4 -> 824968.86 | H23: =YearMap!D4 -> 950158.69 | I23: =A23&"|"&B23 -> E_StatusQuo_Targets_0|FY2028
A24: =A3 -> E_StatusQuo_Targets_0 | B24: FY2029 | C24: =IF(D3=1,0, BaselineCalc!$B$7 + ROUND(L3*F3,0)) -> 257 | D24: =IF(E3=1,0, BaselineCalc!$B$8 + L3 - ROUND(L3*F3,0)) -> 296 | E24: =C24+D24 -> 553 | F24: =YearMap!B5 -> 7677.2394 | G24: =YearMap!C5 -> 845593.08 | H24: =YearMap!D5 -> 973912.66 | I24: =A24&"|"&B24 -> E_StatusQuo_Targets_0|FY2029
A25: =A3 -> E_StatusQuo_Targets_0 | B25: FY2030 | C25: =IF(D3=1,0, BaselineCalc!$B$7 + ROUND(M3*F3,0)) -> 257 | D25: =IF(E3=1,0, BaselineCalc!$B$8 + M3 - ROUND(M3*F3,0)) -> 296 | E25: =C25+D25 -> 553 | F25: =YearMap!B6 -> 7869.1704 | G25: =YearMap!C6 -> 866732.91 | H25: =YearMap!D6 -> 998260.47 | I25: =A25&"|"&B25 -> E_StatusQuo_Targets_0|FY2030
A26: =A4 -> F_CoLocation_Echo_0 | B26: FY2026 | C26: =IF(D4=1,0, BaselineCalc!$B$7 + ROUND(I4*F4,0)) -> 257 | D26: =IF(E4=1,0, BaselineCalc!$B$8 + I4 - ROUND(I4*F4,0)) -> 296 | E26: =C26+D26 -> 553 | F26: =YearMap!B2 -> 7129.08 | G26: =YearMap!C2 -> 785217.24 | H26: =YearMap!D2 -> 904374.72 | I26: =A26&"|"&B26 -> F_CoLocation_Echo_0|FY2026
A27: =A4 -> F_CoLocation_Echo_0 | B27: FY2027 | C27: =IF(D4=1,0, BaselineCalc!$B$7 + ROUND(J4*F4,0)) -> 257 | D27: =IF(E4=1,0, BaselineCalc!$B$8 + J4 - ROUND(J4*F4,0)) -> 296 | E27: =C27+D27 -> 553 | F27: =YearMap!B3 -> 7307.307 | G27: =YearMap!C3 -> 804847.67 | H27: =YearMap!D3 -> 926984.09 | I27: =A27&"|"&B27 -> F_CoLocation_Echo_0|FY2027
A28: =A4 -> F_CoLocation_Echo_0 | B28: FY2028 | C28: =IF(D4=1,0, BaselineCalc!$B$7 + ROUND(K4*F4,0)) -> 257 | D28: =IF(E4=1,0, BaselineCalc!$B$8 + K4 - ROUND(K4*F4,0)) -> 296 | E28: =C28+D28 -> 553 | F28: =YearMap!B4 -> 7489.9897 | G28: =YearMap!C4 -> 824968.86 | H28: =YearMap!D4 -> 950158.69 | I28: =A28&"|"&B28 -> F_CoLocation_Echo_0|FY2028
A29: =A4 -> F_CoLocation_Echo_0 | B29: FY2029 | C29: =IF(D4=1,0, BaselineCalc!$B$7 + ROUND(L4*F4,0)) -> 257 | D29: =IF(E4=1,0, BaselineCalc!$B$8 + L4 - ROUND(L4*F4,0)) -> 296 | E29: =C29+D29 -> 553 | F29: =YearMap!B5 -> 7677.2394 | G29: =YearMap!C5 -> 845593.08 | H29: =YearMap!D5 -> 973912.66 | I29: =A29&"|"&B29 -> F_CoLocation_Echo_0|FY2029
A30: =A4 -> F_CoLocation_Echo_0 | B30: FY2030 | C30: =IF(D4=1,0, BaselineCalc!$B$7 + ROUND(M4*F4,0)) -> 257 | D30: =IF(E4=1,0, BaselineCalc!$B$8 + M4 - ROUND(M4*F4,0)) -> 296 | E30: =C30+D30 -> 553 | F30: =YearMap!B6 -> 7869.1704 | G30: =YearMap!C6 -> 866732.91 | H30: =YearMap!D6 -> 998260.47 | I30: =A30&"|"&B30 -> F_CoLocation_Echo_0|FY2030
A31: =A5 -> D_Grow_Both_100 | B31: FY2026 | C31: =IF(D5=1,0, BaselineCalc!$B$7 + ROUND(I5*F5,0)) -> 307 | D31: =IF(E5=1,0, BaselineCalc!$B$8 + I5 - ROUND(I5*F5,0)) -> 346 | E31: =C31+D31 -> 653 | F31: =YearMap!B2 -> 7129.08 | G31: =YearMap!C2 -> 785217.24 | H31: =YearMap!D2 -> 904374.72 | I31: =A31&"|"&B31 -> D_Grow_Both_100|FY2026
A32: =A5 -> D_Grow_Both_100 | B32: FY2027 | C32: =IF(D5=1,0, BaselineCalc!$B$7 + ROUND(J5*F5,0)) -> 307 | D32: =IF(E5=1,0, BaselineCalc!$B$8 + J5 - ROUND(J5*F5,0)) -> 346 | E32: =C32+D32 -> 653 | F32: =YearMap!B3 -> 7307.307 | G32: =YearMap!C3 -> 804847.67 | H32: =YearMap!D3 -> 926984.09 | I32: =A32&"|"&B32 -> D_Grow_Both_100|FY2027
A33: =A5 -> D_Grow_Both_100 | B33: FY2028 | C33: =IF(D5=1,0, BaselineCalc!$B$7 + ROUND(K5*F5,0)) -> 307 | D33: =IF(E5=1,0, BaselineCalc!$B$8 + K5 - ROUND(K5*F5,0)) -> 346 | E33: =C33+D33 -> 653 | F33: =YearMap!B4 -> 7489.9897 | G33: =YearMap!C4 -> 824968.86 | H33: =YearMap!D4 -> 950158.69 | I33: =A33&"|"&B33 -> D_Grow_Both_100|FY2028
A34: =A5 -> D_Grow_Both_100 | B34: FY2029 | C34: =IF(D5=1,0, BaselineCalc!$B$7 + ROUND(L5*F5,0)) -> 307 | D34: =IF(E5=1,0, BaselineCalc!$B$8 + L5 - ROUND(L5*F5,0)) -> 346 | E34: =C34+D34 -> 653 | F34: =YearMap!B5 -> 7677.2394 | G34: =YearMap!C5 -> 845593.08 | H34: =YearMap!D5 -> 973912.66 | I34: =A34&"|"&B34 -> D_Grow_Both_100|FY2029
A35: =A5 -> D_Grow_Both_100 | B35: FY2030 | C35: =IF(D5=1,0, BaselineCalc!$B$7 + ROUND(M5*F5,0)) -> 307 | D35: =IF(E5=1,0, BaselineCalc!$B$8 + M5 - ROUND(M5*F5,0)) -> 346 | E35: =C35+D35 -> 653 | F35: =YearMap!B6 -> 7869.1704 | G35: =YearMap!C6 -> 866732.91 | H35: =YearMap!D6 -> 998260.47 | I35: =A35&"|"&B35 -> D_Grow_Both_100|FY2030
A36: =A6 -> D_Grow_Both_150 | B36: FY2026 | C36: =IF(D6=1,0, BaselineCalc!$B$7 + ROUND(I6*F6,0)) -> 332 | D36: =IF(E6=1,0, BaselineCalc!$B$8 + I6 - ROUND(I6*F6,0)) -> 371 | E36: =C36+D36 -> 703 | F36: =YearMap!B2 -> 7129.08 | G36: =YearMap!C2 -> 785217.24 | H36: =YearMap!D2 -> 904374.72 | I36: =A36&"|"&B36 -> D_Grow_Both_150|FY2026
A37: =A6 -> D_Grow_Both_150 | B37: FY2027 | C37: =IF(D6=1,0, BaselineCalc!$B$7 + ROUND(J6*F6,0)) -> 332 | D37: =IF(E6=1,0, BaselineCalc!$B$8 + J6 - ROUND(J6*F6,0)) -> 371 | E37: =C37+D37 -> 703 | F37: =YearMap!B3 -> 7307.307 | G37: =YearMap!C3 -> 804847.67 | H37: =YearMap!D3 -> 926984.09 | I37: =A37&"|"&B37 -> D_Grow_Both_150|FY2027
A38: =A6 -> D_Grow_Both_150 | B38: FY2028 | C38: =IF(D6=1,0, BaselineCalc!$B$7 + ROUND(K6*F6,0)) -> 332 | D38: =IF(E6=1,0, BaselineCalc!$B$8 + K6 - ROUND(K6*F6,0)) -> 371 | E38: =C38+D38 -> 703 | F38: =YearMap!B4 -> 7489.9897 | G38: =YearMap!C4 -> 824968.86 | H38: =YearMap!D4 -> 950158.69 | I38: =A38&"|"&B38 -> D_Grow_Both_150|FY2028
A39: =A6 -> D_Grow_Both_150 | B39: FY2029 | C39: =IF(D6=1,0, BaselineCalc!$B$7 + ROUND(L6*F6,0)) -> 332 | D39: =IF(E6=1,0, BaselineCalc!$B$8 + L6 - ROUND(L6*F6,0)) -> 371 | E39: =C39+D39 -> 703 | F39: =YearMap!B5 -> 7677.2394 | G39: =YearMap!C5 -> 845593.08 | H39: =YearMap!D5 -> 973912.66 | I39: =A39&"|"&B39 -> D_Grow_Both_150|FY2029
A40: =A6 -> D_Grow_Both_150 | B40: FY2030 | C40: =IF(D6=1,0, BaselineCalc!$B$7 + ROUND(M6*F6,0)) -> 332 | D40: =IF(E6=1,0, BaselineCalc!$B$8 + M6 - ROUND(M6*F6,0)) -> 371 | E40: =C40+D40 -> 703 | F40: =YearMap!B6 -> 7869.1704 | G40: =YearMap!C6 -> 866732.91 | H40: =YearMap!D6 -> 998260.47 | I40: =A40&"|"&B40 -> D_Grow_Both_150|FY2030
A41: =A7 -> G_DHub_EchoRamp | B41: FY2026 | C41: =IF(D7=1,0, BaselineCalc!$B$7 + ROUND(I7*F7,0)) -> 292 | D41: =IF(E7=1,0, BaselineCalc!$B$8 + I7 - ROUND(I7*F7,0)) -> 311 | E41: =C41+D41 -> 603 | F41: =YearMap!B2 -> 7129.08 | G41: =YearMap!C2 -> 785217.24 | H41: =YearMap!D2 -> 904374.72 | I41: =A41&"|"&B41 -> G_DHub_EchoRamp|FY2026
A42: =A7 -> G_DHub_EchoRamp | B42: FY2027 | C42: =IF(D7=1,0, BaselineCalc!$B$7 + ROUND(J7*F7,0)) -> 327 | D42: =IF(E7=1,0, BaselineCalc!$B$8 + J7 - ROUND(J7*F7,0)) -> 326 | E42: =C42+D42 -> 653 | F42: =YearMap!B3 -> 7307.307 | G42: =YearMap!C3 -> 804847.67 | H42: =YearMap!D3 -> 926984.09 | I42: =A42&"|"&B42 -> G_DHub_EchoRamp|FY2027
A43: =A7 -> G_DHub_EchoRamp | B43: FY2028 | C43: =IF(D7=1,0, BaselineCalc!$B$7 + ROUND(K7*F7,0)) -> 362 | D43: =IF(E7=1,0, BaselineCalc!$B$8 + K7 - ROUND(K7*F7,0)) -> 341 | E43: =C43+D43 -> 703 | F43: =YearMap!B4 -> 7489.9897 | G43: =YearMap!C4 -> 824968.86 | H43: =YearMap!D4 -> 950158.69 | I43: =A43&"|"&B43 -> G_DHub_EchoRamp|FY2028
A44: =A7 -> G_DHub_EchoRamp | B44: FY2029 | C44: =IF(D7=1,0, BaselineCalc!$B$7 + ROUND(L7*F7,0)) -> 362 | D44: =IF(E7=1,0, BaselineCalc!$B$8 + L7 - ROUND(L7*F7,0)) -> 341 | E44: =C44+D44 -> 703 | F44: =YearMap!B5 -> 7677.2394 | G44: =YearMap!C5 -> 845593.08 | H44: =YearMap!D5 -> 973912.66 | I44: =A44&"|"&B44 -> G_DHub_EchoRamp|FY2029
A45: =A7 -> G_DHub_EchoRamp | B45: FY2030 | C45: =IF(D7=1,0, BaselineCalc!$B$7 + ROUND(M7*F7,0)) -> 362 | D45: =IF(E7=1,0, BaselineCalc!$B$8 + M7 - ROUND(M7*F7,0)) -> 341 | E45: =C45+D45 -> 703 | F45: =YearMap!B6 -> 7869.1704 | G45: =YearMap!C6 -> 866732.91 | H45: =YearMap!D6 -> 998260.47 | I45: =A45&"|"&B45 -> G_DHub_EchoRamp|FY2030
A46: =A8 -> A_Repurpose_Both_lease | B46: FY2026 | C46: =IF(D8=1,0, BaselineCalc!$B$7 + ROUND(I8*F8,0)) -> 0 | D46: =IF(E8=1,0, BaselineCalc!$B$8 + I8 - ROUND(I8*F8,0)) -> 0 | E46: =C46+D46 -> 0 | F46: =YearMap!B2 -> 7129.08 | G46: =YearMap!C2 -> 785217.24 | H46: =YearMap!D2 -> 904374.72 | I46: =A46&"|"&B46 -> A_Repurpose_Both_lease|FY2026
A47: =A8 -> A_Repurpose_Both_lease | B47: FY2027 | C47: =IF(D8=1,0, BaselineCalc!$B$7 + ROUND(J8*F8,0)) -> 0 | D47: =IF(E8=1,0, BaselineCalc!$B$8 + J8 - ROUND(J8*F8,0)) -> 0 | E47: =C47+D47 -> 0 | F47: =YearMap!B3 -> 7307.307 | G47: =YearMap!C3 -> 804847.67 | H47: =YearMap!D3 -> 926984.09 | I47: =A47&"|"&B47 -> A_Repurpose_Both_lease|FY2027
A48: =A8 -> A_Repurpose_Both_lease | B48: FY2028 | C48: =IF(D8=1,0, BaselineCalc!$B$7 + ROUND(K8*F8,0)) -> 0 | D48: =IF(E8=1,0, BaselineCalc!$B$8 + K8 - ROUND(K8*F8,0)) -> 0 | E48: =C48+D48 -> 0 | F48: =YearMap!B4 -> 7489.9897 | G48: =YearMap!C4 -> 824968.86 | H48: =YearMap!D4 -> 950158.69 | I48: =A48&"|"&B48 -> A_Repurpose_Both_lease|FY2028
A49: =A8 -> A_Repurpose_Both_lease | B49: FY2029 | C49: =IF(D8=1,0, BaselineCalc!$B$7 + ROUND(L8*F8,0)) -> 0 | D49: =IF(E8=1,0, BaselineCalc!$B$8 + L8 - ROUND(L8*F8,0)) -> 0 | E49: =C49+D49 -> 0 | F49: =YearMap!B5 -> 7677.2394 | G49: =YearMap!C5 -> 845593.08 | H49: =YearMap!D5 -> 973912.66 | I49: =A49&"|"&B49 -> A_Repurpose_Both_lease|FY2029
A50: =A8 -> A_Repurpose_Both_lease | B50: FY2030 | C50: =IF(D8=1,0, BaselineCalc!$B$7 + ROUND(M8*F8,0)) -> 0 | D50: =IF(E8=1,0, BaselineCalc!$B$8 + M8 - ROUND(M8*F8,0)) -> 0 | E50: =C50+D50 -> 0 | F50: =YearMap!B6 -> 7869.1704 | G50: =YearMap!C6 -> 866732.91 | H50: =YearMap!D6 -> 998260.47 | I50: =A50&"|"&B50 -> A_Repurpose_Both_lease|FY2030
A51: =A9 -> A_Repurpose_Both_ops | B51: FY2026 | C51: =IF(D9=1,0, BaselineCalc!$B$7 + ROUND(I9*F9,0)) -> 0 | D51: =IF(E9=1,0, BaselineCalc!$B$8 + I9 - ROUND(I9*F9,0)) -> 0 | E51: =C51+D51 -> 0 | F51: =YearMap!B2 -> 7129.08 | G51: =YearMap!C2 -> 785217.24 | H51: =YearMap!D2 -> 904374.72 | I51: =A51&"|"&B51 -> A_Repurpose_Both_ops|FY2026
A52: =A9 -> A_Repurpose_Both_ops | B52: FY2027 | C52: =IF(D9=1,0, BaselineCalc!$B$7 + ROUND(J9*F9,0)) -> 0 | D52: =IF(E9=1,0, BaselineCalc!$B$8 + J9 - ROUND(J9*F9,0)) -> 0 | E52: =C52+D52 -> 0 | F52: =YearMap!B3 -> 7307.307 | G52: =YearMap!C3 -> 804847.67 | H52: =YearMap!D3 -> 926984.09 | I52: =A52&"|"&B52 -> A_Repurpose_Both_ops|FY2027
A53: =A9 -> A_Repurpose_Both_ops | B53: FY2028 | C53: =IF(D9=1,0, BaselineCalc!$B$7 + ROUND(K9*F9,0)) -> 0 | D53: =IF(E9=1,0, BaselineCalc!$B$8 + K9 - ROUND(K9*F9,0)) -> 0 | E53: =C53+D53 -> 0 | F53: =YearMap!B4 -> 7489.9897 | G53: =YearMap!C4 -> 824968.86 | H53: =YearMap!D4 -> 950158.69 | I53: =A53&"|"&B53 -> A_Repurpose_Both_ops|FY2028
A54: =A9 -> A_Repurpose_Both_ops | B54: FY2029 | C54: =IF(D9=1,0, BaselineCalc!$B$7 + ROUND(L9*F9,0)) -> 0 | D54: =IF(E9=1,0, BaselineCalc!$B$8 + L9 - ROUND(L9*F9,0)) -> 0 | E54: =C54+D54 -> 0 | F54: =YearMap!B5 -> 7677.2394 | G54: =YearMap!C5 -> 845593.08 | H54: =YearMap!D5 -> 973912.66 | I54: =A54&"|"&B54 -> A_Repurpose_Both_ops|FY2029
A55: =A9 -> A_Repurpose_Both_ops | B55: FY2030 | C55: =IF(D9=1,0, BaselineCalc!$B$7 + ROUND(M9*F9,0)) -> 0 | D55: =IF(E9=1,0, BaselineCalc!$B$8 + M9 - ROUND(M9*F9,0)) -> 0 | E55: =C55+D55 -> 0 | F55: =YearMap!B6 -> 7869.1704 | G55: =YearMap!C6 -> 866732.91 | H55: =YearMap!D6 -> 998260.47 | I55: =A55&"|"&B55 -> A_Repurpose_Both_ops|FY2030
A56: =A10 -> B_Repurpose_Echo_lease | B56: FY2026 | C56: =IF(D10=1,0, BaselineCalc!$B$7 + ROUND(I10*F10,0)) -> 0 | D56: =IF(E10=1,0, BaselineCalc!$B$8 + I10 - ROUND(I10*F10,0)) -> 296 | E56: =C56+D56 -> 296 | F56: =YearMap!B2 -> 7129.08 | G56: =YearMap!C2 -> 785217.24 | H56: =YearMap!D2 -> 904374.72 | I56: =A56&"|"&B56 -> B_Repurpose_Echo_lease|FY2026
A57: =A10 -> B_Repurpose_Echo_lease | B57: FY2027 | C57: =IF(D10=1,0, BaselineCalc!$B$7 + ROUND(J10*F10,0)) -> 0 | D57: =IF(E10=1,0, BaselineCalc!$B$8 + J10 - ROUND(J10*F10,0)) -> 296 | E57: =C57+D57 -> 296 | F57: =YearMap!B3 -> 7307.307 | G57: =YearMap!C3 -> 804847.67 | H57: =YearMap!D3 -> 926984.09 | I57: =A57&"|"&B57 -> B_Repurpose_Echo_lease|FY2027
A58: =A10 -> B_Repurpose_Echo_lease | B58: FY2028 | C58: =IF(D10=1,0, BaselineCalc!$B$7 + ROUND(K10*F10,0)) -> 0 | D58: =IF(E10=1,0, BaselineCalc!$B$8 + K10 - ROUND(K10*F10,0)) -> 296 | E58: =C58+D58 -> 296 | F58: =YearMap!B4 -> 7489.9897 | G58: =YearMap!C4 -> 824968.86 | H58: =YearMap!D4 -> 950158.69 | I58: =A58&"|"&B58 -> B_Repurpose_Echo_lease|FY2028
A59: =A10 -> B_Repurpose_Echo_lease | B59: FY2029 | C59: =IF(D10=1,0, BaselineCalc!$B$7 + ROUND(L10*F10,0)) -> 0 | D59: =IF(E10=1,0, BaselineCalc!$B$8 + L10 - ROUND(L10*F10,0)) -> 296 | E59: =C59+D59 -> 296 | F59: =YearMap!B5 -> 7677.2394 | G59: =YearMap!C5 -> 845593.08 | H59: =YearMap!D5 -> 973912.66 | I59: =A59&"|"&B59 -> B_Repurpose_Echo_lease|FY2029
A60: =A10 -> B_Repurpose_Echo_lease | B60: FY2030 | C60: =IF(D10=1,0, BaselineCalc!$B$7 + ROUND(M10*F10,0)) -> 0 | D60: =IF(E10=1,0, BaselineCalc!$B$8 + M10 - ROUND(M10*F10,0)) -> 296 | E60: =C60+D60 -> 296 | F60: =YearMap!B6 -> 7869.1704 | G60: =YearMap!C6 -> 866732.91 | H60: =YearMap!D6 -> 998260.47 | I60: =A60&"|"&B60 -> B_Repurpose_Echo_lease|FY2030
A61: =A11 -> B_Repurpose_Echo_ops | B61: FY2026 | C61: =IF(D11=1,0, BaselineCalc!$B$7 + ROUND(I11*F11,0)) -> 0 | D61: =IF(E11=1,0, BaselineCalc!$B$8 + I11 - ROUND(I11*F11,0)) -> 296 | E61: =C61+D61 -> 296 | F61: =YearMap!B2 -> 7129.08 | G61: =YearMap!C2 -> 785217.24 | H61: =YearMap!D2 -> 904374.72 | I61: =A61&"|"&B61 -> B_Repurpose_Echo_ops|FY2026
A62: =A11 -> B_Repurpose_Echo_ops | B62: FY2027 | C62: =IF(D11=1,0, BaselineCalc!$B$7 + ROUND(J11*F11,0)) -> 0 | D62: =IF(E11=1,0, BaselineCalc!$B$8 + J11 - ROUND(J11*F11,0)) -> 296 | E62: =C62+D62 -> 296 | F62: =YearMap!B3 -> 7307.307 | G62: =YearMap!C3 -> 804847.67 | H62: =YearMap!D3 -> 926984.09 | I62: =A62&"|"&B62 -> B_Repurpose_Echo_ops|FY2027
A63: =A11 -> B_Repurpose_Echo_ops | B63: FY2028 | C63: =IF(D11=1,0, BaselineCalc!$B$7 + ROUND(K11*F11,0)) -> 0 | D63: =IF(E11=1,0, BaselineCalc!$B$8 + K11 - ROUND(K11*F11,0)) -> 296 | E63: =C63+D63 -> 296 | F63: =YearMap!B4 -> 7489.9897 | G63: =YearMap!C4 -> 824968.86 | H63: =YearMap!D4 -> 950158.69 | I63: =A63&"|"&B63 -> B_Repurpose_Echo_ops|FY2028
A64: =A11 -> B_Repurpose_Echo_ops | B64: FY2029 | C64: =IF(D11=1,0, BaselineCalc!$B$7 + ROUND(L11*F11,0)) -> 0 | D64: =IF(E11=1,0, BaselineCalc!$B$8 + L11 - ROUND(L11*F11,0)) -> 296 | E64: =C64+D64 -> 296 | F64: =YearMap!B5 -> 7677.2394 | G64: =YearMap!C5 -> 845593.08 | H64: =YearMap!D5 -> 973912.66 | I64: =A64&"|"&B64 -> B_Repurpose_Echo_ops|FY2029
A65: =A11 -> B_Repurpose_Echo_ops | B65: FY2030 | C65: =IF(D11=1,0, BaselineCalc!$B$7 + ROUND(M11*F11,0)) -> 0 | D65: =IF(E11=1,0, BaselineCalc!$B$8 + M11 - ROUND(M11*F11,0)) -> 296 | E65: =C65+D65 -> 296 | F65: =YearMap!B6 -> 7869.1704 | G65: =YearMap!C6 -> 866732.91 | H65: =YearMap!D6 -> 998260.47 | I65: =A65&"|"&B65 -> B_Repurpose_Echo_ops|FY2030
A66: =A12 -> C_Repurpose_Pima_lease | B66: FY2026 | C66: =IF(D12=1,0, BaselineCalc!$B$7 + ROUND(I12*F12,0)) -> 257 | D66: =IF(E12=1,0, BaselineCalc!$B$8 + I12 - ROUND(I12*F12,0)) -> 0 | E66: =C66+D66 -> 257 | F66: =YearMap!B2 -> 7129.08 | G66: =YearMap!C2 -> 785217.24 | H66: =YearMap!D2 -> 904374.72 | I66: =A66&"|"&B66 -> C_Repurpose_Pima_lease|FY2026
A67: =A12 -> C_Repurpose_Pima_lease | B67: FY2027 | C67: =IF(D12=1,0, BaselineCalc!$B$7 + ROUND(J12*F12,0)) -> 257 | D67: =IF(E12=1,0, BaselineCalc!$B$8 + J12 - ROUND(J12*F12,0)) -> 0 | E67: =C67+D67 -> 257 | F67: =YearMap!B3 -> 7307.307 | G67: =YearMap!C3 -> 804847.67 | H67: =YearMap!D3 -> 926984.09 | I67: =A67&"|"&B67 -> C_Repurpose_Pima_lease|FY2027
A68: =A12 -> C_Repurpose_Pima_lease | B68: FY2028 | C68: =IF(D12=1,0, BaselineCalc!$B$7 + ROUND(K12*F12,0)) -> 257 | D68: =IF(E12=1,0, BaselineCalc!$B$8 + K12 - ROUND(K12*F12,0)) -> 0 | E68: =C68+D68 -> 257 | F68: =YearMap!B4 -> 7489.9897 | G68: =YearMap!C4 -> 824968.86 | H68: =YearMap!D4 -> 950158.69 | I68: =A68&"|"&B68 -> C_Repurpose_Pima_lease|FY2028
A69: =A12 -> C_Repurpose_Pima_lease | B69: FY2029 | C69: =IF(D12=1,0, BaselineCalc!$B$7 + ROUND(L12*F12,0)) -> 257 | D69: =IF(E12=1,0, BaselineCalc!$B$8 + L12 - ROUND(L12*F12,0)) -> 0 | E69: =C69+D69 -> 257 | F69: =YearMap!B5 -> 7677.2394 | G69: =YearMap!C5 -> 845593.08 | H69: =YearMap!D5 -> 973912.66 | I69: =A69&"|"&B69 -> C_Repurpose_Pima_lease|FY2029
A70: =A12 -> C_Repurpose_Pima_lease | B70: FY2030 | C70: =IF(D12=1,0, BaselineCalc!$B$7 + ROUND(M12*F12,0)) -> 257 | D70: =IF(E12=1,0, BaselineCalc!$B$8 + M12 - ROUND(M12*F12,0)) -> 0 | E70: =C70+D70 -> 257 | F70: =YearMap!B6 -> 7869.1704 | G70: =YearMap!C6 -> 866732.91 | H70: =YearMap!D6 -> 998260.47 | I70: =A70&"|"&B70 -> C_Repurpose_Pima_lease|FY2030
A71: =A13 -> C_Repurpose_Pima_ops | B71: FY2026 | C71: =IF(D13=1,0, BaselineCalc!$B$7 + ROUND(I13*F13,0)) -> 257 | D71: =IF(E13=1,0, BaselineCalc!$B$8 + I13 - ROUND(I13*F13,0)) -> 0 | E71: =C71+D71 -> 257 | F71: =YearMap!B2 -> 7129.08 | G71: =YearMap!C2 -> 785217.24 | H71: =YearMap!D2 -> 904374.72 | I71: =A71&"|"&B71 -> C_Repurpose_Pima_ops|FY2026
A72: =A13 -> C_Repurpose_Pima_ops | B72: FY2027 | C72: =IF(D13=1,0, BaselineCalc!$B$7 + ROUND(J13*F13,0)) -> 257 | D72: =IF(E13=1,0, BaselineCalc!$B$8 + J13 - ROUND(J13*F13,0)) -> 0 | E72: =C72+D72 -> 257 | F72: =YearMap!B3 -> 7307.307 | G72: =YearMap!C3 -> 804847.67 | H72: =YearMap!D3 -> 926984.09 | I72: =A72&"|"&B72 -> C_Repurpose_Pima_ops|FY2027
A73: =A13 -> C_Repurpose_Pima_ops | B73: FY2028 | C73: =IF(D13=1,0, BaselineCalc!$B$7 + ROUND(K13*F13,0)) -> 257 | D73: =IF(E13=1,0, BaselineCalc!$B$8 + K13 - ROUND(K13*F13,0)) -> 0 | E73: =C73+D73 -> 257 | F73: =YearMap!B4 -> 7489.9897 | G73: =YearMap!C4 -> 824968.86 | H73: =YearMap!D4 -> 950158.69 | I73: =A73&"|"&B73 -> C_Repurpose_Pima_ops|FY2028
A74: =A13 -> C_Repurpose_Pima_ops | B74: FY2029 | C74: =IF(D13=1,0, BaselineCalc!$B$7 + ROUND(L13*F13,0)) -> 257 | D74: =IF(E13=1,0, BaselineCalc!$B$8 + L13 - ROUND(L13*F13,0)) -> 0 | E74: =C74+D74 -> 257 | F74: =YearMap!B5 -> 7677.2394 | G74: =YearMap!C5 -> 845593.08 | H74: =YearMap!D5 -> 973912.66 | I74: =A74&"|"&B74 -> C_Repurpose_Pima_ops|FY2029
A75: =A13 -> C_Repurpose_Pima_ops | B75: FY2030 | C75: =IF(D13=1,0, BaselineCalc!$B$7 + ROUND(M13*F13,0)) -> 257 | D75: =IF(E13=1,0, BaselineCalc!$B$8 + M13 - ROUND(M13*F13,0)) -> 0 | E75: =C75+D75 -> 257 | F75: =YearMap!B6 -> 7869.1704 | G75: =YearMap!C6 -> 866732.91 | H75: =YearMap!D6 -> 998260.47 | I75: =A75&"|"&B75 -> C_Repurpose_Pima_ops|FY2030

Sheet Summary_Costs
A1: ScenarioKey | B1: FY2028 Comparable $/Student | C1: FY2030 Comparable $/Student | D1: 3‑yr Avg Comparable $/Student (FY26–FY28) | E1: 5‑yr Avg Comparable $/Student (FY26–FY30) | F1: # students displaced | G1: FY2030 # students served (open & retained) | H1: FY2028 Net ($) | J1: FY2030 Net ($) | M1: 5-yr Net Avg ($)
A2: =Scenarios!A2 -> D_Grow_Both_0 | B2: =INDEX(MultiYear_ProForma!$X$2:$X$61, MATCH(Scenarios!A2&"|FY2028", MultiYear_ProForma!$Y$2:$Y$61, 0)) -> 10625.085 | C2: =INDEX(MultiYear_ProForma!$X$2:$X$61, MATCH(Scenarios!A2&"|FY2030", MultiYear_ProForma!$Y$2:$Y$61, 0)) -> 11162.98 | D2: =AVERAGE(INDEX(MultiYear_ProForma!$X$2:$X$61, MATCH(Scenarios!A2&"|FY2026", MultiYear_ProForma!$Y$2:$Y$61, 0)),INDEX(MultiYear_ProForma!$X$2:$X$61, MATCH(Scenarios!A2&"|FY2027", MultiYear_ProForma!$Y$2:$Y$61, 0)),INDEX(MultiYear_ProForma!$X$2:$X$61, MATCH(Scenarios!A2&"|FY2028", MultiYear_ProForma!$Y$2:$Y$61, 0))) -> 10368.044 | E2: =AVERAGE(INDEX(MultiYear_ProForma!$X$2:$X$61, MATCH(Scenarios!A2&"|FY2026", MultiYear_ProForma!$Y$2:$Y$61, 0)),INDEX(MultiYear_ProForma!$X$2:$X$61, MATCH(Scenarios!A2&"|FY2027", MultiYear_ProForma!$Y$2:$Y$61, 0)),INDEX(MultiYear_ProForma!$X$2:$X$61, MATCH(Scenarios!A2&"|FY2028", MultiYear_ProForma!$Y$2:$Y$61, 0)),INDEX(MultiYear_ProForma!$X$2:$X$61, MATCH(Scenarios!A2&"|FY2029", MultiYear_ProForma!$Y$2:$Y$61, 0)),INDEX(MultiYear_ProForma!$X$2:$X$61, MATCH(Scenarios!A2&"|FY2030", MultiYear_ProForma!$Y$2:$Y$61, 0))) -> 10631.565 | F2: =IFERROR(VLOOKUP($A2&"|FY2026", MultiYear_ProForma!$A:$Y, 14, FALSE), "") -> 0 | G2: =IFERROR(VLOOKUP($A2&"|FY2030", MultiYear_ProForma!$A:$Y, 6, FALSE) + VLOOKUP($A2&"|FY2030", MultiYear_ProForma!$A:$Y, 15, FALSE), "") -> 553 | H2: =SUMIFS(MultiYear_ProForma!$AA:$AA, MultiYear_ProForma!$B:$B, $A2, MultiYear_ProForma!$C:$C, "FY2028") -> 2933952.6 | J2: =SUMIFS(MultiYear_ProForma!$AA:$AA, MultiYear_ProForma!$B:$B, $A2, MultiYear_ProForma!$C:$C, "FY2030") -> 3112563.1 | K2: =INDEX(MultiYear_ProForma!$AA:$AA,MATCH($A2&"|"&"FY2028",MultiYear_ProForma!$B:$B&"|"&MultiYear_ProForma!$C:$C,0)) -> #VALUE! | L2: =INDEX(MultiYear_ProForma!$AA:$AA,MATCH($A2&"|"&"FY2030",MultiYear_ProForma!$B:$B&"|"&MultiYear_ProForma!$C:$C,0)) -> #VALUE! | M2: =(SUMIFS(MultiYear_ProForma!$AA:$AA, MultiYear_ProForma!$B:$B, $A2, MultiYear_ProForma!$C:$C, "FY2026")+SUMIFS(MultiYear_ProForma!$AA:$AA, MultiYear_ProForma!$B:$B, $A2, MultiYear_ProForma!$C:$C, "FY2027")+SUMIFS(MultiYear_ProForma!$AA:$AA, MultiYear_ProForma!$B:$B, $A2, MultiYear_ProForma!$C:$C, "FY2028")+SUMIFS(MultiYear_ProForma!$AA:$AA, MultiYear_ProForma!$B:$B, $A2, MultiYear_ProForma!$C:$C, "FY2029")+SUMIFS(MultiYear_ProForma!$AA:$AA, MultiYear_ProForma!$B:$B, $A2, MultiYear_ProForma!$C:$C, "FY2030"))/5 -> 2936382.1
A3: =Scenarios!A3 -> E_StatusQuo_Targets_0 | B3: =INDEX(MultiYear_ProForma!$X$2:$X$61, MATCH(Scenarios!A3&"|FY2028", MultiYear_ProForma!$Y$2:$Y$61, 0)) -> 10625.085 | C3: =INDEX(MultiYear_ProForma!$X$2:$X$61, MATCH(Scenarios!A3&"|FY2030", MultiYear_ProForma!$Y$2:$Y$61, 0)) -> 11162.98 | D3: =AVERAGE(INDEX(MultiYear_ProForma!$X$2:$X$61, MATCH(Scenarios!A3&"|FY2026", MultiYear_ProForma!$Y$2:$Y$61, 0)),INDEX(MultiYear_ProForma!$X$2:$X$61, MATCH(Scenarios!A3&"|FY2027", MultiYear_ProForma!$Y$2:$Y$61, 0)),INDEX(MultiYear_ProForma!$X$2:$X$61, MATCH(Scenarios!A3&"|FY2028", MultiYear_ProForma!$Y$2:$Y$61, 0))) -> 10368.044 | E3: =AVERAGE(INDEX(MultiYear_ProForma!$X$2:$X$61, MATCH(Scenarios!A3&"|FY2026", MultiYear_ProForma!$Y$2:$Y$61, 0)),INDEX(MultiYear_ProForma!$X$2:$X$61, MATCH(Scenarios!A3&"|FY2027", MultiYear_ProForma!$Y$2:$Y$61, 0)),INDEX(MultiYear_ProForma!$X$2:$X$61, MATCH(Scenarios!A3&"|FY2028", MultiYear_ProForma!$Y$2:$Y$61, 0)),INDEX(MultiYear_ProForma!$X$2:$X$61, MATCH(Scenarios!A3&"|FY2029", MultiYear_ProForma!$Y$2:$Y$61, 0)),INDEX(MultiYear_ProForma!$X$2:$X$61, MATCH(Scenarios!A3&"|FY2030", MultiYear_ProForma!$Y$2:$Y$61, 0))) -> 10631.565 | F3: =IFERROR(VLOOKUP($A3&"|FY2026", MultiYear_ProForma!$A:$Y, 14, FALSE), "") -> 0 | G3: =IFERROR(VLOOKUP($A3&"|FY2030", MultiYear_ProForma!$A:$Y, 6, FALSE) + VLOOKUP($A3&"|FY2030", MultiYear_ProForma!$A:$Y, 15, FALSE), "") -> 553 | H3: =SUMIFS(MultiYear_ProForma!$AA:$AA, MultiYear_ProForma!$B:$B, $A3, MultiYear_ProForma!$C:$C, "FY2028") -> 2933952.6 | J3: =SUMIFS(MultiYear_ProForma!$AA:$AA, MultiYear_ProForma!$B:$B, $A3, MultiYear_ProForma!$C:$C, "FY2030") -> 3112563.1 | K3: =INDEX(MultiYear_ProForma!$AA:$AA,MATCH($A3&"|"&"FY2028",MultiYear_ProForma!$B:$B&"|"&MultiYear_ProForma!$C:$C,0)) -> #VALUE! | L3: =INDEX(MultiYear_ProForma!$AA:$AA,MATCH($A3&"|"&"FY2030",MultiYear_ProForma!$B:$B&"|"&MultiYear_ProForma!$C:$C,0)) -> #VALUE! | M3: =(SUMIFS(MultiYear_ProForma!$AA:$AA, MultiYear_ProForma!$B:$B, $A3, MultiYear_ProForma!$C:$C, "FY2026")+SUMIFS(MultiYear_ProForma!$AA:$AA, MultiYear_ProForma!$B:$B, $A3, MultiYear_ProForma!$C:$C, "FY2027")+SUMIFS(MultiYear_ProForma!$AA:$AA, MultiYear_ProForma!$B:$B, $A3, MultiYear_ProForma!$C:$C, "FY2028")+SUMIFS(MultiYear_ProForma!$AA:$AA, MultiYear_ProForma!$B:$B, $A3, MultiYear_ProForma!$C:$C, "FY2029")+SUMIFS(MultiYear_ProForma!$AA:$AA, MultiYear_ProForma!$B:$B, $A3, MultiYear_ProForma!$C:$C, "FY2030"))/5 -> 2936382.1
A4: =Scenarios!A4 -> F_CoLocation_Echo_0 | B4: =INDEX(MultiYear_ProForma!$X$2:$X$61, MATCH(Scenarios!A4&"|FY2028", MultiYear_ProForma!$Y$2:$Y$61, 0)) -> 10465.709 | C4: =INDEX(MultiYear_ProForma!$X$2:$X$61, MATCH(Scenarios!A4&"|FY2030", MultiYear_ProForma!$Y$2:$Y$61, 0)) -> 10995.536 | D4: =AVERAGE(INDEX(MultiYear_ProForma!$X$2:$X$61, MATCH(Scenarios!A4&"|FY2026", MultiYear_ProForma!$Y$2:$Y$61, 0)),INDEX(MultiYear_ProForma!$X$2:$X$61, MATCH(Scenarios!A4&"|FY2027", MultiYear_ProForma!$Y$2:$Y$61, 0)),INDEX(MultiYear_ProForma!$X$2:$X$61, MATCH(Scenarios!A4&"|FY2028", MultiYear_ProForma!$Y$2:$Y$61, 0))) -> 10212.523 | E4: =AVERAGE(INDEX(MultiYear_ProForma!$X$2:$X$61, MATCH(Scenarios!A4&"|FY2026", MultiYear_ProForma!$Y$2:$Y$61, 0)),INDEX(MultiYear_ProForma!$X$2:$X$61, MATCH(Scenarios!A4&"|FY2027", MultiYear_ProForma!$Y$2:$Y$61, 0)),INDEX(MultiYear_ProForma!$X$2:$X$61, MATCH(Scenarios!A4&"|FY2028", MultiYear_ProForma!$Y$2:$Y$61, 0)),INDEX(MultiYear_ProForma!$X$2:$X$61, MATCH(Scenarios!A4&"|FY2029", MultiYear_ProForma!$Y$2:$Y$61, 0)),INDEX(MultiYear_ProForma!$X$2:$X$61, MATCH(Scenarios!A4&"|FY2030", MultiYear_ProForma!$Y$2:$Y$61, 0))) -> 10472.091 | F4: =IFERROR(VLOOKUP($A4&"|FY2026", MultiYear_ProForma!$A:$Y, 14, FALSE), "") -> 0 | G4: =IFERROR(VLOOKUP($A4&"|FY2030", MultiYear_ProForma!$A:$Y, 6, FALSE) + VLOOKUP($A4&"|FY2030", MultiYear_ProForma!$A:$Y, 15, FALSE), "") -> 553 | H4: =SUMIFS(MultiYear_ProForma!$AA:$AA, MultiYear_ProForma!$B:$B, $A4, MultiYear_ProForma!$C:$C, "FY2028") -> 2845817.6 | J4: =SUMIFS(MultiYear_ProForma!$AA:$AA, MultiYear_ProForma!$B:$B, $A4, MultiYear_ProForma!$C:$C, "FY2030") -> 3019966.2 | K4: =INDEX(MultiYear_ProForma!$AA:$AA,MATCH($A4&"|"&"FY2028",MultiYear_ProForma!$B:$B&"|"&MultiYear_ProForma!$C:$C,0)) -> #VALUE! | L4: =INDEX(MultiYear_ProForma!$AA:$AA,MATCH($A4&"|"&"FY2030",MultiYear_ProForma!$B:$B&"|"&MultiYear_ProForma!$C:$C,0)) -> #VALUE! | M4: =(SUMIFS(MultiYear_ProForma!$AA:$AA, MultiYear_ProForma!$B:$B, $A4, MultiYear_ProForma!$C:$C, "FY2026")+SUMIFS(MultiYear_ProForma!$AA:$AA, MultiYear_ProForma!$B:$B, $A4, MultiYear_ProForma!$C:$C, "FY2027")+SUMIFS(MultiYear_ProForma!$AA:$AA, MultiYear_ProForma!$B:$B, $A4, MultiYear_ProForma!$C:$C, "FY2028")+SUMIFS(MultiYear_ProForma!$AA:$AA, MultiYear_ProForma!$B:$B, $A4, MultiYear_ProForma!$C:$C, "FY2029")+SUMIFS(MultiYear_ProForma!$AA:$AA, MultiYear_ProForma!$B:$B, $A4, MultiYear_ProForma!$C:$C, "FY2030"))/5 -> 2848193.3
A5: =Scenarios!A5 -> D_Grow_Both_100 | B5: =INDEX(MultiYear_ProForma!$X$2:$X$61, MATCH(Scenarios!A5&"|FY2028", MultiYear_ProForma!$Y$2:$Y$61, 0)) -> 10136.95 | C5: =INDEX(MultiYear_ProForma!$X$2:$X$61, MATCH(Scenarios!A5&"|FY2030", MultiYear_ProForma!$Y$2:$Y$61, 0)) -> 10650.133 | D5: =AVERAGE(INDEX(MultiYear_ProForma!$X$2:$X$61, MATCH(Scenarios!A5&"|FY2026", MultiYear_ProForma!$Y$2:$Y$61, 0)),INDEX(MultiYear_ProForma!$X$2:$X$61, MATCH(Scenarios!A5&"|FY2027", MultiYear_ProForma!$Y$2:$Y$61, 0)),INDEX(MultiYear_ProForma!$X$2:$X$61, MATCH(Scenarios!A5&"|FY2028", MultiYear_ProForma!$Y$2:$Y$61, 0))) -> 9891.7172 | E5: =AVERAGE(INDEX(MultiYear_ProForma!$X$2:$X$61, MATCH(Scenarios!A5&"|FY2026", MultiYear_ProForma!$Y$2:$Y$61, 0)),INDEX(MultiYear_ProForma!$X$2:$X$61, MATCH(Scenarios!A5&"|FY2027", MultiYear_ProForma!$Y$2:$Y$61, 0)),INDEX(MultiYear_ProForma!$X$2:$X$61, MATCH(Scenarios!A5&"|FY2028", MultiYear_ProForma!$Y$2:$Y$61, 0)),INDEX(MultiYear_ProForma!$X$2:$X$61, MATCH(Scenarios!A5&"|FY2029", MultiYear_ProForma!$Y$2:$Y$61, 0)),INDEX(MultiYear_ProForma!$X$2:$X$61, MATCH(Scenarios!A5&"|FY2030", MultiYear_ProForma!$Y$2:$Y$61, 0))) -> 10143.132 | F5: =IFERROR(VLOOKUP($A5&"|FY2026", MultiYear_ProForma!$A:$Y, 14, FALSE), "") -> 0 | G5: =IFERROR(VLOOKUP($A5&"|FY2030", MultiYear_ProForma!$A:$Y, 6, FALSE) + VLOOKUP($A5&"|FY2030", MultiYear_ProForma!$A:$Y, 15, FALSE), "") -> 653 | H5: =SUMIFS(MultiYear_ProForma!$AA:$AA, MultiYear_ProForma!$B:$B, $A5, MultiYear_ProForma!$C:$C, "FY2028") -> 3145752.1 | J5: =SUMIFS(MultiYear_ProForma!$AA:$AA, MultiYear_ProForma!$B:$B, $A5, MultiYear_ProForma!$C:$C, "FY2030") -> 3340524.1 | K5: =INDEX(MultiYear_ProForma!$AA:$AA,MATCH($A5&"|"&"FY2028",MultiYear_ProForma!$B:$B&"|"&MultiYear_ProForma!$C:$C,0)) -> #VALUE! | L5: =INDEX(MultiYear_ProForma!$AA:$AA,MATCH($A5&"|"&"FY2030",MultiYear_ProForma!$B:$B&"|"&MultiYear_ProForma!$C:$C,0)) -> #VALUE! | M5: =(SUMIFS(MultiYear_ProForma!$AA:$AA, MultiYear_ProForma!$B:$B, $A5, MultiYear_ProForma!$C:$C, "FY2026")+SUMIFS(MultiYear_ProForma!$AA:$AA, MultiYear_ProForma!$B:$B, $A5, MultiYear_ProForma!$C:$C, "FY2027")+SUMIFS(MultiYear_ProForma!$AA:$AA, MultiYear_ProForma!$B:$B, $A5, MultiYear_ProForma!$C:$C, "FY2028")+SUMIFS(MultiYear_ProForma!$AA:$AA, MultiYear_ProForma!$B:$B, $A5, MultiYear_ProForma!$C:$C, "FY2029")+SUMIFS(MultiYear_ProForma!$AA:$AA, MultiYear_ProForma!$B:$B, $A5, MultiYear_ProForma!$C:$C, "FY2030"))/5 -> 3148426.5
A6: =Scenarios!A6 -> D_Grow_Both_150 | B6: =INDEX(MultiYear_ProForma!$X$2:$X$61, MATCH(Scenarios!A6&"|FY2028", MultiYear_ProForma!$Y$2:$Y$61, 0)) -> 9944.959 | C6: =INDEX(MultiYear_ProForma!$X$2:$X$61, MATCH(Scenarios!A6&"|FY2030", MultiYear_ProForma!$Y$2:$Y$61, 0)) -> 10448.423 | D6: =AVERAGE(INDEX(MultiYear_ProForma!$X$2:$X$61, MATCH(Scenarios!A6&"|FY2026", MultiYear_ProForma!$Y$2:$Y$61, 0)),INDEX(MultiYear_ProForma!$X$2:$X$61, MATCH(Scenarios!A6&"|FY2027", MultiYear_ProForma!$Y$2:$Y$61, 0)),INDEX(MultiYear_ProForma!$X$2:$X$61, MATCH(Scenarios!A6&"|FY2028", MultiYear_ProForma!$Y$2:$Y$61, 0))) -> 9704.371 | E6: =AVERAGE(INDEX(MultiYear_ProForma!$X$2:$X$61, MATCH(Scenarios!A6&"|FY2026", MultiYear_ProForma!$Y$2:$Y$61, 0)),INDEX(MultiYear_ProForma!$X$2:$X$61, MATCH(Scenarios!A6&"|FY2027", MultiYear_ProForma!$Y$2:$Y$61, 0)),INDEX(MultiYear_ProForma!$X$2:$X$61, MATCH(Scenarios!A6&"|FY2028", MultiYear_ProForma!$Y$2:$Y$61, 0)),INDEX(MultiYear_ProForma!$X$2:$X$61, MATCH(Scenarios!A6&"|FY2029", MultiYear_ProForma!$Y$2:$Y$61, 0)),INDEX(MultiYear_ProForma!$X$2:$X$61, MATCH(Scenarios!A6&"|FY2030", MultiYear_ProForma!$Y$2:$Y$61, 0))) -> 9951.0237 | F6: =IFERROR(VLOOKUP($A6&"|FY2026", MultiYear_ProForma!$A:$Y, 14, FALSE), "") -> 0 | G6: =IFERROR(VLOOKUP($A6&"|FY2030", MultiYear_ProForma!$A:$Y, 6, FALSE) + VLOOKUP($A6&"|FY2030", MultiYear_ProForma!$A:$Y, 15, FALSE), "") -> 703 | H6: =SUMIFS(MultiYear_ProForma!$AA:$AA, MultiYear_ProForma!$B:$B, $A6, MultiYear_ProForma!$C:$C, "FY2028") -> 3251651.8 | J6: =SUMIFS(MultiYear_ProForma!$AA:$AA, MultiYear_ProForma!$B:$B, $A6, MultiYear_ProForma!$C:$C, "FY2030") -> 3454504.7 | K6: =INDEX(MultiYear_ProForma!$AA:$AA,MATCH($A6&"|"&"FY2028",MultiYear_ProForma!$B:$B&"|"&MultiYear_ProForma!$C:$C,0)) -> #VALUE! | L6: =INDEX(MultiYear_ProForma!$AA:$AA,MATCH($A6&"|"&"FY2030",MultiYear_ProForma!$B:$B&"|"&MultiYear_ProForma!$C:$C,0)) -> #VALUE! | M6: =(SUMIFS(MultiYear_ProForma!$AA:$AA, MultiYear_ProForma!$B:$B, $A6, MultiYear_ProForma!$C:$C, "FY2026")+SUMIFS(MultiYear_ProForma!$AA:$AA, MultiYear_ProForma!$B:$B, $A6, MultiYear_ProForma!$C:$C, "FY2027")+SUMIFS(MultiYear_ProForma!$AA:$AA, MultiYear_ProForma!$B:$B, $A6, MultiYear_ProForma!$C:$C, "FY2028")+SUMIFS(MultiYear_ProForma!$AA:$AA, MultiYear_ProForma!$B:$B, $A6, MultiYear_ProForma!$C:$C, "FY2029")+SUMIFS(MultiYear_ProForma!$AA:$AA, MultiYear_ProForma!$B:$B, $A6, MultiYear_ProForma!$C:$C, "FY2030"))/5 -> 3254448.7
A7: =Scenarios!A7 -> G_DHub_EchoRamp | B7: =INDEX(MultiYear_ProForma!$X$2:$X$61, MATCH(Scenarios!A7&"|FY2028", MultiYear_ProForma!$Y$2:$Y$61, 0)) -> 9944.959 | C7: =INDEX(MultiYear_ProForma!$X$2:$X$61, MATCH(Scenarios!A7&"|FY2030", MultiYear_ProForma!$Y$2:$Y$61, 0)) -> 10448.423 | D7: =AVERAGE(INDEX(MultiYear_ProForma!$X$2:$X$61, MATCH(Scenarios!A7&"|FY2026", MultiYear_ProForma!$Y$2:$Y$61, 0)),INDEX(MultiYear_ProForma!$X$2:$X$61, MATCH(Scenarios!A7&"|FY2027", MultiYear_ProForma!$Y$2:$Y$61, 0)),INDEX(MultiYear_ProForma!$X$2:$X$61, MATCH(Scenarios!A7&"|FY2028", MultiYear_ProForma!$Y$2:$Y$61, 0))) -> 9898.7351 | E7: =AVERAGE(INDEX(MultiYear_ProForma!$X$2:$X$61, MATCH(Scenarios!A7&"|FY2026", MultiYear_ProForma!$Y$2:$Y$61, 0)),INDEX(MultiYear_ProForma!$X$2:$X$61, MATCH(Scenarios!A7&"|FY2027", MultiYear_ProForma!$Y$2:$Y$61, 0)),INDEX(MultiYear_ProForma!$X$2:$X$61, MATCH(Scenarios!A7&"|FY2028", MultiYear_ProForma!$Y$2:$Y$61, 0)),INDEX(MultiYear_ProForma!$X$2:$X$61, MATCH(Scenarios!A7&"|FY2029", MultiYear_ProForma!$Y$2:$Y$61, 0)),INDEX(MultiYear_ProForma!$X$2:$X$61, MATCH(Scenarios!A7&"|FY2030", MultiYear_ProForma!$Y$2:$Y$61, 0))) -> 10067.642 | F7: =IFERROR(VLOOKUP($A7&"|FY2026", MultiYear_ProForma!$A:$Y, 14, FALSE), "") -> 0 | G7: =IFERROR(VLOOKUP($A7&"|FY2030", MultiYear_ProForma!$A:$Y, 6, FALSE) + VLOOKUP($A7&"|FY2030", MultiYear_ProForma!$A:$Y, 15, FALSE), "") -> 703 | H7: =SUMIFS(MultiYear_ProForma!$AA:$AA, MultiYear_ProForma!$B:$B, $A7, MultiYear_ProForma!$C:$C, "FY2028") -> 3251651.8 | J7: =SUMIFS(MultiYear_ProForma!$AA:$AA, MultiYear_ProForma!$B:$B, $A7, MultiYear_ProForma!$C:$C, "FY2030") -> 3454504.7 | K7: =INDEX(MultiYear_ProForma!$AA:$AA,MATCH($A7&"|"&"FY2028",MultiYear_ProForma!$B:$B&"|"&MultiYear_ProForma!$C:$C,0)) -> #VALUE! | L7: =INDEX(MultiYear_ProForma!$AA:$AA,MATCH($A7&"|"&"FY2030",MultiYear_ProForma!$B:$B&"|"&MultiYear_ProForma!$C:$C,0)) -> #VALUE! | M7: =(SUMIFS(MultiYear_ProForma!$AA:$AA, MultiYear_ProForma!$B:$B, $A7, MultiYear_ProForma!$C:$C, "FY2026")+SUMIFS(MultiYear_ProForma!$AA:$AA, MultiYear_ProForma!$B:$B, $A7, MultiYear_ProForma!$C:$C, "FY2027")+SUMIFS(MultiYear_ProForma!$AA:$AA, MultiYear_ProForma!$B:$B, $A7, MultiYear_ProForma!$C:$C, "FY2028")+SUMIFS(MultiYear_ProForma!$AA:$AA, MultiYear_ProForma!$B:$B, $A7, MultiYear_ProForma!$C:$C, "FY2029")+SUMIFS(MultiYear_ProForma!$AA:$AA, MultiYear_ProForma!$B:$B, $A7, MultiYear_ProForma!$C:$C, "FY2030"))/5 -> 3194716.2
A8: =Scenarios!A8 -> A_Repurpose_Both_lease | B8: =INDEX(MultiYear_ProForma!$X$2:$X$61, MATCH(Scenarios!A8&"|FY2028", MultiYear_ProForma!$Y$2:$Y$61, 0)) -> 8939.9965 | C8: =INDEX(MultiYear_ProForma!$X$2:$X$61, MATCH(Scenarios!A8&"|FY2030", MultiYear_ProForma!$Y$2:$Y$61, 0)) -> 8169.1704 | D8: =AVERAGE(INDEX(MultiYear_ProForma!$X$2:$X$61, MATCH(Scenarios!A8&"|FY2026", MultiYear_ProForma!$Y$2:$Y$61, 0)),INDEX(MultiYear_ProForma!$X$2:$X$61, MATCH(Scenarios!A8&"|FY2027", MultiYear_ProForma!$Y$2:$Y$61, 0)),INDEX(MultiYear_ProForma!$X$2:$X$61, MATCH(Scenarios!A8&"|FY2028", MultiYear_ProForma!$Y$2:$Y$61, 0))) -> 11275.004 | E8: =AVERAGE(INDEX(MultiYear_ProForma!$X$2:$X$61, MATCH(Scenarios!A8&"|FY2026", MultiYear_ProForma!$Y$2:$Y$61, 0)),INDEX(MultiYear_ProForma!$X$2:$X$61, MATCH(Scenarios!A8&"|FY2027", MultiYear_ProForma!$Y$2:$Y$61, 0)),INDEX(MultiYear_ProForma!$X$2:$X$61, MATCH(Scenarios!A8&"|FY2028", MultiYear_ProForma!$Y$2:$Y$61, 0)),INDEX(MultiYear_ProForma!$X$2:$X$61, MATCH(Scenarios!A8&"|FY2029", MultiYear_ProForma!$Y$2:$Y$61, 0)),INDEX(MultiYear_ProForma!$X$2:$X$61, MATCH(Scenarios!A8&"|FY2030", MultiYear_ProForma!$Y$2:$Y$61, 0))) -> 10101.41 | F8: =IFERROR(VLOOKUP($A8&"|FY2026", MultiYear_ProForma!$A:$Y, 14, FALSE), "") -> 553 | G8: =IFERROR(VLOOKUP($A8&"|FY2030", MultiYear_ProForma!$A:$Y, 6, FALSE) + VLOOKUP($A8&"|FY2030", MultiYear_ProForma!$A:$Y, 15, FALSE), "") -> 414.75 | H8: =SUMIFS(MultiYear_ProForma!$AA:$AA, MultiYear_ProForma!$B:$B, $A8, MultiYear_ProForma!$C:$C, "FY2028") -> 1501573.9 | J8: =SUMIFS(MultiYear_ProForma!$AA:$AA, MultiYear_ProForma!$B:$B, $A8, MultiYear_ProForma!$C:$C, "FY2030") -> 1092739.7 | K8: =INDEX(MultiYear_ProForma!$AA:$AA,MATCH($A8&"|"&"FY2028",MultiYear_ProForma!$B:$B&"|"&MultiYear_ProForma!$C:$C,0)) -> #VALUE! | L8: =INDEX(MultiYear_ProForma!$AA:$AA,MATCH($A8&"|"&"FY2030",MultiYear_ProForma!$B:$B&"|"&MultiYear_ProForma!$C:$C,0)) -> #VALUE! | M8: =(SUMIFS(MultiYear_ProForma!$AA:$AA, MultiYear_ProForma!$B:$B, $A8, MultiYear_ProForma!$C:$C, "FY2026")+SUMIFS(MultiYear_ProForma!$AA:$AA, MultiYear_ProForma!$B:$B, $A8, MultiYear_ProForma!$C:$C, "FY2027")+SUMIFS(MultiYear_ProForma!$AA:$AA, MultiYear_ProForma!$B:$B, $A8, MultiYear_ProForma!$C:$C, "FY2028")+SUMIFS(MultiYear_ProForma!$AA:$AA, MultiYear_ProForma!$B:$B, $A8, MultiYear_ProForma!$C:$C, "FY2029")+SUMIFS(MultiYear_ProForma!$AA:$AA, MultiYear_ProForma!$B:$B, $A8, MultiYear_ProForma!$C:$C, "FY2030"))/5 -> 1982404.9
A9: =Scenarios!A9 -> A_Repurpose_Both_ops | B9: =INDEX(MultiYear_ProForma!$X$2:$X$61, MATCH(Scenarios!A9&"|FY2028", MultiYear_ProForma!$Y$2:$Y$61, 0)) -> 9364.9999 | C9: =INDEX(MultiYear_ProForma!$X$2:$X$61, MATCH(Scenarios!A9&"|FY2030", MultiYear_ProForma!$Y$2:$Y$61, 0)) -> 9062.2088 | D9: =AVERAGE(INDEX(MultiYear_ProForma!$X$2:$X$61, MATCH(Scenarios!A9&"|FY2026", MultiYear_ProForma!$Y$2:$Y$61, 0)),INDEX(MultiYear_ProForma!$X$2:$X$61, MATCH(Scenarios!A9&"|FY2027", MultiYear_ProForma!$Y$2:$Y$61, 0)),INDEX(MultiYear_ProForma!$X$2:$X$61, MATCH(Scenarios!A9&"|FY2028", MultiYear_ProForma!$Y$2:$Y$61, 0))) -> 11485.778 | E9: =AVERAGE(INDEX(MultiYear_ProForma!$X$2:$X$61, MATCH(Scenarios!A9&"|FY2026", MultiYear_ProForma!$Y$2:$Y$61, 0)),INDEX(MultiYear_ProForma!$X$2:$X$61, MATCH(Scenarios!A9&"|FY2027", MultiYear_ProForma!$Y$2:$Y$61, 0)),INDEX(MultiYear_ProForma!$X$2:$X$61, MATCH(Scenarios!A9&"|FY2028", MultiYear_ProForma!$Y$2:$Y$61, 0)),INDEX(MultiYear_ProForma!$X$2:$X$61, MATCH(Scenarios!A9&"|FY2029", MultiYear_ProForma!$Y$2:$Y$61, 0)),INDEX(MultiYear_ProForma!$X$2:$X$61, MATCH(Scenarios!A9&"|FY2030", MultiYear_ProForma!$Y$2:$Y$61, 0))) -> 10537.171 | F9: =IFERROR(VLOOKUP($A9&"|FY2026", MultiYear_ProForma!$A:$Y, 14, FALSE), "") -> 553 | G9: =IFERROR(VLOOKUP($A9&"|FY2030", MultiYear_ProForma!$A:$Y, 6, FALSE) + VLOOKUP($A9&"|FY2030", MultiYear_ProForma!$A:$Y, 15, FALSE), "") -> 414.75 | H9: =SUMIFS(MultiYear_ProForma!$AA:$AA, MultiYear_ProForma!$B:$B, $A9, MultiYear_ProForma!$C:$C, "FY2028") -> 1677844 | J9: =SUMIFS(MultiYear_ProForma!$AA:$AA, MultiYear_ProForma!$B:$B, $A9, MultiYear_ProForma!$C:$C, "FY2030") -> 1463127.3 | K9: =INDEX(MultiYear_ProForma!$AA:$AA,MATCH($A9&"|"&"FY2028",MultiYear_ProForma!$B:$B&"|"&MultiYear_ProForma!$C:$C,0)) -> #VALUE! | L9: =INDEX(MultiYear_ProForma!$AA:$AA,MATCH($A9&"|"&"FY2030",MultiYear_ProForma!$B:$B&"|"&MultiYear_ProForma!$C:$C,0)) -> #VALUE! | M9: =(SUMIFS(MultiYear_ProForma!$AA:$AA, MultiYear_ProForma!$B:$B, $A9, MultiYear_ProForma!$C:$C, "FY2026")+SUMIFS(MultiYear_ProForma!$AA:$AA, MultiYear_ProForma!$B:$B, $A9, MultiYear_ProForma!$C:$C, "FY2027")+SUMIFS(MultiYear_ProForma!$AA:$AA, MultiYear_ProForma!$B:$B, $A9, MultiYear_ProForma!$C:$C, "FY2028")+SUMIFS(MultiYear_ProForma!$AA:$AA, MultiYear_ProForma!$B:$B, $A9, MultiYear_ProForma!$C:$C, "FY2029")+SUMIFS(MultiYear_ProForma!$AA:$AA, MultiYear_ProForma!$B:$B, $A9, MultiYear_ProForma!$C:$C, "FY2030"))/5 -> 2163136.6
A10: =Scenarios!A10 -> B_Repurpose_Echo_lease | B10: =INDEX(MultiYear_ProForma!$X$2:$X$61, MATCH(Scenarios!A10&"|FY2028", MultiYear_ProForma!$Y$2:$Y$61, 0)) -> 9960.5311 | C10: =INDEX(MultiYear_ProForma!$X$2:$X$61, MATCH(Scenarios!A10&"|FY2030", MultiYear_ProForma!$Y$2:$Y$61, 0)) -> 9982.3013 | D10: =AVERAGE(INDEX(MultiYear_ProForma!$X$2:$X$61, MATCH(Scenarios!A10&"|FY2026", MultiYear_ProForma!$Y$2:$Y$61, 0)),INDEX(MultiYear_ProForma!$X$2:$X$61, MATCH(Scenarios!A10&"|FY2027", MultiYear_ProForma!$Y$2:$Y$61, 0)),INDEX(MultiYear_ProForma!$X$2:$X$61, MATCH(Scenarios!A10&"|FY2028", MultiYear_ProForma!$Y$2:$Y$61, 0))) -> 10783.443 | E10: =AVERAGE(INDEX(MultiYear_ProForma!$X$2:$X$61, MATCH(Scenarios!A10&"|FY2026", MultiYear_ProForma!$Y$2:$Y$61, 0)),INDEX(MultiYear_ProForma!$X$2:$X$61, MATCH(Scenarios!A10&"|FY2027", MultiYear_ProForma!$Y$2:$Y$61, 0)),INDEX(MultiYear_ProForma!$X$2:$X$61, MATCH(Scenarios!A10&"|FY2028", MultiYear_ProForma!$Y$2:$Y$61, 0)),INDEX(MultiYear_ProForma!$X$2:$X$61, MATCH(Scenarios!A10&"|FY2029", MultiYear_ProForma!$Y$2:$Y$61, 0)),INDEX(MultiYear_ProForma!$X$2:$X$61, MATCH(Scenarios!A10&"|FY2030", MultiYear_ProForma!$Y$2:$Y$61, 0))) -> 10457.117 | F10: =IFERROR(VLOOKUP($A10&"|FY2026", MultiYear_ProForma!$A:$Y, 14, FALSE), "") -> 257 | G10: =IFERROR(VLOOKUP($A10&"|FY2030", MultiYear_ProForma!$A:$Y, 6, FALSE) + VLOOKUP($A10&"|FY2030", MultiYear_ProForma!$A:$Y, 15, FALSE), "") -> 488.75 | H10: =SUMIFS(MultiYear_ProForma!$AA:$AA, MultiYear_ProForma!$B:$B, $A10, MultiYear_ProForma!$C:$C, "FY2028") -> 2268272.1 | J10: =SUMIFS(MultiYear_ProForma!$AA:$AA, MultiYear_ProForma!$B:$B, $A10, MultiYear_ProForma!$C:$C, "FY2030") -> 2173874.8 | K10: =INDEX(MultiYear_ProForma!$AA:$AA,MATCH($A10&"|"&"FY2028",MultiYear_ProForma!$B:$B&"|"&MultiYear_ProForma!$C:$C,0)) -> #VALUE! | L10: =INDEX(MultiYear_ProForma!$AA:$AA,MATCH($A10&"|"&"FY2030",MultiYear_ProForma!$B:$B&"|"&MultiYear_ProForma!$C:$C,0)) -> #VALUE! | M10: =(SUMIFS(MultiYear_ProForma!$AA:$AA, MultiYear_ProForma!$B:$B, $A10, MultiYear_ProForma!$C:$C, "FY2026")+SUMIFS(MultiYear_ProForma!$AA:$AA, MultiYear_ProForma!$B:$B, $A10, MultiYear_ProForma!$C:$C, "FY2027")+SUMIFS(MultiYear_ProForma!$AA:$AA, MultiYear_ProForma!$B:$B, $A10, MultiYear_ProForma!$C:$C, "FY2028")+SUMIFS(MultiYear_ProForma!$AA:$AA, MultiYear_ProForma!$B:$B, $A10, MultiYear_ProForma!$C:$C, "FY2029")+SUMIFS(MultiYear_ProForma!$AA:$AA, MultiYear_ProForma!$B:$B, $A10, MultiYear_ProForma!$C:$C, "FY2030"))/5 -> 2509958.7
A11: =Scenarios!A11 -> B_Repurpose_Echo_ops | B11: =INDEX(MultiYear_ProForma!$X$2:$X$61, MATCH(Scenarios!A11&"|FY2028", MultiYear_ProForma!$Y$2:$Y$61, 0)) -> 10128.141 | C11: =INDEX(MultiYear_ProForma!$X$2:$X$61, MATCH(Scenarios!A11&"|FY2030", MultiYear_ProForma!$Y$2:$Y$61, 0)) -> 10334.492 | D11: =AVERAGE(INDEX(MultiYear_ProForma!$X$2:$X$61, MATCH(Scenarios!A11&"|FY2026", MultiYear_ProForma!$Y$2:$Y$61, 0)),INDEX(MultiYear_ProForma!$X$2:$X$61, MATCH(Scenarios!A11&"|FY2027", MultiYear_ProForma!$Y$2:$Y$61, 0)),INDEX(MultiYear_ProForma!$X$2:$X$61, MATCH(Scenarios!A11&"|FY2028", MultiYear_ProForma!$Y$2:$Y$61, 0))) -> 10866.567 | E11: =AVERAGE(INDEX(MultiYear_ProForma!$X$2:$X$61, MATCH(Scenarios!A11&"|FY2026", MultiYear_ProForma!$Y$2:$Y$61, 0)),INDEX(MultiYear_ProForma!$X$2:$X$61, MATCH(Scenarios!A11&"|FY2027", MultiYear_ProForma!$Y$2:$Y$61, 0)),INDEX(MultiYear_ProForma!$X$2:$X$61, MATCH(Scenarios!A11&"|FY2028", MultiYear_ProForma!$Y$2:$Y$61, 0)),INDEX(MultiYear_ProForma!$X$2:$X$61, MATCH(Scenarios!A11&"|FY2029", MultiYear_ProForma!$Y$2:$Y$61, 0)),INDEX(MultiYear_ProForma!$X$2:$X$61, MATCH(Scenarios!A11&"|FY2030", MultiYear_ProForma!$Y$2:$Y$61, 0))) -> 10628.969 | F11: =IFERROR(VLOOKUP($A11&"|FY2026", MultiYear_ProForma!$A:$Y, 14, FALSE), "") -> 257 | G11: =IFERROR(VLOOKUP($A11&"|FY2030", MultiYear_ProForma!$A:$Y, 6, FALSE) + VLOOKUP($A11&"|FY2030", MultiYear_ProForma!$A:$Y, 15, FALSE), "") -> 488.75 | H11: =SUMIFS(MultiYear_ProForma!$AA:$AA, MultiYear_ProForma!$B:$B, $A11, MultiYear_ProForma!$C:$C, "FY2028") -> 2350191.5 | J11: =SUMIFS(MultiYear_ProForma!$AA:$AA, MultiYear_ProForma!$B:$B, $A11, MultiYear_ProForma!$C:$C, "FY2030") -> 2346008 | K11: =INDEX(MultiYear_ProForma!$AA:$AA,MATCH($A11&"|"&"FY2028",MultiYear_ProForma!$B:$B&"|"&MultiYear_ProForma!$C:$C,0)) -> #VALUE! | L11: =INDEX(MultiYear_ProForma!$AA:$AA,MATCH($A11&"|"&"FY2030",MultiYear_ProForma!$B:$B&"|"&MultiYear_ProForma!$C:$C,0)) -> #VALUE! | M11: =(SUMIFS(MultiYear_ProForma!$AA:$AA, MultiYear_ProForma!$B:$B, $A11, MultiYear_ProForma!$C:$C, "FY2026")+SUMIFS(MultiYear_ProForma!$AA:$AA, MultiYear_ProForma!$B:$B, $A11, MultiYear_ProForma!$C:$C, "FY2027")+SUMIFS(MultiYear_ProForma!$AA:$AA, MultiYear_ProForma!$B:$B, $A11, MultiYear_ProForma!$C:$C, "FY2028")+SUMIFS(MultiYear_ProForma!$AA:$AA, MultiYear_ProForma!$B:$B, $A11, MultiYear_ProForma!$C:$C, "FY2029")+SUMIFS(MultiYear_ProForma!$AA:$AA, MultiYear_ProForma!$B:$B, $A11, MultiYear_ProForma!$C:$C, "FY2030"))/5 -> 2593951.6
A12: =Scenarios!A12 -> C_Repurpose_Pima_lease | B12: =INDEX(MultiYear_ProForma!$X$2:$X$61, MATCH(Scenarios!A12&"|FY2028", MultiYear_ProForma!$Y$2:$Y$61, 0)) -> 9844.1047 | C12: =INDEX(MultiYear_ProForma!$X$2:$X$61, MATCH(Scenarios!A12&"|FY2030", MultiYear_ProForma!$Y$2:$Y$61, 0)) -> 9775.4525 | D12: =AVERAGE(INDEX(MultiYear_ProForma!$X$2:$X$61, MATCH(Scenarios!A12&"|FY2026", MultiYear_ProForma!$Y$2:$Y$61, 0)),INDEX(MultiYear_ProForma!$X$2:$X$61, MATCH(Scenarios!A12&"|FY2027", MultiYear_ProForma!$Y$2:$Y$61, 0)),INDEX(MultiYear_ProForma!$X$2:$X$61, MATCH(Scenarios!A12&"|FY2028", MultiYear_ProForma!$Y$2:$Y$61, 0))) -> 10729.496 | E12: =AVERAGE(INDEX(MultiYear_ProForma!$X$2:$X$61, MATCH(Scenarios!A12&"|FY2026", MultiYear_ProForma!$Y$2:$Y$61, 0)),INDEX(MultiYear_ProForma!$X$2:$X$61, MATCH(Scenarios!A12&"|FY2027", MultiYear_ProForma!$Y$2:$Y$61, 0)),INDEX(MultiYear_ProForma!$X$2:$X$61, MATCH(Scenarios!A12&"|FY2028", MultiYear_ProForma!$Y$2:$Y$61, 0)),INDEX(MultiYear_ProForma!$X$2:$X$61, MATCH(Scenarios!A12&"|FY2029", MultiYear_ProForma!$Y$2:$Y$61, 0)),INDEX(MultiYear_ProForma!$X$2:$X$61, MATCH(Scenarios!A12&"|FY2030", MultiYear_ProForma!$Y$2:$Y$61, 0))) -> 10350.521 | F12: =IFERROR(VLOOKUP($A12&"|FY2026", MultiYear_ProForma!$A:$Y, 14, FALSE), "") -> 296 | G12: =IFERROR(VLOOKUP($A12&"|FY2030", MultiYear_ProForma!$A:$Y, 6, FALSE) + VLOOKUP($A12&"|FY2030", MultiYear_ProForma!$A:$Y, 15, FALSE), "") -> 479 | H12: =SUMIFS(MultiYear_ProForma!$AA:$AA, MultiYear_ProForma!$B:$B, $A12, MultiYear_ProForma!$C:$C, "FY2028") -> 2167254.4 | J12: =SUMIFS(MultiYear_ProForma!$AA:$AA, MultiYear_ProForma!$B:$B, $A12, MultiYear_ProForma!$C:$C, "FY2030") -> 2031427.9 | K12: =INDEX(MultiYear_ProForma!$AA:$AA,MATCH($A12&"|"&"FY2028",MultiYear_ProForma!$B:$B&"|"&MultiYear_ProForma!$C:$C,0)) -> #VALUE! | L12: =INDEX(MultiYear_ProForma!$AA:$AA,MATCH($A12&"|"&"FY2030",MultiYear_ProForma!$B:$B&"|"&MultiYear_ProForma!$C:$C,0)) -> #VALUE! | M12: =(SUMIFS(MultiYear_ProForma!$AA:$AA, MultiYear_ProForma!$B:$B, $A12, MultiYear_ProForma!$C:$C, "FY2026")+SUMIFS(MultiYear_ProForma!$AA:$AA, MultiYear_ProForma!$B:$B, $A12, MultiYear_ProForma!$C:$C, "FY2027")+SUMIFS(MultiYear_ProForma!$AA:$AA, MultiYear_ProForma!$B:$B, $A12, MultiYear_ProForma!$C:$C, "FY2028")+SUMIFS(MultiYear_ProForma!$AA:$AA, MultiYear_ProForma!$B:$B, $A12, MultiYear_ProForma!$C:$C, "FY2029")+SUMIFS(MultiYear_ProForma!$AA:$AA, MultiYear_ProForma!$B:$B, $A12, MultiYear_ProForma!$C:$C, "FY2030"))/5 -> 2408828.3
A13: =Scenarios!A13 -> C_Repurpose_Pima_ops | B13: =INDEX(MultiYear_ProForma!$X$2:$X$61, MATCH(Scenarios!A13&"|FY2028", MultiYear_ProForma!$Y$2:$Y$61, 0)) -> 10041.079 | C13: =INDEX(MultiYear_ProForma!$X$2:$X$61, MATCH(Scenarios!A13&"|FY2030", MultiYear_ProForma!$Y$2:$Y$61, 0)) -> 10189.345 | D13: =AVERAGE(INDEX(MultiYear_ProForma!$X$2:$X$61, MATCH(Scenarios!A13&"|FY2026", MultiYear_ProForma!$Y$2:$Y$61, 0)),INDEX(MultiYear_ProForma!$X$2:$X$61, MATCH(Scenarios!A13&"|FY2027", MultiYear_ProForma!$Y$2:$Y$61, 0)),INDEX(MultiYear_ProForma!$X$2:$X$61, MATCH(Scenarios!A13&"|FY2028", MultiYear_ProForma!$Y$2:$Y$61, 0))) -> 10827.182 | E13: =AVERAGE(INDEX(MultiYear_ProForma!$X$2:$X$61, MATCH(Scenarios!A13&"|FY2026", MultiYear_ProForma!$Y$2:$Y$61, 0)),INDEX(MultiYear_ProForma!$X$2:$X$61, MATCH(Scenarios!A13&"|FY2027", MultiYear_ProForma!$Y$2:$Y$61, 0)),INDEX(MultiYear_ProForma!$X$2:$X$61, MATCH(Scenarios!A13&"|FY2028", MultiYear_ProForma!$Y$2:$Y$61, 0)),INDEX(MultiYear_ProForma!$X$2:$X$61, MATCH(Scenarios!A13&"|FY2029", MultiYear_ProForma!$Y$2:$Y$61, 0)),INDEX(MultiYear_ProForma!$X$2:$X$61, MATCH(Scenarios!A13&"|FY2030", MultiYear_ProForma!$Y$2:$Y$61, 0))) -> 10552.481 | F13: =IFERROR(VLOOKUP($A13&"|FY2026", MultiYear_ProForma!$A:$Y, 14, FALSE), "") -> 296 | G13: =IFERROR(VLOOKUP($A13&"|FY2030", MultiYear_ProForma!$A:$Y, 6, FALSE) + VLOOKUP($A13&"|FY2030", MultiYear_ProForma!$A:$Y, 15, FALSE), "") -> 479 | H13: =SUMIFS(MultiYear_ProForma!$AA:$AA, MultiYear_ProForma!$B:$B, $A13, MultiYear_ProForma!$C:$C, "FY2028") -> 2261605.2 | J13: =SUMIFS(MultiYear_ProForma!$AA:$AA, MultiYear_ProForma!$B:$B, $A13, MultiYear_ProForma!$C:$C, "FY2030") -> 2229682.5 | K13: =INDEX(MultiYear_ProForma!$AA:$AA,MATCH($A13&"|"&"FY2028",MultiYear_ProForma!$B:$B&"|"&MultiYear_ProForma!$C:$C,0)) -> #VALUE! | L13: =INDEX(MultiYear_ProForma!$AA:$AA,MATCH($A13&"|"&"FY2030",MultiYear_ProForma!$B:$B&"|"&MultiYear_ProForma!$C:$C,0)) -> #VALUE! | M13: =(SUMIFS(MultiYear_ProForma!$AA:$AA, MultiYear_ProForma!$B:$B, $A13, MultiYear_ProForma!$C:$C, "FY2026")+SUMIFS(MultiYear_ProForma!$AA:$AA, MultiYear_ProForma!$B:$B, $A13, MultiYear_ProForma!$C:$C, "FY2027")+SUMIFS(MultiYear_ProForma!$AA:$AA, MultiYear_ProForma!$B:$B, $A13, MultiYear_ProForma!$C:$C, "FY2028")+SUMIFS(MultiYear_ProForma!$AA:$AA, MultiYear_ProForma!$B:$B, $A13, MultiYear_ProForma!$C:$C, "FY2029")+SUMIFS(MultiYear_ProForma!$AA:$AA, MultiYear_ProForma!$B:$B, $A13, MultiYear_ProForma!$C:$C, "FY2030"))/5 -> 2505567.2

Sheet BreakEven
A1: Break-even retention r* for A_Repurpose_Both vs selected keep-open scenario
A3: Keep-open scenario (pick from Summary_Costs!A) | B3: D_Grow_Both_0
A5: OpsFactor | B5: =1-BaselineCalc!$B$5 -> 0.993
A6: M (displaced if close both) | B6: =BaselineCalc!$B$7 + BaselineCalc!$B$8 -> 553
A8: FY2028 helpers
A9: Var | B9: =YearMap!B4 -> 7489.9897
A10: EchoFixed | B10: =YearMap!C4 -> 824968.86
A11: PimaFixed | B11: =YearMap!D4 -> 950158.69
A12: f_ops | B12: =YearMap!G4 -> 0.3
A13: f_lease | B13: =YearMap!F4 -> 0.2
A14: Ct(FY2028) | B14: =INDEX(Summary_Costs!$B:$B, MATCH($B$3, Summary_Costs!$A:$A, 0)) -> 10625.085
B16: h → | C16: 200 | D16: 300 | E16: 400 | F16: 600 | G16: 800 | H16: 1000 | I16: 1200 | J16: 1500
A17: FY2028 f_ops | C17: =IF(($B$14-( $B$9+C16))<=0,NA(),($B$5*$B$12*($B$10+$B$11))/($B$6*($B$14-( $B$9+C16)))) -> 0.3258012 | D17: =IF(($B$14-( $B$9+D16))<=0,NA(),($B$5*$B$12*($B$10+$B$11))/($B$6*($B$14-( $B$9+D16)))) -> 0.33729291 | E17: =IF(($B$14-( $B$9+E16))<=0,NA(),($B$5*$B$12*($B$10+$B$11))/($B$6*($B$14-( $B$9+E16)))) -> 0.34962495 | F17: =IF(($B$14-( $B$9+F16))<=0,NA(),($B$5*$B$12*($B$10+$B$11))/($B$6*($B$14-( $B$9+F16)))) -> 0.37720773 | G17: =IF(($B$14-( $B$9+G16))<=0,NA(),($B$5*$B$12*($B$10+$B$11))/($B$6*($B$14-( $B$9+G16)))) -> 0.40951542 | H17: =IF(($B$14-( $B$9+H16))<=0,NA(),($B$5*$B$12*($B$10+$B$11))/($B$6*($B$14-( $B$9+H16)))) -> 0.4478758 | I17: =IF(($B$14-( $B$9+I16))<=0,NA(),($B$5*$B$12*($B$10+$B$11))/($B$6*($B$14-( $B$9+I16)))) -> 0.49416558 | J17: =IF(($B$14-( $B$9+J16))<=0,NA(),($B$5*$B$12*($B$10+$B$11))/($B$6*($B$14-( $B$9+J16)))) -> 0.58483286
A18: FY2028 f_lease | C18: =IF(($B$14-( $B$9+C16))<=0,NA(),($B$5*$B$13*($B$10+$B$11))/($B$6*($B$14-( $B$9+C16)))) -> 0.2172008 | D18: =IF(($B$14-( $B$9+D16))<=0,NA(),($B$5*$B$13*($B$10+$B$11))/($B$6*($B$14-( $B$9+D16)))) -> 0.22486194 | E18: =IF(($B$14-( $B$9+E16))<=0,NA(),($B$5*$B$13*($B$10+$B$11))/($B$6*($B$14-( $B$9+E16)))) -> 0.2330833 | F18: =IF(($B$14-( $B$9+F16))<=0,NA(),($B$5*$B$13*($B$10+$B$11))/($B$6*($B$14-( $B$9+F16)))) -> 0.25147182 | G18: =IF(($B$14-( $B$9+G16))<=0,NA(),($B$5*$B$13*($B$10+$B$11))/($B$6*($B$14-( $B$9+G16)))) -> 0.27301028 | H18: =IF(($B$14-( $B$9+H16))<=0,NA(),($B$5*$B$13*($B$10+$B$11))/($B$6*($B$14-( $B$9+H16)))) -> 0.29858387 | I18: =IF(($B$14-( $B$9+I16))<=0,NA(),($B$5*$B$13*($B$10+$B$11))/($B$6*($B$14-( $B$9+I16)))) -> 0.32944372 | J18: =IF(($B$14-( $B$9+J16))<=0,NA(),($B$5*$B$13*($B$10+$B$11))/($B$6*($B$14-( $B$9+J16)))) -> 0.38988857
A22: FY2030 helpers
A23: Var | B23: =YearMap!B6 -> 7869.1704
A24: EchoFixed | B24: =YearMap!C6 -> 866732.91
A25: PimaFixed | B25: =YearMap!D6 -> 998260.47
A26: f_ops | B26: =YearMap!G6 -> 0.2
A27: f_lease | B27: =YearMap!F6 -> 0
A28: Ct(FY2030) | B28: =INDEX(Summary_Costs!$C:$C, MATCH($B$3, Summary_Costs!$A:$A, 0)) -> 11162.98
B30: h → | C30: 200 | D30: 300 | E30: 400 | F30: 600 | G30: 800 | H30: 1000 | I30: 1200 | J30: 1500
A31: FY2030 f_ops | C31: =IF(($B$28-( $B$23+C30))<=0,NA(),($B$5*$B$26*($B$24+$B$25))/($B$6*($B$28-( $B$23+C30)))) -> 0.21648997 | D31: =IF(($B$28-( $B$23+D30))<=0,NA(),($B$5*$B$26*($B$24+$B$25))/($B$6*($B$28-( $B$23+D30)))) -> 0.22372123 | E31: =IF(($B$28-( $B$23+E30))<=0,NA(),($B$5*$B$26*($B$24+$B$25))/($B$6*($B$28-( $B$23+E30)))) -> 0.23145225 | F31: =IF(($B$28-( $B$23+F30))<=0,NA(),($B$5*$B$26*($B$24+$B$25))/($B$6*($B$28-( $B$23+F30)))) -> 0.24863626 | G31: =IF(($B$28-( $B$23+G30))<=0,NA(),($B$5*$B$26*($B$24+$B$25))/($B$6*($B$28-( $B$23+G30)))) -> 0.26857653 | H31: =IF(($B$28-( $B$23+H30))<=0,NA(),($B$5*$B$26*($B$24+$B$25))/($B$6*($B$28-( $B$23+H30)))) -> 0.29199404 | I31: =IF(($B$28-( $B$23+I30))<=0,NA(),($B$5*$B$26*($B$24+$B$25))/($B$6*($B$28-( $B$23+I30)))) -> 0.31988521 | J31: =IF(($B$28-( $B$23+J30))<=0,NA(),($B$5*$B$26*($B$24+$B$25))/($B$6*($B$28-( $B$23+J30)))) -> 0.37338339
A32: FY2030 f_lease | C32: =IF(($B$28-( $B$23+C30))<=0,NA(),($B$5*$B$27*($B$24+$B$25))/($B$6*($B$28-( $B$23+C30)))) -> 0 | D32: =IF(($B$28-( $B$23+D30))<=0,NA(),($B$5*$B$27*($B$24+$B$25))/($B$6*($B$28-( $B$23+D30)))) -> 0 | E32: =IF(($B$28-( $B$23+E30))<=0,NA(),($B$5*$B$27*($B$24+$B$25))/($B$6*($B$28-( $B$23+E30)))) -> 0 | F32: =IF(($B$28-( $B$23+F30))<=0,NA(),($B$5*$B$27*($B$24+$B$25))/($B$6*($B$28-( $B$23+F30)))) -> 0 | G32: =IF(($B$28-( $B$23+G30))<=0,NA(),($B$5*$B$27*($B$24+$B$25))/($B$6*($B$28-( $B$23+G30)))) -> 0 | H32: =IF(($B$28-( $B$23+H30))<=0,NA(),($B$5*$B$27*($B$24+$B$25))/($B$6*($B$28-( $B$23+H30)))) -> 0 | I32: =IF(($B$28-( $B$23+I30))<=0,NA(),($B$5*$B$27*($B$24+$B$25))/($B$6*($B$28-( $B$23+I30)))) -> 0 | J32: =IF(($B$28-( $B$23+J30))<=0,NA(),($B$5*$B$27*($B$24+$B$25))/($B$6*($B$28-( $B$23+J30)))) -> 0

Sheet Notes
A1: FAQs
B2: Why “Fixed share of M&O = 0.30”?
B3: District M&O typically has a sizable semi‑fixed component (plant ops/custodial/insurance/admin overhead). Without site‑level detail yet, 30% is a conservative placeholder in the middle of the 25–40% range many K‑12 systems sit in. We will replace it with SUSD plant ops + insurance shares when available.
B5: Why “Ops savings (keep‑open) = 0.007 (0.7%)”?
B6: This represents “light discipline” (utilities/purchasing tweaks, route smoothing) that does not depend on closing a site. I set it very low on purpose so it doesn’t drive results. We’ll calibrate with SUSD data (e.g., last year’s utility audits) if provided.
B8: Why “Extra savings (co‑location) = 0.015 (1.5%)”?
B9: This reflects incremental savings from consolidating some services on one campus (custodial/grounds/partial routing). Again kept small and conservative; we’ll swap in real custodial (sq‑ft), grounds and route deltas when we get them.
B11: Why “Repurpose TI per closed site (FY26) = $1.2M”? What is “one‑time carry/TI”?
B12: “TI” = tenant improvements / transition investments needed to convert a K‑8 to a different use (early learning, admin consolidation) and carry costs in year one (e.g., abatement, doors/security, low‑voltage re‑work, furniture, swing space). A light‑touch repurpose can easily run $10–$20/sq‑ft; Echo’s plant is ~77k sq ft, so $1.2M is a reasonable placeholder (we are not assuming a gut remodel). We’ll replace this with SUSD’s scope/estimate if they have one.
A17: Definitions
B18: MO inflation
B19: Base MO per ADM (FY25)
B20: Fixed share of MO
B21: Ops savings (keep‑open)
B22: Extra savings (Co‑location)
B23: Echo base ADM
B24: Pima base ADM
B25: Total base ADM

Sheet Attributes
A1: ScenarioKey | B1: Distinctiveness | C1: Reversibility
A2: A_Repurpose_Both_ops | B2: - | C2: Low
A3: A_Repurpose_Both_lease | B3: - | C3: Low
A4: F_CoLocation_Echo_0 | B4: + | C4: High
A5: D_Grow_Both_0 | B5: + | C5: Med
A6: D_Grow_Both_100 | B6: + | C6: Med
A7: D_Grow_Both_150 | B7: + | C7: Med
A8: E_StatusQuo_Targets_0 | B8: o | C8: High
A9: G_DHub_EchoRamp | B9: + | C9: Med-High

Sheet BreakEven_X
A1: Break-even retention r* for A_Repurpose_Both vs selected keep-open scenario
A3: Keep-open scenario (pick from Summary_Costs!A) | B3: =Dashboard!$B$6 -> G_DHub_EchoRamp
A5: OpsFactor | B5: =1-BaselineCalc!$B$5 -> 0.993
A6: M (displaced if close both) | B6: =BaselineCalc!$B$7 + BaselineCalc!$B$8 -> 553
A8: FY2028 helpers
A9: Var | B9: =YearMap!B4 -> 7489.9897
A10: EchoFixed | B10: =YearMap!C4 -> 824968.86
A11: PimaFixed | B11: =YearMap!D4 -> 950158.69
A12: f_ops | B12: =YearMap!G4 -> 0.3
A13: f_lease | B13: =YearMap!F4 -> 0.2
A14: Ct(FY2028) | B14: =INDEX(Summary_Costs!$B:$B, MATCH($B$3, Summary_Costs!$A:$A, 0)) -> 9944.959
B16: h → | C16: 200 | D16: 300 | E16: 400 | F16: 600 | G16: 800 | H16: 1000 | I16: 1200 | J16: 1500
A17: FY2028 f_ops | C17: =IF(($B$14-( $B$9+C16))<=0,NA(),($B$5*$B$12*($B$10+$B$11))/($B$6*($B$14-( $B$9+C16)))) -> 0.42406683 | D17: =IF(($B$14-( $B$9+D16))<=0,NA(),($B$5*$B$12*($B$10+$B$11))/($B$6*($B$14-( $B$9+D16)))) -> 0.44374538 | E17: =IF(($B$14-( $B$9+E16))<=0,NA(),($B$5*$B$12*($B$10+$B$11))/($B$6*($B$14-( $B$9+E16)))) -> 0.46533916 | F17: =IF(($B$14-( $B$9+F16))<=0,NA(),($B$5*$B$12*($B$10+$B$11))/($B$6*($B$14-( $B$9+F16)))) -> 0.51551132 | G17: =IF(($B$14-( $B$9+G16))<=0,NA(),($B$5*$B$12*($B$10+$B$11))/($B$6*($B$14-( $B$9+G16)))) -> 0.57780992 | H17: =IF(($B$14-( $B$9+H16))<=0,NA(),($B$5*$B$12*($B$10+$B$11))/($B$6*($B$14-( $B$9+H16)))) -> 0.65723564 | I17: =IF(($B$14-( $B$9+I16))<=0,NA(),($B$5*$B$12*($B$10+$B$11))/($B$6*($B$14-( $B$9+I16)))) -> 0.76197695 | J17: =IF(($B$14-( $B$9+J16))<=0,NA(),($B$5*$B$12*($B$10+$B$11))/($B$6*($B$14-( $B$9+J16)))) -> 1.0013491
A18: FY2028 f_lease | C18: =IF(($B$14-( $B$9+C16))<=0,NA(),($B$5*$B$13*($B$10+$B$11))/($B$6*($B$14-( $B$9+C16)))) -> 0.28271122 | D18: =IF(($B$14-( $B$9+D16))<=0,NA(),($B$5*$B$13*($B$10+$B$11))/($B$6*($B$14-( $B$9+D16)))) -> 0.29583026 | E18: =IF(($B$14-( $B$9+E16))<=0,NA(),($B$5*$B$13*($B$10+$B$11))/($B$6*($B$14-( $B$9+E16)))) -> 0.3102261 | F18: =IF(($B$14-( $B$9+F16))<=0,NA(),($B$5*$B$13*($B$10+$B$11))/($B$6*($B$14-( $B$9+F16)))) -> 0.34367422 | G18: =IF(($B$14-( $B$9+G16))<=0,NA(),($B$5*$B$13*($B$10+$B$11))/($B$6*($B$14-( $B$9+G16)))) -> 0.38520661 | H18: =IF(($B$14-( $B$9+H16))<=0,NA(),($B$5*$B$13*($B$10+$B$11))/($B$6*($B$14-( $B$9+H16)))) -> 0.43815709 | I18: =IF(($B$14-( $B$9+I16))<=0,NA(),($B$5*$B$13*($B$10+$B$11))/($B$6*($B$14-( $B$9+I16)))) -> 0.50798463 | J18: =IF(($B$14-( $B$9+J16))<=0,NA(),($B$5*$B$13*($B$10+$B$11))/($B$6*($B$14-( $B$9+J16)))) -> 0.66756609
A22: FY2030 helpers
A23: Var | B23: =YearMap!B6 -> 7869.1704
A24: EchoFixed | B24: =YearMap!C6 -> 866732.91
A25: PimaFixed | B25: =YearMap!D6 -> 998260.47
A26: f_ops | B26: =YearMap!G6 -> 0.2
A27: f_lease | B27: =YearMap!F6 -> 0
A28: Ct(FY2030) | B28: =INDEX(Summary_Costs!$C:$C, MATCH($B$3, Summary_Costs!$A:$A, 0)) -> 10448.423
B30: h → | C30: 200 | D30: 300 | E30: 400 | F30: 600 | G30: 800 | H30: 1000 | I30: 1200 | J30: 1500
A31: FY2030 f_ops | C31: =IF(($B$28-( $B$23+C30))<=0,NA(),($B$5*$B$26*($B$24+$B$25))/($B$6*($B$28-( $B$23+C30)))) -> 0.28150813 | D31: =IF(($B$28-( $B$23+D30))<=0,NA(),($B$5*$B$26*($B$24+$B$25))/($B$6*($B$28-( $B$23+D30)))) -> 0.29385903 | E31: =IF(($B$28-( $B$23+E30))<=0,NA(),($B$5*$B$26*($B$24+$B$25))/($B$6*($B$28-( $B$23+E30)))) -> 0.30734343 | F31: =IF(($B$28-( $B$23+F30))<=0,NA(),($B$5*$B$26*($B$24+$B$25))/($B$6*($B$28-( $B$23+F30)))) -> 0.33839995 | G31: =IF(($B$28-( $B$23+G30))<=0,NA(),($B$5*$B$26*($B$24+$B$25))/($B$6*($B$28-( $B$23+G30)))) -> 0.3764384 | H31: =IF(($B$28-( $B$23+H30))<=0,NA(),($B$5*$B$26*($B$24+$B$25))/($B$6*($B$28-( $B$23+H30)))) -> 0.42411139 | I31: =IF(($B$28-( $B$23+I30))<=0,NA(),($B$5*$B$26*($B$24+$B$25))/($B$6*($B$28-( $B$23+I30)))) -> 0.48561014 | J31: =IF(($B$28-( $B$23+J30))<=0,NA(),($B$5*$B$26*($B$24+$B$25))/($B$6*($B$28-( $B$23+J30)))) -> 0.62059532
A32: FY2030 f_lease | C32: =IF(($B$28-( $B$23+C30))<=0,NA(),($B$5*$B$27*($B$24+$B$25))/($B$6*($B$28-( $B$23+C30)))) -> 0 | D32: =IF(($B$28-( $B$23+D30))<=0,NA(),($B$5*$B$27*($B$24+$B$25))/($B$6*($B$28-( $B$23+D30)))) -> 0 | E32: =IF(($B$28-( $B$23+E30))<=0,NA(),($B$5*$B$27*($B$24+$B$25))/($B$6*($B$28-( $B$23+E30)))) -> 0 | F32: =IF(($B$28-( $B$23+F30))<=0,NA(),($B$5*$B$27*($B$24+$B$25))/($B$6*($B$28-( $B$23+F30)))) -> 0 | G32: =IF(($B$28-( $B$23+G30))<=0,NA(),($B$5*$B$27*($B$24+$B$25))/($B$6*($B$28-( $B$23+G30)))) -> 0 | H32: =IF(($B$28-( $B$23+H30))<=0,NA(),($B$5*$B$27*($B$24+$B$25))/($B$6*($B$28-( $B$23+H30)))) -> 0 | I32: =IF(($B$28-( $B$23+I30))<=0,NA(),($B$5*$B$27*($B$24+$B$25))/($B$6*($B$28-( $B$23+I30)))) -> 0 | J32: =IF(($B$28-( $B$23+J30))<=0,NA(),($B$5*$B$27*($B$24+$B$25))/($B$6*($B$28-( $B$23+J30)))) -> 0

Sheet BreakEven_Y
A1: Break-even retention r* for A_Repurpose_Both vs selected keep-open scenario
A3: Keep-open scenario (pick from Summary_Costs!A) | B3: =Dashboard!$B$7 -> G_DHub_EchoRamp
A5: OpsFactor | B5: =1-BaselineCalc!$B$5 -> 0.993
A6: M (displaced if close both) | B6: =BaselineCalc!$B$7 + BaselineCalc!$B$8 -> 553
A8: FY2028 helpers
A9: Var | B9: =YearMap!B4 -> 7489.9897
A10: EchoFixed | B10: =YearMap!C4 -> 824968.86
A11: PimaFixed | B11: =YearMap!D4 -> 950158.69
A12: f_ops | B12: =YearMap!G4 -> 0.3
A13: f_lease | B13: =YearMap!F4 -> 0.2
A14: Ct(FY2028) | B14: =INDEX(Summary_Costs!$B:$B, MATCH($B$3, Summary_Costs!$A:$A, 0)) -> 9944.959
B16: h → | C16: 200 | D16: 300 | E16: 400 | F16: 600 | G16: 800 | H16: 1000 | I16: 1200 | J16: 1500
A17: FY2028 f_ops | C17: =IF(($B$14-( $B$9+C16))<=0,NA(),($B$5*$B$12*($B$10+$B$11))/($B$6*($B$14-( $B$9+C16)))) -> 0.42406683 | D17: =IF(($B$14-( $B$9+D16))<=0,NA(),($B$5*$B$12*($B$10+$B$11))/($B$6*($B$14-( $B$9+D16)))) -> 0.44374538 | E17: =IF(($B$14-( $B$9+E16))<=0,NA(),($B$5*$B$12*($B$10+$B$11))/($B$6*($B$14-( $B$9+E16)))) -> 0.46533916 | F17: =IF(($B$14-( $B$9+F16))<=0,NA(),($B$5*$B$12*($B$10+$B$11))/($B$6*($B$14-( $B$9+F16)))) -> 0.51551132 | G17: =IF(($B$14-( $B$9+G16))<=0,NA(),($B$5*$B$12*($B$10+$B$11))/($B$6*($B$14-( $B$9+G16)))) -> 0.57780992 | H17: =IF(($B$14-( $B$9+H16))<=0,NA(),($B$5*$B$12*($B$10+$B$11))/($B$6*($B$14-( $B$9+H16)))) -> 0.65723564 | I17: =IF(($B$14-( $B$9+I16))<=0,NA(),($B$5*$B$12*($B$10+$B$11))/($B$6*($B$14-( $B$9+I16)))) -> 0.76197695 | J17: =IF(($B$14-( $B$9+J16))<=0,NA(),($B$5*$B$12*($B$10+$B$11))/($B$6*($B$14-( $B$9+J16)))) -> 1.0013491
A18: FY2028 f_lease | C18: =IF(($B$14-( $B$9+C16))<=0,NA(),($B$5*$B$13*($B$10+$B$11))/($B$6*($B$14-( $B$9+C16)))) -> 0.28271122 | D18: =IF(($B$14-( $B$9+D16))<=0,NA(),($B$5*$B$13*($B$10+$B$11))/($B$6*($B$14-( $B$9+D16)))) -> 0.29583026 | E18: =IF(($B$14-( $B$9+E16))<=0,NA(),($B$5*$B$13*($B$10+$B$11))/($B$6*($B$14-( $B$9+E16)))) -> 0.3102261 | F18: =IF(($B$14-( $B$9+F16))<=0,NA(),($B$5*$B$13*($B$10+$B$11))/($B$6*($B$14-( $B$9+F16)))) -> 0.34367422 | G18: =IF(($B$14-( $B$9+G16))<=0,NA(),($B$5*$B$13*($B$10+$B$11))/($B$6*($B$14-( $B$9+G16)))) -> 0.38520661 | H18: =IF(($B$14-( $B$9+H16))<=0,NA(),($B$5*$B$13*($B$10+$B$11))/($B$6*($B$14-( $B$9+H16)))) -> 0.43815709 | I18: =IF(($B$14-( $B$9+I16))<=0,NA(),($B$5*$B$13*($B$10+$B$11))/($B$6*($B$14-( $B$9+I16)))) -> 0.50798463 | J18: =IF(($B$14-( $B$9+J16))<=0,NA(),($B$5*$B$13*($B$10+$B$11))/($B$6*($B$14-( $B$9+J16)))) -> 0.66756609
A22: FY2030 helpers
A23: Var | B23: =YearMap!B6 -> 7869.1704
A24: EchoFixed | B24: =YearMap!C6 -> 866732.91
A25: PimaFixed | B25: =YearMap!D6 -> 998260.47
A26: f_ops | B26: =YearMap!G6 -> 0.2
A27: f_lease | B27: =YearMap!F6 -> 0
A28: Ct(FY2030) | B28: =INDEX(Summary_Costs!$C:$C, MATCH($B$3, Summary_Costs!$A:$A, 0)) -> 10448.423
B30: h → | C30: 200 | D30: 300 | E30: 400 | F30: 600 | G30: 800 | H30: 1000 | I30: 1200 | J30: 1500
A31: FY2030 f_ops | C31: =IF(($B$28-( $B$23+C30))<=0,NA(),($B$5*$B$26*($B$24+$B$25))/($B$6*($B$28-( $B$23+C30)))) -> 0.28150813 | D31: =IF(($B$28-( $B$23+D30))<=0,NA(),($B$5*$B$26*($B$24+$B$25))/($B$6*($B$28-( $B$23+D30)))) -> 0.29385903 | E31: =IF(($B$28-( $B$23+E30))<=0,NA(),($B$5*$B$26*($B$24+$B$25))/($B$6*($B$28-( $B$23+E30)))) -> 0.30734343 | F31: =IF(($B$28-( $B$23+F30))<=0,NA(),($B$5*$B$26*($B$24+$B$25))/($B$6*($B$28-( $B$23+F30)))) -> 0.33839995 | G31: =IF(($B$28-( $B$23+G30))<=0,NA(),($B$5*$B$26*($B$24+$B$25))/($B$6*($B$28-( $B$23+G30)))) -> 0.3764384 | H31: =IF(($B$28-( $B$23+H30))<=0,NA(),($B$5*$B$26*($B$24+$B$25))/($B$6*($B$28-( $B$23+H30)))) -> 0.42411139 | I31: =IF(($B$28-( $B$23+I30))<=0,NA(),($B$5*$B$26*($B$24+$B$25))/($B$6*($B$28-( $B$23+I30)))) -> 0.48561014 | J31: =IF(($B$28-( $B$23+J30))<=0,NA(),($B$5*$B$26*($B$24+$B$25))/($B$6*($B$28-( $B$23+J30)))) -> 0.62059532
A32: FY2030 f_lease | C32: =IF(($B$28-( $B$23+C30))<=0,NA(),($B$5*$B$27*($B$24+$B$25))/($B$6*($B$28-( $B$23+C30)))) -> 0 | D32: =IF(($B$28-( $B$23+D30))<=0,NA(),($B$5*$B$27*($B$24+$B$25))/($B$6*($B$28-( $B$23+D30)))) -> 0 | E32: =IF(($B$28-( $B$23+E30))<=0,NA(),($B$5*$B$27*($B$24+$B$25))/($B$6*($B$28-( $B$23+E30)))) -> 0 | F32: =IF(($B$28-( $B$23+F30))<=0,NA(),($B$5*$B$27*($B$24+$B$25))/($B$6*($B$28-( $B$23+F30)))) -> 0 | G32: =IF(($B$28-( $B$23+G30))<=0,NA(),($B$5*$B$27*($B$24+$B$25))/($B$6*($B$28-( $B$23+G30)))) -> 0 | H32: =IF(($B$28-( $B$23+H30))<=0,NA(),($B$5*$B$27*($B$24+$B$25))/($B$6*($B$28-( $B$23+H30)))) -> 0 | I32: =IF(($B$28-( $B$23+I30))<=0,NA(),($B$5*$B$27*($B$24+$B$25))/($B$6*($B$28-( $B$23+I30)))) -> 0 | J32: =IF(($B$28-( $B$23+J30))<=0,NA(),($B$5*$B$27*($B$24+$B$25))/($B$6*($B$28-( $B$23+J30)))) -> 0
