Workbook
Name ADM_Day_Select: Parameters_Public!C8
Name Aid_growth: BaselineCalc!B28
Name Base_Aid_per_ADM: Parameters_Public!C18
Name BaseAid_per_ADM: Parameters_Public!C18
Name Capex_ArtsHub: Parameters_Public!C28
Name Capex_in_MO_Toggle: Parameters_Public!C30
Name Capex_InnovHub: Parameters_Public!C29
Name Echo_ADM0: Parameters_Public!C10
Name Echo_ADM0_selected: Parameters_Public!C10
Name Echo_retention_r: Parameters_Public!C23
Name EchoFixed_FY25_Total: Site_Fixed!C8
Name f_lease_profile: Control_Center!$D$23:$H$23
Name f_ops_profile: Control_Center!$D$22:$H$22
Name Growth_overhead_alpha: Parameters_Public!C47
Name h_taper_profile: Control_Center!$C$22:$G$26
Name Incremental_uplift_alpha: Parameters_Public!C49
Name M_O_per_ADM_Audited: Parameters_Public!C14
Name MarginalFactor_for_Overlay: Parameters_Public!C43
Name MO_inflation: Control_Center!C6
Name Override_per_ADM_proxy: Parameters_Public!C19
Name Override_percent: Parameters_Public!C17
Name Override_toggle: Parameters_Public!C20
Name Pima_ADM0: Parameters_Public!C11
Name Pima_ADM0_selected: Parameters_Public!C11
Name Pima_retention_r: Parameters_Public!C24
Name PimaFixed_FY25_Total: Site_Fixed!C15
Name Portable_seat_cost: Parameters_Public!C34
Name TI_in_MO_Toggle: Parameters_Public!C26
Name TI_per_Site: Parameters_Public!C27
Name Uplift_base_per_ADM: Parameters_Public!C21

Sheet Workbook_Purpose_Overview

Sheet How_To_Use_The_Workbook
B1: How to use the workbook
B2: Start on Scenario_Comparison: choose two scenarios to compare; review the operational, capital, and student-related results.
B3: Test assumptions (override switch, retention r, trend flags) only if you would like to check sensitivity.
B4: Check capacity gates (receiving bands).
B5: Open Budget_Neutral_Calculator if you’re considering a non‑repurpose plan: it shows N⁰—how many students are needed to be Net ≥ 0.
B6: Look at Summary_Figures to scan all scenarios with the same signals.
B7: Use Inputs_Definitions_Sources for terms, references, and what’s still awaiting audited paste.
B8: Check What_Is_$900K_Savings if you are curious xxxxxx

Sheet Dashboard
B1: Go-forward scenario summary view* | C1: *SUSD-sourced data used wherever possible. Sources and assumptions are noted in Inputs_Definitions_Sources
B2: Choose view >> | C2: 2026
B4: ="FY"&IF(C2=2026, "26", IF(C2=2030, "30", "Average 2026-2030"))&" simulated P&L and capital spend by scenario" -> FY26 simulated P&L and capital spend by scenario | C4: A2 | D4: B2 | E4: C2 | F4: D1 | G4: E1
C5: Scenario A (Repurpose Both Lease) | D5: Scenario B (Repurpose Echo Lease; Grow Pima) | E5: Scenario C (Repurpose Pima Lease; Grow Echo) | F5: Scenario D (Grow Both) | G5: Scenario E (Continued Decline) | H5: Source / Confidence Level | I5: Model sensitivity | J5: Note
B6: Baseline ADM Echo | C6: =Parameters_Public!$C$10 -> 257 | D6: =Parameters_Public!$C$10 -> 257 | E6: =Parameters_Public!$C$10 -> 257 | F6: =Parameters_Public!$C$10 -> 257 | G6: =Parameters_Public!$C$10 -> 257 | H6: ***
B7: Baseline ADM Pima | C7: =Parameters_Public!$C$11 -> 296 | D7: =Parameters_Public!$C$11 -> 296 | E7: =Parameters_Public!$C$11 -> 296 | F7: =Parameters_Public!$C$11 -> 296 | G7: =Parameters_Public!$C$11 -> 296
B8: ADM change FY26 | C8: 0 | D8: =MultiYear_ProForma!$AB$42 -> 16.666667 | E8: =MultiYear_ProForma!$AB$52 -> 17 | F8: =MultiYear_ProForma!$AB$17 -> 50 | G8: 0
B9: Echo retention ratio | C9: =Parameters_Public!$C$23 -> 0.6 | D9: =Parameters_Public!$C$23 -> 0.6 | E9: ="N/A" -> N/A | F9: ="N/A" -> N/A | G9: ="N/A" -> N/A | H9: *
B10: Pima retention ratio | C10: =Parameters_Public!$C$24 -> 0.85 | D10: ="N/A" -> N/A | E10: =Parameters_Public!$C$24 -> 0.85 | F10: ="N/A" -> N/A | G10: ="N/A" -> N/A | H10: **
B11: Number of students transitioning | C11: =MultiYear_ProForma!$O$32 -> 405.8 | D11: =MultiYear_ProForma!$O$42 -> 154.2 | E11: =MultiYear_ProForma!$O$52 -> 251.31667 | F11: ="N/A" -> N/A | G11: ="N/A" -> N/A
B12: Students served FY26 | C12: =C11+C8 -> 405.8 | D12: =D7+D11+D8 -> 466.86667 | E12: =E11+E6+E8 -> 525.31667 | F12: =F8+F7+F6 -> 603 | G12: =G7+G6+G8 -> 553
B13: Per‑served revenue ($/ADM) | C13: =MultiYear_ProForma!$AD$32/Dashboard!C12 -> 10964.95 | D13: =MultiYear_ProForma!$AD$42/Dashboard!D12 -> 10937.105 | E13: =MultiYear_ProForma!$AD$52/Dashboard!E12 -> 10939.708 | F13: =MultiYear_ProForma!$AD$17/Dashboard!F12 -> 10900.273 | G13: =MultiYear_ProForma!$AD$62/Dashboard!G12 -> 10964.95 | J13: Base+override; to be conservative, small adjustment down for new students
B14: Total 'revenue' | C14: =C13*C12 -> 4449576.7 | D14: =D13*D12 -> 5106169.7 | E14: =E13*E12 -> 5746811 | F14: =F13*F12 -> 6572864.9 | G14: =G13*G12 -> 6063617.3
B15: Districtwide gross Maint & Operations cost per non-new ADM | C15: =Parameters_Public!$C$14 -> 11589 | D15: =Parameters_Public!$C$14 -> 11589 | E15: =Parameters_Public!$C$14 -> 11589 | F15: =Parameters_Public!$C$14 -> 11589 | G15: =Parameters_Public!$C$14 -> 11589 | J15: Maintenance & Operations referred to as "M&O"
B16: Variable cost / non-new ADM | C16: =BaselineCalc!$B$18*(IF(ROUNDUP(IF(C9="N/A", 0, C9)+IF(C10="N/A", 0, C10), 0)=2, 1,IF(ROUNDUP(IF(C9="N/A", 0, C9)+IF(C10="N/A", 0, C10), 0)=1,(1-BaselineCalc!$B$5/2),(1-BaselineCalc!$B$5)))) -> 8403.3633 | D16: =BaselineCalc!$B$18*(IF(ROUNDUP(IF(D9="N/A", 0, D9)+IF(D10="N/A", 0, D10), 0)=2, 1,IF(ROUNDUP(IF(D9="N/A", 0, D9)+IF(D10="N/A", 0, D10), 0)=1,(1-BaselineCalc!$B$5*(D7/(D7+D11))),(1-BaselineCalc!$B$5)))) -> 8364.6877 | E16: =BaselineCalc!$B$18*(IF(ROUNDUP(IF(E9="N/A", 0, E9)+IF(E10="N/A", 0, E10), 0)=2, 1,IF(ROUNDUP(IF(E9="N/A", 0, E9)+IF(E10="N/A", 0, E10), 0)=1,(1-BaselineCalc!$B$5*(E6/(E6+E11))),(1-BaselineCalc!$B$5)))) -> 8373.6227 | F16: =BaselineCalc!$B$18*(IF(ROUNDUP(IF(F9="N/A", 0, F9)+IF(F10="N/A", 0, F10), 0)=2, 1,IF(ROUNDUP(IF(F9="N/A", 0, F9)+IF(F10="N/A", 0, F10), 0)=1,(1-BaselineCalc!$B$5/2),(1-BaselineCalc!$B$5)))) -> 8344.5398 | G16: =BaselineCalc!$B$18*(IF(ROUNDUP(IF(G9="N/A", 0, G9)+IF(G10="N/A", 0, G10), 0)=2, 1,IF(ROUNDUP(IF(G9="N/A", 0, G9)+IF(G10="N/A", 0, G10), 0)=1,(1-BaselineCalc!$B$5/2),(1-BaselineCalc!$B$5)))) -> 8344.5398
B17: Non-new students | C17: =MAX(C12 - C8, 0) -> 405.8 | D17: =MAX(D12 - D8, 0) -> 450.2 | E17: =MAX(E12 - E8, 0) -> 508.31667 | F17: =MAX(F12 - F8, 0) -> 553 | G17: =MAX(G12 - G8, 0) -> 553
B18: Total variable gross cost of non-new students | C18: =C17*C16 -> 3410084.8 | D18: =D17*D16 -> 3765782.4 | E18: =E17*E16 -> 4256452 | F18: =F17*F16 -> 4614530.5 | G18: =G17*G16 -> 4614530.5 | J18: After discounting estimated fixed, adjusting for inflation
B19: New students | C19: =C8 -> 0 | D19: =D8 -> 16.666667 | E19: =E8 -> 17 | F19: =F8 -> 50 | G19: =G8 -> 0
B20: Marginal variable cost to add new students | C20: =Parameters_Public!$C$43 -> 0.6 | D20: =Parameters_Public!$C$43 -> 0.6 | E20: =Parameters_Public!$C$43 -> 0.6 | F20: =Parameters_Public!$C$43 -> 0.6 | G20: =Parameters_Public!$C$43 -> 0.6 | H20: ** | J20: Estimated proportion of full cost
B21: Variable gross M&O / new student | C21: =IFERROR((C16*C20), "N/A") -> 5042.018 | D21: =IFERROR((D16*D20), "N/A") -> 5018.8126 | E21: =IFERROR((E16*E20), "N/A") -> 5024.1736 | F21: =IFERROR((F16*F20), "N/A") -> 5006.7239 | G21: =IFERROR((G16*G20), "N/A") -> 5006.7239 | J21: M&O = Maintenance & Operations cost
B22: Incremental overhead per new student | C22: ="$"&YearMap!$E$2*Parameters_Public!$C$47&"/student" -> $200/student | D22: ="$"&YearMap!$E$2*Parameters_Public!$C$47&"/student" -> $200/student | E22: ="$"&YearMap!$E$2*Parameters_Public!$C$47&"/student" -> $200/student | F22: ="$"&YearMap!$E$2*Parameters_Public!$C$47&"/student" -> $200/student | G22: ="$"&YearMap!$E$2*Parameters_Public!$C$47&"/student" -> $200/student | J22: Estimted in model as proportion of repurpose transition cost
B23: Variable gross M&O + growth overhead / new student | C23: =BaselineCalc!$B$18 * (1 - BaselineCalc!$B$5) * Parameters_Public!$C$43 + YearMap!$Q$2 -> 5206.7239 | D23: =BaselineCalc!$B$18 * (1 - BaselineCalc!$B$5) * Parameters_Public!$C$43 + YearMap!$Q$2 -> 5206.7239 | E23: =BaselineCalc!$B$18 * (1 - BaselineCalc!$B$5) * Parameters_Public!$C$43 + YearMap!$Q$2 -> 5206.7239 | F23: =BaselineCalc!$B$18 * (1 - BaselineCalc!$B$5) * Parameters_Public!$C$43 + YearMap!$Q$2 -> 5206.7239 | G23: =BaselineCalc!$B$18 * (1 - BaselineCalc!$B$5) * Parameters_Public!$C$43 + YearMap!$Q$2 -> 5206.7239
B24: Total variable gross cost of new students | C24: =IF(C23*C8=0, "N/A", C23*C8) -> N/A | D24: =IF(D23*D8=0, "N/A", D23*D8) -> 86778.731 | E24: =IF(E23*E8=0, "N/A", E23*E8) -> 88514.306 | F24: =IF(F23*F8=0, "N/A", F23*F8) -> 260336.19 | G24: =IF(G23*G8=0, "N/A", G23*G8) -> N/A
B25: Total variable gross M&O cost | C25: =IF(C24="N/A", 0, C24)+C18 -> 3410084.8 | D25: =IF(D24="N/A", 0, D24)+D18 -> 3852561.1 | E25: =IF(E24="N/A", 0, E24)+E18 -> 4344966.3 | F25: =IF(F24="N/A", 0, F24)+F18 -> 4874866.7 | G25: =IF(G24="N/A", 0, G24)+G18 -> 4614530.5
B26: Transition cost (routing, transportation, etc.) FY26 | C26: ="$"&YearMap!$E$2&"/student" -> $1000/student | D26: ="$"&YearMap!$E$2&"/student" -> $1000/student | E26: ="$"&YearMap!$E$2&"/student" -> $1000/student | F26: ="N/A" -> N/A | G26: ="N/A" -> N/A | H26: ** | J26: Assuming adjustments in routing or other transportation investment needed for students displaced from repurpose; tapers over time
B27: Total transition cost FY26 | C27: =YearMap!$E$2*C11 -> 405800 | D27: =YearMap!$E$2*D11 -> 154200 | E27: =YearMap!$E$2*E11 -> 251316.67 | F27: ="N/A" -> N/A | G27: ="N/A" -> N/A
B28: Total gross M&O + transition cost | C28: =C25+IF(C27="N/A", 0, C27) -> 3815884.8 | D28: =D25+IF(D27="N/A", 0, D27) -> 4006761.1 | E28: =E25+IF(E27="N/A", 0, E27) -> 4596283 | F28: =F25+IF(F27="N/A", 0, F27) -> 4874866.7 | G28: =G25+IF(G27="N/A", 0, G27) -> 4614530.5
B29: Base open site fixed total | C29: =BaselineCalc!$B$19+BaselineCalc!$B$20 -> 1921875 | D29: =BaselineCalc!$B$20 -> 999375 | E29: =BaselineCalc!$B$19 -> 922500 | F29: =BaselineCalc!$B$19+BaselineCalc!$B$20 -> 1921875 | G29: =BaselineCalc!$B$19+BaselineCalc!$B$20 -> 1921875 | H29: *
B30: Estimated repurpose site fixed cost carry ratio | C30: =YearMap!$F$2 -> 0.2 | D30: =YearMap!$F$2 -> 0.2 | E30: =YearMap!$F$2 -> 0.2 | F30: ="N/A" -> N/A | G30: ="N/A" -> N/A | H30: **
B31: Net fixed cost total | C31: =IFERROR(C29*(C30), C29)*(1-BaselineCalc!$B$5) -> 381684.38 | D31: =(BaselineCalc!$B$20+IFERROR(BaselineCalc!$B$19*(D30), BaselineCalc!$B$19))*(1-BaselineCalc!$B$5) -> 1175587.9 | E31: =(BaselineCalc!$B$19+IFERROR(BaselineCalc!$B$20*(D30), BaselineCalc!$B$20))*(1-BaselineCalc!$B$5) -> 1114518.4 | F31: =IFERROR(F29*(F30), F29)*(1-BaselineCalc!$B$5) -> 1908421.9 | G31: =IFERROR(G29*(G30), G29)*(1-BaselineCalc!$B$5) -> 1908421.9
B32: Net total cost | C32: =C31+C28 -> 4197569.2 | D32: =D31+D28 -> 5182349 | E32: =E31+E28 -> 5710801.3 | F32: =F31+F28 -> 6783288.6 | G32: =G31+G28 -> 6522952.4
B33: Net operating $ FY26 | C33: =C14-C32 -> 252007.49 | D33: =D14-D32 -> -76179.355 | E33: =E14-E32 -> 36009.647 | F33: =F14-F32 -> -210423.72 | G33: =G14-G32 -> -459335.03
B36: FY26 Capital investment | C36: =Capital_Summary!$B$77 -> 2314480 | D36: =Capital_Summary!$B$79 -> 1600000 | E36: =Capital_Summary!B81 -> 1600000 | F36: =Capital_Summary!B74 -> 2000000 | G36: =Capital_Summary!B83 -> 0
B41: (Check-MultiYear_Proforma) Net operating $ / year FY26 | C41: =MultiYear_ProForma!$AF$32 -> 252007.49 | D41: =MultiYear_ProForma!$AF$42 -> -76179.355 | E41: =MultiYear_ProForma!$AF$52 -> 36009.647 | F41: =MultiYear_ProForma!$AF$17 -> -210423.72 | G41: =MultiYear_ProForma!$AF$62 -> -459335.03
B42: Difference in MYP net vs. Dashboard net | C42: =C41-C33 -> 0 | D42: =D41-D33 -> 9.3132257e-10 | E42: =E41-E33 -> 0 | F42: =F41-F33 -> -9.3132257e-10 | G42: =G41-G33 -> 0
B43: % difference in MYP net vs. Dashboard net | C43: =C42/C41 -> 0 | D43: =D42/D41 -> -1.2225393e-14 | E43: =E42/E41 -> 0 | F43: =F42/F41 -> 4.425939e-15 | G43: =G42/G41 -> 0
B65: FY2026 | C65: A2 | D65: B2 | E65: C2 | F65: D1 | G65: E1
C66: Scenario A (Repurpose Both Lease) | D66: Scenario B (Repurpose Echo Lease; Grow Pima) | E66: Scenario C (Repurpose Pima Lease; Grow Echo) | F66: Scenario D (Grow Both) | G66: Scenario E (Continued Decline) | H66: Source / Confidence Level | I66: Model sensitivity | J66: Note
B67: Baseline ADM Echo | C67: =Parameters_Public!$C$10 -> 257 | D67: =Parameters_Public!$C$10 -> 257 | E67: =Parameters_Public!$C$10 -> 257 | F67: =Parameters_Public!$C$10 -> 257 | G67: =Parameters_Public!$C$10 -> 257 | H67: ***
B68: Baseline ADM Pima | C68: =Parameters_Public!$C$11 -> 296 | D68: =Parameters_Public!$C$11 -> 296 | E68: =Parameters_Public!$C$11 -> 296 | F68: =Parameters_Public!$C$11 -> 296 | G68: =Parameters_Public!$C$11 -> 296
B69: ADM change FY26 | C69: 0 | D69: =MultiYear_ProForma!$AB$42 -> 16.666667 | E69: =MultiYear_ProForma!$AB$52 -> 17 | F69: =MultiYear_ProForma!$AB$17 -> 50 | G69: 0
B70: Echo retention ratio | C70: =Parameters_Public!$C$23 -> 0.6 | D70: =Parameters_Public!$C$23 -> 0.6 | E70: ="N/A" -> N/A | F70: ="N/A" -> N/A | G70: ="N/A" -> N/A | H70: *
B71: Pima retention ratio | C71: =Parameters_Public!$C$24 -> 0.85 | D71: ="N/A" -> N/A | E71: =Parameters_Public!$C$24 -> 0.85 | F71: ="N/A" -> N/A | G71: ="N/A" -> N/A | H71: **
B72: Number of students transitioning | C72: =MultiYear_ProForma!$O$32 -> 405.8 | D72: =MultiYear_ProForma!$O$42 -> 154.2 | E72: =MultiYear_ProForma!$O$52 -> 251.31667 | F72: ="N/A" -> N/A | G72: ="N/A" -> N/A
B73: Students served FY26 | C73: =C72+C69 -> 405.8 | D73: =D68+D72+D69 -> 466.86667 | E73: =E72+E67+E69 -> 525.31667 | F73: =F69+F68+F67 -> 603 | G73: =G68+G67+G69 -> 553
B74: Per‑served revenue ($/ADM) | C74: =MultiYear_ProForma!$AD$32/Dashboard!C73 -> 10964.95 | D74: =MultiYear_ProForma!$AD$42/Dashboard!D73 -> 10937.105 | E74: =MultiYear_ProForma!$AD$52/Dashboard!E73 -> 10939.708 | F74: =MultiYear_ProForma!$AD$17/Dashboard!F73 -> 10900.273 | G74: =MultiYear_ProForma!$AD$62/Dashboard!G73 -> 10964.95 | J74: Base+override; to be conservative, small adjustment down for new students
B75: Total 'revenue' | C75: =C74*C73 -> 4449576.7 | D75: =D74*D73 -> 5106169.7 | E75: =E74*E73 -> 5746811 | F75: =F74*F73 -> 6572864.9 | G75: =G74*G73 -> 6063617.3
B76: Districtwide gross Maint & Operations cost per non-new ADM | C76: =Parameters_Public!$C$14 -> 11589 | D76: =Parameters_Public!$C$14 -> 11589 | E76: =Parameters_Public!$C$14 -> 11589 | F76: =Parameters_Public!$C$14 -> 11589 | G76: =Parameters_Public!$C$14 -> 11589 | J76: Maintenance & Operations referred to as "M&O"
B77: Variable cost / non-new ADM | C77: =BaselineCalc!$B$18*(IF(ROUNDUP(IF(C70="N/A", 0, C70)+IF(C71="N/A", 0, C71), 0)=2, 1,IF(ROUNDUP(IF(C70="N/A", 0, C70)+IF(C71="N/A", 0, C71), 0)=1,(1-BaselineCalc!$B$5/2),(1-BaselineCalc!$B$5)))) -> 8403.3633 | D77: =BaselineCalc!$B$18*(IF(ROUNDUP(IF(D70="N/A", 0, D70)+IF(D71="N/A", 0, D71), 0)=2, 1,IF(ROUNDUP(IF(D70="N/A", 0, D70)+IF(D71="N/A", 0, D71), 0)=1,(1-BaselineCalc!$B$5*(D68/(D68+D72))),(1-BaselineCalc!$B$5)))) -> 8364.6877 | E77: =BaselineCalc!$B$18*(IF(ROUNDUP(IF(E70="N/A", 0, E70)+IF(E71="N/A", 0, E71), 0)=2, 1,IF(ROUNDUP(IF(E70="N/A", 0, E70)+IF(E71="N/A", 0, E71), 0)=1,(1-BaselineCalc!$B$5*(E67/(E67+E72))),(1-BaselineCalc!$B$5)))) -> 8373.6227 | F77: =BaselineCalc!$B$18*(IF(ROUNDUP(IF(F70="N/A", 0, F70)+IF(F71="N/A", 0, F71), 0)=2, 1,IF(ROUNDUP(IF(F70="N/A", 0, F70)+IF(F71="N/A", 0, F71), 0)=1,(1-BaselineCalc!$B$5/2),(1-BaselineCalc!$B$5)))) -> 8344.5398 | G77: =BaselineCalc!$B$18*(IF(ROUNDUP(IF(G70="N/A", 0, G70)+IF(G71="N/A", 0, G71), 0)=2, 1,IF(ROUNDUP(IF(G70="N/A", 0, G70)+IF(G71="N/A", 0, G71), 0)=1,(1-BaselineCalc!$B$5/2),(1-BaselineCalc!$B$5)))) -> 8344.5398
B78: Non-new students | C78: =MAX(C73 - C69, 0) -> 405.8 | D78: =MAX(D73 - D69, 0) -> 450.2 | E78: =MAX(E73 - E69, 0) -> 508.31667 | F78: =MAX(F73 - F69, 0) -> 553 | G78: =MAX(G73 - G69, 0) -> 553
B79: Total variable gross cost of non-new students | C79: =C78*C77 -> 3410084.8 | D79: =D78*D77 -> 3765782.4 | E79: =E78*E77 -> 4256452 | F79: =F78*F77 -> 4614530.5 | G79: =G78*G77 -> 4614530.5 | J79: After discounting estimated fixed, adjusting for inflation
B80: New students | C80: =C69 -> 0 | D80: =D69 -> 16.666667 | E80: =E69 -> 17 | F80: =F69 -> 50 | G80: =G69 -> 0
B81: Marginal variable cost to add new students | C81: =Parameters_Public!$C$43 -> 0.6 | D81: =Parameters_Public!$C$43 -> 0.6 | E81: =Parameters_Public!$C$43 -> 0.6 | F81: =Parameters_Public!$C$43 -> 0.6 | G81: =Parameters_Public!$C$43 -> 0.6 | H81: ** | J81: Estimated proportion of full cost
B82: Variable gross M&O / new student | C82: =IFERROR((C77*C81), "N/A") -> 5042.018 | D82: =IFERROR((D77*D81), "N/A") -> 5018.8126 | E82: =IFERROR((E77*E81), "N/A") -> 5024.1736 | F82: =IFERROR((F77*F81), "N/A") -> 5006.7239 | G82: =IFERROR((G77*G81), "N/A") -> 5006.7239 | J82: M&O = Maintenance & Operations cost
B83: Incremental overhead per new student | C83: ="$"&YearMap!$E$2*Parameters_Public!$C$47&"/student" -> $200/student | D83: ="$"&YearMap!$E$2*Parameters_Public!$C$47&"/student" -> $200/student | E83: ="$"&YearMap!$E$2*Parameters_Public!$C$47&"/student" -> $200/student | F83: ="$"&YearMap!$E$2*Parameters_Public!$C$47&"/student" -> $200/student | G83: ="$"&YearMap!$E$2*Parameters_Public!$C$47&"/student" -> $200/student | J83: Estimted in model as proportion of repurpose transition cost
B84: Variable gross M&O + growth overhead / new student | C84: =BaselineCalc!$B$18 * (1 - BaselineCalc!$B$5) * Parameters_Public!$C$43 + YearMap!$Q$2 -> 5206.7239 | D84: =BaselineCalc!$B$18 * (1 - BaselineCalc!$B$5) * Parameters_Public!$C$43 + YearMap!$Q$2 -> 5206.7239 | E84: =BaselineCalc!$B$18 * (1 - BaselineCalc!$B$5) * Parameters_Public!$C$43 + YearMap!$Q$2 -> 5206.7239 | F84: =BaselineCalc!$B$18 * (1 - BaselineCalc!$B$5) * Parameters_Public!$C$43 + YearMap!$Q$2 -> 5206.7239 | G84: =BaselineCalc!$B$18 * (1 - BaselineCalc!$B$5) * Parameters_Public!$C$43 + YearMap!$Q$2 -> 5206.7239
B85: Total variable gross cost of new students | C85: =IF(C84*C69=0, "N/A", C84*C69) -> N/A | D85: =IF(D84*D69=0, "N/A", D84*D69) -> 86778.731 | E85: =IF(E84*E69=0, "N/A", E84*E69) -> 88514.306 | F85: =IF(F84*F69=0, "N/A", F84*F69) -> 260336.19 | G85: =IF(G84*G69=0, "N/A", G84*G69) -> N/A
B86: Total variable gross M&O cost | C86: =IF(C85="N/A", 0, C85)+C79 -> 3410084.8 | D86: =IF(D85="N/A", 0, D85)+D79 -> 3852561.1 | E86: =IF(E85="N/A", 0, E85)+E79 -> 4344966.3 | F86: =IF(F85="N/A", 0, F85)+F79 -> 4874866.7 | G86: =IF(G85="N/A", 0, G85)+G79 -> 4614530.5
B87: Transition cost (routing, transportation, etc.) FY26 | C87: ="$"&YearMap!$E$2&"/student" -> $1000/student | D87: ="$"&YearMap!$E$2&"/student" -> $1000/student | E87: ="$"&YearMap!$E$2&"/student" -> $1000/student | F87: ="N/A" -> N/A | G87: ="N/A" -> N/A | H87: ** | J87: Assuming adjustments in routing or other transportation investment needed for students displaced from repurpose; tapers over time
B88: Total transition cost FY26 | C88: =YearMap!$E$2*C72 -> 405800 | D88: =YearMap!$E$2*D72 -> 154200 | E88: =YearMap!$E$2*E72 -> 251316.67 | F88: ="N/A" -> N/A | G88: ="N/A" -> N/A
B89: Total gross M&O + transition cost | C89: =C86+IF(C88="N/A", 0, C88) -> 3815884.8 | D89: =D86+IF(D88="N/A", 0, D88) -> 4006761.1 | E89: =E86+IF(E88="N/A", 0, E88) -> 4596283 | F89: =F86+IF(F88="N/A", 0, F88) -> 4874866.7 | G89: =G86+IF(G88="N/A", 0, G88) -> 4614530.5
B90: Base open site fixed total | C90: =BaselineCalc!$B$19+BaselineCalc!$B$20 -> 1921875 | D90: =BaselineCalc!$B$20 -> 999375 | E90: =BaselineCalc!$B$19 -> 922500 | F90: =BaselineCalc!$B$19+BaselineCalc!$B$20 -> 1921875 | G90: =BaselineCalc!$B$19+BaselineCalc!$B$20 -> 1921875 | H90: *
B91: Estimated repurpose site fixed cost carry ratio | C91: =YearMap!$F$2 -> 0.2 | D91: =YearMap!$F$2 -> 0.2 | E91: =YearMap!$F$2 -> 0.2 | F91: ="N/A" -> N/A | G91: ="N/A" -> N/A | H91: **
B92: Net fixed cost total | C92: =IFERROR(C90*(C91), C90)*(1-BaselineCalc!$B$5) -> 381684.38 | D92: =(BaselineCalc!$B$20+IFERROR(BaselineCalc!$B$19*(D91), BaselineCalc!$B$19))*(1-BaselineCalc!$B$5) -> 1175587.9 | E92: =(BaselineCalc!$B$19+IFERROR(BaselineCalc!$B$20*(D91), BaselineCalc!$B$20))*(1-BaselineCalc!$B$5) -> 1114518.4 | F92: =IFERROR(F90*(F91), F90)*(1-BaselineCalc!$B$5) -> 1908421.9 | G92: =IFERROR(G90*(G91), G90)*(1-BaselineCalc!$B$5) -> 1908421.9
B93: Net total cost | C93: =C92+C89 -> 4197569.2 | D93: =D92+D89 -> 5182349 | E93: =E92+E89 -> 5710801.3 | F93: =F92+F89 -> 6783288.6 | G93: =G92+G89 -> 6522952.4
B94: Net operating $ FY26 | C94: =C75-C93 -> 252007.49 | D94: =D75-D93 -> -76179.355 | E94: =E75-E93 -> 36009.647 | F94: =F75-F93 -> -210423.72 | G94: =G75-G93 -> -459335.03
B97: Capital investment $ FY26 | C97: =Capital_Summary!$B$77 -> 2314480 | D97: =Capital_Summary!$B$79 -> 1600000 | E97: =Capital_Summary!B142 -> 0 | F97: =Capital_Summary!B135 -> 0 | G97: =Capital_Summary!B144 -> 0
B101: FY2030 | C101: A2 | D101: B2 | E101: C2 | F101: D1 | G101: E1
C102: Scenario A (Repurpose Both Lease) | D102: Scenario B (Repurpose Echo Lease; Grow Pima) | E102: Scenario C (Repurpose Pima Lease; Grow Echo) | F102: Scenario D (Grow Both) | G102: Scenario E (Continued Decline) | H102: Source / Confidence Level | I102: Model sensitivity | J102: Note
B103: Baseline ADM Echo | C103: =Parameters_Public!$C$10 -> 257 | D103: =Parameters_Public!$C$10 -> 257 | E103: =Parameters_Public!$C$10 -> 257 | F103: =Parameters_Public!$C$10 -> 257 | G103: =Parameters_Public!$C$10 -> 257 | H103: ***
B104: Baseline ADM Pima | C104: =Parameters_Public!$C$11 -> 296 | D104: =Parameters_Public!$C$11 -> 296 | E104: =Parameters_Public!$C$11 -> 296 | F104: =Parameters_Public!$C$11 -> 296 | G104: =Parameters_Public!$C$11 -> 296
B105: ADM change FY30 | C105: 0 | D105: =MultiYear_ProForma!$AB$42 -> 16.666667 | E105: =MultiYear_ProForma!$AB$52 -> 17 | F105: =MultiYear_ProForma!$AB$17 -> 50 | G105: 0
B106: Echo retention ratio | C106: =Parameters_Public!$C$23 -> 0.6 | D106: =Parameters_Public!$C$23 -> 0.6 | E106: ="N/A" -> N/A | F106: ="N/A" -> N/A | G106: ="N/A" -> N/A | H106: *
B107: Pima retention ratio | C107: =Parameters_Public!$C$24 -> 0.85 | D107: ="N/A" -> N/A | E107: =Parameters_Public!$C$24 -> 0.85 | F107: ="N/A" -> N/A | G107: ="N/A" -> N/A | H107: **
B108: Number of students transitioning | C108: =MultiYear_ProForma!$O$32 -> 405.8 | D108: =MultiYear_ProForma!$O$42 -> 154.2 | E108: =MultiYear_ProForma!$O$52 -> 251.31667 | F108: ="N/A" -> N/A | G108: ="N/A" -> N/A
B109: Students served FY30 | C109: =C108+C105 -> 405.8 | D109: =D104+D108+D105 -> 466.86667 | E109: =E108+E103+E105 -> 525.31667 | F109: =F105+F104+F103 -> 603 | G109: =G104+G103+G105 -> 553
B110: Per‑served revenue ($/ADM) | C110: =MultiYear_ProForma!$AD$32/Dashboard!C109 -> 10964.95 | D110: =MultiYear_ProForma!$AD$42/Dashboard!D109 -> 10937.105 | E110: =MultiYear_ProForma!$AD$52/Dashboard!E109 -> 10939.708 | F110: =MultiYear_ProForma!$AD$17/Dashboard!F109 -> 10900.273 | G110: =MultiYear_ProForma!$AD$62/Dashboard!G109 -> 10964.95 | J110: Base+override; to be conservative, small adjustment down for new students
B111: Total 'revenue' | C111: =C110*C109 -> 4449576.7 | D111: =D110*D109 -> 5106169.7 | E111: =E110*E109 -> 5746811 | F111: =F110*F109 -> 6572864.9 | G111: =G110*G109 -> 6063617.3
B112: Districtwide gross Maint & Operations cost per non-new ADM | C112: =Parameters_Public!$C$14 -> 11589 | D112: =Parameters_Public!$C$14 -> 11589 | E112: =Parameters_Public!$C$14 -> 11589 | F112: =Parameters_Public!$C$14 -> 11589 | G112: =Parameters_Public!$C$14 -> 11589 | J112: Maintenance & Operations referred to as "M&O"
B113: Variable cost / non-new ADM | C113: =BaselineCalc!$B$18*(IF(ROUNDUP(IF(C106="N/A", 0, C106)+IF(C107="N/A", 0, C107), 0)=2, 1,IF(ROUNDUP(IF(C106="N/A", 0, C106)+IF(C107="N/A", 0, C107), 0)=1,(1-BaselineCalc!$B$5/2),(1-BaselineCalc!$B$5)))) -> 8403.3633 | D113: =BaselineCalc!$B$18*(IF(ROUNDUP(IF(D106="N/A", 0, D106)+IF(D107="N/A", 0, D107), 0)=2, 1,IF(ROUNDUP(IF(D106="N/A", 0, D106)+IF(D107="N/A", 0, D107), 0)=1,(1-BaselineCalc!$B$5*(D104/(D104+D108))),(1-BaselineCalc!$B$5)))) -> 8364.6877 | E113: =BaselineCalc!$B$18*(IF(ROUNDUP(IF(E106="N/A", 0, E106)+IF(E107="N/A", 0, E107), 0)=2, 1,IF(ROUNDUP(IF(E106="N/A", 0, E106)+IF(E107="N/A", 0, E107), 0)=1,(1-BaselineCalc!$B$5*(E103/(E103+E108))),(1-BaselineCalc!$B$5)))) -> 8373.6227 | F113: =BaselineCalc!$B$18*(IF(ROUNDUP(IF(F106="N/A", 0, F106)+IF(F107="N/A", 0, F107), 0)=2, 1,IF(ROUNDUP(IF(F106="N/A", 0, F106)+IF(F107="N/A", 0, F107), 0)=1,(1-BaselineCalc!$B$5/2),(1-BaselineCalc!$B$5)))) -> 8344.5398 | G113: =BaselineCalc!$B$18*(IF(ROUNDUP(IF(G106="N/A", 0, G106)+IF(G107="N/A", 0, G107), 0)=2, 1,IF(ROUNDUP(IF(G106="N/A", 0, G106)+IF(G107="N/A", 0, G107), 0)=1,(1-BaselineCalc!$B$5/2),(1-BaselineCalc!$B$5)))) -> 8344.5398
B114: Non-new students | C114: =MAX(C109 - C105, 0) -> 405.8 | D114: =MAX(D109 - D105, 0) -> 450.2 | E114: =MAX(E109 - E105, 0) -> 508.31667 | F114: =MAX(F109 - F105, 0) -> 553 | G114: =MAX(G109 - G105, 0) -> 553
B115: Total variable gross cost of non-new students | C115: =C114*C113 -> 3410084.8 | D115: =D114*D113 -> 3765782.4 | E115: =E114*E113 -> 4256452 | F115: =F114*F113 -> 4614530.5 | G115: =G114*G113 -> 4614530.5 | J115: After discounting estimated fixed, adjusting for inflation
B116: New students | C116: =C105 -> 0 | D116: =D105 -> 16.666667 | E116: =E105 -> 17 | F116: =F105 -> 50 | G116: =G105 -> 0
B117: Marginal variable cost to add new students | C117: =Parameters_Public!$C$43 -> 0.6 | D117: =Parameters_Public!$C$43 -> 0.6 | E117: =Parameters_Public!$C$43 -> 0.6 | F117: =Parameters_Public!$C$43 -> 0.6 | G117: =Parameters_Public!$C$43 -> 0.6 | H117: ** | J117: Estimated proportion of full cost
B118: Variable gross M&O / new student | C118: =IFERROR((C113*C117), "N/A") -> 5042.018 | D118: =IFERROR((D113*D117), "N/A") -> 5018.8126 | E118: =IFERROR((E113*E117), "N/A") -> 5024.1736 | F118: =IFERROR((F113*F117), "N/A") -> 5006.7239 | G118: =IFERROR((G113*G117), "N/A") -> 5006.7239 | J118: M&O = Maintenance & Operations cost
B119: Incremental overhead per new student | C119: ="$"&YearMap!$E$2*Parameters_Public!$C$47&"/student" -> $200/student | D119: ="$"&YearMap!$E$2*Parameters_Public!$C$47&"/student" -> $200/student | E119: ="$"&YearMap!$E$2*Parameters_Public!$C$47&"/student" -> $200/student | F119: ="$"&YearMap!$E$2*Parameters_Public!$C$47&"/student" -> $200/student | G119: ="$"&YearMap!$E$2*Parameters_Public!$C$47&"/student" -> $200/student | J119: Estimted in model as proportion of repurpose transition cost
B120: Variable gross M&O + growth overhead / new student | C120: =BaselineCalc!$B$18 * (1 - BaselineCalc!$B$5) * Parameters_Public!$C$43 + YearMap!$Q$2 -> 5206.7239 | D120: =BaselineCalc!$B$18 * (1 - BaselineCalc!$B$5) * Parameters_Public!$C$43 + YearMap!$Q$2 -> 5206.7239 | E120: =BaselineCalc!$B$18 * (1 - BaselineCalc!$B$5) * Parameters_Public!$C$43 + YearMap!$Q$2 -> 5206.7239 | F120: =BaselineCalc!$B$18 * (1 - BaselineCalc!$B$5) * Parameters_Public!$C$43 + YearMap!$Q$2 -> 5206.7239 | G120: =BaselineCalc!$B$18 * (1 - BaselineCalc!$B$5) * Parameters_Public!$C$43 + YearMap!$Q$2 -> 5206.7239
B121: Total variable gross cost of new students | C121: =IF(C120*C105=0, "N/A", C120*C105) -> N/A | D121: =IF(D120*D105=0, "N/A", D120*D105) -> 86778.731 | E121: =IF(E120*E105=0, "N/A", E120*E105) -> 88514.306 | F121: =IF(F120*F105=0, "N/A", F120*F105) -> 260336.19 | G121: =IF(G120*G105=0, "N/A", G120*G105) -> N/A
B122: Total variable gross M&O cost | C122: =IF(C121="N/A", 0, C121)+C115 -> 3410084.8 | D122: =IF(D121="N/A", 0, D121)+D115 -> 3852561.1 | E122: =IF(E121="N/A", 0, E121)+E115 -> 4344966.3 | F122: =IF(F121="N/A", 0, F121)+F115 -> 4874866.7 | G122: =IF(G121="N/A", 0, G121)+G115 -> 4614530.5
B123: Transition cost (routing, transportation, etc.) FY30 | C123: ="$"&YearMap!$E$2&"/student" -> $1000/student | D123: ="$"&YearMap!$E$2&"/student" -> $1000/student | E123: ="$"&YearMap!$E$2&"/student" -> $1000/student | F123: ="N/A" -> N/A | G123: ="N/A" -> N/A | H123: ** | J123: Assuming adjustments in routing or other transportation investment needed for students displaced from repurpose; tapers over time
B124: Total transition cost FY30 | C124: =YearMap!$E$2*C108 -> 405800 | D124: =YearMap!$E$2*D108 -> 154200 | E124: =YearMap!$E$2*E108 -> 251316.67 | F124: ="N/A" -> N/A | G124: ="N/A" -> N/A
B125: Total gross M&O + transition cost | C125: =C122+IF(C124="N/A", 0, C124) -> 3815884.8 | D125: =D122+IF(D124="N/A", 0, D124) -> 4006761.1 | E125: =E122+IF(E124="N/A", 0, E124) -> 4596283 | F125: =F122+IF(F124="N/A", 0, F124) -> 4874866.7 | G125: =G122+IF(G124="N/A", 0, G124) -> 4614530.5
B126: Base open site fixed total | C126: =BaselineCalc!$B$19+BaselineCalc!$B$20 -> 1921875 | D126: =BaselineCalc!$B$20 -> 999375 | E126: =BaselineCalc!$B$19 -> 922500 | F126: =BaselineCalc!$B$19+BaselineCalc!$B$20 -> 1921875 | G126: =BaselineCalc!$B$19+BaselineCalc!$B$20 -> 1921875 | H126: *
B127: Estimated repurpose site fixed cost carry ratio | C127: =YearMap!$F$2 -> 0.2 | D127: =YearMap!$F$2 -> 0.2 | E127: =YearMap!$F$2 -> 0.2 | F127: ="N/A" -> N/A | G127: ="N/A" -> N/A | H127: **
B128: Net fixed cost total | C128: =IFERROR(C126*(C127), C126)*(1-BaselineCalc!$B$5) -> 381684.38 | D128: =(BaselineCalc!$B$20+IFERROR(BaselineCalc!$B$19*(D127), BaselineCalc!$B$19))*(1-BaselineCalc!$B$5) -> 1175587.9 | E128: =(BaselineCalc!$B$19+IFERROR(BaselineCalc!$B$20*(D127), BaselineCalc!$B$20))*(1-BaselineCalc!$B$5) -> 1114518.4 | F128: =IFERROR(F126*(F127), F126)*(1-BaselineCalc!$B$5) -> 1908421.9 | G128: =IFERROR(G126*(G127), G126)*(1-BaselineCalc!$B$5) -> 1908421.9
B129: Net total cost | C129: =C128+C125 -> 4197569.2 | D129: =D128+D125 -> 5182349 | E129: =E128+E125 -> 5710801.3 | F129: =F128+F125 -> 6783288.6 | G129: =G128+G125 -> 6522952.4
B130: Net operating $ FY30 | C130: =C111-C129 -> 252007.49 | D130: =D111-D129 -> -76179.355 | E130: =E111-E129 -> 36009.647 | F130: =F111-F129 -> -210423.72 | G130: =G111-G129 -> -459335.03
B133: Capital investment $ FY30 | C133: =Capital_Summary!$B$77 -> 2314480 | D133: =Capital_Summary!$B$79 -> 1600000 | E133: =Capital_Summary!B178 -> 0 | F133: =Capital_Summary!B171 -> 0 | G133: =Capital_Summary!B180 -> 0

Sheet Working_test
B1: FY26 simulated P&L by scenario
C2: Scenario A2 (Repurpose Both Lease) | D2: Scenario D1 (Grow Both) | E2: Scenario E1 (Continued Decline) | F2: Scenario B2 (Repurpose Echo Lease; Grow Pima) | G2: Scenario C2 (Repurpose Pima Lease; Grow Echo) | H2: Source / Confidence Level
B3: Baseline ADM Echo | C3: =Parameters_Public!$C$10 -> 257 | D3: =Parameters_Public!$C$10 -> 257 | E3: =Parameters_Public!$C$10 -> 257 | F3: =Parameters_Public!$C$10 -> 257 | G3: =Parameters_Public!$C$10 -> 257 | H3: ***
B4: Baseline ADM Pima | C4: =Parameters_Public!$C$11 -> 296 | D4: =Parameters_Public!$C$11 -> 296 | E4: =Parameters_Public!$C$11 -> 296 | F4: =Parameters_Public!$C$11 -> 296 | G4: =Parameters_Public!$C$11 -> 296
B5: ADM change FY26 | C5: 0 | D5: =MultiYear_ProForma!$AB$17 -> 50 | E5: 0 | F5: =MultiYear_ProForma!$AB$42 -> 16.666667 | G5: =MultiYear_ProForma!$AB$52 -> 17
B6: r_e (Echo retention ratio) | C6: =Parameters_Public!$C$23 -> 0.6 | D6: ="N/A" -> N/A | E6: ="N/A" -> N/A | F6: =Parameters_Public!$C$23 -> 0.6 | G6: ="N/A" -> N/A | H6: *
B7: r_p (Pima retention ratio) | C7: =Parameters_Public!$C$24 -> 0.85 | D7: ="N/A" -> N/A | E7: ="N/A" -> N/A | F7: N/A | G7: =Parameters_Public!$C$24 -> 0.85 | H7: **
B8: Number of students transitioning | C8: =Parameters_Public!$C$10*Parameters_Public!$C$23+Parameters_Public!$C$11*Parameters_Public!$C$24 -> 405.8 | D8: ="N/A" -> N/A | E8: ="N/A" -> N/A | F8: =Parameters_Public!$C$10*Parameters_Public!$C$23 -> 154.2 | G8: =Parameters_Public!$C$11*Parameters_Public!$C$24 -> 251.6
B9: Students served FY26 | C9: =C8+C5 -> 405.8 | D9: =D5+D4+D3 -> 603 | E9: =E4+E3+E5 -> 553 | F9: =F4+F8+F5 -> 466.86667 | G9: =G8+G3+G5 -> 525.6
B10: Funding/student (base+override; to be conservative, small adjustment down for new students) | C10: =MultiYear_ProForma!$AD$32/Working_test!C9 -> 10964.95 | D10: =MultiYear_ProForma!$AD$17/Working_test!D9 -> 10900.273 | E10: =MultiYear_ProForma!$AD$62/Working_test!E9 -> 10964.95 | F10: =MultiYear_ProForma!$AD$42/Working_test!F9 -> 10937.105 | G10: =MultiYear_ProForma!$AD$52/Working_test!G9 -> 10933.811
B11: Implied total 'revenue' | C11: =C10*C9 -> 4449576.7 | D11: =D10*D9 -> 6572864.9 | E11: =E10*E9 -> 6063617.3 | F11: =F10*F9 -> 5106169.7 | G11: =G10*G9 -> 5746811
B12: Districtwide gross Maintenance & Operations cost per non-new ADM | C12: =Parameters_Public!$C$14 -> 11589 | D12: =Parameters_Public!$C$14 -> 11589 | E12: =Parameters_Public!$C$14 -> 11589 | F12: =Parameters_Public!$C$14 -> 11589 | G12: =Parameters_Public!$C$14 -> 11589
B13: Variable cost / non-new ADM after discounting estimated fixed, adjusting for inflation | C13: =BaselineCalc!$B$18 -> 8403.3633 | D13: =BaselineCalc!$B$18 -> 8403.3633 | E13: =BaselineCalc!$B$18 -> 8403.3633 | F13: =BaselineCalc!$B$18 -> 8403.3633 | G13: =BaselineCalc!$B$18 -> 8403.3633
B14: Non-new students | C14: =C8 -> 405.8 | D14: =D3+D4 -> 553 | E14: =E9 -> 553 | F14: =F3+F4 -> 553 | G14: =G3+G4 -> 553
B15: Implied total variable gross cost of non-new students | C15: =C14*C13 -> 3410084.8 | D15: =D14*D13 -> 4647059.9 | E15: =E14*E13 -> 4647059.9 | F15: =F14*F13 -> 4647059.9 | G15: =G14*G13 -> 4647059.9
B16: New students | C16: =C5 -> 0 | D16: =D5 -> 50 | E16: =E5 -> 0 | F16: =F5 -> 16.666667 | G16: =G5 -> 17
B17: Marginal variable cost to add new students (as proportion of full cost) | C17: =Parameters_Public!$C$43 -> 0.6 | D17: =Parameters_Public!$C$43 -> 0.6 | E17: =Parameters_Public!$C$43 -> 0.6 | F17: =Parameters_Public!$C$43 -> 0.6 | G17: =Parameters_Public!$C$43 -> 0.6 | H17: **
B18: Implied variable gross M&O / new student | C18: =IFERROR((C13*C17), "N/A") -> 5042.018 | D18: =IFERROR((D13*D17), "N/A") -> 5042.018 | E18: =IFERROR((E13*E17), "N/A") -> 5042.018 | F18: =IFERROR((F13*F17), "N/A") -> 5042.018 | G18: =IFERROR((G13*G17), "N/A") -> 5042.018
B19: Implied total variable gross cost of new students | C19: =IF(C18*C5=0, "N/A", C18*C5) -> N/A | D19: =IF(D18*D5=0, "N/A", D18*D5) -> 252100.9 | E19: =IF(E18*E5=0, "N/A", E18*E5) -> N/A | F19: =IF(F18*F5=0, "N/A", F18*F5) -> 84033.633 | G19: =IF(G18*G5=0, "N/A", G18*G5) -> 85714.306
B20: Total variable gross M&O | C20: =IF(C19="N/A", 0, C19)+C15 -> 3410084.8 | D20: =IF(D19="N/A", 0, D19)+D15 -> 4899160.8 | E20: =IF(E19="N/A", 0, E19)+E15 -> 4647059.9 | F20: =IF(F19="N/A", 0, F19)+F15 -> 4731093.6 | G20: =IF(G19="N/A", 0, G19)+G15 -> 4732774.2
B21: h (Transition cost (routing, transportation, etc.) FY26) | C21: ="$"&YearMap!$E$2&"/student" -> $1000/student | D21: ="N/A" -> N/A | E21: ="N/A" -> N/A | F21: ="$"&YearMap!$E$2&"/student" -> $1000/student | G21: ="$"&YearMap!$E$2&"/student" -> $1000/student | H21: **
B22: Implied total transition cost FY26 | C22: =YearMap!$E$2*C8 -> 405800 | D22: ="N/A" -> N/A | E22: ="N/A" -> N/A | F22: =YearMap!$E$2*F8 -> 154200 | G22: =YearMap!$E$2*G8 -> 251600
B23: Total gross M&O + transition cost | C23: =C20+IF(C22="N/A", 0, C22) -> 3815884.8 | D23: =D20+IF(D22="N/A", 0, D22) -> 4899160.8 | E23: =E20+IF(E22="N/A", 0, E22) -> 4647059.9 | F23: =F20+IF(F22="N/A", 0, F22) -> 4885293.6 | G23: =G20+IF(G22="N/A", 0, G22) -> 4984374.2
B24: Base open site fixed total | C24: =Site_Fixed!$D$10+Site_Fixed!$D$17 -> 1875000 | D24: =Site_Fixed!$D$10+Site_Fixed!$D$17 -> 1875000 | E24: =Site_Fixed!$D$10+Site_Fixed!$D$17 -> 1875000 | F24: =Site_Fixed!$D$10 -> 900000 | G24: =Site_Fixed!$D$17 -> 975000 | H24: *
B25: Estimated repurpose site fixed carry ratio | C25: =YearMap!$F$2 -> 0.2 | D25: ="N/A" -> N/A | E25: ="N/A" -> N/A | F25: =YearMap!$F$2 -> 0.2 | G25: =YearMap!$F$2 -> 0.2 | H25: **
B26: Net fixed total | C26: =IFERROR(C24*(C25), C24) -> 375000 | D26: =IFERROR(D24*(D25), D24) -> 1875000 | E26: =IFERROR(E24*(E25), E24) -> 1875000 | F26: =F24+IFERROR(G24*(F25), G24) -> 1095000 | G26: =F24+IFERROR(F24*(G25), F24) -> 1080000
B27: Net total cost | C27: =C26+C23 -> 4190884.8 | D27: =D26+D23 -> 6774160.8 | E27: =E26+E23 -> 6522059.9 | F27: =F26+F23 -> 5980293.6 | G27: =G26+G23 -> 6064374.2
B28: Net operating $ / year FY26 | C28: =C11-C27 -> 258691.87 | D28: =D11-D27 -> -201295.98 | E28: =E11-E27 -> -458442.58 | F28: =F11-F27 -> -874123.9 | G28: =G11-G27 -> -317563.25
B31: Net cost | C31: =C23-C26 -> 3440884.8
B33: Net operating $ / year FY26 | C33: =MultiYear_ProForma!$AF$32 -> 252007.49 | D33: =MultiYear_ProForma!$AF$17 -> -210423.72 | E33: =MultiYear_ProForma!$AF$62 -> -459335.03 | F33: =MultiYear_ProForma!$AF$42 -> -76179.355 | G33: =MultiYear_ProForma!$AF$52 -> 36009.647
B35: Implied fixed cost savings / student | C35: =IFERROR(C26/C9, 0) -> 924.10054 | D35: =IFERROR(D26/D9, 0) -> 3109.4527 | E35: =IFERROR(E26/E9, 0) -> 3390.5967 | F35: =IFERROR(F26/F9, 0) -> 2345.4234 | G35: =IFERROR(G26/G9, 0) -> 2054.7945
B36: Net cost / student | C36: =C18-C35 -> 4117.9175
B37: Total net cost
B39: FY26 Capital Cost | H39: **
B40: Execution Feasibility | C40: HIGH RISK (Logistics / Community) | D40: HIGH RISK (Marketing / Enrollment) | E40: LOW RISK (Passive) | F40: MEDIUM RISK | G40: MEDIUM RISK | H40: **
B41: Distinctiveness / reputation impact | C41: Very negative | D41: Very positive | E41: Positive | F41: Neutral to positive | G41: Neutral to positive
B42: District financial 'health' impact | C42: Positive | D42: Positive | E42: Negative | F42: Neutral to positive | G42: Neutral to positive
B44: h (Transition cost (routing, transportation, etc.) FY30) | C44: ="$"&YearMap!$E$6&"/student" -> $300/student | D44: ="N/A" -> N/A | E44: ="N/A" -> N/A | F44: ="$"&YearMap!$E$6&"/student" -> $300/student | G44: ="$"&YearMap!$E$6&"/student" -> $300/student
B45: Implied total transition cost FY30 | C45: =YearMap!$E$6*C8 -> 121740 | D45: ="N/A" -> N/A | E45: ="N/A" -> N/A | F45: =YearMap!$E$6*F8 -> 46260 | G45: =YearMap!$E$6*G8 -> 75480
B47: f_lease (Proportion of fixed cost carried FY30) | C47: =YearMap!$F$6 -> 0.1 | D47: ="N/A" -> N/A | E47: ="N/A" -> N/A | F47: =YearMap!$F$6 -> 0.1 | G47: =YearMap!$F$6 -> 0.1 | H47: **
B48: Implied actual fixed cost savings FY30 | C48: =C24*(1-C47) -> 1687500 | D48: ="N/A" -> N/A | E48: ="N/A" -> N/A | F48: =F24*(1-F47) -> 810000 | G48: =G24*(1-G47) -> 877500
B50: Change in ADM over 5 years | C50: ="N/A" -> N/A | D50: ="&Scenarios!M6&""students" -> &Scenarios!M6&"students | E50: -43 students | H50: **
B52: Net operating $ / year FY30 | C52: =Summary_Figures!$F$11 -> 815010.46
B53: Average net operating $ / year FY26-FY30 | C53: =Summary_Figures!$G$11 -> 535102.86 | H53: **
B57: how solid is the repurpose savings estimate?
A58: Average net operating $ / year FY26-FY30 if site fixed savings are… | B58: 10% less than assumed
B59: 20% less than assumed
B60: 10% more than assumed
B61: 20% more than assumed
A62: Average net operating $ / year FY26-FY30 if f_lease savings glidepath is… | B62: slightly more conservative (xx)
B63: moderately more conservative (yy)
B64: slightly less conservative (zz)
B65: moderately less conservative (aa)
B66: retention
B69: what does it take to achieve budget-neutral on the keep-open scenarios?
C70: Scenario A2 (Repurpose Lease) | D70: Scenario D1 (Grow Both) | E70: Scenario E1 (Decline) | F70: Scenario E2 (Repurpose Echo lease; Grow Pima) | G70: Scenario D2 (Repurpose Pima; Grow Echo) | H70: Source / Confidence Level
B71: change in number of students to yield budget-neutral
B72: average retention rate required to yield budget-neutral
A73: Average net operating $ / year FY26-FY30 if site fixed savings are… | B73: 10% less than assumed
B74: 20% less than assumed
B75: 10% more than assumed
B76: 20% more than assumed
A77: Average net operating $ / year FY26-FY30 if f_lease savings glidepath is… | B77: slightly more conservative (xx)
B78: moderately more conservative (yy)
B79: slightly less conservative (zz)
B80: moderately less conservative (aa)
B83: what if the input assumptions were adjusted as follows (CHOOSE):

Sheet Scenario_Comparison
B1: Echo & Pima — Go-forward scenario comparison view
B3: Scenarios (CHOOSE) | C3: Description | I3: Assumed enrollment change (over 3 yrs)
B4: A2_Repurpose_Both_lease | C4: =VLOOKUP($B4,Scenarios!$A$2:$C$15, 2, 0) -> Repurpose both Echo & Pima; lease both properties; fixed cost reduction rate, retention %, and transition cost assumptions are key drivers | J4: =IF(ROUND(SUMIFS(MultiYear_ProForma!$AC:$AC,MultiYear_ProForma!$B:$B,$B4,MultiYear_ProForma!$C:$C,"FY2030")-BaselineCalc!$B$9, 0)>0, "+"&ROUND(SUMIFS(MultiYear_ProForma!$AC:$AC,MultiYear_ProForma!$B:$B,$B4,MultiYear_ProForma!$C:$C,"FY2030")-BaselineCalc!$B$9, 0), ROUND(SUMIFS(MultiYear_ProForma!$AC:$AC,MultiYear_ProForma!$B:$B,$B4,MultiYear_ProForma!$C:$C,"FY2030")-BaselineCalc!$B$9, 0)) -> -147
B5: E1_StatusQuo_Decline | C5: =VLOOKUP($B5,Scenarios!$A$2:$C$15, 2, 0) -> Echo & Pima open; no operational or strategic growth actions; enrollment decline trend continues | J5: =IF(ROUND(SUMIFS(MultiYear_ProForma!$AC:$AC,MultiYear_ProForma!$B:$B,$B5,MultiYear_ProForma!$C:$C,"FY2030")-BaselineCalc!$B$9, 0)>0, "+"&ROUND(SUMIFS(MultiYear_ProForma!$AC:$AC,MultiYear_ProForma!$B:$B,$B5,MultiYear_ProForma!$C:$C,"FY2030")-BaselineCalc!$B$9, 0), ROUND(SUMIFS(MultiYear_ProForma!$AC:$AC,MultiYear_ProForma!$B:$B,$B5,MultiYear_ProForma!$C:$C,"FY2030")-BaselineCalc!$B$9, 0)) -> -43
B24: Notes: Assumptions reflect: r (retention assumptions), override, marginal factor (e.g. assumed reduced variable cost to add new students), trend flags; h (receiving schools transportation route adjustment premium) tapers yearly. Receiving site should not exceed spare seats + portables
B26: Year | C26: Operating Net$ (Base) | D26: Operating Net$ (Comparator)
B27: FY2026 | C27: =SUMIFS(MultiYear_ProForma!$AF$2:$AF$66, MultiYear_ProForma!$B$2:$B$66, $B$4, MultiYear_ProForma!$C$2:$C$66, "FY2026") -> 252007.49 | D27: =SUMIFS(MultiYear_ProForma!$AF$2:$AF$66, MultiYear_ProForma!$B$2:$B$66, $B$5, MultiYear_ProForma!$C$2:$C$66, "FY2026") -> -459335.03
B28: FY2027 | C28: =SUMIFS(MultiYear_ProForma!$AF$2:$AF$66, MultiYear_ProForma!$B$2:$B$66, $B$4, MultiYear_ProForma!$C$2:$C$66, "FY2027") -> 349612.68 | D28: =SUMIFS(MultiYear_ProForma!$AF$2:$AF$66, MultiYear_ProForma!$B$2:$B$66, $B$5, MultiYear_ProForma!$C$2:$C$66, "FY2027") -> -500524.69
B29: FY2028 | C29: =SUMIFS(MultiYear_ProForma!$AF$2:$AF$66, MultiYear_ProForma!$B$2:$B$66, $B$4, MultiYear_ProForma!$C$2:$C$66, "FY2028") -> 547880.78 | D29: =SUMIFS(MultiYear_ProForma!$AF$2:$AF$66, MultiYear_ProForma!$B$2:$B$66, $B$5, MultiYear_ProForma!$C$2:$C$66, "FY2028") -> -542877.76
B30: FY2029 | C30: =SUMIFS(MultiYear_ProForma!$AF$2:$AF$66, MultiYear_ProForma!$B$2:$B$66, $B$4, MultiYear_ProForma!$C$2:$C$66, "FY2029") -> 711002.88 | D30: =SUMIFS(MultiYear_ProForma!$AF$2:$AF$66, MultiYear_ProForma!$B$2:$B$66, $B$5, MultiYear_ProForma!$C$2:$C$66, "FY2029") -> -586423.94
B31: FY2030 | C31: =SUMIFS(MultiYear_ProForma!$AF$2:$AF$66, MultiYear_ProForma!$B$2:$B$66, $B$4, MultiYear_ProForma!$C$2:$C$66, "FY2030") -> 815010.46 | D31: =SUMIFS(MultiYear_ProForma!$AF$2:$AF$66, MultiYear_ProForma!$B$2:$B$66, $B$5, MultiYear_ProForma!$C$2:$C$66, "FY2030") -> -631193.67
B33: Assumptions (from Parameters_Public / Control_Center)
B34: Retention r (Echo central) | C34: =Parameters_Public!C23 -> 0.6
B35: Retention r (Pima central) | C35: =Parameters_Public!C24 -> 0.85
B36: MarginalFactor_for_Overlay | C36: =Parameters_Public!C43 -> 0.6
B37: Override % | C37: =Parameters_Public!C17 -> 0.15
B38: Override toggle (0/1) | C38: =Parameters_Public!C20 -> 1
B39: Keep-open ops savings (fraction of MO) | C39: =Control_Center!C10 -> 0.007
B40: Extra savings for co-location (fraction of MO) | C40: =Control_Center!C11 -> 0.015
B41: • Routing/admin overhead h tapers by year (see YearMap). Try ±20% sensitivity when routing assumptions are uncertain.
D43: Interpretation
B44: One-time Capital FY 2026 (Base) | C44: =SUMIFS(Capital_Summary!$H$4:$H$83, Capital_Summary!$A$4:$A$83, B4, Capital_Summary!$B$4:$B$83, "FY2026") -> 2314480 | D44: =""&$B$5&" will be $"&TEXT(ROUND(ABS(C45-C44),0), "#,##0")&" "&IF(C45>C44,"MORE COSTLY","LESS COSTLY")&" than "&$B$4&" in terms of capital investment required " -> E1_StatusQuo_Decline will be $2,314,480 LESS COSTLY than A2_Repurpose_Both_lease in terms of capital investment required
B45: One-time Capital FY 2026 (Comparator) | C45: =SUMIFS(Capital_Summary!$H$4:$H$83, Capital_Summary!$A$4:$A$83, B5, Capital_Summary!$B$4:$B$83, "FY2026") -> 0
B47: Avg Net (FY26–30) (Base)—rounded | C47: =ROUND((SUMIFS(MultiYear_ProForma!$AF$2:$AF$66,MultiYear_ProForma!$B$2:$B$66,$B$4,MultiYear_ProForma!$C$2:$C$66,"FY2026")+SUMIFS(MultiYear_ProForma!$AF$2:$AF$66,MultiYear_ProForma!$B$2:$B$66,$B$4,MultiYear_ProForma!$C$2:$C$66,"FY2027")+SUMIFS(MultiYear_ProForma!$AF$2:$AF$66,MultiYear_ProForma!$B$2:$B$66,$B$4,MultiYear_ProForma!$C$2:$C$66,"FY2028")+SUMIFS(MultiYear_ProForma!$AF$2:$AF$66,MultiYear_ProForma!$B$2:$B$66,$B$4,MultiYear_ProForma!$C$2:$C$66,"FY2029")+SUMIFS(MultiYear_ProForma!$AF$2:$AF$66,MultiYear_ProForma!$B$2:$B$66,$B$4,MultiYear_ProForma!$C$2:$C$66,"FY2030"))/5,-4) -> 540000 | D47: ="On average from 2026 through 2030, "&$B$5&" will be $"&TEXT(ABS(ROUND(C49,0)), "#,##0")&" "&IF(C49<0,"MORE COSTLY","LESS COSTLY")&" to operate annually than "&$B$4&"" -> On average from 2026 through 2030, E1_StatusQuo_Decline will be $980,000 MORE COSTLY to operate annually than A2_Repurpose_Both_lease
B48: Avg Net (FY26–30) (Comparator)—rounded | C48: =ROUND((SUMIFS(MultiYear_ProForma!$AF$2:$AF$66, MultiYear_ProForma!$B$2:$B$66, $B$5, MultiYear_ProForma!$C$2:$C$66, "FY2026")+SUMIFS(MultiYear_ProForma!$AF$2:$AF$66, MultiYear_ProForma!$B$2:$B$66, $C$5, MultiYear_ProForma!$C$2:$C$66, "FY2027")+SUMIFS(MultiYear_ProForma!$AF$2:$AF$66, MultiYear_ProForma!$B$2:$B$66, $B$5, MultiYear_ProForma!$C$2:$C$66, "FY2028")+SUMIFS(MultiYear_ProForma!$AF$2:$AF$66, MultiYear_ProForma!$B$2:$B$66, $B$5, MultiYear_ProForma!$C$2:$C$66, "FY2029")+SUMIFS(MultiYear_ProForma!$AF$2:$AF$66, MultiYear_ProForma!$B$2:$B$66, $B$5, MultiYear_ProForma!$C$2:$C$66, "FY2030"))/5, -4) -> -440000
B49: Δ vs Base (Avg FY26–30)—rounded | C49: =ROUND(C48-C47, -4) -> -980000
B52: FY2030 Net (Base)—rounded | C52: =ROUND(SUMIFS(MultiYear_ProForma!$AF$2:$AF$66, MultiYear_ProForma!$B$2:$B$66, $B$4, MultiYear_ProForma!$C$2:$C$66, "FY2030"), -4) -> 820000 | D52: ="By 2030, "&$B$5&" will be $"&TEXT(ABS(ROUND(C54,0)), "#,##0")&" "&IF(C54<0,"MORE COSTLY","LESS COSTLY")&" to operate annually than "&$B$4&"" -> By 2030, E1_StatusQuo_Decline will be $1,450,000 MORE COSTLY to operate annually than A2_Repurpose_Both_lease
B53: FY2030 Net (Comparator)—rounded | C53: =ROUND(SUMIFS(MultiYear_ProForma!$AF$2:$AF$66, MultiYear_ProForma!$B$2:$B$66, $B$5, MultiYear_ProForma!$C$2:$C$66, "FY2030"), -4) -> -630000
B54: Δ vs Base (FY2030)—rounded | C54: =ROUND(C53-C52, -4) -> -1450000
B56: Students displaced (FY26) (Base) | C56: =SUMIFS(MultiYear_ProForma!$N$2:$N$66, MultiYear_ProForma!$B$2:$B$66, $B$4, MultiYear_ProForma!$C$2:$C$66, "FY2026") -> 553 | D56: =""&$B$5&" will displace "&ROUND(ABS(C57-C56),0)&" "&IF(C57>C56,"MORE STUDENTS","FEWER STUDENTS")&" than "&$B$4&"" -> E1_StatusQuo_Decline will displace 553 FEWER STUDENTS than A2_Repurpose_Both_lease
B57: Students displaced (FY26) (Comparator) | C57: =SUMIFS(MultiYear_ProForma!$N$2:$N$66, MultiYear_ProForma!$B$2:$B$66, $B$5, MultiYear_ProForma!$C$2:$C$66, "FY2026") -> 0
B59: Students served (FY2030) (Base) | C59: =SUMIFS(MultiYear_ProForma!$AC$2:$AC$66, MultiYear_ProForma!$B$2:$B$66, $B$4, MultiYear_ProForma!$C$2:$C$66, "FY2030") -> 405.8 | D59: =""&$B$5&" will serve "&ROUND(ABS(C60-C59),0)&" "&IF(C60>C59,"MORE STUDENTS","FEWER STUDENTS")&" than "&$B$4&"" -> E1_StatusQuo_Decline will serve 104 MORE STUDENTS than A2_Repurpose_Both_lease
B60: Students served (FY2030) (Comparator) | C60: =SUMIFS(MultiYear_ProForma!$AC$2:$AC$66, MultiYear_ProForma!$B$2:$B$66, $B$5, MultiYear_ProForma!$C$2:$C$66, "FY2030") -> 510.06959

Sheet Budget_Neutral_Calculator
B1: Budget‑Neutral Calculator (Operating $)
B3: Scenario (Choose one): | C3: E1_StatusQuo_Decline
B5: Metric | C5: FY2026 | D5: FY2030
B6: mᵗ: Incremental margin per added ADM | C6: =INDEX(YearMap!$I$2:$I$6, MATCH("FY2026",YearMap!$A$2:$A$6,0))+IF(Override_toggle=1, INDEX(YearMap!$O$2:$O$6, MATCH("FY2026",YearMap!$A$2:$A$6,0)),0)+INDEX(YearMap!$P$2:$P$6, MATCH("FY2026",YearMap!$A$2:$A$6,0))-INDEX(YearMap!$B$2:$B$6, MATCH("FY2026",YearMap!$A$2:$A$6,0))-INDEX(YearMap!$Q$2:$Q$6, MATCH("FY2026",YearMap!$A$2:$A$6,0)) -> 1609.6367 | D6: =INDEX(YearMap!$I$2:$I$6, MATCH("FY2030",YearMap!$A$2:$A$6,0))+IF(Override_toggle=1, INDEX(YearMap!$O$2:$O$6, MATCH("FY2030",YearMap!$A$2:$A$6,0)),0)+INDEX(YearMap!$P$2:$P$6, MATCH("FY2030",YearMap!$A$2:$A$6,0))-INDEX(YearMap!$B$2:$B$6, MATCH("FY2030",YearMap!$A$2:$A$6,0))-INDEX(YearMap!$Q$2:$Q$6, MATCH("FY2030",YearMap!$A$2:$A$6,0)) -> 1937.5003
B7: Net (operating) | C7: =SUMIFS(MultiYear_ProForma!$AF$2:$AF$66,MultiYear_ProForma!$B$2:$B$66,$C$3,MultiYear_ProForma!$C$2:$C$66,"FY2026") -> -459335.03 | D7: =SUMIFS(MultiYear_ProForma!$AF$2:$AF$66,MultiYear_ProForma!$B$2:$B$66,$C$3,MultiYear_ProForma!$C$2:$C$66,"FY2030") -> -631193.67
B8: N⁰: Additional students needed for Net ≥ 0 | C8: =IFERROR(MAX(0,-$C$7/$C$6),"") -> 285.36566 | D8: =IFERROR(MAX(0,-$D$7/$D$6),"") -> 325.77733
B10: Interpretation
B11: =IF(D8=0, "The "&C3&" is budget neutral or better given current assumptions in the model; additional enrollment is not necessary.", "Given current assumptions in the model, to be budget neutral by FY2030, the "&C3&" scenario requires enrollment of "&ROUND(D8, 0)&" additional students.") -> Given current assumptions in the model, to be budget neutral by FY2030, the E1_StatusQuo_Decline scenario requires enrollment of 326 additional students.
B13: Notes:
B14: This tool tests budget neutrality for any scenario: N⁰ = max(0, −Netₜ / mᵗ).
B15: mᵗ uses YearMap (Aid + Override_if_on + Uplift − VarUnit$ − Growth_overhead). Net excludes capital.

Sheet Summary_Figures
B1: Choose base scenario (for comparison): | C1: E1_StatusQuo_Decline | N1: Chart titles
A2: Net = (M&O operating) − (Aid + Override + Uplift). Capital is excluded. Uplift is indexed to Aid growth. | N2: ="(Comparison) Change in ops net $ by scenario compared to "&C1&" (Positive = savings)" -> (Comparison) Change in ops net $ by scenario compared to E1_StatusQuo_Decline (Positive = savings)
A3: Students: Displaced = FY2026; Served = FY2030 (open + retained). | N3: ="(Nominal) One-time capital (FY26) & Average 5-yr net ops $ by scenario" -> (Nominal) One-time capital (FY26) & Average 5-yr net ops $ by scenario
A4: Scenario key | B4: Scenario | C4: One-time Capital (FY26) | D4: Net FY26 Operational $ | E4: Net FY28 Operational $ | F4: Net FY30 Operational $ | G4: AVG 5-yr net operational $ | H4: Displaced students | I4: Served students FY30 | J4: Δ vs Base (FY2030 Net) | K4: Δ vs Base (5-yr Avg Net)
A5: =LEFT(B5, 2) -> F1 | B5: F1_CUSTOM1 | C5: =SUMIFS(Capital_Summary!$H$4:$H$83, Capital_Summary!$A$4:$A$83, B5, Capital_Summary!$B$4:$B$83, "FY2026")*-1 -> 0 | D5: =SUMIFS(MultiYear_ProForma!$AF$2:$AF$66, MultiYear_ProForma!$B$2:$B$66, B5, MultiYear_ProForma!$C$2:$C$66, "FY2026") -> -459335.03 | E5: =SUMIFS(MultiYear_ProForma!$AF$2:$AF$66, MultiYear_ProForma!$B$2:$B$66, B5, MultiYear_ProForma!$C$2:$C$66, "FY2028") -> -482588.87 | F5: =SUMIFS(MultiYear_ProForma!$AF$2:$AF$66, MultiYear_ProForma!$B$2:$B$66, B5, MultiYear_ProForma!$C$2:$C$66, "FY2030") -> -507019.93 | G5: =(SUMIFS(MultiYear_ProForma!$AF$2:$AF$66, MultiYear_ProForma!$B$2:$B$66, B5, MultiYear_ProForma!$C$2:$C$66, "FY2026")+SUMIFS(MultiYear_ProForma!$AF$2:$AF$66, MultiYear_ProForma!$B$2:$B$66, B5, MultiYear_ProForma!$C$2:$C$66, "FY2027")+SUMIFS(MultiYear_ProForma!$AF$2:$AF$66, MultiYear_ProForma!$B$2:$B$66, B5, MultiYear_ProForma!$C$2:$C$66, "FY2028")+SUMIFS(MultiYear_ProForma!$AF$2:$AF$66, MultiYear_ProForma!$B$2:$B$66, B5, MultiYear_ProForma!$C$2:$C$66, "FY2029")+SUMIFS(MultiYear_ProForma!$AF$2:$AF$66, MultiYear_ProForma!$B$2:$B$66, B5, MultiYear_ProForma!$C$2:$C$66, "FY2030"))/5 -> -482883.16 | H5: =SUMIFS(MultiYear_ProForma!$N$2:$N$66, MultiYear_ProForma!$B$2:$B$66, B5, MultiYear_ProForma!$C$2:$C$66, "FY2026") -> 0 | I5: =SUMIFS(MultiYear_ProForma!$AC$2:$AC$66, MultiYear_ProForma!$B$2:$B$66, B5, MultiYear_ProForma!$C$2:$C$66, "FY2030") -> 553 | J5: =F5-(VLOOKUP($C$1,$B$5:$G$17,5, 0)) -> 124173.74 | K5: =G5-(VLOOKUP($C$1,$B$5:$I$17,6, 0)) -> 61187.854
A6: =LEFT(B6, 2) -> E3 | B6: E3_StatusQuo_Targets | C6: =SUMIFS(Capital_Summary!$H$4:$H$83, Capital_Summary!$A$4:$A$83, B6, Capital_Summary!$B$4:$B$83, "FY2026")*-1 -> 0 | D6: =SUMIFS(MultiYear_ProForma!$AF$2:$AF$66, MultiYear_ProForma!$B$2:$B$66, B6, MultiYear_ProForma!$C$2:$C$66, "FY2026") -> 0 | E6: =SUMIFS(MultiYear_ProForma!$AF$2:$AF$66, MultiYear_ProForma!$B$2:$B$66, B6, MultiYear_ProForma!$C$2:$C$66, "FY2028") -> 0 | F6: =SUMIFS(MultiYear_ProForma!$AF$2:$AF$66, MultiYear_ProForma!$B$2:$B$66, B6, MultiYear_ProForma!$C$2:$C$66, "FY2030") -> 0 | G6: =(SUMIFS(MultiYear_ProForma!$AF$2:$AF$66, MultiYear_ProForma!$B$2:$B$66, B6, MultiYear_ProForma!$C$2:$C$66, "FY2026")+SUMIFS(MultiYear_ProForma!$AF$2:$AF$66, MultiYear_ProForma!$B$2:$B$66, B6, MultiYear_ProForma!$C$2:$C$66, "FY2027")+SUMIFS(MultiYear_ProForma!$AF$2:$AF$66, MultiYear_ProForma!$B$2:$B$66, B6, MultiYear_ProForma!$C$2:$C$66, "FY2028")+SUMIFS(MultiYear_ProForma!$AF$2:$AF$66, MultiYear_ProForma!$B$2:$B$66, B6, MultiYear_ProForma!$C$2:$C$66, "FY2029")+SUMIFS(MultiYear_ProForma!$AF$2:$AF$66, MultiYear_ProForma!$B$2:$B$66, B6, MultiYear_ProForma!$C$2:$C$66, "FY2030"))/5 -> 0 | H6: =SUMIFS(MultiYear_ProForma!$N$2:$N$66, MultiYear_ProForma!$B$2:$B$66, B6, MultiYear_ProForma!$C$2:$C$66, "FY2026") -> 0 | I6: =SUMIFS(MultiYear_ProForma!$AC$2:$AC$66, MultiYear_ProForma!$B$2:$B$66, B6, MultiYear_ProForma!$C$2:$C$66, "FY2030") -> 0 | J6: =F6-(VLOOKUP($C$1,$B$5:$G$17,5, 0)) -> 631193.67 | K6: =G6-(VLOOKUP($C$1,$B$5:$I$17,6, 0)) -> 544071.02
A7: =LEFT(B7, 2) -> D3 | B7: D3_CoLocation_Echo_Targets | C7: =SUMIFS(Capital_Summary!$H$4:$H$83, Capital_Summary!$A$4:$A$83, B7, Capital_Summary!$B$4:$B$83, "FY2026")*-1 -> 0 | D7: =SUMIFS(MultiYear_ProForma!$AF$2:$AF$66, MultiYear_ProForma!$B$2:$B$66, B7, MultiYear_ProForma!$C$2:$C$66, "FY2026") -> -46044.706 | E7: =SUMIFS(MultiYear_ProForma!$AF$2:$AF$66, MultiYear_ProForma!$B$2:$B$66, B7, MultiYear_ProForma!$C$2:$C$66, "FY2028") -> 139239.14 | F7: =SUMIFS(MultiYear_ProForma!$AF$2:$AF$66, MultiYear_ProForma!$B$2:$B$66, B7, MultiYear_ProForma!$C$2:$C$66, "FY2030") -> 149591.87 | G7: =(SUMIFS(MultiYear_ProForma!$AF$2:$AF$66, MultiYear_ProForma!$B$2:$B$66, B7, MultiYear_ProForma!$C$2:$C$66, "FY2026")+SUMIFS(MultiYear_ProForma!$AF$2:$AF$66, MultiYear_ProForma!$B$2:$B$66, B7, MultiYear_ProForma!$C$2:$C$66, "FY2027")+SUMIFS(MultiYear_ProForma!$AF$2:$AF$66, MultiYear_ProForma!$B$2:$B$66, B7, MultiYear_ProForma!$C$2:$C$66, "FY2028")+SUMIFS(MultiYear_ProForma!$AF$2:$AF$66, MultiYear_ProForma!$B$2:$B$66, B7, MultiYear_ProForma!$C$2:$C$66, "FY2029")+SUMIFS(MultiYear_ProForma!$AF$2:$AF$66, MultiYear_ProForma!$B$2:$B$66, B7, MultiYear_ProForma!$C$2:$C$66, "FY2030"))/5 -> 86056.375 | H7: =SUMIFS(MultiYear_ProForma!$N$2:$N$66, MultiYear_ProForma!$B$2:$B$66, B7, MultiYear_ProForma!$C$2:$C$66, "FY2026") -> 0 | I7: =SUMIFS(MultiYear_ProForma!$AC$2:$AC$66, MultiYear_ProForma!$B$2:$B$66, B7, MultiYear_ProForma!$C$2:$C$66, "FY2030") -> 603 | J7: =F7-(VLOOKUP($C$1,$B$5:$G$17,5, 0)) -> 780785.54 | K7: =G7-(VLOOKUP($C$1,$B$5:$I$17,6, 0)) -> 630127.39
A8: =LEFT(B8, 2) -> D1 | B8: D1_Grow_Both_Targets | C8: =SUMIFS(Capital_Summary!$H$4:$H$83, Capital_Summary!$A$4:$A$83, B8, Capital_Summary!$B$4:$B$83, "FY2026")*-1 -> -2000000 | D8: =SUMIFS(MultiYear_ProForma!$AF$2:$AF$66, MultiYear_ProForma!$B$2:$B$66, B8, MultiYear_ProForma!$C$2:$C$66, "FY2026") -> -210423.72 | E8: =SUMIFS(MultiYear_ProForma!$AF$2:$AF$66, MultiYear_ProForma!$B$2:$B$66, B8, MultiYear_ProForma!$C$2:$C$66, "FY2028") -> 315467.21 | F8: =SUMIFS(MultiYear_ProForma!$AF$2:$AF$66, MultiYear_ProForma!$B$2:$B$66, B8, MultiYear_ProForma!$C$2:$C$66, "FY2030") -> 341348.98 | G8: =(SUMIFS(MultiYear_ProForma!$AF$2:$AF$66, MultiYear_ProForma!$B$2:$B$66, B8, MultiYear_ProForma!$C$2:$C$66, "FY2026")+SUMIFS(MultiYear_ProForma!$AF$2:$AF$66, MultiYear_ProForma!$B$2:$B$66, B8, MultiYear_ProForma!$C$2:$C$66, "FY2027")+SUMIFS(MultiYear_ProForma!$AF$2:$AF$66, MultiYear_ProForma!$B$2:$B$66, B8, MultiYear_ProForma!$C$2:$C$66, "FY2028")+SUMIFS(MultiYear_ProForma!$AF$2:$AF$66, MultiYear_ProForma!$B$2:$B$66, B8, MultiYear_ProForma!$C$2:$C$66, "FY2029")+SUMIFS(MultiYear_ProForma!$AF$2:$AF$66, MultiYear_ProForma!$B$2:$B$66, B8, MultiYear_ProForma!$C$2:$C$66, "FY2030"))/5 -> 163429.23 | H8: =SUMIFS(MultiYear_ProForma!$N$2:$N$66, MultiYear_ProForma!$B$2:$B$66, B8, MultiYear_ProForma!$C$2:$C$66, "FY2026") -> 0 | I8: =SUMIFS(MultiYear_ProForma!$AC$2:$AC$66, MultiYear_ProForma!$B$2:$B$66, B8, MultiYear_ProForma!$C$2:$C$66, "FY2030") -> 703 | J8: =F8-(VLOOKUP($C$1,$B$5:$G$17,5, 0)) -> 972542.65 | K8: =G8-(VLOOKUP($C$1,$B$5:$I$17,6, 0)) -> 707500.24
A9: =LEFT(B9, 2) -> E2 | B9: E2_StatusQuo_Steady | C9: =SUMIFS(Capital_Summary!$H$4:$H$83, Capital_Summary!$A$4:$A$83, B9, Capital_Summary!$B$4:$B$83, "FY2026")*-1 -> 0 | D9: =SUMIFS(MultiYear_ProForma!$AF$2:$AF$66, MultiYear_ProForma!$B$2:$B$66, B9, MultiYear_ProForma!$C$2:$C$66, "FY2026") -> -459335.03 | E9: =SUMIFS(MultiYear_ProForma!$AF$2:$AF$66, MultiYear_ProForma!$B$2:$B$66, B9, MultiYear_ProForma!$C$2:$C$66, "FY2028") -> -482588.87 | F9: =SUMIFS(MultiYear_ProForma!$AF$2:$AF$66, MultiYear_ProForma!$B$2:$B$66, B9, MultiYear_ProForma!$C$2:$C$66, "FY2030") -> -507019.93 | G9: =(SUMIFS(MultiYear_ProForma!$AF$2:$AF$66, MultiYear_ProForma!$B$2:$B$66, B9, MultiYear_ProForma!$C$2:$C$66, "FY2026")+SUMIFS(MultiYear_ProForma!$AF$2:$AF$66, MultiYear_ProForma!$B$2:$B$66, B9, MultiYear_ProForma!$C$2:$C$66, "FY2027")+SUMIFS(MultiYear_ProForma!$AF$2:$AF$66, MultiYear_ProForma!$B$2:$B$66, B9, MultiYear_ProForma!$C$2:$C$66, "FY2028")+SUMIFS(MultiYear_ProForma!$AF$2:$AF$66, MultiYear_ProForma!$B$2:$B$66, B9, MultiYear_ProForma!$C$2:$C$66, "FY2029")+SUMIFS(MultiYear_ProForma!$AF$2:$AF$66, MultiYear_ProForma!$B$2:$B$66, B9, MultiYear_ProForma!$C$2:$C$66, "FY2030"))/5 -> -482883.16 | H9: =SUMIFS(MultiYear_ProForma!$N$2:$N$66, MultiYear_ProForma!$B$2:$B$66, B9, MultiYear_ProForma!$C$2:$C$66, "FY2026") -> 0 | I9: =SUMIFS(MultiYear_ProForma!$AC$2:$AC$66, MultiYear_ProForma!$B$2:$B$66, B9, MultiYear_ProForma!$C$2:$C$66, "FY2030") -> 553 | J9: =F9-(VLOOKUP($C$1,$B$5:$G$17,5, 0)) -> 124173.74 | K9: =G9-(VLOOKUP($C$1,$B$5:$I$17,6, 0)) -> 61187.854
A10: =LEFT(B10, 2) -> D2 | B10: D2_EchoGHubRamp_PimaTargets | C10: =SUMIFS(Capital_Summary!$H$4:$H$83, Capital_Summary!$A$4:$A$83, B10, Capital_Summary!$B$4:$B$83, "FY2026")*-1 -> -800000 | D10: =SUMIFS(MultiYear_ProForma!$AF$2:$AF$66, MultiYear_ProForma!$B$2:$B$66, B10, MultiYear_ProForma!$C$2:$C$66, "FY2026") -> -251908.94 | E10: =SUMIFS(MultiYear_ProForma!$AF$2:$AF$66, MultiYear_ProForma!$B$2:$B$66, B10, MultiYear_ProForma!$C$2:$C$66, "FY2028") -> 182457.86 | F10: =SUMIFS(MultiYear_ProForma!$AF$2:$AF$66, MultiYear_ProForma!$B$2:$B$66, B10, MultiYear_ProForma!$C$2:$C$66, "FY2030") -> 199954.17 | G10: =(SUMIFS(MultiYear_ProForma!$AF$2:$AF$66, MultiYear_ProForma!$B$2:$B$66, B10, MultiYear_ProForma!$C$2:$C$66, "FY2026")+SUMIFS(MultiYear_ProForma!$AF$2:$AF$66, MultiYear_ProForma!$B$2:$B$66, B10, MultiYear_ProForma!$C$2:$C$66, "FY2027")+SUMIFS(MultiYear_ProForma!$AF$2:$AF$66, MultiYear_ProForma!$B$2:$B$66, B10, MultiYear_ProForma!$C$2:$C$66, "FY2028")+SUMIFS(MultiYear_ProForma!$AF$2:$AF$66, MultiYear_ProForma!$B$2:$B$66, B10, MultiYear_ProForma!$C$2:$C$66, "FY2029")+SUMIFS(MultiYear_ProForma!$AF$2:$AF$66, MultiYear_ProForma!$B$2:$B$66, B10, MultiYear_ProForma!$C$2:$C$66, "FY2030"))/5 -> 55710.494 | H10: =SUMIFS(MultiYear_ProForma!$N$2:$N$66, MultiYear_ProForma!$B$2:$B$66, B10, MultiYear_ProForma!$C$2:$C$66, "FY2026") -> 0 | I10: =SUMIFS(MultiYear_ProForma!$AC$2:$AC$66, MultiYear_ProForma!$B$2:$B$66, B10, MultiYear_ProForma!$C$2:$C$66, "FY2030") -> 678 | J10: =F10-(VLOOKUP($C$1,$B$5:$G$17,5, 0)) -> 831147.83 | K10: =G10-(VLOOKUP($C$1,$B$5:$I$17,6, 0)) -> 599781.51
A11: =LEFT(B11, 2) -> A2 | B11: A2_Repurpose_Both_lease | C11: =SUMIFS(Capital_Summary!$H$4:$H$83, Capital_Summary!$A$4:$A$83, B11, Capital_Summary!$B$4:$B$83, "FY2026")*-1 -> -2314480 | D11: =SUMIFS(MultiYear_ProForma!$AF$2:$AF$66, MultiYear_ProForma!$B$2:$B$66, B11, MultiYear_ProForma!$C$2:$C$66, "FY2026") -> 252007.49 | E11: =SUMIFS(MultiYear_ProForma!$AF$2:$AF$66, MultiYear_ProForma!$B$2:$B$66, B11, MultiYear_ProForma!$C$2:$C$66, "FY2028") -> 547880.78 | F11: =SUMIFS(MultiYear_ProForma!$AF$2:$AF$66, MultiYear_ProForma!$B$2:$B$66, B11, MultiYear_ProForma!$C$2:$C$66, "FY2030") -> 815010.46 | G11: =(SUMIFS(MultiYear_ProForma!$AF$2:$AF$66, MultiYear_ProForma!$B$2:$B$66, B11, MultiYear_ProForma!$C$2:$C$66, "FY2026")+SUMIFS(MultiYear_ProForma!$AF$2:$AF$66, MultiYear_ProForma!$B$2:$B$66, B11, MultiYear_ProForma!$C$2:$C$66, "FY2027")+SUMIFS(MultiYear_ProForma!$AF$2:$AF$66, MultiYear_ProForma!$B$2:$B$66, B11, MultiYear_ProForma!$C$2:$C$66, "FY2028")+SUMIFS(MultiYear_ProForma!$AF$2:$AF$66, MultiYear_ProForma!$B$2:$B$66, B11, MultiYear_ProForma!$C$2:$C$66, "FY2029")+SUMIFS(MultiYear_ProForma!$AF$2:$AF$66, MultiYear_ProForma!$B$2:$B$66, B11, MultiYear_ProForma!$C$2:$C$66, "FY2030"))/5 -> 535102.86 | H11: =SUMIFS(MultiYear_ProForma!$N$2:$N$66, MultiYear_ProForma!$B$2:$B$66, B11, MultiYear_ProForma!$C$2:$C$66, "FY2026") -> 553 | I11: =SUMIFS(MultiYear_ProForma!$AC$2:$AC$66, MultiYear_ProForma!$B$2:$B$66, B11, MultiYear_ProForma!$C$2:$C$66, "FY2030") -> 405.8 | J11: =F11-(VLOOKUP($C$1,$B$5:$G$17,5, 0)) -> 1446204.1 | K11: =G11-(VLOOKUP($C$1,$B$5:$I$17,6, 0)) -> 1079173.9
A12: =LEFT(B12, 2) -> A1 | B12: A1_Repurpose_Both_ops | C12: =SUMIFS(Capital_Summary!$H$4:$H$83, Capital_Summary!$A$4:$A$83, B12, Capital_Summary!$B$4:$B$83, "FY2026")*-1 -> -3114480 | D12: =SUMIFS(MultiYear_ProForma!$AF$2:$AF$66, MultiYear_ProForma!$B$2:$B$66, B12, MultiYear_ProForma!$C$2:$C$66, "FY2026") -> -225097.98 | E12: =SUMIFS(MultiYear_ProForma!$AF$2:$AF$66, MultiYear_ProForma!$B$2:$B$66, B12, MultiYear_ProForma!$C$2:$C$66, "FY2028") -> 146873.64 | F12: =SUMIFS(MultiYear_ProForma!$AF$2:$AF$66, MultiYear_ProForma!$B$2:$B$66, B12, MultiYear_ProForma!$C$2:$C$66, "FY2030") -> 393702.32 | G12: =(SUMIFS(MultiYear_ProForma!$AF$2:$AF$66, MultiYear_ProForma!$B$2:$B$66, B12, MultiYear_ProForma!$C$2:$C$66, "FY2026")+SUMIFS(MultiYear_ProForma!$AF$2:$AF$66, MultiYear_ProForma!$B$2:$B$66, B12, MultiYear_ProForma!$C$2:$C$66, "FY2027")+SUMIFS(MultiYear_ProForma!$AF$2:$AF$66, MultiYear_ProForma!$B$2:$B$66, B12, MultiYear_ProForma!$C$2:$C$66, "FY2028")+SUMIFS(MultiYear_ProForma!$AF$2:$AF$66, MultiYear_ProForma!$B$2:$B$66, B12, MultiYear_ProForma!$C$2:$C$66, "FY2029")+SUMIFS(MultiYear_ProForma!$AF$2:$AF$66, MultiYear_ProForma!$B$2:$B$66, B12, MultiYear_ProForma!$C$2:$C$66, "FY2030"))/5 -> 114766.95 | H12: =SUMIFS(MultiYear_ProForma!$N$2:$N$66, MultiYear_ProForma!$B$2:$B$66, B12, MultiYear_ProForma!$C$2:$C$66, "FY2026") -> 553 | I12: =SUMIFS(MultiYear_ProForma!$AC$2:$AC$66, MultiYear_ProForma!$B$2:$B$66, B12, MultiYear_ProForma!$C$2:$C$66, "FY2030") -> 405.8 | J12: =F12-(VLOOKUP($C$1,$B$5:$G$17,5, 0)) -> 1024896 | K12: =G12-(VLOOKUP($C$1,$B$5:$I$17,6, 0)) -> 658837.97
A13: =LEFT(B13, 2) -> B2 | B13: B2_Repurpose_Echo_lease_PimaTargets | C13: =SUMIFS(Capital_Summary!$H$4:$H$83, Capital_Summary!$A$4:$A$83, B13, Capital_Summary!$B$4:$B$83, "FY2026")*-1 -> -1600000 | D13: =SUMIFS(MultiYear_ProForma!$AF$2:$AF$66, MultiYear_ProForma!$B$2:$B$66, B13, MultiYear_ProForma!$C$2:$C$66, "FY2026") -> -76179.355 | E13: =SUMIFS(MultiYear_ProForma!$AF$2:$AF$66, MultiYear_ProForma!$B$2:$B$66, B13, MultiYear_ProForma!$C$2:$C$66, "FY2028") -> 190408.1 | F13: =SUMIFS(MultiYear_ProForma!$AF$2:$AF$66, MultiYear_ProForma!$B$2:$B$66, B13, MultiYear_ProForma!$C$2:$C$66, "FY2030") -> 303244.53 | G13: =(SUMIFS(MultiYear_ProForma!$AF$2:$AF$66, MultiYear_ProForma!$B$2:$B$66, B13, MultiYear_ProForma!$C$2:$C$66, "FY2026")+SUMIFS(MultiYear_ProForma!$AF$2:$AF$66, MultiYear_ProForma!$B$2:$B$66, B13, MultiYear_ProForma!$C$2:$C$66, "FY2027")+SUMIFS(MultiYear_ProForma!$AF$2:$AF$66, MultiYear_ProForma!$B$2:$B$66, B13, MultiYear_ProForma!$C$2:$C$66, "FY2028")+SUMIFS(MultiYear_ProForma!$AF$2:$AF$66, MultiYear_ProForma!$B$2:$B$66, B13, MultiYear_ProForma!$C$2:$C$66, "FY2029")+SUMIFS(MultiYear_ProForma!$AF$2:$AF$66, MultiYear_ProForma!$B$2:$B$66, B13, MultiYear_ProForma!$C$2:$C$66, "FY2030"))/5 -> 139710.42 | H13: =SUMIFS(MultiYear_ProForma!$N$2:$N$66, MultiYear_ProForma!$B$2:$B$66, B13, MultiYear_ProForma!$C$2:$C$66, "FY2026") -> 257 | I13: =SUMIFS(MultiYear_ProForma!$AC$2:$AC$66, MultiYear_ProForma!$B$2:$B$66, B13, MultiYear_ProForma!$C$2:$C$66, "FY2030") -> 500.2 | J13: =F13-(VLOOKUP($C$1,$B$5:$G$17,5, 0)) -> 934438.2 | K13: =G13-(VLOOKUP($C$1,$B$5:$I$17,6, 0)) -> 683781.43
A14: =LEFT(B14, 2) -> B1 | B14: B1_Repurpose_Echo_ops_PimaTargets | C14: =SUMIFS(Capital_Summary!$H$4:$H$83, Capital_Summary!$A$4:$A$83, B14, Capital_Summary!$B$4:$B$83, "FY2026")*-1 -> -2000000 | D14: =SUMIFS(MultiYear_ProForma!$AF$2:$AF$66, MultiYear_ProForma!$B$2:$B$66, B14, MultiYear_ProForma!$C$2:$C$66, "FY2026") -> -305189.98 | E14: =SUMIFS(MultiYear_ProForma!$AF$2:$AF$66, MultiYear_ProForma!$B$2:$B$66, B14, MultiYear_ProForma!$C$2:$C$66, "FY2028") -> 4044.9204 | F14: =SUMIFS(MultiYear_ProForma!$AF$2:$AF$66, MultiYear_ProForma!$B$2:$B$66, B14, MultiYear_ProForma!$C$2:$C$66, "FY2030") -> 107446.72 | G14: =(SUMIFS(MultiYear_ProForma!$AF$2:$AF$66, MultiYear_ProForma!$B$2:$B$66, B14, MultiYear_ProForma!$C$2:$C$66, "FY2026")+SUMIFS(MultiYear_ProForma!$AF$2:$AF$66, MultiYear_ProForma!$B$2:$B$66, B14, MultiYear_ProForma!$C$2:$C$66, "FY2027")+SUMIFS(MultiYear_ProForma!$AF$2:$AF$66, MultiYear_ProForma!$B$2:$B$66, B14, MultiYear_ProForma!$C$2:$C$66, "FY2028")+SUMIFS(MultiYear_ProForma!$AF$2:$AF$66, MultiYear_ProForma!$B$2:$B$66, B14, MultiYear_ProForma!$C$2:$C$66, "FY2029")+SUMIFS(MultiYear_ProForma!$AF$2:$AF$66, MultiYear_ProForma!$B$2:$B$66, B14, MultiYear_ProForma!$C$2:$C$66, "FY2030"))/5 -> -57091.904 | H14: =SUMIFS(MultiYear_ProForma!$N$2:$N$66, MultiYear_ProForma!$B$2:$B$66, B14, MultiYear_ProForma!$C$2:$C$66, "FY2026") -> 257 | I14: =SUMIFS(MultiYear_ProForma!$AC$2:$AC$66, MultiYear_ProForma!$B$2:$B$66, B14, MultiYear_ProForma!$C$2:$C$66, "FY2030") -> 500.2 | J14: =F14-(VLOOKUP($C$1,$B$5:$G$17,5, 0)) -> 738640.39 | K14: =G14-(VLOOKUP($C$1,$B$5:$I$17,6, 0)) -> 486979.11
A15: =LEFT(B15, 2) -> C2 | B15: C2_Repurpose_Pima_lease_EchoGHub_EchoTargets | C15: =SUMIFS(Capital_Summary!$H$4:$H$83, Capital_Summary!$A$4:$A$83, B15, Capital_Summary!$B$4:$B$83, "FY2026")*-1 -> -1600000 | D15: =SUMIFS(MultiYear_ProForma!$AF$2:$AF$66, MultiYear_ProForma!$B$2:$B$66, B15, MultiYear_ProForma!$C$2:$C$66, "FY2026") -> 36009.647 | E15: =SUMIFS(MultiYear_ProForma!$AF$2:$AF$66, MultiYear_ProForma!$B$2:$B$66, B15, MultiYear_ProForma!$C$2:$C$66, "FY2028") -> 406921.2 | F15: =SUMIFS(MultiYear_ProForma!$AF$2:$AF$66, MultiYear_ProForma!$B$2:$B$66, B15, MultiYear_ProForma!$C$2:$C$66, "FY2030") -> 570325.27 | G15: =(SUMIFS(MultiYear_ProForma!$AF$2:$AF$66, MultiYear_ProForma!$B$2:$B$66, B15, MultiYear_ProForma!$C$2:$C$66, "FY2026")+SUMIFS(MultiYear_ProForma!$AF$2:$AF$66, MultiYear_ProForma!$B$2:$B$66, B15, MultiYear_ProForma!$C$2:$C$66, "FY2027")+SUMIFS(MultiYear_ProForma!$AF$2:$AF$66, MultiYear_ProForma!$B$2:$B$66, B15, MultiYear_ProForma!$C$2:$C$66, "FY2028")+SUMIFS(MultiYear_ProForma!$AF$2:$AF$66, MultiYear_ProForma!$B$2:$B$66, B15, MultiYear_ProForma!$C$2:$C$66, "FY2029")+SUMIFS(MultiYear_ProForma!$AF$2:$AF$66, MultiYear_ProForma!$B$2:$B$66, B15, MultiYear_ProForma!$C$2:$C$66, "FY2030"))/5 -> 343387.87 | H15: =SUMIFS(MultiYear_ProForma!$N$2:$N$66, MultiYear_ProForma!$B$2:$B$66, B15, MultiYear_ProForma!$C$2:$C$66, "FY2026") -> 295.66667 | I15: =SUMIFS(MultiYear_ProForma!$AC$2:$AC$66, MultiYear_ProForma!$B$2:$B$66, B15, MultiYear_ProForma!$C$2:$C$66, "FY2030") -> 558.6 | J15: =F15-(VLOOKUP($C$1,$B$5:$G$17,5, 0)) -> 1201518.9 | K15: =G15-(VLOOKUP($C$1,$B$5:$I$17,6, 0)) -> 887458.89
A16: =LEFT(B16, 2) -> C1 | B16: C1_Repurpose_Pima_ops_EchoGHub_EchoTargets | C16: =SUMIFS(Capital_Summary!$H$4:$H$83, Capital_Summary!$A$4:$A$83, B16, Capital_Summary!$B$4:$B$83, "FY2026")*-1 -> -2000000 | D16: =SUMIFS(MultiYear_ProForma!$AF$2:$AF$66, MultiYear_ProForma!$B$2:$B$66, B16, MultiYear_ProForma!$C$2:$C$66, "FY2026") -> -212085.2 | E16: =SUMIFS(MultiYear_ProForma!$AF$2:$AF$66, MultiYear_ProForma!$B$2:$B$66, B16, MultiYear_ProForma!$C$2:$C$66, "FY2028") -> 192277.23 | F16: =SUMIFS(MultiYear_ProForma!$AF$2:$AF$66, MultiYear_ProForma!$B$2:$B$66, B16, MultiYear_ProForma!$C$2:$C$66, "FY2030") -> 344814.95 | G16: =(SUMIFS(MultiYear_ProForma!$AF$2:$AF$66, MultiYear_ProForma!$B$2:$B$66, B16, MultiYear_ProForma!$C$2:$C$66, "FY2026")+SUMIFS(MultiYear_ProForma!$AF$2:$AF$66, MultiYear_ProForma!$B$2:$B$66, B16, MultiYear_ProForma!$C$2:$C$66, "FY2027")+SUMIFS(MultiYear_ProForma!$AF$2:$AF$66, MultiYear_ProForma!$B$2:$B$66, B16, MultiYear_ProForma!$C$2:$C$66, "FY2028")+SUMIFS(MultiYear_ProForma!$AF$2:$AF$66, MultiYear_ProForma!$B$2:$B$66, B16, MultiYear_ProForma!$C$2:$C$66, "FY2029")+SUMIFS(MultiYear_ProForma!$AF$2:$AF$66, MultiYear_ProForma!$B$2:$B$66, B16, MultiYear_ProForma!$C$2:$C$66, "FY2030"))/5 -> 119854.28 | H16: =SUMIFS(MultiYear_ProForma!$N$2:$N$66, MultiYear_ProForma!$B$2:$B$66, B16, MultiYear_ProForma!$C$2:$C$66, "FY2026") -> 295.66667 | I16: =SUMIFS(MultiYear_ProForma!$AC$2:$AC$66, MultiYear_ProForma!$B$2:$B$66, B16, MultiYear_ProForma!$C$2:$C$66, "FY2030") -> 558.6 | J16: =F16-(VLOOKUP($C$1,$B$5:$G$17,5, 0)) -> 976008.61 | K16: =G16-(VLOOKUP($C$1,$B$5:$I$17,6, 0)) -> 663925.3
A17: =LEFT(B17, 2) -> E1 | B17: E1_StatusQuo_Decline | C17: =SUMIFS(Capital_Summary!$H$4:$H$83, Capital_Summary!$A$4:$A$83, B17, Capital_Summary!$B$4:$B$83, "FY2026")*-1 -> 0 | D17: =SUMIFS(MultiYear_ProForma!$AF$2:$AF$66, MultiYear_ProForma!$B$2:$B$66, B17, MultiYear_ProForma!$C$2:$C$66, "FY2026") -> -459335.03 | E17: =SUMIFS(MultiYear_ProForma!$AF$2:$AF$66, MultiYear_ProForma!$B$2:$B$66, B17, MultiYear_ProForma!$C$2:$C$66, "FY2028") -> -542877.76 | F17: =SUMIFS(MultiYear_ProForma!$AF$2:$AF$66, MultiYear_ProForma!$B$2:$B$66, B17, MultiYear_ProForma!$C$2:$C$66, "FY2030") -> -631193.67 | G17: =(SUMIFS(MultiYear_ProForma!$AF$2:$AF$66, MultiYear_ProForma!$B$2:$B$66, B17, MultiYear_ProForma!$C$2:$C$66, "FY2026")+SUMIFS(MultiYear_ProForma!$AF$2:$AF$66, MultiYear_ProForma!$B$2:$B$66, B17, MultiYear_ProForma!$C$2:$C$66, "FY2027")+SUMIFS(MultiYear_ProForma!$AF$2:$AF$66, MultiYear_ProForma!$B$2:$B$66, B17, MultiYear_ProForma!$C$2:$C$66, "FY2028")+SUMIFS(MultiYear_ProForma!$AF$2:$AF$66, MultiYear_ProForma!$B$2:$B$66, B17, MultiYear_ProForma!$C$2:$C$66, "FY2029")+SUMIFS(MultiYear_ProForma!$AF$2:$AF$66, MultiYear_ProForma!$B$2:$B$66, B17, MultiYear_ProForma!$C$2:$C$66, "FY2030"))/5 -> -544071.02 | H17: =SUMIFS(MultiYear_ProForma!$N$2:$N$66, MultiYear_ProForma!$B$2:$B$66, B17, MultiYear_ProForma!$C$2:$C$66, "FY2026") -> 0 | I17: =SUMIFS(MultiYear_ProForma!$AC$2:$AC$66, MultiYear_ProForma!$B$2:$B$66, B17, MultiYear_ProForma!$C$2:$C$66, "FY2030") -> 510.06959 | J17: =F17-(VLOOKUP($C$1,$B$5:$G$17,5, 0)) -> 0 | K17: =G17-(VLOOKUP($C$1,$B$5:$I$17,6, 0)) -> 0
B19: Note: Displaced = FY26; Served = FY30. Net = M&O − (Aid + Override + Uplift); showing one-time capital (fy26) as negative number for visualization purposes

Sheet What_Is_The_$900K-$1M_Savings

Sheet Parameters_Public
A1: Public Inputs — Audited Baselines and Overrides (Phase A) | C1: Yellow fields are editable
A3: ADM (official) | C3: Values | E3: Notes | I3: Notes2
B4: Echo 40th | C4: 257 | E4: Estimate used at this point; need to replace. Find official 40th day ADM for Echo (enter audited)
B5: Echo 100th | C5: 257 | E5: Estimate used at this point; need to replace. Find official 100th day ADM for Echo (enter audited)
B6: Pima 40th | C6: 296 | E6: Estimate used at this point; need to replace. Find official 40th day ADM for Pima (enter audited)
B7: Pima 100th | C7: 296 | E7: Estimate used at this point; need to replace. Find official 100th day ADM for Pima (enter audited)
B8: Use Day (40 or 100) | C8: 40 | E8: Choose which count the model uses (40 or 100).
B10: Echo_ADM0 (selected) | C10: =IF(C8=40,C4,C5) -> 257 | E10: Model‑read Echo_ADM0 selected based on 40/100 day switch.
B11: Pima_ADM0 (selected) | C11: =IF(C8=40,C6,C7) -> 296 | E11: Model‑read Pima_ADM0 selected based on 40/100 day switch.
A13: M&O/ADM (district), audited (ACFR)
B14: M_O_per_ADM_Audited | C14: 11589 | E14: Estimate used at this point. Enter the audited districtwide Maintenance & Operations cost per ADM from the latest ACFR/Adopted Budget. Used as the FY25 base.
A16: Override — property‑tax override
B17: Override percent | C17: 0.15 | E17: Districtwide override percent (e.g., 15%).
B18: Base aid per ADM (proxy for RCL per pupil) | C18: 5013 | E18: Proxy base for calculating per‑ADM override; replace with RCL per pupil if available.
B19: Override per ADM (proxy) | C19: =C17*C18 -> 751.95 | E19: Computed per‑ADM amount used wherever the model needs a per‑student override term.
B20: Override toggle (1=on, 0=off) | C20: 1 | E20: Global on/off switch for including override in revenue calculations.
B21: Other General Fund revenue per served ADM (optional uplift) | C21: 5200 | E21: Everything not in “Base Aid + Override”: add‑on weights (e.g., SPED Group A/B), Transportation Support Level (TSL), and District Additional Assistance (DAA) — all components of the Equalization Base. (The Legislature’s primer shows Equalization Base = BSL + TSL + DAA, BLA = $5,013.33 in FY25. General Fund (Fund 001) revenues, FY2024 (actual): $192.213M (property taxes + state aid & grants). resources.finalsite.net Using SUSD’s FY2024 ACFR (audited): General Fund revenues (FY2024) = $215.4M (MD&A notes), General Fund expenditures = $233.7M. Scottsdale Unified School District Average Daily Membership (FY2024) = 19,748 (Operating Statistics table). Scottsdale Unified School District → GF revenue per ADM ≈ $215.4M / 19,748 ≈ $10,900/ADM. | I21: Using SUSD’s FY2024 ACFR (audited): General Fund revenues (FY2024) = $215.4M (MD&A notes), General Fund expenditures = $233.7M. Scottsdale Unified School District Average Daily Membership (FY2024) = 19,748 (Operating Statistics table). Scottsdale Unified School District → GF revenue per ADM ≈ $215.4M / 19,748 ≈ $10,900/ADM. State base amounts (policy context): FY2024 Base Level Amount (BLA) = $4,914.71. Arizona Department of Education FY2025 BLA = $5,013.33 (Senate research issue brief; also reiterates Equalization Base = BSL + TSL + DAA). Arizona Legislature Your model treats revenue as Aid (BLA‑based) + Override (+ optional uplift). To reconcile absolute Nets with audited magnitudes, we add an uplift that approximates everything in GF that isn’t “base + override,” e.g., TSL, DAA, formula add‑ons/weights, Prop 123 allocations, etc. (that’s what the Equalization Base framework is capturing when you aggregate components). Arizona Legislature Two reasonable calibration anchors: FY2024 basis: Uplift ≈ GF revenue per ADM − (BLA + Override) ≈ 10,900 − (4,914.71 + 0.15 × 4,914.71) ≈ 10,900 − (4,914.71 + 737) ≈ $5,250/ADM (rounded). Scottsdale Unified School District +2 Scottsdale Unified School District +2 FY2025 basis: Uplift ≈ 10,900 − (5,013.33 + 0.15 × 5,013.33) ≈ 10,900 − (5,013.33 + 752) ≈ $5,135/ADM (rounded). Scottsdale Unified School District +2 Scottsdale Unified School District +2 Uplift $5,100–$5,300/ADM is defensible on FY24 data and the state’s formula structure.
B22: Aid per ADM annual growth | C22: 0.025 | E22: Assuming aid grows around the same rate as cost inflation.
B23: Retention r — Echo (central) | C23: 0.6 | E23: Share of displaced Echo students re-enrolling in SUSD (0–1). As a choice school with 50% or more of families living outside the district, we can assume this will be lower than Pima.
B24: Retention r — Pima (central) | C24: 0.85 | E24: Share of displaced Pima students re-enrolling in SUSD (0–1). Not a significant amount of research on retention from closed schools; Chicago public retained 90%+ of students who were majority in boundaries when closing schools.
A26: Capital Treatment & Growth Capex (DRAFT placeholders)
B28: Include TI in Operating M&O? (0/1) | C28: 0 | E28: 0 = treat TI as capital (exclude from operating nets); 1 = include TI in Comparable_MO$
B29: TI per closed site (one-time) | C29: =BaselineCalc!$B$22 -> 1200000 | E29: “TI” = tenant improvements / transition investments needed to convert a K‑8 to a different use (early learning, admin consolidation) and carry costs in year one (e.g., abatement, doors/security, low‑voltage re‑work, furniture, swing space); DRAFT Ops TI: Mirrors BaselineCalc TI unit; replace with capital plan when available
B30: Growth Capex — Arts Hub (one-time) | C30: 800000 | E30: DRAFT placeholder; enter benchmarked capital required to enable Arts hub
B31: Growth Capex — Innovation Hub (one-time) | C31: 1200000 | E31: DRAFT placeholder; enter benchmarked capital required for Innovation hub
B32: Include Growth Capex in Operating? (0/1) | C32: 0 | E32: 0 = treat growth capex as capital (recommended); 1 = include in Comparable_MO$ (what‑if only)
B33: TI per closed site (lease case) | C33: 800000 | E33: DRAFT: lease TI placeholder; separate from ops TI (C27)
B34: Portable seat cost (capital $ per seat) | C34: 12000 | E34: DRAFT: per-seat portables or TI to add seats at receivers
B35: Spare K–5 seats across receivers (FY26) | C35: 300 | E35: User input: available elementary seats to absorb retained K–5
B36: Spare 6–8 seats across receivers (FY26) | C36: 100 | E36: User input: available middle seats to absorb retained 6–8
B38: Echo K–5 share of ADM | C38: 0.7 | E38: DRAFT: distribution of Echo ADM by grade band
B39: Echo 6–8 share of ADM | C39: 0.3
B40: Pima K–5 share of ADM | C40: 1
B41: Pima 6–8 share of ADM | C41: 0
B43: MarginalFactor_for_Overlay (central source) | C43: 0.6 | E43: Assuming marginal cost (as a function of standard variable cost per student) of new students from growth (assuming there is available capacity in Echo and Pima; ideally, this would be a step function)
B44: Echo ADM trend default | C44: -0.02 | E44: Default enrollment trend from forecasts; placeholder value for now -- need to verify this
B45: Pima ADM trend default | C45: -0.02 | E45: Default enrollment trend from forecasts; placeholder value for now -- need to verify this
B47: Growth overhead per added ADM (α × h) | C47: 0.2 | E47: Assuming some incremental transportation overhead for growth-related new students; we model it as a percentage of closed school transition-related incremental transportation overhead
B49: Incremental uplift alpha (overlay share of base uplift) | C49: 0.85 | E49: Applied only to Overlay_ADM; keeps marginal revenue conservative because some ‘other GF’ (weights/TSL/DAA) don’t scale 1:1. Typical range 0.70–0.90 (default 0.85).

Sheet Inputs_Definitions_Sources
A1: Audited & Policy Anchors (paste into Parameters when available)
A2: Anchor | B2: Value / Status | C2: Source (short) | D2: Used for | E2: Owner | F2: Paste location | G2: Source URL
A3: BLA (Base Level Amount) FY2025 | B3: 5,013.33 | C3: AZ Senate Issue Brief / ADE update | D3: YearMap → Aid$ | E3: Finance | F3: Parameters_Public!C18 or BaselineCalc | G3: https://www.azleg.gov/Briefs/Senate/ARIZONA%27S%20SCHOOL%20FINANCE%20SYSTEM%202024.PDF
A4: M&O Override % | B4: 15% (RCL) | C4: SUSD M&O Override page | D4: Override per ADM; Revenue$ | E4: Finance | F4: Parameters_Public!C17 | G4: https://www.susd.org/Page/658
A5: Override toggle | B5: 0/1 (board policy) | C5: Model control | D5: Revenue$ switch | E5: Model | F5: Parameters_Public!C20
A6: District M&O per ADM (audited) | B6: FY2024 value (e.g., 14,049) | C6: SUSD ACFR FY2024, Operating Statistics | D6: Sanity checks / narratives | E6: Finance | F6: Parameters_Public!C14
A7: Transportation Support Level (TSL) | B7: Per route‑mile schedule | C7: AZ Senate Issue Brief / ADE | D7: Revenue context | E7: Finance | F7: Definitions_Sources | G7: https://www.azed.gov/finance/fy2025-school-finance-fiscal-operations-updates
A8: Transport cost per eligible rider | B8: ≈ 3,183 (FY2024 anchor) | C8: City of Scottsdale Auditor report | D8: h₀ (retention overhead) anchor | E8: Ops | F8: Control_Center | G8: https://www.scottsdaleaz.gov/docs/default-source/scottsdaleaz/auditor/2025-reports/susd-transportation---audit-2508.pdf?sfvrsn=144e4f2d_1
A9: Echo/Pima 40th & 100th (FY2025) | B9: To paste (AzEDS export SDADMS72/75) | C9: ADE School Finance / District export | D9: Base ADM by site | E9: Data | F9: Parameters_Public | G9: https://www.ade.az.gov/schoolfinance/Reports
A10: Site‑fixed ledgers (Fund 001, by site) | B10: To paste (Echo & Pima) | C10: SUSD Finance site/cost‑center ledgers | D10: Replace fallback fixed | E10: Finance | F10: Site_Fixed | G10: https://www.azauditor.gov/arizona-school-district-spending-fiscal-year-2024-analysis-and-data-file
A12: Core Definitions & Derivations
A13: Term | B13: Definition / Formula | C13: Appears on | D13: Depends on | E13: Notes | F13: Named range (if any)
A14: Operating Net ($) | B14: M&O − (Aid + Override + Uplift); capital excluded. | C14: Summary_Figures; Scenario_Comparison; Board_OnePager | D14: YearMap revenues, MultiYear_ProForma costs | E14: Fund 001 lens only.
A15: Δ vs Base (FY2030) | B15: Comparator FY2030 Net − Base FY2030 Net. | C15: Summary_Figures; Scenario_Comparison | D15: Net$
A16: Δ vs Base (Avg FY26–30) | B16: Comparator 5‑yr Avg Net − Base 5‑yr Avg Net. | C16: Summary_Figures; Scenario_Comparison | D16: Net$ FY26..30
A17: Displaced (FY26) | B17: Displaced students in first action year. | C17: Summary_Figures; Scenario_Comparison | D17: Scenario mechanics
A18: Served (FY2030) | B18: Open + retained ADM in FY2030. | C18: Summary_Figures; Scenario_Comparison | D18: Served_ADM (MPF col AC)
A19: Comparable net per served | B19: FY2030 Net ÷ FY2030 Served_ADM. | C19: Optional on Summary_Figures | D19: Net$, Served_ADM | E19: Normalization when served counts differ.
A20: mᵗ (incremental margin per ADM) | B20: Aid + Override_if_on + Uplift − VarUnit$ − g | C20: Budget_Neutral_Calculator | D20: YearMap; Override_toggle | E20: Year‑specific.
A21: N⁰ (budget‑neutral students) | B21: max(0, −Netₜ / mᵗ) | C21: Budget_Neutral_Calculator | D21: mᵗ; Netₜ | E21: Shown for FY26 & FY30.
A22: Uplift (base) | B22: Other GF per served ADM; indexed with Aid growth. | C22: YearMap (Uplift_per_ADM) | D22: Aid_growth; Uplift_base_per_ADM | F22: Uplift_base_per_ADM
A23: Uplift (incremental) | B23: α × Uplift(base) applied to Overlay_ADM only. | C23: YearMap; Revenue$ | D23: Incremental_uplift_alpha | E23: Keeps marginal revenue conservative. | F23: Incremental_uplift_alpha
A24: Retention overhead (h) | B24: Routing/admin overhead per retained student; tapers annually. | C24: YearMap (h) | D24: h_taper_profile | E24: First‑year set from transport cost anchor. | F24: h_taper_profile
A25: Growth overhead (g) | B25: α × h applied to Overlay_ADM. | C25: YearMap (Growth_overhead_per_ADM) | D25: Growth_overhead_alpha; h_taper_profile | E25: Smaller than h; symmetry with repurpose. | F25: Growth_overhead_alpha
A26: Fixed savings realization | B26: Savings = (1−f)×SiteFixed$; f_ops, f_lease ramp FY26→FY30. | C26: MPF (EchoFixedEff$, PimaFixedEff$) | D26: f_ops_profile; f_lease_profile; Site_Fixed | E26: Replace fallback with audited site‑fixed. | F26: f_ops_profile; f_lease_profile
A27: Trend gates | B27: Apply_Echo_Trend / Apply_Pima_Trend toggle Potential_ADM by site. | C27: Scenarios; MPF | D27: Scenarios columns R/S; Parameters_Public trends | E27: On by scenario.
A28: ADM (Average Daily Membership) | B28: Unweighted attendance measure used for funding: membership days through the first 100 instructional days (or 200 for year-round) divided by days in period; see A.R.S. 15-901(1). | C28: Parameters; Baselines; Narrative | D28: ADE statute/SDADMS calculations | E28: Pre-K typically excluded from ADM for formula funding.
A29: Variable unit cost (VarUnit$) | B29: $ per served student covering incremental staffing, aides, supplies, and a small transport slice; indexed by MO inflation. | C29: YearMap; Revenue$/Adj_MO$ | D29: MO inflation; baseline unit cost | E29: Used in mᵗ = revenues − VarUnit$ − g.
A30: Marginal-cost factor for overlay seats | B30: Factor (<1) scaling VarUnit$ on overlay ADM to reflect partial sectioning in slack capacity years. | C30: MultiYear_Pro_Forma | D30: Parameters_Public MarginalFactor_for_Overlay | E30: Default 0.50; tune with scheduling/sectioning review.
A31: Retention rate r | B31: Share of displaced students who stay in SUSD and are re-routed to receiving sites; they remain in Served_ADM and incur h. | C31: Scenarios; MultiYear_Pro_Forma | D31: Parameters_Public r values | E31: Higher r keeps revenue but increases overhead h.
A32: Co-location extra savings | B32: Additional operating savings (beyond standard f_ops) modeled when consolidating two programs on one site. | C32: Scenarios; MultiYear_Pro_Forma | D32: Control_Center setting; scenario flags | E32: Small effect; fine-tune with facilities/ops.
A33: Keep-open ops savings | B33: Minor efficiency factor applied to scenarios that keep a site open (e.g., utilities, scheduling refinements). | C33: Scenarios; MultiYear_Pro_Forma | D33: Control_Center setting | E33: Small symmetric adjustment for fairness.
A35: Repurpose-related pathway parameters
A36: Gate / Mechanism | B36: How enforced in model | C36: What to watch | D36: Where implemented | E36: Notes | F36: Owner
A37: Receiving capacity gate | B37: Band‑level spare seats + portables; flag if exceeded. | C37: No site over capacity. | D37: Receiving_Capacity; Scenario_Comparison | F37: Planning
A38: Quality gate (optional) | B38: Receiving schools must meet program‑quality threshold. | C38: Define threshold. | D38: TBD (outside model) | E38: Narrative tie‑in. | F38: Academics
A39: Retention gate | B39: Retention r applied to displaced cohorts. | C39: Measure r achieved. | D39: Parameters_Public; MPF | E39: Supports r* framing if needed. | F39: Enrollment
A40: Budget neutrality | B40: N⁰ calculator for FY26/FY30. | C40: N⁰ = 0 means Net≥0. | D40: Budget_Neutral_Calculator | E40: Scenario‑specific. | F40: Finance
A41: Fixed savings realization | B41: f_ops/f_lease ramp applied to site‑fixed. | C41: Use audited site‑fixed; avoid over‑crediting. | D41: YearMap; MPF | F41: Finance/Ops
A43: Audit paste checklist (to finalize model)
A44: Data item | B44: Status | C44: Source | D44: Paste location | E44: Note
A45: Echo—site‑fixed (Fund 001 by function) | B45: Pending | C45: SUSD Finance site ledger | D45: Site_Fixed | E45: Using estimated figures in site_fixed tab for now
A46: Pima—site‑fixed (Fund 001 by function) | B46: Pending | C46: SUSD Finance site ledger | D46: Site_Fixed | E46: Using estimated figures in site_fixed tab for now
A47: Echo/Pima 40th/100th (FY2025) | B47: Pending | C47: AzEDS SDADMS72/75 export | D47: Parameters_Public
A48: Transport cost unit anchors | B48: Drafted | C48: City of Scottsdale audit | D48: Control_Center (h₀; α)
A50: Other items / additional descriptions
A51: Item | B51: What | C51: Detail
A52: ADM | B52: ADM stands for Average Daily Membership. It is the primary metric used by the state of Arizona to determine funding for a school district. What it is: ADM is essentially the official student count. It is not based on how many students are present on any single day (that would be average daily attendance), but rather on how many students are officially enrolled in the district. | C52: How it's calculated: The state uses enrollment data from specific points in the school year to generate an average. This average, the ADM, becomes the official "student count" for that fiscal year. Why it matters: Nearly all state funding is allocated on a per-student basis using ADM. This number is multiplied by various weights (e.g., for high school students, special education, etc.) to create a "weighted student count," which is the foundational number for calculating the district's total state aid. An audit of SUSD's ADM, for example, is a check to ensure the district reported its enrollment correctly and received the proper amount of funding.
A53: M&O | B53: M&O stands for Maintenance and Operations. This is the largest and most important part of a school district's budget. What it is: The M&O budget is the "bucket" of money that pays for all the day-to-day, non-capital expenses of running the school district. It is the district's operating budget. | C53: What it pays for: Salaries and benefits for all employees (teachers, principals, support staff, administrators) Classroom supplies (textbooks, software, paper, etc.) Utilities (electricity, water, gas) Transportation (bus fuel and maintenance) Student services and athletics
A54: Base state aid per pupil (FY2025) | B54: Revenue per ADM in “Aid per ADM” line; grown by CPI in out‑years (model uses a placeholder near $5.1k) | C54: Arizona FY2025 budget bill (HB 2906) sets the base level per pupil at $5,013 for FY2025. ADE School Finance memo for FY2025 base level (final), plus any FY2026 update; SUSD’s per‑pupil revenue schedule (by weight) if would like to add K‑8 weights locally. Arizona Senate Issue Brief – K‑12 School Finance (official, widely used reference). Shows the Base Level Amount (FY 2024‑25 = $5,013.33), the factor that (with district weights) drives state aid. ADE lists the same figure in its finance materials.
A55: Echo Canyon base ADM (≈257) | B55: Baseline students “served” in keep‑open scenarios | C55: ADE School Report Cards / Arizona Education Profiles (school pages) + SUSD 40th‑day board reports for Echo Canyon’s latest K‑8 enrollment ADE school page data used. SUSD October (40th‑day) ADM sheet listing Echo Canyon K‑8 ADM (most recent year) and the same for the prior 3 years.
A56: Pima base ADM (≈296) | B56: Baseline students “served” in keep‑open scenarios | C56: ADE School Report Cards page for Pima Traditional (enrollment tile). The “Enrollment” 🛈 on that page for the specific year has enrollment data.
A57: District M&O (Fund 001) context | B57: Grounds the “M&O per ADM” baseline used in comparable $/student | C57: From ACFR or adopted budget: Fund 001 totals and function detail by object/function; district ADM used in budget; site‑level M&O if available. | D57: Scottsdale USD ACFR FY2024 (annual comprehensive financial report) — Fund statements and notes establish M&O (Fund 001) totals and function splits (instruction, plant ops, admin, etc.). We used it to sanity‑check the order of magnitude for per‑pupil operating cost. (Scottsdale Unified School District)
A58: “Fixed‑like” share of M&O (used conservative placeholder) | B58: Splits total M&O into “semi‑fixed” (plant ops, insurance, admin, central) vs “variable” (classroom sections, supplies, a slice of transport) to compute EchoFixed$ and PimaFixed$ | C58: SUSD site‑level: plant ops/maintenance, insurance, utilities, admin FTE & benefits at Echo/Pima. Can use that to replace the proxy with real fixed amounts. The file allocates the fixed share across the two schools pro‑rata (by base ADM) as a temporary step. Can replace with the actual plant ops/insurance/utilities/admin for each site from Fund 001 to remove that simplification. | D58: Arizona Auditor General – Arizona School District Spending – FY2024 portal (official statewide analysis). The Overview and category definitions show the functional buckets (instruction, administration, plant operations & maintenance, student support, etc.) districts report and that we treat as the “more fixed‑like” categories. (sdspending.azauditor.gov)
A59: Overlay | B59: Using this term in the spreadsheet to mean addition of new students (growth) | C59: Not an official district term; just using in this spreadsheet
A60: Variable unit cost (VarUnit$) | B60: $ per student applied to “served ADM,” plus marginal‑cost factor on overlay seats | C60: Assumption derived from Fund 001 minus fixed share, divided by total ADM; then Marginal factor (see below) reduces cost for overlay seats. Can tighten with SUSD staffing ratios & actual sectioning at K–8; confirm what portion of M&O truly scales with added sections (teachers, aides, supplies, a slice of transport).
A61: Marginal‑cost factor for overlay seats | B61: Applies only to overlay growth students in keep‑open scenarios; models that not every dollar is average cost | C61: Can tighten with SUSD’s teacher‑section & aide staffing rules, average class sizes, and any marginal staffing adders at K–8 (arts, specialists). | D61: Assumption w/ rationale: Roughly half of per‑pupil cost is staffing/supplies/transport that scale with sections; the remainder is semi‑fixed plant/admin. This aligns with Auditor General function splits and is intentionally conservative. We’ll replace with SUSD’s staffing & plant data if provided. (Sun Devil Central)
A62: Receiving overhead “h” (FY26 $1,000 → FY30 $300) | B62: Per retained student transition/route/admin cost added when a site is repurposed; tapers as routes stabilize | C62: Assumption with AZ context: AZ districts’ transport spend per rider is often $2k–$3k (statewide average $2,862 cited in a district budget narrative), so $1,000 tapering to $300 is a conservative placeholder for incremental cost, not full bus cost. Can tighten with SUSD transportation cost per route-hour, average riders per route, and the specific route changes proposed in the repurpose option.
A63: Retention rate “r” (central 0.75; sensitivities 0.65–0.85) | B63: Share of displaced Echo+Pima students who remain in SUSD (the rest leave choose other options) | C63: SUSD post‑closure enrollment tracking (where displaced students re‑enroll), by receiving school; use that to set “r” from observed data. | D63: Assumption, benchmarked to closure research: large‑district closure work (e.g., Chicago) shows most students remain in‑district the next year (CPS analyses place that figure well above half); retention varies with hand‑off quality and distance. We model 65–85% to bracket. (UChicago Consortium on School Research) Large‑district evidence: UChicago Consortium’s analyses of the 2013 CPS closures found most displaced students remained in district the next year; outcomes varied with the quality and distance of receiving schools. That supports using a central r ~ 0.75 with a band. UChicago Consortium on School Research What we could not find in AZ: districts rarely publish explicit post‑closure retention; we can proxy from post‑closure enrollment by receiving schools if SUSD shares it. Echo nuance: Because Echo is open‑enrollment and draws many out‑of‑district students, those families may be less likely to follow to a different SUSD school after a closure (they already cross a boundary by choice). That argues for running a lower Echo‑weighted r scenario (e.g., 0.55–0.65) in addition to the district‑wide 0.65–0.85 band.
A64: Carry fractions f_ops / f_lease (e.g., 0.40 → 0 by FY30) | B64: Share of each site’s fixed costs that persist after repurpose under ops mothball vs lease/sale | C64: Assumption pending facilities plan. The glide‑path (e.g., 40%→30%→20%→10%→0%) reflects how fast plant/insurance/utilities can be retired or passed to a tenant.
A65: TI / one‑time repurpose costs (e.g., $2.4M) | B65: “TI_adds$” in the pro‑forma for the first 1–2 years. Why “Repurpose TI per closed site (FY26) = $1.2M”? What is “one‑time carry/TI”? “TI” = tenant improvements / transition investments needed to convert a K‑8 to a different use (early learning, admin consolidation) and carry costs in year one (e.g., abatement, doors/security, low‑voltage re‑work, furniture, swing space). A light‑touch repurpose can easily run $10–$20/sq‑ft; Echo’s plant is ~77k sq ft, so $1.2M is a reasonable placeholder (we are not assuming a huge remodel). Can replace this with SUSD’s scope/estimate if they have one. | C65: Tighten with SUSD engineering estimate for tenant improvements or district reconfiguration (scope, cost, which fund, and amortization).
A66: Extra cost savings for co-location scenario | B66: Why “Extra savings (co‑location) = 0.015 (1.5%)”? This reflects incremental savings from consolidating some services on one campus (custodial/grounds/partial routing). Again kept small and conservative; can use real custodial (sq‑ft), grounds and route deltas if available.
A67: Ops savings (for keep-open scenarios) | B67: Ops savings (keep‑open) = 0.007 (0.7%)”? This represents “light discipline” (utilities/purchasing tweaks, route smoothing) that does not depend on closing a site. Set low on purpose so it doesn’t drive results. Can calibrate with SUSD data (e.g., last year’s utility audits) if provided.
A68: K–8 capacity / square footage | B68: Context for “utilization” and whether overlay targets are feasible | C68: To be anchored to SFB (AZ School Facilities Board) capacity files and SUSD construction docs. SUSD/SFB: design capacity and current utilization for Echo & Pima (post‑rebuild specs for Pima).
A69: Pre‑K contribution | B69: Excluded from ADM and revenue in the model (unless tuition/lease modeled) | C69: If SUSD intends district‑operated tuition Pre‑K on site, can request pro forma for net contribution (tuition – staffing – TI). | D69: Supported by statute & ADE finance practice—general Pre‑K does not generate state ADM (exception: SPED preschool). (Arizona Department of Education)
A70: ADM definition (what “counts”) | B70: Explains why Pre‑K is excluded and why K can count at 0.5; supports “served” math | C70: SUSD’s 40th‑day and 100th‑day ADM certification for Echo and Pima (K–8 breakouts). | D70: A.R.S. §15‑901 and legislative fact sheet: Kindergarten generates 0.5 ADM unless full‑time; ADM is a statutory count, and preschool is generally not included in ADM (except some SPED programs). (LegiScan)
A71: MarginalFactor_for_Overlay | B71: Fraction of average per‑ADM MO$ that applies to added students when you grow keep‑open schools. | C71: Default 0.50 (i.e., ~half of average cost is truly variable: teachers/sections, supplies, some transport; the rest is plant/admin which doesn’t scale 1:1). | D71: Grounded in function splits from AAG/USFR: plant/admin/central ≈ 30–40% semi‑fixed, instruction/ops ≈ 60–70% variable; we start at 0.50 to be conservative. (Auditor General) | E71: If we get class‑size/FTE trigger rules, we can upgrade this to step‑functions (sections) by grade.
A72: Site_fixed tab | B72: Utilities are included in plant ops sub-cateogry for now, as an educated estimate was made from district budget information that does not de-couple utilities from plant ops. | C72: To be replaced with audited data when available.

Sheet Scenarios
C1: Yellow fields are editable
A2: ScenarioKey | B2: Label | C2: Enrollment add over 3 years | D2: CloseEcho (0 = no; 1 = yes) | E2: ClosePima (0 = no; 1 = yes) | F2: EchoShareDist (share of enrollment adds) | G2: ExtraSave (cost efficiency assumption) | H2: Notes | I2: Overlay_FY26 | J2: Overlay_FY27 | K2: Overlay_FY28 | L2: Overlay_FY29 | M2: Overlay_FY30 | N2: Carry | O2: Growth_Echo | P2: Growth_Pima | Q2: Apply_Echo_Trend | R2: Apply_Pima_Trend
A3: F1_CUSTOM1 | B3: CUSTOM_KeepOpen_v1 | C3: 0 | D3: 0 | E3: 0 | F3: 0.5 | G3: 0 | H3: Baseline + outreach; no closures | I3: =C3/3 -> 0 | J3: =I3+C3/3 -> 0 | K3: =J3+C3/3 -> 0 | L3: =C3 -> 0 | M3: =C3 -> 0 | O3: None | P3: None | Q3: 0 | R3: 0
A4: D4_StatusQuo_Targets | B4: Echo & Pima open; uplift warm handoff effort (intra-SUSD); initiate cross-district marketing | C4: 75 | D4: 0 | E4: 0 | F4: 0.5 | G4: 0 | H4: Baseline + targets; no closures | I4: =C4/3 -> 25 | J4: =I4+C4/3 -> 50 | K4: =J4+C4/3 -> 75 | L4: =C4 -> 75 | M4: =C4 -> 75 | O4: None | P4: None | Q4: 0 | R4: 0
A5: D3_CoLocation_Echo_Targets | B5: Echo & Pima open; co-locate e.g. district teacher learning center at Echo; uplift warm handoff effort (intra-SUSD); initiate cross-district marketing | C5: 50 | D5: 0 | E5: 0 | F5: 0.5 | G5: 0.05 | H5: Shared‑use efficiencies (no closure) | I5: =C5/3 -> 16.666667 | J5: =I5+C5/3 -> 33.333333 | K5: =J5+C5/3 -> 50 | L5: =C5 -> 50 | M5: =C5 -> 50 | O5: None | P5: None | Q5: 0 | R5: 0
A6: D1_Grow_Both_Targets | B6: Echo & Pima open; growth initiatives Echo (e.g. innovation) & Pima (e.g. arts); uplift warm handoff effort (intra-SUSD); initiate cross-district marketing | C6: 150 | D6: 0 | E6: 0 | F6: 0.5 | G6: 0 | H6: Baseline + growth initiatives | I6: =C6/3 -> 50 | J6: =I6+C6/3 -> 100 | K6: =J6+C6/3 -> 150 | L6: =C6 -> 150 | M6: =C6 -> 150 | O6: Innov | P6: Arts | Q6: 0 | R6: 0
A7: E2_StatusQuo_Steady | B7: Echo & Pima open; no operational or strategic growth actions; no change in enrollment | C7: 0 | D7: 0 | E7: 0 | F7: 0.5 | G7: 0 | H7: Baseline steady enrollment | I7: =C7/3 -> 0 | J7: =I7+C7/3 -> 0 | K7: =J7+C7/3 -> 0 | L7: =C7 -> 0 | M7: =C7 -> 0 | O7: None | P7: None | Q7: 0 | R7: 0
A8: D2_EchoGHubRamp_PimaTargets | B8: Echo & Pima open; growth initiative Echo (e.g. arts); no growth initiative Pima; uplift warm handoff effort (intra-SUSD); initiate cross-district marketing | C8: 125 | D8: 0 | E8: 0 | F8: 0.7 | G8: 0 | H8: Time‑phased ramp over years 1-3 | I8: =C8/3 -> 41.666667 | J8: =I8+C8/3 -> 83.333333 | K8: =J8+C8/3 -> 125 | L8: =C8 -> 125 | M8: =C8 -> 125 | O8: Arts | P8: None | Q8: 0 | R8: 0
A9: A2_Repurpose_Both_lease | B9: Repurpose both Echo & Pima; lease both properties; fixed cost reduction rate, retention %, and transition cost assumptions are key drivers | C9: 0 | D9: 1 | E9: 1 | F9: 0.5 | G9: 0 | H9: Repurpose both; lease/sale glide | I9: =C9/3 -> 0 | J9: =I9+C9/3 -> 0 | K9: =J9+C9/3 -> 0 | L9: =C9 -> 0 | M9: =C9 -> 0 | N9: lease | O9: None | P9: None | Q9: 0 | R9: 0
A10: A1_Repurpose_Both_ops | B10: Repurpose both Echo & Pima; operationally convert both properties (e.g. early learning center); fixed cost reduction rate, retention %, and transition cost assumptions are key drivers | C10: 0 | D10: 1 | E10: 1 | F10: 0.5 | G10: 0 | H10: Repurpose both; operations carry | I10: =C10/3 -> 0 | J10: =I10+C10/3 -> 0 | K10: =J10+C10/3 -> 0 | L10: =C10 -> 0 | M10: =C10 -> 0 | N10: ops | O10: None | P10: None | Q10: 0 | R10: 0
A11: B2_Repurpose_Echo_lease_PimaTargets | B11: Repurpose ECHO (lease) + Growth Hub @ Pima + Pima Op Growth Targets | C11: 50 | D11: 1 | E11: 0 | F11: 0 | G11: 0 | H11: Repurpose Echo only; lease glide | I11: =C11/3 -> 16.666667 | J11: =I11+C11/3 -> 33.333333 | K11: =J11+C11/3 -> 50 | L11: =C11 -> 50 | M11: =C11 -> 50 | N11: lease | O11: None | P11: Arts | Q11: 0 | R11: 0
A12: B1_Repurpose_Echo_ops_PimaTargets | B12: Repurpose ECHO (ops) + Growth Hub @ Pima + Pima Op Growth Targets | C12: 50 | D12: 1 | E12: 0 | F12: 0 | G12: 0 | H12: Repurpose Echo only; ops carry | I12: =C12/3 -> 16.666667 | J12: =I12+C12/3 -> 33.333333 | K12: =J12+C12/3 -> 50 | L12: =C12 -> 50 | M12: =C12 -> 50 | N12: ops | O12: None | P12: Arts | Q12: 0 | R12: 0
A13: C2_Repurpose_Pima_lease_EchoGHub_EchoTargets | B13: Repurpose PIMA (lease) + Growth Hub @ Echo + Echo Op Growth Targets | C13: 50 | D13: 0 | E13: 1 | F13: 1 | G13: 0 | H13: Repurpose Pima only; lease glide | I13: =C13/3 -> 16.666667 | J13: =I13+C13/3 -> 33.333333 | K13: =J13+C13/3 -> 50 | L13: =C13 -> 50 | M13: =C13 -> 50 | N13: lease | O13: Arts | P13: None | Q13: 0 | R13: 0
A14: C1_Repurpose_Pima_ops_EchoGHub_EchoTargets | B14: Repurpose PIMA (ops) + Growth Hub @ Echo + Echo Op Growth Targets | C14: 50 | D14: 0 | E14: 1 | F14: 1 | G14: 0 | H14: Repurpose Pima only; ops carry | I14: =C14/3 -> 16.666667 | J14: =I14+C14/3 -> 33.333333 | K14: =J14+C14/3 -> 50 | L14: =C14 -> 50 | M14: =C14 -> 50 | N14: ops | O14: Arts | P14: None | Q14: 0 | R14: 0
A15: E1_StatusQuo_Decline | B15: Echo & Pima open; no operational or strategic growth actions; enrollment decline trend continues | C15: 0 | D15: 0 | E15: 0 | F15: 0 | G15: 0 | H15: Keep open but decline per district forecast | I15: =C15/3 -> 0 | J15: =I15+C15/3 -> 0 | K15: =J15+C15/3 -> 0 | L15: =C15 -> 0 | M15: =C15 -> 0 | O15: None | P15: None | Q15: 1 | R15: 1
A27: ScenarioKey | B27: Year | C27: Echo_ADM | D27: Pima_ADM | E27: Total_ADM | F27: VarUnit$ | G27: EchoFixed$ | H27: PimaFixed$ | I27: Key | O27: None | P27: None
A28: =A3 -> F1_CUSTOM1 | B28: FY2026 | C28: =IF(D3=1,0, BaselineCalc!$B$7 + ROUND(I3*F3,0)) -> 257 | D28: =IF(E3=1,0, BaselineCalc!$B$8 + I3 - ROUND(I3*F3,0)) -> 296 | E28: =C28+D28 -> 553 | F28: =YearMap!B2 -> 8403.3633 | G28: =YearMap!C2 -> 922500 | H28: =YearMap!D2 -> 999375 | I28: =A28&"|"&B28 -> F1_CUSTOM1|FY2026 | O28: None | P28: None
A29: =A3 -> F1_CUSTOM1 | B29: FY2027 | C29: =IF(D3=1,0, BaselineCalc!$B$7 + ROUND(J3*F3,0)) -> 257 | D29: =IF(E3=1,0, BaselineCalc!$B$8 + J3 - ROUND(J3*F3,0)) -> 296 | E29: =C29+D29 -> 553 | F29: =YearMap!B3 -> 8613.4474 | G29: =YearMap!C3 -> 915497.15 | H29: =YearMap!D3 -> 1054424.7 | I29: =A29&"|"&B29 -> F1_CUSTOM1|FY2027 | O29: None | P29: None
A30: =A3 -> F1_CUSTOM1 | B30: FY2028 | C30: =IF(D3=1,0, BaselineCalc!$B$7 + ROUND(K3*F3,0)) -> 257 | D30: =IF(E3=1,0, BaselineCalc!$B$8 + K3 - ROUND(K3*F3,0)) -> 296 | E30: =C30+D30 -> 553 | F30: =YearMap!B4 -> 8828.7836 | G30: =YearMap!C4 -> 938384.57 | H30: =YearMap!D4 -> 1080785.3 | I30: =A30&"|"&B30 -> F1_CUSTOM1|FY2028 | O30: None | P30: None
A31: =A3 -> F1_CUSTOM1 | B31: FY2029 | C31: =IF(D3=1,0, BaselineCalc!$B$7 + ROUND(L3*F3,0)) -> 257 | D31: =IF(E3=1,0, BaselineCalc!$B$8 + L3 - ROUND(L3*F3,0)) -> 296 | E31: =C31+D31 -> 553 | F31: =YearMap!B5 -> 9049.5032 | G31: =YearMap!C5 -> 961844.19 | H31: =YearMap!D5 -> 1107805 | I31: =A31&"|"&B31 -> F1_CUSTOM1|FY2029 | O31: None | P31: None
A32: =A3 -> F1_CUSTOM1 | B32: FY2030 | C32: =IF(D3=1,0, BaselineCalc!$B$7 + ROUND(M3*F3,0)) -> 257 | D32: =IF(E3=1,0, BaselineCalc!$B$8 + M3 - ROUND(M3*F3,0)) -> 296 | E32: =C32+D32 -> 553 | F32: =YearMap!B6 -> 9275.7408 | G32: =YearMap!C6 -> 985890.29 | H32: =YearMap!D6 -> 1135500.1 | I32: =A32&"|"&B32 -> F1_CUSTOM1|FY2030 | O32: None | P32: None
A33: =A4 -> D4_StatusQuo_Targets | B33: FY2026 | C33: =IF(D4=1,0, BaselineCalc!$B$7 + ROUND(I4*F4,0)) -> 270 | D33: =IF(E4=1,0, BaselineCalc!$B$8 + I4 - ROUND(I4*F4,0)) -> 308 | E33: =C33+D33 -> 578 | F33: =YearMap!B2 -> 8403.3633 | G33: =YearMap!C2 -> 922500 | H33: =YearMap!D2 -> 999375 | I33: =A33&"|"&B33 -> D4_StatusQuo_Targets|FY2026 | O33: None | P33: None
A34: =A4 -> D4_StatusQuo_Targets | B34: FY2027 | C34: =IF(D4=1,0, BaselineCalc!$B$7 + ROUND(J4*F4,0)) -> 282 | D34: =IF(E4=1,0, BaselineCalc!$B$8 + J4 - ROUND(J4*F4,0)) -> 321 | E34: =C34+D34 -> 603 | F34: =YearMap!B3 -> 8613.4474 | G34: =YearMap!C3 -> 915497.15 | H34: =YearMap!D3 -> 1054424.7 | I34: =A34&"|"&B34 -> D4_StatusQuo_Targets|FY2027 | O34: None | P34: None
A35: =A4 -> D4_StatusQuo_Targets | B35: FY2028 | C35: =IF(D4=1,0, BaselineCalc!$B$7 + ROUND(K4*F4,0)) -> 295 | D35: =IF(E4=1,0, BaselineCalc!$B$8 + K4 - ROUND(K4*F4,0)) -> 333 | E35: =C35+D35 -> 628 | F35: =YearMap!B4 -> 8828.7836 | G35: =YearMap!C4 -> 938384.57 | H35: =YearMap!D4 -> 1080785.3 | I35: =A35&"|"&B35 -> D4_StatusQuo_Targets|FY2028 | O35: None | P35: None
A36: =A4 -> D4_StatusQuo_Targets | B36: FY2029 | C36: =IF(D4=1,0, BaselineCalc!$B$7 + ROUND(L4*F4,0)) -> 295 | D36: =IF(E4=1,0, BaselineCalc!$B$8 + L4 - ROUND(L4*F4,0)) -> 333 | E36: =C36+D36 -> 628 | F36: =YearMap!B5 -> 9049.5032 | G36: =YearMap!C5 -> 961844.19 | H36: =YearMap!D5 -> 1107805 | I36: =A36&"|"&B36 -> D4_StatusQuo_Targets|FY2029 | O36: None | P36: None
A37: =A4 -> D4_StatusQuo_Targets | B37: FY2030 | C37: =IF(D4=1,0, BaselineCalc!$B$7 + ROUND(M4*F4,0)) -> 295 | D37: =IF(E4=1,0, BaselineCalc!$B$8 + M4 - ROUND(M4*F4,0)) -> 333 | E37: =C37+D37 -> 628 | F37: =YearMap!B6 -> 9275.7408 | G37: =YearMap!C6 -> 985890.29 | H37: =YearMap!D6 -> 1135500.1 | I37: =A37&"|"&B37 -> D4_StatusQuo_Targets|FY2030 | O37: None | P37: None
A38: =A5 -> D3_CoLocation_Echo_Targets | B38: FY2026 | C38: =IF(D5=1,0, BaselineCalc!$B$7 + ROUND(I5*F5,0)) -> 265 | D38: =IF(E5=1,0, BaselineCalc!$B$8 + I5 - ROUND(I5*F5,0)) -> 304.66667 | E38: =C38+D38 -> 569.66667 | F38: =YearMap!B2 -> 8403.3633 | G38: =YearMap!C2 -> 922500 | H38: =YearMap!D2 -> 999375 | I38: =A38&"|"&B38 -> D3_CoLocation_Echo_Targets|FY2026 | O38: None | P38: None
A39: =A5 -> D3_CoLocation_Echo_Targets | B39: FY2027 | C39: =IF(D5=1,0, BaselineCalc!$B$7 + ROUND(J5*F5,0)) -> 274 | D39: =IF(E5=1,0, BaselineCalc!$B$8 + J5 - ROUND(J5*F5,0)) -> 312.33333 | E39: =C39+D39 -> 586.33333 | F39: =YearMap!B3 -> 8613.4474 | G39: =YearMap!C3 -> 915497.15 | H39: =YearMap!D3 -> 1054424.7 | I39: =A39&"|"&B39 -> D3_CoLocation_Echo_Targets|FY2027 | O39: None | P39: None
A40: =A5 -> D3_CoLocation_Echo_Targets | B40: FY2028 | C40: =IF(D5=1,0, BaselineCalc!$B$7 + ROUND(K5*F5,0)) -> 282 | D40: =IF(E5=1,0, BaselineCalc!$B$8 + K5 - ROUND(K5*F5,0)) -> 321 | E40: =C40+D40 -> 603 | F40: =YearMap!B4 -> 8828.7836 | G40: =YearMap!C4 -> 938384.57 | H40: =YearMap!D4 -> 1080785.3 | I40: =A40&"|"&B40 -> D3_CoLocation_Echo_Targets|FY2028 | O40: None | P40: None
A41: =A5 -> D3_CoLocation_Echo_Targets | B41: FY2029 | C41: =IF(D5=1,0, BaselineCalc!$B$7 + ROUND(L5*F5,0)) -> 282 | D41: =IF(E5=1,0, BaselineCalc!$B$8 + L5 - ROUND(L5*F5,0)) -> 321 | E41: =C41+D41 -> 603 | F41: =YearMap!B5 -> 9049.5032 | G41: =YearMap!C5 -> 961844.19 | H41: =YearMap!D5 -> 1107805 | I41: =A41&"|"&B41 -> D3_CoLocation_Echo_Targets|FY2029 | O41: None | P41: None
A42: =A5 -> D3_CoLocation_Echo_Targets | B42: FY2030 | C42: =IF(D5=1,0, BaselineCalc!$B$7 + ROUND(M5*F5,0)) -> 282 | D42: =IF(E5=1,0, BaselineCalc!$B$8 + M5 - ROUND(M5*F5,0)) -> 321 | E42: =C42+D42 -> 603 | F42: =YearMap!B6 -> 9275.7408 | G42: =YearMap!C6 -> 985890.29 | H42: =YearMap!D6 -> 1135500.1 | I42: =A42&"|"&B42 -> D3_CoLocation_Echo_Targets|FY2030 | O42: None | P42: None
A43: =A6 -> D1_Grow_Both_Targets | B43: FY2026 | C43: =IF(D6=1,0, BaselineCalc!$B$7 + ROUND(I6*F6,0)) -> 282 | D43: =IF(E6=1,0, BaselineCalc!$B$8 + I6 - ROUND(I6*F6,0)) -> 321 | E43: =C43+D43 -> 603 | F43: =YearMap!B2 -> 8403.3633 | G43: =YearMap!C2 -> 922500 | H43: =YearMap!D2 -> 999375 | I43: =A43&"|"&B43 -> D1_Grow_Both_Targets|FY2026 | O43: None | P43: None
A44: =A6 -> D1_Grow_Both_Targets | B44: FY2027 | C44: =IF(D6=1,0, BaselineCalc!$B$7 + ROUND(J6*F6,0)) -> 307 | D44: =IF(E6=1,0, BaselineCalc!$B$8 + J6 - ROUND(J6*F6,0)) -> 346 | E44: =C44+D44 -> 653 | F44: =YearMap!B3 -> 8613.4474 | G44: =YearMap!C3 -> 915497.15 | H44: =YearMap!D3 -> 1054424.7 | I44: =A44&"|"&B44 -> D1_Grow_Both_Targets|FY2027 | O44: None | P44: None
A45: =A6 -> D1_Grow_Both_Targets | B45: FY2028 | C45: =IF(D6=1,0, BaselineCalc!$B$7 + ROUND(K6*F6,0)) -> 332 | D45: =IF(E6=1,0, BaselineCalc!$B$8 + K6 - ROUND(K6*F6,0)) -> 371 | E45: =C45+D45 -> 703 | F45: =YearMap!B4 -> 8828.7836 | G45: =YearMap!C4 -> 938384.57 | H45: =YearMap!D4 -> 1080785.3 | I45: =A45&"|"&B45 -> D1_Grow_Both_Targets|FY2028 | O45: None | P45: None
A46: =A6 -> D1_Grow_Both_Targets | B46: FY2029 | C46: =IF(D6=1,0, BaselineCalc!$B$7 + ROUND(L6*F6,0)) -> 332 | D46: =IF(E6=1,0, BaselineCalc!$B$8 + L6 - ROUND(L6*F6,0)) -> 371 | E46: =C46+D46 -> 703 | F46: =YearMap!B5 -> 9049.5032 | G46: =YearMap!C5 -> 961844.19 | H46: =YearMap!D5 -> 1107805 | I46: =A46&"|"&B46 -> D1_Grow_Both_Targets|FY2029 | O46: None | P46: None
A47: =A6 -> D1_Grow_Both_Targets | B47: FY2030 | C47: =IF(D6=1,0, BaselineCalc!$B$7 + ROUND(M6*F6,0)) -> 332 | D47: =IF(E6=1,0, BaselineCalc!$B$8 + M6 - ROUND(M6*F6,0)) -> 371 | E47: =C47+D47 -> 703 | F47: =YearMap!B6 -> 9275.7408 | G47: =YearMap!C6 -> 985890.29 | H47: =YearMap!D6 -> 1135500.1 | I47: =A47&"|"&B47 -> D1_Grow_Both_Targets|FY2030 | O47: None | P47: None
A48: =A7 -> E2_StatusQuo_Steady | B48: FY2026 | C48: =IF(D7=1,0, BaselineCalc!$B$7 + ROUND(I7*F7,0)) -> 257 | D48: =IF(E7=1,0, BaselineCalc!$B$8 + I7 - ROUND(I7*F7,0)) -> 296 | E48: =C48+D48 -> 553 | F48: =YearMap!B2 -> 8403.3633 | G48: =YearMap!C2 -> 922500 | H48: =YearMap!D2 -> 999375 | I48: =A48&"|"&B48 -> E2_StatusQuo_Steady|FY2026 | O48: None | P48: None
A49: =A7 -> E2_StatusQuo_Steady | B49: FY2027 | C49: =IF(D7=1,0, BaselineCalc!$B$7 + ROUND(J7*F7,0)) -> 257 | D49: =IF(E7=1,0, BaselineCalc!$B$8 + J7 - ROUND(J7*F7,0)) -> 296 | E49: =C49+D49 -> 553 | F49: =YearMap!B3 -> 8613.4474 | G49: =YearMap!C3 -> 915497.15 | H49: =YearMap!D3 -> 1054424.7 | I49: =A49&"|"&B49 -> E2_StatusQuo_Steady|FY2027 | O49: None | P49: None
A50: =A7 -> E2_StatusQuo_Steady | B50: FY2028 | C50: =IF(D7=1,0, BaselineCalc!$B$7 + ROUND(K7*F7,0)) -> 257 | D50: =IF(E7=1,0, BaselineCalc!$B$8 + K7 - ROUND(K7*F7,0)) -> 296 | E50: =C50+D50 -> 553 | F50: =YearMap!B4 -> 8828.7836 | G50: =YearMap!C4 -> 938384.57 | H50: =YearMap!D4 -> 1080785.3 | I50: =A50&"|"&B50 -> E2_StatusQuo_Steady|FY2028 | O50: None | P50: None
A51: =A7 -> E2_StatusQuo_Steady | B51: FY2029 | C51: =IF(D7=1,0, BaselineCalc!$B$7 + ROUND(L7*F7,0)) -> 257 | D51: =IF(E7=1,0, BaselineCalc!$B$8 + L7 - ROUND(L7*F7,0)) -> 296 | E51: =C51+D51 -> 553 | F51: =YearMap!B5 -> 9049.5032 | G51: =YearMap!C5 -> 961844.19 | H51: =YearMap!D5 -> 1107805 | I51: =A51&"|"&B51 -> E2_StatusQuo_Steady|FY2029 | O51: None | P51: None
A52: =A7 -> E2_StatusQuo_Steady | B52: FY2030 | C52: =IF(D7=1,0, BaselineCalc!$B$7 + ROUND(M7*F7,0)) -> 257 | D52: =IF(E7=1,0, BaselineCalc!$B$8 + M7 - ROUND(M7*F7,0)) -> 296 | E52: =C52+D52 -> 553 | F52: =YearMap!B6 -> 9275.7408 | G52: =YearMap!C6 -> 985890.29 | H52: =YearMap!D6 -> 1135500.1 | I52: =A52&"|"&B52 -> E2_StatusQuo_Steady|FY2030 | O52: None | P52: None
A53: =A8 -> D2_EchoGHubRamp_PimaTargets | B53: FY2026 | C53: =IF(D8=1,0, BaselineCalc!$B$7 + ROUND(I8*F8,0)) -> 286 | D53: =IF(E8=1,0, BaselineCalc!$B$8 + I8 - ROUND(I8*F8,0)) -> 308.66667 | E53: =C53+D53 -> 594.66667 | F53: =YearMap!B2 -> 8403.3633 | G53: =YearMap!C2 -> 922500 | H53: =YearMap!D2 -> 999375 | I53: =A53&"|"&B53 -> D2_EchoGHubRamp_PimaTargets|FY2026 | O53: None | P53: None
A54: =A8 -> D2_EchoGHubRamp_PimaTargets | B54: FY2027 | C54: =IF(D8=1,0, BaselineCalc!$B$7 + ROUND(J8*F8,0)) -> 315 | D54: =IF(E8=1,0, BaselineCalc!$B$8 + J8 - ROUND(J8*F8,0)) -> 321.33333 | E54: =C54+D54 -> 636.33333 | F54: =YearMap!B3 -> 8613.4474 | G54: =YearMap!C3 -> 915497.15 | H54: =YearMap!D3 -> 1054424.7 | I54: =A54&"|"&B54 -> D2_EchoGHubRamp_PimaTargets|FY2027 | O54: None | P54: None
A55: =A8 -> D2_EchoGHubRamp_PimaTargets | B55: FY2028 | C55: =IF(D8=1,0, BaselineCalc!$B$7 + ROUND(K8*F8,0)) -> 345 | D55: =IF(E8=1,0, BaselineCalc!$B$8 + K8 - ROUND(K8*F8,0)) -> 333 | E55: =C55+D55 -> 678 | F55: =YearMap!B4 -> 8828.7836 | G55: =YearMap!C4 -> 938384.57 | H55: =YearMap!D4 -> 1080785.3 | I55: =A55&"|"&B55 -> D2_EchoGHubRamp_PimaTargets|FY2028 | O55: None | P55: None
A56: =A8 -> D2_EchoGHubRamp_PimaTargets | B56: FY2029 | C56: =IF(D8=1,0, BaselineCalc!$B$7 + ROUND(L8*F8,0)) -> 345 | D56: =IF(E8=1,0, BaselineCalc!$B$8 + L8 - ROUND(L8*F8,0)) -> 333 | E56: =C56+D56 -> 678 | F56: =YearMap!B5 -> 9049.5032 | G56: =YearMap!C5 -> 961844.19 | H56: =YearMap!D5 -> 1107805 | I56: =A56&"|"&B56 -> D2_EchoGHubRamp_PimaTargets|FY2029 | O56: None | P56: None
A57: =A8 -> D2_EchoGHubRamp_PimaTargets | B57: FY2030 | C57: =IF(D8=1,0, BaselineCalc!$B$7 + ROUND(M8*F8,0)) -> 345 | D57: =IF(E8=1,0, BaselineCalc!$B$8 + M8 - ROUND(M8*F8,0)) -> 333 | E57: =C57+D57 -> 678 | F57: =YearMap!B6 -> 9275.7408 | G57: =YearMap!C6 -> 985890.29 | H57: =YearMap!D6 -> 1135500.1 | I57: =A57&"|"&B57 -> D2_EchoGHubRamp_PimaTargets|FY2030 | O57: None | P57: None
A58: =A9 -> A2_Repurpose_Both_lease | B58: FY2026 | C58: =IF(D9=1,0, BaselineCalc!$B$7 + ROUND(I9*F9,0)) -> 0 | D58: =IF(E9=1,0, BaselineCalc!$B$8 + I9 - ROUND(I9*F9,0)) -> 0 | E58: =C58+D58 -> 0 | F58: =YearMap!B2 -> 8403.3633 | G58: =YearMap!C2 -> 922500 | H58: =YearMap!D2 -> 999375 | I58: =A58&"|"&B58 -> A2_Repurpose_Both_lease|FY2026 | O58: None | P58: None
A59: =A9 -> A2_Repurpose_Both_lease | B59: FY2027 | C59: =IF(D9=1,0, BaselineCalc!$B$7 + ROUND(J9*F9,0)) -> 0 | D59: =IF(E9=1,0, BaselineCalc!$B$8 + J9 - ROUND(J9*F9,0)) -> 0 | E59: =C59+D59 -> 0 | F59: =YearMap!B3 -> 8613.4474 | G59: =YearMap!C3 -> 915497.15 | H59: =YearMap!D3 -> 1054424.7 | I59: =A59&"|"&B59 -> A2_Repurpose_Both_lease|FY2027 | O59: None | P59: None
A60: =A9 -> A2_Repurpose_Both_lease | B60: FY2028 | C60: =IF(D9=1,0, BaselineCalc!$B$7 + ROUND(K9*F9,0)) -> 0 | D60: =IF(E9=1,0, BaselineCalc!$B$8 + K9 - ROUND(K9*F9,0)) -> 0 | E60: =C60+D60 -> 0 | F60: =YearMap!B4 -> 8828.7836 | G60: =YearMap!C4 -> 938384.57 | H60: =YearMap!D4 -> 1080785.3 | I60: =A60&"|"&B60 -> A2_Repurpose_Both_lease|FY2028 | O60: None | P60: None
A61: =A9 -> A2_Repurpose_Both_lease | B61: FY2029 | C61: =IF(D9=1,0, BaselineCalc!$B$7 + ROUND(L9*F9,0)) -> 0 | D61: =IF(E9=1,0, BaselineCalc!$B$8 + L9 - ROUND(L9*F9,0)) -> 0 | E61: =C61+D61 -> 0 | F61: =YearMap!B5 -> 9049.5032 | G61: =YearMap!C5 -> 961844.19 | H61: =YearMap!D5 -> 1107805 | I61: =A61&"|"&B61 -> A2_Repurpose_Both_lease|FY2029 | O61: None | P61: None
A62: =A9 -> A2_Repurpose_Both_lease | B62: FY2030 | C62: =IF(D9=1,0, BaselineCalc!$B$7 + ROUND(M9*F9,0)) -> 0 | D62: =IF(E9=1,0, BaselineCalc!$B$8 + M9 - ROUND(M9*F9,0)) -> 0 | E62: =C62+D62 -> 0 | F62: =YearMap!B6 -> 9275.7408 | G62: =YearMap!C6 -> 985890.29 | H62: =YearMap!D6 -> 1135500.1 | I62: =A62&"|"&B62 -> A2_Repurpose_Both_lease|FY2030 | O62: None | P62: None
A63: =A10 -> A1_Repurpose_Both_ops | B63: FY2026 | C63: =IF(D10=1,0, BaselineCalc!$B$7 + ROUND(I10*F10,0)) -> 0 | D63: =IF(E10=1,0, BaselineCalc!$B$8 + I10 - ROUND(I10*F10,0)) -> 0 | E63: =C63+D63 -> 0 | F63: =YearMap!B2 -> 8403.3633 | G63: =YearMap!C2 -> 922500 | H63: =YearMap!D2 -> 999375 | I63: =A63&"|"&B63 -> A1_Repurpose_Both_ops|FY2026 | O63: None | P63: None
A64: =A10 -> A1_Repurpose_Both_ops | B64: FY2027 | C64: =IF(D10=1,0, BaselineCalc!$B$7 + ROUND(J10*F10,0)) -> 0 | D64: =IF(E10=1,0, BaselineCalc!$B$8 + J10 - ROUND(J10*F10,0)) -> 0 | E64: =C64+D64 -> 0 | F64: =YearMap!B3 -> 8613.4474 | G64: =YearMap!C3 -> 915497.15 | H64: =YearMap!D3 -> 1054424.7 | I64: =A64&"|"&B64 -> A1_Repurpose_Both_ops|FY2027 | O64: None | P64: None
A65: =A10 -> A1_Repurpose_Both_ops | B65: FY2028 | C65: =IF(D10=1,0, BaselineCalc!$B$7 + ROUND(K10*F10,0)) -> 0 | D65: =IF(E10=1,0, BaselineCalc!$B$8 + K10 - ROUND(K10*F10,0)) -> 0 | E65: =C65+D65 -> 0 | F65: =YearMap!B4 -> 8828.7836 | G65: =YearMap!C4 -> 938384.57 | H65: =YearMap!D4 -> 1080785.3 | I65: =A65&"|"&B65 -> A1_Repurpose_Both_ops|FY2028 | O65: None | P65: None
A66: =A10 -> A1_Repurpose_Both_ops | B66: FY2029 | C66: =IF(D10=1,0, BaselineCalc!$B$7 + ROUND(L10*F10,0)) -> 0 | D66: =IF(E10=1,0, BaselineCalc!$B$8 + L10 - ROUND(L10*F10,0)) -> 0 | E66: =C66+D66 -> 0 | F66: =YearMap!B5 -> 9049.5032 | G66: =YearMap!C5 -> 961844.19 | H66: =YearMap!D5 -> 1107805 | I66: =A66&"|"&B66 -> A1_Repurpose_Both_ops|FY2029 | O66: None | P66: None
A67: =A10 -> A1_Repurpose_Both_ops | B67: FY2030 | C67: =IF(D10=1,0, BaselineCalc!$B$7 + ROUND(M10*F10,0)) -> 0 | D67: =IF(E10=1,0, BaselineCalc!$B$8 + M10 - ROUND(M10*F10,0)) -> 0 | E67: =C67+D67 -> 0 | F67: =YearMap!B6 -> 9275.7408 | G67: =YearMap!C6 -> 985890.29 | H67: =YearMap!D6 -> 1135500.1 | I67: =A67&"|"&B67 -> A1_Repurpose_Both_ops|FY2030 | O67: None | P67: None
A68: =A11 -> B2_Repurpose_Echo_lease_PimaTargets | B68: FY2026 | C68: =IF(D11=1,0, BaselineCalc!$B$7 + ROUND(I11*F11,0)) -> 0 | D68: =IF(E11=1,0, BaselineCalc!$B$8 + I11 - ROUND(I11*F11,0)) -> 312.66667 | E68: =C68+D68 -> 312.66667 | F68: =YearMap!B2 -> 8403.3633 | G68: =YearMap!C2 -> 922500 | H68: =YearMap!D2 -> 999375 | I68: =A68&"|"&B68 -> B2_Repurpose_Echo_lease_PimaTargets|FY2026 | O68: None | P68: None
A69: =A11 -> B2_Repurpose_Echo_lease_PimaTargets | B69: FY2027 | C69: =IF(D11=1,0, BaselineCalc!$B$7 + ROUND(J11*F11,0)) -> 0 | D69: =IF(E11=1,0, BaselineCalc!$B$8 + J11 - ROUND(J11*F11,0)) -> 329.33333 | E69: =C69+D69 -> 329.33333 | F69: =YearMap!B3 -> 8613.4474 | G69: =YearMap!C3 -> 915497.15 | H69: =YearMap!D3 -> 1054424.7 | I69: =A69&"|"&B69 -> B2_Repurpose_Echo_lease_PimaTargets|FY2027 | O69: None | P69: None
A70: =A11 -> B2_Repurpose_Echo_lease_PimaTargets | B70: FY2028 | C70: =IF(D11=1,0, BaselineCalc!$B$7 + ROUND(K11*F11,0)) -> 0 | D70: =IF(E11=1,0, BaselineCalc!$B$8 + K11 - ROUND(K11*F11,0)) -> 346 | E70: =C70+D70 -> 346 | F70: =YearMap!B4 -> 8828.7836 | G70: =YearMap!C4 -> 938384.57 | H70: =YearMap!D4 -> 1080785.3 | I70: =A70&"|"&B70 -> B2_Repurpose_Echo_lease_PimaTargets|FY2028 | O70: None | P70: None
A71: =A11 -> B2_Repurpose_Echo_lease_PimaTargets | B71: FY2029 | C71: =IF(D11=1,0, BaselineCalc!$B$7 + ROUND(L11*F11,0)) -> 0 | D71: =IF(E11=1,0, BaselineCalc!$B$8 + L11 - ROUND(L11*F11,0)) -> 346 | E71: =C71+D71 -> 346 | F71: =YearMap!B5 -> 9049.5032 | G71: =YearMap!C5 -> 961844.19 | H71: =YearMap!D5 -> 1107805 | I71: =A71&"|"&B71 -> B2_Repurpose_Echo_lease_PimaTargets|FY2029 | O71: None | P71: None
A72: =A11 -> B2_Repurpose_Echo_lease_PimaTargets | B72: FY2030 | C72: =IF(D11=1,0, BaselineCalc!$B$7 + ROUND(M11*F11,0)) -> 0 | D72: =IF(E11=1,0, BaselineCalc!$B$8 + M11 - ROUND(M11*F11,0)) -> 346 | E72: =C72+D72 -> 346 | F72: =YearMap!B6 -> 9275.7408 | G72: =YearMap!C6 -> 985890.29 | H72: =YearMap!D6 -> 1135500.1 | I72: =A72&"|"&B72 -> B2_Repurpose_Echo_lease_PimaTargets|FY2030 | O72: None | P72: None
A73: =A12 -> B1_Repurpose_Echo_ops_PimaTargets | B73: FY2026 | C73: =IF(D12=1,0, BaselineCalc!$B$7 + ROUND(I12*F12,0)) -> 0 | D73: =IF(E12=1,0, BaselineCalc!$B$8 + I12 - ROUND(I12*F12,0)) -> 312.66667 | E73: =C73+D73 -> 312.66667 | F73: =YearMap!B2 -> 8403.3633 | G73: =YearMap!C2 -> 922500 | H73: =YearMap!D2 -> 999375 | I73: =A73&"|"&B73 -> B1_Repurpose_Echo_ops_PimaTargets|FY2026 | O73: None | P73: None
A74: =A12 -> B1_Repurpose_Echo_ops_PimaTargets | B74: FY2027 | C74: =IF(D12=1,0, BaselineCalc!$B$7 + ROUND(J12*F12,0)) -> 0 | D74: =IF(E12=1,0, BaselineCalc!$B$8 + J12 - ROUND(J12*F12,0)) -> 329.33333 | E74: =C74+D74 -> 329.33333 | F74: =YearMap!B3 -> 8613.4474 | G74: =YearMap!C3 -> 915497.15 | H74: =YearMap!D3 -> 1054424.7 | I74: =A74&"|"&B74 -> B1_Repurpose_Echo_ops_PimaTargets|FY2027 | O74: None | P74: None
A75: =A12 -> B1_Repurpose_Echo_ops_PimaTargets | B75: FY2028 | C75: =IF(D12=1,0, BaselineCalc!$B$7 + ROUND(K12*F12,0)) -> 0 | D75: =IF(E12=1,0, BaselineCalc!$B$8 + K12 - ROUND(K12*F12,0)) -> 346 | E75: =C75+D75 -> 346 | F75: =YearMap!B4 -> 8828.7836 | G75: =YearMap!C4 -> 938384.57 | H75: =YearMap!D4 -> 1080785.3 | I75: =A75&"|"&B75 -> B1_Repurpose_Echo_ops_PimaTargets|FY2028 | O75: None | P75: None
A76: =A12 -> B1_Repurpose_Echo_ops_PimaTargets | B76: FY2029 | C76: =IF(D12=1,0, BaselineCalc!$B$7 + ROUND(L12*F12,0)) -> 0 | D76: =IF(E12=1,0, BaselineCalc!$B$8 + L12 - ROUND(L12*F12,0)) -> 346 | E76: =C76+D76 -> 346 | F76: =YearMap!B5 -> 9049.5032 | G76: =YearMap!C5 -> 961844.19 | H76: =YearMap!D5 -> 1107805 | I76: =A76&"|"&B76 -> B1_Repurpose_Echo_ops_PimaTargets|FY2029 | O76: None | P76: None
A77: =A12 -> B1_Repurpose_Echo_ops_PimaTargets | B77: FY2030 | C77: =IF(D12=1,0, BaselineCalc!$B$7 + ROUND(M12*F12,0)) -> 0 | D77: =IF(E12=1,0, BaselineCalc!$B$8 + M12 - ROUND(M12*F12,0)) -> 346 | E77: =C77+D77 -> 346 | F77: =YearMap!B6 -> 9275.7408 | G77: =YearMap!C6 -> 985890.29 | H77: =YearMap!D6 -> 1135500.1 | I77: =A77&"|"&B77 -> B1_Repurpose_Echo_ops_PimaTargets|FY2030 | O77: None | P77: None
A78: =A13 -> C2_Repurpose_Pima_lease_EchoGHub_EchoTargets | B78: FY2026 | C78: =IF(D13=1,0, BaselineCalc!$B$7 + ROUND(I13*F13,0)) -> 274 | D78: =IF(E13=1,0, BaselineCalc!$B$8 + I13 - ROUND(I13*F13,0)) -> 0 | E78: =C78+D78 -> 274 | F78: =YearMap!B2 -> 8403.3633 | G78: =YearMap!C2 -> 922500 | H78: =YearMap!D2 -> 999375 | I78: =A78&"|"&B78 -> C2_Repurpose_Pima_lease_EchoGHub_EchoTargets|FY2026 | O78: None | P78: None
A79: =A13 -> C2_Repurpose_Pima_lease_EchoGHub_EchoTargets | B79: FY2027 | C79: =IF(D13=1,0, BaselineCalc!$B$7 + ROUND(J13*F13,0)) -> 290 | D79: =IF(E13=1,0, BaselineCalc!$B$8 + J13 - ROUND(J13*F13,0)) -> 0 | E79: =C79+D79 -> 290 | F79: =YearMap!B3 -> 8613.4474 | G79: =YearMap!C3 -> 915497.15 | H79: =YearMap!D3 -> 1054424.7 | I79: =A79&"|"&B79 -> C2_Repurpose_Pima_lease_EchoGHub_EchoTargets|FY2027 | O79: None | P79: None
A80: =A13 -> C2_Repurpose_Pima_lease_EchoGHub_EchoTargets | B80: FY2028 | C80: =IF(D13=1,0, BaselineCalc!$B$7 + ROUND(K13*F13,0)) -> 307 | D80: =IF(E13=1,0, BaselineCalc!$B$8 + K13 - ROUND(K13*F13,0)) -> 0 | E80: =C80+D80 -> 307 | F80: =YearMap!B4 -> 8828.7836 | G80: =YearMap!C4 -> 938384.57 | H80: =YearMap!D4 -> 1080785.3 | I80: =A80&"|"&B80 -> C2_Repurpose_Pima_lease_EchoGHub_EchoTargets|FY2028 | O80: None | P80: None
A81: =A13 -> C2_Repurpose_Pima_lease_EchoGHub_EchoTargets | B81: FY2029 | C81: =IF(D13=1,0, BaselineCalc!$B$7 + ROUND(L13*F13,0)) -> 307 | D81: =IF(E13=1,0, BaselineCalc!$B$8 + L13 - ROUND(L13*F13,0)) -> 0 | E81: =C81+D81 -> 307 | F81: =YearMap!B5 -> 9049.5032 | G81: =YearMap!C5 -> 961844.19 | H81: =YearMap!D5 -> 1107805 | I81: =A81&"|"&B81 -> C2_Repurpose_Pima_lease_EchoGHub_EchoTargets|FY2029 | O81: None | P81: None
A82: =A13 -> C2_Repurpose_Pima_lease_EchoGHub_EchoTargets | B82: FY2030 | C82: =IF(D13=1,0, BaselineCalc!$B$7 + ROUND(M13*F13,0)) -> 307 | D82: =IF(E13=1,0, BaselineCalc!$B$8 + M13 - ROUND(M13*F13,0)) -> 0 | E82: =C82+D82 -> 307 | F82: =YearMap!B6 -> 9275.7408 | G82: =YearMap!C6 -> 985890.29 | H82: =YearMap!D6 -> 1135500.1 | I82: =A82&"|"&B82 -> C2_Repurpose_Pima_lease_EchoGHub_EchoTargets|FY2030 | O82: None | P82: None
A83: =A14 -> C1_Repurpose_Pima_ops_EchoGHub_EchoTargets | B83: FY2026 | C83: =IF(D14=1,0, BaselineCalc!$B$7 + ROUND(I14*F14,0)) -> 274 | D83: =IF(E14=1,0, BaselineCalc!$B$8 + I14 - ROUND(I14*F14,0)) -> 0 | E83: =C83+D83 -> 274 | F83: =YearMap!B2 -> 8403.3633 | G83: =YearMap!C2 -> 922500 | H83: =YearMap!D2 -> 999375 | I83: =A83&"|"&B83 -> C1_Repurpose_Pima_ops_EchoGHub_EchoTargets|FY2026 | O83: None | P83: None
A84: =A14 -> C1_Repurpose_Pima_ops_EchoGHub_EchoTargets | B84: FY2027 | C84: =IF(D14=1,0, BaselineCalc!$B$7 + ROUND(J14*F14,0)) -> 290 | D84: =IF(E14=1,0, BaselineCalc!$B$8 + J14 - ROUND(J14*F14,0)) -> 0 | E84: =C84+D84 -> 290 | F84: =YearMap!B3 -> 8613.4474 | G84: =YearMap!C3 -> 915497.15 | H84: =YearMap!D3 -> 1054424.7 | I84: =A84&"|"&B84 -> C1_Repurpose_Pima_ops_EchoGHub_EchoTargets|FY2027 | O84: None | P84: None
A85: =A14 -> C1_Repurpose_Pima_ops_EchoGHub_EchoTargets | B85: FY2028 | C85: =IF(D14=1,0, BaselineCalc!$B$7 + ROUND(K14*F14,0)) -> 307 | D85: =IF(E14=1,0, BaselineCalc!$B$8 + K14 - ROUND(K14*F14,0)) -> 0 | E85: =C85+D85 -> 307 | F85: =YearMap!B4 -> 8828.7836 | G85: =YearMap!C4 -> 938384.57 | H85: =YearMap!D4 -> 1080785.3 | I85: =A85&"|"&B85 -> C1_Repurpose_Pima_ops_EchoGHub_EchoTargets|FY2028 | O85: None | P85: None
A86: =A14 -> C1_Repurpose_Pima_ops_EchoGHub_EchoTargets | B86: FY2029 | C86: =IF(D14=1,0, BaselineCalc!$B$7 + ROUND(L14*F14,0)) -> 307 | D86: =IF(E14=1,0, BaselineCalc!$B$8 + L14 - ROUND(L14*F14,0)) -> 0 | E86: =C86+D86 -> 307 | F86: =YearMap!B5 -> 9049.5032 | G86: =YearMap!C5 -> 961844.19 | H86: =YearMap!D5 -> 1107805 | I86: =A86&"|"&B86 -> C1_Repurpose_Pima_ops_EchoGHub_EchoTargets|FY2029 | O86: None | P86: None
A87: =A14 -> C1_Repurpose_Pima_ops_EchoGHub_EchoTargets | B87: FY2030 | C87: =IF(D14=1,0, BaselineCalc!$B$7 + ROUND(M14*F14,0)) -> 307 | D87: =IF(E14=1,0, BaselineCalc!$B$8 + M14 - ROUND(M14*F14,0)) -> 0 | E87: =C87+D87 -> 307 | F87: =YearMap!B6 -> 9275.7408 | G87: =YearMap!C6 -> 985890.29 | H87: =YearMap!D6 -> 1135500.1 | I87: =A87&"|"&B87 -> C1_Repurpose_Pima_ops_EchoGHub_EchoTargets|FY2030 | O87: None | P87: None

Sheet MultiYear_ProForma
A1: =AG1 -> Key | B1: ScenarioKey | C1: Year | D1: Echo_ADM | E1: Pima_ADM | F1: Total_ADM | G1: VarUnit$ | H1: EchoFixed$ | I1: PimaFixed$ | J1: OpsFactor | K1: ExtraSave | L1: EchoPotential_ADM | M1: PimaPotential_ADM | N1: Displaced_ADM | O1: Retained_ADM | P1: h | Q1: CarryFrac | R1: EchoFixedEff$ | S1: PimaFixedEff$ | T1: TI_adds$ | U1: SiteCost$ | V1: RetainedSvc$ | W1: Comparable_MO$ | X1: Comparable_per_Student$ | Y1: Aid_per_ADM | Z1: Net_MO_after_aid$ | AA1: Net_per_served$ | AB1: Overlay_ADM | AC1: Served_ADM | AD1: Revenue$ | AE1: Adj_MO$ | AF1: Net$ | AG1: Key
A2: =AG2 -> F1_CUSTOM1|FY2026 | B2: =Scenarios!A3 -> F1_CUSTOM1 | C2: FY2026 | D2: =IF(Scenarios!D3=1,0, L2) -> 257 | E2: =IF(Scenarios!E3=1,0, M2) -> 296 | F2: =D2+E2 -> 553 | G2: =YearMap!B2 -> 8403.3633 | H2: =YearMap!C2 -> 922500 | I2: =YearMap!D2 -> 999375 | J2: =1-BaselineCalc!$B$5 -> 0.993 | K2: =Scenarios!G3 -> 0 | L2: =IF(Scenarios!$Q3=1,BaselineCalc!$B$7*(1+Parameters_Public!$C44)^(IF($C2="FY2026",0,IF($C2="FY2027",1,IF($C2="FY2028",2,IF($C2="FY2029",3,IF($C2="FY2030",4,0))))))+ROUND(Scenarios!I3*Scenarios!$F3,0),BaselineCalc!$B$7+ROUND(Scenarios!I3*Scenarios!$F3,0)) -> 257 | M2: =IF(Scenarios!$R3=1,BaselineCalc!$B$8*(1+Parameters_Public!$C45)^(IF($C2="FY2026",0,IF($C2="FY2027",1,IF($C2="FY2028",2,IF($C2="FY2029",3,IF($C2="FY2030",4,0))))))+Scenarios!I3-ROUND(Scenarios!I3*Scenarios!$F3,0),BaselineCalc!$B$8+Scenarios!I3-ROUND(Scenarios!I3*Scenarios!$F3,0)) -> 296 | N2: =(L2-D2) + (M2-E2) -> 0 | O2: =(Parameters_Public!$C$23*(L2-D2)+Parameters_Public!$C$24*(M2-E2)) -> 0 | P2: =YearMap!E2 -> 1000 | Q2: =IF(Scenarios!N3="lease", YearMap!F2, YearMap!G2) -> 0.45 | R2: =IF(Scenarios!D3=1, Q2*H2, H2) -> 922500 | S2: =IF(Scenarios!E3=1, Q2*I2, I2) -> 999375 | T2: =IF(C2="FY2026", (Scenarios!D3+Scenarios!E3)*BaselineCalc!$B$22, 0) -> 0 | U2: =(R2+S2+G2*F2)*J2*(1-K2) -> 6522952.4 | V2: =O2*(G2+P2) -> 0 | W2: =U2+V2+IF(Parameters_Public!$C$28=1, T2, 0) -> 6522952.4 | X2: =IF(F2+O2>0, W2/(F2+O2),"") -> 11795.574 | Y2: =INDEX(YearMap!$I$2:$I$6, MATCH(C2, YearMap!$A$2:$A$6, 0)) -> 5013 | Z2: =W2 - ((Y2 + IF(Parameters_Public!$C$20=1, Parameters_Public!$C$19, 0))*AC2) -> 3334935 | AA2: =IF($AC2>0, $Z2/$AC2, 0) -> 6030.6239 | AB2: =MAX(0, (MAX(0, $D2-BaselineCalc!$B$7) + MAX(0, $E2-BaselineCalc!$B$8))) -> 0 | AC2: =L2+M2-N2+O2 -> 553 | AD2: =( (Y2 + IF(Parameters_Public!$C20=1, INDEX(YearMap!$O$2:$O$6, MATCH(C2, YearMap!$A$2:$A$6, 0)), 0)) * AC2 ) + AC2*INDEX(YearMap!$P$2:$P$6, MATCH(C2, YearMap!$A$2:$A$6, 0)) + AB2*( INDEX(YearMap!$R$2:$R$6, MATCH(C2, YearMap!$A$2:$A$6, 0)) - INDEX(YearMap!$P$2:$P$6, MATCH(C2, YearMap!$A$2:$A$6, 0)) ) -> 6063617.3 | AE2: =(W2 - (1-Parameters_Public!$C$43)*$G2*$AB2*$J2*(1-$K2)) + AB2*INDEX(YearMap!$Q$2:$Q$6, MATCH(C2, YearMap!$A$2:$A$6, 0)) -> 6522952.4 | AF2: =AD2-AE2 -> -459335.03 | AG2: =B2&"|"&C2 -> F1_CUSTOM1|FY2026
A3: =AG3 -> F1_CUSTOM1|FY2027 | B3: =Scenarios!A3 -> F1_CUSTOM1 | C3: FY2027 | D3: =IF(Scenarios!D3=1,0, L3) -> 257 | E3: =IF(Scenarios!E3=1,0, M3) -> 296 | F3: =D3+E3 -> 553 | G3: =YearMap!B3 -> 8613.4474 | H3: =YearMap!C3 -> 915497.15 | I3: =YearMap!D3 -> 1054424.7 | J3: =1-BaselineCalc!$B$5 -> 0.993 | K3: =Scenarios!G3 -> 0 | L3: =IF(Scenarios!$Q3=1,BaselineCalc!$B$7*(1+Parameters_Public!$C44)^(IF($C3="FY2026",0,IF($C3="FY2027",1,IF($C3="FY2028",2,IF($C3="FY2029",3,IF($C3="FY2030",4,0))))))+ROUND(Scenarios!J3*Scenarios!$F3,0),BaselineCalc!$B$7+ROUND(Scenarios!J3*Scenarios!$F3,0)) -> 257 | M3: =IF(Scenarios!$R3=1,BaselineCalc!$B$8*(1+Parameters_Public!$C45)^(IF($C3="FY2026",0,IF($C3="FY2027",1,IF($C3="FY2028",2,IF($C3="FY2029",3,IF($C3="FY2030",4,0))))))+Scenarios!J3-ROUND(Scenarios!J3*Scenarios!$F3,0),BaselineCalc!$B$8+Scenarios!J3-ROUND(Scenarios!J3*Scenarios!$F3,0)) -> 296 | N3: =(L3-D3) + (M3-E3) -> 0 | O3: =(Parameters_Public!$C$23*(L3-D3)+Parameters_Public!$C$24*(M3-E3)) -> 0 | P3: =YearMap!E3 -> 800 | Q3: =IF(Scenarios!N3="lease", YearMap!F3, YearMap!G3) -> 0.4 | R3: =IF(Scenarios!D3=1, Q3*H3, H3) -> 915497.15 | S3: =IF(Scenarios!E3=1, Q3*I3, I3) -> 1054424.7 | T3: =IF(C3="FY2026", (Scenarios!D3+Scenarios!E3)*BaselineCalc!$B$22, 0) -> 0 | U3: =(R3+S3+G3*F3)*J3*(1-K3) -> 6686026.2 | V3: =O3*(G3+P3) -> 0 | W3: =U3+V3+IF(Parameters_Public!$C$28=1, T3, 0) -> 6686026.2 | X3: =IF(F3+O3>0, W3/(F3+O3),"") -> 12090.463 | Y3: =INDEX(YearMap!$I$2:$I$6, MATCH(C3, YearMap!$A$2:$A$6, 0)) -> 5138.325 | Z3: =W3 - ((Y3 + IF(Parameters_Public!$C$20=1, Parameters_Public!$C$19, 0))*AC3) -> 3428704.1 | AA3: =IF($AC3>0, $Z3/$AC3, 0) -> 6200.1883 | AB3: =MAX(0, (MAX(0, $D3-BaselineCalc!$B$7) + MAX(0, $E3-BaselineCalc!$B$8))) -> 0 | AC3: =L3+M3-N3+O3 -> 553 | AD3: =( (Y3 + IF(Parameters_Public!$C20=1, INDEX(YearMap!$O$2:$O$6, MATCH(C3, YearMap!$A$2:$A$6, 0)), 0)) * AC3 ) + AC3*INDEX(YearMap!$P$2:$P$6, MATCH(C3, YearMap!$A$2:$A$6, 0)) + AB3*( INDEX(YearMap!$R$2:$R$6, MATCH(C3, YearMap!$A$2:$A$6, 0)) - INDEX(YearMap!$P$2:$P$6, MATCH(C3, YearMap!$A$2:$A$6, 0)) ) -> 6215207.8 | AE3: =(W3 - (1-Parameters_Public!$C$43)*$G3*$AB3*$J3*(1-$K3)) + AB3*INDEX(YearMap!$Q$2:$Q$6, MATCH(C3, YearMap!$A$2:$A$6, 0)) -> 6686026.2 | AF3: =AD3-AE3 -> -470818.41 | AG3: =B3&"|"&C3 -> F1_CUSTOM1|FY2027
A4: =AG4 -> F1_CUSTOM1|FY2028 | B4: =Scenarios!A3 -> F1_CUSTOM1 | C4: FY2028 | D4: =IF(Scenarios!D3=1,0, L4) -> 257 | E4: =IF(Scenarios!E3=1,0, M4) -> 296 | F4: =D4+E4 -> 553 | G4: =YearMap!B4 -> 8828.7836 | H4: =YearMap!C4 -> 938384.57 | I4: =YearMap!D4 -> 1080785.3 | J4: =1-BaselineCalc!$B$5 -> 0.993 | K4: =Scenarios!G3 -> 0 | L4: =IF(Scenarios!$Q3=1,BaselineCalc!$B$7*(1+Parameters_Public!$C44)^(IF($C4="FY2026",0,IF($C4="FY2027",1,IF($C4="FY2028",2,IF($C4="FY2029",3,IF($C4="FY2030",4,0))))))+ROUND(Scenarios!K3*Scenarios!$F3,0),BaselineCalc!$B$7+ROUND(Scenarios!K3*Scenarios!$F3,0)) -> 257 | M4: =IF(Scenarios!$R3=1,BaselineCalc!$B$8*(1+Parameters_Public!$C45)^(IF($C4="FY2026",0,IF($C4="FY2027",1,IF($C4="FY2028",2,IF($C4="FY2029",3,IF($C4="FY2030",4,0))))))+Scenarios!K3-ROUND(Scenarios!K3*Scenarios!$F3,0),BaselineCalc!$B$8+Scenarios!K3-ROUND(Scenarios!K3*Scenarios!$F3,0)) -> 296 | N4: =(L4-D4) + (M4-E4) -> 0 | O4: =(Parameters_Public!$C$23*(L4-D4)+Parameters_Public!$C$24*(M4-E4)) -> 0 | P4: =YearMap!E4 -> 600 | Q4: =IF(Scenarios!N3="lease", YearMap!F4, YearMap!G4) -> 0.35 | R4: =IF(Scenarios!D3=1, Q4*H4, H4) -> 938384.57 | S4: =IF(Scenarios!E3=1, Q4*I4, I4) -> 1080785.3 | T4: =IF(C4="FY2026", (Scenarios!D3+Scenarios!E3)*BaselineCalc!$B$22, 0) -> 0 | U4: =(R4+S4+G4*F4)*J4*(1-K4) -> 6853176.8 | V4: =O4*(G4+P4) -> 0 | W4: =U4+V4+IF(Parameters_Public!$C$28=1, T4, 0) -> 6853176.8 | X4: =IF(F4+O4>0, W4/(F4+O4),"") -> 12392.725 | Y4: =INDEX(YearMap!$I$2:$I$6, MATCH(C4, YearMap!$A$2:$A$6, 0)) -> 5266.7831 | Z4: =W4 - ((Y4 + IF(Parameters_Public!$C$20=1, Parameters_Public!$C$19, 0))*AC4) -> 3524817.4 | AA4: =IF($AC4>0, $Z4/$AC4, 0) -> 6373.9917 | AB4: =MAX(0, (MAX(0, $D4-BaselineCalc!$B$7) + MAX(0, $E4-BaselineCalc!$B$8))) -> 0 | AC4: =L4+M4-N4+O4 -> 553 | AD4: =( (Y4 + IF(Parameters_Public!$C20=1, INDEX(YearMap!$O$2:$O$6, MATCH(C4, YearMap!$A$2:$A$6, 0)), 0)) * AC4 ) + AC4*INDEX(YearMap!$P$2:$P$6, MATCH(C4, YearMap!$A$2:$A$6, 0)) + AB4*( INDEX(YearMap!$R$2:$R$6, MATCH(C4, YearMap!$A$2:$A$6, 0)) - INDEX(YearMap!$P$2:$P$6, MATCH(C4, YearMap!$A$2:$A$6, 0)) ) -> 6370588 | AE4: =(W4 - (1-Parameters_Public!$C$43)*$G4*$AB4*$J4*(1-$K4)) + AB4*INDEX(YearMap!$Q$2:$Q$6, MATCH(C4, YearMap!$A$2:$A$6, 0)) -> 6853176.8 | AF4: =AD4-AE4 -> -482588.87 | AG4: =B4&"|"&C4 -> F1_CUSTOM1|FY2028
A5: =AG5 -> F1_CUSTOM1|FY2029 | B5: =Scenarios!A3 -> F1_CUSTOM1 | C5: FY2029 | D5: =IF(Scenarios!D3=1,0, L5) -> 257 | E5: =IF(Scenarios!E3=1,0, M5) -> 296 | F5: =D5+E5 -> 553 | G5: =YearMap!B5 -> 9049.5032 | H5: =YearMap!C5 -> 961844.19 | I5: =YearMap!D5 -> 1107805 | J5: =1-BaselineCalc!$B$5 -> 0.993 | K5: =Scenarios!G3 -> 0 | L5: =IF(Scenarios!$Q3=1,BaselineCalc!$B$7*(1+Parameters_Public!$C44)^(IF($C5="FY2026",0,IF($C5="FY2027",1,IF($C5="FY2028",2,IF($C5="FY2029",3,IF($C5="FY2030",4,0))))))+ROUND(Scenarios!L3*Scenarios!$F3,0),BaselineCalc!$B$7+ROUND(Scenarios!L3*Scenarios!$F3,0)) -> 257 | M5: =IF(Scenarios!$R3=1,BaselineCalc!$B$8*(1+Parameters_Public!$C45)^(IF($C5="FY2026",0,IF($C5="FY2027",1,IF($C5="FY2028",2,IF($C5="FY2029",3,IF($C5="FY2030",4,0))))))+Scenarios!L3-ROUND(Scenarios!L3*Scenarios!$F3,0),BaselineCalc!$B$8+Scenarios!L3-ROUND(Scenarios!L3*Scenarios!$F3,0)) -> 296 | N5: =(L5-D5) + (M5-E5) -> 0 | O5: =(Parameters_Public!$C$23*(L5-D5)+Parameters_Public!$C$24*(M5-E5)) -> 0 | P5: =YearMap!E5 -> 500 | Q5: =IF(Scenarios!N3="lease", YearMap!F5, YearMap!G5) -> 0.3 | R5: =IF(Scenarios!D3=1, Q5*H5, H5) -> 961844.19 | S5: =IF(Scenarios!E3=1, Q5*I5, I5) -> 1107805 | T5: =IF(C5="FY2026", (Scenarios!D3+Scenarios!E3)*BaselineCalc!$B$22, 0) -> 0 | U5: =(R5+S5+G5*F5)*J5*(1-K5) -> 7024506.3 | V5: =O5*(G5+P5) -> 0 | W5: =U5+V5+IF(Parameters_Public!$C$28=1, T5, 0) -> 7024506.3 | X5: =IF(F5+O5>0, W5/(F5+O5),"") -> 12702.543 | Y5: =INDEX(YearMap!$I$2:$I$6, MATCH(C5, YearMap!$A$2:$A$6, 0)) -> 5398.4527 | Z5: =W5 - ((Y5 + IF(Parameters_Public!$C$20=1, Parameters_Public!$C$19, 0))*AC5) -> 3623333.6 | AA5: =IF($AC5>0, $Z5/$AC5, 0) -> 6552.1403 | AB5: =MAX(0, (MAX(0, $D5-BaselineCalc!$B$7) + MAX(0, $E5-BaselineCalc!$B$8))) -> 0 | AC5: =L5+M5-N5+O5 -> 553 | AD5: =( (Y5 + IF(Parameters_Public!$C20=1, INDEX(YearMap!$O$2:$O$6, MATCH(C5, YearMap!$A$2:$A$6, 0)), 0)) * AC5 ) + AC5*INDEX(YearMap!$P$2:$P$6, MATCH(C5, YearMap!$A$2:$A$6, 0)) + AB5*( INDEX(YearMap!$R$2:$R$6, MATCH(C5, YearMap!$A$2:$A$6, 0)) - INDEX(YearMap!$P$2:$P$6, MATCH(C5, YearMap!$A$2:$A$6, 0)) ) -> 6529852.7 | AE5: =(W5 - (1-Parameters_Public!$C$43)*$G5*$AB5*$J5*(1-$K5)) + AB5*INDEX(YearMap!$Q$2:$Q$6, MATCH(C5, YearMap!$A$2:$A$6, 0)) -> 7024506.3 | AF5: =AD5-AE5 -> -494653.59 | AG5: =B5&"|"&C5 -> F1_CUSTOM1|FY2029
A6: =AG6 -> F1_CUSTOM1|FY2030 | B6: =Scenarios!A3 -> F1_CUSTOM1 | C6: FY2030 | D6: =IF(Scenarios!D3=1,0, L6) -> 257 | E6: =IF(Scenarios!E3=1,0, M6) -> 296 | F6: =D6+E6 -> 553 | G6: =YearMap!B6 -> 9275.7408 | H6: =YearMap!C6 -> 985890.29 | I6: =YearMap!D6 -> 1135500.1 | J6: =1-BaselineCalc!$B$5 -> 0.993 | K6: =Scenarios!G3 -> 0 | L6: =IF(Scenarios!$Q3=1,BaselineCalc!$B$7*(1+Parameters_Public!$C44)^(IF($C6="FY2026",0,IF($C6="FY2027",1,IF($C6="FY2028",2,IF($C6="FY2029",3,IF($C6="FY2030",4,0))))))+ROUND(Scenarios!M3*Scenarios!$F3,0),BaselineCalc!$B$7+ROUND(Scenarios!M3*Scenarios!$F3,0)) -> 257 | M6: =IF(Scenarios!$R3=1,BaselineCalc!$B$8*(1+Parameters_Public!$C45)^(IF($C6="FY2026",0,IF($C6="FY2027",1,IF($C6="FY2028",2,IF($C6="FY2029",3,IF($C6="FY2030",4,0))))))+Scenarios!M3-ROUND(Scenarios!M3*Scenarios!$F3,0),BaselineCalc!$B$8+Scenarios!M3-ROUND(Scenarios!M3*Scenarios!$F3,0)) -> 296 | N6: =(L6-D6) + (M6-E6) -> 0 | O6: =(Parameters_Public!$C$23*(L6-D6)+Parameters_Public!$C$24*(M6-E6)) -> 0 | P6: =YearMap!E6 -> 300 | Q6: =IF(Scenarios!N3="lease", YearMap!F6, YearMap!G6) -> 0.3 | R6: =IF(Scenarios!D3=1, Q6*H6, H6) -> 985890.29 | S6: =IF(Scenarios!E3=1, Q6*I6, I6) -> 1135500.1 | T6: =IF(C6="FY2026", (Scenarios!D3+Scenarios!E3)*BaselineCalc!$B$22, 0) -> 0 | U6: =(R6+S6+G6*F6)*J6*(1-K6) -> 7200118.9 | V6: =O6*(G6+P6) -> 0 | W6: =U6+V6+IF(Parameters_Public!$C$28=1, T6, 0) -> 7200118.9 | X6: =IF(F6+O6>0, W6/(F6+O6),"") -> 13020.107 | Y6: =INDEX(YearMap!$I$2:$I$6, MATCH(C6, YearMap!$A$2:$A$6, 0)) -> 5533.414 | Z6: =W6 - ((Y6 + IF(Parameters_Public!$C$20=1, Parameters_Public!$C$19, 0))*AC6) -> 3724312.6 | AA6: =IF($AC6>0, $Z6/$AC6, 0) -> 6734.7425 | AB6: =MAX(0, (MAX(0, $D6-BaselineCalc!$B$7) + MAX(0, $E6-BaselineCalc!$B$8))) -> 0 | AC6: =L6+M6-N6+O6 -> 553 | AD6: =( (Y6 + IF(Parameters_Public!$C20=1, INDEX(YearMap!$O$2:$O$6, MATCH(C6, YearMap!$A$2:$A$6, 0)), 0)) * AC6 ) + AC6*INDEX(YearMap!$P$2:$P$6, MATCH(C6, YearMap!$A$2:$A$6, 0)) + AB6*( INDEX(YearMap!$R$2:$R$6, MATCH(C6, YearMap!$A$2:$A$6, 0)) - INDEX(YearMap!$P$2:$P$6, MATCH(C6, YearMap!$A$2:$A$6, 0)) ) -> 6693099 | AE6: =(W6 - (1-Parameters_Public!$C$43)*$G6*$AB6*$J6*(1-$K6)) + AB6*INDEX(YearMap!$Q$2:$Q$6, MATCH(C6, YearMap!$A$2:$A$6, 0)) -> 7200118.9 | AF6: =AD6-AE6 -> -507019.93 | AG6: =B6&"|"&C6 -> F1_CUSTOM1|FY2030
A7: =AG7 -> D4_StatusQuo_Targets|FY2026 | B7: =Scenarios!A4 -> D4_StatusQuo_Targets | C7: FY2026 | D7: =IF(Scenarios!D4=1,0, L7) -> 270 | E7: =IF(Scenarios!E4=1,0, M7) -> 308 | F7: =D7+E7 -> 578 | G7: =YearMap!B2 -> 8403.3633 | H7: =YearMap!C2 -> 922500 | I7: =YearMap!D2 -> 999375 | J7: =1-BaselineCalc!$B$5 -> 0.993 | K7: =Scenarios!G4 -> 0 | L7: =IF(Scenarios!$Q4=1,BaselineCalc!$B$7*(1+Parameters_Public!$C44)^(IF($C7="FY2026",0,IF($C7="FY2027",1,IF($C7="FY2028",2,IF($C7="FY2029",3,IF($C7="FY2030",4,0))))))+ROUND(Scenarios!I4*Scenarios!$F4,0),BaselineCalc!$B$7+ROUND(Scenarios!I4*Scenarios!$F4,0)) -> 270 | M7: =IF(Scenarios!$R4=1,BaselineCalc!$B$8*(1+Parameters_Public!$C45)^(IF($C7="FY2026",0,IF($C7="FY2027",1,IF($C7="FY2028",2,IF($C7="FY2029",3,IF($C7="FY2030",4,0))))))+Scenarios!I4-ROUND(Scenarios!I4*Scenarios!$F4,0),BaselineCalc!$B$8+Scenarios!I4-ROUND(Scenarios!I4*Scenarios!$F4,0)) -> 308 | N7: =(L7-D7) + (M7-E7) -> 0 | O7: =(Parameters_Public!$C$23*(L7-D7)+Parameters_Public!$C$24*(M7-E7)) -> 0 | P7: =YearMap!E2 -> 1000 | Q7: =IF(Scenarios!N4="lease", YearMap!F2, YearMap!G2) -> 0.45 | R7: =IF(Scenarios!D4=1, Q7*H7, H7) -> 922500 | S7: =IF(Scenarios!E4=1, Q7*I7, I7) -> 999375 | T7: =IF(C7="FY2026", (Scenarios!D4+Scenarios!E4)*BaselineCalc!$B$22, 0) -> 0 | U7: =(R7+S7+G7*F7)*J7*(1-K7) -> 6731565.9 | V7: =O7*(G7+P7) -> 0 | W7: =U7+V7+IF(Parameters_Public!$C$28=1, T7, 0) -> 6731565.9 | X7: =IF(F7+O7>0, W7/(F7+O7),"") -> 11646.308 | Y7: =INDEX(YearMap!$I$2:$I$6, MATCH(C7, YearMap!$A$2:$A$6, 0)) -> 5013 | Z7: =W7 - ((Y7 + IF(Parameters_Public!$C$20=1, Parameters_Public!$C$19, 0))*AC7) -> 3399424.8 | AA7: =IF($AC7>0, $Z7/$AC7, 0) -> 5881.3577 | AB7: =MAX(0, (MAX(0, $D7-BaselineCalc!$B$7) + MAX(0, $E7-BaselineCalc!$B$8))) -> 25 | AC7: =L7+M7-N7+O7 -> 578 | AD7: =( (Y7 + IF(Parameters_Public!$C20=1, INDEX(YearMap!$O$2:$O$6, MATCH(C7, YearMap!$A$2:$A$6, 0)), 0)) * AC7 ) + AC7*INDEX(YearMap!$P$2:$P$6, MATCH(C7, YearMap!$A$2:$A$6, 0)) + AB7*( INDEX(YearMap!$R$2:$R$6, MATCH(C7, YearMap!$A$2:$A$6, 0)) - INDEX(YearMap!$P$2:$P$6, MATCH(C7, YearMap!$A$2:$A$6, 0)) ) -> 6318241.1 | AE7: =(W7 - (1-Parameters_Public!$C$43)*$G7*$AB7*$J7*(1-$K7)) + AB7*INDEX(YearMap!$Q$2:$Q$6, MATCH(C7, YearMap!$A$2:$A$6, 0)) -> 6653120.5 | AF7: =AD7-AE7 -> -334879.38 | AG7: =B7&"|"&C7 -> D4_StatusQuo_Targets|FY2026
A8: =AG8 -> D4_StatusQuo_Targets|FY2027 | B8: =Scenarios!A4 -> D4_StatusQuo_Targets | C8: FY2027 | D8: =IF(Scenarios!D4=1,0, L8) -> 282 | E8: =IF(Scenarios!E4=1,0, M8) -> 321 | F8: =D8+E8 -> 603 | G8: =YearMap!B3 -> 8613.4474 | H8: =YearMap!C3 -> 915497.15 | I8: =YearMap!D3 -> 1054424.7 | J8: =1-BaselineCalc!$B$5 -> 0.993 | K8: =Scenarios!G4 -> 0 | L8: =IF(Scenarios!$Q4=1,BaselineCalc!$B$7*(1+Parameters_Public!$C44)^(IF($C8="FY2026",0,IF($C8="FY2027",1,IF($C8="FY2028",2,IF($C8="FY2029",3,IF($C8="FY2030",4,0))))))+ROUND(Scenarios!J4*Scenarios!$F4,0),BaselineCalc!$B$7+ROUND(Scenarios!J4*Scenarios!$F4,0)) -> 282 | M8: =IF(Scenarios!$R4=1,BaselineCalc!$B$8*(1+Parameters_Public!$C45)^(IF($C8="FY2026",0,IF($C8="FY2027",1,IF($C8="FY2028",2,IF($C8="FY2029",3,IF($C8="FY2030",4,0))))))+Scenarios!J4-ROUND(Scenarios!J4*Scenarios!$F4,0),BaselineCalc!$B$8+Scenarios!J4-ROUND(Scenarios!J4*Scenarios!$F4,0)) -> 321 | N8: =(L8-D8) + (M8-E8) -> 0 | O8: =(Parameters_Public!$C$23*(L8-D8)+Parameters_Public!$C$24*(M8-E8)) -> 0 | P8: =YearMap!E3 -> 800 | Q8: =IF(Scenarios!N4="lease", YearMap!F3, YearMap!G3) -> 0.4 | R8: =IF(Scenarios!D4=1, Q8*H8, H8) -> 915497.15 | S8: =IF(Scenarios!E4=1, Q8*I8, I8) -> 1054424.7 | T8: =IF(C8="FY2026", (Scenarios!D4+Scenarios!E4)*BaselineCalc!$B$22, 0) -> 0 | U8: =(R8+S8+G8*F8)*J8*(1-K8) -> 7113683.9 | V8: =O8*(G8+P8) -> 0 | W8: =U8+V8+IF(Parameters_Public!$C$28=1, T8, 0) -> 7113683.9 | X8: =IF(F8+O8>0, W8/(F8+O8),"") -> 11797.154 | Y8: =INDEX(YearMap!$I$2:$I$6, MATCH(C8, YearMap!$A$2:$A$6, 0)) -> 5138.325 | Z8: =W8 - ((Y8 + IF(Parameters_Public!$C$20=1, Parameters_Public!$C$19, 0))*AC8) -> 3561848 | AA8: =IF($AC8>0, $Z8/$AC8, 0) -> 5906.879 | AB8: =MAX(0, (MAX(0, $D8-BaselineCalc!$B$7) + MAX(0, $E8-BaselineCalc!$B$8))) -> 50 | AC8: =L8+M8-N8+O8 -> 603 | AD8: =( (Y8 + IF(Parameters_Public!$C20=1, INDEX(YearMap!$O$2:$O$6, MATCH(C8, YearMap!$A$2:$A$6, 0)), 0)) * AC8 ) + AC8*INDEX(YearMap!$P$2:$P$6, MATCH(C8, YearMap!$A$2:$A$6, 0)) + AB8*( INDEX(YearMap!$R$2:$R$6, MATCH(C8, YearMap!$A$2:$A$6, 0)) - INDEX(YearMap!$P$2:$P$6, MATCH(C8, YearMap!$A$2:$A$6, 0)) ) -> 6737186.5 | AE8: =(W8 - (1-Parameters_Public!$C$43)*$G8*$AB8*$J8*(1-$K8)) + AB8*INDEX(YearMap!$Q$2:$Q$6, MATCH(C8, YearMap!$A$2:$A$6, 0)) -> 6950620.8 | AF8: =AD8-AE8 -> -213434.32 | AG8: =B8&"|"&C8 -> D4_StatusQuo_Targets|FY2027
A9: =AG9 -> D4_StatusQuo_Targets|FY2028 | B9: =Scenarios!A4 -> D4_StatusQuo_Targets | C9: FY2028 | D9: =IF(Scenarios!D4=1,0, L9) -> 295 | E9: =IF(Scenarios!E4=1,0, M9) -> 333 | F9: =D9+E9 -> 628 | G9: =YearMap!B4 -> 8828.7836 | H9: =YearMap!C4 -> 938384.57 | I9: =YearMap!D4 -> 1080785.3 | J9: =1-BaselineCalc!$B$5 -> 0.993 | K9: =Scenarios!G4 -> 0 | L9: =IF(Scenarios!$Q4=1,BaselineCalc!$B$7*(1+Parameters_Public!$C44)^(IF($C9="FY2026",0,IF($C9="FY2027",1,IF($C9="FY2028",2,IF($C9="FY2029",3,IF($C9="FY2030",4,0))))))+ROUND(Scenarios!K4*Scenarios!$F4,0),BaselineCalc!$B$7+ROUND(Scenarios!K4*Scenarios!$F4,0)) -> 295 | M9: =IF(Scenarios!$R4=1,BaselineCalc!$B$8*(1+Parameters_Public!$C45)^(IF($C9="FY2026",0,IF($C9="FY2027",1,IF($C9="FY2028",2,IF($C9="FY2029",3,IF($C9="FY2030",4,0))))))+Scenarios!K4-ROUND(Scenarios!K4*Scenarios!$F4,0),BaselineCalc!$B$8+Scenarios!K4-ROUND(Scenarios!K4*Scenarios!$F4,0)) -> 333 | N9: =(L9-D9) + (M9-E9) -> 0 | O9: =(Parameters_Public!$C$23*(L9-D9)+Parameters_Public!$C$24*(M9-E9)) -> 0 | P9: =YearMap!E4 -> 600 | Q9: =IF(Scenarios!N4="lease", YearMap!F4, YearMap!G4) -> 0.35 | R9: =IF(Scenarios!D4=1, Q9*H9, H9) -> 938384.57 | S9: =IF(Scenarios!E4=1, Q9*I9, I9) -> 1080785.3 | T9: =IF(C9="FY2026", (Scenarios!D4+Scenarios!E4)*BaselineCalc!$B$22, 0) -> 0 | U9: =(R9+S9+G9*F9)*J9*(1-K9) -> 7510700.5 | V9: =O9*(G9+P9) -> 0 | W9: =U9+V9+IF(Parameters_Public!$C$28=1, T9, 0) -> 7510700.5 | X9: =IF(F9+O9>0, W9/(F9+O9),"") -> 11959.714 | Y9: =INDEX(YearMap!$I$2:$I$6, MATCH(C9, YearMap!$A$2:$A$6, 0)) -> 5266.7831 | Z9: =W9 - ((Y9 + IF(Parameters_Public!$C$20=1, Parameters_Public!$C$19, 0))*AC9) -> 3730936.1 | AA9: =IF($AC9>0, $Z9/$AC9, 0) -> 5940.9811 | AB9: =MAX(0, (MAX(0, $D9-BaselineCalc!$B$7) + MAX(0, $E9-BaselineCalc!$B$8))) -> 75 | AC9: =L9+M9-N9+O9 -> 628 | AD9: =( (Y9 + IF(Parameters_Public!$C20=1, INDEX(YearMap!$O$2:$O$6, MATCH(C9, YearMap!$A$2:$A$6, 0)), 0)) * AC9 ) + AC9*INDEX(YearMap!$P$2:$P$6, MATCH(C9, YearMap!$A$2:$A$6, 0)) + AB9*( INDEX(YearMap!$R$2:$R$6, MATCH(C9, YearMap!$A$2:$A$6, 0)) - INDEX(YearMap!$P$2:$P$6, MATCH(C9, YearMap!$A$2:$A$6, 0)) ) -> 7173130.2 | AE9: =(W9 - (1-Parameters_Public!$C$43)*$G9*$AB9*$J9*(1-$K9)) + AB9*INDEX(YearMap!$Q$2:$Q$6, MATCH(C9, YearMap!$A$2:$A$6, 0)) -> 7256691 | AF9: =AD9-AE9 -> -83560.83 | AG9: =B9&"|"&C9 -> D4_StatusQuo_Targets|FY2028
A10: =AG10 -> D4_StatusQuo_Targets|FY2029 | B10: =Scenarios!A4 -> D4_StatusQuo_Targets | C10: FY2029 | D10: =IF(Scenarios!D4=1,0, L10) -> 295 | E10: =IF(Scenarios!E4=1,0, M10) -> 333 | F10: =D10+E10 -> 628 | G10: =YearMap!B5 -> 9049.5032 | H10: =YearMap!C5 -> 961844.19 | I10: =YearMap!D5 -> 1107805 | J10: =1-BaselineCalc!$B$5 -> 0.993 | K10: =Scenarios!G4 -> 0 | L10: =IF(Scenarios!$Q4=1,BaselineCalc!$B$7*(1+Parameters_Public!$C44)^(IF($C10="FY2026",0,IF($C10="FY2027",1,IF($C10="FY2028",2,IF($C10="FY2029",3,IF($C10="FY2030",4,0))))))+ROUND(Scenarios!L4*Scenarios!$F4,0),BaselineCalc!$B$7+ROUND(Scenarios!L4*Scenarios!$F4,0)) -> 295 | M10: =IF(Scenarios!$R4=1,BaselineCalc!$B$8*(1+Parameters_Public!$C45)^(IF($C10="FY2026",0,IF($C10="FY2027",1,IF($C10="FY2028",2,IF($C10="FY2029",3,IF($C10="FY2030",4,0))))))+Scenarios!L4-ROUND(Scenarios!L4*Scenarios!$F4,0),BaselineCalc!$B$8+Scenarios!L4-ROUND(Scenarios!L4*Scenarios!$F4,0)) -> 333 | N10: =(L10-D10) + (M10-E10) -> 0 | O10: =(Parameters_Public!$C$23*(L10-D10)+Parameters_Public!$C$24*(M10-E10)) -> 0 | P10: =YearMap!E5 -> 500 | Q10: =IF(Scenarios!N4="lease", YearMap!F5, YearMap!G5) -> 0.3 | R10: =IF(Scenarios!D4=1, Q10*H10, H10) -> 961844.19 | S10: =IF(Scenarios!E4=1, Q10*I10, I10) -> 1107805 | T10: =IF(C10="FY2026", (Scenarios!D4+Scenarios!E4)*BaselineCalc!$B$22, 0) -> 0 | U10: =(R10+S10+G10*F10)*J10*(1-K10) -> 7698468 | V10: =O10*(G10+P10) -> 0 | W10: =U10+V10+IF(Parameters_Public!$C$28=1, T10, 0) -> 7698468 | X10: =IF(F10+O10>0, W10/(F10+O10),"") -> 12258.707 | Y10: =INDEX(YearMap!$I$2:$I$6, MATCH(C10, YearMap!$A$2:$A$6, 0)) -> 5398.4527 | Z10: =W10 - ((Y10 + IF(Parameters_Public!$C$20=1, Parameters_Public!$C$19, 0))*AC10) -> 3836015.1 | AA10: =IF($AC10>0, $Z10/$AC10, 0) -> 6108.3043 | AB10: =MAX(0, (MAX(0, $D10-BaselineCalc!$B$7) + MAX(0, $E10-BaselineCalc!$B$8))) -> 75 | AC10: =L10+M10-N10+O10 -> 628 | AD10: =( (Y10 + IF(Parameters_Public!$C20=1, INDEX(YearMap!$O$2:$O$6, MATCH(C10, YearMap!$A$2:$A$6, 0)), 0)) * AC10 ) + AC10*INDEX(YearMap!$P$2:$P$6, MATCH(C10, YearMap!$A$2:$A$6, 0)) + AB10*( INDEX(YearMap!$R$2:$R$6, MATCH(C10, YearMap!$A$2:$A$6, 0)) - INDEX(YearMap!$P$2:$P$6, MATCH(C10, YearMap!$A$2:$A$6, 0)) ) -> 7352458.5 | AE10: =(W10 - (1-Parameters_Public!$C$43)*$G10*$AB10*$J10*(1-$K10)) + AB10*INDEX(YearMap!$Q$2:$Q$6, MATCH(C10, YearMap!$A$2:$A$6, 0)) -> 7436383.3 | AF10: =AD10-AE10 -> -83924.851 | AG10: =B10&"|"&C10 -> D4_StatusQuo_Targets|FY2029
A11: =AG11 -> D4_StatusQuo_Targets|FY2030 | B11: =Scenarios!A4 -> D4_StatusQuo_Targets | C11: FY2030 | D11: =IF(Scenarios!D4=1,0, L11) -> 295 | E11: =IF(Scenarios!E4=1,0, M11) -> 333 | F11: =D11+E11 -> 628 | G11: =YearMap!B6 -> 9275.7408 | H11: =YearMap!C6 -> 985890.29 | I11: =YearMap!D6 -> 1135500.1 | J11: =1-BaselineCalc!$B$5 -> 0.993 | K11: =Scenarios!G4 -> 0 | L11: =IF(Scenarios!$Q4=1,BaselineCalc!$B$7*(1+Parameters_Public!$C44)^(IF($C11="FY2026",0,IF($C11="FY2027",1,IF($C11="FY2028",2,IF($C11="FY2029",3,IF($C11="FY2030",4,0))))))+ROUND(Scenarios!M4*Scenarios!$F4,0),BaselineCalc!$B$7+ROUND(Scenarios!M4*Scenarios!$F4,0)) -> 295 | M11: =IF(Scenarios!$R4=1,BaselineCalc!$B$8*(1+Parameters_Public!$C45)^(IF($C11="FY2026",0,IF($C11="FY2027",1,IF($C11="FY2028",2,IF($C11="FY2029",3,IF($C11="FY2030",4,0))))))+Scenarios!M4-ROUND(Scenarios!M4*Scenarios!$F4,0),BaselineCalc!$B$8+Scenarios!M4-ROUND(Scenarios!M4*Scenarios!$F4,0)) -> 333 | N11: =(L11-D11) + (M11-E11) -> 0 | O11: =(Parameters_Public!$C$23*(L11-D11)+Parameters_Public!$C$24*(M11-E11)) -> 0 | P11: =YearMap!E6 -> 300 | Q11: =IF(Scenarios!N4="lease", YearMap!F6, YearMap!G6) -> 0.3 | R11: =IF(Scenarios!D4=1, Q11*H11, H11) -> 985890.29 | S11: =IF(Scenarios!E4=1, Q11*I11, I11) -> 1135500.1 | T11: =IF(C11="FY2026", (Scenarios!D4+Scenarios!E4)*BaselineCalc!$B$22, 0) -> 0 | U11: =(R11+S11+G11*F11)*J11*(1-K11) -> 7890929.7 | V11: =O11*(G11+P11) -> 0 | W11: =U11+V11+IF(Parameters_Public!$C$28=1, T11, 0) -> 7890929.7 | X11: =IF(F11+O11>0, W11/(F11+O11),"") -> 12565.175 | Y11: =INDEX(YearMap!$I$2:$I$6, MATCH(C11, YearMap!$A$2:$A$6, 0)) -> 5533.414 | Z11: =W11 - ((Y11 + IF(Parameters_Public!$C$20=1, Parameters_Public!$C$19, 0))*AC11) -> 3943721.1 | AA11: =IF($AC11>0, $Z11/$AC11, 0) -> 6279.8107 | AB11: =MAX(0, (MAX(0, $D11-BaselineCalc!$B$7) + MAX(0, $E11-BaselineCalc!$B$8))) -> 75 | AC11: =L11+M11-N11+O11 -> 628 | AD11: =( (Y11 + IF(Parameters_Public!$C20=1, INDEX(YearMap!$O$2:$O$6, MATCH(C11, YearMap!$A$2:$A$6, 0)), 0)) * AC11 ) + AC11*INDEX(YearMap!$P$2:$P$6, MATCH(C11, YearMap!$A$2:$A$6, 0)) + AB11*( INDEX(YearMap!$R$2:$R$6, MATCH(C11, YearMap!$A$2:$A$6, 0)) - INDEX(YearMap!$P$2:$P$6, MATCH(C11, YearMap!$A$2:$A$6, 0)) ) -> 7536269.9 | AE11: =(W11 - (1-Parameters_Public!$C$43)*$G11*$AB11*$J11*(1-$K11)) + AB11*INDEX(YearMap!$Q$2:$Q$6, MATCH(C11, YearMap!$A$2:$A$6, 0)) -> 7619105.4 | AF11: =AD11-AE11 -> -82835.472 | AG11: =B11&"|"&C11 -> D4_StatusQuo_Targets|FY2030
A12: =AG12 -> D3_CoLocation_Echo_Targets|FY2026 | B12: =Scenarios!A5 -> D3_CoLocation_Echo_Targets | C12: FY2026 | D12: =IF(Scenarios!D5=1,0, L12) -> 265 | E12: =IF(Scenarios!E5=1,0, M12) -> 304.66667 | F12: =D12+E12 -> 569.66667 | G12: =YearMap!B2 -> 8403.3633 | H12: =YearMap!C2 -> 922500 | I12: =YearMap!D2 -> 999375 | J12: =1-BaselineCalc!$B$5 -> 0.993 | K12: =Scenarios!G5 -> 0.05 | L12: =IF(Scenarios!$Q5=1,BaselineCalc!$B$7*(1+Parameters_Public!$C44)^(IF($C12="FY2026",0,IF($C12="FY2027",1,IF($C12="FY2028",2,IF($C12="FY2029",3,IF($C12="FY2030",4,0))))))+ROUND(Scenarios!I5*Scenarios!$F5,0),BaselineCalc!$B$7+ROUND(Scenarios!I5*Scenarios!$F5,0)) -> 265 | M12: =IF(Scenarios!$R5=1,BaselineCalc!$B$8*(1+Parameters_Public!$C45)^(IF($C12="FY2026",0,IF($C12="FY2027",1,IF($C12="FY2028",2,IF($C12="FY2029",3,IF($C12="FY2030",4,0))))))+Scenarios!I5-ROUND(Scenarios!I5*Scenarios!$F5,0),BaselineCalc!$B$8+Scenarios!I5-ROUND(Scenarios!I5*Scenarios!$F5,0)) -> 304.66667 | N12: =(L12-D12) + (M12-E12) -> 0 | O12: =(Parameters_Public!$C$23*(L12-D12)+Parameters_Public!$C$24*(M12-E12)) -> 0 | P12: =YearMap!E2 -> 1000 | Q12: =IF(Scenarios!N5="lease", YearMap!F2, YearMap!G2) -> 0.45 | R12: =IF(Scenarios!D5=1, Q12*H12, H12) -> 922500 | S12: =IF(Scenarios!E5=1, Q12*I12, I12) -> 999375 | T12: =IF(C12="FY2026", (Scenarios!D5+Scenarios!E5)*BaselineCalc!$B$22, 0) -> 0 | U12: =(R12+S12+G12*F12)*J12*(1-K12) -> 6328926.6 | V12: =O12*(G12+P12) -> 0 | W12: =U12+V12+IF(Parameters_Public!$C$28=1, T12, 0) -> 6328926.6 | X12: =IF(F12+O12>0, W12/(F12+O12),"") -> 11109.877 | Y12: =INDEX(YearMap!$I$2:$I$6, MATCH(C12, YearMap!$A$2:$A$6, 0)) -> 5013 | Z12: =W12 - ((Y12 + IF(Parameters_Public!$C$20=1, Parameters_Public!$C$19, 0))*AC12) -> 3044826.8 | AA12: =IF($AC12>0, $Z12/$AC12, 0) -> 5344.9271 | AB12: =MAX(0, (MAX(0, $D12-BaselineCalc!$B$7) + MAX(0, $E12-BaselineCalc!$B$8))) -> 16.666667 | AC12: =L12+M12-N12+O12 -> 569.66667 | AD12: =( (Y12 + IF(Parameters_Public!$C20=1, INDEX(YearMap!$O$2:$O$6, MATCH(C12, YearMap!$A$2:$A$6, 0)), 0)) * AC12 ) + AC12*INDEX(YearMap!$P$2:$P$6, MATCH(C12, YearMap!$A$2:$A$6, 0)) + AB12*( INDEX(YearMap!$R$2:$R$6, MATCH(C12, YearMap!$A$2:$A$6, 0)) - INDEX(YearMap!$P$2:$P$6, MATCH(C12, YearMap!$A$2:$A$6, 0)) ) -> 6233366.5 | AE12: =(W12 - (1-Parameters_Public!$C$43)*$G12*$AB12*$J12*(1-$K12)) + AB12*INDEX(YearMap!$Q$2:$Q$6, MATCH(C12, YearMap!$A$2:$A$6, 0)) -> 6279411.2 | AF12: =AD12-AE12 -> -46044.706 | AG12: =B12&"|"&C12 -> D3_CoLocation_Echo_Targets|FY2026
A13: =AG13 -> D3_CoLocation_Echo_Targets|FY2027 | B13: =Scenarios!A5 -> D3_CoLocation_Echo_Targets | C13: FY2027 | D13: =IF(Scenarios!D5=1,0, L13) -> 274 | E13: =IF(Scenarios!E5=1,0, M13) -> 312.33333 | F13: =D13+E13 -> 586.33333 | G13: =YearMap!B3 -> 8613.4474 | H13: =YearMap!C3 -> 915497.15 | I13: =YearMap!D3 -> 1054424.7 | J13: =1-BaselineCalc!$B$5 -> 0.993 | K13: =Scenarios!G5 -> 0.05 | L13: =IF(Scenarios!$Q5=1,BaselineCalc!$B$7*(1+Parameters_Public!$C44)^(IF($C13="FY2026",0,IF($C13="FY2027",1,IF($C13="FY2028",2,IF($C13="FY2029",3,IF($C13="FY2030",4,0))))))+ROUND(Scenarios!J5*Scenarios!$F5,0),BaselineCalc!$B$7+ROUND(Scenarios!J5*Scenarios!$F5,0)) -> 274 | M13: =IF(Scenarios!$R5=1,BaselineCalc!$B$8*(1+Parameters_Public!$C45)^(IF($C13="FY2026",0,IF($C13="FY2027",1,IF($C13="FY2028",2,IF($C13="FY2029",3,IF($C13="FY2030",4,0))))))+Scenarios!J5-ROUND(Scenarios!J5*Scenarios!$F5,0),BaselineCalc!$B$8+Scenarios!J5-ROUND(Scenarios!J5*Scenarios!$F5,0)) -> 312.33333 | N13: =(L13-D13) + (M13-E13) -> 0 | O13: =(Parameters_Public!$C$23*(L13-D13)+Parameters_Public!$C$24*(M13-E13)) -> 0 | P13: =YearMap!E3 -> 800 | Q13: =IF(Scenarios!N5="lease", YearMap!F3, YearMap!G3) -> 0.4 | R13: =IF(Scenarios!D5=1, Q13*H13, H13) -> 915497.15 | S13: =IF(Scenarios!E5=1, Q13*I13, I13) -> 1054424.7 | T13: =IF(C13="FY2026", (Scenarios!D5+Scenarios!E5)*BaselineCalc!$B$22, 0) -> 0 | U13: =(R13+S13+G13*F13)*J13*(1-K13) -> 6622574.7 | V13: =O13*(G13+P13) -> 0 | W13: =U13+V13+IF(Parameters_Public!$C$28=1, T13, 0) -> 6622574.7 | X13: =IF(F13+O13>0, W13/(F13+O13),"") -> 11294.897 | Y13: =INDEX(YearMap!$I$2:$I$6, MATCH(C13, YearMap!$A$2:$A$6, 0)) -> 5138.325 | Z13: =W13 - ((Y13 + IF(Parameters_Public!$C$20=1, Parameters_Public!$C$19, 0))*AC13) -> 3168910.2 | AA13: =IF($AC13>0, $Z13/$AC13, 0) -> 5404.6222 | AB13: =MAX(0, (MAX(0, $D13-BaselineCalc!$B$7) + MAX(0, $E13-BaselineCalc!$B$8))) -> 33.333333 | AC13: =L13+M13-N13+O13 -> 586.33333 | AD13: =( (Y13 + IF(Parameters_Public!$C20=1, INDEX(YearMap!$O$2:$O$6, MATCH(C13, YearMap!$A$2:$A$6, 0)), 0)) * AC13 ) + AC13*INDEX(YearMap!$P$2:$P$6, MATCH(C13, YearMap!$A$2:$A$6, 0)) + AB13*( INDEX(YearMap!$R$2:$R$6, MATCH(C13, YearMap!$A$2:$A$6, 0)) - INDEX(YearMap!$P$2:$P$6, MATCH(C13, YearMap!$A$2:$A$6, 0)) ) -> 6563193.6 | AE13: =(W13 - (1-Parameters_Public!$C$43)*$G13*$AB13*$J13*(1-$K13)) + AB13*INDEX(YearMap!$Q$2:$Q$6, MATCH(C13, YearMap!$A$2:$A$6, 0)) -> 6519568.1 | AF13: =AD13-AE13 -> 43625.449 | AG13: =B13&"|"&C13 -> D3_CoLocation_Echo_Targets|FY2027
A14: =AG14 -> D3_CoLocation_Echo_Targets|FY2028 | B14: =Scenarios!A5 -> D3_CoLocation_Echo_Targets | C14: FY2028 | D14: =IF(Scenarios!D5=1,0, L14) -> 282 | E14: =IF(Scenarios!E5=1,0, M14) -> 321 | F14: =D14+E14 -> 603 | G14: =YearMap!B4 -> 8828.7836 | H14: =YearMap!C4 -> 938384.57 | I14: =YearMap!D4 -> 1080785.3 | J14: =1-BaselineCalc!$B$5 -> 0.993 | K14: =Scenarios!G5 -> 0.05 | L14: =IF(Scenarios!$Q5=1,BaselineCalc!$B$7*(1+Parameters_Public!$C44)^(IF($C14="FY2026",0,IF($C14="FY2027",1,IF($C14="FY2028",2,IF($C14="FY2029",3,IF($C14="FY2030",4,0))))))+ROUND(Scenarios!K5*Scenarios!$F5,0),BaselineCalc!$B$7+ROUND(Scenarios!K5*Scenarios!$F5,0)) -> 282 | M14: =IF(Scenarios!$R5=1,BaselineCalc!$B$8*(1+Parameters_Public!$C45)^(IF($C14="FY2026",0,IF($C14="FY2027",1,IF($C14="FY2028",2,IF($C14="FY2029",3,IF($C14="FY2030",4,0))))))+Scenarios!K5-ROUND(Scenarios!K5*Scenarios!$F5,0),BaselineCalc!$B$8+Scenarios!K5-ROUND(Scenarios!K5*Scenarios!$F5,0)) -> 321 | N14: =(L14-D14) + (M14-E14) -> 0 | O14: =(Parameters_Public!$C$23*(L14-D14)+Parameters_Public!$C$24*(M14-E14)) -> 0 | P14: =YearMap!E4 -> 600 | Q14: =IF(Scenarios!N5="lease", YearMap!F4, YearMap!G4) -> 0.35 | R14: =IF(Scenarios!D5=1, Q14*H14, H14) -> 938384.57 | S14: =IF(Scenarios!E5=1, Q14*I14, I14) -> 1080785.3 | T14: =IF(C14="FY2026", (Scenarios!D5+Scenarios!E5)*BaselineCalc!$B$22, 0) -> 0 | U14: =(R14+S14+G14*F14)*J14*(1-K14) -> 6926949.7 | V14: =O14*(G14+P14) -> 0 | W14: =U14+V14+IF(Parameters_Public!$C$28=1, T14, 0) -> 6926949.7 | X14: =IF(F14+O14>0, W14/(F14+O14),"") -> 11487.479 | Y14: =INDEX(YearMap!$I$2:$I$6, MATCH(C14, YearMap!$A$2:$A$6, 0)) -> 5266.7831 | Z14: =W14 - ((Y14 + IF(Parameters_Public!$C$20=1, Parameters_Public!$C$19, 0))*AC14) -> 3297653.6 | AA14: =IF($AC14>0, $Z14/$AC14, 0) -> 5468.7456 | AB14: =MAX(0, (MAX(0, $D14-BaselineCalc!$B$7) + MAX(0, $E14-BaselineCalc!$B$8))) -> 50 | AC14: =L14+M14-N14+O14 -> 603 | AD14: =( (Y14 + IF(Parameters_Public!$C20=1, INDEX(YearMap!$O$2:$O$6, MATCH(C14, YearMap!$A$2:$A$6, 0)), 0)) * AC14 ) + AC14*INDEX(YearMap!$P$2:$P$6, MATCH(C14, YearMap!$A$2:$A$6, 0)) + AB14*( INDEX(YearMap!$R$2:$R$6, MATCH(C14, YearMap!$A$2:$A$6, 0)) - INDEX(YearMap!$P$2:$P$6, MATCH(C14, YearMap!$A$2:$A$6, 0)) ) -> 6905616.1 | AE14: =(W14 - (1-Parameters_Public!$C$43)*$G14*$AB14*$J14*(1-$K14)) + AB14*INDEX(YearMap!$Q$2:$Q$6, MATCH(C14, YearMap!$A$2:$A$6, 0)) -> 6766377 | AF14: =AD14-AE14 -> 139239.14 | AG14: =B14&"|"&C14 -> D3_CoLocation_Echo_Targets|FY2028
A15: =AG15 -> D3_CoLocation_Echo_Targets|FY2029 | B15: =Scenarios!A5 -> D3_CoLocation_Echo_Targets | C15: FY2029 | D15: =IF(Scenarios!D5=1,0, L15) -> 282 | E15: =IF(Scenarios!E5=1,0, M15) -> 321 | F15: =D15+E15 -> 603 | G15: =YearMap!B5 -> 9049.5032 | H15: =YearMap!C5 -> 961844.19 | I15: =YearMap!D5 -> 1107805 | J15: =1-BaselineCalc!$B$5 -> 0.993 | K15: =Scenarios!G5 -> 0.05 | L15: =IF(Scenarios!$Q5=1,BaselineCalc!$B$7*(1+Parameters_Public!$C44)^(IF($C15="FY2026",0,IF($C15="FY2027",1,IF($C15="FY2028",2,IF($C15="FY2029",3,IF($C15="FY2030",4,0))))))+ROUND(Scenarios!L5*Scenarios!$F5,0),BaselineCalc!$B$7+ROUND(Scenarios!L5*Scenarios!$F5,0)) -> 282 | M15: =IF(Scenarios!$R5=1,BaselineCalc!$B$8*(1+Parameters_Public!$C45)^(IF($C15="FY2026",0,IF($C15="FY2027",1,IF($C15="FY2028",2,IF($C15="FY2029",3,IF($C15="FY2030",4,0))))))+Scenarios!L5-ROUND(Scenarios!L5*Scenarios!$F5,0),BaselineCalc!$B$8+Scenarios!L5-ROUND(Scenarios!L5*Scenarios!$F5,0)) -> 321 | N15: =(L15-D15) + (M15-E15) -> 0 | O15: =(Parameters_Public!$C$23*(L15-D15)+Parameters_Public!$C$24*(M15-E15)) -> 0 | P15: =YearMap!E5 -> 500 | Q15: =IF(Scenarios!N5="lease", YearMap!F5, YearMap!G5) -> 0.3 | R15: =IF(Scenarios!D5=1, Q15*H15, H15) -> 961844.19 | S15: =IF(Scenarios!E5=1, Q15*I15, I15) -> 1107805 | T15: =IF(C15="FY2026", (Scenarios!D5+Scenarios!E5)*BaselineCalc!$B$22, 0) -> 0 | U15: =(R15+S15+G15*F15)*J15*(1-K15) -> 7100123.4 | V15: =O15*(G15+P15) -> 0 | W15: =U15+V15+IF(Parameters_Public!$C$28=1, T15, 0) -> 7100123.4 | X15: =IF(F15+O15>0, W15/(F15+O15),"") -> 11774.666 | Y15: =INDEX(YearMap!$I$2:$I$6, MATCH(C15, YearMap!$A$2:$A$6, 0)) -> 5398.4527 | Z15: =W15 - ((Y15 + IF(Parameters_Public!$C$20=1, Parameters_Public!$C$19, 0))*AC15) -> 3391430.6 | AA15: =IF($AC15>0, $Z15/$AC15, 0) -> 5624.263 | AB15: =MAX(0, (MAX(0, $D15-BaselineCalc!$B$7) + MAX(0, $E15-BaselineCalc!$B$8))) -> 50 | AC15: =L15+M15-N15+O15 -> 603 | AD15: =( (Y15 + IF(Parameters_Public!$C20=1, INDEX(YearMap!$O$2:$O$6, MATCH(C15, YearMap!$A$2:$A$6, 0)), 0)) * AC15 ) + AC15*INDEX(YearMap!$P$2:$P$6, MATCH(C15, YearMap!$A$2:$A$6, 0)) + AB15*( INDEX(YearMap!$R$2:$R$6, MATCH(C15, YearMap!$A$2:$A$6, 0)) - INDEX(YearMap!$P$2:$P$6, MATCH(C15, YearMap!$A$2:$A$6, 0)) ) -> 7078256.5 | AE15: =(W15 - (1-Parameters_Public!$C$43)*$G15*$AB15*$J15*(1-$K15)) + AB15*INDEX(YearMap!$Q$2:$Q$6, MATCH(C15, YearMap!$A$2:$A$6, 0)) -> 6934386.4 | AF15: =AD15-AE15 -> 143870.12 | AG15: =B15&"|"&C15 -> D3_CoLocation_Echo_Targets|FY2029
A16: =AG16 -> D3_CoLocation_Echo_Targets|FY2030 | B16: =Scenarios!A5 -> D3_CoLocation_Echo_Targets | C16: FY2030 | D16: =IF(Scenarios!D5=1,0, L16) -> 282 | E16: =IF(Scenarios!E5=1,0, M16) -> 321 | F16: =D16+E16 -> 603 | G16: =YearMap!B6 -> 9275.7408 | H16: =YearMap!C6 -> 985890.29 | I16: =YearMap!D6 -> 1135500.1 | J16: =1-BaselineCalc!$B$5 -> 0.993 | K16: =Scenarios!G5 -> 0.05 | L16: =IF(Scenarios!$Q5=1,BaselineCalc!$B$7*(1+Parameters_Public!$C44)^(IF($C16="FY2026",0,IF($C16="FY2027",1,IF($C16="FY2028",2,IF($C16="FY2029",3,IF($C16="FY2030",4,0))))))+ROUND(Scenarios!M5*Scenarios!$F5,0),BaselineCalc!$B$7+ROUND(Scenarios!M5*Scenarios!$F5,0)) -> 282 | M16: =IF(Scenarios!$R5=1,BaselineCalc!$B$8*(1+Parameters_Public!$C45)^(IF($C16="FY2026",0,IF($C16="FY2027",1,IF($C16="FY2028",2,IF($C16="FY2029",3,IF($C16="FY2030",4,0))))))+Scenarios!M5-ROUND(Scenarios!M5*Scenarios!$F5,0),BaselineCalc!$B$8+Scenarios!M5-ROUND(Scenarios!M5*Scenarios!$F5,0)) -> 321 | N16: =(L16-D16) + (M16-E16) -> 0 | O16: =(Parameters_Public!$C$23*(L16-D16)+Parameters_Public!$C$24*(M16-E16)) -> 0 | P16: =YearMap!E6 -> 300 | Q16: =IF(Scenarios!N5="lease", YearMap!F6, YearMap!G6) -> 0.3 | R16: =IF(Scenarios!D5=1, Q16*H16, H16) -> 985890.29 | S16: =IF(Scenarios!E5=1, Q16*I16, I16) -> 1135500.1 | T16: =IF(C16="FY2026", (Scenarios!D5+Scenarios!E5)*BaselineCalc!$B$22, 0) -> 0 | U16: =(R16+S16+G16*F16)*J16*(1-K16) -> 7277626.5 | V16: =O16*(G16+P16) -> 0 | W16: =U16+V16+IF(Parameters_Public!$C$28=1, T16, 0) -> 7277626.5 | X16: =IF(F16+O16>0, W16/(F16+O16),"") -> 12069.032 | Y16: =INDEX(YearMap!$I$2:$I$6, MATCH(C16, YearMap!$A$2:$A$6, 0)) -> 5533.414 | Z16: =W16 - ((Y16 + IF(Parameters_Public!$C$20=1, Parameters_Public!$C$19, 0))*AC16) -> 3487552 | AA16: =IF($AC16>0, $Z16/$AC16, 0) -> 5783.6683 | AB16: =MAX(0, (MAX(0, $D16-BaselineCalc!$B$7) + MAX(0, $E16-BaselineCalc!$B$8))) -> 50 | AC16: =L16+M16-N16+O16 -> 603 | AD16: =( (Y16 + IF(Parameters_Public!$C20=1, INDEX(YearMap!$O$2:$O$6, MATCH(C16, YearMap!$A$2:$A$6, 0)), 0)) * AC16 ) + AC16*INDEX(YearMap!$P$2:$P$6, MATCH(C16, YearMap!$A$2:$A$6, 0)) + AB16*( INDEX(YearMap!$R$2:$R$6, MATCH(C16, YearMap!$A$2:$A$6, 0)) - INDEX(YearMap!$P$2:$P$6, MATCH(C16, YearMap!$A$2:$A$6, 0)) ) -> 7255212.9 | AE16: =(W16 - (1-Parameters_Public!$C$43)*$G16*$AB16*$J16*(1-$K16)) + AB16*INDEX(YearMap!$Q$2:$Q$6, MATCH(C16, YearMap!$A$2:$A$6, 0)) -> 7105621.1 | AF16: =AD16-AE16 -> 149591.87 | AG16: =B16&"|"&C16 -> D3_CoLocation_Echo_Targets|FY2030
A17: =AG17 -> D1_Grow_Both_Targets|FY2026 | B17: =Scenarios!A6 -> D1_Grow_Both_Targets | C17: FY2026 | D17: =IF(Scenarios!D6=1,0, L17) -> 282 | E17: =IF(Scenarios!E6=1,0, M17) -> 321 | F17: =D17+E17 -> 603 | G17: =YearMap!B2 -> 8403.3633 | H17: =YearMap!C2 -> 922500 | I17: =YearMap!D2 -> 999375 | J17: =1-BaselineCalc!$B$5 -> 0.993 | K17: =Scenarios!G6 -> 0 | L17: =IF(Scenarios!$Q6=1,BaselineCalc!$B$7*(1+Parameters_Public!$C44)^(IF($C17="FY2026",0,IF($C17="FY2027",1,IF($C17="FY2028",2,IF($C17="FY2029",3,IF($C17="FY2030",4,0))))))+ROUND(Scenarios!I6*Scenarios!$F6,0),BaselineCalc!$B$7+ROUND(Scenarios!I6*Scenarios!$F6,0)) -> 282 | M17: =IF(Scenarios!$R6=1,BaselineCalc!$B$8*(1+Parameters_Public!$C45)^(IF($C17="FY2026",0,IF($C17="FY2027",1,IF($C17="FY2028",2,IF($C17="FY2029",3,IF($C17="FY2030",4,0))))))+Scenarios!I6-ROUND(Scenarios!I6*Scenarios!$F6,0),BaselineCalc!$B$8+Scenarios!I6-ROUND(Scenarios!I6*Scenarios!$F6,0)) -> 321 | N17: =(L17-D17) + (M17-E17) -> 0 | O17: =(Parameters_Public!$C$23*(L17-D17)+Parameters_Public!$C$24*(M17-E17)) -> 0 | P17: =YearMap!E2 -> 1000 | Q17: =IF(Scenarios!N6="lease", YearMap!F2, YearMap!G2) -> 0.45 | R17: =IF(Scenarios!D6=1, Q17*H17, H17) -> 922500 | S17: =IF(Scenarios!E6=1, Q17*I17, I17) -> 999375 | T17: =IF(C17="FY2026", (Scenarios!D6+Scenarios!E6)*BaselineCalc!$B$22, 0) -> 0 | U17: =(R17+S17+G17*F17)*J17*(1-K17) -> 6940179.4 | V17: =O17*(G17+P17) -> 0 | W17: =U17+V17+IF(Parameters_Public!$C$28=1, T17, 0) -> 6940179.4 | X17: =IF(F17+O17>0, W17/(F17+O17),"") -> 11509.419 | Y17: =INDEX(YearMap!$I$2:$I$6, MATCH(C17, YearMap!$A$2:$A$6, 0)) -> 5013 | Z17: =W17 - ((Y17 + IF(Parameters_Public!$C$20=1, Parameters_Public!$C$19, 0))*AC17) -> 3463914.5 | AA17: =IF($AC17>0, $Z17/$AC17, 0) -> 5744.4685 | AB17: =MAX(0, (MAX(0, $D17-BaselineCalc!$B$7) + MAX(0, $E17-BaselineCalc!$B$8))) -> 50 | AC17: =L17+M17-N17+O17 -> 603 | AD17: =( (Y17 + IF(Parameters_Public!$C20=1, INDEX(YearMap!$O$2:$O$6, MATCH(C17, YearMap!$A$2:$A$6, 0)), 0)) * AC17 ) + AC17*INDEX(YearMap!$P$2:$P$6, MATCH(C17, YearMap!$A$2:$A$6, 0)) + AB17*( INDEX(YearMap!$R$2:$R$6, MATCH(C17, YearMap!$A$2:$A$6, 0)) - INDEX(YearMap!$P$2:$P$6, MATCH(C17, YearMap!$A$2:$A$6, 0)) ) -> 6572864.8 | AE17: =(W17 - (1-Parameters_Public!$C$43)*$G17*$AB17*$J17*(1-$K17)) + AB17*INDEX(YearMap!$Q$2:$Q$6, MATCH(C17, YearMap!$A$2:$A$6, 0)) -> 6783288.6 | AF17: =AD17-AE17 -> -210423.72 | AG17: =B17&"|"&C17 -> D1_Grow_Both_Targets|FY2026
A18: =AG18 -> D1_Grow_Both_Targets|FY2027 | B18: =Scenarios!A6 -> D1_Grow_Both_Targets | C18: FY2027 | D18: =IF(Scenarios!D6=1,0, L18) -> 307 | E18: =IF(Scenarios!E6=1,0, M18) -> 346 | F18: =D18+E18 -> 653 | G18: =YearMap!B3 -> 8613.4474 | H18: =YearMap!C3 -> 915497.15 | I18: =YearMap!D3 -> 1054424.7 | J18: =1-BaselineCalc!$B$5 -> 0.993 | K18: =Scenarios!G6 -> 0 | L18: =IF(Scenarios!$Q6=1,BaselineCalc!$B$7*(1+Parameters_Public!$C44)^(IF($C18="FY2026",0,IF($C18="FY2027",1,IF($C18="FY2028",2,IF($C18="FY2029",3,IF($C18="FY2030",4,0))))))+ROUND(Scenarios!J6*Scenarios!$F6,0),BaselineCalc!$B$7+ROUND(Scenarios!J6*Scenarios!$F6,0)) -> 307 | M18: =IF(Scenarios!$R6=1,BaselineCalc!$B$8*(1+Parameters_Public!$C45)^(IF($C18="FY2026",0,IF($C18="FY2027",1,IF($C18="FY2028",2,IF($C18="FY2029",3,IF($C18="FY2030",4,0))))))+Scenarios!J6-ROUND(Scenarios!J6*Scenarios!$F6,0),BaselineCalc!$B$8+Scenarios!J6-ROUND(Scenarios!J6*Scenarios!$F6,0)) -> 346 | N18: =(L18-D18) + (M18-E18) -> 0 | O18: =(Parameters_Public!$C$23*(L18-D18)+Parameters_Public!$C$24*(M18-E18)) -> 0 | P18: =YearMap!E3 -> 800 | Q18: =IF(Scenarios!N6="lease", YearMap!F3, YearMap!G3) -> 0.4 | R18: =IF(Scenarios!D6=1, Q18*H18, H18) -> 915497.15 | S18: =IF(Scenarios!E6=1, Q18*I18, I18) -> 1054424.7 | T18: =IF(C18="FY2026", (Scenarios!D6+Scenarios!E6)*BaselineCalc!$B$22, 0) -> 0 | U18: =(R18+S18+G18*F18)*J18*(1-K18) -> 7541341.5 | V18: =O18*(G18+P18) -> 0 | W18: =U18+V18+IF(Parameters_Public!$C$28=1, T18, 0) -> 7541341.5 | X18: =IF(F18+O18>0, W18/(F18+O18),"") -> 11548.762 | Y18: =INDEX(YearMap!$I$2:$I$6, MATCH(C18, YearMap!$A$2:$A$6, 0)) -> 5138.325 | Z18: =W18 - ((Y18 + IF(Parameters_Public!$C$20=1, Parameters_Public!$C$19, 0))*AC18) -> 3694991.9 | AA18: =IF($AC18>0, $Z18/$AC18, 0) -> 5658.4869 | AB18: =MAX(0, (MAX(0, $D18-BaselineCalc!$B$7) + MAX(0, $E18-BaselineCalc!$B$8))) -> 100 | AC18: =L18+M18-N18+O18 -> 653 | AD18: =( (Y18 + IF(Parameters_Public!$C20=1, INDEX(YearMap!$O$2:$O$6, MATCH(C18, YearMap!$A$2:$A$6, 0)), 0)) * AC18 ) + AC18*INDEX(YearMap!$P$2:$P$6, MATCH(C18, YearMap!$A$2:$A$6, 0)) + AB18*( INDEX(YearMap!$R$2:$R$6, MATCH(C18, YearMap!$A$2:$A$6, 0)) - INDEX(YearMap!$P$2:$P$6, MATCH(C18, YearMap!$A$2:$A$6, 0)) ) -> 7259165.2 | AE18: =(W18 - (1-Parameters_Public!$C$43)*$G18*$AB18*$J18*(1-$K18)) + AB18*INDEX(YearMap!$Q$2:$Q$6, MATCH(C18, YearMap!$A$2:$A$6, 0)) -> 7215215.4 | AF18: =AD18-AE18 -> 43949.771 | AG18: =B18&"|"&C18 -> D1_Grow_Both_Targets|FY2027
A19: =AG19 -> D1_Grow_Both_Targets|FY2028 | B19: =Scenarios!A6 -> D1_Grow_Both_Targets | C19: FY2028 | D19: =IF(Scenarios!D6=1,0, L19) -> 332 | E19: =IF(Scenarios!E6=1,0, M19) -> 371 | F19: =D19+E19 -> 703 | G19: =YearMap!B4 -> 8828.7836 | H19: =YearMap!C4 -> 938384.57 | I19: =YearMap!D4 -> 1080785.3 | J19: =1-BaselineCalc!$B$5 -> 0.993 | K19: =Scenarios!G6 -> 0 | L19: =IF(Scenarios!$Q6=1,BaselineCalc!$B$7*(1+Parameters_Public!$C44)^(IF($C19="FY2026",0,IF($C19="FY2027",1,IF($C19="FY2028",2,IF($C19="FY2029",3,IF($C19="FY2030",4,0))))))+ROUND(Scenarios!K6*Scenarios!$F6,0),BaselineCalc!$B$7+ROUND(Scenarios!K6*Scenarios!$F6,0)) -> 332 | M19: =IF(Scenarios!$R6=1,BaselineCalc!$B$8*(1+Parameters_Public!$C45)^(IF($C19="FY2026",0,IF($C19="FY2027",1,IF($C19="FY2028",2,IF($C19="FY2029",3,IF($C19="FY2030",4,0))))))+Scenarios!K6-ROUND(Scenarios!K6*Scenarios!$F6,0),BaselineCalc!$B$8+Scenarios!K6-ROUND(Scenarios!K6*Scenarios!$F6,0)) -> 371 | N19: =(L19-D19) + (M19-E19) -> 0 | O19: =(Parameters_Public!$C$23*(L19-D19)+Parameters_Public!$C$24*(M19-E19)) -> 0 | P19: =YearMap!E4 -> 600 | Q19: =IF(Scenarios!N6="lease", YearMap!F4, YearMap!G4) -> 0.35 | R19: =IF(Scenarios!D6=1, Q19*H19, H19) -> 938384.57 | S19: =IF(Scenarios!E6=1, Q19*I19, I19) -> 1080785.3 | T19: =IF(C19="FY2026", (Scenarios!D6+Scenarios!E6)*BaselineCalc!$B$22, 0) -> 0 | U19: =(R19+S19+G19*F19)*J19*(1-K19) -> 8168224.2 | V19: =O19*(G19+P19) -> 0 | W19: =U19+V19+IF(Parameters_Public!$C$28=1, T19, 0) -> 8168224.2 | X19: =IF(F19+O19>0, W19/(F19+O19),"") -> 11619.096 | Y19: =INDEX(YearMap!$I$2:$I$6, MATCH(C19, YearMap!$A$2:$A$6, 0)) -> 5266.7831 | Z19: =W19 - ((Y19 + IF(Parameters_Public!$C$20=1, Parameters_Public!$C$19, 0))*AC19) -> 3937054.8 | AA19: =IF($AC19>0, $Z19/$AC19, 0) -> 5600.3624 | AB19: =MAX(0, (MAX(0, $D19-BaselineCalc!$B$7) + MAX(0, $E19-BaselineCalc!$B$8))) -> 150 | AC19: =L19+M19-N19+O19 -> 703 | AD19: =( (Y19 + IF(Parameters_Public!$C20=1, INDEX(YearMap!$O$2:$O$6, MATCH(C19, YearMap!$A$2:$A$6, 0)), 0)) * AC19 ) + AC19*INDEX(YearMap!$P$2:$P$6, MATCH(C19, YearMap!$A$2:$A$6, 0)) + AB19*( INDEX(YearMap!$R$2:$R$6, MATCH(C19, YearMap!$A$2:$A$6, 0)) - INDEX(YearMap!$P$2:$P$6, MATCH(C19, YearMap!$A$2:$A$6, 0)) ) -> 7975672.4 | AE19: =(W19 - (1-Parameters_Public!$C$43)*$G19*$AB19*$J19*(1-$K19)) + AB19*INDEX(YearMap!$Q$2:$Q$6, MATCH(C19, YearMap!$A$2:$A$6, 0)) -> 7660205.2 | AF19: =AD19-AE19 -> 315467.21 | AG19: =B19&"|"&C19 -> D1_Grow_Both_Targets|FY2028
A20: =AG20 -> D1_Grow_Both_Targets|FY2029 | B20: =Scenarios!A6 -> D1_Grow_Both_Targets | C20: FY2029 | D20: =IF(Scenarios!D6=1,0, L20) -> 332 | E20: =IF(Scenarios!E6=1,0, M20) -> 371 | F20: =D20+E20 -> 703 | G20: =YearMap!B5 -> 9049.5032 | H20: =YearMap!C5 -> 961844.19 | I20: =YearMap!D5 -> 1107805 | J20: =1-BaselineCalc!$B$5 -> 0.993 | K20: =Scenarios!G6 -> 0 | L20: =IF(Scenarios!$Q6=1,BaselineCalc!$B$7*(1+Parameters_Public!$C44)^(IF($C20="FY2026",0,IF($C20="FY2027",1,IF($C20="FY2028",2,IF($C20="FY2029",3,IF($C20="FY2030",4,0))))))+ROUND(Scenarios!L6*Scenarios!$F6,0),BaselineCalc!$B$7+ROUND(Scenarios!L6*Scenarios!$F6,0)) -> 332 | M20: =IF(Scenarios!$R6=1,BaselineCalc!$B$8*(1+Parameters_Public!$C45)^(IF($C20="FY2026",0,IF($C20="FY2027",1,IF($C20="FY2028",2,IF($C20="FY2029",3,IF($C20="FY2030",4,0))))))+Scenarios!L6-ROUND(Scenarios!L6*Scenarios!$F6,0),BaselineCalc!$B$8+Scenarios!L6-ROUND(Scenarios!L6*Scenarios!$F6,0)) -> 371 | N20: =(L20-D20) + (M20-E20) -> 0 | O20: =(Parameters_Public!$C$23*(L20-D20)+Parameters_Public!$C$24*(M20-E20)) -> 0 | P20: =YearMap!E5 -> 500 | Q20: =IF(Scenarios!N6="lease", YearMap!F5, YearMap!G5) -> 0.3 | R20: =IF(Scenarios!D6=1, Q20*H20, H20) -> 961844.19 | S20: =IF(Scenarios!E6=1, Q20*I20, I20) -> 1107805 | T20: =IF(C20="FY2026", (Scenarios!D6+Scenarios!E6)*BaselineCalc!$B$22, 0) -> 0 | U20: =(R20+S20+G20*F20)*J20*(1-K20) -> 8372429.8 | V20: =O20*(G20+P20) -> 0 | W20: =U20+V20+IF(Parameters_Public!$C$28=1, T20, 0) -> 8372429.8 | X20: =IF(F20+O20>0, W20/(F20+O20),"") -> 11909.573 | Y20: =INDEX(YearMap!$I$2:$I$6, MATCH(C20, YearMap!$A$2:$A$6, 0)) -> 5398.4527 | Z20: =W20 - ((Y20 + IF(Parameters_Public!$C$20=1, Parameters_Public!$C$19, 0))*AC20) -> 4048696.7 | AA20: =IF($AC20>0, $Z20/$AC20, 0) -> 5759.1702 | AB20: =MAX(0, (MAX(0, $D20-BaselineCalc!$B$7) + MAX(0, $E20-BaselineCalc!$B$8))) -> 150 | AC20: =L20+M20-N20+O20 -> 703 | AD20: =( (Y20 + IF(Parameters_Public!$C20=1, INDEX(YearMap!$O$2:$O$6, MATCH(C20, YearMap!$A$2:$A$6, 0)), 0)) * AC20 ) + AC20*INDEX(YearMap!$P$2:$P$6, MATCH(C20, YearMap!$A$2:$A$6, 0)) + AB20*( INDEX(YearMap!$R$2:$R$6, MATCH(C20, YearMap!$A$2:$A$6, 0)) - INDEX(YearMap!$P$2:$P$6, MATCH(C20, YearMap!$A$2:$A$6, 0)) ) -> 8175064.3 | AE20: =(W20 - (1-Parameters_Public!$C$43)*$G20*$AB20*$J20*(1-$K20)) + AB20*INDEX(YearMap!$Q$2:$Q$6, MATCH(C20, YearMap!$A$2:$A$6, 0)) -> 7848260.4 | AF20: =AD20-AE20 -> 326803.89 | AG20: =B20&"|"&C20 -> D1_Grow_Both_Targets|FY2029
A21: =AG21 -> D1_Grow_Both_Targets|FY2030 | B21: =Scenarios!A6 -> D1_Grow_Both_Targets | C21: FY2030 | D21: =IF(Scenarios!D6=1,0, L21) -> 332 | E21: =IF(Scenarios!E6=1,0, M21) -> 371 | F21: =D21+E21 -> 703 | G21: =YearMap!B6 -> 9275.7408 | H21: =YearMap!C6 -> 985890.29 | I21: =YearMap!D6 -> 1135500.1 | J21: =1-BaselineCalc!$B$5 -> 0.993 | K21: =Scenarios!G6 -> 0 | L21: =IF(Scenarios!$Q6=1,BaselineCalc!$B$7*(1+Parameters_Public!$C44)^(IF($C21="FY2026",0,IF($C21="FY2027",1,IF($C21="FY2028",2,IF($C21="FY2029",3,IF($C21="FY2030",4,0))))))+ROUND(Scenarios!M6*Scenarios!$F6,0),BaselineCalc!$B$7+ROUND(Scenarios!M6*Scenarios!$F6,0)) -> 332 | M21: =IF(Scenarios!$R6=1,BaselineCalc!$B$8*(1+Parameters_Public!$C45)^(IF($C21="FY2026",0,IF($C21="FY2027",1,IF($C21="FY2028",2,IF($C21="FY2029",3,IF($C21="FY2030",4,0))))))+Scenarios!M6-ROUND(Scenarios!M6*Scenarios!$F6,0),BaselineCalc!$B$8+Scenarios!M6-ROUND(Scenarios!M6*Scenarios!$F6,0)) -> 371 | N21: =(L21-D21) + (M21-E21) -> 0 | O21: =(Parameters_Public!$C$23*(L21-D21)+Parameters_Public!$C$24*(M21-E21)) -> 0 | P21: =YearMap!E6 -> 300 | Q21: =IF(Scenarios!N6="lease", YearMap!F6, YearMap!G6) -> 0.3 | R21: =IF(Scenarios!D6=1, Q21*H21, H21) -> 985890.29 | S21: =IF(Scenarios!E6=1, Q21*I21, I21) -> 1135500.1 | T21: =IF(C21="FY2026", (Scenarios!D6+Scenarios!E6)*BaselineCalc!$B$22, 0) -> 0 | U21: =(R21+S21+G21*F21)*J21*(1-K21) -> 8581740.5 | V21: =O21*(G21+P21) -> 0 | W21: =U21+V21+IF(Parameters_Public!$C$28=1, T21, 0) -> 8581740.5 | X21: =IF(F21+O21>0, W21/(F21+O21),"") -> 12207.312 | Y21: =INDEX(YearMap!$I$2:$I$6, MATCH(C21, YearMap!$A$2:$A$6, 0)) -> 5533.414 | Z21: =W21 - ((Y21 + IF(Parameters_Public!$C$20=1, Parameters_Public!$C$19, 0))*AC21) -> 4163129.6 | AA21: =IF($AC21>0, $Z21/$AC21, 0) -> 5921.9482 | AB21: =MAX(0, (MAX(0, $D21-BaselineCalc!$B$7) + MAX(0, $E21-BaselineCalc!$B$8))) -> 150 | AC21: =L21+M21-N21+O21 -> 703 | AD21: =( (Y21 + IF(Parameters_Public!$C20=1, INDEX(YearMap!$O$2:$O$6, MATCH(C21, YearMap!$A$2:$A$6, 0)), 0)) * AC21 ) + AC21*INDEX(YearMap!$P$2:$P$6, MATCH(C21, YearMap!$A$2:$A$6, 0)) + AB21*( INDEX(YearMap!$R$2:$R$6, MATCH(C21, YearMap!$A$2:$A$6, 0)) - INDEX(YearMap!$P$2:$P$6, MATCH(C21, YearMap!$A$2:$A$6, 0)) ) -> 8379440.9 | AE21: =(W21 - (1-Parameters_Public!$C$43)*$G21*$AB21*$J21*(1-$K21)) + AB21*INDEX(YearMap!$Q$2:$Q$6, MATCH(C21, YearMap!$A$2:$A$6, 0)) -> 8038091.9 | AF21: =AD21-AE21 -> 341348.98 | AG21: =B21&"|"&C21 -> D1_Grow_Both_Targets|FY2030
A22: =AG22 -> E2_StatusQuo_Steady|FY2026 | B22: =Scenarios!A7 -> E2_StatusQuo_Steady | C22: FY2026 | D22: =IF(Scenarios!D7=1,0, L22) -> 257 | E22: =IF(Scenarios!E7=1,0, M22) -> 296 | F22: =D22+E22 -> 553 | G22: =YearMap!B2 -> 8403.3633 | H22: =YearMap!C2 -> 922500 | I22: =YearMap!D2 -> 999375 | J22: =1-BaselineCalc!$B$5 -> 0.993 | K22: =Scenarios!G7 -> 0 | L22: =IF(Scenarios!$Q7=1,BaselineCalc!$B$7*(1+Parameters_Public!$C44)^(IF($C22="FY2026",0,IF($C22="FY2027",1,IF($C22="FY2028",2,IF($C22="FY2029",3,IF($C22="FY2030",4,0))))))+ROUND(Scenarios!I7*Scenarios!$F7,0),BaselineCalc!$B$7+ROUND(Scenarios!I7*Scenarios!$F7,0)) -> 257 | M22: =IF(Scenarios!$R7=1,BaselineCalc!$B$8*(1+Parameters_Public!$C45)^(IF($C22="FY2026",0,IF($C22="FY2027",1,IF($C22="FY2028",2,IF($C22="FY2029",3,IF($C22="FY2030",4,0))))))+Scenarios!I7-ROUND(Scenarios!I7*Scenarios!$F7,0),BaselineCalc!$B$8+Scenarios!I7-ROUND(Scenarios!I7*Scenarios!$F7,0)) -> 296 | N22: =(L22-D22) + (M22-E22) -> 0 | O22: =(Parameters_Public!$C$23*(L22-D22)+Parameters_Public!$C$24*(M22-E22)) -> 0 | P22: =YearMap!E2 -> 1000 | Q22: =IF(Scenarios!N7="lease", YearMap!F2, YearMap!G2) -> 0.45 | R22: =IF(Scenarios!D7=1, Q22*H22, H22) -> 922500 | S22: =IF(Scenarios!E7=1, Q22*I22, I22) -> 999375 | T22: =IF(C22="FY2026", (Scenarios!D7+Scenarios!E7)*BaselineCalc!$B$22, 0) -> 0 | U22: =(R22+S22+G22*F22)*J22*(1-K22) -> 6522952.4 | V22: =O22*(G22+P22) -> 0 | W22: =U22+V22+IF(Parameters_Public!$C$28=1, T22, 0) -> 6522952.4 | X22: =IF(F22+O22>0, W22/(F22+O22),"") -> 11795.574 | Y22: =INDEX(YearMap!$I$2:$I$6, MATCH(C22, YearMap!$A$2:$A$6, 0)) -> 5013 | Z22: =W22 - ((Y22 + IF(Parameters_Public!$C$20=1, Parameters_Public!$C$19, 0))*AC22) -> 3334935 | AA22: =IF($AC22>0, $Z22/$AC22, 0) -> 6030.6239 | AB22: =MAX(0, (MAX(0, $D22-BaselineCalc!$B$7) + MAX(0, $E22-BaselineCalc!$B$8))) -> 0 | AC22: =L22+M22-N22+O22 -> 553 | AD22: =( (Y22 + IF(Parameters_Public!$C20=1, INDEX(YearMap!$O$2:$O$6, MATCH(C22, YearMap!$A$2:$A$6, 0)), 0)) * AC22 ) + AC22*INDEX(YearMap!$P$2:$P$6, MATCH(C22, YearMap!$A$2:$A$6, 0)) + AB22*( INDEX(YearMap!$R$2:$R$6, MATCH(C22, YearMap!$A$2:$A$6, 0)) - INDEX(YearMap!$P$2:$P$6, MATCH(C22, YearMap!$A$2:$A$6, 0)) ) -> 6063617.3 | AE22: =(W22 - (1-Parameters_Public!$C$43)*$G22*$AB22*$J22*(1-$K22)) + AB22*INDEX(YearMap!$Q$2:$Q$6, MATCH(C22, YearMap!$A$2:$A$6, 0)) -> 6522952.4 | AF22: =AD22-AE22 -> -459335.03 | AG22: =B22&"|"&C22 -> E2_StatusQuo_Steady|FY2026
A23: =AG23 -> E2_StatusQuo_Steady|FY2027 | B23: =Scenarios!A7 -> E2_StatusQuo_Steady | C23: FY2027 | D23: =IF(Scenarios!D7=1,0, L23) -> 257 | E23: =IF(Scenarios!E7=1,0, M23) -> 296 | F23: =D23+E23 -> 553 | G23: =YearMap!B3 -> 8613.4474 | H23: =YearMap!C3 -> 915497.15 | I23: =YearMap!D3 -> 1054424.7 | J23: =1-BaselineCalc!$B$5 -> 0.993 | K23: =Scenarios!G7 -> 0 | L23: =IF(Scenarios!$Q7=1,BaselineCalc!$B$7*(1+Parameters_Public!$C44)^(IF($C23="FY2026",0,IF($C23="FY2027",1,IF($C23="FY2028",2,IF($C23="FY2029",3,IF($C23="FY2030",4,0))))))+ROUND(Scenarios!J7*Scenarios!$F7,0),BaselineCalc!$B$7+ROUND(Scenarios!J7*Scenarios!$F7,0)) -> 257 | M23: =IF(Scenarios!$R7=1,BaselineCalc!$B$8*(1+Parameters_Public!$C45)^(IF($C23="FY2026",0,IF($C23="FY2027",1,IF($C23="FY2028",2,IF($C23="FY2029",3,IF($C23="FY2030",4,0))))))+Scenarios!J7-ROUND(Scenarios!J7*Scenarios!$F7,0),BaselineCalc!$B$8+Scenarios!J7-ROUND(Scenarios!J7*Scenarios!$F7,0)) -> 296 | N23: =(L23-D23) + (M23-E23) -> 0 | O23: =(Parameters_Public!$C$23*(L23-D23)+Parameters_Public!$C$24*(M23-E23)) -> 0 | P23: =YearMap!E3 -> 800 | Q23: =IF(Scenarios!N7="lease", YearMap!F3, YearMap!G3) -> 0.4 | R23: =IF(Scenarios!D7=1, Q23*H23, H23) -> 915497.15 | S23: =IF(Scenarios!E7=1, Q23*I23, I23) -> 1054424.7 | T23: =IF(C23="FY2026", (Scenarios!D7+Scenarios!E7)*BaselineCalc!$B$22, 0) -> 0 | U23: =(R23+S23+G23*F23)*J23*(1-K23) -> 6686026.2 | V23: =O23*(G23+P23) -> 0 | W23: =U23+V23+IF(Parameters_Public!$C$28=1, T23, 0) -> 6686026.2 | X23: =IF(F23+O23>0, W23/(F23+O23),"") -> 12090.463 | Y23: =INDEX(YearMap!$I$2:$I$6, MATCH(C23, YearMap!$A$2:$A$6, 0)) -> 5138.325 | Z23: =W23 - ((Y23 + IF(Parameters_Public!$C$20=1, Parameters_Public!$C$19, 0))*AC23) -> 3428704.1 | AA23: =IF($AC23>0, $Z23/$AC23, 0) -> 6200.1883 | AB23: =MAX(0, (MAX(0, $D23-BaselineCalc!$B$7) + MAX(0, $E23-BaselineCalc!$B$8))) -> 0 | AC23: =L23+M23-N23+O23 -> 553 | AD23: =( (Y23 + IF(Parameters_Public!$C20=1, INDEX(YearMap!$O$2:$O$6, MATCH(C23, YearMap!$A$2:$A$6, 0)), 0)) * AC23 ) + AC23*INDEX(YearMap!$P$2:$P$6, MATCH(C23, YearMap!$A$2:$A$6, 0)) + AB23*( INDEX(YearMap!$R$2:$R$6, MATCH(C23, YearMap!$A$2:$A$6, 0)) - INDEX(YearMap!$P$2:$P$6, MATCH(C23, YearMap!$A$2:$A$6, 0)) ) -> 6215207.8 | AE23: =(W23 - (1-Parameters_Public!$C$43)*$G23*$AB23*$J23*(1-$K23)) + AB23*INDEX(YearMap!$Q$2:$Q$6, MATCH(C23, YearMap!$A$2:$A$6, 0)) -> 6686026.2 | AF23: =AD23-AE23 -> -470818.41 | AG23: =B23&"|"&C23 -> E2_StatusQuo_Steady|FY2027
A24: =AG24 -> E2_StatusQuo_Steady|FY2028 | B24: =Scenarios!A7 -> E2_StatusQuo_Steady | C24: FY2028 | D24: =IF(Scenarios!D7=1,0, L24) -> 257 | E24: =IF(Scenarios!E7=1,0, M24) -> 296 | F24: =D24+E24 -> 553 | G24: =YearMap!B4 -> 8828.7836 | H24: =YearMap!C4 -> 938384.57 | I24: =YearMap!D4 -> 1080785.3 | J24: =1-BaselineCalc!$B$5 -> 0.993 | K24: =Scenarios!G7 -> 0 | L24: =IF(Scenarios!$Q7=1,BaselineCalc!$B$7*(1+Parameters_Public!$C44)^(IF($C24="FY2026",0,IF($C24="FY2027",1,IF($C24="FY2028",2,IF($C24="FY2029",3,IF($C24="FY2030",4,0))))))+ROUND(Scenarios!K7*Scenarios!$F7,0),BaselineCalc!$B$7+ROUND(Scenarios!K7*Scenarios!$F7,0)) -> 257 | M24: =IF(Scenarios!$R7=1,BaselineCalc!$B$8*(1+Parameters_Public!$C45)^(IF($C24="FY2026",0,IF($C24="FY2027",1,IF($C24="FY2028",2,IF($C24="FY2029",3,IF($C24="FY2030",4,0))))))+Scenarios!K7-ROUND(Scenarios!K7*Scenarios!$F7,0),BaselineCalc!$B$8+Scenarios!K7-ROUND(Scenarios!K7*Scenarios!$F7,0)) -> 296 | N24: =(L24-D24) + (M24-E24) -> 0 | O24: =(Parameters_Public!$C$23*(L24-D24)+Parameters_Public!$C$24*(M24-E24)) -> 0 | P24: =YearMap!E4 -> 600 | Q24: =IF(Scenarios!N7="lease", YearMap!F4, YearMap!G4) -> 0.35 | R24: =IF(Scenarios!D7=1, Q24*H24, H24) -> 938384.57 | S24: =IF(Scenarios!E7=1, Q24*I24, I24) -> 1080785.3 | T24: =IF(C24="FY2026", (Scenarios!D7+Scenarios!E7)*BaselineCalc!$B$22, 0) -> 0 | U24: =(R24+S24+G24*F24)*J24*(1-K24) -> 6853176.8 | V24: =O24*(G24+P24) -> 0 | W24: =U24+V24+IF(Parameters_Public!$C$28=1, T24, 0) -> 6853176.8 | X24: =IF(F24+O24>0, W24/(F24+O24),"") -> 12392.725 | Y24: =INDEX(YearMap!$I$2:$I$6, MATCH(C24, YearMap!$A$2:$A$6, 0)) -> 5266.7831 | Z24: =W24 - ((Y24 + IF(Parameters_Public!$C$20=1, Parameters_Public!$C$19, 0))*AC24) -> 3524817.4 | AA24: =IF($AC24>0, $Z24/$AC24, 0) -> 6373.9917 | AB24: =MAX(0, (MAX(0, $D24-BaselineCalc!$B$7) + MAX(0, $E24-BaselineCalc!$B$8))) -> 0 | AC24: =L24+M24-N24+O24 -> 553 | AD24: =( (Y24 + IF(Parameters_Public!$C20=1, INDEX(YearMap!$O$2:$O$6, MATCH(C24, YearMap!$A$2:$A$6, 0)), 0)) * AC24 ) + AC24*INDEX(YearMap!$P$2:$P$6, MATCH(C24, YearMap!$A$2:$A$6, 0)) + AB24*( INDEX(YearMap!$R$2:$R$6, MATCH(C24, YearMap!$A$2:$A$6, 0)) - INDEX(YearMap!$P$2:$P$6, MATCH(C24, YearMap!$A$2:$A$6, 0)) ) -> 6370588 | AE24: =(W24 - (1-Parameters_Public!$C$43)*$G24*$AB24*$J24*(1-$K24)) + AB24*INDEX(YearMap!$Q$2:$Q$6, MATCH(C24, YearMap!$A$2:$A$6, 0)) -> 6853176.8 | AF24: =AD24-AE24 -> -482588.87 | AG24: =B24&"|"&C24 -> E2_StatusQuo_Steady|FY2028
A25: =AG25 -> E2_StatusQuo_Steady|FY2029 | B25: =Scenarios!A7 -> E2_StatusQuo_Steady | C25: FY2029 | D25: =IF(Scenarios!D7=1,0, L25) -> 257 | E25: =IF(Scenarios!E7=1,0, M25) -> 296 | F25: =D25+E25 -> 553 | G25: =YearMap!B5 -> 9049.5032 | H25: =YearMap!C5 -> 961844.19 | I25: =YearMap!D5 -> 1107805 | J25: =1-BaselineCalc!$B$5 -> 0.993 | K25: =Scenarios!G7 -> 0 | L25: =IF(Scenarios!$Q7=1,BaselineCalc!$B$7*(1+Parameters_Public!$C44)^(IF($C25="FY2026",0,IF($C25="FY2027",1,IF($C25="FY2028",2,IF($C25="FY2029",3,IF($C25="FY2030",4,0))))))+ROUND(Scenarios!L7*Scenarios!$F7,0),BaselineCalc!$B$7+ROUND(Scenarios!L7*Scenarios!$F7,0)) -> 257 | M25: =IF(Scenarios!$R7=1,BaselineCalc!$B$8*(1+Parameters_Public!$C45)^(IF($C25="FY2026",0,IF($C25="FY2027",1,IF($C25="FY2028",2,IF($C25="FY2029",3,IF($C25="FY2030",4,0))))))+Scenarios!L7-ROUND(Scenarios!L7*Scenarios!$F7,0),BaselineCalc!$B$8+Scenarios!L7-ROUND(Scenarios!L7*Scenarios!$F7,0)) -> 296 | N25: =(L25-D25) + (M25-E25) -> 0 | O25: =(Parameters_Public!$C$23*(L25-D25)+Parameters_Public!$C$24*(M25-E25)) -> 0 | P25: =YearMap!E5 -> 500 | Q25: =IF(Scenarios!N7="lease", YearMap!F5, YearMap!G5) -> 0.3 | R25: =IF(Scenarios!D7=1, Q25*H25, H25) -> 961844.19 | S25: =IF(Scenarios!E7=1, Q25*I25, I25) -> 1107805 | T25: =IF(C25="FY2026", (Scenarios!D7+Scenarios!E7)*BaselineCalc!$B$22, 0) -> 0 | U25: =(R25+S25+G25*F25)*J25*(1-K25) -> 7024506.3 | V25: =O25*(G25+P25) -> 0 | W25: =U25+V25+IF(Parameters_Public!$C$28=1, T25, 0) -> 7024506.3 | X25: =IF(F25+O25>0, W25/(F25+O25),"") -> 12702.543 | Y25: =INDEX(YearMap!$I$2:$I$6, MATCH(C25, YearMap!$A$2:$A$6, 0)) -> 5398.4527 | Z25: =W25 - ((Y25 + IF(Parameters_Public!$C$20=1, Parameters_Public!$C$19, 0))*AC25) -> 3623333.6 | AA25: =IF($AC25>0, $Z25/$AC25, 0) -> 6552.1403 | AB25: =MAX(0, (MAX(0, $D25-BaselineCalc!$B$7) + MAX(0, $E25-BaselineCalc!$B$8))) -> 0 | AC25: =L25+M25-N25+O25 -> 553 | AD25: =( (Y25 + IF(Parameters_Public!$C20=1, INDEX(YearMap!$O$2:$O$6, MATCH(C25, YearMap!$A$2:$A$6, 0)), 0)) * AC25 ) + AC25*INDEX(YearMap!$P$2:$P$6, MATCH(C25, YearMap!$A$2:$A$6, 0)) + AB25*( INDEX(YearMap!$R$2:$R$6, MATCH(C25, YearMap!$A$2:$A$6, 0)) - INDEX(YearMap!$P$2:$P$6, MATCH(C25, YearMap!$A$2:$A$6, 0)) ) -> 6529852.7 | AE25: =(W25 - (1-Parameters_Public!$C$43)*$G25*$AB25*$J25*(1-$K25)) + AB25*INDEX(YearMap!$Q$2:$Q$6, MATCH(C25, YearMap!$A$2:$A$6, 0)) -> 7024506.3 | AF25: =AD25-AE25 -> -494653.59 | AG25: =B25&"|"&C25 -> E2_StatusQuo_Steady|FY2029
A26: =AG26 -> E2_StatusQuo_Steady|FY2030 | B26: =Scenarios!A7 -> E2_StatusQuo_Steady | C26: FY2030 | D26: =IF(Scenarios!D7=1,0, L26) -> 257 | E26: =IF(Scenarios!E7=1,0, M26) -> 296 | F26: =D26+E26 -> 553 | G26: =YearMap!B6 -> 9275.7408 | H26: =YearMap!C6 -> 985890.29 | I26: =YearMap!D6 -> 1135500.1 | J26: =1-BaselineCalc!$B$5 -> 0.993 | K26: =Scenarios!G7 -> 0 | L26: =IF(Scenarios!$Q7=1,BaselineCalc!$B$7*(1+Parameters_Public!$C44)^(IF($C26="FY2026",0,IF($C26="FY2027",1,IF($C26="FY2028",2,IF($C26="FY2029",3,IF($C26="FY2030",4,0))))))+ROUND(Scenarios!M7*Scenarios!$F7,0),BaselineCalc!$B$7+ROUND(Scenarios!M7*Scenarios!$F7,0)) -> 257 | M26: =IF(Scenarios!$R7=1,BaselineCalc!$B$8*(1+Parameters_Public!$C45)^(IF($C26="FY2026",0,IF($C26="FY2027",1,IF($C26="FY2028",2,IF($C26="FY2029",3,IF($C26="FY2030",4,0))))))+Scenarios!M7-ROUND(Scenarios!M7*Scenarios!$F7,0),BaselineCalc!$B$8+Scenarios!M7-ROUND(Scenarios!M7*Scenarios!$F7,0)) -> 296 | N26: =(L26-D26) + (M26-E26) -> 0 | O26: =(Parameters_Public!$C$23*(L26-D26)+Parameters_Public!$C$24*(M26-E26)) -> 0 | P26: =YearMap!E6 -> 300 | Q26: =IF(Scenarios!N7="lease", YearMap!F6, YearMap!G6) -> 0.3 | R26: =IF(Scenarios!D7=1, Q26*H26, H26) -> 985890.29 | S26: =IF(Scenarios!E7=1, Q26*I26, I26) -> 1135500.1 | T26: =IF(C26="FY2026", (Scenarios!D7+Scenarios!E7)*BaselineCalc!$B$22, 0) -> 0 | U26: =(R26+S26+G26*F26)*J26*(1-K26) -> 7200118.9 | V26: =O26*(G26+P26) -> 0 | W26: =U26+V26+IF(Parameters_Public!$C$28=1, T26, 0) -> 7200118.9 | X26: =IF(F26+O26>0, W26/(F26+O26),"") -> 13020.107 | Y26: =INDEX(YearMap!$I$2:$I$6, MATCH(C26, YearMap!$A$2:$A$6, 0)) -> 5533.414 | Z26: =W26 - ((Y26 + IF(Parameters_Public!$C$20=1, Parameters_Public!$C$19, 0))*AC26) -> 3724312.6 | AA26: =IF($AC26>0, $Z26/$AC26, 0) -> 6734.7425 | AB26: =MAX(0, (MAX(0, $D26-BaselineCalc!$B$7) + MAX(0, $E26-BaselineCalc!$B$8))) -> 0 | AC26: =L26+M26-N26+O26 -> 553 | AD26: =( (Y26 + IF(Parameters_Public!$C20=1, INDEX(YearMap!$O$2:$O$6, MATCH(C26, YearMap!$A$2:$A$6, 0)), 0)) * AC26 ) + AC26*INDEX(YearMap!$P$2:$P$6, MATCH(C26, YearMap!$A$2:$A$6, 0)) + AB26*( INDEX(YearMap!$R$2:$R$6, MATCH(C26, YearMap!$A$2:$A$6, 0)) - INDEX(YearMap!$P$2:$P$6, MATCH(C26, YearMap!$A$2:$A$6, 0)) ) -> 6693099 | AE26: =(W26 - (1-Parameters_Public!$C$43)*$G26*$AB26*$J26*(1-$K26)) + AB26*INDEX(YearMap!$Q$2:$Q$6, MATCH(C26, YearMap!$A$2:$A$6, 0)) -> 7200118.9 | AF26: =AD26-AE26 -> -507019.93 | AG26: =B26&"|"&C26 -> E2_StatusQuo_Steady|FY2030
A27: =AG27 -> D2_EchoGHubRamp_PimaTargets|FY2026 | B27: =Scenarios!A8 -> D2_EchoGHubRamp_PimaTargets | C27: FY2026 | D27: =IF(Scenarios!D8=1,0, L27) -> 286 | E27: =IF(Scenarios!E8=1,0, M27) -> 308.66667 | F27: =D27+E27 -> 594.66667 | G27: =YearMap!B2 -> 8403.3633 | H27: =YearMap!C2 -> 922500 | I27: =YearMap!D2 -> 999375 | J27: =1-BaselineCalc!$B$5 -> 0.993 | K27: =Scenarios!G8 -> 0 | L27: =IF(Scenarios!$Q8=1,BaselineCalc!$B$7*(1+Parameters_Public!$C44)^(IF($C27="FY2026",0,IF($C27="FY2027",1,IF($C27="FY2028",2,IF($C27="FY2029",3,IF($C27="FY2030",4,0))))))+ROUND(Scenarios!I8*Scenarios!$F8,0),BaselineCalc!$B$7+ROUND(Scenarios!I8*Scenarios!$F8,0)) -> 286 | M27: =IF(Scenarios!$R8=1,BaselineCalc!$B$8*(1+Parameters_Public!$C45)^(IF($C27="FY2026",0,IF($C27="FY2027",1,IF($C27="FY2028",2,IF($C27="FY2029",3,IF($C27="FY2030",4,0))))))+Scenarios!I8-ROUND(Scenarios!I8*Scenarios!$F8,0),BaselineCalc!$B$8+Scenarios!I8-ROUND(Scenarios!I8*Scenarios!$F8,0)) -> 308.66667 | N27: =(L27-D27) + (M27-E27) -> 0 | O27: =(Parameters_Public!$C$23*(L27-D27)+Parameters_Public!$C$24*(M27-E27)) -> 0 | P27: =YearMap!E2 -> 1000 | Q27: =IF(Scenarios!N8="lease", YearMap!F2, YearMap!G2) -> 0.45 | R27: =IF(Scenarios!D8=1, Q27*H27, H27) -> 922500 | S27: =IF(Scenarios!E8=1, Q27*I27, I27) -> 999375 | T27: =IF(C27="FY2026", (Scenarios!D8+Scenarios!E8)*BaselineCalc!$B$22, 0) -> 0 | U27: =(R27+S27+G27*F27)*J27*(1-K27) -> 6870641.5 | V27: =O27*(G27+P27) -> 0 | W27: =U27+V27+IF(Parameters_Public!$C$28=1, T27, 0) -> 6870641.5 | X27: =IF(F27+O27>0, W27/(F27+O27),"") -> 11553.769 | Y27: =INDEX(YearMap!$I$2:$I$6, MATCH(C27, YearMap!$A$2:$A$6, 0)) -> 5013 | Z27: =W27 - ((Y27 + IF(Parameters_Public!$C$20=1, Parameters_Public!$C$19, 0))*AC27) -> 3442417.9 | AA27: =IF($AC27>0, $Z27/$AC27, 0) -> 5788.8194 | AB27: =MAX(0, (MAX(0, $D27-BaselineCalc!$B$7) + MAX(0, $E27-BaselineCalc!$B$8))) -> 41.666667 | AC27: =L27+M27-N27+O27 -> 594.66667 | AD27: =( (Y27 + IF(Parameters_Public!$C20=1, INDEX(YearMap!$O$2:$O$6, MATCH(C27, YearMap!$A$2:$A$6, 0)), 0)) * AC27 ) + AC27*INDEX(YearMap!$P$2:$P$6, MATCH(C27, YearMap!$A$2:$A$6, 0)) + AB27*( INDEX(YearMap!$R$2:$R$6, MATCH(C27, YearMap!$A$2:$A$6, 0)) - INDEX(YearMap!$P$2:$P$6, MATCH(C27, YearMap!$A$2:$A$6, 0)) ) -> 6487990.3 | AE27: =(W27 - (1-Parameters_Public!$C$43)*$G27*$AB27*$J27*(1-$K27)) + AB27*INDEX(YearMap!$Q$2:$Q$6, MATCH(C27, YearMap!$A$2:$A$6, 0)) -> 6739899.2 | AF27: =AD27-AE27 -> -251908.94 | AG27: =B27&"|"&C27 -> D2_EchoGHubRamp_PimaTargets|FY2026
A28: =AG28 -> D2_EchoGHubRamp_PimaTargets|FY2027 | B28: =Scenarios!A8 -> D2_EchoGHubRamp_PimaTargets | C28: FY2027 | D28: =IF(Scenarios!D8=1,0, L28) -> 315 | E28: =IF(Scenarios!E8=1,0, M28) -> 321.33333 | F28: =D28+E28 -> 636.33333 | G28: =YearMap!B3 -> 8613.4474 | H28: =YearMap!C3 -> 915497.15 | I28: =YearMap!D3 -> 1054424.7 | J28: =1-BaselineCalc!$B$5 -> 0.993 | K28: =Scenarios!G8 -> 0 | L28: =IF(Scenarios!$Q8=1,BaselineCalc!$B$7*(1+Parameters_Public!$C44)^(IF($C28="FY2026",0,IF($C28="FY2027",1,IF($C28="FY2028",2,IF($C28="FY2029",3,IF($C28="FY2030",4,0))))))+ROUND(Scenarios!J8*Scenarios!$F8,0),BaselineCalc!$B$7+ROUND(Scenarios!J8*Scenarios!$F8,0)) -> 315 | M28: =IF(Scenarios!$R8=1,BaselineCalc!$B$8*(1+Parameters_Public!$C45)^(IF($C28="FY2026",0,IF($C28="FY2027",1,IF($C28="FY2028",2,IF($C28="FY2029",3,IF($C28="FY2030",4,0))))))+Scenarios!J8-ROUND(Scenarios!J8*Scenarios!$F8,0),BaselineCalc!$B$8+Scenarios!J8-ROUND(Scenarios!J8*Scenarios!$F8,0)) -> 321.33333 | N28: =(L28-D28) + (M28-E28) -> 0 | O28: =(Parameters_Public!$C$23*(L28-D28)+Parameters_Public!$C$24*(M28-E28)) -> 0 | P28: =YearMap!E3 -> 800 | Q28: =IF(Scenarios!N8="lease", YearMap!F3, YearMap!G3) -> 0.4 | R28: =IF(Scenarios!D8=1, Q28*H28, H28) -> 915497.15 | S28: =IF(Scenarios!E8=1, Q28*I28, I28) -> 1054424.7 | T28: =IF(C28="FY2026", (Scenarios!D8+Scenarios!E8)*BaselineCalc!$B$22, 0) -> 0 | U28: =(R28+S28+G28*F28)*J28*(1-K28) -> 7398789 | V28: =O28*(G28+P28) -> 0 | W28: =U28+V28+IF(Parameters_Public!$C$28=1, T28, 0) -> 7398789 | X28: =IF(F28+O28>0, W28/(F28+O28),"") -> 11627.222 | Y28: =INDEX(YearMap!$I$2:$I$6, MATCH(C28, YearMap!$A$2:$A$6, 0)) -> 5138.325 | Z28: =W28 - ((Y28 + IF(Parameters_Public!$C$20=1, Parameters_Public!$C$19, 0))*AC28) -> 3650610.6 | AA28: =IF($AC28>0, $Z28/$AC28, 0) -> 5736.947 | AB28: =MAX(0, (MAX(0, $D28-BaselineCalc!$B$7) + MAX(0, $E28-BaselineCalc!$B$8))) -> 83.333333 | AC28: =L28+M28-N28+O28 -> 636.33333 | AD28: =( (Y28 + IF(Parameters_Public!$C20=1, INDEX(YearMap!$O$2:$O$6, MATCH(C28, YearMap!$A$2:$A$6, 0)), 0)) * AC28 ) + AC28*INDEX(YearMap!$P$2:$P$6, MATCH(C28, YearMap!$A$2:$A$6, 0)) + AB28*( INDEX(YearMap!$R$2:$R$6, MATCH(C28, YearMap!$A$2:$A$6, 0)) - INDEX(YearMap!$P$2:$P$6, MATCH(C28, YearMap!$A$2:$A$6, 0)) ) -> 7085172.3 | AE28: =(W28 - (1-Parameters_Public!$C$43)*$G28*$AB28*$J28*(1-$K28)) + AB28*INDEX(YearMap!$Q$2:$Q$6, MATCH(C28, YearMap!$A$2:$A$6, 0)) -> 7127017.2 | AF28: =AD28-AE28 -> -41844.925 | AG28: =B28&"|"&C28 -> D2_EchoGHubRamp_PimaTargets|FY2027
A29: =AG29 -> D2_EchoGHubRamp_PimaTargets|FY2028 | B29: =Scenarios!A8 -> D2_EchoGHubRamp_PimaTargets | C29: FY2028 | D29: =IF(Scenarios!D8=1,0, L29) -> 345 | E29: =IF(Scenarios!E8=1,0, M29) -> 333 | F29: =D29+E29 -> 678 | G29: =YearMap!B4 -> 8828.7836 | H29: =YearMap!C4 -> 938384.57 | I29: =YearMap!D4 -> 1080785.3 | J29: =1-BaselineCalc!$B$5 -> 0.993 | K29: =Scenarios!G8 -> 0 | L29: =IF(Scenarios!$Q8=1,BaselineCalc!$B$7*(1+Parameters_Public!$C44)^(IF($C29="FY2026",0,IF($C29="FY2027",1,IF($C29="FY2028",2,IF($C29="FY2029",3,IF($C29="FY2030",4,0))))))+ROUND(Scenarios!K8*Scenarios!$F8,0),BaselineCalc!$B$7+ROUND(Scenarios!K8*Scenarios!$F8,0)) -> 345 | M29: =IF(Scenarios!$R8=1,BaselineCalc!$B$8*(1+Parameters_Public!$C45)^(IF($C29="FY2026",0,IF($C29="FY2027",1,IF($C29="FY2028",2,IF($C29="FY2029",3,IF($C29="FY2030",4,0))))))+Scenarios!K8-ROUND(Scenarios!K8*Scenarios!$F8,0),BaselineCalc!$B$8+Scenarios!K8-ROUND(Scenarios!K8*Scenarios!$F8,0)) -> 333 | N29: =(L29-D29) + (M29-E29) -> 0 | O29: =(Parameters_Public!$C$23*(L29-D29)+Parameters_Public!$C$24*(M29-E29)) -> 0 | P29: =YearMap!E4 -> 600 | Q29: =IF(Scenarios!N8="lease", YearMap!F4, YearMap!G4) -> 0.35 | R29: =IF(Scenarios!D8=1, Q29*H29, H29) -> 938384.57 | S29: =IF(Scenarios!E8=1, Q29*I29, I29) -> 1080785.3 | T29: =IF(C29="FY2026", (Scenarios!D8+Scenarios!E8)*BaselineCalc!$B$22, 0) -> 0 | U29: =(R29+S29+G29*F29)*J29*(1-K29) -> 7949049.6 | V29: =O29*(G29+P29) -> 0 | W29: =U29+V29+IF(Parameters_Public!$C$28=1, T29, 0) -> 7949049.6 | X29: =IF(F29+O29>0, W29/(F29+O29),"") -> 11724.262 | Y29: =INDEX(YearMap!$I$2:$I$6, MATCH(C29, YearMap!$A$2:$A$6, 0)) -> 5266.7831 | Z29: =W29 - ((Y29 + IF(Parameters_Public!$C$20=1, Parameters_Public!$C$19, 0))*AC29) -> 3868348.6 | AA29: =IF($AC29>0, $Z29/$AC29, 0) -> 5705.5288 | AB29: =MAX(0, (MAX(0, $D29-BaselineCalc!$B$7) + MAX(0, $E29-BaselineCalc!$B$8))) -> 125 | AC29: =L29+M29-N29+O29 -> 678 | AD29: =( (Y29 + IF(Parameters_Public!$C20=1, INDEX(YearMap!$O$2:$O$6, MATCH(C29, YearMap!$A$2:$A$6, 0)), 0)) * AC29 ) + AC29*INDEX(YearMap!$P$2:$P$6, MATCH(C29, YearMap!$A$2:$A$6, 0)) + AB29*( INDEX(YearMap!$R$2:$R$6, MATCH(C29, YearMap!$A$2:$A$6, 0)) - INDEX(YearMap!$P$2:$P$6, MATCH(C29, YearMap!$A$2:$A$6, 0)) ) -> 7708158.4 | AE29: =(W29 - (1-Parameters_Public!$C$43)*$G29*$AB29*$J29*(1-$K29)) + AB29*INDEX(YearMap!$Q$2:$Q$6, MATCH(C29, YearMap!$A$2:$A$6, 0)) -> 7525700.5 | AF29: =AD29-AE29 -> 182457.86 | AG29: =B29&"|"&C29 -> D2_EchoGHubRamp_PimaTargets|FY2028
A30: =AG30 -> D2_EchoGHubRamp_PimaTargets|FY2029 | B30: =Scenarios!A8 -> D2_EchoGHubRamp_PimaTargets | C30: FY2029 | D30: =IF(Scenarios!D8=1,0, L30) -> 345 | E30: =IF(Scenarios!E8=1,0, M30) -> 333 | F30: =D30+E30 -> 678 | G30: =YearMap!B5 -> 9049.5032 | H30: =YearMap!C5 -> 961844.19 | I30: =YearMap!D5 -> 1107805 | J30: =1-BaselineCalc!$B$5 -> 0.993 | K30: =Scenarios!G8 -> 0 | L30: =IF(Scenarios!$Q8=1,BaselineCalc!$B$7*(1+Parameters_Public!$C44)^(IF($C30="FY2026",0,IF($C30="FY2027",1,IF($C30="FY2028",2,IF($C30="FY2029",3,IF($C30="FY2030",4,0))))))+ROUND(Scenarios!L8*Scenarios!$F8,0),BaselineCalc!$B$7+ROUND(Scenarios!L8*Scenarios!$F8,0)) -> 345 | M30: =IF(Scenarios!$R8=1,BaselineCalc!$B$8*(1+Parameters_Public!$C45)^(IF($C30="FY2026",0,IF($C30="FY2027",1,IF($C30="FY2028",2,IF($C30="FY2029",3,IF($C30="FY2030",4,0))))))+Scenarios!L8-ROUND(Scenarios!L8*Scenarios!$F8,0),BaselineCalc!$B$8+Scenarios!L8-ROUND(Scenarios!L8*Scenarios!$F8,0)) -> 333 | N30: =(L30-D30) + (M30-E30) -> 0 | O30: =(Parameters_Public!$C$23*(L30-D30)+Parameters_Public!$C$24*(M30-E30)) -> 0 | P30: =YearMap!E5 -> 500 | Q30: =IF(Scenarios!N8="lease", YearMap!F5, YearMap!G5) -> 0.3 | R30: =IF(Scenarios!D8=1, Q30*H30, H30) -> 961844.19 | S30: =IF(Scenarios!E8=1, Q30*I30, I30) -> 1107805 | T30: =IF(C30="FY2026", (Scenarios!D8+Scenarios!E8)*BaselineCalc!$B$22, 0) -> 0 | U30: =(R30+S30+G30*F30)*J30*(1-K30) -> 8147775.9 | V30: =O30*(G30+P30) -> 0 | W30: =U30+V30+IF(Parameters_Public!$C$28=1, T30, 0) -> 8147775.9 | X30: =IF(F30+O30>0, W30/(F30+O30),"") -> 12017.369 | Y30: =INDEX(YearMap!$I$2:$I$6, MATCH(C30, YearMap!$A$2:$A$6, 0)) -> 5398.4527 | Z30: =W30 - ((Y30 + IF(Parameters_Public!$C$20=1, Parameters_Public!$C$19, 0))*AC30) -> 3977802.8 | AA30: =IF($AC30>0, $Z30/$AC30, 0) -> 5866.9658 | AB30: =MAX(0, (MAX(0, $D30-BaselineCalc!$B$7) + MAX(0, $E30-BaselineCalc!$B$8))) -> 125 | AC30: =L30+M30-N30+O30 -> 678 | AD30: =( (Y30 + IF(Parameters_Public!$C20=1, INDEX(YearMap!$O$2:$O$6, MATCH(C30, YearMap!$A$2:$A$6, 0)), 0)) * AC30 ) + AC30*INDEX(YearMap!$P$2:$P$6, MATCH(C30, YearMap!$A$2:$A$6, 0)) + AB30*( INDEX(YearMap!$R$2:$R$6, MATCH(C30, YearMap!$A$2:$A$6, 0)) - INDEX(YearMap!$P$2:$P$6, MATCH(C30, YearMap!$A$2:$A$6, 0)) ) -> 7900862.3 | AE30: =(W30 - (1-Parameters_Public!$C$43)*$G30*$AB30*$J30*(1-$K30)) + AB30*INDEX(YearMap!$Q$2:$Q$6, MATCH(C30, YearMap!$A$2:$A$6, 0)) -> 7710968 | AF30: =AD30-AE30 -> 189894.31 | AG30: =B30&"|"&C30 -> D2_EchoGHubRamp_PimaTargets|FY2029
