Workbook

Sheet BaselineCalc
A1: Parameter | B1: Value | C1: Notes
A2: MO inflation | B2: 0.025 | C2: Annual inflation factor.
A3: Base MO per ADM (FY25) | B3: 9936 | C3: Working base for FY25.
A4: Fixed share of MO | B4: 0.3 | C4: Share treated as semi‑fixed (plant/insurance).
A5: Ops savings (keep‑open) | B5: 0.007 | C5: Light discipline if sites remain open (not used here).
A6: Extra savings (Co‑location) | B6: 0.015 | C6: Incremental savings for co‑location (not used here).
A7: Echo base ADM | B7: 257
A8: Pima base ADM | B8: 296
A9: Total base ADM | B9: =B7+B8 -> 553 | C9: Echo base ADM + Pima base ADM
A12: Helper / Derivation | B12: FY26 | C12: FY27 | D12: FY28 | E12: FY29 | F12: FY30 | G12: Notes
A13: Base total MO (FY25) | B13: =B9*B3 -> 5494608 | C13: =C14/$B$4 -> 5631973.2 | D13: =D14/$B$4 -> 5772772.5 | E13: =E14/$B$4 -> 5917091.8 | F13: =F14/$B$4 -> 6065019.1 | G13: Total ADM × Base MO/ADM | K13: B13 = B9*B3 (Base total MO, FY25)
A14: Fixed MO (FY25) | B14: =B13*B4 -> 1648382.4 | C14: =B17 -> 1689592 | D14: =C17 -> 1731831.8 | E14: =D17 -> 1775127.6 | F14: =E17 -> 1819505.7 | G14: Fixed = Base total × Fixed share | K14: B14 = B13*B4 (Fixed MO, FY25)
A15: Var per student (FY25) | B15: =(B13-B14)/B9 -> 6955.2 | C15: =B18 -> 7129.08 | D15: =C18 -> 7307.307 | E15: =D18 -> 7489.9897 | F15: =E18 -> 7677.2394 | G15: Variable = (Base total − Fixed)/Total ADM | K15: B15 = (B13–B14)/B9 (Variable $/student, FY25)
A17: Fixed total ($) | B17: =$B$14*(1+$B$2)^1 -> 1689592 | C17: =$B$14*(1+$B$2)^2 -> 1731831.8 | D17: =$B$14*(1+$B$2)^3 -> 1775127.6 | E17: =$B$14*(1+$B$2)^4 -> 1819505.7 | F17: =$B$14*(1+$B$2)^5 -> 1864993.4
A18: Var unit ($/student) | B18: =$B$15*(1+$B$2)^1 -> 7129.08 | C18: =$B$15*(1+$B$2)^2 -> 7307.307 | D18: =$B$15*(1+$B$2)^3 -> 7489.9897 | E18: =$B$15*(1+$B$2)^4 -> 7677.2394 | F18: =$B$15*(1+$B$2)^5 -> 7869.1704
A19: Echo fixed ($) | B19: =B17*($B$7/$B$9) -> 785217.24 | C19: =C17*($B$7/$B$9) -> 804847.67 | D19: =D17*($B$7/$B$9) -> 824968.86 | E19: =E17*($B$7/$B$9) -> 845593.08 | F19: =F17*($B$7/$B$9) -> 866732.91
A20: Pima fixed ($) | B20: =B17*($B$8/$B$9) -> 904374.72 | C20: =C17*($B$8/$B$9) -> 926984.09 | D20: =D17*($B$8/$B$9) -> 950158.69 | E20: =E17*($B$8/$B$9) -> 973912.66 | F20: =F17*($B$8/$B$9) -> 998260.47
A22: Notes
A23: All formulas are same‑sheet and reference the Parameter cells above.

Sheet YearMap
A1: Year | B1: VarUnit$ | C1: EchoFixed$ | D1: PimaFixed$ | E1: h | F1: f_lease | G1: f_ops | H1: YearIdx
A2: FY2026 | B2: =BaselineCalc!B18 -> 7129.08 | C2: =BaselineCalc!B19 -> 785217.24 | D2: =BaselineCalc!B20 -> 904374.72 | E2: 1000 | F2: 0.4 | G2: 0.4 | H2: 1
A3: FY2027 | B3: =BaselineCalc!C18 -> 7307.307 | C3: =BaselineCalc!C19 -> 804847.67 | D3: =BaselineCalc!C20 -> 926984.09 | E3: 800 | F3: 0.3 | G3: 0.35 | H3: 2
A4: FY2028 | B4: =BaselineCalc!D18 -> 7489.9897 | C4: =BaselineCalc!D19 -> 824968.86 | D4: =BaselineCalc!D20 -> 950158.69 | E4: 600 | F4: 0.2 | G4: 0.3 | H4: 3
A5: FY2029 | B5: =BaselineCalc!E18 -> 7677.2394 | C5: =BaselineCalc!E19 -> 845593.08 | D5: =BaselineCalc!E20 -> 973912.66 | E5: 400 | F5: 0.1 | G5: 0.25 | H5: 4
A6: FY2030 | B6: =BaselineCalc!F18 -> 7869.1704 | C6: =BaselineCalc!F19 -> 866732.91 | D6: =BaselineCalc!F20 -> 998260.47 | E6: 300 | F6: 0 | G6: 0.2 | H6: 5

Sheet Scenarios
A1: ScenarioKey | B1: Label | C1: Overlay | D1: CloseEcho | E1: ClosePima | F1: EchoShareDist | G1: ExtraSave | H1: Notes | I1: Overlay_FY26 | J1: Overlay_FY27 | K1: Overlay_FY28 | L1: Overlay_FY29 | M1: Overlay_FY30
A2: D_Grow_Both_0 | B2: D. Grow Both (Overlay 0) | C2: 0 | D2: 0 | E2: 0 | F2: 0.5 | G2: 0 | H2: Baseline + outreach; no closures | I2: 0 | J2: 0 | K2: 0 | L2: 0 | M2: 0
A3: E_StatusQuo_Targets_0 | B3: E. Status‑Quo + Targets (0) | C3: 0 | D3: 0 | E3: 0 | F3: 0.5 | G3: 0 | H3: Baseline + targets; no closures | I3: 0 | J3: 0 | K3: 0 | L3: 0 | M3: 0
A4: F_CoLocation_Echo_0 | B4: F. Co‑Location @ Echo (0) | C4: 0 | D4: 0 | E4: 0 | F4: 0.7 | G4: 0.015 | H4: Shared‑use efficiencies later (no closure) | I4: 0 | J4: 0 | K4: 0 | L4: 0 | M4: 0
A5: D_Grow_Both_100 | B5: D. Grow Both (Overlay 100) | C5: 100 | D5: 0 | E5: 0 | F5: 0.5 | G5: 0 | H5: Baseline +100 overlay | I5: =$C5 -> 100 | J5: =$C5 -> 100 | K5: =$C5 -> 100 | L5: =$C5 -> 100 | M5: =$C5 -> 100
A6: D_Grow_Both_150 | B6: D. Grow Both (Overlay 150) | C6: 150 | D6: 0 | E6: 0 | F6: 0.5 | G6: 0 | H6: Baseline +150 overlay | I6: =$C6 -> 150 | J6: =$C6 -> 150 | K6: =$C6 -> 150 | L6: =$C6 -> 150 | M6: =$C6 -> 150
A7: G_DHub_EchoRamp | B7: G. D‑Hub @ Echo (Ramp 50→100→150) | C7: 150 | D7: 0 | E7: 0 | F7: 0.7 | G7: 0 | H7: Time‑phased ramp (+50,+100,+150 years 1–3) | I7: =C7/3 -> 50 | J7: =I7+C7/3 -> 100 | K7: =J7+C7/3 -> 150 | L7: =C7 -> 150 | M7: =C7 -> 150
A9: ScenarioKey | B9: Year | C9: Echo_ADM | D9: Pima_ADM | E9: Total_ADM | F9: VarUnit$ | G9: EchoFixed$ | H9: PimaFixed$ | I9: Key
A10: =A2 -> D_Grow_Both_0 | B10: FY2026 | C10: =IF(D2=1,0, BaselineCalc!$B$7 + ROUND(I2*F2,0)) -> 257 | D10: =IF(E2=1,0, BaselineCalc!$B$8 + I2 - ROUND(I2*F2,0)) -> 296 | E10: =C10+D10 -> 553 | F10: =YearMap!B2 -> 7129.08 | G10: =YearMap!C2 -> 785217.24 | H10: =YearMap!D2 -> 904374.72 | I10: =A10&"|"&B10 -> D_Grow_Both_0|FY2026
A11: =A2 -> D_Grow_Both_0 | B11: FY2027 | C11: =IF(D2=1,0, BaselineCalc!$B$7 + ROUND(J2*F2,0)) -> 257 | D11: =IF(E2=1,0, BaselineCalc!$B$8 + J2 - ROUND(J2*F2,0)) -> 296 | E11: =C11+D11 -> 553 | F11: =YearMap!B3 -> 7307.307 | G11: =YearMap!C3 -> 804847.67 | H11: =YearMap!D3 -> 926984.09 | I11: =A11&"|"&B11 -> D_Grow_Both_0|FY2027
A12: =A2 -> D_Grow_Both_0 | B12: FY2028 | C12: =IF(D2=1,0, BaselineCalc!$B$7 + ROUND(K2*F2,0)) -> 257 | D12: =IF(E2=1,0, BaselineCalc!$B$8 + K2 - ROUND(K2*F2,0)) -> 296 | E12: =C12+D12 -> 553 | F12: =YearMap!B4 -> 7489.9897 | G12: =YearMap!C4 -> 824968.86 | H12: =YearMap!D4 -> 950158.69 | I12: =A12&"|"&B12 -> D_Grow_Both_0|FY2028
A13: =A2 -> D_Grow_Both_0 | B13: FY2029 | C13: =IF(D2=1,0, BaselineCalc!$B$7 + ROUND(L2*F2,0)) -> 257 | D13: =IF(E2=1,0, BaselineCalc!$B$8 + L2 - ROUND(L2*F2,0)) -> 296 | E13: =C13+D13 -> 553 | F13: =YearMap!B5 -> 7677.2394 | G13: =YearMap!C5 -> 845593.08 | H13: =YearMap!D5 -> 973912.66 | I13: =A13&"|"&B13 -> D_Grow_Both_0|FY2029
A14: =A2 -> D_Grow_Both_0 | B14: FY2030 | C14: =IF(D2=1,0, BaselineCalc!$B$7 + ROUND(M2*F2,0)) -> 257 | D14: =IF(E2=1,0, BaselineCalc!$B$8 + M2 - ROUND(M2*F2,0)) -> 296 | E14: =C14+D14 -> 553 | F14: =YearMap!B6 -> 7869.1704 | G14: =YearMap!C6 -> 866732.91 | H14: =YearMap!D6 -> 998260.47 | I14: =A14&"|"&B14 -> D_Grow_Both_0|FY2030
A15: =A3 -> E_StatusQuo_Targets_0 | B15: FY2026 | C15: =IF(D3=1,0, BaselineCalc!$B$7 + ROUND(I3*F3,0)) -> 257 | D15: =IF(E3=1,0, BaselineCalc!$B$8 + I3 - ROUND(I3*F3,0)) -> 296 | E15: =C15+D15 -> 553 | F15: =YearMap!B2 -> 7129.08 | G15: =YearMap!C2 -> 785217.24 | H15: =YearMap!D2 -> 904374.72 | I15: =A15&"|"&B15 -> E_StatusQuo_Targets_0|FY2026
A16: =A3 -> E_StatusQuo_Targets_0 | B16: FY2027 | C16: =IF(D3=1,0, BaselineCalc!$B$7 + ROUND(J3*F3,0)) -> 257 | D16: =IF(E3=1,0, BaselineCalc!$B$8 + J3 - ROUND(J3*F3,0)) -> 296 | E16: =C16+D16 -> 553 | F16: =YearMap!B3 -> 7307.307 | G16: =YearMap!C3 -> 804847.67 | H16: =YearMap!D3 -> 926984.09 | I16: =A16&"|"&B16 -> E_StatusQuo_Targets_0|FY2027
A17: =A3 -> E_StatusQuo_Targets_0 | B17: FY2028 | C17: =IF(D3=1,0, BaselineCalc!$B$7 + ROUND(K3*F3,0)) -> 257 | D17: =IF(E3=1,0, BaselineCalc!$B$8 + K3 - ROUND(K3*F3,0)) -> 296 | E17: =C17+D17 -> 553 | F17: =YearMap!B4 -> 7489.9897 | G17: =YearMap!C4 -> 824968.86 | H17: =YearMap!D4 -> 950158.69 | I17: =A17&"|"&B17 -> E_StatusQuo_Targets_0|FY2028
A18: =A3 -> E_StatusQuo_Targets_0 | B18: FY2029 | C18: =IF(D3=1,0, BaselineCalc!$B$7 + ROUND(L3*F3,0)) -> 257 | D18: =IF(E3=1,0, BaselineCalc!$B$8 + L3 - ROUND(L3*F3,0)) -> 296 | E18: =C18+D18 -> 553 | F18: =YearMap!B5 -> 7677.2394 | G18: =YearMap!C5 -> 845593.08 | H18: =YearMap!D5 -> 973912.66 | I18: =A18&"|"&B18 -> E_StatusQuo_Targets_0|FY2029
A19: =A3 -> E_StatusQuo_Targets_0 | B19: FY2030 | C19: =IF(D3=1,0, BaselineCalc!$B$7 + ROUND(M3*F3,0)) -> 257 | D19: =IF(E3=1,0, BaselineCalc!$B$8 + M3 - ROUND(M3*F3,0)) -> 296 | E19: =C19+D19 -> 553 | F19: =YearMap!B6 -> 7869.1704 | G19: =YearMap!C6 -> 866732.91 | H19: =YearMap!D6 -> 998260.47 | I19: =A19&"|"&B19 -> E_StatusQuo_Targets_0|FY2030
A20: =A4 -> F_CoLocation_Echo_0 | B20: FY2026 | C20: =IF(D4=1,0, BaselineCalc!$B$7 + ROUND(I4*F4,0)) -> 257 | D20: =IF(E4=1,0, BaselineCalc!$B$8 + I4 - ROUND(I4*F4,0)) -> 296 | E20: =C20+D20 -> 553 | F20: =YearMap!B2 -> 7129.08 | G20: =YearMap!C2 -> 785217.24 | H20: =YearMap!D2 -> 904374.72 | I20: =A20&"|"&B20 -> F_CoLocation_Echo_0|FY2026
A21: =A4 -> F_CoLocation_Echo_0 | B21: FY2027 | C21: =IF(D4=1,0, BaselineCalc!$B$7 + ROUND(J4*F4,0)) -> 257 | D21: =IF(E4=1,0, BaselineCalc!$B$8 + J4 - ROUND(J4*F4,0)) -> 296 | E21: =C21+D21 -> 553 | F21: =YearMap!B3 -> 7307.307 | G21: =YearMap!C3 -> 804847.67 | H21: =YearMap!D3 -> 926984.09 | I21: =A21&"|"&B21 -> F_CoLocation_Echo_0|FY2027
A22: =A4 -> F_CoLocation_Echo_0 | B22: FY2028 | C22: =IF(D4=1,0, BaselineCalc!$B$7 + ROUND(K4*F4,0)) -> 257 | D22: =IF(E4=1,0, BaselineCalc!$B$8 + K4 - ROUND(K4*F4,0)) -> 296 | E22: =C22+D22 -> 553 | F22: =YearMap!B4 -> 7489.9897 | G22: =YearMap!C4 -> 824968.86 | H22: =YearMap!D4 -> 950158.69 | I22: =A22&"|"&B22 -> F_CoLocation_Echo_0|FY2028
A23: =A4 -> F_CoLocation_Echo_0 | B23: FY2029 | C23: =IF(D4=1,0, BaselineCalc!$B$7 + ROUND(L4*F4,0)) -> 257 | D23: =IF(E4=1,0, BaselineCalc!$B$8 + L4 - ROUND(L4*F4,0)) -> 296 | E23: =C23+D23 -> 553 | F23: =YearMap!B5 -> 7677.2394 | G23: =YearMap!C5 -> 845593.08 | H23: =YearMap!D5 -> 973912.66 | I23: =A23&"|"&B23 -> F_CoLocation_Echo_0|FY2029
A24: =A4 -> F_CoLocation_Echo_0 | B24: FY2030 | C24: =IF(D4=1,0, BaselineCalc!$B$7 + ROUND(M4*F4,0)) -> 257 | D24: =IF(E4=1,0, BaselineCalc!$B$8 + M4 - ROUND(M4*F4,0)) -> 296 | E24: =C24+D24 -> 553 | F24: =YearMap!B6 -> 7869.1704 | G24: =YearMap!C6 -> 866732.91 | H24: =YearMap!D6 -> 998260.47 | I24: =A24&"|"&B24 -> F_CoLocation_Echo_0|FY2030
A25: =A5 -> D_Grow_Both_100 | B25: FY2026 | C25: =IF(D5=1,0, BaselineCalc!$B$7 + ROUND(I5*F5,0)) -> 307 | D25: =IF(E5=1,0, BaselineCalc!$B$8 + I5 - ROUND(I5*F5,0)) -> 346 | E25: =C25+D25 -> 653 | F25: =YearMap!B2 -> 7129.08 | G25: =YearMap!C2 -> 785217.24 | H25: =YearMap!D2 -> 904374.72 | I25: =A25&"|"&B25 -> D_Grow_Both_100|FY2026
A26: =A5 -> D_Grow_Both_100 | B26: FY2027 | C26: =IF(D5=1,0, BaselineCalc!$B$7 + ROUND(J5*F5,0)) -> 307 | D26: =IF(E5=1,0, BaselineCalc!$B$8 + J5 - ROUND(J5*F5,0)) -> 346 | E26: =C26+D26 -> 653 | F26: =YearMap!B3 -> 7307.307 | G26: =YearMap!C3 -> 804847.67 | H26: =YearMap!D3 -> 926984.09 | I26: =A26&"|"&B26 -> D_Grow_Both_100|FY2027
A27: =A5 -> D_Grow_Both_100 | B27: FY2028 | C27: =IF(D5=1,0, BaselineCalc!$B$7 + ROUND(K5*F5,0)) -> 307 | D27: =IF(E5=1,0, BaselineCalc!$B$8 + K5 - ROUND(K5*F5,0)) -> 346 | E27: =C27+D27 -> 653 | F27: =YearMap!B4 -> 7489.9897 | G27: =YearMap!C4 -> 824968.86 | H27: =YearMap!D4 -> 950158.69 | I27: =A27&"|"&B27 -> D_Grow_Both_100|FY2028
A28: =A5 -> D_Grow_Both_100 | B28: FY2029 | C28: =IF(D5=1,0, BaselineCalc!$B$7 + ROUND(L5*F5,0)) -> 307 | D28: =IF(E5=1,0, BaselineCalc!$B$8 + L5 - ROUND(L5*F5,0)) -> 346 | E28: =C28+D28 -> 653 | F28: =YearMap!B5 -> 7677.2394 | G28: =YearMap!C5 -> 845593.08 | H28: =YearMap!D5 -> 973912.66 | I28: =A28&"|"&B28 -> D_Grow_Both_100|FY2029
A29: =A5 -> D_Grow_Both_100 | B29: FY2030 | C29: =IF(D5=1,0, BaselineCalc!$B$7 + ROUND(M5*F5,0)) -> 307 | D29: =IF(E5=1,0, BaselineCalc!$B$8 + M5 - ROUND(M5*F5,0)) -> 346 | E29: =C29+D29 -> 653 | F29: =YearMap!B6 -> 7869.1704 | G29: =YearMap!C6 -> 866732.91 | H29: =YearMap!D6 -> 998260.47 | I29: =A29&"|"&B29 -> D_Grow_Both_100|FY2030
A30: =A6 -> D_Grow_Both_150 | B30: FY2026 | C30: =IF(D6=1,0, BaselineCalc!$B$7 + ROUND(I6*F6,0)) -> 332 | D30: =IF(E6=1,0, BaselineCalc!$B$8 + I6 - ROUND(I6*F6,0)) -> 371 | E30: =C30+D30 -> 703 | F30: =YearMap!B2 -> 7129.08 | G30: =YearMap!C2 -> 785217.24 | H30: =YearMap!D2 -> 904374.72 | I30: =A30&"|"&B30 -> D_Grow_Both_150|FY2026
A31: =A6 -> D_Grow_Both_150 | B31: FY2027 | C31: =IF(D6=1,0, BaselineCalc!$B$7 + ROUND(J6*F6,0)) -> 332 | D31: =IF(E6=1,0, BaselineCalc!$B$8 + J6 - ROUND(J6*F6,0)) -> 371 | E31: =C31+D31 -> 703 | F31: =YearMap!B3 -> 7307.307 | G31: =YearMap!C3 -> 804847.67 | H31: =YearMap!D3 -> 926984.09 | I31: =A31&"|"&B31 -> D_Grow_Both_150|FY2027
A32: =A6 -> D_Grow_Both_150 | B32: FY2028 | C32: =IF(D6=1,0, BaselineCalc!$B$7 + ROUND(K6*F6,0)) -> 332 | D32: =IF(E6=1,0, BaselineCalc!$B$8 + K6 - ROUND(K6*F6,0)) -> 371 | E32: =C32+D32 -> 703 | F32: =YearMap!B4 -> 7489.9897 | G32: =YearMap!C4 -> 824968.86 | H32: =YearMap!D4 -> 950158.69 | I32: =A32&"|"&B32 -> D_Grow_Both_150|FY2028
A33: =A6 -> D_Grow_Both_150 | B33: FY2029 | C33: =IF(D6=1,0, BaselineCalc!$B$7 + ROUND(L6*F6,0)) -> 332 | D33: =IF(E6=1,0, BaselineCalc!$B$8 + L6 - ROUND(L6*F6,0)) -> 371 | E33: =C33+D33 -> 703 | F33: =YearMap!B5 -> 7677.2394 | G33: =YearMap!C5 -> 845593.08 | H33: =YearMap!D5 -> 973912.66 | I33: =A33&"|"&B33 -> D_Grow_Both_150|FY2029
A34: =A6 -> D_Grow_Both_150 | B34: FY2030 | C34: =IF(D6=1,0, BaselineCalc!$B$7 + ROUND(M6*F6,0)) -> 332 | D34: =IF(E6=1,0, BaselineCalc!$B$8 + M6 - ROUND(M6*F6,0)) -> 371 | E34: =C34+D34 -> 703 | F34: =YearMap!B6 -> 7869.1704 | G34: =YearMap!C6 -> 866732.91 | H34: =YearMap!D6 -> 998260.47 | I34: =A34&"|"&B34 -> D_Grow_Both_150|FY2030
A35: =A7 -> G_DHub_EchoRamp | B35: FY2026 | C35: =IF(D7=1,0, BaselineCalc!$B$7 + ROUND(I7*F7,0)) -> 292 | D35: =IF(E7=1,0, BaselineCalc!$B$8 + I7 - ROUND(I7*F7,0)) -> 311 | E35: =C35+D35 -> 603 | F35: =YearMap!B2 -> 7129.08 | G35: =YearMap!C2 -> 785217.24 | H35: =YearMap!D2 -> 904374.72 | I35: =A35&"|"&B35 -> G_DHub_EchoRamp|FY2026
A36: =A7 -> G_DHub_EchoRamp | B36: FY2027 | C36: =IF(D7=1,0, BaselineCalc!$B$7 + ROUND(J7*F7,0)) -> 327 | D36: =IF(E7=1,0, BaselineCalc!$B$8 + J7 - ROUND(J7*F7,0)) -> 326 | E36: =C36+D36 -> 653 | F36: =YearMap!B3 -> 7307.307 | G36: =YearMap!C3 -> 804847.67 | H36: =YearMap!D3 -> 926984.09 | I36: =A36&"|"&B36 -> G_DHub_EchoRamp|FY2027
A37: =A7 -> G_DHub_EchoRamp | B37: FY2028 | C37: =IF(D7=1,0, BaselineCalc!$B$7 + ROUND(K7*F7,0)) -> 362 | D37: =IF(E7=1,0, BaselineCalc!$B$8 + K7 - ROUND(K7*F7,0)) -> 341 | E37: =C37+D37 -> 703 | F37: =YearMap!B4 -> 7489.9897 | G37: =YearMap!C4 -> 824968.86 | H37: =YearMap!D4 -> 950158.69 | I37: =A37&"|"&B37 -> G_DHub_EchoRamp|FY2028
A38: =A7 -> G_DHub_EchoRamp | B38: FY2029 | C38: =IF(D7=1,0, BaselineCalc!$B$7 + ROUND(L7*F7,0)) -> 362 | D38: =IF(E7=1,0, BaselineCalc!$B$8 + L7 - ROUND(L7*F7,0)) -> 341 | E38: =C38+D38 -> 703 | F38: =YearMap!B5 -> 7677.2394 | G38: =YearMap!C5 -> 845593.08 | H38: =YearMap!D5 -> 973912.66 | I38: =A38&"|"&B38 -> G_DHub_EchoRamp|FY2029
A39: =A7 -> G_DHub_EchoRamp | B39: FY2030 | C39: =IF(D7=1,0, BaselineCalc!$B$7 + ROUND(M7*F7,0)) -> 362 | D39: =IF(E7=1,0, BaselineCalc!$B$8 + M7 - ROUND(M7*F7,0)) -> 341 | E39: =C39+D39 -> 703 | F39: =YearMap!B6 -> 7869.1704 | G39: =YearMap!C6 -> 866732.91 | H39: =YearMap!D6 -> 998260.47 | I39: =A39&"|"&B39 -> G_DHub_EchoRamp|FY2030

Sheet MultiYear_ProForma
A1: ScenarioKey | B1: Year | C1: Echo_ADM | D1: Pima_ADM | E1: Total_ADM | F1: VarUnit$ | G1: EchoFixed$ | H1: PimaFixed$ | I1: OpsFactor | J1: ExtraSave | K1: Total_MO$ | L1: MO_per_ADM$ | M1: Key
A2: =Scenarios!A2 -> D_Grow_Both_0 | B2: FY2026 | C2: =IF(Scenarios!D2=1,0, BaselineCalc!$B$7 + ROUND(Scenarios!I2*Scenarios!F2,0)) -> 257 | D2: =IF(Scenarios!E2=1,0, BaselineCalc!$B$8 + Scenarios!I2 - ROUND(Scenarios!I2*Scenarios!F2,0)) -> 296 | E2: =C2+D2 -> 553 | F2: =YearMap!B2 -> 7129.08 | G2: =YearMap!C2 -> 785217.24 | H2: =YearMap!D2 -> 904374.72 | I2: =1-BaselineCalc!$B$5 -> 0.993 | J2: =Scenarios!G2 -> 0 | K2: =(G2+H2+F2*E2)*I2*(1-J2) -> 5592549.4 | L2: =IF(E2>0, K2/E2, "") -> 10113.109 | M2: =A2&"|"&B2 -> D_Grow_Both_0|FY2026
A3: =Scenarios!A2 -> D_Grow_Both_0 | B3: FY2027 | C3: =IF(Scenarios!D2=1,0, BaselineCalc!$B$7 + ROUND(Scenarios!J2*Scenarios!F2,0)) -> 257 | D3: =IF(Scenarios!E2=1,0, BaselineCalc!$B$8 + Scenarios!J2 - ROUND(Scenarios!J2*Scenarios!F2,0)) -> 296 | E3: =C3+D3 -> 553 | F3: =YearMap!B3 -> 7307.307 | G3: =YearMap!C3 -> 804847.67 | H3: =YearMap!D3 -> 926984.09 | I3: =1-BaselineCalc!$B$5 -> 0.993 | J3: =Scenarios!G2 -> 0 | K3: =(G3+H3+F3*E3)*I3*(1-J3) -> 5732363.1 | L3: =IF(E3>0, K3/E3, "") -> 10365.937 | M3: =A3&"|"&B3 -> D_Grow_Both_0|FY2027
A4: =Scenarios!A2 -> D_Grow_Both_0 | B4: FY2028 | C4: =IF(Scenarios!D2=1,0, BaselineCalc!$B$7 + ROUND(Scenarios!K2*Scenarios!F2,0)) -> 257 | D4: =IF(Scenarios!E2=1,0, BaselineCalc!$B$8 + Scenarios!K2 - ROUND(Scenarios!K2*Scenarios!F2,0)) -> 296 | E4: =C4+D4 -> 553 | F4: =YearMap!B4 -> 7489.9897 | G4: =YearMap!C4 -> 824968.86 | H4: =YearMap!D4 -> 950158.69 | I4: =1-BaselineCalc!$B$5 -> 0.993 | J4: =Scenarios!G2 -> 0 | K4: =(G4+H4+F4*E4)*I4*(1-J4) -> 5875672.2 | L4: =IF(E4>0, K4/E4, "") -> 10625.085 | M4: =A4&"|"&B4 -> D_Grow_Both_0|FY2028
A5: =Scenarios!A2 -> D_Grow_Both_0 | B5: FY2029 | C5: =IF(Scenarios!D2=1,0, BaselineCalc!$B$7 + ROUND(Scenarios!L2*Scenarios!F2,0)) -> 257 | D5: =IF(Scenarios!E2=1,0, BaselineCalc!$B$8 + Scenarios!L2 - ROUND(Scenarios!L2*Scenarios!F2,0)) -> 296 | E5: =C5+D5 -> 553 | F5: =YearMap!B5 -> 7677.2394 | G5: =YearMap!C5 -> 845593.08 | H5: =YearMap!D5 -> 973912.66 | I5: =1-BaselineCalc!$B$5 -> 0.993 | J5: =Scenarios!G2 -> 0 | K5: =(G5+H5+F5*E5)*I5*(1-J5) -> 6022564 | L5: =IF(E5>0, K5/E5, "") -> 10890.712 | M5: =A5&"|"&B5 -> D_Grow_Both_0|FY2029
A6: =Scenarios!A2 -> D_Grow_Both_0 | B6: FY2030 | C6: =IF(Scenarios!D2=1,0, BaselineCalc!$B$7 + ROUND(Scenarios!M2*Scenarios!F2,0)) -> 257 | D6: =IF(Scenarios!E2=1,0, BaselineCalc!$B$8 + Scenarios!M2 - ROUND(Scenarios!M2*Scenarios!F2,0)) -> 296 | E6: =C6+D6 -> 553 | F6: =YearMap!B6 -> 7869.1704 | G6: =YearMap!C6 -> 866732.91 | H6: =YearMap!D6 -> 998260.47 | I6: =1-BaselineCalc!$B$5 -> 0.993 | J6: =Scenarios!G2 -> 0 | K6: =(G6+H6+F6*E6)*I6*(1-J6) -> 6173128.1 | L6: =IF(E6>0, K6/E6, "") -> 11162.98 | M6: =A6&"|"&B6 -> D_Grow_Both_0|FY2030
A7: =Scenarios!A3 -> E_StatusQuo_Targets_0 | B7: FY2026 | C7: =IF(Scenarios!D3=1,0, BaselineCalc!$B$7 + ROUND(Scenarios!I3*Scenarios!F3,0)) -> 257 | D7: =IF(Scenarios!E3=1,0, BaselineCalc!$B$8 + Scenarios!I3 - ROUND(Scenarios!I3*Scenarios!F3,0)) -> 296 | E7: =C7+D7 -> 553 | F7: =YearMap!B2 -> 7129.08 | G7: =YearMap!C2 -> 785217.24 | H7: =YearMap!D2 -> 904374.72 | I7: =1-BaselineCalc!$B$5 -> 0.993 | J7: =Scenarios!G3 -> 0 | K7: =(G7+H7+F7*E7)*I7*(1-J7) -> 5592549.4 | L7: =IF(E7>0, K7/E7, "") -> 10113.109 | M7: =A7&"|"&B7 -> E_StatusQuo_Targets_0|FY2026
A8: =Scenarios!A3 -> E_StatusQuo_Targets_0 | B8: FY2027 | C8: =IF(Scenarios!D3=1,0, BaselineCalc!$B$7 + ROUND(Scenarios!J3*Scenarios!F3,0)) -> 257 | D8: =IF(Scenarios!E3=1,0, BaselineCalc!$B$8 + Scenarios!J3 - ROUND(Scenarios!J3*Scenarios!F3,0)) -> 296 | E8: =C8+D8 -> 553 | F8: =YearMap!B3 -> 7307.307 | G8: =YearMap!C3 -> 804847.67 | H8: =YearMap!D3 -> 926984.09 | I8: =1-BaselineCalc!$B$5 -> 0.993 | J8: =Scenarios!G3 -> 0 | K8: =(G8+H8+F8*E8)*I8*(1-J8) -> 5732363.1 | L8: =IF(E8>0, K8/E8, "") -> 10365.937 | M8: =A8&"|"&B8 -> E_StatusQuo_Targets_0|FY2027
A9: =Scenarios!A3 -> E_StatusQuo_Targets_0 | B9: FY2028 | C9: =IF(Scenarios!D3=1,0, BaselineCalc!$B$7 + ROUND(Scenarios!K3*Scenarios!F3,0)) -> 257 | D9: =IF(Scenarios!E3=1,0, BaselineCalc!$B$8 + Scenarios!K3 - ROUND(Scenarios!K3*Scenarios!F3,0)) -> 296 | E9: =C9+D9 -> 553 | F9: =YearMap!B4 -> 7489.9897 | G9: =YearMap!C4 -> 824968.86 | H9: =YearMap!D4 -> 950158.69 | I9: =1-BaselineCalc!$B$5 -> 0.993 | J9: =Scenarios!G3 -> 0 | K9: =(G9+H9+F9*E9)*I9*(1-J9) -> 5875672.2 | L9: =IF(E9>0, K9/E9, "") -> 10625.085 | M9: =A9&"|"&B9 -> E_StatusQuo_Targets_0|FY2028
A10: =Scenarios!A3 -> E_StatusQuo_Targets_0 | B10: FY2029 | C10: =IF(Scenarios!D3=1,0, BaselineCalc!$B$7 + ROUND(Scenarios!L3*Scenarios!F3,0)) -> 257 | D10: =IF(Scenarios!E3=1,0, BaselineCalc!$B$8 + Scenarios!L3 - ROUND(Scenarios!L3*Scenarios!F3,0)) -> 296 | E10: =C10+D10 -> 553 | F10: =YearMap!B5 -> 7677.2394 | G10: =YearMap!C5 -> 845593.08 | H10: =YearMap!D5 -> 973912.66 | I10: =1-BaselineCalc!$B$5 -> 0.993 | J10: =Scenarios!G3 -> 0 | K10: =(G10+H10+F10*E10)*I10*(1-J10) -> 6022564 | L10: =IF(E10>0, K10/E10, "") -> 10890.712 | M10: =A10&"|"&B10 -> E_StatusQuo_Targets_0|FY2029
A11: =Scenarios!A3 -> E_StatusQuo_Targets_0 | B11: FY2030 | C11: =IF(Scenarios!D3=1,0, BaselineCalc!$B$7 + ROUND(Scenarios!M3*Scenarios!F3,0)) -> 257 | D11: =IF(Scenarios!E3=1,0, BaselineCalc!$B$8 + Scenarios!M3 - ROUND(Scenarios!M3*Scenarios!F3,0)) -> 296 | E11: =C11+D11 -> 553 | F11: =YearMap!B6 -> 7869.1704 | G11: =YearMap!C6 -> 866732.91 | H11: =YearMap!D6 -> 998260.47 | I11: =1-BaselineCalc!$B$5 -> 0.993 | J11: =Scenarios!G3 -> 0 | K11: =(G11+H11+F11*E11)*I11*(1-J11) -> 6173128.1 | L11: =IF(E11>0, K11/E11, "") -> 11162.98 | M11: =A11&"|"&B11 -> E_StatusQuo_Targets_0|FY2030
A12: =Scenarios!A4 -> F_CoLocation_Echo_0 | B12: FY2026 | C12: =IF(Scenarios!D4=1,0, BaselineCalc!$B$7 + ROUND(Scenarios!I4*Scenarios!F4,0)) -> 257 | D12: =IF(Scenarios!E4=1,0, BaselineCalc!$B$8 + Scenarios!I4 - ROUND(Scenarios!I4*Scenarios!F4,0)) -> 296 | E12: =C12+D12 -> 553 | F12: =YearMap!B2 -> 7129.08 | G12: =YearMap!C2 -> 785217.24 | H12: =YearMap!D2 -> 904374.72 | I12: =1-BaselineCalc!$B$5 -> 0.993 | J12: =Scenarios!G4 -> 0.015 | K12: =(G12+H12+F12*E12)*I12*(1-J12) -> 5508661.1 | L12: =IF(E12>0, K12/E12, "") -> 9961.4126 | M12: =A12&"|"&B12 -> F_CoLocation_Echo_0|FY2026
A13: =Scenarios!A4 -> F_CoLocation_Echo_0 | B13: FY2027 | C13: =IF(Scenarios!D4=1,0, BaselineCalc!$B$7 + ROUND(Scenarios!J4*Scenarios!F4,0)) -> 257 | D13: =IF(Scenarios!E4=1,0, BaselineCalc!$B$8 + Scenarios!J4 - ROUND(Scenarios!J4*Scenarios!F4,0)) -> 296 | E13: =C13+D13 -> 553 | F13: =YearMap!B3 -> 7307.307 | G13: =YearMap!C3 -> 804847.67 | H13: =YearMap!D3 -> 926984.09 | I13: =1-BaselineCalc!$B$5 -> 0.993 | J13: =Scenarios!G4 -> 0.015 | K13: =(G13+H13+F13*E13)*I13*(1-J13) -> 5646377.7 | L13: =IF(E13>0, K13/E13, "") -> 10210.448 | M13: =A13&"|"&B13 -> F_CoLocation_Echo_0|FY2027
A14: =Scenarios!A4 -> F_CoLocation_Echo_0 | B14: FY2028 | C14: =IF(Scenarios!D4=1,0, BaselineCalc!$B$7 + ROUND(Scenarios!K4*Scenarios!F4,0)) -> 257 | D14: =IF(Scenarios!E4=1,0, BaselineCalc!$B$8 + Scenarios!K4 - ROUND(Scenarios!K4*Scenarios!F4,0)) -> 296 | E14: =C14+D14 -> 553 | F14: =YearMap!B4 -> 7489.9897 | G14: =YearMap!C4 -> 824968.86 | H14: =YearMap!D4 -> 950158.69 | I14: =1-BaselineCalc!$B$5 -> 0.993 | J14: =Scenarios!G4 -> 0.015 | K14: =(G14+H14+F14*E14)*I14*(1-J14) -> 5787537.1 | L14: =IF(E14>0, K14/E14, "") -> 10465.709 | M14: =A14&"|"&B14 -> F_CoLocation_Echo_0|FY2028
A15: =Scenarios!A4 -> F_CoLocation_Echo_0 | B15: FY2029 | C15: =IF(Scenarios!D4=1,0, BaselineCalc!$B$7 + ROUND(Scenarios!L4*Scenarios!F4,0)) -> 257 | D15: =IF(Scenarios!E4=1,0, BaselineCalc!$B$8 + Scenarios!L4 - ROUND(Scenarios!L4*Scenarios!F4,0)) -> 296 | E15: =C15+D15 -> 553 | F15: =YearMap!B5 -> 7677.2394 | G15: =YearMap!C5 -> 845593.08 | H15: =YearMap!D5 -> 973912.66 | I15: =1-BaselineCalc!$B$5 -> 0.993 | J15: =Scenarios!G4 -> 0.015 | K15: =(G15+H15+F15*E15)*I15*(1-J15) -> 5932225.5 | L15: =IF(E15>0, K15/E15, "") -> 10727.352 | M15: =A15&"|"&B15 -> F_CoLocation_Echo_0|FY2029
A16: =Scenarios!A4 -> F_CoLocation_Echo_0 | B16: FY2030 | C16: =IF(Scenarios!D4=1,0, BaselineCalc!$B$7 + ROUND(Scenarios!M4*Scenarios!F4,0)) -> 257 | D16: =IF(Scenarios!E4=1,0, BaselineCalc!$B$8 + Scenarios!M4 - ROUND(Scenarios!M4*Scenarios!F4,0)) -> 296 | E16: =C16+D16 -> 553 | F16: =YearMap!B6 -> 7869.1704 | G16: =YearMap!C6 -> 866732.91 | H16: =YearMap!D6 -> 998260.47 | I16: =1-BaselineCalc!$B$5 -> 0.993 | J16: =Scenarios!G4 -> 0.015 | K16: =(G16+H16+F16*E16)*I16*(1-J16) -> 6080531.2 | L16: =IF(E16>0, K16/E16, "") -> 10995.536 | M16: =A16&"|"&B16 -> F_CoLocation_Echo_0|FY2030
A17: =Scenarios!A5 -> D_Grow_Both_100 | B17: FY2026 | C17: =IF(Scenarios!D5=1,0, BaselineCalc!$B$7 + ROUND(Scenarios!I5*Scenarios!F5,0)) -> 307 | D17: =IF(Scenarios!E5=1,0, BaselineCalc!$B$8 + Scenarios!I5 - ROUND(Scenarios!I5*Scenarios!F5,0)) -> 346 | E17: =C17+D17 -> 653 | F17: =YearMap!B2 -> 7129.08 | G17: =YearMap!C2 -> 785217.24 | H17: =YearMap!D2 -> 904374.72 | I17: =1-BaselineCalc!$B$5 -> 0.993 | J17: =Scenarios!G5 -> 0 | K17: =(G17+H17+F17*E17)*I17*(1-J17) -> 6300467 | L17: =IF(E17>0, K17/E17, "") -> 9648.4947 | M17: =A17&"|"&B17 -> D_Grow_Both_100|FY2026
A18: =Scenarios!A5 -> D_Grow_Both_100 | B18: FY2027 | C18: =IF(Scenarios!D5=1,0, BaselineCalc!$B$7 + ROUND(Scenarios!J5*Scenarios!F5,0)) -> 307 | D18: =IF(Scenarios!E5=1,0, BaselineCalc!$B$8 + Scenarios!J5 - ROUND(Scenarios!J5*Scenarios!F5,0)) -> 346 | E18: =C18+D18 -> 653 | F18: =YearMap!B3 -> 7307.307 | G18: =YearMap!C3 -> 804847.67 | H18: =YearMap!D3 -> 926984.09 | I18: =1-BaselineCalc!$B$5 -> 0.993 | J18: =Scenarios!G5 -> 0 | K18: =(G18+H18+F18*E18)*I18*(1-J18) -> 6457978.7 | L18: =IF(E18>0, K18/E18, "") -> 9889.7071 | M18: =A18&"|"&B18 -> D_Grow_Both_100|FY2027
A19: =Scenarios!A5 -> D_Grow_Both_100 | B19: FY2028 | C19: =IF(Scenarios!D5=1,0, BaselineCalc!$B$7 + ROUND(Scenarios!K5*Scenarios!F5,0)) -> 307 | D19: =IF(Scenarios!E5=1,0, BaselineCalc!$B$8 + Scenarios!K5 - ROUND(Scenarios!K5*Scenarios!F5,0)) -> 346 | E19: =C19+D19 -> 653 | F19: =YearMap!B4 -> 7489.9897 | G19: =YearMap!C4 -> 824968.86 | H19: =YearMap!D4 -> 950158.69 | I19: =1-BaselineCalc!$B$5 -> 0.993 | J19: =Scenarios!G5 -> 0 | K19: =(G19+H19+F19*E19)*I19*(1-J19) -> 6619428.2 | L19: =IF(E19>0, K19/E19, "") -> 10136.95 | M19: =A19&"|"&B19 -> D_Grow_Both_100|FY2028
A20: =Scenarios!A5 -> D_Grow_Both_100 | B20: FY2029 | C20: =IF(Scenarios!D5=1,0, BaselineCalc!$B$7 + ROUND(Scenarios!L5*Scenarios!F5,0)) -> 307 | D20: =IF(Scenarios!E5=1,0, BaselineCalc!$B$8 + Scenarios!L5 - ROUND(Scenarios!L5*Scenarios!F5,0)) -> 346 | E20: =C20+D20 -> 653 | F20: =YearMap!B5 -> 7677.2394 | G20: =YearMap!C5 -> 845593.08 | H20: =YearMap!D5 -> 973912.66 | I20: =1-BaselineCalc!$B$5 -> 0.993 | J20: =Scenarios!G5 -> 0 | K20: =(G20+H20+F20*E20)*I20*(1-J20) -> 6784913.9 | L20: =IF(E20>0, K20/E20, "") -> 10390.373 | M20: =A20&"|"&B20 -> D_Grow_Both_100|FY2029
A21: =Scenarios!A5 -> D_Grow_Both_100 | B21: FY2030 | C21: =IF(Scenarios!D5=1,0, BaselineCalc!$B$7 + ROUND(Scenarios!M5*Scenarios!F5,0)) -> 307 | D21: =IF(Scenarios!E5=1,0, BaselineCalc!$B$8 + Scenarios!M5 - ROUND(Scenarios!M5*Scenarios!F5,0)) -> 346 | E21: =C21+D21 -> 653 | F21: =YearMap!B6 -> 7869.1704 | G21: =YearMap!C6 -> 866732.91 | H21: =YearMap!D6 -> 998260.47 | I21: =1-BaselineCalc!$B$5 -> 0.993 | J21: =Scenarios!G5 -> 0 | K21: =(G21+H21+F21*E21)*I21*(1-J21) -> 6954536.7 | L21: =IF(E21>0, K21/E21, "") -> 10650.133 | M21: =A21&"|"&B21 -> D_Grow_Both_100|FY2030
A22: =Scenarios!A6 -> D_Grow_Both_150 | B22: FY2026 | C22: =IF(Scenarios!D6=1,0, BaselineCalc!$B$7 + ROUND(Scenarios!I6*Scenarios!F6,0)) -> 332 | D22: =IF(Scenarios!E6=1,0, BaselineCalc!$B$8 + Scenarios!I6 - ROUND(Scenarios!I6*Scenarios!F6,0)) -> 371 | E22: =C22+D22 -> 703 | F22: =YearMap!B2 -> 7129.08 | G22: =YearMap!C2 -> 785217.24 | H22: =YearMap!D2 -> 904374.72 | I22: =1-BaselineCalc!$B$5 -> 0.993 | J22: =Scenarios!G6 -> 0 | K22: =(G22+H22+F22*E22)*I22*(1-J22) -> 6654425.9 | L22: =IF(E22>0, K22/E22, "") -> 9465.7551 | M22: =A22&"|"&B22 -> D_Grow_Both_150|FY2026
A23: =Scenarios!A6 -> D_Grow_Both_150 | B23: FY2027 | C23: =IF(Scenarios!D6=1,0, BaselineCalc!$B$7 + ROUND(Scenarios!J6*Scenarios!F6,0)) -> 332 | D23: =IF(Scenarios!E6=1,0, BaselineCalc!$B$8 + Scenarios!J6 - ROUND(Scenarios!J6*Scenarios!F6,0)) -> 371 | E23: =C23+D23 -> 703 | F23: =YearMap!B3 -> 7307.307 | G23: =YearMap!C3 -> 804847.67 | H23: =YearMap!D3 -> 926984.09 | I23: =1-BaselineCalc!$B$5 -> 0.993 | J23: =Scenarios!G6 -> 0 | K23: =(G23+H23+F23*E23)*I23*(1-J23) -> 6820786.5 | L23: =IF(E23>0, K23/E23, "") -> 9702.399 | M23: =A23&"|"&B23 -> D_Grow_Both_150|FY2027
A24: =Scenarios!A6 -> D_Grow_Both_150 | B24: FY2028 | C24: =IF(Scenarios!D6=1,0, BaselineCalc!$B$7 + ROUND(Scenarios!K6*Scenarios!F6,0)) -> 332 | D24: =IF(Scenarios!E6=1,0, BaselineCalc!$B$8 + Scenarios!K6 - ROUND(Scenarios!K6*Scenarios!F6,0)) -> 371 | E24: =C24+D24 -> 703 | F24: =YearMap!B4 -> 7489.9897 | G24: =YearMap!C4 -> 824968.86 | H24: =YearMap!D4 -> 950158.69 | I24: =1-BaselineCalc!$B$5 -> 0.993 | J24: =Scenarios!G6 -> 0 | K24: =(G24+H24+F24*E24)*I24*(1-J24) -> 6991306.2 | L24: =IF(E24>0, K24/E24, "") -> 9944.959 | M24: =A24&"|"&B24 -> D_Grow_Both_150|FY2028
A25: =Scenarios!A6 -> D_Grow_Both_150 | B25: FY2029 | C25: =IF(Scenarios!D6=1,0, BaselineCalc!$B$7 + ROUND(Scenarios!L6*Scenarios!F6,0)) -> 332 | D25: =IF(Scenarios!E6=1,0, BaselineCalc!$B$8 + Scenarios!L6 - ROUND(Scenarios!L6*Scenarios!F6,0)) -> 371 | E25: =C25+D25 -> 703 | F25: =YearMap!B5 -> 7677.2394 | G25: =YearMap!C5 -> 845593.08 | H25: =YearMap!D5 -> 973912.66 | I25: =1-BaselineCalc!$B$5 -> 0.993 | J25: =Scenarios!G6 -> 0 | K25: =(G25+H25+F25*E25)*I25*(1-J25) -> 7166088.8 | L25: =IF(E25>0, K25/E25, "") -> 10193.583 | M25: =A25&"|"&B25 -> D_Grow_Both_150|FY2029
A26: =Scenarios!A6 -> D_Grow_Both_150 | B26: FY2030 | C26: =IF(Scenarios!D6=1,0, BaselineCalc!$B$7 + ROUND(Scenarios!M6*Scenarios!F6,0)) -> 332 | D26: =IF(Scenarios!E6=1,0, BaselineCalc!$B$8 + Scenarios!M6 - ROUND(Scenarios!M6*Scenarios!F6,0)) -> 371 | E26: =C26+D26 -> 703 | F26: =YearMap!B6 -> 7869.1704 | G26: =YearMap!C6 -> 866732.91 | H26: =YearMap!D6 -> 998260.47 | I26: =1-BaselineCalc!$B$5 -> 0.993 | J26: =Scenarios!G6 -> 0 | K26: =(G26+H26+F26*E26)*I26*(1-J26) -> 7345241 | L26: =IF(E26>0, K26/E26, "") -> 10448.423 | M26: =A26&"|"&B26 -> D_Grow_Both_150|FY2030
A27: =Scenarios!A7 -> G_DHub_EchoRamp | B27: FY2026 | C27: =IF(Scenarios!D7=1,0, BaselineCalc!$B$7 + ROUND(Scenarios!I7*Scenarios!F7,0)) -> 292 | D27: =IF(Scenarios!E7=1,0, BaselineCalc!$B$8 + Scenarios!I7 - ROUND(Scenarios!I7*Scenarios!F7,0)) -> 311 | E27: =C27+D27 -> 603 | F27: =YearMap!B2 -> 7129.08 | G27: =YearMap!C2 -> 785217.24 | H27: =YearMap!D2 -> 904374.72 | I27: =1-BaselineCalc!$B$5 -> 0.993 | J27: =Scenarios!G7 -> 0 | K27: =(G27+H27+F27*E27)*I27*(1-J27) -> 5946508.2 | L27: =IF(E27>0, K27/E27, "") -> 9861.5393 | M27: =A27&"|"&B27 -> G_DHub_EchoRamp|FY2026
A28: =Scenarios!A7 -> G_DHub_EchoRamp | B28: FY2027 | C28: =IF(Scenarios!D7=1,0, BaselineCalc!$B$7 + ROUND(Scenarios!J7*Scenarios!F7,0)) -> 327 | D28: =IF(Scenarios!E7=1,0, BaselineCalc!$B$8 + Scenarios!J7 - ROUND(Scenarios!J7*Scenarios!F7,0)) -> 326 | E28: =C28+D28 -> 653 | F28: =YearMap!B3 -> 7307.307 | G28: =YearMap!C3 -> 804847.67 | H28: =YearMap!D3 -> 926984.09 | I28: =1-BaselineCalc!$B$5 -> 0.993 | J28: =Scenarios!G7 -> 0 | K28: =(G28+H28+F28*E28)*I28*(1-J28) -> 6457978.7 | L28: =IF(E28>0, K28/E28, "") -> 9889.7071 | M28: =A28&"|"&B28 -> G_DHub_EchoRamp|FY2027
A29: =Scenarios!A7 -> G_DHub_EchoRamp | B29: FY2028 | C29: =IF(Scenarios!D7=1,0, BaselineCalc!$B$7 + ROUND(Scenarios!K7*Scenarios!F7,0)) -> 362 | D29: =IF(Scenarios!E7=1,0, BaselineCalc!$B$8 + Scenarios!K7 - ROUND(Scenarios!K7*Scenarios!F7,0)) -> 341 | E29: =C29+D29 -> 703 | F29: =YearMap!B4 -> 7489.9897 | G29: =YearMap!C4 -> 824968.86 | H29: =YearMap!D4 -> 950158.69 | I29: =1-BaselineCalc!$B$5 -> 0.993 | J29: =Scenarios!G7 -> 0 | K29: =(G29+H29+F29*E29)*I29*(1-J29) -> 6991306.2 | L29: =IF(E29>0, K29/E29, "") -> 9944.959 | M29: =A29&"|"&B29 -> G_DHub_EchoRamp|FY2028
A30: =Scenarios!A7 -> G_DHub_EchoRamp | B30: FY2029 | C30: =IF(Scenarios!D7=1,0, BaselineCalc!$B$7 + ROUND(Scenarios!L7*Scenarios!F7,0)) -> 362 | D30: =IF(Scenarios!E7=1,0, BaselineCalc!$B$8 + Scenarios!L7 - ROUND(Scenarios!L7*Scenarios!F7,0)) -> 341 | E30: =C30+D30 -> 703 | F30: =YearMap!B5 -> 7677.2394 | G30: =YearMap!C5 -> 845593.08 | H30: =YearMap!D5 -> 973912.66 | I30: =1-BaselineCalc!$B$5 -> 0.993 | J30: =Scenarios!G7 -> 0 | K30: =(G30+H30+F30*E30)*I30*(1-J30) -> 7166088.8 | L30: =IF(E30>0, K30/E30, "") -> 10193.583 | M30: =A30&"|"&B30 -> G_DHub_EchoRamp|FY2029
A31: =Scenarios!A7 -> G_DHub_EchoRamp | B31: FY2030 | C31: =IF(Scenarios!D7=1,0, BaselineCalc!$B$7 + ROUND(Scenarios!M7*Scenarios!F7,0)) -> 362 | D31: =IF(Scenarios!E7=1,0, BaselineCalc!$B$8 + Scenarios!M7 - ROUND(Scenarios!M7*Scenarios!F7,0)) -> 341 | E31: =C31+D31 -> 703 | F31: =YearMap!B6 -> 7869.1704 | G31: =YearMap!C6 -> 866732.91 | H31: =YearMap!D6 -> 998260.47 | I31: =1-BaselineCalc!$B$5 -> 0.993 | J31: =Scenarios!G7 -> 0 | K31: =(G31+H31+F31*E31)*I31*(1-J31) -> 7345241 | L31: =IF(E31>0, K31/E31, "") -> 10448.423 | M31: =A31&"|"&B31 -> G_DHub_EchoRamp|FY2030

Sheet Summary_Costs
A1: ScenarioKey | B1: FY2028 MO/ADM | C1: FY2030 MO/ADM | D1: 3-yr Avg MO/ADM (FY26–FY28) | E1: 5-yr Avg MO/ADM (FY26–FY30)
A2: =Scenarios!A2 -> D_Grow_Both_0 | B2: =INDEX(MultiYear_ProForma!$L$2:$L$31, MATCH( Scenarios!A2&"|FY2028", MultiYear_ProForma!$M$2:$M$31, 0)) -> 10625.085 | C2: =INDEX(MultiYear_ProForma!$L$2:$L$31, MATCH( Scenarios!A2&"|FY2030", MultiYear_ProForma!$M$2:$M$31, 0)) -> 11162.98 | D2: =AVERAGE(INDEX(MultiYear_ProForma!$L$2:$L$31, MATCH(Scenarios!A2&"|FY2026", MultiYear_ProForma!$M$2:$M$31, 0)),INDEX(MultiYear_ProForma!$L$2:$L$31, MATCH(Scenarios!A2&"|FY2027", MultiYear_ProForma!$M$2:$M$31, 0)),INDEX(MultiYear_ProForma!$L$2:$L$31, MATCH(Scenarios!A2&"|FY2028", MultiYear_ProForma!$M$2:$M$31, 0))) -> 10368.044 | E2: =AVERAGE(INDEX(MultiYear_ProForma!$L$2:$L$31, MATCH(Scenarios!A2&"|FY2026", MultiYear_ProForma!$M$2:$M$31, 0)),INDEX(MultiYear_ProForma!$L$2:$L$31, MATCH(Scenarios!A2&"|FY2027", MultiYear_ProForma!$M$2:$M$31, 0)),INDEX(MultiYear_ProForma!$L$2:$L$31, MATCH(Scenarios!A2&"|FY2028", MultiYear_ProForma!$M$2:$M$31, 0)),INDEX(MultiYear_ProForma!$L$2:$L$31, MATCH(Scenarios!A2&"|FY2029", MultiYear_ProForma!$M$2:$M$31, 0)),INDEX(MultiYear_ProForma!$L$2:$L$31, MATCH(Scenarios!A2&"|FY2030", MultiYear_ProForma!$M$2:$M$31, 0))) -> 10631.565
A3: =Scenarios!A3 -> E_StatusQuo_Targets_0 | B3: =INDEX(MultiYear_ProForma!$L$2:$L$31, MATCH( Scenarios!A3&"|FY2028", MultiYear_ProForma!$M$2:$M$31, 0)) -> 10625.085 | C3: =INDEX(MultiYear_ProForma!$L$2:$L$31, MATCH( Scenarios!A3&"|FY2030", MultiYear_ProForma!$M$2:$M$31, 0)) -> 11162.98 | D3: =AVERAGE(INDEX(MultiYear_ProForma!$L$2:$L$31, MATCH(Scenarios!A3&"|FY2026", MultiYear_ProForma!$M$2:$M$31, 0)),INDEX(MultiYear_ProForma!$L$2:$L$31, MATCH(Scenarios!A3&"|FY2027", MultiYear_ProForma!$M$2:$M$31, 0)),INDEX(MultiYear_ProForma!$L$2:$L$31, MATCH(Scenarios!A3&"|FY2028", MultiYear_ProForma!$M$2:$M$31, 0))) -> 10368.044 | E3: =AVERAGE(INDEX(MultiYear_ProForma!$L$2:$L$31, MATCH(Scenarios!A3&"|FY2026", MultiYear_ProForma!$M$2:$M$31, 0)),INDEX(MultiYear_ProForma!$L$2:$L$31, MATCH(Scenarios!A3&"|FY2027", MultiYear_ProForma!$M$2:$M$31, 0)),INDEX(MultiYear_ProForma!$L$2:$L$31, MATCH(Scenarios!A3&"|FY2028", MultiYear_ProForma!$M$2:$M$31, 0)),INDEX(MultiYear_ProForma!$L$2:$L$31, MATCH(Scenarios!A3&"|FY2029", MultiYear_ProForma!$M$2:$M$31, 0)),INDEX(MultiYear_ProForma!$L$2:$L$31, MATCH(Scenarios!A3&"|FY2030", MultiYear_ProForma!$M$2:$M$31, 0))) -> 10631.565
A4: =Scenarios!A4 -> F_CoLocation_Echo_0 | B4: =INDEX(MultiYear_ProForma!$L$2:$L$31, MATCH( Scenarios!A4&"|FY2028", MultiYear_ProForma!$M$2:$M$31, 0)) -> 10465.709 | C4: =INDEX(MultiYear_ProForma!$L$2:$L$31, MATCH( Scenarios!A4&"|FY2030", MultiYear_ProForma!$M$2:$M$31, 0)) -> 10995.536 | D4: =AVERAGE(INDEX(MultiYear_ProForma!$L$2:$L$31, MATCH(Scenarios!A4&"|FY2026", MultiYear_ProForma!$M$2:$M$31, 0)),INDEX(MultiYear_ProForma!$L$2:$L$31, MATCH(Scenarios!A4&"|FY2027", MultiYear_ProForma!$M$2:$M$31, 0)),INDEX(MultiYear_ProForma!$L$2:$L$31, MATCH(Scenarios!A4&"|FY2028", MultiYear_ProForma!$M$2:$M$31, 0))) -> 10212.523 | E4: =AVERAGE(INDEX(MultiYear_ProForma!$L$2:$L$31, MATCH(Scenarios!A4&"|FY2026", MultiYear_ProForma!$M$2:$M$31, 0)),INDEX(MultiYear_ProForma!$L$2:$L$31, MATCH(Scenarios!A4&"|FY2027", MultiYear_ProForma!$M$2:$M$31, 0)),INDEX(MultiYear_ProForma!$L$2:$L$31, MATCH(Scenarios!A4&"|FY2028", MultiYear_ProForma!$M$2:$M$31, 0)),INDEX(MultiYear_ProForma!$L$2:$L$31, MATCH(Scenarios!A4&"|FY2029", MultiYear_ProForma!$M$2:$M$31, 0)),INDEX(MultiYear_ProForma!$L$2:$L$31, MATCH(Scenarios!A4&"|FY2030", MultiYear_ProForma!$M$2:$M$31, 0))) -> 10472.091
A5: =Scenarios!A5 -> D_Grow_Both_100 | B5: =INDEX(MultiYear_ProForma!$L$2:$L$31, MATCH( Scenarios!A5&"|FY2028", MultiYear_ProForma!$M$2:$M$31, 0)) -> 10136.95 | C5: =INDEX(MultiYear_ProForma!$L$2:$L$31, MATCH( Scenarios!A5&"|FY2030", MultiYear_ProForma!$M$2:$M$31, 0)) -> 10650.133 | D5: =AVERAGE(INDEX(MultiYear_ProForma!$L$2:$L$31, MATCH(Scenarios!A5&"|FY2026", MultiYear_ProForma!$M$2:$M$31, 0)),INDEX(MultiYear_ProForma!$L$2:$L$31, MATCH(Scenarios!A5&"|FY2027", MultiYear_ProForma!$M$2:$M$31, 0)),INDEX(MultiYear_ProForma!$L$2:$L$31, MATCH(Scenarios!A5&"|FY2028", MultiYear_ProForma!$M$2:$M$31, 0))) -> 9891.7172 | E5: =AVERAGE(INDEX(MultiYear_ProForma!$L$2:$L$31, MATCH(Scenarios!A5&"|FY2026", MultiYear_ProForma!$M$2:$M$31, 0)),INDEX(MultiYear_ProForma!$L$2:$L$31, MATCH(Scenarios!A5&"|FY2027", MultiYear_ProForma!$M$2:$M$31, 0)),INDEX(MultiYear_ProForma!$L$2:$L$31, MATCH(Scenarios!A5&"|FY2028", MultiYear_ProForma!$M$2:$M$31, 0)),INDEX(MultiYear_ProForma!$L$2:$L$31, MATCH(Scenarios!A5&"|FY2029", MultiYear_ProForma!$M$2:$M$31, 0)),INDEX(MultiYear_ProForma!$L$2:$L$31, MATCH(Scenarios!A5&"|FY2030", MultiYear_ProForma!$M$2:$M$31, 0))) -> 10143.132
A6: =Scenarios!A6 -> D_Grow_Both_150 | B6: =INDEX(MultiYear_ProForma!$L$2:$L$31, MATCH( Scenarios!A6&"|FY2028", MultiYear_ProForma!$M$2:$M$31, 0)) -> 9944.959 | C6: =INDEX(MultiYear_ProForma!$L$2:$L$31, MATCH( Scenarios!A6&"|FY2030", MultiYear_ProForma!$M$2:$M$31, 0)) -> 10448.423 | D6: =AVERAGE(INDEX(MultiYear_ProForma!$L$2:$L$31, MATCH(Scenarios!A6&"|FY2026", MultiYear_ProForma!$M$2:$M$31, 0)),INDEX(MultiYear_ProForma!$L$2:$L$31, MATCH(Scenarios!A6&"|FY2027", MultiYear_ProForma!$M$2:$M$31, 0)),INDEX(MultiYear_ProForma!$L$2:$L$31, MATCH(Scenarios!A6&"|FY2028", MultiYear_ProForma!$M$2:$M$31, 0))) -> 9704.371 | E6: =AVERAGE(INDEX(MultiYear_ProForma!$L$2:$L$31, MATCH(Scenarios!A6&"|FY2026", MultiYear_ProForma!$M$2:$M$31, 0)),INDEX(MultiYear_ProForma!$L$2:$L$31, MATCH(Scenarios!A6&"|FY2027", MultiYear_ProForma!$M$2:$M$31, 0)),INDEX(MultiYear_ProForma!$L$2:$L$31, MATCH(Scenarios!A6&"|FY2028", MultiYear_ProForma!$M$2:$M$31, 0)),INDEX(MultiYear_ProForma!$L$2:$L$31, MATCH(Scenarios!A6&"|FY2029", MultiYear_ProForma!$M$2:$M$31, 0)),INDEX(MultiYear_ProForma!$L$2:$L$31, MATCH(Scenarios!A6&"|FY2030", MultiYear_ProForma!$M$2:$M$31, 0))) -> 9951.0237
A7: =Scenarios!A7 -> G_DHub_EchoRamp | B7: =INDEX(MultiYear_ProForma!$L$2:$L$31, MATCH( Scenarios!A7&"|FY2028", MultiYear_ProForma!$M$2:$M$31, 0)) -> 9944.959 | C7: =INDEX(MultiYear_ProForma!$L$2:$L$31, MATCH( Scenarios!A7&"|FY2030", MultiYear_ProForma!$M$2:$M$31, 0)) -> 10448.423 | D7: =AVERAGE(INDEX(MultiYear_ProForma!$L$2:$L$31, MATCH(Scenarios!A7&"|FY2026", MultiYear_ProForma!$M$2:$M$31, 0)),INDEX(MultiYear_ProForma!$L$2:$L$31, MATCH(Scenarios!A7&"|FY2027", MultiYear_ProForma!$M$2:$M$31, 0)),INDEX(MultiYear_ProForma!$L$2:$L$31, MATCH(Scenarios!A7&"|FY2028", MultiYear_ProForma!$M$2:$M$31, 0))) -> 9898.7351 | E7: =AVERAGE(INDEX(MultiYear_ProForma!$L$2:$L$31, MATCH(Scenarios!A7&"|FY2026", MultiYear_ProForma!$M$2:$M$31, 0)),INDEX(MultiYear_ProForma!$L$2:$L$31, MATCH(Scenarios!A7&"|FY2027", MultiYear_ProForma!$M$2:$M$31, 0)),INDEX(MultiYear_ProForma!$L$2:$L$31, MATCH(Scenarios!A7&"|FY2028", MultiYear_ProForma!$M$2:$M$31, 0)),INDEX(MultiYear_ProForma!$L$2:$L$31, MATCH(Scenarios!A7&"|FY2029", MultiYear_ProForma!$M$2:$M$31, 0)),INDEX(MultiYear_ProForma!$L$2:$L$31, MATCH(Scenarios!A7&"|FY2030", MultiYear_ProForma!$M$2:$M$31, 0))) -> 10067.642

Sheet Notes
A1: FAQs
B2: Why “Fixed share of M&O = 0.30”?
B3: District M&O typically has a sizable semi‑fixed component (plant ops/custodial/insurance/admin overhead). Without site‑level detail yet, 30% is a conservative placeholder in the middle of the 25–40% range many K‑12 systems sit in. We will replace it with SUSD plant ops + insurance shares when available.
B5: Why “Ops savings (keep‑open) = 0.007 (0.7%)”?
B6: This represents “light discipline” (utilities/purchasing tweaks, route smoothing) that does not depend on closing a site. I set it very low on purpose so it doesn’t drive results. We’ll calibrate with SUSD data (e.g., last year’s utility audits) if provided.
B8: Why “Extra savings (co‑location) = 0.015 (1.5%)”?
B9: This reflects incremental savings from consolidating some services on one campus (custodial/grounds/partial routing). Again kept small and conservative; we’ll swap in real custodial (sq‑ft), grounds and route deltas when we get them.
B11: Why “Repurpose TI per closed site (FY26) = $1.2M”? What is “one‑time carry/TI”?
B12: “TI” = tenant improvements / transition investments needed to convert a K‑8 to a different use (early learning, admin consolidation) and carry costs in year one (e.g., abatement, doors/security, low‑voltage re‑work, furniture, swing space). A light‑touch repurpose can easily run $10–$20/sq‑ft; Echo’s plant is ~77k sq ft, so $1.2M is a reasonable placeholder (we are not assuming a gut remodel). We’ll replace this with SUSD’s scope/estimate if they have one.
A17: Definitions
B18: MO inflation
B19: Base MO per ADM (FY25)
B20: Fixed share of MO
B21: Ops savings (keep‑open)
B22: Extra savings (Co‑location)
B23: Echo base ADM
B24: Pima base ADM
B25: Total base ADM
