Workbook
Name ADM_Day_Select: Parameters_Public!C8
Name BaseAid_per_ADM: Parameters_Public!C18
Name Capex_ArtsHub: Parameters_Public!C28
Name Capex_in_MO_Toggle: Parameters_Public!C30
Name Capex_InnovHub: Parameters_Public!C29
Name Echo_ADM0: Parameters_Public!C10
Name EchoFixed_FY25_Total: Site_Fixed!C8
Name M_O_per_ADM_Audited: Parameters_Public!C14
Name Override_per_ADM_proxy: Parameters_Public!C19
Name Override_Percent: Parameters_Public!C17
Name Override_Toggle: Parameters_Public!C20
Name Pima_ADM0: Parameters_Public!C11
Name PimaFixed_FY25_Total: Site_Fixed!C15
Name TI_in_MO_Toggle: Parameters_Public!C26
Name TI_per_Site: Parameters_Public!C27

Sheet Workbook_Purpose_Overview
B2: Why this workbook exists
B3: This model helps the Board weigh three postures for Echo Canyon and Pima: managed decline, strategic consolidation (repurpose), and strategic growth. It separates operating (Fund 001) from one‑time capital (FY26) and makes people impacts visible (Displaced FY26; Served FY30). Net (operating) is M&O − (Aid + Override + Uplift); capital is shown separately. Assumptions (r retention, h overhead with taper, trend gates, override toggle) are visible on comparison views; receiving capacity gates are enforced by band.
B5: How to use it (start here)
B6: Scenario_Comparison – pick Base and Comparator to see the curves; Δ‑cards (FY2030 and 5‑yr avg); FY26 capital; Displaced FY26; Served FY30. Summary_Figures – a ranked table of all scenarios with the same decision signals (useful for board packets). BreakEven – see (i) how many students a growth lane must add to tie a repurpose baseline (N*), and (ii) the minimum retention a repurpose baseline needs to tie growth (r*), for FY26 and FY30.
B8: What the data say right now
B9: We assume a positive marginal contribution per added student where capacity exists (per‑ADM revenues indexed by policy exceed incremental operating cost). This is a reasonable working assumption in AZ’s funding structure. Arizona Legislature • Repurpose is credited with conservative fixed‑savings via a fixed‑share fallback and carry fractions (f_ops, f_lease) that decline over time; we’ll replace those dollars with audited site‑fixed ledgers for Echo/Pima. • To keep comparisons balanced, repurpose bears a tapering retention overhead (h) for displaced students who stay in SUSD, and growth bears a modest growth overhead (g = α × h) for routing/admin. • Use BreakEven to read the trade space: fixed‑savings vs. retention overhead (repurpose) and growth‑driven contribution (growth). Revenue matters too (why a growth lane belongs next to fiscal discipline) The budget hole isn’t just costs; it’s also top line (ADM). At about $5.0k per pupil Base Level Amount (FY2025), 100 K‑8 students ≈ $0.50M/year in base aid ignoring weights; 200 ≈ $1.0M. Weights, override, and other GF elements lift the true marginal revenue further.
B11: Other important context (recent precedents & lessons)
B12: • Chicago (2013 closures): studies report negative short‑term academic effects and no long‑term positive gains on average; some analyses note math effects persisting for students from closed schools, with better outcomes only when receiving schools were substantially higher‑performing. Lesson: overshoot/disruption has real costs. consortium.uchicago.edu +2 consortium.uchicago.edu +2 • Denver (2024–25): after a 2024 closure vote, the board paused further closures until 2030 amid community/legal pushback and governance churn. Lesson: force without consensus begets drag; iterate policy with stakeholders. Chalkbeat +1 • Kyrene (2025): district scheduled multiple public hearings on consolidation/boundaries and revised proposals after feedback. Lesson: iterate, publish, adjust before the final vote. kyrene.org +1 • Innovation hub option (analogy): Campbell School of Innovation (Campbell Union SD, CA) launched a district‑run innovation hub focused on design thinking, grew enrollment, and exported practices across the district. Lesson: a credible hub can strengthen brand and pull.
B14: Decision gates (apply before selecting a path)
B19: Revenue matters too. The budget hole isn’t just costs; it’s also top line (ADM). Capturing even 100 additional K‑8 students ≈ $511k/year in base state aid (ignoring weights) at the FY26 base of $5,113 is real money; 200 ≈ $1.02M. (Add grade/need weights and it’s higher.) That’s why a growth lane belongs next to a fiscal discipline lane. Arizona Department of Education
B20: Chicago (2013): Long‑term negative math effects for students from closed schools; many displaced students did not land in top‑tier schools. Lesson: Overshoot has real, lasting costs. UChicago Consortium on School Research+2WTTW News+2
B21: Denver (2024–25): Rapid closures triggered community/legal blowback and ongoing governance churn; boards are now haggling over pauses and re‑plans midstream. Lesson: Force without consensus begets drag. Denver Public Schools+2Chalkbeat+2
... B184: If the question is “why not put the hub where there’s no enrollment problem?”—the answer is speed-to-value: Echo’s assets mean lower startup friction, faster prototypes, and cleaner measurement, while preserving community value.

Sheet Scenario_Comparison
B1: Echo & Pima — Go-forward scenario comparison view
B3: Scenarios (CHOOSE) | C3: Description | I3: Assumed enrollment change (over 3 yrs)
B4: E1_StatusQuo_Decline | C4: =VLOOKUP($B4,Scenarios!$A$1:$C$14, 2, 0) -> Echo & Pima open; no operational or strategic growth actions; enrollment decline trend continues | J4: =IF(ROUND(SUMIFS(MultiYear_ProForma!$AC:$AC,MultiYear_ProForma!$B:$B,$B4,MultiYear_ProForma!$C:$C,"FY2030")-BaselineCalc!$B$9, 0)>0, "+"&ROUND(SUMIFS(MultiYear_ProForma!$AC:$AC,MultiYear_ProForma!$B:$B,$B4,MultiYear_ProForma!$C:$C,"FY2030")-BaselineCalc!$B$9, 0), ROUND(SUMIFS(MultiYear_ProForma!$AC:$AC,MultiYear_ProForma!$B:$B,$B4,MultiYear_ProForma!$C:$C,"FY2030")-BaselineCalc!$B$9, 0)) -> -43
B5: A2_Repurpose_Both_lease | C5: =VLOOKUP($B5,Scenarios!$A$1:$C$14, 2, 0) -> Repurpose both Echo & Pima; lease both properties; fixed cost reduction rate, retention %, and transition cost assumptions are key drivers | J5: =IF(ROUND(SUMIFS(MultiYear_ProForma!$AC:$AC,MultiYear_ProForma!$B:$B,$B5,MultiYear_ProForma!$C:$C,"FY2030")-BaselineCalc!$B$9, 0)>0, "+"&ROUND(SUMIFS(MultiYear_ProForma!$AC:$AC,MultiYear_ProForma!$B:$B,$B5,MultiYear_ProForma!$C:$C,"FY2030")-BaselineCalc!$B$9, 0), ROUND(SUMIFS(MultiYear_ProForma!$AC:$AC,MultiYear_ProForma!$B:$B,$B5,MultiYear_ProForma!$C:$C,"FY2030")-BaselineCalc!$B$9, 0)) -> -147
B24: Notes: Assumptions reflect: r (retention assumptions), override, marginal factor (e.g. assumed reduced variable cost to add new students), trend flags; h (receiving schools transportation route adjustment premium) tapers yearly. Receiving site should not exceed spare seats + portables
B26: Year | C26: Operating Net$ (Base) | D26: Operating Net$ (Comparator)
B27: FY2026 | C27: =SUMIFS(MultiYear_ProForma!$AF$2:$AF$66, MultiYear_ProForma!$B$2:$B$66, $B$4, MultiYear_ProForma!$C$2:$C$66, "FY2026") -> -459335.03 | D27: =SUMIFS(MultiYear_ProForma!$AF$2:$AF$66, MultiYear_ProForma!$B$2:$B$66, $B$5, MultiYear_ProForma!$C$2:$C$66, "FY2026") -> 840656.32
B28: FY2027 | C28: =SUMIFS(MultiYear_ProForma!$AF$2:$AF$66, MultiYear_ProForma!$B$2:$B$66, $B$4, MultiYear_ProForma!$C$2:$C$66, "FY2027") -> -522913.48 | D28: =SUMIFS(MultiYear_ProForma!$AF$2:$AF$66, MultiYear_ProForma!$B$2:$B$66, $B$5, MultiYear_ProForma!$C$2:$C$66, "FY2027") -> 952977.73
B29: FY2028 | C29: =SUMIFS(MultiYear_ProForma!$AF$2:$AF$66, MultiYear_ProForma!$B$2:$B$66, $B$4, MultiYear_ProForma!$C$2:$C$66, "FY2028") -> -588315.82 | D29: =SUMIFS(MultiYear_ProForma!$AF$2:$AF$66, MultiYear_ProForma!$B$2:$B$66, $B$5, MultiYear_ProForma!$C$2:$C$66, "FY2028") -> 1223701.2
B30: FY2029 | C30: =SUMIFS(MultiYear_ProForma!$AF$2:$AF$66, MultiYear_ProForma!$B$2:$B$66, $B$4, MultiYear_ProForma!$C$2:$C$66, "FY2029") -> -655588.7 | D30: =SUMIFS(MultiYear_ProForma!$AF$2:$AF$66, MultiYear_ProForma!$B$2:$B$66, $B$5, MultiYear_ProForma!$C$2:$C$66, "FY2029") -> 1462524.4
B31: FY2030 | C31: =SUMIFS(MultiYear_ProForma!$AF$2:$AF$66, MultiYear_ProForma!$B$2:$B$66, $B$4, MultiYear_ProForma!$C$2:$C$66, "FY2030") -> -724779.94 | D31: =SUMIFS(MultiYear_ProForma!$AF$2:$AF$66, MultiYear_ProForma!$B$2:$B$66, $B$5, MultiYear_ProForma!$C$2:$C$66, "FY2030") -> 1585320
B33: Assumptions (from Parameters_Public / Control_Center)
B34: Retention r (Echo central) | C34: =Parameters_Public!C23 -> 0.6
B35: Retention r (Pima central) | C35: =Parameters_Public!C24 -> 0.85
B36: MarginalFactor_for_Overlay | C36: =Parameters_Public!C43 -> 0.6
B37: Override % | C37: =Parameters_Public!C17 -> 0.15
B38: Override toggle (0/1) | C38: =Parameters_Public!C20 -> 1
B39: • Keep-open ops savings (fraction of MO): | C39: =Control_Center!C10 -> 0.007
B40: • Extra savings for co-location (fraction of MO): | C40: =Control_Center!C11 -> 0.015
B41: • Routing/admin overhead h tapers by year (see YearMap). Try ±20% sensitivity when routing assumptions are uncertain.
D43: Interpretation
B44: One-time Capital FY 2026 (Base) | C44: =SUMIFS(Capital_Summary!$H$4:$H$83, Capital_Summary!$A$4:$A$83, B4, Capital_Summary!$B$4:$B$83, "FY2026") -> 0 | D44: =""&$B$5&" will be $"&TEXT(ROUND(ABS(C45-C44),0), "#,##0")&" "&IF(C45>C44,"MORE COSTLY","LESS COSTLY")&" than "&$B$4&" in terms of capital investment required " -> A2_Repurpose_Both_lease will be $1,600,000 MORE COSTLY than E1_StatusQuo_Decline in terms of capital investment required
B45: One-time Capital FY 2026 (Comparator) | C45: =SUMIFS(Capital_Summary!$H$4:$H$83, Capital_Summary!$A$4:$A$83, B5, Capital_Summary!$B$4:$B$83, "FY2026") -> 1600000
B47: Avg Net (FY26–30) (Base)—rounded | C47: =ROUND((SUMIFS(MultiYear_ProForma!$AF$2:$AF$66,MultiYear_ProForma!$B$2:$B$66,$B$4,MultiYear_ProForma!$C$2:$C$66,"FY2026")+SUMIFS(MultiYear_ProForma!$AF$2:$AF$66,MultiYear_ProForma!$B$2:$B$66,$B$4,MultiYear_ProForma!$C$2:$C$66,"FY2027")+SUMIFS(MultiYear_ProForma!$AF$2:$AF$66,MultiYear_ProForma!$B$2:$B$66,$B$4,MultiYear_ProForma!$C$2:$C$66,"FY2028")+SUMIFS(MultiYear_ProForma!$AF$2:$AF$66,MultiYear_ProForma!$B$2:$B$66,$B$4,MultiYear_ProForma!$C$2:$C$66,"FY2029")+SUMIFS(MultiYear_ProForma!$AF$2:$AF$66,MultiYear_ProForma!$B$2:$B$66,$B$4,MultiYear_ProForma!$C$2:$C$66,"FY2030"))/5,-4) -> -590000 | D47: ="On average from 2026 through 2030, "&$B$5&" will be $"&TEXT(ABS(ROUND(C49,0)), "#,##0")&" "&IF(C49<0,"MORE COSTLY","LESS COSTLY")&" to operate annually than "&$B$4&"" -> On average from 2026 through 2030, A2_Repurpose_Both_lease will be $1,610,000 LESS COSTLY to operate annually than E1_StatusQuo_Decline
B48: Avg Net (FY26–30) (Comparator)—rounded | C48: =ROUND((SUMIFS(MultiYear_ProForma!$AF$2:$AF$66, MultiYear_ProForma!$B$2:$B$66, $B$5, MultiYear_ProForma!$C$2:$C$66, "FY2026")+SUMIFS(MultiYear_ProForma!$AF$2:$AF$66, MultiYear_ProForma!$B$2:$B$66, $C$5, MultiYear_ProForma!$C$2:$C$66, "FY2027")+SUMIFS(MultiYear_ProForma!$AF$2:$AF$66, MultiYear_ProForma!$B$2:$B$66, $B$5, MultiYear_ProForma!$C$2:$C$66, "FY2028")+SUMIFS(MultiYear_ProForma!$AF$2:$AF$66, MultiYear_ProForma!$B$2:$B$66, $B$5, MultiYear_ProForma!$C$2:$C$66, "FY2029")+SUMIFS(MultiYear_ProForma!$AF$2:$AF$66, MultiYear_ProForma!$B$2:$B$66, $B$5, MultiYear_ProForma!$C$2:$C$66, "FY2030"))/5, -4) -> 1020000
B49: Δ vs Base (Avg FY26–30)—rounded | C49: =ROUND(C48-C47, -4) -> 1610000
B52: FY2030 Net (Base)—rounded | C52: =ROUND(SUMIFS(MultiYear_ProForma!$AF$2:$AF$66, MultiYear_ProForma!$B$2:$B$66, $B$4, MultiYear_ProForma!$C$2:$C$66, "FY2030"), -4) -> -720000 | D52: ="By 2030, "&$B$5&" will be $"&TEXT(ABS(ROUND(C54,0)), "#,##0")&" "&IF(C54<0,"MORE COSTLY","LESS COSTLY")&" to operate annually than "&$B$4&"" -> By 2030, A2_Repurpose_Both_lease will be $2,310,000 LESS COSTLY to operate annually than E1_StatusQuo_Decline
B53: FY2030 Net (Comparator)—rounded | C53: =ROUND(SUMIFS(MultiYear_ProForma!$AF$2:$AF$66, MultiYear_ProForma!$B$2:$B$66, $B$5, MultiYear_ProForma!$C$2:$C$66, "FY2030"), -4) -> 1590000
B54: Δ vs Base (FY2030)—rounded | C54: =ROUND(C53-C52, -4) -> 2310000
B56: Students displaced (FY26) (Base) | C56: =SUMIFS(MultiYear_ProForma!$N$2:$N$66, MultiYear_ProForma!$B$2:$B$66, $B$4, MultiYear_ProForma!$C$2:$C$66, "FY2026") -> 0 | D56: =""&$B$5&" will displace "&ROUND(ABS(C57-C56),0)&" "&IF(C57>C56,"MORE STUDENTS","FEWER STUDENTS")&" than "&$B$4&"" -> A2_Repurpose_Both_lease will displace 553 MORE STUDENTS than E1_StatusQuo_Decline
B57: Students displaced (FY26) (Comparator) | C57: =SUMIFS(MultiYear_ProForma!$N$2:$N$66, MultiYear_ProForma!$B$2:$B$66, $B$5, MultiYear_ProForma!$C$2:$C$66, "FY2026") -> 553
B59: Students served (FY2030) (Base) | C59: =SUMIFS(MultiYear_ProForma!$AC$2:$AC$66, MultiYear_ProForma!$B$2:$B$66, $B$4, MultiYear_ProForma!$C$2:$C$66, "FY2030") -> 510.06959 | D59: =""&$B$5&" will serve "&ROUND(ABS(C60-C59),0)&" "&IF(C60>C59,"MORE STUDENTS","FEWER STUDENTS")&" than "&$B$4&"" -> A2_Repurpose_Both_lease will serve 104 FEWER STUDENTS than E1_StatusQuo_Decline
B60: Students served (FY2030) (Comparator) | C60: =SUMIFS(MultiYear_ProForma!$AC$2:$AC$66, MultiYear_ProForma!$B$2:$B$66, $B$5, MultiYear_ProForma!$C$2:$C$66, "FY2030") -> 405.8

Sheet BreakEven
A1: Break‑Even Calculator (Operating)
A3: Baseline (repurpose) Scenario | B3: A2_Repurpose_Both_lease
A4: Years shown | B4: FY2026 & FY2030
A6: Metric | B6: FY2026 | C6: FY2030
A7: mᵗ: Incremental margin per added ADM | B7: =INDEX(YearMap!$I$2:$I$6, MATCH("FY2026",YearMap!$A$2:$A$6,0))+IF(Parameters_Public!C20=1, INDEX(YearMap!$O$2:$O$6, MATCH("FY2026",YearMap!$A$2:$A$6,0)),0)+INDEX(YearMap!$P$2:$P$6, MATCH("FY2026",YearMap!$A$2:$A$6,0))-INDEX(YearMap!$B$2:$B$6, MATCH("FY2026",YearMap!$A$2:$A$6,0))-INDEX(YearMap!$Q$2:$Q$6, MATCH("FY2026",YearMap!$A$2:$A$6,0)) -> 4350.4385 | C7: =INDEX(YearMap!$I$2:$I$6, MATCH("FY2030",YearMap!$A$2:$A$6,0))+IF(Parameters_Public!C20=1, INDEX(YearMap!$O$2:$O$6, MATCH("FY2030",YearMap!$A$2:$A$6,0)),0)+INDEX(YearMap!$P$2:$P$6, MATCH("FY2030",YearMap!$A$2:$A$6,0))-INDEX(YearMap!$B$2:$B$6, MATCH("FY2030",YearMap!$A$2:$A$6,0))-INDEX(YearMap!$Q$2:$Q$6, MATCH("FY2030",YearMap!$A$2:$A$6,0)) -> 4962.8327
A8: Sᵗ: Fixed savings − retention overhead | B8: =(SUMIFS(MultiYear_ProForma!$H$2:$H$66,MultiYear_ProForma!$B$2:$B$66,$B$3,MultiYear_ProForma!$C$2:$C$66,"FY2026")+SUMIFS(MultiYear_ProForma!$I$2:$I$66,MultiYear_ProForma!$B$2:$B$66,$B$3,MultiYear_ProForma!$C$2:$C$66,"FY2026")-SUMIFS(MultiYear_ProForma!$R$2:$R$66,MultiYear_ProForma!$B$2:$B$66,$B$3,MultiYear_ProForma!$C$2:$C$66,"FY2026")-SUMIFS(MultiYear_ProForma!$S$2:$S$66,MultiYear_ProForma!$B$2:$B$66,$B$3,MultiYear_ProForma!$C$2:$C$66,"FY2026"))-SUMIFS(MultiYear_ProForma!$O$2:$O$66,MultiYear_ProForma!$B$2:$B$66,$B$3,MultiYear_ProForma!$C$2:$C$66,"FY2026")*INDEX(YearMap!$E$2:$E$6, MATCH("FY2026",YearMap!$A$2:$A$6,0)) -> 2011568.1 | C8: =(SUMIFS(MultiYear_ProForma!$H$2:$H$66,MultiYear_ProForma!$B$2:$B$66,$B$3,MultiYear_ProForma!$C$2:$C$66,"FY2030")+SUMIFS(MultiYear_ProForma!$I$2:$I$66,MultiYear_ProForma!$B$2:$B$66,$B$3,MultiYear_ProForma!$C$2:$C$66,"FY2030")-SUMIFS(MultiYear_ProForma!$R$2:$R$66,MultiYear_ProForma!$B$2:$B$66,$B$3,MultiYear_ProForma!$C$2:$C$66,"FY2030")-SUMIFS(MultiYear_ProForma!$S$2:$S$66,MultiYear_ProForma!$B$2:$B$66,$B$3,MultiYear_ProForma!$C$2:$C$66,"FY2030"))-SUMIFS(MultiYear_ProForma!$O$2:$O$66,MultiYear_ProForma!$B$2:$B$66,$B$3,MultiYear_ProForma!$C$2:$C$66,"FY2030")*INDEX(YearMap!$E$2:$E$6, MATCH("FY2030",YearMap!$A$2:$A$6,0)) -> 2880122.3
A9: ΔADM_disp: Displaced under baseline repurpose | B9: =SUMIFS(MultiYear_ProForma!$N$2:$N$66,MultiYear_ProForma!$B$2:$B$66,$B$3,MultiYear_ProForma!$C$2:$C$66,"FY2026") -> 553 | C9: =SUMIFS(MultiYear_ProForma!$N$2:$N$66,MultiYear_ProForma!$B$2:$B$66,$B$3,MultiYear_ProForma!$C$2:$C$66,"FY2030") -> 553
A11: N*: Added students growth needs to tie baseline repurpose | B11: =IFERROR($B$8/$B$7,"") -> 462.38283 | C11: =IFERROR($C$8/$C$7,"") -> 580.33838
A12: r*: Minimum retention for repurpose to tie growth | B12: =IFERROR(1 - $B$8/($B$9*$B$7),"") -> 0.16386469 | C12: =IFERROR(1 - $C$8/($C$9*$C$7),"") -> -0.04943649
A14: Notes:
A15: Baseline must be a repurpose scenario (A1/A2).
A16: mᵗ uses YearMap (Aid + Override_if_on + Uplift − VarUnit$ − Growth_overhead).
A17: Sᵗ = fixed savings credited (Echo+Pima) minus retention overhead (Retained_ADM × h).
A18: N* and r* are shown for FY2026 (transition year) and FY2030 (steady state).

Sheet Summary_Figures
B1: Base (for comparison): | C1: E1_StatusQuo_Decline | N1: Chart titles
N2: ="(Comparison) Change in ops net $ by scenario compared to "&C1&" (Positive = savings)" -> (Comparison) Change in ops net $ by scenario compared to E1_StatusQuo_Decline (Positive = savings)
N3: ="(Nominal) One-time capital (FY26) & Average 5-yr net ops $ by scenario" -> (Nominal) One-time capital (FY26) & Average 5-yr net ops $ by scenario
A4: Scenario key | B4: Scenario | C4: One-time Capital (FY26) | D4: Net FY26 Operational $ | E4: Net FY28 Operational $ | F4: Net FY30 Operational $ | G4: AVG 5-yr net operational $ | H4: Displaced students | I4: Served students FY30 | J4: Δ vs Base (FY2030 Net) | K4: Δ vs Base (5-yr Avg Net)
A5: =LEFT(B5, 2) -> F1 | B5: F1_CUSTOM1 | C5: =SUMIFS(Capital_Summary!$H$4:$H$83, Capital_Summary!$A$4:$A$83, B5, Capital_Summary!$B$4:$B$83, "FY2026")*-1 -> 0 | D5: =SUMIFS(MultiYear_ProForma!$AF$2:$AF$66, MultiYear_ProForma!$B$2:$B$66, B5, MultiYear_ProForma!$C$2:$C$66, "FY2026") -> -459335.03 | E5: =SUMIFS(MultiYear_ProForma!$AF$2:$AF$66, MultiYear_ProForma!$B$2:$B$66, B5, MultiYear_ProForma!$C$2:$C$66, "FY2028") -> -482588.87 | F5: =SUMIFS(MultiYear_ProForma!$AF$2:$AF$66, MultiYear_ProForma!$B$2:$B$66, B5, MultiYear_ProForma!$C$2:$C$66, "FY2030") -> -507019.93 | G5: =(SUMIFS(MultiYear_ProForma!$AF$2:$AF$66, MultiYear_ProForma!$B$2:$B$66, B5, MultiYear_ProForma!$C$2:$C$66, "FY2026")+SUMIFS(MultiYear_ProForma!$AF$2:$AF$66, MultiYear_ProForma!$B$2:$B$66, B5, MultiYear_ProForma!$C$2:$C$66, "FY2027")+SUMIFS(MultiYear_ProForma!$AF$2:$AF$66, MultiYear_ProForma!$B$2:$B$66, B5, MultiYear_ProForma!$C$2:$C$66, "FY2028")+SUMIFS(MultiYear_ProForma!$AF$2:$AF$66, MultiYear_ProForma!$B$2:$B$66, B5, MultiYear_ProForma!$C$2:$C$66, "FY2029")+SUMIFS(MultiYear_ProForma!$AF$2:$AF$66, MultiYear_ProForma!$B$2:$B$66, B5, MultiYear_ProForma!$C$2:$C$66, "FY2030"))/5 -> -482883.16 | H5: =SUMIFS(MultiYear_ProForma!$N$2:$N$66, MultiYear_ProForma!$B$2:$B$66, B5, MultiYear_ProForma!$C$2:$C$66, "FY2026") -> 0 | I5: =SUMIFS(MultiYear_ProForma!$AC$2:$AC$66, MultiYear_ProForma!$B$2:$B$66, B5, MultiYear_ProForma!$C$2:$C$66, "FY2030") -> 553 | J5: =F5-(VLOOKUP($C$1,$B$5:$G$17,5, 0)) -> 217760.01 | K5: =G5-(VLOOKUP($C$1,$B$5:$I$17,6, 0)) -> 107303.43
A6: =LEFT(B6, 2) -> E3 | B6: E3_StatusQuo_Targets | C6: =SUMIFS(Capital_Summary!$H$4:$H$83, Capital_Summary!$A$4:$A$83, B6, Capital_Summary!$B$4:$B$83, "FY2026")*-1 -> 0 | D6: =SUMIFS(MultiYear_ProForma!$AF$2:$AF$66, MultiYear_ProForma!$B$2:$B$66, B6, MultiYear_ProForma!$C$2:$C$66, "FY2030") -> 331651 | E6: =SUMIFS(MultiYear_ProForma!$AF$2:$AF$66, MultiYear_ProForma!$B$2:$B$66, B6, MultiYear_ProForma!$C$2:$C$66, "FY2028") -> 310953.37 | F6: =SUMIFS(MultiYear_ProForma!$AF$2:$AF$66, MultiYear_ProForma!$B$2:$B$66, B6, MultiYear_ProForma!$C$2:$C$66, "FY2030") -> 331651 | G6: =(SUMIFS(MultiYear_ProForma!$AF$2:$AF$66, MultiYear_ProForma!$B$2:$B$66, B6, MultiYear_ProForma!$C$2:$C$66, "FY2026")+SUMIFS(MultiYear_ProForma!$AF$2:$AF$66, MultiYear_ProForma!$B$2:$B$66, B6, MultiYear_ProForma!$C$2:$C$66, "FY2027")+SUMIFS(MultiYear_ProForma!$AF$2:$AF$66, MultiYear_ProForma!$B$2:$B$66, B6, MultiYear_ProForma!$C$2:$C$66, "FY2028")+SUMIFS(MultiYear_ProForma!$AF$2:$AF$66, MultiYear_ProForma!$B$2:$B$66, B6, MultiYear_ProForma!$C$2:$C$66, "FY2029")+SUMIFS(MultiYear_ProForma!$AF$2:$AF$66, MultiYear_ProForma!$B$2:$B$66, B6, MultiYear_ProForma!$C$2:$C$66, "FY2030"))/5 -> 159301.11 | H6: =SUMIFS(MultiYear_ProForma!$N$2:$N$66, MultiYear_ProForma!$B$2:$B$66, B6, MultiYear_ProForma!$C$2:$C$66, "FY2026") -> 0 | I6: =SUMIFS(MultiYear_ProForma!$AC$2:$AC$66, MultiYear_ProForma!$B$2:$B$66, B6, MultiYear_ProForma!$C$2:$C$66, "FY2030") -> 628 | J6: =F6-(VLOOKUP($C$1,$B$5:$G$17,5, 0)) -> 1056430.9 | K6: =G6-(VLOOKUP($C$1,$B$5:$I$17,6, 0)) -> 749487.71
A7: =LEFT(B7, 2) -> D3 | B7: D3_CoLocation_Echo_Targets | C7: =SUMIFS(Capital_Summary!$H$4:$H$83, Capital_Summary!$A$4:$A$83, B7, Capital_Summary!$B$4:$B$83, "FY2026")*-1 -> 0 | D7: =SUMIFS(MultiYear_ProForma!$AF$2:$AF$66, MultiYear_ProForma!$B$2:$B$66, B7, MultiYear_ProForma!$C$2:$C$66, "FY2030") -> 412099.97 | E7: =SUMIFS(MultiYear_ProForma!$AF$2:$AF$66, MultiYear_ProForma!$B$2:$B$66, B7, MultiYear_ProForma!$C$2:$C$66, "FY2028") -> 389098.13 | F7: =SUMIFS(MultiYear_ProForma!$AF$2:$AF$66, MultiYear_ProForma!$B$2:$B$66, B7, MultiYear_ProForma!$C$2:$C$66, "FY2030") -> 412099.97 | G7: =(SUMIFS(MultiYear_ProForma!$AF$2:$AF$66, MultiYear_ProForma!$B$2:$B$66, B7, MultiYear_ProForma!$C$2:$C$66, "FY2026")+SUMIFS(MultiYear_ProForma!$AF$2:$AF$66, MultiYear_ProForma!$B$2:$B$66, B7, MultiYear_ProForma!$C$2:$C$66, "FY2027")+SUMIFS(MultiYear_ProForma!$AF$2:$AF$66, MultiYear_ProForma!$B$2:$B$66, B7, MultiYear_ProForma!$C$2:$C$66, "FY2028")+SUMIFS(MultiYear_ProForma!$AF$2:$AF$66, MultiYear_ProForma!$B$2:$B$66, B7, MultiYear_ProForma!$C$2:$C$66, "FY2029")+SUMIFS(MultiYear_ProForma!$AF$2:$AF$66, MultiYear_ProForma!$B$2:$B$66, B7, MultiYear_ProForma!$C$2:$C$66, "FY2030"))/5 -> 288107.49 | H7: =SUMIFS(MultiYear_ProForma!$N$2:$N$66, MultiYear_ProForma!$B$2:$B$66, B7, MultiYear_ProForma!$C$2:$C$66, "FY2026") -> 0 | I7: =SUMIFS(MultiYear_ProForma!$AC$2:$AC$66, MultiYear_ProForma!$B$2:$B$66, B7, MultiYear_ProForma!$C$2:$C$66, "FY2030") -> 603 | J7: =F7-(VLOOKUP($C$1,$B$5:$G$17,5, 0)) -> 1136879.9 | K7: =G7-(VLOOKUP($C$1,$B$5:$I$17,6, 0)) -> 878294.09
A8: =LEFT(B8, 2) -> D1 | B8: D1_Grow_Both_Targets | C8: =SUMIFS(Capital_Summary!$H$4:$H$83, Capital_Summary!$A$4:$A$83, B8, Capital_Summary!$B$4:$B$83, "FY2026")*-1 -> -2000000 | D8: =SUMIFS(MultiYear_ProForma!$AF$2:$AF$66, MultiYear_ProForma!$B$2:$B$66, B8, MultiYear_ProForma!$C$2:$C$66, "FY2030") -> 1170321.9 | E8: =SUMIFS(MultiYear_ProForma!$AF$2:$AF$66, MultiYear_ProForma!$B$2:$B$66, B8, MultiYear_ProForma!$C$2:$C$66, "FY2028") -> 1104495.6 | F8: =SUMIFS(MultiYear_ProForma!$AF$2:$AF$66, MultiYear_ProForma!$B$2:$B$66, B8, MultiYear_ProForma!$C$2:$C$66, "FY2030") -> 1170321.9 | G8: =(SUMIFS(MultiYear_ProForma!$AF$2:$AF$66, MultiYear_ProForma!$B$2:$B$66, B8, MultiYear_ProForma!$C$2:$C$66, "FY2026")+SUMIFS(MultiYear_ProForma!$AF$2:$AF$66, MultiYear_ProForma!$B$2:$B$66, B8, MultiYear_ProForma!$C$2:$C$66, "FY2027")+SUMIFS(MultiYear_ProForma!$AF$2:$AF$66, MultiYear_ProForma!$B$2:$B$66, B8, MultiYear_ProForma!$C$2:$C$66, "FY2028")+SUMIFS(MultiYear_ProForma!$AF$2:$AF$66, MultiYear_ProForma!$B$2:$B$66, B8, MultiYear_ProForma!$C$2:$C$66, "FY2029")+SUMIFS(MultiYear_ProForma!$AF$2:$AF$66, MultiYear_ProForma!$B$2:$B$66, B8, MultiYear_ProForma!$C$2:$C$66, "FY2030"))/5 -> 801485.39 | H8: =SUMIFS(MultiYear_ProForma!$N$2:$N$66, MultiYear_ProForma!$B$2:$B$66, B8, MultiYear_ProForma!$C$2:$C$66, "FY2026") -> 0 | I8: =SUMIFS(MultiYear_ProForma!$AC$2:$AC$66, MultiYear_ProForma!$B$2:$B$66, B8, MultiYear_ProForma!$C$2:$C$66, "FY2030") -> 703 | J8: =F8-(VLOOKUP($C$1,$B$5:$G$17,5, 0)) -> 1895101.9 | K8: =G8-(VLOOKUP($C$1,$B$5:$I$17,6, 0)) -> 1391672
A9: =LEFT(B9, 2) -> E2 | B9: E2_StatusQuo_Steady | C9: =SUMIFS(Capital_Summary!$H$4:$H$83, Capital_Summary!$A$4:$A$83, B9, Capital_Summary!$B$4:$B$83, "FY2026")*-1 -> 0 | D9: =SUMIFS(MultiYear_ProForma!$AF$2:$AF$66, MultiYear_ProForma!$B$2:$B$66, B9, MultiYear_ProForma!$C$2:$C$66, "FY2030") -> -507019.93 | E9: =SUMIFS(MultiYear_ProForma!$AF$2:$AF$66, MultiYear_ProForma!$B$2:$B$66, B9, MultiYear_ProForma!$C$2:$C$66, "FY2028") -> -482588.87 | F9: =SUMIFS(MultiYear_ProForma!$AF$2:$AF$66, MultiYear_ProForma!$B$2:$B$66, B9, MultiYear_ProForma!$C$2:$C$66, "FY2030") -> -507019.93 | G9: =(SUMIFS(MultiYear_ProForma!$AF$2:$AF$66, MultiYear_ProForma!$B$2:$B$66, B9, MultiYear_ProForma!$C$2:$C$66, "FY2026")+SUMIFS(MultiYear_ProForma!$AF$2:$AF$66, MultiYear_ProForma!$B$2:$B$66, B9, MultiYear_ProForma!$C$2:$C$66, "FY2027")+SUMIFS(MultiYear_ProForma!$AF$2:$AF$66, MultiYear_ProForma!$B$2:$B$66, B9, MultiYear_ProForma!$C$2:$C$66, "FY2028")+SUMIFS(MultiYear_ProForma!$AF$2:$AF$66, MultiYear_ProForma!$B$2:$B$66, B9, MultiYear_ProForma!$C$2:$C$66, "FY2029")+SUMIFS(MultiYear_ProForma!$AF$2:$AF$66, MultiYear_ProForma!$B$2:$B$66, B9, MultiYear_ProForma!$C$2:$C$66, "FY2030"))/5 -> -482883.16 | H9: =SUMIFS(MultiYear_ProForma!$N$2:$N$66, MultiYear_ProForma!$B$2:$B$66, B9, MultiYear_ProForma!$C$2:$C$66, "FY2026") -> 0 | I9: =SUMIFS(MultiYear_ProForma!$AC$2:$AC$66, MultiYear_ProForma!$B$2:$B$66, B9, MultiYear_ProForma!$C$2:$C$66, "FY2030") -> 553 | J9: =F9-(VLOOKUP($C$1,$B$5:$G$17,5, 0)) -> 217760.01 | K9: =G9-(VLOOKUP($C$1,$B$5:$I$17,6, 0)) -> 107303.43
A10: =LEFT(B10, 2) -> D2 | B10: D2_EchoGHubRamp_PimaTargets | C10: =SUMIFS(Capital_Summary!$H$4:$H$83, Capital_Summary!$A$4:$A$83, B10, Capital_Summary!$B$4:$B$83, "FY2026")*-1 -> -800000 | D10: =SUMIFS(MultiYear_ProForma!$AF$2:$AF$66, MultiYear_ProForma!$B$2:$B$66, B10, MultiYear_ProForma!$C$2:$C$66, "FY2030") -> 890764.96 | E10: =SUMIFS(MultiYear_ProForma!$AF$2:$AF$66, MultiYear_ProForma!$B$2:$B$66, B10, MultiYear_ProForma!$C$2:$C$66, "FY2028") -> 839981.52 | F10: =SUMIFS(MultiYear_ProForma!$AF$2:$AF$66, MultiYear_ProForma!$B$2:$B$66, B10, MultiYear_ProForma!$C$2:$C$66, "FY2030") -> 890764.96 | G10: =(SUMIFS(MultiYear_ProForma!$AF$2:$AF$66, MultiYear_ProForma!$B$2:$B$66, B10, MultiYear_ProForma!$C$2:$C$66, "FY2026")+SUMIFS(MultiYear_ProForma!$AF$2:$AF$66, MultiYear_ProForma!$B$2:$B$66, B10, MultiYear_ProForma!$C$2:$C$66, "FY2027")+SUMIFS(MultiYear_ProForma!$AF$2:$AF$66, MultiYear_ProForma!$B$2:$B$66, B10, MultiYear_ProForma!$C$2:$C$66, "FY2028")+SUMIFS(MultiYear_ProForma!$AF$2:$AF$66, MultiYear_ProForma!$B$2:$B$66, B10, MultiYear_ProForma!$C$2:$C$66, "FY2029")+SUMIFS(MultiYear_ProForma!$AF$2:$AF$66, MultiYear_ProForma!$B$2:$B$66, B10, MultiYear_ProForma!$C$2:$C$66, "FY2030"))/5 -> 587423.97 | H10: =SUMIFS(MultiYear_ProForma!$N$2:$N$66, MultiYear_ProForma!$B$2:$B$66, B10, MultiYear_ProForma!$C$2:$C$66, "FY2026") -> 0 | I10: =SUMIFS(MultiYear_ProForma!$AC$2:$AC$66, MultiYear_ProForma!$B$2:$B$66, B10, MultiYear_ProForma!$C$2:$C$66, "FY2030") -> 678 | J10: =F10-(VLOOKUP($C$1,$B$5:$G$17,5, 0)) -> 1615544.9 | K10: =G10-(VLOOKUP($C$1,$B$5:$I$17,6, 0)) -> 1177610.6
A11: =LEFT(B11, 2) -> A2 | B11: A2_Repurpose_Both_lease | C11: =SUMIFS(Capital_Summary!$H$4:$H$83, Capital_Summary!$A$4:$A$83, B11, Capital_Summary!$B$4:$B$83, "FY2026")*-1 -> -1600000 | D11: =SUMIFS(MultiYear_ProForma!$AF$2:$AF$66, MultiYear_ProForma!$B$2:$B$66, B11, MultiYear_ProForma!$C$2:$C$66, "FY2030") -> 1585320 | E11: =SUMIFS(MultiYear_ProForma!$AF$2:$AF$66, MultiYear_ProForma!$B$2:$B$66, B11, MultiYear_ProForma!$C$2:$C$66, "FY2028") -> 1223701.2 | F11: =SUMIFS(MultiYear_ProForma!$AF$2:$AF$66, MultiYear_ProForma!$B$2:$B$66, B11, MultiYear_ProForma!$C$2:$C$66, "FY2030") -> 1585320 | G11: =(SUMIFS(MultiYear_ProForma!$AF$2:$AF$66, MultiYear_ProForma!$B$2:$B$66, B11, MultiYear_ProForma!$C$2:$C$66, "FY2026")+SUMIFS(MultiYear_ProForma!$AF$2:$AF$66, MultiYear_ProForma!$B$2:$B$66, B11, MultiYear_ProForma!$C$2:$C$66, "FY2027")+SUMIFS(MultiYear_ProForma!$AF$2:$AF$66, MultiYear_ProForma!$B$2:$B$66, B11, MultiYear_ProForma!$C$2:$C$66, "FY2028")+SUMIFS(MultiYear_ProForma!$AF$2:$AF$66, MultiYear_ProForma!$B$2:$B$66, B11, MultiYear_ProForma!$C$2:$C$66, "FY2029")+SUMIFS(MultiYear_ProForma!$AF$2:$AF$66, MultiYear_ProForma!$B$2:$B$66, B11, MultiYear_ProForma!$C$2:$C$66, "FY2030"))/5 -> 1213035.9 | H11: =SUMIFS(MultiYear_ProForma!$N$2:$N$66, MultiYear_ProForma!$B$2:$B$66, B11, MultiYear_ProForma!$C$2:$C$66, "FY2026") -> 553 | I11: =SUMIFS(MultiYear_ProForma!$AC$2:$AC$66, MultiYear_ProForma!$B$2:$B$66, B11, MultiYear_ProForma!$C$2:$C$66, "FY2030") -> 405.8 | J11: =F11-(VLOOKUP($C$1,$B$5:$G$17,5, 0)) -> 2310100 | K11: =G11-(VLOOKUP($C$1,$B$5:$I$17,6, 0)) -> 1803222.5
A12: =LEFT(B12, 2) -> A1 | B12: A1_Repurpose_Both_ops | C12: =SUMIFS(Capital_Summary!$H$4:$H$83, Capital_Summary!$A$4:$A$83, B12, Capital_Summary!$B$4:$B$83, "FY2026")*-1 -> -2400000 | D12: =SUMIFS(MultiYear_ProForma!$AF$2:$AF$66, MultiYear_ProForma!$B$2:$B$66, B12, MultiYear_ProForma!$C$2:$C$66, "FY2030") -> 922909.09 | E12: =SUMIFS(MultiYear_ProForma!$AF$2:$AF$66, MultiYear_ProForma!$B$2:$B$66, B12, MultiYear_ProForma!$C$2:$C$66, "FY2028") -> 593208.97 | F12: =SUMIFS(MultiYear_ProForma!$AF$2:$AF$66, MultiYear_ProForma!$B$2:$B$66, B12, MultiYear_ProForma!$C$2:$C$66, "FY2030") -> 922909.09 | G12: =(SUMIFS(MultiYear_ProForma!$AF$2:$AF$66, MultiYear_ProForma!$B$2:$B$66, B12, MultiYear_ProForma!$C$2:$C$66, "FY2026")+SUMIFS(MultiYear_ProForma!$AF$2:$AF$66, MultiYear_ProForma!$B$2:$B$66, B12, MultiYear_ProForma!$C$2:$C$66, "FY2027")+SUMIFS(MultiYear_ProForma!$AF$2:$AF$66, MultiYear_ProForma!$B$2:$B$66, B12, MultiYear_ProForma!$C$2:$C$66, "FY2028")+SUMIFS(MultiYear_ProForma!$AF$2:$AF$66, MultiYear_ProForma!$B$2:$B$66, B12, MultiYear_ProForma!$C$2:$C$66, "FY2029")+SUMIFS(MultiYear_ProForma!$AF$2:$AF$66, MultiYear_ProForma!$B$2:$B$66, B12, MultiYear_ProForma!$C$2:$C$66, "FY2030"))/5 -> 552153.61 | H12: =SUMIFS(MultiYear_ProForma!$N$2:$N$66, MultiYear_ProForma!$B$2:$B$66, B12, MultiYear_ProForma!$C$2:$C$66, "FY2026") -> 553 | I12: =SUMIFS(MultiYear_ProForma!$AC$2:$AC$66, MultiYear_ProForma!$B$2:$B$66, B12, MultiYear_ProForma!$C$2:$C$66, "FY2030") -> 405.8 | J12: =F12-(VLOOKUP($C$1,$B$5:$G$17,5, 0)) -> 1647689 | K12: =G12-(VLOOKUP($C$1,$B$5:$I$17,6, 0)) -> 1142340.2
A13: =LEFT(B13, 2) -> B2 | B13: B2_Repurpose_Echo_lease_PimaTargets | C13: =SUMIFS(Capital_Summary!$H$4:$H$83, Capital_Summary!$A$4:$A$83, B13, Capital_Summary!$B$4:$B$83, "FY2026")*-1 -> -800000 | D13: =SUMIFS(MultiYear_ProForma!$AF$2:$AF$66, MultiYear_ProForma!$B$2:$B$66, B13, MultiYear_ProForma!$C$2:$C$66, "FY2030") -> 302948.49 | E13: =SUMIFS(MultiYear_ProForma!$AF$2:$AF$66, MultiYear_ProForma!$B$2:$B$66, B13, MultiYear_ProForma!$C$2:$C$66, "FY2028") -> 166608.27 | F13: =SUMIFS(MultiYear_ProForma!$AF$2:$AF$66, MultiYear_ProForma!$B$2:$B$66, B13, MultiYear_ProForma!$C$2:$C$66, "FY2030") -> 302948.49 | G13: =(SUMIFS(MultiYear_ProForma!$AF$2:$AF$66, MultiYear_ProForma!$B$2:$B$66, B13, MultiYear_ProForma!$C$2:$C$66, "FY2026")+SUMIFS(MultiYear_ProForma!$AF$2:$AF$66, MultiYear_ProForma!$B$2:$B$66, B13, MultiYear_ProForma!$C$2:$C$66, "FY2027")+SUMIFS(MultiYear_ProForma!$AF$2:$AF$66, MultiYear_ProForma!$B$2:$B$66, B13, MultiYear_ProForma!$C$2:$C$66, "FY2028")+SUMIFS(MultiYear_ProForma!$AF$2:$AF$66, MultiYear_ProForma!$B$2:$B$66, B13, MultiYear_ProForma!$C$2:$C$66, "FY2029")+SUMIFS(MultiYear_ProForma!$AF$2:$AF$66, MultiYear_ProForma!$B$2:$B$66, B13, MultiYear_ProForma!$C$2:$C$66, "FY2030"))/5 -> 162769.54 | H13: =SUMIFS(MultiYear_ProForma!$N$2:$N$66, MultiYear_ProForma!$B$2:$B$66, B13, MultiYear_ProForma!$C$2:$C$66, "FY2026") -> 257 | I13: =SUMIFS(MultiYear_ProForma!$AC$2:$AC$66, MultiYear_ProForma!$B$2:$B$66, B13, MultiYear_ProForma!$C$2:$C$66, "FY2030") -> 450.2 | J13: =F13-(VLOOKUP($C$1,$B$5:$G$17,5, 0)) -> 1027728.4 | K13: =G13-(VLOOKUP($C$1,$B$5:$I$17,6, 0)) -> 752956.13
A14: =LEFT(B14, 2) -> B1 | B14: B1_Repurpose_Echo_ops_PimaTargets | C14: =SUMIFS(Capital_Summary!$H$4:$H$83, Capital_Summary!$A$4:$A$83, B14, Capital_Summary!$B$4:$B$83, "FY2026")*-1 -> -1200000 | D14: =SUMIFS(MultiYear_ProForma!$AF$2:$AF$66, MultiYear_ProForma!$B$2:$B$66, B14, MultiYear_ProForma!$C$2:$C$66, "FY2030") -> 408845.42 | E14: =SUMIFS(MultiYear_ProForma!$AF$2:$AF$66, MultiYear_ProForma!$B$2:$B$66, B14, MultiYear_ProForma!$C$2:$C$66, "FY2028") -> 265075.52 | F14: =SUMIFS(MultiYear_ProForma!$AF$2:$AF$66, MultiYear_ProForma!$B$2:$B$66, B14, MultiYear_ProForma!$C$2:$C$66, "FY2030") -> 408845.42 | G14: =(SUMIFS(MultiYear_ProForma!$AF$2:$AF$66, MultiYear_ProForma!$B$2:$B$66, B14, MultiYear_ProForma!$C$2:$C$66, "FY2026")+SUMIFS(MultiYear_ProForma!$AF$2:$AF$66, MultiYear_ProForma!$B$2:$B$66, B14, MultiYear_ProForma!$C$2:$C$66, "FY2027")+SUMIFS(MultiYear_ProForma!$AF$2:$AF$66, MultiYear_ProForma!$B$2:$B$66, B14, MultiYear_ProForma!$C$2:$C$66, "FY2028")+SUMIFS(MultiYear_ProForma!$AF$2:$AF$66, MultiYear_ProForma!$B$2:$B$66, B14, MultiYear_ProForma!$C$2:$C$66, "FY2029")+SUMIFS(MultiYear_ProForma!$AF$2:$AF$66, MultiYear_ProForma!$B$2:$B$66, B14, MultiYear_ProForma!$C$2:$C$66, "FY2030"))/5 -> 172443.45 | H14: =SUMIFS(MultiYear_ProForma!$N$2:$N$66, MultiYear_ProForma!$B$2:$B$66, B14, MultiYear_ProForma!$C$2:$C$66, "FY2026") -> 257 | I14: =SUMIFS(MultiYear_ProForma!$AC$2:$AC$66, MultiYear_ProForma!$B$2:$B$66, B14, MultiYear_ProForma!$C$2:$C$66, "FY2030") -> 487.2 | J14: =F14-(VLOOKUP($C$1,$B$5:$G$17,5, 0)) -> 1133625.4 | K14: =G14-(VLOOKUP($C$1,$B$5:$I$17,6, 0)) -> 762630.04
A15: =LEFT(B15, 2) -> C2 | B15: C2_Repurpose_Pima_lease_EchoGHub_EchoTargets | C15: =SUMIFS(Capital_Summary!$H$4:$H$83, Capital_Summary!$A$4:$A$83, B15, Capital_Summary!$B$4:$B$83, "FY2026")*-1 -> -1600000 | D15: =SUMIFS(MultiYear_ProForma!$AF$2:$AF$66, MultiYear_ProForma!$B$2:$B$66, B15, MultiYear_ProForma!$C$2:$C$66, "FY2030") -> 775351.61 | E15: =SUMIFS(MultiYear_ProForma!$AF$2:$AF$66, MultiYear_ProForma!$B$2:$B$66, B15, MultiYear_ProForma!$C$2:$C$66, "FY2028") -> 574504.1 | F15: =SUMIFS(MultiYear_ProForma!$AF$2:$AF$66, MultiYear_ProForma!$B$2:$B$66, B15, MultiYear_ProForma!$C$2:$C$66, "FY2030") -> 775351.61 | G15: =(SUMIFS(MultiYear_ProForma!$AF$2:$AF$66, MultiYear_ProForma!$B$2:$B$66, B15, MultiYear_ProForma!$C$2:$C$66, "FY2026")+SUMIFS(MultiYear_ProForma!$AF$2:$AF$66, MultiYear_ProForma!$B$2:$B$66, B15, MultiYear_ProForma!$C$2:$C$66, "FY2027")+SUMIFS(MultiYear_ProForma!$AF$2:$AF$66, MultiYear_ProForma!$B$2:$B$66, B15, MultiYear_ProForma!$C$2:$C$66, "FY2028")+SUMIFS(MultiYear_ProForma!$AF$2:$AF$66, MultiYear_ProForma!$B$2:$B$66, B15, MultiYear_ProForma!$C$2:$C$66, "FY2029")+SUMIFS(MultiYear_ProForma!$AF$2:$AF$66, MultiYear_ProForma!$B$2:$B$66, B15, MultiYear_ProForma!$C$2:$C$66, "FY2030"))/5 -> 567383.24 | H15: =SUMIFS(MultiYear_ProForma!$N$2:$N$66, MultiYear_ProForma!$B$2:$B$66, B15, MultiYear_ProForma!$C$2:$C$66, "FY2026") -> 296 | I15: =SUMIFS(MultiYear_ProForma!$AC$2:$AC$66, MultiYear_ProForma!$B$2:$B$66, B15, MultiYear_ProForma!$C$2:$C$66, "FY2030") -> 508.6 | J15: =F15-(VLOOKUP($C$1,$B$5:$G$17,5, 0)) -> 1500131.5 | K15: =G15-(VLOOKUP($C$1,$B$5:$I$17,6, 0)) -> 1157569.8
A16: =LEFT(B16, 2) -> C1 | B16: C1_Repurpose_Pima_ops_EchoGHub_EchoTargets | C16: =SUMIFS(Capital_Summary!$H$4:$H$83, Capital_Summary!$A$4:$A$83, B16, Capital_Summary!$B$4:$B$83, "FY2026")*-1 -> -2000000 | D16: =SUMIFS(MultiYear_ProForma!$AF$2:$AF$66, MultiYear_ProForma!$B$2:$B$66, B16, MultiYear_ProForma!$C$2:$C$66, "FY2030") -> 979902.02 | E16: =SUMIFS(MultiYear_ProForma!$AF$2:$AF$66, MultiYear_ProForma!$B$2:$B$66, B16, MultiYear_ProForma!$C$2:$C$66, "FY2028") -> 766053.57 | F16: =SUMIFS(MultiYear_ProForma!$AF$2:$AF$66, MultiYear_ProForma!$B$2:$B$66, B16, MultiYear_ProForma!$C$2:$C$66, "FY2030") -> 979902.02 | G16: =(SUMIFS(MultiYear_ProForma!$AF$2:$AF$66, MultiYear_ProForma!$B$2:$B$66, B16, MultiYear_ProForma!$C$2:$C$66, "FY2026")+SUMIFS(MultiYear_ProForma!$AF$2:$AF$66, MultiYear_ProForma!$B$2:$B$66, B16, MultiYear_ProForma!$C$2:$C$66, "FY2027")+SUMIFS(MultiYear_ProForma!$AF$2:$AF$66, MultiYear_ProForma!$B$2:$B$66, B16, MultiYear_ProForma!$C$2:$C$66, "FY2028")+SUMIFS(MultiYear_ProForma!$AF$2:$AF$66, MultiYear_ProForma!$B$2:$B$66, B16, MultiYear_ProForma!$C$2:$C$66, "FY2029")+SUMIFS(MultiYear_ProForma!$AF$2:$AF$66, MultiYear_ProForma!$B$2:$B$66, B16, MultiYear_ProForma!$C$2:$C$66, "FY2030"))/5 -> 641758.89 | H16: =SUMIFS(MultiYear_ProForma!$N$2:$N$66, MultiYear_ProForma!$B$2:$B$66, B16, MultiYear_ProForma!$C$2:$C$66, "FY2026") -> 295.66667 | I16: =SUMIFS(MultiYear_ProForma!$AC$2:$AC$66, MultiYear_ProForma!$B$2:$B$66, B16, MultiYear_ProForma!$C$2:$C$66, "FY2030") -> 558.6 | J16: =F16-(VLOOKUP($C$1,$B$5:$G$17,5, 0)) -> 1704682 | K16: =G16-(VLOOKUP($C$1,$B$5:$I$17,6, 0)) -> 1231945.5
A17: =LEFT(B17, 2) -> E1 | B17: E1_StatusQuo_Decline | C17: =SUMIFS(Capital_Summary!$H$4:$H$83, Capital_Summary!$A$4:$A$83, B17, Capital_Summary!$B$4:$B$83, "FY2026")*-1 -> 0 | D17: =SUMIFS(MultiYear_ProForma!$AF$2:$AF$66, MultiYear_ProForma!$B$2:$B$66, B17, MultiYear_ProForma!$C$2:$C$66, "FY2030") -> -724779.94 | E17: =SUMIFS(MultiYear_ProForma!$AF$2:$AF$66, MultiYear_ProForma!$B$2:$B$66, B17, MultiYear_ProForma!$C$2:$C$66, "FY2028") -> -588315.82 | F17: =SUMIFS(MultiYear_ProForma!$AF$2:$AF$66, MultiYear_ProForma!$B$2:$B$66, B17, MultiYear_ProForma!$C$2:$C$66, "FY2030") -> -724779.94 | G17: =(SUMIFS(MultiYear_ProForma!$AF$2:$AF$66, MultiYear_ProForma!$B$2:$B$66, B17, MultiYear_ProForma!$C$2:$C$66, "FY2026")+SUMIFS(MultiYear_ProForma!$AF$2:$AF$66, MultiYear_ProForma!$B$2:$B$66, B17, MultiYear_ProForma!$C$2:$C$66, "FY2027")+SUMIFS(MultiYear_ProForma!$AF$2:$AF$66, MultiYear_ProForma!$B$2:$B$66, B17, MultiYear_ProForma!$C$2:$C$66, "FY2028")+SUMIFS(MultiYear_ProForma!$AF$2:$AF$66, MultiYear_ProForma!$B$2:$B$66, B17, MultiYear_ProForma!$C$2:$C$66, "FY2029")+SUMIFS(MultiYear_ProForma!$AF$2:$AF$66, MultiYear_ProForma!$B$2:$B$66, B17, MultiYear_ProForma!$C$2:$C$66, "FY2030"))/5 -> -590186.59 | H17: =SUMIFS(MultiYear_ProForma!$N$2:$N$66, MultiYear_ProForma!$B$2:$B$66, B17, MultiYear_ProForma!$C$2:$C$66, "FY2026") -> 0 | I17: =SUMIFS(MultiYear_ProForma!$AC$2:$AC$66, MultiYear_ProForma!$B$2:$B$66, B17, MultiYear_ProForma!$C$2:$C$66, "FY2030") -> 510.06959 | J17: =F17-(VLOOKUP($C$1,$B$5:$G$17,5, 0)) -> 0 | K17: =G17-(VLOOKUP($C$1,$B$5:$I$17,6, 0)) -> 0
B19: Note: Displaced = FY26; Served = FY30. Net = M&O − (Aid + Override + Uplift); showing one-time capital (fy26) as negative number for visualization purposes

Sheet Scenarios
A1: ScenarioKey | B1: Label | C1: Overlay | D1: CloseEcho | E1: ClosePima | F1: EchoShareDist | G1: ExtraSave | H1: Notes | I1: Overlay_FY26 | J1: Overlay_FY27 | K1: Overlay_FY28 | L1: Overlay_FY29 | M1: Overlay_FY30 | N1: Carry | O1: Growth_Echo | P1: Growth_Pima | Q1: Apply_Echo_Trend | R1: Apply_Pima_Trend
A2: F1_CUSTOM1 | B2: =Control_Center!B31 -> CUSTOM_KeepOpen_v1 | C2: =Control_Center!C31 -> 0 | D2: =Control_Center!D31 -> 0 | E2: =Control_Center!E31 -> 0 | F2: =Control_Center!F31 -> 0.5 | G2: =Control_Center!G31 -> 0 | H2: Baseline + outreach; no closures | I2: =C2/3 -> 0 | J2: =I2+C2/3 -> 0 | K2: =J2+C2/3 -> 0 | L2: =C2 -> 0 | M2: =C2 -> 0 | O2: None | P2: None | Q2: 0 | R2: 0
A3: E3_StatusQuo_Targets | B3: =Control_Center!B32 -> Echo & Pima open; uplift warm handoff effort (intra-SUSD); initiate cross-district marketing | C3: =Control_Center!C32 -> 75 | D3: =Control_Center!D32 -> 0 | E3: =Control_Center!E32 -> 0 | F3: =Control_Center!F32 -> 0.5 | G3: =Control_Center!G32 -> 0 | H3: Baseline + targets; no closures | I3: =C3/3 -> 25 | J3: =I3+C3/3 -> 50 | K3: =J3+C3/3 -> 75 | L3: =C3 -> 75 | M3: =C3 -> 75 | O3: None | P3: None | Q3: 0 | R3: 0
A4: D3_CoLocation_Echo_Targets | B4: =Control_Center!B33 -> Echo & Pima open; co-locate e.g. district teacher learning center at Echo; uplift warm handoff effort (intra-SUSD); initiate cross-district marketing | C4: =Control_Center!C33 -> 50 | D4: =Control_Center!D33 -> 0 | E4: =Control_Center!E33 -> 0 | F4: =Control_Center!F33 -> 0.5 | G4: =Control_Center!G33 -> 0.05 | H4: Shared‑use efficiencies later (no closure) | I4: =C4/3 -> 16.666667 | J4: =I4+C4/3 -> 33.333333 | K4: =J4+C4/3 -> 50 | L4: =C4 -> 50 | M4: =C4 -> 50 | O4: None | P4: None | Q4: 0 | R4: 0
A5: D1_Grow_Both_Targets | B5: =Control_Center!B34 -> Echo & Pima open; growth initiatives Echo (e.g. innovation) & Pima (e.g. arts); uplift warm handoff effort (intra-SUSD); initiate cross-district marketing | C5: =Control_Center!C34 -> 150 | D5: =Control_Center!D34 -> 0 | E5: =Control_Center!E34 -> 0 | F5: =Control_Center!F34 -> 0.5 | G5: =Control_Center!G34 -> 0 | H5: Baseline +100 overlay | I5: =C5/3 -> 50 | J5: =I5+C5/3 -> 100 | K5: =J5+C5/3 -> 150 | L5: =C5 -> 150 | M5: =C5 -> 150 | O5: Innov | P5: Arts | Q5: 0 | R5: 0
A6: E2_StatusQuo_Steady | B6: =Control_Center!B35 -> Echo & Pima open; no operational or strategic growth actions; no change in enrollment | C6: =Control_Center!C35 -> 0 | D6: =Control_Center!D35 -> 0 | E6: =Control_Center!E35 -> 0 | F6: =Control_Center!F35 -> 0.5 | G6: =Control_Center!G35 -> 0 | H6: Baseline +150 overlay | I6: =C6/3 -> 0 | J6: =I6+C6/3 -> 0 | K6: =J6+C6/3 -> 0 | L6: =C6 -> 0 | M6: =C6 -> 0 | O6: None | P6: None | Q6: 0 | R6: 0
A7: D2_EchoGHubRamp_PimaTargets | B7: =Control_Center!B36 -> Echo & Pima open; growth initiative Echo (e.g. innovation); no growth initiative Pima; uplift warm handoff effort (intra-SUSD); initiate cross-district marketing | C7: =Control_Center!C36 -> 125 | D7: =Control_Center!D36 -> 0 | E7: =Control_Center!E36 -> 0 | F7: =Control_Center!F36 -> 0.7 | G7: =Control_Center!G36 -> 0 | H7: Time‑phased ramp (+50,+100,+150 years 1–3) | I7: =C7/3 -> 41.666667 | J7: =I7+C7/3 -> 83.333333 | K7: =J7+C7/3 -> 125 | L7: =C7 -> 125 | M7: =C7 -> 125 | O7: Arts | P7: None | Q7: 0 | R7: 0
A8: A2_Repurpose_Both_lease | B8: =Control_Center!B37 -> Repurpose both Echo & Pima; lease both properties; fixed cost reduction rate, retention %, and transition cost assumptions are key drivers | C8: =Control_Center!C37 -> 0 | D8: =Control_Center!D37 -> 1 | E8: =Control_Center!E37 -> 1 | F8: =Control_Center!F37 -> 0.5 | G8: =Control_Center!G37 -> 0 | H8: Repurpose both; lease/sale glide | I8: =C8/3 -> 0 | J8: =I8+C8/3 -> 0 | K8: =J8+C8/3 -> 0 | L8: =C8 -> 0 | M8: =C8 -> 0 | N8: lease | O8: None | P8: None | Q8: 0 | R8: 0
A9: A1_Repurpose_Both_ops | B9: =Control_Center!B38 -> Repurpose both Echo & Pima; operationally convert both properties (e.g. early learning center); fixed cost reduction rate, retention %, and transition cost assumptions are key drivers | C9: =Control_Center!C38 -> 0 | D9: =Control_Center!D38 -> 1 | E9: =Control_Center!E38 -> 1 | F9: =Control_Center!F38 -> 0.5 | G9: =Control_Center!G38 -> 0 | H9: Repurpose both; operations carry | I9: =C9/3 -> 0 | J9: =I9+C9/3 -> 0 | K9: =J9+C9/3 -> 0 | L9: =C9 -> 0 | M9: =C9 -> 0 | N9: ops | O9: None | P9: None | Q9: 0 | R9: 0
A10: B2_Repurpose_Echo_lease_PimaTargets | B10: =Control_Center!B39 -> Repurpose ECHO (lease) + Status-Quo Pima + Pima Op Growth Targets | C10: =Control_Center!C39 -> 0 | D10: =Control_Center!D39 -> 1 | E10: =Control_Center!E39 -> 0 | F10: =Control_Center!F39 -> 0 | G10: =Control_Center!G39 -> 0 | H10: Repurpose Echo only; lease glide | I10: =C10/3 -> 0 | J10: =I10+C10/3 -> 0 | K10: =J10+C10/3 -> 0 | L10: =C10 -> 0 | M10: =C10 -> 0 | N10: lease | O10: None | P10: None | Q10: 0 | R10: 0
A11: B1_Repurpose_Echo_ops_PimaTargets | B11: =Control_Center!B40 -> Repurpose ECHO (ops) + Status-Quo Pima + Pima Op Growth Targets | C11: =Control_Center!C40 -> 37 | D11: =Control_Center!D40 -> 1 | E11: =Control_Center!E40 -> 0 | F11: =Control_Center!F40 -> 0 | G11: =Control_Center!G40 -> 0 | H11: Repurpose Echo only; ops carry | I11: =C11/3 -> 12.333333 | J11: =I11+C11/3 -> 24.666667 | K11: =J11+C11/3 -> 37 | L11: =C11 -> 37 | M11: =C11 -> 37 | N11: ops | O11: None | P11: None | Q11: 0 | R11: 0
A12: C2_Repurpose_Pima_lease_EchoGHub_EchoTargets | B12: =Control_Center!B41 -> Repurpose PIMA (lease) + Growth Hub @ Echo + Echo Op Growth Targets | C12: =Control_Center!C41 -> 0 | D12: =Control_Center!D41 -> 0 | E12: =Control_Center!E41 -> 1 | F12: =Control_Center!F41 -> 1 | G12: =Control_Center!G41 -> 0 | H12: Repurpose Pima only; lease glide | I12: =C12/3 -> 0 | J12: =I12+C12/3 -> 0 | K12: =J12+C12/3 -> 0 | L12: =C12 -> 0 | M12: =C12 -> 0 | N12: lease | O12: Arts | P12: None | Q12: 0 | R12: 0
A13: C1_Repurpose_Pima_ops_EchoGHub_EchoTargets | B13: =Control_Center!B42 -> Repurpose PIMA (ops) + Growth Hub @ Echo + Echo Op Growth Targets | C13: =Control_Center!C42 -> 50 | D13: =Control_Center!D42 -> 0 | E13: =Control_Center!E42 -> 1 | F13: =Control_Center!F42 -> 1 | G13: =Control_Center!G42 -> 0 | H13: Repurpose Pima only; ops carry | I13: =C13/3 -> 16.666667 | J13: =I13+C13/3 -> 33.333333 | K13: =J13+C13/3 -> 50 | L13: =C13 -> 50 | M13: =C13 -> 50 | N13: ops | O13: Arts | P13: None | Q13: 0 | R13: 0
A14: E1_StatusQuo_Decline | B14: Echo & Pima open; no operational or strategic growth actions; enrollment decline trend continues | C14: 0 | D14: 0 | E14: 0 | F14: 0 | G14: 0 | H14: Keep open but decline per district forecast | I14: =C14/3 -> 0 | J14: =I14+C14/3 -> 0 | K14: =J14+C14/3 -> 0 | L14: =C14 -> 0 | M14: =C14 -> 0 | O14: None | P14: None | Q14: 1 | R14: 1
A16: ScenarioKey | B16: Year | C16: Echo_ADM | D16: Pima_ADM | E16: Total_ADM | F16: VarUnit$ | G16: EchoFixed$ | H16: PimaFixed$ | I16: Key | O16: None | P16: None
A17: =A2 -> F1_CUSTOM1 | B17: FY2026 | C17: =IF(D2=1,0, BaselineCalc!$B$7 + ROUND(I2*F2,0)) -> 257 | D17: =IF(E2=1,0, BaselineCalc!$B$8 + I2 - ROUND(I2*F2,0)) -> 296 | E17: =C17+D17 -> 553 | F17: =YearMap!B2 -> 6414.5115 | G17: =YearMap!C2 -> 1404302.9 | H17: =YearMap!D2 -> 1617407.2 | I17: =A17&"|"&B17 -> F1_CUSTOM1|FY2026 | O17: None | P17: None
A18: =A2 -> F1_CUSTOM1 | B18: FY2027 | C18: =IF(D2=1,0, BaselineCalc!$B$7 + ROUND(J2*F2,0)) -> 257 | D18: =IF(E2=1,0, BaselineCalc!$B$8 + J2 - ROUND(J2*F2,0)) -> 296 | E18: =C18+D18 -> 553 | F18: =YearMap!B3 -> 6574.8743 | G18: =YearMap!C3 -> 1439410.4 | H18: =YearMap!D3 -> 1657842.4 | I18: =A18&"|"&B18 -> F1_CUSTOM1|FY2027 | O18: None | P18: None
A19: =A2 -> F1_CUSTOM1 | B19: FY2028 | C19: =IF(D2=1,0, BaselineCalc!$B$7 + ROUND(K2*F2,0)) -> 257 | D19: =IF(E2=1,0, BaselineCalc!$B$8 + K2 - ROUND(K2*F2,0)) -> 296 | E19: =C19+D19 -> 553 | F19: =YearMap!B4 -> 6739.2461 | G19: =YearMap!C4 -> 1475395.7 | H19: =YearMap!D4 -> 1699288.4 | I19: =A19&"|"&B19 -> F1_CUSTOM1|FY2028 | O19: None | P19: None
A20: =A2 -> F1_CUSTOM1 | B20: FY2029 | C20: =IF(D2=1,0, BaselineCalc!$B$7 + ROUND(L2*F2,0)) -> 257 | D20: =IF(E2=1,0, BaselineCalc!$B$8 + L2 - ROUND(L2*F2,0)) -> 296 | E20: =C20+D20 -> 553 | F20: =YearMap!B5 -> 6907.7273 | G20: =YearMap!C5 -> 1512280.6 | H20: =YearMap!D5 -> 1741770.6 | I20: =A20&"|"&B20 -> F1_CUSTOM1|FY2029 | O20: None | P20: None
A21: =A2 -> F1_CUSTOM1 | B21: FY2030 | C21: =IF(D2=1,0, BaselineCalc!$B$7 + ROUND(M2*F2,0)) -> 257 | D21: =IF(E2=1,0, BaselineCalc!$B$8 + M2 - ROUND(M2*F2,0)) -> 296 | E21: =C21+D21 -> 553 | F21: =YearMap!B6 -> 7080.4205 | G21: =YearMap!C6 -> 1550087.6 | H21: =YearMap!D6 -> 1785314.9 | I21: =A21&"|"&B21 -> F1_CUSTOM1|FY2030 | O21: None | P21: None
A22: =A3 -> E3_StatusQuo_Targets | B22: FY2026 | C22: =IF(D3=1,0, BaselineCalc!$B$7 + ROUND(I3*F3,0)) -> 270 | D22: =IF(E3=1,0, BaselineCalc!$B$8 + I3 - ROUND(I3*F3,0)) -> 308 | E22: =C22+D22 -> 578 | F22: =YearMap!B2 -> 6414.5115 | G22: =YearMap!C2 -> 1404302.9 | H22: =YearMap!D2 -> 1617407.2 | I22: =A22&"|"&B22 -> E3_StatusQuo_Targets|FY2026 | O22: None | P22: None
A23: =A3 -> E3_StatusQuo_Targets | B23: FY2027 | C23: =IF(D3=1,0, BaselineCalc!$B$7 + ROUND(J3*F3,0)) -> 282 | D23: =IF(E3=1,0, BaselineCalc!$B$8 + J3 - ROUND(J3*F3,0)) -> 321 | E23: =C23+D23 -> 603 | F23: =YearMap!B3 -> 6574.8743 | G23: =YearMap!C3 -> 1439410.4 | H23: =YearMap!D3 -> 1657842.4 | I23: =A23&"|"&B23 -> E3_StatusQuo_Targets|FY2027 | O23: None | P23: None
A24: =A3 -> E3_StatusQuo_Targets | B24: FY2028 | C24: =IF(D3=1,0, BaselineCalc!$B$7 + ROUND(K3*F3,0)) -> 295 | D24: =IF(E3=1,0, BaselineCalc!$B$8 + K3 - ROUND(K3*F3,0)) -> 333 | E24: =C24+D24 -> 628 | F24: =YearMap!B4 -> 6739.2461 | G24: =YearMap!C4 -> 1475395.7 | H24: =YearMap!D4 -> 1699288.4 | I24: =A24&"|"&B24 -> E3_StatusQuo_Targets|FY2028 | O24: None | P24: None
A25: =A3 -> E3_StatusQuo_Targets | B25: FY2029 | C25: =IF(D3=1,0, BaselineCalc!$B$7 + ROUND(L3*F3,0)) -> 295 | D25: =IF(E3=1,0, BaselineCalc!$B$8 + L3 - ROUND(L3*F3,0)) -> 333 | E25: =C25+D25 -> 628 | F25: =YearMap!B5 -> 6907.7273 | G25: =YearMap!C5 -> 1512280.6 | H25: =YearMap!D5 -> 1741770.6 | I25: =A25&"|"&B25 -> E3_StatusQuo_Targets|FY2029 | O25: None | P25: None
A26: =A3 -> E3_StatusQuo_Targets | B26: FY2030 | C26: =IF(D3=1,0, BaselineCalc!$B$7 + ROUND(M3*F3,0)) -> 295 | D26: =IF(E3=1,0, BaselineCalc!$B$8 + M3 - ROUND(M3*F3,0)) -> 333 | E26: =C26+D26 -> 628 | F26: =YearMap!B6 -> 7080.4205 | G26: =YearMap!C6 -> 1550087.6 | H26: =YearMap!D6 -> 1785314.9 | I26: =A26&"|"&B26 -> E3_StatusQuo_Targets|FY2030 | O26: None | P26: None
A27: =A4 -> D3_CoLocation_Echo_Targets | B27: FY2026 | C27: =IF(D4=1,0, BaselineCalc!$B$7 + ROUND(I4*F4,0)) -> 265 | D27: =IF(E4=1,0, BaselineCalc!$B$8 + I4 - ROUND(I4*F4,0)) -> 304.66667 | E27: =C27+D27 -> 569.66667 | F27: =YearMap!B2 -> 6414.5115 | G27: =YearMap!C2 -> 1404302.9 | H27: =YearMap!D2 -> 1617407.2 | I27: =A27&"|"&B27 -> D3_CoLocation_Echo_Targets|FY2026 | O27: None | P27: None
A28: =A4 -> D3_CoLocation_Echo_Targets | B28: FY2027 | C28: =IF(D4=1,0, BaselineCalc!$B$7 + ROUND(J4*F4,0)) -> 274 | D28: =IF(E4=1,0, BaselineCalc!$B$8 + J4 - ROUND(J4*F4,0)) -> 312.33333 | E28: =C28+D28 -> 586.33333 | F28: =YearMap!B3 -> 6574.8743 | G28: =YearMap!C3 -> 1439410.4 | H28: =YearMap!D3 -> 1657842.4 | I28: =A28&"|"&B28 -> D3_CoLocation_Echo_Targets|FY2027 | O28: None | P28: None
A29: =A4 -> D3_CoLocation_Echo_Targets | B29: FY2028 | C29: =IF(D4=1,0, BaselineCalc!$B$7 + ROUND(K4*F4,0)) -> 282 | D29: =IF(E4=1,0, BaselineCalc!$B$8 + K4 - ROUND(K4*F4,0)) -> 321 | E29: =C29+D29 -> 603 | F29: =YearMap!B4 -> 6739.2461 | G29: =YearMap!C4 -> 1475395.7 | H29: =YearMap!D4 -> 1699288.4 | I29: =A29&"|"&B29 -> D3_CoLocation_Echo_Targets|FY2028 | O29: None | P29: None
A30: =A4 -> D3_CoLocation_Echo_Targets | B30: FY2029 | C30: =IF(D4=1,0, BaselineCalc!$B$7 + ROUND(L4*F4,0)) -> 282 | D30: =IF(E4=1,0, BaselineCalc!$B$8 + L4 - ROUND(L4*F4,0)) -> 321 | E30: =C30+D30 -> 603 | F30: =YearMap!B5 -> 6907.7273 | G30: =YearMap!C5 -> 1512280.6 | H30: =YearMap!D5 -> 1741770.6 | I30: =A30&"|"&B30 -> D3_CoLocation_Echo_Targets|FY2029 | O30: None | P30: None
A31: =A4 -> D3_CoLocation_Echo_Targets | B31: FY2030 | C31: =IF(D4=1,0, BaselineCalc!$B$7 + ROUND(M4*F4,0)) -> 282 | D31: =IF(E4=1,0, BaselineCalc!$B$8 + M4 - ROUND(M4*F4,0)) -> 321 | E31: =C31+D31 -> 603 | F31: =YearMap!B6 -> 7080.4205 | G31: =YearMap!C6 -> 1550087.6 | H31: =YearMap!D6 -> 1785314.9 | I31: =A31&"|"&B31 -> D3_CoLocation_Echo_Targets|FY2030 | O31: None | P31: None
A32: =A5 -> D1_Grow_Both_Targets | B32: FY2026 | C32: =IF(D5=1,0, BaselineCalc!$B$7 + ROUND(I5*F5,0)) -> 282 | D32: =IF(E5=1,0, BaselineCalc!$B$8 + I5 - ROUND(I5*F5,0)) -> 321 | E32: =C32+D32 -> 603 | F32: =YearMap!B2 -> 6414.5115 | G32: =YearMap!C2 -> 1404302.9 | H32: =YearMap!D2 -> 1617407.2 | I32: =A32&"|"&B32 -> D1_Grow_Both_Targets|FY2026 | O32: None | P32: None
A33: =A5 -> D1_Grow_Both_Targets | B33: FY2027 | C33: =IF(D5=1,0, BaselineCalc!$B$7 + ROUND(J5*F5,0)) -> 307 | D33: =IF(E5=1,0, BaselineCalc!$B$8 + J5 - ROUND(J5*F5,0)) -> 346 | E33: =C33+D33 -> 653 | F33: =YearMap!B3 -> 6574.8743 | G33: =YearMap!C3 -> 1439410.4 | H33: =YearMap!D3 -> 1657842.4 | I33: =A33&"|"&B33 -> D1_Grow_Both_Targets|FY2027 | O33: None | P33: None
A34: =A5 -> D1_Grow_Both_Targets | B34: FY2028 | C34: =IF(D5=1,0, BaselineCalc!$B$7 + ROUND(K5*F5,0)) -> 332 | D34: =IF(E5=1,0, BaselineCalc!$B$8 + K5 - ROUND(K5*F5,0)) -> 371 | E34: =C34+D34 -> 703 | F34: =YearMap!B4 -> 6739.2461 | G34: =YearMap!C4 -> 1475395.7 | H34: =YearMap!D4 -> 1699288.4 | I34: =A34&"|"&B34 -> D1_Grow_Both_Targets|FY2028 | O34: None | P34: None
A35: =A5 -> D1_Grow_Both_Targets | B35: FY2029 | C35: =IF(D5=1,0, BaselineCalc!$B$7 + ROUND(L5*F5,0)) -> 332 | D35: =IF(E5=1,0, BaselineCalc!$B$8 + L5 - ROUND(L5*F5,0)) -> 371 | E35: =C35+D35 -> 703 | F35: =YearMap!B5 -> 6907.7273 | G35: =YearMap!C5 -> 1512280.6 | H35: =YearMap!D5 -> 1741770.6 | I35: =A35&"|"&B35 -> D1_Grow_Both_Targets|FY2029 | O35: None | P35: None
A36: =A5 -> D1_Grow_Both_Targets | B36: FY2030 | C36: =IF(D5=1,0, BaselineCalc!$B$7 + ROUND(M5*F5,0)) -> 332 | D36: =IF(E5=1,0, BaselineCalc!$B$8 + M5 - ROUND(M5*F5,0)) -> 371 | E36: =C36+D36 -> 703 | F36: =YearMap!B6 -> 7080.4205 | G36: =YearMap!C6 -> 1550087.6 | H36: =YearMap!D6 -> 1785314.9 | I36: =A36&"|"&B36 -> D1_Grow_Both_Targets|FY2030 | O36: None | P36: None
A37: =A6 -> E2_StatusQuo_Steady | B37: FY2026 | C37: =IF(D6=1,0, BaselineCalc!$B$7 + ROUND(I6*F6,0)) -> 257 | D37: =IF(E6=1,0, BaselineCalc!$B$8 + I6 - ROUND(I6*F6,0)) -> 296 | E37: =C37+D37 -> 553 | F37: =YearMap!B2 -> 6414.5115 | G37: =YearMap!C2 -> 1404302.9 | H37: =YearMap!D2 -> 1617407.2 | I37: =A37&"|"&B37 -> E2_StatusQuo_Steady|FY2026 | O37: None | P37: None
A38: =A6 -> E2_StatusQuo_Steady | B38: FY2027 | C38: =IF(D6=1,0, BaselineCalc!$B$7 + ROUND(J6*F6,0)) -> 257 | D38: =IF(E6=1,0, BaselineCalc!$B$8 + J6 - ROUND(J6*F6,0)) -> 296 | E38: =C38+D38 -> 553 | F38: =YearMap!B3 -> 6574.8743 | G38: =YearMap!C3 -> 1439410.4 | H38: =YearMap!D3 -> 1657842.4 | I38: =A38&"|"&B38 -> E2_StatusQuo_Steady|FY2027 | O38: None | P38: None
A39: =A6 -> E2_StatusQuo_Steady | B39: FY2028 | C39: =IF(D6=1,0, BaselineCalc!$B$7 + ROUND(K6*F6,0)) -> 257 | D39: =IF(E6=1,0, BaselineCalc!$B$8 + K6 - ROUND(K6*F6,0)) -> 296 | E39: =C39+D39 -> 553 | F39: =YearMap!B4 -> 6739.2461 | G39: =YearMap!C4 -> 1475395.7 | H39: =YearMap!D4 -> 1699288.4 | I39: =A39&"|"&B39 -> E2_StatusQuo_Steady|FY2028 | O39: None | P39: None
A40: =A6 -> E2_StatusQuo_Steady | B40: FY2029 | C40: =IF(D6=1,0, BaselineCalc!$B$7 + ROUND(L6*F6,0)) -> 257 | D40: =IF(E6=1,0, BaselineCalc!$B$8 + L6 - ROUND(L6*F6,0)) -> 296 | E40: =C40+D40 -> 553 | F40: =YearMap!B5 -> 6907.7273 | G40: =YearMap!C5 -> 1512280.6 | H40: =YearMap!D5 -> 1741770.6 | I40: =A40&"|"&B40 -> E2_StatusQuo_Steady|FY2029 | O40: None | P40: None
A41: =A6 -> E2_StatusQuo_Steady | B41: FY2030 | C41: =IF(D6=1,0, BaselineCalc!$B$7 + ROUND(M6*F6,0)) -> 257 | D41: =IF(E6=1,0, BaselineCalc!$B$8 + M6 - ROUND(M6*F6,0)) -> 296 | E41: =C41+D41 -> 553 | F41: =YearMap!B6 -> 7080.4205 | G41: =YearMap!C6 -> 1550087.6 | H41: =YearMap!D6 -> 1785314.9 | I41: =A41&"|"&B41 -> E2_StatusQuo_Steady|FY2030 | O41: None | P41: None
A42: =A7 -> D2_EchoGHubRamp_PimaTargets | B42: FY2026 | C42: =IF(D7=1,0, BaselineCalc!$B$7 + ROUND(I7*F7,0)) -> 286 | D42: =IF(E7=1,0, BaselineCalc!$B$8 + I7 - ROUND(I7*F7,0)) -> 308.66667 | E42: =C42+D42 -> 594.66667 | F42: =YearMap!B2 -> 6414.5115 | G42: =YearMap!C2 -> 1404302.9 | H42: =YearMap!D2 -> 1617407.2 | I42: =A42&"|"&B42 -> D2_EchoGHubRamp_PimaTargets|FY2026 | O42: None | P42: None
A43: =A7 -> D2_EchoGHubRamp_PimaTargets | B43: FY2027 | C43: =IF(D7=1,0, BaselineCalc!$B$7 + ROUND(J7*F7,0)) -> 315 | D43: =IF(E7=1,0, BaselineCalc!$B$8 + J7 - ROUND(J7*F7,0)) -> 321.33333 | E43: =C43+D43 -> 636.33333 | F43: =YearMap!B3 -> 6574.8743 | G43: =YearMap!C3 -> 1439410.4 | H43: =YearMap!D3 -> 1657842.4 | I43: =A43&"|"&B43 -> D2_EchoGHubRamp_PimaTargets|FY2027 | O43: None | P43: None
A44: =A7 -> D2_EchoGHubRamp_PimaTargets | B44: FY2028 | C44: =IF(D7=1,0, BaselineCalc!$B$7 + ROUND(K7*F7,0)) -> 345 | D44: =IF(E7=1,0, BaselineCalc!$B$8 + K7 - ROUND(K7*F7,0)) -> 333 | E44: =C44+D44 -> 678 | F44: =YearMap!B4 -> 6739.2461 | G44: =YearMap!C4 -> 1475395.7 | H44: =YearMap!D4 -> 1699288.4 | I44: =A44&"|"&B44 -> D2_EchoGHubRamp_PimaTargets|FY2028 | O44: None | P44: None
A45: =A7 -> D2_EchoGHubRamp_PimaTargets | B45: FY2029 | C45: =IF(D7=1,0, BaselineCalc!$B$7 + ROUND(L7*F7,0)) -> 345 | D45: =IF(E7=1,0, BaselineCalc!$B$8 + L7 - ROUND(L7*F7,0)) -> 333 | E45: =C45+D45 -> 678 | F45: =YearMap!B5 -> 6907.7273 | G45: =YearMap!C5 -> 1512280.6 | H45: =YearMap!D5 -> 1741770.6 | I45: =A45&"|"&B45 -> D2_EchoGHubRamp_PimaTargets|FY2029 | O45: None | P45: None
A46: =A7 -> D2_EchoGHubRamp_PimaTargets | B46: FY2030 | C46: =IF(D7=1,0, BaselineCalc!$B$7 + ROUND(M7*F7,0)) -> 345 | D46: =IF(E7=1,0, BaselineCalc!$B$8 + M7 - ROUND(M7*F7,0)) -> 333 | E46: =C46+D46 -> 678 | F46: =YearMap!B6 -> 7080.4205 | G46: =YearMap!C6 -> 1550087.6 | H46: =YearMap!D6 -> 1785314.9 | I46: =A46&"|"&B46 -> D2_EchoGHubRamp_PimaTargets|FY2030 | O46: None | P46: None
A47: =A8 -> A2_Repurpose_Both_lease | B47: FY2026 | C47: =IF(D8=1,0, BaselineCalc!$B$7 + ROUND(I8*F8,0)) -> 0 | D47: =IF(E8=1,0, BaselineCalc!$B$8 + I8 - ROUND(I8*F8,0)) -> 0 | E47: =C47+D47 -> 0 | F47: =YearMap!B2 -> 6414.5115 | G47: =YearMap!C2 -> 1404302.9 | H47: =YearMap!D2 -> 1617407.2 | I47: =A47&"|"&B47 -> A2_Repurpose_Both_lease|FY2026 | O47: None | P47: None
A48: =A8 -> A2_Repurpose_Both_lease | B48: FY2027 | C48: =IF(D8=1,0, BaselineCalc!$B$7 + ROUND(J8*F8,0)) -> 0 | D48: =IF(E8=1,0, BaselineCalc!$B$8 + J8 - ROUND(J8*F8,0)) -> 0 | E48: =C48+D48 -> 0 | F48: =YearMap!B3 -> 6574.8743 | G48: =YearMap!C3 -> 1439410.4 | H48: =YearMap!D3 -> 1657842.4 | I48: =A48&"|"&B48 -> A2_Repurpose_Both_lease|FY2027 | O48: None | P48: None
A49: =A8 -> A2_Repurpose_Both_lease | B49: FY2028 | C49: =IF(D8=1,0, BaselineCalc!$B$7 + ROUND(K8*F8,0)) -> 0 | D49: =IF(E8=1,0, BaselineCalc!$B$8 + K8 - ROUND(K8*F8,0)) -> 0 | E49: =C49+D49 -> 0 | F49: =YearMap!B4 -> 6739.2461 | G49: =YearMap!C4 -> 1475395.7 | H49: =YearMap!D4 -> 1699288.4 | I49: =A49&"|"&B49 -> A2_Repurpose_Both_lease|FY2028 | O49: None | P49: None
A50: =A8 -> A2_Repurpose_Both_lease | B50: FY2029 | C50: =IF(D8=1,0, BaselineCalc!$B$7 + ROUND(L8*F8,0)) -> 0 | D50: =IF(E8=1,0, BaselineCalc!$B$8 + L8 - ROUND(L8*F8,0)) -> 0 | E50: =C50+D50 -> 0 | F50: =YearMap!B5 -> 6907.7273 | G50: =YearMap!C5 -> 1512280.6 | H50: =YearMap!D5 -> 1741770.6 | I50: =A50&"|"&B50 -> A2_Repurpose_Both_lease|FY2029 | O50: None | P50: None
A51: =A8 -> A2_Repurpose_Both_lease | B51: FY2030 | C51: =IF(D8=1,0, BaselineCalc!$B$7 + ROUND(M8*F8,0)) -> 0 | D51: =IF(E8=1,0, BaselineCalc!$B$8 + M8 - ROUND(M8*F8,0)) -> 0 | E51: =C51+D51 -> 0 | F51: =YearMap!B6 -> 7080.4205 | G51: =YearMap!C6 -> 1550087.6 | H51: =YearMap!D6 -> 1785314.9 | I51: =A51&"|"&B51 -> A2_Repurpose_Both_lease|FY2030 | O51: None | P51: None
A52: =A9 -> A1_Repurpose_Both_ops | B52: FY2026 | C52: =IF(D9=1,0, BaselineCalc!$B$7 + ROUND(I9*F9,0)) -> 0 | D52: =IF(E9=1,0, BaselineCalc!$B$8 + I9 - ROUND(I9*F9,0)) -> 0 | E52: =C52+D52 -> 0 | F52: =YearMap!B2 -> 6414.5115 | G52: =YearMap!C2 -> 1404302.9 | H52: =YearMap!D2 -> 1617407.2 | I52: =A52&"|"&B52 -> A1_Repurpose_Both_ops|FY2026 | O52: None | P52: None
A53: =A9 -> A1_Repurpose_Both_ops | B53: FY2027 | C53: =IF(D9=1,0, BaselineCalc!$B$7 + ROUND(J9*F9,0)) -> 0 | D53: =IF(E9=1,0, BaselineCalc!$B$8 + J9 - ROUND(J9*F9,0)) -> 0 | E53: =C53+D53 -> 0 | F53: =YearMap!B3 -> 6574.8743 | G53: =YearMap!C3 -> 1439410.4 | H53: =YearMap!D3 -> 1657842.4 | I53: =A53&"|"&B53 -> A1_Repurpose_Both_ops|FY2027 | O53: None | P53: None
A54: =A9 -> A1_Repurpose_Both_ops | B54: FY2028 | C54: =IF(D9=1,0, BaselineCalc!$B$7 + ROUND(K9*F9,0)) -> 0 | D54: =IF(E9=1,0, BaselineCalc!$B$8 + K9 - ROUND(K9*F9,0)) -> 0 | E54: =C54+D54 -> 0 | F54: =YearMap!B4 -> 6739.2461 | G54: =YearMap!C4 -> 1475395.7 | H54: =YearMap!D4 -> 1699288.4 | I54: =A54&"|"&B54 -> A1_Repurpose_Both_ops|FY2028 | O54: None | P54: None
A55: =A9 -> A1_Repurpose_Both_ops | B55: FY2029 | C55: =IF(D9=1,0, BaselineCalc!$B$7 + ROUND(L9*F9,0)) -> 0 | D55: =IF(E9=1,0, BaselineCalc!$B$8 + L9 - ROUND(L9*F9,0)) -> 0 | E55: =C55+D55 -> 0 | F55: =YearMap!B5 -> 6907.7273 | G55: =YearMap!C5 -> 1512280.6 | H55: =YearMap!D5 -> 1741770.6 | I55: =A55&"|"&B55 -> A1_Repurpose_Both_ops|FY2029 | O55: None | P55: None
A56: =A9 -> A1_Repurpose_Both_ops | B56: FY2030 | C56: =IF(D9=1,0, BaselineCalc!$B$7 + ROUND(M9*F9,0)) -> 0 | D56: =IF(E9=1,0, BaselineCalc!$B$8 + M9 - ROUND(M9*F9,0)) -> 0 | E56: =C56+D56 -> 0 | F56: =YearMap!B6 -> 7080.4205 | G56: =YearMap!C6 -> 1550087.6 | H56: =YearMap!D6 -> 1785314.9 | I56: =A56&"|"&B56 -> A1_Repurpose_Both_ops|FY2030 | O56: None | P56: None
A57: =A10 -> B2_Repurpose_Echo_lease_PimaTargets | B57: FY2026 | C57: =IF(D10=1,0, BaselineCalc!$B$7 + ROUND(I10*F10,0)) -> 0 | D57: =IF(E10=1,0, BaselineCalc!$B$8 + I10 - ROUND(I10*F10,0)) -> 296 | E57: =C57+D57 -> 296 | F57: =YearMap!B2 -> 6414.5115 | G57: =YearMap!C2 -> 1404302.9 | H57: =YearMap!D2 -> 1617407.2 | I57: =A57&"|"&B57 -> B2_Repurpose_Echo_lease_PimaTargets|FY2026 | O57: None | P57: None
A58: =A10 -> B2_Repurpose_Echo_lease_PimaTargets | B58: FY2027 | C58: =IF(D10=1,0, BaselineCalc!$B$7 + ROUND(J10*F10,0)) -> 0 | D58: =IF(E10=1,0, BaselineCalc!$B$8 + J10 - ROUND(J10*F10,0)) -> 296 | E58: =C58+D58 -> 296 | F58: =YearMap!B3 -> 6574.8743 | G58: =YearMap!C3 -> 1439410.4 | H58: =YearMap!D3 -> 1657842.4 | I58: =A58&"|"&B58 -> B2_Repurpose_Echo_lease_PimaTargets|FY2027 | O58: None | P58: None
A59: =A10 -> B2_Repurpose_Echo_lease_PimaTargets | B59: FY2028 | C59: =IF(D10=1,0, BaselineCalc!$B$7 + ROUND(K10*F10,0)) -> 0 | D59: =IF(E10=1,0, BaselineCalc!$B$8 + K10 - ROUND(K10*F10,0)) -> 296 | E59: =C59+D59 -> 296 | F59: =YearMap!B4 -> 6739.2461 | G59: =YearMap!C4 -> 1475395.7 | H59: =YearMap!D4 -> 1699288.4 | I59: =A59&"|"&B59 -> B2_Repurpose_Echo_lease_PimaTargets|FY2028 | O59: None | P59: None
A60: =A10 -> B2_Repurpose_Echo_lease_PimaTargets | B60: FY2029 | C60: =IF(D10=1,0, BaselineCalc!$B$7 + ROUND(L10*F10,0)) -> 0 | D60: =IF(E10=1,0, BaselineCalc!$B$8 + L10 - ROUND(L10*F10,0)) -> 296 | E60: =C60+D60 -> 296 | F60: =YearMap!B5 -> 6907.7273 | G60: =YearMap!C5 -> 1512280.6 | H60: =YearMap!D5 -> 1741770.6 | I60: =A60&"|"&B60 -> B2_Repurpose_Echo_lease_PimaTargets|FY2029 | O60: None | P60: None
A61: =A10 -> B2_Repurpose_Echo_lease_PimaTargets | B61: FY2030 | C61: =IF(D10=1,0, BaselineCalc!$B$7 + ROUND(M10*F10,0)) -> 0 | D61: =IF(E10=1,0, BaselineCalc!$B$8 + M10 - ROUND(M10*F10,0)) -> 296 | E61: =C61+D61 -> 296 | F61: =YearMap!B6 -> 7080.4205 | G61: =YearMap!C6 -> 1550087.6 | H61: =YearMap!D6 -> 1785314.9 | I61: =A61&"|"&B61 -> B2_Repurpose_Echo_lease_PimaTargets|FY2030 | O61: None | P61: None
A62: =A11 -> B1_Repurpose_Echo_ops_PimaTargets | B62: FY2026 | C62: =IF(D11=1,0, BaselineCalc!$B$7 + ROUND(I11*F11,0)) -> 0 | D62: =IF(E11=1,0, BaselineCalc!$B$8 + I11 - ROUND(I11*F11,0)) -> 308.33333 | E62: =C62+D62 -> 308.33333 | F62: =YearMap!B2 -> 6414.5115 | G62: =YearMap!C2 -> 1404302.9 | H62: =YearMap!D2 -> 1617407.2 | I62: =A62&"|"&B62 -> B1_Repurpose_Echo_ops_PimaTargets|FY2026 | O62: None | P62: None
A63: =A11 -> B1_Repurpose_Echo_ops_PimaTargets | B63: FY2027 | C63: =IF(D11=1,0, BaselineCalc!$B$7 + ROUND(J11*F11,0)) -> 0 | D63: =IF(E11=1,0, BaselineCalc!$B$8 + J11 - ROUND(J11*F11,0)) -> 320.66667 | E63: =C63+D63 -> 320.66667 | F63: =YearMap!B3 -> 6574.8743 | G63: =YearMap!C3 -> 1439410.4 | H63: =YearMap!D3 -> 1657842.4 | I63: =A63&"|"&B63 -> B1_Repurpose_Echo_ops_PimaTargets|FY2027 | O63: None | P63: None
A64: =A11 -> B1_Repurpose_Echo_ops_PimaTargets | B64: FY2028 | C64: =IF(D11=1,0, BaselineCalc!$B$7 + ROUND(K11*F11,0)) -> 0 | D64: =IF(E11=1,0, BaselineCalc!$B$8 + K11 - ROUND(K11*F11,0)) -> 333 | E64: =C64+D64 -> 333 | F64: =YearMap!B4 -> 6739.2461 | G64: =YearMap!C4 -> 1475395.7 | H64: =YearMap!D4 -> 1699288.4 | I64: =A64&"|"&B64 -> B1_Repurpose_Echo_ops_PimaTargets|FY2028 | O64: None | P64: None
A65: =A11 -> B1_Repurpose_Echo_ops_PimaTargets | B65: FY2029 | C65: =IF(D11=1,0, BaselineCalc!$B$7 + ROUND(L11*F11,0)) -> 0 | D65: =IF(E11=1,0, BaselineCalc!$B$8 + L11 - ROUND(L11*F11,0)) -> 333 | E65: =C65+D65 -> 333 | F65: =YearMap!B5 -> 6907.7273 | G65: =YearMap!C5 -> 1512280.6 | H65: =YearMap!D5 -> 1741770.6 | I65: =A65&"|"&B65 -> B1_Repurpose_Echo_ops_PimaTargets|FY2029 | O65: None | P65: None
A66: =A11 -> B1_Repurpose_Echo_ops_PimaTargets | B66: FY2030 | C66: =IF(D11=1,0, BaselineCalc!$B$7 + ROUND(M11*F11,0)) -> 0 | D66: =IF(E11=1,0, BaselineCalc!$B$8 + M11 - ROUND(M11*F11,0)) -> 333 | E66: =C66+D66 -> 333 | F66: =YearMap!B6 -> 7080.4205 | G66: =YearMap!C6 -> 1550087.6 | H66: =YearMap!D6 -> 1785314.9 | I66: =A66&"|"&B66 -> B1_Repurpose_Echo_ops_PimaTargets|FY2030 | O66: None | P66: None
A67: =A12 -> C2_Repurpose_Pima_lease_EchoGHub_EchoTargets | B67: FY2026 | C67: =IF(D12=1,0, BaselineCalc!$B$7 + ROUND(I12*F12,0)) -> 257 | D67: =IF(E12=1,0, BaselineCalc!$B$8 + I12 - ROUND(I12*F12,0)) -> 0 | E67: =C67+D67 -> 257 | F67: =YearMap!B2 -> 6414.5115 | G67: =YearMap!C2 -> 1404302.9 | H67: =YearMap!D2 -> 1617407.2 | I67: =A67&"|"&B67 -> C2_Repurpose_Pima_lease_EchoGHub_EchoTargets|FY2026 | O67: None | P67: None
A68: =A12 -> C2_Repurpose_Pima_lease_EchoGHub_EchoTargets | B68: FY2027 | C68: =IF(D12=1,0, BaselineCalc!$B$7 + ROUND(J12*F12,0)) -> 257 | D68: =IF(E12=1,0, BaselineCalc!$B$8 + J12 - ROUND(J12*F12,0)) -> 0 | E68: =C68+D68 -> 257 | F68: =YearMap!B3 -> 6574.8743 | G68: =YearMap!C3 -> 1439410.4 | H68: =YearMap!D3 -> 1657842.4 | I68: =A68&"|"&B68 -> C2_Repurpose_Pima_lease_EchoGHub_EchoTargets|FY2027 | O68: None | P68: None
A69: =A12 -> C2_Repurpose_Pima_lease_EchoGHub_EchoTargets | B69: FY2028 | C69: =IF(D12=1,0, BaselineCalc!$B$7 + ROUND(K12*F12,0)) -> 257 | D69: =IF(E12=1,0, BaselineCalc!$B$8 + K12 - ROUND(K12*F12,0)) -> 0 | E69: =C69+D69 -> 257 | F69: =YearMap!B4 -> 6739.2461 | G69: =YearMap!C4 -> 1475395.7 | H69: =YearMap!D4 -> 1699288.4 | I69: =A69&"|"&B69 -> C2_Repurpose_Pima_lease_EchoGHub_EchoTargets|FY2028 | O69: None | P69: None
A70: =A12 -> C2_Repurpose_Pima_lease_EchoGHub_EchoTargets | B70: FY2029 | C70: =IF(D12=1,0, BaselineCalc!$B$7 + ROUND(L12*F12,0)) -> 257 | D70: =IF(E12=1,0, BaselineCalc!$B$8 + L12 - ROUND(L12*F12,0)) -> 0 | E70: =C70+D70 -> 257 | F70: =YearMap!B5 -> 6907.7273 | G70: =YearMap!C5 -> 1512280.6 | H70: =YearMap!D5 -> 1741770.6 | I70: =A70&"|"&B70 -> C2_Repurpose_Pima_lease_EchoGHub_EchoTargets|FY2029 | O70: None | P70: None
A71: =A12 -> C2_Repurpose_Pima_lease_EchoGHub_EchoTargets | B71: FY2030 | C71: =IF(D12=1,0, BaselineCalc!$B$7 + ROUND(M12*F12,0)) -> 257 | D71: =IF(E12=1,0, BaselineCalc!$B$8 + M12 - ROUND(M12*F12,0)) -> 0 | E71: =C71+D71 -> 257 | F71: =YearMap!B6 -> 7080.4205 | G71: =YearMap!C6 -> 1550087.6 | H71: =YearMap!D6 -> 1785314.9 | I71: =A71&"|"&B71 -> C2_Repurpose_Pima_lease_EchoGHub_EchoTargets|FY2030 | O71: None | P71: None
A72: =A13 -> C1_Repurpose_Pima_ops_EchoGHub_EchoTargets | B72: FY2026 | C72: =IF(D13=1,0, BaselineCalc!$B$7 + ROUND(I13*F13,0)) -> 274 | D72: =IF(E13=1,0, BaselineCalc!$B$8 + I13 - ROUND(I13*F13,0)) -> 0 | E72: =C72+D72 -> 274 | F72: =YearMap!B2 -> 6414.5115 | G72: =YearMap!C2 -> 1404302.9 | H72: =YearMap!D2 -> 1617407.2 | I72: =A72&"|"&B72 -> C1_Repurpose_Pima_ops_EchoGHub_EchoTargets|FY2026 | O72: None | P72: None
A73: =A13 -> C1_Repurpose_Pima_ops_EchoGHub_EchoTargets | B73: FY2027 | C73: =IF(D13=1,0, BaselineCalc!$B$7 + ROUND(J13*F13,0)) -> 290 | D73: =IF(E13=1,0, BaselineCalc!$B$8 + J13 - ROUND(J13*F13,0)) -> 0 | E73: =C73+D73 -> 290 | F73: =YearMap!B3 -> 6574.8743 | G73: =YearMap!C3 -> 1439410.4 | H73: =YearMap!D3 -> 1657842.4 | I73: =A73&"|"&B73 -> C1_Repurpose_Pima_ops_EchoGHub_EchoTargets|FY2027 | O73: None | P73: None
A74: =A13 -> C1_Repurpose_Pima_ops_EchoGHub_EchoTargets | B74: FY2028 | C74: =IF(D13=1,0, BaselineCalc!$B$7 + ROUND(K13*F13,0)) -> 307 | D74: =IF(E13=1,0, BaselineCalc!$B$8 + K13 - ROUND(K13*F13,0)) -> 0 | E74: =C74+D74 -> 307 | F74: =YearMap!B4 -> 6739.2461 | G74: =YearMap!C4 -> 1475395.7 | H74: =YearMap!D4 -> 1699288.4 | I74: =A74&"|"&B74 -> C1_Repurpose_Pima_ops_EchoGHub_EchoTargets|FY2028 | O74: None | P74: None
A75: =A13 -> C1_Repurpose_Pima_ops_EchoGHub_EchoTargets | B75: FY2029 | C75: =IF(D13=1,0, BaselineCalc!$B$7 + ROUND(L13*F13,0)) -> 307 | D75: =IF(E13=1,0, BaselineCalc!$B$8 + L13 - ROUND(L13*F13,0)) -> 0 | E75: =C75+D75 -> 307 | F75: =YearMap!B5 -> 6907.7273 | G75: =YearMap!C5 -> 1512280.6 | H75: =YearMap!D5 -> 1741770.6 | I75: =A75&"|"&B75 -> C1_Repurpose_Pima_ops_EchoGHub_EchoTargets|FY2029 | O75: None | P75: None
A76: =A13 -> C1_Repurpose_Pima_ops_EchoGHub_EchoTargets | B76: FY2030 | C76: =IF(D13=1,0, BaselineCalc!$B$7 + ROUND(M13*F13,0)) -> 307 | D76: =IF(E13=1,0, BaselineCalc!$B$8 + M13 - ROUND(M13*F13,0)) -> 0 | E76: =C76+D76 -> 307 | F76: =YearMap!B6 -> 7080.4205 | G76: =YearMap!C6 -> 1550087.6 | H76: =YearMap!D6 -> 1785314.9 | I76: =A76&"|"&B76 -> C1_Repurpose_Pima_ops_EchoGHub_EchoTargets|FY2030 | O76: None | P76: None

Sheet MultiYear_ProForma
A1: =AG1 -> Key | B1: ScenarioKey | C1: Year | D1: Echo_ADM | E1: Pima_ADM | F1: Total_ADM | G1: VarUnit$ | H1: EchoFixed$ | I1: PimaFixed$ | J1: OpsFactor | K1: ExtraSave | L1: EchoPotential_ADM | M1: PimaPotential_ADM | N1: Displaced_ADM | O1: Retained_ADM | P1: h | Q1: CarryFrac | R1: EchoFixedEff$ | S1: PimaFixedEff$ | T1: TI_adds$ | U1: SiteCost$ | V1: RetainedSvc$ | W1: Comparable_MO$ | X1: Comparable_per_Student$ | Y1: Aid_per_ADM | Z1: Net_MO_after_aid$ | AA1: Net_per_served$ | AB1: Overlay_ADM | AC1: Served_ADM | AD1: Revenue$ | AE1: Adj_MO$ | AF1: Net$ | AG1: Key
A2: =AG2 -> F1_CUSTOM1|FY2026 | B2: =Scenarios!A2 -> F1_CUSTOM1 | C2: FY2026 | D2: =IF(Scenarios!D2=1,0, L2) -> 257 | E2: =IF(Scenarios!E2=1,0, M2) -> 296 | F2: =D2+E2 -> 553 | G2: =YearMap!B2 -> 6414.5115 | H2: =YearMap!C2 -> 1404302.9 | I2: =YearMap!D2 -> 1617407.2 | J2: =1-BaselineCalc!$B$5 -> 0.993 | K2: =Scenarios!G2 -> 0 | L2: =IF(Scenarios!$Q2=1,BaselineCalc!$B$7*(1+Parameters_Public!$C44)^(IF($C2="FY2026",0,IF($C2="FY2027",1,IF($C2="FY2028",2,IF($C2="FY2029",3,IF($C2="FY2030",4,0))))))+ROUND(Scenarios!I2*Scenarios!$F2,0),BaselineCalc!$B$7+ROUND(Scenarios!I2*Scenarios!$F2,0)) -> 257 | M2: =IF(Scenarios!$R2=1,BaselineCalc!$B$8*(1+Parameters_Public!$C45)^(IF($C2="FY2026",0,IF($C2="FY2027",1,IF($C2="FY2028",2,IF($C2="FY2029",3,IF($C2="FY2030",4,0))))))+Scenarios!I2-ROUND(Scenarios!I2*Scenarios!$F2,0),BaselineCalc!$B$8+Scenarios!I2-ROUND(Scenarios!I2*Scenarios!$F2,0)) -> 296 | N2: =(L2-D2) + (M2-E2) -> 0 | O2: =(Parameters_Public!$C$23*(L2-D2)+Parameters_Public!$C$24*(M2-E2)) -> 0 | P2: =YearMap!E2 -> 1000 | Q2: =IF(Scenarios!N2="lease", YearMap!F2, YearMap!G2) -> 0.45 | R2: =IF(Scenarios!D2=1, Q2*H2, H2) -> 1404302.9 | S2: =IF(Scenarios!E2=1, Q2*I2, I2) -> 1617407.2 | T2: =IF(C2="FY2026", (Scenarios!D2+Scenarios!E2)*BaselineCalc!$B$22, 0) -> 0 | U2: =(R2+S2+G2*F2)*J2*(1-K2) -> 6522952.4 | V2: =O2*(G2+P2) -> 0 | W2: =U2+V2+IF(Parameters_Public!$C$26=1, T2, 0) -> 6522952.4 | X2: =IF(F2+O2>0, W2/(F2+O2),"") -> 11795.574 | Y2: =INDEX(YearMap!$I$2:$I$6, MATCH(C2, YearMap!$A$2:$A$6, 0)) -> 5013 | Z2: =W2 - ((Y2 + IF(Parameters_Public!$C$20=1, Parameters_Public!$C$19, 0))*AC2) -> 3334935 | AA2: =IF($AC2>0, $Z2/$AC2, 0) -> 6030.6239 | AB2: =MAX(0, (MAX(0, $D2-BaselineCalc!$B$7) + MAX(0, $E2-BaselineCalc!$B$8))) -> 0 | AC2: =L2+M2-N2+O2 -> 553 | AD2: =( (Y2 + IF(Parameters_Public!$C20=1, INDEX(YearMap!$O$2:$O$6, MATCH(C2, YearMap!$A$2:$A$6, 0)), 0)) * AC2 ) + AC2*INDEX(YearMap!$P$2:$P$6, MATCH(C2, YearMap!$A$2:$A$6, 0)) + AB2*( INDEX(YearMap!$R$2:$R$6, MATCH(C2, YearMap!$A$2:$A$6, 0)) - INDEX(YearMap!$P$2:$P$6, MATCH(C2, YearMap!$A$2:$A$6, 0)) ) -> 6063617.3 | AE2: =(W2 - (1-Parameters_Public!$C42)*$G2*$AB2*$J2*(1-$K2)) + AB2*INDEX(YearMap!$Q$2:$Q$6, MATCH(C2, YearMap!$A$2:$A$6, 0)) -> 6522952.4 | AF2: =AD2-AE2 -> -459335.03 | AG2: =B2&"|"&C2 -> F1_CUSTOM1|FY2026
A3: =AG3 -> F1_CUSTOM1|FY2027 | B3: =Scenarios!A2 -> F1_CUSTOM1 | C3: FY2027 | D3: =IF(Scenarios!D2=1,0, L3) -> 257 | E3: =IF(Scenarios!E2=1,0, M3) -> 296 | F3: =D3+E3 -> 553 | G3: =YearMap!B3 -> 6574.8743 | H3: =YearMap!C3 -> 1439410.4 | I3: =YearMap!D3 -> 1657842.4 | J3: =1-BaselineCalc!$B$5 -> 0.993 | K3: =Scenarios!G2 -> 0 | L3: =IF(Scenarios!$Q2=1,BaselineCalc!$B$7*(1+Parameters_Public!$C44)^(IF($C3="FY2026",0,IF($C3="FY2027",1,IF($C3="FY2028",2,IF($C3="FY2029",3,IF($C3="FY2030",4,0))))))+ROUND(Scenarios!J2*Scenarios!$F2,0),BaselineCalc!$B$7+ROUND(Scenarios!J2*Scenarios!$F2,0)) -> 257 | M3: =IF(Scenarios!$R2=1,BaselineCalc!$B$8*(1+Parameters_Public!$C45)^(IF($C3="FY2026",0,IF($C3="FY2027",1,IF($C3="FY2028",2,IF($C3="FY2029",3,IF($C3="FY2030",4,0))))))+Scenarios!J2-ROUND(Scenarios!J2*Scenarios!$F2,0),BaselineCalc!$B$8+Scenarios!J2-ROUND(Scenarios!J2*Scenarios!$F2,0)) -> 296 | N3: =(L3-D3) + (M3-E3) -> 0 | O3: =(Parameters_Public!$C$23*(L3-D3)+Parameters_Public!$C$24*(M3-E3)) -> 0 | P3: =YearMap!E3 -> 800 | Q3: =IF(Scenarios!N2="lease", YearMap!F3, YearMap!G3) -> 0.4 | R3: =IF(Scenarios!D2=1, Q3*H3, H3) -> 1439410.4 | S3: =IF(Scenarios!E2=1, Q3*I3, I3) -> 1657842.4 | T3: =IF(C3="FY2026", (Scenarios!D2+Scenarios!E2)*BaselineCalc!$B$22, 0) -> 0 | U3: =(R3+S3+G3*F3)*J3*(1-K3) -> 6686026.2 | V3: =O3*(G3+P3) -> 0 | W3: =U3+V3+IF(Parameters_Public!$C$26=1, T3, 0) -> 6686026.2 | X3: =IF(F3+O3>0, W3/(F3+O3),"") -> 12090.463 | Y3: =INDEX(YearMap!$I$2:$I$6, MATCH(C3, YearMap!$A$2:$A$6, 0)) -> 5138.325 | Z3: =W3 - ((Y3 + IF(Parameters_Public!$C$20=1, Parameters_Public!$C$19, 0))*AC3) -> 3428704.1 | AA3: =IF($AC3>0, $Z3/$AC3, 0) -> 6200.1883 | AB3: =MAX(0, (MAX(0, $D3-BaselineCalc!$B$7) + MAX(0, $E3-BaselineCalc!$B$8))) -> 0 | AC3: =L3+M3-N3+O3 -> 553 | AD3: =( (Y3 + IF(Parameters_Public!$C20=1, INDEX(YearMap!$O$2:$O$6, MATCH(C3, YearMap!$A$2:$A$6, 0)), 0)) * AC3 ) + AC3*INDEX(YearMap!$P$2:$P$6, MATCH(C3, YearMap!$A$2:$A$6, 0)) + AB3*( INDEX(YearMap!$R$2:$R$6, MATCH(C3, YearMap!$A$2:$A$6, 0)) - INDEX(YearMap!$P$2:$P$6, MATCH(C3, YearMap!$A$2:$A$6, 0)) ) -> 6215207.8 | AE3: =(W3 - (1-Parameters_Public!$C42)*$G3*$AB3*$J3*(1-$K3)) + AB3*INDEX(YearMap!$Q$2:$Q$6, MATCH(C3, YearMap!$A$2:$A$6, 0)) -> 6686026.2 | AF3: =AD3-AE3 -> -470818.41 | AG3: =B3&"|"&C3 -> F1_CUSTOM1|FY2027
A4: =AG4 -> F1_CUSTOM1|FY2028 | B4: =Scenarios!A2 -> F1_CUSTOM1 | C4: FY2028 | D4: =IF(Scenarios!D2=1,0, L4) -> 257 | E4: =IF(Scenarios!E2=1,0, M4) -> 296 | F4: =D4+E4 -> 553 | G4: =YearMap!B4 -> 6739.2461 | H4: =YearMap!C4 -> 1475395.7 | I4: =YearMap!D4 -> 1699288.4 | J4: =1-BaselineCalc!$B$5 -> 0.993 | K4: =Scenarios!G2 -> 0 | L4: =IF(Scenarios!$Q2=1,BaselineCalc!$B$7*(1+Parameters_Public!$C44)^(IF($C4="FY2026",0,IF($C4="FY2027",1,IF($C4="FY2028",2,IF($C4="FY2029",3,IF($C4="FY2030",4,0))))))+ROUND(Scenarios!K2*Scenarios!$F2,0),BaselineCalc!$B$7+ROUND(Scenarios!K2*Scenarios!$F2,0)) -> 257 | M4: =IF(Scenarios!$R2=1,BaselineCalc!$B$8*(1+Parameters_Public!$C45)^(IF($C4="FY2026",0,IF($C4="FY2027",1,IF($C4="FY2028",2,IF($C4="FY2029",3,IF($C4="FY2030",4,0))))))+Scenarios!K2-ROUND(Scenarios!K2*Scenarios!$F2,0),BaselineCalc!$B$8+Scenarios!K2-ROUND(Scenarios!K2*Scenarios!$F2,0)) -> 296 | N4: =(L4-D4) + (M4-E4) -> 0 | O4: =(Parameters_Public!$C$23*(L4-D4)+Parameters_Public!$C$24*(M4-E4)) -> 0 | P4: =YearMap!E4 -> 600 | Q4: =IF(Scenarios!N2="lease", YearMap!F4, YearMap!G4) -> 0.35 | R4: =IF(Scenarios!D2=1, Q4*H4, H4) -> 1475395.7 | S4: =IF(Scenarios!E2=1, Q4*I4, I4) -> 1699288.4 | T4: =IF(C4="FY2026", (Scenarios!D2+Scenarios!E2)*BaselineCalc!$B$22, 0) -> 0 | U4: =(R4+S4+G4*F4)*J4*(1-K4) -> 6853176.8 | V4: =O4*(G4+P4) -> 0 | W4: =U4+V4+IF(Parameters_Public!$C$26=1, T4, 0) -> 6853176.8 | X4: =IF(F4+O4>0, W4/(F4+O4),"") -> 12392.725 | Y4: =INDEX(YearMap!$I$2:$I$6, MATCH(C4, YearMap!$A$2:$A$6, 0)) -> 5266.7831 | Z4: =W4 - ((Y4 + IF(Parameters_Public!$C$20=1, Parameters_Public!$C$19, 0))*AC4) -> 3524817.4 | AA4: =IF($AC4>0, $Z4/$AC4, 0) -> 6373.9917 | AB4: =MAX(0, (MAX(0, $D4-BaselineCalc!$B$7) + MAX(0, $E4-BaselineCalc!$B$8))) -> 0 | AC4: =L4+M4-N4+O4 -> 553 | AD4: =( (Y4 + IF(Parameters_Public!$C20=1, INDEX(YearMap!$O$2:$O$6, MATCH(C4, YearMap!$A$2:$A$6, 0)), 0)) * AC4 ) + AC4*INDEX(YearMap!$P$2:$P$6, MATCH(C4, YearMap!$A$2:$A$6, 0)) + AB4*( INDEX(YearMap!$R$2:$R$6, MATCH(C4, YearMap!$A$2:$A$6, 0)) - INDEX(YearMap!$P$2:$P$6, MATCH(C4, YearMap!$A$2:$A$6, 0)) ) -> 6370588 | AE4: =(W4 - (1-Parameters_Public!$C42)*$G4*$AB4*$J4*(1-$K4)) + AB4*INDEX(YearMap!$Q$2:$Q$6, MATCH(C4, YearMap!$A$2:$A$6, 0)) -> 6853176.8 | AF4: =AD4-AE4 -> -482588.87 | AG4: =B4&"|"&C4 -> F1_CUSTOM1|FY2028
A5: =AG5 -> F1_CUSTOM1|FY2029 | B5: =Scenarios!A2 -> F1_CUSTOM1 | C5: FY2029 | D5: =IF(Scenarios!D2=1,0, L5) -> 257 | E5: =IF(Scenarios!E2=1,0, M5) -> 296 | F5: =D5+E5 -> 553 | G5: =YearMap!B5 -> 6907.7273 | H5: =YearMap!C5 -> 1512280.6 | I5: =YearMap!D5 -> 1741770.6 | J5: =1-BaselineCalc!$B$5 -> 0.993 | K5: =Scenarios!G2 -> 0 | L5: =IF(Scenarios!$Q2=1,BaselineCalc!$B$7*(1+Parameters_Public!$C44)^(IF($C5="FY2026",0,IF($C5="FY2027",1,IF($C5="FY2028",2,IF($C5="FY2029",3,IF($C5="FY2030",4,0))))))+ROUND(Scenarios!L2*Scenarios!$F2,0),BaselineCalc!$B$7+ROUND(Scenarios!L2*Scenarios!$F2,0)) -> 257 | M5: =IF(Scenarios!$R2=1,BaselineCalc!$B$8*(1+Parameters_Public!$C45)^(IF($C5="FY2026",0,IF($C5="FY2027",1,IF($C5="FY2028",2,IF($C5="FY2029",3,IF($C5="FY2030",4,0))))))+Scenarios!L2-ROUND(Scenarios!L2*Scenarios!$F2,0),BaselineCalc!$B$8+Scenarios!L2-ROUND(Scenarios!L2*Scenarios!$F2,0)) -> 296 | N5: =(L5-D5) + (M5-E5) -> 0 | O5: =(Parameters_Public!$C$23*(L5-D5)+Parameters_Public!$C$24*(M5-E5)) -> 0 | P5: =YearMap!E5 -> 500 | Q5: =IF(Scenarios!N2="lease", YearMap!F5, YearMap!G5) -> 0.3 | R5: =IF(Scenarios!D2=1, Q5*H5, H5) -> 1512280.6 | S5: =IF(Scenarios!E2=1, Q5*I5, I5) -> 1741770.6 | T5: =IF(C5="FY2026", (Scenarios!D2+Scenarios!E2)*BaselineCalc!$B$22, 0) -> 0 | U5: =(R5+S5+G5*F5)*J5*(1-K5) -> 7024506.3 | V5: =O5*(G5+P5) -> 0 | W5: =U5+V5+IF(Parameters_Public!$C$26=1, T5, 0) -> 7024506.3 | X5: =IF(F5+O5>0, W5/(F5+O5),"") -> 12702.543 | Y5: =INDEX(YearMap!$I$2:$I$6, MATCH(C5, YearMap!$A$2:$A$6, 0)) -> 5398.4527 | Z5: =W5 - ((Y5 + IF(Parameters_Public!$C$20=1, Parameters_Public!$C$19, 0))*AC5) -> 3623333.6 | AA5: =IF($AC5>0, $Z5/$AC5, 0) -> 6552.1403 | AB5: =MAX(0, (MAX(0, $D5-BaselineCalc!$B$7) + MAX(0, $E5-BaselineCalc!$B$8))) -> 0 | AC5: =L5+M5-N5+O5 -> 553 | AD5: =( (Y5 + IF(Parameters_Public!$C20=1, INDEX(YearMap!$O$2:$O$6, MATCH(C5, YearMap!$A$2:$A$6, 0)), 0)) * AC5 ) + AC5*INDEX(YearMap!$P$2:$P$6, MATCH(C5, YearMap!$A$2:$A$6, 0)) + AB5*( INDEX(YearMap!$R$2:$R$6, MATCH(C5, YearMap!$A$2:$A$6, 0)) - INDEX(YearMap!$P$2:$P$6, MATCH(C5, YearMap!$A$2:$A$6, 0)) ) -> 6529852.7 | AE5: =(W5 - (1-Parameters_Public!$C42)*$G5*$AB5*$J5*(1-$K5)) + AB5*INDEX(YearMap!$Q$2:$Q$6, MATCH(C5, YearMap!$A$2:$A$6, 0)) -> 7024506.3 | AF5: =AD5-AE5 -> -494653.59 | AG5: =B5&"|"&C5 -> F1_CUSTOM1|FY2029
A6: =AG6 -> F1_CUSTOM1|FY2030 | B6: =Scenarios!A2 -> F1_CUSTOM1 | C6: FY2030 | D6: =IF(Scenarios!D2=1,0, L6) -> 257 | E6: =IF(Scenarios!E2=1,0, M6) -> 296 | F6: =D6+E6 -> 553 | G6: =YearMap!B6 -> 7080.4205 | H6: =YearMap!C6 -> 1550087.6 | I6: =YearMap!D6 -> 1785314.9 | J6: =1-BaselineCalc!$B$5 -> 0.993 | K6: =Scenarios!G2 -> 0 | L6: =IF(Scenarios!$Q2=1,BaselineCalc!$B$7*(1+Parameters_Public!$C44)^(IF($C6="FY2026",0,IF($C6="FY2027",1,IF($C6="FY2028",2,IF($C6="FY2029",3,IF($C6="FY2030",4,0))))))+ROUND(Scenarios!M2*Scenarios!$F2,0),BaselineCalc!$B$7+ROUND(Scenarios!M2*Scenarios!$F2,0)) -> 257 | M6: =IF(Scenarios!$R2=1,BaselineCalc!$B$8*(1+Parameters_Public!$C45)^(IF($C6="FY2026",0,IF($C6="FY2027",1,IF($C6="FY2028",2,IF($C6="FY2029",3,IF($C6="FY2030",4,0))))))+Scenarios!M2-ROUND(Scenarios!M2*Scenarios!$F2,0),BaselineCalc!$B$8+Scenarios!M2-ROUND(Scenarios!M2*Scenarios!$F2,0)) -> 296 | N6: =(L6-D6) + (M6-E6) -> 0 | O6: =(Parameters_Public!$C$23*(L6-D6)+Parameters_Public!$C$24*(M6-E6)) -> 0 | P6: =YearMap!E6 -> 300 | Q6: =IF(Scenarios!N2="lease", YearMap!F6, YearMap!G6) -> 0.3 | R6: =IF(Scenarios!D2=1, Q6*H6, H6) -> 1550087.6 | S6: =IF(Scenarios!E2=1, Q6*I6, I6) -> 1785314.9 | T6: =IF(C6="FY2026", (Scenarios!D2+Scenarios!E2)*BaselineCalc!$B$22, 0) -> 0 | U6: =(R6+S6+G6*F6)*J6*(1-K6) -> 7200118.9 | V6: =O6*(G6+P6) -> 0 | W6: =U6+V6+IF(Parameters_Public!$C$26=1, T6, 0) -> 7200118.9 | X6: =IF(F6+O6>0, W6/(F6+O6),"") -> 13020.107 | Y6: =INDEX(YearMap!$I$2:$I$6, MATCH(C6, YearMap!$A$2:$A$6, 0)) -> 5533.414 | Z6: =W6 - ((Y6 + IF(Parameters_Public!$C$20=1, Parameters_Public!$C$19, 0))*AC6) -> 3724312.6 | AA6: =IF($AC6>0, $Z6/$AC6, 0) -> 6734.7425 | AB6: =MAX(0, (MAX(0, $D6-BaselineCalc!$B$7) + MAX(0, $E6-BaselineCalc!$B$8))) -> 0 | AC6: =L6+M6-N6+O6 -> 553 | AD6: =( (Y6 + IF(Parameters_Public!$C20=1, INDEX(YearMap!$O$2:$O$6, MATCH(C6, YearMap!$A$2:$A$6, 0)), 0)) * AC6 ) + AC6*INDEX(YearMap!$P$2:$P$6, MATCH(C6, YearMap!$A$2:$A$6, 0)) + AB6*( INDEX(YearMap!$R$2:$R$6, MATCH(C6, YearMap!$A$2:$A$6, 0)) - INDEX(YearMap!$P$2:$P$6, MATCH(C6, YearMap!$A$2:$A$6, 0)) ) -> 6693099 | AE6: =(W6 - (1-Parameters_Public!$C42)*$G6*$AB6*$J6*(1-$K6)) + AB6*INDEX(YearMap!$Q$2:$Q$6, MATCH(C6, YearMap!$A$2:$A$6, 0)) -> 7200118.9 | AF6: =AD6-AE6 -> -507019.93 | AG6: =B6&"|"&C6 -> F1_CUSTOM1|FY2030
A7: =AG7 -> E3_StatusQuo_Targets|FY2026 | B7: =Scenarios!A3 -> E3_StatusQuo_Targets | C7: FY2026 | D7: =IF(Scenarios!D3=1,0, L7) -> 270 | E7: =IF(Scenarios!E3=1,0, M7) -> 308 | F7: =D7+E7 -> 578 | G7: =YearMap!B2 -> 6414.5115 | H7: =YearMap!C2 -> 1404302.9 | I7: =YearMap!D2 -> 1617407.2 | J7: =1-BaselineCalc!$B$5 -> 0.993 | K7: =Scenarios!G3 -> 0 | L7: =IF(Scenarios!$Q3=1,BaselineCalc!$B$7*(1+Parameters_Public!$C44)^(IF($C7="FY2026",0,IF($C7="FY2027",1,IF($C7="FY2028",2,IF($C7="FY2029",3,IF($C7="FY2030",4,0))))))+ROUND(Scenarios!I3*Scenarios!$F3,0),BaselineCalc!$B$7+ROUND(Scenarios!I3*Scenarios!$F3,0)) -> 270 | M7: =IF(Scenarios!$R3=1,BaselineCalc!$B$8*(1+Parameters_Public!$C45)^(IF($C7="FY2026",0,IF($C7="FY2027",1,IF($C7="FY2028",2,IF($C7="FY2029",3,IF($C7="FY2030",4,0))))))+Scenarios!I3-ROUND(Scenarios!I3*Scenarios!$F3,0),BaselineCalc!$B$8+Scenarios!I3-ROUND(Scenarios!I3*Scenarios!$F3,0)) -> 308 | N7: =(L7-D7) + (M7-E7) -> 0 | O7: =(Parameters_Public!$C$23*(L7-D7)+Parameters_Public!$C$24*(M7-E7)) -> 0 | P7: =YearMap!E2 -> 1000 | Q7: =IF(Scenarios!N3="lease", YearMap!F2, YearMap!G2) -> 0.45 | R7: =IF(Scenarios!D3=1, Q7*H7, H7) -> 1404302.9 | S7: =IF(Scenarios!E3=1, Q7*I7, I7) -> 1617407.2 | T7: =IF(C7="FY2026", (Scenarios!D3+Scenarios!E3)*BaselineCalc!$B$22, 0) -> 0 | U7: =(R7+S7+G7*F7)*J7*(1-K7) -> 6682192.6 | V7: =O7*(G7+P7) -> 0 | W7: =U7+V7+IF(Parameters_Public!$C$26=1, T7, 0) -> 6682192.6 | X7: =IF(F7+O7>0, W7/(F7+O7),"") -> 11560.887 | Y7: =INDEX(YearMap!$I$2:$I$6, MATCH(C7, YearMap!$A$2:$A$6, 0)) -> 5013 | Z7: =W7 - ((Y7 + IF(Parameters_Public!$C$20=1, Parameters_Public!$C$19, 0))*AC7) -> 3350051.5 | AA7: =IF($AC7>0, $Z7/$AC7, 0) -> 5795.9369 | AB7: =MAX(0, (MAX(0, $D7-BaselineCalc!$B$7) + MAX(0, $E7-BaselineCalc!$B$8))) -> 25 | AC7: =L7+M7-N7+O7 -> 578 | AD7: =( (Y7 + IF(Parameters_Public!$C20=1, INDEX(YearMap!$O$2:$O$6, MATCH(C7, YearMap!$A$2:$A$6, 0)), 0)) * AC7 ) + AC7*INDEX(YearMap!$P$2:$P$6, MATCH(C7, YearMap!$A$2:$A$6, 0)) + AB7*( INDEX(YearMap!$R$2:$R$6, MATCH(C7, YearMap!$A$2:$A$6, 0)) - INDEX(YearMap!$P$2:$P$6, MATCH(C7, YearMap!$A$2:$A$6, 0)) ) -> 6318241.1 | AE7: =(W7 - (1-Parameters_Public!$C42)*$G7*$AB7*$J7*(1-$K7)) + AB7*INDEX(YearMap!$Q$2:$Q$6, MATCH(C7, YearMap!$A$2:$A$6, 0)) -> 6527952.4 | AF7: =AD7-AE7 -> -209711.28 | AG7: =B7&"|"&C7 -> E3_StatusQuo_Targets|FY2026
A8: =AG8 -> E3_StatusQuo_Targets|FY2027 | B8: =Scenarios!A3 -> E3_StatusQuo_Targets | C8: FY2027 | D8: =IF(Scenarios!D3=1,0, L8) -> 282 | E8: =IF(Scenarios!E3=1,0, M8) -> 321 | F8: =D8+E8 -> 603 | G8: =YearMap!B3 -> 6574.8743 | H8: =YearMap!C3 -> 1439410.4 | I8: =YearMap!D3 -> 1657842.4 | J8: =1-BaselineCalc!$B$5 -> 0.993 | K8: =Scenarios!G3 -> 0 | L8: =IF(Scenarios!$Q3=1,BaselineCalc!$B$7*(1+Parameters_Public!$C44)^(IF($C8="FY2026",0,IF($C8="FY2027",1,IF($C8="FY2028",2,IF($C8="FY2029",3,IF($C8="FY2030",4,0))))))+ROUND(Scenarios!J3*Scenarios!$F3,0),BaselineCalc!$B$7+ROUND(Scenarios!J3*Scenarios!$F3,0)) -> 282 | M8: =IF(Scenarios!$R3=1,BaselineCalc!$B$8*(1+Parameters_Public!$C45)^(IF($C8="FY2026",0,IF($C8="FY2027",1,IF($C8="FY2028",2,IF($C8="FY2029",3,IF($C8="FY2030",4,0))))))+Scenarios!J3-ROUND(Scenarios!J3*Scenarios!$F3,0),BaselineCalc!$B$8+Scenarios!J3-ROUND(Scenarios!J3*Scenarios!$F3,0)) -> 321 | N8: =(L8-D8) + (M8-E8) -> 0 | O8: =(Parameters_Public!$C$23*(L8-D8)+Parameters_Public!$C$24*(M8-E8)) -> 0 | P8: =YearMap!E3 -> 800 | Q8: =IF(Scenarios!N3="lease", YearMap!F3, YearMap!G3) -> 0.4 | R8: =IF(Scenarios!D3=1, Q8*H8, H8) -> 1439410.4 | S8: =IF(Scenarios!E3=1, Q8*I8, I8) -> 1657842.4 | T8: =IF(C8="FY2026", (Scenarios!D3+Scenarios!E3)*BaselineCalc!$B$22, 0) -> 0 | U8: =(R8+S8+G8*F8)*J8*(1-K8) -> 7012468.7 | V8: =O8*(G8+P8) -> 0 | W8: =U8+V8+IF(Parameters_Public!$C$26=1, T8, 0) -> 7012468.7 | X8: =IF(F8+O8>0, W8/(F8+O8),"") -> 11629.301 | Y8: =INDEX(YearMap!$I$2:$I$6, MATCH(C8, YearMap!$A$2:$A$6, 0)) -> 5138.325 | Z8: =W8 - ((Y8 + IF(Parameters_Public!$C$20=1, Parameters_Public!$C$19, 0))*AC8) -> 3460632.9 | AA8: =IF($AC8>0, $Z8/$AC8, 0) -> 5739.0263 | AB8: =MAX(0, (MAX(0, $D8-BaselineCalc!$B$7) + MAX(0, $E8-BaselineCalc!$B$8))) -> 50 | AC8: =L8+M8-N8+O8 -> 603 | AD8: =( (Y8 + IF(Parameters_Public!$C20=1, INDEX(YearMap!$O$2:$O$6, MATCH(C8, YearMap!$A$2:$A$6, 0)), 0)) * AC8 ) + AC8*INDEX(YearMap!$P$2:$P$6, MATCH(C8, YearMap!$A$2:$A$6, 0)) + AB8*( INDEX(YearMap!$R$2:$R$6, MATCH(C8, YearMap!$A$2:$A$6, 0)) - INDEX(YearMap!$P$2:$P$6, MATCH(C8, YearMap!$A$2:$A$6, 0)) ) -> 6737186.5 | AE8: =(W8 - (1-Parameters_Public!$C42)*$G8*$AB8*$J8*(1-$K8)) + AB8*INDEX(YearMap!$Q$2:$Q$6, MATCH(C8, YearMap!$A$2:$A$6, 0)) -> 6694026.2 | AF8: =AD8-AE8 -> 43160.281 | AG8: =B8&"|"&C8 -> E3_StatusQuo_Targets|FY2027
A9: =AG9 -> E3_StatusQuo_Targets|FY2028 | B9: =Scenarios!A3 -> E3_StatusQuo_Targets | C9: FY2028 | D9: =IF(Scenarios!D3=1,0, L9) -> 295 | E9: =IF(Scenarios!E3=1,0, M9) -> 333 | F9: =D9+E9 -> 628 | G9: =YearMap!B4 -> 6739.2461 | H9: =YearMap!C4 -> 1475395.7 | I9: =YearMap!D4 -> 1699288.4 | J9: =1-BaselineCalc!$B$5 -> 0.993 | K9: =Scenarios!G3 -> 0 | L9: =IF(Scenarios!$Q3=1,BaselineCalc!$B$7*(1+Parameters_Public!$C44)^(IF($C9="FY2026",0,IF($C9="FY2027",1,IF($C9="FY2028",2,IF($C9="FY2029",3,IF($C9="FY2030",4,0))))))+ROUND(Scenarios!K3*Scenarios!$F3,0),BaselineCalc!$B$7+ROUND(Scenarios!K3*Scenarios!$F3,0)) -> 295 | M9: =IF(Scenarios!$R3=1,BaselineCalc!$B$8*(1+Parameters_Public!$C45)^(IF($C9="FY2026",0,IF($C9="FY2027",1,IF($C9="FY2028",2,IF($C9="FY2029",3,IF($C9="FY2030",4,0))))))+Scenarios!K3-ROUND(Scenarios!K3*Scenarios!$F3,0),BaselineCalc!$B$8+Scenarios!K3-ROUND(Scenarios!K3*Scenarios!$F3,0)) -> 333 | N9: =(L9-D9) + (M9-E9) -> 0 | O9: =(Parameters_Public!$C$23*(L9-D9)+Parameters_Public!$C$24*(M9-E9)) -> 0 | P9: =YearMap!E4 -> 600 | Q9: =IF(Scenarios!N3="lease", YearMap!F4, YearMap!G4) -> 0.35 | R9: =IF(Scenarios!D3=1, Q9*H9, H9) -> 1475395.7 | S9: =IF(Scenarios!E3=1, Q9*I9, I9) -> 1699288.4 | T9: =IF(C9="FY2026", (Scenarios!D3+Scenarios!E3)*BaselineCalc!$B$22, 0) -> 0 | U9: =(R9+S9+G9*F9)*J9*(1-K9) -> 7355082.2 | V9: =O9*(G9+P9) -> 0 | W9: =U9+V9+IF(Parameters_Public!$C$26=1, T9, 0) -> 7355082.2 | X9: =IF(F9+O9>0, W9/(F9+O9),"") -> 11711.914 | Y9: =INDEX(YearMap!$I$2:$I$6, MATCH(C9, YearMap!$A$2:$A$6, 0)) -> 5266.7831 | Z9: =W9 - ((Y9 + IF(Parameters_Public!$C$20=1, Parameters_Public!$C$19, 0))*AC9) -> 3575317.8 | AA9: =IF($AC9>0, $Z9/$AC9, 0) -> 5693.1812 | AB9: =MAX(0, (MAX(0, $D9-BaselineCalc!$B$7) + MAX(0, $E9-BaselineCalc!$B$8))) -> 75 | AC9: =L9+M9-N9+O9 -> 628 | AD9: =( (Y9 + IF(Parameters_Public!$C20=1, INDEX(YearMap!$O$2:$O$6, MATCH(C9, YearMap!$A$2:$A$6, 0)), 0)) * AC9 ) + AC9*INDEX(YearMap!$P$2:$P$6, MATCH(C9, YearMap!$A$2:$A$6, 0)) + AB9*( INDEX(YearMap!$R$2:$R$6, MATCH(C9, YearMap!$A$2:$A$6, 0)) - INDEX(YearMap!$P$2:$P$6, MATCH(C9, YearMap!$A$2:$A$6, 0)) ) -> 7173130.2 | AE9: =(W9 - (1-Parameters_Public!$C42)*$G9*$AB9*$J9*(1-$K9)) + AB9*INDEX(YearMap!$Q$2:$Q$6, MATCH(C9, YearMap!$A$2:$A$6, 0)) -> 6862176.8 | AF9: =AD9-AE9 -> 310953.37 | AG9: =B9&"|"&C9 -> E3_StatusQuo_Targets|FY2028
A10: =AG10 -> E3_StatusQuo_Targets|FY2029 | B10: =Scenarios!A3 -> E3_StatusQuo_Targets | C10: FY2029 | D10: =IF(Scenarios!D3=1,0, L10) -> 295 | E10: =IF(Scenarios!E3=1,0, M10) -> 333 | F10: =D10+E10 -> 628 | G10: =YearMap!B5 -> 6907.7273 | H10: =YearMap!C5 -> 1512280.6 | I10: =YearMap!D5 -> 1741770.6 | J10: =1-BaselineCalc!$B$5 -> 0.993 | K10: =Scenarios!G3 -> 0 | L10: =IF(Scenarios!$Q3=1,BaselineCalc!$B$7*(1+Parameters_Public!$C44)^(IF($C10="FY2026",0,IF($C10="FY2027",1,IF($C10="FY2028",2,IF($C10="FY2029",3,IF($C10="FY2030",4,0))))))+ROUND(Scenarios!L3*Scenarios!$F3,0),BaselineCalc!$B$7+ROUND(Scenarios!L3*Scenarios!$F3,0)) -> 295 | M10: =IF(Scenarios!$R3=1,BaselineCalc!$B$8*(1+Parameters_Public!$C45)^(IF($C10="FY2026",0,IF($C10="FY2027",1,IF($C10="FY2028",2,IF($C10="FY2029",3,IF($C10="FY2030",4,0))))))+Scenarios!L3-ROUND(Scenarios!L3*Scenarios!$F3,0),BaselineCalc!$B$8+Scenarios!L3-ROUND(Scenarios!L3*Scenarios!$F3,0)) -> 333 | N10: =(L10-D10) + (M10-E10) -> 0 | O10: =(Parameters_Public!$C$23*(L10-D10)+Parameters_Public!$C$24*(M10-E10)) -> 0 | P10: =YearMap!E5 -> 500 | Q10: =IF(Scenarios!N3="lease", YearMap!F5, YearMap!G5) -> 0.3 | R10: =IF(Scenarios!D3=1, Q10*H10, H10) -> 1512280.6 | S10: =IF(Scenarios!E3=1, Q10*I10, I10) -> 1741770.6 | T10: =IF(C10="FY2026", (Scenarios!D3+Scenarios!E3)*BaselineCalc!$B$22, 0) -> 0 | U10: =(R10+S10+G10*F10)*J10*(1-K10) -> 7538959.3 | V10: =O10*(G10+P10) -> 0 | W10: =U10+V10+IF(Parameters_Public!$C$26=1, T10, 0) -> 7538959.3 | X10: =IF(F10+O10>0, W10/(F10+O10),"") -> 12004.712 | Y10: =INDEX(YearMap!$I$2:$I$6, MATCH(C10, YearMap!$A$2:$A$6, 0)) -> 5398.4527 | Z10: =W10 - ((Y10 + IF(Parameters_Public!$C$20=1, Parameters_Public!$C$19, 0))*AC10) -> 3676506.4 | AA10: =IF($AC10>0, $Z10/$AC10, 0) -> 5854.3095 | AB10: =MAX(0, (MAX(0, $D10-BaselineCalc!$B$7) + MAX(0, $E10-BaselineCalc!$B$8))) -> 75 | AC10: =L10+M10-N10+O10 -> 628 | AD10: =( (Y10 + IF(Parameters_Public!$C20=1, INDEX(YearMap!$O$2:$O$6, MATCH(C10, YearMap!$A$2:$A$6, 0)), 0)) * AC10 ) + AC10*INDEX(YearMap!$P$2:$P$6, MATCH(C10, YearMap!$A$2:$A$6, 0)) + AB10*( INDEX(YearMap!$R$2:$R$6, MATCH(C10, YearMap!$A$2:$A$6, 0)) - INDEX(YearMap!$P$2:$P$6, MATCH(C10, YearMap!$A$2:$A$6, 0)) ) -> 7352458.5 | AE10: =(W10 - (1-Parameters_Public!$C42)*$G10*$AB10*$J10*(1-$K10)) + AB10*INDEX(YearMap!$Q$2:$Q$6, MATCH(C10, YearMap!$A$2:$A$6, 0)) -> 7032006.3 | AF10: =AD10-AE10 -> 320452.2 | AG10: =B10&"|"&C10 -> E3_StatusQuo_Targets|FY2029
A11: =AG11 -> E3_StatusQuo_Targets|FY2030 | B11: =Scenarios!A3 -> E3_StatusQuo_Targets | C11: FY2030 | D11: =IF(Scenarios!D3=1,0, L11) -> 295 | E11: =IF(Scenarios!E3=1,0, M11) -> 333 | F11: =D11+E11 -> 628 | G11: =YearMap!B6 -> 7080.4205 | H11: =YearMap!C6 -> 1550087.6 | I11: =YearMap!D6 -> 1785314.9 | J11: =1-BaselineCalc!$B$5 -> 0.993 | K11: =Scenarios!G3 -> 0 | L11: =IF(Scenarios!$Q3=1,BaselineCalc!$B$7*(1+Parameters_Public!$C44)^(IF($C11="FY2026",0,IF($C11="FY2027",1,IF($C11="FY2028",2,IF($C11="FY2029",3,IF($C11="FY2030",4,0))))))+ROUND(Scenarios!M3*Scenarios!$F3,0),BaselineCalc!$B$7+ROUND(Scenarios!M3*Scenarios!$F3,0)) -> 295 | M11: =IF(Scenarios!$R3=1,BaselineCalc!$B$8*(1+Parameters_Public!$C45)^(IF($C11="FY2026",0,IF($C11="FY2027",1,IF($C11="FY2028",2,IF($C11="FY2029",3,IF($C11="FY2030",4,0))))))+Scenarios!M3-ROUND(Scenarios!M3*Scenarios!$F3,0),BaselineCalc!$B$8+Scenarios!M3-ROUND(Scenarios!M3*Scenarios!$F3,0)) -> 333 | N11: =(L11-D11) + (M11-E11) -> 0 | O11: =(Parameters_Public!$C$23*(L11-D11)+Parameters_Public!$C$24*(M11-E11)) -> 0 | P11: =YearMap!E6 -> 300 | Q11: =IF(Scenarios!N3="lease", YearMap!F6, YearMap!G6) -> 0.3 | R11: =IF(Scenarios!D3=1, Q11*H11, H11) -> 1550087.6 | S11: =IF(Scenarios!E3=1, Q11*I11, I11) -> 1785314.9 | T11: =IF(C11="FY2026", (Scenarios!D3+Scenarios!E3)*BaselineCalc!$B$22, 0) -> 0 | U11: =(R11+S11+G11*F11)*J11*(1-K11) -> 7727433.2 | V11: =O11*(G11+P11) -> 0 | W11: =U11+V11+IF(Parameters_Public!$C$26=1, T11, 0) -> 7727433.2 | X11: =IF(F11+O11>0, W11/(F11+O11),"") -> 12304.83 | Y11: =INDEX(YearMap!$I$2:$I$6, MATCH(C11, YearMap!$A$2:$A$6, 0)) -> 5533.414 | Z11: =W11 - ((Y11 + IF(Parameters_Public!$C$20=1, Parameters_Public!$C$19, 0))*AC11) -> 3780224.6 | AA11: =IF($AC11>0, $Z11/$AC11, 0) -> 6019.466 | AB11: =MAX(0, (MAX(0, $D11-BaselineCalc!$B$7) + MAX(0, $E11-BaselineCalc!$B$8))) -> 75 | AC11: =L11+M11-N11+O11 -> 628 | AD11: =( (Y11 + IF(Parameters_Public!$C20=1, INDEX(YearMap!$O$2:$O$6, MATCH(C11, YearMap!$A$2:$A$6, 0)), 0)) * AC11 ) + AC11*INDEX(YearMap!$P$2:$P$6, MATCH(C11, YearMap!$A$2:$A$6, 0)) + AB11*( INDEX(YearMap!$R$2:$R$6, MATCH(C11, YearMap!$A$2:$A$6, 0)) - INDEX(YearMap!$P$2:$P$6, MATCH(C11, YearMap!$A$2:$A$6, 0)) ) -> 7536269.9 | AE11: =(W11 - (1-Parameters_Public!$C42)*$G11*$AB11*$J11*(1-$K11)) + AB11*INDEX(YearMap!$Q$2:$Q$6, MATCH(C11, YearMap!$A$2:$A$6, 0)) -> 7204618.9 | AF11: =AD11-AE11 -> 331651 | AG11: =B11&"|"&C11 -> E3_StatusQuo_Targets|FY2030
A12: =AG12 -> D3_CoLocation_Echo_Targets|FY2026 | B12: =Scenarios!A4 -> D3_CoLocation_Echo_Targets | C12: FY2026 | D12: =IF(Scenarios!D4=1,0, L12) -> 265 | E12: =IF(Scenarios!E4=1,0, M12) -> 304.66667 | F12: =D12+E12 -> 569.66667 | G12: =YearMap!B2 -> 6414.5115 | H12: =YearMap!C2 -> 1404302.9 | I12: =YearMap!D2 -> 1617407.2 | J12: =1-BaselineCalc!$B$5 -> 0.993 | K12: =Scenarios!G4 -> 0.05 | L12: =IF(Scenarios!$Q4=1,BaselineCalc!$B$7*(1+Parameters_Public!$C44)^(IF($C12="FY2026",0,IF($C12="FY2027",1,IF($C12="FY2028",2,IF($C12="FY2029",3,IF($C12="FY2030",4,0))))))+ROUND(Scenarios!I4*Scenarios!$F4,0),BaselineCalc!$B$7+ROUND(Scenarios!I4*Scenarios!$F4,0)) -> 265 | M12: =IF(Scenarios!$R4=1,BaselineCalc!$B$8*(1+Parameters_Public!$C45)^(IF($C12="FY2026",0,IF($C12="FY2027",1,IF($C12="FY2028",2,IF($C12="FY2029",3,IF($C12="FY2030",4,0))))))+Scenarios!I4-ROUND(Scenarios!I4*Scenarios!$F4,0),BaselineCalc!$B$8+Scenarios!I4-ROUND(Scenarios!I4*Scenarios!$F4,0)) -> 304.66667 | N12: =(L12-D12) + (M12-E12) -> 0 | O12: =(Parameters_Public!$C$23*(L12-D12)+Parameters_Public!$C$24*(M12-E12)) -> 0 | P12: =YearMap!E2 -> 1000 | Q12: =IF(Scenarios!N4="lease", YearMap!F2, YearMap!G2) -> 0.45 | R12: =IF(Scenarios!D4=1, Q12*H12, H12) -> 1404302.9 | S12: =IF(Scenarios!E4=1, Q12*I12, I12) -> 1617407.2 | T12: =IF(C12="FY2026", (Scenarios!D4+Scenarios!E4)*BaselineCalc!$B$22, 0) -> 0 | U12: =(R12+S12+G12*F12)*J12*(1-K12) -> 6297656.9 | V12: =O12*(G12+P12) -> 0 | W12: =U12+V12+IF(Parameters_Public!$C$26=1, T12, 0) -> 6297656.9 | X12: =IF(F12+O12>0, W12/(F12+O12),"") -> 11054.986 | Y12: =INDEX(YearMap!$I$2:$I$6, MATCH(C12, YearMap!$A$2:$A$6, 0)) -> 5013 | Z12: =W12 - ((Y12 + IF(Parameters_Public!$C$20=1, Parameters_Public!$C$19, 0))*AC12) -> 3013557.1 | AA12: =IF($AC12>0, $Z12/$AC12, 0) -> 5290.0358 | AB12: =MAX(0, (MAX(0, $D12-BaselineCalc!$B$7) + MAX(0, $E12-BaselineCalc!$B$8))) -> 16.666667 | AC12: =L12+M12-N12+O12 -> 569.66667 | AD12: =( (Y12 + IF(Parameters_Public!$C20=1, INDEX(YearMap!$O$2:$O$6, MATCH(C12, YearMap!$A$2:$A$6, 0)), 0)) * AC12 ) + AC12*INDEX(YearMap!$P$2:$P$6, MATCH(C12, YearMap!$A$2:$A$6, 0)) + AB12*( INDEX(YearMap!$R$2:$R$6, MATCH(C12, YearMap!$A$2:$A$6, 0)) - INDEX(YearMap!$P$2:$P$6, MATCH(C12, YearMap!$A$2:$A$6, 0)) ) -> 6233366.5 | AE12: =(W12 - (1-Parameters_Public!$C42)*$G12*$AB12*$J12*(1-$K12)) + AB12*INDEX(YearMap!$Q$2:$Q$6, MATCH(C12, YearMap!$A$2:$A$6, 0)) -> 6200138.1 | AF12: =AD12-AE12 -> 33228.422 | AG12: =B12&"|"&C12 -> D3_CoLocation_Echo_Targets|FY2026
A13: =AG13 -> D3_CoLocation_Echo_Targets|FY2027 | B13: =Scenarios!A4 -> D3_CoLocation_Echo_Targets | C13: FY2027 | D13: =IF(Scenarios!D4=1,0, L13) -> 274 | E13: =IF(Scenarios!E4=1,0, M13) -> 312.33333 | F13: =D13+E13 -> 586.33333 | G13: =YearMap!B3 -> 6574.8743 | H13: =YearMap!C3 -> 1439410.4 | I13: =YearMap!D3 -> 1657842.4 | J13: =1-BaselineCalc!$B$5 -> 0.993 | K13: =Scenarios!G4 -> 0.05 | L13: =IF(Scenarios!$Q4=1,BaselineCalc!$B$7*(1+Parameters_Public!$C44)^(IF($C13="FY2026",0,IF($C13="FY2027",1,IF($C13="FY2028",2,IF($C13="FY2029",3,IF($C13="FY2030",4,0))))))+ROUND(Scenarios!J4*Scenarios!$F4,0),BaselineCalc!$B$7+ROUND(Scenarios!J4*Scenarios!$F4,0)) -> 274 | M13: =IF(Scenarios!$R4=1,BaselineCalc!$B$8*(1+Parameters_Public!$C45)^(IF($C13="FY2026",0,IF($C13="FY2027",1,IF($C13="FY2028",2,IF($C13="FY2029",3,IF($C13="FY2030",4,0))))))+Scenarios!J4-ROUND(Scenarios!J4*Scenarios!$F4,0),BaselineCalc!$B$8+Scenarios!J4-ROUND(Scenarios!J4*Scenarios!$F4,0)) -> 312.33333 | N13: =(L13-D13) + (M13-E13) -> 0 | O13: =(Parameters_Public!$C$23*(L13-D13)+Parameters_Public!$C$24*(M13-E13)) -> 0 | P13: =YearMap!E3 -> 800 | Q13: =IF(Scenarios!N4="lease", YearMap!F3, YearMap!G3) -> 0.4 | R13: =IF(Scenarios!D4=1, Q13*H13, H13) -> 1439410.4 | S13: =IF(Scenarios!E4=1, Q13*I13, I13) -> 1657842.4 | T13: =IF(C13="FY2026", (Scenarios!D4+Scenarios!E4)*BaselineCalc!$B$22, 0) -> 0 | U13: =(R13+S13+G13*F13)*J13*(1-K13) -> 6558471.8 | V13: =O13*(G13+P13) -> 0 | W13: =U13+V13+IF(Parameters_Public!$C$26=1, T13, 0) -> 6558471.8 | X13: =IF(F13+O13>0, W13/(F13+O13),"") -> 11185.569 | Y13: =INDEX(YearMap!$I$2:$I$6, MATCH(C13, YearMap!$A$2:$A$6, 0)) -> 5138.325 | Z13: =W13 - ((Y13 + IF(Parameters_Public!$C$20=1, Parameters_Public!$C$19, 0))*AC13) -> 3104807.2 | AA13: =IF($AC13>0, $Z13/$AC13, 0) -> 5295.2937 | AB13: =MAX(0, (MAX(0, $D13-BaselineCalc!$B$7) + MAX(0, $E13-BaselineCalc!$B$8))) -> 33.333333 | AC13: =L13+M13-N13+O13 -> 586.33333 | AD13: =( (Y13 + IF(Parameters_Public!$C20=1, INDEX(YearMap!$O$2:$O$6, MATCH(C13, YearMap!$A$2:$A$6, 0)), 0)) * AC13 ) + AC13*INDEX(YearMap!$P$2:$P$6, MATCH(C13, YearMap!$A$2:$A$6, 0)) + AB13*( INDEX(YearMap!$R$2:$R$6, MATCH(C13, YearMap!$A$2:$A$6, 0)) - INDEX(YearMap!$P$2:$P$6, MATCH(C13, YearMap!$A$2:$A$6, 0)) ) -> 6563193.6 | AE13: =(W13 - (1-Parameters_Public!$C42)*$G13*$AB13*$J13*(1-$K13)) + AB13*INDEX(YearMap!$Q$2:$Q$6, MATCH(C13, YearMap!$A$2:$A$6, 0)) -> 6357058.2 | AF13: =AD13-AE13 -> 206135.36 | AG13: =B13&"|"&C13 -> D3_CoLocation_Echo_Targets|FY2027
A14: =AG14 -> D3_CoLocation_Echo_Targets|FY2028 | B14: =Scenarios!A4 -> D3_CoLocation_Echo_Targets | C14: FY2028 | D14: =IF(Scenarios!D4=1,0, L14) -> 282 | E14: =IF(Scenarios!E4=1,0, M14) -> 321 | F14: =D14+E14 -> 603 | G14: =YearMap!B4 -> 6739.2461 | H14: =YearMap!C4 -> 1475395.7 | I14: =YearMap!D4 -> 1699288.4 | J14: =1-BaselineCalc!$B$5 -> 0.993 | K14: =Scenarios!G4 -> 0.05 | L14: =IF(Scenarios!$Q4=1,BaselineCalc!$B$7*(1+Parameters_Public!$C44)^(IF($C14="FY2026",0,IF($C14="FY2027",1,IF($C14="FY2028",2,IF($C14="FY2029",3,IF($C14="FY2030",4,0))))))+ROUND(Scenarios!K4*Scenarios!$F4,0),BaselineCalc!$B$7+ROUND(Scenarios!K4*Scenarios!$F4,0)) -> 282 | M14: =IF(Scenarios!$R4=1,BaselineCalc!$B$8*(1+Parameters_Public!$C45)^(IF($C14="FY2026",0,IF($C14="FY2027",1,IF($C14="FY2028",2,IF($C14="FY2029",3,IF($C14="FY2030",4,0))))))+Scenarios!K4-ROUND(Scenarios!K4*Scenarios!$F4,0),BaselineCalc!$B$8+Scenarios!K4-ROUND(Scenarios!K4*Scenarios!$F4,0)) -> 321 | N14: =(L14-D14) + (M14-E14) -> 0 | O14: =(Parameters_Public!$C$23*(L14-D14)+Parameters_Public!$C$24*(M14-E14)) -> 0 | P14: =YearMap!E4 -> 600 | Q14: =IF(Scenarios!N4="lease", YearMap!F4, YearMap!G4) -> 0.35 | R14: =IF(Scenarios!D4=1, Q14*H14, H14) -> 1475395.7 | S14: =IF(Scenarios!E4=1, Q14*I14, I14) -> 1699288.4 | T14: =IF(C14="FY2026", (Scenarios!D4+Scenarios!E4)*BaselineCalc!$B$22, 0) -> 0 | U14: =(R14+S14+G14*F14)*J14*(1-K14) -> 6828391.4 | V14: =O14*(G14+P14) -> 0 | W14: =U14+V14+IF(Parameters_Public!$C$26=1, T14, 0) -> 6828391.4 | X14: =IF(F14+O14>0, W14/(F14+O14),"") -> 11324.032 | Y14: =INDEX(YearMap!$I$2:$I$6, MATCH(C14, YearMap!$A$2:$A$6, 0)) -> 5266.7831 | Z14: =W14 - ((Y14 + IF(Parameters_Public!$C$20=1, Parameters_Public!$C$19, 0))*AC14) -> 3199095.3 | AA14: =IF($AC14>0, $Z14/$AC14, 0) -> 5305.299 | AB14: =MAX(0, (MAX(0, $D14-BaselineCalc!$B$7) + MAX(0, $E14-BaselineCalc!$B$8))) -> 50 | AC14: =L14+M14-N14+O14 -> 603 | AD14: =( (Y14 + IF(Parameters_Public!$C20=1, INDEX(YearMap!$O$2:$O$6, MATCH(C14, YearMap!$A$2:$A$6, 0)), 0)) * AC14 ) + AC14*INDEX(YearMap!$P$2:$P$6, MATCH(C14, YearMap!$A$2:$A$6, 0)) + AB14*( INDEX(YearMap!$R$2:$R$6, MATCH(C14, YearMap!$A$2:$A$6, 0)) - INDEX(YearMap!$P$2:$P$6, MATCH(C14, YearMap!$A$2:$A$6, 0)) ) -> 6905616.1 | AE14: =(W14 - (1-Parameters_Public!$C42)*$G14*$AB14*$J14*(1-$K14)) + AB14*INDEX(YearMap!$Q$2:$Q$6, MATCH(C14, YearMap!$A$2:$A$6, 0)) -> 6516518 | AF14: =AD14-AE14 -> 389098.13 | AG14: =B14&"|"&C14 -> D3_CoLocation_Echo_Targets|FY2028
A15: =AG15 -> D3_CoLocation_Echo_Targets|FY2029 | B15: =Scenarios!A4 -> D3_CoLocation_Echo_Targets | C15: FY2029 | D15: =IF(Scenarios!D4=1,0, L15) -> 282 | E15: =IF(Scenarios!E4=1,0, M15) -> 321 | F15: =D15+E15 -> 603 | G15: =YearMap!B5 -> 6907.7273 | H15: =YearMap!C5 -> 1512280.6 | I15: =YearMap!D5 -> 1741770.6 | J15: =1-BaselineCalc!$B$5 -> 0.993 | K15: =Scenarios!G4 -> 0.05 | L15: =IF(Scenarios!$Q4=1,BaselineCalc!$B$7*(1+Parameters_Public!$C44)^(IF($C15="FY2026",0,IF($C15="FY2027",1,IF($C15="FY2028",2,IF($C15="FY2029",3,IF($C15="FY2030",4,0))))))+ROUND(Scenarios!L4*Scenarios!$F4,0),BaselineCalc!$B$7+ROUND(Scenarios!L4*Scenarios!$F4,0)) -> 282 | M15: =IF(Scenarios!$R4=1,BaselineCalc!$B$8*(1+Parameters_Public!$C45)^(IF($C15="FY2026",0,IF($C15="FY2027",1,IF($C15="FY2028",2,IF($C15="FY2029",3,IF($C15="FY2030",4,0))))))+Scenarios!L4-ROUND(Scenarios!L4*Scenarios!$F4,0),BaselineCalc!$B$8+Scenarios!L4-ROUND(Scenarios!L4*Scenarios!$F4,0)) -> 321 | N15: =(L15-D15) + (M15-E15) -> 0 | O15: =(Parameters_Public!$C$23*(L15-D15)+Parameters_Public!$C$24*(M15-E15)) -> 0 | P15: =YearMap!E5 -> 500 | Q15: =IF(Scenarios!N4="lease", YearMap!F5, YearMap!G5) -> 0.3 | R15: =IF(Scenarios!D4=1, Q15*H15, H15) -> 1512280.6 | S15: =IF(Scenarios!E4=1, Q15*I15, I15) -> 1741770.6 | T15: =IF(C15="FY2026", (Scenarios!D4+Scenarios!E4)*BaselineCalc!$B$22, 0) -> 0 | U15: =(R15+S15+G15*F15)*J15*(1-K15) -> 6999101.2 | V15: =O15*(G15+P15) -> 0 | W15: =U15+V15+IF(Parameters_Public!$C$26=1, T15, 0) -> 6999101.2 | X15: =IF(F15+O15>0, W15/(F15+O15),"") -> 11607.133 | Y15: =INDEX(YearMap!$I$2:$I$6, MATCH(C15, YearMap!$A$2:$A$6, 0)) -> 5398.4527 | Z15: =W15 - ((Y15 + IF(Parameters_Public!$C$20=1, Parameters_Public!$C$19, 0))*AC15) -> 3290408.3 | AA15: =IF($AC15>0, $Z15/$AC15, 0) -> 5456.7303 | AB15: =MAX(0, (MAX(0, $D15-BaselineCalc!$B$7) + MAX(0, $E15-BaselineCalc!$B$8))) -> 50 | AC15: =L15+M15-N15+O15 -> 603 | AD15: =( (Y15 + IF(Parameters_Public!$C20=1, INDEX(YearMap!$O$2:$O$6, MATCH(C15, YearMap!$A$2:$A$6, 0)), 0)) * AC15 ) + AC15*INDEX(YearMap!$P$2:$P$6, MATCH(C15, YearMap!$A$2:$A$6, 0)) + AB15*( INDEX(YearMap!$R$2:$R$6, MATCH(C15, YearMap!$A$2:$A$6, 0)) - INDEX(YearMap!$P$2:$P$6, MATCH(C15, YearMap!$A$2:$A$6, 0)) ) -> 7078256.5 | AE15: =(W15 - (1-Parameters_Public!$C42)*$G15*$AB15*$J15*(1-$K15)) + AB15*INDEX(YearMap!$Q$2:$Q$6, MATCH(C15, YearMap!$A$2:$A$6, 0)) -> 6678281 | AF15: =AD15-AE15 -> 399975.58 | AG15: =B15&"|"&C15 -> D3_CoLocation_Echo_Targets|FY2029
A16: =AG16 -> D3_CoLocation_Echo_Targets|FY2030 | B16: =Scenarios!A4 -> D3_CoLocation_Echo_Targets | C16: FY2030 | D16: =IF(Scenarios!D4=1,0, L16) -> 282 | E16: =IF(Scenarios!E4=1,0, M16) -> 321 | F16: =D16+E16 -> 603 | G16: =YearMap!B6 -> 7080.4205 | H16: =YearMap!C6 -> 1550087.6 | I16: =YearMap!D6 -> 1785314.9 | J16: =1-BaselineCalc!$B$5 -> 0.993 | K16: =Scenarios!G4 -> 0.05 | L16: =IF(Scenarios!$Q4=1,BaselineCalc!$B$7*(1+Parameters_Public!$C44)^(IF($C16="FY2026",0,IF($C16="FY2027",1,IF($C16="FY2028",2,IF($C16="FY2029",3,IF($C16="FY2030",4,0))))))+ROUND(Scenarios!M4*Scenarios!$F4,0),BaselineCalc!$B$7+ROUND(Scenarios!M4*Scenarios!$F4,0)) -> 282 | M16: =IF(Scenarios!$R4=1,BaselineCalc!$B$8*(1+Parameters_Public!$C45)^(IF($C16="FY2026",0,IF($C16="FY2027",1,IF($C16="FY2028",2,IF($C16="FY2029",3,IF($C16="FY2030",4,0))))))+Scenarios!M4-ROUND(Scenarios!M4*Scenarios!$F4,0),BaselineCalc!$B$8+Scenarios!M4-ROUND(Scenarios!M4*Scenarios!$F4,0)) -> 321 | N16: =(L16-D16) + (M16-E16) -> 0 | O16: =(Parameters_Public!$C$23*(L16-D16)+Parameters_Public!$C$24*(M16-E16)) -> 0 | P16: =YearMap!E6 -> 300 | Q16: =IF(Scenarios!N4="lease", YearMap!F6, YearMap!G6) -> 0.3 | R16: =IF(Scenarios!D4=1, Q16*H16, H16) -> 1550087.6 | S16: =IF(Scenarios!E4=1, Q16*I16, I16) -> 1785314.9 | T16: =IF(C16="FY2026", (Scenarios!D4+Scenarios!E4)*BaselineCalc!$B$22, 0) -> 0 | U16: =(R16+S16+G16*F16)*J16*(1-K16) -> 7174078.7 | V16: =O16*(G16+P16) -> 0 | W16: =U16+V16+IF(Parameters_Public!$C$26=1, T16, 0) -> 7174078.7 | X16: =IF(F16+O16>0, W16/(F16+O16),"") -> 11897.311 | Y16: =INDEX(YearMap!$I$2:$I$6, MATCH(C16, YearMap!$A$2:$A$6, 0)) -> 5533.414 | Z16: =W16 - ((Y16 + IF(Parameters_Public!$C$20=1, Parameters_Public!$C$19, 0))*AC16) -> 3384004.2 | AA16: =IF($AC16>0, $Z16/$AC16, 0) -> 5611.9473 | AB16: =MAX(0, (MAX(0, $D16-BaselineCalc!$B$7) + MAX(0, $E16-BaselineCalc!$B$8))) -> 50 | AC16: =L16+M16-N16+O16 -> 603 | AD16: =( (Y16 + IF(Parameters_Public!$C20=1, INDEX(YearMap!$O$2:$O$6, MATCH(C16, YearMap!$A$2:$A$6, 0)), 0)) * AC16 ) + AC16*INDEX(YearMap!$P$2:$P$6, MATCH(C16, YearMap!$A$2:$A$6, 0)) + AB16*( INDEX(YearMap!$R$2:$R$6, MATCH(C16, YearMap!$A$2:$A$6, 0)) - INDEX(YearMap!$P$2:$P$6, MATCH(C16, YearMap!$A$2:$A$6, 0)) ) -> 7255212.9 | AE16: =(W16 - (1-Parameters_Public!$C42)*$G16*$AB16*$J16*(1-$K16)) + AB16*INDEX(YearMap!$Q$2:$Q$6, MATCH(C16, YearMap!$A$2:$A$6, 0)) -> 6843113 | AF16: =AD16-AE16 -> 412099.97 | AG16: =B16&"|"&C16 -> D3_CoLocation_Echo_Targets|FY2030
A17: =AG17 -> D1_Grow_Both_Targets|FY2026 | B17: =Scenarios!A5 -> D1_Grow_Both_Targets | C17: FY2026 | D17: =IF(Scenarios!D5=1,0, L17) -> 282 | E17: =IF(Scenarios!E5=1,0, M17) -> 321 | F17: =D17+E17 -> 603 | G17: =YearMap!B2 -> 6414.5115 | H17: =YearMap!C2 -> 1404302.9 | I17: =YearMap!D2 -> 1617407.2 | J17: =1-BaselineCalc!$B$5 -> 0.993 | K17: =Scenarios!G5 -> 0 | L17: =IF(Scenarios!$Q5=1,BaselineCalc!$B$7*(1+Parameters_Public!$C44)^(IF($C17="FY2026",0,IF($C17="FY2027",1,IF($C17="FY2028",2,IF($C17="FY2029",3,IF($C17="FY2030",4,0))))))+ROUND(Scenarios!I5*Scenarios!$F5,0),BaselineCalc!$B$7+ROUND(Scenarios!I5*Scenarios!$F5,0)) -> 282 | M17: =IF(Scenarios!$R5=1,BaselineCalc!$B$8*(1+Parameters_Public!$C45)^(IF($C17="FY2026",0,IF($C17="FY2027",1,IF($C17="FY2028",2,IF($C17="FY2029",3,IF($C17="FY2030",4,0))))))+Scenarios!I5-ROUND(Scenarios!I5*Scenarios!$F5,0),BaselineCalc!$B$8+Scenarios!I5-ROUND(Scenarios!I5*Scenarios!$F5,0)) -> 321 | N17: =(L17-D17) + (M17-E17) -> 0 | O17: =(Parameters_Public!$C$23*(L17-D17)+Parameters_Public!$C$24*(M17-E17)) -> 0 | P17: =YearMap!E2 -> 1000 | Q17: =IF(Scenarios!N5="lease", YearMap!F2, YearMap!G2) -> 0.45 | R17: =IF(Scenarios!D5=1, Q17*H17, H17) -> 1404302.9 | S17: =IF(Scenarios!E5=1, Q17*I17, I17) -> 1617407.2 | T17: =IF(C17="FY2026", (Scenarios!D5+Scenarios!E5)*BaselineCalc!$B$22, 0) -> 0 | U17: =(R17+S17+G17*F17)*J17*(1-K17) -> 6841432.9 | V17: =O17*(G17+P17) -> 0 | W17: =U17+V17+IF(Parameters_Public!$C$26=1, T17, 0) -> 6841432.9 | X17: =IF(F17+O17>0, W17/(F17+O17),"") -> 11345.66 | Y17: =INDEX(YearMap!$I$2:$I$6, MATCH(C17, YearMap!$A$2:$A$6, 0)) -> 5013 | Z17: =W17 - ((Y17 + IF(Parameters_Public!$C$20=1, Parameters_Public!$C$19, 0))*AC17) -> 3365168 | AA17: =IF($AC17>0, $Z17/$AC17, 0) -> 5580.7098 | AB17: =MAX(0, (MAX(0, $D17-BaselineCalc!$B$7) + MAX(0, $E17-BaselineCalc!$B$8))) -> 50 | AC17: =L17+M17-N17+O17 -> 603 | AD17: =( (Y17 + IF(Parameters_Public!$C20=1, INDEX(YearMap!$O$2:$O$6, MATCH(C17, YearMap!$A$2:$A$6, 0)), 0)) * AC17 ) + AC17*INDEX(YearMap!$P$2:$P$6, MATCH(C17, YearMap!$A$2:$A$6, 0)) + AB17*( INDEX(YearMap!$R$2:$R$6, MATCH(C17, YearMap!$A$2:$A$6, 0)) - INDEX(YearMap!$P$2:$P$6, MATCH(C17, YearMap!$A$2:$A$6, 0)) ) -> 6572864.8 | AE17: =(W17 - (1-Parameters_Public!$C42)*$G17*$AB17*$J17*(1-$K17)) + AB17*INDEX(YearMap!$Q$2:$Q$6, MATCH(C17, YearMap!$A$2:$A$6, 0)) -> 6532952.4 | AF17: =AD17-AE17 -> 39912.469 | AG17: =B17&"|"&C17 -> D1_Grow_Both_Targets|FY2026
A18: =AG18 -> D1_Grow_Both_Targets|FY2027 | B18: =Scenarios!A5 -> D1_Grow_Both_Targets | C18: FY2027 | D18: =IF(Scenarios!D5=1,0, L18) -> 307 | E18: =IF(Scenarios!E5=1,0, M18) -> 346 | F18: =D18+E18 -> 653 | G18: =YearMap!B3 -> 6574.8743 | H18: =YearMap!C3 -> 1439410.4 | I18: =YearMap!D3 -> 1657842.4 | J18: =1-BaselineCalc!$B$5 -> 0.993 | K18: =Scenarios!G5 -> 0 | L18: =IF(Scenarios!$Q5=1,BaselineCalc!$B$7*(1+Parameters_Public!$C44)^(IF($C18="FY2026",0,IF($C18="FY2027",1,IF($C18="FY2028",2,IF($C18="FY2029",3,IF($C18="FY2030",4,0))))))+ROUND(Scenarios!J5*Scenarios!$F5,0),BaselineCalc!$B$7+ROUND(Scenarios!J5*Scenarios!$F5,0)) -> 307 | M18: =IF(Scenarios!$R5=1,BaselineCalc!$B$8*(1+Parameters_Public!$C45)^(IF($C18="FY2026",0,IF($C18="FY2027",1,IF($C18="FY2028",2,IF($C18="FY2029",3,IF($C18="FY2030",4,0))))))+Scenarios!J5-ROUND(Scenarios!J5*Scenarios!$F5,0),BaselineCalc!$B$8+Scenarios!J5-ROUND(Scenarios!J5*Scenarios!$F5,0)) -> 346 | N18: =(L18-D18) + (M18-E18) -> 0 | O18: =(Parameters_Public!$C$23*(L18-D18)+Parameters_Public!$C$24*(M18-E18)) -> 0 | P18: =YearMap!E3 -> 800 | Q18: =IF(Scenarios!N5="lease", YearMap!F3, YearMap!G3) -> 0.4 | R18: =IF(Scenarios!D5=1, Q18*H18, H18) -> 1439410.4 | S18: =IF(Scenarios!E5=1, Q18*I18, I18) -> 1657842.4 | T18: =IF(C18="FY2026", (Scenarios!D5+Scenarios!E5)*BaselineCalc!$B$22, 0) -> 0 | U18: =(R18+S18+G18*F18)*J18*(1-K18) -> 7338911.2 | V18: =O18*(G18+P18) -> 0 | W18: =U18+V18+IF(Parameters_Public!$C$26=1, T18, 0) -> 7338911.2 | X18: =IF(F18+O18>0, W18/(F18+O18),"") -> 11238.761 | Y18: =INDEX(YearMap!$I$2:$I$6, MATCH(C18, YearMap!$A$2:$A$6, 0)) -> 5138.325 | Z18: =W18 - ((Y18 + IF(Parameters_Public!$C$20=1, Parameters_Public!$C$19, 0))*AC18) -> 3492561.6 | AA18: =IF($AC18>0, $Z18/$AC18, 0) -> 5348.4864 | AB18: =MAX(0, (MAX(0, $D18-BaselineCalc!$B$7) + MAX(0, $E18-BaselineCalc!$B$8))) -> 100 | AC18: =L18+M18-N18+O18 -> 653 | AD18: =( (Y18 + IF(Parameters_Public!$C20=1, INDEX(YearMap!$O$2:$O$6, MATCH(C18, YearMap!$A$2:$A$6, 0)), 0)) * AC18 ) + AC18*INDEX(YearMap!$P$2:$P$6, MATCH(C18, YearMap!$A$2:$A$6, 0)) + AB18*( INDEX(YearMap!$R$2:$R$6, MATCH(C18, YearMap!$A$2:$A$6, 0)) - INDEX(YearMap!$P$2:$P$6, MATCH(C18, YearMap!$A$2:$A$6, 0)) ) -> 7259165.2 | AE18: =(W18 - (1-Parameters_Public!$C42)*$G18*$AB18*$J18*(1-$K18)) + AB18*INDEX(YearMap!$Q$2:$Q$6, MATCH(C18, YearMap!$A$2:$A$6, 0)) -> 6702026.2 | AF18: =AD18-AE18 -> 557138.97 | AG18: =B18&"|"&C18 -> D1_Grow_Both_Targets|FY2027
A19: =AG19 -> D1_Grow_Both_Targets|FY2028 | B19: =Scenarios!A5 -> D1_Grow_Both_Targets | C19: FY2028 | D19: =IF(Scenarios!D5=1,0, L19) -> 332 | E19: =IF(Scenarios!E5=1,0, M19) -> 371 | F19: =D19+E19 -> 703 | G19: =YearMap!B4 -> 6739.2461 | H19: =YearMap!C4 -> 1475395.7 | I19: =YearMap!D4 -> 1699288.4 | J19: =1-BaselineCalc!$B$5 -> 0.993 | K19: =Scenarios!G5 -> 0 | L19: =IF(Scenarios!$Q5=1,BaselineCalc!$B$7*(1+Parameters_Public!$C44)^(IF($C19="FY2026",0,IF($C19="FY2027",1,IF($C19="FY2028",2,IF($C19="FY2029",3,IF($C19="FY2030",4,0))))))+ROUND(Scenarios!K5*Scenarios!$F5,0),BaselineCalc!$B$7+ROUND(Scenarios!K5*Scenarios!$F5,0)) -> 332 | M19: =IF(Scenarios!$R5=1,BaselineCalc!$B$8*(1+Parameters_Public!$C45)^(IF($C19="FY2026",0,IF($C19="FY2027",1,IF($C19="FY2028",2,IF($C19="FY2029",3,IF($C19="FY2030",4,0))))))+Scenarios!K5-ROUND(Scenarios!K5*Scenarios!$F5,0),BaselineCalc!$B$8+Scenarios!K5-ROUND(Scenarios!K5*Scenarios!$F5,0)) -> 371 | N19: =(L19-D19) + (M19-E19) -> 0 | O19: =(Parameters_Public!$C$23*(L19-D19)+Parameters_Public!$C$24*(M19-E19)) -> 0 | P19: =YearMap!E4 -> 600 | Q19: =IF(Scenarios!N5="lease", YearMap!F4, YearMap!G4) -> 0.35 | R19: =IF(Scenarios!D5=1, Q19*H19, H19) -> 1475395.7 | S19: =IF(Scenarios!E5=1, Q19*I19, I19) -> 1699288.4 | T19: =IF(C19="FY2026", (Scenarios!D5+Scenarios!E5)*BaselineCalc!$B$22, 0) -> 0 | U19: =(R19+S19+G19*F19)*J19*(1-K19) -> 7856987.6 | V19: =O19*(G19+P19) -> 0 | W19: =U19+V19+IF(Parameters_Public!$C$26=1, T19, 0) -> 7856987.6 | X19: =IF(F19+O19>0, W19/(F19+O19),"") -> 11176.369 | Y19: =INDEX(YearMap!$I$2:$I$6, MATCH(C19, YearMap!$A$2:$A$6, 0)) -> 5266.7831 | Z19: =W19 - ((Y19 + IF(Parameters_Public!$C$20=1, Parameters_Public!$C$19, 0))*AC19) -> 3625818.2 | AA19: =IF($AC19>0, $Z19/$AC19, 0) -> 5157.6361 | AB19: =MAX(0, (MAX(0, $D19-BaselineCalc!$B$7) + MAX(0, $E19-BaselineCalc!$B$8))) -> 150 | AC19: =L19+M19-N19+O19 -> 703 | AD19: =( (Y19 + IF(Parameters_Public!$C20=1, INDEX(YearMap!$O$2:$O$6, MATCH(C19, YearMap!$A$2:$A$6, 0)), 0)) * AC19 ) + AC19*INDEX(YearMap!$P$2:$P$6, MATCH(C19, YearMap!$A$2:$A$6, 0)) + AB19*( INDEX(YearMap!$R$2:$R$6, MATCH(C19, YearMap!$A$2:$A$6, 0)) - INDEX(YearMap!$P$2:$P$6, MATCH(C19, YearMap!$A$2:$A$6, 0)) ) -> 7975672.4 | AE19: =(W19 - (1-Parameters_Public!$C42)*$G19*$AB19*$J19*(1-$K19)) + AB19*INDEX(YearMap!$Q$2:$Q$6, MATCH(C19, YearMap!$A$2:$A$6, 0)) -> 6871176.8 | AF19: =AD19-AE19 -> 1104495.6 | AG19: =B19&"|"&C19 -> D1_Grow_Both_Targets|FY2028
A20: =AG20 -> D1_Grow_Both_Targets|FY2029 | B20: =Scenarios!A5 -> D1_Grow_Both_Targets | C20: FY2029 | D20: =IF(Scenarios!D5=1,0, L20) -> 332 | E20: =IF(Scenarios!E5=1,0, M20) -> 371 | F20: =D20+E20 -> 703 | G20: =YearMap!B5 -> 6907.7273 | H20: =YearMap!C5 -> 1512280.6 | I20: =YearMap!D5 -> 1741770.6 | J20: =1-BaselineCalc!$B$5 -> 0.993 | K20: =Scenarios!G5 -> 0 | L20: =IF(Scenarios!$Q5=1,BaselineCalc!$B$7*(1+Parameters_Public!$C44)^(IF($C20="FY2026",0,IF($C20="FY2027",1,IF($C20="FY2028",2,IF($C20="FY2029",3,IF($C20="FY2030",4,0))))))+ROUND(Scenarios!L5*Scenarios!$F5,0),BaselineCalc!$B$7+ROUND(Scenarios!L5*Scenarios!$F5,0)) -> 332 | M20: =IF(Scenarios!$R5=1,BaselineCalc!$B$8*(1+Parameters_Public!$C45)^(IF($C20="FY2026",0,IF($C20="FY2027",1,IF($C20="FY2028",2,IF($C20="FY2029",3,IF($C20="FY2030",4,0))))))+Scenarios!L5-ROUND(Scenarios!L5*Scenarios!$F5,0),BaselineCalc!$B$8+Scenarios!L5-ROUND(Scenarios!L5*Scenarios!$F5,0)) -> 371 | N20: =(L20-D20) + (M20-E20) -> 0 | O20: =(Parameters_Public!$C$23*(L20-D20)+Parameters_Public!$C$24*(M20-E20)) -> 0 | P20: =YearMap!E5 -> 500 | Q20: =IF(Scenarios!N5="lease", YearMap!F5, YearMap!G5) -> 0.3 | R20: =IF(Scenarios!D5=1, Q20*H20, H20) -> 1512280.6 | S20: =IF(Scenarios!E5=1, Q20*I20, I20) -> 1741770.6 | T20: =IF(C20="FY2026", (Scenarios!D5+Scenarios!E5)*BaselineCalc!$B$22, 0) -> 0 | U20: =(R20+S20+G20*F20)*J20*(1-K20) -> 8053412.2 | V20: =O20*(G20+P20) -> 0 | W20: =U20+V20+IF(Parameters_Public!$C$26=1, T20, 0) -> 8053412.2 | X20: =IF(F20+O20>0, W20/(F20+O20),"") -> 11455.778 | Y20: =INDEX(YearMap!$I$2:$I$6, MATCH(C20, YearMap!$A$2:$A$6, 0)) -> 5398.4527 | Z20: =W20 - ((Y20 + IF(Parameters_Public!$C$20=1, Parameters_Public!$C$19, 0))*AC20) -> 3729679.1 | AA20: =IF($AC20>0, $Z20/$AC20, 0) -> 5305.3757 | AB20: =MAX(0, (MAX(0, $D20-BaselineCalc!$B$7) + MAX(0, $E20-BaselineCalc!$B$8))) -> 150 | AC20: =L20+M20-N20+O20 -> 703 | AD20: =( (Y20 + IF(Parameters_Public!$C20=1, INDEX(YearMap!$O$2:$O$6, MATCH(C20, YearMap!$A$2:$A$6, 0)), 0)) * AC20 ) + AC20*INDEX(YearMap!$P$2:$P$6, MATCH(C20, YearMap!$A$2:$A$6, 0)) + AB20*( INDEX(YearMap!$R$2:$R$6, MATCH(C20, YearMap!$A$2:$A$6, 0)) - INDEX(YearMap!$P$2:$P$6, MATCH(C20, YearMap!$A$2:$A$6, 0)) ) -> 8175064.3 | AE20: =(W20 - (1-Parameters_Public!$C42)*$G20*$AB20*$J20*(1-$K20)) + AB20*INDEX(YearMap!$Q$2:$Q$6, MATCH(C20, YearMap!$A$2:$A$6, 0)) -> 7039506.3 | AF20: =AD20-AE20 -> 1135558 | AG20: =B20&"|"&C20 -> D1_Grow_Both_Targets|FY2029
A21: =AG21 -> D1_Grow_Both_Targets|FY2030 | B21: =Scenarios!A5 -> D1_Grow_Both_Targets | C21: FY2030 | D21: =IF(Scenarios!D5=1,0, L21) -> 332 | E21: =IF(Scenarios!E5=1,0, M21) -> 371 | F21: =D21+E21 -> 703 | G21: =YearMap!B6 -> 7080.4205 | H21: =YearMap!C6 -> 1550087.6 | I21: =YearMap!D6 -> 1785314.9 | J21: =1-BaselineCalc!$B$5 -> 0.993 | K21: =Scenarios!G5 -> 0 | L21: =IF(Scenarios!$Q5=1,BaselineCalc!$B$7*(1+Parameters_Public!$C44)^(IF($C21="FY2026",0,IF($C21="FY2027",1,IF($C21="FY2028",2,IF($C21="FY2029",3,IF($C21="FY2030",4,0))))))+ROUND(Scenarios!M5*Scenarios!$F5,0),BaselineCalc!$B$7+ROUND(Scenarios!M5*Scenarios!$F5,0)) -> 332 | M21: =IF(Scenarios!$R5=1,BaselineCalc!$B$8*(1+Parameters_Public!$C45)^(IF($C21="FY2026",0,IF($C21="FY2027",1,IF($C21="FY2028",2,IF($C21="FY2029",3,IF($C21="FY2030",4,0))))))+Scenarios!M5-ROUND(Scenarios!M5*Scenarios!$F5,0),BaselineCalc!$B$8+Scenarios!M5-ROUND(Scenarios!M5*Scenarios!$F5,0)) -> 371 | N21: =(L21-D21) + (M21-E21) -> 0 | O21: =(Parameters_Public!$C$23*(L21-D21)+Parameters_Public!$C$24*(M21-E21)) -> 0 | P21: =YearMap!E6 -> 300 | Q21: =IF(Scenarios!N5="lease", YearMap!F6, YearMap!G6) -> 0.3 | R21: =IF(Scenarios!D5=1, Q21*H21, H21) -> 1550087.6 | S21: =IF(Scenarios!E5=1, Q21*I21, I21) -> 1785314.9 | T21: =IF(C21="FY2026", (Scenarios!D5+Scenarios!E5)*BaselineCalc!$B$22, 0) -> 0 | U21: =(R21+S21+G21*F21)*J21*(1-K21) -> 8254747.6 | V21: =O21*(G21+P21) -> 0 | W21: =U21+V21+IF(Parameters_Public!$C$26=1, T21, 0) -> 8254747.6 | X21: =IF(F21+O21>0, W21/(F21+O21),"") -> 11742.173 | Y21: =INDEX(YearMap!$I$2:$I$6, MATCH(C21, YearMap!$A$2:$A$6, 0)) -> 5533.414 | Z21: =W21 - ((Y21 + IF(Parameters_Public!$C$20=1, Parameters_Public!$C$19, 0))*AC21) -> 3836136.6 | AA21: =IF($AC21>0, $Z21/$AC21, 0) -> 5456.8089 | AB21: =MAX(0, (MAX(0, $D21-BaselineCalc!$B$7) + MAX(0, $E21-BaselineCalc!$B$8))) -> 150 | AC21: =L21+M21-N21+O21 -> 703 | AD21: =( (Y21 + IF(Parameters_Public!$C20=1, INDEX(YearMap!$O$2:$O$6, MATCH(C21, YearMap!$A$2:$A$6, 0)), 0)) * AC21 ) + AC21*INDEX(YearMap!$P$2:$P$6, MATCH(C21, YearMap!$A$2:$A$6, 0)) + AB21*( INDEX(YearMap!$R$2:$R$6, MATCH(C21, YearMap!$A$2:$A$6, 0)) - INDEX(YearMap!$P$2:$P$6, MATCH(C21, YearMap!$A$2:$A$6, 0)) ) -> 8379440.9 | AE21: =(W21 - (1-Parameters_Public!$C42)*$G21*$AB21*$J21*(1-$K21)) + AB21*INDEX(YearMap!$Q$2:$Q$6, MATCH(C21, YearMap!$A$2:$A$6, 0)) -> 7209118.9 | AF21: =AD21-AE21 -> 1170321.9 | AG21: =B21&"|"&C21 -> D1_Grow_Both_Targets|FY2030
A22: =AG22 -> E2_StatusQuo_Steady|FY2026 | B22: =Scenarios!A6 -> E2_StatusQuo_Steady | C22: FY2026 | D22: =IF(Scenarios!D6=1,0, L22) -> 257 | E22: =IF(Scenarios!E6=1,0, M22) -> 296 | F22: =D22+E22 -> 553 | G22: =YearMap!B2 -> 6414.5115 | H22: =YearMap!C2 -> 1404302.9 | I22: =YearMap!D2 -> 1617407.2 | J22: =1-BaselineCalc!$B$5 -> 0.993 | K22: =Scenarios!G6 -> 0 | L22: =IF(Scenarios!$Q6=1,BaselineCalc!$B$7*(1+Parameters_Public!$C44)^(IF($C22="FY2026",0,IF($C22="FY2027",1,IF($C22="FY2028",2,IF($C22="FY2029",3,IF($C22="FY2030",4,0))))))+ROUND(Scenarios!I6*Scenarios!$F6,0),BaselineCalc!$B$7+ROUND(Scenarios!I6*Scenarios!$F6,0)) -> 257 | M22: =IF(Scenarios!$R6=1,BaselineCalc!$B$8*(1+Parameters_Public!$C45)^(IF($C22="FY2026",0,IF($C22="FY2027",1,IF($C22="FY2028",2,IF($C22="FY2029",3,IF($C22="FY2030",4,0))))))+Scenarios!I6-ROUND(Scenarios!I6*Scenarios!$F6,0),BaselineCalc!$B$8+Scenarios!I6-ROUND(Scenarios!I6*Scenarios!$F6,0)) -> 296 | N22: =(L22-D22) + (M22-E22) -> 0 | O22: =(Parameters_Public!$C$23*(L22-D22)+Parameters_Public!$C$24*(M22-E22)) -> 0 | P22: =YearMap!E2 -> 1000 | Q22: =IF(Scenarios!N6="lease", YearMap!F2, YearMap!G2) -> 0.45 | R22: =IF(Scenarios!D6=1, Q22*H22, H22) -> 1404302.9 | S22: =IF(Scenarios!E6=1, Q22*I22, I22) -> 1617407.2 | T22: =IF(C22="FY2026", (Scenarios!D6+Scenarios!E6)*BaselineCalc!$B$22, 0) -> 0 | U22: =(R22+S22+G22*F22)*J22*(1-K22) -> 6522952.4 | V22: =O22*(G22+P22) -> 0 | W22: =U22+V22+IF(Parameters_Public!$C$26=1, T22, 0) -> 6522952.4 | X22: =IF(F22+O22>0, W22/(F22+O22),"") -> 11795.574 | Y22: =INDEX(YearMap!$I$2:$I$6, MATCH(C22, YearMap!$A$2:$A$6, 0)) -> 5013 | Z22: =W22 - ((Y22 + IF(Parameters_Public!$C$20=1, Parameters_Public!$C$19, 0))*AC22) -> 3334935 | AA22: =IF($AC22>0, $Z22/$AC22, 0) -> 6030.6239 | AB22: =MAX(0, (MAX(0, $D22-BaselineCalc!$B$7) + MAX(0, $E22-BaselineCalc!$B$8))) -> 0 | AC22: =L22+M22-N22+O22 -> 553 | AD22: =( (Y22 + IF(Parameters_Public!$C20=1, INDEX(YearMap!$O$2:$O$6, MATCH(C22, YearMap!$A$2:$A$6, 0)), 0)) * AC22 ) + AC22*INDEX(YearMap!$P$2:$P$6, MATCH(C22, YearMap!$A$2:$A$6, 0)) + AB22*( INDEX(YearMap!$R$2:$R$6, MATCH(C22, YearMap!$A$2:$A$6, 0)) - INDEX(YearMap!$P$2:$P$6, MATCH(C22, YearMap!$A$2:$A$6, 0)) ) -> 6063617.3 | AE22: =(W22 - (1-Parameters_Public!$C42)*$G22*$AB22*$J22*(1-$K22)) + AB22*INDEX(YearMap!$Q$2:$Q$6, MATCH(C22, YearMap!$A$2:$A$6, 0)) -> 6522952.4 | AF22: =AD22-AE22 -> -459335.03 | AG22: =B22&"|"&C22 -> E2_StatusQuo_Steady|FY2026
A23: =AG23 -> E2_StatusQuo_Steady|FY2027 | B23: =Scenarios!A6 -> E2_StatusQuo_Steady | C23: FY2027 | D23: =IF(Scenarios!D6=1,0, L23) -> 257 | E23: =IF(Scenarios!E6=1,0, M23) -> 296 | F23: =D23+E23 -> 553 | G23: =YearMap!B3 -> 6574.8743 | H23: =YearMap!C3 -> 1439410.4 | I23: =YearMap!D3 -> 1657842.4 | J23: =1-BaselineCalc!$B$5 -> 0.993 | K23: =Scenarios!G6 -> 0 | L23: =IF(Scenarios!$Q6=1,BaselineCalc!$B$7*(1+Parameters_Public!$C44)^(IF($C23="FY2026",0,IF($C23="FY2027",1,IF($C23="FY2028",2,IF($C23="FY2029",3,IF($C23="FY2030",4,0))))))+ROUND(Scenarios!J6*Scenarios!$F6,0),BaselineCalc!$B$7+ROUND(Scenarios!J6*Scenarios!$F6,0)) -> 257 | M23: =IF(Scenarios!$R6=1,BaselineCalc!$B$8*(1+Parameters_Public!$C45)^(IF($C23="FY2026",0,IF($C23="FY2027",1,IF($C23="FY2028",2,IF($C23="FY2029",3,IF($C23="FY2030",4,0))))))+Scenarios!J6-ROUND(Scenarios!J6*Scenarios!$F6,0),BaselineCalc!$B$8+Scenarios!J6-ROUND(Scenarios!J6*Scenarios!$F6,0)) -> 296 | N23: =(L23-D23) + (M23-E23) -> 0 | O23: =(Parameters_Public!$C$23*(L23-D23)+Parameters_Public!$C$24*(M23-E23)) -> 0 | P23: =YearMap!E3 -> 800 | Q23: =IF(Scenarios!N6="lease", YearMap!F3, YearMap!G3) -> 0.4 | R23: =IF(Scenarios!D6=1, Q23*H23, H23) -> 1439410.4 | S23: =IF(Scenarios!E6=1, Q23*I23, I23) -> 1657842.4 | T23: =IF(C23="FY2026", (Scenarios!D6+Scenarios!E6)*BaselineCalc!$B$22, 0) -> 0 | U23: =(R23+S23+G23*F23)*J23*(1-K23) -> 6686026.2 | V23: =O23*(G23+P23) -> 0 | W23: =U23+V23+IF(Parameters_Public!$C$26=1, T23, 0) -> 6686026.2 | X23: =IF(F23+O23>0, W23/(F23+O23),"") -> 12090.463 | Y23: =INDEX(YearMap!$I$2:$I$6, MATCH(C23, YearMap!$A$2:$A$6, 0)) -> 5138.325 | Z23: =W23 - ((Y23 + IF(Parameters_Public!$C$20=1, Parameters_Public!$C$19, 0))*AC23) -> 3428704.1 | AA23: =IF($AC23>0, $Z23/$AC23, 0) -> 6200.1883 | AB23: =MAX(0, (MAX(0, $D23-BaselineCalc!$B$7) + MAX(0, $E23-BaselineCalc!$B$8))) -> 0 | AC23: =L23+M23-N23+O23 -> 553 | AD23: =( (Y23 + IF(Parameters_Public!$C20=1, INDEX(YearMap!$O$2:$O$6, MATCH(C23, YearMap!$A$2:$A$6, 0)), 0)) * AC23 ) + AC23*INDEX(YearMap!$P$2:$P$6, MATCH(C23, YearMap!$A$2:$A$6, 0)) + AB23*( INDEX(YearMap!$R$2:$R$6, MATCH(C23, YearMap!$A$2:$A$6, 0)) - INDEX(YearMap!$P$2:$P$6, MATCH(C23, YearMap!$A$2:$A$6, 0)) ) -> 6215207.8 | AE23: =(W23 - (1-Parameters_Public!$C42)*$G23*$AB23*$J23*(1-$K23)) + AB23*INDEX(YearMap!$Q$2:$Q$6, MATCH(C23, YearMap!$A$2:$A$6, 0)) -> 6686026.2 | AF23: =AD23-AE23 -> -470818.41 | AG23: =B23&"|"&C23 -> E2_StatusQuo_Steady|FY2027
A24: =AG24 -> E2_StatusQuo_Steady|FY2028 | B24: =Scenarios!A6 -> E2_StatusQuo_Steady | C24: FY2028 | D24: =IF(Scenarios!D6=1,0, L24) -> 257 | E24: =IF(Scenarios!E6=1,0, M24) -> 296 | F24: =D24+E24 -> 553 | G24: =YearMap!B4 -> 6739.2461 | H24: =YearMap!C4 -> 1475395.7 | I24: =YearMap!D4 -> 1699288.4 | J24: =1-BaselineCalc!$B$5 -> 0.993 | K24: =Scenarios!G6 -> 0 | L24: =IF(Scenarios!$Q6=1,BaselineCalc!$B$7*(1+Parameters_Public!$C44)^(IF($C24="FY2026",0,IF($C24="FY2027",1,IF($C24="FY2028",2,IF($C24="FY2029",3,IF($C24="FY2030",4,0))))))+ROUND(Scenarios!K6*Scenarios!$F6,0),BaselineCalc!$B$7+ROUND(Scenarios!K6*Scenarios!$F6,0)) -> 257 | M24: =IF(Scenarios!$R6=1,BaselineCalc!$B$8*(1+Parameters_Public!$C45)^(IF($C24="FY2026",0,IF($C24="FY2027",1,IF($C24="FY2028",2,IF($C24="FY2029",3,IF($C24="FY2030",4,0))))))+Scenarios!K6-ROUND(Scenarios!K6*Scenarios!$F6,0),BaselineCalc!$B$8+Scenarios!K6-ROUND(Scenarios!K6*Scenarios!$F6,0)) -> 296 | N24: =(L24-D24) + (M24-E24) -> 0 | O24: =(Parameters_Public!$C$23*(L24-D24)+Parameters_Public!$C$24*(M24-E24)) -> 0 | P24: =YearMap!E4 -> 600 | Q24: =IF(Scenarios!N6="lease", YearMap!F4, YearMap!G4) -> 0.35 | R24: =IF(Scenarios!D6=1, Q24*H24, H24) -> 1475395.7 | S24: =IF(Scenarios!E6=1, Q24*I24, I24) -> 1699288.4 | T24: =IF(C24="FY2026", (Scenarios!D6+Scenarios!E6)*BaselineCalc!$B$22, 0) -> 0 | U24: =(R24+S24+G24*F24)*J24*(1-K24) -> 6853176.8 | V24: =O24*(G24+P24) -> 0 | W24: =U24+V24+IF(Parameters_Public!$C$26=1, T24, 0) -> 6853176.8 | X24: =IF(F24+O24>0, W24/(F24+O24),"") -> 12392.725 | Y24: =INDEX(YearMap!$I$2:$I$6, MATCH(C24, YearMap!$A$2:$A$6, 0)) -> 5266.7831 | Z24: =W24 - ((Y24 + IF(Parameters_Public!$C$20=1, Parameters_Public!$C$19, 0))*AC24) -> 3524817.4 | AA24: =IF($AC24>0, $Z24/$AC24, 0) -> 6373.9917 | AB24: =MAX(0, (MAX(0, $D24-BaselineCalc!$B$7) + MAX(0, $E24-BaselineCalc!$B$8))) -> 0 | AC24: =L24+M24-N24+O24 -> 553 | AD24: =( (Y24 + IF(Parameters_Public!$C20=1, INDEX(YearMap!$O$2:$O$6, MATCH(C24, YearMap!$A$2:$A$6, 0)), 0)) * AC24 ) + AC24*INDEX(YearMap!$P$2:$P$6, MATCH(C24, YearMap!$A$2:$A$6, 0)) + AB24*( INDEX(YearMap!$R$2:$R$6, MATCH(C24, YearMap!$A$2:$A$6, 0)) - INDEX(YearMap!$P$2:$P$6, MATCH(C24, YearMap!$A$2:$A$6, 0)) ) -> 6370588 | AE24: =(W24 - (1-Parameters_Public!$C42)*$G24*$AB24*$J24*(1-$K24)) + AB24*INDEX(YearMap!$Q$2:$Q$6, MATCH(C24, YearMap!$A$2:$A$6, 0)) -> 6853176.8 | AF24: =AD24-AE24 -> -482588.87 | AG24: =B24&"|"&C24 -> E2_StatusQuo_Steady|FY2028
A25: =AG25 -> E2_StatusQuo_Steady|FY2029 | B25: =Scenarios!A6 -> E2_StatusQuo_Steady | C25: FY2029 | D25: =IF(Scenarios!D6=1,0, L25) -> 257 | E25: =IF(Scenarios!E6=1,0, M25) -> 296 | F25: =D25+E25 -> 553 | G25: =YearMap!B5 -> 6907.7273 | H25: =YearMap!C5 -> 1512280.6 | I25: =YearMap!D5 -> 1741770.6 | J25: =1-BaselineCalc!$B$5 -> 0.993 | K25: =Scenarios!G6 -> 0 | L25: =IF(Scenarios!$Q6=1,BaselineCalc!$B$7*(1+Parameters_Public!$C44)^(IF($C25="FY2026",0,IF($C25="FY2027",1,IF($C25="FY2028",2,IF($C25="FY2029",3,IF($C25="FY2030",4,0))))))+ROUND(Scenarios!L6*Scenarios!$F6,0),BaselineCalc!$B$7+ROUND(Scenarios!L6*Scenarios!$F6,0)) -> 257 | M25: =IF(Scenarios!$R6=1,BaselineCalc!$B$8*(1+Parameters_Public!$C45)^(IF($C25="FY2026",0,IF($C25="FY2027",1,IF($C25="FY2028",2,IF($C25="FY2029",3,IF($C25="FY2030",4,0))))))+Scenarios!L6-ROUND(Scenarios!L6*Scenarios!$F6,0),BaselineCalc!$B$8+Scenarios!L6-ROUND(Scenarios!L6*Scenarios!$F6,0)) -> 296 | N25: =(L25-D25) + (M25-E25) -> 0 | O25: =(Parameters_Public!$C$23*(L25-D25)+Parameters_Public!$C$24*(M25-E25)) -> 0 | P25: =YearMap!E5 -> 500 | Q25: =IF(Scenarios!N6="lease", YearMap!F5, YearMap!G5) -> 0.3 | R25: =IF(Scenarios!D6=1, Q25*H25, H25) -> 1512280.6 | S25: =IF(Scenarios!E6=1, Q25*I25, I25) -> 1741770.6 | T25: =IF(C25="FY2026", (Scenarios!D6+Scenarios!E6)*BaselineCalc!$B$22, 0) -> 0 | U25: =(R25+S25+G25*F25)*J25*(1-K25) -> 7024506.3 | V25: =O25*(G25+P25) -> 0 | W25: =U25+V25+IF(Parameters_Public!$C$26=1, T25, 0) -> 7024506.3 | X25: =IF(F25+O25>0, W25/(F25+O25),"") -> 12702.543 | Y25: =INDEX(YearMap!$I$2:$I$6, MATCH(C25, YearMap!$A$2:$A$6, 0)) -> 5398.4527 | Z25: =W25 - ((Y25 + IF(Parameters_Public!$C$20=1, Parameters_Public!$C$19, 0))*AC25) -> 3623333.6 | AA25: =IF($AC25>0, $Z25/$AC25, 0) -> 6552.1403 | AB25: =MAX(0, (MAX(0, $D25-BaselineCalc!$B$7) + MAX(0, $E25-BaselineCalc!$B$8))) -> 0 | AC25: =L25+M25-N25+O25 -> 553 | AD25: =( (Y25 + IF(Parameters_Public!$C20=1, INDEX(YearMap!$O$2:$O$6, MATCH(C25, YearMap!$A$2:$A$6, 0)), 0)) * AC25 ) + AC25*INDEX(YearMap!$P$2:$P$6, MATCH(C25, YearMap!$A$2:$A$6, 0)) + AB25*( INDEX(YearMap!$R$2:$R$6, MATCH(C25, YearMap!$A$2:$A$6, 0)) - INDEX(YearMap!$P$2:$P$6, MATCH(C25, YearMap!$A$2:$A$6, 0)) ) -> 6529852.7 | AE25: =(W25 - (1-Parameters_Public!$C42)*$G25*$AB25*$J25*(1-$K25)) + AB25*INDEX(YearMap!$Q$2:$Q$6, MATCH(C25, YearMap!$A$2:$A$6, 0)) -> 7024506.3 | AF25: =AD25-AE25 -> -494653.59 | AG25: =B25&"|"&C25 -> E2_StatusQuo_Steady|FY2029
A26: =AG26 -> E2_StatusQuo_Steady|FY2030 | B26: =Scenarios!A6 -> E2_StatusQuo_Steady | C26: FY2030 | D26: =IF(Scenarios!D6=1,0, L26) -> 257 | E26: =IF(Scenarios!E6=1,0, M26) -> 296 | F26: =D26+E26 -> 553 | G26: =YearMap!B6 -> 7080.4205 | H26: =YearMap!C6 -> 1550087.6 | I26: =YearMap!D6 -> 1785314.9 | J26: =1-BaselineCalc!$B$5 -> 0.993 | K26: =Scenarios!G6 -> 0 | L26: =IF(Scenarios!$Q6=1,BaselineCalc!$B$7*(1+Parameters_Public!$C44)^(IF($C26="FY2026",0,IF($C26="FY2027",1,IF($C26="FY2028",2,IF($C26="FY2029",3,IF($C26="FY2030",4,0))))))+ROUND(Scenarios!M6*Scenarios!$F6,0),BaselineCalc!$B$7+ROUND(Scenarios!M6*Scenarios!$F6,0)) -> 257 | M26: =IF(Scenarios!$R6=1,BaselineCalc!$B$8*(1+Parameters_Public!$C45)^(IF($C26="FY2026",0,IF($C26="FY2027",1,IF($C26="FY2028",2,IF($C26="FY2029",3,IF($C26="FY2030",4,0))))))+Scenarios!M6-ROUND(Scenarios!M6*Scenarios!$F6,0),BaselineCalc!$B$8+Scenarios!M6-ROUND(Scenarios!M6*Scenarios!$F6,0)) -> 296 | N26: =(L26-D26) + (M26-E26) -> 0 | O26: =(Parameters_Public!$C$23*(L26-D26)+Parameters_Public!$C$24*(M26-E26)) -> 0 | P26: =YearMap!E6 -> 300 | Q26: =IF(Scenarios!N6="lease", YearMap!F6, YearMap!G6) -> 0.3 | R26: =IF(Scenarios!D6=1, Q26*H26, H26) -> 1550087.6 | S26: =IF(Scenarios!E6=1, Q26*I26, I26) -> 1785314.9 | T26: =IF(C26="FY2026", (Scenarios!D6+Scenarios!E6)*BaselineCalc!$B$22, 0) -> 0 | U26: =(R26+S26+G26*F26)*J26*(1-K26) -> 7200118.9 | V26: =O26*(G26+P26) -> 0 | W26: =U26+V26+IF(Parameters_Public!$C$26=1, T26, 0) -> 7200118.9 | X26: =IF(F26+O26>0, W26/(F26+O26),"") -> 13020.107 | Y26: =INDEX(YearMap!$I$2:$I$6, MATCH(C26, YearMap!$A$2:$A$6, 0)) -> 5533.414 | Z26: =W26 - ((Y26 + IF(Parameters_Public!$C$20=1, Parameters_Public!$C$19, 0))*AC26) -> 3724312.6 | AA26: =IF($AC26>0, $Z26/$AC26, 0) -> 6734.7425 | AB26: =MAX(0, (MAX(0, $D26-BaselineCalc!$B$7) + MAX(0, $E26-BaselineCalc!$B$8))) -> 0 | AC26: =L26+M26-N26+O26 -> 553 | AD26: =( (Y26 + IF(Parameters_Public!$C20=1, INDEX(YearMap!$O$2:$O$6, MATCH(C26, YearMap!$A$2:$A$6, 0)), 0)) * AC26 ) + AC26*INDEX(YearMap!$P$2:$P$6, MATCH(C26, YearMap!$A$2:$A$6, 0)) + AB26*( INDEX(YearMap!$R$2:$R$6, MATCH(C26, YearMap!$A$2:$A$6, 0)) - INDEX(YearMap!$P$2:$P$6, MATCH(C26, YearMap!$A$2:$A$6, 0)) ) -> 6693099 | AE26: =(W26 - (1-Parameters_Public!$C42)*$G26*$AB26*$J26*(1-$K26)) + AB26*INDEX(YearMap!$Q$2:$Q$6, MATCH(C26, YearMap!$A$2:$A$6, 0)) -> 7200118.9 | AF26: =AD26-AE26 -> -507019.93 | AG26: =B26&"|"&C26 -> E2_StatusQuo_Steady|FY2030
A27: =AG27 -> D2_EchoGHubRamp_PimaTargets|FY2026 | B27: =Scenarios!A7 -> D2_EchoGHubRamp_PimaTargets | C27: FY2026 | D27: =IF(Scenarios!D7=1,0, L27) -> 286 | E27: =IF(Scenarios!E7=1,0, M27) -> 308.66667 | F27: =D27+E27 -> 594.66667 | G27: =YearMap!B2 -> 6414.5115 | H27: =YearMap!C2 -> 1404302.9 | I27: =YearMap!D2 -> 1617407.2 | J27: =1-BaselineCalc!$B$5 -> 0.993 | K27: =Scenarios!G7 -> 0 | L27: =IF(Scenarios!$Q7=1,BaselineCalc!$B$7*(1+Parameters_Public!$C44)^(IF($C27="FY2026",0,IF($C27="FY2027",1,IF($C27="FY2028",2,IF($C27="FY2029",3,IF($C27="FY2030",4,0))))))+ROUND(Scenarios!I7*Scenarios!$F7,0),BaselineCalc!$B$7+ROUND(Scenarios!I7*Scenarios!$F7,0)) -> 286 | M27: =IF(Scenarios!$R7=1,BaselineCalc!$B$8*(1+Parameters_Public!$C45)^(IF($C27="FY2026",0,IF($C27="FY2027",1,IF($C27="FY2028",2,IF($C27="FY2029",3,IF($C27="FY2030",4,0))))))+Scenarios!I7-ROUND(Scenarios!I7*Scenarios!$F7,0),BaselineCalc!$B$8+Scenarios!I7-ROUND(Scenarios!I7*Scenarios!$F7,0)) -> 308.66667 | N27: =(L27-D27) + (M27-E27) -> 0 | O27: =(Parameters_Public!$C$23*(L27-D27)+Parameters_Public!$C$24*(M27-E27)) -> 0 | P27: =YearMap!E2 -> 1000 | Q27: =IF(Scenarios!N7="lease", YearMap!F2, YearMap!G2) -> 0.45 | R27: =IF(Scenarios!D7=1, Q27*H27, H27) -> 1404302.9 | S27: =IF(Scenarios!E7=1, Q27*I27, I27) -> 1617407.2 | T27: =IF(C27="FY2026", (Scenarios!D7+Scenarios!E7)*BaselineCalc!$B$22, 0) -> 0 | U27: =(R27+S27+G27*F27)*J27*(1-K27) -> 6788352.8 | V27: =O27*(G27+P27) -> 0 | W27: =U27+V27+IF(Parameters_Public!$C$26=1, T27, 0) -> 6788352.8 | X27: =IF(F27+O27>0, W27/(F27+O27),"") -> 11415.391 | Y27: =INDEX(YearMap!$I$2:$I$6, MATCH(C27, YearMap!$A$2:$A$6, 0)) -> 5013 | Z27: =W27 - ((Y27 + IF(Parameters_Public!$C$20=1, Parameters_Public!$C$19, 0))*AC27) -> 3360129.2 | AA27: =IF($AC27>0, $Z27/$AC27, 0) -> 5650.4415 | AB27: =MAX(0, (MAX(0, $D27-BaselineCalc!$B$7) + MAX(0, $E27-BaselineCalc!$B$8))) -> 41.666667 | AC27: =L27+M27-N27+O27 -> 594.66667 | AD27: =( (Y27 + IF(Parameters_Public!$C20=1, INDEX(YearMap!$O$2:$O$6, MATCH(C27, YearMap!$A$2:$A$6, 0)), 0)) * AC27 ) + AC27*INDEX(YearMap!$P$2:$P$6, MATCH(C27, YearMap!$A$2:$A$6, 0)) + AB27*( INDEX(YearMap!$R$2:$R$6, MATCH(C27, YearMap!$A$2:$A$6, 0)) - INDEX(YearMap!$P$2:$P$6, MATCH(C27, YearMap!$A$2:$A$6, 0)) ) -> 6487990.3 | AE27: =(W27 - (1-Parameters_Public!$C42)*$G27*$AB27*$J27*(1-$K27)) + AB27*INDEX(YearMap!$Q$2:$Q$6, MATCH(C27, YearMap!$A$2:$A$6, 0)) -> 6531285.7 | AF27: =AD27-AE27 -> -43295.447 | AG27: =B27&"|"&C27 -> D2_EchoGHubRamp_PimaTargets|FY2026
A28: =AG28 -> D2_EchoGHubRamp_PimaTargets|FY2027 | B28: =Scenarios!A7 -> D2_EchoGHubRamp_PimaTargets | C28: FY2027 | D28: =IF(Scenarios!D7=1,0, L28) -> 315 | E28: =IF(Scenarios!E7=1,0, M28) -> 321.33333 | F28: =D28+E28 -> 636.33333 | G28: =YearMap!B3 -> 6574.8743 | H28: =YearMap!C3 -> 1439410.4 | I28: =YearMap!D3 -> 1657842.4 | J28: =1-BaselineCalc!$B$5 -> 0.993 | K28: =Scenarios!G7 -> 0 | L28: =IF(Scenarios!$Q7=1,BaselineCalc!$B$7*(1+Parameters_Public!$C44)^(IF($C28="FY2026",0,IF($C28="FY2027",1,IF($C28="FY2028",2,IF($C28="FY2029",3,IF($C28="FY2030",4,0))))))+ROUND(Scenarios!J7*Scenarios!$F7,0),BaselineCalc!$B$7+ROUND(Scenarios!J7*Scenarios!$F7,0)) -> 315 | M28: =IF(Scenarios!$R7=1,BaselineCalc!$B$8*(1+Parameters_Public!$C45)^(IF($C28="FY2026",0,IF($C28="FY2027",1,IF($C28="FY2028",2,IF($C28="FY2029",3,IF($C28="FY2030",4,0))))))+Scenarios!J7-ROUND(Scenarios!J7*Scenarios!$F7,0),BaselineCalc!$B$8+Scenarios!J7-ROUND(Scenarios!J7*Scenarios!$F7,0)) -> 321.33333 | N28: =(L28-D28) + (M28-E28) -> 0 | O28: =(Parameters_Public!$C$23*(L28-D28)+Parameters_Public!$C$24*(M28-E28)) -> 0 | P28: =YearMap!E3 -> 800 | Q28: =IF(Scenarios!N7="lease", YearMap!F3, YearMap!G3) -> 0.4 | R28: =IF(Scenarios!D7=1, Q28*H28, H28) -> 1439410.4 | S28: =IF(Scenarios!E7=1, Q28*I28, I28) -> 1657842.4 | T28: =IF(C28="FY2026", (Scenarios!D7+Scenarios!E7)*BaselineCalc!$B$22, 0) -> 0 | U28: =(R28+S28+G28*F28)*J28*(1-K28) -> 7230097 | V28: =O28*(G28+P28) -> 0 | W28: =U28+V28+IF(Parameters_Public!$C$26=1, T28, 0) -> 7230097 | X28: =IF(F28+O28>0, W28/(F28+O28),"") -> 11362.122 | Y28: =INDEX(YearMap!$I$2:$I$6, MATCH(C28, YearMap!$A$2:$A$6, 0)) -> 5138.325 | Z28: =W28 - ((Y28 + IF(Parameters_Public!$C$20=1, Parameters_Public!$C$19, 0))*AC28) -> 3481918.7 | AA28: =IF($AC28>0, $Z28/$AC28, 0) -> 5471.8471 | AB28: =MAX(0, (MAX(0, $D28-BaselineCalc!$B$7) + MAX(0, $E28-BaselineCalc!$B$8))) -> 83.333333 | AC28: =L28+M28-N28+O28 -> 636.33333 | AD28: =( (Y28 + IF(Parameters_Public!$C20=1, INDEX(YearMap!$O$2:$O$6, MATCH(C28, YearMap!$A$2:$A$6, 0)), 0)) * AC28 ) + AC28*INDEX(YearMap!$P$2:$P$6, MATCH(C28, YearMap!$A$2:$A$6, 0)) + AB28*( INDEX(YearMap!$R$2:$R$6, MATCH(C28, YearMap!$A$2:$A$6, 0)) - INDEX(YearMap!$P$2:$P$6, MATCH(C28, YearMap!$A$2:$A$6, 0)) ) -> 7085172.3 | AE28: =(W28 - (1-Parameters_Public!$C42)*$G28*$AB28*$J28*(1-$K28)) + AB28*INDEX(YearMap!$Q$2:$Q$6, MATCH(C28, YearMap!$A$2:$A$6, 0)) -> 6699359.5 | AF28: =AD28-AE28 -> 385812.74 | AG28: =B28&"|"&C28 -> D2_EchoGHubRamp_PimaTargets|FY2027
A29: =AG29 -> D2_EchoGHubRamp_PimaTargets|FY2028 | B29: =Scenarios!A7 -> D2_EchoGHubRamp_PimaTargets | C29: FY2028 | D29: =IF(Scenarios!D7=1,0, L29) -> 345 | E29: =IF(Scenarios!E7=1,0, M29) -> 333 | F29: =D29+E29 -> 678 | G29: =YearMap!B4 -> 6739.2461 | H29: =YearMap!C4 -> 1475395.7 | I29: =YearMap!D4 -> 1699288.4 | J29: =1-BaselineCalc!$B$5 -> 0.993 | K29: =Scenarios!G7 -> 0 | L29: =IF(Scenarios!$Q7=1,BaselineCalc!$B$7*(1+Parameters_Public!$C44)^(IF($C29="FY2026",0,IF($C29="FY2027",1,IF($C29="FY2028",2,IF($C29="FY2029",3,IF($C29="FY2030",4,0))))))+ROUND(Scenarios!K7*Scenarios!$F7,0),BaselineCalc!$B$7+ROUND(Scenarios!K7*Scenarios!$F7,0)) -> 345 | M29: =IF(Scenarios!$R7=1,BaselineCalc!$B$8*(1+Parameters_Public!$C45)^(IF($C29="FY2026",0,IF($C29="FY2027",1,IF($C29="FY2028",2,IF($C29="FY2029",3,IF($C29="FY2030",4,0))))))+Scenarios!K7-ROUND(Scenarios!K7*Scenarios!$F7,0),BaselineCalc!$B$8+Scenarios!K7-ROUND(Scenarios!K7*Scenarios!$F7,0)) -> 333 | N29: =(L29-D29) + (M29-E29) -> 0 | O29: =(Parameters_Public!$C$23*(L29-D29)+Parameters_Public!$C$24*(M29-E29)) -> 0 | P29: =YearMap!E4 -> 600 | Q29: =IF(Scenarios!N7="lease", YearMap!F4, YearMap!G4) -> 0.35 | R29: =IF(Scenarios!D7=1, Q29*H29, H29) -> 1475395.7 | S29: =IF(Scenarios!E7=1, Q29*I29, I29) -> 1699288.4 | T29: =IF(C29="FY2026", (Scenarios!D7+Scenarios!E7)*BaselineCalc!$B$22, 0) -> 0 | U29: =(R29+S29+G29*F29)*J29*(1-K29) -> 7689685.8 | V29: =O29*(G29+P29) -> 0 | W29: =U29+V29+IF(Parameters_Public!$C$26=1, T29, 0) -> 7689685.8 | X29: =IF(F29+O29>0, W29/(F29+O29),"") -> 11341.719 | Y29: =INDEX(YearMap!$I$2:$I$6, MATCH(C29, YearMap!$A$2:$A$6, 0)) -> 5266.7831 | Z29: =W29 - ((Y29 + IF(Parameters_Public!$C$20=1, Parameters_Public!$C$19, 0))*AC29) -> 3608984.7 | AA29: =IF($AC29>0, $Z29/$AC29, 0) -> 5322.9863 | AB29: =MAX(0, (MAX(0, $D29-BaselineCalc!$B$7) + MAX(0, $E29-BaselineCalc!$B$8))) -> 125 | AC29: =L29+M29-N29+O29 -> 678 | AD29: =( (Y29 + IF(Parameters_Public!$C20=1, INDEX(YearMap!$O$2:$O$6, MATCH(C29, YearMap!$A$2:$A$6, 0)), 0)) * AC29 ) + AC29*INDEX(YearMap!$P$2:$P$6, MATCH(C29, YearMap!$A$2:$A$6, 0)) + AB29*( INDEX(YearMap!$R$2:$R$6, MATCH(C29, YearMap!$A$2:$A$6, 0)) - INDEX(YearMap!$P$2:$P$6, MATCH(C29, YearMap!$A$2:$A$6, 0)) ) -> 7708158.4 | AE29: =(W29 - (1-Parameters_Public!$C42)*$G29*$AB29*$J29*(1-$K29)) + AB29*INDEX(YearMap!$Q$2:$Q$6, MATCH(C29, YearMap!$A$2:$A$6, 0)) -> 6868176.8 | AF29: =AD29-AE29 -> 839981.52 | AG29: =B29&"|"&C29 -> D2_EchoGHubRamp_PimaTargets|FY2028
A30: =AG30 -> D2_EchoGHubRamp_PimaTargets|FY2029 | B30: =Scenarios!A7 -> D2_EchoGHubRamp_PimaTargets | C30: FY2029 | D30: =IF(Scenarios!D7=1,0, L30) -> 345 | E30: =IF(Scenarios!E7=1,0, M30) -> 333 | F30: =D30+E30 -> 678 | G30: =YearMap!B5 -> 6907.7273 | H30: =YearMap!C5 -> 1512280.6 | I30: =YearMap!D5 -> 1741770.6 | J30: =1-BaselineCalc!$B$5 -> 0.993 | K30: =Scenarios!G7 -> 0 | L30: =IF(Scenarios!$Q7=1,BaselineCalc!$B$7*(1+Parameters_Public!$C44)^(IF($C30="FY2026",0,IF($C30="FY2027",1,IF($C30="FY2028",2,IF($C30="FY2029",3,IF($C30="FY2030",4,0))))))+ROUND(Scenarios!L7*Scenarios!$F7,0),BaselineCalc!$B$7+ROUND(Scenarios!L7*Scenarios!$F7,0)) -> 345 | M30: =IF(Scenarios!$R7=1,BaselineCalc!$B$8*(1+Parameters_Public!$C45)^(IF($C30="FY2026",0,IF($C30="FY2027",1,IF($C30="FY2028",2,IF($C30="FY2029",3,IF($C30="FY2030",4,0))))))+Scenarios!L7-ROUND(Scenarios!L7*Scenarios!$F7,0),BaselineCalc!$B$8+Scenarios!L7-ROUND(Scenarios!L7*Scenarios!$F7,0)) -> 333 | N30: =(L30-D30) + (M30-E30) -> 0 | O30: =(Parameters_Public!$C$23*(L30-D30)+Parameters_Public!$C$24*(M30-E30)) -> 0 | P30: =YearMap!E5 -> 500 | Q30: =IF(Scenarios!N7="lease", YearMap!F5, YearMap!G5) -> 0.3 | R30: =IF(Scenarios!D7=1, Q30*H30, H30) -> 1512280.6 | S30: =IF(Scenarios!E7=1, Q30*I30, I30) -> 1741770.6 | T30: =IF(C30="FY2026", (Scenarios!D7+Scenarios!E7)*BaselineCalc!$B$22, 0) -> 0 | U30: =(R30+S30+G30*F30)*J30*(1-K30) -> 7881927.9 | V30: =O30*(G30+P30) -> 0 | W30: =U30+V30+IF(Parameters_Public!$C$26=1, T30, 0) -> 7881927.9 | X30: =IF(F30+O30>0, W30/(F30+O30),"") -> 11625.262 | Y30: =INDEX(YearMap!$I$2:$I$6, MATCH(C30, YearMap!$A$2:$A$6, 0)) -> 5398.4527 | Z30: =W30 - ((Y30 + IF(Parameters_Public!$C$20=1, Parameters_Public!$C$19, 0))*AC30) -> 3711954.9 | AA30: =IF($AC30>0, $Z30/$AC30, 0) -> 5474.8597 | AB30: =MAX(0, (MAX(0, $D30-BaselineCalc!$B$7) + MAX(0, $E30-BaselineCalc!$B$8))) -> 125 | AC30: =L30+M30-N30+O30 -> 678 | AD30: =( (Y30 + IF(Parameters_Public!$C20=1, INDEX(YearMap!$O$2:$O$6, MATCH(C30, YearMap!$A$2:$A$6, 0)), 0)) * AC30 ) + AC30*INDEX(YearMap!$P$2:$P$6, MATCH(C30, YearMap!$A$2:$A$6, 0)) + AB30*( INDEX(YearMap!$R$2:$R$6, MATCH(C30, YearMap!$A$2:$A$6, 0)) - INDEX(YearMap!$P$2:$P$6, MATCH(C30, YearMap!$A$2:$A$6, 0)) ) -> 7900862.3 | AE30: =(W30 - (1-Parameters_Public!$C42)*$G30*$AB30*$J30*(1-$K30)) + AB30*INDEX(YearMap!$Q$2:$Q$6, MATCH(C30, YearMap!$A$2:$A$6, 0)) -> 7037006.3 | AF30: =AD30-AE30 -> 863856.06 | AG30: =B30&"|"&C30 -> D2_EchoGHubRamp_PimaTargets|FY2029
A31: =AG31 -> D2_EchoGHubRamp_PimaTargets|FY2030 | B31: =Scenarios!A7 -> D2_EchoGHubRamp_PimaTargets | C31: FY2030 | D31: =IF(Scenarios!D7=1,0, L31) -> 345 | E31: =IF(Scenarios!E7=1,0, M31) -> 333 | F31: =D31+E31 -> 678 | G31: =YearMap!B6 -> 7080.4205 | H31: =YearMap!C6 -> 1550087.6 | I31: =YearMap!D6 -> 1785314.9 | J31: =1-BaselineCalc!$B$5 -> 0.993 | K31: =Scenarios!G7 -> 0 | L31: =IF(Scenarios!$Q7=1,BaselineCalc!$B$7*(1+Parameters_Public!$C44)^(IF($C31="FY2026",0,IF($C31="FY2027",1,IF($C31="FY2028",2,IF($C31="FY2029",3,IF($C31="FY2030",4,0))))))+ROUND(Scenarios!M7*Scenarios!$F7,0),BaselineCalc!$B$7+ROUND(Scenarios!M7*Scenarios!$F7,0)) -> 345 | M31: =IF(Scenarios!$R7=1,BaselineCalc!$B$8*(1+Parameters_Public!$C45)^(IF($C31="FY2026",0,IF($C31="FY2027",1,IF($C31="FY2028",2,IF($C31="FY2029",3,IF($C31="FY2030",4,0))))))+Scenarios!M7-ROUND(Scenarios!M7*Scenarios!$F7,0),BaselineCalc!$B$8+Scenarios!M7-ROUND(Scenarios!M7*Scenarios!$F7,0)) -> 333 | N31: =(L31-D31) + (M31-E31) -> 0 | O31: =(Parameters_Public!$C$23*(L31-D31)+Parameters_Public!$C$24*(M31-E31)) -> 0 | P31: =YearMap!E6 -> 300 | Q31: =IF(Scenarios!N7="lease", YearMap!F6, YearMap!G6) -> 0.3 | R31: =IF(Scenarios!D7=1, Q31*H31, H31) -> 1550087.6 | S31: =IF(Scenarios!E7=1, Q31*I31, I31) -> 1785314.9 | T31: =IF(C31="FY2026", (Scenarios!D7+Scenarios!E7)*BaselineCalc!$B$22, 0) -> 0 | U31: =(R31+S31+G31*F31)*J31*(1-K31) -> 8078976.1 | V31: =O31*(G31+P31) -> 0 | W31: =U31+V31+IF(Parameters_Public!$C$26=1, T31, 0) -> 8078976.1 | X31: =IF(F31+O31>0, W31/(F31+O31),"") -> 11915.894 | Y31: =INDEX(YearMap!$I$2:$I$6, MATCH(C31, YearMap!$A$2:$A$6, 0)) -> 5533.414 | Z31: =W31 - ((Y31 + IF(Parameters_Public!$C$20=1, Parameters_Public!$C$19, 0))*AC31) -> 3817499.3 | AA31: =IF($AC31>0, $Z31/$AC31, 0) -> 5630.53 | AB31: =MAX(0, (MAX(0, $D31-BaselineCalc!$B$7) + MAX(0, $E31-BaselineCalc!$B$8))) -> 125 | AC31: =L31+M31-N31+O31 -> 678 | AD31: =( (Y31 + IF(Parameters_Public!$C20=1, INDEX(YearMap!$O$2:$O$6, MATCH(C31, YearMap!$A$2:$A$6, 0)), 0)) * AC31 ) + AC31*INDEX(YearMap!$P$2:$P$6, MATCH(C31, YearMap!$A$2:$A$6, 0)) + AB31*( INDEX(YearMap!$R$2:$R$6, MATCH(C31, YearMap!$A$2:$A$6, 0)) - INDEX(YearMap!$P$2:$P$6, MATCH(C31, YearMap!$A$2:$A$6, 0)) ) -> 8098383.9 | AE31: =(W31 - (1-Parameters_Public!$C42)*$G31*$AB31*$J31*(1-$K31)) + AB31*INDEX(YearMap!$Q$2:$Q$6, MATCH(C31, YearMap!$A$2:$A$6, 0)) -> 7207618.9 | AF31: =AD31-AE31 -> 890764.96 | AG31: =B31&"|"&C31 -> D2_EchoGHubRamp_PimaTargets|FY2030
A32: =AG32 -> A2_Repurpose_Both_lease|FY2026 | B32: =Scenarios!A8 -> A2_Repurpose_Both_lease | C32: FY2026 | D32: =IF(Scenarios!D8=1,0, L32) -> 0 | E32: =IF(Scenarios!E8=1,0, M32) -> 0 | F32: =D32+E32 -> 0 | G32: =YearMap!B2 -> 6414.5115 | H32: =YearMap!C2 -> 1404302.9 | I32: =YearMap!D2 -> 1617407.2 | J32: =1-BaselineCalc!$B$5 -> 0.993 | K32: =Scenarios!G8 -> 0 | L32: =IF(Scenarios!$Q8=1,BaselineCalc!$B$7*(1+Parameters_Public!$C44)^(IF($C32="FY2026",0,IF($C32="FY2027",1,IF($C32="FY2028",2,IF($C32="FY2029",3,IF($C32="FY2030",4,0))))))+ROUND(Scenarios!I8*Scenarios!$F8,0),BaselineCalc!$B$7+ROUND(Scenarios!I8*Scenarios!$F8,0)) -> 257 | M32: =IF(Scenarios!$R8=1,BaselineCalc!$B$8*(1+Parameters_Public!$C45)^(IF($C32="FY2026",0,IF($C32="FY2027",1,IF($C32="FY2028",2,IF($C32="FY2029",3,IF($C32="FY2030",4,0))))))+Scenarios!I8-ROUND(Scenarios!I8*Scenarios!$F8,0),BaselineCalc!$B$8+Scenarios!I8-ROUND(Scenarios!I8*Scenarios!$F8,0)) -> 296 | N32: =(L32-D32) + (M32-E32) -> 553 | O32: =(Parameters_Public!$C$23*(L32-D32)+Parameters_Public!$C$24*(M32-E32)) -> 405.8 | P32: =YearMap!E2 -> 1000 | Q32: =IF(Scenarios!N8="lease", YearMap!F2, YearMap!G2) -> 0.2 | R32: =IF(Scenarios!D8=1, Q32*H32, H32) -> 280860.57 | S32: =IF(Scenarios!E8=1, Q32*I32, I32) -> 323481.44 | T32: =IF(C32="FY2026", (Scenarios!D8+Scenarios!E8)*BaselineCalc!$B$22, 0) -> 2400000 | U32: =(R32+S32+G32*F32)*J32*(1-K32) -> 600111.62 | V32: =O32*(G32+P32) -> 3008808.8 | W32: =U32+V32+IF(Parameters_Public!$C$26=1, T32, 0) -> 3608920.4 | X32: =IF(F32+O32>0, W32/(F32+O32),"") -> 8893.3474 | Y32: =INDEX(YearMap!$I$2:$I$6, MATCH(C32, YearMap!$A$2:$A$6, 0)) -> 5013 | Z32: =W32 - ((Y32 + IF(Parameters_Public!$C$20=1, Parameters_Public!$C$19, 0))*AC32) -> 1269503.7 | AA32: =IF($AC32>0, $Z32/$AC32, 0) -> 3128.3974 | AB32: =MAX(0, (MAX(0, $D32-BaselineCalc!$B$7) + MAX(0, $E32-BaselineCalc!$B$8))) -> 0 | AC32: =L32+M32-N32+O32 -> 405.8 | AD32: =( (Y32 + IF(Parameters_Public!$C20=1, INDEX(YearMap!$O$2:$O$6, MATCH(C32, YearMap!$A$2:$A$6, 0)), 0)) * AC32 ) + AC32*INDEX(YearMap!$P$2:$P$6, MATCH(C32, YearMap!$A$2:$A$6, 0)) + AB32*( INDEX(YearMap!$R$2:$R$6, MATCH(C32, YearMap!$A$2:$A$6, 0)) - INDEX(YearMap!$P$2:$P$6, MATCH(C32, YearMap!$A$2:$A$6, 0)) ) -> 4449576.7 | AE32: =(W32 - (1-Parameters_Public!$C42)*$G32*$AB32*$J32*(1-$K32)) + AB32*INDEX(YearMap!$Q$2:$Q$6, MATCH(C32, YearMap!$A$2:$A$6, 0)) -> 3608920.4 | AF32: =AD32-AE32 -> 840656.32 | AG32: =B32&"|"&C32 -> A2_Repurpose_Both_lease|FY2026
A33: =AG33 -> A2_Repurpose_Both_lease|FY2027 | B33: =Scenarios!A8 -> A2_Repurpose_Both_lease | C33: FY2027 | D33: =IF(Scenarios!D8=1,0, L33) -> 0 | E33: =IF(Scenarios!E8=1,0, M33) -> 0 | F33: =D33+E33 -> 0 | G33: =YearMap!B3 -> 6574.8743 | H33: =YearMap!C3 -> 1439410.4 | I33: =YearMap!D3 -> 1657842.4 | J33: =1-BaselineCalc!$B$5 -> 0.993 | K33: =Scenarios!G8 -> 0 | L33: =IF(Scenarios!$Q8=1,BaselineCalc!$B$7*(1+Parameters_Public!$C44)^(IF($C33="FY2026",0,IF($C33="FY2027",1,IF($C33="FY2028",2,IF($C33="FY2029",3,IF($C33="FY2030",4,0))))))+ROUND(Scenarios!J8*Scenarios!$F8,0),BaselineCalc!$B$7+ROUND(Scenarios!J8*Scenarios!$F8,0)) -> 257 | M33: =IF(Scenarios!$R8=1,BaselineCalc!$B$8*(1+Parameters_Public!$C45)^(IF($C33="FY2026",0,IF($C33="FY2027",1,IF($C33="FY2028",2,IF($C33="FY2029",3,IF($C33="FY2030",4,0))))))+Scenarios!J8-ROUND(Scenarios!J8*Scenarios!$F8,0),BaselineCalc!$B$8+Scenarios!J8-ROUND(Scenarios!J8*Scenarios!$F8,0)) -> 296 | N33: =(L33-D33) + (M33-E33) -> 553 | O33: =(Parameters_Public!$C$23*(L33-D33)+Parameters_Public!$C$24*(M33-E33)) -> 405.8 | P33: =YearMap!E3 -> 800 | Q33: =IF(Scenarios!N8="lease", YearMap!F3, YearMap!G3) -> 0.2 | R33: =IF(Scenarios!D8=1, Q33*H33, H33) -> 287882.09 | S33: =IF(Scenarios!E8=1, Q33*I33, I33) -> 331568.48 | T33: =IF(C33="FY2026", (Scenarios!D8+Scenarios!E8)*BaselineCalc!$B$22, 0) -> 0 | U33: =(R33+S33+G33*F33)*J33*(1-K33) -> 615114.41 | V33: =O33*(G33+P33) -> 2992724 | W33: =U33+V33+IF(Parameters_Public!$C$26=1, T33, 0) -> 3607838.4 | X33: =IF(F33+O33>0, W33/(F33+O33),"") -> 8890.6811 | Y33: =INDEX(YearMap!$I$2:$I$6, MATCH(C33, YearMap!$A$2:$A$6, 0)) -> 5138.325 | Z33: =W33 - ((Y33 + IF(Parameters_Public!$C$20=1, Parameters_Public!$C$19, 0))*AC33) -> 1217564.8 | AA33: =IF($AC33>0, $Z33/$AC33, 0) -> 3000.4061 | AB33: =MAX(0, (MAX(0, $D33-BaselineCalc!$B$7) + MAX(0, $E33-BaselineCalc!$B$8))) -> 0 | AC33: =L33+M33-N33+O33 -> 405.8 | AD33: =( (Y33 + IF(Parameters_Public!$C20=1, INDEX(YearMap!$O$2:$O$6, MATCH(C33, YearMap!$A$2:$A$6, 0)), 0)) * AC33 ) + AC33*INDEX(YearMap!$P$2:$P$6, MATCH(C33, YearMap!$A$2:$A$6, 0)) + AB33*( INDEX(YearMap!$R$2:$R$6, MATCH(C33, YearMap!$A$2:$A$6, 0)) - INDEX(YearMap!$P$2:$P$6, MATCH(C33, YearMap!$A$2:$A$6, 0)) ) -> 4560816.1 | AE33: =(W33 - (1-Parameters_Public!$C42)*$G33*$AB33*$J33*(1-$K33)) + AB33*INDEX(YearMap!$Q$2:$Q$6, MATCH(C33, YearMap!$A$2:$A$6, 0)) -> 3607838.4 | AF33: =AD33-AE33 -> 952977.73 | AG33: =B33&"|"&C33 -> A2_Repurpose_Both_lease|FY2027
A34: =AG34 -> A2_Repurpose_Both_lease|FY2028 | B34: =Scenarios!A8 -> A2_Repurpose_Both_lease | C34: FY2028 | D34: =IF(Scenarios!D8=1,0, L34) -> 0 | E34: =IF(Scenarios!E8=1,0, M34) -> 0 | F34: =D34+E34 -> 0 | G34: =YearMap!B4 -> 6739.2461 | H34: =YearMap!C4 -> 1475395.7 | I34: =YearMap!D4 -> 1699288.4 | J34: =1-BaselineCalc!$B$5 -> 0.993 | K34: =Scenarios!G8 -> 0 | L34: =IF(Scenarios!$Q8=1,BaselineCalc!$B$7*(1+Parameters_Public!$C44)^(IF($C34="FY2026",0,IF($C34="FY2027",1,IF($C34="FY2028",2,IF($C34="FY2029",3,IF($C34="FY2030",4,0))))))+ROUND(Scenarios!K8*Scenarios!$F8,0),BaselineCalc!$B$7+ROUND(Scenarios!K8*Scenarios!$F8,0)) -> 257 | M34: =IF(Scenarios!$R8=1,BaselineCalc!$B$8*(1+Parameters_Public!$C45)^(IF($C34="FY2026",0,IF($C34="FY2027",1,IF($C34="FY2028",2,IF($C34="FY2029",3,IF($C34="FY2030",4,0))))))+Scenarios!K8-ROUND(Scenarios!K8*Scenarios!$F8,0),BaselineCalc!$B$8+Scenarios!K8-ROUND(Scenarios!K8*Scenarios!$F8,0)) -> 296 | N34: =(L34-D34) + (M34-E34) -> 553 | O34: =(Parameters_Public!$C$23*(L34-D34)+Parameters_Public!$C$24*(M34-E34)) -> 405.8 | P34: =YearMap!E4 -> 600 | Q34: =IF(Scenarios!N8="lease", YearMap!F4, YearMap!G4) -> 0.15 | R34: =IF(Scenarios!D8=1, Q34*H34, H34) -> 221309.36 | S34: =IF(Scenarios!E8=1, Q34*I34, I34) -> 254893.27 | T34: =IF(C34="FY2026", (Scenarios!D8+Scenarios!E8)*BaselineCalc!$B$22, 0) -> 0 | U34: =(R34+S34+G34*F34)*J34*(1-K34) -> 472869.2 | V34: =O34*(G34+P34) -> 2978266.1 | W34: =U34+V34+IF(Parameters_Public!$C$26=1, T34, 0) -> 3451135.3 | X34: =IF(F34+O34>0, W34/(F34+O34),"") -> 8504.5226 | Y34: =INDEX(YearMap!$I$2:$I$6, MATCH(C34, YearMap!$A$2:$A$6, 0)) -> 5266.7831 | Z34: =W34 - ((Y34 + IF(Parameters_Public!$C$20=1, Parameters_Public!$C$19, 0))*AC34) -> 1008733.4 | AA34: =IF($AC34>0, $Z34/$AC34, 0) -> 2485.7895 | AB34: =MAX(0, (MAX(0, $D34-BaselineCalc!$B$7) + MAX(0, $E34-BaselineCalc!$B$8))) -> 0 | AC34: =L34+M34-N34+O34 -> 405.8 | AD34: =( (Y34 + IF(Parameters_Public!$C20=1, INDEX(YearMap!$O$2:$O$6, MATCH(C34, YearMap!$A$2:$A$6, 0)), 0)) * AC34 ) + AC34*INDEX(YearMap!$P$2:$P$6, MATCH(C34, YearMap!$A$2:$A$6, 0)) + AB34*( INDEX(YearMap!$R$2:$R$6, MATCH(C34, YearMap!$A$2:$A$6, 0)) - INDEX(YearMap!$P$2:$P$6, MATCH(C34, YearMap!$A$2:$A$6, 0)) ) -> 4674836.5 | AE34: =(W34 - (1-Parameters_Public!$C42)*$G34*$AB34*$J34*(1-$K34)) + AB34*INDEX(YearMap!$Q$2:$Q$6, MATCH(C34, YearMap!$A$2:$A$6, 0)) -> 3451135.3 | AF34: =AD34-AE34 -> 1223701.2 | AG34: =B34&"|"&C34 -> A2_Repurpose_Both_lease|FY2028
A35: =AG35 -> A2_Repurpose_Both_lease|FY2029 | B35: =Scenarios!A8 -> A2_Repurpose_Both_lease | C35: FY2029 | D35: =IF(Scenarios!D8=1,0, L35) -> 0 | E35: =IF(Scenarios!E8=1,0, M35) -> 0 | F35: =D35+E35 -> 0 | G35: =YearMap!B5 -> 6907.7273 | H35: =YearMap!C5 -> 1512280.6 | I35: =YearMap!D5 -> 1741770.6 | J35: =1-BaselineCalc!$B$5 -> 0.993 | K35: =Scenarios!G8 -> 0 | L35: =IF(Scenarios!$Q8=1,BaselineCalc!$B$7*(1+Parameters_Public!$C44)^(IF($C35="FY2026",0,IF($C35="FY2027",1,IF($C35="FY2028",2,IF($C35="FY2029",3,IF($C35="FY2030",4,0))))))+ROUND(Scenarios!L8*Scenarios!$F8,0),BaselineCalc!$B$7+ROUND(Scenarios!L8*Scenarios!$F8,0)) -> 257 | M35: =IF(Scenarios!$R8=1,BaselineCalc!$B$8*(1+Parameters_Public!$C45)^(IF($C35="FY2026",0,IF($C35="FY2027",1,IF($C35="FY2028",2,IF($C35="FY2029",3,IF($C35="FY2030",4,0))))))+Scenarios!L8-ROUND(Scenarios!L8*Scenarios!$F8,0),BaselineCalc!$B$8+Scenarios!L8-ROUND(Scenarios!L8*Scenarios!$F8,0)) -> 296 | N35: =(L35-D35) + (M35-E35) -> 553 | O35: =(Parameters_Public!$C$23*(L35-D35)+Parameters_Public!$C$24*(M35-E35)) -> 405.8 | P35: =YearMap!E5 -> 500 | Q35: =IF(Scenarios!N8="lease", YearMap!F5, YearMap!G5) -> 0.1 | R35: =IF(Scenarios!D8=1, Q35*H35, H35) -> 151228.06 | S35: =IF(Scenarios!E8=1, Q35*I35, I35) -> 174177.06 | T35: =IF(C35="FY2026", (Scenarios!D8+Scenarios!E8)*BaselineCalc!$B$22, 0) -> 0 | U35: =(R35+S35+G35*F35)*J35*(1-K35) -> 323127.29 | V35: =O35*(G35+P35) -> 3006055.7 | W35: =U35+V35+IF(Parameters_Public!$C$26=1, T35, 0) -> 3329183 | X35: =IF(F35+O35>0, W35/(F35+O35),"") -> 8203.9996 | Y35: =INDEX(YearMap!$I$2:$I$6, MATCH(C35, YearMap!$A$2:$A$6, 0)) -> 5398.4527 | Z35: =W35 - ((Y35 + IF(Parameters_Public!$C$20=1, Parameters_Public!$C$19, 0))*AC35) -> 833349.61 | AA35: =IF($AC35>0, $Z35/$AC35, 0) -> 2053.5969 | AB35: =MAX(0, (MAX(0, $D35-BaselineCalc!$B$7) + MAX(0, $E35-BaselineCalc!$B$8))) -> 0 | AC35: =L35+M35-N35+O35 -> 405.8 | AD35: =( (Y35 + IF(Parameters_Public!$C20=1, INDEX(YearMap!$O$2:$O$6, MATCH(C35, YearMap!$A$2:$A$6, 0)), 0)) * AC35 ) + AC35*INDEX(YearMap!$P$2:$P$6, MATCH(C35, YearMap!$A$2:$A$6, 0)) + AB35*( INDEX(YearMap!$R$2:$R$6, MATCH(C35, YearMap!$A$2:$A$6, 0)) - INDEX(YearMap!$P$2:$P$6, MATCH(C35, YearMap!$A$2:$A$6, 0)) ) -> 4791707.4 | AE35: =(W35 - (1-Parameters_Public!$C42)*$G35*$AB35*$J35*(1-$K35)) + AB35*INDEX(YearMap!$Q$2:$Q$6, MATCH(C35, YearMap!$A$2:$A$6, 0)) -> 3329183 | AF35: =AD35-AE35 -> 1462524.4 | AG35: =B35&"|"&C35 -> A2_Repurpose_Both_lease|FY2029
A36: =AG36 -> A2_Repurpose_Both_lease|FY2030 | B36: =Scenarios!A8 -> A2_Repurpose_Both_lease | C36: FY2030 | D36: =IF(Scenarios!D8=1,0, L36) -> 0 | E36: =IF(Scenarios!E8=1,0, M36) -> 0 | F36: =D36+E36 -> 0 | G36: =YearMap!B6 -> 7080.4205 | H36: =YearMap!C6 -> 1550087.6 | I36: =YearMap!D6 -> 1785314.9 | J36: =1-BaselineCalc!$B$5 -> 0.993 | K36: =Scenarios!G8 -> 0 | L36: =IF(Scenarios!$Q8=1,BaselineCalc!$B$7*(1+Parameters_Public!$C44)^(IF($C36="FY2026",0,IF($C36="FY2027",1,IF($C36="FY2028",2,IF($C36="FY2029",3,IF($C36="FY2030",4,0))))))+ROUND(Scenarios!M8*Scenarios!$F8,0),BaselineCalc!$B$7+ROUND(Scenarios!M8*Scenarios!$F8,0)) -> 257 | M36: =IF(Scenarios!$R8=1,BaselineCalc!$B$8*(1+Parameters_Public!$C45)^(IF($C36="FY2026",0,IF($C36="FY2027",1,IF($C36="FY2028",2,IF($C36="FY2029",3,IF($C36="FY2030",4,0))))))+Scenarios!M8-ROUND(Scenarios!M8*Scenarios!$F8,0),BaselineCalc!$B$8+Scenarios!M8-ROUND(Scenarios!M8*Scenarios!$F8,0)) -> 296 | N36: =(L36-D36) + (M36-E36) -> 553 | O36: =(Parameters_Public!$C$23*(L36-D36)+Parameters_Public!$C$24*(M36-E36)) -> 405.8 | P36: =YearMap!E6 -> 300 | Q36: =IF(Scenarios!N8="lease", YearMap!F6, YearMap!G6) -> 0.1 | R36: =IF(Scenarios!D8=1, Q36*H36, H36) -> 155008.76 | S36: =IF(Scenarios!E8=1, Q36*I36, I36) -> 178531.49 | T36: =IF(C36="FY2026", (Scenarios!D8+Scenarios!E8)*BaselineCalc!$B$22, 0) -> 0 | U36: =(R36+S36+G36*F36)*J36*(1-K36) -> 331205.47 | V36: =O36*(G36+P36) -> 2994974.6 | W36: =U36+V36+IF(Parameters_Public!$C$26=1, T36, 0) -> 3326180.1 | X36: =IF(F36+O36>0, W36/(F36+O36),"") -> 8196.5996 | Y36: =INDEX(YearMap!$I$2:$I$6, MATCH(C36, YearMap!$A$2:$A$6, 0)) -> 5533.414 | Z36: =W36 - ((Y36 + IF(Parameters_Public!$C$20=1, Parameters_Public!$C$19, 0))*AC36) -> 775579.38 | AA36: =IF($AC36>0, $Z36/$AC36, 0) -> 1911.2355 | AB36: =MAX(0, (MAX(0, $D36-BaselineCalc!$B$7) + MAX(0, $E36-BaselineCalc!$B$8))) -> 0 | AC36: =L36+M36-N36+O36 -> 405.8 | AD36: =( (Y36 + IF(Parameters_Public!$C20=1, INDEX(YearMap!$O$2:$O$6, MATCH(C36, YearMap!$A$2:$A$6, 0)), 0)) * AC36 ) + AC36*INDEX(YearMap!$P$2:$P$6, MATCH(C36, YearMap!$A$2:$A$6, 0)) + AB36*( INDEX(YearMap!$R$2:$R$6, MATCH(C36, YearMap!$A$2:$A$6, 0)) - INDEX(YearMap!$P$2:$P$6, MATCH(C36, YearMap!$A$2:$A$6, 0)) ) -> 4911500.1 | AE36: =(W36 - (1-Parameters_Public!$C42)*$G36*$AB36*$J36*(1-$K36)) + AB36*INDEX(YearMap!$Q$2:$Q$6, MATCH(C36, YearMap!$A$2:$A$6, 0)) -> 3326180.1 | AF36: =AD36-AE36 -> 1585320 | AG36: =B36&"|"&C36 -> A2_Repurpose_Both_lease|FY2030
A37: =AG37 -> A1_Repurpose_Both_ops|FY2026 | B37: =Scenarios!A9 -> A1_Repurpose_Both_ops | C37: FY2026 | D37: =IF(Scenarios!D9=1,0, L37) -> 0 | E37: =IF(Scenarios!E9=1,0, M37) -> 0 | F37: =D37+E37 -> 0 | G37: =YearMap!B2 -> 6414.5115 | H37: =YearMap!C2 -> 1404302.9 | I37: =YearMap!D2 -> 1617407.2 | J37: =1-BaselineCalc!$B$5 -> 0.993 | K37: =Scenarios!G9 -> 0 | L37: =IF(Scenarios!$Q9=1,BaselineCalc!$B$7*(1+Parameters_Public!$C44)^(IF($C37="FY2026",0,IF($C37="FY2027",1,IF($C37="FY2028",2,IF($C37="FY2029",3,IF($C37="FY2030",4,0))))))+ROUND(Scenarios!I9*Scenarios!$F9,0),BaselineCalc!$B$7+ROUND(Scenarios!I9*Scenarios!$F9,0)) -> 257 | M37: =IF(Scenarios!$R9=1,BaselineCalc!$B$8*(1+Parameters_Public!$C45)^(IF($C37="FY2026",0,IF($C37="FY2027",1,IF($C37="FY2028",2,IF($C37="FY2029",3,IF($C37="FY2030",4,0))))))+Scenarios!I9-ROUND(Scenarios!I9*Scenarios!$F9,0),BaselineCalc!$B$8+Scenarios!I9-ROUND(Scenarios!I9*Scenarios!$F9,0)) -> 296 | N37: =(L37-D37) + (M37-E37) -> 553 | O37: =(Parameters_Public!$C$23*(L37-D37)+Parameters_Public!$C$24*(M37-E37)) -> 405.8 | P37: =YearMap!E2 -> 1000 | Q37: =IF(Scenarios!N9="lease", YearMap!F2, YearMap!G2) -> 0.45 | R37: =IF(Scenarios!D9=1, Q37*H37, H37) -> 631936.29 | S37: =IF(Scenarios!E9=1, Q37*I37, I37) -> 727833.24 | T37: =IF(C37="FY2026", (Scenarios!D9+Scenarios!E9)*BaselineCalc!$B$22, 0) -> 2400000 | U37: =(R37+S37+G37*F37)*J37*(1-K37) -> 1350251.1 | V37: =O37*(G37+P37) -> 3008808.8 | W37: =U37+V37+IF(Parameters_Public!$C$26=1, T37, 0) -> 4359059.9 | X37: =IF(F37+O37>0, W37/(F37+O37),"") -> 10741.892 | Y37: =INDEX(YearMap!$I$2:$I$6, MATCH(C37, YearMap!$A$2:$A$6, 0)) -> 5013 | Z37: =W37 - ((Y37 + IF(Parameters_Public!$C$20=1, Parameters_Public!$C$19, 0))*AC37) -> 2019643.2 | AA37: =IF($AC37>0, $Z37/$AC37, 0) -> 4976.9423 | AB37: =MAX(0, (MAX(0, $D37-BaselineCalc!$B$7) + MAX(0, $E37-BaselineCalc!$B$8))) -> 0 | AC37: =L37+M37-N37+O37 -> 405.8 | AD37: =( (Y37 + IF(Parameters_Public!$C20=1, INDEX(YearMap!$O$2:$O$6, MATCH(C37, YearMap!$A$2:$A$6, 0)), 0)) * AC37 ) + AC37*INDEX(YearMap!$P$2:$P$6, MATCH(C37, YearMap!$A$2:$A$6, 0)) + AB37*( INDEX(YearMap!$R$2:$R$6, MATCH(C37, YearMap!$A$2:$A$6, 0)) - INDEX(YearMap!$P$2:$P$6, MATCH(C37, YearMap!$A$2:$A$6, 0)) ) -> 4449576.7 | AE37: =(W37 - (1-Parameters_Public!$C42)*$G37*$AB37*$J37*(1-$K37)) + AB37*INDEX(YearMap!$Q$2:$Q$6, MATCH(C37, YearMap!$A$2:$A$6, 0)) -> 4359059.9 | AF37: =AD37-AE37 -> 90516.801 | AG37: =B37&"|"&C37 -> A1_Repurpose_Both_ops|FY2026
A38: =AG38 -> A1_Repurpose_Both_ops|FY2027 | B38: =Scenarios!A9 -> A1_Repurpose_Both_ops | C38: FY2027 | D38: =IF(Scenarios!D9=1,0, L38) -> 0 | E38: =IF(Scenarios!E9=1,0, M38) -> 0 | F38: =D38+E38 -> 0 | G38: =YearMap!B3 -> 6574.8743 | H38: =YearMap!C3 -> 1439410.4 | I38: =YearMap!D3 -> 1657842.4 | J38: =1-BaselineCalc!$B$5 -> 0.993 | K38: =Scenarios!G9 -> 0 | L38: =IF(Scenarios!$Q9=1,BaselineCalc!$B$7*(1+Parameters_Public!$C44)^(IF($C38="FY2026",0,IF($C38="FY2027",1,IF($C38="FY2028",2,IF($C38="FY2029",3,IF($C38="FY2030",4,0))))))+ROUND(Scenarios!J9*Scenarios!$F9,0),BaselineCalc!$B$7+ROUND(Scenarios!J9*Scenarios!$F9,0)) -> 257 | M38: =IF(Scenarios!$R9=1,BaselineCalc!$B$8*(1+Parameters_Public!$C45)^(IF($C38="FY2026",0,IF($C38="FY2027",1,IF($C38="FY2028",2,IF($C38="FY2029",3,IF($C38="FY2030",4,0))))))+Scenarios!J9-ROUND(Scenarios!J9*Scenarios!$F9,0),BaselineCalc!$B$8+Scenarios!J9-ROUND(Scenarios!J9*Scenarios!$F9,0)) -> 296 | N38: =(L38-D38) + (M38-E38) -> 553 | O38: =(Parameters_Public!$C$23*(L38-D38)+Parameters_Public!$C$24*(M38-E38)) -> 405.8 | P38: =YearMap!E3 -> 800 | Q38: =IF(Scenarios!N9="lease", YearMap!F3, YearMap!G3) -> 0.4 | R38: =IF(Scenarios!D9=1, Q38*H38, H38) -> 575764.18 | S38: =IF(Scenarios!E9=1, Q38*I38, I38) -> 663136.95 | T38: =IF(C38="FY2026", (Scenarios!D9+Scenarios!E9)*BaselineCalc!$B$22, 0) -> 0 | U38: =(R38+S38+G38*F38)*J38*(1-K38) -> 1230228.8 | V38: =O38*(G38+P38) -> 2992724 | W38: =U38+V38+IF(Parameters_Public!$C$26=1, T38, 0) -> 4222952.8 | X38: =IF(F38+O38>0, W38/(F38+O38),"") -> 10406.488 | Y38: =INDEX(YearMap!$I$2:$I$6, MATCH(C38, YearMap!$A$2:$A$6, 0)) -> 5138.325 | Z38: =W38 - ((Y38 + IF(Parameters_Public!$C$20=1, Parameters_Public!$C$19, 0))*AC38) -> 1832679.2 | AA38: =IF($AC38>0, $Z38/$AC38, 0) -> 4516.2129 | AB38: =MAX(0, (MAX(0, $D38-BaselineCalc!$B$7) + MAX(0, $E38-BaselineCalc!$B$8))) -> 0 | AC38: =L38+M38-N38+O38 -> 405.8 | AD38: =( (Y38 + IF(Parameters_Public!$C20=1, INDEX(YearMap!$O$2:$O$6, MATCH(C38, YearMap!$A$2:$A$6, 0)), 0)) * AC38 ) + AC38*INDEX(YearMap!$P$2:$P$6, MATCH(C38, YearMap!$A$2:$A$6, 0)) + AB38*( INDEX(YearMap!$R$2:$R$6, MATCH(C38, YearMap!$A$2:$A$6, 0)) - INDEX(YearMap!$P$2:$P$6, MATCH(C38, YearMap!$A$2:$A$6, 0)) ) -> 4560816.1 | AE38: =(W38 - (1-Parameters_Public!$C42)*$G38*$AB38*$J38*(1-$K38)) + AB38*INDEX(YearMap!$Q$2:$Q$6, MATCH(C38, YearMap!$A$2:$A$6, 0)) -> 4222952.8 | AF38: =AD38-AE38 -> 337863.32 | AG38: =B38&"|"&C38 -> A1_Repurpose_Both_ops|FY2027
A39: =AG39 -> A1_Repurpose_Both_ops|FY2028 | B39: =Scenarios!A9 -> A1_Repurpose_Both_ops | C39: FY2028 | D39: =IF(Scenarios!D9=1,0, L39) -> 0 | E39: =IF(Scenarios!E9=1,0, M39) -> 0 | F39: =D39+E39 -> 0 | G39: =YearMap!B4 -> 6739.2461 | H39: =YearMap!C4 -> 1475395.7 | I39: =YearMap!D4 -> 1699288.4 | J39: =1-BaselineCalc!$B$5 -> 0.993 | K39: =Scenarios!G9 -> 0 | L39: =IF(Scenarios!$Q9=1,BaselineCalc!$B$7*(1+Parameters_Public!$C44)^(IF($C39="FY2026",0,IF($C39="FY2027",1,IF($C39="FY2028",2,IF($C39="FY2029",3,IF($C39="FY2030",4,0))))))+ROUND(Scenarios!K9*Scenarios!$F9,0),BaselineCalc!$B$7+ROUND(Scenarios!K9*Scenarios!$F9,0)) -> 257 | M39: =IF(Scenarios!$R9=1,BaselineCalc!$B$8*(1+Parameters_Public!$C45)^(IF($C39="FY2026",0,IF($C39="FY2027",1,IF($C39="FY2028",2,IF($C39="FY2029",3,IF($C39="FY2030",4,0))))))+Scenarios!K9-ROUND(Scenarios!K9*Scenarios!$F9,0),BaselineCalc!$B$8+Scenarios!K9-ROUND(Scenarios!K9*Scenarios!$F9,0)) -> 296 | N39: =(L39-D39) + (M39-E39) -> 553 | O39: =(Parameters_Public!$C$23*(L39-D39)+Parameters_Public!$C$24*(M39-E39)) -> 405.8 | P39: =YearMap!E4 -> 600 | Q39: =IF(Scenarios!N9="lease", YearMap!F4, YearMap!G4) -> 0.35 | R39: =IF(Scenarios!D9=1, Q39*H39, H39) -> 516388.5 | S39: =IF(Scenarios!E9=1, Q39*I39, I39) -> 594750.95 | T39: =IF(C39="FY2026", (Scenarios!D9+Scenarios!E9)*BaselineCalc!$B$22, 0) -> 0 | U39: =(R39+S39+G39*F39)*J39*(1-K39) -> 1103361.5 | V39: =O39*(G39+P39) -> 2978266.1 | W39: =U39+V39+IF(Parameters_Public!$C$26=1, T39, 0) -> 4081627.6 | X39: =IF(F39+O39>0, W39/(F39+O39),"") -> 10058.225 | Y39: =INDEX(YearMap!$I$2:$I$6, MATCH(C39, YearMap!$A$2:$A$6, 0)) -> 5266.7831 | Z39: =W39 - ((Y39 + IF(Parameters_Public!$C$20=1, Parameters_Public!$C$19, 0))*AC39) -> 1639225.7 | AA39: =IF($AC39>0, $Z39/$AC39, 0) -> 4039.4915 | AB39: =MAX(0, (MAX(0, $D39-BaselineCalc!$B$7) + MAX(0, $E39-BaselineCalc!$B$8))) -> 0 | AC39: =L39+M39-N39+O39 -> 405.8 | AD39: =( (Y39 + IF(Parameters_Public!$C20=1, INDEX(YearMap!$O$2:$O$6, MATCH(C39, YearMap!$A$2:$A$6, 0)), 0)) * AC39 ) + AC39*INDEX(YearMap!$P$2:$P$6, MATCH(C39, YearMap!$A$2:$A$6, 0)) + AB39*( INDEX(YearMap!$R$2:$R$6, MATCH(C39, YearMap!$A$2:$A$6, 0)) - INDEX(YearMap!$P$2:$P$6, MATCH(C39, YearMap!$A$2:$A$6, 0)) ) -> 4674836.5 | AE39: =(W39 - (1-Parameters_Public!$C42)*$G39*$AB39*$J39*(1-$K39)) + AB39*INDEX(YearMap!$Q$2:$Q$6, MATCH(C39, YearMap!$A$2:$A$6, 0)) -> 4081627.6 | AF39: =AD39-AE39 -> 593208.97 | AG39: =B39&"|"&C39 -> A1_Repurpose_Both_ops|FY2028
A40: =AG40 -> A1_Repurpose_Both_ops|FY2029 | B40: =Scenarios!A9 -> A1_Repurpose_Both_ops | C40: FY2029 | D40: =IF(Scenarios!D9=1,0, L40) -> 0 | E40: =IF(Scenarios!E9=1,0, M40) -> 0 | F40: =D40+E40 -> 0 | G40: =YearMap!B5 -> 6907.7273 | H40: =YearMap!C5 -> 1512280.6 | I40: =YearMap!D5 -> 1741770.6 | J40: =1-BaselineCalc!$B$5 -> 0.993 | K40: =Scenarios!G9 -> 0 | L40: =IF(Scenarios!$Q9=1,BaselineCalc!$B$7*(1+Parameters_Public!$C44)^(IF($C40="FY2026",0,IF($C40="FY2027",1,IF($C40="FY2028",2,IF($C40="FY2029",3,IF($C40="FY2030",4,0))))))+ROUND(Scenarios!L9*Scenarios!$F9,0),BaselineCalc!$B$7+ROUND(Scenarios!L9*Scenarios!$F9,0)) -> 257 | M40: =IF(Scenarios!$R9=1,BaselineCalc!$B$8*(1+Parameters_Public!$C45)^(IF($C40="FY2026",0,IF($C40="FY2027",1,IF($C40="FY2028",2,IF($C40="FY2029",3,IF($C40="FY2030",4,0))))))+Scenarios!L9-ROUND(Scenarios!L9*Scenarios!$F9,0),BaselineCalc!$B$8+Scenarios!L9-ROUND(Scenarios!L9*Scenarios!$F9,0)) -> 296 | N40: =(L40-D40) + (M40-E40) -> 553 | O40: =(Parameters_Public!$C$23*(L40-D40)+Parameters_Public!$C$24*(M40-E40)) -> 405.8 | P40: =YearMap!E5 -> 500 | Q40: =IF(Scenarios!N9="lease", YearMap!F5, YearMap!G5) -> 0.3 | R40: =IF(Scenarios!D9=1, Q40*H40, H40) -> 453684.18 | S40: =IF(Scenarios!E9=1, Q40*I40, I40) -> 522531.19 | T40: =IF(C40="FY2026", (Scenarios!D9+Scenarios!E9)*BaselineCalc!$B$22, 0) -> 0 | U40: =(R40+S40+G40*F40)*J40*(1-K40) -> 969381.86 | V40: =O40*(G40+P40) -> 3006055.7 | W40: =U40+V40+IF(Parameters_Public!$C$26=1, T40, 0) -> 3975437.6 | X40: =IF(F40+O40>0, W40/(F40+O40),"") -> 9796.5441 | Y40: =INDEX(YearMap!$I$2:$I$6, MATCH(C40, YearMap!$A$2:$A$6, 0)) -> 5398.4527 | Z40: =W40 - ((Y40 + IF(Parameters_Public!$C$20=1, Parameters_Public!$C$19, 0))*AC40) -> 1479604.2 | AA40: =IF($AC40>0, $Z40/$AC40, 0) -> 3646.1414 | AB40: =MAX(0, (MAX(0, $D40-BaselineCalc!$B$7) + MAX(0, $E40-BaselineCalc!$B$8))) -> 0 | AC40: =L40+M40-N40+O40 -> 405.8 | AD40: =( (Y40 + IF(Parameters_Public!$C20=1, INDEX(YearMap!$O$2:$O$6, MATCH(C40, YearMap!$A$2:$A$6, 0)), 0)) * AC40 ) + AC40*INDEX(YearMap!$P$2:$P$6, MATCH(C40, YearMap!$A$2:$A$6, 0)) + AB40*( INDEX(YearMap!$R$2:$R$6, MATCH(C40, YearMap!$A$2:$A$6, 0)) - INDEX(YearMap!$P$2:$P$6, MATCH(C40, YearMap!$A$2:$A$6, 0)) ) -> 4791707.4 | AE40: =(W40 - (1-Parameters_Public!$C42)*$G40*$AB40*$J40*(1-$K40)) + AB40*INDEX(YearMap!$Q$2:$Q$6, MATCH(C40, YearMap!$A$2:$A$6, 0)) -> 3975437.6 | AF40: =AD40-AE40 -> 816269.84 | AG40: =B40&"|"&C40 -> A1_Repurpose_Both_ops|FY2029
A41: =AG41 -> A1_Repurpose_Both_ops|FY2030 | B41: =Scenarios!A9 -> A1_Repurpose_Both_ops | C41: FY2030 | D41: =IF(Scenarios!D9=1,0, L41) -> 0 | E41: =IF(Scenarios!E9=1,0, M41) -> 0 | F41: =D41+E41 -> 0 | G41: =YearMap!B6 -> 7080.4205 | H41: =YearMap!C6 -> 1550087.6 | I41: =YearMap!D6 -> 1785314.9 | J41: =1-BaselineCalc!$B$5 -> 0.993 | K41: =Scenarios!G9 -> 0 | L41: =IF(Scenarios!$Q9=1,BaselineCalc!$B$7*(1+Parameters_Public!$C44)^(IF($C41="FY2026",0,IF($C41="FY2027",1,IF($C41="FY2028",2,IF($C41="FY2029",3,IF($C41="FY2030",4,0))))))+ROUND(Scenarios!M9*Scenarios!$F9,0),BaselineCalc!$B$7+ROUND(Scenarios!M9*Scenarios!$F9,0)) -> 257 | M41: =IF(Scenarios!$R9=1,BaselineCalc!$B$8*(1+Parameters_Public!$C45)^(IF($C41="FY2026",0,IF($C41="FY2027",1,IF($C41="FY2028",2,IF($C41="FY2029",3,IF($C41="FY2030",4,0))))))+Scenarios!M9-ROUND(Scenarios!M9*Scenarios!$F9,0),BaselineCalc!$B$8+Scenarios!M9-ROUND(Scenarios!M9*Scenarios!$F9,0)) -> 296 | N41: =(L41-D41) + (M41-E41) -> 553 | O41: =(Parameters_Public!$C$23*(L41-D41)+Parameters_Public!$C$24*(M41-E41)) -> 405.8 | P41: =YearMap!E6 -> 300 | Q41: =IF(Scenarios!N9="lease", YearMap!F6, YearMap!G6) -> 0.3 | R41: =IF(Scenarios!D9=1, Q41*H41, H41) -> 465026.28 | S41: =IF(Scenarios!E9=1, Q41*I41, I41) -> 535594.47 | T41: =IF(C41="FY2026", (Scenarios!D9+Scenarios!E9)*BaselineCalc!$B$22, 0) -> 0 | U41: =(R41+S41+G41*F41)*J41*(1-K41) -> 993616.41 | V41: =O41*(G41+P41) -> 2994974.6 | W41: =U41+V41+IF(Parameters_Public!$C$26=1, T41, 0) -> 3988591 | X41: =IF(F41+O41>0, W41/(F41+O41),"") -> 9828.9577 | Y41: =INDEX(YearMap!$I$2:$I$6, MATCH(C41, YearMap!$A$2:$A$6, 0)) -> 5533.414 | Z41: =W41 - ((Y41 + IF(Parameters_Public!$C$20=1, Parameters_Public!$C$19, 0))*AC41) -> 1437990.3 | AA41: =IF($AC41>0, $Z41/$AC41, 0) -> 3543.5937 | AB41: =MAX(0, (MAX(0, $D41-BaselineCalc!$B$7) + MAX(0, $E41-BaselineCalc!$B$8))) -> 0 | AC41: =L41+M41-N41+O41 -> 405.8 | AD41: =( (Y41 + IF(Parameters_Public!$C20=1, INDEX(YearMap!$O$2:$O$6, MATCH(C41, YearMap!$A$2:$A$6, 0)), 0)) * AC41 ) + AC41*INDEX(YearMap!$P$2:$P$6, MATCH(C41, YearMap!$A$2:$A$6, 0)) + AB41*( INDEX(YearMap!$R$2:$R$6, MATCH(C41, YearMap!$A$2:$A$6, 0)) - INDEX(YearMap!$P$2:$P$6, MATCH(C41, YearMap!$A$2:$A$6, 0)) ) -> 4911500.1 | AE41: =(W41 - (1-Parameters_Public!$C42)*$G41*$AB41*$J41*(1-$K41)) + AB41*INDEX(YearMap!$Q$2:$Q$6, MATCH(C41, YearMap!$A$2:$A$6, 0)) -> 3988591 | AF41: =AD41-AE41 -> 922909.09 | AG41: =B41&"|"&C41 -> A1_Repurpose_Both_ops|FY2030
A42: =AG42 -> B2_Repurpose_Echo_lease_PimaTargets|FY2026 | B42: =Scenarios!A10 -> B2_Repurpose_Echo_lease_PimaTargets | C42: FY2026 | D42: =IF(Scenarios!D10=1,0, L42) -> 0 | E42: =IF(Scenarios!E10=1,0, M42) -> 296 | F42: =D42+E42 -> 296 | G42: =YearMap!B2 -> 6414.5115 | H42: =YearMap!C2 -> 1404302.9 | I42: =YearMap!D2 -> 1617407.2 | J42: =1-BaselineCalc!$B$5 -> 0.993 | K42: =Scenarios!G10 -> 0 | L42: =IF(Scenarios!$Q10=1,BaselineCalc!$B$7*(1+Parameters_Public!$C44)^(IF($C42="FY2026",0,IF($C42="FY2027",1,IF($C42="FY2028",2,IF($C42="FY2029",3,IF($C42="FY2030",4,0))))))+ROUND(Scenarios!I10*Scenarios!$F10,0),BaselineCalc!$B$7+ROUND(Scenarios!I10*Scenarios!$F10,0)) -> 257 | M42: =IF(Scenarios!$R10=1,BaselineCalc!$B$8*(1+Parameters_Public!$C45)^(IF($C42="FY2026",0,IF($C42="FY2027",1,IF($C42="FY2028",2,IF($C42="FY2029",3,IF($C42="FY2030",4,0))))))+Scenarios!I10-ROUND(Scenarios!I10*Scenarios!$F10,0),BaselineCalc!$B$8+Scenarios!I10-ROUND(Scenarios!I10*Scenarios!$F10,0)) -> 296 | N42: =(L42-D42) + (M42-E42) -> 257 | O42: =(Parameters_Public!$C$23*(L42-D42)+Parameters_Public!$C$24*(M42-E42)) -> 154.2 | P42: =YearMap!E2 -> 1000 | Q42: =IF(Scenarios!N10="lease", YearMap!F2, YearMap!G2) -> 0.2 | R42: =IF(Scenarios!D10=1, Q42*H42, H42) -> 280860.57 | S42: =IF(Scenarios!E10=1, Q42*I42, I42) -> 1617407.2 | T42: =IF(C42="FY2026", (Scenarios!D10+Scenarios!E10)*BaselineCalc!$B$22, 0) -> 1200000 | U42: =(R42+S42+G42*F42)*J42*(1-K42) -> 3770384.4 | V42: =O42*(G42+P42) -> 1143317.7 | W42: =U42+V42+IF(Parameters_Public!$C$26=1, T42, 0) -> 4913702.1 | X42: =IF(F42+O42>0, W42/(F42+O42),"") -> 10914.487 | Y42: =INDEX(YearMap!$I$2:$I$6, MATCH(C42, YearMap!$A$2:$A$6, 0)) -> 5013 | Z42: =W42 - ((Y42 + IF(Parameters_Public!$C$20=1, Parameters_Public!$C$19, 0))*AC42) -> 2318321.6 | AA42: =IF($AC42>0, $Z42/$AC42, 0) -> 5149.5371 | AB42: =MAX(0, (MAX(0, $D42-BaselineCalc!$B$7) + MAX(0, $E42-BaselineCalc!$B$8))) -> 0 | AC42: =L42+M42-N42+O42 -> 450.2 | AD42: =( (Y42 + IF(Parameters_Public!$C20=1, INDEX(YearMap!$O$2:$O$6, MATCH(C42, YearMap!$A$2:$A$6, 0)), 0)) * AC42 ) + AC42*INDEX(YearMap!$P$2:$P$6, MATCH(C42, YearMap!$A$2:$A$6, 0)) + AB42*( INDEX(YearMap!$R$2:$R$6, MATCH(C42, YearMap!$A$2:$A$6, 0)) - INDEX(YearMap!$P$2:$P$6, MATCH(C42, YearMap!$A$2:$A$6, 0)) ) -> 4936420.5 | AE42: =(W42 - (1-Parameters_Public!$C42)*$G42*$AB42*$J42*(1-$K42)) + AB42*INDEX(YearMap!$Q$2:$Q$6, MATCH(C42, YearMap!$A$2:$A$6, 0)) -> 4913702.1 | AF42: =AD42-AE42 -> 22718.385 | AG42: =B42&"|"&C42 -> B2_Repurpose_Echo_lease_PimaTargets|FY2026
A43: =AG43 -> B2_Repurpose_Echo_lease_PimaTargets|FY2027 | B43: =Scenarios!A10 -> B2_Repurpose_Echo_lease_PimaTargets | C43: FY2027 | D43: =IF(Scenarios!D10=1,0, L43) -> 0 | E43: =IF(Scenarios!E10=1,0, M43) -> 296 | F43: =D43+E43 -> 296 | G43: =YearMap!B3 -> 6574.8743 | H43: =YearMap!C3 -> 1439410.4 | I43: =YearMap!D3 -> 1657842.4 | J43: =1-BaselineCalc!$B$5 -> 0.993 | K43: =Scenarios!G10 -> 0 | L43: =IF(Scenarios!$Q10=1,BaselineCalc!$B$7*(1+Parameters_Public!$C44)^(IF($C43="FY2026",0,IF($C43="FY2027",1,IF($C43="FY2028",2,IF($C43="FY2029",3,IF($C43="FY2030",4,0))))))+ROUND(Scenarios!J10*Scenarios!$F10,0),BaselineCalc!$B$7+ROUND(Scenarios!J10*Scenarios!$F10,0)) -> 257 | M43: =IF(Scenarios!$R10=1,BaselineCalc!$B$8*(1+Parameters_Public!$C45)^(IF($C43="FY2026",0,IF($C43="FY2027",1,IF($C43="FY2028",2,IF($C43="FY2029",3,IF($C43="FY2030",4,0))))))+Scenarios!J10-ROUND(Scenarios!J10*Scenarios!$F10,0),BaselineCalc!$B$8+Scenarios!J10-ROUND(Scenarios!J10*Scenarios!$F10,0)) -> 296 | N43: =(L43-D43) + (M43-E43) -> 257 | O43: =(Parameters_Public!$C$23*(L43-D43)+Parameters_Public!$C$24*(M43-E43)) -> 154.2 | P43: =YearMap!E3 -> 800 | Q43: =IF(Scenarios!N10="lease", YearMap!F3, YearMap!G3) -> 0.2 | R43: =IF(Scenarios!D10=1, Q43*H43, H43) -> 287882.09 | S43: =IF(Scenarios!E10=1, Q43*I43, I43) -> 1657842.4 | T43: =IF(C43="FY2026", (Scenarios!D10+Scenarios!E10)*BaselineCalc!$B$22, 0) -> 0 | U43: =(R43+S43+G43*F43)*J43*(1-K43) -> 3864644 | V43: =O43*(G43+P43) -> 1137205.6 | W43: =U43+V43+IF(Parameters_Public!$C$26=1, T43, 0) -> 5001849.7 | X43: =IF(F43+O43>0, W43/(F43+O43),"") -> 11110.284 | Y43: =INDEX(YearMap!$I$2:$I$6, MATCH(C43, YearMap!$A$2:$A$6, 0)) -> 5138.325 | Z43: =W43 - ((Y43 + IF(Parameters_Public!$C$20=1, Parameters_Public!$C$19, 0))*AC43) -> 2350047.9 | AA43: =IF($AC43>0, $Z43/$AC43, 0) -> 5220.0086 | AB43: =MAX(0, (MAX(0, $D43-BaselineCalc!$B$7) + MAX(0, $E43-BaselineCalc!$B$8))) -> 0 | AC43: =L43+M43-N43+O43 -> 450.2 | AD43: =( (Y43 + IF(Parameters_Public!$C20=1, INDEX(YearMap!$O$2:$O$6, MATCH(C43, YearMap!$A$2:$A$6, 0)), 0)) * AC43 ) + AC43*INDEX(YearMap!$P$2:$P$6, MATCH(C43, YearMap!$A$2:$A$6, 0)) + AB43*( INDEX(YearMap!$R$2:$R$6, MATCH(C43, YearMap!$A$2:$A$6, 0)) - INDEX(YearMap!$P$2:$P$6, MATCH(C43, YearMap!$A$2:$A$6, 0)) ) -> 5059831 | AE43: =(W43 - (1-Parameters_Public!$C42)*$G43*$AB43*$J43*(1-$K43)) + AB43*INDEX(YearMap!$Q$2:$Q$6, MATCH(C43, YearMap!$A$2:$A$6, 0)) -> 5001849.7 | AF43: =AD43-AE43 -> 57981.345 | AG43: =B43&"|"&C43 -> B2_Repurpose_Echo_lease_PimaTargets|FY2027
A44: =AG44 -> B2_Repurpose_Echo_lease_PimaTargets|FY2028 | B44: =Scenarios!A10 -> B2_Repurpose_Echo_lease_PimaTargets | C44: FY2028 | D44: =IF(Scenarios!D10=1,0, L44) -> 0 | E44: =IF(Scenarios!E10=1,0, M44) -> 296 | F44: =D44+E44 -> 296 | G44: =YearMap!B4 -> 6739.2461 | H44: =YearMap!C4 -> 1475395.7 | I44: =YearMap!D4 -> 1699288.4 | J44: =1-BaselineCalc!$B$5 -> 0.993 | K44: =Scenarios!G10 -> 0 | L44: =IF(Scenarios!$Q10=1,BaselineCalc!$B$7*(1+Parameters_Public!$C44)^(IF($C44="FY2026",0,IF($C44="FY2027",1,IF($C44="FY2028",2,IF($C44="FY2029",3,IF($C44="FY2030",4,0))))))+ROUND(Scenarios!K10*Scenarios!$F10,0),BaselineCalc!$B$7+ROUND(Scenarios!K10*Scenarios!$F10,0)) -> 257 | M44: =IF(Scenarios!$R10=1,BaselineCalc!$B$8*(1+Parameters_Public!$C45)^(IF($C44="FY2026",0,IF($C44="FY2027",1,IF($C44="FY2028",2,IF($C44="FY2029",3,IF($C44="FY2030",4,0))))))+Scenarios!K10-ROUND(Scenarios!K10*Scenarios!$F10,0),BaselineCalc!$B$8+Scenarios!K10-ROUND(Scenarios!K10*Scenarios!$F10,0)) -> 296 | N44: =(L44-D44) + (M44-E44) -> 257 | O44: =(Parameters_Public!$C$23*(L44-D44)+Parameters_Public!$C$24*(M44-E44)) -> 154.2 | P44: =YearMap!E4 -> 600 | Q44: =IF(Scenarios!N10="lease", YearMap!F4, YearMap!G4) -> 0.15 | R44: =IF(Scenarios!D10=1, Q44*H44, H44) -> 221309.36 | S44: =IF(Scenarios!E10=1, Q44*I44, I44) -> 1699288.4 | T44: =IF(C44="FY2026", (Scenarios!D10+Scenarios!E10)*BaselineCalc!$B$22, 0) -> 0 | U44: =(R44+S44+G44*F44)*J44*(1-K44) -> 3888006.7 | V44: =O44*(G44+P44) -> 1131711.8 | W44: =U44+V44+IF(Parameters_Public!$C$26=1, T44, 0) -> 5019718.5 | X44: =IF(F44+O44>0, W44/(F44+O44),"") -> 11149.974 | Y44: =INDEX(YearMap!$I$2:$I$6, MATCH(C44, YearMap!$A$2:$A$6, 0)) -> 5266.7831 | Z44: =W44 - ((Y44 + IF(Parameters_Public!$C$20=1, Parameters_Public!$C$19, 0))*AC44) -> 2310084.8 | AA44: =IF($AC44>0, $Z44/$AC44, 0) -> 5131.2413 | AB44: =MAX(0, (MAX(0, $D44-BaselineCalc!$B$7) + MAX(0, $E44-BaselineCalc!$B$8))) -> 0 | AC44: =L44+M44-N44+O44 -> 450.2 | AD44: =( (Y44 + IF(Parameters_Public!$C20=1, INDEX(YearMap!$O$2:$O$6, MATCH(C44, YearMap!$A$2:$A$6, 0)), 0)) * AC44 ) + AC44*INDEX(YearMap!$P$2:$P$6, MATCH(C44, YearMap!$A$2:$A$6, 0)) + AB44*( INDEX(YearMap!$R$2:$R$6, MATCH(C44, YearMap!$A$2:$A$6, 0)) - INDEX(YearMap!$P$2:$P$6, MATCH(C44, YearMap!$A$2:$A$6, 0)) ) -> 5186326.8 | AE44: =(W44 - (1-Parameters_Public!$C42)*$G44*$AB44*$J44*(1-$K44)) + AB44*INDEX(YearMap!$Q$2:$Q$6, MATCH(C44, YearMap!$A$2:$A$6, 0)) -> 5019718.5 | AF44: =AD44-AE44 -> 166608.27 | AG44: =B44&"|"&C44 -> B2_Repurpose_Echo_lease_PimaTargets|FY2028
A45: =AG45 -> B2_Repurpose_Echo_lease_PimaTargets|FY2029 | B45: =Scenarios!A10 -> B2_Repurpose_Echo_lease_PimaTargets | C45: FY2029 | D45: =IF(Scenarios!D10=1,0, L45) -> 0 | E45: =IF(Scenarios!E10=1,0, M45) -> 296 | F45: =D45+E45 -> 296 | G45: =YearMap!B5 -> 6907.7273 | H45: =YearMap!C5 -> 1512280.6 | I45: =YearMap!D5 -> 1741770.6 | J45: =1-BaselineCalc!$B$5 -> 0.993 | K45: =Scenarios!G10 -> 0 | L45: =IF(Scenarios!$Q10=1,BaselineCalc!$B$7*(1+Parameters_Public!$C44)^(IF($C45="FY2026",0,IF($C45="FY2027",1,IF($C45="FY2028",2,IF($C45="FY2029",3,IF($C45="FY2030",4,0))))))+ROUND(Scenarios!L10*Scenarios!$F10,0),BaselineCalc!$B$7+ROUND(Scenarios!L10*Scenarios!$F10,0)) -> 257 | M45: =IF(Scenarios!$R10=1,BaselineCalc!$B$8*(1+Parameters_Public!$C45)^(IF($C45="FY2026",0,IF($C45="FY2027",1,IF($C45="FY2028",2,IF($C45="FY2029",3,IF($C45="FY2030",4,0))))))+Scenarios!L10-ROUND(Scenarios!L10*Scenarios!$F10,0),BaselineCalc!$B$8+Scenarios!L10-ROUND(Scenarios!L10*Scenarios!$F10,0)) -> 296 | N45: =(L45-D45) + (M45-E45) -> 257 | O45: =(Parameters_Public!$C$23*(L45-D45)+Parameters_Public!$C$24*(M45-E45)) -> 154.2 | P45: =YearMap!E5 -> 500 | Q45: =IF(Scenarios!N10="lease", YearMap!F5, YearMap!G5) -> 0.1 | R45: =IF(Scenarios!D10=1, Q45*H45, H45) -> 151228.06 | S45: =IF(Scenarios!E10=1, Q45*I45, I45) -> 1741770.6 | T45: =IF(C45="FY2026", (Scenarios!D10+Scenarios!E10)*BaselineCalc!$B$22, 0) -> 0 | U45: =(R45+S45+G45*F45)*J45*(1-K45) -> 3910122.2 | V45: =O45*(G45+P45) -> 1142271.5 | W45: =U45+V45+IF(Parameters_Public!$C$26=1, T45, 0) -> 5052393.7 | X45: =IF(F45+O45>0, W45/(F45+O45),"") -> 11222.554 | Y45: =INDEX(YearMap!$I$2:$I$6, MATCH(C45, YearMap!$A$2:$A$6, 0)) -> 5398.4527 | Z45: =W45 - ((Y45 + IF(Parameters_Public!$C$20=1, Parameters_Public!$C$19, 0))*AC45) -> 2283482.4 | AA45: =IF($AC45>0, $Z45/$AC45, 0) -> 5072.1511 | AB45: =MAX(0, (MAX(0, $D45-BaselineCalc!$B$7) + MAX(0, $E45-BaselineCalc!$B$8))) -> 0 | AC45: =L45+M45-N45+O45 -> 450.2 | AD45: =( (Y45 + IF(Parameters_Public!$C20=1, INDEX(YearMap!$O$2:$O$6, MATCH(C45, YearMap!$A$2:$A$6, 0)), 0)) * AC45 ) + AC45*INDEX(YearMap!$P$2:$P$6, MATCH(C45, YearMap!$A$2:$A$6, 0)) + AB45*( INDEX(YearMap!$R$2:$R$6, MATCH(C45, YearMap!$A$2:$A$6, 0)) - INDEX(YearMap!$P$2:$P$6, MATCH(C45, YearMap!$A$2:$A$6, 0)) ) -> 5315984.9 | AE45: =(W45 - (1-Parameters_Public!$C42)*$G45*$AB45*$J45*(1-$K45)) + AB45*INDEX(YearMap!$Q$2:$Q$6, MATCH(C45, YearMap!$A$2:$A$6, 0)) -> 5052393.7 | AF45: =AD45-AE45 -> 263591.21 | AG45: =B45&"|"&C45 -> B2_Repurpose_Echo_lease_PimaTargets|FY2029
A46: =AG46 -> B2_Repurpose_Echo_lease_PimaTargets|FY2030 | B46: =Scenarios!A10 -> B2_Repurpose_Echo_lease_PimaTargets | C46: FY2030 | D46: =IF(Scenarios!D10=1,0, L46) -> 0 | E46: =IF(Scenarios!E10=1,0, M46) -> 296 | F46: =D46+E46 -> 296 | G46: =YearMap!B6 -> 7080.4205 | H46: =YearMap!C6 -> 1550087.6 | I46: =YearMap!D6 -> 1785314.9 | J46: =1-BaselineCalc!$B$5 -> 0.993 | K46: =Scenarios!G10 -> 0 | L46: =IF(Scenarios!$Q10=1,BaselineCalc!$B$7*(1+Parameters_Public!$C44)^(IF($C46="FY2026",0,IF($C46="FY2027",1,IF($C46="FY2028",2,IF($C46="FY2029",3,IF($C46="FY2030",4,0))))))+ROUND(Scenarios!M10*Scenarios!$F10,0),BaselineCalc!$B$7+ROUND(Scenarios!M10*Scenarios!$F10,0)) -> 257 | M46: =IF(Scenarios!$R10=1,BaselineCalc!$B$8*(1+Parameters_Public!$C45)^(IF($C46="FY2026",0,IF($C46="FY2027",1,IF($C46="FY2028",2,IF($C46="FY2029",3,IF($C46="FY2030",4,0))))))+Scenarios!M10-ROUND(Scenarios!M10*Scenarios!$F10,0),BaselineCalc!$B$8+Scenarios!M10-ROUND(Scenarios!M10*Scenarios!$F10,0)) -> 296 | N46: =(L46-D46) + (M46-E46) -> 257 | O46: =(Parameters_Public!$C$23*(L46-D46)+Parameters_Public!$C$24*(M46-E46)) -> 154.2 | P46: =YearMap!E6 -> 300 | Q46: =IF(Scenarios!N10="lease", YearMap!F6, YearMap!G6) -> 0.1 | R46: =IF(Scenarios!D10=1, Q46*H46, H46) -> 155008.76 | S46: =IF(Scenarios!E10=1, Q46*I46, I46) -> 1785314.9 | T46: =IF(C46="FY2026", (Scenarios!D10+Scenarios!E10)*BaselineCalc!$B$22, 0) -> 0 | U46: =(R46+S46+G46*F46)*J46*(1-K46) -> 4007875.2 | V46: =O46*(G46+P46) -> 1138060.8 | W46: =U46+V46+IF(Parameters_Public!$C$26=1, T46, 0) -> 5145936.1 | X46: =IF(F46+O46>0, W46/(F46+O46),"") -> 11430.333 | Y46: =INDEX(YearMap!$I$2:$I$6, MATCH(C46, YearMap!$A$2:$A$6, 0)) -> 5533.414 | Z46: =W46 - ((Y46 + IF(Parameters_Public!$C$20=1, Parameters_Public!$C$19, 0))*AC46) -> 2316265.2 | AA46: =IF($AC46>0, $Z46/$AC46, 0) -> 5144.9693 | AB46: =MAX(0, (MAX(0, $D46-BaselineCalc!$B$7) + MAX(0, $E46-BaselineCalc!$B$8))) -> 0 | AC46: =L46+M46-N46+O46 -> 450.2 | AD46: =( (Y46 + IF(Parameters_Public!$C20=1, INDEX(YearMap!$O$2:$O$6, MATCH(C46, YearMap!$A$2:$A$6, 0)), 0)) * AC46 ) + AC46*INDEX(YearMap!$P$2:$P$6, MATCH(C46, YearMap!$A$2:$A$6, 0)) + AB46*( INDEX(YearMap!$R$2:$R$6, MATCH(C46, YearMap!$A$2:$A$6, 0)) - INDEX(YearMap!$P$2:$P$6, MATCH(C46, YearMap!$A$2:$A$6, 0)) ) -> 5448884.6 | AE46: =(W46 - (1-Parameters_Public!$C42)*$G46*$AB46*$J46*(1-$K46)) + AB46*INDEX(YearMap!$Q$2:$Q$6, MATCH(C46, YearMap!$A$2:$A$6, 0)) -> 5145936.1 | AF46: =AD46-AE46 -> 302948.49 | AG46: =B46&"|"&C46 -> B2_Repurpose_Echo_lease_PimaTargets|FY2030
A47: =AG47 -> B1_Repurpose_Echo_ops_PimaTargets|FY2026 | B47: =Scenarios!A11 -> B1_Repurpose_Echo_ops_PimaTargets | C47: FY2026 | D47: =IF(Scenarios!D11=1,0, L47) -> 0 | E47: =IF(Scenarios!E11=1,0, M47) -> 308.33333 | F47: =D47+E47 -> 308.33333 | G47: =YearMap!B2 -> 6414.5115 | H47: =YearMap!C2 -> 1404302.9 | I47: =YearMap!D2 -> 1617407.2 | J47: =1-BaselineCalc!$B$5 -> 0.993 | K47: =Scenarios!G11 -> 0 | L47: =IF(Scenarios!$Q11=1,BaselineCalc!$B$7*(1+Parameters_Public!$C44)^(IF($C47="FY2026",0,IF($C47="FY2027",1,IF($C47="FY2028",2,IF($C47="FY2029",3,IF($C47="FY2030",4,0))))))+ROUND(Scenarios!I11*Scenarios!$F11,0),BaselineCalc!$B$7+ROUND(Scenarios!I11*Scenarios!$F11,0)) -> 257 | M47: =IF(Scenarios!$R11=1,BaselineCalc!$B$8*(1+Parameters_Public!$C45)^(IF($C47="FY2026",0,IF($C47="FY2027",1,IF($C47="FY2028",2,IF($C47="FY2029",3,IF($C47="FY2030",4,0))))))+Scenarios!I11-ROUND(Scenarios!I11*Scenarios!$F11,0),BaselineCalc!$B$8+Scenarios!I11-ROUND(Scenarios!I11*Scenarios!$F11,0)) -> 308.33333 | N47: =(L47-D47) + (M47-E47) -> 257 | O47: =(Parameters_Public!$C$23*(L47-D47)+Parameters_Public!$C$24*(M47-E47)) -> 154.2 | P47: =YearMap!E2 -> 1000 | Q47: =IF(Scenarios!N11="lease", YearMap!F2, YearMap!G2) -> 0.45 | R47: =IF(Scenarios!D11=1, Q47*H47, H47) -> 631936.29 | S47: =IF(Scenarios!E11=1, Q47*I47, I47) -> 1617407.2 | T47: =IF(C47="FY2026", (Scenarios!D11+Scenarios!E11)*BaselineCalc!$B$22, 0) -> 1200000 | U47: =(R47+S47+G47*F47)*J47*(1-K47) -> 4197561.1 | V47: =O47*(G47+P47) -> 1143317.7 | W47: =U47+V47+IF(Parameters_Public!$C$26=1, T47, 0) -> 5340878.8 | X47: =IF(F47+O47>0, W47/(F47+O47),"") -> 11547.014 | Y47: =INDEX(YearMap!$I$2:$I$6, MATCH(C47, YearMap!$A$2:$A$6, 0)) -> 5013 | Z47: =W47 - ((Y47 + IF(Parameters_Public!$C$20=1, Parameters_Public!$C$19, 0))*AC47) -> 2674397.3 | AA47: =IF($AC47>0, $Z47/$AC47, 0) -> 5782.0639 | AB47: =MAX(0, (MAX(0, $D47-BaselineCalc!$B$7) + MAX(0, $E47-BaselineCalc!$B$8))) -> 12.333333 | AC47: =L47+M47-N47+O47 -> 462.53333 | AD47: =( (Y47 + IF(Parameters_Public!$C20=1, INDEX(YearMap!$O$2:$O$6, MATCH(C47, YearMap!$A$2:$A$6, 0)), 0)) * AC47 ) + AC47*INDEX(YearMap!$P$2:$P$6, MATCH(C47, YearMap!$A$2:$A$6, 0)) + AB47*( INDEX(YearMap!$R$2:$R$6, MATCH(C47, YearMap!$A$2:$A$6, 0)) - INDEX(YearMap!$P$2:$P$6, MATCH(C47, YearMap!$A$2:$A$6, 0)) ) -> 5062034.9 | AE47: =(W47 - (1-Parameters_Public!$C42)*$G47*$AB47*$J47*(1-$K47)) + AB47*INDEX(YearMap!$Q$2:$Q$6, MATCH(C47, YearMap!$A$2:$A$6, 0)) -> 5264787 | AF47: =AD47-AE47 -> -202752.09 | AG47: =B47&"|"&C47 -> B1_Repurpose_Echo_ops_PimaTargets|FY2026
A48: =AG48 -> B1_Repurpose_Echo_ops_PimaTargets|FY2027 | B48: =Scenarios!A11 -> B1_Repurpose_Echo_ops_PimaTargets | C48: FY2027 | D48: =IF(Scenarios!D11=1,0, L48) -> 0 | E48: =IF(Scenarios!E11=1,0, M48) -> 320.66667 | F48: =D48+E48 -> 320.66667 | G48: =YearMap!B3 -> 6574.8743 | H48: =YearMap!C3 -> 1439410.4 | I48: =YearMap!D3 -> 1657842.4 | J48: =1-BaselineCalc!$B$5 -> 0.993 | K48: =Scenarios!G11 -> 0 | L48: =IF(Scenarios!$Q11=1,BaselineCalc!$B$7*(1+Parameters_Public!$C44)^(IF($C48="FY2026",0,IF($C48="FY2027",1,IF($C48="FY2028",2,IF($C48="FY2029",3,IF($C48="FY2030",4,0))))))+ROUND(Scenarios!J11*Scenarios!$F11,0),BaselineCalc!$B$7+ROUND(Scenarios!J11*Scenarios!$F11,0)) -> 257 | M48: =IF(Scenarios!$R11=1,BaselineCalc!$B$8*(1+Parameters_Public!$C45)^(IF($C48="FY2026",0,IF($C48="FY2027",1,IF($C48="FY2028",2,IF($C48="FY2029",3,IF($C48="FY2030",4,0))))))+Scenarios!J11-ROUND(Scenarios!J11*Scenarios!$F11,0),BaselineCalc!$B$8+Scenarios!J11-ROUND(Scenarios!J11*Scenarios!$F11,0)) -> 320.66667 | N48: =(L48-D48) + (M48-E48) -> 257 | O48: =(Parameters_Public!$C$23*(L48-D48)+Parameters_Public!$C$24*(M48-E48)) -> 154.2 | P48: =YearMap!E3 -> 800 | Q48: =IF(Scenarios!N11="lease", YearMap!F3, YearMap!G3) -> 0.4 | R48: =IF(Scenarios!D11=1, Q48*H48, H48) -> 575764.18 | S48: =IF(Scenarios!E11=1, Q48*I48, I48) -> 1657842.4 | T48: =IF(C48="FY2026", (Scenarios!D11+Scenarios!E11)*BaselineCalc!$B$22, 0) -> 0 | U48: =(R48+S48+G48*F48)*J48*(1-K48) -> 4311555.9 | V48: =O48*(G48+P48) -> 1137205.6 | W48: =U48+V48+IF(Parameters_Public!$C$26=1, T48, 0) -> 5448761.5 | X48: =IF(F48+O48>0, W48/(F48+O48),"") -> 11474.298 | Y48: =INDEX(YearMap!$I$2:$I$6, MATCH(C48, YearMap!$A$2:$A$6, 0)) -> 5138.325 | Z48: =W48 - ((Y48 + IF(Parameters_Public!$C$20=1, Parameters_Public!$C$19, 0))*AC48) -> 2651666.3 | AA48: =IF($AC48>0, $Z48/$AC48, 0) -> 5584.0228 | AB48: =MAX(0, (MAX(0, $D48-BaselineCalc!$B$7) + MAX(0, $E48-BaselineCalc!$B$8))) -> 24.666667 | AC48: =L48+M48-N48+O48 -> 474.86667 | AD48: =( (Y48 + IF(Parameters_Public!$C20=1, INDEX(YearMap!$O$2:$O$6, MATCH(C48, YearMap!$A$2:$A$6, 0)), 0)) * AC48 ) + AC48*INDEX(YearMap!$P$2:$P$6, MATCH(C48, YearMap!$A$2:$A$6, 0)) + AB48*( INDEX(YearMap!$R$2:$R$6, MATCH(C48, YearMap!$A$2:$A$6, 0)) - INDEX(YearMap!$P$2:$P$6, MATCH(C48, YearMap!$A$2:$A$6, 0)) ) -> 5317340.5 | AE48: =(W48 - (1-Parameters_Public!$C42)*$G48*$AB48*$J48*(1-$K48)) + AB48*INDEX(YearMap!$Q$2:$Q$6, MATCH(C48, YearMap!$A$2:$A$6, 0)) -> 5291663.2 | AF48: =AD48-AE48 -> 25677.25 | AG48: =B48&"|"&C48 -> B1_Repurpose_Echo_ops_PimaTargets|FY2027
A49: =AG49 -> B1_Repurpose_Echo_ops_PimaTargets|FY2028 | B49: =Scenarios!A11 -> B1_Repurpose_Echo_ops_PimaTargets | C49: FY2028 | D49: =IF(Scenarios!D11=1,0, L49) -> 0 | E49: =IF(Scenarios!E11=1,0, M49) -> 333 | F49: =D49+E49 -> 333 | G49: =YearMap!B4 -> 6739.2461 | H49: =YearMap!C4 -> 1475395.7 | I49: =YearMap!D4 -> 1699288.4 | J49: =1-BaselineCalc!$B$5 -> 0.993 | K49: =Scenarios!G11 -> 0 | L49: =IF(Scenarios!$Q11=1,BaselineCalc!$B$7*(1+Parameters_Public!$C44)^(IF($C49="FY2026",0,IF($C49="FY2027",1,IF($C49="FY2028",2,IF($C49="FY2029",3,IF($C49="FY2030",4,0))))))+ROUND(Scenarios!K11*Scenarios!$F11,0),BaselineCalc!$B$7+ROUND(Scenarios!K11*Scenarios!$F11,0)) -> 257 | M49: =IF(Scenarios!$R11=1,BaselineCalc!$B$8*(1+Parameters_Public!$C45)^(IF($C49="FY2026",0,IF($C49="FY2027",1,IF($C49="FY2028",2,IF($C49="FY2029",3,IF($C49="FY2030",4,0))))))+Scenarios!K11-ROUND(Scenarios!K11*Scenarios!$F11,0),BaselineCalc!$B$8+Scenarios!K11-ROUND(Scenarios!K11*Scenarios!$F11,0)) -> 333 | N49: =(L49-D49) + (M49-E49) -> 257 | O49: =(Parameters_Public!$C$23*(L49-D49)+Parameters_Public!$C$24*(M49-E49)) -> 154.2 | P49: =YearMap!E4 -> 600 | Q49: =IF(Scenarios!N11="lease", YearMap!F4, YearMap!G4) -> 0.35 | R49: =IF(Scenarios!D11=1, Q49*H49, H49) -> 516388.5 | S49: =IF(Scenarios!E11=1, Q49*I49, I49) -> 1699288.4 | T49: =IF(C49="FY2026", (Scenarios!D11+Scenarios!E11)*BaselineCalc!$B$22, 0) -> 0 | U49: =(R49+S49+G49*F49)*J49*(1-K49) -> 4428627 | V49: =O49*(G49+P49) -> 1131711.8 | W49: =U49+V49+IF(Parameters_Public!$C$26=1, T49, 0) -> 5560338.7 | X49: =IF(F49+O49>0, W49/(F49+O49),"") -> 11412.846 | Y49: =INDEX(YearMap!$I$2:$I$6, MATCH(C49, YearMap!$A$2:$A$6, 0)) -> 5266.7831 | Z49: =W49 - ((Y49 + IF(Parameters_Public!$C$20=1, Parameters_Public!$C$19, 0))*AC49) -> 2628012 | AA49: =IF($AC49>0, $Z49/$AC49, 0) -> 5394.1132 | AB49: =MAX(0, (MAX(0, $D49-BaselineCalc!$B$7) + MAX(0, $E49-BaselineCalc!$B$8))) -> 37 | AC49: =L49+M49-N49+O49 -> 487.2 | AD49: =( (Y49 + IF(Parameters_Public!$C20=1, INDEX(YearMap!$O$2:$O$6, MATCH(C49, YearMap!$A$2:$A$6, 0)), 0)) * AC49 ) + AC49*INDEX(YearMap!$P$2:$P$6, MATCH(C49, YearMap!$A$2:$A$6, 0)) + AB49*( INDEX(YearMap!$R$2:$R$6, MATCH(C49, YearMap!$A$2:$A$6, 0)) - INDEX(YearMap!$P$2:$P$6, MATCH(C49, YearMap!$A$2:$A$6, 0)) ) -> 5582247.6 | AE49: =(W49 - (1-Parameters_Public!$C42)*$G49*$AB49*$J49*(1-$K49)) + AB49*INDEX(YearMap!$Q$2:$Q$6, MATCH(C49, YearMap!$A$2:$A$6, 0)) -> 5317172.1 | AF49: =AD49-AE49 -> 265075.52 | AG49: =B49&"|"&C49 -> B1_Repurpose_Echo_ops_PimaTargets|FY2028
A50: =AG50 -> B1_Repurpose_Echo_ops_PimaTargets|FY2029 | B50: =Scenarios!A11 -> B1_Repurpose_Echo_ops_PimaTargets | C50: FY2029 | D50: =IF(Scenarios!D11=1,0, L50) -> 0 | E50: =IF(Scenarios!E11=1,0, M50) -> 333 | F50: =D50+E50 -> 333 | G50: =YearMap!B5 -> 6907.7273 | H50: =YearMap!C5 -> 1512280.6 | I50: =YearMap!D5 -> 1741770.6 | J50: =1-BaselineCalc!$B$5 -> 0.993 | K50: =Scenarios!G11 -> 0 | L50: =IF(Scenarios!$Q11=1,BaselineCalc!$B$7*(1+Parameters_Public!$C44)^(IF($C50="FY2026",0,IF($C50="FY2027",1,IF($C50="FY2028",2,IF($C50="FY2029",3,IF($C50="FY2030",4,0))))))+ROUND(Scenarios!L11*Scenarios!$F11,0),BaselineCalc!$B$7+ROUND(Scenarios!L11*Scenarios!$F11,0)) -> 257 | M50: =IF(Scenarios!$R11=1,BaselineCalc!$B$8*(1+Parameters_Public!$C45)^(IF($C50="FY2026",0,IF($C50="FY2027",1,IF($C50="FY2028",2,IF($C50="FY2029",3,IF($C50="FY2030",4,0))))))+Scenarios!L11-ROUND(Scenarios!L11*Scenarios!$F11,0),BaselineCalc!$B$8+Scenarios!L11-ROUND(Scenarios!L11*Scenarios!$F11,0)) -> 333 | N50: =(L50-D50) + (M50-E50) -> 257 | O50: =(Parameters_Public!$C$23*(L50-D50)+Parameters_Public!$C$24*(M50-E50)) -> 154.2 | P50: =YearMap!E5 -> 500 | Q50: =IF(Scenarios!N11="lease", YearMap!F5, YearMap!G5) -> 0.3 | R50: =IF(Scenarios!D11=1, Q50*H50, H50) -> 453684.18 | S50: =IF(Scenarios!E11=1, Q50*I50, I50) -> 1741770.6 | T50: =IF(C50="FY2026", (Scenarios!D11+Scenarios!E11)*BaselineCalc!$B$22, 0) -> 0 | U50: =(R50+S50+G50*F50)*J50*(1-K50) -> 4464257.9 | V50: =O50*(G50+P50) -> 1142271.5 | W50: =U50+V50+IF(Parameters_Public!$C$26=1, T50, 0) -> 5606529.5 | X50: =IF(F50+O50>0, W50/(F50+O50),"") -> 11507.655 | Y50: =INDEX(YearMap!$I$2:$I$6, MATCH(C50, YearMap!$A$2:$A$6, 0)) -> 5398.4527 | Z50: =W50 - ((Y50 + IF(Parameters_Public!$C$20=1, Parameters_Public!$C$19, 0))*AC50) -> 2610053.3 | AA50: =IF($AC50>0, $Z50/$AC50, 0) -> 5357.2522 | AB50: =MAX(0, (MAX(0, $D50-BaselineCalc!$B$7) + MAX(0, $E50-BaselineCalc!$B$8))) -> 37 | AC50: =L50+M50-N50+O50 -> 487.2 | AD50: =( (Y50 + IF(Parameters_Public!$C20=1, INDEX(YearMap!$O$2:$O$6, MATCH(C50, YearMap!$A$2:$A$6, 0)), 0)) * AC50 ) + AC50*INDEX(YearMap!$P$2:$P$6, MATCH(C50, YearMap!$A$2:$A$6, 0)) + AB50*( INDEX(YearMap!$R$2:$R$6, MATCH(C50, YearMap!$A$2:$A$6, 0)) - INDEX(YearMap!$P$2:$P$6, MATCH(C50, YearMap!$A$2:$A$6, 0)) ) -> 5721803.8 | AE50: =(W50 - (1-Parameters_Public!$C42)*$G50*$AB50*$J50*(1-$K50)) + AB50*INDEX(YearMap!$Q$2:$Q$6, MATCH(C50, YearMap!$A$2:$A$6, 0)) -> 5356432.7 | AF50: =AD50-AE50 -> 365371.14 | AG50: =B50&"|"&C50 -> B1_Repurpose_Echo_ops_PimaTargets|FY2029
A51: =AG51 -> B1_Repurpose_Echo_ops_PimaTargets|FY2030 | B51: =Scenarios!A11 -> B1_Repurpose_Echo_ops_PimaTargets | C51: FY2030 | D51: =IF(Scenarios!D11=1,0, L51) -> 0 | E51: =IF(Scenarios!E11=1,0, M51) -> 333 | F51: =D51+E51 -> 333 | G51: =YearMap!B6 -> 7080.4205 | H51: =YearMap!C6 -> 1550087.6 | I51: =YearMap!D6 -> 1785314.9 | J51: =1-BaselineCalc!$B$5 -> 0.993 | K51: =Scenarios!G11 -> 0 | L51: =IF(Scenarios!$Q11=1,BaselineCalc!$B$7*(1+Parameters_Public!$C44)^(IF($C51="FY2026",0,IF($C51="FY2027",1,IF($C51="FY2028",2,IF($C51="FY2029",3,IF($C51="FY2030",4,0))))))+ROUND(Scenarios!M11*Scenarios!$F11,0),BaselineCalc!$B$7+ROUND(Scenarios!M11*Scenarios!$F11,0)) -> 257 | M51: =IF(Scenarios!$R11=1,BaselineCalc!$B$8*(1+Parameters_Public!$C45)^(IF($C51="FY2026",0,IF($C51="FY2027",1,IF($C51="FY2028",2,IF($C51="FY2029",3,IF($C51="FY2030",4,0))))))+Scenarios!M11-ROUND(Scenarios!M11*Scenarios!$F11,0),BaselineCalc!$B$8+Scenarios!M11-ROUND(Scenarios!M11*Scenarios!$F11,0)) -> 333 | N51: =(L51-D51) + (M51-E51) -> 257 | O51: =(Parameters_Public!$C$23*(L51-D51)+Parameters_Public!$C$24*(M51-E51)) -> 154.2 | P51: =YearMap!E6 -> 300 | Q51: =IF(Scenarios!N11="lease", YearMap!F6, YearMap!G6) -> 0.3 | R51: =IF(Scenarios!D11=1, Q51*H51, H51) -> 465026.28 | S51: =IF(Scenarios!E11=1, Q51*I51, I51) -> 1785314.9 | T51: =IF(C51="FY2026", (Scenarios!D11+Scenarios!E11)*BaselineCalc!$B$22, 0) -> 0 | U51: =(R51+S51+G51*F51)*J51*(1-K51) -> 4575864.4 | V51: =O51*(G51+P51) -> 1138060.8 | W51: =U51+V51+IF(Parameters_Public!$C$26=1, T51, 0) -> 5713925.2 | X51: =IF(F51+O51>0, W51/(F51+O51),"") -> 11728.09 | Y51: =INDEX(YearMap!$I$2:$I$6, MATCH(C51, YearMap!$A$2:$A$6, 0)) -> 5533.414 | Z51: =W51 - ((Y51 + IF(Parameters_Public!$C$20=1, Parameters_Public!$C$19, 0))*AC51) -> 2651695.9 | AA51: =IF($AC51>0, $Z51/$AC51, 0) -> 5442.7255 | AB51: =MAX(0, (MAX(0, $D51-BaselineCalc!$B$7) + MAX(0, $E51-BaselineCalc!$B$8))) -> 37 | AC51: =L51+M51-N51+O51 -> 487.2 | AD51: =( (Y51 + IF(Parameters_Public!$C20=1, INDEX(YearMap!$O$2:$O$6, MATCH(C51, YearMap!$A$2:$A$6, 0)), 0)) * AC51 ) + AC51*INDEX(YearMap!$P$2:$P$6, MATCH(C51, YearMap!$A$2:$A$6, 0)) + AB51*( INDEX(YearMap!$R$2:$R$6, MATCH(C51, YearMap!$A$2:$A$6, 0)) - INDEX(YearMap!$P$2:$P$6, MATCH(C51, YearMap!$A$2:$A$6, 0)) ) -> 5864848.9 | AE51: =(W51 - (1-Parameters_Public!$C42)*$G51*$AB51*$J51*(1-$K51)) + AB51*INDEX(YearMap!$Q$2:$Q$6, MATCH(C51, YearMap!$A$2:$A$6, 0)) -> 5456003.5 | AF51: =AD51-AE51 -> 408845.42 | AG51: =B51&"|"&C51 -> B1_Repurpose_Echo_ops_PimaTargets|FY2030
A52: =AG52 -> C2_Repurpose_Pima_lease_EchoGHub_EchoTargets|FY2026 | B52: =Scenarios!A12 -> C2_Repurpose_Pima_lease_EchoGHub_EchoTargets | C52: FY2026 | D52: =IF(Scenarios!D12=1,0, L52) -> 257 | E52: =IF(Scenarios!E12=1,0, M52) -> 0 | F52: =D52+E52 -> 257 | G52: =YearMap!B2 -> 6414.5115 | H52: =YearMap!C2 -> 1404302.9 | I52: =YearMap!D2 -> 1617407.2 | J52: =1-BaselineCalc!$B$5 -> 0.993 | K52: =Scenarios!G12 -> 0 | L52: =IF(Scenarios!$Q12=1,BaselineCalc!$B$7*(1+Parameters_Public!$C44)^(IF($C52="FY2026",0,IF($C52="FY2027",1,IF($C52="FY2028",2,IF($C52="FY2029",3,IF($C52="FY2030",4,0))))))+ROUND(Scenarios!I12*Scenarios!$F12,0),BaselineCalc!$B$7+ROUND(Scenarios!I12*Scenarios!$F12,0)) -> 257 | M52: =IF(Scenarios!$R12=1,BaselineCalc!$B$8*(1+Parameters_Public!$C45)^(IF($C52="FY2026",0,IF($C52="FY2027",1,IF($C52="FY2028",2,IF($C52="FY2029",3,IF($C52="FY2030",4,0))))))+Scenarios!I12-ROUND(Scenarios!I12*Scenarios!$F12,0),BaselineCalc!$B$8+Scenarios!I12-ROUND(Scenarios!I12*Scenarios!$F12,0)) -> 296 | N52: =(L52-D52) + (M52-E52) -> 296 | O52: =(Parameters_Public!$C$23*(L52-D52)+Parameters_Public!$C$24*(M52-E52)) -> 251.6 | P52: =YearMap!E2 -> 1000 | Q52: =IF(Scenarios!N12="lease", YearMap!F2, YearMap!G2) -> 0.2 | R52: =IF(Scenarios!D12=1, Q52*H52, H52) -> 1404302.9 | S52: =IF(Scenarios!E12=1, Q52*I52, I52) -> 323481.44 | T52: =IF(C52="FY2026", (Scenarios!D12+Scenarios!E12)*BaselineCalc!$B$22, 0) -> 1200000 | U52: =(R52+S52+G52*F52)*J52*(1-K52) -> 3352679.6 | V52: =O52*(G52+P52) -> 1865491.1 | W52: =U52+V52+IF(Parameters_Public!$C$26=1, T52, 0) -> 5218170.7 | X52: =IF(F52+O52>0, W52/(F52+O52),"") -> 10259.872 | Y52: =INDEX(YearMap!$I$2:$I$6, MATCH(C52, YearMap!$A$2:$A$6, 0)) -> 5013 | Z52: =W52 - ((Y52 + IF(Parameters_Public!$C$20=1, Parameters_Public!$C$19, 0))*AC52) -> 2286117.1 | AA52: =IF($AC52>0, $Z52/$AC52, 0) -> 4494.9215 | AB52: =MAX(0, (MAX(0, $D52-BaselineCalc!$B$7) + MAX(0, $E52-BaselineCalc!$B$8))) -> 0 | AC52: =L52+M52-N52+O52 -> 508.6 | AD52: =( (Y52 + IF(Parameters_Public!$C20=1, INDEX(YearMap!$O$2:$O$6, MATCH(C52, YearMap!$A$2:$A$6, 0)), 0)) * AC52 ) + AC52*INDEX(YearMap!$P$2:$P$6, MATCH(C52, YearMap!$A$2:$A$6, 0)) + AB52*( INDEX(YearMap!$R$2:$R$6, MATCH(C52, YearMap!$A$2:$A$6, 0)) - INDEX(YearMap!$P$2:$P$6, MATCH(C52, YearMap!$A$2:$A$6, 0)) ) -> 5576773.6 | AE52: =(W52 - (1-Parameters_Public!$C42)*$G52*$AB52*$J52*(1-$K52)) + AB52*INDEX(YearMap!$Q$2:$Q$6, MATCH(C52, YearMap!$A$2:$A$6, 0)) -> 5218170.7 | AF52: =AD52-AE52 -> 358602.91 | AG52: =B52&"|"&C52 -> C2_Repurpose_Pima_lease_EchoGHub_EchoTargets|FY2026
A53: =AG53 -> C2_Repurpose_Pima_lease_EchoGHub_EchoTargets|FY2027 | B53: =Scenarios!A12 -> C2_Repurpose_Pima_lease_EchoGHub_EchoTargets | C53: FY2027 | D53: =IF(Scenarios!D12=1,0, L53) -> 257 | E53: =IF(Scenarios!E12=1,0, M53) -> 0 | F53: =D53+E53 -> 257 | G53: =YearMap!B3 -> 6574.8743 | H53: =YearMap!C3 -> 1439410.4 | I53: =YearMap!D3 -> 1657842.4 | J53: =1-BaselineCalc!$B$5 -> 0.993 | K53: =Scenarios!G12 -> 0 | L53: =IF(Scenarios!$Q12=1,BaselineCalc!$B$7*(1+Parameters_Public!$C44)^(IF($C53="FY2026",0,IF($C53="FY2027",1,IF($C53="FY2028",2,IF($C53="FY2029",3,IF($C53="FY2030",4,0))))))+ROUND(Scenarios!J12*Scenarios!$F12,0),BaselineCalc!$B$7+ROUND(Scenarios!J12*Scenarios!$F12,0)) -> 257 | M53: =IF(Scenarios!$R12=1,BaselineCalc!$B$8*(1+Parameters_Public!$C45)^(IF($C53="FY2026",0,IF($C53="FY2027",1,IF($C53="FY2028",2,IF($C53="FY2029",3,IF($C53="FY2030",4,0))))))+Scenarios!J12-ROUND(Scenarios!J12*Scenarios!$F12,0),BaselineCalc!$B$8+Scenarios!J12-ROUND(Scenarios!J12*Scenarios!$F12,0)) -> 296 | N53: =(L53-D53) + (M53-E53) -> 296 | O53: =(Parameters_Public!$C$23*(L53-D53)+Parameters_Public!$C$24*(M53-E53)) -> 251.6 | P53: =YearMap!E3 -> 800 | Q53: =IF(Scenarios!N12="lease", YearMap!F3, YearMap!G3) -> 0.2 | R53: =IF(Scenarios!D12=1, Q53*H53, H53) -> 1439410.4 | S53: =IF(Scenarios!E12=1, Q53*I53, I53) -> 331568.48 | T53: =IF(C53="FY2026", (Scenarios!D12+Scenarios!E12)*BaselineCalc!$B$22, 0) -> 0 | U53: =(R53+S53+G53*F53)*J53*(1-K53) -> 3436496.6 | V53: =O53*(G53+P53) -> 1855518.4 | W53: =U53+V53+IF(Parameters_Public!$C$26=1, T53, 0) -> 5292014.9 | X53: =IF(F53+O53>0, W53/(F53+O53),"") -> 10405.063 | Y53: =INDEX(YearMap!$I$2:$I$6, MATCH(C53, YearMap!$A$2:$A$6, 0)) -> 5138.325 | Z53: =W53 - ((Y53 + IF(Parameters_Public!$C$20=1, Parameters_Public!$C$19, 0))*AC53) -> 2296221.1 | AA53: =IF($AC53>0, $Z53/$AC53, 0) -> 4514.7878 | AB53: =MAX(0, (MAX(0, $D53-BaselineCalc!$B$7) + MAX(0, $E53-BaselineCalc!$B$8))) -> 0 | AC53: =L53+M53-N53+O53 -> 508.6 | AD53: =( (Y53 + IF(Parameters_Public!$C20=1, INDEX(YearMap!$O$2:$O$6, MATCH(C53, YearMap!$A$2:$A$6, 0)), 0)) * AC53 ) + AC53*INDEX(YearMap!$P$2:$P$6, MATCH(C53, YearMap!$A$2:$A$6, 0)) + AB53*( INDEX(YearMap!$R$2:$R$6, MATCH(C53, YearMap!$A$2:$A$6, 0)) - INDEX(YearMap!$P$2:$P$6, MATCH(C53, YearMap!$A$2:$A$6, 0)) ) -> 5716192.9 | AE53: =(W53 - (1-Parameters_Public!$C42)*$G53*$AB53*$J53*(1-$K53)) + AB53*INDEX(YearMap!$Q$2:$Q$6, MATCH(C53, YearMap!$A$2:$A$6, 0)) -> 5292014.9 | AF53: =AD53-AE53 -> 424177.98 | AG53: =B53&"|"&C53 -> C2_Repurpose_Pima_lease_EchoGHub_EchoTargets|FY2027
A54: =AG54 -> C2_Repurpose_Pima_lease_EchoGHub_EchoTargets|FY2028 | B54: =Scenarios!A12 -> C2_Repurpose_Pima_lease_EchoGHub_EchoTargets | C54: FY2028 | D54: =IF(Scenarios!D12=1,0, L54) -> 257 | E54: =IF(Scenarios!E12=1,0, M54) -> 0 | F54: =D54+E54 -> 257 | G54: =YearMap!B4 -> 6739.2461 | H54: =YearMap!C4 -> 1475395.7 | I54: =YearMap!D4 -> 1699288.4 | J54: =1-BaselineCalc!$B$5 -> 0.993 | K54: =Scenarios!G12 -> 0 | L54: =IF(Scenarios!$Q12=1,BaselineCalc!$B$7*(1+Parameters_Public!$C44)^(IF($C54="FY2026",0,IF($C54="FY2027",1,IF($C54="FY2028",2,IF($C54="FY2029",3,IF($C54="FY2030",4,0))))))+ROUND(Scenarios!K12*Scenarios!$F12,0),BaselineCalc!$B$7+ROUND(Scenarios!K12*Scenarios!$F12,0)) -> 257 | M54: =IF(Scenarios!$R12=1,BaselineCalc!$B$8*(1+Parameters_Public!$C45)^(IF($C54="FY2026",0,IF($C54="FY2027",1,IF($C54="FY2028",2,IF($C54="FY2029",3,IF($C54="FY2030",4,0))))))+Scenarios!K12-ROUND(Scenarios!K12*Scenarios!$F12,0),BaselineCalc!$B$8+Scenarios!K12-ROUND(Scenarios!K12*Scenarios!$F12,0)) -> 296 | N54: =(L54-D54) + (M54-E54) -> 296 | O54: =(Parameters_Public!$C$23*(L54-D54)+Parameters_Public!$C$24*(M54-E54)) -> 251.6 | P54: =YearMap!E4 -> 600 | Q54: =IF(Scenarios!N12="lease", YearMap!F4, YearMap!G4) -> 0.15 | R54: =IF(Scenarios!D12=1, Q54*H54, H54) -> 1475395.7 | S54: =IF(Scenarios!E12=1, Q54*I54, I54) -> 254893.27 | T54: =IF(C54="FY2026", (Scenarios!D12+Scenarios!E12)*BaselineCalc!$B$22, 0) -> 0 | U54: =(R54+S54+G54*F54)*J54*(1-K54) -> 3438039.3 | V54: =O54*(G54+P54) -> 1846554.3 | W54: =U54+V54+IF(Parameters_Public!$C$26=1, T54, 0) -> 5284593.6 | X54: =IF(F54+O54>0, W54/(F54+O54),"") -> 10390.471 | Y54: =INDEX(YearMap!$I$2:$I$6, MATCH(C54, YearMap!$A$2:$A$6, 0)) -> 5266.7831 | Z54: =W54 - ((Y54 + IF(Parameters_Public!$C$20=1, Parameters_Public!$C$19, 0))*AC54) -> 2223466 | AA54: =IF($AC54>0, $Z54/$AC54, 0) -> 4371.738 | AB54: =MAX(0, (MAX(0, $D54-BaselineCalc!$B$7) + MAX(0, $E54-BaselineCalc!$B$8))) -> 0 | AC54: =L54+M54-N54+O54 -> 508.6 | AD54: =( (Y54 + IF(Parameters_Public!$C20=1, INDEX(YearMap!$O$2:$O$6, MATCH(C54, YearMap!$A$2:$A$6, 0)), 0)) * AC54 ) + AC54*INDEX(YearMap!$P$2:$P$6, MATCH(C54, YearMap!$A$2:$A$6, 0)) + AB54*( INDEX(YearMap!$R$2:$R$6, MATCH(C54, YearMap!$A$2:$A$6, 0)) - INDEX(YearMap!$P$2:$P$6, MATCH(C54, YearMap!$A$2:$A$6, 0)) ) -> 5859097.7 | AE54: =(W54 - (1-Parameters_Public!$C42)*$G54*$AB54*$J54*(1-$K54)) + AB54*INDEX(YearMap!$Q$2:$Q$6, MATCH(C54, YearMap!$A$2:$A$6, 0)) -> 5284593.6 | AF54: =AD54-AE54 -> 574504.1 | AG54: =B54&"|"&C54 -> C2_Repurpose_Pima_lease_EchoGHub_EchoTargets|FY2028
